{
  "type": "Feature",
  "properties": {
    "addr:full":"6298 Jamestown Rd Waycross GA 31503",
    "addr:housenumber":"6298",
    "addr:postcode":"31503",
    "addr:street":"Jamestown Rd",
    "iso:country":"US",
    "sg:address":"6298 Jamestown Rd",
    "sg:city":"Waycross",
    "sg:classifiers":[
        {
            "category":"Personal",
            "subcategory":"Beauty Salon",
            "type":"Services"
        }
    ],
    "sg:phone":"+1 912 284 9487",
    "sg:postcode":"31503",
    "sg:province":"GA",
    "wof:name":"Hendricks Sammy & Brandy",
    "wof:placetype":"venue"
},
  "geometry": {"coordinates":[-82.391139,31.322358],"type":"Point"}
}