{
  "type": "Feature",
  "properties": {
    "iso:country":"US",
    "sg:address":"94 W Howell St",
    "sg:city":"Hartwell",
    "sg:classifiers":[
        {
            "category":"Restaurant",
            "type":"Food & Drink"
        }
    ],
    "sg:phone":"+1 706 376 5566",
    "sg:postcode":"30643",
    "sg:province":"GA",
    "sg:tags":[
        "eating"
    ],
    "wof:name":"S & W Diner",
    "wof:placetype":"venue"
},
  "geometry": {"coordinates":[-82.94014199999999,34.354685],"type":"Point"}
}