{
  "type": "Feature",
  "properties": {
    "addr:full":"2910 N Druid Hills Road NE Atlanta GA 30329",
    "addr:housenumber":"2910",
    "addr:postcode":"30329",
    "addr:street":"N Druid Hills Road Ne",
    "iso:country":"US",
    "sg:address":"2910 N Druid Hills Road NE",
    "sg:city":"Atlanta",
    "sg:classifiers":[
        {
            "category":"Health Services",
            "subcategory":"Doctor",
            "type":"Services"
        }
    ],
    "sg:phone":"+1 404 320 6050",
    "sg:postcode":"30329",
    "sg:province":"GA",
    "sg:tags":[
        "physician",
        "family",
        "practice",
        "surgeons",
        "medicine",
        "surgeon"
    ],
    "wof:name":"Lavista Family Medicine & Rehabilitation",
    "wof:placetype":"venue"
},
  "geometry": {"coordinates":[-84.311211,33.816575],"type":"Point"}
}