{
  "type": "Feature",
  "properties": {
    "iso:country":"US",
    "sg:address":"3353 Clevemont Way",
    "sg:city":"Ellenwood",
    "sg:classifiers":[
        {
            "category":"Personal",
            "subcategory":"Beauty Salon",
            "type":"Services"
        }
    ],
    "sg:phone":"+1 404 549 1487",
    "sg:postcode":"30294",
    "sg:province":"GA",
    "sg:tags":[
        "hair"
    ],
    "sg:website":"www.facebook.com/pages/Lady-of-B...",
    "wof:name":"Lady of Braids",
    "wof:placetype":"venue"
},
  "geometry": {"coordinates":[-84.252803,33.652286],"type":"Point"}
}