{
  "type": "Feature",
  "properties": {
    "addr:full":"5075 Buford Hwy Norcross GA 30071",
    "addr:housenumber":"5075",
    "addr:postcode":"30071",
    "addr:street":"Buford Hwy",
    "iso:country":"US",
    "sg:address":"5075 Buford Hwy",
    "sg:city":"Norcross",
    "sg:classifiers":[
        {
            "category":"Home & Garden",
            "subcategory":"Home Furnishings",
            "type":"Retail Goods"
        }
    ],
    "sg:phone":"+1 770 409 9098",
    "sg:postcode":"30071",
    "sg:province":"GA",
    "sg:tags":[
        "housewares"
    ],
    "wof:name":"Hometex Furnishings Inc",
    "wof:placetype":"venue"
},
  "geometry": {"coordinates":[-84.193381,33.954052],"type":"Point"}
}