{
  "type": "Feature",
  "properties": {
    "iso:country":"US",
    "sg:address":"1019 Friar Tuck Ct",
    "sg:city":"Dublin",
    "sg:classifiers":[
        {
            "category":"Building & Trades",
            "subcategory":"Cleaning & Sanitation",
            "type":"Services"
        }
    ],
    "sg:phone":"+1 478 275 2649",
    "sg:postcode":"31021",
    "sg:province":"GA",
    "sg:tags":[
        "janitor"
    ],
    "wof:name":"Howard Cleaning Svc",
    "wof:placetype":"venue"
},
  "geometry": {"coordinates":[-83.004474,32.561386],"type":"Point"}
}