{
  "type": "Feature",
  "properties": {
    "iso:country":"US",
    "sg:address":"5582 Williams Rd",
    "sg:city":"Norcross",
    "sg:classifiers":[
        {
            "category":"Shopping",
            "subcategory":"Used Merchandise",
            "type":"Retail Goods"
        }
    ],
    "sg:phone":"+1 770 564 2775",
    "sg:postcode":"30093",
    "sg:province":"GA",
    "wof:name":"Delightful Treasures",
    "wof:placetype":"venue"
},
  "geometry": {"coordinates":[-84.175898,33.898156],"type":"Point"}
}