{
  "type": "Feature",
  "properties": {
    "iso:country":"US",
    "sg:address":"614 N Church St",
    "sg:city":"Thomaston",
    "sg:classifiers":[
        {
            "category":"Retail",
            "subcategory":"Storage",
            "type":"Services"
        }
    ],
    "sg:phone":"+1 706 647 2100",
    "sg:postcode":"30286",
    "sg:province":"GA",
    "sg:tags":[
        "self"
    ],
    "wof:name":"Your Extra Attic",
    "wof:placetype":"venue"
},
  "geometry": {"coordinates":[-84.328411,32.898543],"type":"Point"}
}