{
  "type": "Feature",
  "properties": {
    "addr:full":"975 Buttermilk Rd Sylvania GA 30467",
    "addr:housenumber":"975",
    "addr:postcode":"30467",
    "addr:street":"Buttermilk Rd",
    "iso:country":"US",
    "sg:address":"975 Buttermilk Rd",
    "sg:city":"Sylvania",
    "sg:classifiers":[
        {
            "category":"Wholesale",
            "subcategory":"Auto Parts",
            "type":"Manufacturing & Wholesale Goods"
        }
    ],
    "sg:phone":"+1 912 564 7654",
    "sg:postcode":"30467",
    "sg:province":"GA",
    "sg:tags":[
        "automobile",
        "rebuilt"
    ],
    "wof:name":"Weaver Automotive",
    "wof:placetype":"venue"
},
  "geometry": {"coordinates":[-81.665684,32.776279],"type":"Point"}
}