{
  "type": "Feature",
  "properties": {
    "iso:country":"US",
    "sg:address":"1155 Melvin Westberry Rd",
    "sg:city":"Jesup",
    "sg:classifiers":[
        {
            "category":"Health Services",
            "subcategory":"Doctor",
            "type":"Services"
        }
    ],
    "sg:phone":"+1 912 586 6676",
    "sg:postcode":"31545",
    "sg:province":"GA",
    "sg:tags":[
        "medical"
    ],
    "wof:name":"Michael Westberry",
    "wof:placetype":"venue"
},
  "geometry": {"coordinates":[-81.98961199999999,31.745014],"type":"Point"}
}