{
  "type": "Feature",
  "properties": {
    "addr:full":"544 Medlock Rd Decatur GA 30030",
    "addr:housenumber":"544",
    "addr:postcode":"30030",
    "addr:street":"Medlock Rd",
    "iso:country":"US",
    "sg:address":"544 Medlock Rd",
    "sg:city":"Decatur",
    "sg:classifiers":[
        {
            "category":"Health Services",
            "subcategory":"Doctor",
            "type":"Services"
        },
        {
            "category":"Health Services",
            "subcategory":"Clinic",
            "type":"Services"
        }
    ],
    "sg:phone":"+1 404 378 1210",
    "sg:postcode":"30030",
    "sg:province":"GA",
    "sg:tags":[
        "counseling",
        "mental"
    ],
    "wof:name":"Goch Amy E PHD",
    "wof:placetype":"venue"
},
  "geometry": {"coordinates":[-84.2901,33.7925],"type":"Point"}
}