{
  "type": "Feature",
  "properties": {
    "iso:country":"US",
    "sg:address":"1739 Sylvan Rd SW",
    "sg:city":"Atlanta",
    "sg:classifiers":[
        {
            "category":"Social Services",
            "subcategory":"Child Care",
            "type":"Services"
        }
    ],
    "sg:phone":"+1 770 517 7668",
    "sg:postcode":"30310",
    "sg:province":"GA",
    "sg:tags":[
        "nursery",
        "day"
    ],
    "wof:name":"Linda's Home Daycare",
    "wof:placetype":"venue"
},
  "geometry": {"coordinates":[-84.418181,33.707319],"type":"Point"}
}