{
  "type": "Feature",
  "properties": {
    "iso:country":"US",
    "sg:address":"239 Alexander St NW",
    "sg:city":"Atlanta",
    "sg:classifiers":[
        {
            "category":"Health Services",
            "subcategory":"Doctor",
            "type":"Services"
        }
    ],
    "sg:phone":"+1 770 419 3120",
    "sg:postcode":"30313",
    "sg:province":"GA",
    "sg:tags":[
        "physician",
        "surgeon"
    ],
    "wof:name":"James L Hornsby Jr MD",
    "wof:placetype":"venue"
},
  "geometry": {"coordinates":[-84.394881,33.764713],"type":"Point"}
}