{
  "type": "Feature",
  "properties": {
    "addr:full":"4938 Roswell Rd Marietta GA 30062",
    "addr:housenumber":"4938",
    "addr:postcode":"30062",
    "addr:street":"Roswell Rd",
    "iso:country":"US",
    "sg:address":"4938 Roswell Rd",
    "sg:city":"Marietta",
    "sg:classifiers":[
        {
            "category":"Shopping",
            "subcategory":"Pharmacy",
            "type":"Retail Goods"
        }
    ],
    "sg:phone":"+1 770 973 1810",
    "sg:postcode":"30062",
    "sg:province":"GA",
    "sg:tags":[
        "drug",
        "store"
    ],
    "wof:name":"Cvs",
    "wof:placetype":"venue"
},
  "geometry": {"coordinates":[-84.405137,34.000474],"type":"Point"}
}