{
  "type": "Feature",
  "properties": {
    "iso:country":"US",
    "sg:address":"204 Maryland Dr",
    "sg:city":"Camilla",
    "sg:classifiers":[
        {
            "category":"Farming",
            "subcategory":"Farm & Veterinary Services",
            "type":"Manufacturing & Wholesale Goods"
        }
    ],
    "sg:phone":"+1 229 336 0552",
    "sg:postcode":"31730",
    "sg:province":"GA",
    "sg:tags":[
        "management"
    ],
    "wof:name":"Bobby Gay",
    "wof:placetype":"venue"
},
  "geometry": {"coordinates":[-84.217584,31.226201],"type":"Point"}
}