{
  "type": "Feature",
  "properties": {
    "iso:country":"US",
    "sg:address":"2100 Atlanta Hwy",
    "sg:city":"Gainesville",
    "sg:classifiers":[
        {
            "category":"Manufacturing",
            "subcategory":"Paper Products",
            "type":"Manufacturing & Wholesale Goods"
        }
    ],
    "sg:phone":"+1 770 534 5259",
    "sg:postcode":"30504",
    "sg:province":"GA",
    "wof:name":"First State Packaging Inc",
    "wof:placetype":"venue"
},
  "geometry": {"coordinates":[-83.84549699999999,34.253977],"type":"Point"}
}