{
  "type": "Feature",
  "properties": {
    "addr:full":"890 Oriole Ln Marietta GA 30067",
    "addr:housenumber":"890",
    "addr:postcode":"30067",
    "addr:street":"Oriole Ln",
    "iso:country":"US",
    "sg:address":"890 Oriole Ln",
    "sg:city":"Marietta",
    "sg:classifiers":[
        {
            "category":"Professional",
            "type":"Services"
        }
    ],
    "sg:phone":"+1 770 973 6994",
    "sg:postcode":"30067",
    "sg:province":"GA",
    "wof:name":"Grams Services Inc",
    "wof:placetype":"venue"
},
  "geometry": {"coordinates":[-84.493235,33.938695],"type":"Point"}
}