{
  "type": "Feature",
  "properties": {
    "addr:full":"2611 Springdale Rd SW Atlanta GA 30315",
    "addr:housenumber":"2611",
    "addr:postcode":"30315",
    "addr:street":"Springdale Rd Sw",
    "iso:country":"US",
    "sg:address":"2611 Springdale Rd SW",
    "sg:city":"Atlanta",
    "sg:classifiers":[
        {
            "category":"Manufacturing",
            "subcategory":"Chemicals & Compounds",
            "type":"Manufacturing & Wholesale Goods"
        }
    ],
    "sg:phone":"+1 404 669 9046",
    "sg:postcode":"30315",
    "sg:province":"GA",
    "sg:tags":[
        "preparation",
        "pharmaceutical",
        "mfg"
    ],
    "wof:name":"Henreys Interprises",
    "wof:placetype":"venue"
},
  "geometry": {"coordinates":[-84.41518000000001,33.684005],"type":"Point"}
}