{
  "type": "Feature",
  "properties": {
    "iso:country":"US",
    "sg:address":"993C Johnson Ferry Rd NE",
    "sg:city":"Atlanta",
    "sg:classifiers":[
        {
            "category":"Health Services",
            "subcategory":"Doctor",
            "type":"Services"
        }
    ],
    "sg:phone":"+1 404 255 8730",
    "sg:postcode":"30342",
    "sg:province":"GA",
    "wof:name":"Peachtree Perimeter OB Gyn PC",
    "wof:placetype":"venue"
},
  "geometry": {"coordinates":[-84.355903,33.90735],"type":"Point"}
}