{
  "type": "Feature",
  "properties": {
    "iso:country":"US",
    "sg:address":"1072 Baxter St",
    "sg:city":"Athens",
    "sg:classifiers":[
        {
            "category":"Personal",
            "subcategory":"Beauty Salon",
            "type":"Services"
        }
    ],
    "sg:phone":"+1 706 613 9899",
    "sg:postcode":"30606",
    "sg:province":"GA",
    "wof:name":"Kaleidoscope",
    "wof:placetype":"venue"
},
  "geometry": {"coordinates":[-83.399429,33.946982],"type":"Point"}
}