{
  "type": "Feature",
  "properties": {
    "iso:country":"US",
    "sg:address":"576 Fairview Rd",
    "sg:city":"Stockbridge",
    "sg:classifiers":[
        {
            "category":"Insurance",
            "subcategory":"Insurance Agent",
            "type":"Services"
        }
    ],
    "sg:phone":"+1 770 507 2900",
    "sg:postcode":"30281",
    "sg:province":"GA",
    "wof:name":"Bivens Insurance",
    "wof:placetype":"venue"
},
  "geometry": {"coordinates":[-84.227403,33.609614],"type":"Point"}
}