{
  "type": "Feature",
  "properties": {
    "addr:full":"320 Hospital Dr Thomson GA 30824",
    "addr:housenumber":"320",
    "addr:postcode":"30824",
    "addr:street":"Hospital Dr",
    "iso:country":"US",
    "sg:address":"320 Hospital Dr",
    "sg:city":"Thomson",
    "sg:classifiers":[
        {
            "category":"Health Services",
            "subcategory":"Clinic",
            "type":"Services"
        }
    ],
    "sg:phone":"+1 706 595 4170",
    "sg:postcode":"30824",
    "sg:province":"GA",
    "sg:tags":[
        "home",
        "care"
    ],
    "wof:name":"First Choice Medical",
    "wof:placetype":"venue"
},
  "geometry": {"coordinates":[-82.506756,33.459843],"type":"Point"}
}