{
  "type": "Feature",
  "properties": {
    "iso:country":"US",
    "sg:address":"60 Floyd Creek Church Rd",
    "sg:city":"Taylorsville",
    "sg:classifiers":[
        {
            "category":"Building & Trades",
            "subcategory":"Construction",
            "type":"Services"
        }
    ],
    "sg:phone":"+1 770 606 1646",
    "sg:postcode":"30178",
    "sg:province":"GA",
    "sg:tags":[
        "house"
    ],
    "wof:name":"Lemmings Construction Inc",
    "wof:placetype":"venue"
},
  "geometry": {"coordinates":[-84.92775399999999,34.097939],"type":"Point"}
}