{
  "type": "Feature",
  "properties": {
    "iso:country":"US",
    "sg:address":"766 Riverbend Dr",
    "sg:city":"Macon",
    "sg:classifiers":[
        {
            "category":"Building & Trades",
            "subcategory":"Construction",
            "type":"Services"
        }
    ],
    "sg:phone":"+1 478 755 1111",
    "sg:postcode":"31211",
    "sg:province":"GA",
    "sg:tags":[
        "house"
    ],
    "wof:name":"Taylor Contruction Co",
    "wof:placetype":"venue"
},
  "geometry": {"coordinates":[-83.64855799999999,32.888334],"type":"Point"}
}