{
  "type": "Feature",
  "properties": {
    "iso:country":"US",
    "sg:address":"1827 Powers Ferry Rd SE",
    "sg:city":"Atlanta",
    "sg:classifiers":[
        {
            "category":"Autos & Motor Vehicles",
            "subcategory":"Automobile Sales",
            "type":"Retail Goods"
        }
    ],
    "sg:phone":"+1 770 933 9555",
    "sg:postcode":"30339",
    "sg:province":"GA",
    "sg:tags":[
        "limo"
    ],
    "wof:name":"A Atlanta Classic Transport",
    "wof:placetype":"venue"
},
  "geometry": {"coordinates":[-84.464996,33.912701],"type":"Point"}
}