{
  "type": "Feature",
  "properties": {
    "addr:full":"301 S Main St Glennville GA 30427",
    "addr:housenumber":"301",
    "addr:postcode":"30427",
    "addr:street":"S Main St",
    "iso:country":"US",
    "sg:address":"301 S Main St",
    "sg:city":"Glennville",
    "sg:classifiers":[
        {
            "category":"Autos & Motor Vehicles",
            "subcategory":"Fuel & Gas Station",
            "type":"Retail Goods"
        }
    ],
    "sg:phone":"+1 912 654 4821",
    "sg:postcode":"30427",
    "sg:province":"GA",
    "sg:tags":[
        "grocery",
        "station",
        "gasoline"
    ],
    "wof:name":"Flash Foods Store 39",
    "wof:placetype":"venue"
},
  "geometry": {"coordinates":[-81.930031,31.933422],"type":"Point"}
}