{
  "type": "Feature",
  "properties": {
    "addr:full":"3080 McCall Dr Ste 10 Atlanta GA 30340",
    "addr:housenumber":"3080",
    "addr:postcode":"30340",
    "addr:street":"Mccall Dr Ste 10",
    "iso:country":"US",
    "sg:address":"3080 McCall Dr Ste 10",
    "sg:city":"Atlanta",
    "sg:classifiers":[
        {
            "category":"Shopping",
            "subcategory":"Stationery & Office Supplies",
            "type":"Retail Goods"
        }
    ],
    "sg:phone":"+1 770 457 9350",
    "sg:postcode":"30340",
    "sg:province":"GA",
    "sg:tags":[
        "equipment"
    ],
    "wof:name":"Pbi Professional Built Installation",
    "wof:placetype":"venue"
},
  "geometry": {"coordinates":[-84.258421,33.898518],"type":"Point"}
}