{
  "type": "Feature",
  "properties": {
    "iso:country":"US",
    "sg:address":"1470 Lanier Pl NE",
    "sg:city":"Atlanta",
    "sg:classifiers":[
        {
            "category":"Professional",
            "subcategory":"Management & Consulting",
            "type":"Services"
        }
    ],
    "sg:phone":"+1 404 249 9308",
    "sg:postcode":"30306",
    "sg:province":"GA",
    "sg:tags":[
        "consultant",
        "business"
    ],
    "wof:name":"Enterasia Inc",
    "wof:placetype":"venue"
},
  "geometry": {"coordinates":[-84.35381700000001,33.793041],"type":"Point"}
}