{
  "type": "Feature",
  "properties": {
    "iso:country":"US",
    "sg:address":"3894 C L Moore Rd",
    "sg:city":"Valdosta",
    "sg:classifiers":[
        {
            "category":"Building & Trades",
            "subcategory":"Construction",
            "type":"Services"
        }
    ],
    "sg:phone":"+1 229 241 0112",
    "sg:postcode":"31606",
    "sg:province":"GA",
    "sg:tags":[
        "contractor",
        "carpentry"
    ],
    "wof:name":"API Construction Inc",
    "wof:placetype":"venue"
},
  "geometry": {"coordinates":[-83.18168,30.902917],"type":"Point"}
}