{
  "type": "Feature",
  "properties": {
    "addr:full":"431 State Capitol SW Atlanta GA 30334",
    "addr:housenumber":"431",
    "addr:postcode":"30334",
    "addr:street":"State Capitol Sw",
    "iso:country":"US",
    "sg:address":"431 State Capitol SW",
    "sg:city":"Atlanta",
    "sg:classifiers":[
        {
            "category":"Museum",
            "type":"Entertainment"
        }
    ],
    "sg:phone":"+1 404 656 2846",
    "sg:postcode":"30334",
    "sg:province":"GA",
    "sg:website":"www.georgia.gov",
    "wof:name":"Georgia State Government",
    "wof:placetype":"venue"
},
  "geometry": {"coordinates":[-84.387959,33.749701],"type":"Point"}
}