{
  "type": "Feature",
  "properties": {
    "addr:full":"106 Shoppers Way Brunswick GA 31525",
    "addr:housenumber":"106",
    "addr:postcode":"31525",
    "addr:street":"Shoppers Way",
    "iso:country":"US",
    "sg:address":"106 Shoppers Way",
    "sg:city":"Brunswick",
    "sg:classifiers":[
        {
            "category":"Banks & Credit Unions",
            "subcategory":"Bank",
            "type":"Services"
        }
    ],
    "sg:phone":"+1 912 554 1500",
    "sg:postcode":"31525",
    "sg:province":"GA",
    "sg:tags":[
        "loan",
        "real estate"
    ],
    "wof:name":"Somerset Mortgage Corp",
    "wof:placetype":"venue"
},
  "geometry": {"coordinates":[-81.487897,31.219697],"type":"Point"}
}