{
  "type": "Feature",
  "properties": {
    "iso:country":"US",
    "sg:address":"4558 Roswell Rd",
    "sg:city":"Atlanta",
    "sg:classifiers":[
        {
            "category":"Organizations",
            "subcategory":"Religious Organization",
            "type":"Services"
        }
    ],
    "sg:phone":"+1 404 303 8821",
    "sg:postcode":"30342",
    "sg:province":"GA",
    "wof:name":"Covenant Love Inc",
    "wof:placetype":"venue"
},
  "geometry": {"coordinates":[-84.379874,33.87973],"type":"Point"}
}