{
  "type": "Feature",
  "properties": {
    "addr:full":"1008 Treecrest Pkwy Decatur GA 30035",
    "addr:housenumber":"1008",
    "addr:postcode":"30035",
    "addr:street":"Treecrest Pkwy",
    "iso:country":"US",
    "sg:address":"1008 Treecrest Pkwy",
    "sg:city":"Decatur",
    "sg:classifiers":[
        {
            "category":"Professional",
            "subcategory":"Management & Consulting",
            "type":"Services"
        }
    ],
    "sg:phone":"+1 404 216 3350",
    "sg:postcode":"30035",
    "sg:province":"GA",
    "sg:tags":[
        "process",
        "event",
        "risk",
        "special",
        "strategy"
    ],
    "wof:name":"Fisher Management Group",
    "wof:placetype":"venue"
},
  "geometry": {"coordinates":[-84.189554,33.715684],"type":"Point"}
}