{
  "type": "Feature",
  "properties": {
    "iso:country":"US",
    "sg:address":"916 Washington St",
    "sg:city":"Jefferson",
    "sg:classifiers":[
        {
            "category":"Retail",
            "subcategory":"Auto Repair",
            "type":"Services"
        },
        {
            "category":"Wholesale",
            "subcategory":"Auto Parts",
            "type":"Manufacturing & Wholesale Goods"
        }
    ],
    "sg:phone":"+1 706 367 4444",
    "sg:postcode":"30549",
    "sg:province":"GA",
    "sg:tags":[
        "transmission"
    ],
    "wof:name":"Angel's Transmission",
    "wof:placetype":"venue"
},
  "geometry": {"coordinates":[-83.584608,34.127852],"type":"Point"}
}