{
  "type": "Feature",
  "properties": {
    "addr:full":"989 N Grove St Dahlonega GA 30533",
    "addr:housenumber":"989",
    "addr:postcode":"30533",
    "addr:street":"N Grove St",
    "iso:country":"US",
    "sg:address":"989 N Grove St",
    "sg:city":"Dahlonega",
    "sg:classifiers":[
        {
            "category":"Shopping",
            "subcategory":"Music",
            "type":"Retail Goods"
        }
    ],
    "sg:phone":"+1 706 864 4335",
    "sg:postcode":"30533",
    "sg:province":"GA",
    "sg:tags":[
        "video",
        "disc",
        "tape",
        "cassette"
    ],
    "wof:name":"Video Shop",
    "wof:placetype":"venue"
},
  "geometry": {"coordinates":[-83.992784,34.545794],"type":"Point"}
}