{
  "type": "Feature",
  "properties": {
    "addr:full":"517 State Hwy 138 Riverdale GA 30274",
    "addr:housenumber":"517",
    "addr:postcode":"30274",
    "addr:street":"State Hwy 138",
    "iso:country":"US",
    "sg:address":"517 State Hwy 138",
    "sg:city":"Riverdale",
    "sg:classifiers":[
        {
            "category":"Professional",
            "type":"Services"
        }
    ],
    "sg:phone":"+1 770 210 2366",
    "sg:postcode":"30274",
    "sg:province":"GA",
    "sg:tags":[
        "arts",
        "artist"
    ],
    "wof:name":"Just Fine Art & More",
    "wof:placetype":"venue"
},
  "geometry": {"coordinates":[-84.406043,33.546394],"type":"Point"}
}