{
  "type": "Feature",
  "properties": {
    "addr:full":"127 Crown Park Dr Mcdonough GA 30253",
    "addr:housenumber":"127",
    "addr:postcode":"30253",
    "addr:street":"Crown Park Dr",
    "iso:country":"US",
    "sg:address":"127 Crown Park Dr",
    "sg:city":"Mcdonough",
    "sg:classifiers":[
        {
            "category":"Building & Trades",
            "subcategory":"Construction",
            "type":"Services"
        }
    ],
    "sg:phone":"+1 770 898 2545",
    "sg:postcode":"30253",
    "sg:province":"GA",
    "sg:tags":[
        "house",
        "contractor"
    ],
    "wof:name":"P B Lindsey Builders Inc",
    "wof:placetype":"venue"
},
  "geometry": {"coordinates":[-84.22671800000001,33.466555],"type":"Point"}
}