{
  "type": "Feature",
  "properties": {
    "iso:country":"US",
    "sg:address":"451 S Deshon Rd",
    "sg:city":"Lithonia",
    "sg:classifiers":[
        {
            "category":"Restaurant",
            "type":"Food & Drink"
        }
    ],
    "sg:menulink":"http://www.allmenus.com/ga/lithonia/154006-zaxbys/menu/",
    "sg:phone":"+1 770 465 3595",
    "sg:postcode":"30058",
    "sg:province":"GA",
    "sg:tags":[
        "american",
        "wing"
    ],
    "wof:name":"Zaxby's",
    "wof:placetype":"venue"
},
  "geometry": {"coordinates":[-84.10238099999999,33.783954],"type":"Point"}
}