{
  "type": "Feature",
  "properties": {
    "iso:country":"US",
    "sg:address":"109 Magnolia Rd",
    "sg:city":"Americus",
    "sg:classifiers":[
        {
            "category":"Building & Trades",
            "subcategory":"Construction",
            "type":"Services"
        }
    ],
    "sg:phone":"+1 229 924 9553",
    "sg:postcode":"31719",
    "sg:province":"GA",
    "sg:tags":[
        "roofing",
        "work",
        "gutter"
    ],
    "wof:name":"Bauder Seamless Gutters",
    "wof:placetype":"venue"
},
  "geometry": {"coordinates":[-84.291106,32.128331],"type":"Point"}
}