{
  "type": "Feature",
  "properties": {
    "iso:country":"US",
    "sg:address":"104 Zena Dr",
    "sg:city":"Cartersville",
    "sg:classifiers":[
        {
            "category":"Government",
            "subcategory":"Police Station",
            "type":"Public Place"
        }
    ],
    "sg:phone":"+1 770 382 5050",
    "sg:postcode":"30121",
    "sg:province":"GA",
    "sg:tags":[
        "sheriff"
    ],
    "sg:website":"www.bartow.org",
    "wof:name":"Bartow County Sheriff",
    "wof:placetype":"venue"
},
  "geometry": {"coordinates":[-84.779989,34.189816],"type":"Point"}
}