{
  "type": "Feature",
  "properties": {
    "addr:full":"95 S Peachtree St Norcross GA 30071",
    "addr:housenumber":"95",
    "addr:postcode":"30071",
    "addr:street":"S Peachtree St",
    "iso:country":"US",
    "sg:address":"95 S Peachtree St",
    "sg:city":"Norcross",
    "sg:classifiers":[
        {
            "category":"Banks & Credit Unions",
            "subcategory":"Financial Services",
            "type":"Services"
        },
        {
            "category":"Professional",
            "subcategory":"Credit Reporting & Collection",
            "type":"Services"
        }
    ],
    "sg:phone":"+1 770 449 9809",
    "sg:postcode":"30071",
    "sg:province":"GA",
    "sg:tags":[
        "repair",
        "investigator",
        "plan",
        "counseling",
        "debt"
    ],
    "wof:name":"A American Debt Consolidation",
    "wof:placetype":"venue"
},
  "geometry": {"coordinates":[-84.213618,33.941313],"type":"Point"}
}