{
  "type": "Feature",
  "properties": {
    "iso:country":"US",
    "sg:address":"1005 State Rte 32 E",
    "sg:city":"Ashburn",
    "sg:classifiers":[
        {
            "category":"Building & Trades",
            "subcategory":"Cleaning & Sanitation",
            "type":"Services"
        }
    ],
    "sg:phone":"+1 229 535 6672",
    "sg:postcode":"31714",
    "sg:province":"GA",
    "sg:tags":[
        "house",
        "maintenance"
    ],
    "wof:name":"Provisions Cleaning Service",
    "wof:placetype":"venue"
},
  "geometry": {"coordinates":[-83.836082,31.695548],"type":"Point"}
}