{
  "type": "Feature",
  "properties": {
    "addr:full":"2984 Panola Rd Lithonia GA 30038",
    "addr:housenumber":"2984",
    "addr:postcode":"30038",
    "addr:street":"Panola Rd",
    "iso:country":"US",
    "sg:address":"2984 Panola Rd",
    "sg:city":"Lithonia",
    "sg:classifiers":[
        {
            "category":"Retail",
            "subcategory":"Laundry & Dry Cleaning",
            "type":"Services"
        }
    ],
    "sg:phone":"+1 770 987 9253",
    "sg:postcode":"30038",
    "sg:province":"GA",
    "sg:tags":[
        "drycleaning",
        "plant",
        "cleaners"
    ],
    "wof:name":"Professional Cleaners",
    "wof:placetype":"venue"
},
  "geometry": {"coordinates":[-84.173125,33.697227],"type":"Point"}
}