{
  "type": "Feature",
  "properties": {
    "addr:full":"309 Turner McCall Blvd Rome GA 30161",
    "addr:housenumber":"309",
    "addr:postcode":"ga 30161",
    "addr:street":"Turner Mccall Blvd",
    "iso:country":"US",
    "sg:address":"309 Turner McCall Blvd",
    "sg:city":"Rome",
    "sg:classifiers":[
        {
            "category":"Shopping",
            "subcategory":"Pharmacy",
            "type":"Retail Goods"
        }
    ],
    "sg:phone":"+1 706 295 5713",
    "sg:postcode":"30161",
    "sg:province":"GA",
    "wof:name":"Medicine Shoppe Pharmacy",
    "wof:placetype":"venue"
},
  "geometry": {"coordinates":[-85.178889,34.260408],"type":"Point"}
}