{
  "type": "Feature",
  "properties": {
    "iso:country":"US",
    "sg:address":"740 Arlington Way",
    "sg:city":"Canton",
    "sg:classifiers":[
        {
            "category":"Building & Trades",
            "subcategory":"Landscaping Services",
            "type":"Services"
        }
    ],
    "sg:phone":"+1 770 720 8281",
    "sg:postcode":"30114",
    "sg:province":"GA",
    "sg:tags":[
        "landscape"
    ],
    "wof:name":"Shane Stephenson Landscap",
    "wof:placetype":"venue"
},
  "geometry": {"coordinates":[-84.481936,34.335899],"type":"Point"}
}