{
  "type": "Feature",
  "properties": {
    "addr:full":"382 Woodland Trails Rd Dublin GA 31021",
    "addr:housenumber":"382",
    "addr:postcode":"31021",
    "addr:street":"Woodland Trails Rd",
    "iso:country":"US",
    "sg:address":"382 Woodland Trails Rd",
    "sg:city":"Dublin",
    "sg:classifiers":[
        {
            "category":"Social Services",
            "type":"Services"
        }
    ],
    "sg:phone":"+1 478 275 9010",
    "sg:postcode":"31021",
    "sg:province":"GA",
    "sg:tags":[
        "organization",
        "welfare"
    ],
    "wof:name":"Stepping Stone",
    "wof:placetype":"venue"
},
  "geometry": {"coordinates":[-82.95599799999999,32.570742],"type":"Point"}
}