{
  "type": "Feature",
  "properties": {
    "addr:full":"1599 Memorial Dr SE Atlanta GA 30317",
    "addr:housenumber":"1599",
    "addr:postcode":"30317",
    "addr:street":"Memorial Dr Se",
    "iso:country":"US",
    "sg:address":"1599 Memorial Dr SE",
    "sg:city":"Atlanta",
    "sg:classifiers":[
        {
            "category":"Shopping",
            "subcategory":"Department Store",
            "type":"Retail Goods"
        }
    ],
    "sg:phone":"+1 404 377 3094",
    "sg:postcode":"30317",
    "sg:province":"GA",
    "sg:website":"http://www.familydollar.com",
    "wof:name":"Family Dollar Stores",
    "wof:placetype":"venue"
},
  "geometry": {"coordinates":[-84.33548,33.747509],"type":"Point"}
}