{
  "type": "Feature",
  "properties": {
    "iso:country":"US",
    "sg:address":"1261 Parker Rd SE",
    "sg:city":"Conyers",
    "sg:classifiers":[
        {
            "category":"Organizations",
            "subcategory":"Religious Organization",
            "type":"Services"
        }
    ],
    "sg:phone":"+1 770 922 9331",
    "sg:postcode":"30094",
    "sg:province":"GA",
    "sg:tags":[
        "church"
    ],
    "wof:name":"South Coastal Dist Weslyan Chr",
    "wof:placetype":"venue"
},
  "geometry": {"coordinates":[-84.020349,33.656706],"type":"Point"}
}