{
  "type": "Feature",
  "properties": {
    "addr:full":"408 Couper Ave Saint Simons Island GA 31522",
    "addr:housenumber":"408",
    "addr:postcode":"31522",
    "addr:street":"Couper Ave",
    "iso:country":"US",
    "sg:address":"408 Couper Ave",
    "sg:city":"Saint Simons Island",
    "sg:classifiers":[
        {
            "category":"Health Services",
            "subcategory":"Clinic",
            "type":"Services"
        }
    ],
    "sg:phone":"+1 912 638 4249",
    "sg:postcode":"31522",
    "sg:province":"GA",
    "sg:tags":[
        "specialty",
        "outpatient"
    ],
    "wof:name":"Novacare Orthotics Prosthetics",
    "wof:placetype":"venue"
},
  "geometry": {"coordinates":[-81.382064,31.1962],"type":"Point"}
}