{
  "type": "Feature",
  "properties": {
    "iso:country":"US",
    "sg:address":"4603 Lawrenceville Hwy",
    "sg:city":"Lilburn",
    "sg:classifiers":[
        {
            "category":"Organizations",
            "subcategory":"Religious Organization",
            "type":"Services"
        }
    ],
    "sg:phone":"+1 770 921 6365",
    "sg:postcode":"30047",
    "sg:province":"GA",
    "wof:name":"Living Word Assembly of God",
    "wof:placetype":"venue"
},
  "geometry": {"coordinates":[-84.13543799999999,33.899317],"type":"Point"}
}