{
  "type": "Feature",
  "properties": {
    "iso:country":"US",
    "sg:address":"724 E Pine St",
    "sg:city":"Jesup",
    "sg:classifiers":[
        {
            "category":"Food & Beverages",
            "subcategory":"Groceries & Convenience Stores",
            "type":"Retail Goods"
        }
    ],
    "sg:phone":"+1 912 588 0143",
    "sg:postcode":"31546",
    "sg:province":"GA",
    "wof:name":"Keep Sakes",
    "wof:placetype":"venue"
},
  "geometry": {"coordinates":[-81.873035,31.60081],"type":"Point"}
}