{
  "type": "Feature",
  "properties": {
    "iso:country":"US",
    "sg:address":"912 Blanton St",
    "sg:city":"Valdosta",
    "sg:classifiers":[
        {
            "category":"Building & Trades",
            "subcategory":"Construction",
            "type":"Services"
        }
    ],
    "sg:phone":"+1 229 247 5127",
    "sg:postcode":"31601",
    "sg:province":"GA",
    "sg:tags":[
        "roofing",
        "industrial",
        "contractors-commercial",
        "contractor"
    ],
    "wof:name":"Winnersville Roofing Co",
    "wof:placetype":"venue"
},
  "geometry": {"coordinates":[-83.302983,30.845518],"type":"Point"}
}