{
  "type": "Feature",
  "properties": {
    "addr:full":"1874 Moccasin Gap Rd Lula GA 30554",
    "addr:housenumber":"1874",
    "addr:postcode":"30554",
    "addr:street":"Moccasin Gap Rd",
    "iso:country":"US",
    "sg:address":"1874 Moccasin Gap Rd",
    "sg:city":"Lula",
    "sg:classifiers":[
        {
            "category":"Manufacturing",
            "subcategory":"Tools & Machinery",
            "type":"Manufacturing & Wholesale Goods"
        }
    ],
    "sg:phone":"+1 770 869 1190",
    "sg:postcode":"30554",
    "sg:province":"GA",
    "sg:tags":[
        "poultry",
        "equipment",
        "processing",
        "mfg"
    ],
    "wof:name":"Thurston Dodd Welding Shop",
    "wof:placetype":"venue"
},
  "geometry": {"coordinates":[-83.62343300000001,34.399686],"type":"Point"}
}