{
  "type": "Feature",
  "properties": {
    "addr:full":"215 New Franklin Rd La Grange GA 30240",
    "addr:housenumber":"215",
    "addr:postcode":"30240",
    "addr:street":"New Franklin Rd",
    "iso:country":"US",
    "sg:address":"215 New Franklin Rd",
    "sg:city":"La Grange",
    "sg:classifiers":[
        {
            "category":"Restaurant",
            "type":"Food & Drink"
        }
    ],
    "sg:phone":"+1 706 882 2628",
    "sg:postcode":"30240",
    "sg:province":"GA",
    "sg:tags":[
        "seafood"
    ],
    "wof:name":"Long John Silvers",
    "wof:placetype":"venue"
},
  "geometry": {"coordinates":[-85.028667,33.055868],"type":"Point"}
}