{
  "type": "Feature",
  "properties": {
    "addr:full":"4307 Beachview Dr SE Smyrna GA 30082",
    "addr:housenumber":"4307",
    "addr:postcode":"30082",
    "addr:street":"Beachview Dr Se",
    "iso:country":"US",
    "sg:address":"4307 Beachview Dr SE",
    "sg:city":"Smyrna",
    "sg:classifiers":[
        {
            "category":"Real Estate",
            "subcategory":"Architect",
            "type":"Services"
        }
    ],
    "sg:phone":"+1 770 333 9502",
    "sg:postcode":"30082",
    "sg:province":"GA",
    "sg:tags":[
        "architectural"
    ],
    "wof:name":"Pastor Design Inc",
    "wof:placetype":"venue"
},
  "geometry": {"coordinates":[-84.513606,33.848518],"type":"Point"}
}