{
  "type": "Feature",
  "properties": {
    "iso:country":"US",
    "sg:address":"880 Indian Trail Lilburn Rd NW",
    "sg:city":"Lilburn",
    "sg:classifiers":[
        {
            "category":"Personal",
            "subcategory":"Beauty Salon",
            "type":"Services"
        }
    ],
    "sg:phone":"+1 770 935 6707",
    "sg:postcode":"30047",
    "sg:province":"GA",
    "sg:tags":[
        "manicuring"
    ],
    "wof:name":"Nails By Mai Huynh",
    "wof:placetype":"venue"
},
  "geometry": {"coordinates":[-84.15524499999999,33.905522],"type":"Point"}
}