{
  "type": "Feature",
  "properties": {
    "iso:country":"US",
    "sg:address":"5665 Peachtree Dunwoody Rd NE",
    "sg:city":"Atlanta",
    "sg:classifiers":[
        {
            "category":"Health Services",
            "subcategory":"Doctor",
            "type":"Services"
        }
    ],
    "sg:phone":"+1 404 851 5400",
    "sg:postcode":"30342",
    "sg:province":"GA",
    "wof:name":"Knapp William S",
    "wof:placetype":"venue"
},
  "geometry": {"coordinates":[-84.35166599999999,33.908809],"type":"Point"}
}