{
  "type": "Feature",
  "properties": {
    "iso:country":"US",
    "sg:address":"111 Northwood Dr NW",
    "sg:city":"Milledgeville",
    "sg:classifiers":[
        {
            "category":"Shopping",
            "subcategory":"Used Merchandise",
            "type":"Retail Goods"
        }
    ],
    "sg:phone":"+1 478 451 5460",
    "sg:postcode":"31061",
    "sg:province":"GA",
    "wof:name":"Fourfourty One Antiques",
    "wof:placetype":"venue"
},
  "geometry": {"coordinates":[-83.285577,33.13283],"type":"Point"}
}