{
  "type": "Feature",
  "properties": {
    "addr:full":"111 Woolman Ln Griffin GA 30223",
    "addr:housenumber":"111",
    "addr:postcode":"30223",
    "addr:street":"Woolman Ln",
    "iso:country":"US",
    "sg:address":"111 Woolman Ln",
    "sg:city":"Griffin",
    "sg:classifiers":[
        {
            "category":"Manufacturing",
            "subcategory":"Furniture",
            "type":"Manufacturing & Wholesale Goods"
        }
    ],
    "sg:phone":"+1 770 229 4421",
    "sg:postcode":"30223",
    "sg:province":"GA",
    "sg:tags":[
        "mfg",
        "cabinet"
    ],
    "wof:name":"Fj Woodworks",
    "wof:placetype":"venue"
},
  "geometry": {"coordinates":[-84.408322,33.276935],"type":"Point"}
}