{
  "type": "Feature",
  "properties": {
    "iso:country":"US",
    "sg:address":"1815 Satellite Blvd. Bldg. 200",
    "sg:city":"Duluth",
    "sg:classifiers":[
        {
            "category":"Shopping",
            "subcategory":"Stationery & Office Supplies",
            "type":"Retail Goods"
        }
    ],
    "sg:phone":"+1 770 558 8001",
    "sg:postcode":"30097",
    "sg:province":"GA",
    "sg:tags":[
        "equipment"
    ],
    "sg:website":"http://www.mydigitalofficesolutions.com",
    "wof:name":"Digital Office Solutions",
    "wof:placetype":"venue"
},
  "geometry": {"coordinates":[-84.087593,33.996466],"type":"Point"}
}