{
  "type": "Feature",
  "properties": {
    "addr:full":"2399 Piedmont Rd NE Atlanta GA 30324",
    "addr:housenumber":"2399",
    "addr:postcode":"30324",
    "addr:street":"Piedmont Rd Ne",
    "iso:country":"US",
    "sg:address":"2399 Piedmont Rd NE",
    "sg:city":"Atlanta",
    "sg:classifiers":[
        {
            "category":"Retail",
            "subcategory":"Auto Repair",
            "type":"Services"
        }
    ],
    "sg:phone":"+1 404 231 0032",
    "sg:postcode":"30324",
    "sg:province":"GA",
    "sg:website":"www.pepboys.com",
    "wof:name":"Pep Boys Auto",
    "wof:placetype":"venue"
},
  "geometry": {"coordinates":[-84.367559,33.820599],"type":"Point"}
}