{
  "type": "Feature",
  "properties": {
    "iso:country":"US",
    "sg:address":"1545 Peachtree St NE Ste 115",
    "sg:city":"Atlanta",
    "sg:classifiers":[
        {
            "category":"Restaurant",
            "type":"Food & Drink"
        },
        {
            "category":"Bakery",
            "type":"Food & Drink"
        }
    ],
    "sg:phone":"+1 404 870 0640",
    "sg:postcode":"30309",
    "sg:province":"GA",
    "sg:website":"www.jolikobe.com/",
    "wof:name":"Joli Kobe Bakery and Bistro",
    "wof:placetype":"venue"
},
  "geometry": {"coordinates":[-84.389056,33.797288],"type":"Point"}
}