{
  "type": "Feature",
  "properties": {
    "addr:full":"3915 Johns Creek Pkwy Suwanee GA 30024",
    "addr:housenumber":"3915",
    "addr:postcode":"30024",
    "addr:street":"Johns Creek Pkwy",
    "iso:country":"US",
    "sg:address":"3915 Johns Creek Pkwy",
    "sg:city":"Suwanee",
    "sg:classifiers":[
        {
            "category":"Health Services",
            "subcategory":"Doctor",
            "type":"Services"
        }
    ],
    "sg:phone":"+1 770 814 8883",
    "sg:postcode":"30024",
    "sg:province":"GA",
    "sg:tags":[
        "physician",
        "pediatrics-emergency",
        "pediatrics",
        "surgeons",
        "medicine",
        "surgeon"
    ],
    "wof:name":"Georgetown Pediatrics",
    "wof:placetype":"venue"
},
  "geometry": {"coordinates":[-84.164688,34.071514],"type":"Point"}
}