{
  "type": "Feature",
  "properties": {
    "addr:full":"530 State Rte 81 W Mc Donough GA 30253",
    "addr:housenumber":"530",
    "addr:postcode":"30253",
    "addr:street":"State Rte 81 W Mc Donough",
    "iso:country":"US",
    "sg:address":"530 State Rte 81 W",
    "sg:city":"Mc Donough",
    "sg:classifiers":[
        {
            "category":"Banks & Credit Unions",
            "subcategory":"Bank",
            "type":"Services"
        }
    ],
    "sg:phone":"+1 770 957 0408",
    "sg:postcode":"30253",
    "sg:province":"GA",
    "sg:tags":[
        "national",
        "commercial"
    ],
    "wof:name":"McDonough Financial Center BR",
    "wof:placetype":"venue"
},
  "geometry": {"coordinates":[-84.199442,33.431671],"type":"Point"}
}