{
  "type": "Feature",
  "properties": {
    "addr:full":"416 State Hwy 82 S Jefferson GA 30549",
    "addr:housenumber":"416",
    "addr:postcode":"30549",
    "addr:street":"State Hwy 82 S",
    "iso:country":"US",
    "sg:address":"416 State Hwy 82 S",
    "sg:city":"Jefferson",
    "sg:classifiers":[
        {
            "category":"Retail",
            "subcategory":"Repair Shop",
            "type":"Services"
        }
    ],
    "sg:phone":"+1 706 367 8856",
    "sg:postcode":"30549",
    "sg:province":"GA",
    "sg:tags":[
        "upholsterer"
    ],
    "wof:name":"Clark Upholstery",
    "wof:placetype":"venue"
},
  "geometry": {"coordinates":[-83.56645399999999,34.073014],"type":"Point"}
}