{
  "type": "Feature",
  "properties": {
    "iso:country":"US",
    "sg:address":"2499 Ivy Plantation Dr",
    "sg:city":"Buford",
    "sg:classifiers":[
        {
            "category":"Professional",
            "subcategory":"Detective & Security Services",
            "type":"Services"
        }
    ],
    "sg:phone":"+1 770 614 3454",
    "sg:postcode":"30519",
    "sg:province":"GA",
    "sg:tags":[
        "system"
    ],
    "wof:name":"Coliant Systems LLC",
    "wof:placetype":"venue"
},
  "geometry": {"coordinates":[-83.950806,34.068014],"type":"Point"}
}