{
  "type": "Feature",
  "properties": {
    "iso:country":"US",
    "sg:address":"2519 Cobb Pkwy",
    "sg:city":"Kennesaw",
    "sg:classifiers":[
        {
            "category":"Autos & Motor Vehicles",
            "subcategory":"Automobile Sales",
            "type":"Retail Goods"
        }
    ],
    "sg:phone":"+1 770 425 1618",
    "sg:postcode":"30152",
    "sg:province":"GA",
    "sg:tags":[
        "used"
    ],
    "wof:name":"Dwms Inc",
    "wof:placetype":"venue"
},
  "geometry": {"coordinates":[-84.61838299999999,34.017956],"type":"Point"}
}