{
  "type": "Feature",
  "properties": {
    "addr:full":"539 Hwy 53 West SW Calhoun GA 30701",
    "addr:housenumber":"539",
    "addr:postcode":"30701",
    "addr:street":"Hwy 53 West Sw",
    "iso:country":"US",
    "sg:address":"539 Hwy 53 West SW",
    "sg:city":"Calhoun",
    "sg:classifiers":[
        {
            "category":"Banks & Credit Unions",
            "subcategory":"Bank",
            "type":"Services"
        }
    ],
    "sg:phone":"+1 706 625 4608",
    "sg:postcode":"30701",
    "sg:province":"GA",
    "sg:tags":[
        "personal",
        "institution"
    ],
    "wof:name":"Advance America",
    "wof:placetype":"venue"
},
  "geometry": {"coordinates":[-84.964454,34.47521],"type":"Point"}
}