{
  "type": "Feature",
  "properties": {
    "iso:country":"US",
    "sg:address":"5000 Clark Howell Hwy",
    "sg:city":"Atlanta",
    "sg:classifiers":[
        {
            "category":"Freight",
            "type":"Transportation"
        }
    ],
    "sg:phone":"+1 404 767 7119",
    "sg:postcode":"30349",
    "sg:province":"GA",
    "sg:tags":[
        "arrangement"
    ],
    "wof:name":"Triad Intl Frt Fwdg USA Ltd",
    "wof:placetype":"venue"
},
  "geometry": {"coordinates":[-84.40304399999999,33.615286],"type":"Point"}
}