{
  "type": "Feature",
  "properties": {
    "iso:country":"US",
    "sg:address":"6539 State Hwy 42",
    "sg:city":"Rex",
    "sg:classifiers":[
        {
            "category":"Health Services",
            "subcategory":"Doctor",
            "type":"Services"
        }
    ],
    "sg:phone":"+1 404 363 2441",
    "sg:postcode":"30273",
    "sg:province":"GA",
    "sg:tags":[
        "physician",
        "surgeon"
    ],
    "wof:name":"Medcert",
    "wof:placetype":"venue"
},
  "geometry": {"coordinates":[-84.28166,33.577149],"type":"Point"}
}