{
  "type": "Feature",
  "properties": {
    "iso:country":"US",
    "sg:address":"5658 Riverdale Rd",
    "sg:city":"Atlanta",
    "sg:classifiers":[
        {
            "category":"Shopping",
            "subcategory":"Florist",
            "type":"Retail Goods"
        }
    ],
    "sg:phone":"+1 770 996 1584",
    "sg:postcode":"30349",
    "sg:province":"GA",
    "wof:name":"Eagles Floral",
    "wof:placetype":"venue"
},
  "geometry": {"coordinates":[-84.428854,33.599764],"type":"Point"}
}