{
  "type": "Feature",
  "properties": {
    "addr:full":"112 Kings Ridge Dr Peachtree City GA 30269",
    "addr:housenumber":"112",
    "addr:postcode":"30269",
    "addr:street":"Kings Ridge Dr",
    "iso:country":"US",
    "sg:address":"112 Kings Ridge Dr",
    "sg:city":"Peachtree City",
    "sg:classifiers":[
        {
            "category":"Professional",
            "subcategory":"Lawyer & Legal Services",
            "type":"Services"
        }
    ],
    "sg:phone":"+1 404 209 6292",
    "sg:postcode":"30269",
    "sg:province":"GA",
    "wof:name":"Cathy K Feaster",
    "wof:placetype":"venue"
},
  "geometry": {"coordinates":[-84.61045799999999,33.404806],"type":"Point"}
}