{
  "type": "Feature",
  "properties": {
    "iso:country":"US",
    "sg:address":"545 S Milledge Ave",
    "sg:city":"Athens",
    "sg:classifiers":[
        {
            "category":"Organizations",
            "subcategory":"Community Association",
            "type":"Services"
        }
    ],
    "sg:phone":"+1 706 549 6950",
    "sg:postcode":"30605",
    "sg:province":"GA",
    "sg:tags":[
        "fraternal"
    ],
    "wof:name":"Alpha Kappa Psi Frat",
    "wof:placetype":"venue"
},
  "geometry": {"coordinates":[-83.387394,33.948553],"type":"Point"}
}