{
  "type": "Feature",
  "properties": {
    "iso:country":"US",
    "sg:address":"225 8th St",
    "sg:city":"Augusta",
    "sg:classifiers":[
        {
            "category":"Banks & Credit Unions",
            "subcategory":"Bank",
            "type":"Services"
        }
    ],
    "sg:phone":"+1 706 724 8785",
    "sg:postcode":"30901",
    "sg:province":"GA",
    "sg:tags":[
        "institution",
        "business"
    ],
    "wof:name":"Colvin Finance Co",
    "wof:placetype":"venue"
},
  "geometry": {"coordinates":[-81.96581500000001,33.474561],"type":"Point"}
}