{
  "type": "Feature",
  "properties": {
    "addr:full":"49 W Main St Buford GA 30518",
    "addr:housenumber":"49",
    "addr:postcode":"30518",
    "addr:street":"W Main St",
    "iso:country":"US",
    "sg:address":"49 W Main St",
    "sg:city":"Buford",
    "sg:classifiers":[
        {
            "category":"Shopping",
            "subcategory":"Gifts & Souvenirs",
            "type":"Retail Goods"
        }
    ],
    "sg:phone":"+1 770 932 9990",
    "sg:postcode":"30518",
    "sg:province":"GA",
    "sg:tags":[
        "shop"
    ],
    "wof:name":"Tresor Unique",
    "wof:placetype":"venue"
},
  "geometry": {"coordinates":[-84.007645,34.119191],"type":"Point"}
}