{
  "type": "Feature",
  "properties": {
    "iso:country":"US",
    "sg:address":"63 Peebles Dr",
    "sg:city":"Forsyth",
    "sg:classifiers":[
        {
            "category":"Manufacturing",
            "subcategory":"Metals",
            "type":"Manufacturing & Wholesale Goods"
        }
    ],
    "sg:phone":"+1 478 994 3787",
    "sg:postcode":"31029",
    "sg:province":"GA",
    "sg:tags":[
        "plate",
        "work",
        "fabricated",
        "mfg"
    ],
    "wof:name":"Marley Cooling Technologies",
    "wof:placetype":"venue"
},
  "geometry": {"coordinates":[-83.98136100000001,32.96694],"type":"Point"}
}