{
  "type": "Feature",
  "properties": {
    "addr:full":"40 Villa Rosa Rd Temple GA 30179",
    "addr:housenumber":"40",
    "addr:postcode":"30179",
    "addr:street":"Villa Rosa Rd",
    "iso:country":"US",
    "sg:address":"40 Villa Rosa Rd",
    "sg:city":"Temple",
    "sg:classifiers":[
        {
            "category":"Health Services",
            "subcategory":"Clinic",
            "type":"Services"
        },
        {
            "category":"Social Services",
            "subcategory":"Child Care",
            "type":"Services"
        },
        {
            "category":"Health Services",
            "subcategory":"Chiropractor",
            "type":"Services"
        }
    ],
    "sg:phone":"+1 770 562 8590",
    "sg:postcode":"30179",
    "sg:province":"GA",
    "sg:tags":[
        "product",
        "back",
        "chiropractic"
    ],
    "wof:name":"Temple Chiropractic",
    "wof:placetype":"venue"
},
  "geometry": {"coordinates":[-85.02522999999999,33.72028],"type":"Point"}
}