{
  "type": "Feature",
  "properties": {
    "addr:full":"250 Scientific Dr NW Norcross GA 30092",
    "addr:housenumber":"250",
    "addr:postcode":"30092",
    "addr:street":"Scientific Dr Nw",
    "iso:country":"US",
    "sg:address":"250 Scientific Dr NW",
    "sg:city":"Norcross",
    "sg:classifiers":[
        {
            "category":"Professional",
            "subcategory":"Art Services",
            "type":"Services"
        }
    ],
    "sg:phone":"+1 770 446 3340",
    "sg:postcode":"30092",
    "sg:province":"GA",
    "sg:tags":[
        "photographer"
    ],
    "wof:name":"Fuji Photo Film USA Inc",
    "wof:placetype":"venue"
},
  "geometry": {"coordinates":[-84.22284000000001,33.965144],"type":"Point"}
}