{
  "type": "Feature",
  "properties": {
    "iso:country":"US",
    "sg:address":"9185 Duran Cir",
    "sg:city":"Gainesville",
    "sg:classifiers":[
        {
            "category":"Building & Trades",
            "subcategory":"Construction",
            "type":"Services"
        }
    ],
    "sg:phone":"+1 770 888 9080",
    "sg:postcode":"30506",
    "sg:province":"GA",
    "sg:tags":[
        "general",
        "industrial",
        "commercial",
        "contractor"
    ],
    "wof:name":"Frontier Contracting Co Inc",
    "wof:placetype":"venue"
},
  "geometry": {"coordinates":[-83.97875500000001,34.237258],"type":"Point"}
}