{
  "type": "Feature",
  "properties": {
    "iso:country":"US",
    "sg:address":"1601 Lake Douglas Rd",
    "sg:city":"Bainbridge",
    "sg:classifiers":[
        {
            "category":"Wholesale",
            "subcategory":"Scrap",
            "type":"Manufacturing & Wholesale Goods"
        }
    ],
    "sg:phone":"+1 229 246 3222",
    "sg:postcode":"39819",
    "sg:province":"FL",
    "sg:tags":[
        "material"
    ],
    "wof:name":"Durham Scrap & Iron LLC",
    "wof:placetype":"venue"
},
  "geometry": {"coordinates":[-84.559888,30.888019],"type":"Point"}
}