{
  "type": "Feature",
  "properties": {
    "addr:full":"2600 Century Pkwy NE Atlanta GA 30345",
    "addr:housenumber":"2600",
    "addr:postcode":"30345",
    "addr:street":"Century Pkwy Ne",
    "iso:country":"US",
    "sg:address":"2600 Century Pkwy NE",
    "sg:city":"Atlanta",
    "sg:classifiers":[
        {
            "category":"Real Estate",
            "subcategory":"Real Estate Services",
            "type":"Services"
        },
        {
            "category":"Banks & Credit Unions",
            "subcategory":"Financial Services",
            "type":"Services"
        }
    ],
    "sg:phone":"+1 404 327 5114",
    "sg:postcode":"30345",
    "sg:province":"GA",
    "sg:tags":[
        "loan",
        "processing"
    ],
    "wof:name":"Kenneth Garcia",
    "wof:placetype":"venue"
},
  "geometry": {"coordinates":[-84.30619900000001,33.848701],"type":"Point"}
}