{
  "type": "Feature",
  "properties": {
    "addr:full":"2420 Bethany Rd Alpharetta GA 30004",
    "addr:housenumber":"2420",
    "addr:postcode":"30004",
    "addr:street":"Bethany Rd",
    "iso:country":"US",
    "sg:address":"2420 Bethany Rd",
    "sg:city":"Alpharetta",
    "sg:classifiers":[
        {
            "category":"Professional",
            "subcategory":"Management & Consulting",
            "type":"Services"
        }
    ],
    "sg:phone":"+1 678 366 8009",
    "sg:postcode":"30004",
    "sg:province":"GA",
    "sg:tags":[
        "consultant",
        "business"
    ],
    "wof:name":"CVR Assoc Inc",
    "wof:placetype":"venue"
},
  "geometry": {"coordinates":[-84.29328,34.116022],"type":"Point"}
}