{
  "type": "Feature",
  "properties": {
    "addr:full":"5695 Cub Ct SW Stone Mountain GA 30087",
    "addr:housenumber":"5695",
    "addr:postcode":"30087",
    "addr:street":"Cub Ct Sw",
    "iso:country":"US",
    "sg:address":"5695 Cub Ct SW",
    "sg:city":"Stone Mountain",
    "sg:classifiers":[
        {
            "category":"Education",
            "subcategory":"Dance Studio",
            "type":"Public Place"
        }
    ],
    "sg:phone":"+1 770 925 7687",
    "sg:postcode":"30087",
    "sg:province":"GA",
    "wof:name":"Dance Bruce Etal",
    "wof:placetype":"venue"
},
  "geometry": {"coordinates":[-84.14918900000001,33.852913],"type":"Point"}
}