{
  "type": "Feature",
  "properties": {
    "iso:country":"US",
    "sg:address":"935 Telfair St",
    "sg:city":"Augusta",
    "sg:classifiers":[
        {
            "category":"Professional",
            "subcategory":"Employment Agencies",
            "type":"Services"
        }
    ],
    "sg:phone":"+1 706 724 7777",
    "sg:postcode":"30901",
    "sg:province":"GA",
    "sg:tags":[
        "help",
        "contractor"
    ],
    "wof:name":"Labor Finders",
    "wof:placetype":"venue"
},
  "geometry": {"coordinates":[-81.971002,33.473556],"type":"Point"}
}