{
  "type": "Feature",
  "properties": {
    "addr:full":"2529 Peachwood Cir NE Atlanta GA 30345",
    "addr:postcode":"2529;30345",
    "addr:street":"Peachwood Cir Ne",
    "iso:country":"US",
    "sg:address":"2529 Peachwood Cir NE",
    "sg:city":"Atlanta",
    "sg:classifiers":[
        {
            "category":"Real Estate",
            "subcategory":"Real Estate Operator",
            "type":"Services"
        }
    ],
    "sg:phone":"+1 404 325 7072",
    "sg:postcode":"30345",
    "sg:province":"GA",
    "sg:tags":[
        "apartment"
    ],
    "wof:name":"Tara Trail Apartments",
    "wof:placetype":"venue"
},
  "geometry": {"coordinates":[-84.291217,33.857589],"type":"Point"}
}