{
  "type": "Feature",
  "properties": {
    "iso:country":"US",
    "sg:address":"72 Marietta St",
    "sg:city":"Atlanta",
    "sg:classifiers":[
        {
            "category":"Restaurant",
            "type":"Food & Drink"
        }
    ],
    "sg:phone":"+1 404 526 5226",
    "sg:postcode":"30303",
    "sg:province":"GA",
    "sg:tags":[
        "eating"
    ],
    "wof:name":"Southern Foodservice Mngm Inc",
    "wof:placetype":"venue"
},
  "geometry": {"coordinates":[-84.39211299999999,33.756442],"type":"Point"}
}