{
  "type": "Feature",
  "properties": {
    "iso:country":"US",
    "sg:address":"712 Winer Industrial Way",
    "sg:city":"Lawrenceville",
    "sg:classifiers":[
        {
            "category":"Freight",
            "type":"Transportation"
        }
    ],
    "sg:phone":"+1 770 963 4441",
    "sg:postcode":"30045",
    "sg:province":"GA",
    "sg:tags":[
        "hauling",
        "trucking"
    ],
    "wof:name":"James L Bruce Trucking Co",
    "wof:placetype":"venue"
},
  "geometry": {"coordinates":[-84.012343,33.958122],"type":"Point"}
}