{
  "type": "Feature",
  "properties": {
    "iso:country":"US",
    "sg:address":"828 Clemont Dr NE",
    "sg:city":"Atlanta",
    "sg:classifiers":[
        {
            "category":"Communications",
            "subcategory":"Film & Video Production",
            "type":"Services"
        }
    ],
    "sg:phone":"+1 404 355 6161",
    "sg:postcode":"30306",
    "sg:province":"GA",
    "sg:tags":[
        "studio",
        "facility"
    ],
    "wof:name":"Crews",
    "wof:placetype":"venue"
},
  "geometry": {"coordinates":[-84.360373,33.783081],"type":"Point"}
}