{
  "type": "Feature",
  "properties": {
    "addr:full":"1039 Avery Creek Dr Woodstock GA 30188",
    "addr:housenumber":"1039",
    "addr:postcode":"30188",
    "addr:street":"Avery Creek Dr",
    "iso:country":"US",
    "sg:address":"1039 Avery Creek Dr",
    "sg:city":"Woodstock",
    "sg:classifiers":[
        {
            "category":"Education",
            "subcategory":"Vocational School",
            "type":"Public Place"
        }
    ],
    "sg:phone":"+1 770 401 5372",
    "sg:postcode":"30188",
    "sg:province":"GA",
    "sg:tags":[
        "training",
        "computer"
    ],
    "wof:name":"Computer Techeez",
    "wof:placetype":"venue"
},
  "geometry": {"coordinates":[-84.450852,34.149207],"type":"Point"}
}