{
  "type": "Feature",
  "properties": {
    "addr:full":"11285 Elkins Rd Roswell GA 30076",
    "addr:housenumber":"11285",
    "addr:postcode":"30076",
    "addr:street":"Elkins Rd",
    "iso:country":"US",
    "sg:address":"11285 Elkins Rd",
    "sg:city":"Roswell",
    "sg:classifiers":[
        {
            "category":"Professional",
            "subcategory":"Accounting & Tax Preparation",
            "type":"Services"
        }
    ],
    "sg:phone":"+1 770 664 3634",
    "sg:postcode":"30076",
    "sg:province":"GA",
    "wof:name":"Bowen McElrath & Co LLC",
    "wof:placetype":"venue"
},
  "geometry": {"coordinates":[-84.33459999999999,34.052597],"type":"Point"}
}