{
  "type": "Feature",
  "properties": {
    "iso:country":"US",
    "sg:address":"529 Flat Shoals Ave",
    "sg:city":"Atlanta",
    "sg:classifiers":[
        {
            "category":"Bars & Pubs",
            "type":"Food & Drink"
        },
        {
            "category":"Recreation",
            "subcategory":"Dance Hall",
            "type":"Entertainment"
        },
        {
            "category":"Bars & Pubs",
            "subcategory":"Sports Bar",
            "type":"Food & Drink"
        }
    ],
    "sg:phone":"+1 404 228 6769",
    "sg:postcode":"30316",
    "sg:province":"GA",
    "sg:tags":[
        "club",
        "pool"
    ],
    "sg:website":"www.529EAV.com",
    "wof:name":"529",
    "wof:placetype":"venue"
},
  "geometry": {"coordinates":[-84.345108,33.739922],"type":"Point"}
}