{
  "type": "Feature",
  "properties": {
    "addr:full":"660 Blvd NE Atlanta GA 31136",
    "addr:housenumber":"660",
    "addr:postcode":"31136",
    "addr:street":"Blvd Ne",
    "iso:country":"US",
    "sg:address":"660 Blvd NE",
    "sg:city":"Atlanta",
    "sg:classifiers":[
        {
            "category":"Fast Food",
            "type":"Food & Drink"
        }
    ],
    "sg:phone":"+1 404 874 8069",
    "sg:postcode":"31136",
    "sg:province":"GA",
    "sg:website":"www.wendys.com",
    "wof:name":"Wendy's",
    "wof:placetype":"venue"
},
  "geometry": {"coordinates":[-84.23450200000001,33.565454],"type":"Point"}
}