{
  "type": "Feature",
  "properties": {
    "iso:country":"US",
    "sg:address":"145 US Hwy 19",
    "sg:city":"Zebulon",
    "sg:classifiers":[
        {
            "category":"Wholesale",
            "subcategory":"Groceries",
            "type":"Manufacturing & Wholesale Goods"
        }
    ],
    "sg:phone":"+1 770 567 3169",
    "sg:postcode":"30295",
    "sg:province":"GA",
    "sg:tags":[
        "nut",
        "processing"
    ],
    "wof:name":"Booth Pecan Co",
    "wof:placetype":"venue"
},
  "geometry": {"coordinates":[-84.344477,33.048678],"type":"Point"}
}