{
  "type": "Feature",
  "properties": {
    "addr:full":"3363 Chattanooga Rd Tunnel Hill GA 30755",
    "addr:housenumber":"3363",
    "addr:postcode":"30755",
    "addr:street":"Chattanooga Rd",
    "iso:country":"US",
    "sg:address":"3363 Chattanooga Rd",
    "sg:city":"Tunnel Hill",
    "sg:classifiers":[
        {
            "category":"Building & Trades",
            "subcategory":"Plumbing",
            "type":"Services"
        }
    ],
    "sg:phone":"+1 706 278 6362",
    "sg:postcode":"30755",
    "sg:province":"GA",
    "sg:tags":[
        "conditioning",
        "air",
        "system",
        "contractor"
    ],
    "sg:website":"www.aircomfortheatingandair.com",
    "wof:name":"Air Comfort",
    "wof:placetype":"venue"
},
  "geometry": {"coordinates":[-85.044809,34.831469],"type":"Point"}
}