{
  "type": "Feature",
  "properties": {
    "addr:full":"4540 Matt Hwy Cumming GA 30040",
    "addr:housenumber":"4540",
    "addr:postcode":"30040",
    "addr:street":"Matt Hwy",
    "iso:country":"US",
    "sg:address":"4540 Matt Hwy",
    "sg:city":"Cumming",
    "sg:classifiers":[
        {
            "category":"Manufacturing",
            "subcategory":"Motor Vehicles & Parts",
            "type":"Manufacturing & Wholesale Goods"
        }
    ],
    "sg:phone":"+1 770 886 3007",
    "sg:postcode":"30040",
    "sg:province":"GA",
    "sg:tags":[
        "equipment",
        "truck"
    ],
    "wof:name":"Metro Fleet Parts & Svc",
    "wof:placetype":"venue"
},
  "geometry": {"coordinates":[-84.13182999999999,34.289613],"type":"Point"}
}