{
  "type": "Feature",
  "properties": {
    "addr:full":"2014 US Hwy 41 N Tifton GA 31794",
    "addr:housenumber":"2014",
    "addr:postcode":"31794",
    "addr:street":"Us Hwy 41 N",
    "iso:country":"US",
    "sg:address":"2014 US Hwy 41 N",
    "sg:city":"Tifton",
    "sg:classifiers":[
        {
            "category":"Health Services",
            "subcategory":"Clinic",
            "type":"Services"
        }
    ],
    "sg:phone":"+1 229 386 8571",
    "sg:postcode":"31794",
    "sg:province":"GA",
    "sg:tags":[
        "home"
    ],
    "wof:name":"Visiting Nurse Assn",
    "wof:placetype":"venue"
},
  "geometry": {"coordinates":[-83.519381,31.474763],"type":"Point"}
}