{
  "type": "Feature",
  "properties": {
    "iso:country":"US",
    "sg:address":"114 S Broad St",
    "sg:city":"Bainbridge",
    "sg:classifiers":[
        {
            "category":"Insurance",
            "subcategory":"Hazard Insurance",
            "type":"Services"
        }
    ],
    "sg:phone":"+1 229 246 8952",
    "sg:postcode":"39817",
    "sg:province":"GA",
    "sg:tags":[
        "commercial",
        "business"
    ],
    "wof:name":"Interstate Motor Club Inc",
    "wof:placetype":"venue"
},
  "geometry": {"coordinates":[-84.575585,30.905576],"type":"Point"}
}