{
  "type": "Feature",
  "properties": {
    "iso:country":"US",
    "sg:address":"3145 Washington Rd",
    "sg:city":"Augusta",
    "sg:classifiers":[
        {
            "category":"Professional",
            "subcategory":"Advertising",
            "type":"Services"
        }
    ],
    "sg:phone":"+1 706 863 6511",
    "sg:postcode":"30907",
    "sg:province":"GA",
    "sg:tags":[
        "mailing",
        "shipping"
    ],
    "wof:name":"Fed Ex",
    "wof:placetype":"venue"
},
  "geometry": {"coordinates":[-82.056652,33.514097],"type":"Point"}
}