{
  "type": "Feature",
  "properties": {
    "addr:full":"11555 Medlock Bridge Suite 190 Duluth GA 30097",
    "addr:housenumber":"11555",
    "addr:postcode":"30097",
    "addr:street":"Medlock Bridge Suite 190",
    "iso:country":"US",
    "sg:address":"11555 Medlock Bridge Suite 190",
    "sg:city":"Duluth",
    "sg:classifiers":[
        {
            "category":"Professional",
            "subcategory":"Research",
            "type":"Services"
        }
    ],
    "sg:phone":"+1 770 622 4158",
    "sg:postcode":"30097",
    "sg:province":"GA",
    "sg:website":"http://www.solohealth.com/",
    "wof:name":"SoloHealth",
    "wof:placetype":"venue"
},
  "geometry": {"coordinates":[-84.173509,34.058537],"type":"Point"}
}