{
  "type": "Feature",
  "properties": {
    "iso:country":"US",
    "sg:address":"745 Glynn St S",
    "sg:city":"Fayetteville",
    "sg:classifiers":[
        {
            "category":"Health Services",
            "subcategory":"Doctor",
            "type":"Services"
        }
    ],
    "sg:phone":"+1 770 719 5490",
    "sg:postcode":"30214",
    "sg:province":"GA",
    "sg:tags":[
        "medicine",
        "internal"
    ],
    "wof:name":"Horton Betsy-MD PC",
    "wof:placetype":"venue"
},
  "geometry": {"coordinates":[-84.45666300000001,33.434633],"type":"Point"}
}