{
  "type": "Feature",
  "properties": {
    "iso:country":"US",
    "sg:address":"4416 Drury Ln SE",
    "sg:city":"Acworth",
    "sg:classifiers":[
        {
            "category":"Manufacturing",
            "subcategory":"Buildings",
            "type":"Manufacturing & Wholesale Goods"
        },
        {
            "category":"Building & Trades",
            "subcategory":"Construction",
            "type":"Services"
        }
    ],
    "sg:phone":"+1 678 574 3082",
    "sg:postcode":"30102",
    "sg:province":"GA",
    "sg:tags":[
        "home",
        "builder",
        "contractor"
    ],
    "wof:name":"The Phoenix Home",
    "wof:placetype":"venue"
},
  "geometry": {"coordinates":[-84.680605,34.138945],"type":"Point"}
}