{
  "type": "Feature",
  "properties": {
    "addr:full":"1754 Mill Creek Rd Rocky Face GA 30740",
    "addr:housenumber":"1754",
    "addr:postcode":"30740",
    "addr:street":"Mill Creek Rd",
    "iso:country":"US",
    "sg:address":"1754 Mill Creek Rd",
    "sg:city":"Rocky Face",
    "sg:classifiers":[
        {
            "category":"Restaurant",
            "type":"Food & Drink"
        }
    ],
    "sg:phone":"+1 706 673 6398",
    "sg:postcode":"30740",
    "sg:province":"GA",
    "sg:tags":[
        "eating"
    ],
    "wof:name":"Mill Creek Diner",
    "wof:placetype":"venue"
},
  "geometry": {"coordinates":[-85.03607599999999,34.745344],"type":"Point"}
}