{
  "type": "Feature",
  "properties": {
    "iso:country":"US",
    "sg:address":"825 E Kytle St",
    "sg:city":"Cleveland",
    "sg:classifiers":[
        {
            "category":"Utilities",
            "subcategory":"Refuse",
            "type":"Services"
        }
    ],
    "sg:phone":"+1 706 865 1515",
    "sg:postcode":"30528",
    "sg:province":"GA",
    "sg:tags":[
        "garbage",
        "collection",
        "system"
    ],
    "wof:name":"H & N Sanitation Inc",
    "wof:placetype":"venue"
},
  "geometry": {"coordinates":[-83.753755,34.594981],"type":"Point"}
}