{
  "type": "Feature",
  "properties": {
    "addr:full":"153 E Kytle St Cleveland GA 30528",
    "addr:housenumber":"153",
    "addr:postcode":"30528",
    "addr:street":"E Kytle St",
    "iso:country":"US",
    "sg:address":"153 E Kytle St",
    "sg:city":"Cleveland",
    "sg:classifiers":[
        {
            "category":"Banks & Credit Unions",
            "subcategory":"Bank",
            "type":"Services"
        }
    ],
    "sg:phone":"+1 706 865 3151",
    "sg:postcode":"30528",
    "sg:province":"GA",
    "wof:name":"United Community Bank",
    "wof:placetype":"venue"
},
  "geometry": {"coordinates":[-83.761483,34.596594],"type":"Point"}
}