{
  "type": "Feature",
  "properties": {
    "addr:full":"1620 Lavista Rd NE Atlanta GA 30329",
    "addr:housenumber":"1620",
    "addr:postcode":"30329",
    "addr:street":"Lavista Rd Ne",
    "iso:country":"US",
    "sg:address":"1620 Lavista Rd NE",
    "sg:city":"Atlanta",
    "sg:classifiers":[
        {
            "category":"Retail",
            "subcategory":"Laundry & Dry Cleaning",
            "type":"Services"
        }
    ],
    "sg:phone":"+1 404 636 0099",
    "sg:postcode":"30329",
    "sg:province":"GA",
    "sg:tags":[
        "garment",
        "agent"
    ],
    "wof:name":"Briar Vista Cleaners",
    "wof:placetype":"venue"
},
  "geometry": {"coordinates":[-84.33635099999999,33.814961],"type":"Point"}
}