{
  "type": "Feature",
  "properties": {
    "addr:full":"112 Athens St Homer GA 30547",
    "addr:housenumber":"112",
    "addr:postcode":"30547",
    "addr:street":"Athens St",
    "iso:country":"US",
    "sg:address":"112 Athens St",
    "sg:city":"Homer",
    "sg:classifiers":[
        {
            "category":"Government",
            "subcategory":"Fire Station",
            "type":"Public Place"
        }
    ],
    "sg:phone":"+1 706 677 2881",
    "sg:postcode":"30547",
    "sg:province":"GA",
    "sg:tags":[
        "department"
    ],
    "wof:name":"Homer Fire Dept",
    "wof:placetype":"venue"
},
  "geometry": {"coordinates":[-83.498727,34.33368],"type":"Point"}
}