{
  "type": "Feature",
  "properties": {
    "addr:full":"4818 Fulton Industrial Blvd SW Atlanta GA 30336",
    "addr:housenumber":"4818",
    "addr:postcode":"30336",
    "addr:street":"Fulton Industrial Blvd Sw",
    "iso:country":"US",
    "sg:address":"4818 Fulton Industrial Blvd SW",
    "sg:city":"Atlanta",
    "sg:classifiers":[
        {
            "category":"Arts & Performance",
            "subcategory":"Theater",
            "type":"Entertainment"
        }
    ],
    "sg:phone":"+1 404 472 2995",
    "sg:postcode":"30336",
    "sg:province":"GA",
    "sg:tags":[
        "bureau"
    ],
    "wof:name":"VIP Entertainment",
    "wof:placetype":"venue"
},
  "geometry": {"coordinates":[-84.550556,33.750765],"type":"Point"}
}