{
  "type": "Feature",
  "properties": {
    "addr:full":"931 Monroe Dr NE Atlanta GA 30308",
    "addr:housenumber":"931",
    "addr:postcode":"30308",
    "addr:street":"Monroe Dr Ne",
    "iso:country":"US",
    "sg:address":"931 Monroe Dr NE",
    "sg:city":"Atlanta",
    "sg:classifiers":[
        {
            "category":"Recreation",
            "type":"Entertainment"
        }
    ],
    "sg:phone":"+1 404 874 7813",
    "sg:postcode":"30308",
    "sg:province":"GA",
    "sg:tags":[
        "instruction",
        "yoga"
    ],
    "sg:website":"www.stillyoga.com/home.html",
    "wof:name":"Stillwater Yoga Studio",
    "wof:placetype":"venue"
},
  "geometry": {"coordinates":[-84.36930099999999,33.7798],"type":"Point"}
}