{
  "type": "Feature",
  "properties": {
    "addr:full":"101 N Jackson St Albany GA 31701",
    "addr:housenumber":"101",
    "addr:postcode":"31701",
    "addr:street":"N Jackson St",
    "iso:country":"US",
    "sg:address":"101 N Jackson St",
    "sg:city":"Albany",
    "sg:classifiers":[
        {
            "category":"Banks & Credit Unions",
            "subcategory":"Bank",
            "type":"Services"
        }
    ],
    "sg:phone":"+1 229 435 0285",
    "sg:postcode":"31701",
    "sg:province":"GA",
    "sg:tags":[
        "personal",
        "institution"
    ],
    "wof:name":"Service Loan & Income Tax Co",
    "wof:placetype":"venue"
},
  "geometry": {"coordinates":[-84.153679,31.578404],"type":"Point"}
}