{
  "type": "Feature",
  "properties": {
    "iso:country":"US",
    "sg:address":"2971 Tribble Ln NW",
    "sg:city":"Atlanta",
    "sg:classifiers":[
        {
            "category":"Shopping",
            "subcategory":"Clothing, Apparel, & Fashions",
            "type":"Retail Goods"
        }
    ],
    "sg:phone":"+1 404 696 1631",
    "sg:postcode":"30311",
    "sg:province":"GA",
    "wof:name":"Candys Traveling Boutique",
    "wof:placetype":"venue"
},
  "geometry": {"coordinates":[-84.48398299999999,33.759396],"type":"Point"}
}