{
  "type": "Feature",
  "properties": {
    "addr:full":"2316 Apple Pie Ridge Rd Alto GA 30510",
    "addr:housenumber":"2316",
    "addr:postcode":"30510",
    "addr:street":"Apple Pie Ridge Rd",
    "iso:country":"US",
    "sg:address":"2316 Apple Pie Ridge Rd",
    "sg:city":"Alto",
    "sg:classifiers":[
        {
            "category":"Recreation",
            "type":"Entertainment"
        }
    ],
    "sg:phone":"+1 706 778 3724",
    "sg:postcode":"30510",
    "sg:province":"GA",
    "wof:name":"With Stitches",
    "wof:placetype":"venue"
},
  "geometry": {"coordinates":[-83.560143,34.473542],"type":"Point"}
}