{
  "type": "Feature",
  "properties": {
    "addr:full":"120 Colony Center Dr Woodstock GA 30188",
    "addr:housenumber":"120",
    "addr:postcode":"30188",
    "addr:street":"Colony Center Dr",
    "iso:country":"US",
    "sg:address":"120 Colony Center Dr",
    "sg:city":"Woodstock",
    "sg:classifiers":[
        {
            "category":"Professional",
            "subcategory":"Business Services",
            "type":"Services"
        }
    ],
    "sg:phone":"+1 770 516 0813",
    "sg:postcode":"30188",
    "sg:province":"GA",
    "wof:name":"Colony Center",
    "wof:placetype":"venue"
},
  "geometry": {"coordinates":[-84.432956,34.079443],"type":"Point"}
}