{
  "type": "Feature",
  "properties": {
    "addr:full":"4713 Gillionville Rd Albany GA 31721",
    "addr:housenumber":"4713",
    "addr:postcode":"31721",
    "addr:street":"Gillionville Rd",
    "iso:country":"US",
    "sg:address":"4713 Gillionville Rd",
    "sg:city":"Albany",
    "sg:classifiers":[
        {
            "category":"Organizations",
            "subcategory":"Religious Organization",
            "type":"Services"
        }
    ],
    "sg:phone":"+1 229 432 2163",
    "sg:postcode":"31721",
    "sg:province":"GA",
    "wof:name":"Oakie Hl Mssnary Baptst Church",
    "wof:placetype":"venue"
},
  "geometry": {"coordinates":[-84.28205699999999,31.58577],"type":"Point"}
}