{
  "type": "Feature",
  "properties": {
    "iso:country":"US",
    "sg:address":"999 Lee St SW",
    "sg:city":"Atlanta",
    "sg:classifiers":[
        {
            "category":"Manufacturing",
            "subcategory":"Glass & Minerals",
            "type":"Manufacturing & Wholesale Goods"
        }
    ],
    "sg:phone":"+1 404 758 4487",
    "sg:postcode":"30310",
    "sg:province":"GA",
    "sg:tags":[
        "concrete",
        "brick",
        "prod",
        "block"
    ],
    "wof:name":"Oldcastle Precast",
    "wof:placetype":"venue"
},
  "geometry": {"coordinates":[-84.416923,33.727961],"type":"Point"}
}