{
  "type": "Feature",
  "properties": {
    "addr:full":"739 Winston Rd Columbus GA 31903",
    "addr:housenumber":"739",
    "addr:postcode":"31903",
    "addr:street":"Winston Rd",
    "iso:country":"US",
    "sg:address":"739 Winston Rd",
    "sg:city":"Columbus",
    "sg:classifiers":[
        {
            "category":"Organizations",
            "subcategory":"Religious Organization",
            "type":"Services"
        }
    ],
    "sg:phone":"+1 706 687 9600",
    "sg:postcode":"31903",
    "sg:province":"GA",
    "wof:name":"New Bthel Tbernacle Church God",
    "wof:placetype":"venue"
},
  "geometry": {"coordinates":[-84.94576499999999,32.437223],"type":"Point"}
}