{
  "type": "Feature",
  "properties": {
    "iso:country":"US",
    "sg:address":"2625 N Berkeley Lake Rd NW",
    "sg:city":"Duluth",
    "sg:classifiers":[
        {
            "category":"Professional",
            "subcategory":"Business Services",
            "type":"Services"
        }
    ],
    "sg:phone":"+1 678 436 0121",
    "sg:postcode":"30096",
    "sg:province":"GA",
    "sg:tags":[
        "system",
        "form"
    ],
    "wof:name":"Cfm",
    "wof:placetype":"venue"
},
  "geometry": {"coordinates":[-84.15522799999999,33.971081],"type":"Point"}
}