{
  "type": "Feature",
  "properties": {
    "iso:country":"US",
    "sg:address":"1268 Fenway Cir",
    "sg:city":"Decatur",
    "sg:classifiers":[
        {
            "category":"Building & Trades",
            "subcategory":"Cleaning & Sanitation",
            "type":"Services"
        }
    ],
    "sg:phone":"+1 404 373 6524",
    "sg:postcode":"30030",
    "sg:province":"GA",
    "sg:tags":[
        "maintenance"
    ],
    "wof:name":"CRC Janitorial Cleaning",
    "wof:placetype":"venue"
},
  "geometry": {"coordinates":[-84.283315,33.756281],"type":"Point"}
}