{
  "type": "Feature",
  "properties": {
    "iso:country":"US",
    "sg:address":"1460 E Victory Dr",
    "sg:city":"Savannah",
    "sg:classifiers":[
        {
            "category":"Health Services",
            "subcategory":"Doctor",
            "type":"Services"
        }
    ],
    "sg:phone":"+1 912 232 2691",
    "sg:postcode":"31404",
    "sg:province":"GA",
    "sg:tags":[
        "clinic"
    ],
    "wof:name":"Coastal Dialysis",
    "wof:placetype":"venue"
},
  "geometry": {"coordinates":[-81.077009,32.04601],"type":"Point"}
}