{
  "type": "Feature",
  "properties": {
    "addr:full":"1138 West Ave SW Conyers GA 30012",
    "addr:housenumber":"1138",
    "addr:postcode":"30012",
    "addr:street":"West Ave Sw",
    "iso:country":"US",
    "sg:address":"1138 West Ave SW",
    "sg:city":"Conyers",
    "sg:classifiers":[
        {
            "category":"Restaurant",
            "type":"Food & Drink"
        }
    ],
    "sg:phone":"+1 770 922 6626",
    "sg:postcode":"30012",
    "sg:province":"GA",
    "wof:name":"Mrs Winners Chicken & Biscuits",
    "wof:placetype":"venue"
},
  "geometry": {"coordinates":[-84.02697499999999,33.665999],"type":"Point"}
}