{
  "type": "Feature",
  "properties": {
    "iso:country":"US",
    "sg:address":"3920 Troupe Smith Rd SE",
    "sg:city":"Conyers",
    "sg:classifiers":[
        {
            "category":"Wholesale",
            "subcategory":"Sporting Goods",
            "type":"Manufacturing & Wholesale Goods"
        }
    ],
    "sg:phone":"+1 770 483 8341",
    "sg:postcode":"30094",
    "sg:province":"GA",
    "wof:name":"Plantation Productions",
    "wof:placetype":"venue"
},
  "geometry": {"coordinates":[-84.03998,33.584359],"type":"Point"}
}