{
  "type": "Feature",
  "properties": {
    "iso:country":"US",
    "sg:address":"2651 Weigelia Rd NE",
    "sg:city":"Atlanta",
    "sg:classifiers":[
        {
            "category":"Building & Trades",
            "subcategory":"Landscaping Services",
            "type":"Services"
        }
    ],
    "sg:phone":"+1 404 217 1576",
    "sg:postcode":"30345",
    "sg:province":"GA",
    "sg:tags":[
        "landscape",
        "contractor"
    ],
    "wof:name":"Redwood Landscapes",
    "wof:placetype":"venue"
},
  "geometry": {"coordinates":[-84.27854600000001,33.835681],"type":"Point"}
}