{
  "type": "Feature",
  "properties": {
    "addr:full":"1 E 73rd St Savannah GA 31405",
    "addr:housenumber":"1",
    "addr:postcode":"31405",
    "addr:street":"E 73Rd St",
    "iso:country":"US",
    "sg:address":"1 E 73rd St",
    "sg:city":"Savannah",
    "sg:classifiers":[
        {
            "category":"Retail",
            "subcategory":"Car Wash",
            "type":"Services"
        }
    ],
    "sg:phone":"+1 912 354 9857",
    "sg:postcode":"31405",
    "sg:province":"GA",
    "sg:tags":[
        "automobile",
        "detail",
        "clean"
    ],
    "wof:name":"Swanns Window Tinting",
    "wof:placetype":"venue"
},
  "geometry": {"coordinates":[-81.1096,32.027423],"type":"Point"}
}