{
  "type": "Feature",
  "properties": {
    "iso:country":"US",
    "sg:address":"5845 Hillvale Rd",
    "sg:city":"Lithonia",
    "sg:classifiers":[
        {
            "category":"Social Services",
            "type":"Services"
        }
    ],
    "sg:phone":"+1 770 593 0212",
    "sg:postcode":"30058",
    "sg:province":"GA",
    "wof:name":"Attack Youth Soccer Club",
    "wof:placetype":"venue"
},
  "geometry": {"coordinates":[-84.14596,33.715545],"type":"Point"}
}