{
  "type": "Feature",
  "properties": {
    "iso:country":"US",
    "sg:address":"510 Sharp St",
    "sg:city":"Woodstock",
    "sg:classifiers":[
        {
            "category":"Building & Trades",
            "subcategory":"Construction",
            "type":"Services"
        }
    ],
    "sg:phone":"+1 770 591 2121",
    "sg:postcode":"30189",
    "sg:province":"GA",
    "sg:tags":[
        "swimming",
        "pool",
        "contractor"
    ],
    "wof:name":"Carmel Springs LLC Avalon Pool",
    "wof:placetype":"venue"
},
  "geometry": {"coordinates":[-84.581075,34.106078],"type":"Point"}
}