{
  "type": "Feature",
  "properties": {
    "iso:country":"US",
    "sg:address":"1814 Utility Rd",
    "sg:city":"Rocky Face",
    "sg:classifiers":[
        {
            "category":"Social Services",
            "subcategory":"Child Care",
            "type":"Services"
        }
    ],
    "sg:phone":"+1 706 673 2514",
    "sg:postcode":"30740",
    "sg:province":"GA",
    "sg:tags":[
        "kindergarten",
        "academic",
        "school"
    ],
    "wof:name":"Valley Point",
    "wof:placetype":"venue"
},
  "geometry": {"coordinates":[-85.05159999999999,34.783599],"type":"Point"}
}