{
  "type": "Feature",
  "properties": {
    "addr:full":"161 Hightower Lake Trl Ball Ground GA 30107",
    "addr:housenumber":"161",
    "addr:postcode":"30107",
    "addr:street":"Hightower Lake Trl",
    "iso:country":"US",
    "sg:address":"161 Hightower Lake Trl",
    "sg:city":"Ball Ground",
    "sg:classifiers":[
        {
            "category":"Building & Trades",
            "subcategory":"Construction",
            "type":"Services"
        }
    ],
    "sg:phone":"+1 678 455 4711",
    "sg:postcode":"30107",
    "sg:province":"GA",
    "sg:tags":[
        "carpentry",
        "contractor"
    ],
    "wof:name":"Kevin Thomas",
    "wof:placetype":"venue"
},
  "geometry": {"coordinates":[-84.28946999999999,34.272163],"type":"Point"}
}