{
  "type": "Feature",
  "properties": {
    "iso:country":"US",
    "sg:address":"1270 Caroline Street Suite D120 Box 254",
    "sg:city":"Atlanta",
    "sg:classifiers":[
        {
            "category":"Professional",
            "type":"Services"
        }
    ],
    "sg:phone":"+1 877 427 5724",
    "sg:postcode":"30307",
    "sg:province":"GA",
    "sg:website":"www.askpcg.com",
    "wof:name":"The Purvis Consulting Group",
    "wof:placetype":"venue"
},
  "geometry": {"coordinates":[-84.34712500000001,33.758455],"type":"Point"}
}