{
  "type": "Feature",
  "properties": {
    "addr:full":"4618 Five Oaks Pl Powder Springs GA 30127",
    "addr:housenumber":"4618",
    "addr:postcode":"30127",
    "addr:street":"Five Oaks Pl",
    "iso:country":"US",
    "sg:address":"4618 Five Oaks Pl",
    "sg:city":"Powder Springs",
    "sg:classifiers":[
        {
            "category":"Local Transit",
            "type":"Transportation"
        }
    ],
    "sg:phone":"+1 770 948 8997",
    "sg:postcode":"30127",
    "sg:province":"GA",
    "sg:tags":[
        "passenger"
    ],
    "wof:name":"Top Gun Limousine Inc",
    "wof:placetype":"venue"
},
  "geometry": {"coordinates":[-84.674644,33.839691],"type":"Point"}
}