{
  "type": "Feature",
  "properties": {
    "iso:country":"US",
    "sg:address":"1160 Utoy Springs Rd SW",
    "sg:city":"Atlanta",
    "sg:classifiers":[
        {
            "category":"Building & Trades",
            "subcategory":"Locksmith",
            "type":"Services"
        }
    ],
    "sg:phone":"+1 800 466 8996",
    "sg:postcode":"30331",
    "sg:province":"GA",
    "sg:tags":[
        "key"
    ],
    "wof:name":"24 Hour 1 Emergency Locksmith",
    "wof:placetype":"venue"
},
  "geometry": {"coordinates":[-84.506418,33.722537],"type":"Point"}
}