{
  "type": "Feature",
  "properties": {
    "iso:country":"US",
    "sg:address":"5626 Hwy 20 SE",
    "sg:city":"Cartersville",
    "sg:classifiers":[
        {
            "category":"Food & Beverages",
            "subcategory":"Groceries & Convenience Stores",
            "type":"Retail Goods"
        }
    ],
    "sg:phone":"+1 770 606 8093",
    "sg:postcode":"30121",
    "sg:province":"GA",
    "wof:name":"Citgo Mart",
    "wof:placetype":"venue"
},
  "geometry": {"coordinates":[-84.76758599999999,34.204959],"type":"Point"}
}