{
  "type": "Feature",
  "properties": {
    "iso:country":"US",
    "sg:address":"100 Columns Dr",
    "sg:city":"Lithia Springs",
    "sg:classifiers":[
        {
            "category":"Real Estate",
            "subcategory":"Real Estate Operator",
            "type":"Services"
        }
    ],
    "sg:phone":"+1 770 948 0255",
    "sg:postcode":"30122",
    "sg:province":"GA",
    "sg:tags":[
        "apartment"
    ],
    "wof:name":"The Columns At Sweetwater Creek Apartments",
    "wof:placetype":"venue"
},
  "geometry": {"coordinates":[-84.62930299999999,33.768501],"type":"Point"}
}