{
  "type": "Feature",
  "properties": {
    "addr:full":"5358 Mcginnis Ferry Rd Alpharetta GA 30005",
    "addr:housenumber":"5358",
    "addr:postcode":"30005",
    "addr:street":"Mcginnis Ferry Rd",
    "iso:country":"US",
    "sg:address":"5358 Mcginnis Ferry Rd",
    "sg:city":"Alpharetta",
    "sg:phone":"+1 770 667 9847",
    "sg:postcode":"30005",
    "sg:province":"GA",
    "wof:name":"Goodyear",
    "wof:placetype":"venue"
},
  "geometry": {"coordinates":[-84.20293100000001,34.090081],"type":"Point"}
}