{
  "type": "Feature",
  "properties": {
    "iso:country":"US",
    "sg:address":"1317 Yarborough Dr",
    "sg:city":"Peachtree City",
    "sg:classifiers":[
        {
            "category":"Shopping",
            "subcategory":"Gifts & Souvenirs",
            "type":"Retail Goods"
        }
    ],
    "sg:phone":"+1 770 487 2135",
    "sg:postcode":"30269",
    "sg:province":"GA",
    "wof:name":"Hallmark Cards",
    "wof:placetype":"venue"
},
  "geometry": {"coordinates":[-84.530507,33.363239],"type":"Point"}
}