{
  "type": "Feature",
  "properties": {
    "iso:country":"US",
    "sg:address":"2343 Bonner Gilbert Rd",
    "sg:city":"Lizella",
    "sg:classifiers":[
        {
            "category":"Manufacturing",
            "subcategory":"Buildings",
            "type":"Manufacturing & Wholesale Goods"
        },
        {
            "category":"Building & Trades",
            "subcategory":"Construction",
            "type":"Services"
        }
    ],
    "sg:phone":"+1 478 935 2762",
    "sg:postcode":"31052",
    "sg:province":"GA",
    "sg:tags":[
        "home",
        "builder",
        "contractor",
        "grading"
    ],
    "wof:name":"Yarbrough Construction",
    "wof:placetype":"venue"
},
  "geometry": {"coordinates":[-83.83819699999999,32.824094],"type":"Point"}
}