{
  "type": "Feature",
  "properties": {
    "addr:full":"1372 Nine Dime Doctor Rd Meigs GA 31765",
    "addr:housenumber":"1372",
    "addr:postcode":"31765",
    "addr:street":"Doctor Rd",
    "iso:country":"US",
    "sg:address":"1372 Nine Dime Doctor Rd",
    "sg:city":"Meigs",
    "sg:classifiers":[
        {
            "category":"Social Services",
            "subcategory":"Child Care",
            "type":"Services"
        }
    ],
    "sg:phone":"+1 229 683 3066",
    "sg:postcode":"31765",
    "sg:province":"GA",
    "sg:tags":[
        "day"
    ],
    "wof:name":"Angel Little Child Care",
    "wof:placetype":"venue"
},
  "geometry": {"coordinates":[-84.079931,31.0566],"type":"Point"}
}