{
  "type": "Feature",
  "properties": {
    "addr:full":"617 E Pelham Rd NE Atlanta GA 30324",
    "addr:housenumber":"617",
    "addr:postcode":"30324",
    "addr:street":"E Pelham Rd Ne",
    "iso:country":"US",
    "sg:address":"617 E Pelham Rd NE",
    "sg:city":"Atlanta",
    "sg:classifiers":[
        {
            "category":"Communications",
            "subcategory":"Newspaper",
            "type":"Services"
        }
    ],
    "sg:phone":"+1 770 331 9290",
    "sg:postcode":"30324",
    "sg:province":"GA",
    "sg:tags":[
        "feature",
        "syndicate"
    ],
    "wof:name":"Global Media Bridge",
    "wof:placetype":"venue"
},
  "geometry": {"coordinates":[-84.367026,33.801374],"type":"Point"}
}