{
  "type": "Feature",
  "properties": {
    "addr:full":"388 Lynne Cir Alpharetta GA 30004",
    "addr:housenumber":"388",
    "addr:postcode":"30004",
    "addr:street":"Lynne Cir",
    "iso:country":"US",
    "sg:address":"388 Lynne Cir",
    "sg:city":"Alpharetta",
    "sg:classifiers":[
        {
            "category":"Real Estate",
            "subcategory":"Real Estate Agent",
            "type":"Services"
        }
    ],
    "sg:phone":"+1 770 475 4742",
    "sg:postcode":"30004",
    "sg:province":"GA",
    "wof:name":"Beal Robert A Sr & Associates",
    "wof:placetype":"venue"
},
  "geometry": {"coordinates":[-84.30494899999999,34.077608],"type":"Point"}
}