{
  "type": "Feature",
  "properties": {
    "iso:country":"US",
    "sg:address":"4279 Roswell Rd NE Ste 204",
    "sg:city":"Atlanta",
    "sg:classifiers":[
        {
            "category":"Health Services",
            "subcategory":"Optometrist",
            "type":"Services"
        },
        {
            "category":"Shopping",
            "subcategory":"Optician",
            "type":"Retail Goods"
        }
    ],
    "sg:phone":"+1 404 252 1702",
    "sg:postcode":"30342",
    "sg:province":"GA",
    "sg:tags":[
        "eyewear"
    ],
    "wof:name":"Eye 1st Vision Center",
    "wof:placetype":"venue"
},
  "geometry": {"coordinates":[-84.38099699999999,33.871799],"type":"Point"}
}