{
  "type": "Feature",
  "properties": {
    "iso:country":"US",
    "sg:address":"425 Pharr Rd NE",
    "sg:city":"Atlanta",
    "sg:classifiers":[
        {
            "category":"Professional",
            "type":"Services"
        }
    ],
    "sg:phone":"+1 404 467 1578",
    "sg:postcode":"30305",
    "sg:province":"GA",
    "sg:tags":[
        "establishment"
    ],
    "wof:name":"Frankie Allen Park Buckhead",
    "wof:placetype":"venue"
},
  "geometry": {"coordinates":[-84.374234,33.836946],"type":"Point"}
}