{
  "type": "Feature",
  "properties": {
    "addr:full":"250 Sky Lake Rd Sautee Nacoochee GA 30571",
    "addr:housenumber":"250",
    "addr:postcode":"30571",
    "addr:street":"Sky Lake Rd",
    "iso:country":"US",
    "sg:address":"250 Sky Lake Rd",
    "sg:city":"Sautee Nacoochee",
    "sg:classifiers":[
        {
            "category":"Professional",
            "subcategory":"Management & Consulting",
            "type":"Services"
        }
    ],
    "sg:phone":"+1 404 727 2446",
    "sg:postcode":"30571",
    "sg:province":"GA",
    "wof:name":"Hippos Inc",
    "wof:placetype":"venue"
},
  "geometry": {"coordinates":[-83.664276,34.725273],"type":"Point"}
}