{
  "type": "Feature",
  "properties": {
    "iso:country":"US",
    "sg:address":"2684 Sterling Dr",
    "sg:city":"Lawrenceville",
    "sg:classifiers":[
        {
            "category":"Retail",
            "subcategory":"Repair Shop",
            "type":"Services"
        },
        {
            "category":"Wholesale",
            "subcategory":"Machinery & Supplies",
            "type":"Manufacturing & Wholesale Goods"
        },
        {
            "category":"Building & Trades",
            "subcategory":"Equipment Rental",
            "type":"Services"
        },
        {
            "category":"Building & Trades",
            "subcategory":"Electrical",
            "type":"Services"
        }
    ],
    "sg:phone":"+1 404 519 4407",
    "sg:postcode":"30043",
    "sg:province":"GA",
    "sg:tags":[
        "generators-electric-service",
        "electrician",
        "electric",
        "generator",
        "protection",
        "lightning",
        "industrial",
        "contractors-commercial"
    ],
    "wof:name":"Improvement Electric",
    "wof:placetype":"venue"
},
  "geometry": {"coordinates":[-84.026775,34.026449],"type":"Point"}
}