{
  "type": "Feature",
  "properties": {
    "addr:full":"129 S Main St Cleveland GA 30528",
    "addr:housenumber":"129",
    "addr:postcode":"30528",
    "addr:street":"S Main St",
    "iso:country":"US",
    "sg:address":"129 S Main St",
    "sg:city":"Cleveland",
    "sg:classifiers":[
        {
            "category":"Cinema",
            "subcategory":"Movie Rental",
            "type":"Entertainment"
        }
    ],
    "sg:phone":"+1 706 865 9661",
    "sg:postcode":"30528",
    "sg:province":"GA",
    "sg:tags":[
        "video",
        "tape"
    ],
    "wof:name":"Cleveland Video",
    "wof:placetype":"venue"
},
  "geometry": {"coordinates":[-83.76330299999999,34.594747],"type":"Point"}
}