{
  "type": "Feature",
  "properties": {
    "iso:country":"US",
    "sg:address":"6095 Barfield Road NE",
    "sg:city":"Atlanta",
    "sg:classifiers":[
        {
            "category":"Personal",
            "type":"Services"
        }
    ],
    "sg:phone":"+1 404 843 3765",
    "sg:postcode":"30328",
    "sg:province":"GA",
    "sg:tags":[
        "sewing",
        "alteration"
    ],
    "wof:name":"Custom Clothing of Atlanta",
    "wof:placetype":"venue"
},
  "geometry": {"coordinates":[-84.359844,33.9226],"type":"Point"}
}