{
  "type": "Feature",
  "properties": {
    "iso:country":"US",
    "sg:address":"405 Princeton Way",
    "sg:city":"Covington",
    "sg:classifiers":[
        {
            "category":"Manufacturing",
            "subcategory":"Tools & Machinery",
            "type":"Manufacturing & Wholesale Goods"
        }
    ],
    "sg:phone":"+1 678 342 8230",
    "sg:postcode":"30016",
    "sg:province":"GA",
    "sg:tags":[
        "small",
        "information",
        "security",
        "consulting",
        "business"
    ],
    "wof:name":"Trimir Enterprises Inc",
    "wof:placetype":"venue"
},
  "geometry": {"coordinates":[-83.937873,33.59382],"type":"Point"}
}