{
  "type": "Feature",
  "properties": {
    "iso:country":"US",
    "sg:address":"17 1st Ave NE Ste 100",
    "sg:city":"Cairo",
    "sg:classifiers":[
        {
            "category":"Professional",
            "subcategory":"Lawyer & Legal Services",
            "type":"Services"
        }
    ],
    "sg:phone":"+1 229 378 1060",
    "sg:postcode":"39828",
    "sg:province":"GA",
    "sg:tags":[
        "attorney",
        "practice"
    ],
    "wof:name":"Chason & Willett",
    "wof:placetype":"venue"
},
  "geometry": {"coordinates":[-84.20791199999999,30.877606],"type":"Point"}
}