{
  "type": "Feature",
  "properties": {
    "addr:full":"1975 Clairmont Road Atlanta GA 30329",
    "addr:housenumber":"1975",
    "addr:postcode":"30329",
    "addr:street":"Clairmont Road",
    "iso:country":"US",
    "sg:address":"1975 Clairmont Road",
    "sg:city":"Atlanta",
    "sg:classifiers":[
        {
            "category":"Autos & Motor Vehicles",
            "subcategory":"Fuel & Gas Station",
            "type":"Retail Goods"
        }
    ],
    "sg:phone":"+1 404 636 7704",
    "sg:postcode":"30329",
    "sg:province":"GA",
    "wof:name":"Bp Products North America",
    "wof:placetype":"venue"
},
  "geometry": {"coordinates":[-84.303967,33.820388],"type":"Point"}
}