{
  "type": "Feature",
  "properties": {
    "addr:full":"1816 US Hwy 41 N Tifton GA 31794",
    "addr:housenumber":"1816",
    "addr:postcode":"31794",
    "addr:street":"Us Hwy 41 N",
    "iso:country":"US",
    "sg:address":"1816 US Hwy 41 N",
    "sg:city":"Tifton",
    "sg:classifiers":[
        {
            "category":"Personal",
            "subcategory":"Beauty Salon",
            "type":"Services"
        }
    ],
    "sg:phone":"+1 229 382 8112",
    "sg:postcode":"31794",
    "sg:province":"GA",
    "wof:name":"A Cut In Time",
    "wof:placetype":"venue"
},
  "geometry": {"coordinates":[-83.518913,31.471341],"type":"Point"}
}