{
  "type": "Feature",
  "properties": {
    "addr:full":"216 Walden Run Pl Mc Donough GA 30253",
    "addr:housenumber":"216",
    "addr:postcode":"30253",
    "addr:street":"Walden Run Pl",
    "iso:country":"US",
    "sg:address":"216 Walden Run Pl",
    "sg:city":"Mc Donough",
    "sg:classifiers":[
        {
            "category":"Banks & Credit Unions",
            "subcategory":"Investment Brokerage",
            "type":"Services"
        }
    ],
    "sg:phone":"+1 770 957 2734",
    "sg:postcode":"30253",
    "sg:province":"GA",
    "sg:tags":[
        "advisory"
    ],
    "wof:name":"Transatlantic Inv Consulting",
    "wof:placetype":"venue"
},
  "geometry": {"coordinates":[-84.168245,33.448076],"type":"Point"}
}