{
  "type": "Feature",
  "properties": {
    "iso:country":"US",
    "sg:address":"35 Wagon Wheel Trl",
    "sg:city":"Thomasville",
    "sg:classifiers":[
        {
            "category":"Building & Trades",
            "subcategory":"Construction",
            "type":"Services"
        }
    ],
    "sg:phone":"+1 229 227 0730",
    "sg:postcode":"31757",
    "sg:province":"GA",
    "sg:tags":[
        "carpentry",
        "contractor"
    ],
    "wof:name":"Prevatt D Quality Cabts T",
    "wof:placetype":"venue"
},
  "geometry": {"coordinates":[-83.90600499999999,30.854649],"type":"Point"}
}