{
  "type": "Feature",
  "properties": {
    "iso:country":"US",
    "sg:address":"215 E Martin Luther King Dr",
    "sg:city":"Valdosta",
    "sg:classifiers":[
        {
            "category":"Retail",
            "subcategory":"Funeral Services",
            "type":"Services"
        }
    ],
    "sg:phone":"+1 229 244 1717",
    "sg:postcode":"31601",
    "sg:province":"GA",
    "sg:tags":[
        "director"
    ],
    "wof:name":"Stevens Funeral Home",
    "wof:placetype":"venue"
},
  "geometry": {"coordinates":[-83.27497,30.827061],"type":"Point"}
}