{
  "type": "Feature",
  "properties": {
    "iso:country":"US",
    "sg:address":"4951 Kings Camp Rd SE",
    "sg:city":"Acworth",
    "sg:classifiers":[
        {
            "category":"Shopping",
            "subcategory":"Hobbies, Toys, & Games",
            "type":"Retail Goods"
        }
    ],
    "sg:phone":"+1 770 974 9623",
    "sg:postcode":"30102",
    "sg:province":"GA",
    "wof:name":"Big Beaks Bird Toys",
    "wof:placetype":"venue"
},
  "geometry": {"coordinates":[-84.699009,34.117038],"type":"Point"}
}