{
  "type": "Feature",
  "properties": {
    "addr:full":"108 Willowpeg Rd Rincon GA 31326",
    "addr:housenumber":"108",
    "addr:postcode":"31326",
    "addr:street":"Willowpeg Rd",
    "iso:country":"US",
    "sg:address":"108 Willowpeg Rd",
    "sg:city":"Rincon",
    "sg:classifiers":[
        {
            "category":"Education",
            "subcategory":"Dance Studio",
            "type":"Public Place"
        }
    ],
    "sg:phone":"+1 912 826 0314",
    "sg:postcode":"31326",
    "sg:province":"GA",
    "wof:name":"Southern Dance Center",
    "wof:placetype":"venue"
},
  "geometry": {"coordinates":[-81.21492600000001,32.267264],"type":"Point"}
}