{
  "type": "Feature",
  "properties": {
    "iso:country":"US",
    "sg:address":"1502 Roswell Rd",
    "sg:city":"Marietta",
    "sg:classifiers":[
        {
            "category":"Retail",
            "subcategory":"Laundry & Dry Cleaning",
            "type":"Services"
        }
    ],
    "sg:phone":"+1 770 973 6939",
    "sg:postcode":"30062",
    "sg:province":"GA",
    "wof:name":"Admiral Cleaners & Laundry",
    "wof:placetype":"venue"
},
  "geometry": {"coordinates":[-84.509399,33.950699],"type":"Point"}
}