{
  "type": "Feature",
  "properties": {
    "iso:country":"US",
    "sg:address":"3560 Hilton Ave",
    "sg:city":"Columbus",
    "sg:classifiers":[
        {
            "category":"Professional",
            "subcategory":"Computer Services",
            "type":"Services"
        }
    ],
    "sg:phone":"+1 706 641 3100",
    "sg:postcode":"31904",
    "sg:province":"GA",
    "sg:tags":[
        "internet"
    ],
    "wof:name":"First Internet Alliance Inc",
    "wof:placetype":"venue"
},
  "geometry": {"coordinates":[-84.95889699999999,32.498231],"type":"Point"}
}