{
  "type": "Feature",
  "properties": {
    "addr:full":"2100 E Exchange Pl Tucker GA 30084",
    "addr:housenumber":"2100",
    "addr:postcode":"30084",
    "addr:street":"E Exchange Pl",
    "iso:country":"US",
    "sg:address":"2100 E Exchange Pl",
    "sg:city":"Tucker",
    "sg:classifiers":[
        {
            "category":"Travel",
            "subcategory":"Hotels & Motels",
            "type":"Entertainment"
        }
    ],
    "sg:phone":"+1 770 270 7479",
    "sg:postcode":"30084",
    "sg:province":"GA",
    "sg:tags":[
        "operation"
    ],
    "wof:name":"Marriott",
    "wof:placetype":"venue"
},
  "geometry": {"coordinates":[-84.24247099999999,33.844123],"type":"Point"}
}