{
  "type": "Feature",
  "properties": {
    "addr:full":"2034 Queensbury Dr Acworth GA 30102",
    "addr:housenumber":"2034",
    "addr:postcode":"30102",
    "addr:street":"Queensbury Dr",
    "iso:country":"US",
    "sg:address":"2034 Queensbury Dr",
    "sg:city":"Acworth",
    "sg:classifiers":[
        {
            "category":"Building & Trades",
            "subcategory":"Plumbing",
            "type":"Services"
        }
    ],
    "sg:phone":"+1 404 391 7021",
    "sg:postcode":"30102",
    "sg:province":"GA",
    "sg:tags":[
        "plumbing",
        "contractor"
    ],
    "wof:name":"Nabor Plumbing",
    "wof:placetype":"venue"
},
  "geometry": {"coordinates":[-84.59308799999999,34.106319],"type":"Point"}
}