{
  "type": "Feature",
  "properties": {
    "addr:full":"1818 Independence Sq Atlanta GA 30338",
    "addr:housenumber":"1818",
    "addr:postcode":"30338",
    "addr:street":"Independence Sq",
    "iso:country":"US",
    "sg:address":"1818 Independence Sq",
    "sg:city":"Atlanta",
    "sg:classifiers":[
        {
            "category":"Wholesale",
            "subcategory":"Photographic Equipment",
            "type":"Manufacturing & Wholesale Goods"
        }
    ],
    "sg:phone":"+1 770 393 3366",
    "sg:postcode":"30338",
    "sg:province":"GA",
    "sg:tags":[
        "portable",
        "rental",
        "datum",
        "projector",
        "sales"
    ],
    "wof:name":"Easy Audio-Visual",
    "wof:placetype":"venue"
},
  "geometry": {"coordinates":[-84.312039,33.930512],"type":"Point"}
}