{
  "type": "Feature",
  "properties": {
    "addr:full":"100 Blackberry Run Fayetteville GA 30214",
    "addr:housenumber":"100",
    "addr:postcode":"30214",
    "addr:street":"Blackberry Run",
    "iso:country":"US",
    "sg:address":"100 Blackberry Run",
    "sg:city":"Fayetteville",
    "sg:classifiers":[
        {
            "category":"Health Services",
            "subcategory":"Doctor",
            "type":"Services"
        }
    ],
    "sg:phone":"+1 404 766 3471",
    "sg:postcode":"30214",
    "sg:province":"GA",
    "sg:tags":[
        "medical"
    ],
    "wof:name":"Joe U Choi",
    "wof:placetype":"venue"
},
  "geometry": {"coordinates":[-84.513958,33.488755],"type":"Point"}
}