{
  "type": "Feature",
  "properties": {
    "iso:country":"US",
    "sg:address":"1528 Wildwood Ave",
    "sg:city":"Columbus",
    "sg:classifiers":[
        {
            "category":"Real Estate",
            "subcategory":"Real Estate Operator",
            "type":"Services"
        }
    ],
    "sg:phone":"+1 706 596 9111",
    "sg:postcode":"31906",
    "sg:province":"GA",
    "sg:tags":[
        "building",
        "apartment"
    ],
    "wof:name":"Hillcrest Apts",
    "wof:placetype":"venue"
},
  "geometry": {"coordinates":[-84.95768700000001,32.475437],"type":"Point"}
}