{
  "type": "Feature",
  "properties": {
    "iso:country":"US",
    "sg:address":"903 Hillcrest Pkwy",
    "sg:city":"Dublin",
    "sg:classifiers":[
        {
            "category":"Food & Beverages",
            "subcategory":"Liquor & Beverages",
            "type":"Retail Goods"
        },
        {
            "category":"Wholesale",
            "subcategory":"Beer",
            "type":"Manufacturing & Wholesale Goods"
        }
    ],
    "sg:phone":"+1 478 272 7085",
    "sg:postcode":"31021",
    "sg:province":"GA",
    "sg:tags":[
        "alcoholic"
    ],
    "wof:name":"Shamrock Beverage Mart",
    "wof:placetype":"venue"
},
  "geometry": {"coordinates":[-82.92616,32.549341],"type":"Point"}
}