{
  "type": "Feature",
  "properties": {
    "addr:full":"510 W Mary St Dublin GA 31021",
    "addr:housenumber":"510",
    "addr:postcode":"31021",
    "addr:street":"W Mary St",
    "iso:country":"US",
    "sg:address":"510 W Mary St",
    "sg:city":"Dublin",
    "sg:classifiers":[
        {
            "category":"Personal",
            "subcategory":"Beauty Salon",
            "type":"Services"
        }
    ],
    "sg:phone":"+1 478 275 0026",
    "sg:postcode":"31021",
    "sg:province":"GA",
    "wof:name":"DHA Hair Extravangaza",
    "wof:placetype":"venue"
},
  "geometry": {"coordinates":[-82.914452,32.543897],"type":"Point"}
}