{
  "type": "Feature",
  "properties": {
    "addr:full":"3573 Pine St Atlanta GA 30340",
    "addr:housenumber":"3573",
    "addr:postcode":"30340",
    "addr:street":"Pine St",
    "iso:country":"US",
    "sg:address":"3573 Pine St",
    "sg:city":"Atlanta",
    "sg:classifiers":[
        {
            "category":"Food & Beverages",
            "subcategory":"Groceries & Convenience Stores",
            "type":"Retail Goods"
        }
    ],
    "sg:phone":"+1 770 458 3655",
    "sg:postcode":"30340",
    "sg:province":"GA",
    "wof:name":"Chawk Bazar Inc",
    "wof:placetype":"venue"
},
  "geometry": {"coordinates":[-84.27067099999999,33.895358],"type":"Point"}
}