{
  "type": "Feature",
  "properties": {
    "iso:country":"US",
    "sg:address":"1144 Alpharetta St Ste 2A",
    "sg:city":"Roswell",
    "sg:classifiers":[
        {
            "category":"Banks & Credit Unions",
            "subcategory":"Financial Services",
            "type":"Services"
        }
    ],
    "sg:phone":"+1 678 277 9090",
    "sg:postcode":"30075",
    "sg:province":"GA",
    "sg:tags":[
        "money",
        "order"
    ],
    "wof:name":"Servicious Pronto",
    "wof:placetype":"venue"
},
  "geometry": {"coordinates":[-84.355467,34.029782],"type":"Point"}
}