{
  "type": "Feature",
  "properties": {
    "addr:full":"401 Cherry St Macon GA 31201",
    "addr:housenumber":"401",
    "addr:postcode":"31201",
    "addr:street":"Cherry St",
    "iso:country":"US",
    "sg:address":"401 Cherry St",
    "sg:city":"Macon",
    "sg:classifiers":[
        {
            "category":"Professional",
            "type":"Services"
        },
        {
            "category":"Professional",
            "subcategory":"Lawyer & Legal Services",
            "type":"Services"
        }
    ],
    "sg:phone":"+1 478 750 1444",
    "sg:postcode":"31201",
    "sg:province":"GA",
    "sg:tags":[
        "arbitration",
        "attorney",
        "family",
        "divorce",
        "mediation",
        "adoption",
        "law"
    ],
    "sg:website":"http://www.boylanhill.com",
    "wof:name":"Boylan-Hill, Pamela M",
    "wof:placetype":"venue"
},
  "geometry": {"coordinates":[-83.62603,32.834782],"type":"Point"}
}