{
  "type": "Feature",
  "properties": {
    "addr:full":"56 River Ridge Ct Blue Ridge GA 30513",
    "addr:housenumber":"56",
    "addr:postcode":"30513",
    "addr:street":"River Ridge Ct",
    "iso:country":"US",
    "sg:address":"56 River Ridge Ct",
    "sg:city":"Blue Ridge",
    "sg:classifiers":[
        {
            "category":"Organizations",
            "subcategory":"Membership Organization",
            "type":"Services"
        }
    ],
    "sg:phone":"+1 706 838 4112",
    "sg:postcode":"30513",
    "sg:province":"GA",
    "wof:name":"Abeca Foundation",
    "wof:placetype":"venue"
},
  "geometry": {"coordinates":[-84.24328300000001,34.78456],"type":"Point"}
}