{
  "type": "Feature",
  "properties": {
    "iso:country":"US",
    "sg:address":"599 Leah Dr",
    "sg:city":"Powder Springs",
    "sg:classifiers":[
        {
            "category":"Professional",
            "subcategory":"Business Services",
            "type":"Services"
        }
    ],
    "sg:phone":"+1 770 426 7126",
    "sg:postcode":"30127",
    "sg:province":"GA",
    "sg:tags":[
        "broker"
    ],
    "wof:name":"Martin Enterprises",
    "wof:placetype":"venue"
},
  "geometry": {"coordinates":[-84.663944,33.936064],"type":"Point"}
}