{
  "type": "Feature",
  "properties": {
    "iso:country":"US",
    "sg:address":"5196 Corinth Cir",
    "sg:city":"Stone Mountain",
    "sg:classifiers":[
        {
            "category":"Professional",
            "subcategory":"Art Services",
            "type":"Services"
        }
    ],
    "sg:phone":"+1 404 307 9719",
    "sg:postcode":"30087",
    "sg:province":"GA",
    "sg:tags":[
        "commercial",
        "design"
    ],
    "wof:name":"Chazzer Net Designs LLC",
    "wof:placetype":"venue"
},
  "geometry": {"coordinates":[-84.11672900000001,33.833943],"type":"Point"}
}