{
  "type": "Feature",
  "properties": {
    "addr:full":"2620 Milledgeville Rd Augusta GA 30904",
    "addr:housenumber":"2620",
    "addr:postcode":"30904",
    "addr:street":"Milledgeville Rd",
    "iso:country":"US",
    "sg:address":"2620 Milledgeville Rd",
    "sg:city":"Augusta",
    "sg:classifiers":[
        {
            "category":"Recreation",
            "type":"Entertainment"
        }
    ],
    "sg:phone":"+1 706 733 8862",
    "sg:postcode":"30904",
    "sg:province":"GA",
    "wof:name":"Casino Connection Ltd",
    "wof:placetype":"venue"
},
  "geometry": {"coordinates":[-82.02115999999999,33.44679],"type":"Point"}
}