{
  "type": "Feature",
  "properties": {
    "addr:full":"1225 Tifton Eldorado Rd Tifton GA 31794",
    "addr:housenumber":"1225",
    "addr:postcode":"31794",
    "addr:street":"Eldorado Rd",
    "iso:country":"US",
    "sg:address":"1225 Tifton Eldorado Rd",
    "sg:city":"Tifton",
    "sg:phone":"+1 229 382 2799",
    "sg:postcode":"31794",
    "sg:province":"GA",
    "sg:tags":[
        "farm",
        "tobacco"
    ],
    "wof:name":"Willie Moore",
    "wof:placetype":"venue"
},
  "geometry": {"coordinates":[-83.474287,31.386594],"type":"Point"}
}