{
  "type": "Feature",
  "properties": {
    "iso:country":"US",
    "sg:address":"7525 Covington Hwy",
    "sg:city":"Lithonia",
    "sg:classifiers":[
        {
            "category":"Wholesale",
            "subcategory":"Machinery & Supplies",
            "type":"Manufacturing & Wholesale Goods"
        }
    ],
    "sg:phone":"+1 770 482 4712",
    "sg:postcode":"30058",
    "sg:province":"GA",
    "sg:tags":[
        "shop",
        "equipment",
        "salon",
        "barber",
        "beauty"
    ],
    "wof:name":"Sally Beauty Supply 655",
    "wof:placetype":"venue"
},
  "geometry": {"coordinates":[-84.11417299999999,33.706627],"type":"Point"}
}