{
  "type": "Feature",
  "properties": {
    "iso:country":"US",
    "sg:address":"327 N McIntosh St",
    "sg:city":"Elberton",
    "sg:classifiers":[
        {
            "category":"Home & Garden",
            "subcategory":"Carpets & Floor Coverings",
            "type":"Retail Goods"
        }
    ],
    "sg:phone":"+1 706 283 8299",
    "sg:postcode":"30635",
    "sg:province":"GA",
    "sg:tags":[
        "tile"
    ],
    "wof:name":"Hover Carpet & Paint",
    "wof:placetype":"venue"
},
  "geometry": {"coordinates":[-82.863028,34.115878],"type":"Point"}
}