{
  "type": "Feature",
  "properties": {
    "iso:country":"US",
    "sg:address":"57 Forsyth St NW",
    "sg:city":"Atlanta",
    "sg:classifiers":[
        {
            "category":"Health Services",
            "subcategory":"Optometrist",
            "type":"Services"
        }
    ],
    "sg:phone":"+1 404 688 7398",
    "sg:postcode":"30303",
    "sg:province":"GA",
    "wof:name":"Gurin Ronald B Dr",
    "wof:placetype":"venue"
},
  "geometry": {"coordinates":[-84.38979999999999,33.756009],"type":"Point"}
}