{
  "type": "Feature",
  "properties": {
    "iso:country":"US",
    "sg:address":"2653 Marcia Dr SW",
    "sg:city":"Lawrenceville",
    "sg:classifiers":[
        {
            "category":"Building & Trades",
            "subcategory":"Construction",
            "type":"Services"
        }
    ],
    "sg:phone":"+1 770 736 0804",
    "sg:postcode":"30044",
    "sg:province":"GA",
    "sg:tags":[
        "carpentry",
        "contractor"
    ],
    "wof:name":"Starr Interior Trim & Finish",
    "wof:placetype":"venue"
},
  "geometry": {"coordinates":[-84.049364,33.892675],"type":"Point"}
}