{
  "type": "Feature",
  "properties": {
    "iso:country":"US",
    "sg:address":"6930 Polo Dr",
    "sg:city":"Cumming",
    "sg:classifiers":[
        {
            "category":"Organizations",
            "subcategory":"Community Association",
            "type":"Services"
        }
    ],
    "sg:phone":"+1 770 844 7844",
    "sg:postcode":"30040",
    "sg:province":"GA",
    "wof:name":"Adams Crossing Homeowners",
    "wof:placetype":"venue"
},
  "geometry": {"coordinates":[-84.204403,34.186896],"type":"Point"}
}