{
  "type": "Feature",
  "properties": {
    "addr:full":"3400 Peachtree Rd NE Ste 1400 Atlanta GA 30326",
    "addr:housenumber":"3400",
    "addr:postcode":"30326",
    "addr:street":"Peachtree Rd Ne Ste 1400",
    "iso:country":"US",
    "sg:address":"3400 Peachtree Rd NE Ste 1400",
    "sg:city":"Atlanta",
    "sg:classifiers":[
        {
            "category":"Professional",
            "subcategory":"Lawyer & Legal Services",
            "type":"Services"
        }
    ],
    "sg:phone":"+1 404 261 3900",
    "sg:postcode":"30326",
    "sg:province":"GA",
    "wof:name":"McBurney Emily W Atty",
    "wof:placetype":"venue"
},
  "geometry": {"coordinates":[-84.364502,33.8489],"type":"Point"}
}