{
  "type": "Feature",
  "properties": {
    "addr:full":"9723 Spruill Rd Alpharetta GA 30022",
    "addr:housenumber":"9723",
    "addr:postcode":"30022",
    "addr:street":"Spruill Rd",
    "iso:country":"US",
    "sg:address":"9723 Spruill Rd",
    "sg:city":"Alpharetta",
    "sg:classifiers":[
        {
            "category":"Professional",
            "subcategory":"Business Services",
            "type":"Services"
        },
        {
            "category":"Home & Garden",
            "subcategory":"Home Furnishings",
            "type":"Retail Goods"
        }
    ],
    "sg:phone":"+1 770 663 3048",
    "sg:postcode":"30022",
    "sg:province":"GA",
    "sg:tags":[
        "curtain",
        "made",
        "drapery"
    ],
    "sg:website":"www.fabriccreations.net",
    "wof:name":"Fabric Creations",
    "wof:placetype":"venue"
},
  "geometry": {"coordinates":[-84.22250099999999,34.015092],"type":"Point"}
}