{
  "type": "Feature",
  "properties": {
    "addr:full":"90 Kelli Clark Ct SE Cartersville GA 30121",
    "addr:housenumber":"90",
    "addr:postcode":"30121",
    "addr:street":"Kelli Clark Ct Se",
    "iso:country":"US",
    "sg:address":"90 Kelli Clark Ct SE",
    "sg:city":"Cartersville",
    "sg:classifiers":[
        {
            "category":"Building & Trades",
            "subcategory":"Construction",
            "type":"Services"
        }
    ],
    "sg:phone":"+1 770 917 0945",
    "sg:postcode":"30121",
    "sg:province":"GA",
    "sg:tags":[
        "downspouts",
        "gutter"
    ],
    "wof:name":"Gutter & Metal Enterprises",
    "wof:placetype":"venue"
},
  "geometry": {"coordinates":[-84.728134,34.084541],"type":"Point"}
}