{
  "type": "Feature",
  "properties": {
    "iso:country":"US",
    "sg:address":"239 12th Ave NE",
    "sg:city":"Cairo",
    "sg:classifiers":[
        {
            "category":"Place Of Worship",
            "subcategory":"Church",
            "type":"Public Place"
        },
        {
            "category":"Place Of Worship",
            "type":"Public Place"
        }
    ],
    "sg:phone":"+1 229 377 1007",
    "sg:postcode":"39828",
    "sg:province":"GA",
    "sg:tags":[
        "churches-non-denominational"
    ],
    "wof:name":"Cairo Church Of Christ Inc",
    "wof:placetype":"venue"
},
  "geometry": {"coordinates":[-84.205152,30.889663],"type":"Point"}
}