{
  "type": "Feature",
  "properties": {
    "iso:country":"US",
    "sg:address":"4440 Pierwood Way",
    "sg:city":"Evans",
    "sg:classifiers":[
        {
            "category":"Restaurant",
            "type":"Food & Drink"
        }
    ],
    "sg:phone":"+1 706 210 8697",
    "sg:postcode":"30809",
    "sg:province":"GA",
    "sg:tags":[
        "eating"
    ],
    "wof:name":"Mason Jar",
    "wof:placetype":"venue"
},
  "geometry": {"coordinates":[-82.135318,33.557811],"type":"Point"}
}