{
  "type": "Feature",
  "properties": {
    "iso:country":"US",
    "sg:address":"306 Gordon St",
    "sg:city":"Glennville",
    "sg:classifiers":[
        {
            "category":"Shopping",
            "subcategory":"Bicycles & Sporting Goods",
            "type":"Retail Goods"
        }
    ],
    "sg:phone":"+1 912 654 3408",
    "sg:postcode":"30427",
    "sg:province":"GA",
    "sg:tags":[
        "bait",
        "fishing"
    ],
    "sg:website":"www.armstrongcricket.com",
    "wof:name":"Armstrong Cricket Farm",
    "wof:placetype":"venue"
},
  "geometry": {"coordinates":[-81.93525099999999,31.930323],"type":"Point"}
}