{
  "type": "Feature",
  "properties": {
    "iso:country":"US",
    "sg:address":"2373 Brittany Ln",
    "sg:city":"Marietta",
    "sg:classifiers":[
        {
            "category":"Wholesale",
            "subcategory":"Medical Equipment & Supplies",
            "type":"Manufacturing & Wholesale Goods"
        }
    ],
    "sg:phone":"+1 770 998 1501",
    "sg:postcode":"30062",
    "sg:province":"GA",
    "wof:name":"Robert Hodges",
    "wof:placetype":"venue"
},
  "geometry": {"coordinates":[-84.421654,34.005094],"type":"Point"}
}