{
  "type": "Feature",
  "properties": {
    "iso:country":"US",
    "sg:address":"493 E Clayton St",
    "sg:city":"Athens",
    "sg:classifiers":[
        {
            "category":"Restaurant",
            "type":"Food & Drink"
        }
    ],
    "sg:phone":"+1 706 549 3663",
    "sg:postcode":"30601",
    "sg:province":"GA",
    "sg:tags":[
        "eating"
    ],
    "wof:name":"Bluebird Cafe",
    "wof:placetype":"venue"
},
  "geometry": {"coordinates":[-83.37369200000001,33.958984],"type":"Point"}
}