{
  "type": "Feature",
  "properties": {
    "addr:full":"787 Cascade Avenue SW Atlanta GA 30310",
    "addr:housenumber":"787",
    "addr:postcode":"30310",
    "addr:street":"Cascade Avenue Sw",
    "iso:country":"US",
    "sg:address":"787 Cascade Avenue SW",
    "sg:city":"Atlanta",
    "sg:classifiers":[
        {
            "category":"Food & Beverages",
            "subcategory":"Groceries & Convenience Stores",
            "type":"Retail Goods"
        }
    ],
    "sg:phone":"+1 404 755 8718",
    "sg:postcode":"30310",
    "sg:province":"GA",
    "wof:name":"Cleopatra",
    "wof:placetype":"venue"
},
  "geometry": {"coordinates":[-84.43676499999999,33.734483],"type":"Point"}
}