{
  "type": "Feature",
  "properties": {
    "addr:full":"229 Peachtree St NW Atlanta GA 30303",
    "addr:housenumber":"229",
    "addr:postcode":"30303",
    "addr:street":"Peachtree St Nw",
    "iso:country":"US",
    "sg:address":"229 Peachtree St NW",
    "sg:city":"Atlanta",
    "sg:classifiers":[
        {
            "category":"Professional",
            "subcategory":"Lawyer & Legal Services",
            "type":"Services"
        }
    ],
    "sg:phone":"+1 404 607 9008",
    "sg:postcode":"30303",
    "sg:province":"GA",
    "sg:tags":[
        "attorney"
    ],
    "wof:name":"Martha A Miller Law Office",
    "wof:placetype":"venue"
},
  "geometry": {"coordinates":[-84.38749,33.760771],"type":"Point"}
}