{
  "type": "Feature",
  "properties": {
    "addr:full":"3702 2nd Ave Columbus GA 31904",
    "addr:housenumber":"3702",
    "addr:postcode":"31904",
    "addr:street":"2Nd Ave",
    "iso:country":"US",
    "sg:address":"3702 2nd Ave",
    "sg:city":"Columbus",
    "sg:classifiers":[
        {
            "category":"Banks & Credit Unions",
            "subcategory":"Bank",
            "type":"Services"
        }
    ],
    "sg:phone":"+1 706 649 2643",
    "sg:postcode":"31904",
    "sg:province":"GA",
    "wof:name":"Columbus Bank & Trust Co",
    "wof:placetype":"venue"
},
  "geometry": {"coordinates":[-84.989977,32.49726],"type":"Point"}
}