{
  "type": "Feature",
  "properties": {
    "addr:full":"5270 Lawrenceville Hwy NW Lilburn GA 30047",
    "addr:housenumber":"5270",
    "addr:postcode":"30047",
    "addr:street":"Lawrenceville Hwy Nw",
    "iso:country":"US",
    "sg:address":"5270 Lawrenceville Hwy NW",
    "sg:city":"Lilburn",
    "sg:classifiers":[
        {
            "category":"Retail",
            "subcategory":"Auto Repair",
            "type":"Services"
        }
    ],
    "sg:phone":"+1 770 923 6494",
    "sg:postcode":"30047",
    "sg:province":"GA",
    "wof:name":"Jackovitch Enterprise",
    "wof:placetype":"venue"
},
  "geometry": {"coordinates":[-84.15560600000001,33.889003],"type":"Point"}
}