{
  "type": "Feature",
  "properties": {
    "addr:full":"3726 Peach Orchard Rd Augusta GA 30906",
    "addr:housenumber":"3726",
    "addr:postcode":"30906",
    "addr:street":"Peach Orchard Rd",
    "iso:country":"US",
    "sg:address":"3726 Peach Orchard Rd",
    "sg:city":"Augusta",
    "sg:classifiers":[
        {
            "category":"Building & Trades",
            "subcategory":"Plumbing",
            "type":"Services"
        }
    ],
    "sg:phone":"+1 706 793 3593",
    "sg:postcode":"30906",
    "sg:province":"GA",
    "sg:tags":[
        "conditioning",
        "air",
        "system",
        "contractor"
    ],
    "wof:name":"Williford Heating & Air Cond",
    "wof:placetype":"venue"
},
  "geometry": {"coordinates":[-82.041653,33.360599],"type":"Point"}
}