{
  "type": "Feature",
  "properties": {
    "iso:country":"US",
    "sg:address":"4270 Klondike Rd",
    "sg:city":"Lithonia",
    "sg:classifiers":[
        {
            "category":"Building & Trades",
            "subcategory":"Construction",
            "type":"Services"
        }
    ],
    "sg:phone":"+1 770 987 7036",
    "sg:postcode":"30038",
    "sg:province":"GA",
    "sg:tags":[
        "mason",
        "masonry",
        "industrial",
        "contractors-commercial",
        "contractor"
    ],
    "wof:name":"B&L Quality Masonry Inc",
    "wof:placetype":"venue"
},
  "geometry": {"coordinates":[-84.124236,33.657765],"type":"Point"}
}