{
  "type": "Feature",
  "properties": {
    "addr:full":"3425 Cascade Rd Atlanta GA 30311",
    "addr:housenumber":"3425",
    "addr:postcode":"30311",
    "addr:street":"Cascade Rd",
    "iso:country":"US",
    "sg:address":"3425 Cascade Rd",
    "sg:city":"Atlanta",
    "sg:classifiers":[
        {
            "category":"Cinema",
            "subcategory":"Movie Rental",
            "type":"Entertainment"
        }
    ],
    "sg:phone":"+1 404 699 6046",
    "sg:postcode":"30311",
    "sg:province":"GA",
    "sg:tags":[
        "motion",
        "picture",
        "video",
        "tape"
    ],
    "wof:name":"Blockbuster",
    "wof:placetype":"venue"
},
  "geometry": {"coordinates":[-84.50196699999999,33.7231],"type":"Point"}
}