{
  "type": "Feature",
  "properties": {
    "iso:country":"US",
    "sg:address":"4560 Blakedale Rd",
    "sg:city":"Roswell",
    "sg:classifiers":[
        {
            "category":"Real Estate",
            "subcategory":"Real Estate Agent",
            "type":"Services"
        }
    ],
    "sg:phone":"+1 770 641 7034",
    "sg:postcode":"30075",
    "sg:province":"GA",
    "sg:tags":[
        "agency",
        "rental"
    ],
    "wof:name":"Bounce Atlanta Moonwalk Rental",
    "wof:placetype":"venue"
},
  "geometry": {"coordinates":[-84.42637499999999,34.051403],"type":"Point"}
}