{
  "type": "Feature",
  "properties": {
    "addr:full":"680 Smokey Rd Newnan GA 30263",
    "addr:housenumber":"680",
    "addr:postcode":"30263",
    "addr:street":"Smokey Rd",
    "iso:country":"US",
    "sg:address":"680 Smokey Rd",
    "sg:city":"Newnan",
    "sg:classifiers":[
        {
            "category":"Building & Trades",
            "subcategory":"Electrical",
            "type":"Services"
        }
    ],
    "sg:phone":"+1 770 304 8335",
    "sg:postcode":"30263",
    "sg:province":"GA",
    "sg:tags":[
        "electrical",
        "contractor"
    ],
    "wof:name":"Kaufman Electric",
    "wof:placetype":"venue"
},
  "geometry": {"coordinates":[-84.83398800000001,33.359054],"type":"Point"}
}