{
  "type": "Feature",
  "properties": {
    "addr:full":"259 Peters St Atlanta GA 30313",
    "addr:housenumber":"259",
    "addr:postcode":"30313",
    "addr:street":"Peters St",
    "iso:country":"US",
    "sg:address":"259 Peters St",
    "sg:city":"Atlanta",
    "sg:classifiers":[
        {
            "category":"Restaurant",
            "type":"Food & Drink"
        },
        {
            "category":"Food & Beverages",
            "subcategory":"Bakery",
            "type":"Retail Goods"
        }
    ],
    "sg:phone":"+1 404 588 1820",
    "sg:postcode":"30313",
    "sg:province":"GA",
    "sg:tags":[
        "sandwich",
        "pizza",
        "italian"
    ],
    "sg:website":"www.sliceatlanta.com/",
    "wof:name":"Slice",
    "wof:placetype":"venue"
},
  "geometry": {"coordinates":[-84.40173799999999,33.747472],"type":"Point"}
}