{
  "type": "Feature",
  "properties": {
    "iso:country":"US",
    "sg:address":"4708 Stagecoach Rd",
    "sg:city":"Albany",
    "sg:classifiers":[
        {
            "category":"Home & Garden",
            "subcategory":"Furniture",
            "type":"Retail Goods"
        }
    ],
    "sg:phone":"+1 229 395 2291",
    "sg:postcode":"31705",
    "sg:province":"GA",
    "sg:tags":[
        "store"
    ],
    "wof:name":"Graham Collection",
    "wof:placetype":"venue"
},
  "geometry": {"coordinates":[-84.11861500000001,31.456429],"type":"Point"}
}