{
  "type": "Feature",
  "properties": {
    "addr:full":"476 Glen Iris Drive NE Atlanta GA 30308",
    "addr:housenumber":"476",
    "addr:postcode":"30308",
    "addr:street":"Glen Iris Drive Ne",
    "iso:country":"US",
    "sg:address":"476 Glen Iris Drive NE",
    "sg:city":"Atlanta",
    "sg:classifiers":[
        {
            "category":"Organizations",
            "subcategory":"Religious Organization",
            "type":"Services"
        }
    ],
    "sg:phone":"+1 404 688 0528",
    "sg:postcode":"30308",
    "sg:province":"GA",
    "wof:name":"Saint Luke Baptist Church",
    "wof:placetype":"venue"
},
  "geometry": {"coordinates":[-84.367597,33.767396],"type":"Point"}
}