{
  "type": "Feature",
  "properties": {
    "iso:country":"US",
    "sg:address":"3015 Sonya Ln",
    "sg:city":"Snellville",
    "sg:classifiers":[
        {
            "category":"Professional",
            "type":"Services"
        }
    ],
    "sg:phone":"+1 678 344 0888",
    "sg:postcode":"30078",
    "sg:province":"GA",
    "wof:name":"Harrison Aj Corp",
    "wof:placetype":"venue"
},
  "geometry": {"coordinates":[-84.006253,33.836598],"type":"Point"}
}