{
  "type": "Feature",
  "properties": {
    "iso:country":"US",
    "sg:address":"301 Delwood Dr",
    "sg:city":"Rome",
    "sg:classifiers":[
        {
            "category":"Shopping",
            "subcategory":"Gifts & Souvenirs",
            "type":"Retail Goods"
        }
    ],
    "sg:phone":"+1 706 234 7963",
    "sg:postcode":"30165",
    "sg:province":"GA",
    "wof:name":"L & P Gifts & Collectables",
    "wof:placetype":"venue"
},
  "geometry": {"coordinates":[-85.21269599999999,34.272741],"type":"Point"}
}