{
  "type": "Feature",
  "properties": {
    "iso:country":"US",
    "sg:address":"3897 Flowers Rd",
    "sg:city":"Atlanta",
    "sg:classifiers":[
        {
            "category":"Building & Trades",
            "subcategory":"Locksmith",
            "type":"Services"
        }
    ],
    "sg:phone":"+1 866 822 2497",
    "sg:postcode":"30360",
    "sg:province":"GA",
    "sg:tags":[
        "key"
    ],
    "wof:name":"A 1 Emergency Locksmith",
    "wof:placetype":"venue"
},
  "geometry": {"coordinates":[-84.277101,33.906713],"type":"Point"}
}