{
  "type": "Feature",
  "properties": {
    "addr:full":"117 Glynn Ave Fitzgerald GA 31750",
    "addr:housenumber":"117",
    "addr:postcode":"31750",
    "addr:street":"Glynn Ave",
    "iso:country":"US",
    "sg:address":"117 Glynn Ave",
    "sg:city":"Fitzgerald",
    "sg:phone":"+1 229 423 4484",
    "sg:postcode":"31750",
    "sg:province":"GA",
    "sg:tags":[
        "communications",
        "telegraph"
    ],
    "wof:name":"Quik Internet South Georgia",
    "wof:placetype":"venue"
},
  "geometry": {"coordinates":[-83.267121,31.715638],"type":"Point"}
}