{
  "type": "Feature",
  "properties": {
    "iso:country":"US",
    "sg:address":"2190 Connally Dr",
    "sg:city":"Atlanta",
    "sg:classifiers":[
        {
            "category":"Professional",
            "type":"Services"
        },
        {
            "category":"Shopping",
            "subcategory":"Party Supplies",
            "type":"Retail Goods"
        },
        {
            "category":"Food & Beverages",
            "subcategory":"Liquor & Beverages",
            "type":"Retail Goods"
        }
    ],
    "sg:phone":"+1 770 330 0213",
    "sg:postcode":"30344",
    "sg:province":"GA",
    "sg:tags":[
        "beer",
        "wine",
        "spirit",
        "caterer"
    ],
    "sg:website":"www.AtlantaMargaritaMan.com",
    "wof:name":"Atlanta Margarita Man",
    "wof:placetype":"venue"
},
  "geometry": {"coordinates":[-84.460261,33.695509],"type":"Point"}
}