{
  "type": "Feature",
  "properties": {
    "addr:full":"1797 N Akin Dr NE Atlanta GA 30345",
    "addr:housenumber":"1797",
    "addr:postcode":"30345",
    "addr:street":"N Akin Dr Ne",
    "iso:country":"US",
    "sg:address":"1797 N Akin Dr NE",
    "sg:city":"Atlanta",
    "sg:classifiers":[
        {
            "category":"Health Services",
            "subcategory":"Doctor",
            "type":"Services"
        }
    ],
    "sg:phone":"+1 404 325 8080",
    "sg:postcode":"30345",
    "sg:province":"GA",
    "sg:tags":[
        "physician",
        "surgeon"
    ],
    "wof:name":"Eleanor Ho MD",
    "wof:placetype":"venue"
},
  "geometry": {"coordinates":[-84.286295,33.835482],"type":"Point"}
}