{
  "type": "Feature",
  "properties": {
    "addr:full":"105 Andrea Cir Villa Rica GA 30180",
    "addr:housenumber":"105",
    "addr:postcode":"30180",
    "addr:street":"Andrea Cir",
    "iso:country":"US",
    "sg:address":"105 Andrea Cir",
    "sg:city":"Villa Rica",
    "sg:classifiers":[
        {
            "category":"Professional",
            "type":"Services"
        }
    ],
    "sg:phone":"+1 770 832 8018",
    "sg:postcode":"30180",
    "sg:province":"GA",
    "wof:name":"Michael S Dean",
    "wof:placetype":"venue"
},
  "geometry": {"coordinates":[-84.92086999999999,33.622202],"type":"Point"}
}