{
  "type": "Feature",
  "properties": {
    "iso:country":"US",
    "sg:address":"1143 Lancaster Close NW",
    "sg:city":"Lawrenceville",
    "sg:classifiers":[
        {
            "category":"Building & Trades",
            "subcategory":"Construction",
            "type":"Services"
        }
    ],
    "sg:phone":"+1 678 614 3528",
    "sg:postcode":"30043",
    "sg:province":"GA",
    "sg:tags":[
        "house"
    ],
    "wof:name":"Apex Construction",
    "wof:placetype":"venue"
},
  "geometry": {"coordinates":[-84.022133,33.972594],"type":"Point"}
}