{
  "type": "Feature",
  "properties": {
    "iso:country":"US",
    "sg:address":"3016 Adriatic Ct",
    "sg:city":"Norcross",
    "sg:classifiers":[
        {
            "category":"Building & Trades",
            "subcategory":"Cleaning & Sanitation",
            "type":"Services"
        }
    ],
    "sg:phone":"+1 770 840 6018",
    "sg:postcode":"30071",
    "sg:province":"GA",
    "sg:tags":[
        "carpet"
    ],
    "wof:name":"Sears Authorized Carpet & Uph Clng",
    "wof:placetype":"venue"
},
  "geometry": {"coordinates":[-84.239197,33.939301],"type":"Point"}
}