{
  "type": "Feature",
  "properties": {
    "iso:country":"US",
    "sg:address":"527 Commercial Dr",
    "sg:city":"Statham",
    "sg:classifiers":[
        {
            "category":"Restaurant",
            "type":"Food & Drink"
        }
    ],
    "sg:phone":"+1 770 725 4622",
    "sg:postcode":"30666",
    "sg:province":"GA",
    "sg:tags":[
        "mexican"
    ],
    "wof:name":"Tamale Factory",
    "wof:placetype":"venue"
},
  "geometry": {"coordinates":[-83.591881,33.959259],"type":"Point"}
}