{
  "type": "Feature",
  "properties": {
    "addr:full":"633 High St SE Gainesville GA 30501",
    "addr:housenumber":"633",
    "addr:postcode":"30501",
    "addr:street":"High St Se;Ga",
    "iso:country":"US",
    "sg:address":"633 High St SE",
    "sg:city":"Gainesville",
    "sg:classifiers":[
        {
            "category":"Wholesale",
            "subcategory":"Machinery & Supplies",
            "type":"Manufacturing & Wholesale Goods"
        }
    ],
    "sg:phone":"+1 770 297 8444",
    "sg:postcode":"30501",
    "sg:province":"GA",
    "sg:tags":[
        "pump"
    ],
    "wof:name":"Preferred Pump & Equipment",
    "wof:placetype":"venue"
},
  "geometry": {"coordinates":[-83.816581,34.295913],"type":"Point"}
}