{
  "type": "Feature",
  "properties": {
    "addr:full":"3117 E 1st St Vidalia GA 30474",
    "addr:housenumber":"3117",
    "addr:postcode":"30474",
    "addr:street":"E 1St St",
    "iso:country":"US",
    "sg:address":"3117 E 1st St",
    "sg:city":"Vidalia",
    "sg:classifiers":[
        {
            "category":"Shopping",
            "subcategory":"Clothing, Apparel, & Fashions",
            "type":"Retail Goods"
        }
    ],
    "sg:phone":"+1 912 538 0884",
    "sg:postcode":"30474",
    "sg:province":"GA",
    "sg:tags":[
        "apparel",
        "handbag",
        "accessory",
        "women's"
    ],
    "sg:website":"http://www.catofashions.com/",
    "wof:name":"Cato",
    "wof:placetype":"venue"
},
  "geometry": {"coordinates":[-82.361073,32.204743],"type":"Point"}
}