{
  "type": "Feature",
  "properties": {
    "addr:full":"2651 Walnut Rd Gainesville GA 30506",
    "addr:housenumber":"2651",
    "addr:postcode":"30506",
    "addr:street":"Walnut Rd",
    "iso:country":"US",
    "sg:address":"2651 Walnut Rd",
    "sg:city":"Gainesville",
    "sg:classifiers":[
        {
            "category":"Building & Trades",
            "subcategory":"Landscaping Services",
            "type":"Services"
        }
    ],
    "sg:phone":"+1 770 535 0416",
    "sg:postcode":"30506",
    "sg:province":"GA",
    "wof:name":"Complete Lawn Care",
    "wof:placetype":"venue"
},
  "geometry": {"coordinates":[-83.902855,34.339592],"type":"Point"}
}