{
  "type": "Feature",
  "properties": {
    "iso:country":"US",
    "sg:address":"1535 Foye Ave",
    "sg:city":"Columbus",
    "sg:classifiers":[
        {
            "category":"Shopping",
            "subcategory":"Used Merchandise",
            "type":"Retail Goods"
        }
    ],
    "sg:phone":"+1 706 687 5272",
    "sg:postcode":"31903",
    "sg:province":"GA",
    "wof:name":"Henry & Son",
    "wof:placetype":"venue"
},
  "geometry": {"coordinates":[-84.93359100000001,32.423693],"type":"Point"}
}