{
  "type": "Feature",
  "properties": {
    "addr:full":"260 14th St NW Atlanta GA 30318",
    "addr:housenumber":"260",
    "addr:postcode":"30318",
    "addr:street":"14Th St Nw",
    "iso:country":"US",
    "sg:address":"260 14th St NW",
    "sg:city":"Atlanta",
    "sg:classifiers":[
        {
            "category":"Education",
            "subcategory":"Special Training",
            "type":"Public Place"
        }
    ],
    "sg:phone":"+1 404 685 2820",
    "sg:postcode":"30318",
    "sg:province":"GA",
    "sg:tags":[
        "educational"
    ],
    "wof:name":"Georgia Radio Reading Svc",
    "wof:placetype":"venue"
},
  "geometry": {"coordinates":[-84.395081,33.786372],"type":"Point"}
}