{
  "type": "Feature",
  "properties": {
    "iso:country":"US",
    "sg:address":"75 14th Street NE",
    "sg:city":"Atlanta",
    "sg:classifiers":[
        {
            "category":"Professional",
            "subcategory":"Lawyer & Legal Services",
            "type":"Services"
        }
    ],
    "sg:phone":"+1 404 892 4900",
    "sg:postcode":"30309",
    "sg:province":"GA",
    "sg:tags":[
        "personal",
        "injury"
    ],
    "wof:name":"Thomas Brad W",
    "wof:placetype":"venue"
},
  "geometry": {"coordinates":[-84.385177,33.786632],"type":"Point"}
}