{
  "type": "Feature",
  "properties": {
    "iso:country":"US",
    "sg:address":"1402 Drum Flower Ct",
    "sg:city":"Stone Mountain",
    "sg:classifiers":[
        {
            "category":"Building & Trades",
            "subcategory":"Plumbing",
            "type":"Services"
        }
    ],
    "sg:phone":"+1 404 289 5427",
    "sg:postcode":"30083",
    "sg:province":"GA",
    "sg:tags":[
        "contractor"
    ],
    "wof:name":"A OK Heating & Cooling",
    "wof:placetype":"venue"
},
  "geometry": {"coordinates":[-84.21862,33.752236],"type":"Point"}
}