{
  "type": "Feature",
  "properties": {
    "iso:country":"US",
    "sg:address":"3228 Caley Mill Dr",
    "sg:city":"Powder Springs",
    "sg:classifiers":[
        {
            "category":"Building & Trades",
            "subcategory":"Cleaning & Sanitation",
            "type":"Services"
        }
    ],
    "sg:phone":"+1 770 943 1339",
    "sg:postcode":"30127",
    "sg:province":"GA",
    "sg:tags":[
        "maintenance"
    ],
    "wof:name":"Strippers Janitorial Service",
    "wof:placetype":"venue"
},
  "geometry": {"coordinates":[-84.65385000000001,33.873522],"type":"Point"}
}