{
  "type": "Feature",
  "properties": {
    "addr:full":"2138 US Hwy 319 S Moultrie GA 31768",
    "addr:housenumber":"2138",
    "addr:postcode":"31768",
    "addr:street":"Us Hwy 319 S",
    "iso:country":"US",
    "sg:address":"2138 US Hwy 319 S",
    "sg:city":"Moultrie",
    "sg:classifiers":[
        {
            "category":"Organizations",
            "subcategory":"Religious Organization",
            "type":"Services"
        }
    ],
    "sg:phone":"+1 229 890 1156",
    "sg:postcode":"31768",
    "sg:province":"GA",
    "sg:tags":[
        "church"
    ],
    "wof:name":"Temple Baptist Church",
    "wof:placetype":"venue"
},
  "geometry": {"coordinates":[-83.823978,31.070775],"type":"Point"}
}