{
  "type": "Feature",
  "properties": {
    "iso:country":"US",
    "sg:address":"131 Park Ln",
    "sg:city":"Thomaston",
    "sg:classifiers":[
        {
            "category":"Personal",
            "subcategory":"Beauty Salon",
            "type":"Services"
        }
    ],
    "sg:phone":"+1 706 647 8151",
    "sg:postcode":"30286",
    "sg:province":"GA",
    "sg:tags":[
        "shop"
    ],
    "wof:name":"Cut N Up",
    "wof:placetype":"venue"
},
  "geometry": {"coordinates":[-84.315549,32.898389],"type":"Point"}
}