{
  "type": "Feature",
  "properties": {
    "addr:full":"1200 Abernathy Road N.E. Building 600, Suite 175 Atlanta GA 30328",
    "addr:housenumber":"1200;600 suite 175",
    "addr:postcode":"30328",
    "addr:street":"Abernathy Road",
    "iso:country":"US",
    "sg:address":"1200 Abernathy Road N.E. Building 600, Suite 175",
    "sg:city":"Atlanta",
    "sg:classifiers":[
        {
            "category":"Professional",
            "subcategory":"Computer Services",
            "type":"Services"
        }
    ],
    "sg:phone":"+1 770 390 8360",
    "sg:postcode":"30328",
    "sg:province":"GA",
    "sg:tags":[
        "rpo",
        "staffing-and-recruiting",
        "hr",
        "hr-consulting"
    ],
    "sg:website":"http://www.kinetixhr.com",
    "wof:name":"Kinetix",
    "wof:placetype":"venue"
},
  "geometry": {"coordinates":[-84.34782199999999,33.938016],"type":"Point"}
}