{
  "type": "Feature",
  "properties": {
    "iso:country":"US",
    "sg:address":"2747 Davis Rd Bldg 1",
    "sg:city":"Tifton",
    "sg:classifiers":[
        {
            "category":"Professional",
            "subcategory":"Management & Consulting",
            "type":"Services"
        },
        {
            "category":"Professional",
            "subcategory":"Research",
            "type":"Services"
        },
        {
            "category":"Education",
            "subcategory":"Library",
            "type":"Public Place"
        }
    ],
    "sg:phone":"+1 229 387 2330",
    "sg:postcode":"31793",
    "sg:province":"GA",
    "sg:tags":[
        "consultant",
        "agricultural"
    ],
    "sg:website":"http://www.ars-grin.gov",
    "wof:name":"Agricultural Research Service",
    "wof:placetype":"venue"
},
  "geometry": {"coordinates":[-83.542236,31.480795],"type":"Point"}
}