{
  "type": "Feature",
  "properties": {
    "addr:full":"311 Linda Dr Milledgeville GA 31061",
    "addr:housenumber":"311",
    "addr:postcode":"31061",
    "addr:street":"Linda Dr",
    "iso:country":"US",
    "sg:address":"311 Linda Dr",
    "sg:city":"Milledgeville",
    "sg:classifiers":[
        {
            "category":"Government",
            "subcategory":"Police Station",
            "type":"Public Place"
        }
    ],
    "sg:phone":"+1 478 445 4891",
    "sg:postcode":"31061",
    "sg:province":"GA",
    "sg:tags":[
        "sheriff"
    ],
    "wof:name":"Baldwin County Sheriff",
    "wof:placetype":"venue"
},
  "geometry": {"coordinates":[-83.228983,33.101018],"type":"Point"}
}