{
  "type": "Feature",
  "properties": {
    "addr:full":"6145 Hickory Flat Hwy Canton GA 30115",
    "addr:housenumber":"6145",
    "addr:postcode":"30115",
    "addr:street":"Hickory Flat Hwy",
    "iso:country":"US",
    "sg:address":"6145 Hickory Flat Hwy",
    "sg:city":"Canton",
    "sg:classifiers":[
        {
            "category":"Banks & Credit Unions",
            "subcategory":"Bank",
            "type":"Services"
        }
    ],
    "sg:phone":"+1 678 493 8690",
    "sg:postcode":"30115",
    "sg:province":"GA",
    "wof:name":"First Union",
    "wof:placetype":"venue"
},
  "geometry": {"coordinates":[-84.42004300000001,34.176691],"type":"Point"}
}