{
  "type": "Feature",
  "properties": {
    "iso:country":"US",
    "sg:address":"111 N Crawford St",
    "sg:city":"Thomasville",
    "sg:classifiers":[
        {
            "category":"Shopping",
            "subcategory":"Clothing, Apparel, & Fashions",
            "type":"Retail Goods"
        }
    ],
    "sg:phone":"+1 229 228 5626",
    "sg:postcode":"31792",
    "sg:province":"GA",
    "wof:name":"Ambers Fashions & Tanning",
    "wof:placetype":"venue"
},
  "geometry": {"coordinates":[-83.97992499999999,30.839332],"type":"Point"}
}