{
  "type": "Feature",
  "properties": {
    "iso:country":"US",
    "sg:address":"702 Johnson St",
    "sg:city":"Valdosta",
    "sg:classifiers":[
        {
            "category":"Organizations",
            "subcategory":"Religious Organization",
            "type":"Services"
        }
    ],
    "sg:phone":"+1 229 245 0091",
    "sg:postcode":"31601",
    "sg:province":"GA",
    "sg:tags":[
        "church"
    ],
    "wof:name":"Bethel CME Church",
    "wof:placetype":"venue"
},
  "geometry": {"coordinates":[-83.28631900000001,30.835995],"type":"Point"}
}