{
  "type": "Feature",
  "properties": {
    "addr:full":"3042 Oak Vista Way Lawrenceville GA 30044",
    "addr:housenumber":"3042",
    "addr:postcode":"30044",
    "addr:street":"Oak Vista Way",
    "iso:country":"US",
    "sg:address":"3042 Oak Vista Way",
    "sg:city":"Lawrenceville",
    "sg:classifiers":[
        {
            "category":"Utilities",
            "subcategory":"Telephone",
            "type":"Services"
        }
    ],
    "sg:phone":"+1 678 380 6784",
    "sg:postcode":"30044",
    "sg:province":"GA",
    "sg:tags":[
        "communications"
    ],
    "wof:name":"Corporate Solution",
    "wof:placetype":"venue"
},
  "geometry": {"coordinates":[-84.068369,33.910016],"type":"Point"}
}