{
  "type": "Feature",
  "properties": {
    "iso:country":"US",
    "sg:address":"1650 Cheshire Bridge Rd",
    "sg:city":"Atlanta",
    "sg:classifiers":[
        {
            "category":"Building & Trades",
            "subcategory":"Locksmith",
            "type":"Services"
        }
    ],
    "sg:phone":"+1 404 602 5435",
    "sg:postcode":"30324",
    "sg:province":"GA",
    "sg:tags":[
        "key"
    ],
    "wof:name":"Locksmith 24 7",
    "wof:placetype":"venue"
},
  "geometry": {"coordinates":[-84.366045,33.807656],"type":"Point"}
}