{
  "type": "Feature",
  "properties": {
    "addr:full":"11242 Cumming Hwy Canton GA 30115",
    "addr:housenumber":"11242",
    "addr:postcode":"30115",
    "addr:street":"Cumming Hwy",
    "iso:country":"US",
    "sg:address":"11242 Cumming Hwy",
    "sg:city":"Canton",
    "sg:classifiers":[
        {
            "category":"Personal",
            "subcategory":"Beauty Salon",
            "type":"Services"
        }
    ],
    "sg:phone":"+1 770 205 6256",
    "sg:postcode":"30115",
    "sg:province":"GA",
    "sg:tags":[
        "shop"
    ],
    "wof:name":"Justice & Remington Salon",
    "wof:placetype":"venue"
},
  "geometry": {"coordinates":[-84.30718299999999,34.248283],"type":"Point"}
}