{
  "type": "Feature",
  "properties": {
    "addr:full":"101 Davis St Athens GA 30606",
    "addr:housenumber":"101",
    "addr:postcode":"30606",
    "addr:street":"Davis St",
    "iso:country":"US",
    "sg:address":"101 Davis St",
    "sg:city":"Athens",
    "sg:classifiers":[
        {
            "category":"Real Estate",
            "subcategory":"Real Estate Operator",
            "type":"Services"
        }
    ],
    "sg:phone":"+1 706 546 1509",
    "sg:postcode":"30606",
    "sg:province":"GA",
    "sg:tags":[
        "building",
        "apartment"
    ],
    "sg:website":"www.mooseclubcondos.com",
    "wof:name":"Moose Club Condos",
    "wof:placetype":"venue"
},
  "geometry": {"coordinates":[-83.37950499999999,33.924787],"type":"Point"}
}