{
  "type": "Feature",
  "properties": {
    "addr:full":"3 Vandy Ln Savannah GA 31411",
    "addr:housenumber":"3",
    "addr:postcode":"31411",
    "addr:street":"Vandy Ln",
    "iso:country":"US",
    "sg:address":"3 Vandy Ln",
    "sg:city":"Savannah",
    "sg:classifiers":[
        {
            "category":"Professional",
            "type":"Services"
        }
    ],
    "sg:phone":"+1 912 598 7217",
    "sg:postcode":"31411",
    "sg:province":"GA",
    "wof:name":"V & R Ingredients Inc",
    "wof:placetype":"venue"
},
  "geometry": {"coordinates":[-81.057052,31.897197],"type":"Point"}
}