{
  "type": "Feature",
  "properties": {
    "iso:country":"US",
    "sg:address":"420 Houston Pl SW",
    "sg:city":"Marietta",
    "sg:classifiers":[
        {
            "category":"Building & Trades",
            "subcategory":"Landscaping Services",
            "type":"Services"
        }
    ],
    "sg:phone":"+1 404 759 7393",
    "sg:postcode":"30008",
    "sg:province":"GA",
    "sg:tags":[
        "landscape"
    ],
    "wof:name":"Flores Landscape",
    "wof:placetype":"venue"
},
  "geometry": {"coordinates":[-84.56505199999999,33.927304],"type":"Point"}
}