{
  "type": "Feature",
  "properties": {
    "addr:full":"1328 Windsor Pkwy NE Atlanta GA 30319",
    "addr:housenumber":"1328",
    "addr:postcode":"30319",
    "addr:street":"Windsor Pkwy Ne",
    "iso:country":"US",
    "sg:address":"1328 Windsor Pkwy NE",
    "sg:city":"Atlanta",
    "sg:classifiers":[
        {
            "category":"Building & Trades",
            "subcategory":"Locksmith",
            "type":"Services"
        }
    ],
    "sg:phone":"+1 800 542 4759",
    "sg:postcode":"30319",
    "sg:province":"GA",
    "sg:tags":[
        "key"
    ],
    "wof:name":"24 Hour 1 Emergency Locksmith",
    "wof:placetype":"venue"
},
  "geometry": {"coordinates":[-84.342626,33.880934],"type":"Point"}
}