{
  "type": "Feature",
  "properties": {
    "addr:full":"1040 Wordsworth Dr Roswell GA 30075",
    "addr:housenumber":"1040",
    "addr:postcode":"30075",
    "addr:street":"Wordsworth Dr",
    "iso:country":"US",
    "sg:address":"1040 Wordsworth Dr",
    "sg:city":"Roswell",
    "sg:classifiers":[
        {
            "category":"Health Services",
            "subcategory":"Health Practitioner",
            "type":"Services"
        }
    ],
    "sg:phone":"+1 770 642 8730",
    "sg:postcode":"30075",
    "sg:province":"GA",
    "sg:tags":[
        "nurse",
        "registry"
    ],
    "wof:name":"Pacific Link Healthcare",
    "wof:placetype":"venue"
},
  "geometry": {"coordinates":[-84.379991,34.038286],"type":"Point"}
}