{
  "type": "Feature",
  "properties": {
    "addr:full":"6935 York Pl Cumming GA 30040",
    "addr:housenumber":"6935",
    "addr:postcode":"30040",
    "addr:street":"York Pl",
    "iso:country":"US",
    "sg:address":"6935 York Pl",
    "sg:city":"Cumming",
    "sg:classifiers":[
        {
            "category":"Real Estate",
            "subcategory":"Architect",
            "type":"Services"
        }
    ],
    "sg:phone":"+1 770 888 0045",
    "sg:postcode":"30040",
    "sg:province":"GA",
    "sg:tags":[
        "architectural"
    ],
    "wof:name":"Matthew Butler Architecture PC",
    "wof:placetype":"venue"
},
  "geometry": {"coordinates":[-84.207658,34.174447],"type":"Point"}
}