{
  "type": "Feature",
  "properties": {
    "addr:full":"444 Manget St SE Ste 700 Marietta GA 30060",
    "addr:housenumber":"444",
    "addr:postcode":"30060",
    "addr:street":"Manget St Se Ste 700",
    "iso:country":"US",
    "sg:address":"444 Manget St SE Ste 700",
    "sg:city":"Marietta",
    "sg:classifiers":[
        {
            "category":"Real Estate",
            "subcategory":"Real Estate Services",
            "type":"Services"
        }
    ],
    "sg:phone":"+1 770 590 9995",
    "sg:postcode":"30060",
    "sg:province":"GA",
    "sg:tags":[
        "management",
        "property"
    ],
    "wof:name":"Institute of Real Estate Management",
    "wof:placetype":"venue"
},
  "geometry": {"coordinates":[-84.53980300000001,33.944],"type":"Point"}
}