{
  "type": "Feature",
  "properties": {
    "addr:full":"1098 Herrington Rd NW Lawrenceville GA 30044",
    "addr:housenumber":"1098",
    "addr:postcode":"30044",
    "addr:street":"Herrington Rd Nw",
    "iso:country":"US",
    "sg:address":"1098 Herrington Rd NW",
    "sg:city":"Lawrenceville",
    "sg:classifiers":[
        {
            "category":"Banks & Credit Unions",
            "subcategory":"Financial Services",
            "type":"Services"
        },
        {
            "category":"Professional",
            "subcategory":"Accounting & Tax Preparation",
            "type":"Services"
        }
    ],
    "sg:phone":"+1 770 236 5015",
    "sg:postcode":"30044",
    "sg:province":"GA",
    "sg:tags":[
        "investor",
        "return",
        "filing"
    ],
    "wof:name":"G Burg Investment Group Inc",
    "wof:placetype":"venue"
},
  "geometry": {"coordinates":[-84.08247900000001,33.947794],"type":"Point"}
}