{
  "type": "Feature",
  "properties": {
    "addr:full":"2099 Whippoorwill Trl Hartwell GA 30643",
    "addr:housenumber":"2099",
    "addr:postcode":"30643",
    "addr:street":"Whippoorwill Trl",
    "iso:country":"US",
    "sg:address":"2099 Whippoorwill Trl",
    "sg:city":"Hartwell",
    "sg:classifiers":[
        {
            "category":"Professional",
            "type":"Services"
        }
    ],
    "sg:phone":"+1 706 245 0000",
    "sg:postcode":"30643",
    "sg:province":"GA",
    "sg:tags":[
        "establishment"
    ],
    "wof:name":"Fantasy Trux Inc",
    "wof:placetype":"venue"
},
  "geometry": {"coordinates":[-82.86715599999999,34.304724],"type":"Point"}
}