{
  "type": "Feature",
  "properties": {
    "addr:full":"2195 Eastview Pkwy Conyers GA 30013",
    "addr:housenumber":"2195",
    "addr:postcode":"30013",
    "addr:street":"Eastview Pkwy",
    "iso:country":"US",
    "sg:address":"2195 Eastview Pkwy",
    "sg:city":"Conyers",
    "sg:classifiers":[
        {
            "category":"Professional",
            "subcategory":"Computer Services",
            "type":"Services"
        }
    ],
    "sg:phone":"+1 770 602 1858",
    "sg:postcode":"30013",
    "sg:province":"GA",
    "sg:tags":[
        "developer",
        "repair",
        "software",
        "equipment-service",
        "publisher"
    ],
    "sg:website":"http://www.lexicontech.com",
    "wof:name":"Lexicon Technologies",
    "wof:placetype":"venue"
},
  "geometry": {"coordinates":[-83.97637,33.667025],"type":"Point"}
}