{
  "type": "Feature",
  "properties": {
    "addr:full":"3190 N Henry Blvd Stockbridge GA 30281",
    "addr:housenumber":"3190",
    "addr:postcode":"30281",
    "addr:street":"N Henry Blvd",
    "iso:country":"US",
    "sg:address":"3190 N Henry Blvd",
    "sg:city":"Stockbridge",
    "sg:classifiers":[
        {
            "category":"Building & Trades",
            "subcategory":"Plumbing",
            "type":"Services"
        }
    ],
    "sg:phone":"+1 770 474 8788",
    "sg:postcode":"30281",
    "sg:province":"GA",
    "sg:tags":[
        "system",
        "heating",
        "contractor",
        "air conditioning",
        "conditioning/hvac"
    ],
    "sg:website":"www.mvheatandair.com",
    "wof:name":"Mike Vining Heating & Air Conditioning",
    "wof:placetype":"venue"
},
  "geometry": {"coordinates":[-84.195702,33.525101],"type":"Point"}
}