{
  "type": "Feature",
  "properties": {
    "addr:full":"1315 Tippettville Rd Vienna GA 31092",
    "addr:housenumber":"1315",
    "addr:postcode":"31092",
    "addr:street":"Tippettville Rd",
    "iso:country":"US",
    "sg:address":"1315 Tippettville Rd",
    "sg:city":"Vienna",
    "sg:classifiers":[
        {
            "category":"Wholesale",
            "subcategory":"Farm Supplies",
            "type":"Manufacturing & Wholesale Goods"
        }
    ],
    "sg:phone":"+1 229 268 9041",
    "sg:postcode":"31092",
    "sg:province":"GA",
    "sg:tags":[
        "ca",
        "pecan",
        "candy",
        "mfg"
    ],
    "wof:name":"Ellis Farms",
    "wof:placetype":"venue"
},
  "geometry": {"coordinates":[-83.749455,32.094605],"type":"Point"}
}