{
  "type": "Feature",
  "properties": {
    "iso:country":"US",
    "sg:address":"525 Industrial Way",
    "sg:city":"Cumming",
    "sg:classifiers":[
        {
            "category":"Building & Trades",
            "subcategory":"Electrical",
            "type":"Services"
        }
    ],
    "sg:phone":"+1 770 889 3944",
    "sg:postcode":"30040",
    "sg:province":"GA",
    "sg:tags":[
        "electrical",
        "wiring"
    ],
    "wof:name":"Electric Maintainance Systems",
    "wof:placetype":"venue"
},
  "geometry": {"coordinates":[-84.147842,34.202429],"type":"Point"}
}