{
  "type": "Feature",
  "properties": {
    "iso:country":"US",
    "sg:address":"965 Highway 138 SW",
    "sg:city":"Riverdale",
    "sg:classifiers":[
        {
            "category":"Arena",
            "subcategory":"Auto Racetrack",
            "type":"Entertainment"
        }
    ],
    "sg:phone":"+1 770 997 4246",
    "sg:postcode":"30296",
    "sg:province":"GA",
    "sg:tags":[
        "racing"
    ],
    "wof:name":"Benefield Racing",
    "wof:placetype":"venue"
},
  "geometry": {"coordinates":[-84.421031,33.55031],"type":"Point"}
}