{
  "type": "Feature",
  "properties": {
    "iso:country":"US",
    "sg:address":"1877 Lake Ridge Ter",
    "sg:city":"Lawrenceville",
    "sg:classifiers":[
        {
            "category":"Manufacturing",
            "subcategory":"Leather Goods",
            "type":"Manufacturing & Wholesale Goods"
        }
    ],
    "sg:phone":"+1 678 481 7110",
    "sg:postcode":"30043",
    "sg:province":"GA",
    "sg:tags":[
        "mfg"
    ],
    "wof:name":"Leather Plus",
    "wof:placetype":"venue"
},
  "geometry": {"coordinates":[-84.003024,34.01319],"type":"Point"}
}