{
  "type": "Feature",
  "properties": {
    "addr:full":"5916 Old Pendergrass Rd Jefferson GA 30549",
    "addr:housenumber":"5916",
    "addr:postcode":"30549",
    "addr:street":"Old Pendergrass Rd",
    "iso:country":"US",
    "sg:address":"5916 Old Pendergrass Rd",
    "sg:city":"Jefferson",
    "sg:classifiers":[
        {
            "category":"Building & Trades",
            "subcategory":"Plumbing",
            "type":"Services"
        }
    ],
    "sg:phone":"+1 706 654 9017",
    "sg:postcode":"30549",
    "sg:province":"GA",
    "sg:tags":[
        "contractor"
    ],
    "wof:name":"Shepherd Services LLC",
    "wof:placetype":"venue"
},
  "geometry": {"coordinates":[-83.674386,34.128252],"type":"Point"}
}