{
  "type": "Feature",
  "properties": {
    "addr:full":"570 Golden Ct Stockbridge GA 30281",
    "addr:housenumber":"570",
    "addr:postcode":"30281",
    "addr:street":"Golden Ct",
    "iso:country":"US",
    "sg:address":"570 Golden Ct",
    "sg:city":"Stockbridge",
    "sg:classifiers":[
        {
            "category":"Arts & Performance",
            "subcategory":"Theater",
            "type":"Entertainment"
        }
    ],
    "sg:phone":"+1 770 507 1177",
    "sg:postcode":"30281",
    "sg:province":"GA",
    "sg:tags":[
        "theatrical"
    ],
    "wof:name":"Stars of Heaven",
    "wof:placetype":"venue"
},
  "geometry": {"coordinates":[-84.16129100000001,33.56999],"type":"Point"}
}