{
  "type": "Feature",
  "properties": {
    "addr:full":"2092 Metropolitan Pkwy SW Atlanta GA 30315",
    "addr:housenumber":"2092",
    "addr:postcode":"30315",
    "addr:street":"Metropolitan Pkwy Sw",
    "iso:country":"US",
    "sg:address":"2092 Metropolitan Pkwy SW",
    "sg:city":"Atlanta",
    "sg:classifiers":[
        {
            "category":"Home & Garden",
            "subcategory":"Furniture",
            "type":"Retail Goods"
        }
    ],
    "sg:phone":"+1 404 768 6002",
    "sg:postcode":"30315",
    "sg:province":"GA",
    "sg:tags":[
        "bedroom",
        "set",
        "bed",
        "mattress"
    ],
    "wof:name":"Metro Bedding",
    "wof:placetype":"venue"
},
  "geometry": {"coordinates":[-84.40810999999999,33.697409],"type":"Point"}
}