{
  "type": "Feature",
  "properties": {
    "iso:country":"US",
    "sg:address":"504 N Parrish Ave",
    "sg:city":"Adel",
    "sg:classifiers":[
        {
            "category":"Wholesale",
            "subcategory":"Non-durable Goods",
            "type":"Manufacturing & Wholesale Goods"
        }
    ],
    "sg:phone":"+1 229 896 8743",
    "sg:postcode":"31620",
    "sg:province":"GA",
    "sg:tags":[
        "specialist",
        "whole",
        "advertising"
    ],
    "wof:name":"Cabco Advertising & Printing",
    "wof:placetype":"venue"
},
  "geometry": {"coordinates":[-83.42419599999999,31.142375],"type":"Point"}
}