{
  "type": "Feature",
  "properties": {
    "iso:country":"US",
    "sg:address":"1994 Thigpen Trl",
    "sg:city":"Hartsfield",
    "sg:classifiers":[
        {
            "category":"Wholesale",
            "subcategory":"Machinery & Supplies",
            "type":"Manufacturing & Wholesale Goods"
        }
    ],
    "sg:phone":"+1 229 941 5031",
    "sg:postcode":"31756",
    "sg:province":"GA",
    "sg:tags":[
        "equipment",
        "industrial"
    ],
    "wof:name":"Hartsfield Equipment",
    "wof:placetype":"venue"
},
  "geometry": {"coordinates":[-83.95604899999999,31.17049],"type":"Point"}
}