{
  "type": "Feature",
  "properties": {
    "iso:country":"US",
    "sg:address":"103 Ennis St",
    "sg:city":"Sylvania",
    "sg:classifiers":[
        {
            "category":"Organizations",
            "subcategory":"Religious Organization",
            "type":"Services"
        }
    ],
    "sg:phone":"+1 912 564 5650",
    "sg:postcode":"30467",
    "sg:province":"GA",
    "sg:tags":[
        "church"
    ],
    "wof:name":"Shechinah Worship Ctr",
    "wof:placetype":"venue"
},
  "geometry": {"coordinates":[-81.638074,32.74964],"type":"Point"}
}