{
  "type": "Feature",
  "properties": {
    "addr:full":"3321 Northside Dr Macon GA 31210",
    "addr:housenumber":"3321",
    "addr:postcode":"31210",
    "addr:street":"Northside Dr",
    "iso:country":"US",
    "sg:address":"3321 Northside Dr",
    "sg:city":"Macon",
    "sg:classifiers":[
        {
            "category":"Professional",
            "subcategory":"Employment Agencies",
            "type":"Services"
        }
    ],
    "sg:phone":"+1 478 405 9301",
    "sg:postcode":"31210",
    "sg:province":"GA",
    "sg:tags":[
        "opportunity",
        "contractor"
    ],
    "sg:website":"http://www.kellyservices.com",
    "wof:name":"Kelly Services",
    "wof:placetype":"venue"
},
  "geometry": {"coordinates":[-83.67885,32.891225],"type":"Point"}
}