{
  "type": "Feature",
  "properties": {
    "iso:country":"US",
    "sg:address":"831 1st Ave NE",
    "sg:city":"Cairo",
    "sg:classifiers":[
        {
            "category":"Shopping",
            "type":"Retail Goods"
        }
    ],
    "sg:phone":"+1 229 377 1585",
    "sg:postcode":"39828",
    "sg:province":"GA",
    "sg:tags":[
        "agricultural",
        "machinery",
        "tractor"
    ],
    "wof:name":"South Georgia Tractor Inc",
    "wof:placetype":"venue"
},
  "geometry": {"coordinates":[-84.196822,30.877687],"type":"Point"}
}