{
  "type": "Feature",
  "properties": {
    "addr:full":"966 Killian Hill Rd SW # A Lilburn GA 30047",
    "addr:housenumber":"966",
    "addr:postcode":"30047",
    "addr:street":"Killian Hill Rd Sw # A",
    "iso:country":"US",
    "sg:address":"966 Killian Hill Rd SW # A",
    "sg:city":"Lilburn",
    "sg:classifiers":[
        {
            "category":"Health Services",
            "subcategory":"Health Practitioner",
            "type":"Services"
        }
    ],
    "sg:phone":"+1 770 923 4815",
    "sg:postcode":"30047",
    "sg:province":"GA",
    "sg:tags":[
        "therapy",
        "physical"
    ],
    "sg:website":"www.myphysio.com",
    "wof:name":"Physiotherapy Associates",
    "wof:placetype":"venue"
},
  "geometry": {"coordinates":[-84.095001,33.868599],"type":"Point"}
}