{
  "type": "Feature",
  "properties": {
    "iso:country":"US",
    "sg:address":"124 Ave D",
    "sg:city":"Lindale",
    "sg:classifiers":[
        {
            "category":"Shopping",
            "type":"Retail Goods"
        }
    ],
    "sg:phone":"+1 706 235 9298",
    "sg:postcode":"30147",
    "sg:province":"GA",
    "sg:tags":[
        "plastic"
    ],
    "wof:name":"Mathis Plastic Sales",
    "wof:placetype":"venue"
},
  "geometry": {"coordinates":[-85.175433,34.192817],"type":"Point"}
}