{
  "type": "Feature",
  "properties": {
    "addr:full":"131 Morris St Fort Valley GA 31030",
    "addr:housenumber":"131",
    "addr:postcode":"31030",
    "addr:street":"Morris St",
    "iso:country":"US",
    "sg:address":"131 Morris St",
    "sg:city":"Fort Valley",
    "sg:classifiers":[
        {
            "category":"Professional",
            "type":"Services"
        }
    ],
    "sg:phone":"+1 478 825 3227",
    "sg:postcode":"31030",
    "sg:province":"GA",
    "wof:name":"Thomas B Williams",
    "wof:placetype":"venue"
},
  "geometry": {"coordinates":[-83.88029299999999,32.544243],"type":"Point"}
}