{
  "type": "Feature",
  "properties": {
    "addr:full":"4660 N Royal Atlanta Dr Tucker GA 30084",
    "addr:housenumber":"4660",
    "addr:postcode":"30084",
    "addr:street":"N Royal Atlanta Dr",
    "iso:country":"US",
    "sg:address":"4660 N Royal Atlanta Dr",
    "sg:city":"Tucker",
    "sg:classifiers":[
        {
            "category":"Freight",
            "type":"Transportation"
        }
    ],
    "sg:phone":"+1 770 270 1234",
    "sg:postcode":"30084",
    "sg:province":"GA",
    "sg:tags":[
        "trucking"
    ],
    "wof:name":"American Transportation Systs",
    "wof:placetype":"venue"
},
  "geometry": {"coordinates":[-84.196877,33.85969],"type":"Point"}
}