{
  "type": "Feature",
  "properties": {
    "addr:full":"3821 Highpointe Dr Hephzibah GA 30815",
    "addr:housenumber":"3821",
    "addr:postcode":"30815",
    "addr:street":"Highpointe Dr",
    "iso:country":"US",
    "sg:address":"3821 Highpointe Dr",
    "sg:city":"Hephzibah",
    "sg:classifiers":[
        {
            "category":"Building & Trades",
            "subcategory":"Construction",
            "type":"Services"
        }
    ],
    "sg:phone":"+1 706 798 0920",
    "sg:postcode":"30815",
    "sg:province":"GA",
    "sg:tags":[
        "hanging",
        "contractor"
    ],
    "wof:name":"Angelas Decorating Access",
    "wof:placetype":"venue"
},
  "geometry": {"coordinates":[-82.091179,33.380617],"type":"Point"}
}