{
  "type": "Feature",
  "properties": {
    "iso:country":"US",
    "sg:address":"165 Water Oak Dr",
    "sg:city":"Albany",
    "sg:classifiers":[
        {
            "category":"Retail",
            "subcategory":"Repair Shop",
            "type":"Services"
        }
    ],
    "sg:phone":"+1 229 435 4780",
    "sg:postcode":"31763",
    "sg:province":"GA",
    "sg:tags":[
        "lock",
        "locksmith"
    ],
    "wof:name":"Unlock Specialist",
    "wof:placetype":"venue"
},
  "geometry": {"coordinates":[-84.107169,31.631725],"type":"Point"}
}