{
  "type": "Feature",
  "properties": {
    "iso:country":"US",
    "sg:address":"258 Bobby Jones Expy",
    "sg:city":"Augusta",
    "sg:classifiers":[
        {
            "category":"Shopping",
            "subcategory":"Optical Goods",
            "type":"Retail Goods"
        }
    ],
    "sg:phone":"+1 706 868 7000",
    "sg:postcode":"30907",
    "sg:province":"GA",
    "wof:name":"Eye Glass World",
    "wof:placetype":"venue"
},
  "geometry": {"coordinates":[-82.094522,33.510015],"type":"Point"}
}