{
  "type": "Feature",
  "properties": {
    "addr:full":"3995 Brushy Creek Way Suwanee GA 30024",
    "addr:housenumber":"3995",
    "addr:postcode":"30024",
    "addr:street":"Brushy Creek Way",
    "iso:country":"US",
    "sg:address":"3995 Brushy Creek Way",
    "sg:city":"Suwanee",
    "sg:classifiers":[
        {
            "category":"Professional",
            "subcategory":"Management & Consulting",
            "type":"Services"
        }
    ],
    "sg:phone":"+1 770 831 4743",
    "sg:postcode":"30024",
    "sg:province":"GA",
    "sg:tags":[
        "business"
    ],
    "wof:name":"Performance Nutrition",
    "wof:placetype":"venue"
},
  "geometry": {"coordinates":[-84.082229,34.051671],"type":"Point"}
}