{
  "type": "Feature",
  "properties": {
    "addr:full":"1816 Magnolia Ave Dalton GA 30720",
    "addr:housenumber":"1816",
    "addr:postcode":"30720",
    "addr:street":"Magnolia Ave",
    "iso:country":"US",
    "sg:address":"1816 Magnolia Ave",
    "sg:city":"Dalton",
    "sg:classifiers":[
        {
            "category":"Wholesale",
            "subcategory":"Machinery & Supplies",
            "type":"Manufacturing & Wholesale Goods"
        },
        {
            "category":"Home & Garden",
            "subcategory":"Household Appliances",
            "type":"Retail Goods"
        }
    ],
    "sg:phone":"+1 706 226 9230",
    "sg:postcode":"30720",
    "sg:province":"GA",
    "sg:tags":[
        "chemical",
        "pump",
        "mfg"
    ],
    "wof:name":"Environmental Technology & Eqp",
    "wof:placetype":"venue"
},
  "geometry": {"coordinates":[-84.98256600000001,34.742725],"type":"Point"}
}