{
  "type": "Feature",
  "properties": {
    "iso:country":"US",
    "sg:address":"340 Spalding Lake Ct",
    "sg:city":"Atlanta",
    "sg:classifiers":[
        {
            "category":"Manufacturing",
            "subcategory":"Wood Products",
            "type":"Manufacturing & Wholesale Goods"
        }
    ],
    "sg:phone":"+1 770 394 1002",
    "sg:postcode":"30350",
    "sg:province":"GA",
    "sg:tags":[
        "preserving"
    ],
    "wof:name":"Sales Office",
    "wof:placetype":"venue"
},
  "geometry": {"coordinates":[-84.266777,33.965767],"type":"Point"}
}