{
  "type": "Feature",
  "properties": {
    "addr:full":"3471 Clifton Farm Dr Decatur GA 30034",
    "addr:housenumber":"3471",
    "addr:postcode":"30034",
    "addr:street":"Clifton Farm Dr",
    "iso:country":"US",
    "sg:address":"3471 Clifton Farm Dr",
    "sg:city":"Decatur",
    "sg:classifiers":[
        {
            "category":"Building & Trades",
            "subcategory":"Cleaning & Sanitation",
            "type":"Services"
        }
    ],
    "sg:phone":"+1 404 241 2437",
    "sg:postcode":"30034",
    "sg:province":"GA",
    "sg:tags":[
        "maintenance"
    ],
    "wof:name":"Par 5 Commercial Cleaning Svcs",
    "wof:placetype":"venue"
},
  "geometry": {"coordinates":[-84.283281,33.690964],"type":"Point"}
}