{
  "type": "Feature",
  "properties": {
    "iso:country":"US",
    "sg:address":"3448 Mountain Dr",
    "sg:city":"Decatur",
    "sg:classifiers":[
        {
            "category":"Social Services",
            "type":"Services"
        }
    ],
    "sg:phone":"+1 404 294 5171",
    "sg:postcode":"30032",
    "sg:province":"GA",
    "sg:tags":[
        "care",
        "center",
        "day"
    ],
    "wof:name":"Remkiks Adult Daycare",
    "wof:placetype":"venue"
},
  "geometry": {"coordinates":[-84.24806100000001,33.775424],"type":"Point"}
}