{
  "type": "Feature",
  "properties": {
    "addr:full":"1856 Columbia Dr Decatur GA 30032",
    "addr:housenumber":"1856",
    "addr:postcode":"30032",
    "addr:street":"Columbia Dr",
    "iso:country":"US",
    "sg:address":"1856 Columbia Dr",
    "sg:city":"Decatur",
    "sg:classifiers":[
        {
            "category":"Autos & Motor Vehicles",
            "subcategory":"Auto Supplies",
            "type":"Retail Goods"
        }
    ],
    "sg:phone":"+1 404 284 4640",
    "sg:postcode":"30032",
    "sg:province":"GA",
    "sg:tags":[
        "equipment",
        "parts",
        "electrical",
        "automobile"
    ],
    "wof:name":"Advance Auto Parts Inc",
    "wof:placetype":"venue"
},
  "geometry": {"coordinates":[-84.25199000000001,33.737933],"type":"Point"}
}