{
  "type": "Feature",
  "properties": {
    "addr:full":"520 S Main St Ste C Alpharetta GA 30009",
    "addr:housenumber":"520",
    "addr:postcode":"30009",
    "addr:street":"S Main St Ste C",
    "iso:country":"US",
    "sg:address":"520 S Main St Ste C",
    "sg:city":"Alpharetta",
    "sg:classifiers":[
        {
            "category":"Personal",
            "subcategory":"Beauty Salon",
            "type":"Services"
        }
    ],
    "sg:phone":"+1 770 667 9231",
    "sg:postcode":"30009",
    "sg:province":"GA",
    "sg:tags":[
        "hair"
    ],
    "sg:website":"www.lawrenceyates.com",
    "wof:name":"LNY Hair Salon And Wig Boutique",
    "wof:placetype":"venue"
},
  "geometry": {"coordinates":[-84.305977,34.06619],"type":"Point"}
}