{
  "type": "Feature",
  "properties": {
    "addr:full":"35 Sagebrush Trl Covington GA 30014",
    "addr:housenumber":"35",
    "addr:postcode":"30014",
    "addr:street":"Sagebrush Trl",
    "iso:country":"US",
    "sg:address":"35 Sagebrush Trl",
    "sg:city":"Covington",
    "sg:classifiers":[
        {
            "category":"Professional",
            "type":"Services"
        }
    ],
    "sg:phone":"+1 678 625 2902",
    "sg:postcode":"30014",
    "sg:province":"GA",
    "sg:tags":[
        "writer"
    ],
    "wof:name":"Talking Drumz",
    "wof:placetype":"venue"
},
  "geometry": {"coordinates":[-83.830427,33.564495],"type":"Point"}
}