{
  "type": "Feature",
  "properties": {
    "iso:country":"US",
    "sg:address":"650 E Duffy St",
    "sg:city":"Savannah",
    "sg:classifiers":[
        {
            "category":"Real Estate",
            "subcategory":"Real Estate Operator",
            "type":"Services"
        }
    ],
    "sg:phone":"+1 912 238 9298",
    "sg:postcode":"31401",
    "sg:province":"GA",
    "sg:tags":[
        "apartment"
    ],
    "wof:name":"Duffy St Sro",
    "wof:placetype":"venue"
},
  "geometry": {"coordinates":[-81.087619,32.061525],"type":"Point"}
}