{
  "type": "Feature",
  "properties": {
    "addr:full":"1223 Sherwood Park Dr NE Gainesville GA 30501",
    "addr:housenumber":"1223",
    "addr:postcode":"30501",
    "addr:street":"Sherwood Park Dr Ne;Ga",
    "iso:country":"US",
    "sg:address":"1223 Sherwood Park Dr NE",
    "sg:city":"Gainesville",
    "sg:classifiers":[
        {
            "category":"Health Services",
            "subcategory":"Doctor",
            "type":"Services"
        }
    ],
    "sg:phone":"+1 770 536 2562",
    "sg:postcode":"30501",
    "sg:province":"GA",
    "wof:name":"Rick Gadbois DDS PC",
    "wof:placetype":"venue"
},
  "geometry": {"coordinates":[-83.81818,34.306768],"type":"Point"}
}