{
  "type": "Feature",
  "properties": {
    "iso:country":"US",
    "sg:address":"8610 Roswell Rd",
    "sg:city":"Atlanta",
    "sg:classifiers":[
        {
            "category":"Restaurant",
            "type":"Food & Drink"
        }
    ],
    "sg:phone":"+1 770 552 1717",
    "sg:postcode":"30350",
    "sg:province":"GA",
    "sg:tags":[
        "pizza"
    ],
    "wof:name":"Chicago Pizza & Sports Arena",
    "wof:placetype":"venue"
},
  "geometry": {"coordinates":[-84.351799,33.9907],"type":"Point"}
}