{
  "type": "Feature",
  "properties": {
    "addr:full":"59 Executive Park South Atlanta GA 30329",
    "addr:housenumber":"59",
    "addr:postcode":"30329",
    "addr:street":"Executive Park South",
    "iso:country":"US",
    "sg:address":"59 Executive Park South",
    "sg:city":"Atlanta",
    "sg:classifiers":[
        {
            "category":"Community Center",
            "type":"Public Place"
        }
    ],
    "sg:phone":"+1 404 778 7000",
    "sg:postcode":"30329",
    "sg:province":"GA",
    "sg:tags":[
        "medical"
    ],
    "sg:website":"www.emoryhealthcare.org/departme...",
    "wof:name":"Emory Spine Center",
    "wof:placetype":"venue"
},
  "geometry": {"coordinates":[-84.341454,33.828056],"type":"Point"}
}