{
  "type": "Feature",
  "properties": {
    "addr:full":"5405 U S Highway 78 Bremen GA 30110",
    "addr:housenumber":"5405",
    "addr:postcode":"30110",
    "addr:street":"U S Highway 78",
    "iso:country":"US",
    "sg:address":"5405 U S Highway 78",
    "sg:city":"Bremen",
    "sg:classifiers":[
        {
            "category":"Autos & Motor Vehicles",
            "subcategory":"Automobile Sales",
            "type":"Retail Goods"
        },
        {
            "category":"Wholesale",
            "subcategory":"Scrap",
            "type":"Manufacturing & Wholesale Goods"
        },
        {
            "category":"Banks & Credit Unions",
            "subcategory":"Bank",
            "type":"Services"
        },
        {
            "category":"Autos & Motor Vehicles",
            "subcategory":"Auto Supplies",
            "type":"Retail Goods"
        },
        {
            "category":"Retail",
            "subcategory":"Auto Repair",
            "type":"Services"
        }
    ],
    "sg:phone":"+1 770 537 6666",
    "sg:postcode":"30110",
    "sg:province":"GA",
    "sg:tags":[
        "body",
        "junk",
        "painting",
        "diagnostic",
        "second",
        "part",
        "supplies-used",
        "rebuilt",
        "hand",
        "salvage",
        "repairing"
    ],
    "wof:name":"Mr Auto West Ga",
    "wof:placetype":"venue"
},
  "geometry": {"coordinates":[-85.197884,33.707081],"type":"Point"}
}