{
  "type": "Feature",
  "properties": {
    "addr:full":"809 Grindle Bridge Rd Dahlonega GA 30533",
    "addr:housenumber":"809",
    "addr:postcode":"30533",
    "addr:street":"Grindle Bridge Rd",
    "iso:country":"US",
    "sg:address":"809 Grindle Bridge Rd",
    "sg:city":"Dahlonega",
    "sg:classifiers":[
        {
            "category":"Professional",
            "type":"Services"
        },
        {
            "category":"Shopping",
            "subcategory":"Musical Instruments",
            "type":"Retail Goods"
        }
    ],
    "sg:phone":"+1 706 348 8436",
    "sg:postcode":"30533",
    "sg:province":"GA",
    "wof:name":"King's Music",
    "wof:placetype":"venue"
},
  "geometry": {"coordinates":[-83.866815,34.566183],"type":"Point"}
}