{
  "type": "Feature",
  "properties": {
    "iso:country":"US",
    "sg:address":"202 Central High Rd",
    "sg:city":"Carrollton",
    "sg:classifiers":[
        {
            "category":"Organizations",
            "subcategory":"Religious Organization",
            "type":"Services"
        }
    ],
    "sg:phone":"+1 770 834 7047",
    "sg:postcode":"30116",
    "sg:province":"GA",
    "sg:tags":[
        "church"
    ],
    "wof:name":"Central Baptist Church",
    "wof:placetype":"venue"
},
  "geometry": {"coordinates":[-85.067427,33.55364],"type":"Point"}
}