{
  "type": "Feature",
  "properties": {
    "addr:full":"285 Parkway 575 Woodstock GA 30188",
    "addr:housenumber":"285",
    "addr:postcode":"30188",
    "addr:street":"Parkway 575",
    "iso:country":"US",
    "sg:address":"285 Parkway 575",
    "sg:city":"Woodstock",
    "sg:classifiers":[
        {
            "category":"Structure",
            "subcategory":"Office Building",
            "type":"Public Place"
        }
    ],
    "sg:phone":"+1 770 517 2774",
    "sg:postcode":"30188",
    "sg:province":"GA",
    "sg:tags":[
        "desk",
        "rental",
        "space"
    ],
    "wof:name":"Colbert Investments Inc",
    "wof:placetype":"venue"
},
  "geometry": {"coordinates":[-84.53154000000001,34.09108],"type":"Point"}
}