{
  "type": "Feature",
  "properties": {
    "addr:full":"5235 Poplar St Buford GA 30518",
    "addr:housenumber":"5235",
    "addr:postcode":"30518",
    "addr:street":"Poplar St",
    "iso:country":"US",
    "sg:address":"5235 Poplar St",
    "sg:city":"Buford",
    "sg:classifiers":[
        {
            "category":"Manufacturing",
            "subcategory":"Signs",
            "type":"Manufacturing & Wholesale Goods"
        }
    ],
    "sg:phone":"+1 770 614 6613",
    "sg:postcode":"30518",
    "sg:province":"GA",
    "sg:tags":[
        "specialty",
        "mfg"
    ],
    "wof:name":"Atlantic Sign and Graphics",
    "wof:placetype":"venue"
},
  "geometry": {"coordinates":[-84.020664,34.123216],"type":"Point"}
}