{
  "type": "Feature",
  "properties": {
    "addr:full":"79 S Tallahassee St Hazlehurst GA 31539",
    "addr:housenumber":"79",
    "addr:postcode":"31539",
    "addr:street":"S Tallahassee St",
    "iso:country":"US",
    "sg:address":"79 S Tallahassee St",
    "sg:city":"Hazlehurst",
    "sg:classifiers":[
        {
            "category":"Real Estate",
            "subcategory":"Surveying",
            "type":"Services"
        }
    ],
    "sg:phone":"+1 912 375 4645",
    "sg:postcode":"31539",
    "sg:province":"GA",
    "sg:tags":[
        "surveyor",
        "land"
    ],
    "wof:name":"Copeland & Associates",
    "wof:placetype":"venue"
},
  "geometry": {"coordinates":[-82.59513099999999,31.871229],"type":"Point"}
}