{
  "type": "Feature",
  "properties": {
    "iso:country":"US",
    "sg:address":"5962 Zebulon Rd",
    "sg:city":"Macon",
    "sg:classifiers":[
        {
            "category":"Professional",
            "subcategory":"Management & Consulting",
            "type":"Services"
        }
    ],
    "sg:phone":"+1 478 318 1049",
    "sg:postcode":"31210",
    "sg:province":"GA",
    "sg:tags":[
        "marketing",
        "technology"
    ],
    "wof:name":"Sight & Sound Advertising LLC",
    "wof:placetype":"venue"
},
  "geometry": {"coordinates":[-83.75749999999999,32.879758],"type":"Point"}
}