{
  "type": "Feature",
  "properties": {
    "addr:full":"208 Pine Dr Rincon GA 31326",
    "addr:housenumber":"208",
    "addr:postcode":"31326",
    "addr:street":"Pine Dr",
    "iso:country":"US",
    "sg:address":"208 Pine Dr",
    "sg:city":"Rincon",
    "sg:classifiers":[
        {
            "category":"Building & Trades",
            "subcategory":"Construction",
            "type":"Services"
        }
    ],
    "sg:phone":"+1 912 826 6976",
    "sg:postcode":"31326",
    "sg:province":"GA",
    "sg:tags":[
        "house"
    ],
    "wof:name":"Gy Construction",
    "wof:placetype":"venue"
},
  "geometry": {"coordinates":[-81.234554,32.247864],"type":"Point"}
}