{
  "type": "Feature",
  "properties": {
    "addr:full":"1001 Maple St Carrollton GA 30117",
    "addr:housenumber":"1001",
    "addr:postcode":"30117",
    "addr:street":"Maple St",
    "iso:country":"US",
    "sg:address":"1001 Maple St",
    "sg:city":"Carrollton",
    "sg:classifiers":[
        {
            "category":"Shopping",
            "subcategory":"Bicycles & Sporting Goods",
            "type":"Retail Goods"
        }
    ],
    "sg:phone":"+1 770 832 8200",
    "sg:postcode":"30117",
    "sg:province":"GA",
    "sg:tags":[
        "climbing",
        "camping",
        "hiking",
        "supply"
    ],
    "wof:name":"Georgia West Outfitters Inc",
    "wof:placetype":"venue"
},
  "geometry": {"coordinates":[-85.08744799999999,33.573257],"type":"Point"}
}