{
  "type": "Feature",
  "properties": {
    "addr:full":"810 Pine St Trion GA 30753",
    "addr:housenumber":"810",
    "addr:postcode":"30753",
    "addr:street":"Pine St",
    "iso:country":"US",
    "sg:address":"810 Pine St",
    "sg:city":"Trion",
    "sg:classifiers":[
        {
            "category":"Organizations",
            "subcategory":"Religious Organization",
            "type":"Services"
        }
    ],
    "sg:phone":"+1 706 734 2802",
    "sg:postcode":"30753",
    "sg:province":"GA",
    "wof:name":"Trion United Methodist Church",
    "wof:placetype":"venue"
},
  "geometry": {"coordinates":[-85.318236,34.538394],"type":"Point"}
}