{
  "type": "Feature",
  "properties": {
    "iso:country":"US",
    "sg:address":"1919 Metropolitan Pkwy SW",
    "sg:city":"Atlanta",
    "sg:classifiers":[
        {
            "category":"Shopping",
            "subcategory":"Clothing, Apparel, & Fashions",
            "type":"Retail Goods"
        }
    ],
    "sg:phone":"+1 404 762 7320",
    "sg:postcode":"30315",
    "sg:province":"GA",
    "sg:tags":[
        "accessory",
        "clothing",
        "women's"
    ],
    "wof:name":"Hyundai Fashions",
    "wof:placetype":"venue"
},
  "geometry": {"coordinates":[-84.407898,33.703499],"type":"Point"}
}