{
  "type": "Feature",
  "properties": {
    "addr:full":"104 Andrews St Toccoa GA 30577",
    "addr:housenumber":"104",
    "addr:postcode":"30577",
    "addr:street":"Andrews St",
    "iso:country":"US",
    "sg:address":"104 Andrews St",
    "sg:city":"Toccoa",
    "sg:classifiers":[
        {
            "category":"Restaurant",
            "type":"Food & Drink"
        }
    ],
    "sg:phone":"+1 706 282 1230",
    "sg:postcode":"30577",
    "sg:province":"GA",
    "sg:tags":[
        "caterer"
    ],
    "wof:name":"Humble Pie Catering",
    "wof:placetype":"venue"
},
  "geometry": {"coordinates":[-83.31974,34.578846],"type":"Point"}
}