{
  "type": "Feature",
  "properties": {
    "iso:country":"US",
    "sg:address":"2639 Leeshire Ct",
    "sg:city":"Tucker",
    "sg:classifiers":[
        {
            "category":"Banks & Credit Unions",
            "subcategory":"Investment Brokerage",
            "type":"Services"
        }
    ],
    "sg:phone":"+1 770 934 4048",
    "sg:postcode":"30084",
    "sg:province":"GA",
    "wof:name":"Sherman Investment",
    "wof:placetype":"venue"
},
  "geometry": {"coordinates":[-84.182517,33.862633],"type":"Point"}
}