{
  "type": "Feature",
  "properties": {
    "addr:full":"3447 Peach Orchard Rd Augusta GA 30906",
    "addr:housenumber":"3447",
    "addr:postcode":"30906",
    "addr:street":"Peach Orchard Rd",
    "iso:country":"US",
    "sg:address":"3447 Peach Orchard Rd",
    "sg:city":"Augusta",
    "sg:phone":"+1 706 798 1852",
    "sg:postcode":"30906",
    "sg:province":"GA",
    "sg:tags":[
        "gas"
    ],
    "wof:name":"Pro AM Propane",
    "wof:placetype":"venue"
},
  "geometry": {"coordinates":[-82.02659199999999,33.393606],"type":"Point"}
}