{
  "type": "Feature",
  "properties": {
    "iso:country":"US",
    "sg:address":"870 Woodstock Rd",
    "sg:city":"Roswell",
    "sg:classifiers":[
        {
            "category":"Home & Garden",
            "subcategory":"Building Materials",
            "type":"Retail Goods"
        }
    ],
    "sg:phone":"+1 678 461 0155",
    "sg:postcode":"30075",
    "sg:province":"GA",
    "wof:name":"Home Depot",
    "wof:placetype":"venue"
},
  "geometry": {"coordinates":[-84.38358100000001,34.059467],"type":"Point"}
}