{
  "type": "Feature",
  "properties": {
    "iso:country":"US",
    "sg:address":"1435 Holly Springs Rd NE",
    "sg:city":"Marietta",
    "sg:classifiers":[
        {
            "category":"Wholesale",
            "subcategory":"Painting Supplies",
            "type":"Manufacturing & Wholesale Goods"
        },
        {
            "category":"Home & Garden",
            "subcategory":"Building Materials",
            "type":"Retail Goods"
        }
    ],
    "sg:phone":"+1 770 977 8628",
    "sg:postcode":"30062",
    "sg:province":"GA",
    "sg:tags":[
        "wall",
        "wallpaper",
        "coating",
        "wallcoverings"
    ],
    "wof:name":"U S Vinyl",
    "wof:placetype":"venue"
},
  "geometry": {"coordinates":[-84.47756200000001,33.985512],"type":"Point"}
}