{
  "type": "Feature",
  "properties": {
    "iso:country":"US",
    "sg:address":"45 Bennett St NW Ste B",
    "sg:city":"Atlanta",
    "sg:classifiers":[
        {
            "category":"Sports & Exercise",
            "subcategory":"Gym",
            "type":"Entertainment"
        }
    ],
    "sg:phone":"+1 404 704 4822",
    "sg:postcode":"30309",
    "sg:province":"GA",
    "sg:tags":[
        "trainer"
    ],
    "sg:website":"www.crossfitpeachtree.com",
    "wof:name":"CrossFit Peachtree",
    "wof:placetype":"venue"
},
  "geometry": {"coordinates":[-84.39377500000001,33.812014],"type":"Point"}
}