{
  "type": "Feature",
  "properties": {
    "iso:country":"US",
    "sg:address":"6685 Crescent Dr NW",
    "sg:city":"Norcross",
    "sg:classifiers":[
        {
            "category":"Wholesale",
            "subcategory":"Groceries",
            "type":"Manufacturing & Wholesale Goods"
        }
    ],
    "sg:phone":"+1 770 263 4300",
    "sg:postcode":"30071",
    "sg:province":"GA",
    "sg:tags":[
        "packaged",
        "fro",
        "general"
    ],
    "wof:name":"US Foodservice",
    "wof:placetype":"venue"
},
  "geometry": {"coordinates":[-84.22959899999999,33.909211],"type":"Point"}
}