{
  "type": "Feature",
  "properties": {
    "iso:country":"US",
    "sg:address":"1399 Lafayette Pkwy",
    "sg:city":"Lagrange",
    "sg:classifiers":[
        {
            "category":"Restaurant",
            "type":"Food & Drink"
        }
    ],
    "sg:phone":"+1 706 882 0809",
    "sg:postcode":"30241",
    "sg:province":"GA",
    "sg:tags":[
        "pizza"
    ],
    "wof:name":"Pizza Villa",
    "wof:placetype":"venue"
},
  "geometry": {"coordinates":[-84.99018599999999,33.041004],"type":"Point"}
}