{
  "type": "Feature",
  "properties": {
    "addr:full":"614 S Harris St Sandersville GA 31082",
    "addr:housenumber":"614",
    "addr:postcode":"31082",
    "addr:street":"S Harris St",
    "iso:country":"US",
    "sg:address":"614 S Harris St",
    "sg:city":"Sandersville",
    "sg:classifiers":[
        {
            "category":"Cinema",
            "subcategory":"Movie Rental",
            "type":"Entertainment"
        }
    ],
    "sg:phone":"+1 478 552 6252",
    "sg:postcode":"31082",
    "sg:province":"GA",
    "sg:tags":[
        "leasing",
        "video",
        "disc",
        "tape"
    ],
    "wof:name":"Movie Gallery",
    "wof:placetype":"venue"
},
  "geometry": {"coordinates":[-82.809068,32.973968],"type":"Point"}
}