{
  "type": "Feature",
  "properties": {
    "addr:full":"15 Oxbo Rd Roswell GA 30075",
    "addr:housenumber":"15",
    "addr:postcode":"30075",
    "addr:street":"Oxbo Rd",
    "iso:country":"US",
    "sg:address":"15 Oxbo Rd",
    "sg:city":"Roswell",
    "sg:classifiers":[
        {
            "category":"Building & Trades",
            "subcategory":"Plumbing",
            "type":"Services"
        }
    ],
    "sg:phone":"+1 678 352 9833",
    "sg:postcode":"30075",
    "sg:province":"GA",
    "sg:tags":[
        "contractor"
    ],
    "wof:name":"Underdog Trenching & Boring",
    "wof:placetype":"venue"
},
  "geometry": {"coordinates":[-84.361118,34.017241],"type":"Point"}
}