{
  "type": "Feature",
  "properties": {
    "iso:country":"US",
    "sg:address":"55 Trinity Ave SW",
    "sg:city":"Atlanta",
    "sg:classifiers":[
        {
            "category":"Organizations",
            "subcategory":"Political Organization",
            "type":"Services"
        }
    ],
    "sg:phone":"+1 404 330 6100",
    "sg:postcode":"30303",
    "sg:province":"GA",
    "wof:name":"External Affirs Intl Relations",
    "wof:placetype":"venue"
},
  "geometry": {"coordinates":[-84.390061,33.747807],"type":"Point"}
}