{
  "type": "Feature",
  "properties": {
    "iso:country":"US",
    "sg:address":"7295 State Rte 85",
    "sg:city":"Riverdale",
    "sg:classifiers":[
        {
            "category":"Personal",
            "subcategory":"Beauty Salon",
            "type":"Services"
        }
    ],
    "sg:phone":"+1 770 991 2793",
    "sg:postcode":"30274",
    "sg:province":"GA",
    "sg:tags":[
        "shop"
    ],
    "wof:name":"Paisley Park Hair Salon",
    "wof:placetype":"venue"
},
  "geometry": {"coordinates":[-84.413832,33.561188],"type":"Point"}
}