{
  "type": "Feature",
  "properties": {
    "addr:full":"124 Sharon Dr Stockbridge GA 30281",
    "addr:housenumber":"124",
    "addr:postcode":"30281",
    "addr:street":"Sharon Dr",
    "iso:country":"US",
    "sg:address":"124 Sharon Dr",
    "sg:city":"Stockbridge",
    "sg:classifiers":[
        {
            "category":"Wholesale",
            "subcategory":"Electrical",
            "type":"Manufacturing & Wholesale Goods"
        }
    ],
    "sg:phone":"+1 770 474 9997",
    "sg:postcode":"30281",
    "sg:province":"GA",
    "sg:tags":[
        "generator"
    ],
    "wof:name":"Diversified Power Systems Inc",
    "wof:placetype":"venue"
},
  "geometry": {"coordinates":[-84.254998,33.502136],"type":"Point"}
}