{
  "type": "Feature",
  "properties": {
    "addr:full":"2576 Habersham Dr Decatur GA 30032",
    "addr:housenumber":"2576",
    "addr:postcode":"30032",
    "addr:street":"Habersham Dr",
    "iso:country":"US",
    "sg:address":"2576 Habersham Dr",
    "sg:city":"Decatur",
    "sg:classifiers":[
        {
            "category":"Retail",
            "subcategory":"Auto Repair",
            "type":"Services"
        }
    ],
    "sg:phone":"+1 404 243 8846",
    "sg:postcode":"30032",
    "sg:province":"GA",
    "sg:tags":[
        "tire"
    ],
    "wof:name":"Jackson Tire Service",
    "wof:placetype":"venue"
},
  "geometry": {"coordinates":[-84.283873,33.725267],"type":"Point"}
}