{
  "type": "Feature",
  "properties": {
    "addr:full":"104 N Walker's Mill Rd Griffin GA 30223",
    "addr:housenumber":"104",
    "addr:postcode":"30223",
    "addr:street":"N Walker'S Mill Rd",
    "iso:country":"US",
    "sg:address":"104 N Walker's Mill Rd",
    "sg:city":"Griffin",
    "sg:classifiers":[
        {
            "category":"Freight",
            "type":"Transportation"
        }
    ],
    "sg:phone":"+1 770 227 1641",
    "sg:postcode":"30223",
    "sg:province":"GA",
    "sg:tags":[
        "operator",
        "local",
        "trucking"
    ],
    "wof:name":"Clark Trucking",
    "wof:placetype":"venue"
},
  "geometry": {"coordinates":[-84.178607,33.247911],"type":"Point"}
}