{
  "type": "Feature",
  "properties": {
    "addr:full":"268 Jonesboro Rd Jonesboro GA 30236",
    "addr:housenumber":"268",
    "addr:postcode":"30236",
    "addr:street":"Jonesboro Rd",
    "iso:country":"US",
    "sg:address":"268 Jonesboro Rd",
    "sg:city":"Jonesboro",
    "sg:classifiers":[
        {
            "category":"Health Services",
            "subcategory":"Clinic",
            "type":"Services"
        },
        {
            "category":"Health Services",
            "subcategory":"Doctor",
            "type":"Services"
        }
    ],
    "sg:phone":"+1 770 471 6177",
    "sg:postcode":"30236",
    "sg:province":"GA",
    "wof:name":"Allied Healthcare Clinics Inc",
    "wof:placetype":"venue"
},
  "geometry": {"coordinates":[-84.350368,33.54125],"type":"Point"}
}