{
  "type": "Feature",
  "properties": {
    "addr:full":"6525 Tara Blvd Jonesboro GA 30236",
    "addr:housenumber":"6525",
    "addr:postcode":"30236",
    "addr:street":"Tara Blvd",
    "iso:country":"US",
    "sg:address":"6525 Tara Blvd",
    "sg:city":"Jonesboro",
    "sg:classifiers":[
        {
            "category":"Shopping",
            "subcategory":"Baby Store",
            "type":"Retail Goods"
        }
    ],
    "sg:phone":"+1 770 472 1929",
    "sg:postcode":"30236",
    "sg:province":"GA",
    "sg:tags":[
        "children's",
        "infant",
        "wear"
    ],
    "wof:name":"Sunkids",
    "wof:placetype":"venue"
},
  "geometry": {"coordinates":[-84.37299899999999,33.577082],"type":"Point"}
}