{
  "type": "Feature",
  "properties": {
    "addr:full":"750 N Jefferson St Milledgeville GA 31061",
    "addr:housenumber":"750",
    "addr:postcode":"31061",
    "addr:street":"N Jefferson St",
    "iso:country":"US",
    "sg:address":"750 N Jefferson St",
    "sg:city":"Milledgeville",
    "sg:classifiers":[
        {
            "category":"Utilities",
            "subcategory":"Mobile Phone",
            "type":"Services"
        }
    ],
    "sg:phone":"+1 478 453 3588",
    "sg:postcode":"31061",
    "sg:province":"GA",
    "sg:tags":[
        "telephone",
        "cellular"
    ],
    "sg:website":"www.alltel.com",
    "wof:name":"Alltel Georgia Communications",
    "wof:placetype":"venue"
},
  "geometry": {"coordinates":[-83.22821999999999,33.091068],"type":"Point"}
}