{
  "type": "Feature",
  "properties": {
    "addr:full":"4879 Lavista Rd Tucker GA 30084",
    "addr:housenumber":"4879",
    "addr:postcode":"30084",
    "addr:street":"Lavista Rd",
    "iso:country":"US",
    "sg:address":"4879 Lavista Rd",
    "sg:city":"Tucker",
    "sg:classifiers":[
        {
            "category":"Professional",
            "subcategory":"Lawyer & Legal Services",
            "type":"Services"
        }
    ],
    "sg:phone":"+1 770 621 5499",
    "sg:postcode":"30084",
    "sg:province":"GA",
    "sg:website":"www.mignottlaw.com",
    "wof:name":"Mignott Law Group Llc",
    "wof:placetype":"venue"
},
  "geometry": {"coordinates":[-84.221452,33.854563],"type":"Point"}
}