{
  "type": "Feature",
  "properties": {
    "iso:country":"US",
    "sg:address":"451 Petunia Rd",
    "sg:city":"Rebecca",
    "sg:phone":"+1 229 423 5510",
    "sg:postcode":"31783",
    "sg:province":"GA",
    "sg:tags":[
        "farm",
        "cotton"
    ],
    "wof:name":"Tim Hall",
    "wof:placetype":"venue"
},
  "geometry": {"coordinates":[-83.426365,31.808522],"type":"Point"}
}