{
  "type": "Feature",
  "properties": {
    "addr:full":"395 Whaleys Lake Dr Jonesboro GA 30238",
    "addr:housenumber":"395",
    "addr:postcode":"30238",
    "addr:street":"Whaleys Lake Dr",
    "iso:country":"US",
    "sg:address":"395 Whaleys Lake Dr",
    "sg:city":"Jonesboro",
    "sg:classifiers":[
        {
            "category":"Travel",
            "subcategory":"Travel Agent",
            "type":"Entertainment"
        }
    ],
    "sg:phone":"+1 770 478 3904",
    "sg:postcode":"30238",
    "sg:province":"GA",
    "sg:tags":[
        "consultant",
        "transportation"
    ],
    "wof:name":"Clb Transportation Consulting & Logistics Inc",
    "wof:placetype":"venue"
},
  "geometry": {"coordinates":[-84.380723,33.505564],"type":"Point"}
}