{
  "type": "Feature",
  "properties": {
    "iso:country":"US",
    "sg:address":"621 North Avenue NE",
    "sg:city":"Atlanta",
    "sg:classifiers":[
        {
            "category":"Communications",
            "type":"Services"
        }
    ],
    "sg:phone":"+1 404 733 6100",
    "sg:postcode":"30308",
    "sg:province":"GA",
    "sg:tags":[
        "recording",
        "rehearsal",
        "studio"
    ],
    "wof:name":"Bt Post",
    "wof:placetype":"venue"
},
  "geometry": {"coordinates":[-84.367062,33.771112],"type":"Point"}
}