{
  "type": "Feature",
  "properties": {
    "addr:full":"2100 Logan Dr Jonesboro GA 30236",
    "addr:housenumber":"2100",
    "addr:postcode":"30236",
    "addr:street":"Logan Dr",
    "iso:country":"US",
    "sg:address":"2100 Logan Dr",
    "sg:city":"Jonesboro",
    "sg:classifiers":[
        {
            "category":"Professional",
            "type":"Services"
        }
    ],
    "sg:phone":"+1 770 472 4356",
    "sg:postcode":"30236",
    "sg:province":"GA",
    "wof:name":"Mercury Communications Inc",
    "wof:placetype":"venue"
},
  "geometry": {"coordinates":[-84.31931299999999,33.544837],"type":"Point"}
}