{
  "type": "Feature",
  "properties": {
    "iso:country":"US",
    "sg:address":"1101 Hillcrest Pkwy",
    "sg:city":"Dublin",
    "sg:classifiers":[
        {
            "category":"Professional",
            "subcategory":"Lawyer & Legal Services",
            "type":"Services"
        }
    ],
    "sg:phone":"+1 478 275 1518",
    "sg:postcode":"31021",
    "sg:province":"GA",
    "sg:tags":[
        "attorney",
        "law",
        "bankruptcy"
    ],
    "wof:name":"Luman C Earle Bankruptcy Attorney",
    "wof:placetype":"venue"
},
  "geometry": {"coordinates":[-82.928301,32.547947],"type":"Point"}
}