{
  "type": "Feature",
  "properties": {
    "addr:full":"103A Church St Byron GA 31008",
    "addr:housenumber":"103a",
    "addr:postcode":"31008",
    "addr:street":"Church St",
    "iso:country":"US",
    "sg:address":"103A Church St",
    "sg:city":"Byron",
    "sg:classifiers":[
        {
            "category":"Restaurant",
            "type":"Food & Drink"
        }
    ],
    "sg:phone":"+1 478 956 5244",
    "sg:postcode":"31008",
    "sg:province":"GA",
    "sg:tags":[
        "barbecue"
    ],
    "wof:name":"Jones Farm Bar-B-Q",
    "wof:placetype":"venue"
},
  "geometry": {"coordinates":[-83.758415,32.649987],"type":"Point"}
}