{
  "type": "Feature",
  "properties": {
    "iso:country":"US",
    "sg:address":"461 Story Rd",
    "sg:city":"Sylvester",
    "sg:classifiers":[
        {
            "category":"Professional",
            "subcategory":"Management & Consulting",
            "type":"Services"
        }
    ],
    "sg:phone":"+1 229 776 8816",
    "sg:postcode":"31791",
    "sg:province":"GA",
    "sg:tags":[
        "environmental"
    ],
    "wof:name":"Industrial Municipal Services",
    "wof:placetype":"venue"
},
  "geometry": {"coordinates":[-83.968738,31.641397],"type":"Point"}
}