{
  "type": "Feature",
  "properties": {
    "iso:country":"US",
    "sg:address":"1525 Distribution Ct",
    "sg:city":"Lithia Springs",
    "sg:classifiers":[
        {
            "category":"Wholesale",
            "subcategory":"Machinery & Supplies",
            "type":"Manufacturing & Wholesale Goods"
        }
    ],
    "sg:phone":"+1 404 691 7340",
    "sg:postcode":"30122",
    "sg:province":"GA",
    "sg:tags":[
        "equipment",
        "industrial"
    ],
    "sg:website":"www.appliedindustrial.com",
    "wof:name":"Applied Industrial Tech Inc",
    "wof:placetype":"venue"
},
  "geometry": {"coordinates":[-84.625704,33.785233],"type":"Point"}
}