{
  "type": "Feature",
  "properties": {
    "iso:country":"US",
    "sg:address":"213 Linkwood Rd NW",
    "sg:city":"Atlanta",
    "sg:classifiers":[
        {
            "category":"Shopping",
            "subcategory":"Clothing, Apparel, & Fashions",
            "type":"Retail Goods"
        }
    ],
    "sg:phone":"+1 404 914 5896",
    "sg:postcode":"30318",
    "sg:province":"GA",
    "sg:tags":[
        "clothing",
        "store"
    ],
    "wof:name":"Mecca Designs",
    "wof:placetype":"venue"
},
  "geometry": {"coordinates":[-84.482652,33.761166],"type":"Point"}
}