{
  "type": "Feature",
  "properties": {
    "iso:country":"US",
    "sg:address":"250 W Pine St",
    "sg:city":"Colquitt",
    "sg:classifiers":[
        {
            "category":"Government",
            "subcategory":"Office",
            "type":"Public Place"
        }
    ],
    "sg:phone":"+1 229 758 3344",
    "sg:postcode":"31750",
    "sg:province":"GA",
    "sg:tags":[
        "county",
        "program",
        "health"
    ],
    "wof:name":"Miller County Health Dept",
    "wof:placetype":"venue"
},
  "geometry": {"coordinates":[-83.256575,31.713495],"type":"Point"}
}