{
  "type": "Feature",
  "properties": {
    "addr:full":"312 Tucker Rd Valdosta GA 31601",
    "addr:housenumber":"312",
    "addr:postcode":"31601",
    "addr:street":"Tucker Rd",
    "iso:country":"US",
    "sg:address":"312 Tucker Rd",
    "sg:city":"Valdosta",
    "sg:classifiers":[
        {
            "category":"Autos & Motor Vehicles",
            "subcategory":"Auto Supplies",
            "type":"Retail Goods"
        }
    ],
    "sg:phone":"+1 229 245 1830",
    "sg:postcode":"31601",
    "sg:province":"GA",
    "sg:tags":[
        "repair",
        "truck"
    ],
    "wof:name":"Truck Center of South Georgia",
    "wof:placetype":"venue"
},
  "geometry": {"coordinates":[-83.27130099999999,30.809532],"type":"Point"}
}