{
  "type": "Feature",
  "properties": {
    "addr:full":"6180 Jones Rd Atlanta GA 30349",
    "addr:housenumber":"6180",
    "addr:postcode":"30349",
    "addr:street":"Jones Rd",
    "iso:country":"US",
    "sg:address":"6180 Jones Rd",
    "sg:city":"Atlanta",
    "sg:classifiers":[
        {
            "category":"Real Estate",
            "subcategory":"Real Estate Services",
            "type":"Services"
        },
        {
            "category":"Building & Trades",
            "subcategory":"Cleaning & Sanitation",
            "type":"Services"
        }
    ],
    "sg:phone":"+1 770 306 0553",
    "sg:postcode":"30349",
    "sg:province":"GA",
    "sg:tags":[
        "maintenance",
        "cleaners-interior"
    ],
    "wof:name":"A & L Cleaning Service",
    "wof:placetype":"venue"
},
  "geometry": {"coordinates":[-84.589968,33.639235],"type":"Point"}
}