{
  "type": "Feature",
  "properties": {
    "addr:full":"31 Magazine Ave Savannah GA 31415",
    "addr:housenumber":"31",
    "addr:postcode":"31415",
    "addr:street":"Magazine Ave",
    "iso:country":"US",
    "sg:address":"31 Magazine Ave",
    "sg:city":"Savannah",
    "sg:classifiers":[
        {
            "category":"Wholesale",
            "subcategory":"Machinery & Supplies",
            "type":"Manufacturing & Wholesale Goods"
        }
    ],
    "sg:phone":"+1 912 238 1717",
    "sg:postcode":"31415",
    "sg:province":"GA",
    "sg:tags":[
        "cargo",
        "devices",
        "stabilizing"
    ],
    "wof:name":"Cargo Containment Corp",
    "wof:placetype":"venue"
},
  "geometry": {"coordinates":[-81.116209,32.078857],"type":"Point"}
}