{
  "type": "Feature",
  "properties": {
    "addr:full":"5181 Zebulon Rd Macon GA 31210",
    "addr:housenumber":"5181",
    "addr:postcode":"31210",
    "addr:street":"Zebulon Rd",
    "iso:country":"US",
    "sg:address":"5181 Zebulon Rd",
    "sg:city":"Macon",
    "sg:classifiers":[
        {
            "category":"Personal",
            "subcategory":"Beauty Salon",
            "type":"Services"
        }
    ],
    "sg:phone":"+1 478 745 6567",
    "sg:postcode":"31210",
    "sg:province":"GA",
    "sg:tags":[
        "shop"
    ],
    "wof:name":"Hair Shop",
    "wof:placetype":"venue"
},
  "geometry": {"coordinates":[-83.733169,32.879502],"type":"Point"}
}