{
  "type": "Feature",
  "properties": {
    "iso:country":"US",
    "sg:address":"108 Bond Dr",
    "sg:city":"Ellenwood",
    "sg:classifiers":[
        {
            "category":"Freight",
            "type":"Transportation"
        }
    ],
    "sg:phone":"+1 404 975 9360",
    "sg:postcode":"30294",
    "sg:province":"GA",
    "sg:tags":[
        "courier"
    ],
    "wof:name":"Ftf Courier-Services",
    "wof:placetype":"venue"
},
  "geometry": {"coordinates":[-84.258915,33.639465],"type":"Point"}
}