{
  "type": "Feature",
  "properties": {
    "iso:country":"US",
    "sg:address":"240 Pullman Trl",
    "sg:city":"Roswell",
    "sg:classifiers":[
        {
            "category":"Professional",
            "subcategory":"Employment Agencies",
            "type":"Services"
        }
    ],
    "sg:phone":"+1 770 641 1112",
    "sg:postcode":"30075",
    "sg:province":"GA",
    "sg:tags":[
        "opportunity"
    ],
    "wof:name":"Best Performance Management",
    "wof:placetype":"venue"
},
  "geometry": {"coordinates":[-84.354581,34.036342],"type":"Point"}
}