{
  "type": "Feature",
  "properties": {
    "iso:country":"US",
    "sg:address":"740 Falls Landing Ct",
    "sg:city":"Alpharetta",
    "sg:classifiers":[
        {
            "category":"Building & Trades",
            "subcategory":"Construction",
            "type":"Services"
        }
    ],
    "sg:phone":"+1 678 893 0999",
    "sg:postcode":"30022",
    "sg:province":"GA",
    "sg:tags":[
        "hanging",
        "contractor"
    ],
    "wof:name":"1875 Old Alabama LLC",
    "wof:placetype":"venue"
},
  "geometry": {"coordinates":[-84.24489199999999,34.023043],"type":"Point"}
}