{
  "type": "Feature",
  "properties": {
    "addr:full":"1371 Daniel Ln Lawrenceville GA 30045",
    "addr:housenumber":"1371",
    "addr:postcode":"30045",
    "addr:street":"Daniel Ln",
    "iso:country":"US",
    "sg:address":"1371 Daniel Ln",
    "sg:city":"Lawrenceville",
    "sg:classifiers":[
        {
            "category":"Arts & Performance",
            "subcategory":"Theater",
            "type":"Entertainment"
        }
    ],
    "sg:phone":"+1 678 467 0261",
    "sg:postcode":"30045",
    "sg:province":"GA",
    "sg:tags":[
        "entertainer",
        "manager",
        "or",
        "agent",
        "for"
    ],
    "wof:name":"Burnem Up Productions LLC",
    "wof:placetype":"venue"
},
  "geometry": {"coordinates":[-84.015049,33.9261],"type":"Point"}
}