{
  "type": "Feature",
  "properties": {
    "iso:country":"US",
    "sg:address":"3150 Helen St",
    "sg:city":"Savannah",
    "sg:classifiers":[
        {
            "category":"Building & Trades",
            "subcategory":"Construction",
            "type":"Services"
        }
    ],
    "sg:phone":"+1 912 352 3528",
    "sg:postcode":"31404",
    "sg:province":"GA",
    "sg:tags":[
        "insulation",
        "material",
        "contractor"
    ],
    "wof:name":"Mallard Insulation Co Inc",
    "wof:placetype":"venue"
},
  "geometry": {"coordinates":[-81.064992,32.03663],"type":"Point"}
}