{
  "type": "Feature",
  "properties": {
    "addr:full":"2445 Herring Rd SW Atlanta GA 30311",
    "addr:housenumber":"2445",
    "addr:postcode":"30311",
    "addr:street":"Herring Rd Sw",
    "iso:country":"US",
    "sg:address":"2445 Herring Rd SW",
    "sg:city":"Atlanta",
    "sg:classifiers":[
        {
            "category":"Wholesale",
            "subcategory":"Auto Parts",
            "type":"Manufacturing & Wholesale Goods"
        }
    ],
    "sg:phone":"+1 404 755 4024",
    "sg:postcode":"30311",
    "sg:province":"GA",
    "sg:tags":[
        "tire"
    ],
    "wof:name":"Moh Tires",
    "wof:placetype":"venue"
},
  "geometry": {"coordinates":[-84.462898,33.7243],"type":"Point"}
}