{
  "type": "Feature",
  "properties": {
    "iso:country":"US",
    "sg:address":"5399 Memorial Dr",
    "sg:city":"Stone Mountain",
    "sg:classifiers":[
        {
            "category":"Building & Trades",
            "subcategory":"Equipment Rental",
            "type":"Services"
        }
    ],
    "sg:phone":"+1 404 292 7750",
    "sg:postcode":"30083",
    "sg:province":"GA",
    "sg:tags":[
        "leasing",
        "furniture"
    ],
    "wof:name":"Aarons Sales & Lease Ownership",
    "wof:placetype":"venue"
},
  "geometry": {"coordinates":[-84.217805,33.799481],"type":"Point"}
}