{
  "type": "Feature",
  "properties": {
    "iso:country":"US",
    "sg:address":"1564 Herrington Rd NW",
    "sg:city":"Lawrenceville",
    "sg:classifiers":[
        {
            "category":"Real Estate",
            "subcategory":"Real Estate Agent",
            "type":"Services"
        }
    ],
    "sg:phone":"+1 770 338 0642",
    "sg:postcode":"30043",
    "sg:province":"GA",
    "wof:name":"Pcm Management",
    "wof:placetype":"venue"
},
  "geometry": {"coordinates":[-84.078064,33.968603],"type":"Point"}
}