{
  "type": "Feature",
  "properties": {
    "addr:full":"3651 Shallowford Rd NE Atlanta GA 30340",
    "addr:housenumber":"3651",
    "addr:postcode":"30340",
    "addr:street":"Shallowford Rd Ne",
    "iso:country":"US",
    "sg:address":"3651 Shallowford Rd NE",
    "sg:city":"Atlanta",
    "sg:classifiers":[
        {
            "category":"Taxi",
            "type":"Transportation"
        }
    ],
    "sg:phone":"+1 770 455 9939",
    "sg:postcode":"30340",
    "sg:province":"GA",
    "sg:tags":[
        "taxicab"
    ],
    "wof:name":"Express Taxicab",
    "wof:placetype":"venue"
},
  "geometry": {"coordinates":[-84.285222,33.895505],"type":"Point"}
}