{
  "type": "Feature",
  "properties": {
    "addr:full":"5128 Oak Field Ct Murrayville GA 30564",
    "addr:housenumber":"5128",
    "addr:postcode":"30564",
    "addr:street":"Oak Field Ct",
    "iso:country":"US",
    "sg:address":"5128 Oak Field Ct",
    "sg:city":"Murrayville",
    "sg:classifiers":[
        {
            "category":"Recreation",
            "type":"Entertainment"
        }
    ],
    "sg:phone":"+1 678 450 5501",
    "sg:postcode":"30564",
    "sg:province":"GA",
    "sg:tags":[
        "entertainers-family",
        "business"
    ],
    "wof:name":"Big Fitz Entertainment",
    "wof:placetype":"venue"
},
  "geometry": {"coordinates":[-83.89622799999999,34.411321],"type":"Point"}
}