{
  "type": "Feature",
  "properties": {
    "iso:country":"US",
    "sg:address":"1783 E Washington Rd",
    "sg:city":"East Point",
    "sg:classifiers":[
        {
            "category":"Real Estate",
            "subcategory":"Real Estate Agent",
            "type":"Services"
        }
    ],
    "sg:phone":"+1 404 766 1350",
    "sg:postcode":"30344",
    "sg:province":"GA",
    "sg:tags":[
        "appraiser"
    ],
    "wof:name":"Bob Pratt Realty & Appraisal",
    "wof:placetype":"venue"
},
  "geometry": {"coordinates":[-84.447227,33.67582],"type":"Point"}
}