{
  "type": "Feature",
  "properties": {
    "iso:country":"US",
    "sg:address":"1300 Joseph E Boone Blvd NW",
    "sg:city":"Atlanta",
    "sg:classifiers":[
        {
            "category":"Place Of Worship",
            "subcategory":"Church",
            "type":"Public Place"
        },
        {
            "category":"Place Of Worship",
            "type":"Public Place"
        },
        {
            "category":"Organizations",
            "subcategory":"Religious Organization",
            "type":"Services"
        }
    ],
    "sg:phone":"+1 404 874 2241",
    "sg:postcode":"30314",
    "sg:province":"GA",
    "sg:tags":[
        "god",
        "churches-church",
        "churches-pentecostal"
    ],
    "wof:name":"Midtown Mission Church Of God",
    "wof:placetype":"venue"
},
  "geometry": {"coordinates":[-84.430164,33.763538],"type":"Point"}
}