{
  "type": "Feature",
  "properties": {
    "addr:full":"1149 Corner Rd Powder Springs GA 30127",
    "addr:housenumber":"1149",
    "addr:postcode":"30127",
    "addr:street":"Corner Rd",
    "iso:country":"US",
    "sg:address":"1149 Corner Rd",
    "sg:city":"Powder Springs",
    "sg:classifiers":[
        {
            "category":"Utilities",
            "subcategory":"Telephone",
            "type":"Services"
        }
    ],
    "sg:phone":"+1 770 222 6448",
    "sg:postcode":"30127",
    "sg:province":"GA",
    "sg:tags":[
        "communications"
    ],
    "wof:name":"McCall Communications Inc",
    "wof:placetype":"venue"
},
  "geometry": {"coordinates":[-84.705493,33.92808],"type":"Point"}
}