{
  "type": "Feature",
  "properties": {
    "addr:full":"1372 Peachtree St NE Atlanta GA 30309",
    "addr:housenumber":"1372",
    "addr:postcode":"30309",
    "addr:street":"Peachtree St Ne",
    "iso:country":"US",
    "sg:address":"1372 Peachtree St NE",
    "sg:city":"Atlanta",
    "sg:classifiers":[
        {
            "category":"Professional",
            "subcategory":"Employment Agencies",
            "type":"Services"
        }
    ],
    "sg:phone":"+1 404 888 0800",
    "sg:postcode":"30309",
    "sg:province":"GA",
    "wof:name":"Computerxperts of Atlanta Inc",
    "wof:placetype":"venue"
},
  "geometry": {"coordinates":[-84.3862,33.792099],"type":"Point"}
}