{
  "type": "Feature",
  "properties": {
    "iso:country":"US",
    "sg:address":"2805 Clairmont Rd NE",
    "sg:city":"Atlanta",
    "sg:classifiers":[
        {
            "category":"Professional",
            "subcategory":"Management & Consulting",
            "type":"Services"
        }
    ],
    "sg:phone":"+1 678 793 8086",
    "sg:postcode":"30329",
    "sg:province":"GA",
    "wof:name":"Rain Drop Company",
    "wof:placetype":"venue"
},
  "geometry": {"coordinates":[-84.311949,33.837621],"type":"Point"}
}