{
  "type": "Feature",
  "properties": {
    "addr:full":"6190 Rachel Ridge Norcross GA 30092",
    "addr:housenumber":"6190",
    "addr:postcode":"30092",
    "addr:street":"Rachel Ridge",
    "iso:country":"US",
    "sg:address":"6190 Rachel Ridge",
    "sg:city":"Norcross",
    "sg:classifiers":[
        {
            "category":"Manufacturing",
            "subcategory":"Paper Products",
            "type":"Manufacturing & Wholesale Goods"
        }
    ],
    "sg:phone":"+1 770 729 9817",
    "sg:postcode":"30092",
    "sg:province":"GA",
    "sg:tags":[
        "mill"
    ],
    "wof:name":"Southern Notes",
    "wof:placetype":"venue"
},
  "geometry": {"coordinates":[-84.25630200000001,33.978735],"type":"Point"}
}