{
  "type": "Feature",
  "properties": {
    "iso:country":"US",
    "sg:address":"73 Pine Grove Rd",
    "sg:city":"Locust Grove",
    "sg:classifiers":[
        {
            "category":"Building & Trades",
            "subcategory":"Plumbing",
            "type":"Services"
        }
    ],
    "sg:phone":"+1 770 914 1071",
    "sg:postcode":"30248",
    "sg:province":"GA",
    "sg:tags":[
        "conditioning",
        "air",
        "system",
        "contractor"
    ],
    "wof:name":"Alliance Heating & AC SVC",
    "wof:placetype":"venue"
},
  "geometry": {"coordinates":[-84.124985,33.373663],"type":"Point"}
}