{
  "type": "Feature",
  "properties": {
    "iso:country":"US",
    "sg:address":"1230 Johnson Ferry Rd",
    "sg:city":"Marietta",
    "sg:classifiers":[
        {
            "category":"Wholesale",
            "subcategory":"Durable Goods & Equipment",
            "type":"Manufacturing & Wholesale Goods"
        }
    ],
    "sg:phone":"+1 770 509 8722",
    "sg:postcode":"30068",
    "sg:province":"GA",
    "sg:tags":[
        "representative",
        "manufacturer"
    ],
    "sg:website":"www.isprep.com",
    "wof:name":"Independent Security Products",
    "wof:placetype":"venue"
},
  "geometry": {"coordinates":[-84.420405,33.979078],"type":"Point"}
}