{
  "type": "Feature",
  "properties": {
    "addr:full":"9442 S Main St Jonesboro GA 30236",
    "addr:housenumber":"9442",
    "addr:postcode":"30236",
    "addr:street":"S Main St",
    "iso:country":"US",
    "sg:address":"9442 S Main St",
    "sg:city":"Jonesboro",
    "sg:classifiers":[
        {
            "category":"Real Estate",
            "subcategory":"Real Estate Agent",
            "type":"Services"
        }
    ],
    "sg:phone":"+1 770 478 9100",
    "sg:postcode":"30236",
    "sg:province":"GA",
    "sg:tags":[
        "management"
    ],
    "wof:name":"Bluebird Realty",
    "wof:placetype":"venue"
},
  "geometry": {"coordinates":[-84.338804,33.492786],"type":"Point"}
}