{
  "type": "Feature",
  "properties": {
    "iso:country":"US",
    "sg:address":"177 Laura Cir",
    "sg:city":"Bowdon",
    "sg:classifiers":[
        {
            "category":"Building & Trades",
            "subcategory":"Pest Control",
            "type":"Services"
        }
    ],
    "sg:phone":"+1 770 258 8568",
    "sg:postcode":"30108",
    "sg:province":"GA",
    "sg:tags":[
        "trapper",
        "animal"
    ],
    "wof:name":"Adcock's Rid-A-Critter",
    "wof:placetype":"venue"
},
  "geometry": {"coordinates":[-85.235613,33.532183],"type":"Point"}
}