{
  "type": "Feature",
  "properties": {
    "addr:full":"182 Carriage Trce Marietta GA 30068",
    "addr:housenumber":"182",
    "addr:postcode":"30068",
    "addr:street":"Carriage Trce",
    "iso:country":"US",
    "sg:address":"182 Carriage Trce",
    "sg:city":"Marietta",
    "sg:classifiers":[
        {
            "category":"Professional",
            "subcategory":"Business Services",
            "type":"Services"
        }
    ],
    "sg:phone":"+1 770 578 1201",
    "sg:postcode":"30068",
    "sg:province":"GA",
    "wof:name":"United Ventures Inc",
    "wof:placetype":"venue"
},
  "geometry": {"coordinates":[-84.466579,33.951075],"type":"Point"}
}