{
  "type": "Feature",
  "properties": {
    "iso:country":"US",
    "sg:address":"2325 Ventura Rd",
    "sg:city":"Smyrna",
    "sg:classifiers":[
        {
            "category":"Health Services",
            "subcategory":"Medical Lab",
            "type":"Services"
        }
    ],
    "sg:phone":"+1 770 432 4494",
    "sg:postcode":"30080",
    "sg:province":"GA",
    "sg:tags":[
        "laboratory"
    ],
    "wof:name":"Natural Restoration Inc",
    "wof:placetype":"venue"
},
  "geometry": {"coordinates":[-84.53814300000001,33.896256],"type":"Point"}
}