{
  "type": "Feature",
  "properties": {
    "addr:full":"537 Blackburn Dr Augusta GA 30907",
    "addr:housenumber":"537",
    "addr:postcode":"30907",
    "addr:street":"Blackburn Dr",
    "iso:country":"US",
    "sg:address":"537 Blackburn Dr",
    "sg:city":"Augusta",
    "sg:classifiers":[
        {
            "category":"Banks & Credit Unions",
            "subcategory":"Investment Brokerage",
            "type":"Services"
        },
        {
            "category":"Professional",
            "subcategory":"Management & Consulting",
            "type":"Services"
        }
    ],
    "sg:phone":"+1 706 854 8040",
    "sg:postcode":"30907",
    "sg:province":"GA",
    "sg:tags":[
        "advisory",
        "planning",
        "financial",
        "consultant"
    ],
    "wof:name":"Monitor Group Inc",
    "wof:placetype":"venue"
},
  "geometry": {"coordinates":[-82.078778,33.533757],"type":"Point"}
}