{
  "type": "Feature",
  "properties": {
    "iso:country":"US",
    "sg:address":"1530 Nabell Avenue",
    "sg:city":"Atlanta",
    "sg:classifiers":[
        {
            "category":"Personal",
            "type":"Services"
        },
        {
            "category":"Travel",
            "subcategory":"Bed & Breakfast",
            "type":"Entertainment"
        }
    ],
    "sg:phone":"+1 404 768 7007",
    "sg:postcode":"30344",
    "sg:province":"GA",
    "sg:tags":[
        "party",
        "planning",
        "barricade",
        "event"
    ],
    "wof:name":"American Message Center",
    "wof:placetype":"venue"
},
  "geometry": {"coordinates":[-84.438675,33.689803],"type":"Point"}
}