{
  "type": "Feature",
  "properties": {
    "addr:full":"1355 Terrell Mill Rd SE Se1464 Marietta GA 30067",
    "addr:housenumber":"1355",
    "addr:postcode":"30067",
    "addr:street":"Terrell Mill Rd Se Se1464",
    "iso:country":"US",
    "sg:address":"1355 Terrell Mill Rd SE Se1464",
    "sg:city":"Marietta",
    "sg:classifiers":[
        {
            "category":"Banks & Credit Unions",
            "subcategory":"Bank",
            "type":"Services"
        }
    ],
    "sg:phone":"+1 770 591 6509",
    "sg:postcode":"30067",
    "sg:province":"GA",
    "sg:tags":[
        "letter"
    ],
    "sg:website":"http://www.gecas.com",
    "wof:name":"General Electric Capital Corporation",
    "wof:placetype":"venue"
},
  "geometry": {"coordinates":[-84.46592099999999,33.918715],"type":"Point"}
}