{
  "type": "Feature",
  "properties": {
    "iso:country":"US",
    "sg:address":"1207 River Forest Ln",
    "sg:city":"Woodstock",
    "sg:classifiers":[
        {
            "category":"Building & Trades",
            "subcategory":"Construction",
            "type":"Services"
        }
    ],
    "sg:phone":"+1 770 928 1528",
    "sg:postcode":"30188",
    "sg:province":"GA",
    "sg:tags":[
        "house"
    ],
    "wof:name":"Ken Andrews Contracting",
    "wof:placetype":"venue"
},
  "geometry": {"coordinates":[-84.4425,34.103012],"type":"Point"}
}