{
  "type": "Feature",
  "properties": {
    "iso:country":"US",
    "sg:address":"3700 Data Dr",
    "sg:city":"Norcross",
    "sg:classifiers":[
        {
            "category":"Building & Trades",
            "subcategory":"Locksmith",
            "type":"Services"
        }
    ],
    "sg:phone":"+1 770 326 5000",
    "sg:postcode":"30092",
    "sg:province":"GA",
    "sg:tags":[
        "key"
    ],
    "wof:name":"Norris Locksmith",
    "wof:placetype":"venue"
},
  "geometry": {"coordinates":[-84.226296,33.970231],"type":"Point"}
}