{
  "type": "Feature",
  "properties": {
    "addr:full":"7130 New Calhoun Hwy NE Rome GA 30161",
    "addr:housenumber":"7130",
    "addr:postcode":"ga 30161",
    "addr:street":"New Calhoun Hwy Ne",
    "iso:country":"US",
    "sg:address":"7130 New Calhoun Hwy NE",
    "sg:city":"Rome",
    "sg:classifiers":[
        {
            "category":"Food & Beverages",
            "subcategory":"Groceries & Convenience Stores",
            "type":"Retail Goods"
        }
    ],
    "sg:phone":"+1 706 235 8092",
    "sg:postcode":"30161",
    "sg:province":"GA",
    "sg:tags":[
        "station",
        "gasoline"
    ],
    "wof:name":"Favorite Markets",
    "wof:placetype":"venue"
},
  "geometry": {"coordinates":[-85.113201,34.306984],"type":"Point"}
}