{
  "type": "Feature",
  "properties": {
    "addr:full":"3629 Burlingham Dr Lithonia GA 30038",
    "addr:housenumber":"3629",
    "addr:postcode":"30038",
    "addr:street":"Burlingham Dr",
    "iso:country":"US",
    "sg:address":"3629 Burlingham Dr",
    "sg:city":"Lithonia",
    "sg:classifiers":[
        {
            "category":"Building & Trades",
            "subcategory":"Locksmith",
            "type":"Services"
        }
    ],
    "sg:phone":"+1 888 271 1713",
    "sg:postcode":"30038",
    "sg:province":"GA",
    "sg:tags":[
        "key"
    ],
    "wof:name":"24 Hour 7 Day Emergency Locksmith",
    "wof:placetype":"venue"
},
  "geometry": {"coordinates":[-84.19132500000001,33.675906],"type":"Point"}
}