{
  "type": "Feature",
  "properties": {
    "addr:full":"4270 Chatham View Dr Buford GA 30518",
    "addr:housenumber":"4270",
    "addr:postcode":"30518",
    "addr:street":"Chatham View Dr",
    "iso:country":"US",
    "sg:address":"4270 Chatham View Dr",
    "sg:city":"Buford",
    "sg:classifiers":[
        {
            "category":"Shopping",
            "subcategory":"Clothing, Apparel, & Fashions",
            "type":"Retail Goods"
        }
    ],
    "sg:phone":"+1 770 932 6205",
    "sg:postcode":"30518",
    "sg:province":"GA",
    "sg:tags":[
        "wear"
    ],
    "wof:name":"Designs By Sherrie",
    "wof:placetype":"venue"
},
  "geometry": {"coordinates":[-84.022226,34.082531],"type":"Point"}
}