{
  "type": "Feature",
  "properties": {
    "iso:country":"US",
    "sg:address":"1870 Midtown Dr",
    "sg:city":"Columbus",
    "sg:classifiers":[
        {
            "category":"Utilities",
            "subcategory":"Mobile Phone",
            "type":"Services"
        },
        {
            "category":"Utilities",
            "subcategory":"Telephone",
            "type":"Services"
        },
        {
            "category":"Communications",
            "type":"Services"
        }
    ],
    "sg:phone":"+1 706 563 0900",
    "sg:postcode":"31906",
    "sg:province":"GA",
    "sg:tags":[
        "cellular"
    ],
    "sg:website":"http://www.verizonwireless.com",
    "wof:name":"Verizon Wireless",
    "wof:placetype":"venue"
},
  "geometry": {"coordinates":[-84.94019299999999,32.480275],"type":"Point"}
}