{
  "type": "Feature",
  "properties": {
    "iso:country":"US",
    "sg:address":"212 Shady Dr",
    "sg:city":"Dalton",
    "sg:classifiers":[
        {
            "category":"Home & Garden",
            "subcategory":"Garden Supply",
            "type":"Retail Goods"
        }
    ],
    "sg:phone":"+1 706 277 3932",
    "sg:postcode":"30720",
    "sg:province":"GA",
    "sg:tags":[
        "mulch"
    ],
    "wof:name":"A Professional Tree & Stump",
    "wof:placetype":"venue"
},
  "geometry": {"coordinates":[-84.97493799999999,34.722184],"type":"Point"}
}