{
  "type": "Feature",
  "properties": {
    "addr:full":"15 Magnolia Cv Hawkinsville GA 31036",
    "addr:housenumber":"15",
    "addr:postcode":"31036",
    "addr:street":"Magnolia Cv",
    "iso:country":"US",
    "sg:address":"15 Magnolia Cv",
    "sg:city":"Hawkinsville",
    "sg:classifiers":[
        {
            "category":"Professional",
            "subcategory":"Lawyer & Legal Services",
            "type":"Services"
        }
    ],
    "sg:phone":"+1 478 783 1962",
    "sg:postcode":"31036",
    "sg:province":"GA",
    "sg:tags":[
        "attorney"
    ],
    "wof:name":"Karen Brown",
    "wof:placetype":"venue"
},
  "geometry": {"coordinates":[-83.49796600000001,32.292062],"type":"Point"}
}