{
  "type": "Feature",
  "properties": {
    "addr:full":"3985 Pio Nono Ave Macon GA 31206",
    "addr:housenumber":"3985",
    "addr:postcode":"31206",
    "addr:street":"Pio Nono Ave",
    "iso:country":"US",
    "sg:address":"3985 Pio Nono Ave",
    "sg:city":"Macon",
    "sg:classifiers":[
        {
            "category":"Health Services",
            "subcategory":"Doctor",
            "type":"Services"
        }
    ],
    "sg:phone":"+1 478 781 8533",
    "sg:postcode":"31206",
    "sg:province":"GA",
    "wof:name":"Lewis R Irby DDS",
    "wof:placetype":"venue"
},
  "geometry": {"coordinates":[-83.668666,32.791183],"type":"Point"}
}