{
  "type": "Feature",
  "properties": {
    "addr:full":"5700 Austell Pwdr Spgs Rd Austell GA 30106",
    "addr:postcode":"5700;30106",
    "addr:street":"Spgs Rd",
    "iso:country":"US",
    "sg:address":"5700 Austell Pwdr Spgs Rd",
    "sg:city":"Austell",
    "sg:classifiers":[
        {
            "category":"Retail",
            "subcategory":"Veterinary Services",
            "type":"Services"
        },
        {
            "category":"Retail",
            "subcategory":"Pet Boarding",
            "type":"Services"
        }
    ],
    "sg:phone":"+1 770 941 3668",
    "sg:postcode":"30106",
    "sg:province":"GA",
    "sg:tags":[
        "veterinarian",
        "boarding/pet",
        "sitting"
    ],
    "wof:name":"Bullard Animal Hospital",
    "wof:placetype":"venue"
},
  "geometry": {"coordinates":[-84.637703,33.816799],"type":"Point"}
}