{
  "type": "Feature",
  "properties": {
    "iso:country":"US",
    "sg:address":"2130 Hamilton Mill Pkwy",
    "sg:city":"Dacula",
    "sg:classifiers":[
        {
            "category":"Retail",
            "subcategory":"Veterinary Services",
            "type":"Services"
        }
    ],
    "sg:phone":"+1 770 932 1616",
    "sg:postcode":"30019",
    "sg:province":"GA",
    "wof:name":"Hamilton Mill Animal Hospital",
    "wof:placetype":"venue"
},
  "geometry": {"coordinates":[-83.90965199999999,34.052626],"type":"Point"}
}