{
  "type": "Feature",
  "properties": {
    "addr:full":"16 Bullsboro Dr Newnan GA 30263",
    "addr:housenumber":"16",
    "addr:postcode":"30263",
    "addr:street":"Bullsboro Dr",
    "iso:country":"US",
    "sg:address":"16 Bullsboro Dr",
    "sg:city":"Newnan",
    "sg:classifiers":[
        {
            "category":"Banks & Credit Unions",
            "subcategory":"Bank",
            "type":"Services"
        }
    ],
    "sg:phone":"+1 770 253 5230",
    "sg:postcode":"30263",
    "sg:province":"GA",
    "sg:tags":[
        "loan"
    ],
    "wof:name":"First Franklin Financial Corp",
    "wof:placetype":"venue"
},
  "geometry": {"coordinates":[-84.791957,33.382976],"type":"Point"}
}