{
  "type": "Feature",
  "properties": {
    "addr:full":"197 Burt Rd Dallas GA 30132",
    "addr:housenumber":"197",
    "addr:postcode":"30132",
    "addr:street":"Burt Rd",
    "iso:country":"US",
    "sg:address":"197 Burt Rd",
    "sg:city":"Dallas",
    "sg:classifiers":[
        {
            "category":"Building & Trades",
            "subcategory":"Construction",
            "type":"Services"
        }
    ],
    "sg:phone":"+1 770 445 2925",
    "sg:postcode":"30132",
    "sg:province":"GA",
    "sg:tags":[
        "house"
    ],
    "wof:name":"C L Collins Construction Co",
    "wof:placetype":"venue"
},
  "geometry": {"coordinates":[-84.86527,34.017338],"type":"Point"}
}