{
  "type": "Feature",
  "properties": {
    "addr:full":"978 Highland Cir SE Conyers GA 30012",
    "addr:housenumber":"978",
    "addr:postcode":"30012",
    "addr:street":"Highland Cir Se",
    "iso:country":"US",
    "sg:address":"978 Highland Cir SE",
    "sg:city":"Conyers",
    "sg:classifiers":[
        {
            "category":"Shopping",
            "subcategory":"Clothing, Apparel, & Fashions",
            "type":"Retail Goods"
        }
    ],
    "sg:phone":"+1 770 483 0578",
    "sg:postcode":"30012",
    "sg:province":"GA",
    "sg:tags":[
        "shop",
        "bridal"
    ],
    "wof:name":"Charming Creations Bridal Shop",
    "wof:placetype":"venue"
},
  "geometry": {"coordinates":[-84.013975,33.6587],"type":"Point"}
}