{
  "type": "Feature",
  "properties": {
    "iso:country":"US",
    "sg:address":"1484 Roswell Rd",
    "sg:city":"Marietta",
    "sg:classifiers":[
        {
            "category":"Restaurant",
            "type":"Food & Drink"
        }
    ],
    "sg:menulink":"http://www.allmenus.com/ga/marietta/229340-cabana/menu/",
    "sg:phone":"+1 678 560 2799",
    "sg:postcode":"30062",
    "sg:province":"GA",
    "sg:tags":[
        "caribbean"
    ],
    "wof:name":"Cabana",
    "wof:placetype":"venue"
},
  "geometry": {"coordinates":[-84.50873799999999,33.951037],"type":"Point"}
}