{
  "type": "Feature",
  "properties": {
    "addr:full":"2350 Beaver Ruin Rd Norcross GA 30071",
    "addr:housenumber":"2350",
    "addr:postcode":"30071",
    "addr:street":"Beaver Ruin Rd",
    "iso:country":"US",
    "sg:address":"2350 Beaver Ruin Rd",
    "sg:city":"Norcross",
    "sg:classifiers":[
        {
            "category":"Building & Trades",
            "subcategory":"Construction",
            "type":"Services"
        }
    ],
    "sg:phone":"+1 770 242 0064",
    "sg:postcode":"30071",
    "sg:province":"GA",
    "sg:tags":[
        "layer",
        "carpet"
    ],
    "wof:name":"Save On Carpets Inc",
    "wof:placetype":"venue"
},
  "geometry": {"coordinates":[-84.193207,33.939749],"type":"Point"}
}