{
  "type": "Feature",
  "properties": {
    "iso:country":"US",
    "sg:address":"209 N Smith St",
    "sg:city":"Sandersville",
    "sg:classifiers":[
        {
            "category":"Building & Trades",
            "subcategory":"Construction",
            "type":"Services"
        }
    ],
    "sg:phone":"+1 478 552 5189",
    "sg:postcode":"31082",
    "sg:province":"GA",
    "sg:tags":[
        "system",
        "specialty",
        "heating",
        "contractor",
        "air conditioning"
    ],
    "wof:name":"Outback Heating & Cooling Inc",
    "wof:placetype":"venue"
},
  "geometry": {"coordinates":[-82.808206,32.983858],"type":"Point"}
}