{
  "type": "Feature",
  "properties": {
    "iso:country":"US",
    "sg:address":"3011 Gibbons St",
    "sg:city":"Savannah",
    "sg:classifiers":[
        {
            "category":"Real Estate",
            "subcategory":"Architect",
            "type":"Services"
        }
    ],
    "sg:phone":"+1 912 356 3308",
    "sg:postcode":"31404",
    "sg:province":"GA",
    "wof:name":"Construction Project Specs Inc",
    "wof:placetype":"venue"
},
  "geometry": {"coordinates":[-81.06564899999999,32.036364],"type":"Point"}
}