{
  "type": "Feature",
  "properties": {
    "iso:country":"US",
    "sg:address":"905 S Davis Rd",
    "sg:city":"Lagrange",
    "sg:classifiers":[
        {
            "category":"Organizations",
            "subcategory":"Community Association",
            "type":"Services"
        }
    ],
    "sg:phone":"+1 706 884 4181",
    "sg:postcode":"30241",
    "sg:province":"GA",
    "sg:tags":[
        "fraternal"
    ],
    "wof:name":"Elks Lodge",
    "wof:placetype":"venue"
},
  "geometry": {"coordinates":[-84.98787299999999,33.034109],"type":"Point"}
}