{
  "type": "Feature",
  "properties": {
    "addr:full":"3468 Winter Wood Ln Marietta GA 30062",
    "addr:housenumber":"3468",
    "addr:postcode":"30062",
    "addr:street":"Winter Wood Ln",
    "iso:country":"US",
    "sg:address":"3468 Winter Wood Ln",
    "sg:city":"Marietta",
    "sg:classifiers":[
        {
            "category":"Freight",
            "type":"Transportation"
        }
    ],
    "sg:phone":"+1 770 579 1229",
    "sg:postcode":"30062",
    "sg:province":"GA",
    "sg:tags":[
        "trucking"
    ],
    "wof:name":"Francis Transport",
    "wof:placetype":"venue"
},
  "geometry": {"coordinates":[-84.45450099999999,34.035085],"type":"Point"}
}