{
  "type": "Feature",
  "properties": {
    "iso:country":"US",
    "sg:address":"974 Yarborough Mill Rd SE",
    "sg:city":"Fairmount",
    "sg:classifiers":[
        {
            "category":"Professional",
            "type":"Services"
        }
    ],
    "sg:phone":"+1 706 629 5012",
    "sg:postcode":"30139",
    "sg:province":"GA",
    "wof:name":"Nora G Barton",
    "wof:placetype":"venue"
},
  "geometry": {"coordinates":[-84.78348,34.431398],"type":"Point"}
}