{
  "type": "Feature",
  "properties": {
    "iso:country":"US",
    "sg:address":"19 Johnston Cir",
    "sg:city":"Palmetto",
    "sg:classifiers":[
        {
            "category":"Wholesale",
            "subcategory":"Construction Materials",
            "type":"Manufacturing & Wholesale Goods"
        },
        {
            "category":"Home & Garden",
            "subcategory":"Building Materials",
            "type":"Retail Goods"
        }
    ],
    "sg:phone":"+1 770 463 1244",
    "sg:postcode":"30268",
    "sg:province":"GA",
    "sg:tags":[
        "sand",
        "gravel"
    ],
    "wof:name":"Sandbox Sand & Gravel",
    "wof:placetype":"venue"
},
  "geometry": {"coordinates":[-84.672389,33.500625],"type":"Point"}
}