{
  "type": "Feature",
  "properties": {
    "iso:country":"US",
    "sg:address":"535 Jesse Jewell Pkwy SE",
    "sg:city":"Gainesville",
    "sg:classifiers":[
        {
            "category":"Health Services",
            "subcategory":"Doctor",
            "type":"Services"
        }
    ],
    "sg:phone":"+1 770 534 1711",
    "sg:postcode":"30501",
    "sg:province":"GA",
    "sg:tags":[
        "physician",
        "surgeon",
        "eye"
    ],
    "wof:name":"North Georgia Eye Clinic PC",
    "wof:placetype":"venue"
},
  "geometry": {"coordinates":[-83.820382,34.299675],"type":"Point"}
}