{
  "type": "Feature",
  "properties": {
    "iso:country":"US",
    "sg:address":"4804 Roswell Rd NE",
    "sg:city":"Atlanta",
    "sg:classifiers":[
        {
            "category":"Social Services",
            "subcategory":"Retirement Home",
            "type":"Services"
        }
    ],
    "sg:phone":"+1 404 531 0145",
    "sg:postcode":"30342",
    "sg:province":"GA",
    "sg:website":"www.sunriseseniorliving.com",
    "wof:name":"Edenbrook of Buckhead",
    "wof:placetype":"venue"
},
  "geometry": {"coordinates":[-84.3815,33.8866],"type":"Point"}
}