{
  "type": "Feature",
  "properties": {
    "iso:country":"US",
    "sg:address":"990 Holcomb Bridge Rd",
    "sg:city":"Roswell",
    "sg:classifiers":[
        {
            "category":"Banks & Credit Unions",
            "subcategory":"Bank",
            "type":"Services"
        }
    ],
    "sg:phone":"+1 404 255 0922",
    "sg:postcode":"30076",
    "sg:province":"GA",
    "sg:tags":[
        "loan",
        "real estate"
    ],
    "wof:name":"Marketplace Financial LLC",
    "wof:placetype":"venue"
},
  "geometry": {"coordinates":[-84.334372,34.028036],"type":"Point"}
}