{
  "type": "Feature",
  "properties": {
    "iso:country":"US",
    "sg:address":"132 Maple St",
    "sg:city":"Carrollton",
    "sg:classifiers":[
        {
            "category":"Autos & Motor Vehicles",
            "subcategory":"Auto Supplies",
            "type":"Retail Goods"
        }
    ],
    "sg:phone":"+1 770 832 6364",
    "sg:postcode":"30117",
    "sg:province":"GA",
    "sg:tags":[
        "tire"
    ],
    "wof:name":"Goodyear",
    "wof:placetype":"venue"
},
  "geometry": {"coordinates":[-85.076956,33.579452],"type":"Point"}
}