{
  "type": "Feature",
  "properties": {
    "iso:country":"US",
    "sg:address":"937 Glynn St N",
    "sg:city":"Fayetteville",
    "sg:classifiers":[
        {
            "category":"Retail",
            "subcategory":"Auto Rental",
            "type":"Services"
        },
        {
            "category":"Building & Trades",
            "subcategory":"Equipment Rental",
            "type":"Services"
        },
        {
            "category":"Retail",
            "subcategory":"Storage",
            "type":"Services"
        }
    ],
    "sg:phone":"+1 770 461 9999",
    "sg:postcode":"30214",
    "sg:province":"GA",
    "sg:tags":[
        "renting",
        "moving-self",
        "leasing",
        "moving",
        "truck",
        "trailer"
    ],
    "sg:website":"http://www.pensketruckrental.com/",
    "wof:name":"Penske Truck Rental",
    "wof:placetype":"venue"
},
  "geometry": {"coordinates":[-84.45002599999999,33.463292],"type":"Point"}
}