{
  "type": "Feature",
  "properties": {
    "iso:country":"US",
    "sg:address":"1322 Wallace St",
    "sg:city":"Augusta",
    "sg:classifiers":[
        {
            "category":"Building & Trades",
            "subcategory":"Landscaping Services",
            "type":"Services"
        }
    ],
    "sg:phone":"+1 706 724 0884",
    "sg:postcode":"30901",
    "sg:province":"GA",
    "sg:tags":[
        "lawn",
        "maintenance",
        "grounds"
    ],
    "wof:name":"Biggers Enterprises",
    "wof:placetype":"venue"
},
  "geometry": {"coordinates":[-81.945331,33.45677],"type":"Point"}
}