{
  "type": "Feature",
  "properties": {
    "addr:full":"5770 Rives Dr Alpharetta GA 30004",
    "addr:housenumber":"5770",
    "addr:postcode":"30004",
    "addr:street":"Rives Dr",
    "iso:country":"US",
    "sg:address":"5770 Rives Dr",
    "sg:city":"Alpharetta",
    "sg:classifiers":[
        {
            "category":"Manufacturing",
            "subcategory":"Printing",
            "type":"Manufacturing & Wholesale Goods"
        }
    ],
    "sg:phone":"+1 678 325 2264",
    "sg:postcode":"30004",
    "sg:province":"GA",
    "sg:tags":[
        "publisher",
        "software"
    ],
    "sg:website":"www.verticalthought.com",
    "wof:name":"Vertical Thought",
    "wof:placetype":"venue"
},
  "geometry": {"coordinates":[-84.223434,34.130874],"type":"Point"}
}