{
  "type": "Feature",
  "properties": {
    "iso:country":"US",
    "sg:address":"5405 Mc Cullers Ln",
    "sg:city":"Loganville",
    "sg:classifiers":[
        {
            "category":"Building & Trades",
            "subcategory":"Construction",
            "type":"Services"
        }
    ],
    "sg:phone":"+1 770 466 8281",
    "sg:postcode":"30052",
    "sg:province":"GA",
    "sg:tags":[
        "house"
    ],
    "wof:name":"RAS Builders Of Georgia Inc",
    "wof:placetype":"venue"
},
  "geometry": {"coordinates":[-83.911169,33.7832],"type":"Point"}
}