{
  "type": "Feature",
  "properties": {
    "iso:country":"US",
    "sg:address":"218 River Dr",
    "sg:city":"Cartersville",
    "sg:classifiers":[
        {
            "category":"Manufacturing",
            "subcategory":"Textiles",
            "type":"Manufacturing & Wholesale Goods"
        }
    ],
    "sg:phone":"+1 770 382 7335",
    "sg:postcode":"30120",
    "sg:province":"GA",
    "sg:tags":[
        "mills",
        "yarn"
    ],
    "wof:name":"Cresent Extrusions",
    "wof:placetype":"venue"
},
  "geometry": {"coordinates":[-84.798633,34.144631],"type":"Point"}
}