{
  "type": "Feature",
  "properties": {
    "addr:full":"1409 N Highland Ave NE # 1 Atlanta GA 30306",
    "addr:housenumber":"1409",
    "addr:postcode":"30306",
    "addr:street":"N Highland Ave Ne # 1",
    "iso:country":"US",
    "sg:address":"1409 N Highland Ave NE # 1",
    "sg:city":"Atlanta",
    "sg:classifiers":[
        {
            "category":"Real Estate",
            "subcategory":"Real Estate Services",
            "type":"Services"
        },
        {
            "category":"Insurance",
            "subcategory":"Hazard Insurance",
            "type":"Services"
        },
        {
            "category":"Insurance",
            "subcategory":"Title Insurance",
            "type":"Services"
        }
    ],
    "sg:phone":"+1 404 876 2597",
    "sg:postcode":"30306",
    "sg:province":"GA",
    "sg:tags":[
        "mortgage"
    ],
    "wof:name":"Southeast Title Corporation",
    "wof:placetype":"venue"
},
  "geometry": {"coordinates":[-84.351679,33.793025],"type":"Point"}
}