{
  "type": "Feature",
  "properties": {
    "addr:full":"244 Pineview Rd Alma GA 31510",
    "addr:housenumber":"244",
    "addr:postcode":"31510",
    "addr:street":"Pineview Rd",
    "iso:country":"US",
    "sg:address":"244 Pineview Rd",
    "sg:city":"Alma",
    "sg:classifiers":[
        {
            "category":"Professional",
            "type":"Services"
        }
    ],
    "sg:phone":"+1 912 632 1409",
    "sg:postcode":"31510",
    "sg:province":"GA",
    "sg:tags":[
        "establishment"
    ],
    "wof:name":"UGA Post Harvest/Vegetable",
    "wof:placetype":"venue"
},
  "geometry": {"coordinates":[-82.513625,31.520262],"type":"Point"}
}