{
  "type": "Feature",
  "properties": {
    "iso:country":"US",
    "sg:address":"1701 Columbia Ave",
    "sg:city":"Atlanta",
    "sg:classifiers":[
        {
            "category":"Government",
            "subcategory":"Office",
            "type":"Public Place"
        }
    ],
    "sg:phone":"+1 404 305 5200",
    "sg:postcode":"30337",
    "sg:province":"GA",
    "sg:tags":[
        "transportation"
    ],
    "wof:name":"Regional Cnsl-Mnaging Attorney",
    "wof:placetype":"venue"
},
  "geometry": {"coordinates":[-84.442888,33.652273],"type":"Point"}
}