{
  "type": "Feature",
  "properties": {
    "iso:country":"US",
    "sg:address":"13 Wooddale Dr SW",
    "sg:city":"Cartersville",
    "sg:classifiers":[
        {
            "category":"Professional",
            "subcategory":"Business Services",
            "type":"Services"
        }
    ],
    "sg:phone":"+1 770 607 0443",
    "sg:postcode":"30120",
    "sg:province":"GA",
    "wof:name":"Holcombe Home Inspection",
    "wof:placetype":"venue"
},
  "geometry": {"coordinates":[-84.849856,34.210345],"type":"Point"}
}