{
  "type": "Feature",
  "properties": {
    "addr:full":"8040 Fieldstone Ct Douglasville GA 30134",
    "addr:housenumber":"8040",
    "addr:postcode":"30134",
    "addr:street":"Fieldstone Ct",
    "iso:country":"US",
    "sg:address":"8040 Fieldstone Ct",
    "sg:city":"Douglasville",
    "sg:classifiers":[
        {
            "category":"Restaurant",
            "type":"Food & Drink"
        }
    ],
    "sg:phone":"+1 215 432 1338",
    "sg:postcode":"30134",
    "sg:province":"GA",
    "sg:tags":[
        "american"
    ],
    "wof:name":"Philly Grilled Cheesesteaks",
    "wof:placetype":"venue"
},
  "geometry": {"coordinates":[-84.72367300000001,33.760876],"type":"Point"}
}