{
  "type": "Feature",
  "properties": {
    "iso:country":"US",
    "sg:address":"255 Southers Cir",
    "sg:city":"Suwanee",
    "sg:classifiers":[
        {
            "category":"Professional",
            "subcategory":"Management & Consulting",
            "type":"Services"
        }
    ],
    "sg:phone":"+1 678 455 9148",
    "sg:postcode":"30024",
    "sg:province":"GA",
    "sg:tags":[
        "consultant",
        "resource",
        "human"
    ],
    "wof:name":"Carciba Business Svc",
    "wof:placetype":"venue"
},
  "geometry": {"coordinates":[-84.11169200000001,34.099833],"type":"Point"}
}