{
  "type": "Feature",
  "properties": {
    "addr:full":"4382 Ball Ground Hwy Canton GA 30114",
    "addr:housenumber":"4382",
    "addr:postcode":"30114",
    "addr:street":"Ball Ground Hwy",
    "iso:country":"US",
    "sg:address":"4382 Ball Ground Hwy",
    "sg:city":"Canton",
    "sg:classifiers":[
        {
            "category":"Farming",
            "subcategory":"Dairy Farm",
            "type":"Manufacturing & Wholesale Goods"
        }
    ],
    "sg:phone":"+1 770 720 1317",
    "sg:postcode":"30114",
    "sg:province":"GA",
    "wof:name":"Gene Wheeler Farm",
    "wof:placetype":"venue"
},
  "geometry": {"coordinates":[-84.43498599999999,34.285471],"type":"Point"}
}