{
  "type": "Feature",
  "properties": {
    "iso:country":"US",
    "sg:address":"3370 Pio Nono Ave",
    "sg:city":"Macon",
    "sg:classifiers":[
        {
            "category":"Shopping",
            "subcategory":"Florist",
            "type":"Retail Goods"
        }
    ],
    "sg:phone":"+1 478 788 5446",
    "sg:postcode":"31206",
    "sg:province":"GA",
    "wof:name":"An Fran's Flowers & Gift Shop",
    "wof:placetype":"venue"
},
  "geometry": {"coordinates":[-83.66345200000001,32.802422],"type":"Point"}
}