{
  "type": "Feature",
  "properties": {
    "addr:full":"1915 Hilton Ave Columbus GA 31906",
    "addr:housenumber":"1915",
    "addr:postcode":"31906",
    "addr:street":"Hilton Ave",
    "iso:country":"US",
    "sg:address":"1915 Hilton Ave",
    "sg:city":"Columbus",
    "sg:classifiers":[
        {
            "category":"Professional",
            "subcategory":"Business Services",
            "type":"Services"
        }
    ],
    "sg:phone":"+1 706 327 4653",
    "sg:postcode":"31906",
    "sg:province":"GA",
    "wof:name":"Joan Yoe Interiors",
    "wof:placetype":"venue"
},
  "geometry": {"coordinates":[-84.956126,32.481821],"type":"Point"}
}