{
  "type": "Feature",
  "properties": {
    "iso:country":"US",
    "sg:address":"1985 Holcomb Bridge Rd",
    "sg:city":"Roswell",
    "sg:classifiers":[
        {
            "category":"Personal",
            "subcategory":"Beauty Salon",
            "type":"Services"
        }
    ],
    "sg:phone":"+1 770 645 2777",
    "sg:postcode":"30022",
    "sg:province":"GA",
    "sg:tags":[
        "shop"
    ],
    "wof:name":"Rosie Nails",
    "wof:placetype":"venue"
},
  "geometry": {"coordinates":[-84.29943299999999,34.00801],"type":"Point"}
}