{
  "type": "Feature",
  "properties": {
    "iso:country":"US",
    "sg:address":"122 Hidden Valley Rd",
    "sg:city":"Fayetteville",
    "sg:classifiers":[
        {
            "category":"Professional",
            "type":"Services"
        }
    ],
    "sg:phone":"+1 770 461 1189",
    "sg:postcode":"30214",
    "sg:province":"GA",
    "wof:name":"RLB Conceptual Desig",
    "wof:placetype":"venue"
},
  "geometry": {"coordinates":[-84.43838100000001,33.468119],"type":"Point"}
}