{
  "type": "Feature",
  "properties": {
    "addr:full":"1075 Pio Nono Ave Macon GA 31204",
    "addr:housenumber":"1075",
    "addr:postcode":"31204",
    "addr:street":"Pio Nono Ave",
    "iso:country":"US",
    "sg:address":"1075 Pio Nono Ave",
    "sg:city":"Macon",
    "sg:classifiers":[
        {
            "category":"Health Services",
            "subcategory":"Doctor",
            "type":"Services"
        }
    ],
    "sg:phone":"+1 478 743 5402",
    "sg:postcode":"31204",
    "sg:province":"GA",
    "sg:tags":[
        "medical"
    ],
    "wof:name":"Henry T Clay MD",
    "wof:placetype":"venue"
},
  "geometry": {"coordinates":[-83.662588,32.836679],"type":"Point"}
}