{
  "type": "Feature",
  "properties": {
    "iso:country":"US",
    "sg:address":"720 Rosehill Ln SW",
    "sg:city":"Lawrenceville",
    "sg:classifiers":[
        {
            "category":"Retail",
            "subcategory":"Repair Shop",
            "type":"Services"
        }
    ],
    "sg:phone":"+1 770 979 2712",
    "sg:postcode":"30044",
    "sg:province":"GA",
    "wof:name":"Cult TV Man",
    "wof:placetype":"venue"
},
  "geometry": {"coordinates":[-84.04700200000001,33.90127],"type":"Point"}
}