{
  "type": "Feature",
  "properties": {
    "addr:full":"3572 Strathmore Dr Duluth GA 30096",
    "addr:housenumber":"3572",
    "addr:postcode":"30096",
    "addr:street":"Strathmore Dr",
    "iso:country":"US",
    "sg:address":"3572 Strathmore Dr",
    "sg:city":"Duluth",
    "sg:classifiers":[
        {
            "category":"Utilities",
            "subcategory":"Mobile Phone",
            "type":"Services"
        }
    ],
    "sg:phone":"+1 770 495 3747",
    "sg:postcode":"30096",
    "sg:province":"GA",
    "sg:tags":[
        "telephone",
        "cellular"
    ],
    "wof:name":"Cellcom International Inc",
    "wof:placetype":"venue"
},
  "geometry": {"coordinates":[-84.15191299999999,34.00442],"type":"Point"}
}