{
  "type": "Feature",
  "properties": {
    "iso:country":"US",
    "sg:address":"2328 Campbellton Rd SW",
    "sg:city":"Atlanta",
    "sg:classifiers":[
        {
            "category":"Social Services",
            "subcategory":"Child Care",
            "type":"Services"
        }
    ],
    "sg:phone":"+1 404 346 7022",
    "sg:postcode":"30311",
    "sg:province":"GA",
    "wof:name":"Murphy's Child Care",
    "wof:placetype":"venue"
},
  "geometry": {"coordinates":[-84.458155,33.706091],"type":"Point"}
}