{
  "type": "Feature",
  "properties": {
    "iso:country":"US",
    "sg:address":"4929 Jonesboro Rd",
    "sg:city":"Forest Park",
    "sg:classifiers":[
        {
            "category":"Retail",
            "subcategory":"Pet Boarding",
            "type":"Services"
        }
    ],
    "sg:phone":"+1 404 363 2667",
    "sg:postcode":"30297",
    "sg:province":"GA",
    "sg:tags":[
        "boarding/pet",
        "sitting"
    ],
    "wof:name":"Wendy's Pet Grooming",
    "wof:placetype":"venue"
},
  "geometry": {"coordinates":[-84.351799,33.6203],"type":"Point"}
}