{
  "type": "Feature",
  "properties": {
    "addr:full":"875 Mansell Rd Roswell GA 30076",
    "addr:housenumber":"875",
    "addr:postcode":"30076",
    "addr:street":"Mansell Rd",
    "iso:country":"US",
    "sg:address":"875 Mansell Rd",
    "sg:city":"Roswell",
    "sg:classifiers":[
        {
            "category":"Building & Trades",
            "subcategory":"Locksmith",
            "type":"Services"
        }
    ],
    "sg:phone":"+1 770 884 1459",
    "sg:postcode":"30076",
    "sg:province":"GA",
    "sg:tags":[
        "key"
    ],
    "wof:name":"777 Emergency Locksmith",
    "wof:placetype":"venue"
},
  "geometry": {"coordinates":[-84.338747,34.042673],"type":"Point"}
}