{
  "type": "Feature",
  "properties": {
    "addr:full":"5145 Cook St NE Covington GA 30014",
    "addr:housenumber":"5145",
    "addr:postcode":"30014",
    "addr:street":"Cook St Ne",
    "iso:country":"US",
    "sg:address":"5145 Cook St NE",
    "sg:city":"Covington",
    "sg:classifiers":[
        {
            "category":"Insurance",
            "subcategory":"Insurance Agent",
            "type":"Services"
        },
        {
            "category":"Insurance",
            "subcategory":"Hazard Insurance",
            "type":"Services"
        }
    ],
    "sg:phone":"+1 770 786 1755",
    "sg:postcode":"30014",
    "sg:province":"GA",
    "sg:tags":[
        "auto",
        "recreational",
        "motorcycle",
        "vehicle",
        "marine",
        "boat"
    ],
    "sg:website":"http://www.lordandassociatesins.com",
    "wof:name":"Lord & Associates Insurance",
    "wof:placetype":"venue"
},
  "geometry": {"coordinates":[-83.845004,33.600637],"type":"Point"}
}