{
  "type": "Feature",
  "properties": {
    "addr:full":"3 Government Plz Rome GA 30161",
    "addr:housenumber":"3",
    "addr:postcode":"ga 30161",
    "addr:street":"Government Plz",
    "iso:country":"US",
    "sg:address":"3 Government Plz",
    "sg:city":"Rome",
    "sg:classifiers":[
        {
            "category":"Government",
            "subcategory":"Office",
            "type":"Public Place"
        }
    ],
    "sg:phone":"+1 706 291 5156",
    "sg:postcode":"30161",
    "sg:province":"GA",
    "sg:tags":[
        "resource",
        "human"
    ],
    "wof:name":"Human Resource Department",
    "wof:placetype":"venue"
},
  "geometry": {"coordinates":[-85.212114,34.168606],"type":"Point"}
}