{
  "type": "Feature",
  "properties": {
    "iso:country":"US",
    "sg:address":"1012 Academy Ave",
    "sg:city":"Dublin",
    "sg:classifiers":[
        {
            "category":"Shopping",
            "type":"Retail Goods"
        }
    ],
    "sg:phone":"+1 478 296 1622",
    "sg:postcode":"31021",
    "sg:province":"GA",
    "sg:tags":[
        "picture",
        "frame",
        "merchandise"
    ],
    "wof:name":"Southerlees",
    "wof:placetype":"venue"
},
  "geometry": {"coordinates":[-82.91456100000001,32.533114],"type":"Point"}
}