{
  "type": "Feature",
  "properties": {
    "iso:country":"US",
    "sg:address":"865 Sandtown Rd SW",
    "sg:city":"Marietta",
    "sg:classifiers":[
        {
            "category":"Retail",
            "subcategory":"Repair Shop",
            "type":"Services"
        }
    ],
    "sg:phone":"+1 770 423 9055",
    "sg:postcode":"30008",
    "sg:province":"GA",
    "sg:tags":[
        "welding"
    ],
    "wof:name":"Kwik's Welding Svc",
    "wof:placetype":"venue"
},
  "geometry": {"coordinates":[-84.554869,33.929026],"type":"Point"}
}