{
  "type": "Feature",
  "properties": {
    "iso:country":"US",
    "sg:address":"4054 Deans Bridge Rd",
    "sg:city":"Hephzibah",
    "sg:classifiers":[
        {
            "category":"Manufacturing",
            "subcategory":"Tools & Machinery",
            "type":"Manufacturing & Wholesale Goods"
        }
    ],
    "sg:phone":"+1 706 796 6729",
    "sg:postcode":"30815",
    "sg:province":"GA",
    "sg:tags":[
        "farm",
        "equipment"
    ],
    "wof:name":"Jim's Tractor & Implement Supl",
    "wof:placetype":"venue"
},
  "geometry": {"coordinates":[-82.121673,33.388123],"type":"Point"}
}