{
  "type": "Feature",
  "properties": {
    "addr:full":"344 Hollywood Cir Gainesville GA 30501",
    "addr:housenumber":"344",
    "addr:postcode":"30501",
    "addr:street":"Hollywood Cir",
    "iso:country":"US",
    "sg:address":"344 Hollywood Cir",
    "sg:city":"Gainesville",
    "sg:classifiers":[
        {
            "category":"Social Services",
            "type":"Services"
        }
    ],
    "sg:phone":"+1 770 535 6538",
    "sg:postcode":"30501",
    "sg:province":"GA",
    "wof:name":"Babies Inside & Out Inc",
    "wof:placetype":"venue"
},
  "geometry": {"coordinates":[-83.839901,34.320994],"type":"Point"}
}