{
  "type": "Feature",
  "properties": {
    "iso:country":"US",
    "sg:address":"104 Gardenwood Dr",
    "sg:city":"Atlanta",
    "sg:classifiers":[
        {
            "category":"Professional",
            "type":"Services"
        }
    ],
    "sg:phone":"+1 770 994 2067",
    "sg:postcode":"30349",
    "sg:province":"GA",
    "wof:name":"HBS Svc",
    "wof:placetype":"venue"
},
  "geometry": {"coordinates":[-84.426209,33.596972],"type":"Point"}
}