{
  "type": "Feature",
  "properties": {
    "addr:full":"137 Sumer Ln Douglasville GA 30134",
    "addr:housenumber":"137",
    "addr:postcode":"30134",
    "addr:street":"Sumer Ln",
    "iso:country":"US",
    "sg:address":"137 Sumer Ln",
    "sg:city":"Douglasville",
    "sg:classifiers":[
        {
            "category":"Professional",
            "type":"Services"
        }
    ],
    "sg:phone":"+1 770 489 1774",
    "sg:postcode":"30134",
    "sg:province":"GA",
    "wof:name":"James G Davis",
    "wof:placetype":"venue"
},
  "geometry": {"coordinates":[-84.788718,33.789848],"type":"Point"}
}