{
  "type": "Feature",
  "properties": {
    "addr:full":"817 US Hwy 17 Midway GA 31320",
    "addr:housenumber":"817",
    "addr:postcode":"31320",
    "addr:street":"Us Hwy 17",
    "iso:country":"US",
    "sg:address":"817 US Hwy 17",
    "sg:city":"Midway",
    "sg:classifiers":[
        {
            "category":"Restaurant",
            "type":"Food & Drink"
        }
    ],
    "sg:phone":"+1 912 884 3388",
    "sg:postcode":"31320",
    "sg:province":"GA",
    "wof:name":"Ida Mae & Joe's North Midway",
    "wof:placetype":"venue"
},
  "geometry": {"coordinates":[-81.43557699999999,31.787623],"type":"Point"}
}