{
  "type": "Feature",
  "properties": {
    "addr:full":"260 Connemara Dr NE Marietta GA 30067",
    "addr:housenumber":"260",
    "addr:postcode":"30067",
    "addr:street":"Connemara Dr Ne",
    "iso:country":"US",
    "sg:address":"260 Connemara Dr NE",
    "sg:city":"Marietta",
    "sg:classifiers":[
        {
            "category":"Professional",
            "subcategory":"Art Services",
            "type":"Services"
        }
    ],
    "sg:phone":"+1 678 361 5309",
    "sg:postcode":"30067",
    "sg:province":"GA",
    "sg:tags":[
        "commercial",
        "design"
    ],
    "wof:name":"Turning Leaf Design",
    "wof:placetype":"venue"
},
  "geometry": {"coordinates":[-84.418274,33.954561],"type":"Point"}
}