{
  "type": "Feature",
  "properties": {
    "addr:full":"2 E Bryan St Savannah GA 31401",
    "addr:housenumber":"2",
    "addr:postcode":"31401",
    "addr:street":"E Bryan St",
    "iso:country":"US",
    "sg:address":"2 E Bryan St",
    "sg:city":"Savannah",
    "sg:classifiers":[
        {
            "category":"Social Services",
            "type":"Services"
        }
    ],
    "sg:phone":"+1 912 790 7822",
    "sg:postcode":"31401",
    "sg:province":"GA",
    "sg:tags":[
        "organization",
        "welfare"
    ],
    "wof:name":"Junior Achievement Of Ga",
    "wof:placetype":"venue"
},
  "geometry": {"coordinates":[-81.0909,32.080095],"type":"Point"}
}