{
  "type": "Feature",
  "properties": {
    "addr:full":"1348 Southlake Plaza Dr Morrow GA 30260",
    "addr:housenumber":"1348",
    "addr:postcode":"30260",
    "addr:street":"Southlake Plaza Dr",
    "iso:country":"US",
    "sg:address":"1348 Southlake Plaza Dr",
    "sg:city":"Morrow",
    "sg:classifiers":[
        {
            "category":"Travel",
            "subcategory":"Hotels & Motels",
            "type":"Entertainment"
        }
    ],
    "sg:phone":"+1 770 968 1483",
    "sg:postcode":"30260",
    "sg:province":"GA",
    "sg:website":"www.redroof.com",
    "wof:name":"Red Roof Inns",
    "wof:placetype":"venue"
},
  "geometry": {"coordinates":[-84.34610000000001,33.5784],"type":"Point"}
}