{
  "type": "Feature",
  "properties": {
    "addr:full":"4001 Horseshoe Rd Augusta GA 30907",
    "addr:housenumber":"4001",
    "addr:postcode":"30907",
    "addr:street":"Horseshoe Rd",
    "iso:country":"US",
    "sg:address":"4001 Horseshoe Rd",
    "sg:city":"Augusta",
    "sg:classifiers":[
        {
            "category":"Shopping",
            "subcategory":"Gifts & Souvenirs",
            "type":"Retail Goods"
        }
    ],
    "sg:phone":"+1 706 863 2715",
    "sg:postcode":"30907",
    "sg:province":"GA",
    "wof:name":"Creations By Jean",
    "wof:placetype":"venue"
},
  "geometry": {"coordinates":[-82.10615799999999,33.513219],"type":"Point"}
}