{
  "type": "Feature",
  "properties": {
    "iso:country":"US",
    "sg:address":"2555 Delk Rd SE",
    "sg:city":"Marietta",
    "sg:classifiers":[
        {
            "category":"Restaurant",
            "type":"Food & Drink"
        }
    ],
    "sg:phone":"+1 770 955 5740",
    "sg:postcode":"30067",
    "sg:province":"GA",
    "sg:tags":[
        "asian",
        "chinese",
        "pan"
    ],
    "wof:name":"Import Zone",
    "wof:placetype":"venue"
},
  "geometry": {"coordinates":[-84.47834,33.922661],"type":"Point"}
}