{
  "type": "Feature",
  "properties": {
    "addr:full":"47 Hannah Dr Rossville GA 30728",
    "addr:housenumber":"47",
    "addr:postcode":"30728",
    "addr:street":"Hannah Dr",
    "iso:country":"US",
    "sg:address":"47 Hannah Dr",
    "sg:city":"Rossville",
    "sg:classifiers":[
        {
            "category":"Utilities",
            "subcategory":"Refuse",
            "type":"Services"
        }
    ],
    "sg:phone":"+1 706 861 6070",
    "sg:postcode":"30728",
    "sg:province":"GA",
    "sg:tags":[
        "system"
    ],
    "wof:name":"R TI of Nevada Inc",
    "wof:placetype":"venue"
},
  "geometry": {"coordinates":[-85.070257,34.697527],"type":"Point"}
}