{
  "type": "Feature",
  "properties": {
    "iso:country":"US",
    "sg:address":"754 Juniper St NE",
    "sg:city":"Atlanta",
    "sg:classifiers":[
        {
            "category":"Professional",
            "subcategory":"Business Services",
            "type":"Services"
        }
    ],
    "sg:phone":"+1 404 876 2976",
    "sg:postcode":"30308",
    "sg:province":"GA",
    "sg:tags":[
        "equipment",
        "appraisal",
        "machinery"
    ],
    "wof:name":"Campbell & Associates",
    "wof:placetype":"venue"
},
  "geometry": {"coordinates":[-84.383087,33.775386],"type":"Point"}
}