{
  "type": "Feature",
  "properties": {
    "addr:full":"107 Hickory Grove Ln Savannah GA 31405",
    "addr:housenumber":"107",
    "addr:postcode":"31405",
    "addr:street":"Hickory Grove Ln",
    "iso:country":"US",
    "sg:address":"107 Hickory Grove Ln",
    "sg:city":"Savannah",
    "sg:classifiers":[
        {
            "category":"Social Services",
            "subcategory":"Retirement Home",
            "type":"Services"
        }
    ],
    "sg:phone":"+1 912 232 2302",
    "sg:postcode":"31405",
    "sg:province":"GA",
    "sg:tags":[
        "convalescent",
        "nursing"
    ],
    "wof:name":"Eldercare Management Of Coastal Georgia",
    "wof:placetype":"venue"
},
  "geometry": {"coordinates":[-81.217991,32.063892],"type":"Point"}
}