{
  "type": "Feature",
  "properties": {
    "iso:country":"US",
    "sg:address":"688 Bahn Innsbruck",
    "sg:city":"Helen",
    "sg:classifiers":[
        {
            "category":"Organizations",
            "subcategory":"Community Association",
            "type":"Services"
        }
    ],
    "sg:phone":"+1 706 878 0110",
    "sg:postcode":"30545",
    "sg:province":"GA",
    "sg:tags":[
        "club"
    ],
    "wof:name":"Innsbruck Poa Club House",
    "wof:placetype":"venue"
},
  "geometry": {"coordinates":[-83.714623,34.705985],"type":"Point"}
}