{
  "type": "Feature",
  "properties": {
    "addr:full":"4833 Lee Rd Gainesville GA 30506",
    "addr:housenumber":"4833",
    "addr:postcode":"30506",
    "addr:street":"Lee Rd",
    "iso:country":"US",
    "sg:address":"4833 Lee Rd",
    "sg:city":"Gainesville",
    "sg:classifiers":[
        {
            "category":"Professional",
            "subcategory":"Accounting & Tax Preparation",
            "type":"Services"
        }
    ],
    "sg:phone":"+1 770 536 4919",
    "sg:postcode":"30506",
    "sg:province":"GA",
    "wof:name":"Smith Accounting Tax",
    "wof:placetype":"venue"
},
  "geometry": {"coordinates":[-83.893917,34.399933],"type":"Point"}
}