{
  "type": "Feature",
  "properties": {
    "iso:country":"US",
    "sg:address":"7197 Buford Hwy NE",
    "sg:city":"Atlanta",
    "sg:classifiers":[
        {
            "category":"Retail",
            "subcategory":"Auto Repair",
            "type":"Services"
        }
    ],
    "sg:phone":"+1 770 449 0000",
    "sg:postcode":"30340",
    "sg:province":"GA",
    "sg:tags":[
        "body",
        "painting",
        "repairing",
        "automobile"
    ],
    "wof:name":"Min Pak",
    "wof:placetype":"venue"
},
  "geometry": {"coordinates":[-84.25764599999999,33.918594],"type":"Point"}
}