{
  "type": "Feature",
  "properties": {
    "addr:full":"121 Myers Plantation Rd Brunswick GA 31523",
    "addr:housenumber":"121",
    "addr:postcode":"31523",
    "addr:street":"Myers Plantation Rd",
    "iso:country":"US",
    "sg:address":"121 Myers Plantation Rd",
    "sg:city":"Brunswick",
    "sg:classifiers":[
        {
            "category":"Food & Beverages",
            "subcategory":"Groceries & Convenience Stores",
            "type":"Retail Goods"
        }
    ],
    "sg:phone":"+1 912 264 1807",
    "sg:postcode":"31523",
    "sg:province":"GA",
    "wof:name":"Wja Inc",
    "wof:placetype":"venue"
},
  "geometry": {"coordinates":[-81.60557799999999,31.194864],"type":"Point"}
}