{
  "type": "Feature",
  "properties": {
    "iso:country":"US",
    "sg:address":"909 W Peachtree Street NW",
    "sg:city":"Atlanta",
    "sg:classifiers":[
        {
            "category":"Arts & Performance",
            "subcategory":"Art Gallery",
            "type":"Entertainment"
        }
    ],
    "sg:phone":"+1 404 874 8047",
    "sg:postcode":"30309",
    "sg:province":"GA",
    "wof:name":"International Art Collaboration",
    "wof:placetype":"venue"
},
  "geometry": {"coordinates":[-84.38806,33.781474],"type":"Point"}
}