{
  "type": "Feature",
  "properties": {
    "iso:country":"US",
    "sg:address":"1412 Baytree Rd",
    "sg:city":"Valdosta",
    "sg:classifiers":[
        {
            "category":"Shopping",
            "subcategory":"Florist",
            "type":"Retail Goods"
        }
    ],
    "sg:phone":"+1 229 242 2026",
    "sg:postcode":"31602",
    "sg:province":"GA",
    "wof:name":"Irbys Flowers Inc",
    "wof:placetype":"venue"
},
  "geometry": {"coordinates":[-83.311369,30.84702],"type":"Point"}
}