{
  "type": "Feature",
  "properties": {
    "addr:full":"2228 Cobb Creek Dr Decatur GA 30032",
    "addr:housenumber":"2228",
    "addr:postcode":"30032",
    "addr:street":"Cobb Creek Dr",
    "iso:country":"US",
    "sg:address":"2228 Cobb Creek Dr",
    "sg:city":"Decatur",
    "sg:classifiers":[
        {
            "category":"Social Services",
            "type":"Services"
        }
    ],
    "sg:phone":"+1 404 284 8799",
    "sg:postcode":"30032",
    "sg:province":"GA",
    "sg:tags":[
        "child",
        "institution",
        "care"
    ],
    "wof:name":"Hands Hlping Hnds Outreach Inc",
    "wof:placetype":"venue"
},
  "geometry": {"coordinates":[-84.241715,33.723641],"type":"Point"}
}