{
  "type": "Feature",
  "properties": {
    "addr:full":"5365 Little Mill Rd Buford GA 30518",
    "addr:housenumber":"5365",
    "addr:postcode":"30518",
    "addr:street":"Little Mill Rd",
    "iso:country":"US",
    "sg:address":"5365 Little Mill Rd",
    "sg:city":"Buford",
    "sg:classifiers":[
        {
            "category":"Building & Trades",
            "subcategory":"Construction",
            "type":"Services"
        }
    ],
    "sg:phone":"+1 770 945 4996",
    "sg:postcode":"30518",
    "sg:province":"GA",
    "sg:tags":[
        "concrete",
        "contractor"
    ],
    "wof:name":"R&J Construction",
    "wof:placetype":"venue"
},
  "geometry": {"coordinates":[-84.02273599999999,34.126129],"type":"Point"}
}