{
  "type": "Feature",
  "properties": {
    "addr:full":"3874 E Ponce De Leon Ave Clarkston GA 30021",
    "addr:housenumber":"3874",
    "addr:postcode":"30021",
    "addr:street":"E Ponce De Leon Ave",
    "iso:country":"US",
    "sg:address":"3874 E Ponce De Leon Ave",
    "sg:city":"Clarkston",
    "sg:classifiers":[
        {
            "category":"Autos & Motor Vehicles",
            "subcategory":"Fuel & Gas Station",
            "type":"Retail Goods"
        }
    ],
    "sg:postcode":"30021",
    "sg:province":"GA",
    "wof:name":"Texaco Food Mart",
    "wof:placetype":"venue"
},
  "geometry": {"coordinates":[-84.248874,33.803228],"type":"Point"}
}