{
  "type": "Feature",
  "properties": {
    "addr:full":"501 S Midway Rd Cordele GA 31015",
    "addr:housenumber":"501",
    "addr:postcode":"31015",
    "addr:street":"S Midway Rd",
    "iso:country":"US",
    "sg:address":"501 S Midway Rd",
    "sg:city":"Cordele",
    "sg:classifiers":[
        {
            "category":"Home & Garden",
            "subcategory":"Building Materials",
            "type":"Retail Goods"
        }
    ],
    "sg:phone":"+1 229 276 1928",
    "sg:postcode":"31015",
    "sg:province":"GA",
    "sg:tags":[
        "modular"
    ],
    "sg:website":"www.heartlandsystems.com",
    "wof:name":"Heartland Building Systems",
    "wof:placetype":"venue"
},
  "geometry": {"coordinates":[-83.745863,31.959023],"type":"Point"}
}