{
  "type": "Feature",
  "properties": {
    "addr:full":"832 Old Powder Springs Rd SW Mableton GA 30126",
    "addr:housenumber":"832",
    "addr:postcode":"30126",
    "addr:street":"Old Powder Springs Rd Sw",
    "iso:country":"US",
    "sg:address":"832 Old Powder Springs Rd SW",
    "sg:city":"Mableton",
    "sg:classifiers":[
        {
            "category":"Social Services",
            "subcategory":"Child Care",
            "type":"Services"
        }
    ],
    "sg:phone":"+1 770 941 6596",
    "sg:postcode":"30126",
    "sg:province":"GA",
    "sg:tags":[
        "day"
    ],
    "wof:name":"River Oaks Day Care Inc",
    "wof:placetype":"venue"
},
  "geometry": {"coordinates":[-84.57966399999999,33.810684],"type":"Point"}
}