{
  "type": "Feature",
  "properties": {
    "addr:full":"560 Cambridge Way NE Atlanta GA 30328",
    "addr:housenumber":"560",
    "addr:postcode":"30328",
    "addr:street":"Cambridge Way Ne",
    "iso:country":"US",
    "sg:address":"560 Cambridge Way NE",
    "sg:city":"Atlanta",
    "sg:classifiers":[
        {
            "category":"Health Services",
            "subcategory":"Doctor",
            "type":"Services"
        },
        {
            "category":"Health Services",
            "subcategory":"Hospital",
            "type":"Services"
        }
    ],
    "sg:phone":"+1 770 394 2221",
    "sg:postcode":"30328",
    "sg:province":"GA",
    "sg:tags":[
        "nursing",
        "consultant",
        "medical",
        "practice",
        "home"
    ],
    "wof:name":"Craig Honaman",
    "wof:placetype":"venue"
},
  "geometry": {"coordinates":[-84.37357900000001,33.957835],"type":"Point"}
}