{
  "type": "Feature",
  "properties": {
    "addr:full":"580 Kenneth Gay Dr Kingsland GA 31548",
    "addr:housenumber":"580",
    "addr:postcode":"31548",
    "addr:street":"Kenneth Gay Dr",
    "iso:country":"US",
    "sg:address":"580 Kenneth Gay Dr",
    "sg:city":"Kingsland",
    "sg:classifiers":[
        {
            "category":"Real Estate",
            "subcategory":"Real Estate Agent",
            "type":"Services"
        }
    ],
    "sg:phone":"+1 912 729 2266",
    "sg:postcode":"31548",
    "sg:province":"GA",
    "sg:website":"http://www.erakingsbay.com",
    "wof:name":"Era",
    "wof:placetype":"venue"
},
  "geometry": {"coordinates":[-81.638569,30.783894],"type":"Point"}
}