{
  "type": "Feature",
  "properties": {
    "iso:country":"US",
    "sg:address":"2725 Jones Mill Rd",
    "sg:city":"Atlanta",
    "sg:classifiers":[
        {
            "category":"Manufacturing",
            "subcategory":"Glass & Minerals",
            "type":"Manufacturing & Wholesale Goods"
        }
    ],
    "sg:phone":"+1 770 447 4841",
    "sg:postcode":"30360",
    "sg:province":"GA",
    "sg:tags":[
        "ready"
    ],
    "wof:name":"Thomas Concrete",
    "wof:placetype":"venue"
},
  "geometry": {"coordinates":[-84.24348500000001,33.932189],"type":"Point"}
}