{
  "type": "Feature",
  "properties": {
    "addr:full":"5505 Buck Hollow Dr Alpharetta GA 30005",
    "addr:housenumber":"5505",
    "addr:postcode":"30005",
    "addr:street":"Buck Hollow Dr",
    "iso:country":"US",
    "sg:address":"5505 Buck Hollow Dr",
    "sg:city":"Alpharetta",
    "sg:classifiers":[
        {
            "category":"Professional",
            "subcategory":"Research",
            "type":"Services"
        }
    ],
    "sg:phone":"+1 770 889 9424",
    "sg:postcode":"30005",
    "sg:province":"GA",
    "sg:tags":[
        "nonphysical",
        "commercial"
    ],
    "wof:name":"March Group Lllp",
    "wof:placetype":"venue"
},
  "geometry": {"coordinates":[-84.170421,34.080735],"type":"Point"}
}