{
  "type": "Feature",
  "properties": {
    "addr:full":"2610 Old Hickory Dr NW Marietta GA 30064",
    "addr:housenumber":"2610",
    "addr:postcode":"30064",
    "addr:street":"Old Hickory Dr Nw",
    "iso:country":"US",
    "sg:address":"2610 Old Hickory Dr NW",
    "sg:city":"Marietta",
    "sg:classifiers":[
        {
            "category":"Building & Trades",
            "subcategory":"Construction",
            "type":"Services"
        }
    ],
    "sg:phone":"+1 770 422 8988",
    "sg:postcode":"30064",
    "sg:province":"GA",
    "sg:tags":[
        "manufactured",
        "housing-communities"
    ],
    "wof:name":"White Oak Estates",
    "wof:placetype":"venue"
},
  "geometry": {"coordinates":[-84.627774,33.965423],"type":"Point"}
}