{
  "type": "Feature",
  "properties": {
    "addr:full":"3625 Mayfair Ln Albany GA 31721",
    "addr:housenumber":"3625",
    "addr:postcode":"31721",
    "addr:street":"Mayfair Ln",
    "iso:country":"US",
    "sg:address":"3625 Mayfair Ln",
    "sg:city":"Albany",
    "sg:classifiers":[
        {
            "category":"Professional",
            "type":"Services"
        }
    ],
    "sg:phone":"+1 229 446 2682",
    "sg:postcode":"31721",
    "sg:province":"GA",
    "wof:name":"Chris Colburn",
    "wof:placetype":"venue"
},
  "geometry": {"coordinates":[-84.242231,31.597185],"type":"Point"}
}