{
  "type": "Feature",
  "properties": {
    "addr:full":"3575 Ontario Ct Buford GA 30519",
    "addr:housenumber":"3575",
    "addr:postcode":"30519",
    "addr:street":"Ontario Ct",
    "iso:country":"US",
    "sg:address":"3575 Ontario Ct",
    "sg:city":"Buford",
    "sg:classifiers":[
        {
            "category":"Building & Trades",
            "subcategory":"Landscaping Services",
            "type":"Services"
        }
    ],
    "sg:phone":"+1 770 932 7787",
    "sg:postcode":"30519",
    "sg:province":"GA",
    "sg:tags":[
        "landscape"
    ],
    "wof:name":"Good Earth",
    "wof:placetype":"venue"
},
  "geometry": {"coordinates":[-83.993872,34.075023],"type":"Point"}
}