{
  "type": "Feature",
  "properties": {
    "addr:full":"140 Ayers Driver Rd Villa Rica GA 30180",
    "addr:housenumber":"140",
    "addr:postcode":"30180",
    "addr:street":"Ayers Driver Rd",
    "iso:country":"US",
    "sg:address":"140 Ayers Driver Rd",
    "sg:city":"Villa Rica",
    "sg:classifiers":[
        {
            "category":"Building & Trades",
            "subcategory":"Construction",
            "type":"Services"
        }
    ],
    "sg:phone":"+1 770 830 9515",
    "sg:postcode":"30180",
    "sg:province":"GA",
    "sg:tags":[
        "heavy"
    ],
    "wof:name":"Corner Stone Builders of W GA",
    "wof:placetype":"venue"
},
  "geometry": {"coordinates":[-84.92423599999999,33.624724],"type":"Point"}
}