{
  "type": "Feature",
  "properties": {
    "addr:full":"5299 Roswell Rd Ste 110 Atlanta GA 30342",
    "addr:housenumber":"5299",
    "addr:postcode":"30342",
    "addr:street":"Roswell Rd Ste 110",
    "iso:country":"US",
    "sg:address":"5299 Roswell Rd Ste 110",
    "sg:city":"Atlanta",
    "sg:classifiers":[
        {
            "category":"Personal",
            "subcategory":"Beauty Salon",
            "type":"Services"
        }
    ],
    "sg:phone":"+1 404 943 9070",
    "sg:postcode":"30342",
    "sg:province":"GA",
    "sg:tags":[
        "hair"
    ],
    "wof:name":"Rio Hair Salon",
    "wof:placetype":"venue"
},
  "geometry": {"coordinates":[-84.380354,33.900099],"type":"Point"}
}