{
  "type": "Feature",
  "properties": {
    "iso:country":"US",
    "sg:address":"805 Professional Blvd",
    "sg:city":"Dalton",
    "sg:classifiers":[
        {
            "category":"Government",
            "subcategory":"Police Station",
            "type":"Public Place"
        }
    ],
    "sg:phone":"+1 706 278 1233",
    "sg:postcode":"30720",
    "sg:province":"GA",
    "sg:tags":[
        "sheriff"
    ],
    "sg:website":"www.wcso.com",
    "wof:name":"Whitfield County Sheriff Dept",
    "wof:placetype":"venue"
},
  "geometry": {"coordinates":[-84.985855,34.792976],"type":"Point"}
}