{
  "type": "Feature",
  "properties": {
    "iso:country":"US",
    "sg:address":"218 W State St",
    "sg:city":"Savannah",
    "sg:classifiers":[
        {
            "category":"Professional",
            "subcategory":"Lawyer & Legal Services",
            "type":"Services"
        }
    ],
    "sg:phone":"+1 912 236 3311",
    "sg:postcode":"31401",
    "sg:province":"GA",
    "sg:tags":[
        "attorney"
    ],
    "wof:name":"Oliver Maner Gray LLP",
    "wof:placetype":"venue"
},
  "geometry": {"coordinates":[-81.094691,32.078987],"type":"Point"}
}