{
  "type": "Feature",
  "properties": {
    "iso:country":"US",
    "sg:address":"2795 Old Alabama Rd",
    "sg:city":"Alpharetta",
    "sg:classifiers":[
        {
            "category":"Cinema",
            "subcategory":"Movie Rental",
            "type":"Entertainment"
        }
    ],
    "sg:phone":"+1 770 346 8576",
    "sg:postcode":"30022",
    "sg:province":"GA",
    "sg:tags":[
        "video",
        "tape"
    ],
    "wof:name":"Hollywood Video",
    "wof:placetype":"venue"
},
  "geometry": {"coordinates":[-84.274038,34.021258],"type":"Point"}
}