{
  "type": "Feature",
  "properties": {
    "iso:country":"US",
    "sg:address":"1558 Marietta Hwy",
    "sg:city":"Canton",
    "sg:classifiers":[
        {
            "category":"Taxi",
            "type":"Transportation"
        }
    ],
    "sg:phone":"+1 770 704 0851",
    "sg:postcode":"30114",
    "sg:province":"GA",
    "sg:tags":[
        "taxicab"
    ],
    "wof:name":"Cab Marketing Inc",
    "wof:placetype":"venue"
},
  "geometry": {"coordinates":[-84.500311,34.225923],"type":"Point"}
}