{
  "type": "Feature",
  "properties": {
    "addr:full":"2133 E Walnut Ave Dalton GA 30721",
    "addr:housenumber":"2133",
    "addr:postcode":"30721",
    "addr:street":"E Walnut Ave",
    "iso:country":"US",
    "sg:address":"2133 E Walnut Ave",
    "sg:city":"Dalton",
    "sg:classifiers":[
        {
            "category":"Cinema",
            "subcategory":"Movie Rental",
            "type":"Entertainment"
        }
    ],
    "sg:phone":"+1 706 226 3232",
    "sg:postcode":"30721",
    "sg:province":"GA",
    "sg:tags":[
        "video",
        "tape"
    ],
    "wof:name":"Blockbuster",
    "wof:placetype":"venue"
},
  "geometry": {"coordinates":[-84.93594,34.761283],"type":"Point"}
}