{
  "type": "Feature",
  "properties": {
    "iso:country":"US",
    "sg:address":"8340 Old Keith Bridge Rd",
    "sg:city":"Gainesville",
    "sg:classifiers":[
        {
            "category":"Personal",
            "subcategory":"Beauty Salon",
            "type":"Services"
        }
    ],
    "sg:phone":"+1 770 887 5037",
    "sg:postcode":"30506",
    "sg:province":"GA",
    "sg:tags":[
        "shop"
    ],
    "wof:name":"Chesta Pee Bay Beauty Shop",
    "wof:placetype":"venue"
},
  "geometry": {"coordinates":[-83.975555,34.30368],"type":"Point"}
}