{
  "type": "Feature",
  "properties": {
    "iso:country":"US",
    "sg:address":"3219 Fosters Mill Rd",
    "sg:city":"Rome",
    "sg:classifiers":[
        {
            "category":"Organizations",
            "subcategory":"Religious Organization",
            "type":"Services"
        }
    ],
    "sg:phone":"+1 706 777 8360",
    "sg:postcode":"30161",
    "sg:province":"GA",
    "wof:name":"Cedar Creek Baptist Church",
    "wof:placetype":"venue"
},
  "geometry": {"coordinates":[-85.342012,34.16909],"type":"Point"}
}