{
  "type": "Feature",
  "properties": {
    "addr:full":"4605 Loftwood Dr Cohutta GA 30710",
    "addr:housenumber":"4605",
    "addr:postcode":"30710",
    "addr:street":"Loftwood Dr",
    "iso:country":"US",
    "sg:address":"4605 Loftwood Dr",
    "sg:city":"Cohutta",
    "sg:classifiers":[
        {
            "category":"Professional",
            "subcategory":"Detective & Security Services",
            "type":"Services"
        }
    ],
    "sg:phone":"+1 706 694 3062",
    "sg:postcode":"30710",
    "sg:province":"GA",
    "sg:tags":[
        "control",
        "monitoring",
        "fire",
        "consultant",
        "alarm",
        "system",
        "equipment"
    ],
    "wof:name":"Safe Tech Alarms Inc",
    "wof:placetype":"venue"
},
  "geometry": {"coordinates":[-84.96447999999999,34.916384],"type":"Point"}
}