{
  "type": "Feature",
  "properties": {
    "iso:country":"US",
    "sg:address":"1650 Williams Dr",
    "sg:city":"Marietta",
    "sg:classifiers":[
        {
            "category":"Building & Trades",
            "subcategory":"Construction",
            "type":"Services"
        }
    ],
    "sg:phone":"+1 770 423 0350",
    "sg:postcode":"30066",
    "sg:province":"GA",
    "sg:tags":[
        "retaining",
        "wall"
    ],
    "sg:website":"http://www.cornerstonewalls.com",
    "wof:name":"CornerStone Wall Systems Inc",
    "wof:placetype":"venue"
},
  "geometry": {"coordinates":[-84.53177599999999,33.997391],"type":"Point"}
}