{
  "type": "Feature",
  "properties": {
    "iso:country":"US",
    "sg:address":"2771 Lawrenceville Hwy",
    "sg:city":"Decatur",
    "sg:classifiers":[
        {
            "category":"Manufacturing",
            "subcategory":"Tools & Machinery",
            "type":"Manufacturing & Wholesale Goods"
        }
    ],
    "sg:phone":"+1 770 908 0268",
    "sg:postcode":"30033",
    "sg:province":"GA",
    "sg:tags":[
        "surgical",
        "mfg"
    ],
    "wof:name":"Multi Sport Orthotics",
    "wof:placetype":"venue"
},
  "geometry": {"coordinates":[-84.256249,33.825795],"type":"Point"}
}