{
  "type": "Feature",
  "properties": {
    "iso:country":"US",
    "sg:address":"373 Morrow Rd SE",
    "sg:city":"Calhoun",
    "sg:classifiers":[
        {
            "category":"Organizations",
            "subcategory":"Religious Organization",
            "type":"Services"
        }
    ],
    "sg:phone":"+1 706 629 5139",
    "sg:postcode":"30701",
    "sg:province":"GA",
    "wof:name":"Gordon County & Memorial Assn",
    "wof:placetype":"venue"
},
  "geometry": {"coordinates":[-84.911466,34.456196],"type":"Point"}
}