{
  "type": "Feature",
  "properties": {
    "iso:country":"US",
    "sg:address":"3066 Hope St",
    "sg:city":"Atlanta",
    "sg:classifiers":[
        {
            "category":"Community Center",
            "type":"Public Place"
        }
    ],
    "sg:phone":"+1 404 209 8131",
    "sg:postcode":"30354",
    "sg:province":"GA",
    "sg:tags":[
        "recreation"
    ],
    "wof:name":"Community Care Homes, Inc.",
    "wof:placetype":"venue"
},
  "geometry": {"coordinates":[-84.41422900000001,33.670632],"type":"Point"}
}