{
  "type": "Feature",
  "properties": {
    "addr:full":"150 Belwood Dr SE Calhoun GA 30701",
    "addr:housenumber":"150",
    "addr:postcode":"30701",
    "addr:street":"Belwood Dr Se",
    "iso:country":"US",
    "sg:address":"150 Belwood Dr SE",
    "sg:city":"Calhoun",
    "sg:classifiers":[
        {
            "category":"Professional",
            "subcategory":"Business Services",
            "type":"Services"
        }
    ],
    "sg:phone":"+1 706 602 8426",
    "sg:postcode":"30701",
    "sg:province":"GA",
    "wof:name":"Exterior Solutions",
    "wof:placetype":"venue"
},
  "geometry": {"coordinates":[-84.913078,34.450111],"type":"Point"}
}