{
  "type": "Feature",
  "properties": {
    "addr:full":"658 Hansell St SE Atlanta GA 30312",
    "addr:housenumber":"658",
    "addr:postcode":"30312",
    "addr:street":"Hansell St Se",
    "iso:country":"US",
    "sg:address":"658 Hansell St SE",
    "sg:city":"Atlanta",
    "sg:classifiers":[
        {
            "category":"Manufacturing",
            "subcategory":"Food",
            "type":"Manufacturing & Wholesale Goods"
        }
    ],
    "sg:phone":"+1 404 627 2635",
    "sg:postcode":"30312",
    "sg:province":"GA",
    "sg:tags":[
        "product",
        "mfg"
    ],
    "wof:name":"Honey Dssrts/Honey Productions",
    "wof:placetype":"venue"
},
  "geometry": {"coordinates":[-84.36571000000001,33.74021],"type":"Point"}
}