{
  "type": "Feature",
  "properties": {
    "iso:country":"US",
    "sg:address":"214 Screven Ave",
    "sg:city":"Waycross",
    "sg:classifiers":[
        {
            "category":"Banks & Credit Unions",
            "subcategory":"Bank",
            "type":"Services"
        }
    ],
    "sg:phone":"+1 912 285 5629",
    "sg:postcode":"31501",
    "sg:province":"GA",
    "sg:tags":[
        "mortgage"
    ],
    "wof:name":"American Financial Svcs Group",
    "wof:placetype":"venue"
},
  "geometry": {"coordinates":[-82.350674,31.215277],"type":"Point"}
}