{
  "type": "Feature",
  "properties": {
    "addr:full":"3035 Clairmont Pl Macon GA 31204",
    "addr:housenumber":"3035",
    "addr:postcode":"31204",
    "addr:street":"Clairmont Pl",
    "iso:country":"US",
    "sg:address":"3035 Clairmont Pl",
    "sg:city":"Macon",
    "sg:classifiers":[
        {
            "category":"Professional",
            "subcategory":"Business Services",
            "type":"Services"
        }
    ],
    "sg:phone":"+1 478 471 7823",
    "sg:postcode":"31204",
    "sg:province":"GA",
    "wof:name":"Vernon King",
    "wof:placetype":"venue"
},
  "geometry": {"coordinates":[-83.663843,32.888002],"type":"Point"}
}