{
  "type": "Feature",
  "properties": {
    "iso:country":"US",
    "sg:address":"209 Edgewood Ave",
    "sg:city":"Atlanta",
    "sg:classifiers":[
        {
            "category":"Restaurant",
            "type":"Food & Drink"
        }
    ],
    "sg:phone":"+1 404 254 2899",
    "sg:postcode":"30312",
    "sg:province":"GA",
    "sg:tags":[
        "greek",
        "pizza"
    ],
    "sg:website":"www.thegreekatl.com",
    "wof:name":"The Greek Gyros and Pizza",
    "wof:placetype":"venue"
},
  "geometry": {"coordinates":[-84.37996699999999,33.754076],"type":"Point"}
}