{
  "type": "Feature",
  "properties": {
    "iso:country":"US",
    "sg:address":"3630 Camp Cir",
    "sg:city":"Decatur",
    "sg:classifiers":[
        {
            "category":"Government",
            "subcategory":"Office",
            "type":"Public Place"
        }
    ],
    "sg:phone":"+1 404 294 2000",
    "sg:postcode":"30032",
    "sg:province":"GA",
    "sg:tags":[
        "county",
        "safety",
        "order"
    ],
    "wof:name":"Public Safety Dept",
    "wof:placetype":"venue"
},
  "geometry": {"coordinates":[-84.241338,33.776319],"type":"Point"}
}