{
  "type": "Feature",
  "properties": {
    "iso:country":"US",
    "sg:address":"3730 Redcoat Way",
    "sg:city":"Alpharetta",
    "sg:classifiers":[
        {
            "category":"Professional",
            "subcategory":"Management & Consulting",
            "type":"Services"
        }
    ],
    "sg:phone":"+1 770 663 8111",
    "sg:postcode":"30022",
    "sg:province":"GA",
    "wof:name":"Huskey Consulting Services LLC",
    "wof:placetype":"venue"
},
  "geometry": {"coordinates":[-84.251458,34.017333],"type":"Point"}
}