{
  "type": "Feature",
  "properties": {
    "iso:country":"US",
    "sg:address":"5496 Silver Ridge Dr",
    "sg:city":"Stone Mountain",
    "sg:classifiers":[
        {
            "category":"Professional",
            "type":"Services"
        }
    ],
    "sg:phone":"+1 770 498 4221",
    "sg:postcode":"30087",
    "sg:province":"GA",
    "wof:name":"James D Bouchard",
    "wof:placetype":"venue"
},
  "geometry": {"coordinates":[-84.164264,33.835409],"type":"Point"}
}