{
  "type": "Feature",
  "properties": {
    "addr:full":"272 Willett Dr Cleveland GA 30528",
    "addr:housenumber":"272",
    "addr:postcode":"30528",
    "addr:street":"Willett Dr",
    "iso:country":"US",
    "sg:address":"272 Willett Dr",
    "sg:city":"Cleveland",
    "sg:classifiers":[
        {
            "category":"Building & Trades",
            "subcategory":"Construction",
            "type":"Services"
        }
    ],
    "sg:phone":"+1 706 865 3212",
    "sg:postcode":"30528",
    "sg:province":"GA",
    "sg:tags":[
        "general",
        "contractor"
    ],
    "wof:name":"Collis Construction",
    "wof:placetype":"venue"
},
  "geometry": {"coordinates":[-83.758315,34.636969],"type":"Point"}
}