{
  "type": "Feature",
  "properties": {
    "iso:country":"US",
    "sg:address":"101 Dale St",
    "sg:city":"Rome",
    "sg:classifiers":[
        {
            "category":"Manufacturing",
            "subcategory":"Toys & Sporting Goods",
            "type":"Manufacturing & Wholesale Goods"
        }
    ],
    "sg:phone":"+1 706 291 8628",
    "sg:postcode":"30161",
    "sg:province":"GA",
    "sg:tags":[
        "mfg"
    ],
    "wof:name":"Doyals Fishing & Wholesale Sup",
    "wof:placetype":"venue"
},
  "geometry": {"coordinates":[-85.15021299999999,34.276846],"type":"Point"}
}