{
  "type": "Feature",
  "properties": {
    "iso:country":"US",
    "sg:address":"316 Joshua Tree Dr",
    "sg:city":"Augusta",
    "sg:classifiers":[
        {
            "category":"Professional",
            "type":"Services"
        }
    ],
    "sg:phone":"+1 706 854 9727",
    "sg:postcode":"30907",
    "sg:province":"GA",
    "wof:name":"Satish K Kalra",
    "wof:placetype":"venue"
},
  "geometry": {"coordinates":[-82.08949,33.53147],"type":"Point"}
}