{
  "type": "Feature",
  "properties": {
    "addr:full":"285 W Washington St Athens GA 30601",
    "addr:housenumber":"285",
    "addr:postcode":"30601",
    "addr:street":"W Washington St",
    "iso:country":"US",
    "sg:address":"285 W Washington St",
    "sg:city":"Athens",
    "sg:classifiers":[
        {
            "category":"Shopping",
            "subcategory":"Music",
            "type":"Retail Goods"
        }
    ],
    "sg:phone":"+1 706 227 6199",
    "sg:postcode":"30601",
    "sg:province":"GA",
    "wof:name":"Low Yo Yo Stuff Records",
    "wof:placetype":"venue"
},
  "geometry": {"coordinates":[-83.37923000000001,33.958601],"type":"Point"}
}