{
  "type": "Feature",
  "properties": {
    "addr:full":"2617 Gillionville Rd Albany GA 31707",
    "addr:housenumber":"2617",
    "addr:postcode":"31707",
    "addr:street":"Gillionville Rd",
    "iso:country":"US",
    "sg:address":"2617 Gillionville Rd",
    "sg:city":"Albany",
    "sg:classifiers":[
        {
            "category":"Professional",
            "subcategory":"Accounting & Tax Preparation",
            "type":"Services"
        }
    ],
    "sg:phone":"+1 229 883 7878",
    "sg:postcode":"31707",
    "sg:province":"GA",
    "sg:tags":[
        "accountant"
    ],
    "wof:name":"Draffin & Tucker",
    "wof:placetype":"venue"
},
  "geometry": {"coordinates":[-84.21696,31.585838],"type":"Point"}
}