{
  "type": "Feature",
  "properties": {
    "iso:country":"US",
    "sg:address":"4075 Gladney Dr",
    "sg:city":"Atlanta",
    "sg:classifiers":[
        {
            "category":"Professional",
            "type":"Services"
        }
    ],
    "sg:phone":"+1 770 939 2599",
    "sg:postcode":"30340",
    "sg:province":"GA",
    "wof:name":"Milne & Company Inc",
    "wof:placetype":"venue"
},
  "geometry": {"coordinates":[-84.22699299999999,33.877525],"type":"Point"}
}