{
  "type": "Feature",
  "properties": {
    "iso:country":"US",
    "sg:address":"133 Park Dr",
    "sg:city":"Eatonton",
    "sg:phone":"+1 706 485 0606",
    "sg:postcode":"31029",
    "sg:province":"GA",
    "sg:tags":[
        "farm"
    ],
    "wof:name":"Edwards Produce",
    "wof:placetype":"venue"
},
  "geometry": {"coordinates":[-83.963481,33.036253],"type":"Point"}
}