{
  "type": "Feature",
  "properties": {
    "iso:country":"US",
    "sg:address":"2945 State Rte 317",
    "sg:city":"Suwanee",
    "sg:classifiers":[
        {
            "category":"Travel",
            "subcategory":"Hotels & Motels",
            "type":"Entertainment"
        }
    ],
    "sg:phone":"+1 770 945 1608",
    "sg:postcode":"30024",
    "sg:province":"GA",
    "sg:tags":[
        "operation"
    ],
    "wof:name":"Comfort Inn",
    "wof:placetype":"venue"
},
  "geometry": {"coordinates":[-84.045176,34.027095],"type":"Point"}
}