{
  "type": "Feature",
  "properties": {
    "iso:country":"US",
    "sg:address":"1025 State Rte 81",
    "sg:city":"Mcdonough",
    "sg:classifiers":[
        {
            "category":"Restaurant",
            "type":"Food & Drink"
        }
    ],
    "sg:phone":"+1 770 914 9435",
    "sg:postcode":"30253",
    "sg:province":"GA",
    "sg:tags":[
        "eating"
    ],
    "wof:name":"Taco Bell",
    "wof:placetype":"venue"
},
  "geometry": {"coordinates":[-84.17726399999999,33.431606],"type":"Point"}
}