{
  "type": "Feature",
  "properties": {
    "addr:full":"313 E Main St Cartersville GA 30120",
    "addr:housenumber":"313",
    "addr:postcode":"30120",
    "addr:street":"E Main St",
    "iso:country":"US",
    "sg:address":"313 E Main St",
    "sg:city":"Cartersville",
    "sg:classifiers":[
        {
            "category":"Travel",
            "subcategory":"Travel Agent",
            "type":"Entertainment"
        }
    ],
    "sg:phone":"+1 770 386 3038",
    "sg:postcode":"30120",
    "sg:province":"GA",
    "sg:tags":[
        "bureau",
        "passenger",
        "agency",
        "transportation",
        "arrangement"
    ],
    "wof:name":"Superior Travel Inc",
    "wof:placetype":"venue"
},
  "geometry": {"coordinates":[-84.792344,34.166173],"type":"Point"}
}