{
  "type": "Feature",
  "properties": {
    "addr:full":"3293 Refuge Rd Jasper GA 30143",
    "addr:housenumber":"3293",
    "addr:postcode":"30143",
    "addr:street":"Refuge Rd",
    "iso:country":"US",
    "sg:address":"3293 Refuge Rd",
    "sg:city":"Jasper",
    "sg:classifiers":[
        {
            "category":"Manufacturing",
            "subcategory":"Tools & Machinery",
            "type":"Manufacturing & Wholesale Goods"
        }
    ],
    "sg:phone":"+1 706 692 6707",
    "sg:postcode":"30143",
    "sg:province":"GA",
    "sg:tags":[
        "machine",
        "shop"
    ],
    "wof:name":"Turning Co",
    "wof:placetype":"venue"
},
  "geometry": {"coordinates":[-84.41918200000001,34.422814],"type":"Point"}
}