{
  "type": "Feature",
  "properties": {
    "addr:full":"38 Wolfridge Trl NE White GA 30184",
    "addr:housenumber":"38",
    "addr:postcode":"30184",
    "addr:street":"Wolfridge Trl Ne",
    "iso:country":"US",
    "sg:address":"38 Wolfridge Trl NE",
    "sg:city":"White",
    "sg:classifiers":[
        {
            "category":"Building & Trades",
            "subcategory":"Construction",
            "type":"Services"
        }
    ],
    "sg:phone":"+1 770 386 1329",
    "sg:postcode":"30184",
    "sg:province":"GA",
    "sg:tags":[
        "woodworker"
    ],
    "wof:name":"Woodcrafts By Paw Paw",
    "wof:placetype":"venue"
},
  "geometry": {"coordinates":[-84.742397,34.23359],"type":"Point"}
}