{
  "type": "Feature",
  "properties": {
    "addr:full":"252 Rio Cir Decatur GA 30030",
    "addr:housenumber":"252",
    "addr:postcode":"30030",
    "addr:street":"Rio Cir",
    "iso:country":"US",
    "sg:address":"252 Rio Cir",
    "sg:city":"Decatur",
    "sg:classifiers":[
        {
            "category":"Wholesale",
            "subcategory":"Groceries",
            "type":"Manufacturing & Wholesale Goods"
        }
    ],
    "sg:phone":"+1 404 377 4555",
    "sg:postcode":"30030",
    "sg:province":"GA",
    "sg:tags":[
        "bakery",
        "product",
        "mfg"
    ],
    "wof:name":"Masada Bakery",
    "wof:placetype":"venue"
},
  "geometry": {"coordinates":[-84.270302,33.781601],"type":"Point"}
}