{
  "type": "Feature",
  "properties": {
    "iso:country":"US",
    "sg:address":"3065 Baxley Ct",
    "sg:city":"Atlanta",
    "sg:classifiers":[
        {
            "category":"Building & Trades",
            "subcategory":"Cleaning & Sanitation",
            "type":"Services"
        }
    ],
    "sg:phone":"+1 770 991 2916",
    "sg:postcode":"30349",
    "sg:province":"GA",
    "sg:tags":[
        "maintenance"
    ],
    "wof:name":"Amos Cleaning",
    "wof:placetype":"venue"
},
  "geometry": {"coordinates":[-84.489656,33.567683],"type":"Point"}
}