{
  "type": "Feature",
  "properties": {
    "iso:country":"US",
    "sg:address":"6455 Rockbridge Rd",
    "sg:city":"Stone Mountain",
    "sg:classifiers":[
        {
            "category":"Building & Trades",
            "subcategory":"Construction",
            "type":"Services"
        }
    ],
    "sg:phone":"+1 770 498 5200",
    "sg:postcode":"30087",
    "sg:province":"GA",
    "sg:tags":[
        "floor",
        "laying",
        "contractor"
    ],
    "wof:name":"Carpet Installer Direct",
    "wof:placetype":"venue"
},
  "geometry": {"coordinates":[-84.13147600000001,33.784906],"type":"Point"}
}