{
  "type": "Feature",
  "properties": {
    "iso:country":"US",
    "sg:address":"345 Gosdin Rd",
    "sg:city":"Palmetto",
    "sg:classifiers":[
        {
            "category":"Building & Trades",
            "subcategory":"Construction",
            "type":"Services"
        }
    ],
    "sg:phone":"+1 770 463 2895",
    "sg:postcode":"30268",
    "sg:province":"GA",
    "sg:tags":[
        "home"
    ],
    "wof:name":"Dean Construction Services",
    "wof:placetype":"venue"
},
  "geometry": {"coordinates":[-84.713538,33.503429],"type":"Point"}
}