{
  "type": "Feature",
  "properties": {
    "addr:full":"2665 Ball Ground Hwy Canton GA 30114",
    "addr:housenumber":"2665",
    "addr:postcode":"30114",
    "addr:street":"Ball Ground Hwy",
    "iso:country":"US",
    "sg:address":"2665 Ball Ground Hwy",
    "sg:city":"Canton",
    "sg:classifiers":[
        {
            "category":"Wholesale",
            "subcategory":"Non-durable Goods",
            "type":"Manufacturing & Wholesale Goods"
        }
    ],
    "sg:phone":"+1 770 479 5252",
    "sg:postcode":"30114",
    "sg:province":"GA",
    "sg:tags":[
        "merchandise",
        "general"
    ],
    "wof:name":"Simple Selections",
    "wof:placetype":"venue"
},
  "geometry": {"coordinates":[-84.457576,34.268689],"type":"Point"}
}