{
  "type": "Feature",
  "properties": {
    "iso:country":"US",
    "sg:address":"546 Paden Dr",
    "sg:city":"Lawrenceville",
    "sg:classifiers":[
        {
            "category":"Restaurant",
            "type":"Food & Drink"
        }
    ],
    "sg:phone":"+1 770 963 8106",
    "sg:postcode":"30044",
    "sg:province":"GA",
    "sg:tags":[
        "caterer"
    ],
    "wof:name":"Casual Catering Of Georgia",
    "wof:placetype":"venue"
},
  "geometry": {"coordinates":[-84.071764,33.935388],"type":"Point"}
}