{
  "type": "Feature",
  "properties": {
    "addr:full":"5098 Rocky Ford Rd Valdosta GA 31601",
    "addr:housenumber":"5098",
    "addr:postcode":"31601",
    "addr:street":"Rocky Ford Rd",
    "iso:country":"US",
    "sg:address":"5098 Rocky Ford Rd",
    "sg:city":"Valdosta",
    "sg:classifiers":[
        {
            "category":"Manufacturing",
            "subcategory":"Printing",
            "type":"Manufacturing & Wholesale Goods"
        }
    ],
    "sg:phone":"+1 229 245 7438",
    "sg:postcode":"31601",
    "sg:province":"GA",
    "sg:tags":[
        "lithographic",
        "commercial"
    ],
    "wof:name":"Lizs Typing & Printing Svcs",
    "wof:placetype":"venue"
},
  "geometry": {"coordinates":[-83.385294,30.707247],"type":"Point"}
}