{
  "type": "Feature",
  "properties": {
    "iso:country":"US",
    "sg:address":"1388 Christiana Dr",
    "sg:city":"Lawrenceville",
    "sg:classifiers":[
        {
            "category":"Professional",
            "type":"Services"
        }
    ],
    "sg:phone":"+1 770 963 0765",
    "sg:postcode":"30043",
    "sg:province":"GA",
    "wof:name":"Savich Risk Management Svc",
    "wof:placetype":"venue"
},
  "geometry": {"coordinates":[-84.044884,33.973323],"type":"Point"}
}