{
  "type": "Feature",
  "properties": {
    "addr:full":"12460 Crabapple Rd Ste 203 Alpharetta GA 30004",
    "addr:housenumber":"12460",
    "addr:postcode":"30004",
    "addr:street":"Crabapple Rd Ste 203",
    "iso:country":"US",
    "sg:address":"12460 Crabapple Rd Ste 203",
    "sg:city":"Alpharetta",
    "sg:classifiers":[
        {
            "category":"Personal",
            "subcategory":"Barber",
            "type":"Services"
        }
    ],
    "sg:phone":"+1 770 740 2066",
    "sg:postcode":"30004",
    "sg:province":"GA",
    "sg:website":"www.greatclips.com",
    "wof:name":"Great Clips For Hair",
    "wof:placetype":"venue"
},
  "geometry": {"coordinates":[-84.354077,34.086129],"type":"Point"}
}