{
  "type": "Feature",
  "properties": {
    "iso:country":"US",
    "sg:address":"15 Highland Park Dr",
    "sg:city":"Sharpsburg",
    "sg:classifiers":[
        {
            "category":"Home & Garden",
            "subcategory":"Furniture",
            "type":"Retail Goods"
        }
    ],
    "sg:phone":"+1 770 254 8077",
    "sg:postcode":"30277",
    "sg:province":"GA",
    "wof:name":"Tck Custom Furniture Inc",
    "wof:placetype":"venue"
},
  "geometry": {"coordinates":[-84.628221,33.420296],"type":"Point"}
}