{
  "type": "Feature",
  "properties": {
    "iso:country":"US",
    "sg:address":"3162 Johnson Ferry Rd",
    "sg:city":"Marietta",
    "sg:classifiers":[
        {
            "category":"Building & Trades",
            "subcategory":"Construction",
            "type":"Services"
        }
    ],
    "sg:phone":"+1 770 482 8234",
    "sg:postcode":"30062",
    "sg:province":"GA",
    "sg:tags":[
        "equipment",
        "industrial",
        "installation"
    ],
    "wof:name":"Mowrey Elevator",
    "wof:placetype":"venue"
},
  "geometry": {"coordinates":[-84.42427499999999,34.025709],"type":"Point"}
}