{
  "type": "Feature",
  "properties": {
    "iso:country":"US",
    "sg:address":"22 Ramsey St # A",
    "sg:city":"Roswell",
    "sg:classifiers":[
        {
            "category":"Health Services",
            "subcategory":"Doctor",
            "type":"Services"
        }
    ],
    "sg:phone":"+1 770 993 9521",
    "sg:postcode":"30075",
    "sg:province":"GA",
    "sg:tags":[
        "surgeon",
        "oral"
    ],
    "wof:name":"Whitesell James B DDS",
    "wof:placetype":"venue"
},
  "geometry": {"coordinates":[-84.361603,34.021599],"type":"Point"}
}