{
  "type": "Feature",
  "properties": {
    "iso:country":"US",
    "sg:address":"1637 Mount Vernon Rd Ste 100",
    "sg:city":"Atlanta",
    "sg:phone":"+1 770 396 3460",
    "sg:postcode":"30338",
    "sg:province":"GA",
    "wof:name":"Briggs James J Od",
    "wof:placetype":"venue"
},
  "geometry": {"coordinates":[-84.332092,33.946819],"type":"Point"}
}