{
  "type": "Feature",
  "properties": {
    "addr:full":"911 Duluth Hwy Ste 3242 Lawrenceville GA 30043",
    "addr:housenumber":"911",
    "addr:postcode":"30043",
    "addr:street":"Duluth Hwy Ste 3242",
    "iso:country":"US",
    "sg:address":"911 Duluth Hwy Ste 3242",
    "sg:city":"Lawrenceville",
    "sg:classifiers":[
        {
            "category":"Manufacturing",
            "subcategory":"Buildings",
            "type":"Manufacturing & Wholesale Goods"
        },
        {
            "category":"Structure",
            "subcategory":"Warehouse",
            "type":"Public Place"
        },
        {
            "category":"Building & Trades",
            "subcategory":"Construction",
            "type":"Services"
        }
    ],
    "sg:phone":"+1 770 449 6700",
    "sg:postcode":"30043",
    "sg:province":"GA",
    "sg:tags":[
        "industrial",
        "warehouses-merchandise",
        "warehouses-public-commercial",
        "builder",
        "contractor",
        "contractors-commercial",
        "home"
    ],
    "wof:name":"Itasca Construction Associates Inc",
    "wof:placetype":"venue"
},
  "geometry": {"coordinates":[-84.023791,33.967949],"type":"Point"}
}