{
  "type": "Feature",
  "properties": {
    "addr:full":"10350 Main St Woodstock GA 30188",
    "addr:housenumber":"10350",
    "addr:postcode":"30188",
    "addr:street":"Main St",
    "iso:country":"US",
    "sg:address":"10350 Main St",
    "sg:city":"Woodstock",
    "sg:classifiers":[
        {
            "category":"Health Services",
            "subcategory":"Chiropractor",
            "type":"Services"
        }
    ],
    "sg:phone":"+1 770 924 1995",
    "sg:postcode":"30188",
    "sg:province":"GA",
    "wof:name":"Dimola Family Chiropractic",
    "wof:placetype":"venue"
},
  "geometry": {"coordinates":[-84.52204500000001,34.075907],"type":"Point"}
}