{
  "type": "Feature",
  "properties": {
    "addr:full":"176 Shawnee Trl Marietta GA 30067",
    "addr:housenumber":"176",
    "addr:postcode":"30067",
    "addr:street":"Shawnee Trl",
    "iso:country":"US",
    "sg:address":"176 Shawnee Trl",
    "sg:city":"Marietta",
    "sg:classifiers":[
        {
            "category":"Shopping",
            "subcategory":"Crafts & Fabrics",
            "type":"Retail Goods"
        }
    ],
    "sg:phone":"+1 770 973 2242",
    "sg:postcode":"30067",
    "sg:province":"GA",
    "sg:tags":[
        "sewing"
    ],
    "wof:name":"Sew Into Your Life",
    "wof:placetype":"venue"
},
  "geometry": {"coordinates":[-84.49295499999999,33.945208],"type":"Point"}
}