{
  "type": "Feature",
  "properties": {
    "iso:country":"US",
    "sg:address":"568 Ripplewater Dr",
    "sg:city":"Marietta",
    "sg:classifiers":[
        {
            "category":"Building & Trades",
            "subcategory":"Construction",
            "type":"Services"
        }
    ],
    "sg:phone":"+1 770 421 9782",
    "sg:postcode":"30064",
    "sg:province":"GA",
    "sg:tags":[
        "house"
    ],
    "wof:name":"Casa Construction Inc",
    "wof:placetype":"venue"
},
  "geometry": {"coordinates":[-84.647171,33.939809],"type":"Point"}
}