{
  "type": "Feature",
  "properties": {
    "addr:full":"600 Virginia Avenue NE Atlanta GA 30306",
    "addr:housenumber":"600",
    "addr:postcode":"30306",
    "addr:street":"Virginia Avenue Ne",
    "iso:country":"US",
    "sg:address":"600 Virginia Avenue NE",
    "sg:city":"Atlanta",
    "sg:classifiers":[
        {
            "category":"Retail",
            "subcategory":"Storage",
            "type":"Services"
        }
    ],
    "sg:phone":"+1 404 874 7410",
    "sg:postcode":"30306",
    "sg:province":"GA",
    "sg:tags":[
        "self"
    ],
    "wof:name":"Extra Space Storage",
    "wof:placetype":"venue"
},
  "geometry": {"coordinates":[-84.367358,33.781251],"type":"Point"}
}