{
  "type": "Feature",
  "properties": {
    "addr:full":"255 Pink Dogwood Ln Pooler GA 31322",
    "addr:housenumber":"255",
    "addr:postcode":"31322",
    "addr:street":"Pink Dogwood Ln",
    "iso:country":"US",
    "sg:address":"255 Pink Dogwood Ln",
    "sg:city":"Pooler",
    "sg:classifiers":[
        {
            "category":"Retail",
            "subcategory":"Auto Rental",
            "type":"Services"
        }
    ],
    "sg:phone":"+1 912 748 5107",
    "sg:postcode":"31322",
    "sg:province":"GA",
    "sg:tags":[
        "limousine"
    ],
    "wof:name":"A Courtesy Limousine",
    "wof:placetype":"venue"
},
  "geometry": {"coordinates":[-81.254114,32.155311],"type":"Point"}
}