{
  "type": "Feature",
  "properties": {
    "addr:full":"112 Miller Ln Sylvester GA 31791",
    "addr:housenumber":"112",
    "addr:postcode":"31791",
    "addr:street":"Miller Ln",
    "iso:country":"US",
    "sg:address":"112 Miller Ln",
    "sg:city":"Sylvester",
    "sg:classifiers":[
        {
            "category":"Real Estate",
            "subcategory":"Developer",
            "type":"Services"
        },
        {
            "category":"Real Estate",
            "subcategory":"Real Estate Agent",
            "type":"Services"
        }
    ],
    "sg:phone":"+1 229 776 6015",
    "sg:postcode":"31791",
    "sg:province":"GA",
    "wof:name":"First Choice Realty",
    "wof:placetype":"venue"
},
  "geometry": {"coordinates":[-83.84199700000001,31.563667],"type":"Point"}
}