{
  "type": "Feature",
  "properties": {
    "iso:country":"US",
    "sg:address":"1201 New East Morris St",
    "sg:city":"Dalton",
    "sg:classifiers":[
        {
            "category":"Building & Trades",
            "subcategory":"Plumbing",
            "type":"Services"
        }
    ],
    "sg:phone":"+1 706 272 3968",
    "sg:postcode":"30721",
    "sg:province":"GA",
    "sg:tags":[
        "system",
        "contractor",
        "air conditioning"
    ],
    "wof:name":"Dalton Heating & Air Conditioning",
    "wof:placetype":"venue"
},
  "geometry": {"coordinates":[-84.949966,34.768719],"type":"Point"}
}