{
  "type": "Feature",
  "properties": {
    "iso:country":"US",
    "sg:address":"911 N Glenwood Ave",
    "sg:city":"Dalton",
    "sg:classifiers":[
        {
            "category":"Professional",
            "type":"Services"
        }
    ],
    "sg:phone":"+1 706 428 2881",
    "sg:postcode":"30721",
    "sg:province":"GA",
    "wof:name":"Kashmir Audio & Electronics",
    "wof:placetype":"venue"
},
  "geometry": {"coordinates":[-84.96299999999999,34.785836],"type":"Point"}
}