{
  "type": "Feature",
  "properties": {
    "addr:full":"247 Willow Rd Fitzgerald GA 31750",
    "addr:housenumber":"247",
    "addr:postcode":"31750",
    "addr:street":"Willow Rd",
    "iso:country":"US",
    "sg:address":"247 Willow Rd",
    "sg:city":"Fitzgerald",
    "sg:classifiers":[
        {
            "category":"Farming",
            "subcategory":"Farm",
            "type":"Manufacturing & Wholesale Goods"
        }
    ],
    "sg:phone":"+1 229 423 7243",
    "sg:postcode":"31750",
    "sg:province":"GA",
    "sg:tags":[
        "crop",
        "general"
    ],
    "wof:name":"Luke John",
    "wof:placetype":"venue"
},
  "geometry": {"coordinates":[-83.381725,31.782845],"type":"Point"}
}