{
  "type": "Feature",
  "properties": {
    "addr:full":"1660 Great Oaks Dr Lawrenceville GA 30045",
    "addr:housenumber":"1660",
    "addr:postcode":"30045",
    "addr:street":"Great Oaks Dr",
    "iso:country":"US",
    "sg:address":"1660 Great Oaks Dr",
    "sg:city":"Lawrenceville",
    "sg:classifiers":[
        {
            "category":"Health Services",
            "subcategory":"Clinic",
            "type":"Services"
        }
    ],
    "sg:phone":"+1 678 320 0001",
    "sg:postcode":"30045",
    "sg:province":"GA",
    "sg:tags":[
        "information",
        "alcoholism",
        "treatment"
    ],
    "wof:name":"Alcohol Abuse Addiciton Helpin",
    "wof:placetype":"venue"
},
  "geometry": {"coordinates":[-83.98252100000001,33.903099],"type":"Point"}
}