{
  "type": "Feature",
  "properties": {
    "addr:full":"1060 Olde Towne Ln Woodstock GA 30189",
    "addr:housenumber":"1060",
    "addr:postcode":"30189",
    "addr:street":"Olde Towne Ln",
    "iso:country":"US",
    "sg:address":"1060 Olde Towne Ln",
    "sg:city":"Woodstock",
    "sg:classifiers":[
        {
            "category":"Personal",
            "subcategory":"Beauty Salon",
            "type":"Services"
        }
    ],
    "sg:phone":"+1 770 517 5204",
    "sg:postcode":"30189",
    "sg:province":"GA",
    "wof:name":"Aspen Falls Auto Spa",
    "wof:placetype":"venue"
},
  "geometry": {"coordinates":[-84.569136,34.130339],"type":"Point"}
}