{
  "type": "Feature",
  "properties": {
    "iso:country":"US",
    "sg:address":"2303 W Broad St",
    "sg:city":"Athens",
    "sg:classifiers":[
        {
            "category":"Food & Beverages",
            "subcategory":"Liquor & Beverages",
            "type":"Retail Goods"
        }
    ],
    "sg:phone":"+1 706 549 1686",
    "sg:postcode":"30606",
    "sg:province":"GA",
    "sg:tags":[
        "alcoholic"
    ],
    "wof:name":"ABC Package Store",
    "wof:placetype":"venue"
},
  "geometry": {"coordinates":[-83.414132,33.948624],"type":"Point"}
}