{
  "type": "Feature",
  "properties": {
    "addr:full":"107 College St Carrollton GA 30117",
    "addr:housenumber":"107",
    "addr:postcode":"30117",
    "addr:street":"College St",
    "iso:country":"US",
    "sg:address":"107 College St",
    "sg:city":"Carrollton",
    "sg:classifiers":[
        {
            "category":"Social Services",
            "type":"Services"
        }
    ],
    "sg:phone":"+1 770 834 3643",
    "sg:postcode":"30117",
    "sg:province":"GA",
    "sg:tags":[
        "counseling"
    ],
    "wof:name":"Carrollton Counseling Svc",
    "wof:placetype":"venue"
},
  "geometry": {"coordinates":[-85.072484,33.580589],"type":"Point"}
}