{
  "type": "Feature",
  "properties": {
    "iso:country":"US",
    "sg:address":"4600 Frederick Dr SW",
    "sg:city":"Atlanta",
    "sg:classifiers":[
        {
            "category":"Utilities",
            "subcategory":"Refuse",
            "type":"Services"
        }
    ],
    "sg:phone":"+1 404 691 5348",
    "sg:postcode":"30336",
    "sg:province":"GA",
    "sg:tags":[
        "system"
    ],
    "wof:name":"B and B Pallet and Recycling",
    "wof:placetype":"venue"
},
  "geometry": {"coordinates":[-84.53916599999999,33.765703],"type":"Point"}
}