{
  "type": "Feature",
  "properties": {
    "iso:country":"US",
    "sg:address":"2488 Murfield Way",
    "sg:city":"Jasper",
    "sg:classifiers":[
        {
            "category":"Wholesale",
            "subcategory":"Chemicals & Plastics",
            "type":"Manufacturing & Wholesale Goods"
        }
    ],
    "sg:phone":"+1 706 268 1220",
    "sg:postcode":"30143",
    "sg:province":"GA",
    "wof:name":"Chase Plastic Services Inc",
    "wof:placetype":"venue"
},
  "geometry": {"coordinates":[-84.27493200000001,34.460394],"type":"Point"}
}