{
  "type": "Feature",
  "properties": {
    "iso:country":"US",
    "sg:address":"1560 Indian Trail Lilburn Rd",
    "sg:city":"Norcross",
    "sg:classifiers":[
        {
            "category":"Shopping",
            "subcategory":"Jewelry",
            "type":"Retail Goods"
        }
    ],
    "sg:phone":"+1 770 279 8166",
    "sg:postcode":"30093",
    "sg:province":"GA",
    "wof:name":"Qp Jewelry",
    "wof:placetype":"venue"
},
  "geometry": {"coordinates":[-84.169831,33.9217],"type":"Point"}
}