{
  "type": "Feature",
  "properties": {
    "iso:country":"US",
    "sg:address":"2340 Holcomb Bridge Rd",
    "sg:city":"Roswell",
    "sg:classifiers":[
        {
            "category":"Shopping",
            "subcategory":"Department Store",
            "type":"Retail Goods"
        }
    ],
    "sg:phone":"+1 678 795 9952",
    "sg:postcode":"30076",
    "sg:province":"GA",
    "wof:name":"Kohls Department Stores Inc",
    "wof:placetype":"venue"
},
  "geometry": {"coordinates":[-84.289737,34.002302],"type":"Point"}
}