{
  "type": "Feature",
  "properties": {
    "iso:country":"US",
    "sg:address":"20 Brae Mill Ct",
    "sg:city":"Dallas",
    "sg:classifiers":[
        {
            "category":"Retail",
            "subcategory":"Auto Repair",
            "type":"Services"
        }
    ],
    "sg:phone":"+1 770 941 7468",
    "sg:postcode":"30157",
    "sg:province":"GA",
    "sg:tags":[
        "tire"
    ],
    "wof:name":"Mikes Tire",
    "wof:placetype":"venue"
},
  "geometry": {"coordinates":[-84.827535,33.862795],"type":"Point"}
}