{
  "type": "Feature",
  "properties": {
    "iso:country":"US",
    "sg:address":"273 Shiloh Rd",
    "sg:city":"Douglas",
    "sg:classifiers":[
        {
            "category":"Farming",
            "subcategory":"Farm",
            "type":"Manufacturing & Wholesale Goods"
        }
    ],
    "sg:phone":"+1 912 384 7310",
    "sg:postcode":"31533",
    "sg:province":"GA",
    "sg:tags":[
        "crop",
        "general"
    ],
    "wof:name":"Ray Lee",
    "wof:placetype":"venue"
},
  "geometry": {"coordinates":[-82.788177,31.510184],"type":"Point"}
}