{
  "type": "Feature",
  "properties": {
    "addr:full":"5985 Old National Hwy Atlanta GA 30349",
    "addr:housenumber":"5985",
    "addr:postcode":"30349",
    "addr:street":"Old National Hwy",
    "iso:country":"US",
    "sg:address":"5985 Old National Hwy",
    "sg:city":"Atlanta",
    "sg:classifiers":[
        {
            "category":"Professional",
            "subcategory":"Management & Consulting",
            "type":"Services"
        },
        {
            "category":"Banks & Credit Unions",
            "subcategory":"Financial Services",
            "type":"Services"
        }
    ],
    "sg:phone":"+1 770 909 3008",
    "sg:postcode":"30349",
    "sg:province":"GA",
    "sg:tags":[
        "consultant",
        "financing",
        "planning"
    ],
    "wof:name":"Riley Financial",
    "wof:placetype":"venue"
},
  "geometry": {"coordinates":[-84.468378,33.59201],"type":"Point"}
}