{
  "type": "Feature",
  "properties": {
    "addr:full":"126 Hicks Dr SE Rome GA 30161",
    "addr:housenumber":"126",
    "addr:postcode":"ga 30161",
    "addr:street":"Hicks Dr Se",
    "iso:country":"US",
    "sg:address":"126 Hicks Dr SE",
    "sg:city":"Rome",
    "sg:classifiers":[
        {
            "category":"Food & Beverages",
            "subcategory":"Specialty",
            "type":"Retail Goods"
        },
        {
            "category":"Food & Beverages",
            "subcategory":"Fruits & Vegetables",
            "type":"Retail Goods"
        },
        {
            "category":"Shopping",
            "subcategory":"Pharmacy",
            "type":"Retail Goods"
        }
    ],
    "sg:phone":"+1 706 234 2054",
    "sg:postcode":"30161",
    "sg:province":"GA",
    "sg:tags":[
        "product",
        "wellness",
        "vitamin",
        "diet",
        "supplement",
        "health",
        "herb"
    ],
    "sg:website":"http://www.gnc.com",
    "wof:name":"GNC",
    "wof:placetype":"venue"
},
  "geometry": {"coordinates":[-85.162595,34.25245],"type":"Point"}
}