{
  "type": "Feature",
  "properties": {
    "addr:full":"6312 Fox Chapel Dr Columbus GA 31904",
    "addr:housenumber":"6312",
    "addr:postcode":"31904",
    "addr:street":"Fox Chapel Dr",
    "iso:country":"US",
    "sg:address":"6312 Fox Chapel Dr",
    "sg:city":"Columbus",
    "sg:classifiers":[
        {
            "category":"Professional",
            "subcategory":"Computer Services",
            "type":"Services"
        }
    ],
    "sg:phone":"+1 706 322 7174",
    "sg:postcode":"31904",
    "sg:province":"GA",
    "wof:name":"Wen Jo Inc",
    "wof:placetype":"venue"
},
  "geometry": {"coordinates":[-84.96508900000001,32.537168],"type":"Point"}
}