{
  "type": "Feature",
  "properties": {
    "addr:full":"6160 Peachtree Dunwoody Rd Atlanta GA 30328",
    "addr:housenumber":"6160",
    "addr:postcode":"30328",
    "addr:street":"Peachtree Dunwoody Rd",
    "iso:country":"US",
    "sg:address":"6160 Peachtree Dunwoody Rd",
    "sg:city":"Atlanta",
    "sg:classifiers":[
        {
            "category":"Wholesale",
            "subcategory":"Electrical",
            "type":"Manufacturing & Wholesale Goods"
        }
    ],
    "sg:phone":"+1 770 392 0002",
    "sg:postcode":"30328",
    "sg:province":"GA",
    "sg:tags":[
        "a",
        "as",
        "company",
        "holding",
        "operates"
    ],
    "wof:name":"Data Radio",
    "wof:placetype":"venue"
},
  "geometry": {"coordinates":[-84.35144200000001,33.923673],"type":"Point"}
}