{
  "type": "Feature",
  "properties": {
    "addr:full":"11 Stoneybrook Ct SE Cartersville GA 30121",
    "addr:housenumber":"11",
    "addr:postcode":"30121",
    "addr:street":"Stoneybrook Ct Se",
    "iso:country":"US",
    "sg:address":"11 Stoneybrook Ct SE",
    "sg:city":"Cartersville",
    "sg:classifiers":[
        {
            "category":"Professional",
            "subcategory":"Accounting & Tax Preparation",
            "type":"Services"
        }
    ],
    "sg:phone":"+1 678 721 5722",
    "sg:postcode":"30121",
    "sg:province":"GA",
    "sg:tags":[
        "bookkeeping",
        "general"
    ],
    "wof:name":"D & L Business Svc",
    "wof:placetype":"venue"
},
  "geometry": {"coordinates":[-84.775842,34.20462],"type":"Point"}
}