{
  "type": "Feature",
  "properties": {
    "iso:country":"US",
    "sg:address":"115 Foxtail Ct",
    "sg:city":"Fayetteville",
    "sg:classifiers":[
        {
            "category":"Professional",
            "subcategory":"Accounting & Tax Preparation",
            "type":"Services"
        }
    ],
    "sg:phone":"+1 770 461 5763",
    "sg:postcode":"30214",
    "sg:province":"GA",
    "sg:tags":[
        "public",
        "accountants-certified"
    ],
    "wof:name":"Janis Phillips, Cpa",
    "wof:placetype":"venue"
},
  "geometry": {"coordinates":[-84.473637,33.490608],"type":"Point"}
}