{
  "type": "Feature",
  "properties": {
    "addr:full":"345 Aylesworth Cove Alpharetta GA 30022",
    "addr:housenumber":"345",
    "addr:postcode":"30022",
    "addr:street":"Aylesworth Cove",
    "iso:country":"US",
    "sg:address":"345 Aylesworth Cove",
    "sg:city":"Alpharetta",
    "sg:classifiers":[
        {
            "category":"Food & Beverages",
            "subcategory":"Specialty",
            "type":"Retail Goods"
        }
    ],
    "sg:phone":"+1 770 360 9641",
    "sg:postcode":"30022",
    "sg:province":"GA",
    "wof:name":"Nibeto LLC",
    "wof:placetype":"venue"
},
  "geometry": {"coordinates":[-84.253787,34.039017],"type":"Point"}
}