{
  "type": "Feature",
  "properties": {
    "iso:country":"US",
    "sg:address":"1254 Scenic Way SW",
    "sg:city":"Lilburn",
    "sg:classifiers":[
        {
            "category":"Building & Trades",
            "subcategory":"Landscaping Services",
            "type":"Services"
        }
    ],
    "sg:phone":"+1 770 921 6007",
    "sg:postcode":"30047",
    "sg:province":"GA",
    "sg:tags":[
        "landscape"
    ],
    "wof:name":"Valdista Company",
    "wof:placetype":"venue"
},
  "geometry": {"coordinates":[-84.124399,33.842147],"type":"Point"}
}