{
  "type": "Feature",
  "properties": {
    "addr:full":"510 14th Street NW Atlanta GA 30318",
    "addr:housenumber":"510",
    "addr:postcode":"30318",
    "addr:street":"14Th Street Nw",
    "iso:country":"US",
    "sg:address":"510 14th Street NW",
    "sg:city":"Atlanta",
    "sg:classifiers":[
        {
            "category":"Shopping",
            "subcategory":"Antiques",
            "type":"Retail Goods"
        }
    ],
    "sg:phone":"+1 404 325 4600",
    "sg:postcode":"30318",
    "sg:province":"GA",
    "wof:name":"14th Street Antiques Market",
    "wof:placetype":"venue"
},
  "geometry": {"coordinates":[-84.40396800000001,33.78617],"type":"Point"}
}