{
  "type": "Feature",
  "properties": {
    "iso:country":"US",
    "sg:address":"65 Jonquil Dr",
    "sg:city":"Carrollton",
    "sg:classifiers":[
        {
            "category":"Freight",
            "type":"Transportation"
        }
    ],
    "sg:phone":"+1 770 834 1180",
    "sg:postcode":"30116",
    "sg:province":"GA",
    "sg:tags":[
        "courier"
    ],
    "wof:name":"Gotto Go",
    "wof:placetype":"venue"
},
  "geometry": {"coordinates":[-85.01086100000001,33.650298],"type":"Point"}
}