{
  "type": "Feature",
  "properties": {
    "iso:country":"US",
    "sg:address":"2392 Cobbham Rd",
    "sg:city":"Thomson",
    "sg:classifiers":[
        {
            "category":"Building & Trades",
            "subcategory":"Construction",
            "type":"Services"
        }
    ],
    "sg:phone":"+1 706 836 2282",
    "sg:postcode":"30824",
    "sg:province":"GA",
    "sg:tags":[
        "house"
    ],
    "wof:name":"Lokey Construction",
    "wof:placetype":"venue"
},
  "geometry": {"coordinates":[-82.450413,33.508422],"type":"Point"}
}