{
  "type": "Feature",
  "properties": {
    "iso:country":"US",
    "sg:address":"214 Sycamore St",
    "sg:city":"Decatur",
    "sg:classifiers":[
        {
            "category":"Organizations",
            "subcategory":"Religious Organization",
            "type":"Services"
        }
    ],
    "sg:phone":"+1 404 378 0014",
    "sg:postcode":"30030",
    "sg:province":"GA",
    "sg:tags":[
        "church"
    ],
    "wof:name":"Decatur Presbyterian Nursery",
    "wof:placetype":"venue"
},
  "geometry": {"coordinates":[-84.293746,33.774645],"type":"Point"}
}