{
  "type": "Feature",
  "properties": {
    "addr:full":"1370 Dogwood Ln Tucker GA 30084",
    "addr:housenumber":"1370",
    "addr:postcode":"30084",
    "addr:street":"Dogwood Ln",
    "iso:country":"US",
    "sg:address":"1370 Dogwood Ln",
    "sg:city":"Tucker",
    "sg:classifiers":[
        {
            "category":"Building & Trades",
            "subcategory":"Construction",
            "type":"Services"
        }
    ],
    "sg:phone":"+1 678 643 7705",
    "sg:postcode":"30084",
    "sg:province":"GA",
    "sg:tags":[
        "carpentry",
        "contractor"
    ],
    "wof:name":"Compani General Carpenters",
    "wof:placetype":"venue"
},
  "geometry": {"coordinates":[-84.215115,33.889594],"type":"Point"}
}