{
  "type": "Feature",
  "properties": {
    "addr:full":"85 Morgan St Columbus GA 31903",
    "addr:housenumber":"85",
    "addr:postcode":"31903",
    "addr:street":"Morgan St",
    "iso:country":"US",
    "sg:address":"85 Morgan St",
    "sg:city":"Columbus",
    "sg:classifiers":[
        {
            "category":"Professional",
            "type":"Services"
        }
    ],
    "sg:phone":"+1 706 545 7957",
    "sg:postcode":"31903",
    "sg:province":"GA",
    "wof:name":"Director of Civilian Personal",
    "wof:placetype":"venue"
},
  "geometry": {"coordinates":[-84.94017100000001,32.408569],"type":"Point"}
}