{
  "type": "Feature",
  "properties": {
    "addr:full":"331 West Ave Cedartown GA 30125",
    "addr:housenumber":"331",
    "addr:postcode":"30125",
    "addr:street":"West Ave",
    "iso:country":"US",
    "sg:address":"331 West Ave",
    "sg:city":"Cedartown",
    "sg:classifiers":[
        {
            "category":"Shopping",
            "subcategory":"Department Store",
            "type":"Retail Goods"
        },
        {
            "category":"Shopping",
            "subcategory":"Discount & Variety Stores",
            "type":"Retail Goods"
        }
    ],
    "sg:phone":"+1 678 246 1498",
    "sg:postcode":"30125",
    "sg:province":"GA",
    "wof:name":"Tjs",
    "wof:placetype":"venue"
},
  "geometry": {"coordinates":[-85.25994900000001,34.01123],"type":"Point"}
}