{
  "type": "Feature",
  "properties": {
    "addr:full":"8970 Homewood Dr Riverdale GA 30274",
    "addr:housenumber":"8970",
    "addr:postcode":"30274",
    "addr:street":"Homewood Dr",
    "iso:country":"US",
    "sg:address":"8970 Homewood Dr",
    "sg:city":"Riverdale",
    "sg:classifiers":[
        {
            "category":"Professional",
            "type":"Services"
        },
        {
            "category":"Building & Trades",
            "subcategory":"Construction",
            "type":"Services"
        }
    ],
    "sg:phone":"+1 404 429 6475",
    "sg:postcode":"30274",
    "sg:province":"GA",
    "sg:tags":[
        "pressure",
        "deck",
        "wash",
        "restoration",
        "cleaning",
        "patio"
    ],
    "wof:name":"Miles Pressure Washing",
    "wof:placetype":"venue"
},
  "geometry": {"coordinates":[-84.39656100000001,33.510649],"type":"Point"}
}