{
  "type": "Feature",
  "properties": {
    "addr:full":"220 State Hwy 54 Jonesboro GA 30236",
    "addr:housenumber":"220",
    "addr:postcode":"30236",
    "addr:street":"State Hwy 54",
    "iso:country":"US",
    "sg:address":"220 State Hwy 54",
    "sg:city":"Jonesboro",
    "sg:classifiers":[
        {
            "category":"Retail",
            "subcategory":"Laundry & Dry Cleaning",
            "type":"Services"
        }
    ],
    "sg:phone":"+1 770 477 7676",
    "sg:postcode":"30236",
    "sg:province":"GA",
    "sg:tags":[
        "garment",
        "agent"
    ],
    "wof:name":"Davids Cleaners Inc",
    "wof:placetype":"venue"
},
  "geometry": {"coordinates":[-84.36265400000001,33.518958],"type":"Point"}
}