{
  "type": "Feature",
  "properties": {
    "iso:country":"US",
    "sg:address":"150 Highland Oaks Ct",
    "sg:city":"Alpharetta",
    "sg:classifiers":[
        {
            "category":"Professional",
            "subcategory":"Detective & Security Services",
            "type":"Services"
        }
    ],
    "sg:phone":"+1 770 360 9725",
    "sg:postcode":"30004",
    "sg:province":"GA",
    "sg:tags":[
        "car"
    ],
    "wof:name":"Digital Security Inc",
    "wof:placetype":"venue"
},
  "geometry": {"coordinates":[-84.295269,34.104524],"type":"Point"}
}