{
  "type": "Feature",
  "properties": {
    "addr:full":"3785 Presidential Pkwy Atlanta GA 30340",
    "addr:housenumber":"3785",
    "addr:postcode":"30340",
    "addr:street":"Presidential Pkwy",
    "iso:country":"US",
    "sg:address":"3785 Presidential Pkwy",
    "sg:city":"Atlanta",
    "sg:classifiers":[
        {
            "category":"Professional",
            "subcategory":"Testing Lab",
            "type":"Services"
        }
    ],
    "sg:phone":"+1 770 457 8177",
    "sg:postcode":"30340",
    "sg:province":"GA",
    "sg:tags":[
        "laboratory",
        "field",
        "environmental"
    ],
    "sg:website":"http://www.aesatlanta.com",
    "wof:name":"Aes",
    "wof:placetype":"venue"
},
  "geometry": {"coordinates":[-84.265353,33.887237],"type":"Point"}
}