{
  "type": "Feature",
  "properties": {
    "addr:full":"7134 Jonesboro Rd Morrow GA 30260",
    "addr:housenumber":"7134",
    "addr:postcode":"30260",
    "addr:street":"Jonesboro Rd",
    "iso:country":"US",
    "sg:address":"7134 Jonesboro Rd",
    "sg:city":"Morrow",
    "sg:classifiers":[
        {
            "category":"Autos & Motor Vehicles",
            "subcategory":"Automobile Sales",
            "type":"Retail Goods"
        },
        {
            "category":"Retail",
            "subcategory":"Auto Repair",
            "type":"Services"
        }
    ],
    "sg:phone":"+1 770 960 0060",
    "sg:postcode":"30260",
    "sg:province":"GA",
    "sg:tags":[
        "car"
    ],
    "wof:name":"Heritage Cadillac Oldsmobile",
    "wof:placetype":"venue"
},
  "geometry": {"coordinates":[-84.345398,33.560799],"type":"Point"}
}