{
  "type": "Feature",
  "properties": {
    "iso:country":"US",
    "sg:address":"4658 Bishop Lake Rd",
    "sg:city":"Marietta",
    "sg:classifiers":[
        {
            "category":"Professional",
            "subcategory":"Advertising",
            "type":"Services"
        }
    ],
    "sg:phone":"+1 770 641 9600",
    "sg:postcode":"30062",
    "sg:province":"GA",
    "sg:tags":[
        "agency"
    ],
    "wof:name":"Burmeister Group",
    "wof:placetype":"venue"
},
  "geometry": {"coordinates":[-84.416792,34.001109],"type":"Point"}
}