{
  "type": "Feature",
  "properties": {
    "iso:country":"US",
    "sg:address":"93 Upper Riverdale Rd",
    "sg:city":"Riverdale",
    "sg:classifiers":[
        {
            "category":"Food & Beverages",
            "subcategory":"Groceries & Convenience Stores",
            "type":"Retail Goods"
        }
    ],
    "sg:phone":"+1 770 991 2655",
    "sg:postcode":"30274",
    "sg:province":"GA",
    "wof:name":"Quik Trip",
    "wof:placetype":"venue"
},
  "geometry": {"coordinates":[-84.39197799999999,33.577242],"type":"Point"}
}