{
  "type": "Feature",
  "properties": {
    "addr:full":"3840 Cherry Ridge Blvd Decatur GA 30034",
    "addr:housenumber":"3840",
    "addr:postcode":"30034",
    "addr:street":"Cherry Ridge Blvd",
    "iso:country":"US",
    "sg:address":"3840 Cherry Ridge Blvd",
    "sg:city":"Decatur",
    "sg:classifiers":[
        {
            "category":"Real Estate",
            "subcategory":"Real Estate Agent",
            "type":"Services"
        }
    ],
    "sg:phone":"+1 404 241 3345",
    "sg:postcode":"30034",
    "sg:province":"GA",
    "wof:name":"Remax Executives The Enclave",
    "wof:placetype":"venue"
},
  "geometry": {"coordinates":[-84.23881299999999,33.676046],"type":"Point"}
}