{
  "type": "Feature",
  "properties": {
    "addr:full":"4071 Britt Dr Macon GA 31204",
    "addr:housenumber":"4071",
    "addr:postcode":"31204",
    "addr:street":"Britt Dr",
    "iso:country":"US",
    "sg:address":"4071 Britt Dr",
    "sg:city":"Macon",
    "sg:classifiers":[
        {
            "category":"Real Estate",
            "subcategory":"Real Estate Operator",
            "type":"Services"
        }
    ],
    "sg:phone":"+1 478 471 8223",
    "sg:postcode":"31204",
    "sg:province":"GA",
    "sg:tags":[
        "apartment"
    ],
    "wof:name":"Seepersaud & Nephew Apt & Real",
    "wof:placetype":"venue"
},
  "geometry": {"coordinates":[-83.68998000000001,32.859],"type":"Point"}
}