{
  "type": "Feature",
  "properties": {
    "addr:full":"206 N Tennessee St Cartersville GA 30120",
    "addr:housenumber":"206",
    "addr:postcode":"30120",
    "addr:street":"N Tennessee St",
    "iso:country":"US",
    "sg:address":"206 N Tennessee St",
    "sg:city":"Cartersville",
    "sg:classifiers":[
        {
            "category":"Shopping",
            "type":"Retail Goods"
        },
        {
            "category":"Food & Beverages",
            "subcategory":"Bakery",
            "type":"Retail Goods"
        }
    ],
    "sg:phone":"+1 770 387 1020",
    "sg:postcode":"30120",
    "sg:province":"GA",
    "sg:tags":[
        "baker",
        "merchandise"
    ],
    "wof:name":"Doves & Cherubs Bakery & Ctrng",
    "wof:placetype":"venue"
},
  "geometry": {"coordinates":[-84.793564,34.170313],"type":"Point"}
}