{
  "type": "Feature",
  "properties": {
    "addr:full":"3162 Heathchase Ln Suwanee GA 30024",
    "addr:housenumber":"3162",
    "addr:postcode":"30024",
    "addr:street":"Heathchase Ln",
    "iso:country":"US",
    "sg:address":"3162 Heathchase Ln",
    "sg:city":"Suwanee",
    "sg:classifiers":[
        {
            "category":"Travel",
            "subcategory":"Hotels & Motels",
            "type":"Entertainment"
        }
    ],
    "sg:phone":"+1 678 765 2653",
    "sg:postcode":"30024",
    "sg:province":"GA",
    "wof:name":"Lakeside Motel",
    "wof:placetype":"venue"
},
  "geometry": {"coordinates":[-84.070767,34.023839],"type":"Point"}
}