{
  "type": "Feature",
  "properties": {
    "addr:full":"615 Ee Butler Pkwy Gainesville GA 30501",
    "addr:housenumber":"615",
    "addr:postcode":"30501",
    "addr:street":"Butler Pkwy",
    "iso:country":"US",
    "sg:address":"615 Ee Butler Pkwy",
    "sg:city":"Gainesville",
    "sg:classifiers":[
        {
            "category":"Food & Beverages",
            "subcategory":"Groceries & Convenience Stores",
            "type":"Retail Goods"
        }
    ],
    "sg:phone":"+1 770 718 3007",
    "sg:postcode":"30501",
    "sg:province":"GA",
    "sg:tags":[
        "gasoline"
    ],
    "wof:name":"Pantry Inc",
    "wof:placetype":"venue"
},
  "geometry": {"coordinates":[-83.82048500000001,34.29684],"type":"Point"}
}