{
  "type": "Feature",
  "properties": {
    "addr:full":"3011 Rainbow Dr Decatur GA 30034",
    "addr:housenumber":"3011",
    "addr:postcode":"30034",
    "addr:street":"Rainbow Dr",
    "iso:country":"US",
    "sg:address":"3011 Rainbow Dr",
    "sg:city":"Decatur",
    "sg:classifiers":[
        {
            "category":"Organizations",
            "subcategory":"Professional Association",
            "type":"Services"
        }
    ],
    "sg:phone":"+1 404 241 8006",
    "sg:postcode":"30034",
    "sg:province":"GA",
    "wof:name":"NAACP",
    "wof:placetype":"venue"
},
  "geometry": {"coordinates":[-84.27074399999999,33.709719],"type":"Point"}
}