{
  "type": "Feature",
  "properties": {
    "addr:full":"1052 Mclendon Dr Decatur GA 30033",
    "addr:housenumber":"1052",
    "addr:postcode":"30033",
    "addr:street":"Mclendon Dr",
    "iso:country":"US",
    "sg:address":"1052 Mclendon Dr",
    "sg:city":"Decatur",
    "sg:classifiers":[
        {
            "category":"Personal",
            "subcategory":"Barber",
            "type":"Services"
        }
    ],
    "sg:phone":"+1 404 294 1072",
    "sg:postcode":"30033",
    "sg:province":"GA",
    "wof:name":"Biffle Clip Barber",
    "wof:placetype":"venue"
},
  "geometry": {"coordinates":[-84.260199,33.809645],"type":"Point"}
}