{
  "type": "Feature",
  "properties": {
    "iso:country":"US",
    "sg:address":"5300 Oakbrook Pkwy",
    "sg:city":"Norcross",
    "sg:classifiers":[
        {
            "category":"Manufacturing",
            "subcategory":"Metals",
            "type":"Manufacturing & Wholesale Goods"
        }
    ],
    "sg:phone":"+1 770 935 4550",
    "sg:postcode":"30093",
    "sg:province":"GA",
    "sg:tags":[
        "fiber",
        "optics",
        "system"
    ],
    "wof:name":"Light",
    "wof:placetype":"venue"
},
  "geometry": {"coordinates":[-84.17898099999999,33.919608],"type":"Point"}
}