{
  "type": "Feature",
  "properties": {
    "addr:full":"638 Springharbor Dr Woodstock GA 30188",
    "addr:housenumber":"638",
    "addr:postcode":"30188",
    "addr:street":"Springharbor Dr",
    "iso:country":"US",
    "sg:address":"638 Springharbor Dr",
    "sg:city":"Woodstock",
    "sg:classifiers":[
        {
            "category":"Professional",
            "type":"Services"
        }
    ],
    "sg:phone":"+1 770 928 1283",
    "sg:postcode":"30188",
    "sg:province":"GA",
    "wof:name":"Executive Systems Plus",
    "wof:placetype":"venue"
},
  "geometry": {"coordinates":[-84.49620899999999,34.142025],"type":"Point"}
}