{
  "type": "Feature",
  "properties": {
    "addr:full":"731 N Lee St Americus GA 31719",
    "addr:housenumber":"731",
    "addr:postcode":"31719",
    "addr:street":"N Lee St",
    "iso:country":"US",
    "sg:address":"731 N Lee St",
    "sg:city":"Americus",
    "sg:classifiers":[
        {
            "category":"Retail",
            "subcategory":"Funeral Services",
            "type":"Services"
        }
    ],
    "sg:phone":"+1 229 924 2343",
    "sg:postcode":"31719",
    "sg:province":"GA",
    "wof:name":"Smith-West Mortuary",
    "wof:placetype":"venue"
},
  "geometry": {"coordinates":[-84.231782,32.082831],"type":"Point"}
}