{
  "type": "Feature",
  "properties": {
    "iso:country":"US",
    "sg:address":"6610 Cameron Rd",
    "sg:city":"Morrow",
    "sg:classifiers":[
        {
            "category":"Retail",
            "subcategory":"Repair Shop",
            "type":"Services"
        }
    ],
    "sg:phone":"+1 678 422 7637",
    "sg:postcode":"30260",
    "sg:province":"GA",
    "wof:name":"Boston Laser Technology",
    "wof:placetype":"venue"
},
  "geometry": {"coordinates":[-84.319079,33.576015],"type":"Point"}
}