{
  "type": "Feature",
  "properties": {
    "addr:full":"2748 Okawana Ct Marietta GA 30068",
    "addr:housenumber":"2748",
    "addr:postcode":"30068",
    "addr:street":"Okawana Ct",
    "iso:country":"US",
    "sg:address":"2748 Okawana Ct",
    "sg:city":"Marietta",
    "sg:classifiers":[
        {
            "category":"Professional",
            "type":"Services"
        }
    ],
    "sg:phone":"+1 770 977 8529",
    "sg:postcode":"30068",
    "sg:province":"GA",
    "wof:name":"Gh Franchising Corp",
    "wof:placetype":"venue"
},
  "geometry": {"coordinates":[-84.471062,33.960445],"type":"Point"}
}