{
  "type": "Feature",
  "properties": {
    "iso:country":"US",
    "sg:address":"2817 Bill Wright Rd",
    "sg:city":"Jefferson",
    "sg:classifiers":[
        {
            "category":"Retail",
            "subcategory":"Auto Rental",
            "type":"Services"
        },
        {
            "category":"Professional",
            "subcategory":"Business Services",
            "type":"Services"
        },
        {
            "category":"Retail",
            "subcategory":"Storage",
            "type":"Services"
        },
        {
            "category":"Freight",
            "type":"Transportation"
        },
        {
            "category":"Manufacturing",
            "subcategory":"Buildings",
            "type":"Manufacturing & Wholesale Goods"
        },
        {
            "category":"Building & Trades",
            "subcategory":"Equipment Rental",
            "type":"Services"
        }
    ],
    "sg:phone":"+1 866 344 4391",
    "sg:postcode":"30549",
    "sg:province":"GA",
    "sg:tags":[
        "renting",
        "cargo",
        "leasing",
        "container",
        "portable",
        "mobile",
        "household",
        "commercial",
        "trailers-offices",
        "trailer",
        "modulars",
        "self",
        "unit",
        "contractors'"
    ],
    "sg:website":"http://ad.doubleclick.net/clk;224317918;45423610;b?http://www.mobilemini.com/branch-locations.php?source=yellowpages",
    "wof:name":"Mobile Mini",
    "wof:placetype":"venue"
},
  "geometry": {"coordinates":[-83.599951,34.182997],"type":"Point"}
}