{
  "type": "Feature",
  "properties": {
    "addr:full":"1897 Godby Rd Atlanta GA 30349",
    "addr:housenumber":"1897",
    "addr:postcode":"30349",
    "addr:street":"Godby Rd",
    "iso:country":"US",
    "sg:address":"1897 Godby Rd",
    "sg:city":"Atlanta",
    "sg:classifiers":[
        {
            "category":"Professional",
            "type":"Services"
        }
    ],
    "sg:phone":"+1 770 996 8058",
    "sg:postcode":"30349",
    "sg:province":"GA",
    "wof:name":"Sherry L Blake PHD",
    "wof:placetype":"venue"
},
  "geometry": {"coordinates":[-84.452202,33.613413],"type":"Point"}
}