{
  "type": "Feature",
  "properties": {
    "iso:country":"US",
    "sg:address":"200 Colonial Homes Dr NW",
    "sg:city":"Atlanta",
    "sg:classifiers":[
        {
            "category":"Real Estate",
            "subcategory":"Real Estate Agent",
            "type":"Services"
        }
    ],
    "sg:phone":"+1 404 355 3155",
    "sg:postcode":"30309",
    "sg:province":"GA",
    "wof:name":"Rejoice Realty",
    "wof:placetype":"venue"
},
  "geometry": {"coordinates":[-84.393036,33.813712],"type":"Point"}
}