{
  "type": "Feature",
  "properties": {
    "addr:full":"3681 Leisure Ct Buford GA 30519",
    "addr:housenumber":"3681",
    "addr:postcode":"30519",
    "addr:street":"Leisure Ct",
    "iso:country":"US",
    "sg:address":"3681 Leisure Ct",
    "sg:city":"Buford",
    "sg:classifiers":[
        {
            "category":"Building & Trades",
            "subcategory":"Construction",
            "type":"Services"
        }
    ],
    "sg:phone":"+1 770 945 1456",
    "sg:postcode":"30519",
    "sg:province":"GA",
    "sg:tags":[
        "contractor"
    ],
    "wof:name":"Ceramic Tile Installatn",
    "wof:placetype":"venue"
},
  "geometry": {"coordinates":[-83.982923,34.086187],"type":"Point"}
}