{
  "type": "Feature",
  "properties": {
    "iso:country":"US",
    "sg:address":"146 Beech Haven Trl SE",
    "sg:city":"Smyrna",
    "sg:classifiers":[
        {
            "category":"Place Of Worship",
            "subcategory":"Church",
            "type":"Public Place"
        },
        {
            "category":"Place Of Worship",
            "type":"Public Place"
        }
    ],
    "sg:phone":"+1 770 436 5310",
    "sg:postcode":"30080",
    "sg:province":"GA",
    "sg:tags":[
        "churches-interdenominational",
        "churches-various",
        "denomination"
    ],
    "wof:name":"Fellowship Christian Center",
    "wof:placetype":"venue"
},
  "geometry": {"coordinates":[-84.48345500000001,33.848347],"type":"Point"}
}