{
  "type": "Feature",
  "properties": {
    "addr:full":"3003 Summit Blvd NE 15th Floor Atlanta GA 30319",
    "addr:housenumber":"3003;15th",
    "addr:postcode":"30319",
    "addr:street":"Summit Blvd Ne;Floor",
    "iso:country":"US",
    "sg:address":"3003 Summit Blvd NE 15th Floor",
    "sg:city":"Atlanta",
    "sg:classifiers":[
        {
            "category":"Professional",
            "subcategory":"Lawyer & Legal Services",
            "type":"Services"
        }
    ],
    "sg:phone":"+1 404 348 4263",
    "sg:postcode":"30319",
    "sg:province":"GA",
    "sg:website":"davisnelsonlaw.com/",
    "wof:name":"Law Offices of Davis W. Nelson",
    "wof:placetype":"venue"
},
  "geometry": {"coordinates":[-84.341548,33.91405],"type":"Point"}
}