{
  "type": "Feature",
  "properties": {
    "addr:full":"186 Metasville Rd Lincolnton GA 30817",
    "addr:housenumber":"186",
    "addr:postcode":"30817",
    "addr:street":"Metasville Rd",
    "iso:country":"US",
    "sg:address":"186 Metasville Rd",
    "sg:city":"Lincolnton",
    "sg:classifiers":[
        {
            "category":"Organizations",
            "subcategory":"Religious Organization",
            "type":"Services"
        }
    ],
    "sg:phone":"+1 706 359 4851",
    "sg:postcode":"30817",
    "sg:province":"GA",
    "sg:tags":[
        "clergy"
    ],
    "wof:name":"Andrews Roy D Rev",
    "wof:placetype":"venue"
},
  "geometry": {"coordinates":[-82.48937599999999,33.793255],"type":"Point"}
}