{
  "type": "Feature",
  "properties": {
    "addr:full":"7215 State Rte 72 E Carlton GA 30627",
    "addr:housenumber":"7215",
    "addr:postcode":"30627",
    "addr:street":"State Rte 72 E",
    "iso:country":"US",
    "sg:address":"7215 State Rte 72 E",
    "sg:city":"Carlton",
    "sg:classifiers":[
        {
            "category":"Autos & Motor Vehicles",
            "subcategory":"Automobile Sales",
            "type":"Retail Goods"
        }
    ],
    "sg:phone":"+1 706 797 3193",
    "sg:postcode":"30627",
    "sg:province":"GA",
    "sg:tags":[
        "car",
        "dealer"
    ],
    "wof:name":"Tiny Town Used Cars",
    "wof:placetype":"venue"
},
  "geometry": {"coordinates":[-83.015275,34.058678],"type":"Point"}
}