{
  "type": "Feature",
  "properties": {
    "addr:full":"262 Carrington Ln Douglasville GA 30135",
    "addr:housenumber":"262",
    "addr:postcode":"30135",
    "addr:street":"Carrington Ln",
    "iso:country":"US",
    "sg:address":"262 Carrington Ln",
    "sg:city":"Douglasville",
    "sg:classifiers":[
        {
            "category":"Professional",
            "subcategory":"Business Services",
            "type":"Services"
        }
    ],
    "sg:phone":"+1 770 364 0536",
    "sg:postcode":"30135",
    "sg:province":"GA",
    "wof:name":"Kvlividze  Manana",
    "wof:placetype":"venue"
},
  "geometry": {"coordinates":[-84.75445499999999,33.711988],"type":"Point"}
}