{
  "type": "Feature",
  "properties": {
    "iso:country":"US",
    "sg:address":"107 N 6th St",
    "sg:city":"Griffin",
    "sg:classifiers":[
        {
            "category":"Professional",
            "subcategory":"Lawyer & Legal Services",
            "type":"Services"
        }
    ],
    "sg:phone":"+1 770 227 5585",
    "sg:postcode":"30223",
    "sg:province":"GA",
    "sg:tags":[
        "attorney"
    ],
    "wof:name":"Howard P Wallace",
    "wof:placetype":"venue"
},
  "geometry": {"coordinates":[-84.262139,33.251324],"type":"Point"}
}