{
  "type": "Feature",
  "properties": {
    "addr:full":"820 W Main St Swainsboro GA 30401",
    "addr:housenumber":"820",
    "addr:postcode":"30401",
    "addr:street":"W Main St",
    "iso:country":"US",
    "sg:address":"820 W Main St",
    "sg:city":"Swainsboro",
    "sg:classifiers":[
        {
            "category":"Building & Trades",
            "subcategory":"Electrical",
            "type":"Services"
        }
    ],
    "sg:phone":"+1 478 237 0798",
    "sg:postcode":"30401",
    "sg:province":"GA",
    "sg:tags":[
        "electrical",
        "contractor"
    ],
    "wof:name":"Bush Electric",
    "wof:placetype":"venue"
},
  "geometry": {"coordinates":[-82.353174,32.588974],"type":"Point"}
}