{
  "type": "Feature",
  "properties": {
    "addr:full":"4809 Rilla Rd Gainesville GA 30506",
    "addr:housenumber":"4809",
    "addr:postcode":"30506",
    "addr:street":"Rilla Rd",
    "iso:country":"US",
    "sg:address":"4809 Rilla Rd",
    "sg:city":"Gainesville",
    "sg:classifiers":[
        {
            "category":"Shopping",
            "subcategory":"Gifts & Souvenirs",
            "type":"Retail Goods"
        }
    ],
    "sg:phone":"+1 678 530 0691",
    "sg:postcode":"30506",
    "sg:province":"GA",
    "wof:name":"Raf Combres Mexican Imports",
    "wof:placetype":"venue"
},
  "geometry": {"coordinates":[-83.847508,34.42304],"type":"Point"}
}