{
  "type": "Feature",
  "properties": {
    "iso:country":"US",
    "sg:address":"751 Windy Hill Rd SE",
    "sg:city":"Smyrna",
    "sg:classifiers":[
        {
            "category":"Personal",
            "subcategory":"Barber",
            "type":"Services"
        }
    ],
    "sg:phone":"+1 770 432 8884",
    "sg:postcode":"30080",
    "sg:province":"GA",
    "wof:name":"Thee Barber & Beauty Salon",
    "wof:placetype":"venue"
},
  "geometry": {"coordinates":[-84.53057200000001,33.894493],"type":"Point"}
}