{
  "type": "Feature",
  "properties": {
    "iso:country":"US",
    "sg:address":"1000 Wynnton Rd",
    "sg:city":"Columbus",
    "sg:classifiers":[
        {
            "category":"Real Estate",
            "subcategory":"Real Estate Agent",
            "type":"Services"
        }
    ],
    "sg:phone":"+1 706 571 2800",
    "sg:postcode":"31906",
    "sg:province":"GA",
    "sg:tags":[
        "authorities",
        "housing"
    ],
    "sg:website":"www.columbushousing.org",
    "wof:name":"Housing Authority Of Columbus",
    "wof:placetype":"venue"
},
  "geometry": {"coordinates":[-84.979688,32.465803],"type":"Point"}
}