{
  "type": "Feature",
  "properties": {
    "iso:country":"US",
    "sg:address":"3115 Cross Country Hill",
    "sg:city":"Columbus",
    "sg:classifiers":[
        {
            "category":"Shopping",
            "subcategory":"Gifts & Souvenirs",
            "type":"Retail Goods"
        }
    ],
    "sg:phone":"+1 706 562 0150",
    "sg:postcode":"31906",
    "sg:province":"GA",
    "sg:tags":[
        "shop"
    ],
    "wof:name":"Tuesday Morning",
    "wof:placetype":"venue"
},
  "geometry": {"coordinates":[-84.94681799999999,32.482453],"type":"Point"}
}