{
  "type": "Feature",
  "properties": {
    "addr:full":"125 Clairemont Ave Ste 170 Decatur GA 30030",
    "addr:housenumber":"125",
    "addr:postcode":"30030",
    "addr:street":"Clairemont Ave Ste 170",
    "iso:country":"US",
    "sg:address":"125 Clairemont Ave Ste 170",
    "sg:city":"Decatur",
    "sg:classifiers":[
        {
            "category":"Professional",
            "subcategory":"Employment Agencies",
            "type":"Services"
        }
    ],
    "sg:phone":"+1 404 370 0205",
    "sg:postcode":"30030",
    "sg:province":"GA",
    "sg:website":"www.staffingone.com",
    "wof:name":"Staffing One Inc",
    "wof:placetype":"venue"
},
  "geometry": {"coordinates":[-84.296333,33.77614],"type":"Point"}
}