{
  "type": "Feature",
  "properties": {
    "addr:full":"250 Sullivan Dr Byron GA 31008",
    "addr:housenumber":"250",
    "addr:postcode":"31008",
    "addr:street":"Sullivan Dr",
    "iso:country":"US",
    "sg:address":"250 Sullivan Dr",
    "sg:city":"Byron",
    "sg:classifiers":[
        {
            "category":"Building & Trades",
            "subcategory":"Construction",
            "type":"Services"
        }
    ],
    "sg:phone":"+1 478 956 3271",
    "sg:postcode":"31008",
    "sg:province":"GA",
    "sg:tags":[
        "well",
        "drilling"
    ],
    "wof:name":"Banner Hardware",
    "wof:placetype":"venue"
},
  "geometry": {"coordinates":[-83.772794,32.625005],"type":"Point"}
}