{
  "type": "Feature",
  "properties": {
    "addr:full":"484 Mulberry St Macon GA 31201",
    "addr:housenumber":"484",
    "addr:postcode":"31201",
    "addr:street":"Mulberry St",
    "iso:country":"US",
    "sg:address":"484 Mulberry St",
    "sg:city":"Macon",
    "sg:classifiers":[
        {
            "category":"Real Estate",
            "subcategory":"Architect",
            "type":"Services"
        }
    ],
    "sg:phone":"+1 478 742 5321",
    "sg:postcode":"31201",
    "sg:province":"GA",
    "wof:name":"Dunwody Beeland Architects",
    "wof:placetype":"venue"
},
  "geometry": {"coordinates":[-83.625502,32.836596],"type":"Point"}
}