{
  "type": "Feature",
  "properties": {
    "iso:country":"US",
    "sg:address":"2208 Medfield Trl NE",
    "sg:city":"Atlanta",
    "sg:classifiers":[
        {
            "category":"Professional",
            "subcategory":"Business Services",
            "type":"Services"
        }
    ],
    "sg:phone":"+1 404 325 0489",
    "sg:postcode":"30345",
    "sg:province":"GA",
    "sg:tags":[
        "proofreading",
        "b",
        "for"
    ],
    "wof:name":"Opturian Solutions LLC",
    "wof:placetype":"venue"
},
  "geometry": {"coordinates":[-84.308488,33.848496],"type":"Point"}
}