{
  "type": "Feature",
  "properties": {
    "iso:country":"US",
    "sg:address":"616 7th St W",
    "sg:city":"Tifton",
    "sg:classifiers":[
        {
            "category":"Autos & Motor Vehicles",
            "subcategory":"Auto Supplies",
            "type":"Retail Goods"
        }
    ],
    "sg:phone":"+1 229 386 2718",
    "sg:postcode":"31794",
    "sg:province":"GA",
    "sg:tags":[
        "automotive",
        "parts",
        "automobile"
    ],
    "sg:website":"www.advanceautoparts.com",
    "wof:name":"Advance Auto Parts Inc",
    "wof:placetype":"venue"
},
  "geometry": {"coordinates":[-83.522555,31.450785],"type":"Point"}
}