{
  "type": "Feature",
  "properties": {
    "addr:full":"1121 Big Creek Rd Ellijay GA 30536",
    "addr:housenumber":"1121",
    "addr:postcode":"30536",
    "addr:street":"Big Creek Rd",
    "iso:country":"US",
    "sg:address":"1121 Big Creek Rd",
    "sg:city":"Ellijay",
    "sg:classifiers":[
        {
            "category":"Wholesale",
            "subcategory":"Auto Parts",
            "type":"Manufacturing & Wholesale Goods"
        }
    ],
    "sg:phone":"+1 706 273 3415",
    "sg:postcode":"30536",
    "sg:province":"GA",
    "sg:tags":[
        "automobile",
        "rebuilt"
    ],
    "wof:name":"Clark's Used Parts & Towing",
    "wof:placetype":"venue"
},
  "geometry": {"coordinates":[-84.39586199999999,34.658992],"type":"Point"}
}