{
  "type": "Feature",
  "properties": {
    "iso:country":"US",
    "sg:address":"500 Simmons Rd",
    "sg:city":"Warner Robins",
    "sg:classifiers":[
        {
            "category":"Farming",
            "subcategory":"Orchard",
            "type":"Manufacturing & Wholesale Goods"
        }
    ],
    "sg:phone":"+1 478 781 6641",
    "sg:postcode":"31093",
    "sg:province":"GA",
    "sg:tags":[
        "fruit",
        "tree"
    ],
    "wof:name":"Hollow Oak Farm",
    "wof:placetype":"venue"
},
  "geometry": {"coordinates":[-83.68924,32.659975],"type":"Point"}
}