{
  "type": "Feature",
  "properties": {
    "iso:country":"US",
    "sg:address":"1190 Collinsworth Rd",
    "sg:city":"Atlanta",
    "sg:classifiers":[
        {
            "category":"Food & Beverages",
            "subcategory":"Groceries & Convenience Stores",
            "type":"Retail Goods"
        }
    ],
    "sg:phone":"+1 770 463 5883",
    "sg:postcode":"30303",
    "sg:province":"GA",
    "wof:name":"Alyce's Amoco II",
    "wof:placetype":"venue"
},
  "geometry": {"coordinates":[-84.39070100000001,33.756302],"type":"Point"}
}