{
  "type": "Feature",
  "properties": {
    "addr:full":"3605 Sandy Plains Rd Marietta GA 30066",
    "addr:housenumber":"3605",
    "addr:postcode":"30066",
    "addr:street":"Sandy Plains Rd",
    "iso:country":"US",
    "sg:address":"3605 Sandy Plains Rd",
    "sg:city":"Marietta",
    "sg:classifiers":[
        {
            "category":"Food & Beverages",
            "subcategory":"Candy",
            "type":"Retail Goods"
        },
        {
            "category":"Food & Beverages",
            "subcategory":"Chocolate",
            "type":"Retail Goods"
        }
    ],
    "sg:phone":"+1 770 509 1294",
    "sg:postcode":"30066",
    "sg:province":"GA",
    "sg:tags":[
        "shop",
        "chocolatiers",
        "store"
    ],
    "wof:name":"Chocolate Jewels",
    "wof:placetype":"venue"
},
  "geometry": {"coordinates":[-84.46126,34.038059],"type":"Point"}
}