{
  "type": "Feature",
  "properties": {
    "iso:country":"US",
    "sg:address":"130 Shamrock Industrial Blvd",
    "sg:city":"Tyrone",
    "sg:classifiers":[
        {
            "category":"Building & Trades",
            "subcategory":"Landscaping Services",
            "type":"Services"
        }
    ],
    "sg:phone":"+1 770 487 3205",
    "sg:postcode":"30290",
    "sg:province":"GA",
    "sg:tags":[
        "lawn",
        "maintenance",
        "grounds"
    ],
    "wof:name":"Ivy Green Lawn Svc",
    "wof:placetype":"venue"
},
  "geometry": {"coordinates":[-84.60879199999999,33.443716],"type":"Point"}
}