{
  "type": "Feature",
  "properties": {
    "addr:full":"64 Old Griffin Rd Mcdonough GA 30253",
    "addr:housenumber":"64",
    "addr:postcode":"30253",
    "addr:street":"Old Griffin Rd",
    "iso:country":"US",
    "sg:address":"64 Old Griffin Rd",
    "sg:city":"Mcdonough",
    "sg:classifiers":[
        {
            "category":"Organizations",
            "subcategory":"Religious Organization",
            "type":"Services"
        }
    ],
    "sg:phone":"+1 770 914 1104",
    "sg:postcode":"30253",
    "sg:province":"GA",
    "sg:tags":[
        "church"
    ],
    "wof:name":"Community United Pentecostal",
    "wof:placetype":"venue"
},
  "geometry": {"coordinates":[-84.148251,33.43465],"type":"Point"}
}