{
  "type": "Feature",
  "properties": {
    "iso:country":"US",
    "sg:address":"60 Morrison St",
    "sg:city":"Watkinsville",
    "sg:classifiers":[
        {
            "category":"Professional",
            "subcategory":"Art Services",
            "type":"Services"
        },
        {
            "category":"Shopping",
            "subcategory":"Clothing, Apparel, & Fashions",
            "type":"Retail Goods"
        }
    ],
    "sg:phone":"+1 706 769 4320",
    "sg:postcode":"30677",
    "sg:province":"GA",
    "sg:tags":[
        "screen",
        "printing",
        "t"
    ],
    "wof:name":"Dawg Prints",
    "wof:placetype":"venue"
},
  "geometry": {"coordinates":[-83.403386,33.852033],"type":"Point"}
}