{
  "type": "Feature",
  "properties": {
    "addr:full":"261 State Rte 155 S Mcdonough GA 30253",
    "addr:housenumber":"261",
    "addr:postcode":"30253",
    "addr:street":"State Rte 155 S",
    "iso:country":"US",
    "sg:address":"261 State Rte 155 S",
    "sg:city":"Mcdonough",
    "sg:classifiers":[
        {
            "category":"Freight",
            "type":"Transportation"
        }
    ],
    "sg:phone":"+1 678 432 5428",
    "sg:postcode":"30253",
    "sg:province":"GA",
    "sg:tags":[
        "trucking"
    ],
    "wof:name":"Highway Transport Inc",
    "wof:placetype":"venue"
},
  "geometry": {"coordinates":[-84.151729,33.42386],"type":"Point"}
}