{
  "type": "Feature",
  "properties": {
    "iso:country":"US",
    "sg:address":"700 E Oglethorpe Blvd",
    "sg:city":"Albany",
    "sg:classifiers":[
        {
            "category":"Autos & Motor Vehicles",
            "subcategory":"Automobile Sales",
            "type":"Retail Goods"
        }
    ],
    "sg:phone":"+1 229 446 4777",
    "sg:postcode":"31705",
    "sg:province":"GA",
    "sg:tags":[
        "car",
        "dealer"
    ],
    "wof:name":"KIA Autosport",
    "wof:placetype":"venue"
},
  "geometry": {"coordinates":[-84.132119,31.573254],"type":"Point"}
}