{
  "type": "Feature",
  "properties": {
    "addr:full":"1308 Veterans Pkwy N Moultrie GA 31788",
    "addr:housenumber":"1308",
    "addr:postcode":"31788",
    "addr:street":"Veterans Pkwy N",
    "iso:country":"US",
    "sg:address":"1308 Veterans Pkwy N",
    "sg:city":"Moultrie",
    "sg:classifiers":[
        {
            "category":"Restaurant",
            "type":"Food & Drink"
        }
    ],
    "sg:menulink":"http://www.allmenus.com/ga/moultrie/238664-royal-waffel-king/menu/",
    "sg:phone":"+1 229 891 3149",
    "sg:postcode":"31788",
    "sg:province":"GA",
    "sg:tags":[
        "american"
    ],
    "wof:name":"Royal Waffel King",
    "wof:placetype":"venue"
},
  "geometry": {"coordinates":[-83.77577100000001,31.205358],"type":"Point"}
}