{
  "type": "Feature",
  "properties": {
    "addr:full":"122 Palmetto St Saint Simons Island GA 31522",
    "addr:housenumber":"122",
    "addr:postcode":"31522",
    "addr:street":"Palmetto St",
    "iso:country":"US",
    "sg:address":"122 Palmetto St",
    "sg:city":"Saint Simons Island",
    "sg:classifiers":[
        {
            "category":"Freight",
            "type":"Transportation"
        }
    ],
    "sg:phone":"+1 912 638 6181",
    "sg:postcode":"31522",
    "sg:province":"GA",
    "wof:name":"Misty Oaks Carriage & Stables",
    "wof:placetype":"venue"
},
  "geometry": {"coordinates":[-81.377568,31.187427],"type":"Point"}
}