{
  "type": "Feature",
  "properties": {
    "addr:full":"590 Macedonia Rd Covington GA 30014",
    "addr:housenumber":"590",
    "addr:postcode":"30014",
    "addr:street":"Macedonia Rd",
    "iso:country":"US",
    "sg:address":"590 Macedonia Rd",
    "sg:city":"Covington",
    "sg:classifiers":[
        {
            "category":"Building & Trades",
            "subcategory":"Construction",
            "type":"Services"
        },
        {
            "category":"Military Area",
            "subcategory":"Armory",
            "type":"Public Place"
        }
    ],
    "sg:phone":"+1 770 787 0401",
    "sg:postcode":"30014",
    "sg:province":"GA",
    "sg:tags":[
        "repair",
        "fence-sales",
        "fence",
        "contractor"
    ],
    "wof:name":"A Plus Fence And Deck Co",
    "wof:placetype":"venue"
},
  "geometry": {"coordinates":[-83.78567700000001,33.509373],"type":"Point"}
}