{
  "type": "Feature",
  "properties": {
    "addr:full":"140 Stonewall Ave W Fayetteville GA 30214",
    "addr:housenumber":"140",
    "addr:postcode":"30214",
    "addr:street":"Stonewall Ave W",
    "iso:country":"US",
    "sg:address":"140 Stonewall Ave W",
    "sg:city":"Fayetteville",
    "sg:classifiers":[
        {
            "category":"Government",
            "subcategory":"Office",
            "type":"Public Place"
        }
    ],
    "sg:phone":"+1 770 461 4357",
    "sg:postcode":"30214",
    "sg:province":"GA",
    "sg:tags":[
        "parish",
        "government-county"
    ],
    "sg:website":"http://www.fayettecountytaxcomm.com",
    "wof:name":"911 Communication Center",
    "wof:placetype":"venue"
},
  "geometry": {"coordinates":[-84.456023,33.447747],"type":"Point"}
}