{
  "type": "Feature",
  "properties": {
    "iso:country":"US",
    "sg:address":"2753 Holly Ridge Cir",
    "sg:city":"Marietta",
    "sg:classifiers":[
        {
            "category":"Building & Trades",
            "subcategory":"Construction",
            "type":"Services"
        }
    ],
    "sg:phone":"+1 770 579 0333",
    "sg:postcode":"30062",
    "sg:province":"GA",
    "sg:tags":[
        "house"
    ],
    "wof:name":"Pocoson Homes LLC",
    "wof:placetype":"venue"
},
  "geometry": {"coordinates":[-84.46933300000001,34.007943],"type":"Point"}
}