{
  "type": "Feature",
  "properties": {
    "iso:country":"US",
    "sg:address":"2865 Woodbine Hill Way",
    "sg:city":"Norcross",
    "sg:classifiers":[
        {
            "category":"Food & Beverages",
            "subcategory":"Specialty",
            "type":"Retail Goods"
        }
    ],
    "sg:phone":"+1 770 242 0270",
    "sg:postcode":"30071",
    "sg:province":"GA",
    "wof:name":"All About Health",
    "wof:placetype":"venue"
},
  "geometry": {"coordinates":[-84.172567,33.968647],"type":"Point"}
}