{
  "type": "Feature",
  "properties": {
    "iso:country":"US",
    "sg:address":"1380 Bridle Path Dr",
    "sg:city":"Lawrenceville",
    "sg:classifiers":[
        {
            "category":"Retail",
            "subcategory":"Repair Shop",
            "type":"Services"
        }
    ],
    "sg:phone":"+1 678 733 0312",
    "sg:postcode":"30045",
    "sg:province":"GA",
    "sg:tags":[
        "electrical"
    ],
    "wof:name":"Lazer Sound Corporation",
    "wof:placetype":"venue"
},
  "geometry": {"coordinates":[-83.994488,33.913853],"type":"Point"}
}