{
  "type": "Feature",
  "properties": {
    "iso:country":"US",
    "sg:address":"636 Exchange Pl NW",
    "sg:city":"Lilburn",
    "sg:classifiers":[
        {
            "category":"Professional",
            "type":"Services"
        }
    ],
    "sg:phone":"+1 770 931 7652",
    "sg:postcode":"30047",
    "sg:province":"GA",
    "sg:tags":[
        "establishment"
    ],
    "wof:name":"Barrow Group LLC",
    "wof:placetype":"venue"
},
  "geometry": {"coordinates":[-84.143907,33.901158],"type":"Point"}
}