{
  "type": "Feature",
  "properties": {
    "iso:country":"US",
    "sg:address":"5881 Glenridge Dr NE Ste 240",
    "sg:city":"Atlanta",
    "sg:phone":"+1 404 705 7066",
    "sg:postcode":"30328",
    "sg:province":"GA",
    "wof:name":"Zagoria Jan S",
    "wof:placetype":"venue"
},
  "geometry": {"coordinates":[-84.362358,33.916302],"type":"Point"}
}