{
  "type": "Feature",
  "properties": {
    "iso:country":"US",
    "sg:address":"78 Atlanta St SE",
    "sg:city":"Marietta",
    "sg:classifiers":[
        {
            "category":"Real Estate",
            "subcategory":"Real Estate Agent",
            "type":"Services"
        }
    ],
    "sg:phone":"+1 770 424 8447",
    "sg:postcode":"30060",
    "sg:province":"GA",
    "sg:website":"www.hudhomesatlanta.com",
    "wof:name":"Sinclair & Assoc Inc",
    "wof:placetype":"venue"
},
  "geometry": {"coordinates":[-84.54898,33.948577],"type":"Point"}
}