{
  "type": "Feature",
  "properties": {
    "addr:full":"3536 Highland Pine Way Duluth GA 30096",
    "addr:housenumber":"3536",
    "addr:postcode":"30096",
    "addr:street":"Highland Pine Way",
    "iso:country":"US",
    "sg:address":"3536 Highland Pine Way",
    "sg:city":"Duluth",
    "sg:classifiers":[
        {
            "category":"Building & Trades",
            "subcategory":"Plumbing",
            "type":"Services"
        }
    ],
    "sg:phone":"+1 770 476 9672",
    "sg:postcode":"30096",
    "sg:province":"GA",
    "sg:tags":[
        "contractor"
    ],
    "wof:name":"Mech Electro Industries",
    "wof:placetype":"venue"
},
  "geometry": {"coordinates":[-84.147644,33.984951],"type":"Point"}
}