{
  "type": "Feature",
  "properties": {
    "addr:full":"318 Columbia Dr Apt 202 Carrollton GA 30117",
    "addr:housenumber":"318;202",
    "addr:postcode":"30117",
    "addr:street":"Columbia Dr Apt",
    "iso:country":"US",
    "sg:address":"318 Columbia Dr Apt 202",
    "sg:city":"Carrollton",
    "sg:classifiers":[
        {
            "category":"Real Estate",
            "subcategory":"Real Estate Operator",
            "type":"Services"
        }
    ],
    "sg:phone":"+1 770 214 8066",
    "sg:postcode":"30117",
    "sg:province":"GA",
    "sg:tags":[
        "apartment"
    ],
    "sg:website":"http://www.mayfairatcarrollton.com",
    "wof:name":"Mayfair At Carrollton",
    "wof:placetype":"venue"
},
  "geometry": {"coordinates":[-85.100967,33.595581],"type":"Point"}
}