{
  "type": "Feature",
  "properties": {
    "iso:country":"US",
    "sg:address":"6750 Camp Valley Rd",
    "sg:city":"Riverdale",
    "sg:classifiers":[
        {
            "category":"Building & Trades",
            "subcategory":"Landscaping Services",
            "type":"Services"
        }
    ],
    "sg:phone":"+1 770 455 0374",
    "sg:postcode":"30296",
    "sg:province":"GA",
    "wof:name":"Ultimate Scapes",
    "wof:placetype":"venue"
},
  "geometry": {"coordinates":[-84.466089,33.566002],"type":"Point"}
}