{
  "type": "Feature",
  "properties": {
    "iso:country":"US",
    "sg:address":"878 Kurtz Rd",
    "sg:city":"Marietta",
    "sg:classifiers":[
        {
            "category":"Professional",
            "type":"Services"
        }
    ],
    "sg:phone":"+1 678 581 5010",
    "sg:postcode":"30066",
    "sg:province":"GA",
    "sg:tags":[
        "tubs-repair",
        "hot",
        "spa"
    ],
    "wof:name":"AAA Pool & Spa Service",
    "wof:placetype":"venue"
},
  "geometry": {"coordinates":[-84.525384,34.002269],"type":"Point"}
}