{
  "type": "Feature",
  "properties": {
    "iso:country":"US",
    "sg:address":"110 Sedgewicke Dr",
    "sg:city":"Peachtree City",
    "sg:classifiers":[
        {
            "category":"Professional",
            "type":"Services"
        }
    ],
    "sg:phone":"+1 770 487 1188",
    "sg:postcode":"30269",
    "sg:province":"GA",
    "wof:name":"Walt Weiss Authorized Mac Tool",
    "wof:placetype":"venue"
},
  "geometry": {"coordinates":[-84.55745,33.435121],"type":"Point"}
}