{
  "type": "Feature",
  "properties": {
    "addr:full":"107 Southwind Ter Dalton GA 30720",
    "addr:housenumber":"107",
    "addr:postcode":"30720",
    "addr:street":"Southwind Ter Dalton",
    "iso:country":"US",
    "sg:address":"107 Southwind Ter",
    "sg:city":"Dalton",
    "sg:classifiers":[
        {
            "category":"Banks & Credit Unions",
            "subcategory":"Investment Brokerage",
            "type":"Services"
        }
    ],
    "sg:phone":"+1 706 226 2084",
    "sg:postcode":"30720",
    "sg:province":"GA",
    "sg:tags":[
        "firm",
        "brokerage",
        "general"
    ],
    "wof:name":"Cbc Trading Inc",
    "wof:placetype":"venue"
},
  "geometry": {"coordinates":[-85.000626,34.716891],"type":"Point"}
}