{
  "type": "Feature",
  "properties": {
    "addr:full":"199 Gabbettville Cir Lagrange GA 30240",
    "addr:housenumber":"199",
    "addr:postcode":"30240",
    "addr:street":"Gabbettville Cir",
    "iso:country":"US",
    "sg:address":"199 Gabbettville Cir",
    "sg:city":"Lagrange",
    "sg:classifiers":[
        {
            "category":"Building & Trades",
            "subcategory":"Construction",
            "type":"Services"
        }
    ],
    "sg:phone":"+1 706 882 8250",
    "sg:postcode":"30240",
    "sg:province":"GA",
    "sg:tags":[
        "paving",
        "contractor"
    ],
    "wof:name":"Jim Bailey Contractor",
    "wof:placetype":"venue"
},
  "geometry": {"coordinates":[-85.138181,32.943867],"type":"Point"}
}