{
  "type": "Feature",
  "properties": {
    "iso:country":"US",
    "sg:address":"693 Hwy 3 N",
    "sg:city":"Hampton",
    "sg:classifiers":[
        {
            "category":"Banks & Credit Unions",
            "subcategory":"Investment Brokerage",
            "type":"Services"
        }
    ],
    "sg:phone":"+1 770 707 4041",
    "sg:postcode":"30228",
    "sg:province":"GA",
    "sg:tags":[
        "advisory",
        "financial"
    ],
    "wof:name":"Financial Solutions",
    "wof:placetype":"venue"
},
  "geometry": {"coordinates":[-84.28505199999999,33.42539],"type":"Point"}
}