{
  "type": "Feature",
  "properties": {
    "addr:full":"50 Electric Ave NW Atlanta GA 30314",
    "addr:housenumber":"50",
    "addr:postcode":"30314",
    "addr:street":"Electric Ave Nw",
    "iso:country":"US",
    "sg:address":"50 Electric Ave NW",
    "sg:city":"Atlanta",
    "sg:classifiers":[
        {
            "category":"Building & Trades",
            "subcategory":"Locksmith",
            "type":"Services"
        }
    ],
    "sg:phone":"+1 404 682 9458",
    "sg:postcode":"30314",
    "sg:province":"GA",
    "sg:tags":[
        "key"
    ],
    "wof:name":"24 Hour Emergency Locksmith",
    "wof:placetype":"venue"
},
  "geometry": {"coordinates":[-84.40511600000001,33.755486],"type":"Point"}
}