{
  "type": "Feature",
  "properties": {
    "addr:full":"3333 Buford Dr Buford GA 30519",
    "addr:housenumber":"3333",
    "addr:postcode":"30519",
    "addr:street":"Buford Dr",
    "iso:country":"US",
    "sg:address":"3333 Buford Dr",
    "sg:city":"Buford",
    "sg:classifiers":[
        {
            "category":"Personal",
            "subcategory":"Beauty Salon",
            "type":"Services"
        }
    ],
    "sg:phone":"+1 678 482 2122",
    "sg:postcode":"30519",
    "sg:province":"GA",
    "wof:name":"Dillard's Hair & Nail Salon",
    "wof:placetype":"venue"
},
  "geometry": {"coordinates":[-83.98545799999999,34.079583],"type":"Point"}
}