{
  "type": "Feature",
  "properties": {
    "addr:full":"590 Nancy St. Marietta GA 30060",
    "addr:housenumber":"590",
    "addr:postcode":"30060",
    "addr:street":"Nancy St.",
    "iso:country":"US",
    "sg:address":"590 Nancy St.",
    "sg:city":"Marietta",
    "sg:classifiers":[
        {
            "category":"Health Services",
            "subcategory":"Doctor",
            "type":"Services"
        }
    ],
    "sg:phone":"+1 770 423 0395",
    "sg:postcode":"30060",
    "sg:province":"GA",
    "sg:website":"summitsurgicalga.com/index.html",
    "wof:name":"Summit Surgical Specialists PC",
    "wof:placetype":"venue"
},
  "geometry": {"coordinates":[-84.55630600000001,33.965456],"type":"Point"}
}