{
  "type": "Feature",
  "properties": {
    "iso:country":"US",
    "sg:address":"381 Cherokee St",
    "sg:city":"Marietta",
    "sg:classifiers":[
        {
            "category":"Professional",
            "subcategory":"Management & Consulting",
            "type":"Services"
        }
    ],
    "sg:phone":"+1 770 919 7070",
    "sg:postcode":"30060",
    "sg:province":"GA",
    "sg:tags":[
        "operations",
        "facility"
    ],
    "wof:name":"Link Resources Inc",
    "wof:placetype":"venue"
},
  "geometry": {"coordinates":[-84.548227,33.961847],"type":"Point"}
}