{
  "type": "Feature",
  "properties": {
    "addr:full":"2920 Bankhead Hwy Lithia Springs GA 30122",
    "addr:housenumber":"2920",
    "addr:postcode":"30122",
    "addr:street":"Bankhead Hwy",
    "iso:country":"US",
    "sg:address":"2920 Bankhead Hwy",
    "sg:city":"Lithia Springs",
    "sg:classifiers":[
        {
            "category":"Autos & Motor Vehicles",
            "subcategory":"Fuel & Gas Station",
            "type":"Retail Goods"
        }
    ],
    "sg:phone":"+1 770 948 4172",
    "sg:postcode":"30122",
    "sg:province":"GA",
    "sg:website":"www.chevron.com",
    "wof:name":"Frog Rock Chevron",
    "wof:placetype":"venue"
},
  "geometry": {"coordinates":[-84.662598,33.7733],"type":"Point"}
}