{
  "type": "Feature",
  "properties": {
    "iso:country":"US",
    "sg:address":"6375 Atlantic Blvd",
    "sg:city":"Norcross",
    "sg:classifiers":[
        {
            "category":"Retail",
            "subcategory":"Repair Shop",
            "type":"Services"
        },
        {
            "category":"Building & Trades",
            "subcategory":"Construction",
            "type":"Services"
        },
        {
            "category":"Wholesale",
            "subcategory":"Home Furnishings",
            "type":"Manufacturing & Wholesale Goods"
        }
    ],
    "sg:phone":"+1 770 447 5555",
    "sg:postcode":"30071",
    "sg:province":"GA",
    "sg:tags":[
        "blind",
        "reupholstery",
        "design",
        "shade",
        "interior",
        "furniture"
    ],
    "wof:name":"BP Upholstery",
    "wof:placetype":"venue"
},
  "geometry": {"coordinates":[-84.23760900000001,33.938839],"type":"Point"}
}