{
  "type": "Feature",
  "properties": {
    "iso:country":"US",
    "sg:address":"4006 Brockett Oaks",
    "sg:city":"Tucker",
    "sg:classifiers":[
        {
            "category":"Wholesale",
            "subcategory":"Groceries",
            "type":"Manufacturing & Wholesale Goods"
        }
    ],
    "sg:phone":"+1 770 491 3867",
    "sg:postcode":"30084",
    "sg:province":"GA",
    "sg:tags":[
        "general"
    ],
    "wof:name":"Main Street Marketing",
    "wof:placetype":"venue"
},
  "geometry": {"coordinates":[-84.223754,33.834381],"type":"Point"}
}