{
  "type": "Feature",
  "properties": {
    "addr:full":"3916 Fleming Rd Albany GA 31705",
    "addr:housenumber":"3916",
    "addr:postcode":"31705",
    "addr:street":"Fleming Rd",
    "iso:country":"US",
    "sg:address":"3916 Fleming Rd",
    "sg:city":"Albany",
    "sg:classifiers":[
        {
            "category":"Recreation",
            "type":"Entertainment"
        }
    ],
    "sg:phone":"+1 229 439 2660",
    "sg:postcode":"31705",
    "sg:province":"GA",
    "wof:name":"Council Capp Barn",
    "wof:placetype":"venue"
},
  "geometry": {"coordinates":[-84.014887,31.54374],"type":"Point"}
}