{
  "type": "Feature",
  "properties": {
    "iso:country":"US",
    "sg:address":"2100 Hilton Ave",
    "sg:city":"Columbus",
    "sg:classifiers":[
        {
            "category":"Social Services",
            "subcategory":"Child Care",
            "type":"Services"
        }
    ],
    "sg:phone":"+1 706 324 1268",
    "sg:postcode":"31906",
    "sg:province":"GA",
    "sg:tags":[
        "kindergarten",
        "academic",
        "school"
    ],
    "wof:name":"St Thomas Day School",
    "wof:placetype":"venue"
},
  "geometry": {"coordinates":[-84.95605500000001,32.48328],"type":"Point"}
}