{
  "type": "Feature",
  "properties": {
    "iso:country":"US",
    "sg:address":"2270 Old Milton Pkwy",
    "sg:city":"Alpharetta",
    "sg:classifiers":[
        {
            "category":"Retail",
            "subcategory":"Pet Boarding",
            "type":"Services"
        }
    ],
    "sg:phone":"+1 770 475 9255",
    "sg:postcode":"30004",
    "sg:province":"GA",
    "sg:tags":[
        "boarding/pet",
        "sitting"
    ],
    "sg:website":"www.ruffntumble.net",
    "wof:name":"Ruff N'tumble",
    "wof:placetype":"venue"
},
  "geometry": {"coordinates":[-84.292,34.070702],"type":"Point"}
}