{
  "type": "Feature",
  "properties": {
    "addr:full":"2482 Waterscape Trl Snellville GA 30078",
    "addr:housenumber":"2482",
    "addr:postcode":"30078",
    "addr:street":"Waterscape Trl",
    "iso:country":"US",
    "sg:address":"2482 Waterscape Trl",
    "sg:city":"Snellville",
    "sg:classifiers":[
        {
            "category":"Professional",
            "type":"Services"
        }
    ],
    "sg:phone":"+1 770 978 8684",
    "sg:postcode":"30078",
    "sg:province":"GA",
    "sg:tags":[
        "establishment"
    ],
    "wof:name":"M J's Future LTD",
    "wof:placetype":"venue"
},
  "geometry": {"coordinates":[-84.03665700000001,33.890091],"type":"Point"}
}