{
  "type": "Feature",
  "properties": {
    "iso:country":"US",
    "sg:address":"425 N Lumpkin St",
    "sg:city":"Athens",
    "sg:classifiers":[
        {
            "category":"Building & Trades",
            "subcategory":"Cleaning & Sanitation",
            "type":"Services"
        },
        {
            "category":"Professional",
            "type":"Services"
        }
    ],
    "sg:phone":"+1 706 354 4645",
    "sg:postcode":"30601",
    "sg:province":"GA",
    "sg:tags":[
        "cleaners",
        "establishment",
        "factory"
    ],
    "wof:name":"Professional Systems",
    "wof:placetype":"venue"
},
  "geometry": {"coordinates":[-83.377855,33.960456],"type":"Point"}
}