{
  "type": "Feature",
  "properties": {
    "addr:full":"1439 Bailey Farm Dr Marietta GA 30064",
    "addr:housenumber":"1439",
    "addr:postcode":"30064",
    "addr:street":"Bailey Farm Dr",
    "iso:country":"US",
    "sg:address":"1439 Bailey Farm Dr",
    "sg:city":"Marietta",
    "sg:classifiers":[
        {
            "category":"Building & Trades",
            "subcategory":"Construction",
            "type":"Services"
        }
    ],
    "sg:phone":"+1 770 499 7848",
    "sg:postcode":"30064",
    "sg:province":"GA",
    "sg:tags":[
        "contractor"
    ],
    "wof:name":"Live Oak Builders",
    "wof:placetype":"venue"
},
  "geometry": {"coordinates":[-84.59564399999999,33.91915],"type":"Point"}
}