{
  "type": "Feature",
  "properties": {
    "iso:country":"US",
    "sg:address":"103 Woodpecker Trl",
    "sg:city":"Guyton",
    "sg:classifiers":[
        {
            "category":"Manufacturing",
            "subcategory":"Retail Goods",
            "type":"Manufacturing & Wholesale Goods"
        }
    ],
    "sg:phone":"+1 912 728 7250",
    "sg:postcode":"31312",
    "sg:province":"GA",
    "sg:tags":[
        "product",
        "mfg"
    ],
    "wof:name":"Badges Etc",
    "wof:placetype":"venue"
},
  "geometry": {"coordinates":[-81.272375,32.212475],"type":"Point"}
}