{
  "type": "Feature",
  "properties": {
    "addr:full":"915 Woodland Trl Smyrna GA 30080",
    "addr:housenumber":"915",
    "addr:postcode":"30080",
    "addr:street":"Woodland Trl",
    "iso:country":"US",
    "sg:address":"915 Woodland Trl",
    "sg:city":"Smyrna",
    "sg:classifiers":[
        {
            "category":"Real Estate",
            "subcategory":"Real Estate Operator",
            "type":"Services"
        }
    ],
    "sg:phone":"+1 770 432 6718",
    "sg:postcode":"30080",
    "sg:province":"GA",
    "sg:tags":[
        "building",
        "apartment"
    ],
    "wof:name":"Woodland Arms Apartments",
    "wof:placetype":"venue"
},
  "geometry": {"coordinates":[-84.52483599999999,33.897406],"type":"Point"}
}