{
  "type": "Feature",
  "properties": {
    "iso:country":"US",
    "sg:address":"2427 Temperance Hall Rd",
    "sg:city":"Rock Spring",
    "sg:classifiers":[
        {
            "category":"Farming",
            "subcategory":"Dairy Farm",
            "type":"Manufacturing & Wholesale Goods"
        }
    ],
    "sg:phone":"+1 706 965 3825",
    "sg:postcode":"30739",
    "sg:province":"GA",
    "wof:name":"Mack Waters",
    "wof:placetype":"venue"
},
  "geometry": {"coordinates":[-85.18747999999999,34.790176],"type":"Point"}
}