{
  "type": "Feature",
  "properties": {
    "addr:full":"1049 Doe Dr Lincolnton GA 30817",
    "addr:housenumber":"1049",
    "addr:postcode":"30817",
    "addr:street":"Doe Dr",
    "iso:country":"US",
    "sg:address":"1049 Doe Dr",
    "sg:city":"Lincolnton",
    "sg:classifiers":[
        {
            "category":"Building & Trades",
            "subcategory":"Landscaping Services",
            "type":"Services"
        }
    ],
    "sg:phone":"+1 706 359 1608",
    "sg:postcode":"30817",
    "sg:province":"GA",
    "sg:tags":[
        "landscape"
    ],
    "wof:name":"Chris Nurs Ldscpg & Lawn Maint",
    "wof:placetype":"venue"
},
  "geometry": {"coordinates":[-82.55264099999999,33.909115],"type":"Point"}
}