{
  "type": "Feature",
  "properties": {
    "iso:country":"US",
    "sg:address":"2636 Peachtree Walk",
    "sg:city":"Duluth",
    "sg:classifiers":[
        {
            "category":"Professional",
            "subcategory":"Computer Services",
            "type":"Services"
        }
    ],
    "sg:phone":"+1 770 982 3400",
    "sg:postcode":"30096",
    "sg:province":"GA",
    "sg:tags":[
        "prepackaged",
        "software"
    ],
    "wof:name":"Cadcam Solutions Inc",
    "wof:placetype":"venue"
},
  "geometry": {"coordinates":[-84.12616800000001,34.005769],"type":"Point"}
}