{
  "type": "Feature",
  "properties": {
    "iso:country":"US",
    "sg:address":"607 W Whitehall St SW",
    "sg:city":"Atlanta",
    "sg:classifiers":[
        {
            "category":"Building & Trades",
            "subcategory":"Locksmith",
            "type":"Services"
        }
    ],
    "sg:phone":"+1 404 682 5270",
    "sg:postcode":"30310",
    "sg:province":"GA",
    "sg:tags":[
        "key"
    ],
    "wof:name":"1 2 3 24 Hour A Locksmith",
    "wof:placetype":"venue"
},
  "geometry": {"coordinates":[-84.413015,33.738095],"type":"Point"}
}