{
  "type": "Feature",
  "properties": {
    "iso:country":"US",
    "sg:address":"210 Spring St",
    "sg:city":"Palmetto",
    "sg:classifiers":[
        {
            "category":"Organizations",
            "subcategory":"Religious Organization",
            "type":"Services"
        }
    ],
    "sg:phone":"+1 770 463 4409",
    "sg:postcode":"30268",
    "sg:province":"GA",
    "wof:name":"Ramah Baptist Church",
    "wof:placetype":"venue"
},
  "geometry": {"coordinates":[-84.662531,33.519987],"type":"Point"}
}