{
  "type": "Feature",
  "properties": {
    "addr:full":"1133 Daves Rd Morganton GA 30560",
    "addr:housenumber":"1133",
    "addr:postcode":"30560",
    "addr:street":"Daves Rd",
    "iso:country":"US",
    "sg:address":"1133 Daves Rd",
    "sg:city":"Morganton",
    "sg:classifiers":[
        {
            "category":"Real Estate",
            "subcategory":"Real Estate Agent",
            "type":"Services"
        }
    ],
    "sg:phone":"+1 706 838 5372",
    "sg:postcode":"30560",
    "sg:province":"GA",
    "wof:name":"Daves Real Estate Family Ltd",
    "wof:placetype":"venue"
},
  "geometry": {"coordinates":[-84.180666,34.847899],"type":"Point"}
}