{
  "type": "Feature",
  "properties": {
    "addr:full":"6100 Neely Farm Dr Norcross GA 30092",
    "addr:housenumber":"6100",
    "addr:postcode":"30092",
    "addr:street":"Neely Farm Dr",
    "iso:country":"US",
    "sg:address":"6100 Neely Farm Dr",
    "sg:city":"Norcross",
    "sg:classifiers":[
        {
            "category":"Professional",
            "subcategory":"Business Services",
            "type":"Services"
        }
    ],
    "sg:phone":"+1 770 416 9805",
    "sg:postcode":"30092",
    "sg:province":"GA",
    "wof:name":"Pavtec Engineering Technology",
    "wof:placetype":"venue"
},
  "geometry": {"coordinates":[-84.254661,33.979345],"type":"Point"}
}