{
  "type": "Feature",
  "properties": {
    "addr:full":"250 Spring St NW 6N311 Atlanta GA 30303",
    "addr:housenumber":"250",
    "addr:postcode":"30303",
    "addr:street":"Spring St Nw",
    "iso:country":"US",
    "sg:address":"250 Spring St NW 6N311",
    "sg:city":"Atlanta",
    "sg:classifiers":[
        {
            "category":"Manufacturing",
            "subcategory":"Jewelry",
            "type":"Manufacturing & Wholesale Goods"
        }
    ],
    "sg:phone":"+1 404 525 7705",
    "sg:postcode":"30303",
    "sg:province":"GA",
    "sg:tags":[
        "repairing"
    ],
    "wof:name":"Rodriquez's Repair",
    "wof:placetype":"venue"
},
  "geometry": {"coordinates":[-84.38902299999999,33.761421],"type":"Point"}
}