{
  "type": "Feature",
  "properties": {
    "addr:full":"110 Queens Way Woodstock GA 30189",
    "addr:housenumber":"110",
    "addr:postcode":"30189",
    "addr:street":"Queens Way",
    "iso:country":"US",
    "sg:address":"110 Queens Way",
    "sg:city":"Woodstock",
    "sg:classifiers":[
        {
            "category":"Banks & Credit Unions",
            "subcategory":"Bank",
            "type":"Services"
        }
    ],
    "sg:phone":"+1 770 852 2022",
    "sg:postcode":"30189",
    "sg:province":"GA",
    "sg:tags":[
        "financing"
    ],
    "wof:name":"Old Fashioned Finance Inc",
    "wof:placetype":"venue"
},
  "geometry": {"coordinates":[-84.561086,34.084988],"type":"Point"}
}