{
  "type": "Feature",
  "properties": {
    "iso:country":"US",
    "sg:address":"20 W Main St",
    "sg:city":"Cartersville",
    "sg:classifiers":[
        {
            "category":"Personal",
            "type":"Services"
        },
        {
            "category":"Sports & Exercise",
            "subcategory":"Gym",
            "type":"Entertainment"
        },
        {
            "category":"Health Services",
            "subcategory":"Health Practitioner",
            "type":"Services"
        }
    ],
    "sg:phone":"+1 770 334 3241",
    "sg:postcode":"30120",
    "sg:province":"GA",
    "sg:tags":[
        "nutritionist",
        "consultant",
        "program",
        "gymnasium",
        "fitness"
    ],
    "wof:name":"Bjj Coffey And Fitness",
    "wof:placetype":"venue"
},
  "geometry": {"coordinates":[-84.795997,34.165077],"type":"Point"}
}