{
  "type": "Feature",
  "properties": {
    "addr:full":"109 Westcliff Blvd Warner Robins GA 31093",
    "addr:housenumber":"109",
    "addr:postcode":"31093",
    "addr:street":"Westcliff Blvd",
    "iso:country":"US",
    "sg:address":"109 Westcliff Blvd",
    "sg:city":"Warner Robins",
    "sg:classifiers":[
        {
            "category":"Professional",
            "subcategory":"Lawyer & Legal Services",
            "type":"Services"
        }
    ],
    "sg:phone":"+1 478 922 6776",
    "sg:postcode":"31093",
    "sg:province":"GA",
    "wof:name":"Alex H Morrow",
    "wof:placetype":"venue"
},
  "geometry": {"coordinates":[-83.65003900000001,32.620251],"type":"Point"}
}