{
  "type": "Feature",
  "properties": {
    "iso:country":"US",
    "sg:address":"2260 John Wells Rd",
    "sg:city":"Hinesville",
    "sg:classifiers":[
        {
            "category":"Building & Trades",
            "subcategory":"Construction",
            "type":"Services"
        }
    ],
    "sg:phone":"+1 912 876 6060",
    "sg:postcode":"31313",
    "sg:province":"GA",
    "sg:tags":[
        "general",
        "contractor"
    ],
    "wof:name":"Dixie Contractors",
    "wof:placetype":"venue"
},
  "geometry": {"coordinates":[-81.73481099999999,31.871525],"type":"Point"}
}