{
  "type": "Feature",
  "properties": {
    "addr:full":"5242 Royal Woods Pkwy Tucker GA 30084",
    "addr:housenumber":"5242",
    "addr:postcode":"30084",
    "addr:street":"Royal Woods Pkwy",
    "iso:country":"US",
    "sg:address":"5242 Royal Woods Pkwy",
    "sg:city":"Tucker",
    "sg:classifiers":[
        {
            "category":"Wholesale",
            "subcategory":"Computers",
            "type":"Manufacturing & Wholesale Goods"
        }
    ],
    "sg:phone":"+1 770 939 8886",
    "sg:postcode":"30084",
    "sg:province":"GA",
    "wof:name":"Monarch Computers",
    "wof:placetype":"venue"
},
  "geometry": {"coordinates":[-84.218002,33.865398],"type":"Point"}
}