{
  "type": "Feature",
  "properties": {
    "iso:country":"US",
    "sg:address":"1716 Glen Arm Dr",
    "sg:city":"Lithonia",
    "sg:classifiers":[
        {
            "category":"Building & Trades",
            "subcategory":"Plumbing",
            "type":"Services"
        }
    ],
    "sg:phone":"+1 770 593 8374",
    "sg:postcode":"30058",
    "sg:province":"GA",
    "sg:tags":[
        "heating",
        "contractor"
    ],
    "wof:name":"Mary Wilson Hvac",
    "wof:placetype":"venue"
},
  "geometry": {"coordinates":[-84.163464,33.739894],"type":"Point"}
}