{
  "type": "Feature",
  "properties": {
    "iso:country":"US",
    "sg:address":"1904 Tremont Rd",
    "sg:city":"Savannah",
    "sg:classifiers":[
        {
            "category":"Home & Garden",
            "subcategory":"Building Materials",
            "type":"Retail Goods"
        },
        {
            "category":"Building & Trades",
            "subcategory":"Electrical",
            "type":"Services"
        }
    ],
    "sg:phone":"+1 912 236 9519",
    "sg:postcode":"31405",
    "sg:province":"GA",
    "sg:tags":[
        "electrician",
        "improvement"
    ],
    "wof:name":"Av Electric Co Inc",
    "wof:placetype":"venue"
},
  "geometry": {"coordinates":[-81.146162,32.078964],"type":"Point"}
}