{
  "type": "Feature",
  "properties": {
    "addr:full":"3200 Pointe Pkwy Ste 400 Norcross GA 30092",
    "addr:housenumber":"3200",
    "addr:postcode":"30092",
    "addr:street":"Pointe Pkwy Ste 400",
    "iso:country":"US",
    "sg:address":"3200 Pointe Pkwy Ste 400",
    "sg:city":"Norcross",
    "sg:classifiers":[
        {
            "category":"Professional",
            "subcategory":"Employment Agencies",
            "type":"Services"
        }
    ],
    "sg:phone":"+1 678 646 0907",
    "sg:postcode":"30092",
    "sg:province":"GA",
    "wof:name":"Local Contact Jobs Inc",
    "wof:placetype":"venue"
},
  "geometry": {"coordinates":[-84.229275,33.950648],"type":"Point"}
}