{
  "type": "Feature",
  "properties": {
    "iso:country":"US",
    "sg:address":"1275 Powers Ferry Rd SE",
    "sg:city":"Marietta",
    "sg:classifiers":[
        {
            "category":"Restaurant",
            "type":"Food & Drink"
        }
    ],
    "sg:phone":"+1 770 618 8451",
    "sg:postcode":"30067",
    "sg:province":"GA",
    "sg:tags":[
        "traditional",
        "american",
        "southern"
    ],
    "wof:name":"Green Tomato Buffet",
    "wof:placetype":"venue"
},
  "geometry": {"coordinates":[-84.46779600000001,33.922001],"type":"Point"}
}