{
  "type": "Feature",
  "properties": {
    "addr:full":"1312 Atlantic Ave Waycross GA 31501",
    "addr:housenumber":"1312",
    "addr:postcode":"31501",
    "addr:street":"Atlantic Ave",
    "iso:country":"US",
    "sg:address":"1312 Atlantic Ave",
    "sg:city":"Waycross",
    "sg:classifiers":[
        {
            "category":"Education",
            "subcategory":"Dance Studio",
            "type":"Public Place"
        }
    ],
    "sg:phone":"+1 912 283 3025",
    "sg:postcode":"31501",
    "sg:province":"GA",
    "wof:name":"Waycross Dance & Gymnastics",
    "wof:placetype":"venue"
},
  "geometry": {"coordinates":[-82.327601,31.216161],"type":"Point"}
}