{
  "type": "Feature",
  "properties": {
    "addr:full":"1512 Piedmont Ave Ste 201 Atlanta GA 30324",
    "addr:housenumber":"1512",
    "addr:postcode":"30324",
    "addr:street":"Piedmont Ave Ste 201",
    "iso:country":"US",
    "sg:address":"1512 Piedmont Ave Ste 201",
    "sg:city":"Atlanta",
    "sg:classifiers":[
        {
            "category":"Professional",
            "subcategory":"Management & Consulting",
            "type":"Services"
        },
        {
            "category":"Health Services",
            "subcategory":"Clinic",
            "type":"Services"
        }
    ],
    "sg:phone":"+1 404 815 1217",
    "sg:postcode":"30324",
    "sg:province":"GA",
    "sg:tags":[
        "consultant",
        "medical"
    ],
    "sg:website":"www.neighborhoodnurse.com",
    "wof:name":"Neighborhood Nurse",
    "wof:placetype":"venue"
},
  "geometry": {"coordinates":[-84.370403,33.796137],"type":"Point"}
}