{
  "type": "Feature",
  "properties": {
    "iso:country":"US",
    "sg:address":"4867 Invermere Ct",
    "sg:city":"Lithonia",
    "sg:classifiers":[
        {
            "category":"Local Transit",
            "type":"Transportation"
        }
    ],
    "sg:phone":"+1 770 378 7335",
    "sg:postcode":"30038",
    "sg:province":"GA",
    "sg:tags":[
        "shuttle",
        "airport"
    ],
    "wof:name":"Jd's Airport Connection",
    "wof:placetype":"venue"
},
  "geometry": {"coordinates":[-84.19083500000001,33.6959],"type":"Point"}
}