{
  "type": "Feature",
  "properties": {
    "iso:country":"US",
    "sg:address":"1996 Cliff Valley Way NE",
    "sg:city":"Atlanta",
    "sg:classifiers":[
        {
            "category":"Health Services",
            "subcategory":"Doctor",
            "type":"Services"
        }
    ],
    "sg:phone":"+1 404 633 2334",
    "sg:postcode":"30329",
    "sg:province":"GA",
    "wof:name":"Scott Roslyn Harden PHD",
    "wof:placetype":"venue"
},
  "geometry": {"coordinates":[-84.323196,33.832199],"type":"Point"}
}