{
  "type": "Feature",
  "properties": {
    "addr:full":"194 Gwinnett Dr Lawrenceville GA 30046",
    "addr:housenumber":"194",
    "addr:postcode":"30046",
    "addr:street":"Gwinnett Dr",
    "iso:country":"US",
    "sg:address":"194 Gwinnett Dr",
    "sg:city":"Lawrenceville",
    "sg:classifiers":[
        {
            "category":"Building & Trades",
            "subcategory":"Locksmith",
            "type":"Services"
        }
    ],
    "sg:phone":"+1 888 239 2281",
    "sg:postcode":"30046",
    "sg:province":"GA",
    "sg:tags":[
        "key"
    ],
    "wof:name":"1 24 Hour Emergency Locksmith",
    "wof:placetype":"venue"
},
  "geometry": {"coordinates":[-83.993427,33.943893],"type":"Point"}
}