{
  "type": "Feature",
  "properties": {
    "iso:country":"US",
    "sg:address":"3330 Rebecca Lake Trce",
    "sg:city":"Fairburn",
    "sg:classifiers":[
        {
            "category":"Professional",
            "type":"Services"
        }
    ],
    "sg:phone":"+1 770 969 1378",
    "sg:postcode":"30213",
    "sg:province":"GA",
    "sg:tags":[
        "establishment"
    ],
    "wof:name":"Three Brothers",
    "wof:placetype":"venue"
},
  "geometry": {"coordinates":[-84.498745,33.561513],"type":"Point"}
}