{
  "type": "Feature",
  "properties": {
    "iso:country":"US",
    "sg:address":"633 Park Crest Pl",
    "sg:city":"Marietta",
    "sg:classifiers":[
        {
            "category":"Banks & Credit Unions",
            "subcategory":"Bank",
            "type":"Services"
        }
    ],
    "sg:phone":"+1 770 579 5433",
    "sg:postcode":"30068",
    "sg:province":"GA",
    "sg:tags":[
        "mortgage"
    ],
    "wof:name":"Hampton Mortgage Corp",
    "wof:placetype":"venue"
},
  "geometry": {"coordinates":[-84.418274,33.964606],"type":"Point"}
}