{
  "type": "Feature",
  "properties": {
    "addr:full":"750 Rocky Cir Blairsville GA 30512",
    "addr:housenumber":"750",
    "addr:postcode":"30512",
    "addr:street":"Rocky Cir",
    "iso:country":"US",
    "sg:address":"750 Rocky Cir",
    "sg:city":"Blairsville",
    "sg:classifiers":[
        {
            "category":"Manufacturing",
            "subcategory":"Tools & Machinery",
            "type":"Manufacturing & Wholesale Goods"
        }
    ],
    "sg:phone":"+1 706 781 3248",
    "sg:postcode":"30512",
    "sg:province":"GA",
    "sg:tags":[
        "machine",
        "shop"
    ],
    "wof:name":"Pro-Tech Machining & Fab Inc",
    "wof:placetype":"venue"
},
  "geometry": {"coordinates":[-84.04481699999999,34.917995],"type":"Point"}
}