{
  "type": "Feature",
  "properties": {
    "iso:country":"US",
    "sg:address":"114 Old Kersey Rd",
    "sg:city":"Jackson",
    "sg:classifiers":[
        {
            "category":"Recreation",
            "type":"Entertainment"
        }
    ],
    "sg:phone":"+1 678 752 0734",
    "sg:postcode":"30233",
    "sg:province":"GA",
    "sg:tags":[
        "camps-recreational"
    ],
    "wof:name":"Edward Kirkland",
    "wof:placetype":"venue"
},
  "geometry": {"coordinates":[-83.886278,33.346643],"type":"Point"}
}