{
  "type": "Feature",
  "properties": {
    "addr:full":"1232 Anderson Ave Augusta GA 30901",
    "addr:housenumber":"1232",
    "addr:postcode":"30901",
    "addr:street":"Anderson Ave",
    "iso:country":"US",
    "sg:address":"1232 Anderson Ave",
    "sg:city":"Augusta",
    "sg:classifiers":[
        {
            "category":"Organizations",
            "subcategory":"Religious Organization",
            "type":"Services"
        }
    ],
    "sg:phone":"+1 706 724 3322",
    "sg:postcode":"30901",
    "sg:province":"GA",
    "sg:tags":[
        "church"
    ],
    "wof:name":"Liberty Baptist Church",
    "wof:placetype":"venue"
},
  "geometry": {"coordinates":[-81.983045,33.459733],"type":"Point"}
}