{
  "type": "Feature",
  "properties": {
    "addr:full":"1343 N Decatur Rd Atlanta GA 30306",
    "addr:housenumber":"1343",
    "addr:postcode":"30306",
    "addr:street":"N Decatur Rd",
    "iso:country":"US",
    "sg:address":"1343 N Decatur Rd",
    "sg:city":"Atlanta",
    "sg:classifiers":[
        {
            "category":"Real Estate",
            "subcategory":"Real Estate Agent",
            "type":"Services"
        }
    ],
    "sg:phone":"+1 404 373 7665",
    "sg:postcode":"30306",
    "sg:province":"GA",
    "wof:name":"Cornerstone Corp",
    "wof:placetype":"venue"
},
  "geometry": {"coordinates":[-84.337608,33.790837],"type":"Point"}
}