{
  "type": "Feature",
  "properties": {
    "iso:country":"US",
    "sg:address":"4841 Bill Gardner Pkwy",
    "sg:city":"Locust Grove",
    "sg:classifiers":[
        {
            "category":"Autos & Motor Vehicles",
            "subcategory":"Fuel & Gas Station",
            "type":"Retail Goods"
        }
    ],
    "sg:phone":"+1 770 898 6666",
    "sg:postcode":"30248",
    "sg:province":"GA",
    "sg:tags":[
        "station",
        "gasoline"
    ],
    "wof:name":"Exxon",
    "wof:placetype":"venue"
},
  "geometry": {"coordinates":[-84.118821,33.354064],"type":"Point"}
}