{
  "type": "Feature",
  "properties": {
    "addr:full":"425 Concord Cir Mcdonough GA 30253",
    "addr:housenumber":"425",
    "addr:postcode":"30253",
    "addr:street":"Concord Cir",
    "iso:country":"US",
    "sg:address":"425 Concord Cir",
    "sg:city":"Mcdonough",
    "sg:classifiers":[
        {
            "category":"Professional",
            "subcategory":"Business Services",
            "type":"Services"
        }
    ],
    "sg:phone":"+1 770 898 9429",
    "sg:postcode":"30253",
    "sg:province":"GA",
    "sg:tags":[
        "interior",
        "consultant",
        "design",
        "decorator"
    ],
    "wof:name":"Ivey's Decor",
    "wof:placetype":"venue"
},
  "geometry": {"coordinates":[-84.18813,33.488671],"type":"Point"}
}