{
  "type": "Feature",
  "properties": {
    "iso:country":"US",
    "sg:address":"460 Vine St",
    "sg:city":"Monroe",
    "sg:classifiers":[
        {
            "category":"Building & Trades",
            "subcategory":"Construction",
            "type":"Services"
        }
    ],
    "sg:phone":"+1 770 207 9262",
    "sg:postcode":"30655",
    "sg:province":"GA",
    "sg:tags":[
        "carpentry",
        "contractor"
    ],
    "wof:name":"Custom Cabinets By Design",
    "wof:placetype":"venue"
},
  "geometry": {"coordinates":[-83.69857399999999,33.774028],"type":"Point"}
}