{
  "type": "Feature",
  "properties": {
    "iso:country":"US",
    "sg:address":"6606 Abercorn St",
    "sg:city":"Savannah",
    "sg:classifiers":[
        {
            "category":"Professional",
            "subcategory":"Management & Consulting",
            "type":"Services"
        }
    ],
    "sg:phone":"+1 912 352 7155",
    "sg:postcode":"31405",
    "sg:province":"GA",
    "wof:name":"Budget Finance Company Inc",
    "wof:placetype":"venue"
},
  "geometry": {"coordinates":[-81.112493,32.015902],"type":"Point"}
}