{
  "type": "Feature",
  "properties": {
    "addr:full":"5015 Old National Hwy # G Atlanta GA 30349",
    "addr:housenumber":"5015",
    "addr:postcode":"30349",
    "addr:street":"Old National Hwy # G",
    "iso:country":"US",
    "sg:address":"5015 Old National Hwy # G",
    "sg:city":"Atlanta",
    "sg:classifiers":[
        {
            "category":"Personal",
            "subcategory":"Beauty Salon",
            "type":"Services"
        }
    ],
    "sg:phone":"+1 404 549 9028",
    "sg:postcode":"30349",
    "sg:province":"GA",
    "sg:tags":[
        "hair",
        "stylist"
    ],
    "wof:name":"Conteh African Hair Braiding",
    "wof:placetype":"venue"
},
  "geometry": {"coordinates":[-84.472883,33.618214],"type":"Point"}
}