{
  "type": "Feature",
  "properties": {
    "addr:full":"169 Nellie Rose St Lyons GA 30436",
    "addr:housenumber":"169",
    "addr:postcode":"30436",
    "addr:street":"Nellie Rose St",
    "iso:country":"US",
    "sg:address":"169 Nellie Rose St",
    "sg:city":"Lyons",
    "sg:classifiers":[
        {
            "category":"Professional",
            "subcategory":"Business Services",
            "type":"Services"
        }
    ],
    "sg:phone":"+1 912 526 7488",
    "sg:postcode":"30436",
    "sg:province":"GA",
    "sg:tags":[
        "translator",
        "interpreter"
    ],
    "wof:name":"Multiservicious Hispanoamerica",
    "wof:placetype":"venue"
},
  "geometry": {"coordinates":[-82.33675100000001,32.205843],"type":"Point"}
}