{
  "type": "Feature",
  "properties": {
    "iso:country":"US",
    "sg:address":"118 Cindy St",
    "sg:city":"Barnesville",
    "sg:phone":"+1 770 358 5163",
    "sg:postcode":"30233",
    "sg:province":"GA",
    "sg:tags":[
        "farm",
        "marketing",
        "cash",
        "regulation",
        "grain",
        "agricultural"
    ],
    "wof:name":"Lamar County Extension Service",
    "wof:placetype":"venue"
},
  "geometry": {"coordinates":[-83.967403,33.30642],"type":"Point"}
}