{
  "type": "Feature",
  "properties": {
    "iso:country":"US",
    "sg:address":"319 N Young St",
    "sg:city":"Thomasville",
    "sg:classifiers":[
        {
            "category":"Home & Garden",
            "subcategory":"Building Materials",
            "type":"Retail Goods"
        },
        {
            "category":"Building & Trades",
            "subcategory":"Construction",
            "type":"Services"
        },
        {
            "category":"Building & Trades",
            "subcategory":"Electrical",
            "type":"Services"
        },
        {
            "category":"Utilities",
            "subcategory":"Cable",
            "type":"Services"
        }
    ],
    "sg:phone":"+1 229 221 4214",
    "sg:postcode":"31792",
    "sg:province":"GA",
    "sg:tags":[
        "industrial",
        "electrician",
        "electric",
        "altering",
        "improvement",
        "pipe",
        "wire",
        "contractors-commercial",
        "underground",
        "contractor",
        "remodeling",
        "locating"
    ],
    "sg:website":"http://www.bigoakelectricalservices.com",
    "wof:name":"Big Oak Electrical Services LLC",
    "wof:placetype":"venue"
},
  "geometry": {"coordinates":[-83.98037600000001,30.844475],"type":"Point"}
}