{
  "type": "Feature",
  "properties": {
    "iso:country":"US",
    "sg:address":"321 Adams St",
    "sg:city":"Decatur",
    "sg:classifiers":[
        {
            "category":"Professional",
            "subcategory":"Management & Consulting",
            "type":"Services"
        }
    ],
    "sg:phone":"+1 404 378 9149",
    "sg:postcode":"30030",
    "sg:province":"GA",
    "sg:tags":[
        "business"
    ],
    "wof:name":"Hallman Smith Consulting",
    "wof:placetype":"venue"
},
  "geometry": {"coordinates":[-84.298219,33.765019],"type":"Point"}
}