{
  "type": "Feature",
  "properties": {
    "iso:country":"US",
    "sg:address":"320 Paulding Ln",
    "sg:city":"Dallas",
    "sg:classifiers":[
        {
            "category":"Insurance",
            "subcategory":"Insurance Agent",
            "type":"Services"
        }
    ],
    "sg:phone":"+1 770 445 4474",
    "sg:postcode":"30132",
    "sg:province":"GA",
    "wof:name":"Mc Adams Insurance",
    "wof:placetype":"venue"
},
  "geometry": {"coordinates":[-84.83414399999999,33.912558],"type":"Point"}
}