{
  "type": "Feature",
  "properties": {
    "addr:full":"72 Rayner Dr Newnan GA 30265",
    "addr:housenumber":"72",
    "addr:postcode":"30265",
    "addr:street":"Rayner Dr",
    "iso:country":"US",
    "sg:address":"72 Rayner Dr",
    "sg:city":"Newnan",
    "sg:classifiers":[
        {
            "category":"Restaurant",
            "type":"Food & Drink"
        }
    ],
    "sg:phone":"+1 770 252 0803",
    "sg:postcode":"30265",
    "sg:province":"GA",
    "sg:tags":[
        "eating"
    ],
    "wof:name":"Cbb Catering",
    "wof:placetype":"venue"
},
  "geometry": {"coordinates":[-84.700338,33.377966],"type":"Point"}
}