{
  "type": "Feature",
  "properties": {
    "iso:country":"US",
    "sg:address":"5650 Hillandale Dr",
    "sg:city":"Lithonia",
    "sg:classifiers":[
        {
            "category":"Real Estate",
            "subcategory":"Real Estate Services",
            "type":"Services"
        }
    ],
    "sg:phone":"+1 888 811 9647",
    "sg:postcode":"30058",
    "sg:province":"GA",
    "sg:tags":[
        "apartment",
        "management",
        "rental",
        "finder"
    ],
    "sg:website":"http://www.forrent.com/apartment-community-profile/1000396.php?cmp=CAC-CSearchProfile",
    "wof:name":"Concepts 21- Hillandale",
    "wof:placetype":"venue"
},
  "geometry": {"coordinates":[-84.158834,33.703602],"type":"Point"}
}