{
  "type": "Feature",
  "properties": {
    "addr:full":"3059 S Cobb Dr SE Smyrna GA 30080",
    "addr:housenumber":"3059",
    "addr:postcode":"30080",
    "addr:street":"S Cobb Dr Se",
    "iso:country":"US",
    "sg:address":"3059 S Cobb Dr SE",
    "sg:city":"Smyrna",
    "sg:classifiers":[
        {
            "category":"Organizations",
            "subcategory":"Religious Organization",
            "type":"Services"
        }
    ],
    "sg:phone":"+1 770 433 8800",
    "sg:postcode":"30080",
    "sg:province":"GA",
    "wof:name":"Faith Christian Center",
    "wof:placetype":"venue"
},
  "geometry": {"coordinates":[-84.529701,33.872898],"type":"Point"}
}