{
  "type": "Feature",
  "properties": {
    "addr:full":"596 Mitchell St Macon GA 31217",
    "addr:housenumber":"596",
    "addr:postcode":"31217",
    "addr:street":"Mitchell St",
    "iso:country":"US",
    "sg:address":"596 Mitchell St",
    "sg:city":"Macon",
    "sg:classifiers":[
        {
            "category":"Building & Trades",
            "subcategory":"Construction",
            "type":"Services"
        }
    ],
    "sg:phone":"+1 478 746 9353",
    "sg:postcode":"31217",
    "sg:province":"GA",
    "sg:tags":[
        "hanging",
        "contractor"
    ],
    "wof:name":"Booze Painting Service",
    "wof:placetype":"venue"
},
  "geometry": {"coordinates":[-83.614216,32.853978],"type":"Point"}
}