{
  "type": "Feature",
  "properties": {
    "addr:full":"155 International Dr Athens GA 30605",
    "addr:housenumber":"155",
    "addr:postcode":"30605",
    "addr:street":"International Dr",
    "iso:country":"US",
    "sg:address":"155 International Dr",
    "sg:city":"Athens",
    "sg:classifiers":[
        {
            "category":"Shopping",
            "subcategory":"Bicycles & Sporting Goods",
            "type":"Retail Goods"
        }
    ],
    "sg:phone":"+1 706 316 3370",
    "sg:postcode":"30605",
    "sg:province":"GA",
    "wof:name":"Sport Kelly",
    "wof:placetype":"venue"
},
  "geometry": {"coordinates":[-83.34612799999999,33.922213],"type":"Point"}
}