{
  "type": "Feature",
  "properties": {
    "addr:full":"3580 Hildon Cir Atlanta GA 30341",
    "addr:housenumber":"3580",
    "addr:postcode":"30341",
    "addr:street":"Hildon Cir",
    "iso:country":"US",
    "sg:address":"3580 Hildon Cir",
    "sg:city":"Atlanta",
    "sg:classifiers":[
        {
            "category":"Professional",
            "type":"Services"
        }
    ],
    "sg:phone":"+1 770 452 7654",
    "sg:postcode":"30341",
    "sg:province":"GA",
    "wof:name":"Yourmarkcom",
    "wof:placetype":"venue"
},
  "geometry": {"coordinates":[-84.31607200000001,33.891531],"type":"Point"}
}