{
  "type": "Feature",
  "properties": {
    "addr:full":"3883 Browns Bridge Rd Cumming GA 30041",
    "addr:housenumber":"3883",
    "addr:postcode":"30041",
    "addr:street":"Browns Bridge Rd",
    "iso:country":"US",
    "sg:address":"3883 Browns Bridge Rd",
    "sg:city":"Cumming",
    "sg:classifiers":[
        {
            "category":"Building & Trades",
            "subcategory":"Landscaping Services",
            "type":"Services"
        }
    ],
    "sg:phone":"+1 678 513 2300",
    "sg:postcode":"30041",
    "sg:province":"GA",
    "wof:name":"Champion Lwn Care",
    "wof:placetype":"venue"
},
  "geometry": {"coordinates":[-84.08413899999999,34.262724],"type":"Point"}
}