{
  "type": "Feature",
  "properties": {
    "iso:country":"US",
    "sg:address":"2346 Hidden Valley Rd",
    "sg:city":"Hiawassee",
    "sg:classifiers":[
        {
            "category":"Wholesale",
            "subcategory":"Non-durable Goods",
            "type":"Manufacturing & Wholesale Goods"
        },
        {
            "category":"Professional",
            "subcategory":"Business Services",
            "type":"Services"
        }
    ],
    "sg:phone":"+1 706 896 9742",
    "sg:postcode":"30546",
    "sg:province":"GA",
    "sg:tags":[
        "broker",
        "merchandise",
        "merchandise-wholesale"
    ],
    "wof:name":"Crime Scene Supply Inc",
    "wof:placetype":"venue"
},
  "geometry": {"coordinates":[-83.76539,34.983901],"type":"Point"}
}