{
  "type": "Feature",
  "properties": {
    "addr:full":"3384 Peachtree Rd NE Ste 900 Atlanta GA 30326",
    "addr:housenumber":"3384",
    "addr:postcode":"30326",
    "addr:street":"Peachtree Rd Ne Ste 900",
    "iso:country":"US",
    "sg:address":"3384 Peachtree Rd NE Ste 900",
    "sg:city":"Atlanta",
    "sg:classifiers":[
        {
            "category":"Professional",
            "subcategory":"Employment Agencies",
            "type":"Services"
        }
    ],
    "sg:phone":"+1 404 239 5630",
    "sg:postcode":"30326",
    "sg:province":"GA",
    "sg:website":"www.lucasgroup.com",
    "wof:name":"Lucas Group",
    "wof:placetype":"venue"
},
  "geometry": {"coordinates":[-84.365595,33.848958],"type":"Point"}
}