{
  "type": "Feature",
  "properties": {
    "iso:country":"US",
    "sg:address":"2020 Federal Rd",
    "sg:city":"Roswell",
    "sg:classifiers":[
        {
            "category":"Professional",
            "subcategory":"Management & Consulting",
            "type":"Services"
        }
    ],
    "sg:phone":"+1 770 594 8717",
    "sg:postcode":"30075",
    "sg:province":"GA",
    "sg:tags":[
        "business"
    ],
    "wof:name":"Bravo Echo Consulting LLC",
    "wof:placetype":"venue"
},
  "geometry": {"coordinates":[-84.386667,34.020513],"type":"Point"}
}