{
  "type": "Feature",
  "properties": {
    "addr:full":"408 Perry St Manchester GA 31816",
    "addr:housenumber":"408",
    "addr:postcode":"31816",
    "addr:street":"Perry St",
    "iso:country":"US",
    "sg:address":"408 Perry St",
    "sg:city":"Manchester",
    "sg:classifiers":[
        {
            "category":"Health Services",
            "subcategory":"Doctor",
            "type":"Services"
        }
    ],
    "sg:phone":"+1 706 846 3128",
    "sg:postcode":"31816",
    "sg:province":"GA",
    "sg:tags":[
        "dentist"
    ],
    "wof:name":"Thomas G Hopkin DDS",
    "wof:placetype":"venue"
},
  "geometry": {"coordinates":[-84.618645,32.860105],"type":"Point"}
}