{
  "type": "Feature",
  "properties": {
    "iso:country":"US",
    "sg:address":"106 Marion Dairy Rd",
    "sg:city":"Lindale",
    "sg:classifiers":[
        {
            "category":"Retail",
            "subcategory":"Repair Shop",
            "type":"Services"
        }
    ],
    "sg:phone":"+1 706 235 5968",
    "sg:postcode":"30147",
    "sg:province":"GA",
    "sg:tags":[
        "repairing",
        "lawn",
        "mower"
    ],
    "wof:name":"Lindale Mo-Shop",
    "wof:placetype":"venue"
},
  "geometry": {"coordinates":[-85.19588299999999,34.162312],"type":"Point"}
}