{
  "type": "Feature",
  "properties": {
    "iso:country":"US",
    "sg:address":"3401 1st Ave",
    "sg:city":"Columbus",
    "sg:classifiers":[
        {
            "category":"Wholesale",
            "subcategory":"Scrap",
            "type":"Manufacturing & Wholesale Goods"
        }
    ],
    "sg:phone":"+1 706 317 4716",
    "sg:postcode":"31904",
    "sg:province":"GA",
    "sg:tags":[
        "recycling",
        "center"
    ],
    "wof:name":"River Mill Record Management",
    "wof:placetype":"venue"
},
  "geometry": {"coordinates":[-84.991349,32.495481],"type":"Point"}
}