{
  "type": "Feature",
  "properties": {
    "iso:country":"US",
    "sg:address":"4090 Paran Pointe Dr NW",
    "sg:city":"Atlanta",
    "sg:classifiers":[
        {
            "category":"Banks & Credit Unions",
            "subcategory":"Investment Brokerage",
            "type":"Services"
        }
    ],
    "sg:phone":"+1 404 237 5142",
    "sg:postcode":"30327",
    "sg:province":"GA",
    "sg:tags":[
        "advisory"
    ],
    "wof:name":"Providence Capital Inc",
    "wof:placetype":"venue"
},
  "geometry": {"coordinates":[-84.436784,33.866117],"type":"Point"}
}