{
  "type": "Feature",
  "properties": {
    "addr:full":"5143 Wispering Pines Dr Gainesville GA 30504",
    "addr:housenumber":"5143",
    "addr:postcode":"30504",
    "addr:street":"Wispering Pines Dr",
    "iso:country":"US",
    "sg:address":"5143 Wispering Pines Dr",
    "sg:city":"Gainesville",
    "sg:classifiers":[
        {
            "category":"Professional",
            "type":"Services"
        }
    ],
    "sg:phone":"+1 770 536 8449",
    "sg:postcode":"30504",
    "sg:province":"GA",
    "wof:name":"Johnny M Mincey",
    "wof:placetype":"venue"
},
  "geometry": {"coordinates":[-83.93165500000001,34.263579],"type":"Point"}
}