{
  "type": "Feature",
  "properties": {
    "addr:full":"1366 Wellbrook Cir NE Conyers GA 30012",
    "addr:housenumber":"1366",
    "addr:postcode":"30012",
    "addr:street":"Wellbrook Cir Ne",
    "iso:country":"US",
    "sg:address":"1366 Wellbrook Cir NE",
    "sg:city":"Conyers",
    "sg:classifiers":[
        {
            "category":"Health Services",
            "subcategory":"Doctor",
            "type":"Services"
        }
    ],
    "sg:phone":"+1 770 602 0852",
    "sg:postcode":"30012",
    "sg:province":"GA",
    "sg:tags":[
        "physician",
        "surgeon"
    ],
    "wof:name":"Diabetes & Endocrinology",
    "wof:placetype":"venue"
},
  "geometry": {"coordinates":[-84.002754,33.679429],"type":"Point"}
}