{
  "type": "Feature",
  "properties": {
    "iso:country":"US",
    "sg:address":"1306 Maple Ave SW",
    "sg:city":"Rome",
    "sg:classifiers":[
        {
            "category":"Personal",
            "subcategory":"Beauty Salon",
            "type":"Services"
        }
    ],
    "sg:phone":"+1 706 234 3519",
    "sg:postcode":"30161",
    "sg:province":"GA",
    "wof:name":"Finishing Touch By Conni",
    "wof:placetype":"venue"
},
  "geometry": {"coordinates":[-85.16729100000001,34.236297],"type":"Point"}
}