{
  "type": "Feature",
  "properties": {
    "iso:country":"US",
    "sg:address":"4245 Christine Ter",
    "sg:city":"Suwanee",
    "sg:classifiers":[
        {
            "category":"Building & Trades",
            "subcategory":"Landscaping Services",
            "type":"Services"
        }
    ],
    "sg:phone":"+1 770 889 1609",
    "sg:postcode":"30024",
    "sg:province":"GA",
    "wof:name":"Suburban Lawns Inc",
    "wof:placetype":"venue"
},
  "geometry": {"coordinates":[-84.130126,34.092906],"type":"Point"}
}