{
  "type": "Feature",
  "properties": {
    "iso:country":"US",
    "sg:address":"627 N Tennessee St",
    "sg:city":"Cartersville",
    "sg:classifiers":[
        {
            "category":"Education",
            "subcategory":"Special Training",
            "type":"Public Place"
        }
    ],
    "sg:phone":"+1 770 387 9125",
    "sg:postcode":"30120",
    "sg:province":"GA",
    "wof:name":"Willow WY Karate Schl/Mrtl Art",
    "wof:placetype":"venue"
},
  "geometry": {"coordinates":[-84.793335,34.177738],"type":"Point"}
}