{
  "type": "Feature",
  "properties": {
    "iso:country":"US",
    "sg:address":"523 New Franklin Rd",
    "sg:city":"Lagrange",
    "sg:classifiers":[
        {
            "category":"Food & Beverages",
            "subcategory":"Bakery",
            "type":"Retail Goods"
        },
        {
            "category":"Wholesale",
            "subcategory":"Groceries",
            "type":"Manufacturing & Wholesale Goods"
        }
    ],
    "sg:phone":"+1 706 884 8622",
    "sg:postcode":"30240",
    "sg:province":"GA",
    "sg:tags":[
        "baker"
    ],
    "wof:name":"Flowers Baking Co",
    "wof:placetype":"venue"
},
  "geometry": {"coordinates":[-85.028637,33.063107],"type":"Point"}
}