{
  "type": "Feature",
  "properties": {
    "iso:country":"US",
    "sg:address":"225 E Render St",
    "sg:city":"La Grange",
    "sg:classifiers":[
        {
            "category":"Manufacturing",
            "subcategory":"Tools & Machinery",
            "type":"Manufacturing & Wholesale Goods"
        }
    ],
    "sg:phone":"+1 706 845 7784",
    "sg:postcode":"30241",
    "sg:province":"GA",
    "sg:tags":[
        "power",
        "mfg"
    ],
    "wof:name":"Murphys Power Equipment",
    "wof:placetype":"venue"
},
  "geometry": {"coordinates":[-85.016458,33.039236],"type":"Point"}
}