{
  "type": "Feature",
  "properties": {
    "iso:country":"US",
    "sg:address":"2215 Fairburn Rd",
    "sg:city":"Douglasville",
    "sg:classifiers":[
        {
            "category":"Shopping",
            "subcategory":"Florist",
            "type":"Retail Goods"
        }
    ],
    "sg:phone":"+1 770 942 5651",
    "sg:postcode":"30135",
    "sg:province":"GA",
    "wof:name":"Blossoms & Bows",
    "wof:placetype":"venue"
},
  "geometry": {"coordinates":[-84.692398,33.745399],"type":"Point"}
}