{
  "type": "Feature",
  "properties": {
    "addr:full":"75 Ridge Rd Canton GA 30114",
    "addr:housenumber":"75",
    "addr:postcode":"30114",
    "addr:street":"Ridge Rd",
    "iso:country":"US",
    "sg:address":"75 Ridge Rd",
    "sg:city":"Canton",
    "sg:classifiers":[
        {
            "category":"Organizations",
            "subcategory":"Religious Organization",
            "type":"Services"
        }
    ],
    "sg:phone":"+1 770 345 5723",
    "sg:postcode":"30114",
    "sg:province":"GA",
    "wof:name":"Hopewell Baptist Pre School",
    "wof:placetype":"venue"
},
  "geometry": {"coordinates":[-84.550386,34.173516],"type":"Point"}
}