{
  "type": "Feature",
  "properties": {
    "addr:full":"990 Cobb Pkwy Marietta GA 30062",
    "addr:housenumber":"990",
    "addr:postcode":"30062",
    "addr:street":"Cobb Pkwy",
    "iso:country":"US",
    "sg:address":"990 Cobb Pkwy",
    "sg:city":"Marietta",
    "sg:classifiers":[
        {
            "category":"Organizations",
            "subcategory":"Religious Organization",
            "type":"Services"
        }
    ],
    "sg:phone":"+1 678 290 7711",
    "sg:postcode":"30062",
    "sg:province":"GA",
    "wof:name":"Calvary Chapel",
    "wof:placetype":"venue"
},
  "geometry": {"coordinates":[-84.547363,33.976442],"type":"Point"}
}