{
  "type": "Feature",
  "properties": {
    "iso:country":"US",
    "sg:address":"438 Beulah Church Rd",
    "sg:city":"Carrollton",
    "sg:classifiers":[
        {
            "category":"Professional",
            "subcategory":"Accounting & Tax Preparation",
            "type":"Services"
        }
    ],
    "sg:phone":"+1 770 834 0405",
    "sg:postcode":"30117",
    "sg:province":"GA",
    "sg:tags":[
        "billing"
    ],
    "wof:name":"Absolute Billing Svc",
    "wof:placetype":"venue"
},
  "geometry": {"coordinates":[-85.106111,33.600627],"type":"Point"}
}