{
  "type": "Feature",
  "properties": {
    "addr:full":"235 Risen Star Ln Alpharetta GA 30005",
    "addr:housenumber":"235",
    "addr:postcode":"30005",
    "addr:street":"Risen Star Ln",
    "iso:country":"US",
    "sg:address":"235 Risen Star Ln",
    "sg:city":"Alpharetta",
    "sg:classifiers":[
        {
            "category":"Professional",
            "type":"Services"
        }
    ],
    "sg:phone":"+1 678 297 7866",
    "sg:postcode":"30005",
    "sg:province":"GA",
    "wof:name":"Gerrolyn L Wood",
    "wof:placetype":"venue"
},
  "geometry": {"coordinates":[-84.204043,34.087972],"type":"Point"}
}