{
  "type": "Feature",
  "properties": {
    "addr:full":"6270 Riverside Dr NW Atlanta GA 30328",
    "addr:housenumber":"6270",
    "addr:postcode":"30328",
    "addr:street":"Riverside Dr Nw",
    "iso:country":"US",
    "sg:address":"6270 Riverside Dr NW",
    "sg:city":"Atlanta",
    "sg:classifiers":[
        {
            "category":"Real Estate",
            "subcategory":"Real Estate Agent",
            "type":"Services"
        }
    ],
    "sg:phone":"+1 404 250 8945",
    "sg:postcode":"30328",
    "sg:province":"GA",
    "wof:name":"Home Buyers Choice Realty Inc",
    "wof:placetype":"venue"
},
  "geometry": {"coordinates":[-84.411596,33.927683],"type":"Point"}
}