{
  "type": "Feature",
  "properties": {
    "addr:full":"3679 Cochise Dr SE Atlanta GA 30339",
    "addr:housenumber":"3679",
    "addr:postcode":"30339",
    "addr:street":"Cochise Dr Se",
    "iso:country":"US",
    "sg:address":"3679 Cochise Dr SE",
    "sg:city":"Atlanta",
    "sg:classifiers":[
        {
            "category":"Communications",
            "subcategory":"Film & Video Production",
            "type":"Services"
        }
    ],
    "sg:phone":"+1 770 438 6565",
    "sg:postcode":"30339",
    "sg:province":"GA",
    "sg:tags":[
        "motion",
        "picture"
    ],
    "wof:name":"The Benk Family Limited Partnership",
    "wof:placetype":"venue"
},
  "geometry": {"coordinates":[-84.457359,33.86196],"type":"Point"}
}