{
  "type": "Feature",
  "properties": {
    "addr:full":"4040 Jonesboro Rd Hampton GA 30228",
    "addr:housenumber":"4040",
    "addr:postcode":"30228",
    "addr:street":"Jonesboro Rd",
    "iso:country":"US",
    "sg:address":"4040 Jonesboro Rd",
    "sg:city":"Hampton",
    "sg:classifiers":[
        {
            "category":"Place Of Worship",
            "subcategory":"Church",
            "type":"Public Place"
        },
        {
            "category":"Place Of Worship",
            "type":"Public Place"
        }
    ],
    "sg:phone":"+1 770 603 2211",
    "sg:postcode":"30228",
    "sg:province":"GA",
    "sg:tags":[
        "churches-non-denominational"
    ],
    "wof:name":"Agape International Ministries Inc",
    "wof:placetype":"venue"
},
  "geometry": {"coordinates":[-84.287475,33.467056],"type":"Point"}
}