{
  "type": "Feature",
  "properties": {
    "addr:full":"2455 Paces Ferry Rd SE Atlanta GA 30339",
    "addr:housenumber":"2455",
    "addr:postcode":"30339",
    "addr:street":"Paces Ferry Rd Se",
    "iso:country":"US",
    "sg:address":"2455 Paces Ferry Rd SE",
    "sg:city":"Atlanta",
    "sg:classifiers":[
        {
            "category":"Banks & Credit Unions",
            "subcategory":"Financial Services",
            "type":"Services"
        }
    ],
    "sg:phone":"+1 770 384 5000",
    "sg:postcode":"30339",
    "sg:province":"GA",
    "sg:tags":[
        "trust",
        "management"
    ],
    "wof:name":"Marcus Foundation",
    "wof:placetype":"venue"
},
  "geometry": {"coordinates":[-84.48423699999999,33.861621],"type":"Point"}
}