{
  "type": "Feature",
  "properties": {
    "addr:full":"6419 Highway 42 Rex GA 30273",
    "addr:housenumber":"6419",
    "addr:postcode":"30273",
    "addr:street":"Highway 42",
    "iso:country":"US",
    "sg:address":"6419 Highway 42",
    "sg:city":"Rex",
    "sg:classifiers":[
        {
            "category":"Autos & Motor Vehicles",
            "subcategory":"Automobile Sales",
            "type":"Retail Goods"
        }
    ],
    "sg:phone":"+1 770 968 3753",
    "sg:postcode":"30273",
    "sg:province":"GA",
    "sg:tags":[
        "dealers-used",
        "car",
        "used",
        "cars-wholesale"
    ],
    "wof:name":"Unique Imports",
    "wof:placetype":"venue"
},
  "geometry": {"coordinates":[-84.284294,33.577247],"type":"Point"}
}