{
  "type": "Feature",
  "properties": {
    "addr:full":"1572 Red Briar Way Jonesboro GA 30236",
    "addr:housenumber":"1572",
    "addr:postcode":"30236",
    "addr:street":"Red Briar Way",
    "iso:country":"US",
    "sg:address":"1572 Red Briar Way",
    "sg:city":"Jonesboro",
    "sg:classifiers":[
        {
            "category":"Professional",
            "subcategory":"Management & Consulting",
            "type":"Services"
        }
    ],
    "sg:phone":"+1 770 473 9875",
    "sg:postcode":"30236",
    "sg:province":"GA",
    "sg:tags":[
        "business"
    ],
    "wof:name":"Private Education Consultant",
    "wof:placetype":"venue"
},
  "geometry": {"coordinates":[-84.345573,33.51234],"type":"Point"}
}