{
  "type": "Feature",
  "properties": {
    "addr:full":"1101 Juniper St NE # 829 Atlanta GA 30309",
    "addr:housenumber":"1101",
    "addr:postcode":"30309",
    "addr:street":"Juniper St Ne # 829",
    "iso:country":"US",
    "sg:address":"1101 Juniper St NE # 829",
    "sg:city":"Atlanta",
    "sg:classifiers":[
        {
            "category":"Shopping",
            "subcategory":"Pets & Pet Supplies",
            "type":"Retail Goods"
        }
    ],
    "sg:phone":"+1 404 874 4477",
    "sg:postcode":"30309",
    "sg:province":"GA",
    "sg:tags":[
        "furnishing",
        "dog",
        "store",
        "cat"
    ],
    "wof:name":"Noahs Ark Pet Products",
    "wof:placetype":"venue"
},
  "geometry": {"coordinates":[-84.382186,33.784971],"type":"Point"}
}