{
  "type": "Feature",
  "properties": {
    "addr:full":"3386 Mount Zion Rd Stockbridge GA 30281",
    "addr:housenumber":"3386",
    "addr:postcode":"30281",
    "addr:street":"Mount Zion Rd",
    "iso:country":"US",
    "sg:address":"3386 Mount Zion Rd",
    "sg:city":"Stockbridge",
    "sg:classifiers":[
        {
            "category":"Retail",
            "subcategory":"Repair Shop",
            "type":"Services"
        },
        {
            "category":"Home & Garden",
            "subcategory":"Carpets & Floor Coverings",
            "type":"Retail Goods"
        }
    ],
    "sg:phone":"+1 866 310 3987",
    "sg:postcode":"30281",
    "sg:province":"GA",
    "sg:tags":[
        "installation",
        "rug"
    ],
    "wof:name":"Trinity Carpet",
    "wof:placetype":"venue"
},
  "geometry": {"coordinates":[-84.280906,33.5514],"type":"Point"}
}