{
  "type": "Feature",
  "properties": {
    "addr:full":"1217 Crestwood Dr SE Atlanta GA 30316",
    "addr:housenumber":"1217",
    "addr:postcode":"30316",
    "addr:street":"Crestwood Dr Se",
    "iso:country":"US",
    "sg:address":"1217 Crestwood Dr SE",
    "sg:city":"Atlanta",
    "sg:classifiers":[
        {
            "category":"Building & Trades",
            "subcategory":"Locksmith",
            "type":"Services"
        }
    ],
    "sg:phone":"+1 800 537 9906",
    "sg:postcode":"30316",
    "sg:province":"GA",
    "sg:tags":[
        "key"
    ],
    "wof:name":"A 1 Emergency Locksmith",
    "wof:placetype":"venue"
},
  "geometry": {"coordinates":[-84.340637,33.730225],"type":"Point"}
}