{
  "type": "Feature",
  "properties": {
    "addr:full":"3255 Peachtree Road Suite 6 Atlanta GA 30305",
    "addr:housenumber":"3255",
    "addr:postcode":"30305",
    "addr:street":"Peachtree Road Suite 6",
    "iso:country":"US",
    "sg:address":"3255 Peachtree Road Suite 6",
    "sg:city":"Atlanta",
    "sg:classifiers":[
        {
            "category":"Shopping",
            "subcategory":"Clothing, Apparel, & Fashions",
            "type":"Retail Goods"
        },
        {
            "category":"Shopping",
            "subcategory":"Bridal",
            "type":"Retail Goods"
        }
    ],
    "sg:phone":"+1 404 842 1955",
    "sg:postcode":"30305",
    "sg:province":"GA",
    "sg:website":"www.ledressboutique.com",
    "wof:name":"Le Dress Boutique",
    "wof:placetype":"venue"
},
  "geometry": {"coordinates":[-84.37099499999999,33.843932],"type":"Point"}
}