{
  "type": "Feature",
  "properties": {
    "iso:country":"US",
    "sg:address":"2975 Gateway Dr NW",
    "sg:city":"Norcross",
    "sg:classifiers":[
        {
            "category":"Professional",
            "subcategory":"Research",
            "type":"Services"
        },
        {
            "category":"Manufacturing",
            "subcategory":"Tools & Machinery",
            "type":"Manufacturing & Wholesale Goods"
        }
    ],
    "sg:phone":"+1 678 966 3400",
    "sg:postcode":"30360",
    "sg:province":"GA",
    "sg:tags":[
        "development",
        "physician",
        "surgeon"
    ],
    "wof:name":"Biocure Inc",
    "wof:placetype":"venue"
},
  "geometry": {"coordinates":[-84.259261,33.932981],"type":"Point"}
}