{
  "type": "Feature",
  "properties": {
    "iso:country":"US",
    "sg:address":"8035 English Rose Way",
    "sg:city":"Roswell",
    "sg:classifiers":[
        {
            "category":"Professional",
            "subcategory":"Business Services",
            "type":"Services"
        }
    ],
    "sg:phone":"+1 678 585 9925",
    "sg:postcode":"30076",
    "sg:province":"GA",
    "wof:name":"Harman & Moore Group LLC",
    "wof:placetype":"venue"
},
  "geometry": {"coordinates":[-84.355992,34.049111],"type":"Point"}
}