{
  "type": "Feature",
  "properties": {
    "iso:country":"US",
    "sg:address":"305 Belgrave Ct",
    "sg:city":"Atlanta",
    "sg:classifiers":[
        {
            "category":"Professional",
            "type":"Services"
        }
    ],
    "sg:phone":"+1 404 344 4234",
    "sg:postcode":"30331",
    "sg:province":"GA",
    "sg:tags":[
        "establishment"
    ],
    "wof:name":"Marks & Sons",
    "wof:placetype":"venue"
},
  "geometry": {"coordinates":[-84.573466,33.715206],"type":"Point"}
}