{
  "type": "Feature",
  "properties": {
    "addr:full":"678 NW Frontage Rd Augusta GA 30907",
    "addr:housenumber":"678",
    "addr:postcode":"30907",
    "addr:street":"Nw Frontage Rd",
    "iso:country":"US",
    "sg:address":"678 NW Frontage Rd",
    "sg:city":"Augusta",
    "sg:classifiers":[
        {
            "category":"Building & Trades",
            "subcategory":"Plumbing",
            "type":"Services"
        }
    ],
    "sg:phone":"+1 706 869 1007",
    "sg:postcode":"30907",
    "sg:province":"GA",
    "sg:tags":[
        "plumbing",
        "contractor"
    ],
    "wof:name":"Clarks Plumbing & Maintenance",
    "wof:placetype":"venue"
},
  "geometry": {"coordinates":[-82.090833,33.492264],"type":"Point"}
}