{
  "type": "Feature",
  "properties": {
    "addr:full":"423 Cole St NE Marietta GA 30060",
    "addr:housenumber":"423",
    "addr:postcode":"30060",
    "addr:street":"Cole St Ne",
    "iso:country":"US",
    "sg:address":"423 Cole St NE",
    "sg:city":"Marietta",
    "sg:classifiers":[
        {
            "category":"Manufacturing",
            "subcategory":"Printing",
            "type":"Manufacturing & Wholesale Goods"
        }
    ],
    "sg:phone":"+1 770 423 7597",
    "sg:postcode":"30060",
    "sg:province":"GA",
    "sg:tags":[
        "newspaper"
    ],
    "wof:name":"Whats Going On",
    "wof:placetype":"venue"
},
  "geometry": {"coordinates":[-84.54272400000001,33.961656],"type":"Point"}
}