{
  "type": "Feature",
  "properties": {
    "addr:full":"451 Norwood St Culloden GA 31016",
    "addr:housenumber":"451",
    "addr:postcode":"31016",
    "addr:street":"Norwood St",
    "iso:country":"US",
    "sg:address":"451 Norwood St",
    "sg:city":"Culloden",
    "sg:classifiers":[
        {
            "category":"Building & Trades",
            "subcategory":"Construction",
            "type":"Services"
        }
    ],
    "sg:phone":"+1 478 885 2434",
    "sg:postcode":"31016",
    "sg:province":"GA",
    "sg:tags":[
        "nonresidential"
    ],
    "wof:name":"W E Holliz Company",
    "wof:placetype":"venue"
},
  "geometry": {"coordinates":[-84.092601,32.869779],"type":"Point"}
}