{
  "type": "Feature",
  "properties": {
    "addr:full":"600 New St Macon GA 31201",
    "addr:housenumber":"600",
    "addr:postcode":"31201",
    "addr:street":"New St",
    "iso:country":"US",
    "sg:address":"600 New St",
    "sg:city":"Macon",
    "sg:classifiers":[
        {
            "category":"Health Services",
            "subcategory":"Medical Lab",
            "type":"Services"
        }
    ],
    "sg:phone":"+1 478 746 4646",
    "sg:postcode":"31201",
    "sg:province":"GA",
    "sg:tags":[
        "laboratory"
    ],
    "wof:name":"Physician Referral Program",
    "wof:placetype":"venue"
},
  "geometry": {"coordinates":[-83.634852,32.83516],"type":"Point"}
}