{
  "type": "Feature",
  "properties": {
    "iso:country":"US",
    "sg:address":"1131 13th St",
    "sg:city":"Columbus",
    "sg:classifiers":[
        {
            "category":"Professional",
            "subcategory":"Secretarial Services",
            "type":"Services"
        }
    ],
    "sg:phone":"+1 706 322 2594",
    "sg:postcode":"31901",
    "sg:province":"GA",
    "sg:tags":[
        "reporting"
    ],
    "wof:name":"Typing Express",
    "wof:placetype":"venue"
},
  "geometry": {"coordinates":[-84.975499,32.470586],"type":"Point"}
}