{
  "type": "Feature",
  "properties": {
    "addr:full":"400 Ernest W Barrett Pkwy Kennesaw GA 30144",
    "addr:housenumber":"400",
    "addr:postcode":"30144",
    "addr:street":"Ernest W Barrett Pkwy",
    "iso:country":"US",
    "sg:address":"400 Ernest W Barrett Pkwy",
    "sg:city":"Kennesaw",
    "sg:classifiers":[
        {
            "category":"Shopping",
            "subcategory":"Clothing, Apparel, & Fashions",
            "type":"Retail Goods"
        }
    ],
    "sg:phone":"+1 678 290 0906",
    "sg:postcode":"30144",
    "sg:province":"GA",
    "sg:tags":[
        "clothing",
        "women's"
    ],
    "sg:website":"www.forever21.com",
    "wof:name":"Forever 21",
    "wof:placetype":"venue"
},
  "geometry": {"coordinates":[-84.563366,34.012723],"type":"Point"}
}