{
  "type": "Feature",
  "properties": {
    "addr:full":"318 Lindbergh Drive NE Atlanta GA 30305",
    "addr:housenumber":"318",
    "addr:postcode":"30305",
    "addr:street":"Lindbergh Drive Ne",
    "iso:country":"US",
    "sg:address":"318 Lindbergh Drive NE",
    "sg:city":"Atlanta",
    "sg:classifiers":[
        {
            "category":"Health Services",
            "subcategory":"Doctor",
            "type":"Services"
        }
    ],
    "sg:phone":"+1 404 812 1980",
    "sg:postcode":"30305",
    "sg:province":"GA",
    "sg:tags":[
        "psychiatrist"
    ],
    "wof:name":"Herron William S MD",
    "wof:placetype":"venue"
},
  "geometry": {"coordinates":[-84.37746799999999,33.822407],"type":"Point"}
}