{
  "type": "Feature",
  "properties": {
    "addr:full":"6 Steve Dr Doraville GA 30340",
    "addr:housenumber":"6",
    "addr:postcode":"30340",
    "addr:street":"Steve Dr",
    "iso:country":"US",
    "sg:address":"6 Steve Dr",
    "sg:city":"Doraville",
    "sg:classifiers":[
        {
            "category":"Manufacturing",
            "subcategory":"Metals",
            "type":"Manufacturing & Wholesale Goods"
        }
    ],
    "sg:phone":"+1 770 448 7240",
    "sg:postcode":"30340",
    "sg:province":"GA",
    "sg:tags":[
        "machine",
        "screw",
        "product"
    ],
    "wof:name":"Guthrie Machine Works",
    "wof:placetype":"venue"
},
  "geometry": {"coordinates":[-84.25305400000001,33.919152],"type":"Point"}
}