{
  "type": "Feature",
  "properties": {
    "iso:country":"US",
    "sg:address":"2175 Providence Oaks St",
    "sg:city":"Alpharetta",
    "sg:classifiers":[
        {
            "category":"Place Of Worship",
            "type":"Public Place"
        }
    ],
    "sg:phone":"+1 404 277 8511",
    "sg:postcode":"30009",
    "sg:province":"GA",
    "sg:tags":[
        "church"
    ],
    "wof:name":"Glaxosmthkline Hldngs Ame",
    "wof:placetype":"venue"
},
  "geometry": {"coordinates":[-84.29935999999999,34.098208],"type":"Point"}
}