{
  "type": "Feature",
  "properties": {
    "addr:full":"210 Battlecreek Rd Jonesboro GA 30236",
    "addr:housenumber":"210",
    "addr:postcode":"30236",
    "addr:street":"Battlecreek Rd",
    "iso:country":"US",
    "sg:address":"210 Battlecreek Rd",
    "sg:city":"Jonesboro",
    "sg:classifiers":[
        {
            "category":"Professional",
            "type":"Services"
        }
    ],
    "sg:phone":"+1 770 968 0575",
    "sg:postcode":"30236",
    "sg:province":"GA",
    "wof:name":"Ramon Jean",
    "wof:placetype":"venue"
},
  "geometry": {"coordinates":[-84.37360700000001,33.5556],"type":"Point"}
}