{
  "type": "Feature",
  "properties": {
    "iso:country":"US",
    "sg:address":"5294 Lawrenceville Hwy",
    "sg:city":"Lilburn",
    "sg:classifiers":[
        {
            "category":"Manufacturing",
            "subcategory":"Printing",
            "type":"Manufacturing & Wholesale Goods"
        }
    ],
    "sg:phone":"+1 770 925 1072",
    "sg:postcode":"30047",
    "sg:province":"GA",
    "sg:tags":[
        "commercial",
        "offset"
    ],
    "wof:name":"Byrd Printing Company",
    "wof:placetype":"venue"
},
  "geometry": {"coordinates":[-84.155993,33.888805],"type":"Point"}
}