{
  "type": "Feature",
  "properties": {
    "addr:full":"103 Bass Reef Rd Baxley GA 31513",
    "addr:housenumber":"103",
    "addr:postcode":"31513",
    "addr:street":"Bass Reef Rd",
    "iso:country":"US",
    "sg:address":"103 Bass Reef Rd",
    "sg:city":"Baxley",
    "sg:classifiers":[
        {
            "category":"Professional",
            "type":"Services"
        }
    ],
    "sg:phone":"+1 912 366 0841",
    "sg:postcode":"31513",
    "sg:province":"GA",
    "wof:name":"Lottsloan",
    "wof:placetype":"venue"
},
  "geometry": {"coordinates":[-82.46999099999999,31.790231],"type":"Point"}
}