{
  "type": "Feature",
  "properties": {
    "iso:country":"US",
    "sg:address":"5605 Glenridge Dr NE",
    "sg:city":"Atlanta",
    "sg:classifiers":[
        {
            "category":"Professional",
            "subcategory":"Lawyer & Legal Services",
            "type":"Services"
        }
    ],
    "sg:phone":"+1 404 256 0700",
    "sg:postcode":"30342",
    "sg:province":"GA",
    "wof:name":"Terry Benjamin H",
    "wof:placetype":"venue"
},
  "geometry": {"coordinates":[-84.364087,33.907168],"type":"Point"}
}