{
  "type": "Feature",
  "properties": {
    "iso:country":"US",
    "sg:address":"1015 Alpharetta Hwy",
    "sg:city":"Roswell",
    "sg:classifiers":[
        {
            "category":"Cinema",
            "subcategory":"Movie Rental",
            "type":"Entertainment"
        }
    ],
    "sg:phone":"+1 678 352 1590",
    "sg:postcode":"30075",
    "sg:province":"GA",
    "sg:tags":[
        "video",
        "tape"
    ],
    "wof:name":"El Poder Musica I Video",
    "wof:placetype":"venue"
},
  "geometry": {"coordinates":[-84.35831899999999,34.027589],"type":"Point"}
}