{
  "type": "Feature",
  "properties": {
    "addr:full":"2400 Double Churches Rd Columbus GA 31909",
    "addr:housenumber":"2400",
    "addr:postcode":"31909",
    "addr:street":"Double Churches Rd",
    "iso:country":"US",
    "sg:address":"2400 Double Churches Rd",
    "sg:city":"Columbus",
    "sg:classifiers":[
        {
            "category":"Health Services",
            "subcategory":"Doctor",
            "type":"Services"
        }
    ],
    "sg:phone":"+1 706 596 1876",
    "sg:postcode":"31909",
    "sg:province":"GA",
    "sg:tags":[
        "dentist"
    ],
    "wof:name":"Lisa A Strickland DMD",
    "wof:placetype":"venue"
},
  "geometry": {"coordinates":[-84.956515,32.55544],"type":"Point"}
}