{
  "type": "Feature",
  "properties": {
    "iso:country":"US",
    "sg:address":"6550 Jimmy Carter Blvd",
    "sg:city":"Norcross",
    "sg:classifiers":[
        {
            "category":"Travel",
            "subcategory":"Travel Agent",
            "type":"Entertainment"
        }
    ],
    "sg:phone":"+1 770 491 8305",
    "sg:postcode":"30071",
    "sg:province":"GA",
    "sg:tags":[
        "consultant",
        "transportation"
    ],
    "wof:name":"Exel Direct",
    "wof:placetype":"venue"
},
  "geometry": {"coordinates":[-84.227722,33.9356],"type":"Point"}
}