{
  "type": "Feature",
  "properties": {
    "iso:country":"US",
    "sg:address":"4730 Emerald Glen Dr",
    "sg:city":"Douglasville",
    "sg:classifiers":[
        {
            "category":"Professional",
            "subcategory":"Management & Consulting",
            "type":"Services"
        }
    ],
    "sg:phone":"+1 678 517 2422",
    "sg:postcode":"30135",
    "sg:province":"GA",
    "sg:tags":[
        "public",
        "relations"
    ],
    "wof:name":"Paige & Associates",
    "wof:placetype":"venue"
},
  "geometry": {"coordinates":[-84.701606,33.67499],"type":"Point"}
}