{
  "type": "Feature",
  "properties": {
    "iso:country":"US",
    "sg:address":"3390 Peachtree Rd NE",
    "sg:city":"Atlanta",
    "sg:classifiers":[
        {
            "category":"Health Services",
            "subcategory":"Doctor",
            "type":"Services"
        }
    ],
    "sg:phone":"+1 404 846 2440",
    "sg:postcode":"30326",
    "sg:province":"GA",
    "sg:tags":[
        "physician",
        "surgery",
        "surgeons",
        "vascular"
    ],
    "wof:name":"Vein Care Pavilion Of Atlanta",
    "wof:placetype":"venue"
},
  "geometry": {"coordinates":[-84.36528800000001,33.848942],"type":"Point"}
}