{
  "type": "Feature",
  "properties": {
    "addr:full":"8275 Saint Marlo Fairway Dr Duluth GA 30097",
    "addr:housenumber":"8275",
    "addr:postcode":"30097",
    "addr:street":"Saint Marlo Fairway Dr",
    "iso:country":"US",
    "sg:address":"8275 Saint Marlo Fairway Dr",
    "sg:city":"Duluth",
    "sg:classifiers":[
        {
            "category":"Building & Trades",
            "subcategory":"Construction",
            "type":"Services"
        }
    ],
    "sg:phone":"+1 770 622 9458",
    "sg:postcode":"30097",
    "sg:province":"GA",
    "sg:tags":[
        "residential"
    ],
    "wof:name":"Timothy Porche Homes Inc",
    "wof:placetype":"venue"
},
  "geometry": {"coordinates":[-84.145281,34.076878],"type":"Point"}
}