{
  "type": "Feature",
  "properties": {
    "addr:full":"101 W Main St Hoboken GA 31542",
    "addr:housenumber":"101",
    "addr:postcode":"31542",
    "addr:street":"W Main St",
    "iso:country":"US",
    "sg:address":"101 W Main St",
    "sg:city":"Hoboken",
    "sg:classifiers":[
        {
            "category":"Food & Beverages",
            "subcategory":"Groceries & Convenience Stores",
            "type":"Retail Goods"
        }
    ],
    "sg:phone":"+1 912 458 3161",
    "sg:postcode":"31542",
    "sg:province":"GA",
    "wof:name":"Griffins Country Mall II",
    "wof:placetype":"venue"
},
  "geometry": {"coordinates":[-82.124848,31.181289],"type":"Point"}
}