{
  "type": "Feature",
  "properties": {
    "iso:country":"US",
    "sg:address":"421 S Garrett St",
    "sg:city":"Carrollton",
    "sg:classifiers":[
        {
            "category":"Manufacturing",
            "subcategory":"Chemicals & Compounds",
            "type":"Manufacturing & Wholesale Goods"
        }
    ],
    "sg:phone":"+1 770 832 3507",
    "sg:postcode":"30117",
    "sg:province":"GA",
    "sg:website":"www.houghtonintl.com",
    "wof:name":"Houghton International Inc",
    "wof:placetype":"venue"
},
  "geometry": {"coordinates":[-85.068444,33.569736],"type":"Point"}
}