{
  "type": "Feature",
  "properties": {
    "addr:full":"201 Church St Vienna GA 31092",
    "addr:housenumber":"201",
    "addr:postcode":"31092",
    "addr:street":"Church St",
    "iso:country":"US",
    "sg:address":"201 Church St",
    "sg:city":"Vienna",
    "sg:classifiers":[
        {
            "category":"Shopping",
            "subcategory":"Florist",
            "type":"Retail Goods"
        }
    ],
    "sg:phone":"+1 229 268 4063",
    "sg:postcode":"31092",
    "sg:province":"GA",
    "wof:name":"Diane B Couch",
    "wof:placetype":"venue"
},
  "geometry": {"coordinates":[-83.793876,32.092388],"type":"Point"}
}