{
  "type": "Feature",
  "properties": {
    "iso:country":"US",
    "sg:address":"3333 Buford Dr Ste 1045",
    "sg:city":"Buford",
    "sg:classifiers":[
        {
            "category":"Home & Garden",
            "subcategory":"Carpets & Floor Coverings",
            "type":"Retail Goods"
        }
    ],
    "sg:phone":"+1 678 482 6912",
    "sg:postcode":"30519",
    "sg:province":"GA",
    "sg:tags":[
        "mattress"
    ],
    "sg:website":"www.selectcomfort.com",
    "wof:name":"Select Comfort",
    "wof:placetype":"venue"
},
  "geometry": {"coordinates":[-83.984145,34.064225],"type":"Point"}
}