{
  "type": "Feature",
  "properties": {
    "iso:country":"US",
    "sg:address":"6124 Highway 278 NW",
    "sg:city":"Covington",
    "sg:classifiers":[
        {
            "category":"Banks & Credit Unions",
            "subcategory":"Bank",
            "type":"Services"
        }
    ],
    "sg:phone":"+1 770 784 0014",
    "sg:postcode":"30014",
    "sg:province":"GA",
    "sg:website":"http://www.peoples.com",
    "wof:name":"Peoples Bank The",
    "wof:placetype":"venue"
},
  "geometry": {"coordinates":[-83.843085,33.60218],"type":"Point"}
}