{
  "type": "Feature",
  "properties": {
    "addr:full":"1370 Atlanta Hwy Cumming GA 30040",
    "addr:housenumber":"1370",
    "addr:postcode":"30040",
    "addr:street":"Atlanta Hwy",
    "iso:country":"US",
    "sg:address":"1370 Atlanta Hwy",
    "sg:city":"Cumming",
    "sg:classifiers":[
        {
            "category":"Food & Beverages",
            "subcategory":"Specialty",
            "type":"Retail Goods"
        }
    ],
    "sg:phone":"+1 678 513 2532",
    "sg:postcode":"30040",
    "sg:province":"GA",
    "sg:tags":[
        "american",
        "latin",
        "mexican",
        "product"
    ],
    "wof:name":"Los Corrales",
    "wof:placetype":"venue"
},
  "geometry": {"coordinates":[-84.162446,34.171786],"type":"Point"}
}