{
  "type": "Feature",
  "properties": {
    "addr:full":"10 N Clarendon Ave Avondale Estates GA 30002",
    "addr:housenumber":"10",
    "addr:postcode":"30002",
    "addr:street":"N Clarendon Ave",
    "iso:country":"US",
    "sg:address":"10 N Clarendon Ave",
    "sg:city":"Avondale Estates",
    "sg:classifiers":[
        {
            "category":"Restaurant",
            "type":"Food & Drink"
        }
    ],
    "sg:menulink":"http://www.allmenus.com/ga/atlanta-decatur/186701-fellinis-pizza/menu/",
    "sg:phone":"+1 404 298 4660",
    "sg:postcode":"30002",
    "sg:province":"GA",
    "sg:tags":[
        "american",
        "pizza"
    ],
    "wof:name":"Fellini's Pizza",
    "wof:placetype":"venue"
},
  "geometry": {"coordinates":[-84.26751899999999,33.777007],"type":"Point"}
}