{
  "type": "Feature",
  "properties": {
    "addr:full":"201 Magnolia Tree Ct Alpharetta GA 30022",
    "addr:housenumber":"201",
    "addr:postcode":"30022",
    "addr:street":"Magnolia Tree Ct",
    "iso:country":"US",
    "sg:address":"201 Magnolia Tree Ct",
    "sg:city":"Alpharetta",
    "sg:classifiers":[
        {
            "category":"Building & Trades",
            "subcategory":"Locksmith",
            "type":"Services"
        }
    ],
    "sg:phone":"+1 678 259 0094",
    "sg:postcode":"30022",
    "sg:province":"GA",
    "sg:tags":[
        "key"
    ],
    "wof:name":"A Locksmith A 1-24 Hour",
    "wof:placetype":"venue"
},
  "geometry": {"coordinates":[-84.21115500000001,34.041022],"type":"Point"}
}