{
  "type": "Feature",
  "properties": {
    "iso:country":"US",
    "sg:address":"199 Westview Dr NE",
    "sg:city":"Cartersville",
    "sg:classifiers":[
        {
            "category":"Government",
            "subcategory":"Office",
            "type":"Public Place"
        }
    ],
    "sg:phone":"+1 770 387 3679",
    "sg:postcode":"30121",
    "sg:province":"GA",
    "wof:name":"Routine Maintenance",
    "wof:placetype":"venue"
},
  "geometry": {"coordinates":[-84.800381,34.212386],"type":"Point"}
}