{
  "type": "Feature",
  "properties": {
    "iso:country":"US",
    "sg:address":"3697 Highway 5 Ste 2",
    "sg:city":"Douglasville",
    "sg:classifiers":[
        {
            "category":"Personal",
            "subcategory":"Barber",
            "type":"Services"
        }
    ],
    "sg:phone":"+1 770 713 7064",
    "sg:postcode":"30135",
    "sg:province":"GA",
    "wof:name":"Lingerfelt's Barber Shop",
    "wof:placetype":"venue"
},
  "geometry": {"coordinates":[-84.7782,33.706721],"type":"Point"}
}