{
  "type": "Feature",
  "properties": {
    "addr:full":"538 Grace Dr Waycross GA 31503",
    "addr:housenumber":"538",
    "addr:postcode":"31503",
    "addr:street":"Grace Dr",
    "iso:country":"US",
    "sg:address":"538 Grace Dr",
    "sg:city":"Waycross",
    "sg:classifiers":[
        {
            "category":"Professional",
            "type":"Services"
        }
    ],
    "sg:phone":"+1 912 285 4352",
    "sg:postcode":"31503",
    "sg:province":"GA",
    "wof:name":"Georgia C Fullard",
    "wof:placetype":"venue"
},
  "geometry": {"coordinates":[-82.28619,31.208056],"type":"Point"}
}