{
  "type": "Feature",
  "properties": {
    "addr:full":"294 Kenwood Rd Fayetteville GA 30214",
    "addr:housenumber":"294",
    "addr:postcode":"30214",
    "addr:street":"Kenwood Rd",
    "iso:country":"US",
    "sg:address":"294 Kenwood Rd",
    "sg:city":"Fayetteville",
    "sg:classifiers":[
        {
            "category":"Shopping",
            "subcategory":"Optical Goods",
            "type":"Retail Goods"
        }
    ],
    "sg:phone":"+1 770 719 2717",
    "sg:postcode":"30214",
    "sg:province":"GA",
    "wof:name":"Dales Optical",
    "wof:placetype":"venue"
},
  "geometry": {"coordinates":[-84.44587,33.510468],"type":"Point"}
}