{
  "type": "Feature",
  "properties": {
    "iso:country":"US",
    "sg:address":"468 Arbour Run",
    "sg:city":"Suwanee",
    "sg:classifiers":[
        {
            "category":"Building & Trades",
            "subcategory":"Construction",
            "type":"Services"
        }
    ],
    "sg:phone":"+1 404 626 2831",
    "sg:postcode":"30024",
    "sg:province":"GA",
    "sg:tags":[
        "contractor",
        "fence-sales"
    ],
    "wof:name":"Keystone Fence",
    "wof:placetype":"venue"
},
  "geometry": {"coordinates":[-84.041038,34.013359],"type":"Point"}
}