{
  "type": "Feature",
  "properties": {
    "addr:full":"310 W Oglethorpe Blvd Albany GA 31701",
    "addr:housenumber":"310",
    "addr:postcode":"31701",
    "addr:street":"W Oglethorpe Blvd",
    "iso:country":"US",
    "sg:address":"310 W Oglethorpe Blvd",
    "sg:city":"Albany",
    "sg:classifiers":[
        {
            "category":"Banks & Credit Unions",
            "subcategory":"Bank",
            "type":"Services"
        }
    ],
    "sg:phone":"+1 229 888 8296",
    "sg:postcode":"31701",
    "sg:province":"GA",
    "wof:name":"Age Credit Union",
    "wof:placetype":"venue"
},
  "geometry": {"coordinates":[-84.155693,31.575223],"type":"Point"}
}