{
  "type": "Feature",
  "properties": {
    "iso:country":"US",
    "sg:address":"86 Mount Vernon Hwy NW",
    "sg:city":"Atlanta",
    "sg:classifiers":[
        {
            "category":"Education",
            "subcategory":"Preschool",
            "type":"Public Place"
        },
        {
            "category":"Education",
            "subcategory":"School",
            "type":"Public Place"
        }
    ],
    "sg:phone":"+1 404 250 9455",
    "sg:postcode":"30328",
    "sg:province":"GA",
    "sg:tags":[
        "elementary"
    ],
    "wof:name":"Sandy Springs United Methodist Church Preschool",
    "wof:placetype":"venue"
},
  "geometry": {"coordinates":[-84.389099,33.921501],"type":"Point"}
}