{
  "type": "Feature",
  "properties": {
    "addr:full":"2333 Victory Church Rd Bowdon GA 30108",
    "addr:housenumber":"2333",
    "addr:postcode":"30108",
    "addr:street":"Victory Church Rd",
    "iso:country":"US",
    "sg:address":"2333 Victory Church Rd",
    "sg:city":"Bowdon",
    "sg:classifiers":[
        {
            "category":"Organizations",
            "subcategory":"Religious Organization",
            "type":"Services"
        }
    ],
    "sg:phone":"+1 770 258 0097",
    "sg:postcode":"30108",
    "sg:province":"GA",
    "sg:tags":[
        "church"
    ],
    "wof:name":"New Life Covenant",
    "wof:placetype":"venue"
},
  "geometry": {"coordinates":[-85.211842,33.510119],"type":"Point"}
}