{
  "type": "Feature",
  "properties": {
    "iso:country":"US",
    "sg:address":"5730 Wells Cir",
    "sg:city":"Stone Mountain",
    "sg:classifiers":[
        {
            "category":"Professional",
            "type":"Services"
        }
    ],
    "sg:phone":"+1 404 683 0183",
    "sg:postcode":"30087",
    "sg:province":"GA",
    "wof:name":"Goldenscapes Inc",
    "wof:placetype":"venue"
},
  "geometry": {"coordinates":[-84.158962,33.781056],"type":"Point"}
}