{
  "type": "Feature",
  "properties": {
    "addr:full":"2 East Bryan Street Suite 601 Savannah GA 31401",
    "addr:housenumber":"2",
    "addr:postcode":"31401",
    "addr:street":"East Bryan Street Suite 601",
    "iso:country":"US",
    "sg:address":"2 East Bryan Street Suite 601",
    "sg:city":"Savannah",
    "sg:classifiers":[
        {
            "category":"Professional",
            "subcategory":"Research",
            "type":"Services"
        }
    ],
    "sg:phone":"+1 912 443 1987",
    "sg:postcode":"31401",
    "sg:province":"GA",
    "sg:website":"http://www.healthdiscoverycorp.com",
    "wof:name":"Health Discovery",
    "wof:placetype":"venue"
},
  "geometry": {"coordinates":[-81.0909,32.080095],"type":"Point"}
}