{
  "type": "Feature",
  "properties": {
    "iso:country":"US",
    "sg:address":"3450 Wrightsboro Rd",
    "sg:city":"Augusta",
    "sg:classifiers":[
        {
            "category":"Shopping",
            "subcategory":"Department Store",
            "type":"Retail Goods"
        }
    ],
    "sg:phone":"+1 706 731 8689",
    "sg:postcode":"30909",
    "sg:province":"GA",
    "wof:name":"Sears Roebuck & Co",
    "wof:placetype":"venue"
},
  "geometry": {"coordinates":[-82.080421,33.46729],"type":"Point"}
}