{
  "type": "Feature",
  "properties": {
    "iso:country":"US",
    "sg:address":"710 28th Ave SE",
    "sg:city":"Moultrie",
    "sg:classifiers":[
        {
            "category":"Health Services",
            "subcategory":"Health Practitioner",
            "type":"Services"
        }
    ],
    "sg:phone":"+1 229 890 6228",
    "sg:postcode":"31768",
    "sg:province":"GA",
    "sg:tags":[
        "nutritionist"
    ],
    "wof:name":"Cc Board Of Board Service",
    "wof:placetype":"venue"
},
  "geometry": {"coordinates":[-83.776937,31.134746],"type":"Point"}
}