{
  "type": "Feature",
  "properties": {
    "addr:full":"3744 Upland Dr Marietta GA 30066",
    "addr:housenumber":"3744",
    "addr:postcode":"30066",
    "addr:street":"Upland Dr",
    "iso:country":"US",
    "sg:address":"3744 Upland Dr",
    "sg:city":"Marietta",
    "sg:classifiers":[
        {
            "category":"Real Estate",
            "subcategory":"Developer",
            "type":"Services"
        }
    ],
    "sg:phone":"+1 770 579 5103",
    "sg:postcode":"30066",
    "sg:province":"GA",
    "sg:tags":[
        "development",
        "residential",
        "land"
    ],
    "wof:name":"Vertiqa LLC",
    "wof:placetype":"venue"
},
  "geometry": {"coordinates":[-84.467204,34.043304],"type":"Point"}
}