{
  "type": "Feature",
  "properties": {
    "addr:full":"6248 Dawson Blvd Norcross GA 30093",
    "addr:housenumber":"6248",
    "addr:postcode":"30093",
    "addr:street":"Dawson Blvd",
    "iso:country":"US",
    "sg:address":"6248 Dawson Blvd",
    "sg:city":"Norcross",
    "sg:classifiers":[
        {
            "category":"Home & Garden",
            "subcategory":"Furniture",
            "type":"Retail Goods"
        }
    ],
    "sg:phone":"+1 770 449 5740",
    "sg:postcode":"30093",
    "sg:province":"GA",
    "sg:tags":[
        "store"
    ],
    "wof:name":"Scandinavian Furniture by House of Denmark",
    "wof:placetype":"venue"
},
  "geometry": {"coordinates":[-84.212402,33.911098],"type":"Point"}
}