{
  "type": "Feature",
  "properties": {
    "iso:country":"US",
    "sg:address":"1066 Salem Valley Rd",
    "sg:city":"Ringgold",
    "sg:classifiers":[
        {
            "category":"Building & Trades",
            "subcategory":"Landscaping Services",
            "type":"Services"
        }
    ],
    "sg:phone":"+1 706 965 6351",
    "sg:postcode":"30736",
    "sg:province":"GA",
    "wof:name":"Advanced Lawn Cutting",
    "wof:placetype":"venue"
},
  "geometry": {"coordinates":[-85.07806600000001,34.909347],"type":"Point"}
}