{
  "type": "Feature",
  "properties": {
    "iso:country":"US",
    "sg:address":"1595 Peachtree Pkwy",
    "sg:city":"Cumming",
    "sg:classifiers":[
        {
            "category":"Education",
            "subcategory":"Special Training",
            "type":"Public Place"
        }
    ],
    "sg:phone":"+1 770 844 8408",
    "sg:postcode":"30041",
    "sg:province":"GA",
    "sg:tags":[
        "tutoring"
    ],
    "wof:name":"Kumon Math & Reading Ctr",
    "wof:placetype":"venue"
},
  "geometry": {"coordinates":[-84.171434,34.122346],"type":"Point"}
}