{
  "type": "Feature",
  "properties": {
    "iso:country":"US",
    "sg:address":"3011 Fox Spring Rd",
    "sg:city":"Augusta",
    "sg:classifiers":[
        {
            "category":"Organizations",
            "subcategory":"Non-profit Organization",
            "type":"Services"
        }
    ],
    "sg:phone":"+1 706 738 2602",
    "sg:postcode":"30909",
    "sg:province":"GA",
    "sg:tags":[
        "breastfeeding",
        "information",
        "supply"
    ],
    "wof:name":"Bosom Buddies",
    "wof:placetype":"venue"
},
  "geometry": {"coordinates":[-82.04315800000001,33.477855],"type":"Point"}
}