{
  "type": "Feature",
  "properties": {
    "iso:country":"US",
    "sg:address":"2704 Castleberry Bridge Rd",
    "sg:city":"Dawsonville",
    "sg:classifiers":[
        {
            "category":"Wholesale",
            "subcategory":"Groceries",
            "type":"Manufacturing & Wholesale Goods"
        }
    ],
    "sg:phone":"+1 706 265 3175",
    "sg:postcode":"30534",
    "sg:province":"GA",
    "sg:tags":[
        "food",
        "snack"
    ],
    "wof:name":"Mashburn Distributing Co",
    "wof:placetype":"venue"
},
  "geometry": {"coordinates":[-84.065434,34.471225],"type":"Point"}
}