{
  "type": "Feature",
  "properties": {
    "iso:country":"US",
    "sg:address":"5580 Stapleton Dr",
    "sg:city":"Atlanta",
    "sg:classifiers":[
        {
            "category":"Professional",
            "subcategory":"Printing & Photocopies",
            "type":"Services"
        }
    ],
    "sg:phone":"+1 770 512 0029",
    "sg:postcode":"30338",
    "sg:province":"GA",
    "sg:tags":[
        "photocopying"
    ],
    "wof:name":"Blueprint Communication",
    "wof:placetype":"venue"
},
  "geometry": {"coordinates":[-84.31007200000001,33.962116],"type":"Point"}
}