{
  "type": "Feature",
  "properties": {
    "addr:full":"253 Old Tassel Ct Woodstock GA 30189",
    "addr:housenumber":"253",
    "addr:postcode":"30189",
    "addr:street":"Old Tassel Ct",
    "iso:country":"US",
    "sg:address":"253 Old Tassel Ct",
    "sg:city":"Woodstock",
    "sg:classifiers":[
        {
            "category":"Building & Trades",
            "subcategory":"Electrical",
            "type":"Services"
        }
    ],
    "sg:phone":"+1 678 873 1084",
    "sg:postcode":"30189",
    "sg:province":"GA",
    "sg:tags":[
        "electrical",
        "contractor"
    ],
    "wof:name":"DC & J Electric Co",
    "wof:placetype":"venue"
},
  "geometry": {"coordinates":[-84.53604300000001,34.113567],"type":"Point"}
}