{
  "type": "Feature",
  "properties": {
    "addr:full":"1233 Old Jackson Rd Locust Grove GA 30248",
    "addr:housenumber":"1233",
    "addr:postcode":"30248",
    "addr:street":"Old Jackson Rd",
    "iso:country":"US",
    "sg:address":"1233 Old Jackson Rd",
    "sg:city":"Locust Grove",
    "sg:classifiers":[
        {
            "category":"Freight",
            "type":"Transportation"
        }
    ],
    "sg:phone":"+1 770 898 7011",
    "sg:postcode":"30248",
    "sg:province":"GA",
    "sg:tags":[
        "operator",
        "local",
        "trucking"
    ],
    "wof:name":"A/H Transport Inc",
    "wof:placetype":"venue"
},
  "geometry": {"coordinates":[-84.07126700000001,33.402137],"type":"Point"}
}