{
  "type": "Feature",
  "properties": {
    "iso:country":"US",
    "sg:address":"101 Elliott Dr NW",
    "sg:city":"Rome",
    "sg:classifiers":[
        {
            "category":"Health Services",
            "subcategory":"Doctor",
            "type":"Services"
        }
    ],
    "sg:phone":"+1 706 295 5331",
    "sg:postcode":"30165",
    "sg:province":"GA",
    "sg:tags":[
        "physician",
        "surgeon"
    ],
    "wof:name":"Harbin Clinic",
    "wof:placetype":"venue"
},
  "geometry": {"coordinates":[-85.228064,34.285789],"type":"Point"}
}