{
  "type": "Feature",
  "properties": {
    "addr:full":"406 N Westberry St Sylvester GA 31791",
    "addr:housenumber":"406",
    "addr:postcode":"31791",
    "addr:street":"N Westberry St",
    "iso:country":"US",
    "sg:address":"406 N Westberry St",
    "sg:city":"Sylvester",
    "sg:classifiers":[
        {
            "category":"Personal",
            "subcategory":"Tanning Parlor",
            "type":"Services"
        }
    ],
    "sg:phone":"+1 229 777 8105",
    "sg:postcode":"31791",
    "sg:province":"GA",
    "sg:tags":[
        "salon"
    ],
    "wof:name":"Southern Tanz",
    "wof:placetype":"venue"
},
  "geometry": {"coordinates":[-83.83353099999999,31.531871],"type":"Point"}
}