{
  "type": "Feature",
  "properties": {
    "addr:full":"431 K Wade Rd Alto GA 30510",
    "addr:housenumber":"431",
    "addr:postcode":"30510",
    "addr:street":"K Wade Rd",
    "iso:country":"US",
    "sg:address":"431 K Wade Rd",
    "sg:city":"Alto",
    "sg:classifiers":[
        {
            "category":"Farming",
            "subcategory":"Farm",
            "type":"Manufacturing & Wholesale Goods"
        }
    ],
    "sg:phone":"+1 706 778 5755",
    "sg:postcode":"30510",
    "sg:province":"GA",
    "wof:name":"Grier Farms",
    "wof:placetype":"venue"
},
  "geometry": {"coordinates":[-83.626778,34.447701],"type":"Point"}
}