{
  "type": "Feature",
  "properties": {
    "addr:full":"230 County Line Rd Waycross GA 31503",
    "addr:housenumber":"230",
    "addr:postcode":"31503",
    "addr:street":"County Line Rd",
    "iso:country":"US",
    "sg:address":"230 County Line Rd",
    "sg:city":"Waycross",
    "sg:classifiers":[
        {
            "category":"Freight",
            "type":"Transportation"
        }
    ],
    "sg:phone":"+1 912 284 9584",
    "sg:postcode":"31503",
    "sg:province":"GA",
    "sg:tags":[
        "delivery"
    ],
    "wof:name":"Top Shelf Moving & Delivery",
    "wof:placetype":"venue"
},
  "geometry": {"coordinates":[-82.284313,31.201511],"type":"Point"}
}