{
  "type": "Feature",
  "properties": {
    "addr:full":"303 Bells Ferry Rd NE Rome GA 30161",
    "addr:housenumber":"303",
    "addr:postcode":"ga 30161",
    "addr:street":"Bells Ferry Rd Ne",
    "iso:country":"US",
    "sg:address":"303 Bells Ferry Rd NE",
    "sg:city":"Rome",
    "sg:classifiers":[
        {
            "category":"Building & Trades",
            "subcategory":"Construction",
            "type":"Services"
        }
    ],
    "sg:phone":"+1 706 346 3798",
    "sg:postcode":"30161",
    "sg:province":"GA",
    "sg:tags":[
        "system",
        "specialty",
        "heating",
        "contractor",
        "air conditioning"
    ],
    "wof:name":"Henderson Hvac, Inc.",
    "wof:placetype":"venue"
},
  "geometry": {"coordinates":[-85.11712300000001,34.308624],"type":"Point"}
}