{
  "type": "Feature",
  "properties": {
    "iso:country":"US",
    "sg:address":"1100 Westchester Rdg NE",
    "sg:city":"Atlanta",
    "sg:classifiers":[
        {
            "category":"Real Estate",
            "subcategory":"Real Estate Operator",
            "type":"Services"
        }
    ],
    "sg:phone":"+1 404 417 0155",
    "sg:postcode":"30329",
    "sg:province":"GA",
    "sg:tags":[
        "apartment"
    ],
    "wof:name":"The Westchester At Briarcliff",
    "wof:placetype":"venue"
},
  "geometry": {"coordinates":[-84.324798,33.835432],"type":"Point"}
}