{
  "type": "Feature",
  "properties": {
    "iso:country":"US",
    "sg:address":"2118 November Glen Dr",
    "sg:city":"Acworth",
    "sg:classifiers":[
        {
            "category":"Professional",
            "subcategory":"Employment Agencies",
            "type":"Services"
        }
    ],
    "sg:phone":"+1 770 917 0392",
    "sg:postcode":"30102",
    "sg:province":"GA",
    "sg:tags":[
        "help",
        "supply"
    ],
    "wof:name":"Associated Temporary Staffing",
    "wof:placetype":"venue"
},
  "geometry": {"coordinates":[-84.608958,34.07239],"type":"Point"}
}