{
  "type": "Feature",
  "properties": {
    "iso:country":"US",
    "sg:address":"259 N Price Rd",
    "sg:city":"Buford",
    "sg:classifiers":[
        {
            "category":"Building & Trades",
            "subcategory":"Construction",
            "type":"Services"
        },
        {
            "category":"Home & Garden",
            "subcategory":"Furniture",
            "type":"Retail Goods"
        }
    ],
    "sg:phone":"+1 770 271 3814",
    "sg:postcode":"30518",
    "sg:province":"GA",
    "sg:tags":[
        "mfg",
        "contractor",
        "woo",
        "wood",
        "cabinet",
        "carpentry"
    ],
    "wof:name":"Craftsmen Custom Cabinets Inc",
    "wof:placetype":"venue"
},
  "geometry": {"coordinates":[-84.055761,34.080303],"type":"Point"}
}