{
  "type": "Feature",
  "properties": {
    "addr:full":"2451 Pleasantdale Road Atlanta GA 30340",
    "addr:housenumber":"2451",
    "addr:postcode":"30340",
    "addr:street":"Pleasantdale Road",
    "iso:country":"US",
    "sg:address":"2451 Pleasantdale Road",
    "sg:city":"Atlanta",
    "sg:classifiers":[
        {
            "category":"Professional",
            "subcategory":"Lawyer & Legal Services",
            "type":"Services"
        }
    ],
    "sg:phone":"+1 770 662 5192",
    "sg:postcode":"30340",
    "sg:province":"GA",
    "wof:name":"Morris Gary L Atty",
    "wof:placetype":"venue"
},
  "geometry": {"coordinates":[-84.24490299999999,33.917798],"type":"Point"}
}