{
  "type": "Feature",
  "properties": {
    "iso:country":"US",
    "sg:address":"1778 Highway 78 NW",
    "sg:city":"Monroe",
    "sg:classifiers":[
        {
            "category":"Building & Trades",
            "subcategory":"Landscaping Services",
            "type":"Services"
        }
    ],
    "sg:phone":"+1 770 267 8733",
    "sg:postcode":"30655",
    "sg:province":"GA",
    "sg:tags":[
        "consultant",
        "designer",
        "tree",
        "landscape"
    ],
    "wof:name":"Premier Tree & Shrub Care",
    "wof:placetype":"venue"
},
  "geometry": {"coordinates":[-83.645246,33.834274],"type":"Point"}
}