{
  "type": "Feature",
  "properties": {
    "addr:full":"5172 Brook Hollow Pkwy Norcross GA 30071",
    "addr:housenumber":"5172",
    "addr:postcode":"30071",
    "addr:street":"Brook Hollow Pkwy",
    "iso:country":"US",
    "sg:address":"5172 Brook Hollow Pkwy",
    "sg:city":"Norcross",
    "sg:classifiers":[
        {
            "category":"Building & Trades",
            "subcategory":"Electrical",
            "type":"Services"
        }
    ],
    "sg:phone":"+1 678 730 0111",
    "sg:postcode":"30071",
    "sg:province":"GA",
    "sg:tags":[
        "installation"
    ],
    "wof:name":"MBR Office Solutions Inc",
    "wof:placetype":"venue"
},
  "geometry": {"coordinates":[-84.18266300000001,33.927936],"type":"Point"}
}