{
  "type": "Feature",
  "properties": {
    "iso:country":"US",
    "sg:address":"185 N Norcross Tucker Rd",
    "sg:city":"Norcross",
    "sg:classifiers":[
        {
            "category":"Bars & Pubs",
            "subcategory":"Sports Bar",
            "type":"Food & Drink"
        }
    ],
    "sg:phone":"+1 770 734 0490",
    "sg:postcode":"30071",
    "sg:province":"GA",
    "sg:tags":[
        "hall",
        "pool"
    ],
    "wof:name":"Billards Lucky 77",
    "wof:placetype":"venue"
},
  "geometry": {"coordinates":[-84.216003,33.933998],"type":"Point"}
}