{
  "type": "Feature",
  "properties": {
    "iso:country":"US",
    "sg:address":"2463 Hamilton Mill Pkwy",
    "sg:city":"Dacula",
    "sg:classifiers":[
        {
            "category":"Retail",
            "subcategory":"Laundry & Dry Cleaning",
            "type":"Services"
        }
    ],
    "sg:phone":"+1 770 271 3377",
    "sg:postcode":"30019",
    "sg:province":"GA",
    "sg:tags":[
        "drycleaning"
    ],
    "wof:name":"Art Cleaners Inc",
    "wof:placetype":"venue"
},
  "geometry": {"coordinates":[-83.913568,34.058053],"type":"Point"}
}