{
  "type": "Feature",
  "properties": {
    "iso:country":"US",
    "sg:address":"3403 Bemiss Rd",
    "sg:city":"Valdosta",
    "sg:classifiers":[
        {
            "category":"Shopping",
            "subcategory":"Used Merchandise",
            "type":"Retail Goods"
        },
        {
            "category":"Shopping",
            "subcategory":"Clothing, Apparel, & Fashions",
            "type":"Retail Goods"
        }
    ],
    "sg:phone":"+1 229 242 2643",
    "sg:postcode":"31605",
    "sg:province":"GA",
    "sg:tags":[
        "shop",
        "consignment",
        "child"
    ],
    "wof:name":"Family Consignment Shop",
    "wof:placetype":"venue"
},
  "geometry": {"coordinates":[-83.270754,30.88982],"type":"Point"}
}