{
  "type": "Feature",
  "properties": {
    "iso:country":"US",
    "sg:address":"7556 Chad's Cir",
    "sg:city":"Jonesboro",
    "sg:classifiers":[
        {
            "category":"Professional",
            "type":"Services"
        }
    ],
    "sg:phone":"+1 678 662 6692",
    "sg:postcode":"30236",
    "sg:province":"GA",
    "wof:name":"Make N It Up",
    "wof:placetype":"venue"
},
  "geometry": {"coordinates":[-84.308075,33.547832],"type":"Point"}
}