{
  "type": "Feature",
  "properties": {
    "iso:country":"US",
    "sg:address":"734 Reeceburg Rd SE",
    "sg:city":"Silver Creek",
    "sg:classifiers":[
        {
            "category":"Freight",
            "type":"Transportation"
        }
    ],
    "sg:phone":"+1 706 291 1013",
    "sg:postcode":"30173",
    "sg:province":"GA",
    "sg:tags":[
        "trailer"
    ],
    "wof:name":"JRG Storage Trailers",
    "wof:placetype":"venue"
},
  "geometry": {"coordinates":[-85.17218099999999,34.147522],"type":"Point"}
}