{
  "type": "Feature",
  "properties": {
    "iso:country":"US",
    "sg:address":"330 Hudson Rd",
    "sg:city":"Griffin",
    "sg:classifiers":[
        {
            "category":"Freight",
            "type":"Transportation"
        },
        {
            "category":"Wholesale",
            "subcategory":"Durable Goods & Equipment",
            "type":"Manufacturing & Wholesale Goods"
        }
    ],
    "sg:phone":"+1 770 233 6070",
    "sg:postcode":"30224",
    "sg:province":"GA",
    "sg:tags":[
        "operator",
        "exporter",
        "trucking"
    ],
    "wof:name":"North Star Dedicated Services",
    "wof:placetype":"venue"
},
  "geometry": {"coordinates":[-84.236289,33.229526],"type":"Point"}
}