{
  "type": "Feature",
  "properties": {
    "iso:country":"US",
    "sg:address":"123 Jackson St",
    "sg:city":"Bowman",
    "sg:classifiers":[
        {
            "category":"Restaurant",
            "type":"Food & Drink"
        }
    ],
    "sg:phone":"+1 706 552 0051",
    "sg:postcode":"30624",
    "sg:province":"GA",
    "wof:name":"The Pita Pit",
    "wof:placetype":"venue"
},
  "geometry": {"coordinates":[-83.025671,34.205687],"type":"Point"}
}