{
  "type": "Feature",
  "properties": {
    "iso:country":"US",
    "sg:address":"2835 Brandywine Rd",
    "sg:city":"Atlanta",
    "sg:classifiers":[
        {
            "category":"Food & Beverages",
            "subcategory":"Groceries & Convenience Stores",
            "type":"Retail Goods"
        }
    ],
    "sg:phone":"+1 770 457 5448",
    "sg:postcode":"30341",
    "sg:province":"GA",
    "wof:name":"Kroger Equity Inc",
    "wof:placetype":"venue"
},
  "geometry": {"coordinates":[-84.26973099999999,33.870833],"type":"Point"}
}