{
  "type": "Feature",
  "properties": {
    "addr:full":"1030 Stevens Creek Rd Augusta GA 30907",
    "addr:housenumber":"1030",
    "addr:postcode":"30907",
    "addr:street":"Stevens Creek Rd",
    "iso:country":"US",
    "sg:address":"1030 Stevens Creek Rd",
    "sg:city":"Augusta",
    "sg:classifiers":[
        {
            "category":"Manufacturing",
            "subcategory":"Tools & Machinery",
            "type":"Manufacturing & Wholesale Goods"
        }
    ],
    "sg:phone":"+1 706 826 6900",
    "sg:postcode":"30907",
    "sg:province":"GA",
    "wof:name":"Electrolux Consumer Prod North",
    "wof:placetype":"venue"
},
  "geometry": {"coordinates":[-82.04571300000001,33.521031],"type":"Point"}
}