{
  "type": "Feature",
  "properties": {
    "addr:full":"134 Scott Rd Fitzgerald GA 31750",
    "addr:housenumber":"134",
    "addr:postcode":"31750",
    "addr:street":"Scott Rd",
    "iso:country":"US",
    "sg:address":"134 Scott Rd",
    "sg:city":"Fitzgerald",
    "sg:phone":"+1 229 423 3165",
    "sg:postcode":"31750",
    "sg:province":"GA",
    "sg:tags":[
        "farm",
        "field",
        "corn",
        "crop",
        "cotton"
    ],
    "wof:name":"Robert Wayne Dixon",
    "wof:placetype":"venue"
},
  "geometry": {"coordinates":[-83.297158,31.705864],"type":"Point"}
}