{
  "type": "Feature",
  "properties": {
    "iso:country":"US",
    "sg:address":"134 S Main St",
    "sg:city":"Jasper",
    "sg:classifiers":[
        {
            "category":"Communications",
            "subcategory":"Radio Station",
            "type":"Services"
        }
    ],
    "sg:phone":"+1 706 276 2016",
    "sg:postcode":"30143",
    "sg:province":"GA",
    "sg:tags":[
        "company",
        "broadcasting"
    ],
    "wof:name":"WLJA",
    "wof:placetype":"venue"
},
  "geometry": {"coordinates":[-84.429154,34.466136],"type":"Point"}
}