{
  "type": "Feature",
  "properties": {
    "addr:full":"3149 Hammock Creek Ct Conyers GA 30058",
    "addr:housenumber":"3149",
    "addr:postcode":"30058",
    "addr:street":"Hammock Creek Ct",
    "iso:country":"US",
    "sg:address":"3149 Hammock Creek Ct",
    "sg:city":"Conyers",
    "sg:classifiers":[
        {
            "category":"Retail",
            "subcategory":"Repair Shop",
            "type":"Services"
        }
    ],
    "sg:phone":"+1 770 595 8646",
    "sg:postcode":"30058",
    "sg:province":"GA",
    "wof:name":"Genes Locksmith Service LLC",
    "wof:placetype":"venue"
},
  "geometry": {"coordinates":[-84.03792799999999,33.731647],"type":"Point"}
}