{
  "type": "Feature",
  "properties": {
    "addr:full":"5237 W Fayetteville Road Atlanta GA 30349",
    "addr:housenumber":"5237",
    "addr:postcode":"30349",
    "addr:street":"W Fayetteville Road",
    "iso:country":"US",
    "sg:address":"5237 W Fayetteville Road",
    "sg:city":"Atlanta",
    "sg:classifiers":[
        {
            "category":"Banks & Credit Unions",
            "subcategory":"Bank",
            "type":"Services"
        }
    ],
    "sg:phone":"+1 770 994 7464",
    "sg:postcode":"30349",
    "sg:province":"GA",
    "sg:website":"statefarm.com",
    "wof:name":"State Farm Insurance",
    "wof:placetype":"venue"
},
  "geometry": {"coordinates":[-84.448224,33.612476],"type":"Point"}
}