{
  "type": "Feature",
  "properties": {
    "iso:country":"US",
    "sg:address":"3146 Young Harris Hwy",
    "sg:city":"Blairsville",
    "sg:classifiers":[
        {
            "category":"Shopping",
            "subcategory":"Gifts & Souvenirs",
            "type":"Retail Goods"
        }
    ],
    "sg:phone":"+1 706 745 8991",
    "sg:postcode":"30512",
    "sg:province":"GA",
    "sg:tags":[
        "shop"
    ],
    "wof:name":"Up The Creek Gifts",
    "wof:placetype":"venue"
},
  "geometry": {"coordinates":[-83.883326,34.907162],"type":"Point"}
}