{
  "type": "Feature",
  "properties": {
    "addr:full":"1616 Piedmont Avenue NE Apt F18 Atlanta GA 30324",
    "addr:housenumber":"1616",
    "addr:postcode":"30324",
    "addr:street":"Piedmont Avenue Ne Apt F18",
    "iso:country":"US",
    "sg:address":"1616 Piedmont Avenue NE Apt F18",
    "sg:city":"Atlanta",
    "sg:classifiers":[
        {
            "category":"Real Estate",
            "subcategory":"Real Estate Operator",
            "type":"Services"
        }
    ],
    "sg:phone":"+1 404 875 4702",
    "sg:postcode":"30324",
    "sg:province":"GA",
    "sg:tags":[
        "apartment"
    ],
    "wof:name":"Ansley Forest Apartments",
    "wof:placetype":"venue"
},
  "geometry": {"coordinates":[-84.368082,33.798807],"type":"Point"}
}