{
  "type": "Feature",
  "properties": {
    "iso:country":"US",
    "sg:address":"461 Johnny Mercer Blvd",
    "sg:city":"Savannah",
    "sg:classifiers":[
        {
            "category":"Restaurant",
            "type":"Food & Drink"
        }
    ],
    "sg:menulink":"http://www.allmenus.com/ga/tybee-island-wilmington/57489-beef-obradys/menu/",
    "sg:phone":"+1 912 897 8277",
    "sg:postcode":"31410",
    "sg:province":"GA",
    "sg:tags":[
        "burger",
        "american",
        "wing",
        "pub"
    ],
    "wof:name":"Beef O'Brady's",
    "wof:placetype":"venue"
},
  "geometry": {"coordinates":[-80.977827,32.014841],"type":"Point"}
}