{
  "type": "Feature",
  "properties": {
    "iso:country":"US",
    "sg:address":"151 N Main St",
    "sg:city":"Dawson",
    "sg:classifiers":[
        {
            "category":"Real Estate",
            "subcategory":"Real Estate Agent",
            "type":"Services"
        }
    ],
    "sg:phone":"+1 229 995 3238",
    "sg:postcode":"39842",
    "sg:province":"GA",
    "sg:tags":[
        "agency",
        "rental"
    ],
    "wof:name":"Dawson Compress & Storage",
    "wof:placetype":"venue"
},
  "geometry": {"coordinates":[-84.446808,31.774125],"type":"Point"}
}