{
  "type": "Feature",
  "properties": {
    "iso:country":"US",
    "sg:address":"4350 Martha Berry Hwy",
    "sg:city":"Rome",
    "sg:classifiers":[
        {
            "category":"Banks & Credit Unions",
            "subcategory":"Bank",
            "type":"Services"
        }
    ],
    "sg:phone":"+1 706 232 0665",
    "sg:postcode":"30165",
    "sg:province":"GA",
    "sg:tags":[
        "machine",
        "teller",
        "automated"
    ],
    "wof:name":"E TRADE Atm",
    "wof:placetype":"venue"
},
  "geometry": {"coordinates":[-85.172325,34.346676],"type":"Point"}
}