{
  "type": "Feature",
  "properties": {
    "addr:full":"2447 Rock Springs Rd Buford GA 30519",
    "addr:housenumber":"2447",
    "addr:postcode":"30519",
    "addr:street":"Rock Springs Rd",
    "iso:country":"US",
    "sg:address":"2447 Rock Springs Rd",
    "sg:city":"Buford",
    "sg:classifiers":[
        {
            "category":"Building & Trades",
            "subcategory":"Landscaping Services",
            "type":"Services"
        }
    ],
    "sg:phone":"+1 770 963 5607",
    "sg:postcode":"30519",
    "sg:province":"GA",
    "wof:name":"Lawns of South Inc",
    "wof:placetype":"venue"
},
  "geometry": {"coordinates":[-83.966793,34.047731],"type":"Point"}
}