{
  "type": "Feature",
  "properties": {
    "iso:country":"US",
    "sg:address":"63 Keys Ferry St",
    "sg:city":"McDonough",
    "sg:classifiers":[
        {
            "category":"Building & Trades",
            "subcategory":"Plumbing",
            "type":"Services"
        }
    ],
    "sg:phone":"+1 770 957 5770",
    "sg:postcode":"30253",
    "sg:province":"GA",
    "sg:website":"www.hardingplumbingsupply.com",
    "wof:name":"Harding Plumbing & Supply Inc",
    "wof:placetype":"venue"
},
  "geometry": {"coordinates":[-84.145203,33.447102],"type":"Point"}
}