{
  "type": "Feature",
  "properties": {
    "addr:full":"420 Rockmart Rd Villa Rica GA 30180",
    "addr:housenumber":"420",
    "addr:postcode":"30180",
    "addr:street":"Rockmart Rd",
    "iso:country":"US",
    "sg:address":"420 Rockmart Rd",
    "sg:city":"Villa Rica",
    "sg:classifiers":[
        {
            "category":"Personal",
            "subcategory":"Beauty Salon",
            "type":"Services"
        }
    ],
    "sg:phone":"+1 770 456 9276",
    "sg:postcode":"30180",
    "sg:province":"GA",
    "sg:tags":[
        "shop"
    ],
    "wof:name":"T & M Hair Palace",
    "wof:placetype":"venue"
},
  "geometry": {"coordinates":[-84.924374,33.742547],"type":"Point"}
}