{
  "type": "Feature",
  "properties": {
    "addr:full":"106 Malone St Sandersville GA 31082",
    "addr:housenumber":"106",
    "addr:postcode":"31082",
    "addr:street":"Malone St",
    "iso:country":"US",
    "sg:address":"106 Malone St",
    "sg:city":"Sandersville",
    "sg:classifiers":[
        {
            "category":"Banks & Credit Unions",
            "subcategory":"Investment Brokerage",
            "type":"Services"
        }
    ],
    "sg:phone":"+1 478 553 1665",
    "sg:postcode":"31082",
    "sg:province":"GA",
    "wof:name":"Raymond James",
    "wof:placetype":"venue"
},
  "geometry": {"coordinates":[-82.81208599999999,32.98386],"type":"Point"}
}