{
  "type": "Feature",
  "properties": {
    "addr:full":"5652 Jonesboro Rd Morrow GA 30260",
    "addr:housenumber":"5652",
    "addr:postcode":"30260",
    "addr:street":"Jonesboro Rd",
    "iso:country":"US",
    "sg:address":"5652 Jonesboro Rd",
    "sg:city":"Morrow",
    "sg:classifiers":[
        {
            "category":"Shopping",
            "subcategory":"Clothing, Apparel, & Fashions",
            "type":"Retail Goods"
        }
    ],
    "sg:phone":"+1 678 422 6719",
    "sg:postcode":"30260",
    "sg:province":"GA",
    "sg:tags":[
        "accessory"
    ],
    "sg:website":"www.catofashions.com",
    "wof:name":"Cato",
    "wof:placetype":"venue"
},
  "geometry": {"coordinates":[-84.340211,33.602628],"type":"Point"}
}