{
  "type": "Feature",
  "properties": {
    "iso:country":"US",
    "sg:address":"221 Cleveland Ave SW",
    "sg:city":"Atlanta",
    "sg:classifiers":[
        {
            "category":"Banks & Credit Unions",
            "subcategory":"Bank",
            "type":"Services"
        }
    ],
    "sg:phone":"+1 404 762 5250",
    "sg:postcode":"30315",
    "sg:province":"GA",
    "sg:tags":[
        "financing"
    ],
    "wof:name":"Eu Finance",
    "wof:placetype":"venue"
},
  "geometry": {"coordinates":[-84.398353,33.681043],"type":"Point"}
}