{
  "type": "Feature",
  "properties": {
    "iso:country":"US",
    "sg:address":"2900 Peachtree Road NW",
    "sg:city":"Atlanta",
    "sg:classifiers":[
        {
            "category":"Insurance",
            "subcategory":"Health Insurance",
            "type":"Services"
        }
    ],
    "sg:phone":"+1 404 266 9115",
    "sg:postcode":"30305",
    "sg:province":"GA",
    "sg:tags":[
        "market"
    ],
    "wof:name":"Willner Chemists",
    "wof:placetype":"venue"
},
  "geometry": {"coordinates":[-84.38328300000001,33.833563],"type":"Point"}
}