{
  "type": "Feature",
  "properties": {
    "addr:full":"1235 US Hwy 84 Hinesville GA 31313",
    "addr:housenumber":"1235",
    "addr:postcode":"31313",
    "addr:street":"Us Hwy 84",
    "iso:country":"US",
    "sg:address":"1235 US Hwy 84",
    "sg:city":"Hinesville",
    "sg:classifiers":[
        {
            "category":"Wholesale",
            "subcategory":"Groceries",
            "type":"Manufacturing & Wholesale Goods"
        }
    ],
    "sg:phone":"+1 912 876 8946",
    "sg:postcode":"31313",
    "sg:province":"GA",
    "sg:tags":[
        "baker"
    ],
    "wof:name":"Derst Baking Co",
    "wof:placetype":"venue"
},
  "geometry": {"coordinates":[-81.604703,31.803752],"type":"Point"}
}