{
  "type": "Feature",
  "properties": {
    "addr:full":"1307 Oak Ct Eastman GA 31023",
    "addr:housenumber":"1307",
    "addr:postcode":"31023",
    "addr:street":"Oak Ct",
    "iso:country":"US",
    "sg:address":"1307 Oak Ct",
    "sg:city":"Eastman",
    "sg:classifiers":[
        {
            "category":"Shopping",
            "subcategory":"Department Store",
            "type":"Retail Goods"
        }
    ],
    "sg:phone":"+1 478 374 7782",
    "sg:postcode":"31023",
    "sg:province":"GA",
    "wof:name":"Wal-Mart",
    "wof:placetype":"venue"
},
  "geometry": {"coordinates":[-83.170682,32.176368],"type":"Point"}
}