{
  "type": "Feature",
  "properties": {
    "iso:country":"US",
    "sg:address":"8176 Connally Dr",
    "sg:city":"Douglasville",
    "sg:classifiers":[
        {
            "category":"Building & Trades",
            "subcategory":"Landscaping Services",
            "type":"Services"
        }
    ],
    "sg:phone":"+1 770 489 4016",
    "sg:postcode":"30134",
    "sg:province":"GA",
    "wof:name":"Quality Tree Care & Ldscpg",
    "wof:placetype":"venue"
},
  "geometry": {"coordinates":[-84.729075,33.751146],"type":"Point"}
}