{
  "type": "Feature",
  "properties": {
    "addr:full":"Two Ravinia Dr Ste 500 Atlanta GA 30346",
    "addr:postcode":"30346",
    "addr:street":"Ravinia Dr Ste 500",
    "iso:country":"US",
    "sg:address":"Two Ravinia Dr Ste 500",
    "sg:city":"Atlanta",
    "sg:classifiers":[
        {
            "category":"Health Services",
            "subcategory":"Chiropractor",
            "type":"Services"
        }
    ],
    "sg:phone":"+1 678 520 4578",
    "sg:postcode":"30346",
    "sg:province":"GA",
    "sg:website":"www.ventichiropractic.com",
    "wof:name":"Venti Chiropractic and Sports Medicine",
    "wof:placetype":"venue"
},
  "geometry": {"coordinates":[-84.335965,33.922157],"type":"Point"}
}