{
  "type": "Feature",
  "properties": {
    "iso:country":"US",
    "sg:address":"3377 English Oaks Dr NW",
    "sg:city":"Kennesaw",
    "sg:classifiers":[
        {
            "category":"Professional",
            "type":"Services"
        }
    ],
    "sg:phone":"+1 770 547 0110",
    "sg:postcode":"30144",
    "sg:province":"GA",
    "wof:name":"S&S Custom Designs",
    "wof:placetype":"venue"
},
  "geometry": {"coordinates":[-84.63308499999999,34.040101],"type":"Point"}
}