{
  "type": "Feature",
  "properties": {
    "iso:country":"US",
    "sg:address":"941 Ellis St",
    "sg:city":"Augusta",
    "sg:classifiers":[
        {
            "category":"Retail",
            "subcategory":"Repair Shop",
            "type":"Services"
        }
    ],
    "sg:phone":"+1 706 823 7031",
    "sg:postcode":"30901",
    "sg:province":"GA",
    "sg:tags":[
        "maintenance",
        "furniture"
    ],
    "wof:name":"Augusta Office & Fixture Co",
    "wof:placetype":"venue"
},
  "geometry": {"coordinates":[-81.969258,33.475523],"type":"Point"}
}