{
  "type": "Feature",
  "properties": {
    "addr:full":"2930 Alden Green Trl Atlanta GA 30344",
    "addr:housenumber":"2930",
    "addr:postcode":"30344",
    "addr:street":"Alden Green Trl",
    "iso:country":"US",
    "sg:address":"2930 Alden Green Trl",
    "sg:city":"Atlanta",
    "sg:classifiers":[
        {
            "category":"Organizations",
            "subcategory":"Religious Organization",
            "type":"Services"
        }
    ],
    "sg:phone":"+1 404 344 0969",
    "sg:postcode":"30344",
    "sg:province":"GA",
    "wof:name":"D E Bryant",
    "wof:placetype":"venue"
},
  "geometry": {"coordinates":[-84.48407899999999,33.676082],"type":"Point"}
}