{
  "type": "Feature",
  "properties": {
    "iso:country":"US",
    "sg:address":"743 Washington Ave NE",
    "sg:city":"Marietta",
    "sg:classifiers":[
        {
            "category":"Social Services",
            "type":"Services"
        },
        {
            "category":"Professional",
            "subcategory":"Employment Agencies",
            "type":"Services"
        }
    ],
    "sg:phone":"+1 770 231 9669",
    "sg:postcode":"30060",
    "sg:province":"GA",
    "sg:tags":[
        "workers'",
        "placement",
        "volunteer"
    ],
    "wof:name":"The Kendayl Craig Foundation Limited",
    "wof:placetype":"venue"
},
  "geometry": {"coordinates":[-84.530271,33.951881],"type":"Point"}
}