{
  "type": "Feature",
  "properties": {
    "addr:full":"1041 N 3rd Ave Chatsworth GA 30705",
    "addr:housenumber":"1041",
    "addr:postcode":"30705",
    "addr:street":"N 3Rd Ave",
    "iso:country":"US",
    "sg:address":"1041 N 3rd Ave",
    "sg:city":"Chatsworth",
    "sg:classifiers":[
        {
            "category":"Restaurant",
            "type":"Food & Drink"
        }
    ],
    "sg:menulink":"http://www.allmenus.com/ga/chatsworth/180695-wendys/menu/",
    "sg:phone":"+1 706 695 4100",
    "sg:postcode":"30705",
    "sg:province":"GA",
    "sg:tags":[
        "burger",
        "american",
        "soup"
    ],
    "wof:name":"Wendy's",
    "wof:placetype":"venue"
},
  "geometry": {"coordinates":[-84.77055900000001,34.783279],"type":"Point"}
}