{
  "type": "Feature",
  "properties": {
    "addr:full":"404 Martin Luther King Jr Dr Tifton GA 31794",
    "addr:housenumber":"404",
    "addr:postcode":"31794",
    "addr:street":"Martin Luther King Jr Dr",
    "iso:country":"US",
    "sg:address":"404 Martin Luther King Jr Dr",
    "sg:city":"Tifton",
    "sg:classifiers":[
        {
            "category":"Education",
            "subcategory":"School",
            "type":"Public Place"
        }
    ],
    "sg:phone":"+1 229 386 6520",
    "sg:postcode":"31794",
    "sg:province":"GA",
    "wof:name":"J T Reddick Elementry School",
    "wof:placetype":"venue"
},
  "geometry": {"coordinates":[-83.50981,31.438121],"type":"Point"}
}