{
  "type": "Feature",
  "properties": {
    "addr:full":"7804 Senoia Rd Fairburn GA 30213",
    "addr:housenumber":"7804",
    "addr:postcode":"30213",
    "addr:street":"Senoia Rd",
    "iso:country":"US",
    "sg:address":"7804 Senoia Rd",
    "sg:city":"Fairburn",
    "sg:classifiers":[
        {
            "category":"Bakery",
            "type":"Food & Drink"
        },
        {
            "category":"Coffee & Tea",
            "type":"Food & Drink"
        },
        {
            "category":"Bagels",
            "type":"Food & Drink"
        },
        {
            "category":"Donuts",
            "type":"Food & Drink"
        }
    ],
    "sg:menulink":"http://www.allmenus.com/ga/fairburn-union-city/130386-dunkin-donuts/menu/",
    "sg:phone":"+1 770 774 0318",
    "sg:postcode":"30213",
    "sg:province":"GA",
    "sg:tags":[
        "american",
        "diner",
        "pastry"
    ],
    "wof:name":"Dunkin' Donuts",
    "wof:placetype":"venue"
},
  "geometry": {"coordinates":[-84.57701,33.544279],"type":"Point"}
}