{
  "type": "Feature",
  "properties": {
    "addr:full":"2800 Club Dr Gainesville GA 30506",
    "addr:housenumber":"2800",
    "addr:postcode":"30506",
    "addr:street":"Club Dr",
    "iso:country":"US",
    "sg:address":"2800 Club Dr",
    "sg:city":"Gainesville",
    "sg:classifiers":[
        {
            "category":"Retail",
            "subcategory":"Storage",
            "type":"Services"
        }
    ],
    "sg:phone":"+1 770 297 9212",
    "sg:postcode":"30506",
    "sg:province":"GA",
    "sg:tags":[
        "self",
        "commercial",
        "household"
    ],
    "wof:name":"Oak Street Mini Storage",
    "wof:placetype":"venue"
},
  "geometry": {"coordinates":[-83.863213,34.342789],"type":"Point"}
}