{
  "type": "Feature",
  "properties": {
    "iso:country":"US",
    "sg:address":"705 3rd St W",
    "sg:city":"Tifton",
    "sg:classifiers":[
        {
            "category":"Retail",
            "subcategory":"Laundry & Dry Cleaning",
            "type":"Services"
        }
    ],
    "sg:phone":"+1 229 382 6522",
    "sg:postcode":"31794",
    "sg:province":"GA",
    "wof:name":"Julias Dressmaking & Alterati",
    "wof:placetype":"venue"
},
  "geometry": {"coordinates":[-83.52493,31.452273],"type":"Point"}
}