{
  "type": "Feature",
  "properties": {
    "iso:country":"US",
    "sg:address":"2014 Center Point Rd",
    "sg:city":"Temple",
    "sg:classifiers":[
        {
            "category":"Professional",
            "type":"Services"
        }
    ],
    "sg:phone":"+1 770 562 3806",
    "sg:postcode":"30179",
    "sg:province":"GA",
    "wof:name":"Jimmy R Parrish Jr",
    "wof:placetype":"venue"
},
  "geometry": {"coordinates":[-85.059538,33.688893],"type":"Point"}
}