{
  "type": "Feature",
  "properties": {
    "addr:full":"14 Foundation Dr Savannah GA 31408",
    "addr:housenumber":"14",
    "addr:postcode":"31408",
    "addr:street":"Foundation Dr",
    "iso:country":"US",
    "sg:address":"14 Foundation Dr",
    "sg:city":"Savannah",
    "sg:classifiers":[
        {
            "category":"Building & Trades",
            "subcategory":"Construction",
            "type":"Services"
        }
    ],
    "sg:phone":"+1 912 964 0811",
    "sg:postcode":"31408",
    "sg:province":"GA",
    "sg:tags":[
        "product",
        "asphalt"
    ],
    "wof:name":"Koch Materials Co",
    "wof:placetype":"venue"
},
  "geometry": {"coordinates":[-81.140648,32.099883],"type":"Point"}
}