{
  "type": "Feature",
  "properties": {
    "iso:country":"US",
    "sg:address":"4794 Mercer University Dr",
    "sg:city":"Macon",
    "sg:classifiers":[
        {
            "category":"Real Estate",
            "subcategory":"Real Estate Agent",
            "type":"Services"
        }
    ],
    "sg:phone":"+1 478 405 6506",
    "sg:postcode":"31210",
    "sg:province":"GA",
    "wof:name":"Steve Stone Enterprises",
    "wof:placetype":"venue"
},
  "geometry": {"coordinates":[-83.72578799999999,32.830928],"type":"Point"}
}