{
  "type": "Feature",
  "properties": {
    "addr:full":"102 Social Cir Cumming GA 30040",
    "addr:postcode":"30040",
    "addr:street":"Social Cir",
    "iso:country":"US",
    "sg:address":"102 Social Cir",
    "sg:city":"Cumming",
    "sg:classifiers":[
        {
            "category":"Real Estate",
            "subcategory":"Real Estate Operator",
            "type":"Services"
        }
    ],
    "sg:phone":"+1 770 887 5331",
    "sg:postcode":"30040",
    "sg:province":"GA",
    "sg:tags":[
        "building",
        "apartment"
    ],
    "wof:name":"Oakland Oaks Apartments Inc",
    "wof:placetype":"venue"
},
  "geometry": {"coordinates":[-84.14597999999999,34.206536],"type":"Point"}
}