{
  "type": "Feature",
  "properties": {
    "iso:country":"US",
    "sg:address":"59 Holmesville Rd",
    "sg:city":"Jesup",
    "sg:classifiers":[
        {
            "category":"Manufacturing",
            "subcategory":"Building Materials",
            "type":"Manufacturing & Wholesale Goods"
        }
    ],
    "sg:phone":"+1 912 427 0586",
    "sg:postcode":"31545",
    "sg:province":"GA",
    "sg:tags":[
        "cabinet"
    ],
    "wof:name":"Jesup Cabinet",
    "wof:placetype":"venue"
},
  "geometry": {"coordinates":[-81.92720300000001,31.601837],"type":"Point"}
}