{
  "type": "Feature",
  "properties": {
    "addr:full":"2807 Roger Lacey Ave Savannah GA 31404",
    "addr:housenumber":"2807",
    "addr:postcode":"31404",
    "addr:street":"Roger Lacey Ave",
    "iso:country":"US",
    "sg:address":"2807 Roger Lacey Ave",
    "sg:city":"Savannah",
    "sg:classifiers":[
        {
            "category":"Real Estate",
            "subcategory":"Developer",
            "type":"Services"
        }
    ],
    "sg:phone":"+1 912 691 1234",
    "sg:postcode":"31404",
    "sg:province":"GA",
    "wof:name":"Southeastern Land Co LLC",
    "wof:placetype":"venue"
},
  "geometry": {"coordinates":[-81.06047700000001,32.036562],"type":"Point"}
}