{
  "type": "Feature",
  "properties": {
    "addr:full":"4212 Bucknell Pl Decatur GA 30034",
    "addr:housenumber":"4212",
    "addr:postcode":"30034",
    "addr:street":"Bucknell Pl",
    "iso:country":"US",
    "sg:address":"4212 Bucknell Pl",
    "sg:city":"Decatur",
    "sg:classifiers":[
        {
            "category":"Professional",
            "subcategory":"Business Services",
            "type":"Services"
        }
    ],
    "sg:phone":"+1 770 322 7863",
    "sg:postcode":"30034",
    "sg:province":"GA",
    "wof:name":"Murphey Enterprises",
    "wof:placetype":"venue"
},
  "geometry": {"coordinates":[-84.215892,33.668473],"type":"Point"}
}