{
  "type": "Feature",
  "properties": {
    "iso:country":"US",
    "sg:address":"3120 Roswell Rd NW",
    "sg:city":"Atlanta",
    "sg:classifiers":[
        {
            "category":"Restaurant",
            "type":"Food & Drink"
        }
    ],
    "sg:phone":"+1 404 231 1798",
    "sg:postcode":"30305",
    "sg:province":"GA",
    "wof:name":"Sushi Rock Cafe",
    "wof:placetype":"venue"
},
  "geometry": {"coordinates":[-84.379097,33.840599],"type":"Point"}
}