{
  "type": "Feature",
  "properties": {
    "addr:full":"2138 Hamilton Rd Lagrange GA 30241",
    "addr:housenumber":"2138",
    "addr:postcode":"30241",
    "addr:street":"Hamilton Rd",
    "iso:country":"US",
    "sg:address":"2138 Hamilton Rd",
    "sg:city":"Lagrange",
    "sg:classifiers":[
        {
            "category":"Home & Garden",
            "subcategory":"Furniture",
            "type":"Retail Goods"
        }
    ],
    "sg:phone":"+1 706 812 0017",
    "sg:postcode":"30241",
    "sg:province":"GA",
    "sg:tags":[
        "top",
        "counter"
    ],
    "wof:name":"CDS",
    "wof:placetype":"venue"
},
  "geometry": {"coordinates":[-85.00967199999999,32.996818],"type":"Point"}
}