{
  "type": "Feature",
  "properties": {
    "addr:full":"2275 Schatulga Rd Columbus GA 31907",
    "addr:housenumber":"2275",
    "addr:postcode":"31907",
    "addr:street":"Schatulga Rd",
    "iso:country":"US",
    "sg:address":"2275 Schatulga Rd",
    "sg:city":"Columbus",
    "sg:classifiers":[
        {
            "category":"Organizations",
            "subcategory":"Religious Organization",
            "type":"Services"
        }
    ],
    "sg:phone":"+1 706 562 0026",
    "sg:postcode":"31907",
    "sg:province":"GA",
    "sg:tags":[
        "church"
    ],
    "wof:name":"Baptist Church Of Christ",
    "wof:placetype":"venue"
},
  "geometry": {"coordinates":[-84.86976900000001,32.480606],"type":"Point"}
}