{
  "type": "Feature",
  "properties": {
    "addr:full":"248 Alabama St St Simons Island GA 31522",
    "addr:housenumber":"248",
    "addr:postcode":"31522",
    "addr:street":"Alabama St",
    "iso:country":"US",
    "sg:address":"248 Alabama St",
    "sg:city":"St Simons Island",
    "sg:classifiers":[
        {
            "category":"Shopping",
            "subcategory":"Gifts & Souvenirs",
            "type":"Retail Goods"
        }
    ],
    "sg:phone":"+1 912 634 8100",
    "sg:postcode":"31522",
    "sg:province":"GA",
    "sg:tags":[
        "shop"
    ],
    "wof:name":"Village Holiday & Gifts",
    "wof:placetype":"venue"
},
  "geometry": {"coordinates":[-81.38398100000001,31.162963],"type":"Point"}
}