{
  "type": "Feature",
  "properties": {
    "iso:country":"US",
    "sg:address":"2301 Henry Clower Blvd",
    "sg:city":"Snellville",
    "sg:classifiers":[
        {
            "category":"Banks & Credit Unions",
            "subcategory":"Financial Services",
            "type":"Services"
        }
    ],
    "sg:phone":"+1 678 397 1010",
    "sg:postcode":"30078",
    "sg:province":"GA",
    "sg:tags":[
        "broker",
        "mortgage"
    ],
    "wof:name":"Home America Mortgage",
    "wof:placetype":"venue"
},
  "geometry": {"coordinates":[-84.025302,33.854446],"type":"Point"}
}