{
  "type": "Feature",
  "properties": {
    "addr:full":"4003 Shady Cir NW Lilburn GA 30047",
    "addr:housenumber":"4003",
    "addr:postcode":"30047",
    "addr:street":"Shady Cir Nw",
    "iso:country":"US",
    "sg:address":"4003 Shady Cir NW",
    "sg:city":"Lilburn",
    "sg:classifiers":[
        {
            "category":"Professional",
            "subcategory":"Management & Consulting",
            "type":"Services"
        }
    ],
    "sg:phone":"+1 770 921 8021",
    "sg:postcode":"30047",
    "sg:province":"GA",
    "sg:tags":[
        "marketing",
        "program"
    ],
    "wof:name":"Mc Kelvey-Fulkes Marketing",
    "wof:placetype":"venue"
},
  "geometry": {"coordinates":[-84.127628,33.918721],"type":"Point"}
}