{
  "type": "Feature",
  "properties": {
    "addr:full":"12521 White Bluff Rd Savannah GA 31419",
    "addr:housenumber":"12521",
    "addr:postcode":"31419",
    "addr:street":"White Bluff Rd",
    "iso:country":"US",
    "sg:address":"12521 White Bluff Rd",
    "sg:city":"Savannah",
    "sg:classifiers":[
        {
            "category":"Organizations",
            "subcategory":"Religious Organization",
            "type":"Services"
        }
    ],
    "sg:phone":"+1 912 925 8658",
    "sg:postcode":"31419",
    "sg:province":"GA",
    "sg:tags":[
        "baptist",
        "church"
    ],
    "wof:name":"Windsor Forest Pre School",
    "wof:placetype":"venue"
},
  "geometry": {"coordinates":[-81.133038,31.972876],"type":"Point"}
}