{
  "type": "Feature",
  "properties": {
    "addr:full":"1448 N Morningside Dr NE Atlanta GA 30306",
    "addr:housenumber":"1448",
    "addr:postcode":"30306",
    "addr:street":"N Morningside Dr Ne",
    "iso:country":"US",
    "sg:address":"1448 N Morningside Dr NE",
    "sg:city":"Atlanta",
    "sg:classifiers":[
        {
            "category":"Retail",
            "subcategory":"Portrait Studio",
            "type":"Services"
        },
        {
            "category":"Professional",
            "subcategory":"Art Services",
            "type":"Services"
        }
    ],
    "sg:phone":"+1 404 872 7272",
    "sg:postcode":"30306",
    "sg:province":"GA",
    "sg:tags":[
        "rental",
        "photographers-portrait",
        "photographic",
        "darkroom"
    ],
    "wof:name":"S A & A",
    "wof:placetype":"venue"
},
  "geometry": {"coordinates":[-84.358333,33.794256],"type":"Point"}
}