{
  "type": "Feature",
  "properties": {
    "addr:full":"606 Whatley Dr Ashburn GA 31714",
    "addr:housenumber":"606",
    "addr:postcode":"31714",
    "addr:street":"Whatley Dr",
    "iso:country":"US",
    "sg:address":"606 Whatley Dr",
    "sg:city":"Ashburn",
    "sg:classifiers":[
        {
            "category":"Shopping",
            "subcategory":"Books",
            "type":"Retail Goods"
        }
    ],
    "sg:phone":"+1 229 567 2757",
    "sg:postcode":"31714",
    "sg:province":"GA",
    "wof:name":"T Judy Gregory",
    "wof:placetype":"venue"
},
  "geometry": {"coordinates":[-83.64042499999999,31.717837],"type":"Point"}
}