{
  "type": "Feature",
  "properties": {
    "addr:full":"955 Florence St Augusta GA 30901",
    "addr:housenumber":"955",
    "addr:postcode":"30901",
    "addr:street":"Florence St",
    "iso:country":"US",
    "sg:address":"955 Florence St",
    "sg:city":"Augusta",
    "sg:classifiers":[
        {
            "category":"Organizations",
            "subcategory":"Religious Organization",
            "type":"Services"
        }
    ],
    "sg:phone":"+1 706 724 2009",
    "sg:postcode":"30901",
    "sg:province":"GA",
    "sg:tags":[
        "church"
    ],
    "wof:name":"Crawford Baptist Church",
    "wof:placetype":"venue"
},
  "geometry": {"coordinates":[-81.97590599999999,33.462322],"type":"Point"}
}