{
  "type": "Feature",
  "properties": {
    "addr:full":"1910 Pat Lewis Rd Baxley GA 31513",
    "addr:housenumber":"1910",
    "addr:postcode":"31513",
    "addr:street":"Pat Lewis Rd",
    "iso:country":"US",
    "sg:address":"1910 Pat Lewis Rd",
    "sg:city":"Baxley",
    "sg:classifiers":[
        {
            "category":"Mining & Drilling",
            "type":"Manufacturing & Wholesale Goods"
        }
    ],
    "sg:phone":"+1 912 367 0886",
    "sg:postcode":"31513",
    "sg:province":"GA",
    "sg:tags":[
        "tank",
        "gas",
        "testing",
        "storage",
        "underground",
        "line"
    ],
    "wof:name":"Tim Flood and Son Inc",
    "wof:placetype":"venue"
},
  "geometry": {"coordinates":[-82.398386,31.659421],"type":"Point"}
}