{
  "type": "Feature",
  "properties": {
    "addr:full":"7066 Lodgetown Rd Pelham GA 31779",
    "addr:housenumber":"7066",
    "addr:postcode":"31779",
    "addr:street":"Lodgetown Rd",
    "iso:country":"US",
    "sg:address":"7066 Lodgetown Rd",
    "sg:city":"Pelham",
    "sg:classifiers":[
        {
            "category":"Farming",
            "subcategory":"Farm & Veterinary Services",
            "type":"Manufacturing & Wholesale Goods"
        }
    ],
    "sg:phone":"+1 912 294 2273",
    "sg:postcode":"31779",
    "sg:province":"GA",
    "sg:tags":[
        "management"
    ],
    "wof:name":"Advanced Crop Care Inc",
    "wof:placetype":"venue"
},
  "geometry": {"coordinates":[-84.27931700000001,31.096228],"type":"Point"}
}