{
  "type": "Feature",
  "properties": {
    "addr:full":"3600 Dallas Hwy Ste 290 Marietta GA 30064",
    "addr:housenumber":"3600",
    "addr:postcode":"30064",
    "addr:street":"Dallas Hwy Ste 290",
    "iso:country":"US",
    "sg:address":"3600 Dallas Hwy Ste 290",
    "sg:city":"Marietta",
    "sg:classifiers":[
        {
            "category":"Personal",
            "subcategory":"Tanning Parlor",
            "type":"Services"
        }
    ],
    "sg:phone":"+1 770 426 4004",
    "sg:postcode":"30064",
    "sg:province":"GA",
    "sg:website":"www.mauibeachtanningsalon.com",
    "wof:name":"Maui Beach Tanning Salon",
    "wof:placetype":"venue"
},
  "geometry": {"coordinates":[-84.65539699999999,33.953832],"type":"Point"}
}