{
  "type": "Feature",
  "properties": {
    "iso:country":"US",
    "sg:address":"900 Audubon Dr",
    "sg:city":"Marietta",
    "sg:classifiers":[
        {
            "category":"Sports & Exercise",
            "subcategory":"Tennis Court",
            "type":"Entertainment"
        }
    ],
    "sg:phone":"+1 770 973 0341",
    "sg:postcode":"30068",
    "sg:province":"GA",
    "wof:name":"Tennis Academy of Ga",
    "wof:placetype":"venue"
},
  "geometry": {"coordinates":[-84.434757,33.975207],"type":"Point"}
}