{
  "type": "Feature",
  "properties": {
    "iso:country":"US",
    "sg:address":"11 Gateway Blvd S",
    "sg:city":"Savannah",
    "sg:classifiers":[
        {
            "category":"Shopping",
            "subcategory":"Hobbies, Toys, & Games",
            "type":"Retail Goods"
        }
    ],
    "sg:phone":"+1 912 961 7891",
    "sg:postcode":"31419",
    "sg:province":"GA",
    "wof:name":"Kb Toy Outlet",
    "wof:placetype":"venue"
},
  "geometry": {"coordinates":[-81.283249,32.000967],"type":"Point"}
}