{
  "type": "Feature",
  "properties": {
    "addr:full":"1594 Mount Vernon Rd Atlanta GA 30338",
    "addr:housenumber":"1594",
    "addr:postcode":"30338",
    "addr:street":"Mount Vernon Rd",
    "iso:country":"US",
    "sg:address":"1594 Mount Vernon Rd",
    "sg:city":"Atlanta",
    "sg:classifiers":[
        {
            "category":"Food & Beverages",
            "subcategory":"Bakery",
            "type":"Retail Goods"
        }
    ],
    "sg:phone":"+1 678 587 9895",
    "sg:postcode":"30338",
    "sg:province":"GA",
    "sg:tags":[
        "coffee",
        "espresso",
        "doughnut",
        "restaurant"
    ],
    "sg:website":"http://www.dunkindonuts.com",
    "wof:name":"Dunkin' Donuts",
    "wof:placetype":"venue"
},
  "geometry": {"coordinates":[-84.33477000000001,33.945889],"type":"Point"}
}