{
  "type": "Feature",
  "properties": {
    "addr:full":"1007 N Ashley St Valdosta GA 31601",
    "addr:housenumber":"1007",
    "addr:postcode":"31601",
    "addr:street":"N Ashley St",
    "iso:country":"US",
    "sg:address":"1007 N Ashley St",
    "sg:city":"Valdosta",
    "sg:classifiers":[
        {
            "category":"Manufacturing",
            "subcategory":"Buildings",
            "type":"Manufacturing & Wholesale Goods"
        },
        {
            "category":"Building & Trades",
            "subcategory":"Construction",
            "type":"Services"
        }
    ],
    "sg:phone":"+1 229 253 0963",
    "sg:postcode":"31601",
    "sg:province":"GA",
    "sg:tags":[
        "industrial",
        "system",
        "specialty",
        "builder",
        "heating",
        "contractor",
        "contractors-commercial",
        "home",
        "air conditioning"
    ],
    "wof:name":"C & W Builders Inc",
    "wof:placetype":"venue"
},
  "geometry": {"coordinates":[-83.280129,30.842077],"type":"Point"}
}