{
  "type": "Feature",
  "properties": {
    "iso:country":"US",
    "sg:address":"349 Glynn St N",
    "sg:city":"Fayetteville",
    "sg:classifiers":[
        {
            "category":"Retail",
            "subcategory":"Repair Shop",
            "type":"Services"
        }
    ],
    "sg:phone":"+1 770 716 3895",
    "sg:postcode":"30214",
    "sg:province":"GA",
    "sg:tags":[
        "cleaners",
        "parts",
        "vacuum"
    ],
    "wof:name":"JWH Svc",
    "wof:placetype":"venue"
},
  "geometry": {"coordinates":[-84.45485600000001,33.454726],"type":"Point"}
}