{
  "type": "Feature",
  "properties": {
    "addr:full":"119 Martin Luther King Jr Dr Dublin GA 31021",
    "addr:housenumber":"119",
    "addr:postcode":"31021",
    "addr:street":"Martin Luther King Jr Dr",
    "iso:country":"US",
    "sg:address":"119 Martin Luther King Jr Dr",
    "sg:city":"Dublin",
    "sg:classifiers":[
        {
            "category":"Social Services",
            "subcategory":"Child Care",
            "type":"Services"
        }
    ],
    "sg:phone":"+1 478 272 2866",
    "sg:postcode":"31021",
    "sg:province":"GA",
    "sg:tags":[
        "kindergarten",
        "academic",
        "school"
    ],
    "wof:name":"Dublin Headstart",
    "wof:placetype":"venue"
},
  "geometry": {"coordinates":[-82.901195,32.535071],"type":"Point"}
}