{
  "type": "Feature",
  "properties": {
    "addr:full":"633 J O Stewart Rd Norman Park GA 31771",
    "addr:housenumber":"633",
    "addr:postcode":"31771",
    "addr:street":"J O Stewart Rd",
    "iso:country":"US",
    "sg:address":"633 J O Stewart Rd",
    "sg:city":"Norman Park",
    "sg:classifiers":[
        {
            "category":"Professional",
            "type":"Services"
        }
    ],
    "sg:phone":"+1 229 890 2572",
    "sg:postcode":"31771",
    "sg:province":"GA",
    "wof:name":"Charlotte P Land",
    "wof:placetype":"venue"
},
  "geometry": {"coordinates":[-83.750528,31.241335],"type":"Point"}
}