{
  "type": "Feature",
  "properties": {
    "iso:country":"US",
    "sg:address":"118 Roswell Green Ln",
    "sg:city":"Roswell",
    "sg:classifiers":[
        {
            "category":"Shopping",
            "type":"Retail Goods"
        }
    ],
    "sg:phone":"+1 770 643 4784",
    "sg:postcode":"30075",
    "sg:province":"GA",
    "sg:tags":[
        "merchandise"
    ],
    "wof:name":"Applied Ionics Inc",
    "wof:placetype":"venue"
},
  "geometry": {"coordinates":[-84.36392600000001,34.051111],"type":"Point"}
}