{
  "type": "Feature",
  "properties": {
    "iso:country":"US",
    "sg:address":"471 S Church St Ste C",
    "sg:city":"Homerville",
    "sg:classifiers":[
        {
            "category":"Communications",
            "subcategory":"Television Station",
            "type":"Services"
        },
        {
            "category":"Professional",
            "subcategory":"Computer Services",
            "type":"Services"
        }
    ],
    "sg:phone":"+1 912 487 2224",
    "sg:postcode":"31634",
    "sg:province":"GA",
    "sg:tags":[
        "satellite",
        "isp",
        "internet",
        "cable",
        "provider"
    ],
    "sg:website":"http://www.comcast.com",
    "wof:name":"Comcast",
    "wof:placetype":"venue"
},
  "geometry": {"coordinates":[-82.743362,31.029711],"type":"Point"}
}