{
  "type": "Feature",
  "properties": {
    "iso:country":"US",
    "sg:address":"4 E Cypress St",
    "sg:city":"Ludowici",
    "sg:classifiers":[
        {
            "category":"Restaurant",
            "type":"Food & Drink"
        }
    ],
    "sg:menulink":"http://www.allmenus.com/ga/ludowici-south/147393-chesters/menu/",
    "sg:phone":"+1 912 545 9386",
    "sg:postcode":"31316",
    "sg:province":"GA",
    "sg:tags":[
        "american"
    ],
    "wof:name":"Chester's",
    "wof:placetype":"venue"
},
  "geometry": {"coordinates":[-81.745994,31.713185],"type":"Point"}
}