{
  "type": "Feature",
  "properties": {
    "iso:country":"US",
    "sg:address":"2584 Alston Drive SE",
    "sg:city":"Atlanta",
    "sg:classifiers":[
        {
            "category":"Sports & Exercise",
            "subcategory":"Golf",
            "type":"Entertainment"
        }
    ],
    "sg:phone":"+1 404 378 8687",
    "sg:postcode":"30317",
    "sg:province":"GA",
    "wof:name":"The Tour Championship",
    "wof:placetype":"venue"
},
  "geometry": {"coordinates":[-84.302136,33.744959],"type":"Point"}
}