{
  "type": "Feature",
  "properties": {
    "iso:country":"US",
    "sg:address":"416 Southern Hills Dr",
    "sg:city":"Monroe",
    "sg:classifiers":[
        {
            "category":"Building & Trades",
            "subcategory":"Landscaping Services",
            "type":"Services"
        }
    ],
    "sg:phone":"+1 770 266 0602",
    "sg:postcode":"30655",
    "sg:province":"GA",
    "sg:tags":[
        "landscape"
    ],
    "wof:name":"Phillip McDonald Inc",
    "wof:placetype":"venue"
},
  "geometry": {"coordinates":[-83.80611399999999,33.805693],"type":"Point"}
}