{
  "type": "Feature",
  "properties": {
    "addr:full":"2945 Cobb Pkwy NW Kennesaw GA 30152",
    "addr:housenumber":"2945",
    "addr:postcode":"30152",
    "addr:street":"Cobb Pkwy Nw",
    "iso:country":"US",
    "sg:address":"2945 Cobb Pkwy NW",
    "sg:city":"Kennesaw",
    "sg:classifiers":[
        {
            "category":"Travel",
            "subcategory":"Hotels & Motels",
            "type":"Entertainment"
        }
    ],
    "sg:phone":"+1 770 426 8400",
    "sg:postcode":"30152",
    "sg:province":"GA",
    "wof:name":"Superior Creek Lodge",
    "wof:placetype":"venue"
},
  "geometry": {"coordinates":[-84.635373,34.025913],"type":"Point"}
}