{
  "type": "Feature",
  "properties": {
    "iso:country":"US",
    "sg:address":"2804 Shell Bark Rd",
    "sg:city":"Decatur",
    "sg:classifiers":[
        {
            "category":"Social Services",
            "type":"Services"
        }
    ],
    "sg:phone":"+1 770 987 0925",
    "sg:postcode":"30035",
    "sg:province":"GA",
    "wof:name":"Walking Tgther In Sstrhood Inc",
    "wof:placetype":"venue"
},
  "geometry": {"coordinates":[-84.19192700000001,33.708339],"type":"Point"}
}