{
  "type": "Feature",
  "properties": {
    "iso:country":"US",
    "sg:address":"4821 Karls Gate Dr",
    "sg:city":"Marietta",
    "sg:classifiers":[
        {
            "category":"Wholesale",
            "subcategory":"Apparel",
            "type":"Manufacturing & Wholesale Goods"
        }
    ],
    "sg:phone":"+1 770 992 4329",
    "sg:postcode":"30068",
    "sg:province":"GA",
    "sg:tags":[
        "piece",
        "metal",
        "center"
    ],
    "wof:name":"Coleccion Luna",
    "wof:placetype":"venue"
},
  "geometry": {"coordinates":[-84.408553,33.988198],"type":"Point"}
}