{
  "type": "Feature",
  "properties": {
    "iso:country":"US",
    "sg:address":"7 Pinson Dr",
    "sg:city":"Cartersville",
    "sg:classifiers":[
        {
            "category":"Professional",
            "subcategory":"Accounting & Tax Preparation",
            "type":"Services"
        }
    ],
    "sg:phone":"+1 770 386 4529",
    "sg:postcode":"30120",
    "sg:province":"GA",
    "sg:tags":[
        "return",
        "filing"
    ],
    "wof:name":"Martin's Tax Svc",
    "wof:placetype":"venue"
},
  "geometry": {"coordinates":[-84.82959099999999,34.209905],"type":"Point"}
}