{
  "type": "Feature",
  "properties": {
    "addr:full":"790 Cobb Place Blvd NW Kennesaw GA 30144",
    "addr:housenumber":"790",
    "addr:postcode":"30144",
    "addr:street":"Cobb Place Blvd Nw",
    "iso:country":"US",
    "sg:address":"790 Cobb Place Blvd NW",
    "sg:city":"Kennesaw",
    "sg:classifiers":[
        {
            "category":"Restaurant",
            "type":"Food & Drink"
        }
    ],
    "sg:phone":"+1 678 797 9670",
    "sg:postcode":"30144",
    "sg:province":"GA",
    "sg:tags":[
        "mexican"
    ],
    "wof:name":"On the Border Mexican Grill & Cantina",
    "wof:placetype":"venue"
},
  "geometry": {"coordinates":[-84.571404,34.008701],"type":"Point"}
}