{
  "type": "Feature",
  "properties": {
    "iso:country":"US",
    "sg:address":"5495 Level Acres Dr",
    "sg:city":"Macon",
    "sg:classifiers":[
        {
            "category":"Manufacturing",
            "subcategory":"Tools & Machinery",
            "type":"Manufacturing & Wholesale Goods"
        }
    ],
    "sg:phone":"+1 478 745 0279",
    "sg:postcode":"31217",
    "sg:province":"GA",
    "sg:tags":[
        "machine",
        "shop"
    ],
    "sg:website":"www.elliottms.com",
    "wof:name":"Elliott Machine Shop",
    "wof:placetype":"venue"
},
  "geometry": {"coordinates":[-83.568579,32.782744],"type":"Point"}
}