{
  "type": "Feature",
  "properties": {
    "iso:country":"US",
    "sg:address":"662 Bellemeade Dr SW",
    "sg:city":"Marietta",
    "sg:classifiers":[
        {
            "category":"Social Services",
            "subcategory":"Child Care",
            "type":"Services"
        }
    ],
    "sg:phone":"+1 770 795 8245",
    "sg:postcode":"30008",
    "sg:province":"GA",
    "sg:tags":[
        "consulting",
        "childcare"
    ],
    "wof:name":"Jso Childcare Services",
    "wof:placetype":"venue"
},
  "geometry": {"coordinates":[-84.573572,33.918234],"type":"Point"}
}