{
  "type": "Feature",
  "properties": {
    "iso:country":"US",
    "sg:address":"572 Maddox Dr Ste 201B",
    "sg:city":"Ellijay",
    "sg:classifiers":[
        {
            "category":"Home & Garden",
            "subcategory":"Furniture",
            "type":"Retail Goods"
        }
    ],
    "sg:phone":"+1 706 635 2337",
    "sg:postcode":"30540",
    "sg:province":"GA",
    "sg:tags":[
        "store"
    ],
    "sg:website":"http://www.thebedstoreonline.com/",
    "wof:name":"Bed Store Inc",
    "wof:placetype":"venue"
},
  "geometry": {"coordinates":[-84.48509300000001,34.679996],"type":"Point"}
}