{
  "type": "Feature",
  "properties": {
    "addr:full":"5295 Stone Mountain Fwy SW Stone Mountain GA 30087",
    "addr:housenumber":"5295",
    "addr:postcode":"30087",
    "addr:street":"Fwy Sw",
    "iso:country":"US",
    "sg:address":"5295 Stone Mountain Fwy SW",
    "sg:city":"Stone Mountain",
    "sg:classifiers":[
        {
            "category":"Shopping",
            "subcategory":"Catalog Store",
            "type":"Retail Goods"
        }
    ],
    "sg:phone":"+1 678 344 8174",
    "sg:postcode":"30087",
    "sg:province":"GA",
    "sg:tags":[
        "house",
        "mail"
    ],
    "wof:name":"Postal Express Inc",
    "wof:placetype":"venue"
},
  "geometry": {"coordinates":[-84.11278299999999,33.823303],"type":"Point"}
}