{
  "type": "Feature",
  "properties": {
    "iso:country":"US",
    "sg:address":"1564 Farmer Rd NW",
    "sg:city":"Conyers",
    "sg:classifiers":[
        {
            "category":"Autos & Motor Vehicles",
            "subcategory":"Automobile Sales",
            "type":"Retail Goods"
        }
    ],
    "sg:phone":"+1 770 922 3345",
    "sg:postcode":"30012",
    "sg:province":"GA",
    "sg:tags":[
        "car",
        "dealer"
    ],
    "wof:name":"CNG Motors",
    "wof:placetype":"venue"
},
  "geometry": {"coordinates":[-84.05443099999999,33.679691],"type":"Point"}
}