{
  "type": "Feature",
  "properties": {
    "addr:full":"3855 Wieuca Ter NE Atlanta GA 30342",
    "addr:housenumber":"3855",
    "addr:postcode":"30342",
    "addr:street":"Wieuca Ter Ne",
    "iso:country":"US",
    "sg:address":"3855 Wieuca Ter NE",
    "sg:city":"Atlanta",
    "sg:classifiers":[
        {
            "category":"Professional",
            "subcategory":"Business Services",
            "type":"Services"
        }
    ],
    "sg:phone":"+1 404 467 0243",
    "sg:postcode":"30342",
    "sg:province":"GA",
    "sg:tags":[
        "personal",
        "bureau",
        "broker",
        "agent"
    ],
    "wof:name":"Rmal",
    "wof:placetype":"venue"
},
  "geometry": {"coordinates":[-84.362008,33.859569],"type":"Point"}
}