{
  "type": "Feature",
  "properties": {
    "iso:country":"US",
    "sg:address":"1140 S River Industrial Blvd SE",
    "sg:city":"Atlanta",
    "sg:classifiers":[
        {
            "category":"Retail",
            "subcategory":"Auto Repair",
            "type":"Services"
        }
    ],
    "sg:phone":"+1 404 635 0803",
    "sg:postcode":"30315",
    "sg:province":"GA",
    "sg:tags":[
        "repairing",
        "automobile"
    ],
    "wof:name":"Berry Enterprise",
    "wof:placetype":"venue"
},
  "geometry": {"coordinates":[-84.350435,33.683035],"type":"Point"}
}