{
  "type": "Feature",
  "properties": {
    "addr:full":"5851 West Ave Lavonia GA 30553",
    "addr:housenumber":"5851",
    "addr:postcode":"30553",
    "addr:street":"West Ave",
    "iso:country":"US",
    "sg:address":"5851 West Ave",
    "sg:city":"Lavonia",
    "sg:classifiers":[
        {
            "category":"Home & Garden",
            "subcategory":"Garden Supply",
            "type":"Retail Goods"
        }
    ],
    "sg:phone":"+1 706 356 8998",
    "sg:postcode":"30553",
    "sg:province":"GA",
    "sg:tags":[
        "lawn",
        "mower"
    ],
    "wof:name":"Lavonia Lawnmower Repair",
    "wof:placetype":"venue"
},
  "geometry": {"coordinates":[-83.11002499999999,34.434646],"type":"Point"}
}