{
  "type": "Feature",
  "properties": {
    "iso:country":"US",
    "sg:address":"5504 Magnolia Ave",
    "sg:city":"Savannah",
    "sg:classifiers":[
        {
            "category":"Professional",
            "subcategory":"Management & Consulting",
            "type":"Services"
        }
    ],
    "sg:phone":"+1 912 355 6065",
    "sg:postcode":"31406",
    "sg:province":"GA",
    "sg:tags":[
        "business"
    ],
    "wof:name":"Safety Director Service",
    "wof:placetype":"venue"
},
  "geometry": {"coordinates":[-81.08353099999999,32.017308],"type":"Point"}
}