{
  "type": "Feature",
  "properties": {
    "iso:country":"US",
    "sg:address":"905 S Thornton Ave",
    "sg:city":"Dalton",
    "sg:classifiers":[
        {
            "category":"Communications",
            "subcategory":"Television Station",
            "type":"Services"
        }
    ],
    "sg:phone":"+1 706 217 1174",
    "sg:postcode":"30720",
    "sg:province":"GA",
    "sg:tags":[
        "satellite",
        "cable"
    ],
    "sg:website":"http://www.besttvformyfamily.com",
    "wof:name":"A Advanced Satellite Television",
    "wof:placetype":"venue"
},
  "geometry": {"coordinates":[-84.970134,34.758887],"type":"Point"}
}