{
  "type": "Feature",
  "properties": {
    "addr:full":"160 Cherokee Ct Canton GA 30115",
    "addr:housenumber":"160",
    "addr:postcode":"30115",
    "addr:street":"Cherokee Ct",
    "iso:country":"US",
    "sg:address":"160 Cherokee Ct",
    "sg:city":"Canton",
    "sg:classifiers":[
        {
            "category":"Social Services",
            "subcategory":"Child Care",
            "type":"Services"
        }
    ],
    "sg:phone":"+1 770 360 9954",
    "sg:postcode":"30115",
    "sg:province":"GA",
    "wof:name":"Miss Connie's",
    "wof:placetype":"venue"
},
  "geometry": {"coordinates":[-84.397175,34.161068],"type":"Point"}
}