{
  "type": "Feature",
  "properties": {
    "addr:full":"718 Simon Way Lawrenceville GA 30045",
    "addr:housenumber":"718",
    "addr:postcode":"30045",
    "addr:street":"Simon Way",
    "iso:country":"US",
    "sg:address":"718 Simon Way",
    "sg:city":"Lawrenceville",
    "sg:classifiers":[
        {
            "category":"Shopping",
            "subcategory":"Clothing, Apparel, & Fashions",
            "type":"Retail Goods"
        }
    ],
    "sg:phone":"+1 678 376 3784",
    "sg:postcode":"30045",
    "sg:province":"GA",
    "wof:name":"Fashion Axxessories",
    "wof:placetype":"venue"
},
  "geometry": {"coordinates":[-83.94611999999999,33.948605],"type":"Point"}
}