{
  "type": "Feature",
  "properties": {
    "iso:country":"US",
    "sg:address":"11607 Abercorn St",
    "sg:city":"Savannah",
    "sg:classifiers":[
        {
            "category":"Autos & Motor Vehicles",
            "subcategory":"Boat Sales",
            "type":"Retail Goods"
        }
    ],
    "sg:phone":"+1 912 925 2363",
    "sg:postcode":"31419",
    "sg:province":"GA",
    "sg:tags":[
        "equipment",
        "supply"
    ],
    "sg:website":"www.boatus.com",
    "wof:name":"Boat/US Marine Ctr",
    "wof:placetype":"venue"
},
  "geometry": {"coordinates":[-81.151473,31.982419],"type":"Point"}
}