{
  "type": "Feature",
  "properties": {
    "iso:country":"US",
    "sg:address":"3260 Flat Shoals Rd",
    "sg:city":"Atlanta",
    "sg:classifiers":[
        {
            "category":"Banks & Credit Unions",
            "subcategory":"Financial Services",
            "type":"Services"
        }
    ],
    "sg:phone":"+1 404 312 1474",
    "sg:postcode":"30349",
    "sg:province":"GA",
    "sg:tags":[
        "investor"
    ],
    "wof:name":"Freedom Land Investments",
    "wof:placetype":"venue"
},
  "geometry": {"coordinates":[-84.494652,33.580383],"type":"Point"}
}