{
  "type": "Feature",
  "properties": {
    "addr:full":"4103 Gregory Manor Cir SW Smyrna GA 30082",
    "addr:housenumber":"4103",
    "addr:postcode":"30082",
    "addr:street":"Gregory Manor Cir Sw",
    "iso:country":"US",
    "sg:address":"4103 Gregory Manor Cir SW",
    "sg:city":"Smyrna",
    "sg:classifiers":[
        {
            "category":"Building & Trades",
            "subcategory":"Landscaping Services",
            "type":"Services"
        }
    ],
    "sg:phone":"+1 678 733 3151",
    "sg:postcode":"30082",
    "sg:province":"GA",
    "sg:tags":[
        "lawn",
        "maintenance"
    ],
    "wof:name":"Lawn Service Inc",
    "wof:placetype":"venue"
},
  "geometry": {"coordinates":[-84.570314,33.849326],"type":"Point"}
}