{
  "type": "Feature",
  "properties": {
    "addr:full":"2917 Professional Pkwy Augusta GA 30907",
    "addr:housenumber":"2917",
    "addr:postcode":"30907",
    "addr:street":"Professional Pkwy",
    "iso:country":"US",
    "sg:address":"2917 Professional Pkwy",
    "sg:city":"Augusta",
    "sg:classifiers":[
        {
            "category":"Insurance",
            "subcategory":"Insurance Agent",
            "type":"Services"
        }
    ],
    "sg:phone":"+1 706 855 7259",
    "sg:postcode":"30907",
    "sg:province":"GA",
    "wof:name":"Colonial Life",
    "wof:placetype":"venue"
},
  "geometry": {"coordinates":[-82.081008,33.49907],"type":"Point"}
}