{
  "type": "Feature",
  "properties": {
    "addr:full":"303 Wickersham Dr Savannah GA 31411",
    "addr:housenumber":"303",
    "addr:postcode":"31411",
    "addr:street":"Wickersham Dr",
    "iso:country":"US",
    "sg:address":"303 Wickersham Dr",
    "sg:city":"Savannah",
    "sg:classifiers":[
        {
            "category":"Professional",
            "subcategory":"Business Services",
            "type":"Services"
        }
    ],
    "sg:phone":"+1 912 598 4393",
    "sg:postcode":"31411",
    "sg:province":"GA",
    "wof:name":"Joseph J Artus",
    "wof:placetype":"venue"
},
  "geometry": {"coordinates":[-81.04355700000001,31.938755],"type":"Point"}
}