{
  "type": "Feature",
  "properties": {
    "addr:full":"630 Cobb Pkwy NE Marietta GA 30060",
    "addr:housenumber":"630",
    "addr:postcode":"30060",
    "addr:street":"Cobb Pkwy Ne",
    "iso:country":"US",
    "sg:address":"630 Cobb Pkwy NE",
    "sg:city":"Marietta",
    "sg:classifiers":[
        {
            "category":"Retail",
            "subcategory":"Veterinary Services",
            "type":"Services"
        }
    ],
    "sg:phone":"+1 770 427 3199",
    "sg:postcode":"30060",
    "sg:province":"GA",
    "sg:tags":[
        "veterinarian"
    ],
    "wof:name":"King Tracey DVM Dacvo",
    "wof:placetype":"venue"
},
  "geometry": {"coordinates":[-84.550201,33.923],"type":"Point"}
}