{
  "type": "Feature",
  "properties": {
    "iso:country":"US",
    "sg:address":"4701 Austell Rd",
    "sg:city":"Austell",
    "sg:classifiers":[
        {
            "category":"Autos & Motor Vehicles",
            "subcategory":"Auto Supplies",
            "type":"Retail Goods"
        }
    ],
    "sg:phone":"+1 770 941 7422",
    "sg:postcode":"30106",
    "sg:province":"GA",
    "sg:tags":[
        "tire"
    ],
    "sg:website":"www.butlertire.com",
    "wof:name":"Butler Tire Co Inc",
    "wof:placetype":"venue"
},
  "geometry": {"coordinates":[-84.610603,33.839901],"type":"Point"}
}