{
  "type": "Feature",
  "properties": {
    "iso:country":"US",
    "sg:address":"400 Perimeter Center Ter NE",
    "sg:city":"Atlanta",
    "sg:classifiers":[
        {
            "category":"Professional",
            "subcategory":"Management & Consulting",
            "type":"Services"
        }
    ],
    "sg:phone":"+1 770 392 4267",
    "sg:postcode":"30346",
    "sg:province":"GA",
    "sg:tags":[
        "consultant"
    ],
    "wof:name":"Blue Palm Shelter & Investment Corporation",
    "wof:placetype":"venue"
},
  "geometry": {"coordinates":[-84.33824199999999,33.92907],"type":"Point"}
}