{
  "type": "Feature",
  "properties": {
    "addr:full":"420 Birdie Rd Griffin GA 30223",
    "addr:housenumber":"420",
    "addr:postcode":"30223",
    "addr:street":"Birdie Rd",
    "iso:country":"US",
    "sg:address":"420 Birdie Rd",
    "sg:city":"Griffin",
    "sg:classifiers":[
        {
            "category":"Building & Trades",
            "subcategory":"Landscaping Services",
            "type":"Services"
        }
    ],
    "sg:phone":"+1 770 228 4775",
    "sg:postcode":"30223",
    "sg:province":"GA",
    "sg:tags":[
        "designer",
        "landscape"
    ],
    "wof:name":"D & A Enterprises Landscaping",
    "wof:placetype":"venue"
},
  "geometry": {"coordinates":[-84.3023,33.319197],"type":"Point"}
}