{
  "type": "Feature",
  "properties": {
    "addr:full":"6504 Church St Riverdale GA 30274",
    "addr:housenumber":"6504",
    "addr:postcode":"30274",
    "addr:street":"Church St",
    "iso:country":"US",
    "sg:address":"6504 Church St",
    "sg:city":"Riverdale",
    "sg:classifiers":[
        {
            "category":"Professional",
            "subcategory":"Business Services",
            "type":"Services"
        }
    ],
    "sg:phone":"+1 678 592 0254",
    "sg:postcode":"30274",
    "sg:province":"GA",
    "sg:tags":[
        "notary",
        "public"
    ],
    "wof:name":"Kingdom Business",
    "wof:placetype":"venue"
},
  "geometry": {"coordinates":[-84.415829,33.556332],"type":"Point"}
}