{
  "type": "Feature",
  "properties": {
    "addr:full":"498 Chattin Dr Canton GA 30115",
    "addr:housenumber":"498",
    "addr:postcode":"30115",
    "addr:street":"Chattin Dr",
    "iso:country":"US",
    "sg:address":"498 Chattin Dr",
    "sg:city":"Canton",
    "sg:classifiers":[
        {
            "category":"Utilities",
            "subcategory":"Telephone",
            "type":"Services"
        }
    ],
    "sg:phone":"+1 770 704 9293",
    "sg:postcode":"30115",
    "sg:province":"GA",
    "sg:tags":[
        "telecommunication"
    ],
    "wof:name":"Consolidated Telecom",
    "wof:placetype":"venue"
},
  "geometry": {"coordinates":[-84.492261,34.196818],"type":"Point"}
}