{
  "type": "Feature",
  "properties": {
    "addr:full":"37 Tarvin Rd Rock Spring GA 30739",
    "addr:housenumber":"37",
    "addr:postcode":"30739",
    "addr:street":"Tarvin Rd",
    "iso:country":"US",
    "sg:address":"37 Tarvin Rd",
    "sg:city":"Rock Spring",
    "sg:classifiers":[
        {
            "category":"Organizations",
            "subcategory":"Religious Organization",
            "type":"Services"
        }
    ],
    "sg:phone":"+1 706 764 2468",
    "sg:postcode":"30739",
    "sg:province":"GA",
    "sg:tags":[
        "church"
    ],
    "wof:name":"Center Grove Church",
    "wof:placetype":"venue"
},
  "geometry": {"coordinates":[-85.214395,34.781443],"type":"Point"}
}