{
  "type": "Feature",
  "properties": {
    "addr:full":"1 Cantey Pl NW Atlanta GA 30327",
    "addr:housenumber":"1",
    "addr:postcode":"30327",
    "addr:street":"Cantey Pl Nw",
    "iso:country":"US",
    "sg:address":"1 Cantey Pl NW",
    "sg:city":"Atlanta",
    "sg:classifiers":[
        {
            "category":"Professional",
            "type":"Services"
        }
    ],
    "sg:phone":"+1 404 367 9690",
    "sg:postcode":"30327",
    "sg:province":"GA",
    "wof:name":"Govlink Inc",
    "wof:placetype":"venue"
},
  "geometry": {"coordinates":[-84.42609299999999,33.819932],"type":"Point"}
}