{
  "type": "Feature",
  "properties": {
    "addr:full":"106 Chatillon Rd Rome GA 30161",
    "addr:housenumber":"106",
    "addr:postcode":"ga 30161",
    "addr:street":"Chatillon Rd",
    "iso:country":"US",
    "sg:address":"106 Chatillon Rd",
    "sg:city":"Rome",
    "sg:classifiers":[
        {
            "category":"Autos & Motor Vehicles",
            "subcategory":"Automobile Sales",
            "type":"Retail Goods"
        }
    ],
    "sg:phone":"+1 706 238 9860",
    "sg:postcode":"30161",
    "sg:province":"GA",
    "sg:tags":[
        "car",
        "dealer"
    ],
    "wof:name":"Tom Burns Pontiac Buick GMC",
    "wof:placetype":"venue"
},
  "geometry": {"coordinates":[-85.168059,34.281176],"type":"Point"}
}