{
  "type": "Feature",
  "properties": {
    "iso:country":"US",
    "sg:address":"1660 Northeast Expy NE",
    "sg:city":"Atlanta",
    "sg:classifiers":[
        {
            "category":"Shopping",
            "subcategory":"Stationery & Office Supplies",
            "type":"Retail Goods"
        }
    ],
    "sg:phone":"+1 404 522 1835",
    "sg:postcode":"30329",
    "sg:province":"GA",
    "sg:tags":[
        "home",
        "furniture"
    ],
    "wof:name":"Knoll Inc",
    "wof:placetype":"venue"
},
  "geometry": {"coordinates":[-84.325287,33.837168],"type":"Point"}
}