{
  "type": "Feature",
  "properties": {
    "iso:country":"US",
    "sg:address":"3272 Beechwood Dr",
    "sg:city":"Lithia Springs",
    "sg:classifiers":[
        {
            "category":"Retail",
            "subcategory":"Auto Repair",
            "type":"Services"
        }
    ],
    "sg:phone":"+1 678 283 7862",
    "sg:postcode":"30122",
    "sg:province":"GA",
    "sg:tags":[
        "tire"
    ],
    "wof:name":"Sweet Water Tire",
    "wof:placetype":"venue"
},
  "geometry": {"coordinates":[-84.64966200000001,33.776941],"type":"Point"}
}