{
  "type": "Feature",
  "properties": {
    "addr:full":"2949 US Hwy 41 Valdosta GA 31606",
    "addr:housenumber":"2949",
    "addr:postcode":"31606",
    "addr:street":"Us Hwy 41",
    "iso:country":"US",
    "sg:address":"2949 US Hwy 41",
    "sg:city":"Valdosta",
    "sg:classifiers":[
        {
            "category":"Retail",
            "subcategory":"Repair Shop",
            "type":"Services"
        }
    ],
    "sg:phone":"+1 229 247 1268",
    "sg:postcode":"31606",
    "sg:province":"GA",
    "sg:tags":[
        "scooter",
        "motorcycle",
        "motor"
    ],
    "wof:name":"Valdosta Motorcycle Acces",
    "wof:placetype":"venue"
},
  "geometry": {"coordinates":[-83.231972,30.778523],"type":"Point"}
}