{
  "type": "Feature",
  "properties": {
    "addr:full":"61 Oak St Roswell GA 30075",
    "addr:housenumber":"61",
    "addr:postcode":"30075",
    "addr:street":"Oak St",
    "iso:country":"US",
    "sg:address":"61 Oak St",
    "sg:city":"Roswell",
    "sg:classifiers":[
        {
            "category":"Utilities",
            "subcategory":"Telephone",
            "type":"Services"
        }
    ],
    "sg:phone":"+1 770 641 9000",
    "sg:postcode":"30075",
    "sg:province":"GA",
    "sg:tags":[
        "communication"
    ],
    "wof:name":"Partner Communications",
    "wof:placetype":"venue"
},
  "geometry": {"coordinates":[-84.359644,34.019777],"type":"Point"}
}