{
  "type": "Feature",
  "properties": {
    "addr:full":"685 Duluth Hwy Lawrenceville GA 30045",
    "addr:housenumber":"685",
    "addr:postcode":"30045",
    "addr:street":"Duluth Hwy",
    "iso:country":"US",
    "sg:address":"685 Duluth Hwy",
    "sg:city":"Lawrenceville",
    "sg:classifiers":[
        {
            "category":"Restaurant",
            "type":"Food & Drink"
        }
    ],
    "sg:menulink":"http://www.allmenus.com/ga/lawrenceville/196034-taco-bell/menu/",
    "sg:postcode":"30045",
    "sg:province":"GA",
    "sg:tags":[
        "mexican"
    ],
    "wof:name":"Taco Bell",
    "wof:placetype":"venue"
},
  "geometry": {"coordinates":[-84.00999,33.965963],"type":"Point"}
}