{
  "type": "Feature",
  "properties": {
    "addr:full":"499 Spring Valley Rd NW Atlanta GA 30318",
    "addr:housenumber":"499",
    "addr:postcode":"30318",
    "addr:street":"Spring Valley Rd Nw",
    "iso:country":"US",
    "sg:address":"499 Spring Valley Rd NW",
    "sg:city":"Atlanta",
    "sg:classifiers":[
        {
            "category":"Professional",
            "subcategory":"Management & Consulting",
            "type":"Services"
        }
    ],
    "sg:phone":"+1 404 352 1146",
    "sg:postcode":"30318",
    "sg:province":"GA",
    "wof:name":"Judye Greene Marketing Ltd",
    "wof:placetype":"venue"
},
  "geometry": {"coordinates":[-84.40616300000001,33.809318],"type":"Point"}
}