{
  "type": "Feature",
  "properties": {
    "addr:full":"1255 Johnson Ferry Rd Marietta GA 30068",
    "addr:housenumber":"1255",
    "addr:postcode":"30068",
    "addr:street":"Johnson Ferry Rd",
    "iso:country":"US",
    "sg:address":"1255 Johnson Ferry Rd",
    "sg:city":"Marietta",
    "sg:classifiers":[
        {
            "category":"Shopping",
            "subcategory":"Catalog Store",
            "type":"Retail Goods"
        }
    ],
    "sg:phone":"+1 770 971 8566",
    "sg:postcode":"30068",
    "sg:province":"GA",
    "sg:tags":[
        "mail",
        "cookie",
        "order",
        "gift",
        "house"
    ],
    "wof:name":"Chocolate Chips Company LLC",
    "wof:placetype":"venue"
},
  "geometry": {"coordinates":[-84.421491,33.979275],"type":"Point"}
}