{
  "type": "Feature",
  "properties": {
    "addr:full":"145 Postwood Dr Fayetteville GA 30215",
    "addr:housenumber":"145",
    "addr:postcode":"30215",
    "addr:street":"Postwood Dr",
    "iso:country":"US",
    "sg:address":"145 Postwood Dr",
    "sg:city":"Fayetteville",
    "sg:classifiers":[
        {
            "category":"Building & Trades",
            "subcategory":"Cleaning & Sanitation",
            "type":"Services"
        }
    ],
    "sg:phone":"+1 770 719 9664",
    "sg:postcode":"30215",
    "sg:province":"GA",
    "sg:tags":[
        "maintenance"
    ],
    "wof:name":"Fiber Tech Janitorial Service",
    "wof:placetype":"venue"
},
  "geometry": {"coordinates":[-84.49555599999999,33.348501],"type":"Point"}
}