{
  "type": "Feature",
  "properties": {
    "addr:full":"382 S Main St Madison GA 30650",
    "addr:housenumber":"382",
    "addr:postcode":"30650",
    "addr:street":"S Main St",
    "iso:country":"US",
    "sg:address":"382 S Main St",
    "sg:city":"Madison",
    "sg:classifiers":[
        {
            "category":"Organizations",
            "subcategory":"Religious Organization",
            "type":"Services"
        }
    ],
    "sg:phone":"+1 706 342 2813",
    "sg:postcode":"30650",
    "sg:province":"GA",
    "sg:tags":[
        "place",
        "worship",
        "church"
    ],
    "sg:website":"http://www.madisonpresbyterian.org",
    "wof:name":"Madison Presbyterian Church",
    "wof:placetype":"venue"
},
  "geometry": {"coordinates":[-83.470809,33.592893],"type":"Point"}
}