{
  "type": "Feature",
  "properties": {
    "iso:country":"US",
    "sg:address":"2681 Da Vinci Blvd",
    "sg:city":"Decatur",
    "sg:classifiers":[
        {
            "category":"Building & Trades",
            "subcategory":"Construction",
            "type":"Services"
        }
    ],
    "sg:phone":"+1 404 286 0855",
    "sg:postcode":"30034",
    "sg:province":"GA",
    "sg:tags":[
        "painter"
    ],
    "wof:name":"Curbside Painting",
    "wof:placetype":"venue"
},
  "geometry": {"coordinates":[-84.25577,33.709149],"type":"Point"}
}