{
  "type": "Feature",
  "properties": {
    "iso:country":"US",
    "sg:address":"3190 Canton Rd",
    "sg:city":"Marietta",
    "sg:classifiers":[
        {
            "category":"Food & Beverages",
            "subcategory":"Groceries & Convenience Stores",
            "type":"Retail Goods"
        }
    ],
    "sg:phone":"+1 770 590 9400",
    "sg:postcode":"30066",
    "sg:province":"GA",
    "wof:name":"Quik Go Enterprises Inc",
    "wof:placetype":"venue"
},
  "geometry": {"coordinates":[-84.52780199999999,34.028599],"type":"Point"}
}