{
  "type": "Feature",
  "properties": {
    "iso:country":"US",
    "sg:address":"4017 Augusta Rd",
    "sg:city":"Savannah",
    "sg:classifiers":[
        {
            "category":"Wholesale",
            "subcategory":"Machinery & Supplies",
            "type":"Manufacturing & Wholesale Goods"
        }
    ],
    "sg:phone":"+1 912 964 0121",
    "sg:postcode":"31408",
    "sg:province":"GA",
    "sg:tags":[
        "industrial",
        "equipment",
        "material",
        "handling"
    ],
    "wof:name":"Arbon Equipment Corporation",
    "wof:placetype":"venue"
},
  "geometry": {"coordinates":[-81.14679099999999,32.101648],"type":"Point"}
}