{
  "type": "Feature",
  "properties": {
    "iso:country":"US",
    "sg:address":"2728 Humphries St",
    "sg:city":"Atlanta",
    "sg:classifiers":[
        {
            "category":"Education",
            "subcategory":"Special Training",
            "type":"Public Place"
        }
    ],
    "sg:phone":"+1 404 763 2868",
    "sg:postcode":"30344",
    "sg:province":"GA",
    "wof:name":"Project Rise Inc",
    "wof:placetype":"venue"
},
  "geometry": {"coordinates":[-84.43080399999999,33.683303],"type":"Point"}
}