{
  "type": "Feature",
  "properties": {
    "iso:country":"US",
    "sg:address":"545 Quillian Ave SE",
    "sg:city":"Decatur",
    "sg:classifiers":[
        {
            "category":"Health Services",
            "subcategory":"Clinic",
            "type":"Services"
        }
    ],
    "sg:phone":"+1 404 377 9060",
    "sg:postcode":"30032",
    "sg:province":"GA",
    "sg:tags":[
        "holistic",
        "practitioner"
    ],
    "wof:name":"Southeastern Reiki Ctr",
    "wof:placetype":"venue"
},
  "geometry": {"coordinates":[-84.29790300000001,33.737923],"type":"Point"}
}