{
  "type": "Feature",
  "properties": {
    "iso:country":"US",
    "sg:address":"2451 Cumberland Pkwy SE",
    "sg:city":"Atlanta",
    "sg:classifiers":[
        {
            "category":"Shopping",
            "subcategory":"Computers & Home Electronics",
            "type":"Retail Goods"
        }
    ],
    "sg:phone":"+1 770 949 4808",
    "sg:postcode":"30339",
    "sg:province":"GA",
    "sg:tags":[
        "software"
    ],
    "wof:name":"Friendly Systems Inc",
    "wof:placetype":"venue"
},
  "geometry": {"coordinates":[-84.47870399999999,33.860474],"type":"Point"}
}