{
  "type": "Feature",
  "properties": {
    "iso:country":"US",
    "sg:address":"160 North St",
    "sg:city":"Canton",
    "sg:classifiers":[
        {
            "category":"Professional",
            "subcategory":"Lawyer & Legal Services",
            "type":"Services"
        }
    ],
    "sg:phone":"+1 770 720 6336",
    "sg:postcode":"30114",
    "sg:province":"GA",
    "sg:tags":[
        "divorce",
        "attorney",
        "criminal",
        "family",
        "law"
    ],
    "sg:website":"www.pglawoffice.com",
    "wof:name":"A Paul Ghanouni PC",
    "wof:placetype":"venue"
},
  "geometry": {"coordinates":[-84.49039,34.237174],"type":"Point"}
}