{
  "type": "Feature",
  "properties": {
    "addr:full":"5730 Glenridge Dr NE Atlanta GA 30328",
    "addr:housenumber":"5730",
    "addr:postcode":"30328",
    "addr:street":"Glenridge Dr Ne",
    "iso:country":"US",
    "sg:address":"5730 Glenridge Dr NE",
    "sg:city":"Atlanta",
    "sg:classifiers":[
        {
            "category":"Real Estate",
            "subcategory":"Real Estate Operator",
            "type":"Services"
        }
    ],
    "sg:phone":"+1 404 843 0101",
    "sg:postcode":"30328",
    "sg:province":"GA",
    "sg:tags":[
        "owner",
        "manager",
        "property"
    ],
    "sg:website":"www.ipgmgmt.com",
    "wof:name":"Investment Property Group",
    "wof:placetype":"venue"
},
  "geometry": {"coordinates":[-84.36199000000001,33.912237],"type":"Point"}
}