{
  "type": "Feature",
  "properties": {
    "iso:country":"US",
    "sg:address":"4932 Turnberry Ln",
    "sg:city":"Columbus",
    "sg:classifiers":[
        {
            "category":"Health Services",
            "subcategory":"Doctor",
            "type":"Services"
        }
    ],
    "sg:phone":"+1 706 565 4148",
    "sg:postcode":"31909",
    "sg:province":"GA",
    "sg:tags":[
        "physician",
        "family",
        "practice",
        "surgeons",
        "medicine"
    ],
    "wof:name":"Carlos Wise, M.D",
    "wof:placetype":"venue"
},
  "geometry": {"coordinates":[-84.923306,32.567008],"type":"Point"}
}