{
  "type": "Feature",
  "properties": {
    "addr:full":"205 Lady Helen Ct Fayetteville GA 30214",
    "addr:housenumber":"205",
    "addr:postcode":"30214",
    "addr:street":"Lady Helen Ct",
    "iso:country":"US",
    "sg:address":"205 Lady Helen Ct",
    "sg:city":"Fayetteville",
    "sg:classifiers":[
        {
            "category":"Insurance",
            "subcategory":"Insurance Agent",
            "type":"Services"
        }
    ],
    "sg:phone":"+1 770 716 6225",
    "sg:postcode":"30214",
    "sg:province":"GA",
    "sg:tags":[
        "processing"
    ],
    "wof:name":"Healthcare Business Mgmt Sltns",
    "wof:placetype":"venue"
},
  "geometry": {"coordinates":[-84.492706,33.490378],"type":"Point"}
}