{
  "type": "Feature",
  "properties": {
    "addr:full":"850 Oak Rd Lawrenceville GA 30044",
    "addr:housenumber":"850",
    "addr:postcode":"30044",
    "addr:street":"Oak Rd",
    "iso:country":"US",
    "sg:address":"850 Oak Rd",
    "sg:city":"Lawrenceville",
    "sg:classifiers":[
        {
            "category":"Retail",
            "subcategory":"Auto Repair",
            "type":"Services"
        }
    ],
    "sg:phone":"+1 770 982 0082",
    "sg:postcode":"30044",
    "sg:province":"GA",
    "wof:name":"T Jr-V Corp",
    "wof:placetype":"venue"
},
  "geometry": {"coordinates":[-84.061072,33.888545],"type":"Point"}
}