{
  "type": "Feature",
  "properties": {
    "addr:full":"820 Lawrenceville Suwanee Rd Lawrenceville GA 30043",
    "addr:housenumber":"820",
    "addr:postcode":"30043",
    "addr:street":"Lawrenceville Suwanee Rd",
    "iso:country":"US",
    "sg:address":"820 Lawrenceville Suwanee Rd",
    "sg:city":"Lawrenceville",
    "sg:classifiers":[
        {
            "category":"Restaurant",
            "type":"Food & Drink"
        }
    ],
    "sg:phone":"+1 770 962 1600",
    "sg:postcode":"30043",
    "sg:province":"GA",
    "wof:name":"Steak N Shake",
    "wof:placetype":"venue"
},
  "geometry": {"coordinates":[-84.02248899999999,33.968498],"type":"Point"}
}