{
  "type": "Feature",
  "properties": {
    "addr:full":"5119 Kanawha Bluff Stone Mountain GA 30087",
    "addr:housenumber":"5119",
    "addr:postcode":"30087",
    "addr:street":"Kanawha Bluff",
    "iso:country":"US",
    "sg:address":"5119 Kanawha Bluff",
    "sg:city":"Stone Mountain",
    "sg:classifiers":[
        {
            "category":"Professional",
            "subcategory":"Business Services",
            "type":"Services"
        }
    ],
    "sg:phone":"+1 770 938 5935",
    "sg:postcode":"30087",
    "sg:province":"GA",
    "wof:name":"Gemini Enterprises Lllp",
    "wof:placetype":"venue"
},
  "geometry": {"coordinates":[-84.18055,33.835489],"type":"Point"}
}