{
  "type": "Feature",
  "properties": {
    "iso:country":"US",
    "sg:address":"5550 Clarks Bridge Rd",
    "sg:city":"Clermont",
    "sg:classifiers":[
        {
            "category":"Professional",
            "type":"Services"
        }
    ],
    "sg:phone":"+1 770 983 0573",
    "sg:postcode":"30527",
    "sg:province":"GA",
    "wof:name":"Carters Creatives",
    "wof:placetype":"venue"
},
  "geometry": {"coordinates":[-83.779329,34.45415],"type":"Point"}
}