{
  "type": "Feature",
  "properties": {
    "iso:country":"US",
    "sg:address":"33 Basswood Cir NE",
    "sg:city":"Atlanta",
    "sg:classifiers":[
        {
            "category":"Professional",
            "subcategory":"Computer Services",
            "type":"Services"
        }
    ],
    "sg:phone":"+1 770 396 8178",
    "sg:postcode":"30328",
    "sg:province":"GA",
    "sg:tags":[
        "prepackaged",
        "software"
    ],
    "wof:name":"Indo American Software Inc",
    "wof:placetype":"venue"
},
  "geometry": {"coordinates":[-84.356099,33.924832],"type":"Point"}
}