{
  "type": "Feature",
  "properties": {
    "iso:country":"US",
    "sg:address":"2805 Hamil Chase Dr",
    "sg:city":"Buford",
    "sg:classifiers":[
        {
            "category":"Professional",
            "subcategory":"Engineering",
            "type":"Services"
        }
    ],
    "sg:phone":"+1 770 271 2709",
    "sg:postcode":"30519",
    "sg:province":"GA",
    "wof:name":"Walter J Schager Etal",
    "wof:placetype":"venue"
},
  "geometry": {"coordinates":[-83.95814900000001,34.095108],"type":"Point"}
}