{
  "type": "Feature",
  "properties": {
    "addr:full":"519 Veterans Pkwy Columbus GA 31901",
    "addr:housenumber":"519",
    "addr:postcode":"31901",
    "addr:street":"Veterans Pkwy",
    "iso:country":"US",
    "sg:address":"519 Veterans Pkwy",
    "sg:city":"Columbus",
    "sg:classifiers":[
        {
            "category":"Place Of Worship",
            "subcategory":"Church",
            "type":"Public Place"
        },
        {
            "category":"Place Of Worship",
            "type":"Public Place"
        }
    ],
    "sg:phone":"+1 706 653 1129",
    "sg:postcode":"31901",
    "sg:province":"GA",
    "sg:tags":[
        "churches-pentecostal-independent",
        "churches-pentecostal"
    ],
    "wof:name":"True Vine Praise & Worship Center",
    "wof:placetype":"venue"
},
  "geometry": {"coordinates":[-84.98774400000001,32.455633],"type":"Point"}
}