{
  "type": "Feature",
  "properties": {
    "iso:country":"US",
    "sg:address":"806 E 67th St",
    "sg:city":"Savannah",
    "sg:classifiers":[
        {
            "category":"Professional",
            "subcategory":"Accounting & Tax Preparation",
            "type":"Services"
        }
    ],
    "sg:phone":"+1 912 352 8484",
    "sg:postcode":"31405",
    "sg:province":"GA",
    "sg:tags":[
        "accountant"
    ],
    "wof:name":"Verna R Harden-Baker CPA",
    "wof:placetype":"venue"
},
  "geometry": {"coordinates":[-81.094251,32.028804],"type":"Point"}
}