{
  "type": "Feature",
  "properties": {
    "addr:full":"185 Old Camp Church Rd Carrollton GA 30117",
    "addr:housenumber":"185",
    "addr:postcode":"30117",
    "addr:street":"Old;Church Rd",
    "iso:country":"US",
    "sg:address":"185 Old Camp Church Rd",
    "sg:city":"Carrollton",
    "sg:classifiers":[
        {
            "category":"Shopping",
            "subcategory":"Discount & Variety Stores",
            "type":"Retail Goods"
        }
    ],
    "sg:phone":"+1 770 830 7519",
    "sg:postcode":"30117",
    "sg:province":"GA",
    "sg:tags":[
        "merchandise",
        "general"
    ],
    "wof:name":"Rks Supplies",
    "wof:placetype":"venue"
},
  "geometry": {"coordinates":[-85.13235400000001,33.554777],"type":"Point"}
}