{
  "type": "Feature",
  "properties": {
    "iso:country":"US",
    "sg:address":"3521 Northside Pkwy NW",
    "sg:city":"Atlanta",
    "sg:classifiers":[
        {
            "category":"Building & Trades",
            "subcategory":"Locksmith",
            "type":"Services"
        }
    ],
    "sg:phone":"+1 404 419 7097",
    "sg:postcode":"30327",
    "sg:province":"GA",
    "sg:tags":[
        "key"
    ],
    "wof:name":"Locksmith of Atlanta",
    "wof:placetype":"venue"
},
  "geometry": {"coordinates":[-84.430228,33.851168],"type":"Point"}
}