{
  "type": "Feature",
  "properties": {
    "iso:country":"US",
    "sg:address":"1153 Altamaha Rd",
    "sg:city":"Hazlehurst",
    "sg:classifiers":[
        {
            "category":"Food & Beverages",
            "subcategory":"Groceries & Convenience Stores",
            "type":"Retail Goods"
        }
    ],
    "sg:phone":"+1 912 375 2292",
    "sg:postcode":"31539",
    "sg:province":"GA",
    "wof:name":"Music's Kountry Krossroads",
    "wof:placetype":"venue"
},
  "geometry": {"coordinates":[-82.50570399999999,31.888415],"type":"Point"}
}