{
  "type": "Feature",
  "properties": {
    "iso:country":"US",
    "sg:address":"5430 McGinnis Ferry Rd",
    "sg:city":"Alpharetta",
    "sg:classifiers":[
        {
            "category":"Retail",
            "subcategory":"Laundry & Dry Cleaning",
            "type":"Services"
        }
    ],
    "sg:phone":"+1 770 619 5557",
    "sg:postcode":"30005",
    "sg:province":"GA",
    "sg:tags":[
        "drycleaning",
        "plant"
    ],
    "wof:name":"Procare Cleaners",
    "wof:placetype":"venue"
},
  "geometry": {"coordinates":[-84.199941,34.089944],"type":"Point"}
}