{
  "type": "Feature",
  "properties": {
    "iso:country":"US",
    "sg:address":"4715 Woodland Pt",
    "sg:city":"Valdosta",
    "sg:classifiers":[
        {
            "category":"Professional",
            "subcategory":"Research",
            "type":"Services"
        }
    ],
    "sg:phone":"+1 229 249 0848",
    "sg:postcode":"31602",
    "sg:province":"GA",
    "sg:tags":[
        "environmental",
        "ecological"
    ],
    "wof:name":"Evans Environmental/Geological",
    "wof:placetype":"venue"
},
  "geometry": {"coordinates":[-83.352941,30.909253],"type":"Point"}
}