{
  "type": "Feature",
  "properties": {
    "addr:full":"6690 Jones Mill Ct Ste D Norcross GA 30092",
    "addr:housenumber":"6690",
    "addr:postcode":"30092",
    "addr:street":"Jones Mill Ct Ste D",
    "iso:country":"US",
    "sg:address":"6690 Jones Mill Ct Ste D",
    "sg:city":"Norcross",
    "sg:classifiers":[
        {
            "category":"Professional",
            "subcategory":"Business Services",
            "type":"Services"
        }
    ],
    "sg:phone":"+1 770 246 0007",
    "sg:postcode":"30092",
    "sg:province":"GA",
    "sg:tags":[
        "delivery",
        "courier"
    ],
    "wof:name":"Couriersouth Inc",
    "wof:placetype":"venue"
},
  "geometry": {"coordinates":[-84.239998,33.966099],"type":"Point"}
}