{
  "type": "Feature",
  "properties": {
    "addr:full":"25 26th St NW Atlanta GA 30309",
    "addr:housenumber":"25",
    "addr:postcode":"30309",
    "addr:street":"26Th St Nw",
    "iso:country":"US",
    "sg:address":"25 26th St NW",
    "sg:city":"Atlanta",
    "sg:classifiers":[
        {
            "category":"Education",
            "subcategory":"Library",
            "type":"Public Place"
        }
    ],
    "sg:phone":"+1 404 873 0015",
    "sg:postcode":"30309",
    "sg:province":"GA",
    "wof:name":"North Branch Townhouses L",
    "wof:placetype":"venue"
},
  "geometry": {"coordinates":[-84.39713399999999,33.801874],"type":"Point"}
}