{
  "type": "Feature",
  "properties": {
    "iso:country":"US",
    "sg:address":"4915 Highway 138",
    "sg:city":"Loganville",
    "sg:classifiers":[
        {
            "category":"Restaurant",
            "type":"Food & Drink"
        }
    ],
    "sg:menulink":"http://www.allmenus.com/ga/jersey/80886-papa-johns-pizza/menu/",
    "sg:phone":"+1 770 787 7272",
    "sg:postcode":"30052",
    "sg:province":"GA",
    "sg:tags":[
        "american",
        "pizza"
    ],
    "wof:name":"Papa John's Pizza",
    "wof:placetype":"venue"
},
  "geometry": {"coordinates":[-83.86703300000001,33.740775],"type":"Point"}
}