{
  "type": "Feature",
  "properties": {
    "iso:country":"US",
    "sg:address":"6203 Abercorn St",
    "sg:city":"Savannah",
    "sg:classifiers":[
        {
            "category":"Retail",
            "subcategory":"Portrait Studio",
            "type":"Services"
        }
    ],
    "sg:phone":"+1 912 352 0088",
    "sg:postcode":"31405",
    "sg:province":"GA",
    "sg:tags":[
        "photo"
    ],
    "wof:name":"Tammy Williams Photography",
    "wof:placetype":"venue"
},
  "geometry": {"coordinates":[-81.111949,32.018017],"type":"Point"}
}