{
  "type": "Feature",
  "properties": {
    "iso:country":"US",
    "sg:address":"342 Log Cabin Rd NE",
    "sg:city":"Milledgeville",
    "sg:classifiers":[
        {
            "category":"Real Estate",
            "subcategory":"Real Estate Operator",
            "type":"Services"
        }
    ],
    "sg:phone":"+1 478 452 1424",
    "sg:postcode":"31061",
    "sg:province":"GA",
    "sg:tags":[
        "apartment"
    ],
    "wof:name":"Villamar",
    "wof:placetype":"venue"
},
  "geometry": {"coordinates":[-83.24066999999999,33.139208],"type":"Point"}
}