{
  "type": "Feature",
  "properties": {
    "addr:full":"317 Habersham Ter Cornelia GA 30531",
    "addr:housenumber":"317",
    "addr:postcode":"30531",
    "addr:street":"Habersham Ter Cornelia",
    "iso:country":"US",
    "sg:address":"317 Habersham Ter",
    "sg:city":"Cornelia",
    "sg:classifiers":[
        {
            "category":"Shopping",
            "subcategory":"Department Store",
            "type":"Retail Goods"
        }
    ],
    "sg:phone":"+1 706 778 9400",
    "sg:postcode":"30531",
    "sg:province":"GA",
    "wof:name":"Belk",
    "wof:placetype":"venue"
},
  "geometry": {"coordinates":[-83.51645499999999,34.512963],"type":"Point"}
}