{
  "type": "Feature",
  "properties": {
    "iso:country":"US",
    "sg:address":"2190 Huntington Dr",
    "sg:city":"Loganville",
    "sg:classifiers":[
        {
            "category":"Building & Trades",
            "subcategory":"Construction",
            "type":"Services"
        }
    ],
    "sg:phone":"+1 770 466 3884",
    "sg:postcode":"30052",
    "sg:province":"GA",
    "sg:tags":[
        "house"
    ],
    "wof:name":"Dean Skinner Const Inc",
    "wof:placetype":"venue"
},
  "geometry": {"coordinates":[-83.903316,33.828053],"type":"Point"}
}