{
  "type": "Feature",
  "properties": {
    "iso:country":"US",
    "sg:address":"1520 Atlanta Rd",
    "sg:city":"Gainesville",
    "sg:classifiers":[
        {
            "category":"Manufacturing",
            "subcategory":"Rubber & Plastics",
            "type":"Manufacturing & Wholesale Goods"
        },
        {
            "category":"Autos & Motor Vehicles",
            "subcategory":"Auto Supplies",
            "type":"Retail Goods"
        },
        {
            "category":"Retail",
            "subcategory":"Auto Repair",
            "type":"Services"
        }
    ],
    "sg:phone":"+1 770 536 4493",
    "sg:postcode":"30504",
    "sg:province":"GA",
    "sg:tags":[
        "recap",
        "retread",
        "tires-wholesale",
        "tire",
        "manufacturer"
    ],
    "sg:website":"http://www.coopertire.com/html/",
    "wof:name":"Kesler Tire Service Inc",
    "wof:placetype":"venue"
},
  "geometry": {"coordinates":[-83.839156,34.270936],"type":"Point"}
}