{
  "type": "Feature",
  "properties": {
    "iso:country":"US",
    "sg:address":"1093 Old Social Cir",
    "sg:city":"Social Circle",
    "sg:classifiers":[
        {
            "category":"Retail",
            "subcategory":"Auto Repair",
            "type":"Services"
        }
    ],
    "sg:phone":"+1 770 464 2022",
    "sg:postcode":"30025",
    "sg:province":"GA",
    "sg:tags":[
        "wrecker"
    ],
    "wof:name":"Circle A Towing",
    "wof:placetype":"venue"
},
  "geometry": {"coordinates":[-83.723686,33.63383],"type":"Point"}
}