{
  "type": "Feature",
  "properties": {
    "iso:country":"US",
    "sg:address":"2088 Yatesville Hwy",
    "sg:city":"Thomaston",
    "sg:classifiers":[
        {
            "category":"Organizations",
            "subcategory":"Religious Organization",
            "type":"Services"
        }
    ],
    "sg:phone":"+1 706 647 3113",
    "sg:postcode":"30286",
    "sg:province":"GA",
    "wof:name":"Faith Baptist Church",
    "wof:placetype":"venue"
},
  "geometry": {"coordinates":[-84.273278,32.904866],"type":"Point"}
}