{
  "type": "Feature",
  "properties": {
    "addr:full":"325 W Duffy St Savannah GA 31401",
    "addr:housenumber":"325",
    "addr:postcode":"31401",
    "addr:street":"W Duffy St",
    "iso:country":"US",
    "sg:address":"325 W Duffy St",
    "sg:city":"Savannah",
    "sg:classifiers":[
        {
            "category":"Food & Beverages",
            "subcategory":"Liquor & Beverages",
            "type":"Retail Goods"
        }
    ],
    "sg:phone":"+1 912 233 9425",
    "sg:postcode":"31401",
    "sg:province":"GA",
    "wof:name":"Adlers Package Shop Inc",
    "wof:placetype":"venue"
},
  "geometry": {"coordinates":[-81.101669,32.065049],"type":"Point"}
}