{
  "type": "Feature",
  "properties": {
    "addr:full":"12891 State Rte 32 Ambrose GA 31533",
    "addr:housenumber":"12891",
    "addr:postcode":"31533",
    "addr:street":"State Rte 32",
    "iso:country":"US",
    "sg:address":"12891 State Rte 32",
    "sg:city":"Ambrose",
    "sg:classifiers":[
        {
            "category":"Building & Trades",
            "subcategory":"Electrical",
            "type":"Services"
        }
    ],
    "sg:phone":"+1 912 384 0927",
    "sg:postcode":"31533",
    "sg:province":"GA",
    "sg:tags":[
        "electrical",
        "contractor"
    ],
    "wof:name":"Batten Aubrey Electric",
    "wof:placetype":"venue"
},
  "geometry": {"coordinates":[-83.014168,31.568341],"type":"Point"}
}