{
  "type": "Feature",
  "properties": {
    "addr:full":"112 Glen Arven Dr Thomasville GA 31792",
    "addr:housenumber":"112",
    "addr:postcode":"31792",
    "addr:street":"Glen Arven Dr",
    "iso:country":"US",
    "sg:address":"112 Glen Arven Dr",
    "sg:city":"Thomasville",
    "sg:classifiers":[
        {
            "category":"Professional",
            "type":"Services"
        }
    ],
    "sg:phone":"+1 229 228 6309",
    "sg:postcode":"31792",
    "sg:province":"GA",
    "wof:name":"Gerri R Simpson",
    "wof:placetype":"venue"
},
  "geometry": {"coordinates":[-83.952898,30.819321],"type":"Point"}
}