{
  "type": "Feature",
  "properties": {
    "iso:country":"US",
    "sg:address":"2091 Jeffersonville Rd",
    "sg:city":"Macon",
    "sg:classifiers":[
        {
            "category":"Personal",
            "subcategory":"Beauty Salon",
            "type":"Services"
        }
    ],
    "sg:phone":"+1 478 621 0680",
    "sg:postcode":"31217",
    "sg:province":"GA",
    "wof:name":"Exotic Microbraiding-Atlanta",
    "wof:placetype":"venue"
},
  "geometry": {"coordinates":[-83.585588,32.851517],"type":"Point"}
}