{
  "type": "Feature",
  "properties": {
    "addr:full":"6019 New Jesup Hwy Brunswick GA 31523",
    "addr:housenumber":"6019",
    "addr:postcode":"31523",
    "addr:street":"New Jesup Hwy",
    "iso:country":"US",
    "sg:address":"6019 New Jesup Hwy",
    "sg:city":"Brunswick",
    "sg:classifiers":[
        {
            "category":"Manufacturing",
            "subcategory":"Tools & Machinery",
            "type":"Manufacturing & Wholesale Goods"
        }
    ],
    "sg:phone":"+1 912 265 5951",
    "sg:postcode":"31523",
    "sg:province":"GA",
    "sg:tags":[
        "repair",
        "c",
        "industrial",
        "mfg",
        "trade",
        "special",
        "welding"
    ],
    "wof:name":"Barlow Fabrication",
    "wof:placetype":"venue"
},
  "geometry": {"coordinates":[-81.540646,31.239396],"type":"Point"}
}