{
  "type": "Feature",
  "properties": {
    "addr:full":"2904 Stonecreek Rd Smyrna GA 30080",
    "addr:housenumber":"2904",
    "addr:postcode":"30080",
    "addr:street":"Stonecreek Rd",
    "iso:country":"US",
    "sg:address":"2904 Stonecreek Rd",
    "sg:city":"Smyrna",
    "sg:classifiers":[
        {
            "category":"Building & Trades",
            "subcategory":"Construction",
            "type":"Services"
        }
    ],
    "sg:phone":"+1 770 333 9076",
    "sg:postcode":"30080",
    "sg:province":"GA",
    "sg:tags":[
        "dry wall",
        "contractor"
    ],
    "wof:name":"Mejia Dry Wall Inc",
    "wof:placetype":"venue"
},
  "geometry": {"coordinates":[-84.53279000000001,33.882621],"type":"Point"}
}