{
  "type": "Feature",
  "properties": {
    "addr:full":"621 N Westover Blvd Albany GA 31707",
    "addr:housenumber":"621",
    "addr:postcode":"31707",
    "addr:street":"N Westover Blvd",
    "iso:country":"US",
    "sg:address":"621 N Westover Blvd",
    "sg:city":"Albany",
    "sg:classifiers":[
        {
            "category":"Wholesale",
            "subcategory":"Meat",
            "type":"Manufacturing & Wholesale Goods"
        },
        {
            "category":"Restaurant",
            "type":"Food & Drink"
        }
    ],
    "sg:phone":"+1 229 436 4267",
    "sg:postcode":"31707",
    "sg:province":"GA",
    "sg:tags":[
        "meat-wholesale"
    ],
    "sg:website":"http://www.heavenlyham.com",
    "wof:name":"Heavenly Hams",
    "wof:placetype":"venue"
},
  "geometry": {"coordinates":[-84.223123,31.611116],"type":"Point"}
}