{
  "type": "Feature",
  "properties": {
    "iso:country":"US",
    "sg:address":"2735 New College Way",
    "sg:city":"Cumming",
    "sg:classifiers":[
        {
            "category":"Real Estate",
            "subcategory":"Real Estate Operator",
            "type":"Services"
        }
    ],
    "sg:phone":"+1 770 887 4746",
    "sg:postcode":"30041",
    "sg:province":"GA",
    "sg:tags":[
        "building",
        "nonresidential"
    ],
    "wof:name":"Razorback Properties",
    "wof:placetype":"venue"
},
  "geometry": {"coordinates":[-84.095635,34.163655],"type":"Point"}
}