{
  "type": "Feature",
  "properties": {
    "iso:country":"US",
    "sg:address":"2020 Northside Pkwy NW",
    "sg:city":"Atlanta",
    "sg:classifiers":[
        {
            "category":"Building & Trades",
            "subcategory":"Construction",
            "type":"Services"
        }
    ],
    "sg:phone":"+1 770 736 5678",
    "sg:postcode":"30318",
    "sg:province":"GA",
    "sg:tags":[
        "hanging",
        "contractor"
    ],
    "wof:name":"Ortiz Decorating Inc",
    "wof:placetype":"venue"
},
  "geometry": {"coordinates":[-84.407791,33.808318],"type":"Point"}
}