{
  "type": "Feature",
  "properties": {
    "iso:country":"US",
    "sg:address":"934 E Church St",
    "sg:city":"Jasper",
    "sg:classifiers":[
        {
            "category":"Home & Garden",
            "subcategory":"Carpets & Floor Coverings",
            "type":"Retail Goods"
        }
    ],
    "sg:phone":"+1 706 299 5800",
    "sg:postcode":"30143",
    "sg:province":"GA",
    "sg:tags":[
        "material",
        "rug",
        "flooring",
        "contractor"
    ],
    "wof:name":"Jasper Carpets",
    "wof:placetype":"venue"
},
  "geometry": {"coordinates":[-84.41669400000001,34.463372],"type":"Point"}
}