{
  "type": "Feature",
  "properties": {
    "iso:country":"US",
    "sg:address":"669 Cook St",
    "sg:city":"Royston",
    "sg:classifiers":[
        {
            "category":"Personal",
            "subcategory":"Beauty Salon",
            "type":"Services"
        }
    ],
    "sg:phone":"+1 706 245 6562",
    "sg:postcode":"30662",
    "sg:province":"GA",
    "wof:name":"Patricia's Beauty Salon",
    "wof:placetype":"venue"
},
  "geometry": {"coordinates":[-83.122148,34.284291],"type":"Point"}
}