{
  "type": "Feature",
  "properties": {
    "addr:full":"1354 Moreland Ave SE Atlanta GA 30316",
    "addr:housenumber":"1354",
    "addr:postcode":"30316",
    "addr:street":"Moreland Ave Se",
    "iso:country":"US",
    "sg:address":"1354 Moreland Ave SE",
    "sg:city":"Atlanta",
    "sg:classifiers":[
        {
            "category":"Personal",
            "subcategory":"Nail Salon",
            "type":"Services"
        }
    ],
    "sg:phone":"+1 404 627 6774",
    "sg:postcode":"30316",
    "sg:province":"GA",
    "wof:name":"Nail Hot",
    "wof:placetype":"venue"
},
  "geometry": {"coordinates":[-84.349602,33.7131],"type":"Point"}
}