{
  "type": "Feature",
  "properties": {
    "addr:full":"119 Huffaker Rd NW Rome GA 30165",
    "addr:housenumber":"119",
    "addr:postcode":"ga 30165",
    "addr:street":"Huffaker Rd Nw",
    "iso:country":"US",
    "sg:address":"119 Huffaker Rd NW",
    "sg:city":"Rome",
    "sg:classifiers":[
        {
            "category":"Freight",
            "type":"Transportation"
        }
    ],
    "sg:phone":"+1 706 235 4998",
    "sg:postcode":"30165",
    "sg:province":"GA",
    "sg:tags":[
        "refrigeration"
    ],
    "wof:name":"Huffaker Self Storage",
    "wof:placetype":"venue"
},
  "geometry": {"coordinates":[-85.240286,34.278068],"type":"Point"}
}