{
  "type": "Feature",
  "properties": {
    "iso:country":"US",
    "sg:address":"241 Peachtree St",
    "sg:city":"Atlanta",
    "sg:classifiers":[
        {
            "category":"Organizations",
            "subcategory":"Religious Organization",
            "type":"Services"
        }
    ],
    "sg:phone":"+1 404 965 3979",
    "sg:postcode":"30303",
    "sg:province":"GA",
    "wof:name":"New Birth Inner City Ministries",
    "wof:placetype":"venue"
},
  "geometry": {"coordinates":[-84.39547899999999,33.74784],"type":"Point"}
}