{
  "type": "Feature",
  "properties": {
    "iso:country":"US",
    "sg:address":"1454 Willingham Dr",
    "sg:city":"East Point",
    "sg:classifiers":[
        {
            "category":"Retail",
            "subcategory":"Auto Repair",
            "type":"Services"
        }
    ],
    "sg:phone":"+1 404 767 9922",
    "sg:postcode":"30344",
    "sg:province":"GA",
    "sg:tags":[
        "truck"
    ],
    "wof:name":"S & S Fleet Svc",
    "wof:placetype":"venue"
},
  "geometry": {"coordinates":[-84.434775,33.667407],"type":"Point"}
}