{
  "type": "Feature",
  "properties": {
    "iso:country":"US",
    "sg:address":"8337 State Rte 53",
    "sg:city":"Braselton",
    "sg:classifiers":[
        {
            "category":"Real Estate",
            "subcategory":"Real Estate Operator",
            "type":"Services"
        }
    ],
    "sg:phone":"+1 706 654 5860",
    "sg:postcode":"30517",
    "sg:province":"GA",
    "sg:tags":[
        "mobile",
        "home",
        "site"
    ],
    "wof:name":"Village Mobile Home Community",
    "wof:placetype":"venue"
},
  "geometry": {"coordinates":[-83.795422,34.141959],"type":"Point"}
}