{
  "type": "Feature",
  "properties": {
    "iso:country":"US",
    "sg:address":"1005 Oakley Industrial Blvd",
    "sg:city":"Fairburn",
    "sg:classifiers":[
        {
            "category":"Travel",
            "subcategory":"Hotels & Motels",
            "type":"Entertainment"
        }
    ],
    "sg:phone":"+1 678 782 4700",
    "sg:postcode":"30213",
    "sg:province":"GA",
    "sg:website":"www.sleepinn.com",
    "wof:name":"Sleep Inn Fairburn",
    "wof:placetype":"venue"
},
  "geometry": {"coordinates":[-84.579516,33.542505],"type":"Point"}
}