{
  "type": "Feature",
  "properties": {
    "addr:full":"36 E Spring St Jasper GA 30143",
    "addr:housenumber":"36",
    "addr:postcode":"30143",
    "addr:street":"E Spring St",
    "iso:country":"US",
    "sg:address":"36 E Spring St",
    "sg:city":"Jasper",
    "sg:classifiers":[
        {
            "category":"Health Services",
            "subcategory":"Doctor",
            "type":"Services"
        }
    ],
    "sg:phone":"+1 706 253 6076",
    "sg:postcode":"30143",
    "sg:province":"GA",
    "sg:tags":[
        "physician",
        "medical",
        "surgeon"
    ],
    "wof:name":"Jasper Family Practice LLC",
    "wof:placetype":"venue"
},
  "geometry": {"coordinates":[-84.428404,34.467676],"type":"Point"}
}