{
  "type": "Feature",
  "properties": {
    "iso:country":"US",
    "sg:address":"145 Shoal Creek Rd",
    "sg:city":"Fayetteville",
    "sg:classifiers":[
        {
            "category":"Building & Trades",
            "subcategory":"Construction",
            "type":"Services"
        }
    ],
    "sg:phone":"+1 770 461 3936",
    "sg:postcode":"30215",
    "sg:province":"GA",
    "sg:tags":[
        "contractor"
    ],
    "wof:name":"Absolute Tile & Marble",
    "wof:placetype":"venue"
},
  "geometry": {"coordinates":[-84.49858999999999,33.359754],"type":"Point"}
}