{
  "type": "Feature",
  "properties": {
    "iso:country":"US",
    "sg:address":"5124 Highway 92 Ste 100",
    "sg:city":"Douglasville",
    "sg:classifiers":[
        {
            "category":"Professional",
            "subcategory":"Business Services",
            "type":"Services"
        },
        {
            "category":"Government",
            "subcategory":"Post Office",
            "type":"Public Place"
        }
    ],
    "sg:phone":"+1 678 732 5388",
    "sg:postcode":"30135",
    "sg:province":"GA",
    "sg:tags":[
        "delivery",
        "messenger",
        "courier"
    ],
    "wof:name":"Transportation",
    "wof:placetype":"venue"
},
  "geometry": {"coordinates":[-84.67176000000001,33.665751],"type":"Point"}
}