{
  "type": "Feature",
  "properties": {
    "addr:full":"100 Dodd St SE Marietta GA 30060",
    "addr:housenumber":"100",
    "addr:postcode":"30060",
    "addr:street":"Dodd St Se",
    "iso:country":"US",
    "sg:address":"100 Dodd St SE",
    "sg:city":"Marietta",
    "sg:classifiers":[
        {
            "category":"Retail",
            "subcategory":"Auto Rental",
            "type":"Services"
        }
    ],
    "sg:phone":"+1 770 424 9584",
    "sg:postcode":"30060",
    "sg:province":"GA",
    "sg:tags":[
        "renting",
        "truck",
        "leasing"
    ],
    "wof:name":"U-Haul Co",
    "wof:placetype":"venue"
},
  "geometry": {"coordinates":[-84.52381,33.950915],"type":"Point"}
}