{
  "type": "Feature",
  "properties": {
    "addr:full":"250 S Macarthur Dr Camilla GA 31730",
    "addr:housenumber":"250",
    "addr:postcode":"31730",
    "addr:street":"S Macarthur Dr",
    "iso:country":"US",
    "sg:address":"250 S Macarthur Dr",
    "sg:city":"Camilla",
    "sg:classifiers":[
        {
            "category":"Real Estate",
            "subcategory":"Real Estate Agent",
            "type":"Services"
        }
    ],
    "sg:phone":"+1 229 336 1111",
    "sg:postcode":"31730",
    "sg:province":"GA",
    "wof:name":"Panorama Properties",
    "wof:placetype":"venue"
},
  "geometry": {"coordinates":[-84.19321100000001,31.224176],"type":"Point"}
}