{
  "type": "Feature",
  "properties": {
    "addr:full":"1701 Barrett Lakes Blvd NW Kennesaw GA 30144",
    "addr:housenumber":"1701",
    "addr:postcode":"30144",
    "addr:street":"Barrett Lakes Blvd Nw",
    "iso:country":"US",
    "sg:address":"1701 Barrett Lakes Blvd NW",
    "sg:city":"Kennesaw",
    "sg:classifiers":[
        {
            "category":"Insurance",
            "subcategory":"Insurance Agent",
            "type":"Services"
        }
    ],
    "sg:phone":"+1 678 581 9371",
    "sg:postcode":"30144",
    "sg:province":"GA",
    "wof:name":"Colvin Kazinec & Assoc",
    "wof:placetype":"venue"
},
  "geometry": {"coordinates":[-84.57748599999999,34.011534],"type":"Point"}
}