{
  "type": "Feature",
  "properties": {
    "iso:country":"US",
    "sg:address":"3416 Keswick Dr",
    "sg:city":"Atlanta",
    "sg:classifiers":[
        {
            "category":"Sports & Exercise",
            "subcategory":"Gym",
            "type":"Entertainment"
        }
    ],
    "sg:phone":"+1 770 936 9566",
    "sg:postcode":"30341",
    "sg:province":"GA",
    "sg:tags":[
        "fitness",
        "physical",
        "facility"
    ],
    "wof:name":"Millennium Solutions",
    "wof:placetype":"venue"
},
  "geometry": {"coordinates":[-84.315752,33.890746],"type":"Point"}
}