{
  "type": "Feature",
  "properties": {
    "addr:full":"445 Pat Mell Rd SE Smyrna GA 30060",
    "addr:housenumber":"445",
    "addr:postcode":"30060",
    "addr:street":"Pat Mell Rd Se",
    "iso:country":"US",
    "sg:address":"445 Pat Mell Rd SE",
    "sg:city":"Smyrna",
    "sg:classifiers":[
        {
            "category":"Food & Beverages",
            "subcategory":"Groceries & Convenience Stores",
            "type":"Retail Goods"
        }
    ],
    "sg:phone":"+1 770 433 8111",
    "sg:postcode":"30060",
    "sg:province":"GA",
    "wof:name":"Save & Go",
    "wof:placetype":"venue"
},
  "geometry": {"coordinates":[-84.54046,33.90207],"type":"Point"}
}