{
  "type": "Feature",
  "properties": {
    "addr:full":"3239 Rangers Gate Marietta GA 30062",
    "addr:housenumber":"3239",
    "addr:postcode":"30062",
    "addr:street":"Rangers Gate",
    "iso:country":"US",
    "sg:address":"3239 Rangers Gate",
    "sg:city":"Marietta",
    "sg:classifiers":[
        {
            "category":"Professional",
            "subcategory":"Business Services",
            "type":"Services"
        }
    ],
    "sg:phone":"+1 770 851 2214",
    "sg:postcode":"30062",
    "sg:province":"GA",
    "wof:name":"King Creations",
    "wof:placetype":"venue"
},
  "geometry": {"coordinates":[-84.459633,34.027735],"type":"Point"}
}