{
  "type": "Feature",
  "properties": {
    "addr:full":"Mall of Georgia 3333 Buford Dr Buford GA 30519",
    "addr:housenumber":"3333",
    "addr:postcode":"30519",
    "addr:street":"Buford Dr",
    "iso:country":"US",
    "sg:address":"Mall of Georgia 3333 Buford Dr",
    "sg:city":"Buford",
    "sg:classifiers":[
        {
            "category":"Utilities",
            "type":"Services"
        }
    ],
    "sg:phone":"+1 678 266 9971",
    "sg:postcode":"30519",
    "sg:province":"GA",
    "sg:tags":[
        "provider",
        "internet"
    ],
    "sg:website":"www.clear.com/landing/state/GA",
    "wof:name":"Clear Internet",
    "wof:placetype":"venue"
},
  "geometry": {"coordinates":[-83.984145,34.064225],"type":"Point"}
}