{
  "type": "Feature",
  "properties": {
    "iso:country":"US",
    "sg:address":"214 Nacoochee Dr",
    "sg:city":"Woodstock",
    "sg:classifiers":[
        {
            "category":"Professional",
            "subcategory":"Engineering",
            "type":"Services"
        }
    ],
    "sg:phone":"+1 770 924 3902",
    "sg:postcode":"30188",
    "sg:province":"GA",
    "sg:tags":[
        "engineer"
    ],
    "wof:name":"5m Industries Inc",
    "wof:placetype":"venue"
},
  "geometry": {"coordinates":[-84.416848,34.114492],"type":"Point"}
}