{
  "type": "Feature",
  "properties": {
    "addr:full":"11832 E Cherokee Dr Ball Ground GA 30107",
    "addr:housenumber":"11832",
    "addr:postcode":"30107",
    "addr:street":"E Cherokee Dr",
    "iso:country":"US",
    "sg:address":"11832 E Cherokee Dr",
    "sg:city":"Ball Ground",
    "sg:classifiers":[
        {
            "category":"Travel",
            "subcategory":"Hotels & Motels",
            "type":"Entertainment"
        },
        {
            "category":"Organizations",
            "subcategory":"Community Association",
            "type":"Services"
        }
    ],
    "sg:phone":"+1 770 479 0155",
    "sg:postcode":"30107",
    "sg:province":"GA",
    "sg:tags":[
        "operation",
        "fraternal"
    ],
    "wof:name":"Cherokee Wilderness Lodge",
    "wof:placetype":"venue"
},
  "geometry": {"coordinates":[-84.365168,34.267308],"type":"Point"}
}