{
  "type": "Feature",
  "properties": {
    "addr:full":"9360 The Landing Dr Douglasville GA 30135",
    "addr:housenumber":"9360",
    "addr:postcode":"30135",
    "addr:street":"The Landing Dr",
    "iso:country":"US",
    "sg:address":"9360 The Landing Dr",
    "sg:city":"Douglasville",
    "sg:classifiers":[
        {
            "category":"Banks & Credit Unions",
            "subcategory":"Bank",
            "type":"Services"
        },
        {
            "category":"Banks & Credit Unions",
            "subcategory":"Financial Services",
            "type":"Services"
        }
    ],
    "sg:phone":"+1 770 544 0263",
    "sg:postcode":"30135",
    "sg:province":"GA",
    "sg:tags":[
        "loan",
        "stock",
        "broker",
        "mortgage",
        "bond"
    ],
    "sg:website":"http://www.thecsbank.com",
    "wof:name":"Community and Southern Bank",
    "wof:placetype":"venue"
},
  "geometry": {"coordinates":[-84.73823299999999,33.728104],"type":"Point"}
}