{
  "type": "Feature",
  "properties": {
    "iso:country":"US",
    "sg:address":"2708 Michael Rd",
    "sg:city":"Albany",
    "sg:classifiers":[
        {
            "category":"Real Estate",
            "subcategory":"Real Estate Operator",
            "type":"Services"
        }
    ],
    "sg:phone":"+1 229 883 1789",
    "sg:postcode":"31721",
    "sg:province":"GA",
    "sg:tags":[
        "property",
        "lessor"
    ],
    "wof:name":"Grave Springs Development",
    "wof:placetype":"venue"
},
  "geometry": {"coordinates":[-84.247371,31.619217],"type":"Point"}
}