{
  "type": "Feature",
  "properties": {
    "iso:country":"US",
    "sg:address":"406 Johnson Dr",
    "sg:city":"Braselton",
    "sg:classifiers":[
        {
            "category":"Professional",
            "subcategory":"Business Services",
            "type":"Services"
        }
    ],
    "sg:phone":"+1 706 658 2970",
    "sg:postcode":"30517",
    "sg:province":"GA",
    "wof:name":"A & S Business Svc Inc",
    "wof:placetype":"venue"
},
  "geometry": {"coordinates":[-83.763014,34.129459],"type":"Point"}
}