{
  "type": "Feature",
  "properties": {
    "addr:full":"1871 Chamblee Tucker Rd Chamblee GA 30341",
    "addr:housenumber":"1871",
    "addr:postcode":"30341",
    "addr:street":"Chamblee Tucker Rd",
    "iso:country":"US",
    "sg:address":"1871 Chamblee Tucker Rd",
    "sg:city":"Chamblee",
    "sg:classifiers":[
        {
            "category":"Shopping",
            "subcategory":"Department Store",
            "type":"Retail Goods"
        },
        {
            "category":"Shopping",
            "subcategory":"Mobile Phones",
            "type":"Retail Goods"
        },
        {
            "category":"Food & Beverages",
            "subcategory":"Groceries & Convenience Stores",
            "type":"Retail Goods"
        }
    ],
    "sg:phone":"+1 770 455 0422",
    "sg:postcode":"30341",
    "sg:province":"GA",
    "sg:website":"www.walmart.com",
    "wof:name":"Walmart",
    "wof:placetype":"venue"
},
  "geometry": {"coordinates":[-84.311077,33.888702],"type":"Point"}
}