{
  "type": "Feature",
  "properties": {
    "iso:country":"US",
    "sg:address":"106 Lucy Cir",
    "sg:city":"Warner Robins",
    "sg:classifiers":[
        {
            "category":"Freight",
            "type":"Transportation"
        }
    ],
    "sg:phone":"+1 478 953 7280",
    "sg:postcode":"31093",
    "sg:province":"GA",
    "sg:tags":[
        "tour",
        "trucking"
    ],
    "wof:name":"G & L Enterprises Inc",
    "wof:placetype":"venue"
},
  "geometry": {"coordinates":[-83.62088300000001,32.656309],"type":"Point"}
}