{
  "type": "Feature",
  "properties": {
    "addr:full":"316 E Tyler St Dalton GA 30721",
    "addr:housenumber":"316",
    "addr:postcode":"30721",
    "addr:street":"E Tyler St",
    "iso:country":"US",
    "sg:address":"316 E Tyler St",
    "sg:city":"Dalton",
    "sg:classifiers":[
        {
            "category":"Building & Trades",
            "subcategory":"Landscaping Services",
            "type":"Services"
        }
    ],
    "sg:phone":"+1 706 529 8866",
    "sg:postcode":"30721",
    "sg:province":"GA",
    "sg:tags":[
        "lawn",
        "maintenance",
        "grounds"
    ],
    "wof:name":"Grass Masters Inc",
    "wof:placetype":"venue"
},
  "geometry": {"coordinates":[-84.964518,34.779685],"type":"Point"}
}