{
  "type": "Feature",
  "properties": {
    "addr:full":"102 Trojan Dr Carrollton GA 30117",
    "addr:housenumber":"102",
    "addr:postcode":"30117",
    "addr:street":"Trojan Dr",
    "iso:country":"US",
    "sg:address":"102 Trojan Dr",
    "sg:city":"Carrollton",
    "sg:classifiers":[
        {
            "category":"Social Services",
            "subcategory":"Child Care",
            "type":"Services"
        }
    ],
    "sg:phone":"+1 770 838 9095",
    "sg:postcode":"30117",
    "sg:province":"GA",
    "sg:tags":[
        "day"
    ],
    "wof:name":"Indulge Day Spa",
    "wof:placetype":"venue"
},
  "geometry": {"coordinates":[-85.07805399999999,33.569024],"type":"Point"}
}