{
  "type": "Feature",
  "properties": {
    "iso:country":"US",
    "sg:address":"2751 Buford Hwy NE",
    "sg:city":"Atlanta",
    "sg:classifiers":[
        {
            "category":"Community Center",
            "subcategory":"Senior",
            "type":"Public Place"
        },
        {
            "category":"Social Services",
            "subcategory":"Child Care",
            "type":"Services"
        },
        {
            "category":"Health Services",
            "subcategory":"Health Practitioner",
            "type":"Services"
        },
        {
            "category":"Social Services",
            "subcategory":"Adult Care",
            "type":"Services"
        },
        {
            "category":"Health Services",
            "subcategory":"Nursing And Care Facility",
            "type":"Services"
        }
    ],
    "sg:phone":"+1 404 633 1935",
    "sg:postcode":"30324",
    "sg:province":"GA",
    "sg:tags":[
        "living",
        "sitting",
        "assisted",
        "elder",
        "citizen",
        "home",
        "nurse"
    ],
    "sg:website":"http://www.trimarkhealth.com",
    "wof:name":"Trimark Health Services",
    "wof:placetype":"venue"
},
  "geometry": {"coordinates":[-84.34545199999999,33.829024],"type":"Point"}
}