{
  "type": "Feature",
  "properties": {
    "iso:country":"US",
    "sg:address":"2145 Roswell Rd",
    "sg:city":"Marietta",
    "sg:classifiers":[
        {
            "category":"Professional",
            "type":"Services"
        }
    ],
    "sg:phone":"+1 770 977 9388",
    "sg:postcode":"30062",
    "sg:province":"GA",
    "sg:tags":[
        "caterer"
    ],
    "wof:name":"Atlanta Corporate Caterers the Silver Platter",
    "wof:placetype":"venue"
},
  "geometry": {"coordinates":[-84.490196,33.9678],"type":"Point"}
}