{
  "type": "Feature",
  "properties": {
    "addr:full":"2353 Cheshire Bridge Road N Atlanta GA 30324",
    "addr:housenumber":"2353",
    "addr:postcode":"30324",
    "addr:street":"Cheshire Bridge Road N",
    "iso:country":"US",
    "sg:address":"2353 Cheshire Bridge Road N",
    "sg:city":"Atlanta",
    "sg:classifiers":[
        {
            "category":"Autos & Motor Vehicles",
            "subcategory":"Fuel & Gas Station",
            "type":"Retail Goods"
        }
    ],
    "sg:phone":"+1 404 320 6260",
    "sg:postcode":"30324",
    "sg:province":"GA",
    "wof:name":"A and A Food Mart",
    "wof:placetype":"venue"
},
  "geometry": {"coordinates":[-84.35154799999999,33.819027],"type":"Point"}
}