{
  "type": "Feature",
  "properties": {
    "addr:full":"1717 Laney Walker Blvd Augusta GA 30904",
    "addr:housenumber":"1717",
    "addr:postcode":"30904",
    "addr:street":"Laney Walker Blvd",
    "iso:country":"US",
    "sg:address":"1717 Laney Walker Blvd",
    "sg:city":"Augusta",
    "sg:classifiers":[
        {
            "category":"Restaurant",
            "type":"Food & Drink"
        }
    ],
    "sg:phone":"+1 706 733 1740",
    "sg:postcode":"30904",
    "sg:province":"GA",
    "wof:name":"Fatsville Chow Restaurant",
    "wof:placetype":"venue"
},
  "geometry": {"coordinates":[-81.996273,33.471645],"type":"Point"}
}