{
  "type": "Feature",
  "properties": {
    "iso:country":"US",
    "sg:address":"6949 Bryce Rd",
    "sg:city":"Riverdale",
    "sg:classifiers":[
        {
            "category":"Retail",
            "subcategory":"Repair Shop",
            "type":"Services"
        }
    ],
    "sg:phone":"+1 770 996 7840",
    "sg:postcode":"30296",
    "sg:province":"GA",
    "sg:tags":[
        "electrical"
    ],
    "wof:name":"Orphes Appliance Repair",
    "wof:placetype":"venue"
},
  "geometry": {"coordinates":[-84.446253,33.565413],"type":"Point"}
}