{
  "type": "Feature",
  "properties": {
    "addr:full":"2807 Frontier Trl Atlanta GA 30341",
    "addr:housenumber":"2807",
    "addr:postcode":"30341",
    "addr:street":"Frontier Trl",
    "iso:country":"US",
    "sg:address":"2807 Frontier Trl",
    "sg:city":"Atlanta",
    "sg:classifiers":[
        {
            "category":"Professional",
            "type":"Services"
        }
    ],
    "sg:phone":"+1 770 220 0243",
    "sg:postcode":"30341",
    "sg:province":"GA",
    "wof:name":"Holdem High Inc",
    "wof:placetype":"venue"
},
  "geometry": {"coordinates":[-84.29352299999999,33.87035],"type":"Point"}
}