{
  "type": "Feature",
  "properties": {
    "addr:full":"4400 Ashford Dunwoody Rd Space #3035 Atlanta GA 30346",
    "addr:housenumber":"4400;# 3035",
    "addr:postcode":"30346",
    "addr:street":"Ashford Dunwoody Rd",
    "iso:country":"US",
    "sg:address":"4400 Ashford Dunwoody Rd Space #3035",
    "sg:city":"Atlanta",
    "sg:classifiers":[
        {
            "category":"Restaurant",
            "type":"Food & Drink"
        }
    ],
    "sg:phone":"+1 770 804 3313",
    "sg:postcode":"30346",
    "sg:province":"GA",
    "sg:tags":[
        "italian"
    ],
    "sg:website":"www.maggianos.com",
    "wof:name":"Maggiano's Little Italy",
    "wof:placetype":"venue"
},
  "geometry": {"coordinates":[-84.33811300000001,33.923769],"type":"Point"}
}