{
  "type": "Feature",
  "properties": {
    "addr:full":"4947 Winters Chapel Rd Atlanta GA 30360",
    "addr:housenumber":"4947",
    "addr:postcode":"30360",
    "addr:street":"Winters Chapel Rd",
    "iso:country":"US",
    "sg:address":"4947 Winters Chapel Rd",
    "sg:city":"Atlanta",
    "sg:classifiers":[
        {
            "category":"Shopping",
            "type":"Retail Goods"
        }
    ],
    "sg:phone":"+1 770 393 8530",
    "sg:postcode":"30360",
    "sg:province":"GA",
    "sg:tags":[
        "glass",
        "sculpture"
    ],
    "wof:name":"Glass Guild",
    "wof:placetype":"venue"
},
  "geometry": {"coordinates":[-84.271638,33.941243],"type":"Point"}
}