{
  "type": "Feature",
  "properties": {
    "addr:full":"9 Glenn Ct Decatur GA 30030",
    "addr:housenumber":"9",
    "addr:postcode":"30030",
    "addr:street":"Glenn Ct",
    "iso:country":"US",
    "sg:address":"9 Glenn Ct",
    "sg:city":"Decatur",
    "sg:classifiers":[
        {
            "category":"Professional",
            "subcategory":"Business Services",
            "type":"Services"
        }
    ],
    "sg:phone":"+1 404 378 6123",
    "sg:postcode":"30030",
    "sg:province":"GA",
    "wof:name":"Glenn Court Partners LLC",
    "wof:placetype":"venue"
},
  "geometry": {"coordinates":[-84.285517,33.78621],"type":"Point"}
}