{
  "type": "Feature",
  "properties": {
    "addr:full":"7048 State Rte 85 Riverdale GA 30274",
    "addr:housenumber":"7048",
    "addr:postcode":"30274",
    "addr:street":"State Rte 85",
    "iso:country":"US",
    "sg:address":"7048 State Rte 85",
    "sg:city":"Riverdale",
    "sg:classifiers":[
        {
            "category":"Shopping",
            "subcategory":"Computers & Home Electronics",
            "type":"Retail Goods"
        }
    ],
    "sg:phone":"+1 770 907 3834",
    "sg:postcode":"30274",
    "sg:province":"GA",
    "sg:tags":[
        "game",
        "video"
    ],
    "wof:name":"Game Stop Corp",
    "wof:placetype":"venue"
},
  "geometry": {"coordinates":[-84.411779,33.578945],"type":"Point"}
}