{
  "type": "Feature",
  "properties": {
    "iso:country":"US",
    "sg:address":"4610 Peachtree Place Pkwy",
    "sg:city":"Atlanta",
    "sg:classifiers":[
        {
            "category":"Building & Trades",
            "subcategory":"Cleaning & Sanitation",
            "type":"Services"
        }
    ],
    "sg:phone":"+1 678 760 2961",
    "sg:postcode":"30360",
    "sg:province":"GA",
    "sg:tags":[
        "maintenance"
    ],
    "wof:name":"Royalty Cleaning Services",
    "wof:placetype":"venue"
},
  "geometry": {"coordinates":[-84.268629,33.933328],"type":"Point"}
}