{
  "type": "Feature",
  "properties": {
    "addr:full":"3550 Financial Center Way Buford GA 30519",
    "addr:housenumber":"3550",
    "addr:postcode":"30519",
    "addr:street":"Financial Center Way",
    "iso:country":"US",
    "sg:address":"3550 Financial Center Way",
    "sg:city":"Buford",
    "sg:classifiers":[
        {
            "category":"Transit Center",
            "subcategory":"Freight",
            "type":"Transportation"
        },
        {
            "category":"Professional",
            "subcategory":"Advertising",
            "type":"Services"
        }
    ],
    "sg:phone":"+1 706 208 9873",
    "sg:postcode":"30519",
    "sg:province":"GA",
    "sg:tags":[
        "outdoor"
    ],
    "wof:name":"Diamond Outdoor",
    "wof:placetype":"venue"
},
  "geometry": {"coordinates":[-83.985489,34.073818],"type":"Point"}
}