{
  "type": "Feature",
  "properties": {
    "addr:full":"4215 2nd Ave Columbus GA 31904",
    "addr:housenumber":"4215",
    "addr:postcode":"31904",
    "addr:street":"2Nd Ave",
    "iso:country":"US",
    "sg:address":"4215 2nd Ave",
    "sg:city":"Columbus",
    "sg:classifiers":[
        {
            "category":"Autos & Motor Vehicles",
            "subcategory":"Motorcycle Sales",
            "type":"Retail Goods"
        }
    ],
    "sg:phone":"+1 706 494 1375",
    "sg:postcode":"31904",
    "sg:province":"GA",
    "sg:tags":[
        "carwash"
    ],
    "wof:name":"Columbus Custom Carts",
    "wof:placetype":"venue"
},
  "geometry": {"coordinates":[-84.989946,32.504654],"type":"Point"}
}