{
  "type": "Feature",
  "properties": {
    "iso:country":"US",
    "sg:address":"1230 Kendrick Rd NE",
    "sg:city":"Atlanta",
    "sg:classifiers":[
        {
            "category":"Autos & Motor Vehicles",
            "subcategory":"Automobile Sales",
            "type":"Retail Goods"
        }
    ],
    "sg:phone":"+1 404 358 1452",
    "sg:postcode":"30319",
    "sg:province":"GA",
    "sg:tags":[
        "used"
    ],
    "wof:name":"Maxham Motors Inc",
    "wof:placetype":"venue"
},
  "geometry": {"coordinates":[-84.33704299999999,33.868529],"type":"Point"}
}