{
  "type": "Feature",
  "properties": {
    "addr:full":"900 Autumn Ct Apt 3 Dalton GA 30721",
    "addr:housenumber":"900;3",
    "addr:postcode":"30721",
    "addr:street":"Autumn Ct Apt",
    "iso:country":"US",
    "sg:address":"900 Autumn Ct Apt 3",
    "sg:city":"Dalton",
    "sg:classifiers":[
        {
            "category":"Organizations",
            "subcategory":"Religious Organization",
            "type":"Services"
        }
    ],
    "sg:phone":"+1 706 659 4586",
    "sg:postcode":"30721",
    "sg:province":"GA",
    "wof:name":"Emmaus Road Ministries",
    "wof:placetype":"venue"
},
  "geometry": {"coordinates":[-84.953518,34.811403],"type":"Point"}
}