{
  "type": "Feature",
  "properties": {
    "addr:full":"7990 Lanier Dr Cumming GA 30041",
    "addr:housenumber":"7990",
    "addr:postcode":"30041",
    "addr:street":"Lanier Dr",
    "iso:country":"US",
    "sg:address":"7990 Lanier Dr",
    "sg:city":"Cumming",
    "sg:classifiers":[
        {
            "category":"Real Estate",
            "subcategory":"Developer",
            "type":"Services"
        }
    ],
    "sg:phone":"+1 770 888 0028",
    "sg:postcode":"30041",
    "sg:province":"GA",
    "sg:website":"www.startcommunicating.com",
    "wof:name":"Hamilton Diversified",
    "wof:placetype":"venue"
},
  "geometry": {"coordinates":[-84.04983199999999,34.203709],"type":"Point"}
}