{
  "type": "Feature",
  "properties": {
    "addr:full":"4575 E Conway Dr NW Atlanta GA 30327",
    "addr:housenumber":"4575",
    "addr:postcode":"30327",
    "addr:street":"E Conway Dr Nw",
    "iso:country":"US",
    "sg:address":"4575 E Conway Dr NW",
    "sg:city":"Atlanta",
    "sg:classifiers":[
        {
            "category":"Professional",
            "subcategory":"Accounting & Tax Preparation",
            "type":"Services"
        }
    ],
    "sg:phone":"+1 404 252 3841",
    "sg:postcode":"30327",
    "sg:province":"GA",
    "wof:name":"Belsak Kendric J Cpa P",
    "wof:placetype":"venue"
},
  "geometry": {"coordinates":[-84.402027,33.880025],"type":"Point"}
}