{
  "type": "Feature",
  "properties": {
    "addr:full":"1860 State Rte 113 Carrollton GA 30117",
    "addr:housenumber":"1860",
    "addr:postcode":"30117",
    "addr:street":"State Rte 113",
    "iso:country":"US",
    "sg:address":"1860 State Rte 113",
    "sg:city":"Carrollton",
    "sg:classifiers":[
        {
            "category":"Organizations",
            "subcategory":"Religious Organization",
            "type":"Services"
        }
    ],
    "sg:phone":"+1 770 834 3834",
    "sg:postcode":"30117",
    "sg:province":"GA",
    "sg:tags":[
        "church"
    ],
    "sg:website":"www.deeperlifechristiancenter.org",
    "wof:name":"Deeper Life Christian Cntr",
    "wof:placetype":"venue"
},
  "geometry": {"coordinates":[-85.04981600000001,33.64928],"type":"Point"}
}