{
  "type": "Feature",
  "properties": {
    "iso:country":"US",
    "sg:address":"4104 Bevel Cir",
    "sg:city":"Valdosta",
    "sg:classifiers":[
        {
            "category":"Social Services",
            "subcategory":"Child Care",
            "type":"Services"
        }
    ],
    "sg:phone":"+1 229 559 3787",
    "sg:postcode":"31601",
    "sg:province":"GA",
    "sg:tags":[
        "nursery",
        "day"
    ],
    "wof:name":"Kesha's Kiddie Care",
    "wof:placetype":"venue"
},
  "geometry": {"coordinates":[-83.24545999999999,30.696975],"type":"Point"}
}