{
  "type": "Feature",
  "properties": {
    "iso:country":"US",
    "sg:address":"6700 Douglas Blvd",
    "sg:city":"Douglasville",
    "sg:phone":"+1 770 577 2636",
    "sg:postcode":"30135",
    "sg:province":"GA",
    "sg:website":"http://www.johnnyrockets.com",
    "wof:name":"Johnny Rockets",
    "wof:placetype":"venue"
},
  "geometry": {"coordinates":[-84.750674,33.729249],"type":"Point"}
}