{
  "type": "Feature",
  "properties": {
    "addr:full":"2120 Bethany Church Rd Monroe GA 30655",
    "addr:housenumber":"2120",
    "addr:postcode":"30655",
    "addr:street":"Bethany Church Rd",
    "iso:country":"US",
    "sg:address":"2120 Bethany Church Rd",
    "sg:city":"Monroe",
    "sg:classifiers":[
        {
            "category":"Building & Trades",
            "subcategory":"Construction",
            "type":"Services"
        }
    ],
    "sg:phone":"+1 770 267 8211",
    "sg:postcode":"30655",
    "sg:province":"GA",
    "sg:tags":[
        "hanging",
        "contractor"
    ],
    "wof:name":"Keyway Painting",
    "wof:placetype":"venue"
},
  "geometry": {"coordinates":[-83.65080399999999,33.816387],"type":"Point"}
}