{
  "type": "Feature",
  "properties": {
    "addr:full":"1438 N Park St Carrollton GA 30117",
    "addr:housenumber":"1438",
    "addr:postcode":"30117",
    "addr:street":"N Park St",
    "iso:country":"US",
    "sg:address":"1438 N Park St",
    "sg:city":"Carrollton",
    "sg:classifiers":[
        {
            "category":"Professional",
            "subcategory":"Business Services",
            "type":"Services"
        }
    ],
    "sg:phone":"+1 770 834 1070",
    "sg:postcode":"30117",
    "sg:province":"GA",
    "sg:tags":[
        "auctioneer"
    ],
    "wof:name":"West Georgia's Auction",
    "wof:placetype":"venue"
},
  "geometry": {"coordinates":[-85.088971,33.61296],"type":"Point"}
}