{
  "type": "Feature",
  "properties": {
    "iso:country":"US",
    "sg:address":"3269 Wellington Walk SW",
    "sg:city":"Atlanta",
    "sg:classifiers":[
        {
            "category":"Shopping",
            "subcategory":"Jewelry",
            "type":"Retail Goods"
        }
    ],
    "sg:phone":"+1 404 344 4909",
    "sg:postcode":"30331",
    "sg:province":"GA",
    "wof:name":"Polished & Pretty Jewelry",
    "wof:placetype":"venue"
},
  "geometry": {"coordinates":[-84.51601100000001,33.660992],"type":"Point"}
}