{
  "type": "Feature",
  "properties": {
    "iso:country":"US",
    "sg:address":"4467 Campbellton Rd SW",
    "sg:city":"Atlanta",
    "sg:classifiers":[
        {
            "category":"Personal",
            "subcategory":"Barber",
            "type":"Services"
        }
    ],
    "sg:phone":"+1 404 629 5760",
    "sg:postcode":"30331",
    "sg:province":"GA",
    "wof:name":"SIR Charles Professional Touch Barber",
    "wof:placetype":"venue"
},
  "geometry": {"coordinates":[-84.534897,33.695999],"type":"Point"}
}