{
  "type": "Feature",
  "properties": {
    "iso:country":"US",
    "sg:address":"4631 Calleigh Way",
    "sg:city":"Snellville",
    "sg:classifiers":[
        {
            "category":"Professional",
            "subcategory":"Management & Consulting",
            "type":"Services"
        }
    ],
    "sg:phone":"+1 770 982 3937",
    "sg:postcode":"30039",
    "sg:province":"GA",
    "sg:tags":[
        "business"
    ],
    "wof:name":"NJ Consulting Inc",
    "wof:placetype":"venue"
},
  "geometry": {"coordinates":[-84.06915100000001,33.799747],"type":"Point"}
}