{
  "type": "Feature",
  "properties": {
    "addr:full":"5565 Hearn Rd Ellenwood GA 30294",
    "addr:housenumber":"5565",
    "addr:postcode":"30294",
    "addr:street":"Hearn Rd",
    "iso:country":"US",
    "sg:address":"5565 Hearn Rd",
    "sg:city":"Ellenwood",
    "sg:classifiers":[
        {
            "category":"Building & Trades",
            "subcategory":"Plumbing",
            "type":"Services"
        }
    ],
    "sg:phone":"+1 770 981 5947",
    "sg:postcode":"30294",
    "sg:province":"GA",
    "sg:tags":[
        "contractor"
    ],
    "wof:name":"Metro Lawn Sprinkler",
    "wof:placetype":"venue"
},
  "geometry": {"coordinates":[-84.200592,33.628015],"type":"Point"}
}