{
  "type": "Feature",
  "properties": {
    "iso:country":"US",
    "sg:address":"3997 Five Forks Trickum Rd SW",
    "sg:city":"Lilburn",
    "sg:classifiers":[
        {
            "category":"Health Services",
            "subcategory":"Nursing And Care Facility",
            "type":"Services"
        }
    ],
    "sg:phone":"+1 770 381 7733",
    "sg:postcode":"30047",
    "sg:province":"GA",
    "sg:tags":[
        "home",
        "convalescent"
    ],
    "wof:name":"Sunrise At Five Forks",
    "wof:placetype":"venue"
},
  "geometry": {"coordinates":[-84.08771900000001,33.871382],"type":"Point"}
}