{
  "type": "Feature",
  "properties": {
    "addr:full":"4115 Belvedere Sq Decatur GA 30035",
    "addr:housenumber":"4115",
    "addr:postcode":"30035",
    "addr:street":"Belvedere Sq",
    "iso:country":"US",
    "sg:address":"4115 Belvedere Sq",
    "sg:city":"Decatur",
    "sg:classifiers":[
        {
            "category":"Professional",
            "type":"Services"
        }
    ],
    "sg:phone":"+1 404 284 9199",
    "sg:postcode":"30035",
    "sg:province":"GA",
    "wof:name":"Enchanged Evenings Two",
    "wof:placetype":"venue"
},
  "geometry": {"coordinates":[-84.221136,33.743608],"type":"Point"}
}