{
  "type": "Feature",
  "properties": {
    "addr:full":"1275 Oakdale Rd NE Atlanta GA 30307",
    "addr:housenumber":"1275",
    "addr:postcode":"30307",
    "addr:street":"Oakdale Rd Ne",
    "iso:country":"US",
    "sg:address":"1275 Oakdale Rd NE",
    "sg:city":"Atlanta",
    "sg:classifiers":[
        {
            "category":"Professional",
            "subcategory":"Engineering",
            "type":"Services"
        }
    ],
    "sg:phone":"+1 404 371 9190",
    "sg:postcode":"30307",
    "sg:province":"GA",
    "wof:name":"Alexander Engineering PC",
    "wof:placetype":"venue"
},
  "geometry": {"coordinates":[-84.331288,33.789154],"type":"Point"}
}