{
  "type": "Feature",
  "properties": {
    "addr:full":"2830 Battle Forrest Dr Decatur GA 30034",
    "addr:housenumber":"2830",
    "addr:postcode":"30034",
    "addr:street":"Battle Forrest Dr",
    "iso:country":"US",
    "sg:address":"2830 Battle Forrest Dr",
    "sg:city":"Decatur",
    "sg:classifiers":[
        {
            "category":"Education",
            "subcategory":"Special Training",
            "type":"Public Place"
        }
    ],
    "sg:phone":"+1 404 212 2037",
    "sg:postcode":"30034",
    "sg:province":"GA",
    "wof:name":"M T I Resources",
    "wof:placetype":"venue"
},
  "geometry": {"coordinates":[-84.28799100000001,33.70286],"type":"Point"}
}