{
  "type": "Feature",
  "properties": {
    "addr:full":"5007 S Royal Atlanta Dr Tucker GA 30084",
    "addr:housenumber":"5007",
    "addr:postcode":"30084",
    "addr:street":"S Royal Atlanta Dr",
    "iso:country":"US",
    "sg:address":"5007 S Royal Atlanta Dr",
    "sg:city":"Tucker",
    "sg:classifiers":[
        {
            "category":"Shopping",
            "subcategory":"Computers & Home Electronics",
            "type":"Retail Goods"
        }
    ],
    "sg:phone":"+1 770 493 6862",
    "sg:postcode":"30084",
    "sg:province":"GA",
    "sg:tags":[
        "high",
        "fidelity",
        "stereophonic",
        "equipment-dealers"
    ],
    "wof:name":"Rock-N-Road Audio",
    "wof:placetype":"venue"
},
  "geometry": {"coordinates":[-84.18548199999999,33.856242],"type":"Point"}
}