{
  "type": "Feature",
  "properties": {
    "addr:full":"118 S Hutchinson Ave Adel GA 31620",
    "addr:housenumber":"118",
    "addr:postcode":"31620",
    "addr:street":"S Hutchinson Ave",
    "iso:country":"US",
    "sg:address":"118 S Hutchinson Ave",
    "sg:city":"Adel",
    "sg:classifiers":[
        {
            "category":"Personal",
            "subcategory":"Barber",
            "type":"Services"
        }
    ],
    "sg:phone":"+1 229 896 9718",
    "sg:postcode":"31620",
    "sg:province":"GA",
    "wof:name":"O K Barber Shop",
    "wof:placetype":"venue"
},
  "geometry": {"coordinates":[-83.423359,31.136776],"type":"Point"}
}