{
  "type": "Feature",
  "properties": {
    "iso:country":"US",
    "sg:address":"800 Crawfordville Rd",
    "sg:city":"Union Point",
    "sg:classifiers":[
        {
            "category":"Real Estate",
            "subcategory":"Real Estate Agent",
            "type":"Services"
        }
    ],
    "sg:phone":"+1 706 486 4501",
    "sg:postcode":"30669",
    "sg:province":"GA",
    "sg:tags":[
        "authorities",
        "housing"
    ],
    "wof:name":"Union Point Housing Authority",
    "wof:placetype":"venue"
},
  "geometry": {"coordinates":[-83.07405199999999,33.622246],"type":"Point"}
}