{
  "type": "Feature",
  "properties": {
    "addr:full":"6068 Sumter Dr Douglasville GA 30135",
    "addr:housenumber":"6068",
    "addr:postcode":"30135",
    "addr:street":"Sumter Dr",
    "iso:country":"US",
    "sg:address":"6068 Sumter Dr",
    "sg:city":"Douglasville",
    "sg:classifiers":[
        {
            "category":"Building & Trades",
            "subcategory":"Cleaning & Sanitation",
            "type":"Services"
        }
    ],
    "sg:phone":"+1 770 489 9654",
    "sg:postcode":"30135",
    "sg:province":"GA",
    "sg:tags":[
        "janitor"
    ],
    "wof:name":"Queen Of Hearts",
    "wof:placetype":"venue"
},
  "geometry": {"coordinates":[-84.773816,33.673436],"type":"Point"}
}