{
  "type": "Feature",
  "properties": {
    "iso:country":"US",
    "sg:address":"3901 Garrett Springs Dr",
    "sg:city":"Powder Springs",
    "sg:classifiers":[
        {
            "category":"Building & Trades",
            "subcategory":"Electrical",
            "type":"Services"
        }
    ],
    "sg:phone":"+1 770 924 8244",
    "sg:postcode":"30127",
    "sg:province":"GA",
    "sg:tags":[
        "home",
        "system",
        "automation"
    ],
    "wof:name":"JNC Technologies",
    "wof:placetype":"venue"
},
  "geometry": {"coordinates":[-84.671605,33.821017],"type":"Point"}
}