{
  "type": "Feature",
  "properties": {
    "iso:country":"US",
    "sg:address":"156 Rainbow Way",
    "sg:city":"Fayetteville",
    "sg:classifiers":[
        {
            "category":"Food & Beverages",
            "subcategory":"Bakery",
            "type":"Retail Goods"
        }
    ],
    "sg:phone":"+1 770 719 2253",
    "sg:postcode":"30214",
    "sg:province":"GA",
    "sg:tags":[
        "baker"
    ],
    "wof:name":"E J's Sweets",
    "wof:placetype":"venue"
},
  "geometry": {"coordinates":[-84.428892,33.5063],"type":"Point"}
}