{
  "type": "Feature",
  "properties": {
    "iso:country":"US",
    "sg:address":"2609 Bridlewood Ln SE",
    "sg:city":"Smyrna",
    "sg:classifiers":[
        {
            "category":"Health Services",
            "subcategory":"Chiropractor",
            "type":"Services"
        }
    ],
    "sg:phone":"+1 404 966 6954",
    "sg:postcode":"30080",
    "sg:province":"GA",
    "sg:tags":[
        "chiropractic"
    ],
    "wof:name":"Susan Hopkins Dc",
    "wof:placetype":"venue"
},
  "geometry": {"coordinates":[-84.47923299999999,33.833481],"type":"Point"}
}