{
  "type": "Feature",
  "properties": {
    "iso:country":"US",
    "sg:address":"2795 Chaucer Dr SW",
    "sg:city":"Atlanta",
    "sg:classifiers":[
        {
            "category":"Professional",
            "subcategory":"Business Services",
            "type":"Services"
        }
    ],
    "sg:phone":"+1 404 691 5261",
    "sg:postcode":"30311",
    "sg:province":"GA",
    "wof:name":"Faw Enterprises Inc",
    "wof:placetype":"venue"
},
  "geometry": {"coordinates":[-84.48057300000001,33.747114],"type":"Point"}
}