{
  "type": "Feature",
  "properties": {
    "addr:full":"683 Winters Mountain Rd Dahlonega GA 30533",
    "addr:housenumber":"683",
    "addr:postcode":"30533",
    "addr:street":"Winters Mountain Rd",
    "iso:country":"US",
    "sg:address":"683 Winters Mountain Rd",
    "sg:city":"Dahlonega",
    "sg:classifiers":[
        {
            "category":"Building & Trades",
            "subcategory":"Plumbing",
            "type":"Services"
        }
    ],
    "sg:phone":"+1 706 864 8344",
    "sg:postcode":"30533",
    "sg:province":"GA",
    "sg:tags":[
        "plumbing",
        "contractor"
    ],
    "wof:name":"Smith's Plumbing",
    "wof:placetype":"venue"
},
  "geometry": {"coordinates":[-83.93460899999999,34.52245],"type":"Point"}
}