{
  "type": "Feature",
  "properties": {
    "iso:country":"US",
    "sg:address":"937 Greene St",
    "sg:city":"Augusta",
    "sg:classifiers":[
        {
            "category":"Professional",
            "type":"Services"
        }
    ],
    "sg:phone":"+1 706 722 0201",
    "sg:postcode":"30901",
    "sg:province":"GA",
    "wof:name":"Nail Techniques",
    "wof:placetype":"venue"
},
  "geometry": {"coordinates":[-81.969838,33.474696],"type":"Point"}
}