{
  "type": "Feature",
  "properties": {
    "addr:full":"2165 Northmont Pkwy Duluth GA 30096",
    "addr:housenumber":"2165",
    "addr:postcode":"30096",
    "addr:street":"Northmont Pkwy",
    "iso:country":"US",
    "sg:address":"2165 Northmont Pkwy",
    "sg:city":"Duluth",
    "sg:classifiers":[
        {
            "category":"Shopping",
            "type":"Retail Goods"
        }
    ],
    "sg:phone":"+1 800 295 5510",
    "sg:postcode":"30096",
    "sg:province":"GA",
    "sg:website":"www.uline.com",
    "wof:name":"Uline Shipping Supplies",
    "wof:placetype":"venue"
},
  "geometry": {"coordinates":[-84.11489899999999,33.9711],"type":"Point"}
}