{
  "type": "Feature",
  "properties": {
    "addr:full":"1080 Chestnut St Woodville GA 30669",
    "addr:housenumber":"1080",
    "addr:postcode":"30669",
    "addr:street":"Chestnut St",
    "iso:country":"US",
    "sg:address":"1080 Chestnut St",
    "sg:city":"Woodville",
    "sg:classifiers":[
        {
            "category":"Retail",
            "subcategory":"Portrait Studio",
            "type":"Services"
        }
    ],
    "sg:phone":"+1 706 431 6018",
    "sg:postcode":"30669",
    "sg:province":"GA",
    "wof:name":"Mcn Media Svc",
    "wof:placetype":"venue"
},
  "geometry": {"coordinates":[-83.10064199999999,33.669807],"type":"Point"}
}