{
  "type": "Feature",
  "properties": {
    "addr:full":"7878 Post Rd Winston GA 30187",
    "addr:housenumber":"7878",
    "addr:postcode":"30187",
    "addr:street":"Post Rd",
    "iso:country":"US",
    "sg:address":"7878 Post Rd",
    "sg:city":"Winston",
    "sg:classifiers":[
        {
            "category":"Recreation",
            "type":"Entertainment"
        }
    ],
    "sg:phone":"+1 770 489 1007",
    "sg:postcode":"30187",
    "sg:province":"GA",
    "sg:tags":[
        "amusement"
    ],
    "wof:name":"Morning Glory Farm",
    "wof:placetype":"venue"
},
  "geometry": {"coordinates":[-84.86332299999999,33.589568],"type":"Point"}
}