{
  "type": "Feature",
  "properties": {
    "iso:country":"US",
    "sg:address":"1872 Enterprise Dr NW",
    "sg:city":"Norcross",
    "sg:classifiers":[
        {
            "category":"Home & Garden",
            "subcategory":"Carpets & Floor Coverings",
            "type":"Retail Goods"
        }
    ],
    "sg:phone":"+1 770 441 7671",
    "sg:postcode":"30093",
    "sg:province":"GA",
    "wof:name":"Quality Carpet & Vinyl Inc",
    "wof:placetype":"venue"
},
  "geometry": {"coordinates":[-84.220304,33.910021],"type":"Point"}
}