{
  "type": "Feature",
  "properties": {
    "iso:country":"US",
    "sg:address":"9465 State Rte 5",
    "sg:city":"Douglasville",
    "sg:classifiers":[
        {
            "category":"Retail",
            "subcategory":"Auto Repair",
            "type":"Services"
        }
    ],
    "sg:phone":"+1 770 942 6889",
    "sg:postcode":"30135",
    "sg:province":"GA",
    "sg:tags":[
        "repairing",
        "automobile"
    ],
    "wof:name":"Mike's Automotive",
    "wof:placetype":"venue"
},
  "geometry": {"coordinates":[-84.762019,33.725581],"type":"Point"}
}