{
  "type": "Feature",
  "properties": {
    "addr:full":"508 Alford St La Grange GA 30240",
    "addr:housenumber":"508",
    "addr:postcode":"30240",
    "addr:street":"Alford St",
    "iso:country":"US",
    "sg:address":"508 Alford St",
    "sg:city":"La Grange",
    "sg:classifiers":[
        {
            "category":"Building & Trades",
            "subcategory":"Construction",
            "type":"Services"
        }
    ],
    "sg:phone":"+1 706 884 8756",
    "sg:postcode":"30240",
    "sg:province":"GA",
    "wof:name":"Cheek Gen Constructing Svcs",
    "wof:placetype":"venue"
},
  "geometry": {"coordinates":[-85.038263,33.03294],"type":"Point"}
}