{
  "type": "Feature",
  "properties": {
    "iso:country":"US",
    "sg:address":"1628 E Shotwell St",
    "sg:city":"Bainbridge",
    "sg:classifiers":[
        {
            "category":"Autos & Motor Vehicles",
            "subcategory":"Auto Supplies",
            "type":"Retail Goods"
        },
        {
            "category":"Wholesale",
            "subcategory":"Auto Parts",
            "type":"Manufacturing & Wholesale Goods"
        }
    ],
    "sg:phone":"+1 229 246 1611",
    "sg:postcode":"39819",
    "sg:province":"GA",
    "sg:tags":[
        "automobile"
    ],
    "wof:name":"Brooks Auto Parts Co",
    "wof:placetype":"venue"
},
  "geometry": {"coordinates":[-84.550175,30.90377],"type":"Point"}
}