{
  "type": "Feature",
  "properties": {
    "addr:full":"4057 Plainview Rd Maysville GA 30558",
    "addr:housenumber":"4057",
    "addr:postcode":"30558",
    "addr:street":"Plainview Rd",
    "iso:country":"US",
    "sg:address":"4057 Plainview Rd",
    "sg:city":"Maysville",
    "sg:classifiers":[
        {
            "category":"Farming",
            "subcategory":"Farm",
            "type":"Manufacturing & Wholesale Goods"
        }
    ],
    "sg:phone":"+1 706 693 2453",
    "sg:postcode":"30558",
    "sg:province":"GA",
    "sg:tags":[
        "crop",
        "general"
    ],
    "wof:name":"American Opportunity Inc",
    "wof:placetype":"venue"
},
  "geometry": {"coordinates":[-83.624239,34.219626],"type":"Point"}
}