{
  "type": "Feature",
  "properties": {
    "addr:full":"308 Cherokee Pl SE Atlanta GA 30312",
    "addr:housenumber":"308",
    "addr:postcode":"30312",
    "addr:street":"Cherokee Pl Se",
    "iso:country":"US",
    "sg:address":"308 Cherokee Pl SE",
    "sg:city":"Atlanta",
    "sg:classifiers":[
        {
            "category":"Place Of Worship",
            "subcategory":"Church",
            "type":"Public Place"
        },
        {
            "category":"Place Of Worship",
            "type":"Public Place"
        }
    ],
    "sg:phone":"+1 404 423 2783",
    "sg:postcode":"30312",
    "sg:province":"GA",
    "sg:tags":[
        "christ",
        "churches-community"
    ],
    "wof:name":"Mercy Community Church",
    "wof:placetype":"venue"
},
  "geometry": {"coordinates":[-84.377666,33.737814],"type":"Point"}
}