{
  "type": "Feature",
  "properties": {
    "iso:country":"US",
    "sg:address":"1 Hospital Park",
    "sg:city":"Moultrie",
    "sg:classifiers":[
        {
            "category":"Health Services",
            "subcategory":"Doctor",
            "type":"Services"
        }
    ],
    "sg:phone":"+1 229 985 3363",
    "sg:postcode":"31768",
    "sg:province":"GA",
    "wof:name":"Redding Lee C DDS PC",
    "wof:placetype":"venue"
},
  "geometry": {"coordinates":[-83.778808,31.126917],"type":"Point"}
}