{
  "type": "Feature",
  "properties": {
    "addr:full":"1910 Sandringham Dr SW Atlanta GA 30311",
    "addr:housenumber":"1910",
    "addr:postcode":"30311",
    "addr:street":"Sandringham Dr Sw",
    "iso:country":"US",
    "sg:address":"1910 Sandringham Dr SW",
    "sg:city":"Atlanta",
    "sg:classifiers":[
        {
            "category":"Building & Trades",
            "subcategory":"Construction",
            "type":"Services"
        }
    ],
    "sg:phone":"+1 404 349 1347",
    "sg:postcode":"30311",
    "sg:province":"GA",
    "sg:tags":[
        "house"
    ],
    "wof:name":"Barksdale Construction Inc",
    "wof:placetype":"venue"
},
  "geometry": {"coordinates":[-84.474474,33.705822],"type":"Point"}
}