{
  "type": "Feature",
  "properties": {
    "addr:full":"2626 Rainbow Way Decatur GA 30034",
    "addr:housenumber":"2626",
    "addr:postcode":"30034",
    "addr:street":"Rainbow Way",
    "iso:country":"US",
    "sg:address":"2626 Rainbow Way",
    "sg:city":"Decatur",
    "sg:classifiers":[
        {
            "category":"Health Services",
            "subcategory":"Doctor",
            "type":"Services"
        }
    ],
    "sg:phone":"+1 404 241 1866",
    "sg:postcode":"30034",
    "sg:province":"GA",
    "sg:tags":[
        "clinic"
    ],
    "wof:name":"Grady Health Ctr South De Kalb",
    "wof:placetype":"venue"
},
  "geometry": {"coordinates":[-84.271092,33.711326],"type":"Point"}
}