{
  "type": "Feature",
  "properties": {
    "iso:country":"US",
    "sg:address":"1605 Dogwood Dr",
    "sg:city":"Cumming",
    "sg:classifiers":[
        {
            "category":"Building & Trades",
            "subcategory":"Construction",
            "type":"Services"
        }
    ],
    "sg:phone":"+1 770 887 3388",
    "sg:postcode":"30041",
    "sg:province":"GA",
    "sg:tags":[
        "res",
        "remodeling",
        "com"
    ],
    "wof:name":"Innovative Remodeling & Constr",
    "wof:placetype":"venue"
},
  "geometry": {"coordinates":[-84.108497,34.214991],"type":"Point"}
}