{
  "type": "Feature",
  "properties": {
    "addr:full":"468 Park Dr Grovetown GA 30830",
    "addr:housenumber":"468",
    "addr:postcode":"30830",
    "addr:street":"Park Dr",
    "iso:country":"US",
    "sg:address":"468 Park Dr",
    "sg:city":"Grovetown",
    "sg:classifiers":[
        {
            "category":"Restaurant",
            "type":"Food & Drink"
        }
    ],
    "sg:phone":"+1 706 860 1980",
    "sg:postcode":"30830",
    "sg:province":"GA",
    "sg:tags":[
        "eating"
    ],
    "wof:name":"Huddle House",
    "wof:placetype":"venue"
},
  "geometry": {"coordinates":[-82.02298,33.08289],"type":"Point"}
}