{
  "type": "Feature",
  "properties": {
    "iso:country":"US",
    "sg:address":"333 Industrial Blvd",
    "sg:city":"Mc Donough",
    "sg:classifiers":[
        {
            "category":"Autos & Motor Vehicles",
            "subcategory":"Automobile Sales",
            "type":"Retail Goods"
        }
    ],
    "sg:phone":"+1 770 957 1997",
    "sg:postcode":"30253",
    "sg:province":"GA",
    "sg:tags":[
        "parts",
        "truck",
        "used"
    ],
    "wof:name":"Chrysler Select Trucks",
    "wof:placetype":"venue"
},
  "geometry": {"coordinates":[-84.15673099999999,33.414115],"type":"Point"}
}