{
  "type": "Feature",
  "properties": {
    "addr:full":"1935 Cherokee Way Riverdale GA 30296",
    "addr:housenumber":"1935",
    "addr:postcode":"30296",
    "addr:street":"Cherokee Way",
    "iso:country":"US",
    "sg:address":"1935 Cherokee Way",
    "sg:city":"Riverdale",
    "sg:classifiers":[
        {
            "category":"Building & Trades",
            "subcategory":"Locksmith",
            "type":"Services"
        }
    ],
    "sg:phone":"+1 770 308 8103",
    "sg:postcode":"30296",
    "sg:province":"GA",
    "sg:tags":[
        "locksmiths-commercial",
        "industrial",
        "key",
        "lock"
    ],
    "wof:name":"Lock And Key of Riverdale",
    "wof:placetype":"venue"
},
  "geometry": {"coordinates":[-84.451708,33.558208],"type":"Point"}
}