{
  "type": "Feature",
  "properties": {
    "iso:country":"US",
    "sg:address":"1383 Oglethorpe St",
    "sg:city":"Macon",
    "sg:classifiers":[
        {
            "category":"Social Services",
            "type":"Services"
        }
    ],
    "sg:phone":"+1 478 972 3583",
    "sg:postcode":"31201",
    "sg:province":"GA",
    "sg:tags":[
        "academy",
        "tennis"
    ],
    "wof:name":"Middle Georgia Tennis Academy",
    "wof:placetype":"venue"
},
  "geometry": {"coordinates":[-83.64493899999999,32.833921],"type":"Point"}
}