{
  "type": "Feature",
  "properties": {
    "iso:country":"US",
    "sg:address":"1196 Brannen Dr",
    "sg:city":"Louisville",
    "sg:classifiers":[
        {
            "category":"Shopping",
            "type":"Retail Goods"
        }
    ],
    "sg:phone":"+1 478 625 7475",
    "sg:postcode":"30434",
    "sg:province":"GA",
    "sg:tags":[
        "cosmetic",
        "perfume"
    ],
    "wof:name":"Seafus Cosmetics",
    "wof:placetype":"venue"
},
  "geometry": {"coordinates":[-82.395048,32.990003],"type":"Point"}
}