{
  "type": "Feature",
  "properties": {
    "addr:full":"7 E Lake Dr SE Atlanta GA 30317",
    "addr:housenumber":"7",
    "addr:postcode":"30317",
    "addr:street":"E Lake Dr Se",
    "iso:country":"US",
    "sg:address":"7 E Lake Dr SE",
    "sg:city":"Atlanta",
    "sg:classifiers":[
        {
            "category":"Government",
            "subcategory":"Office",
            "type":"Public Place"
        }
    ],
    "sg:phone":"+1 404 651 5120",
    "sg:postcode":"30317",
    "sg:province":"GA",
    "sg:website":"www.p2ad.com",
    "wof:name":"Pollution Prevention Assn",
    "wof:placetype":"venue"
},
  "geometry": {"coordinates":[-84.301417,33.750341],"type":"Point"}
}