{
  "type": "Feature",
  "properties": {
    "iso:country":"US",
    "sg:address":"1075 Cobb International Pl NW",
    "sg:city":"Kennesaw",
    "sg:classifiers":[
        {
            "category":"Personal",
            "type":"Services"
        }
    ],
    "sg:phone":"+1 678 594 0201",
    "sg:postcode":"30152",
    "sg:province":"GA",
    "sg:tags":[
        "mover"
    ],
    "wof:name":"Smartbox",
    "wof:placetype":"venue"
},
  "geometry": {"coordinates":[-84.61129,34.006187],"type":"Point"}
}