{
  "type": "Feature",
  "properties": {
    "addr:full":"1414 Douglas Hwy Hazlehurst GA 31539",
    "addr:housenumber":"1414",
    "addr:postcode":"31539",
    "addr:street":"Douglas Hwy",
    "iso:country":"US",
    "sg:address":"1414 Douglas Hwy",
    "sg:city":"Hazlehurst",
    "sg:classifiers":[
        {
            "category":"Manufacturing",
            "subcategory":"Lumber",
            "type":"Manufacturing & Wholesale Goods"
        }
    ],
    "sg:phone":"+1 912 375 5189",
    "sg:postcode":"31539",
    "sg:province":"GA",
    "sg:tags":[
        "government"
    ],
    "wof:name":"Forestry Commission",
    "wof:placetype":"venue"
},
  "geometry": {"coordinates":[-82.67465900000001,31.794093],"type":"Point"}
}