{
  "type": "Feature",
  "properties": {
    "addr:full":"1465 Beacon Light Rd Hartwell GA 30643",
    "addr:housenumber":"1465",
    "addr:postcode":"30643",
    "addr:street":"Beacon Light Rd",
    "iso:country":"US",
    "sg:address":"1465 Beacon Light Rd",
    "sg:city":"Hartwell",
    "sg:classifiers":[
        {
            "category":"Building & Trades",
            "subcategory":"Construction",
            "type":"Services"
        }
    ],
    "sg:phone":"+1 706 376 2319",
    "sg:postcode":"30643",
    "sg:province":"GA",
    "sg:tags":[
        "house"
    ],
    "wof:name":"Quality Homebuilders",
    "wof:placetype":"venue"
},
  "geometry": {"coordinates":[-82.97797,34.378804],"type":"Point"}
}