{
  "type": "Feature",
  "properties": {
    "addr:full":"109 E Robert Toombs Ave Washington GA 30673",
    "addr:housenumber":"109",
    "addr:postcode":"30673",
    "addr:street":"E Robert Toombs Ave",
    "iso:country":"US",
    "sg:address":"109 E Robert Toombs Ave",
    "sg:city":"Washington",
    "sg:classifiers":[
        {
            "category":"Shopping",
            "subcategory":"Stationery & Office Supplies",
            "type":"Retail Goods"
        }
    ],
    "sg:phone":"+1 706 678 5222",
    "sg:postcode":"30673",
    "sg:province":"GA",
    "wof:name":"M & Mcsra OFFICE Products",
    "wof:placetype":"venue"
},
  "geometry": {"coordinates":[-82.73884099999999,33.736807],"type":"Point"}
}