{
  "type": "Feature",
  "properties": {
    "addr:full":"409 E 3rd St Jackson GA 30233",
    "addr:housenumber":"409",
    "addr:postcode":"30233",
    "addr:street":"E 3Rd St",
    "iso:country":"US",
    "sg:address":"409 E 3rd St",
    "sg:city":"Jackson",
    "sg:classifiers":[
        {
            "category":"Place Of Worship",
            "type":"Public Place"
        }
    ],
    "sg:phone":"+1 770 504 1281",
    "sg:postcode":"30233",
    "sg:province":"GA",
    "sg:tags":[
        "church"
    ],
    "wof:name":"Mary Buttrill Day School The",
    "wof:placetype":"venue"
},
  "geometry": {"coordinates":[-83.962964,33.294451],"type":"Point"}
}