{
  "type": "Feature",
  "properties": {
    "iso:country":"US",
    "sg:address":"821 Mill Pond Rd",
    "sg:city":"Valdosta",
    "sg:classifiers":[
        {
            "category":"Recreation",
            "type":"Entertainment"
        }
    ],
    "sg:phone":"+1 229 244 2559",
    "sg:postcode":"31602",
    "sg:province":"GA",
    "sg:tags":[
        "club",
        "membership"
    ],
    "wof:name":"Lake Alcyone Sportsmens Club",
    "wof:placetype":"venue"
},
  "geometry": {"coordinates":[-83.305755,30.865966],"type":"Point"}
}