{
  "type": "Feature",
  "properties": {
    "addr:full":"1544 Benning Dr Columbus GA 31903",
    "addr:housenumber":"1544",
    "addr:postcode":"31903",
    "addr:street":"Benning Dr",
    "iso:country":"US",
    "sg:address":"1544 Benning Dr",
    "sg:city":"Columbus",
    "sg:classifiers":[
        {
            "category":"Education",
            "subcategory":"School",
            "type":"Public Place"
        }
    ],
    "sg:phone":"+1 706 685 7600",
    "sg:postcode":"31903",
    "sg:province":"GA",
    "wof:name":"Baker Middle School",
    "wof:placetype":"venue"
},
  "geometry": {"coordinates":[-84.944817,32.426467],"type":"Point"}
}