{
  "type": "Feature",
  "properties": {
    "iso:country":"US",
    "sg:address":"7 Oemler Ct E",
    "sg:city":"Savannah",
    "sg:classifiers":[
        {
            "category":"Building & Trades",
            "subcategory":"Construction",
            "type":"Services"
        }
    ],
    "sg:phone":"+1 912 897 1031",
    "sg:postcode":"31410",
    "sg:province":"GA",
    "sg:tags":[
        "heavy"
    ],
    "wof:name":"Presley Land Clearing & Proper",
    "wof:placetype":"venue"
},
  "geometry": {"coordinates":[-80.956361,32.014059],"type":"Point"}
}