{
  "type": "Feature",
  "properties": {
    "addr:full":"639 Thornton Rd Lithia Springs GA 30122",
    "addr:housenumber":"639",
    "addr:postcode":"30122",
    "addr:street":"Thornton Rd",
    "iso:country":"US",
    "sg:address":"639 Thornton Rd",
    "sg:city":"Lithia Springs",
    "sg:classifiers":[
        {
            "category":"Professional",
            "subcategory":"Employment Agencies",
            "type":"Services"
        }
    ],
    "sg:phone":"+1 770 819 6444",
    "sg:postcode":"30122",
    "sg:province":"GA",
    "wof:name":"Adecco Employment Services",
    "wof:placetype":"venue"
},
  "geometry": {"coordinates":[-84.619698,33.7878],"type":"Point"}
}