{
  "type": "Feature",
  "properties": {
    "iso:country":"US",
    "sg:address":"3813 Franklin Ave",
    "sg:city":"Brunswick",
    "sg:classifiers":[
        {
            "category":"Freight",
            "type":"Transportation"
        }
    ],
    "sg:phone":"+1 912 264 3123",
    "sg:postcode":"31520",
    "sg:province":"GA",
    "sg:tags":[
        "operator",
        "local",
        "trucking"
    ],
    "wof:name":"C W Futch Trucking",
    "wof:placetype":"venue"
},
  "geometry": {"coordinates":[-81.501164,31.181486],"type":"Point"}
}