{
  "type": "Feature",
  "properties": {
    "iso:country":"US",
    "sg:address":"115 Coleman Blvd",
    "sg:city":"Savannah",
    "sg:classifiers":[
        {
            "category":"Home & Garden",
            "subcategory":"Building Materials",
            "type":"Retail Goods"
        }
    ],
    "sg:phone":"+1 912 330 9599",
    "sg:postcode":"31408",
    "sg:province":"GA",
    "sg:tags":[
        "door"
    ],
    "wof:name":"Coastal Millworks",
    "wof:placetype":"venue"
},
  "geometry": {"coordinates":[-81.224926,32.11136],"type":"Point"}
}