{
  "type": "Feature",
  "properties": {
    "addr:full":"2681 Monroe Hwy Bogart GA 30622",
    "addr:housenumber":"2681",
    "addr:postcode":"30622",
    "addr:street":"Monroe Hwy Bogart",
    "iso:country":"US",
    "sg:address":"2681 Monroe Hwy",
    "sg:city":"Bogart",
    "sg:classifiers":[
        {
            "category":"Autos & Motor Vehicles",
            "subcategory":"Auto Supplies",
            "type":"Retail Goods"
        }
    ],
    "sg:phone":"+1 770 725 0811",
    "sg:postcode":"30622",
    "sg:province":"GA",
    "sg:tags":[
        "transmission",
        "transmissions-other"
    ],
    "wof:name":"Complete Transmission Service",
    "wof:placetype":"venue"
},
  "geometry": {"coordinates":[-83.522131,33.918028],"type":"Point"}
}