{
  "type": "Feature",
  "properties": {
    "iso:country":"US",
    "sg:address":"330 Fairleaf Ct",
    "sg:city":"Alpharetta",
    "sg:classifiers":[
        {
            "category":"Retail",
            "subcategory":"Self-service Laundry",
            "type":"Services"
        }
    ],
    "sg:phone":"+1 770 569 9503",
    "sg:postcode":"30022",
    "sg:province":"GA",
    "sg:tags":[
        "coin"
    ],
    "wof:name":"Our Lady of Laundry",
    "wof:placetype":"venue"
},
  "geometry": {"coordinates":[-84.25848999999999,34.041796],"type":"Point"}
}