{
  "type": "Feature",
  "properties": {
    "iso:country":"US",
    "sg:address":"303 Batiste Way SE",
    "sg:city":"Jonesboro",
    "sg:classifiers":[
        {
            "category":"Building & Trades",
            "subcategory":"Construction",
            "type":"Services"
        }
    ],
    "sg:phone":"+1 770 210 5090",
    "sg:postcode":"30236",
    "sg:province":"GA",
    "sg:tags":[
        "hanging",
        "contractor"
    ],
    "wof:name":"Coles Painting Service",
    "wof:placetype":"venue"
},
  "geometry": {"coordinates":[-84.352352,33.510992],"type":"Point"}
}