{
  "type": "Feature",
  "properties": {
    "addr:full":"105 Lang Dr Fayetteville GA 30214",
    "addr:housenumber":"105",
    "addr:postcode":"30214",
    "addr:street":"Lang Dr",
    "iso:country":"US",
    "sg:address":"105 Lang Dr",
    "sg:city":"Fayetteville",
    "sg:classifiers":[
        {
            "category":"Banks & Credit Unions",
            "subcategory":"Bank",
            "type":"Services"
        }
    ],
    "sg:phone":"+1 770 716 7251",
    "sg:postcode":"30214",
    "sg:province":"GA",
    "sg:tags":[
        "loan"
    ],
    "wof:name":"Premont Commercial Sba Loans",
    "wof:placetype":"venue"
},
  "geometry": {"coordinates":[-84.463303,33.496167],"type":"Point"}
}