{
  "type": "Feature",
  "properties": {
    "addr:full":"150 Lake Ter Macon GA 31204",
    "addr:housenumber":"150",
    "addr:postcode":"31204",
    "addr:street":"Lake Ter",
    "iso:country":"US",
    "sg:address":"150 Lake Ter",
    "sg:city":"Macon",
    "sg:classifiers":[
        {
            "category":"Social Services",
            "subcategory":"Child Care",
            "type":"Services"
        }
    ],
    "sg:phone":"+1 478 474 2684",
    "sg:postcode":"31204",
    "sg:province":"GA",
    "wof:name":"Children's Friend Learning Ctr",
    "wof:placetype":"venue"
},
  "geometry": {"coordinates":[-83.683959,32.857309],"type":"Point"}
}