{
  "type": "Feature",
  "properties": {
    "iso:country":"US",
    "sg:address":"800 State Rte 9 E",
    "sg:city":"Dawsonville",
    "sg:classifiers":[
        {
            "category":"Shopping",
            "type":"Retail Goods"
        }
    ],
    "sg:phone":"+1 706 216 5496",
    "sg:postcode":"30534",
    "sg:province":"GA",
    "sg:tags":[
        "miscellaneous",
        "store"
    ],
    "wof:name":"Lego Retail Outlet",
    "wof:placetype":"venue"
},
  "geometry": {"coordinates":[-84.004272,34.404654],"type":"Point"}
}