{
  "type": "Feature",
  "properties": {
    "iso:country":"US",
    "sg:address":"1513 W Walnut Ave",
    "sg:city":"Dalton",
    "sg:classifiers":[
        {
            "category":"Personal",
            "subcategory":"Beauty Salon",
            "type":"Services"
        }
    ],
    "sg:phone":"+1 706 278 4330",
    "sg:postcode":"30720",
    "sg:province":"GA",
    "wof:name":"Gazebo Hair Salon",
    "wof:placetype":"venue"
},
  "geometry": {"coordinates":[-84.99922599999999,34.76083],"type":"Point"}
}