{
  "type": "Feature",
  "properties": {
    "addr:full":"1212 Wilkes Cir NW Atlanta GA 30318",
    "addr:housenumber":"1212",
    "addr:postcode":"30318",
    "addr:street":"Wilkes Cir Nw",
    "iso:country":"US",
    "sg:address":"1212 Wilkes Cir NW",
    "sg:city":"Atlanta",
    "sg:classifiers":[
        {
            "category":"Organizations",
            "subcategory":"Religious Organization",
            "type":"Services"
        }
    ],
    "sg:phone":"+1 404 794 7014",
    "sg:postcode":"30318",
    "sg:province":"GA",
    "sg:tags":[
        "church"
    ],
    "wof:name":"Salvation Ministries Ctr Inc",
    "wof:placetype":"venue"
},
  "geometry": {"coordinates":[-84.480926,33.78487],"type":"Point"}
}