{
  "type": "Feature",
  "properties": {
    "addr:full":"807 S Fry St Valdosta GA 31601",
    "addr:housenumber":"807",
    "addr:postcode":"31601",
    "addr:street":"S Fry St",
    "iso:country":"US",
    "sg:address":"807 S Fry St",
    "sg:city":"Valdosta",
    "sg:classifiers":[
        {
            "category":"Health Services",
            "subcategory":"Clinic",
            "type":"Services"
        }
    ],
    "sg:phone":"+1 229 245 7838",
    "sg:postcode":"31601",
    "sg:province":"GA",
    "sg:tags":[
        "home"
    ],
    "wof:name":"Personal Home Health Care",
    "wof:placetype":"venue"
},
  "geometry": {"coordinates":[-83.267281,30.827482],"type":"Point"}
}