{
  "type": "Feature",
  "properties": {
    "addr:full":"9919 Old Savannah Rd Sandersville GA 31082",
    "addr:housenumber":"9919",
    "addr:postcode":"31082",
    "addr:street":"Old Savannah Rd",
    "iso:country":"US",
    "sg:address":"9919 Old Savannah Rd",
    "sg:city":"Sandersville",
    "sg:classifiers":[
        {
            "category":"Organizations",
            "subcategory":"Religious Organization",
            "type":"Services"
        }
    ],
    "sg:phone":"+1 478 552 8511",
    "sg:postcode":"31082",
    "sg:province":"GA",
    "wof:name":"Camp Spring Baptist Church",
    "wof:placetype":"venue"
},
  "geometry": {"coordinates":[-82.69468000000001,32.919697],"type":"Point"}
}