{
  "type": "Feature",
  "properties": {
    "iso:country":"US",
    "sg:address":"6646 Hawes Dr",
    "sg:city":"Lithonia",
    "sg:classifiers":[
        {
            "category":"Organizations",
            "subcategory":"Community Association",
            "type":"Services"
        }
    ],
    "sg:phone":"+1 770 484 4515",
    "sg:postcode":"30058",
    "sg:province":"GA",
    "wof:name":"Hawley Cove Home Owners Assn",
    "wof:placetype":"venue"
},
  "geometry": {"coordinates":[-84.116342,33.7113],"type":"Point"}
}