{
  "type": "Feature",
  "properties": {
    "addr:full":"811 N Court St Quitman GA 31643",
    "addr:housenumber":"811",
    "addr:postcode":"31643",
    "addr:street":"N Court St",
    "iso:country":"US",
    "sg:address":"811 N Court St",
    "sg:city":"Quitman",
    "sg:classifiers":[
        {
            "category":"Professional",
            "subcategory":"Computer Services",
            "type":"Services"
        }
    ],
    "sg:phone":"+1 229 263 8134",
    "sg:postcode":"31643",
    "sg:province":"GA",
    "sg:tags":[
        "datum"
    ],
    "wof:name":"Sunbelt Web Services",
    "wof:placetype":"venue"
},
  "geometry": {"coordinates":[-83.559498,30.794495],"type":"Point"}
}