{
  "type": "Feature",
  "properties": {
    "addr:full":"201 Lee Blvd Savannah GA 31405",
    "addr:housenumber":"201",
    "addr:postcode":"31405",
    "addr:street":"Lee Blvd",
    "iso:country":"US",
    "sg:address":"201 Lee Blvd",
    "sg:city":"Savannah",
    "sg:classifiers":[
        {
            "category":"Health Services",
            "subcategory":"Doctor",
            "type":"Services"
        }
    ],
    "sg:phone":"+1 912 355 2260",
    "sg:postcode":"31405",
    "sg:province":"GA",
    "sg:tags":[
        "medical"
    ],
    "wof:name":"Murphy H Jack Dr",
    "wof:placetype":"venue"
},
  "geometry": {"coordinates":[-81.10466,32.017801],"type":"Point"}
}