{
  "type": "Feature",
  "properties": {
    "iso:country":"US",
    "sg:address":"1710 Cumberland Point Dr",
    "sg:city":"Marietta",
    "sg:classifiers":[
        {
            "category":"Professional",
            "subcategory":"Business Services",
            "type":"Services"
        }
    ],
    "sg:phone":"+1 770 996 0256",
    "sg:postcode":"30067",
    "sg:province":"GA",
    "sg:tags":[
        "fund",
        "promotion",
        "raising"
    ],
    "wof:name":"B C Promotions",
    "wof:placetype":"venue"
},
  "geometry": {"coordinates":[-84.49253899999999,33.911605],"type":"Point"}
}