{
  "type": "Feature",
  "properties": {
    "addr:full":"224 Powers Ferry Rd Marietta GA 30067",
    "addr:housenumber":"224",
    "addr:postcode":"30067",
    "addr:street":"Powers Ferry Rd",
    "iso:country":"US",
    "sg:address":"224 Powers Ferry Rd",
    "sg:city":"Marietta",
    "sg:classifiers":[
        {
            "category":"Professional",
            "subcategory":"Art Services",
            "type":"Services"
        }
    ],
    "sg:phone":"+1 770 565 4422",
    "sg:postcode":"30067",
    "sg:province":"GA",
    "sg:tags":[
        "graphic",
        "design",
        "typesetting"
    ],
    "wof:name":"Penstroke Graphics",
    "wof:placetype":"venue"
},
  "geometry": {"coordinates":[-84.500812,33.947546],"type":"Point"}
}