{
  "type": "Feature",
  "properties": {
    "iso:country":"US",
    "sg:address":"4208 Northeast Expy",
    "sg:city":"Atlanta",
    "sg:classifiers":[
        {
            "category":"Professional",
            "subcategory":"Art Services",
            "type":"Services"
        },
        {
            "category":"Manufacturing",
            "subcategory":"Printing",
            "type":"Manufacturing & Wholesale Goods"
        }
    ],
    "sg:phone":"+1 770 457 6707",
    "sg:postcode":"30340",
    "sg:province":"GA",
    "sg:tags":[
        "designer",
        "graphic",
        "bureau",
        "processing"
    ],
    "wof:name":"Nuvision Graphics Inc",
    "wof:placetype":"venue"
},
  "geometry": {"coordinates":[-84.25265899999999,33.895901],"type":"Point"}
}