{
  "type": "Feature",
  "properties": {
    "addr:full":"1000 Parkwood Cir SE Atlanta GA 30339",
    "addr:housenumber":"1000",
    "addr:postcode":"30339",
    "addr:street":"Parkwood Cir Se",
    "iso:country":"US",
    "sg:address":"1000 Parkwood Cir SE",
    "sg:city":"Atlanta",
    "sg:classifiers":[
        {
            "category":"Professional",
            "subcategory":"Lawyer & Legal Services",
            "type":"Services"
        }
    ],
    "sg:phone":"+1 770 859 1660",
    "sg:postcode":"30339",
    "sg:province":"GA",
    "wof:name":"Curphey & Associates Lc William E",
    "wof:placetype":"venue"
},
  "geometry": {"coordinates":[-84.45963,33.903297],"type":"Point"}
}