{
  "type": "Feature",
  "properties": {
    "iso:country":"US",
    "sg:address":"315 Willow Wind Ct",
    "sg:city":"Roswell",
    "sg:classifiers":[
        {
            "category":"Professional",
            "subcategory":"Art Services",
            "type":"Services"
        }
    ],
    "sg:phone":"+1 770 641 8544",
    "sg:postcode":"30076",
    "sg:province":"GA",
    "sg:tags":[
        "commercial",
        "design"
    ],
    "wof:name":"Golf Graphics Inc",
    "wof:placetype":"venue"
},
  "geometry": {"coordinates":[-84.28539600000001,33.990702],"type":"Point"}
}