{
  "type": "Feature",
  "properties": {
    "iso:country":"US",
    "sg:address":"172 Colonial Dr",
    "sg:city":"Woodstock",
    "sg:classifiers":[
        {
            "category":"Manufacturing",
            "subcategory":"Metals",
            "type":"Manufacturing & Wholesale Goods"
        }
    ],
    "sg:phone":"+1 770 926 8695",
    "sg:postcode":"30189",
    "sg:province":"GA",
    "sg:tags":[
        "product",
        "wire",
        "fabricated",
        "mfg"
    ],
    "wof:name":"Max Wire Works Inc",
    "wof:placetype":"venue"
},
  "geometry": {"coordinates":[-84.56373499999999,34.135977],"type":"Point"}
}