{
  "type": "Feature",
  "properties": {
    "iso:country":"US",
    "sg:address":"1304 Hogansville Rd",
    "sg:city":"Lagrange",
    "sg:classifiers":[
        {
            "category":"Freight",
            "type":"Transportation"
        }
    ],
    "sg:phone":"+1 706 882 4648",
    "sg:postcode":"30241",
    "sg:province":"GA",
    "sg:tags":[
        "commercial",
        "storage"
    ],
    "wof:name":"Sentry Self Storage",
    "wof:placetype":"venue"
},
  "geometry": {"coordinates":[-84.99792600000001,33.055243],"type":"Point"}
}