{
  "type": "Feature",
  "properties": {
    "addr:full":"2153 Vineville Ave Macon GA 31204",
    "addr:housenumber":"2153",
    "addr:postcode":"31204",
    "addr:street":"Vineville Ave",
    "iso:country":"US",
    "sg:address":"2153 Vineville Ave",
    "sg:city":"Macon",
    "sg:classifiers":[
        {
            "category":"Professional",
            "subcategory":"Testing Lab",
            "type":"Services"
        }
    ],
    "sg:phone":"+1 478 745 6624",
    "sg:postcode":"31204",
    "sg:province":"GA",
    "sg:tags":[
        "laboratory"
    ],
    "sg:website":"www.sacalglobal.com",
    "wof:name":"Omega Analytical Laboratories",
    "wof:placetype":"venue"
},
  "geometry": {"coordinates":[-83.653914,32.844568],"type":"Point"}
}