{
  "type": "Feature",
  "properties": {
    "addr:full":"6425 Dahlonega Hwy Clermont GA 30527",
    "addr:housenumber":"6425",
    "addr:postcode":"30527",
    "addr:street":"Dahlonega Hwy",
    "iso:country":"US",
    "sg:address":"6425 Dahlonega Hwy",
    "sg:city":"Clermont",
    "sg:classifiers":[
        {
            "category":"Farming",
            "subcategory":"Nursery",
            "type":"Manufacturing & Wholesale Goods"
        }
    ],
    "sg:phone":"+1 770 983 0126",
    "sg:postcode":"30527",
    "sg:province":"GA",
    "sg:tags":[
        "growing",
        "stock"
    ],
    "wof:name":"Sweetwater Nursery Inc",
    "wof:placetype":"venue"
},
  "geometry": {"coordinates":[-83.847466,34.491796],"type":"Point"}
}