{
  "type": "Feature",
  "properties": {
    "addr:full":"4000 McGinnis Ferry Rd Suwanee GA 30024",
    "addr:postcode":"4000;30024",
    "addr:street":"Mcginnis Ferry Rd",
    "iso:country":"US",
    "sg:address":"4000 McGinnis Ferry Rd",
    "sg:city":"Suwanee",
    "sg:classifiers":[
        {
            "category":"Professional",
            "subcategory":"Advertising",
            "type":"Services"
        }
    ],
    "sg:phone":"+1 770 945 3007",
    "sg:postcode":"30024",
    "sg:province":"GA",
    "sg:tags":[
        "counselor"
    ],
    "wof:name":"M & R Advertising & Public",
    "wof:placetype":"venue"
},
  "geometry": {"coordinates":[-84.08834299999999,34.046268],"type":"Point"}
}