{
  "type": "Feature",
  "properties": {
    "iso:country":"US",
    "sg:address":"209 W Gordon Ave",
    "sg:city":"Rossville",
    "sg:classifiers":[
        {
            "category":"Restaurant",
            "type":"Food & Drink"
        }
    ],
    "sg:phone":"+1 706 858 0061",
    "sg:postcode":"30741",
    "sg:province":"GA",
    "sg:tags":[
        "eating"
    ],
    "wof:name":"Open Door Restaurant",
    "wof:placetype":"venue"
},
  "geometry": {"coordinates":[-85.289665,34.984068],"type":"Point"}
}