{
  "type": "Feature",
  "properties": {
    "iso:country":"US",
    "sg:address":"4335 Pinehollow Ct",
    "sg:city":"Alpharetta",
    "sg:classifiers":[
        {
            "category":"Manufacturing",
            "subcategory":"Printing",
            "type":"Manufacturing & Wholesale Goods"
        }
    ],
    "sg:phone":"+1 770 740 9803",
    "sg:postcode":"30022",
    "sg:province":"GA",
    "sg:tags":[
        "commercial",
        "offset"
    ],
    "wof:name":"Pbf Ink",
    "wof:placetype":"venue"
},
  "geometry": {"coordinates":[-84.23332499999999,34.042394],"type":"Point"}
}