{
  "type": "Feature",
  "properties": {
    "addr:full":"11997 S Main St Trenton GA 30752",
    "addr:housenumber":"11997",
    "addr:postcode":"30752",
    "addr:street":"S Main St",
    "iso:country":"US",
    "sg:address":"11997 S Main St",
    "sg:city":"Trenton",
    "sg:classifiers":[
        {
            "category":"Shopping",
            "subcategory":"Pharmacy",
            "type":"Retail Goods"
        }
    ],
    "sg:phone":"+1 706 657 8100",
    "sg:postcode":"30752",
    "sg:province":"GA",
    "wof:name":"Ponder Pharmacy",
    "wof:placetype":"venue"
},
  "geometry": {"coordinates":[-85.514933,34.864753],"type":"Point"}
}