{
  "type": "Feature",
  "properties": {
    "iso:country":"US",
    "sg:address":"424 W Bolton St",
    "sg:city":"Savannah",
    "sg:classifiers":[
        {
            "category":"Organizations",
            "subcategory":"Religious Organization",
            "type":"Services"
        }
    ],
    "sg:phone":"+1 912 234 4810",
    "sg:postcode":"31401",
    "sg:province":"GA",
    "wof:name":"Thankful Baptist Church",
    "wof:placetype":"venue"
},
  "geometry": {"coordinates":[-81.101872,32.067834],"type":"Point"}
}