{
  "type": "Feature",
  "properties": {
    "iso:country":"US",
    "sg:address":"900 Ashwood Pkwy",
    "sg:city":"Atlanta",
    "sg:classifiers":[
        {
            "category":"Personal",
            "subcategory":"Shoe Repair & Shine",
            "type":"Services"
        }
    ],
    "sg:phone":"+1 770 481 0601",
    "sg:postcode":"30338",
    "sg:province":"GA",
    "sg:tags":[
        "shining"
    ],
    "wof:name":"M F S",
    "wof:placetype":"venue"
},
  "geometry": {"coordinates":[-84.340259,33.933162],"type":"Point"}
}