{
  "type": "Feature",
  "properties": {
    "iso:country":"US",
    "sg:address":"2907 Yale Ct",
    "sg:city":"Atlanta",
    "sg:classifiers":[
        {
            "category":"Professional",
            "subcategory":"Business Services",
            "type":"Services"
        }
    ],
    "sg:phone":"+1 770 801 1861",
    "sg:postcode":"30339",
    "sg:province":"GA",
    "wof:name":"Peg Simms Interiors",
    "wof:placetype":"venue"
},
  "geometry": {"coordinates":[-84.46701,33.861499],"type":"Point"}
}