{
  "type": "Feature",
  "properties": {
    "addr:full":"10921 Hwy 36 Covington GA 30014",
    "addr:housenumber":"10921",
    "addr:postcode":"30014",
    "addr:street":"Hwy 36",
    "iso:country":"US",
    "sg:address":"10921 Hwy 36",
    "sg:city":"Covington",
    "sg:classifiers":[
        {
            "category":"Professional",
            "type":"Services"
        }
    ],
    "sg:phone":"+1 770 787 6012",
    "sg:postcode":"30014",
    "sg:province":"GA",
    "wof:name":"Kenneth Grindle",
    "wof:placetype":"venue"
},
  "geometry": {"coordinates":[-83.847544,33.552846],"type":"Point"}
}