{
  "type": "Feature",
  "properties": {
    "iso:country":"US",
    "sg:address":"5600 Claire Rose Ln",
    "sg:city":"Atlanta",
    "sg:classifiers":[
        {
            "category":"Manufacturing",
            "subcategory":"Printing",
            "type":"Manufacturing & Wholesale Goods"
        }
    ],
    "sg:phone":"+1 404 252 4012",
    "sg:postcode":"30327",
    "sg:province":"GA",
    "sg:tags":[
        "book",
        "publishing"
    ],
    "wof:name":"Michaels Mind LLC",
    "wof:placetype":"venue"
},
  "geometry": {"coordinates":[-84.402857,33.910363],"type":"Point"}
}