{
  "type": "Feature",
  "properties": {
    "addr:full":"1871 Woodpoint Ct Lawrenceville GA 30043",
    "addr:housenumber":"1871",
    "addr:postcode":"30043",
    "addr:street":"Woodpoint Ct",
    "iso:country":"US",
    "sg:address":"1871 Woodpoint Ct",
    "sg:city":"Lawrenceville",
    "sg:classifiers":[
        {
            "category":"Real Estate",
            "subcategory":"Real Estate Services",
            "type":"Services"
        }
    ],
    "sg:phone":"+1 770 237 9285",
    "sg:postcode":"30043",
    "sg:province":"GA",
    "sg:tags":[
        "vacancy",
        "rental",
        "listing"
    ],
    "wof:name":"Arnett Rental Pro",
    "wof:placetype":"venue"
},
  "geometry": {"coordinates":[-83.951431,34.026961],"type":"Point"}
}