{
  "type": "Feature",
  "properties": {
    "addr:full":"2675 N Columbia St Milledgeville GA 31061",
    "addr:housenumber":"2675",
    "addr:postcode":"31061",
    "addr:street":"N Columbia St",
    "iso:country":"US",
    "sg:address":"2675 N Columbia St",
    "sg:city":"Milledgeville",
    "sg:classifiers":[
        {
            "category":"Building & Trades",
            "subcategory":"Equipment Rental",
            "type":"Services"
        }
    ],
    "sg:phone":"+1 478 454 3093",
    "sg:postcode":"31061",
    "sg:province":"GA",
    "sg:tags":[
        "contractor"
    ],
    "wof:name":"A-1 U Rent",
    "wof:placetype":"venue"
},
  "geometry": {"coordinates":[-83.269194,33.136459],"type":"Point"}
}