{
  "type": "Feature",
  "properties": {
    "addr:full":"301 Fairmont Dr Norcross GA 30071",
    "addr:housenumber":"301",
    "addr:postcode":"30071",
    "addr:street":"Fairmont Dr",
    "iso:country":"US",
    "sg:address":"301 Fairmont Dr",
    "sg:city":"Norcross",
    "sg:classifiers":[
        {
            "category":"Professional",
            "subcategory":"Detective & Security Services",
            "type":"Services"
        },
        {
            "category":"Organizations",
            "subcategory":"Professional Association",
            "type":"Services"
        }
    ],
    "sg:phone":"+1 678 421 0119",
    "sg:postcode":"30071",
    "sg:province":"GA",
    "sg:tags":[
        "information",
        "bureau",
        "representative",
        "agent",
        "manufacturers'"
    ],
    "sg:website":"http://www.aloscuisine.com",
    "wof:name":"Alos",
    "wof:placetype":"venue"
},
  "geometry": {"coordinates":[-84.210309,33.936831],"type":"Point"}
}