{
  "type": "Feature",
  "properties": {
    "addr:full":"1394 Broadway Ave Braselton GA 30517",
    "addr:housenumber":"1394",
    "addr:postcode":"30517",
    "addr:street":"Broadway Ave",
    "iso:country":"US",
    "sg:address":"1394 Broadway Ave",
    "sg:city":"Braselton",
    "sg:classifiers":[
        {
            "category":"Autos & Motor Vehicles",
            "subcategory":"Automobile Sales",
            "type":"Retail Goods"
        }
    ],
    "sg:phone":"+1 706 658 2672",
    "sg:postcode":"30517",
    "sg:province":"GA",
    "sg:tags":[
        "performance",
        "race",
        "dealer"
    ],
    "sg:website":"www.gforceracing.net",
    "wof:name":"G Force",
    "wof:placetype":"venue"
},
  "geometry": {"coordinates":[-83.78312,34.103457],"type":"Point"}
}