{
  "type": "Feature",
  "properties": {
    "iso:country":"US",
    "sg:address":"3139 S Coastal Hwy",
    "sg:city":"Riceboro",
    "sg:classifiers":[
        {
            "category":"Transit Center",
            "subcategory":"Freight",
            "type":"Transportation"
        },
        {
            "category":"Freight",
            "type":"Transportation"
        }
    ],
    "sg:phone":"+1 912 663 1117",
    "sg:postcode":"31323",
    "sg:province":"GA",
    "sg:tags":[
        "local",
        "trucking-motor",
        "trucking"
    ],
    "wof:name":"Micheal W Trucking",
    "wof:placetype":"venue"
},
  "geometry": {"coordinates":[-81.44047399999999,31.75122],"type":"Point"}
}