{
  "type": "Feature",
  "properties": {
    "addr:full":"4525 Flat Shoals Pkwy Decatur GA 30034",
    "addr:housenumber":"4525",
    "addr:postcode":"30034",
    "addr:street":"Flat Shoals Pkwy",
    "iso:country":"US",
    "sg:address":"4525 Flat Shoals Pkwy",
    "sg:city":"Decatur",
    "sg:classifiers":[
        {
            "category":"Social Services",
            "subcategory":"Child Care",
            "type":"Services"
        }
    ],
    "sg:phone":"+1 404 244 5568",
    "sg:postcode":"30034",
    "sg:province":"GA",
    "sg:tags":[
        "day"
    ],
    "wof:name":"Kids Kollege",
    "wof:placetype":"venue"
},
  "geometry": {"coordinates":[-84.236008,33.683736],"type":"Point"}
}