{
  "type": "Feature",
  "properties": {
    "addr:full":"2299 Main St Tucker GA 30084",
    "addr:housenumber":"2299",
    "addr:postcode":"30084",
    "addr:street":"Main St",
    "iso:country":"US",
    "sg:address":"2299 Main St",
    "sg:city":"Tucker",
    "sg:classifiers":[
        {
            "category":"Restaurant",
            "type":"Food & Drink"
        }
    ],
    "sg:phone":"+1 770 939 2357",
    "sg:postcode":"30084",
    "sg:province":"GA",
    "sg:tags":[
        "southern"
    ],
    "sg:website":"www.matthewscafeteria.com",
    "wof:name":"Matthews Cafeteria",
    "wof:placetype":"venue"
},
  "geometry": {"coordinates":[-84.213651,33.85239],"type":"Point"}
}