{
  "type": "Feature",
  "properties": {
    "addr:full":"101 Cedar St Athens GA 30605",
    "addr:housenumber":"101",
    "addr:postcode":"30605",
    "addr:street":"Cedar St",
    "iso:country":"US",
    "sg:address":"101 Cedar St",
    "sg:city":"Athens",
    "sg:classifiers":[
        {
            "category":"Retail",
            "subcategory":"Repair Shop",
            "type":"Services"
        }
    ],
    "sg:phone":"+1 706 369 6627",
    "sg:postcode":"30605",
    "sg:province":"GA",
    "wof:name":"Nichols Casework Inc",
    "wof:placetype":"venue"
},
  "geometry": {"coordinates":[-83.371087,33.94533],"type":"Point"}
}