{
  "type": "Feature",
  "properties": {
    "iso:country":"US",
    "sg:address":"125 N Hill St",
    "sg:city":"Griffin",
    "sg:classifiers":[
        {
            "category":"Real Estate",
            "subcategory":"Real Estate Operator",
            "type":"Services"
        }
    ],
    "sg:phone":"+1 770 227 5634",
    "sg:postcode":"30223",
    "sg:province":"GA",
    "sg:tags":[
        "apartment"
    ],
    "sg:website":"http://www.hollbergproperties.com",
    "wof:name":"Hollberg Properties",
    "wof:placetype":"venue"
},
  "geometry": {"coordinates":[-84.263863,33.24956],"type":"Point"}
}