{
  "type": "Feature",
  "properties": {
    "addr:full":"921 Lawshe Rd Senoia GA 30276",
    "addr:housenumber":"921",
    "addr:postcode":"30276",
    "addr:street":"Lawshe Rd",
    "iso:country":"US",
    "sg:address":"921 Lawshe Rd",
    "sg:city":"Senoia",
    "sg:classifiers":[
        {
            "category":"Personal",
            "type":"Services"
        }
    ],
    "sg:phone":"+1 770 599 1420",
    "sg:postcode":"30276",
    "sg:province":"GA",
    "wof:name":"Buckys Home Improvement",
    "wof:placetype":"venue"
},
  "geometry": {"coordinates":[-84.595215,33.295949],"type":"Point"}
}