{
  "type": "Feature",
  "properties": {
    "iso:country":"US",
    "sg:address":"72 Alvah Brazzell Rd S",
    "sg:city":"Kingsland",
    "sg:classifiers":[
        {
            "category":"Building & Trades",
            "subcategory":"Construction",
            "type":"Services"
        }
    ],
    "sg:phone":"+1 912 729 3444",
    "sg:postcode":"31548",
    "sg:province":"GA",
    "sg:tags":[
        "nonresidential"
    ],
    "wof:name":"House Calls",
    "wof:placetype":"venue"
},
  "geometry": {"coordinates":[-81.665628,30.77183],"type":"Point"}
}