{
  "type": "Feature",
  "properties": {
    "addr:full":"412 Commerce St Hawkinsville GA 31036",
    "addr:housenumber":"412",
    "addr:postcode":"31036",
    "addr:street":"Commerce St",
    "iso:country":"US",
    "sg:address":"412 Commerce St",
    "sg:city":"Hawkinsville",
    "sg:classifiers":[
        {
            "category":"Health Services",
            "subcategory":"Doctor",
            "type":"Services"
        }
    ],
    "sg:phone":"+1 478 783 4060",
    "sg:postcode":"31036",
    "sg:province":"GA",
    "sg:tags":[
        "physician",
        "surgeon"
    ],
    "wof:name":"Hawkinsville Health Care Ctr",
    "wof:placetype":"venue"
},
  "geometry": {"coordinates":[-83.471881,32.283728],"type":"Point"}
}