{
  "type": "Feature",
  "properties": {
    "addr:full":"3505 Koger Blvd Ste 130 Duluth GA 30096",
    "addr:housenumber":"3505",
    "addr:postcode":"30096",
    "addr:street":"Koger Blvd Ste 130",
    "iso:country":"US",
    "sg:address":"3505 Koger Blvd Ste 130",
    "sg:city":"Duluth",
    "sg:classifiers":[
        {
            "category":"Structure",
            "subcategory":"Office Building",
            "type":"Public Place"
        }
    ],
    "sg:phone":"+1 770 458 7231",
    "sg:postcode":"30096",
    "sg:province":"GA",
    "sg:tags":[
        "park"
    ],
    "wof:name":"Dra Crt Gwinnett Center",
    "wof:placetype":"venue"
},
  "geometry": {"coordinates":[-84.122229,33.949298],"type":"Point"}
}