{
  "type": "Feature",
  "properties": {
    "addr:full":"1527 Madison Hwy Valdosta GA 31601",
    "addr:housenumber":"1527",
    "addr:postcode":"31601",
    "addr:street":"Madison Hwy",
    "iso:country":"US",
    "sg:address":"1527 Madison Hwy",
    "sg:city":"Valdosta",
    "sg:classifiers":[
        {
            "category":"Manufacturing",
            "subcategory":"Tools & Machinery",
            "type":"Manufacturing & Wholesale Goods"
        }
    ],
    "sg:phone":"+1 229 247 1101",
    "sg:postcode":"31601",
    "sg:province":"GA",
    "sg:tags":[
        "machine",
        "shop"
    ],
    "wof:name":"Southern Machine Shop",
    "wof:placetype":"venue"
},
  "geometry": {"coordinates":[-83.27443599999999,30.806192],"type":"Point"}
}