{
  "type": "Feature",
  "properties": {
    "iso:country":"US",
    "sg:address":"924 Kirkland Dr",
    "sg:city":"Columbus",
    "sg:classifiers":[
        {
            "category":"Retail",
            "subcategory":"Auto Repair",
            "type":"Services"
        }
    ],
    "sg:phone":"+1 706 689 3680",
    "sg:postcode":"31906",
    "sg:province":"GA",
    "wof:name":"Lewis Automotive",
    "wof:placetype":"venue"
},
  "geometry": {"coordinates":[-84.93182299999999,32.462951],"type":"Point"}
}