{
  "type": "Feature",
  "properties": {
    "addr:full":"1114 Maple Ridge Ct Evans GA 30809",
    "addr:housenumber":"1114",
    "addr:postcode":"30809",
    "addr:street":"Maple Ridge Ct",
    "iso:country":"US",
    "sg:address":"1114 Maple Ridge Ct",
    "sg:city":"Evans",
    "sg:classifiers":[
        {
            "category":"Wholesale",
            "subcategory":"Hardware",
            "type":"Manufacturing & Wholesale Goods"
        }
    ],
    "sg:phone":"+1 706 863 5005",
    "sg:postcode":"30809",
    "sg:province":"GA",
    "sg:tags":[
        "plumbing",
        "merchandise"
    ],
    "wof:name":"Electronic Air & Water Prfctn",
    "wof:placetype":"venue"
},
  "geometry": {"coordinates":[-82.14775400000001,33.579345],"type":"Point"}
}