{
  "type": "Feature",
  "properties": {
    "iso:country":"US",
    "sg:address":"2400 Commerce Ave Ste 500",
    "sg:city":"Duluth",
    "sg:classifiers":[
        {
            "category":"Professional",
            "subcategory":"Detective & Security Services",
            "type":"Services"
        },
        {
            "category":"Manufacturing",
            "subcategory":"Electronics",
            "type":"Manufacturing & Wholesale Goods"
        },
        {
            "category":"Shopping",
            "subcategory":"Computers & Home Electronics",
            "type":"Retail Goods"
        }
    ],
    "sg:phone":"+1 678 474 1720",
    "sg:postcode":"30096",
    "sg:province":"GA",
    "sg:tags":[
        "control",
        "monitoring",
        "equipment-wholesale",
        "system",
        "surveillance",
        "equipment",
        "manufacturer"
    ],
    "wof:name":"Securitas Systems",
    "wof:placetype":"venue"
},
  "geometry": {"coordinates":[-84.118431,33.96817],"type":"Point"}
}