{
  "type": "Feature",
  "properties": {
    "iso:country":"US",
    "sg:address":"4228 Carillon Trce NW",
    "sg:city":"Kennesaw",
    "sg:classifiers":[
        {
            "category":"Professional",
            "subcategory":"Computer Services",
            "type":"Services"
        }
    ],
    "sg:phone":"+1 770 420 0545",
    "sg:postcode":"30144",
    "sg:province":"GA",
    "sg:tags":[
        "control",
        "system",
        "automation",
        "engineering",
        "engineer",
        "software"
    ],
    "sg:website":"http://www.modelogics.com",
    "wof:name":"Modelogics Inc",
    "wof:placetype":"venue"
},
  "geometry": {"coordinates":[-84.62873399999999,34.053583],"type":"Point"}
}