{
  "type": "Feature",
  "properties": {
    "iso:country":"US",
    "sg:address":"5133 Highway 36",
    "sg:city":"Covington",
    "sg:phone":"+1 770 787 2220",
    "sg:postcode":"30014",
    "sg:province":"GA",
    "wof:name":"Covington First Ch Of Nazarene",
    "wof:placetype":"venue"
},
  "geometry": {"coordinates":[-83.855805,33.586416],"type":"Point"}
}