{
  "type": "Feature",
  "properties": {
    "iso:country":"US",
    "sg:address":"5000 Old Medlock Bridge Rd",
    "sg:city":"Johns Creek",
    "sg:classifiers":[
        {
            "category":"Building & Trades",
            "subcategory":"Landscaping Services",
            "type":"Services"
        }
    ],
    "sg:phone":"+1 404 826 9388",
    "sg:postcode":"30022",
    "sg:province":"GA",
    "sg:website":"www.lawnsprinklertech.com",
    "wof:name":"Lawn Sprinkler Tech",
    "wof:placetype":"venue"
},
  "geometry": {"coordinates":[-84.19643499999999,34.022893],"type":"Point"}
}