{
  "type": "Feature",
  "properties": {
    "addr:full":"500 Devonshire Farms Way Alpharetta GA 30004",
    "addr:housenumber":"500",
    "addr:postcode":"30004",
    "addr:street":"Devonshire Farms Way",
    "iso:country":"US",
    "sg:address":"500 Devonshire Farms Way",
    "sg:city":"Alpharetta",
    "sg:classifiers":[
        {
            "category":"Organizations",
            "subcategory":"Religious Organization",
            "type":"Services"
        }
    ],
    "sg:phone":"+1 770 752 0577",
    "sg:postcode":"30004",
    "sg:province":"GA",
    "wof:name":"New Millennium Church Inc",
    "wof:placetype":"venue"
},
  "geometry": {"coordinates":[-84.284761,34.123281],"type":"Point"}
}