{
  "type": "Feature",
  "properties": {
    "addr:full":"1013 Carl Vinson Pkwy Centerville GA 31028",
    "addr:housenumber":"1013",
    "addr:postcode":"31028",
    "addr:street":"Carl Vinson Pkwy",
    "iso:country":"US",
    "sg:address":"1013 Carl Vinson Pkwy",
    "sg:city":"Centerville",
    "sg:classifiers":[
        {
            "category":"Organizations",
            "subcategory":"Religious Organization",
            "type":"Services"
        }
    ],
    "sg:phone":"+1 478 923 9892",
    "sg:postcode":"31028",
    "sg:province":"GA",
    "wof:name":"Northside Baptist Church",
    "wof:placetype":"venue"
},
  "geometry": {"coordinates":[-83.660535,32.643665],"type":"Point"}
}