{
  "type": "Feature",
  "properties": {
    "addr:full":"610 McGarity Dr McDonough GA 30252",
    "addr:housenumber":"610",
    "addr:postcode":"30252",
    "addr:street":"Mcgarity Dr",
    "iso:country":"US",
    "sg:address":"610 McGarity Dr",
    "sg:city":"McDonough",
    "sg:classifiers":[
        {
            "category":"Professional",
            "subcategory":"Accounting & Tax Preparation",
            "type":"Services"
        }
    ],
    "sg:phone":"+1 770 898 6299",
    "sg:postcode":"30252",
    "sg:province":"GA",
    "sg:tags":[
        "accountant"
    ],
    "wof:name":"Garrison Billy W Financial Services",
    "wof:placetype":"venue"
},
  "geometry": {"coordinates":[-84.078102,33.4506],"type":"Point"}
}