{
  "type": "Feature",
  "properties": {
    "iso:country":"US",
    "sg:address":"412 SE Broad St",
    "sg:city":"Fairburn",
    "sg:classifiers":[
        {
            "category":"Wholesale",
            "subcategory":"Machinery & Supplies",
            "type":"Manufacturing & Wholesale Goods"
        },
        {
            "category":"Restaurant",
            "type":"Food & Drink"
        },
        {
            "category":"Home & Garden",
            "subcategory":"Kitchen Supply",
            "type":"Retail Goods"
        }
    ],
    "sg:phone":"+1 770 306 1959",
    "sg:postcode":"30213",
    "sg:province":"GA",
    "sg:tags":[
        "equipment-commercial",
        "supplies-refrigeration",
        "equipment",
        "industrial",
        "refrigeration"
    ],
    "wof:name":"Food Equip",
    "wof:placetype":"venue"
},
  "geometry": {"coordinates":[-84.588606,33.55916],"type":"Point"}
}