{
  "type": "Feature",
  "properties": {
    "iso:country":"US",
    "sg:address":"6084 Mableton Pkwy SW",
    "sg:city":"Mableton",
    "sg:classifiers":[
        {
            "category":"Autos & Motor Vehicles",
            "subcategory":"Auto Supplies",
            "type":"Retail Goods"
        }
    ],
    "sg:phone":"+1 770 745 9082",
    "sg:postcode":"30126",
    "sg:province":"GA",
    "sg:tags":[
        "tire"
    ],
    "wof:name":"Sonko Tires Surplus",
    "wof:placetype":"venue"
},
  "geometry": {"coordinates":[-84.569714,33.805485],"type":"Point"}
}