{
  "type": "Feature",
  "properties": {
    "iso:country":"US",
    "sg:address":"188 Brookwood Ave",
    "sg:city":"Jackson",
    "sg:classifiers":[
        {
            "category":"Retail",
            "subcategory":"Veterinary Services",
            "type":"Services"
        }
    ],
    "sg:phone":"+1 770 504 0853",
    "sg:postcode":"30233",
    "sg:province":"GA",
    "sg:tags":[
        "clinic",
        "veterinarian",
        "hospital"
    ],
    "wof:name":"Mathis, G DVM",
    "wof:placetype":"venue"
},
  "geometry": {"coordinates":[-83.974846,33.294775],"type":"Point"}
}