{
  "type": "Feature",
  "properties": {
    "iso:country":"US",
    "sg:address":"11 School St",
    "sg:city":"Watkinsville",
    "sg:classifiers":[
        {
            "category":"Professional",
            "subcategory":"Business Services",
            "type":"Services"
        }
    ],
    "sg:phone":"+1 706 310 1166",
    "sg:postcode":"30677",
    "sg:province":"GA",
    "sg:tags":[
        "paralegal"
    ],
    "wof:name":"Professional Paralegal Svc Inc",
    "wof:placetype":"venue"
},
  "geometry": {"coordinates":[-83.40790699999999,33.863592],"type":"Point"}
}