{
  "type": "Feature",
  "properties": {
    "iso:country":"US",
    "sg:address":"688 Highway 29 N",
    "sg:city":"Newnan",
    "sg:classifiers":[
        {
            "category":"Place Of Worship",
            "subcategory":"Church",
            "type":"Public Place"
        },
        {
            "category":"Place Of Worship",
            "type":"Public Place"
        }
    ],
    "sg:phone":"+1 770 252 2710",
    "sg:postcode":"30263",
    "sg:province":"GA",
    "sg:tags":[
        "testament",
        "christ-new",
        "churches-church",
        "christ"
    ],
    "wof:name":"All Souls Church Of God In Christ",
    "wof:placetype":"venue"
},
  "geometry": {"coordinates":[-84.79181800000001,33.402745],"type":"Point"}
}