{
  "type": "Feature",
  "properties": {
    "addr:full":"1135 Resaca Lafayette Rd NW Resaca GA 30735",
    "addr:housenumber":"1135",
    "addr:postcode":"resaca;30735",
    "addr:street":"Resaca;Rd Nw",
    "iso:country":"US",
    "sg:address":"1135 Resaca Lafayette Rd NW",
    "sg:city":"Resaca",
    "sg:classifiers":[
        {
            "category":"Food & Beverages",
            "subcategory":"Groceries & Convenience Stores",
            "type":"Retail Goods"
        }
    ],
    "sg:phone":"+1 706 629 9911",
    "sg:postcode":"30735",
    "sg:province":"GA",
    "wof:name":"ABC Convenience & Tobacco",
    "wof:placetype":"venue"
},
  "geometry": {"coordinates":[-84.97920499999999,34.572957],"type":"Point"}
}