{
  "type": "Feature",
  "properties": {
    "addr:full":"100 Southern Way Columbus GA 31904",
    "addr:housenumber":"100",
    "addr:postcode":"31904",
    "addr:street":"Southern Way",
    "iso:country":"US",
    "sg:address":"100 Southern Way",
    "sg:city":"Columbus",
    "sg:classifiers":[
        {
            "category":"Health Services",
            "subcategory":"Hospital",
            "type":"Services"
        }
    ],
    "sg:phone":"+1 706 324 1934",
    "sg:postcode":"31904",
    "sg:province":"GA",
    "sg:tags":[
        "general"
    ],
    "wof:name":"HealthSouth",
    "wof:placetype":"venue"
},
  "geometry": {"coordinates":[-84.963661,32.533605],"type":"Point"}
}