{
  "type": "Feature",
  "properties": {
    "iso:country":"US",
    "sg:address":"3527 Community Rd",
    "sg:city":"Brunswick",
    "sg:classifiers":[
        {
            "category":"Restaurant",
            "type":"Food & Drink"
        }
    ],
    "sg:phone":"+1 912 264 4644",
    "sg:postcode":"31520",
    "sg:province":"GA",
    "sg:tags":[
        "eating"
    ],
    "wof:name":"Steaks To Go & More",
    "wof:placetype":"venue"
},
  "geometry": {"coordinates":[-81.496989,31.203148],"type":"Point"}
}