{
  "type": "Feature",
  "properties": {
    "addr:full":"1001 Piedmont Ave NE Atlanta GA 30309",
    "addr:housenumber":"1001",
    "addr:postcode":"30309",
    "addr:street":"Piedmont Ave Ne",
    "iso:country":"US",
    "sg:address":"1001 Piedmont Ave NE",
    "sg:city":"Atlanta",
    "sg:classifiers":[
        {
            "category":"Ice Cream",
            "type":"Food & Drink"
        }
    ],
    "sg:phone":"+1 404 815 9935",
    "sg:postcode":"30309",
    "sg:province":"GA",
    "sg:tags":[
        "frozen",
        "dessert"
    ],
    "wof:name":"Repicci's Italian Ice",
    "wof:placetype":"venue"
},
  "geometry": {"coordinates":[-84.38042,33.781846],"type":"Point"}
}