{
  "type": "Feature",
  "properties": {
    "iso:country":"US",
    "sg:address":"31 Dundee Pl",
    "sg:city":"Sharpsburg",
    "sg:classifiers":[
        {
            "category":"Building & Trades",
            "subcategory":"Construction",
            "type":"Services"
        }
    ],
    "sg:phone":"+1 770 463 4767",
    "sg:postcode":"30277",
    "sg:province":"GA",
    "sg:tags":[
        "house"
    ],
    "wof:name":"Beluk Construction",
    "wof:placetype":"venue"
},
  "geometry": {"coordinates":[-84.632698,33.458717],"type":"Point"}
}