{
  "type": "Feature",
  "properties": {
    "addr:full":"220 Buckland Run Alpharetta GA 30004",
    "addr:housenumber":"220",
    "addr:postcode":"30004",
    "addr:street":"Buckland Run",
    "iso:country":"US",
    "sg:address":"220 Buckland Run",
    "sg:city":"Alpharetta",
    "sg:classifiers":[
        {
            "category":"Professional",
            "subcategory":"Business Services",
            "type":"Services"
        }
    ],
    "sg:phone":"+1 770 752 5564",
    "sg:postcode":"30004",
    "sg:province":"GA",
    "wof:name":"World Inspection Network",
    "wof:placetype":"venue"
},
  "geometry": {"coordinates":[-84.36790499999999,34.108398],"type":"Point"}
}