{
  "type": "Feature",
  "properties": {
    "iso:country":"US",
    "sg:address":"200 Vaughn Rd",
    "sg:city":"Rome",
    "sg:classifiers":[
        {
            "category":"Government",
            "subcategory":"Office",
            "type":"Public Place"
        }
    ],
    "sg:phone":"+1 706 236 4580",
    "sg:postcode":"30161",
    "sg:province":"GA",
    "sg:tags":[
        "city",
        "program"
    ],
    "wof:name":"Solid Waste Collections",
    "wof:placetype":"venue"
},
  "geometry": {"coordinates":[-85.162268,34.267829],"type":"Point"}
}