{
  "type": "Feature",
  "properties": {
    "iso:country":"US",
    "sg:address":"2306 Milledgeville Rd",
    "sg:city":"Augusta",
    "sg:classifiers":[
        {
            "category":"Wholesale",
            "subcategory":"Hardware",
            "type":"Manufacturing & Wholesale Goods"
        }
    ],
    "sg:phone":"+1 706 733 6553",
    "sg:postcode":"30904",
    "sg:province":"GA",
    "sg:tags":[
        "plumbing",
        "supply"
    ],
    "wof:name":"Interstate Supply Company Inc",
    "wof:placetype":"venue"
},
  "geometry": {"coordinates":[-82.007865,33.447469],"type":"Point"}
}