{
  "type": "Feature",
  "properties": {
    "addr:full":"62 Burke St Marietta GA 30060",
    "addr:housenumber":"62",
    "addr:postcode":"30060",
    "addr:street":"Burke St",
    "iso:country":"US",
    "sg:address":"62 Burke St",
    "sg:city":"Marietta",
    "sg:classifiers":[
        {
            "category":"Freight",
            "type":"Transportation"
        }
    ],
    "sg:phone":"+1 770 419 9333",
    "sg:postcode":"30060",
    "sg:province":"GA",
    "wof:name":"Vitran Logistics Corp",
    "wof:placetype":"venue"
},
  "geometry": {"coordinates":[-84.550071,33.91051],"type":"Point"}
}