{
  "type": "Feature",
  "properties": {
    "iso:country":"US",
    "sg:address":"748 Marietta St NW",
    "sg:city":"Atlanta",
    "sg:classifiers":[
        {
            "category":"Shopping",
            "subcategory":"Books",
            "type":"Retail Goods"
        }
    ],
    "sg:phone":"+1 404 221 1669",
    "sg:postcode":"30318",
    "sg:province":"GA",
    "sg:tags":[
        "bookstore"
    ],
    "sg:website":"www.engrbookstore.com",
    "wof:name":"Engineer's Bookstore",
    "wof:placetype":"venue"
},
  "geometry": {"coordinates":[-84.403702,33.773399],"type":"Point"}
}