{
  "type": "Feature",
  "properties": {
    "iso:country":"US",
    "sg:address":"3888 Pio Nono Ave",
    "sg:city":"Macon",
    "sg:classifiers":[
        {
            "category":"Personal",
            "subcategory":"Nail Salon",
            "type":"Services"
        }
    ],
    "sg:phone":"+1 478 785 2279",
    "sg:postcode":"31206",
    "sg:province":"GA",
    "wof:name":"Judy's Nail Salon",
    "wof:placetype":"venue"
},
  "geometry": {"coordinates":[-83.668194,32.793472],"type":"Point"}
}