{
  "type": "Feature",
  "properties": {
    "iso:country":"US",
    "sg:address":"108 Ga Highway 32 W",
    "sg:city":"Leesburg",
    "sg:classifiers":[
        {
            "category":"Shopping",
            "subcategory":"Florist",
            "type":"Retail Goods"
        }
    ],
    "sg:phone":"+1 229 759 6900",
    "sg:postcode":"31763",
    "sg:province":"GA",
    "wof:name":"Leesburg Flower & Gift Shop",
    "wof:placetype":"venue"
},
  "geometry": {"coordinates":[-84.17774300000001,31.721467],"type":"Point"}
}