{
  "type": "Feature",
  "properties": {
    "iso:country":"US",
    "sg:address":"1847 State Rte 15",
    "sg:city":"Sandersville",
    "sg:classifiers":[
        {
            "category":"Retail",
            "subcategory":"Portrait Studio",
            "type":"Services"
        }
    ],
    "sg:phone":"+1 478 552 9672",
    "sg:postcode":"31082",
    "sg:province":"GA",
    "sg:tags":[
        "photo"
    ],
    "wof:name":"Jo Still Photography",
    "wof:placetype":"venue"
},
  "geometry": {"coordinates":[-82.78658799999999,33.021],"type":"Point"}
}