{
  "type": "Feature",
  "properties": {
    "addr:full":"3248 Chamblee Dunwoody Rd Atlanta GA 30341",
    "addr:housenumber":"3248",
    "addr:postcode":"30341",
    "addr:street":"Chamblee Dunwoody Rd",
    "iso:country":"US",
    "sg:address":"3248 Chamblee Dunwoody Rd",
    "sg:city":"Atlanta",
    "sg:classifiers":[
        {
            "category":"Shopping",
            "subcategory":"Discount & Variety Stores",
            "type":"Retail Goods"
        }
    ],
    "sg:phone":"+1 770 457 6562",
    "sg:postcode":"30341",
    "sg:province":"GA",
    "sg:tags":[
        "merchandise",
        "general"
    ],
    "wof:name":"Luciano Garcia Inc",
    "wof:placetype":"venue"
},
  "geometry": {"coordinates":[-84.29131099999999,33.891482],"type":"Point"}
}