{
  "type": "Feature",
  "properties": {
    "addr:full":"3030 Alta Ridge Way Snellville GA 30078",
    "addr:housenumber":"3030",
    "addr:postcode":"30078",
    "addr:street":"Alta Ridge Way",
    "iso:country":"US",
    "sg:address":"3030 Alta Ridge Way",
    "sg:city":"Snellville",
    "sg:classifiers":[
        {
            "category":"Manufacturing",
            "subcategory":"Metals",
            "type":"Manufacturing & Wholesale Goods"
        }
    ],
    "sg:phone":"+1 770 736 1118",
    "sg:postcode":"30078",
    "sg:province":"GA",
    "sg:tags":[
        "plating"
    ],
    "wof:name":"Custom Plating Co",
    "wof:placetype":"venue"
},
  "geometry": {"coordinates":[-83.972598,33.85283],"type":"Point"}
}