{
  "type": "Feature",
  "properties": {
    "iso:country":"US",
    "sg:address":"702 Lumpkin Campground Rd N",
    "sg:city":"Dawsonville",
    "sg:classifiers":[
        {
            "category":"Real Estate",
            "subcategory":"Real Estate Agent",
            "type":"Services"
        }
    ],
    "sg:phone":"+1 706 216 2094",
    "sg:postcode":"30534",
    "sg:province":"GA",
    "wof:name":"Byrd Appraisal Service",
    "wof:placetype":"venue"
},
  "geometry": {"coordinates":[-84.033485,34.375119],"type":"Point"}
}