{
  "type": "Feature",
  "properties": {
    "iso:country":"US",
    "sg:address":"500 Atlnta Cntry Clb Dr",
    "sg:city":"Marietta",
    "sg:classifiers":[
        {
            "category":"Shopping",
            "subcategory":"Bicycles & Sporting Goods",
            "type":"Retail Goods"
        },
        {
            "category":"Sports & Exercise",
            "subcategory":"Golf",
            "type":"Entertainment"
        }
    ],
    "sg:phone":"+1 770 984 2543",
    "sg:postcode":"30067",
    "sg:province":"GA",
    "wof:name":"Atlanta Country Club",
    "wof:placetype":"venue"
},
  "geometry": {"coordinates":[-84.421997,33.937401],"type":"Point"}
}