{
  "type": "Feature",
  "properties": {
    "iso:country":"US",
    "sg:address":"2904 Brockton Loop",
    "sg:city":"Jefferson",
    "sg:classifiers":[
        {
            "category":"Farming",
            "subcategory":"Livestock Farm",
            "type":"Manufacturing & Wholesale Goods"
        }
    ],
    "sg:phone":"+1 706 367 7400",
    "sg:postcode":"30549",
    "sg:province":"GA",
    "sg:tags":[
        "equine"
    ],
    "wof:name":"Road Apple Ranch",
    "wof:placetype":"venue"
},
  "geometry": {"coordinates":[-83.49942299999999,34.092779],"type":"Point"}
}