{
  "type": "Feature",
  "properties": {
    "iso:country":"US",
    "sg:address":"9920 Bankside Dr",
    "sg:city":"Roswell",
    "sg:classifiers":[
        {
            "category":"Wholesale",
            "subcategory":"Non-durable Goods",
            "type":"Manufacturing & Wholesale Goods"
        }
    ],
    "sg:phone":"+1 770 663 4852",
    "sg:postcode":"30076",
    "sg:province":"GA",
    "sg:tags":[
        "bag",
        "travel",
        "golf"
    ],
    "wof:name":"Golf Travel Bags",
    "wof:placetype":"venue"
},
  "geometry": {"coordinates":[-84.277581,34.024167],"type":"Point"}
}