{
  "type": "Feature",
  "properties": {
    "addr:full":"4925 13th Ave Columbus GA 31904",
    "addr:housenumber":"4925",
    "addr:postcode":"31904",
    "addr:street":"13Th Ave",
    "iso:country":"US",
    "sg:address":"4925 13th Ave",
    "sg:city":"Columbus",
    "sg:phone":"+1 706 563 3763",
    "sg:postcode":"31904",
    "sg:province":"GA",
    "sg:website":"http://www.davojrtowingautorepairs.net",
    "wof:name":"Davo Jr Automotive 24/7 Wrecker Service",
    "wof:placetype":"venue"
},
  "geometry": {"coordinates":[-84.97197799999999,32.512106],"type":"Point"}
}