{
  "type": "Feature",
  "properties": {
    "iso:country":"US",
    "sg:address":"400 Ernest W Barrett Pkwy",
    "sg:city":"Kennesaw",
    "sg:classifiers":[
        {
            "category":"Shopping",
            "subcategory":"Gifts & Souvenirs",
            "type":"Retail Goods"
        }
    ],
    "sg:phone":"+1 770 426 5604",
    "sg:postcode":"30144",
    "sg:province":"GA",
    "sg:tags":[
        "business"
    ],
    "wof:name":"Things Remembered",
    "wof:placetype":"venue"
},
  "geometry": {"coordinates":[-84.56442199999999,34.011907],"type":"Point"}
}