{
  "type": "Feature",
  "properties": {
    "addr:full":"11120 Indian Village Dr Alpharetta GA 30022",
    "addr:housenumber":"11120",
    "addr:postcode":"30022",
    "addr:street":"Indian Village Dr",
    "iso:country":"US",
    "sg:address":"11120 Indian Village Dr",
    "sg:city":"Alpharetta",
    "sg:classifiers":[
        {
            "category":"Farming",
            "subcategory":"Farm & Veterinary Services",
            "type":"Manufacturing & Wholesale Goods"
        }
    ],
    "sg:phone":"+1 770 619 9997",
    "sg:postcode":"30022",
    "sg:province":"GA",
    "sg:tags":[
        "control",
        "weed"
    ],
    "wof:name":"Weed Pro",
    "wof:placetype":"venue"
},
  "geometry": {"coordinates":[-84.228515,34.051303],"type":"Point"}
}