{
  "type": "Feature",
  "properties": {
    "iso:country":"US",
    "sg:address":"216 3rd St SW",
    "sg:city":"Cairo",
    "sg:classifiers":[
        {
            "category":"Place Of Worship",
            "subcategory":"Church",
            "type":"Public Place"
        },
        {
            "category":"Place Of Worship",
            "type":"Public Place"
        }
    ],
    "sg:phone":"+1 229 377 8520",
    "sg:postcode":"39828",
    "sg:province":"GA",
    "sg:tags":[
        "churches-baptist-general",
        "churches-baptist"
    ],
    "wof:name":"Greater New Corinth Missionary Baptist Church",
    "wof:placetype":"venue"
},
  "geometry": {"coordinates":[-84.21381,30.874408],"type":"Point"}
}