{
  "type": "Feature",
  "properties": {
    "iso:country":"US",
    "sg:address":"2229 Runnymead Ridge SE",
    "sg:city":"Marietta",
    "sg:classifiers":[
        {
            "category":"Personal",
            "type":"Services"
        }
    ],
    "sg:phone":"+1 770 378 2329",
    "sg:postcode":"30067",
    "sg:province":"GA",
    "wof:name":"Bionics Services",
    "wof:placetype":"venue"
},
  "geometry": {"coordinates":[-84.478916,33.929899],"type":"Point"}
}