{
  "type": "Feature",
  "properties": {
    "iso:country":"US",
    "sg:address":"120 W Bay St",
    "sg:city":"Savannah",
    "sg:classifiers":[
        {
            "category":"Organizations",
            "subcategory":"Non-profit Organization",
            "type":"Services"
        }
    ],
    "sg:phone":"+1 912 238 3388",
    "sg:postcode":"31401",
    "sg:province":"GA",
    "sg:tags":[
        "social"
    ],
    "wof:name":"American Business Corp LLC",
    "wof:placetype":"venue"
},
  "geometry": {"coordinates":[-81.09253699999999,32.0813],"type":"Point"}
}