{
  "type": "Feature",
  "properties": {
    "addr:full":"333 Cotton Ave Macon GA 31201",
    "addr:housenumber":"333",
    "addr:postcode":"31201",
    "addr:street":"Cotton Ave",
    "iso:country":"US",
    "sg:address":"333 Cotton Ave",
    "sg:city":"Macon",
    "sg:classifiers":[
        {
            "category":"Real Estate",
            "subcategory":"Real Estate Agent",
            "type":"Services"
        }
    ],
    "sg:phone":"+1 478 746 0286",
    "sg:postcode":"31201",
    "sg:province":"GA",
    "wof:name":"Bill Hardeman Realty Co",
    "wof:placetype":"venue"
},
  "geometry": {"coordinates":[-83.628444,32.837659],"type":"Point"}
}