{
  "type": "Feature",
  "properties": {
    "iso:country":"US",
    "sg:address":"3865 Holcomb Bridge Rd",
    "sg:city":"Norcross",
    "sg:classifiers":[
        {
            "category":"Wholesale",
            "subcategory":"Painting Supplies",
            "type":"Manufacturing & Wholesale Goods"
        }
    ],
    "sg:phone":"+1 770 662 8112",
    "sg:postcode":"30092",
    "sg:province":"GA",
    "sg:tags":[
        "hardware",
        "home",
        "improvement"
    ],
    "sg:website":"www.salesmanagers.com",
    "wof:name":"Sales Managers Inc",
    "wof:placetype":"venue"
},
  "geometry": {"coordinates":[-84.253744,33.965022],"type":"Point"}
}