{
  "type": "Feature",
  "properties": {
    "iso:country":"US",
    "sg:address":"1139 Hubbard St SW",
    "sg:city":"Atlanta",
    "sg:classifiers":[
        {
            "category":"Professional",
            "subcategory":"Engineering",
            "type":"Services"
        }
    ],
    "sg:phone":"+1 404 614 0742",
    "sg:postcode":"30310",
    "sg:province":"GA",
    "wof:name":"People Reaching Out Helping Pe",
    "wof:placetype":"venue"
},
  "geometry": {"coordinates":[-84.40250899999999,33.723367],"type":"Point"}
}