{
  "type": "Feature",
  "properties": {
    "iso:country":"US",
    "sg:address":"3428 Kenland Rd",
    "sg:city":"Smyrna",
    "sg:classifiers":[
        {
            "category":"Building & Trades",
            "subcategory":"Electrical",
            "type":"Services"
        }
    ],
    "sg:phone":"+1 770 436 8615",
    "sg:postcode":"30082",
    "sg:province":"GA",
    "sg:tags":[
        "electrical",
        "electric",
        "contractor"
    ],
    "wof:name":"Mc Cord Electric Inc",
    "wof:placetype":"venue"
},
  "geometry": {"coordinates":[-84.54155,33.871024],"type":"Point"}
}