{
  "type": "Feature",
  "properties": {
    "addr:full":"5100 Annistown Rd Stone Mountain GA 30087",
    "addr:housenumber":"5100",
    "addr:postcode":"30087",
    "addr:street":"Annistown Rd",
    "iso:country":"US",
    "sg:address":"5100 Annistown Rd",
    "sg:city":"Stone Mountain",
    "sg:classifiers":[
        {
            "category":"Retail",
            "subcategory":"Laundry & Dry Cleaning",
            "type":"Services"
        }
    ],
    "sg:phone":"+1 770 879 6481",
    "sg:postcode":"30087",
    "sg:province":"GA",
    "wof:name":"Cachet Classic Cleaners",
    "wof:placetype":"venue"
},
  "geometry": {"coordinates":[-84.09279600000001,33.806801],"type":"Point"}
}