{
  "type": "Feature",
  "properties": {
    "addr:full":"4745 Ashford Dunwoody Rd Atlanta GA 30338",
    "addr:housenumber":"4745",
    "addr:postcode":"30338",
    "addr:street":"Ashford Dunwoody Rd",
    "iso:country":"US",
    "sg:address":"4745 Ashford Dunwoody Rd",
    "sg:city":"Atlanta",
    "sg:classifiers":[
        {
            "category":"Shopping",
            "subcategory":"Clothing, Apparel, & Fashions",
            "type":"Retail Goods"
        },
        {
            "category":"Retail",
            "subcategory":"Laundry & Dry Cleaning",
            "type":"Services"
        }
    ],
    "sg:phone":"+1 770 394 4885",
    "sg:postcode":"30338",
    "sg:province":"GA",
    "sg:tags":[
        "costumes-renting",
        "costume"
    ],
    "wof:name":"Halloween Express",
    "wof:placetype":"venue"
},
  "geometry": {"coordinates":[-84.337591,33.933462],"type":"Point"}
}