{
  "type": "Feature",
  "properties": {
    "addr:full":"1841 Ga Highway 90 S Cordele GA 31015",
    "addr:housenumber":"1841",
    "addr:postcode":"31015",
    "addr:street":"Ga Highway 90 S",
    "iso:country":"US",
    "sg:address":"1841 Ga Highway 90 S",
    "sg:city":"Cordele",
    "sg:classifiers":[
        {
            "category":"Banks & Credit Unions",
            "subcategory":"Investment Brokerage",
            "type":"Services"
        }
    ],
    "sg:phone":"+1 229 273 7237",
    "sg:postcode":"31015",
    "sg:province":"GA",
    "sg:tags":[
        "advisory"
    ],
    "wof:name":"Outlaw Investments",
    "wof:placetype":"venue"
},
  "geometry": {"coordinates":[-83.729219,31.933552],"type":"Point"}
}