{
  "type": "Feature",
  "properties": {
    "iso:country":"US",
    "sg:address":"3552 Panola Rd",
    "sg:city":"Lithonia",
    "sg:classifiers":[
        {
            "category":"Retail",
            "subcategory":"Laundry & Dry Cleaning",
            "type":"Services"
        }
    ],
    "sg:phone":"+1 770 987 4749",
    "sg:postcode":"30038",
    "sg:province":"GA",
    "wof:name":"Esquire Cleaners",
    "wof:placetype":"venue"
},
  "geometry": {"coordinates":[-84.17600299999999,33.681599],"type":"Point"}
}