{
  "type": "Feature",
  "properties": {
    "iso:country":"US",
    "sg:address":"291 Jarvis St",
    "sg:city":"Canton",
    "sg:classifiers":[
        {
            "category":"Professional",
            "subcategory":"Lawyer & Legal Services",
            "type":"Services"
        }
    ],
    "sg:phone":"+1 404 307 8233",
    "sg:postcode":"30114",
    "sg:province":"GA",
    "sg:tags":[
        "litigation"
    ],
    "wof:name":"Law Offices of Martin A. Lively, P.C.",
    "wof:placetype":"venue"
},
  "geometry": {"coordinates":[-84.486671,34.235379],"type":"Point"}
}