{
  "type": "Feature",
  "properties": {
    "iso:country":"US",
    "sg:address":"5000 Olde Towne Parkway Suite 100",
    "sg:city":"Marietta",
    "sg:classifiers":[
        {
            "category":"Professional",
            "subcategory":"Computer Services",
            "type":"Services"
        }
    ],
    "sg:phone":"+1 877 769 2388",
    "sg:postcode":"30068",
    "sg:province":"GA",
    "sg:website":"http://www.evestmentalliance.com/",
    "wof:name":"eVestment Alliance",
    "wof:placetype":"venue"
},
  "geometry": {"coordinates":[-84.41294600000001,33.969308],"type":"Point"}
}