{
  "type": "Feature",
  "properties": {
    "addr:full":"4515 Hartley Bridge Rd Macon GA 31216",
    "addr:housenumber":"4515",
    "addr:postcode":"31216",
    "addr:street":"Hartley Bridge Rd",
    "iso:country":"US",
    "sg:address":"4515 Hartley Bridge Rd",
    "sg:city":"Macon",
    "sg:classifiers":[
        {
            "category":"Restaurant",
            "type":"Food & Drink"
        }
    ],
    "sg:menulink":"http://www.allmenus.com/ga/lizella/140614-waffle-house/menu/",
    "sg:phone":"+1 478 781 7208",
    "sg:postcode":"31216",
    "sg:province":"GA",
    "sg:tags":[
        "american"
    ],
    "wof:name":"Waffle House",
    "wof:placetype":"venue"
},
  "geometry": {"coordinates":[-83.71994100000001,32.745076],"type":"Point"}
}