{
  "type": "Feature",
  "properties": {
    "addr:full":"1107 Memorial Dr Dalton GA 30720",
    "addr:housenumber":"1107",
    "addr:postcode":"30720",
    "addr:street":"Memorial Dr",
    "iso:country":"US",
    "sg:address":"1107 Memorial Dr",
    "sg:city":"Dalton",
    "sg:classifiers":[
        {
            "category":"Health Services",
            "subcategory":"Doctor",
            "type":"Services"
        }
    ],
    "sg:phone":"+1 706 278 5344",
    "sg:postcode":"30720",
    "sg:province":"GA",
    "wof:name":"Parham Dmdms Phillip L",
    "wof:placetype":"venue"
},
  "geometry": {"coordinates":[-84.981281,34.789041],"type":"Point"}
}