{
  "type": "Feature",
  "properties": {
    "addr:full":"111 Freeman St Tallapoosa GA 30176",
    "addr:housenumber":"111",
    "addr:postcode":"30176",
    "addr:street":"Freeman St",
    "iso:country":"US",
    "sg:address":"111 Freeman St",
    "sg:city":"Tallapoosa",
    "sg:classifiers":[
        {
            "category":"Personal",
            "subcategory":"Beauty Salon",
            "type":"Services"
        }
    ],
    "sg:phone":"+1 770 574 2814",
    "sg:postcode":"30176",
    "sg:province":"GA",
    "wof:name":"Sizzor Wizzard",
    "wof:placetype":"venue"
},
  "geometry": {"coordinates":[-85.286248,33.746775],"type":"Point"}
}