{
  "type": "Feature",
  "properties": {
    "iso:country":"US",
    "sg:address":"4159 Wheeler Rd",
    "sg:city":"Augusta",
    "sg:classifiers":[
        {
            "category":"Professional",
            "type":"Services"
        }
    ],
    "sg:phone":"+1 706 860 7822",
    "sg:postcode":"30907",
    "sg:province":"GA",
    "wof:name":"Tna Transco",
    "wof:placetype":"venue"
},
  "geometry": {"coordinates":[-82.108451,33.488496],"type":"Point"}
}