{
  "type": "Feature",
  "properties": {
    "iso:country":"US",
    "sg:address":"133 E Main St",
    "sg:city":"Manchester",
    "sg:classifiers":[
        {
            "category":"Professional",
            "subcategory":"Lawyer & Legal Services",
            "type":"Services"
        }
    ],
    "sg:phone":"+1 706 846 8427",
    "sg:postcode":"31816",
    "sg:province":"GA",
    "sg:tags":[
        "attorney"
    ],
    "wof:name":"David J Turner Jr",
    "wof:placetype":"venue"
},
  "geometry": {"coordinates":[-84.607709,32.850479],"type":"Point"}
}