{
  "type": "Feature",
  "properties": {
    "addr:full":"2845 Hitchcock Mill Run Marietta GA 30068",
    "addr:housenumber":"2845",
    "addr:postcode":"30068",
    "addr:street":"Hitchcock Mill Run",
    "iso:country":"US",
    "sg:address":"2845 Hitchcock Mill Run",
    "sg:city":"Marietta",
    "sg:classifiers":[
        {
            "category":"Shopping",
            "subcategory":"Bicycles & Sporting Goods",
            "type":"Retail Goods"
        }
    ],
    "sg:phone":"+1 770 566 0081",
    "sg:postcode":"30068",
    "sg:province":"GA",
    "wof:name":"FLB Online Enterprises",
    "wof:placetype":"venue"
},
  "geometry": {"coordinates":[-84.469444,33.961994],"type":"Point"}
}