{
  "type": "Feature",
  "properties": {
    "iso:country":"US",
    "sg:address":"8380 Grady St Ste A",
    "sg:city":"Douglasville",
    "sg:classifiers":[
        {
            "category":"Building & Trades",
            "subcategory":"Construction",
            "type":"Services"
        }
    ],
    "sg:phone":"+1 770 949 5577",
    "sg:postcode":"30134",
    "sg:province":"GA",
    "sg:tags":[
        "contractor"
    ],
    "wof:name":"Titleist Building Systems",
    "wof:placetype":"venue"
},
  "geometry": {"coordinates":[-84.738569,33.752216],"type":"Point"}
}