{
  "type": "Feature",
  "properties": {
    "iso:country":"US",
    "sg:address":"1141 Gresham Rd",
    "sg:city":"Good Hope",
    "sg:classifiers":[
        {
            "category":"Wholesale",
            "subcategory":"Chemicals & Plastics",
            "type":"Manufacturing & Wholesale Goods"
        }
    ],
    "sg:phone":"+1 706 342 4434",
    "sg:postcode":"30641",
    "sg:province":"GA",
    "sg:website":"www.madisonchem.com",
    "wof:name":"Madison Chemical Co",
    "wof:placetype":"venue"
},
  "geometry": {"coordinates":[-83.562574,33.733455],"type":"Point"}
}