{
  "type": "Feature",
  "properties": {
    "addr:full":"411 S Greenwood St Lagrange GA 30240",
    "addr:housenumber":"411",
    "addr:postcode":"30240",
    "addr:street":"S Greenwood St",
    "iso:country":"US",
    "sg:address":"411 S Greenwood St",
    "sg:city":"Lagrange",
    "sg:classifiers":[
        {
            "category":"Health Services",
            "subcategory":"Podiatrist",
            "type":"Services"
        }
    ],
    "sg:phone":"+1 706 883 6415",
    "sg:postcode":"30240",
    "sg:province":"GA",
    "wof:name":"LA Grange Foot & Ankle Clinic",
    "wof:placetype":"venue"
},
  "geometry": {"coordinates":[-85.03513599999999,33.036319],"type":"Point"}
}