{
  "type": "Feature",
  "properties": {
    "addr:full":"2354 N Main St La Fayette GA 30728",
    "addr:housenumber":"2354",
    "addr:postcode":"30728",
    "addr:street":"N Main St;Fayette",
    "iso:country":"US",
    "sg:address":"2354 N Main St",
    "sg:city":"La Fayette",
    "sg:classifiers":[
        {
            "category":"Restaurant",
            "type":"Food & Drink"
        }
    ],
    "sg:menulink":"http://www.allmenus.com/ga/lafayette/246104-krystal/menu/",
    "sg:phone":"+1 706 638 9416",
    "sg:postcode":"30728",
    "sg:province":"GA",
    "sg:tags":[
        "burger",
        "american"
    ],
    "wof:name":"Krystal",
    "wof:placetype":"venue"
},
  "geometry": {"coordinates":[-85.27123,34.743091],"type":"Point"}
}