{
  "type": "Feature",
  "properties": {
    "addr:full":"1922 Northlake Pkwy Tucker GA 30084",
    "addr:housenumber":"1922",
    "addr:postcode":"30084",
    "addr:street":"Northlake Pkwy",
    "iso:country":"US",
    "sg:address":"1922 Northlake Pkwy",
    "sg:city":"Tucker",
    "sg:classifiers":[
        {
            "category":"Insurance",
            "subcategory":"Insurance Agent",
            "type":"Services"
        }
    ],
    "sg:phone":"+1 770 493 1931",
    "sg:postcode":"30084",
    "sg:province":"GA",
    "wof:name":"Southern Guaranty Insurance Co",
    "wof:placetype":"venue"
},
  "geometry": {"coordinates":[-84.237635,33.83778],"type":"Point"}
}