{
  "type": "Feature",
  "properties": {
    "iso:country":"US",
    "sg:address":"3904 Newton Rd",
    "sg:city":"Albany",
    "sg:classifiers":[
        {
            "category":"Manufacturing",
            "subcategory":"Wood Products",
            "type":"Manufacturing & Wholesale Goods"
        }
    ],
    "sg:phone":"+1 229 888 3303",
    "sg:postcode":"31701",
    "sg:province":"GA",
    "sg:tags":[
        "millwork"
    ],
    "wof:name":"A C M I Inc",
    "wof:placetype":"venue"
},
  "geometry": {"coordinates":[-84.187141,31.532181],"type":"Point"}
}