{
  "type": "Feature",
  "properties": {
    "iso:country":"US",
    "sg:address":"407 Ridgestone Dr",
    "sg:city":"Warner Robins",
    "sg:classifiers":[
        {
            "category":"Organizations",
            "subcategory":"Religious Organization",
            "type":"Services"
        }
    ],
    "sg:phone":"+1 478 929 0710",
    "sg:postcode":"31088",
    "sg:province":"GA",
    "wof:name":"Full Gspl Church Warren Robins",
    "wof:placetype":"venue"
},
  "geometry": {"coordinates":[-83.647308,32.577296],"type":"Point"}
}