{
  "type": "Feature",
  "properties": {
    "addr:full":"518 Golf View Dr Peachtree City GA 30269",
    "addr:housenumber":"518",
    "addr:postcode":"30269",
    "addr:street":"Golf View Dr",
    "iso:country":"US",
    "sg:address":"518 Golf View Dr",
    "sg:city":"Peachtree City",
    "sg:classifiers":[
        {
            "category":"Building & Trades",
            "subcategory":"Locksmith",
            "type":"Services"
        }
    ],
    "sg:phone":"+1 678 269 7173",
    "sg:postcode":"30269",
    "sg:province":"GA",
    "sg:tags":[
        "key"
    ],
    "wof:name":"7 Days Emergency Locksmith",
    "wof:placetype":"venue"
},
  "geometry": {"coordinates":[-84.582328,33.416815],"type":"Point"}
}