{
  "type": "Feature",
  "properties": {
    "addr:full":"111 Barnett Shoals Rd Watkinsville GA 30677",
    "addr:housenumber":"111",
    "addr:postcode":"30677",
    "addr:street":"Barnett Shoals Rd",
    "iso:country":"US",
    "sg:address":"111 Barnett Shoals Rd",
    "sg:city":"Watkinsville",
    "sg:classifiers":[
        {
            "category":"Manufacturing",
            "subcategory":"Metals",
            "type":"Manufacturing & Wholesale Goods"
        }
    ],
    "sg:phone":"+1 706 769 5611",
    "sg:postcode":"30677",
    "sg:province":"GA",
    "sg:tags":[
        "cable"
    ],
    "wof:name":"Southwire Watkinsville Plant",
    "wof:placetype":"venue"
},
  "geometry": {"coordinates":[-83.39203999999999,33.858463],"type":"Point"}
}