{
  "type": "Feature",
  "properties": {
    "addr:full":"311 W Harris St Savannah GA 31401",
    "addr:housenumber":"311",
    "addr:postcode":"31401",
    "addr:street":"W Harris St",
    "iso:country":"US",
    "sg:address":"311 W Harris St",
    "sg:city":"Savannah",
    "sg:classifiers":[
        {
            "category":"Professional",
            "subcategory":"Lawyer & Legal Services",
            "type":"Services"
        }
    ],
    "sg:phone":"+1 912 231 0906",
    "sg:postcode":"31401",
    "sg:province":"GA",
    "sg:tags":[
        "attorney"
    ],
    "wof:name":"Francesca Rehal",
    "wof:placetype":"venue"
},
  "geometry": {"coordinates":[-81.09819400000001,32.074942],"type":"Point"}
}