{
  "type": "Feature",
  "properties": {
    "addr:full":"712 W 2nd St Rome GA 30161",
    "addr:housenumber":"712",
    "addr:postcode":"ga 30161",
    "addr:street":"W 2Nd St",
    "iso:country":"US",
    "sg:address":"712 W 2nd St",
    "sg:city":"Rome",
    "sg:classifiers":[
        {
            "category":"Social Services",
            "type":"Services"
        }
    ],
    "sg:phone":"+1 706 232 6613",
    "sg:postcode":"30161",
    "sg:province":"GA",
    "sg:tags":[
        "counselor",
        "marriage",
        "family"
    ],
    "wof:name":"Phoenix Counseling Innovation",
    "wof:placetype":"venue"
},
  "geometry": {"coordinates":[-85.166612,34.258633],"type":"Point"}
}