{
  "type": "Feature",
  "properties": {
    "iso:country":"US",
    "sg:address":"3553 Victory Rd",
    "sg:city":"Franklin",
    "sg:classifiers":[
        {
            "category":"Banks & Credit Unions",
            "subcategory":"Financial Services",
            "type":"Services"
        }
    ],
    "sg:phone":"+1 706 675 6414",
    "sg:postcode":"30217",
    "sg:province":"GA",
    "sg:tags":[
        "investor"
    ],
    "wof:name":"Lipham Family Investments LP",
    "wof:placetype":"venue"
},
  "geometry": {"coordinates":[-85.16708,33.19608],"type":"Point"}
}