{
  "type": "Feature",
  "properties": {
    "iso:country":"US",
    "sg:address":"2430 Dawson Rd",
    "sg:city":"Albany",
    "sg:classifiers":[
        {
            "category":"Retail",
            "subcategory":"Laundry & Dry Cleaning",
            "type":"Services"
        }
    ],
    "sg:phone":"+1 229 439 7598",
    "sg:postcode":"31707",
    "sg:province":"GA",
    "sg:tags":[
        "drycleaning",
        "plant"
    ],
    "wof:name":"Trinity Dry Cleaners Inc",
    "wof:placetype":"venue"
},
  "geometry": {"coordinates":[-84.21004000000001,31.608837],"type":"Point"}
}