{
  "type": "Feature",
  "properties": {
    "addr:full":"6225 Bells Ferry Rd Acworth GA 30102",
    "addr:housenumber":"6225",
    "addr:postcode":"30102",
    "addr:street":"Bells Ferry Rd",
    "iso:country":"US",
    "sg:address":"6225 Bells Ferry Rd",
    "sg:city":"Acworth",
    "sg:classifiers":[
        {
            "category":"Building & Trades",
            "subcategory":"Construction",
            "type":"Services"
        }
    ],
    "sg:phone":"+1 770 926 8938",
    "sg:postcode":"30102",
    "sg:province":"GA",
    "sg:tags":[
        "contractor"
    ],
    "wof:name":"Acworth Fence",
    "wof:placetype":"venue"
},
  "geometry": {"coordinates":[-84.581283,34.107872],"type":"Point"}
}