{
  "type": "Feature",
  "properties": {
    "addr:full":"3210 Fern Valley Dr SW Marietta GA 30008",
    "addr:housenumber":"3210",
    "addr:postcode":"30008",
    "addr:street":"Fern Valley Dr Sw",
    "iso:country":"US",
    "sg:address":"3210 Fern Valley Dr SW",
    "sg:city":"Marietta",
    "sg:classifiers":[
        {
            "category":"Restaurant",
            "type":"Food & Drink"
        }
    ],
    "sg:phone":"+1 770 792 0869",
    "sg:postcode":"30008",
    "sg:province":"GA",
    "sg:tags":[
        "caterer"
    ],
    "wof:name":"Jacky's Lunch",
    "wof:placetype":"venue"
},
  "geometry": {"coordinates":[-84.607652,33.882352],"type":"Point"}
}