{
  "type": "Feature",
  "properties": {
    "iso:country":"US",
    "sg:address":"2030 Will Ross Ct",
    "sg:city":"Atlanta",
    "sg:classifiers":[
        {
            "category":"Wholesale",
            "subcategory":"Groceries",
            "type":"Manufacturing & Wholesale Goods"
        }
    ],
    "sg:phone":"+1 770 454 7569",
    "sg:postcode":"30341",
    "sg:province":"GA",
    "sg:tags":[
        "food",
        "oriental"
    ],
    "wof:name":"Lotte Oriental Food Inc",
    "wof:placetype":"venue"
},
  "geometry": {"coordinates":[-84.307907,33.895154],"type":"Point"}
}