{
  "type": "Feature",
  "properties": {
    "iso:country":"US",
    "sg:address":"1047 Farr Rd",
    "sg:city":"Columbus",
    "sg:classifiers":[
        {
            "category":"Restaurant",
            "type":"Food & Drink"
        }
    ],
    "sg:phone":"+1 706 685 1968",
    "sg:postcode":"31907",
    "sg:province":"GA",
    "wof:name":"Quick Take Rstrnt & Ice Cream",
    "wof:placetype":"venue"
},
  "geometry": {"coordinates":[-84.925749,32.432086],"type":"Point"}
}