{
  "type": "Feature",
  "properties": {
    "iso:country":"US",
    "sg:address":"5579 Chamblee Dunwoody Rd",
    "sg:city":"Atlanta",
    "sg:classifiers":[
        {
            "category":"Shopping",
            "subcategory":"Jewelry",
            "type":"Retail Goods"
        },
        {
            "category":"Wholesale",
            "subcategory":"Jewelry",
            "type":"Manufacturing & Wholesale Goods"
        }
    ],
    "sg:phone":"+1 770 396 1787",
    "sg:postcode":"30338",
    "sg:province":"GA",
    "sg:tags":[
        "company",
        "liquidation",
        "silverware"
    ],
    "wof:name":"W F N Enterprises Inc",
    "wof:placetype":"venue"
},
  "geometry": {"coordinates":[-84.336381,33.950432],"type":"Point"}
}