{
  "type": "Feature",
  "properties": {
    "iso:country":"US",
    "sg:address":"829 Arbor Hill Dr",
    "sg:city":"Stone Mountain",
    "sg:classifiers":[
        {
            "category":"Professional",
            "subcategory":"Employment Agencies",
            "type":"Services"
        }
    ],
    "sg:phone":"+1 404 296 8489",
    "sg:postcode":"30088",
    "sg:province":"GA",
    "sg:tags":[
        "help",
        "supply"
    ],
    "wof:name":"Campbell Frederick",
    "wof:placetype":"venue"
},
  "geometry": {"coordinates":[-84.19202199999999,33.770732],"type":"Point"}
}