{
  "type": "Feature",
  "properties": {
    "iso:country":"US",
    "sg:address":"2276 Mandeville Rd",
    "sg:city":"Bremen",
    "sg:classifiers":[
        {
            "category":"Building & Trades",
            "subcategory":"Construction",
            "type":"Services"
        }
    ],
    "sg:phone":"+1 770 537 3587",
    "sg:postcode":"30110",
    "sg:province":"GA",
    "sg:tags":[
        "roofing",
        "industrial",
        "contractors-commercial",
        "contractor"
    ],
    "wof:name":"Ayers Roofing",
    "wof:placetype":"venue"
},
  "geometry": {"coordinates":[-85.08851300000001,33.685237],"type":"Point"}
}