{
  "type": "Feature",
  "properties": {
    "iso:country":"US",
    "sg:address":"263 Lost Lake Way",
    "sg:city":"Villa Rica",
    "sg:classifiers":[
        {
            "category":"Retail",
            "subcategory":"Repair Shop",
            "type":"Services"
        }
    ],
    "sg:phone":"+1 770 459 6275",
    "sg:postcode":"30180",
    "sg:province":"GA",
    "wof:name":"Drain Go Drain Service",
    "wof:placetype":"venue"
},
  "geometry": {"coordinates":[-84.95693799999999,33.710268],"type":"Point"}
}