{
  "type": "Feature",
  "properties": {
    "addr:full":"2233 Lake Park Dr SE Smyrna GA 30080",
    "addr:housenumber":"2233",
    "addr:postcode":"30080",
    "addr:street":"Lake Park Dr Se",
    "iso:country":"US",
    "sg:address":"2233 Lake Park Dr SE",
    "sg:city":"Smyrna",
    "sg:classifiers":[
        {
            "category":"Professional",
            "type":"Services"
        }
    ],
    "sg:phone":"+1 770 436 1969",
    "sg:postcode":"30080",
    "sg:province":"GA",
    "sg:tags":[
        "caterer"
    ],
    "wof:name":"Brandino's",
    "wof:placetype":"venue"
},
  "geometry": {"coordinates":[-84.486479,33.894634],"type":"Point"}
}