{
  "type": "Feature",
  "properties": {
    "addr:full":"1316 Rockbridge Rd Stone Mountain GA 30087",
    "addr:housenumber":"1316",
    "addr:postcode":"30087",
    "addr:street":"Rockbridge Rd",
    "iso:country":"US",
    "sg:address":"1316 Rockbridge Rd",
    "sg:city":"Stone Mountain",
    "sg:classifiers":[
        {
            "category":"Organizations",
            "subcategory":"Religious Organization",
            "type":"Services"
        }
    ],
    "sg:phone":"+1 770 925 0553",
    "sg:postcode":"30087",
    "sg:province":"GA",
    "sg:tags":[
        "church"
    ],
    "wof:name":"Truth In Lending",
    "wof:placetype":"venue"
},
  "geometry": {"coordinates":[-84.129745,33.838351],"type":"Point"}
}