{
  "type": "Feature",
  "properties": {
    "addr:full":"7 Galway Dr Cartersville GA 30120",
    "addr:housenumber":"7",
    "addr:postcode":"30120",
    "addr:street":"Galway Dr",
    "iso:country":"US",
    "sg:address":"7 Galway Dr",
    "sg:city":"Cartersville",
    "sg:classifiers":[
        {
            "category":"Building & Trades",
            "subcategory":"Construction",
            "type":"Services"
        }
    ],
    "sg:phone":"+1 678 721 9350",
    "sg:postcode":"30120",
    "sg:province":"GA",
    "sg:tags":[
        "general",
        "contractor"
    ],
    "wof:name":"Outlook Construction Co",
    "wof:placetype":"venue"
},
  "geometry": {"coordinates":[-84.793941,34.137038],"type":"Point"}
}