{
  "type": "Feature",
  "properties": {
    "addr:full":"519 N McDonough St Decatur GA 30030",
    "addr:housenumber":"519",
    "addr:postcode":"30030",
    "addr:street":"N Mcdonough St",
    "iso:country":"US",
    "sg:address":"519 N McDonough St",
    "sg:city":"Decatur",
    "sg:classifiers":[
        {
            "category":"Education",
            "subcategory":"Dance Studio",
            "type":"Public Place"
        }
    ],
    "sg:phone":"+1 404 873 5986",
    "sg:postcode":"30030",
    "sg:province":"GA",
    "sg:tags":[
        "instruction",
        "dancing"
    ],
    "wof:name":"Tap Mania",
    "wof:placetype":"venue"
},
  "geometry": {"coordinates":[-84.296448,33.774371],"type":"Point"}
}