{
  "type": "Feature",
  "properties": {
    "addr:full":"3462 Sheridan Chase SE Marietta GA 30067",
    "addr:housenumber":"3462",
    "addr:postcode":"30067",
    "addr:street":"Sheridan Chase Se",
    "iso:country":"US",
    "sg:address":"3462 Sheridan Chase SE",
    "sg:city":"Marietta",
    "sg:classifiers":[
        {
            "category":"Shopping",
            "subcategory":"Computers & Home Electronics",
            "type":"Retail Goods"
        }
    ],
    "sg:phone":"+1 678 560 3906",
    "sg:postcode":"30067",
    "sg:province":"GA",
    "wof:name":"Mainline Information Systems",
    "wof:placetype":"venue"
},
  "geometry": {"coordinates":[-84.450203,33.9482],"type":"Point"}
}