{
  "type": "Feature",
  "properties": {
    "iso:country":"US",
    "sg:address":"3414 Peachtree Rd NE",
    "sg:city":"Atlanta",
    "sg:classifiers":[
        {
            "category":"Professional",
            "subcategory":"Lawyer & Legal Services",
            "type":"Services"
        }
    ],
    "sg:phone":"+1 404 577 6000",
    "sg:postcode":"30326",
    "sg:province":"GA",
    "wof:name":"Stine Kevin A Atty",
    "wof:placetype":"venue"
},
  "geometry": {"coordinates":[-84.36394900000001,33.849889],"type":"Point"}
}