{
  "type": "Feature",
  "properties": {
    "addr:full":"1945 Highway 138 NE Conyers GA 30013",
    "addr:housenumber":"1945",
    "addr:postcode":"30013",
    "addr:street":"Highway 138 Ne",
    "iso:country":"US",
    "sg:address":"1945 Highway 138 NE",
    "sg:city":"Conyers",
    "sg:classifiers":[
        {
            "category":"Banks & Credit Unions",
            "subcategory":"Bank",
            "type":"Services"
        }
    ],
    "sg:phone":"+1 440 553 2300",
    "sg:postcode":"30013",
    "sg:province":"GA",
    "sg:tags":[
        "saving",
        "commercial"
    ],
    "wof:name":"Fidelity National Bank (Inc)",
    "wof:placetype":"venue"
},
  "geometry": {"coordinates":[-83.981421,33.672541],"type":"Point"}
}