{
  "type": "Feature",
  "properties": {
    "addr:full":"280 Whigham Rd Whigham GA 31779",
    "addr:housenumber":"280",
    "addr:postcode":"31779",
    "addr:street":"Whigham Rd",
    "iso:country":"US",
    "sg:address":"280 Whigham Rd",
    "sg:city":"Whigham",
    "sg:classifiers":[
        {
            "category":"Autos & Motor Vehicles",
            "subcategory":"Automobile Sales",
            "type":"Retail Goods"
        }
    ],
    "sg:phone":"+1 229 762 3307",
    "sg:postcode":"31779",
    "sg:province":"GA",
    "sg:tags":[
        "used"
    ],
    "wof:name":"Whigam Auto Repair",
    "wof:placetype":"venue"
},
  "geometry": {"coordinates":[-84.32596100000001,31.090973],"type":"Point"}
}