{
  "type": "Feature",
  "properties": {
    "iso:country":"US",
    "sg:address":"27 Oak St",
    "sg:city":"Roswell",
    "sg:classifiers":[
        {
            "category":"Banks & Credit Unions",
            "subcategory":"Financial Services",
            "type":"Services"
        }
    ],
    "sg:phone":"+1 770 640 2796",
    "sg:postcode":"30075",
    "sg:province":"GA",
    "sg:tags":[
        "company",
        "holding"
    ],
    "wof:name":"Transworld Holding",
    "wof:placetype":"venue"
},
  "geometry": {"coordinates":[-84.361667,34.01975],"type":"Point"}
}