{
  "type": "Feature",
  "properties": {
    "iso:country":"US",
    "sg:address":"6300 Moseley Dixon Rd",
    "sg:city":"Macon",
    "sg:classifiers":[
        {
            "category":"Real Estate",
            "subcategory":"Real Estate Operator",
            "type":"Services"
        }
    ],
    "sg:phone":"+1 478 474 9411",
    "sg:postcode":"31220",
    "sg:province":"GA",
    "sg:tags":[
        "building",
        "apartment"
    ],
    "wof:name":"West Harbor Apartments",
    "wof:placetype":"venue"
},
  "geometry": {"coordinates":[-83.766769,32.831216],"type":"Point"}
}