{
  "type": "Feature",
  "properties": {
    "addr:full":"300 Holloway Rd Thomaston GA 30286",
    "addr:housenumber":"300",
    "addr:postcode":"30286",
    "addr:street":"Holloway Rd",
    "iso:country":"US",
    "sg:address":"300 Holloway Rd",
    "sg:city":"Thomaston",
    "sg:classifiers":[
        {
            "category":"Farming",
            "subcategory":"Livestock Farm",
            "type":"Manufacturing & Wholesale Goods"
        }
    ],
    "sg:phone":"+1 706 647 5936",
    "sg:postcode":"30286",
    "sg:province":"GA",
    "sg:tags":[
        "general"
    ],
    "wof:name":"Four See Farm",
    "wof:placetype":"venue"
},
  "geometry": {"coordinates":[-84.24290499999999,32.908867],"type":"Point"}
}