{
  "type": "Feature",
  "properties": {
    "addr:full":"3475 Lenox Road NE Suite 710 Atlanta GA 30326",
    "addr:housenumber":"3475",
    "addr:postcode":"30326",
    "addr:street":"Lenox Road Ne Suite 710",
    "iso:country":"US",
    "sg:address":"3475 Lenox Road NE Suite 710",
    "sg:city":"Atlanta",
    "sg:classifiers":[
        {
            "category":"Professional",
            "subcategory":"Accounting & Tax Preparation",
            "type":"Services"
        }
    ],
    "sg:phone":"+1 404 816 8100",
    "sg:postcode":"30326",
    "sg:province":"GA",
    "sg:tags":[
        "accountant"
    ],
    "wof:name":"Barnwell and Company",
    "wof:placetype":"venue"
},
  "geometry": {"coordinates":[-84.362561,33.849905],"type":"Point"}
}