{
  "type": "Feature",
  "properties": {
    "addr:full":"3525 Piedmont Rd NE Atlanta GA 30305",
    "addr:housenumber":"3525",
    "addr:postcode":"30305",
    "addr:street":"Piedmont Rd Ne",
    "iso:country":"US",
    "sg:address":"3525 Piedmont Rd NE",
    "sg:city":"Atlanta",
    "sg:classifiers":[
        {
            "category":"Utilities",
            "subcategory":"Telephone",
            "type":"Services"
        }
    ],
    "sg:phone":"+1 404 364 9200",
    "sg:postcode":"30305",
    "sg:province":"GA",
    "sg:tags":[
        "internet",
        "provider"
    ],
    "wof:name":"Visiprise Inc",
    "wof:placetype":"venue"
},
  "geometry": {"coordinates":[-84.372834,33.846594],"type":"Point"}
}