{
  "type": "Feature",
  "properties": {
    "iso:country":"US",
    "sg:address":"3191 New Franklin Rd",
    "sg:city":"Lagrange",
    "sg:classifiers":[
        {
            "category":"Food & Beverages",
            "subcategory":"Groceries & Convenience Stores",
            "type":"Retail Goods"
        }
    ],
    "sg:phone":"+1 706 884 2812",
    "sg:postcode":"30240",
    "sg:province":"GA",
    "sg:tags":[
        "grocer"
    ],
    "wof:name":"Tall Tales Bait & Grocery",
    "wof:placetype":"venue"
},
  "geometry": {"coordinates":[-85.042072,33.123418],"type":"Point"}
}