{
  "type": "Feature",
  "properties": {
    "addr:full":"45 SW Broad St Fairburn GA 30213",
    "addr:housenumber":"45",
    "addr:postcode":"30213",
    "addr:street":"Sw Broad St",
    "iso:country":"US",
    "sg:address":"45 SW Broad St",
    "sg:city":"Fairburn",
    "sg:classifiers":[
        {
            "category":"Restaurant",
            "type":"Food & Drink"
        }
    ],
    "sg:phone":"+1 770 969 0101",
    "sg:postcode":"30213",
    "sg:province":"GA",
    "sg:tags":[
        "pizza"
    ],
    "sg:website":"www.dominos.com",
    "wof:name":"Domino's Pizza",
    "wof:placetype":"venue"
},
  "geometry": {"coordinates":[-84.582286,33.566015],"type":"Point"}
}