{
  "type": "Feature",
  "properties": {
    "addr:full":"5370 Oakdale Rd SE Smyrna GA 30082",
    "addr:housenumber":"5370",
    "addr:postcode":"30082",
    "addr:street":"Oakdale Rd Se",
    "iso:country":"US",
    "sg:address":"5370 Oakdale Rd SE",
    "sg:city":"Smyrna",
    "sg:classifiers":[
        {
            "category":"Wholesale",
            "subcategory":"Petroleum",
            "type":"Manufacturing & Wholesale Goods"
        }
    ],
    "sg:phone":"+1 404 799 9400",
    "sg:postcode":"30082",
    "sg:province":"GA",
    "sg:tags":[
        "gasoline-wholesale"
    ],
    "wof:name":"Wallace Oil Co",
    "wof:placetype":"venue"
},
  "geometry": {"coordinates":[-84.49548299999999,33.827925],"type":"Point"}
}