{
  "type": "Feature",
  "properties": {
    "iso:country":"US",
    "sg:address":"1730 Lawrenceville Hwy",
    "sg:city":"Lawrenceville",
    "sg:classifiers":[
        {
            "category":"Health Services",
            "subcategory":"Doctor",
            "type":"Services"
        }
    ],
    "sg:phone":"+1 770 338 0089",
    "sg:postcode":"30044",
    "sg:province":"GA",
    "sg:tags":[
        "practice",
        "family"
    ],
    "wof:name":"Yun Inchol MD",
    "wof:placetype":"venue"
},
  "geometry": {"coordinates":[-84.03823300000001,33.933063],"type":"Point"}
}