{
  "type": "Feature",
  "properties": {
    "addr:full":"2200 Roswell Rd Marietta GA 30062",
    "addr:housenumber":"2200",
    "addr:postcode":"30062",
    "addr:street":"Roswell Rd",
    "iso:country":"US",
    "sg:address":"2200 Roswell Rd",
    "sg:city":"Marietta",
    "sg:classifiers":[
        {
            "category":"Professional",
            "type":"Services"
        }
    ],
    "sg:phone":"+1 770 509 0280",
    "sg:postcode":"30062",
    "sg:province":"GA",
    "wof:name":"Ccberries LLC",
    "wof:placetype":"venue"
},
  "geometry": {"coordinates":[-84.487793,33.970671],"type":"Point"}
}