{
  "type": "Feature",
  "properties": {
    "iso:country":"US",
    "sg:address":"4461 Bretton Ct NW",
    "sg:city":"Acworth",
    "sg:classifiers":[
        {
            "category":"Home & Garden",
            "subcategory":"Building Materials",
            "type":"Retail Goods"
        },
        {
            "category":"Manufacturing",
            "subcategory":"Building Materials",
            "type":"Manufacturing & Wholesale Goods"
        }
    ],
    "sg:phone":"+1 770 529 0627",
    "sg:postcode":"30101",
    "sg:province":"GA",
    "sg:tags":[
        "solid",
        "top",
        "counter",
        "surface"
    ],
    "wof:name":"Granite & Marble & Concepts",
    "wof:placetype":"venue"
},
  "geometry": {"coordinates":[-84.634328,34.061789],"type":"Point"}
}