{
  "type": "Feature",
  "properties": {
    "addr:full":"4050 Dream Catcher Dr Woodstock GA 30189",
    "addr:housenumber":"4050",
    "addr:postcode":"30189",
    "addr:street":"Dream Catcher Dr",
    "iso:country":"US",
    "sg:address":"4050 Dream Catcher Dr",
    "sg:city":"Woodstock",
    "sg:classifiers":[
        {
            "category":"Social Services",
            "type":"Services"
        },
        {
            "category":"Professional",
            "subcategory":"Employment Agencies",
            "type":"Services"
        },
        {
            "category":"Organizations",
            "subcategory":"Community Association",
            "type":"Services"
        }
    ],
    "sg:phone":"+1 678 494 2993",
    "sg:postcode":"30189",
    "sg:province":"GA",
    "sg:tags":[
        "workers'",
        "placement",
        "volunteer"
    ],
    "wof:name":"Deer Run Home Owners Associates",
    "wof:placetype":"venue"
},
  "geometry": {"coordinates":[-84.53407900000001,34.116697],"type":"Point"}
}