{
  "type": "Feature",
  "properties": {
    "iso:country":"US",
    "sg:address":"1001 S Jenkins Rd",
    "sg:city":"Chickamauga",
    "sg:classifiers":[
        {
            "category":"Retail",
            "subcategory":"Auto Repair",
            "type":"Services"
        }
    ],
    "sg:phone":"+1 706 861 2277",
    "sg:postcode":"30707",
    "sg:province":"GA",
    "sg:tags":[
        "general"
    ],
    "wof:name":"J & E Automotive",
    "wof:placetype":"venue"
},
  "geometry": {"coordinates":[-85.287514,34.918188],"type":"Point"}
}