{
  "type": "Feature",
  "properties": {
    "iso:country":"US",
    "sg:address":"309 W Collins St",
    "sg:city":"Pooler",
    "sg:classifiers":[
        {
            "category":"Real Estate",
            "subcategory":"Real Estate Operator",
            "type":"Services"
        }
    ],
    "sg:phone":"+1 912 748 0720",
    "sg:postcode":"31322",
    "sg:province":"GA",
    "sg:tags":[
        "property",
        "lessor"
    ],
    "wof:name":"Glenn A Taulbee",
    "wof:placetype":"venue"
},
  "geometry": {"coordinates":[-81.251938,32.115667],"type":"Point"}
}