{
  "type": "Feature",
  "properties": {
    "iso:country":"US",
    "sg:address":"301 E Dykes St",
    "sg:city":"Cochran",
    "sg:classifiers":[
        {
            "category":"Health Services",
            "subcategory":"Chiropractor",
            "type":"Services"
        }
    ],
    "sg:phone":"+1 478 934 8855",
    "sg:postcode":"31014",
    "sg:province":"GA",
    "wof:name":"Covenant Chiropractic Ctr P C",
    "wof:placetype":"venue"
},
  "geometry": {"coordinates":[-83.352662,32.388351],"type":"Point"}
}