{
  "type": "Feature",
  "properties": {
    "iso:country":"US",
    "sg:address":"829 Univeter Rd",
    "sg:city":"Canton",
    "sg:classifiers":[
        {
            "category":"Home & Garden",
            "subcategory":"Building Materials",
            "type":"Retail Goods"
        }
    ],
    "sg:phone":"+1 770 345 5502",
    "sg:postcode":"30115",
    "sg:province":"GA",
    "sg:tags":[
        "mixed",
        "concrete"
    ],
    "wof:name":"Lafarge Corp",
    "wof:placetype":"venue"
},
  "geometry": {"coordinates":[-84.49872000000001,34.195261],"type":"Point"}
}