{
  "type": "Feature",
  "properties": {
    "iso:country":"US",
    "sg:address":"670 Iron Mountain Rd",
    "sg:city":"Canton",
    "sg:classifiers":[
        {
            "category":"Shopping",
            "subcategory":"Clothing, Apparel, & Fashions",
            "type":"Retail Goods"
        }
    ],
    "sg:phone":"+1 770 479 7083",
    "sg:postcode":"30115",
    "sg:province":"GA",
    "wof:name":"L Male",
    "wof:placetype":"venue"
},
  "geometry": {"coordinates":[-84.31910499999999,34.204517],"type":"Point"}
}