{
  "type": "Feature",
  "properties": {
    "addr:full":"2137 Kingston Ct Marietta GA 30067",
    "addr:housenumber":"2137",
    "addr:postcode":"30067",
    "addr:street":"Kingston Ct",
    "iso:country":"US",
    "sg:address":"2137 Kingston Ct",
    "sg:city":"Marietta",
    "sg:classifiers":[
        {
            "category":"Professional",
            "subcategory":"Business Services",
            "type":"Services"
        },
        {
            "category":"Wholesale",
            "subcategory":"Sporting Goods",
            "type":"Manufacturing & Wholesale Goods"
        }
    ],
    "sg:phone":"+1 770 850 0160",
    "sg:postcode":"30067",
    "sg:province":"GA",
    "sg:tags":[
        "equipment",
        "pool",
        "swimming"
    ],
    "wof:name":"H20 Pool Svc Inc",
    "wof:placetype":"venue"
},
  "geometry": {"coordinates":[-84.49205000000001,33.925467],"type":"Point"}
}