{
  "type": "Feature",
  "properties": {
    "addr:full":"667 Tommy Cowart Rd Cleveland GA 30528",
    "addr:housenumber":"667",
    "addr:postcode":"30528",
    "addr:street":"Tommy Cowart Rd",
    "iso:country":"US",
    "sg:address":"667 Tommy Cowart Rd",
    "sg:city":"Cleveland",
    "sg:classifiers":[
        {
            "category":"Professional",
            "subcategory":"Detective & Security Services",
            "type":"Services"
        }
    ],
    "sg:phone":"+1 706 865 4794",
    "sg:postcode":"30528",
    "sg:province":"GA",
    "sg:tags":[
        "information",
        "bureau"
    ],
    "wof:name":"Copp Backhoe Tractor Servic",
    "wof:placetype":"venue"
},
  "geometry": {"coordinates":[-83.767978,34.557383],"type":"Point"}
}