{
  "type": "Feature",
  "properties": {
    "iso:country":"US",
    "sg:address":"2740 Greenbriar Pkwy SW",
    "sg:city":"Atlanta",
    "sg:classifiers":[
        {
            "category":"Retail",
            "subcategory":"Repair Shop",
            "type":"Services"
        }
    ],
    "sg:phone":"+1 770 477 8277",
    "sg:postcode":"30311",
    "sg:province":"GA",
    "wof:name":"Duraclean",
    "wof:placetype":"venue"
},
  "geometry": {"coordinates":[-84.48964100000001,33.691506],"type":"Point"}
}