{
  "type": "Feature",
  "properties": {
    "addr:full":"5040 Damon Pl Atlanta GA 30338",
    "addr:housenumber":"5040",
    "addr:postcode":"30338",
    "addr:street":"Damon Pl",
    "iso:country":"US",
    "sg:address":"5040 Damon Pl",
    "sg:city":"Atlanta",
    "sg:classifiers":[
        {
            "category":"Professional",
            "subcategory":"Business Services",
            "type":"Services"
        }
    ],
    "sg:phone":"+1 770 399 6674",
    "sg:postcode":"30338",
    "sg:province":"GA",
    "wof:name":"Custom Window Designs",
    "wof:placetype":"venue"
},
  "geometry": {"coordinates":[-84.321716,33.946061],"type":"Point"}
}