{
  "type": "Feature",
  "properties": {
    "iso:country":"US",
    "sg:address":"151 State Rte 24",
    "sg:city":"Waynesboro",
    "sg:classifiers":[
        {
            "category":"Government",
            "subcategory":"Office",
            "type":"Public Place"
        }
    ],
    "sg:phone":"+1 706 554 3141",
    "sg:postcode":"30830",
    "sg:province":"GA",
    "wof:name":"Operations Maintenance Div",
    "wof:placetype":"venue"
},
  "geometry": {"coordinates":[-82.016276,33.089868],"type":"Point"}
}