{
  "type": "Feature",
  "properties": {
    "iso:country":"US",
    "sg:address":"3673 Hog Liver Rd",
    "sg:city":"Carrollton",
    "sg:classifiers":[
        {
            "category":"Freight",
            "type":"Transportation"
        }
    ],
    "sg:phone":"+1 770 830 6799",
    "sg:postcode":"30117",
    "sg:province":"GA",
    "sg:tags":[
        "operator",
        "trucking"
    ],
    "wof:name":"Gcp Trucking Co",
    "wof:placetype":"venue"
},
  "geometry": {"coordinates":[-85.050859,33.649256],"type":"Point"}
}