{
  "type": "Feature",
  "properties": {
    "iso:country":"US",
    "sg:address":"102 Georgia Ave",
    "sg:city":"Thomaston",
    "sg:classifiers":[
        {
            "category":"Restaurant",
            "type":"Food & Drink"
        }
    ],
    "sg:phone":"+1 706 647 1234",
    "sg:postcode":"30286",
    "sg:province":"GA",
    "wof:name":"Frank's Fine Foods",
    "wof:placetype":"venue"
},
  "geometry": {"coordinates":[-84.326561,32.895493],"type":"Point"}
}