{
  "type": "Feature",
  "properties": {
    "addr:full":"3339 Old Salem Rd SE Conyers GA 30013",
    "addr:housenumber":"3339",
    "addr:postcode":"30013",
    "addr:street":"Old Salem Rd Se",
    "iso:country":"US",
    "sg:address":"3339 Old Salem Rd SE",
    "sg:city":"Conyers",
    "sg:classifiers":[
        {
            "category":"Professional",
            "subcategory":"Lawyer & Legal Services",
            "type":"Services"
        }
    ],
    "sg:phone":"+1 678 750 0023",
    "sg:postcode":"30013",
    "sg:province":"GA",
    "sg:tags":[
        "attorney"
    ],
    "wof:name":"Walker & Waldrop",
    "wof:placetype":"venue"
},
  "geometry": {"coordinates":[-83.97971099999999,33.602979],"type":"Point"}
}