{
  "type": "Feature",
  "properties": {
    "iso:country":"US",
    "sg:address":"118 Juniper St",
    "sg:city":"Roswell",
    "sg:classifiers":[
        {
            "category":"Professional",
            "type":"Services"
        }
    ],
    "sg:phone":"+1 770 993 6281",
    "sg:postcode":"30075",
    "sg:province":"GA",
    "wof:name":"Justin D Cagle",
    "wof:placetype":"venue"
},
  "geometry": {"coordinates":[-84.407022,34.07877],"type":"Point"}
}