{
  "type": "Feature",
  "properties": {
    "addr:full":"2200 Northlake Pkwy Tucker GA 30084",
    "addr:housenumber":"2200",
    "addr:postcode":"30084",
    "addr:street":"Northlake Pkwy",
    "iso:country":"US",
    "sg:address":"2200 Northlake Pkwy",
    "sg:city":"Tucker",
    "sg:classifiers":[
        {
            "category":"Personal",
            "subcategory":"Beauty Salon",
            "type":"Services"
        }
    ],
    "sg:phone":"+1 770 493 9872",
    "sg:postcode":"30084",
    "sg:province":"GA",
    "sg:tags":[
        "shop"
    ],
    "wof:name":"Oasis",
    "wof:placetype":"venue"
},
  "geometry": {"coordinates":[-84.244608,33.8469],"type":"Point"}
}