{
  "type": "Feature",
  "properties": {
    "addr:full":"2316 Panola Rd Lithonia GA 30058",
    "addr:housenumber":"2316",
    "addr:postcode":"30058",
    "addr:street":"Panola Rd",
    "iso:country":"US",
    "sg:address":"2316 Panola Rd",
    "sg:city":"Lithonia",
    "sg:classifiers":[
        {
            "category":"Fast Food",
            "type":"Food & Drink"
        },
        {
            "category":"Restaurant",
            "type":"Food & Drink"
        }
    ],
    "sg:phone":"+1 770 323 7458",
    "sg:postcode":"30058",
    "sg:province":"GA",
    "sg:tags":[
        "chicken",
        "style",
        "american",
        "family",
        "take"
    ],
    "sg:website":"http://www.zaxbys.com",
    "wof:name":"Zaxby's",
    "wof:placetype":"venue"
},
  "geometry": {"coordinates":[-84.16637900000001,33.721535],"type":"Point"}
}