{
  "type": "Feature",
  "properties": {
    "addr:full":"2604 Gladstone Ter Woodstock GA 30189",
    "addr:housenumber":"2604",
    "addr:postcode":"30189",
    "addr:street":"Gladstone Ter",
    "iso:country":"US",
    "sg:address":"2604 Gladstone Ter",
    "sg:city":"Woodstock",
    "sg:classifiers":[
        {
            "category":"Building & Trades",
            "subcategory":"Construction",
            "type":"Services"
        }
    ],
    "sg:phone":"+1 770 565 8188",
    "sg:postcode":"30189",
    "sg:province":"GA",
    "sg:tags":[
        "general",
        "contractor"
    ],
    "wof:name":"Metro Construction",
    "wof:placetype":"venue"
},
  "geometry": {"coordinates":[-84.55403699999999,34.128372],"type":"Point"}
}