{
  "type": "Feature",
  "properties": {
    "iso:country":"US",
    "sg:address":"120 Ford Dr",
    "sg:city":"Lagrange",
    "sg:classifiers":[
        {
            "category":"Professional",
            "subcategory":"Business Services",
            "type":"Services"
        }
    ],
    "sg:phone":"+1 706 812 8676",
    "sg:postcode":"30240",
    "sg:province":"GA",
    "sg:tags":[
        "interior",
        "consultant",
        "design",
        "decorator"
    ],
    "wof:name":"Interiors By Mary Lee",
    "wof:placetype":"venue"
},
  "geometry": {"coordinates":[-85.060151,33.130241],"type":"Point"}
}