{
  "type": "Feature",
  "properties": {
    "addr:full":"1690 Memorial Dr SE Atlanta GA 30317",
    "addr:housenumber":"1690",
    "addr:postcode":"30317",
    "addr:street":"Memorial Dr Se",
    "iso:country":"US",
    "sg:address":"1690 Memorial Dr SE",
    "sg:city":"Atlanta",
    "sg:classifiers":[
        {
            "category":"Professional",
            "type":"Services"
        }
    ],
    "sg:phone":"+1 404 371 9775",
    "sg:postcode":"30317",
    "sg:province":"GA",
    "sg:tags":[
        "transportation"
    ],
    "wof:name":"Allied Transportation Inc",
    "wof:placetype":"venue"
},
  "geometry": {"coordinates":[-84.33253000000001,33.747459],"type":"Point"}
}