{
  "type": "Feature",
  "properties": {
    "iso:country":"US",
    "sg:address":"3037 Loridan Way SE",
    "sg:city":"Atlanta",
    "sg:classifiers":[
        {
            "category":"Professional",
            "subcategory":"Management & Consulting",
            "type":"Services"
        }
    ],
    "sg:phone":"+1 770 916 0381",
    "sg:postcode":"30339",
    "sg:province":"GA",
    "sg:tags":[
        "economic"
    ],
    "wof:name":"J A Wright and Associates",
    "wof:placetype":"venue"
},
  "geometry": {"coordinates":[-84.464905,33.867709],"type":"Point"}
}