{
  "type": "Feature",
  "properties": {
    "addr:full":"3822 Roswell Rd Marietta GA 30062",
    "addr:housenumber":"3822",
    "addr:postcode":"30062",
    "addr:street":"Roswell Rd",
    "iso:country":"US",
    "sg:address":"3822 Roswell Rd",
    "sg:city":"Marietta",
    "sg:classifiers":[
        {
            "category":"Shopping",
            "subcategory":"Clothing, Apparel, & Fashions",
            "type":"Retail Goods"
        }
    ],
    "sg:phone":"+1 770 578 6289",
    "sg:postcode":"30062",
    "sg:province":"GA",
    "sg:tags":[
        "clothing",
        "women's"
    ],
    "wof:name":"Hip Chic",
    "wof:placetype":"venue"
},
  "geometry": {"coordinates":[-84.440045,33.977914],"type":"Point"}
}