{
  "type": "Feature",
  "properties": {
    "iso:country":"US",
    "sg:address":"5841 Roswell Rd NE Ste 3",
    "sg:city":"Atlanta",
    "sg:classifiers":[
        {
            "category":"Retail",
            "subcategory":"Laundry & Dry Cleaning",
            "type":"Services"
        }
    ],
    "sg:phone":"+1 404 261 9420",
    "sg:postcode":"30328",
    "sg:province":"GA",
    "sg:tags":[
        "cleaner",
        "commercial"
    ],
    "wof:name":"Mik Cleaners",
    "wof:placetype":"venue"
},
  "geometry": {"coordinates":[-84.379276,33.914114],"type":"Point"}
}