{
  "type": "Feature",
  "properties": {
    "iso:country":"US",
    "sg:address":"506 Habersham Mill Rd",
    "sg:city":"Demorest",
    "sg:classifiers":[
        {
            "category":"Place Of Worship",
            "subcategory":"Church",
            "type":"Public Place"
        },
        {
            "category":"Place Of Worship",
            "type":"Public Place"
        }
    ],
    "sg:phone":"+1 706 754 4054",
    "sg:postcode":"30535",
    "sg:province":"GA",
    "sg:tags":[
        "churches-baptist-general",
        "churches-baptist"
    ],
    "wof:name":"Habersham Baptist Church Inc",
    "wof:placetype":"venue"
},
  "geometry": {"coordinates":[-83.533474,34.588209],"type":"Point"}
}