{
  "type": "Feature",
  "properties": {
    "iso:country":"US",
    "sg:address":"9040 Roswell Rd",
    "sg:city":"Atlanta",
    "sg:classifiers":[
        {
            "category":"Real Estate",
            "subcategory":"Real Estate Agent",
            "type":"Services"
        }
    ],
    "sg:phone":"+1 770 641 6400",
    "sg:postcode":"30350",
    "sg:province":"GA",
    "sg:tags":[
        "management"
    ],
    "wof:name":"GMH Management Inc",
    "wof:placetype":"venue"
},
  "geometry": {"coordinates":[-84.350555,34.00351],"type":"Point"}
}