{
  "type": "Feature",
  "properties": {
    "iso:country":"US",
    "sg:address":"1820 State Rte 20",
    "sg:city":"Conyers",
    "sg:classifiers":[
        {
            "category":"Shopping",
            "subcategory":"Computers & Home Electronics",
            "type":"Retail Goods"
        }
    ],
    "sg:phone":"+1 770 787 9199",
    "sg:postcode":"30013",
    "sg:province":"GA",
    "sg:tags":[
        "industry",
        "lumber",
        "for",
        "software"
    ],
    "wof:name":"Lumber Pro Inc",
    "wof:placetype":"venue"
},
  "geometry": {"coordinates":[-84.014274,33.640795],"type":"Point"}
}