{
  "type": "Feature",
  "properties": {
    "iso:country":"US",
    "sg:address":"8040 Roswell Rd",
    "sg:city":"Atlanta",
    "sg:classifiers":[
        {
            "category":"Home & Garden",
            "subcategory":"Carpets & Floor Coverings",
            "type":"Retail Goods"
        }
    ],
    "sg:phone":"+1 770 399 9110",
    "sg:postcode":"30350",
    "sg:province":"GA",
    "sg:tags":[
        "material"
    ],
    "sg:website":"http://www.greatamericanfloors.com",
    "wof:name":"Great American Floors",
    "wof:placetype":"venue"
},
  "geometry": {"coordinates":[-84.355402,33.974325],"type":"Point"}
}