{
  "type": "Feature",
  "properties": {
    "addr:full":"875 Lawrenceville Suwanee Rd Ste 5000 Lawrenceville GA 30043",
    "addr:housenumber":"875",
    "addr:postcode":"30043",
    "addr:street":"Lawrenceville Suwanee Rd Ste 5000",
    "iso:country":"US",
    "sg:address":"875 Lawrenceville Suwanee Rd Ste 5000",
    "sg:city":"Lawrenceville",
    "sg:classifiers":[
        {
            "category":"Shopping",
            "subcategory":"Department Store",
            "type":"Retail Goods"
        },
        {
            "category":"Shopping",
            "subcategory":"Clothing, Apparel, & Fashions",
            "type":"Retail Goods"
        },
        {
            "category":"Shopping",
            "subcategory":"Discount & Variety Stores",
            "type":"Retail Goods"
        }
    ],
    "sg:phone":"+1 770 339 4300",
    "sg:postcode":"30043",
    "sg:province":"GA",
    "sg:tags":[
        "clothing"
    ],
    "sg:website":"http://www.rossstores.com",
    "wof:name":"Ross Dress For Less",
    "wof:placetype":"venue"
},
  "geometry": {"coordinates":[-84.01909999999999,33.970032],"type":"Point"}
}