{
  "type": "Feature",
  "properties": {
    "addr:full":"200 Ottley Dr NE Atlanta GA 30324",
    "addr:housenumber":"200",
    "addr:postcode":"30324",
    "addr:street":"Ottley Dr Ne",
    "iso:country":"US",
    "sg:address":"200 Ottley Dr NE",
    "sg:city":"Atlanta",
    "sg:classifiers":[
        {
            "category":"Personal",
            "type":"Services"
        }
    ],
    "sg:phone":"+1 404 607 0658",
    "sg:postcode":"30324",
    "sg:province":"GA",
    "sg:tags":[
        "assistant"
    ],
    "sg:website":"http://www.parisia.com",
    "wof:name":"Parisia, Ltd.",
    "wof:placetype":"venue"
},
  "geometry": {"coordinates":[-84.381213,33.808713],"type":"Point"}
}