{
  "type": "Feature",
  "properties": {
    "iso:country":"US",
    "sg:address":"525 W Broad Ave",
    "sg:city":"Albany",
    "sg:classifiers":[
        {
            "category":"Professional",
            "subcategory":"Lawyer & Legal Services",
            "type":"Services"
        }
    ],
    "sg:phone":"+1 229 435 0021",
    "sg:postcode":"31701",
    "sg:province":"GA",
    "sg:tags":[
        "attorney"
    ],
    "wof:name":"Wingate & Mitchell",
    "wof:placetype":"venue"
},
  "geometry": {"coordinates":[-84.160053,31.577032],"type":"Point"}
}