{
  "type": "Feature",
  "properties": {
    "iso:country":"US",
    "sg:address":"10430 Ivygate Ter",
    "sg:city":"Jonesboro",
    "sg:classifiers":[
        {
            "category":"Professional",
            "subcategory":"Business Services",
            "type":"Services"
        }
    ],
    "sg:phone":"+1 770 472 3678",
    "sg:postcode":"30238",
    "sg:province":"GA",
    "wof:name":"Michelles Celestial Design",
    "wof:placetype":"venue"
},
  "geometry": {"coordinates":[-84.361926,33.472308],"type":"Point"}
}