{
  "type": "Feature",
  "properties": {
    "addr:full":"1040 Old Mill Dr Watkinsville GA 30677",
    "addr:housenumber":"1040",
    "addr:postcode":"30677",
    "addr:street":"Old Mill Dr",
    "iso:country":"US",
    "sg:address":"1040 Old Mill Dr",
    "sg:city":"Watkinsville",
    "sg:classifiers":[
        {
            "category":"Building & Trades",
            "subcategory":"Construction",
            "type":"Services"
        }
    ],
    "sg:phone":"+1 706 207 3901",
    "sg:postcode":"30677",
    "sg:province":"GA",
    "sg:tags":[
        "carport"
    ],
    "wof:name":"Custom Carports",
    "wof:placetype":"venue"
},
  "geometry": {"coordinates":[-83.325103,33.846802],"type":"Point"}
}