{
  "type": "Feature",
  "properties": {
    "iso:country":"US",
    "sg:address":"504 Fond du Lac Dr",
    "sg:city":"Stone Mountain",
    "sg:classifiers":[
        {
            "category":"Shopping",
            "subcategory":"Gifts & Souvenirs",
            "type":"Retail Goods"
        }
    ],
    "sg:phone":"+1 770 498 4610",
    "sg:postcode":"30088",
    "sg:province":"GA",
    "wof:name":"Annie Maes Gift Gallery",
    "wof:placetype":"venue"
},
  "geometry": {"coordinates":[-84.186398,33.782537],"type":"Point"}
}