{
  "type": "Feature",
  "properties": {
    "iso:country":"US",
    "sg:address":"2801 Dekalb Medical Pkwy",
    "sg:city":"Lithonia",
    "sg:classifiers":[
        {
            "category":"Health Services",
            "subcategory":"Hospital",
            "type":"Services"
        }
    ],
    "sg:phone":"+1 404 501 8000",
    "sg:postcode":"30058",
    "sg:province":"GA",
    "sg:website":"www.dekalbmedical.org",
    "wof:name":"Dekalb Medical",
    "wof:placetype":"venue"
},
  "geometry": {"coordinates":[-84.147051,33.706558],"type":"Point"}
}