{
  "type": "Feature",
  "properties": {
    "addr:full":"146 Evergreen Dr Villa Rica GA 30180",
    "addr:housenumber":"146",
    "addr:postcode":"30180",
    "addr:street":"Evergreen Dr",
    "iso:country":"US",
    "sg:address":"146 Evergreen Dr",
    "sg:city":"Villa Rica",
    "sg:classifiers":[
        {
            "category":"Professional",
            "subcategory":"Business Services",
            "type":"Services"
        }
    ],
    "sg:phone":"+1 770 456 9116",
    "sg:postcode":"30180",
    "sg:province":"GA",
    "wof:name":"Affordable Business Solutions",
    "wof:placetype":"venue"
},
  "geometry": {"coordinates":[-84.943477,33.715508],"type":"Point"}
}