{
  "type": "Feature",
  "properties": {
    "addr:full":"1695 Russells Pond Ln Lawrenceville GA 30043",
    "addr:housenumber":"1695",
    "addr:postcode":"30043",
    "addr:street":"Russells Pond Ln",
    "iso:country":"US",
    "sg:address":"1695 Russells Pond Ln",
    "sg:city":"Lawrenceville",
    "sg:classifiers":[
        {
            "category":"Professional",
            "subcategory":"Computer Services",
            "type":"Services"
        }
    ],
    "sg:phone":"+1 678 488 0634",
    "sg:postcode":"30043",
    "sg:province":"GA",
    "sg:tags":[
        "consulting",
        "technology"
    ],
    "wof:name":"ECR Consulting LLC",
    "wof:placetype":"venue"
},
  "geometry": {"coordinates":[-83.99840399999999,34.004189],"type":"Point"}
}