{
  "type": "Feature",
  "properties": {
    "addr:full":"811 Pio Nono Ave Macon GA 31204",
    "addr:postcode":"31204",
    "addr:street":"Pio Nono Ave",
    "iso:country":"US",
    "sg:address":"811 Pio Nono Ave",
    "sg:city":"Macon",
    "sg:classifiers":[
        {
            "category":"Food & Beverages",
            "subcategory":"Groceries & Convenience Stores",
            "type":"Retail Goods"
        }
    ],
    "sg:phone":"+1 478 746 0099",
    "sg:postcode":"31204",
    "sg:province":"GA",
    "wof:name":"Tom's Food Mart",
    "wof:placetype":"venue"
},
  "geometry": {"coordinates":[-83.66251200000001,32.839342],"type":"Point"}
}