{
  "type": "Feature",
  "properties": {
    "addr:full":"4112 Radcliffe Ct Decatur GA 30034",
    "addr:housenumber":"4112",
    "addr:postcode":"30034",
    "addr:street":"Radcliffe Ct",
    "iso:country":"US",
    "sg:address":"4112 Radcliffe Ct",
    "sg:city":"Decatur",
    "sg:classifiers":[
        {
            "category":"Retail",
            "subcategory":"Repair Shop",
            "type":"Services"
        }
    ],
    "sg:phone":"+1 770 322 0014",
    "sg:postcode":"30034",
    "sg:province":"GA",
    "sg:tags":[
        "reupholstery",
        "upholsterer",
        "furniture"
    ],
    "wof:name":"Alright Upholstery Shop",
    "wof:placetype":"venue"
},
  "geometry": {"coordinates":[-84.220001,33.678902],"type":"Point"}
}