{
  "type": "Feature",
  "properties": {
    "addr:full":"356 Peachtree St NE Pelham GA 31779",
    "addr:housenumber":"356",
    "addr:postcode":"31779",
    "addr:street":"Peachtree St Ne",
    "iso:country":"US",
    "sg:address":"356 Peachtree St NE",
    "sg:city":"Pelham",
    "sg:classifiers":[
        {
            "category":"Wholesale",
            "subcategory":"Auto Parts",
            "type":"Manufacturing & Wholesale Goods"
        }
    ],
    "sg:phone":"+1 229 294 4084",
    "sg:postcode":"31779",
    "sg:province":"GA",
    "sg:tags":[
        "tire"
    ],
    "wof:name":"Beall Tire Co",
    "wof:placetype":"venue"
},
  "geometry": {"coordinates":[-84.147014,31.133517],"type":"Point"}
}