{
  "type": "Feature",
  "properties": {
    "addr:full":"3230 Medlock Bridge Rd Norcross GA 30092",
    "addr:housenumber":"3230",
    "addr:postcode":"30092",
    "addr:street":"Medlock Bridge Rd",
    "iso:country":"US",
    "sg:address":"3230 Medlock Bridge Rd",
    "sg:city":"Norcross",
    "sg:classifiers":[
        {
            "category":"Restaurant",
            "type":"Food & Drink"
        }
    ],
    "sg:menulink":"http://www.allmenus.com/ga/norcross/132618-subway/menu/",
    "sg:phone":"+1 770 729 8771",
    "sg:postcode":"30092",
    "sg:province":"GA",
    "sg:tags":[
        "american",
        "sandwich"
    ],
    "wof:name":"Subway",
    "wof:placetype":"venue"
},
  "geometry": {"coordinates":[-84.207303,33.962931],"type":"Point"}
}