{
  "type": "Feature",
  "properties": {
    "addr:full":"736 Emerald Forest Cir SW Lawrenceville GA 30044",
    "addr:housenumber":"736",
    "addr:postcode":"30044",
    "addr:street":"Emerald Forest Cir Sw",
    "iso:country":"US",
    "sg:address":"736 Emerald Forest Cir SW",
    "sg:city":"Lawrenceville",
    "sg:classifiers":[
        {
            "category":"Building & Trades",
            "subcategory":"Landscaping Services",
            "type":"Services"
        }
    ],
    "sg:phone":"+1 770 985 2788",
    "sg:postcode":"30044",
    "sg:province":"GA",
    "sg:tags":[
        "landscape",
        "contractor"
    ],
    "wof:name":"Daniel Landscaping",
    "wof:placetype":"venue"
},
  "geometry": {"coordinates":[-84.044956,33.895982],"type":"Point"}
}