{
  "type": "Feature",
  "properties": {
    "iso:country":"US",
    "sg:address":"4553 Woodruff Rd",
    "sg:city":"Columbus",
    "sg:classifiers":[
        {
            "category":"Restaurant",
            "type":"Food & Drink"
        }
    ],
    "sg:menulink":"http://www.allmenus.com/ga/columbus/94241-mi-casa/menu/",
    "sg:phone":"+1 706 327 2248",
    "sg:postcode":"31904",
    "sg:province":"GA",
    "sg:tags":[
        "mexican"
    ],
    "wof:name":"Mi Casa",
    "wof:placetype":"venue"
},
  "geometry": {"coordinates":[-84.96199799999999,32.509417],"type":"Point"}
}