{
  "type": "Feature",
  "properties": {
    "addr:full":"1649 Sands Pl Marietta GA 30067",
    "addr:housenumber":"1649",
    "addr:postcode":"30067",
    "addr:street":"Sands Pl",
    "iso:country":"US",
    "sg:address":"1649 Sands Pl",
    "sg:city":"Marietta",
    "sg:classifiers":[
        {
            "category":"Manufacturing",
            "subcategory":"Tools & Machinery",
            "type":"Manufacturing & Wholesale Goods"
        }
    ],
    "sg:phone":"+1 770 952 3337",
    "sg:postcode":"30067",
    "sg:province":"GA",
    "sg:tags":[
        "physician",
        "surgeon"
    ],
    "wof:name":"Tri State Hospital Supply",
    "wof:placetype":"venue"
},
  "geometry": {"coordinates":[-84.493618,33.914912],"type":"Point"}
}