{
  "type": "Feature",
  "properties": {
    "addr:full":"131 Johns Blf Auburn GA 30011",
    "addr:housenumber":"131",
    "addr:postcode":"30011",
    "addr:street":"Johns Blf",
    "iso:country":"US",
    "sg:address":"131 Johns Blf",
    "sg:city":"Auburn",
    "sg:classifiers":[
        {
            "category":"Real Estate",
            "subcategory":"Real Estate Services",
            "type":"Services"
        },
        {
            "category":"Real Estate",
            "subcategory":"Real Estate Agent",
            "type":"Services"
        }
    ],
    "sg:phone":"+1 770 682 0758",
    "sg:postcode":"30011",
    "sg:province":"GA",
    "sg:tags":[
        "buyer",
        "broker"
    ],
    "wof:name":"Preston Properties Realty",
    "wof:placetype":"venue"
},
  "geometry": {"coordinates":[-83.81988200000001,33.999354],"type":"Point"}
}