{
  "type": "Feature",
  "properties": {
    "addr:full":"1343 Steeple Run Lawrenceville GA 30043",
    "addr:housenumber":"1343",
    "addr:postcode":"30043",
    "iso:country":"US",
    "sg:address":"1343 Steeple Run",
    "sg:city":"Lawrenceville",
    "sg:classifiers":[
        {
            "category":"Manufacturing",
            "subcategory":"Signs",
            "type":"Manufacturing & Wholesale Goods"
        }
    ],
    "sg:phone":"+1 770 682 3994",
    "sg:postcode":"30043",
    "sg:province":"GA",
    "sg:tags":[
        "specialty",
        "mfg"
    ],
    "wof:name":"Shakir & Company Inc",
    "wof:placetype":"venue"
},
  "geometry": {"coordinates":[-84.062485,33.992773],"type":"Point"}
}