{
  "type": "Feature",
  "properties": {
    "addr:full":"1630 Martin Luther King Jr Dr Greensboro GA 30642",
    "addr:housenumber":"1630",
    "addr:postcode":"30642",
    "addr:street":"Martin Luther King Jr Dr",
    "iso:country":"US",
    "sg:address":"1630 Martin Luther King Jr Dr",
    "sg:city":"Greensboro",
    "sg:classifiers":[
        {
            "category":"Professional",
            "subcategory":"Business Services",
            "type":"Services"
        }
    ],
    "sg:phone":"+1 706 453 9283",
    "sg:postcode":"30642",
    "sg:province":"GA",
    "sg:tags":[
        "consultant",
        "coach"
    ],
    "wof:name":"Hutchinson House Holiness Label",
    "wof:placetype":"venue"
},
  "geometry": {"coordinates":[-83.17411,33.56041],"type":"Point"}
}