{
  "type": "Feature",
  "properties": {
    "addr:full":"2144 Hills Ave NW Atlanta GA 30318",
    "addr:housenumber":"2144",
    "addr:postcode":"30318",
    "addr:street":"Hills Ave Nw",
    "iso:country":"US",
    "sg:address":"2144 Hills Ave NW",
    "sg:city":"Atlanta",
    "sg:classifiers":[
        {
            "category":"Manufacturing",
            "subcategory":"Printing",
            "type":"Manufacturing & Wholesale Goods"
        }
    ],
    "sg:phone":"+1 404 351 6659",
    "sg:postcode":"30318",
    "sg:province":"GA",
    "sg:tags":[
        "w",
        "high",
        "copying",
        "offset",
        "document",
        "speed"
    ],
    "wof:name":"Copy Express",
    "wof:placetype":"venue"
},
  "geometry": {"coordinates":[-84.43093500000001,33.814113],"type":"Point"}
}