{
  "type": "Feature",
  "properties": {
    "iso:country":"US",
    "sg:address":"3428 Hickory Grove Rd N",
    "sg:city":"Valdosta",
    "sg:classifiers":[
        {
            "category":"Banks & Credit Unions",
            "subcategory":"Financial Services",
            "type":"Services"
        }
    ],
    "sg:phone":"+1 229 249 9695",
    "sg:postcode":"31606",
    "sg:province":"GA",
    "sg:tags":[
        "trust",
        "nonprofit",
        "management"
    ],
    "wof:name":"Katherine P Foundati",
    "wof:placetype":"venue"
},
  "geometry": {"coordinates":[-83.22283899999999,30.791571],"type":"Point"}
}