{
  "type": "Feature",
  "properties": {
    "addr:full":"303 W Main St Hahira GA 31632",
    "addr:housenumber":"303",
    "addr:postcode":"31632",
    "addr:street":"W Main St",
    "iso:country":"US",
    "sg:address":"303 W Main St",
    "sg:city":"Hahira",
    "sg:classifiers":[
        {
            "category":"Bars & Pubs",
            "type":"Food & Drink"
        },
        {
            "category":"Restaurant",
            "type":"Food & Drink"
        },
        {
            "category":"Bars & Pubs",
            "subcategory":"Lounge",
            "type":"Food & Drink"
        }
    ],
    "sg:phone":"+1 229 794 1664",
    "sg:postcode":"31632",
    "sg:province":"GA",
    "sg:tags":[
        "cocktail"
    ],
    "wof:name":"Smack Mama Cafe And Pub",
    "wof:placetype":"venue"
},
  "geometry": {"coordinates":[-83.375252,30.990738],"type":"Point"}
}