{
  "type": "Feature",
  "properties": {
    "iso:country":"US",
    "sg:address":"304 Broken Bit Way",
    "sg:city":"Peachtree City",
    "sg:classifiers":[
        {
            "category":"Professional",
            "subcategory":"Business Services",
            "type":"Services"
        }
    ],
    "sg:phone":"+1 770 251 8968",
    "sg:postcode":"30269",
    "sg:province":"GA",
    "wof:name":"Prospect Park Assoc",
    "wof:placetype":"venue"
},
  "geometry": {"coordinates":[-84.556707,33.400913],"type":"Point"}
}