{
  "type": "Feature",
  "properties": {
    "addr:full":"640 Allgood Rd Stone Mountain GA 30083",
    "addr:housenumber":"640",
    "addr:postcode":"30083",
    "addr:street":"Allgood Rd",
    "iso:country":"US",
    "sg:address":"640 Allgood Rd",
    "sg:city":"Stone Mountain",
    "sg:classifiers":[
        {
            "category":"Organizations",
            "subcategory":"Religious Organization",
            "type":"Services"
        }
    ],
    "sg:phone":"+1 404 292 1005",
    "sg:postcode":"30083",
    "sg:province":"GA",
    "sg:tags":[
        "church"
    ],
    "sg:website":"www.umc.org",
    "wof:name":"Allgood Road United Methodist Church",
    "wof:placetype":"venue"
},
  "geometry": {"coordinates":[-84.2118,33.778599],"type":"Point"}
}