{
  "type": "Feature",
  "properties": {
    "addr:full":"1453 Calvin Murphy Rd Grantville GA 30220",
    "addr:housenumber":"1453",
    "addr:postcode":"30220",
    "addr:street":"Calvin Murphy Rd",
    "iso:country":"US",
    "sg:address":"1453 Calvin Murphy Rd",
    "sg:city":"Grantville",
    "sg:classifiers":[
        {
            "category":"Building & Trades",
            "subcategory":"Construction",
            "type":"Services"
        }
    ],
    "sg:phone":"+1 770 927 9061",
    "sg:postcode":"30220",
    "sg:province":"GA",
    "sg:tags":[
        "hanging",
        "contractor"
    ],
    "wof:name":"Tib S Painting",
    "wof:placetype":"venue"
},
  "geometry": {"coordinates":[-84.77431,33.216469],"type":"Point"}
}