{
  "type": "Feature",
  "properties": {
    "iso:country":"US",
    "sg:address":"3997 Lawrenceville Hwy",
    "sg:city":"Lilburn",
    "sg:classifiers":[
        {
            "category":"Health Services",
            "subcategory":"Doctor",
            "type":"Services"
        }
    ],
    "sg:phone":"+1 770 921 3641",
    "sg:postcode":"30047",
    "sg:province":"GA",
    "wof:name":"Huff Calvin W DDS PC",
    "wof:placetype":"venue"
},
  "geometry": {"coordinates":[-84.115201,33.904068],"type":"Point"}
}