{
  "type": "Feature",
  "properties": {
    "addr:full":"107 The Ridge Ct Newnan GA 30265",
    "addr:housenumber":"107",
    "addr:postcode":"30265",
    "addr:street":"The Ridge Ct",
    "iso:country":"US",
    "sg:address":"107 The Ridge Ct",
    "sg:city":"Newnan",
    "sg:classifiers":[
        {
            "category":"Building & Trades",
            "subcategory":"Construction",
            "type":"Services"
        }
    ],
    "sg:phone":"+1 770 502 8438",
    "sg:postcode":"30265",
    "sg:province":"GA",
    "sg:tags":[
        "restoration",
        "cleaning",
        "patio",
        "deck"
    ],
    "wof:name":"Quality Window & Pressure Cln",
    "wof:placetype":"venue"
},
  "geometry": {"coordinates":[-84.638366,33.38943],"type":"Point"}
}