{
  "type": "Feature",
  "properties": {
    "addr:full":"1805 Kelleytown Rd Mc Donough GA 30252",
    "addr:housenumber":"1805",
    "addr:postcode":"30252",
    "addr:street":"Kelleytown Rd",
    "iso:country":"US",
    "sg:address":"1805 Kelleytown Rd",
    "sg:city":"Mc Donough",
    "sg:classifiers":[
        {
            "category":"Restaurant",
            "type":"Food & Drink"
        }
    ],
    "sg:phone":"+1 678 432 5847",
    "sg:postcode":"30252",
    "sg:province":"GA",
    "sg:tags":[
        "eating"
    ],
    "wof:name":"Fats Wings",
    "wof:placetype":"venue"
},
  "geometry": {"coordinates":[-84.090283,33.537785],"type":"Point"}
}