{
  "type": "Feature",
  "properties": {
    "addr:full":"2700 Dawson Rd Albany GA 31707",
    "addr:housenumber":"2700",
    "addr:postcode":"31707",
    "addr:street":"Dawson Rd",
    "iso:country":"US",
    "sg:address":"2700 Dawson Rd",
    "sg:city":"Albany",
    "sg:classifiers":[
        {
            "category":"Fast Food",
            "type":"Food & Drink"
        },
        {
            "category":"Restaurant",
            "type":"Food & Drink"
        }
    ],
    "sg:phone":"+1 229 435 8448",
    "sg:postcode":"31707",
    "sg:province":"GA",
    "sg:tags":[
        "mexican",
        "take"
    ],
    "wof:name":"El Vaquero Mexican Restaurant",
    "wof:placetype":"venue"
},
  "geometry": {"coordinates":[-84.2229,31.61832],"type":"Point"}
}