{
  "type": "Feature",
  "properties": {
    "addr:full":"100 Sweetgum Cir Canton GA 30115",
    "addr:housenumber":"100",
    "addr:postcode":"30115",
    "addr:street":"Sweetgum Cir",
    "iso:country":"US",
    "sg:address":"100 Sweetgum Cir",
    "sg:city":"Canton",
    "sg:classifiers":[
        {
            "category":"Professional",
            "subcategory":"Business Services",
            "type":"Services"
        }
    ],
    "sg:phone":"+1 770 345 1897",
    "sg:postcode":"30115",
    "sg:province":"GA",
    "sg:tags":[
        "building",
        "maintenance"
    ],
    "wof:name":"Hoods Unlimited",
    "wof:placetype":"venue"
},
  "geometry": {"coordinates":[-84.508668,34.169899],"type":"Point"}
}