{
  "type": "Feature",
  "properties": {
    "addr:full":"311 W Broome St La Grange GA 30240",
    "addr:housenumber":"311",
    "addr:postcode":"30240",
    "addr:street":"W Broome St",
    "iso:country":"US",
    "sg:address":"311 W Broome St",
    "sg:city":"La Grange",
    "sg:classifiers":[
        {
            "category":"Insurance",
            "subcategory":"Insurance Agent",
            "type":"Services"
        }
    ],
    "sg:phone":"+1 706 882 0018",
    "sg:postcode":"30240",
    "sg:province":"GA",
    "wof:name":"State Farm Insurance",
    "wof:placetype":"venue"
},
  "geometry": {"coordinates":[-85.034972,33.03734],"type":"Point"}
}