{
  "type": "Feature",
  "properties": {
    "addr:full":"11763 Bells Ferry Rd Canton GA 30114",
    "addr:housenumber":"11763",
    "addr:postcode":"30114",
    "addr:street":"Bells Ferry Rd",
    "iso:country":"US",
    "sg:address":"11763 Bells Ferry Rd",
    "sg:city":"Canton",
    "sg:classifiers":[
        {
            "category":"Professional",
            "type":"Services"
        }
    ],
    "sg:phone":"+1 770 720 4500",
    "sg:postcode":"30114",
    "sg:province":"GA",
    "wof:name":"Jeff Pettigrew",
    "wof:placetype":"venue"
},
  "geometry": {"coordinates":[-84.52231399999999,34.206188],"type":"Point"}
}