{
  "type": "Feature",
  "properties": {
    "iso:country":"US",
    "sg:address":"10 10th St NW Ste 175",
    "sg:city":"Atlanta",
    "sg:classifiers":[
        {
            "category":"Parking",
            "type":"Transportation"
        },
        {
            "category":"Parking",
            "subcategory":"Garage",
            "type":"Transportation"
        }
    ],
    "sg:phone":"+1 404 815 1854",
    "sg:postcode":"30309",
    "sg:province":"GA",
    "sg:tags":[
        "attendant",
        "lot"
    ],
    "wof:name":"Central Perk Midtown",
    "wof:placetype":"venue"
},
  "geometry": {"coordinates":[-84.38799299999999,33.781492],"type":"Point"}
}