{
  "type": "Feature",
  "properties": {
    "iso:country":"US",
    "sg:address":"1721 Apalachee Woods Trl",
    "sg:city":"Buckhead",
    "sg:classifiers":[
        {
            "category":"Building & Trades",
            "subcategory":"Construction",
            "type":"Services"
        }
    ],
    "sg:phone":"+1 706 342 8933",
    "sg:postcode":"30625",
    "sg:province":"GA",
    "sg:tags":[
        "house"
    ],
    "wof:name":"Honey Do Home Repair Inc",
    "wof:placetype":"venue"
},
  "geometry": {"coordinates":[-83.329454,33.578365],"type":"Point"}
}