{
  "type": "Feature",
  "properties": {
    "iso:country":"US",
    "sg:address":"44 Lakeland Dr NW",
    "sg:city":"Atlanta",
    "sg:classifiers":[
        {
            "category":"Professional",
            "subcategory":"Business Services",
            "type":"Services"
        }
    ],
    "sg:phone":"+1 404 228 2187",
    "sg:postcode":"30305",
    "sg:province":"GA",
    "wof:name":"Hanna Medley Interiors",
    "wof:placetype":"venue"
},
  "geometry": {"coordinates":[-84.386436,33.848864],"type":"Point"}
}