{
  "type": "Feature",
  "properties": {
    "iso:country":"US",
    "sg:address":"358 E Wesley Rd NE",
    "sg:city":"Atlanta",
    "sg:classifiers":[
        {
            "category":"Banks & Credit Unions",
            "subcategory":"Bank",
            "type":"Services"
        },
        {
            "category":"Shopping",
            "subcategory":"Used Merchandise",
            "type":"Retail Goods"
        }
    ],
    "sg:phone":"+1 404 848 1457",
    "sg:postcode":"30305",
    "sg:province":"GA",
    "sg:tags":[
        "resale",
        "shop",
        "second",
        "hand"
    ],
    "wof:name":"Five Arches Imports & Antiques",
    "wof:placetype":"venue"
},
  "geometry": {"coordinates":[-84.376133,33.828643],"type":"Point"}
}