{
  "type": "Feature",
  "properties": {
    "iso:country":"US",
    "sg:address":"2230 Flat Rock Rd",
    "sg:city":"Watkinsville",
    "sg:classifiers":[
        {
            "category":"Building & Trades",
            "subcategory":"Plumbing",
            "type":"Services"
        }
    ],
    "sg:phone":"+1 706 769 6405",
    "sg:postcode":"30677",
    "sg:province":"GA",
    "sg:tags":[
        "contractor"
    ],
    "wof:name":"Marshall Mechanical",
    "wof:placetype":"venue"
},
  "geometry": {"coordinates":[-83.345108,33.837246],"type":"Point"}
}