{
  "type": "Feature",
  "properties": {
    "addr:full":"1933 Highway 34 E Newnan GA 30265",
    "addr:housenumber":"1933",
    "addr:postcode":"30265",
    "addr:street":"Highway 34 E",
    "iso:country":"US",
    "sg:address":"1933 Highway 34 E",
    "sg:city":"Newnan",
    "sg:classifiers":[
        {
            "category":"Organizations",
            "subcategory":"Community Association",
            "type":"Services"
        }
    ],
    "sg:phone":"+1 770 683 0990",
    "sg:postcode":"30265",
    "sg:province":"GA",
    "wof:name":"Newnan Coweta Board of Realtor",
    "wof:placetype":"venue"
},
  "geometry": {"coordinates":[-84.702851,33.405199],"type":"Point"}
}