{
  "type": "Feature",
  "properties": {
    "iso:country":"US",
    "sg:address":"2207 N Hill Pkwy",
    "sg:city":"Atlanta",
    "sg:classifiers":[
        {
            "category":"Real Estate",
            "subcategory":"Real Estate Services",
            "type":"Services"
        },
        {
            "category":"Building & Trades",
            "subcategory":"Cleaning & Sanitation",
            "type":"Services"
        }
    ],
    "sg:phone":"+1 678 227 1238",
    "sg:postcode":"30341",
    "sg:province":"GA",
    "sg:tags":[
        "maintenance",
        "cleaners-interior"
    ],
    "wof:name":"Rqf Cleaning Service",
    "wof:placetype":"venue"
},
  "geometry": {"coordinates":[-84.296159,33.914813],"type":"Point"}
}