{
  "type": "Feature",
  "properties": {
    "addr:full":"3078 Clairmont Rd NE Atlanta GA 30329",
    "addr:housenumber":"3078",
    "addr:postcode":"30329",
    "addr:street":"Clairmont Rd Ne",
    "iso:country":"US",
    "sg:address":"3078 Clairmont Rd NE",
    "sg:city":"Atlanta",
    "sg:classifiers":[
        {
            "category":"Local Transit",
            "type":"Transportation"
        }
    ],
    "sg:phone":"+1 404 897 5611",
    "sg:postcode":"30329",
    "sg:province":"GA",
    "sg:tags":[
        "limousine"
    ],
    "wof:name":"Dunwoody Limousine Svc",
    "wof:placetype":"venue"
},
  "geometry": {"coordinates":[-84.31550900000001,33.847363],"type":"Point"}
}