{
  "type": "Feature",
  "properties": {
    "addr:full":"3952 Woburn Dr Tucker GA 30084",
    "addr:housenumber":"3952",
    "addr:postcode":"30084",
    "addr:street":"Woburn Dr",
    "iso:country":"US",
    "sg:address":"3952 Woburn Dr",
    "sg:city":"Tucker",
    "sg:classifiers":[
        {
            "category":"Education",
            "subcategory":"Special Training",
            "type":"Public Place"
        }
    ],
    "sg:phone":"+1 770 939 1333",
    "sg:postcode":"30084",
    "sg:province":"GA",
    "wof:name":"Private Piano Teacher",
    "wof:placetype":"venue"
},
  "geometry": {"coordinates":[-84.228174,33.840662],"type":"Point"}
}