{
  "type": "Feature",
  "properties": {
    "iso:country":"US",
    "sg:address":"2647 Warwick Cir NE",
    "sg:city":"Atlanta",
    "sg:classifiers":[
        {
            "category":"Communications",
            "type":"Services"
        }
    ],
    "sg:phone":"+1 404 634 5788",
    "sg:postcode":"30345",
    "sg:province":"GA",
    "sg:tags":[
        "communication"
    ],
    "wof:name":"Jerry Immel Voiceovers",
    "wof:placetype":"venue"
},
  "geometry": {"coordinates":[-84.302814,33.862513],"type":"Point"}
}