{
  "type": "Feature",
  "properties": {
    "addr:full":"280 Camp Osborn Rd Sylvester GA 31791",
    "addr:housenumber":"280",
    "addr:postcode":"31791",
    "addr:street":"Camp Osborn Rd",
    "iso:country":"US",
    "sg:address":"280 Camp Osborn Rd",
    "sg:city":"Sylvester",
    "sg:classifiers":[
        {
            "category":"Professional",
            "type":"Services"
        },
        {
            "category":"Building & Trades",
            "subcategory":"Construction",
            "type":"Services"
        }
    ],
    "sg:phone":"+1 229 881 0558",
    "sg:postcode":"31791",
    "sg:province":"GA",
    "sg:tags":[
        "restoration",
        "cleaning",
        "patio",
        "deck"
    ],
    "wof:name":"Darryl Goodman Pressure Clnng",
    "wof:placetype":"venue"
},
  "geometry": {"coordinates":[-83.94511,31.644209],"type":"Point"}
}