{
  "type": "Feature",
  "properties": {
    "iso:country":"US",
    "sg:address":"5835 Live Oak Pkwy",
    "sg:city":"Norcross",
    "sg:classifiers":[
        {
            "category":"Insurance",
            "subcategory":"Insurance Agent",
            "type":"Services"
        }
    ],
    "sg:phone":"+1 770 416 1100",
    "sg:postcode":"30093",
    "sg:province":"GA",
    "sg:tags":[
        "consultant",
        "analyst"
    ],
    "wof:name":"Aflac",
    "wof:placetype":"venue"
},
  "geometry": {"coordinates":[-84.20071799999999,33.912829],"type":"Point"}
}