{
  "type": "Feature",
  "properties": {
    "addr:full":"1925 Coventry Way Jonesboro GA 30236",
    "addr:housenumber":"1925",
    "addr:postcode":"30236",
    "addr:street":"Coventry Way",
    "iso:country":"US",
    "sg:address":"1925 Coventry Way",
    "sg:city":"Jonesboro",
    "sg:classifiers":[
        {
            "category":"Building & Trades",
            "subcategory":"Cleaning & Sanitation",
            "type":"Services"
        }
    ],
    "sg:phone":"+1 770 210 3329",
    "sg:postcode":"30236",
    "sg:province":"GA",
    "sg:tags":[
        "maintenance"
    ],
    "wof:name":"By Faith Cleaning Service",
    "wof:placetype":"venue"
},
  "geometry": {"coordinates":[-84.32584300000001,33.542634],"type":"Point"}
}