{
  "type": "Feature",
  "properties": {
    "addr:full":"2440 Cobb Pkwy S Smyrna GA 30080",
    "addr:housenumber":"2440",
    "addr:postcode":"30080",
    "addr:street":"Cobb Pkwy S",
    "iso:country":"US",
    "sg:address":"2440 Cobb Pkwy S",
    "sg:city":"Smyrna",
    "sg:classifiers":[
        {
            "category":"Manufacturing",
            "subcategory":"Tools & Machinery",
            "type":"Manufacturing & Wholesale Goods"
        }
    ],
    "sg:phone":"+1 770 984 0013",
    "sg:postcode":"30080",
    "sg:province":"GA",
    "wof:name":"Corporate Binding Solutions",
    "wof:placetype":"venue"
},
  "geometry": {"coordinates":[-84.477716,33.892241],"type":"Point"}
}