{
  "type": "Feature",
  "properties": {
    "iso:country":"US",
    "sg:address":"119 Broadview Ter",
    "sg:city":"Dalton",
    "sg:classifiers":[
        {
            "category":"Home & Garden",
            "subcategory":"Carpets & Floor Coverings",
            "type":"Retail Goods"
        }
    ],
    "sg:phone":"+1 706 277 3341",
    "sg:postcode":"30720",
    "sg:province":"GA",
    "sg:tags":[
        "dealer",
        "rug"
    ],
    "sg:website":"www.majorcarpets.com",
    "wof:name":"Major Carpets Inc",
    "wof:placetype":"venue"
},
  "geometry": {"coordinates":[-84.999779,34.762525],"type":"Point"}
}