{
  "type": "Feature",
  "properties": {
    "addr:full":"3073 Peachtree Dr NE Atlanta GA 30305",
    "addr:housenumber":"3073",
    "addr:postcode":"30305",
    "addr:street":"Peachtree Dr Ne",
    "iso:country":"US",
    "sg:address":"3073 Peachtree Dr NE",
    "sg:city":"Atlanta",
    "sg:classifiers":[
        {
            "category":"Bars & Pubs",
            "type":"Food & Drink"
        }
    ],
    "sg:phone":"+1 404 869 1511",
    "sg:postcode":"30305",
    "sg:province":"GA",
    "sg:tags":[
        "lounge",
        "cocktail"
    ],
    "wof:name":"Babylon",
    "wof:placetype":"venue"
},
  "geometry": {"coordinates":[-84.366556,33.838657],"type":"Point"}
}