{
  "type": "Feature",
  "properties": {
    "iso:country":"US",
    "sg:address":"925 Walker Dr",
    "sg:city":"Locust Grove",
    "sg:classifiers":[
        {
            "category":"Shopping",
            "type":"Retail Goods"
        }
    ],
    "sg:phone":"+1 770 957 1539",
    "sg:postcode":"30248",
    "sg:province":"GA",
    "sg:tags":[
        "coin",
        "dealer",
        "supply"
    ],
    "wof:name":"A Leak Spec Pilgrims Point",
    "wof:placetype":"venue"
},
  "geometry": {"coordinates":[-84.207657,33.377042],"type":"Point"}
}