{
  "type": "Feature",
  "properties": {
    "addr:full":"155 Commerce Dr Fayetteville GA 30214",
    "addr:housenumber":"155",
    "addr:postcode":"30214",
    "addr:street":"Commerce Dr",
    "iso:country":"US",
    "sg:address":"155 Commerce Dr",
    "sg:city":"Fayetteville",
    "sg:classifiers":[
        {
            "category":"Manufacturing",
            "subcategory":"Printing",
            "type":"Manufacturing & Wholesale Goods"
        }
    ],
    "sg:phone":"+1 770 460 0704",
    "sg:postcode":"30214",
    "sg:province":"GA",
    "sg:tags":[
        "lithographic",
        "commercial"
    ],
    "wof:name":"A Plus Printing",
    "wof:placetype":"venue"
},
  "geometry": {"coordinates":[-84.450822,33.46409],"type":"Point"}
}