{
  "type": "Feature",
  "properties": {
    "iso:country":"US",
    "sg:address":"100 N Valdosta Rd",
    "sg:city":"Valdosta",
    "sg:classifiers":[
        {
            "category":"Autos & Motor Vehicles",
            "subcategory":"Automobile Sales",
            "type":"Retail Goods"
        }
    ],
    "sg:phone":"+1 229 242 5277",
    "sg:postcode":"31602",
    "sg:province":"GA",
    "sg:tags":[
        "used"
    ],
    "wof:name":"Tillman Motors",
    "wof:placetype":"venue"
},
  "geometry": {"coordinates":[-83.29321299999999,30.877167],"type":"Point"}
}