{
  "type": "Feature",
  "properties": {
    "iso:country":"US",
    "sg:address":"3015 Windward Plz",
    "sg:city":"Alpharetta",
    "sg:classifiers":[
        {
            "category":"Professional",
            "type":"Services"
        }
    ],
    "sg:phone":"+1 770 475 0943",
    "sg:postcode":"30005",
    "sg:province":"GA",
    "sg:tags":[
        "establishment"
    ],
    "wof:name":"Childress Klein Ww11",
    "wof:placetype":"venue"
},
  "geometry": {"coordinates":[-84.239949,34.093221],"type":"Point"}
}