{
  "type": "Feature",
  "properties": {
    "iso:country":"US",
    "sg:address":"304 Bennett Grooms Rd",
    "sg:city":"Brooklet",
    "sg:classifiers":[
        {
            "category":"Building & Trades",
            "subcategory":"Landscaping Services",
            "type":"Services"
        }
    ],
    "sg:phone":"+1 912 823 3485",
    "sg:postcode":"30415",
    "sg:province":"GA",
    "sg:tags":[
        "lawn",
        "care"
    ],
    "wof:name":"Forever Green Lawn Care Inc",
    "wof:placetype":"venue"
},
  "geometry": {"coordinates":[-81.562893,32.352729],"type":"Point"}
}