{
  "type": "Feature",
  "properties": {
    "iso:country":"US",
    "sg:address":"1631 E Victory Dr",
    "sg:city":"Savannah",
    "sg:classifiers":[
        {
            "category":"Retail",
            "subcategory":"Auto Repair",
            "type":"Services"
        }
    ],
    "sg:phone":"+1 912 354 8453",
    "sg:postcode":"31404",
    "sg:province":"GA",
    "sg:tags":[
        "repairing",
        "automobile"
    ],
    "wof:name":"Car Care Ctr",
    "wof:placetype":"venue"
},
  "geometry": {"coordinates":[-81.07457599999999,32.045223],"type":"Point"}
}