{
  "type": "Feature",
  "properties": {
    "iso:country":"US",
    "sg:address":"223 Lockett Station Rd",
    "sg:city":"Albany",
    "sg:classifiers":[
        {
            "category":"Building & Trades",
            "subcategory":"Electrical",
            "type":"Services"
        }
    ],
    "sg:phone":"+1 229 883 2070",
    "sg:postcode":"31721",
    "sg:province":"GA",
    "sg:tags":[
        "industrial",
        "electrician",
        "contractors-commercial",
        "electric"
    ],
    "wof:name":"Parr Electric",
    "wof:placetype":"venue"
},
  "geometry": {"coordinates":[-84.25137700000001,31.579743],"type":"Point"}
}