{
  "type": "Feature",
  "properties": {
    "addr:full":"6977 Skyline Dr Lithia Springs GA 30122",
    "addr:housenumber":"6977",
    "addr:postcode":"30122",
    "addr:street":"Skyline Dr",
    "iso:country":"US",
    "sg:address":"6977 Skyline Dr",
    "sg:city":"Lithia Springs",
    "sg:classifiers":[
        {
            "category":"Health Services",
            "subcategory":"Doctor",
            "type":"Services"
        }
    ],
    "sg:phone":"+1 770 944 1944",
    "sg:postcode":"30122",
    "sg:province":"GA",
    "sg:tags":[
        "medical"
    ],
    "wof:name":"David Estes",
    "wof:placetype":"venue"
},
  "geometry": {"coordinates":[-84.65414199999999,33.785208],"type":"Point"}
}