{
  "type": "Feature",
  "properties": {
    "iso:country":"US",
    "sg:address":"34 Upper Riverdale Rd SE",
    "sg:city":"Riverdale",
    "sg:classifiers":[
        {
            "category":"Community Center",
            "type":"Public Place"
        }
    ],
    "sg:phone":"+1 770 996 2880",
    "sg:postcode":"30274",
    "sg:province":"GA",
    "sg:tags":[
        "medical"
    ],
    "wof:name":"Med Center PC",
    "wof:placetype":"venue"
},
  "geometry": {"coordinates":[-84.388077,33.57819],"type":"Point"}
}