{
  "type": "Feature",
  "properties": {
    "iso:country":"US",
    "sg:address":"1409 Rockcut Rd",
    "sg:city":"Forest Park",
    "sg:classifiers":[
        {
            "category":"Professional",
            "type":"Services"
        }
    ],
    "sg:phone":"+1 404 366 9292",
    "sg:postcode":"30297",
    "sg:province":"GA",
    "sg:tags":[
        "establishment"
    ],
    "wof:name":"Pool Phone",
    "wof:placetype":"venue"
},
  "geometry": {"coordinates":[-84.344426,33.636013],"type":"Point"}
}