{
  "type": "Feature",
  "properties": {
    "iso:country":"US",
    "sg:address":"172 Glynn St S",
    "sg:city":"Fayetteville",
    "sg:classifiers":[
        {
            "category":"Personal",
            "type":"Services"
        }
    ],
    "sg:phone":"+1 770 716 9077",
    "sg:postcode":"30214",
    "sg:province":"GA",
    "sg:tags":[
        "mover"
    ],
    "wof:name":"The Moving Men",
    "wof:placetype":"venue"
},
  "geometry": {"coordinates":[-84.455223,33.446223],"type":"Point"}
}