{
  "type": "Feature",
  "properties": {
    "addr:full":"2925 Courtyards Dr Norcross GA 30071",
    "addr:housenumber":"2925",
    "addr:postcode":"30071",
    "addr:street":"Courtyards Dr",
    "iso:country":"US",
    "sg:address":"2925 Courtyards Dr",
    "sg:city":"Norcross",
    "sg:classifiers":[
        {
            "category":"Manufacturing",
            "subcategory":"Chemicals & Compounds",
            "type":"Manufacturing & Wholesale Goods"
        }
    ],
    "sg:phone":"+1 770 447 5402",
    "sg:postcode":"30071",
    "sg:province":"GA",
    "sg:tags":[
        "mfg"
    ],
    "wof:name":"Borden Chemical Inc",
    "wof:placetype":"venue"
},
  "geometry": {"coordinates":[-84.20216000000001,33.954846],"type":"Point"}
}