{
  "type": "Feature",
  "properties": {
    "addr:full":"5815 Marbut Rd Lithonia GA 30058",
    "addr:housenumber":"5815",
    "addr:postcode":"30058",
    "addr:street":"Marbut Rd",
    "iso:country":"US",
    "sg:address":"5815 Marbut Rd",
    "sg:city":"Lithonia",
    "sg:classifiers":[
        {
            "category":"Building & Trades",
            "subcategory":"Electrical",
            "type":"Services"
        }
    ],
    "sg:phone":"+1 770 323 2245",
    "sg:postcode":"30058",
    "sg:province":"GA",
    "sg:tags":[
        "electrician"
    ],
    "wof:name":"Expert Installation",
    "wof:placetype":"venue"
},
  "geometry": {"coordinates":[-84.150633,33.727622],"type":"Point"}
}