{
  "type": "Feature",
  "properties": {
    "iso:country":"US",
    "sg:address":"240 N Oak St",
    "sg:city":"Jackson",
    "sg:classifiers":[
        {
            "category":"Organizations",
            "subcategory":"Religious Organization",
            "type":"Services"
        }
    ],
    "sg:phone":"+1 770 775 5683",
    "sg:postcode":"30233",
    "sg:province":"GA",
    "sg:tags":[
        "church"
    ],
    "sg:website":"www.jacksonpresbyterianchurch.org",
    "wof:name":"Jackson Presbyterian Church",
    "wof:placetype":"venue"
},
  "geometry": {"coordinates":[-83.967448,33.297202],"type":"Point"}
}