{
  "type": "Feature",
  "properties": {
    "iso:country":"US",
    "sg:address":"4603 Wieuca Rd Ste 100",
    "sg:city":"Atlanta",
    "sg:classifiers":[
        {
            "category":"Health Services",
            "subcategory":"Clinic",
            "type":"Services"
        },
        {
            "category":"Personal",
            "subcategory":"Skin Care",
            "type":"Services"
        }
    ],
    "sg:phone":"+1 678 908 3491",
    "sg:postcode":"30342",
    "sg:province":"GA",
    "sg:tags":[
        "spa",
        "medical"
    ],
    "sg:website":"www.beautybyalethea.net",
    "wof:name":"Bella by Alethea",
    "wof:placetype":"venue"
},
  "geometry": {"coordinates":[-84.378703,33.872655],"type":"Point"}
}