{
  "type": "Feature",
  "properties": {
    "iso:country":"US",
    "sg:address":"3475 Dallas Hwy",
    "sg:city":"Marietta",
    "sg:classifiers":[
        {
            "category":"Freight",
            "type":"Transportation"
        }
    ],
    "sg:phone":"+1 770 421 0755",
    "sg:postcode":"30064",
    "sg:province":"GA",
    "sg:tags":[
        "operator",
        "trucking"
    ],
    "wof:name":"Viking Freight System",
    "wof:placetype":"venue"
},
  "geometry": {"coordinates":[-84.652074,33.953499],"type":"Point"}
}