{
  "type": "Feature",
  "properties": {
    "iso:country":"US",
    "sg:address":"208 S 3rd Ave",
    "sg:city":"Chatsworth",
    "sg:classifiers":[
        {
            "category":"Retail",
            "subcategory":"Funeral Services",
            "type":"Services"
        }
    ],
    "sg:phone":"+1 706 695 4634",
    "sg:postcode":"30705",
    "sg:province":"GA",
    "sg:tags":[
        "director"
    ],
    "wof:name":"Peeples Funeral Home",
    "wof:placetype":"venue"
},
  "geometry": {"coordinates":[-84.76946,34.763446],"type":"Point"}
}