{
  "type": "Feature",
  "properties": {
    "iso:country":"US",
    "sg:address":"534 Pat Dixon Rd",
    "sg:city":"Hazlehurst",
    "sg:classifiers":[
        {
            "category":"Food & Beverages",
            "subcategory":"Groceries & Convenience Stores",
            "type":"Retail Goods"
        }
    ],
    "sg:phone":"+1 912 375 5120",
    "sg:postcode":"31539",
    "sg:province":"GA",
    "wof:name":"Las Corner",
    "wof:placetype":"venue"
},
  "geometry": {"coordinates":[-82.65214899999999,31.864508],"type":"Point"}
}