{
  "type": "Feature",
  "properties": {
    "addr:full":"440 Barbashela Dr Stone Mountain GA 30088",
    "addr:housenumber":"440",
    "addr:postcode":"30088",
    "addr:street":"Barbashela Dr",
    "iso:country":"US",
    "sg:address":"440 Barbashela Dr",
    "sg:city":"Stone Mountain",
    "sg:classifiers":[
        {
            "category":"Manufacturing",
            "subcategory":"Tools & Machinery",
            "type":"Manufacturing & Wholesale Goods"
        }
    ],
    "sg:phone":"+1 770 469 1796",
    "sg:postcode":"30088",
    "sg:province":"GA",
    "sg:tags":[
        "measuring",
        "instrument",
        "electrical",
        "mfg"
    ],
    "wof:name":"Lewis & Assoc",
    "wof:placetype":"venue"
},
  "geometry": {"coordinates":[-84.183892,33.783053],"type":"Point"}
}