{
  "type": "Feature",
  "properties": {
    "iso:country":"US",
    "sg:address":"6814 Best Friend Rd",
    "sg:city":"Atlanta",
    "sg:classifiers":[
        {
            "category":"Wholesale",
            "subcategory":"Durable Goods & Equipment",
            "type":"Manufacturing & Wholesale Goods"
        }
    ],
    "sg:phone":"+1 770 662 8359",
    "sg:postcode":"30340",
    "sg:province":"GA",
    "sg:tags":[
        "importer"
    ],
    "sg:website":"www.goldharpinc.com",
    "wof:name":"Gold Harp Inc",
    "wof:placetype":"venue"
},
  "geometry": {"coordinates":[-84.239963,33.910864],"type":"Point"}
}