{
  "type": "Feature",
  "properties": {
    "addr:full":"200 Bond Brg Exd Royston GA 30662",
    "addr:housenumber":"200",
    "addr:postcode":"30662",
    "addr:street":"Bond;Exd",
    "iso:country":"US",
    "sg:address":"200 Bond Brg Exd",
    "sg:city":"Royston",
    "sg:classifiers":[
        {
            "category":"Health Services",
            "subcategory":"Doctor",
            "type":"Services"
        }
    ],
    "sg:phone":"+1 706 246 9009",
    "sg:postcode":"30662",
    "sg:province":"GA",
    "sg:tags":[
        "clinic"
    ],
    "wof:name":"Global Wound Care",
    "wof:placetype":"venue"
},
  "geometry": {"coordinates":[-83.186077,34.271198],"type":"Point"}
}