{
  "type": "Feature",
  "properties": {
    "iso:country":"US",
    "sg:address":"70 Roundup Ct",
    "sg:city":"Ellenwood",
    "sg:classifiers":[
        {
            "category":"Professional",
            "subcategory":"Management & Consulting",
            "type":"Services"
        }
    ],
    "sg:phone":"+1 678 565 9180",
    "sg:postcode":"30294",
    "sg:province":"GA",
    "sg:tags":[
        "personnel",
        "consultant"
    ],
    "wof:name":"God's Love Staffing Svc",
    "wof:placetype":"venue"
},
  "geometry": {"coordinates":[-84.25750600000001,33.610152],"type":"Point"}
}