{
  "type": "Feature",
  "properties": {
    "iso:country":"US",
    "sg:address":"1900 Gronto Rd",
    "sg:city":"Valdosta",
    "sg:classifiers":[
        {
            "category":"Shopping",
            "type":"Retail Goods"
        }
    ],
    "sg:phone":"+1 229 245 8494",
    "sg:postcode":"31601",
    "sg:province":"GA",
    "sg:tags":[
        "equipment",
        "merchandise",
        "cellular",
        "telephone"
    ],
    "wof:name":"Cellular South",
    "wof:placetype":"venue"
},
  "geometry": {"coordinates":[-83.323228,30.849753],"type":"Point"}
}