{
  "type": "Feature",
  "properties": {
    "addr:full":"1512 Emory Rd NE Atlanta GA 30306",
    "addr:housenumber":"1512",
    "addr:postcode":"30306",
    "addr:street":"Emory Rd Ne",
    "iso:country":"US",
    "sg:address":"1512 Emory Rd NE",
    "sg:city":"Atlanta",
    "sg:classifiers":[
        {
            "category":"Wholesale",
            "subcategory":"Computers",
            "type":"Manufacturing & Wholesale Goods"
        },
        {
            "category":"Professional",
            "subcategory":"Computer Services",
            "type":"Services"
        }
    ],
    "sg:phone":"+1 404 373 7786",
    "sg:postcode":"30306",
    "sg:province":"GA",
    "sg:tags":[
        "software",
        "publisher",
        "cd-rom",
        "developer",
        "equipment"
    ],
    "wof:name":"Heuristic Park Inc",
    "wof:placetype":"venue"
},
  "geometry": {"coordinates":[-84.33014799999999,33.792901],"type":"Point"}
}