{
  "type": "Feature",
  "properties": {
    "addr:full":"4110 4th St Garden City GA 31408",
    "addr:housenumber":"4110",
    "addr:postcode":"31408",
    "addr:street":"4Th St",
    "iso:country":"US",
    "sg:address":"4110 4th St",
    "sg:city":"Garden City",
    "sg:classifiers":[
        {
            "category":"Local Transit",
            "type":"Transportation"
        }
    ],
    "sg:phone":"+1 912 966 2777",
    "sg:postcode":"31408",
    "sg:province":"GA",
    "sg:tags":[
        "limousine"
    ],
    "wof:name":"Bryant Transport Svc",
    "wof:placetype":"venue"
},
  "geometry": {"coordinates":[-81.149643,32.098991],"type":"Point"}
}