{
  "type": "Feature",
  "properties": {
    "addr:full":"8030 Rockbridge Rd Lithonia GA 30058",
    "addr:housenumber":"8030",
    "addr:postcode":"30058",
    "addr:street":"Rockbridge Rd",
    "iso:country":"US",
    "sg:address":"8030 Rockbridge Rd",
    "sg:city":"Lithonia",
    "sg:classifiers":[
        {
            "category":"Sports & Exercise",
            "subcategory":"Gym",
            "type":"Entertainment"
        }
    ],
    "sg:phone":"+1 770 482 5825",
    "sg:postcode":"30058",
    "sg:province":"GA",
    "sg:tags":[
        "fitness",
        "physical",
        "facility"
    ],
    "wof:name":"Champion Bdys Per Trning Stdio",
    "wof:placetype":"venue"
},
  "geometry": {"coordinates":[-84.074482,33.775016],"type":"Point"}
}