{
  "type": "Feature",
  "properties": {
    "addr:full":"1393 N Highland Ave NE Atlanta GA 30306",
    "addr:housenumber":"1393",
    "addr:postcode":"30306",
    "addr:street":"N Highland Ave Ne",
    "iso:country":"US",
    "sg:address":"1393 N Highland Ave NE",
    "sg:city":"Atlanta",
    "sg:classifiers":[
        {
            "category":"Building & Trades",
            "subcategory":"Locksmith",
            "type":"Services"
        }
    ],
    "sg:phone":"+1 404 270 1675",
    "sg:postcode":"30306",
    "sg:province":"GA",
    "sg:tags":[
        "key"
    ],
    "wof:name":"24-Hours Emergency Locksmith",
    "wof:placetype":"venue"
},
  "geometry": {"coordinates":[-84.351804,33.792727],"type":"Point"}
}