{
  "type": "Feature",
  "properties": {
    "addr:full":"1958 Appling Harlem Rd Appling GA 30802",
    "addr:housenumber":"1958",
    "addr:postcode":"30802",
    "addr:street":"Appling Harlem Rd",
    "iso:country":"US",
    "sg:address":"1958 Appling Harlem Rd",
    "sg:city":"Appling",
    "sg:classifiers":[
        {
            "category":"Social Services",
            "type":"Services"
        }
    ],
    "sg:phone":"+1 706 541 0033",
    "sg:postcode":"30802",
    "sg:province":"GA",
    "sg:tags":[
        "probation"
    ],
    "wof:name":"State Probation Office",
    "wof:placetype":"venue"
},
  "geometry": {"coordinates":[-82.31677999999999,33.548147],"type":"Point"}
}