{
  "type": "Feature",
  "properties": {
    "addr:full":"3980 Indian Shoals Rd SE Bethlehem GA 30620",
    "addr:housenumber":"3980",
    "addr:postcode":"30620",
    "addr:street":"Indian Shoals Rd Se",
    "iso:country":"US",
    "sg:address":"3980 Indian Shoals Rd SE",
    "sg:city":"Bethlehem",
    "sg:classifiers":[
        {
            "category":"Professional",
            "subcategory":"Business Services",
            "type":"Services"
        }
    ],
    "sg:phone":"+1 770 339 1549",
    "sg:postcode":"30620",
    "sg:province":"GA",
    "wof:name":"Interior Treasures Inc",
    "wof:placetype":"venue"
},
  "geometry": {"coordinates":[-83.817932,33.943629],"type":"Point"}
}