{
  "type": "Feature",
  "properties": {
    "addr:full":"409 S College St Statesboro GA 30458",
    "addr:housenumber":"409",
    "addr:postcode":"30458",
    "addr:street":"S College St",
    "iso:country":"US",
    "sg:address":"409 S College St",
    "sg:city":"Statesboro",
    "sg:classifiers":[
        {
            "category":"Organizations",
            "subcategory":"Professional Association",
            "type":"Services"
        }
    ],
    "sg:phone":"+1 912 764 4210",
    "sg:postcode":"30458",
    "sg:province":"GA",
    "sg:tags":[
        "business"
    ],
    "wof:name":"Smoke House Group",
    "wof:placetype":"venue"
},
  "geometry": {"coordinates":[-81.78691000000001,32.435836],"type":"Point"}
}