{
  "type": "Feature",
  "properties": {
    "addr:full":"2204 Lavista Rd NE Atlanta GA 30329",
    "addr:housenumber":"2204",
    "addr:postcode":"30329",
    "addr:street":"Lavista Rd Ne",
    "iso:country":"US",
    "sg:address":"2204 Lavista Rd NE",
    "sg:city":"Atlanta",
    "sg:classifiers":[
        {
            "category":"Professional",
            "subcategory":"Computer Services",
            "type":"Services"
        },
        {
            "category":"Communications",
            "type":"Services"
        },
        {
            "category":"Communications",
            "subcategory":"Television Station",
            "type":"Services"
        }
    ],
    "sg:phone":"+1 866 310 4761",
    "sg:postcode":"30329",
    "sg:province":"GA",
    "sg:tags":[
        "satellite",
        "cable",
        "tv",
        "isp",
        "system",
        "equipment",
        "internet",
        "provider"
    ],
    "sg:website":"http://www.directsattv.com/directv/?tfid=ypm",
    "wof:name":"Direct Sat TV - An Authorized DIRECTV Dealer",
    "wof:placetype":"venue"
},
  "geometry": {"coordinates":[-84.31420900000001,33.817581],"type":"Point"}
}