{
  "type": "Feature",
  "properties": {
    "addr:full":"2151 Cumberland Pkwy SE # 1211 Atlanta GA 30339",
    "addr:housenumber":"2151",
    "addr:postcode":"30339",
    "addr:street":"Cumberland Pkwy Se # 1211",
    "iso:country":"US",
    "sg:address":"2151 Cumberland Pkwy SE # 1211",
    "sg:city":"Atlanta",
    "sg:classifiers":[
        {
            "category":"Utilities",
            "subcategory":"Electric",
            "type":"Services"
        }
    ],
    "sg:phone":"+1 404 597 7580",
    "sg:postcode":"30339",
    "sg:province":"GA",
    "sg:tags":[
        "equipment-repair"
    ],
    "wof:name":"Just System Solutions",
    "wof:placetype":"venue"
},
  "geometry": {"coordinates":[-84.485466,33.848705],"type":"Point"}
}