{
  "type": "Feature",
  "properties": {
    "iso:country":"US",
    "sg:address":"1075 Bellaire Ct",
    "sg:city":"Lawrenceville",
    "sg:classifiers":[
        {
            "category":"Professional",
            "subcategory":"Art Services",
            "type":"Services"
        }
    ],
    "sg:phone":"+1 678 377 2199",
    "sg:postcode":"30043",
    "sg:province":"GA",
    "sg:tags":[
        "commercial",
        "design"
    ],
    "wof:name":"Cadindia Inc",
    "wof:placetype":"venue"
},
  "geometry": {"coordinates":[-84.039141,33.976401],"type":"Point"}
}