{
  "type": "Feature",
  "properties": {
    "addr:full":"2435 Candler Rd Decatur GA 30032",
    "addr:postcode":"2435;30032",
    "addr:street":"Candler Rd",
    "iso:country":"US",
    "sg:address":"2435 Candler Rd",
    "sg:city":"Decatur",
    "sg:classifiers":[
        {
            "category":"Personal",
            "subcategory":"Beauty Salon",
            "type":"Services"
        }
    ],
    "sg:phone":"+1 404 285 8011",
    "sg:postcode":"30032",
    "sg:province":"GA",
    "wof:name":"Platinum Touch",
    "wof:placetype":"venue"
},
  "geometry": {"coordinates":[-84.27600200000001,33.719271],"type":"Point"}
}