{
  "type": "Feature",
  "properties": {
    "iso:country":"US",
    "sg:address":"604 W US Hwy 80",
    "sg:city":"Pooler",
    "sg:classifiers":[
        {
            "category":"Banks & Credit Unions",
            "subcategory":"Bank",
            "type":"Services"
        }
    ],
    "sg:phone":"+1 912 356 1666",
    "sg:postcode":"31322",
    "sg:province":"GA",
    "sg:tags":[
        "loan",
        "real estate"
    ],
    "wof:name":"Coastal Mortgage Co",
    "wof:placetype":"venue"
},
  "geometry": {"coordinates":[-81.25815299999999,32.119464],"type":"Point"}
}