{
  "type": "Feature",
  "properties": {
    "addr:full":"1001 Mc Dowell St St Marys GA 31558",
    "addr:housenumber":"1001",
    "addr:postcode":"31558",
    "addr:street":"Mc Dowell St",
    "iso:country":"US",
    "sg:address":"1001 Mc Dowell St",
    "sg:city":"St Marys",
    "sg:classifiers":[
        {
            "category":"Personal",
            "subcategory":"Beauty Salon",
            "type":"Services"
        }
    ],
    "sg:phone":"+1 912 882 6425",
    "sg:postcode":"31558",
    "sg:province":"GA",
    "wof:name":"Olde Towne Barber & Style Shop",
    "wof:placetype":"venue"
},
  "geometry": {"coordinates":[-81.56639199999999,30.743916],"type":"Point"}
}