{
  "type": "Feature",
  "properties": {
    "iso:country":"US",
    "sg:address":"595 Creekwood Xing E",
    "sg:city":"Roswell",
    "sg:classifiers":[
        {
            "category":"Building & Trades",
            "subcategory":"Construction",
            "type":"Services"
        }
    ],
    "sg:phone":"+1 404 925 1437",
    "sg:postcode":"30076",
    "sg:province":"GA",
    "sg:tags":[
        "demolition",
        "contractor"
    ],
    "wof:name":"J J Hauling & Demolition",
    "wof:placetype":"venue"
},
  "geometry": {"coordinates":[-84.304513,34.017282],"type":"Point"}
}