{
  "type": "Feature",
  "properties": {
    "addr:full":"2714 Crest Ridge Dr Atlanta GA 30344",
    "addr:housenumber":"2714",
    "addr:postcode":"30344",
    "addr:street":"Crest Ridge Dr",
    "iso:country":"US",
    "sg:address":"2714 Crest Ridge Dr",
    "sg:city":"Atlanta",
    "sg:classifiers":[
        {
            "category":"Food & Beverages",
            "subcategory":"Candy",
            "type":"Retail Goods"
        }
    ],
    "sg:phone":"+1 404 647 3223",
    "sg:postcode":"30344",
    "sg:province":"GA",
    "sg:tags":[
        "confectionery"
    ],
    "wof:name":"Cheri's Candy Galore",
    "wof:placetype":"venue"
},
  "geometry": {"coordinates":[-84.500893,33.662472],"type":"Point"}
}