{
  "type": "Feature",
  "properties": {
    "iso:country":"US",
    "sg:address":"904 Pine Cir",
    "sg:city":"Woodstock",
    "sg:classifiers":[
        {
            "category":"Retail",
            "subcategory":"Repair Shop",
            "type":"Services"
        }
    ],
    "sg:phone":"+1 770 926 8770",
    "sg:postcode":"30189",
    "sg:province":"GA",
    "wof:name":"Performance Inboard Marine",
    "wof:placetype":"venue"
},
  "geometry": {"coordinates":[-84.60628,34.138806],"type":"Point"}
}