{
  "type": "Feature",
  "properties": {
    "addr:full":"19 Greystone Ct Hiram GA 30141",
    "addr:housenumber":"19",
    "addr:postcode":"30141",
    "addr:street":"Greystone Ct",
    "iso:country":"US",
    "sg:address":"19 Greystone Ct",
    "sg:city":"Hiram",
    "sg:classifiers":[
        {
            "category":"Restaurant",
            "type":"Food & Drink"
        }
    ],
    "sg:phone":"+1 678 398 9367",
    "sg:postcode":"30141",
    "sg:province":"GA",
    "sg:tags":[
        "mexican"
    ],
    "wof:name":"Alfredo Avalos Garcia",
    "wof:placetype":"venue"
},
  "geometry": {"coordinates":[-84.775441,33.894825],"type":"Point"}
}