{
  "type": "Feature",
  "properties": {
    "iso:country":"US",
    "sg:address":"443 S Main St",
    "sg:city":"Statesboro",
    "sg:classifiers":[
        {
            "category":"Freight",
            "type":"Transportation"
        }
    ],
    "sg:phone":"+1 912 764 5589",
    "sg:postcode":"30458",
    "sg:province":"GA",
    "sg:tags":[
        "special"
    ],
    "wof:name":"A Main Street Storage",
    "wof:placetype":"venue"
},
  "geometry": {"coordinates":[-81.78464,32.43561],"type":"Point"}
}