{
  "type": "Feature",
  "properties": {
    "addr:full":"200 Galleria Parkway SE Atlanta GA 30339",
    "addr:housenumber":"200",
    "addr:postcode":"30339",
    "addr:street":"Galleria Parkway Se",
    "iso:country":"US",
    "sg:address":"200 Galleria Parkway SE",
    "sg:city":"Atlanta",
    "sg:classifiers":[
        {
            "category":"Building & Trades",
            "subcategory":"Construction",
            "type":"Services"
        }
    ],
    "sg:phone":"+1 770 984 9083",
    "sg:postcode":"30339",
    "sg:province":"GA",
    "sg:tags":[
        "contractor"
    ],
    "wof:name":"Preferred Builders",
    "wof:placetype":"venue"
},
  "geometry": {"coordinates":[-84.46550000000001,33.882511],"type":"Point"}
}