{
  "type": "Feature",
  "properties": {
    "iso:country":"US",
    "sg:address":"1265 Upper Hembree Rd",
    "sg:city":"Roswell",
    "sg:classifiers":[
        {
            "category":"Health Services",
            "subcategory":"Medical Lab",
            "type":"Services"
        }
    ],
    "sg:phone":"+1 770 619 0891",
    "sg:postcode":"30076",
    "sg:province":"GA",
    "sg:tags":[
        "laboratory"
    ],
    "wof:name":"Quest Diagnostics Inc",
    "wof:placetype":"venue"
},
  "geometry": {"coordinates":[-84.320712,34.066866],"type":"Point"}
}