{
  "type": "Feature",
  "properties": {
    "iso:country":"US",
    "sg:address":"1100 Broadway Ave",
    "sg:city":"Columbus",
    "sg:classifiers":[
        {
            "category":"Professional",
            "type":"Services"
        }
    ],
    "sg:phone":"+1 706 327 5576",
    "sg:postcode":"31901",
    "sg:province":"GA",
    "wof:name":"Maryanne Mathews Oubin Fr",
    "wof:placetype":"venue"
},
  "geometry": {"coordinates":[-84.99317000000001,32.468623],"type":"Point"}
}