{
  "type": "Feature",
  "properties": {
    "iso:country":"US",
    "sg:address":"401 Anson Ave",
    "sg:city":"Eastman",
    "sg:classifiers":[
        {
            "category":"Professional",
            "type":"Services"
        }
    ],
    "sg:phone":"+1 478 374 4121",
    "sg:postcode":"31023",
    "sg:province":"GA",
    "wof:name":"Southern Co Svc",
    "wof:placetype":"venue"
},
  "geometry": {"coordinates":[-83.167675,32.204361],"type":"Point"}
}