{
  "type": "Feature",
  "properties": {
    "addr:full":"80 Newnan Station Dr Newnan GA 30265",
    "addr:housenumber":"80",
    "addr:postcode":"30265",
    "addr:street":"Newnan Station Dr",
    "iso:country":"US",
    "sg:address":"80 Newnan Station Dr",
    "sg:city":"Newnan",
    "sg:classifiers":[
        {
            "category":"Food & Beverages",
            "subcategory":"Meat & Fish",
            "type":"Retail Goods"
        }
    ],
    "sg:phone":"+1 770 683 6328",
    "sg:postcode":"30265",
    "sg:province":"GA",
    "sg:tags":[
        "market"
    ],
    "wof:name":"The Butcher Shop",
    "wof:placetype":"venue"
},
  "geometry": {"coordinates":[-84.73728300000001,33.397305],"type":"Point"}
}