{
  "type": "Feature",
  "properties": {
    "addr:full":"612 Valley Brook Rd Decatur GA 30033",
    "addr:housenumber":"612",
    "addr:postcode":"30033",
    "addr:street":"Valley Brook Rd",
    "iso:country":"US",
    "sg:address":"612 Valley Brook Rd",
    "sg:city":"Decatur",
    "sg:classifiers":[
        {
            "category":"Utilities",
            "subcategory":"Electric",
            "type":"Services"
        }
    ],
    "sg:phone":"+1 404 292 7558",
    "sg:postcode":"30033",
    "sg:province":"GA",
    "sg:tags":[
        "equipment",
        "supplies-repair",
        "electronic",
        "equipment-repair"
    ],
    "wof:name":"In Sink Erator Authorized Service",
    "wof:placetype":"venue"
},
  "geometry": {"coordinates":[-84.265747,33.81255],"type":"Point"}
}