{
  "type": "Feature",
  "properties": {
    "addr:full":"1410 Eatonton Rd Madison GA 30650",
    "addr:housenumber":"1410",
    "addr:postcode":"30650",
    "addr:street":"Eatonton Rd",
    "iso:country":"US",
    "sg:address":"1410 Eatonton Rd",
    "sg:city":"Madison",
    "sg:classifiers":[
        {
            "category":"Personal",
            "subcategory":"Barber",
            "type":"Services"
        }
    ],
    "sg:phone":"+1 706 342 2260",
    "sg:postcode":"30650",
    "sg:province":"GA",
    "wof:name":"Bulldog Barber Shop",
    "wof:placetype":"venue"
},
  "geometry": {"coordinates":[-83.477053,33.57542],"type":"Point"}
}