{
  "type": "Feature",
  "properties": {
    "iso:country":"US",
    "sg:address":"2150 E Walnut Ave",
    "sg:city":"Dalton",
    "sg:classifiers":[
        {
            "category":"Shopping",
            "type":"Retail Goods"
        },
        {
            "category":"Shopping",
            "subcategory":"Beauty & Cosmetics",
            "type":"Retail Goods"
        }
    ],
    "sg:phone":"+1 706 279 4125",
    "sg:postcode":"30721",
    "sg:province":"GA",
    "sg:tags":[
        "personal",
        "product",
        "care",
        "perfume"
    ],
    "sg:website":"www.bathandbodyworks.com",
    "wof:name":"Bath & Body Works Inc",
    "wof:placetype":"venue"
},
  "geometry": {"coordinates":[-84.931392,34.762548],"type":"Point"}
}