{
  "type": "Feature",
  "properties": {
    "iso:country":"US",
    "sg:address":"3438 Burkardt Dr",
    "sg:city":"Valdosta",
    "sg:classifiers":[
        {
            "category":"Building & Trades",
            "subcategory":"Construction",
            "type":"Services"
        }
    ],
    "sg:phone":"+1 229 249 8295",
    "sg:postcode":"31605",
    "sg:province":"GA",
    "sg:tags":[
        "house"
    ],
    "wof:name":"JB Home Construction LLC",
    "wof:placetype":"venue"
},
  "geometry": {"coordinates":[-83.259987,30.919905],"type":"Point"}
}