{
  "type": "Feature",
  "properties": {
    "iso:country":"US",
    "sg:address":"209 E Adams St",
    "sg:city":"Tennille",
    "sg:classifiers":[
        {
            "category":"Professional",
            "subcategory":"Detective & Security Services",
            "type":"Services"
        }
    ],
    "sg:phone":"+1 478 552 0563",
    "sg:postcode":"31089",
    "sg:province":"GA",
    "sg:tags":[
        "information",
        "bureau"
    ],
    "wof:name":"Colleens Catering Service",
    "wof:placetype":"venue"
},
  "geometry": {"coordinates":[-82.809432,32.938741],"type":"Point"}
}