{
  "type": "Feature",
  "properties": {
    "addr:full":"604 John Ross Ct Woodstock GA 30188",
    "addr:housenumber":"604",
    "addr:postcode":"30188",
    "addr:street":"John Ross Ct",
    "iso:country":"US",
    "sg:address":"604 John Ross Ct",
    "sg:city":"Woodstock",
    "sg:classifiers":[
        {
            "category":"Wholesale",
            "subcategory":"Chemicals & Plastics",
            "type":"Manufacturing & Wholesale Goods"
        }
    ],
    "sg:phone":"+1 770 928 3641",
    "sg:postcode":"30188",
    "sg:province":"GA",
    "sg:tags":[
        "additive"
    ],
    "wof:name":"Banstatic Plus LLC",
    "wof:placetype":"venue"
},
  "geometry": {"coordinates":[-84.407641,34.117289],"type":"Point"}
}