{
  "type": "Feature",
  "properties": {
    "addr:full":"4393 Victory Dr Columbus GA 31903",
    "addr:housenumber":"4393",
    "addr:postcode":"31903",
    "addr:street":"Victory Dr",
    "iso:country":"US",
    "sg:address":"4393 Victory Dr",
    "sg:city":"Columbus",
    "sg:classifiers":[
        {
            "category":"Professional",
            "subcategory":"Business Services",
            "type":"Services"
        }
    ],
    "sg:phone":"+1 706 682 9555",
    "sg:postcode":"31903",
    "sg:province":"GA",
    "wof:name":"Atlanta Telecommunications",
    "wof:placetype":"venue"
},
  "geometry": {"coordinates":[-84.936846,32.40623],"type":"Point"}
}