{
  "type": "Feature",
  "properties": {
    "iso:country":"US",
    "sg:address":"501 Sparta Rd Ste F",
    "sg:city":"Sandersville",
    "sg:classifiers":[
        {
            "category":"Health Services",
            "subcategory":"Doctor",
            "type":"Services"
        }
    ],
    "sg:phone":"+1 478 552 0001",
    "sg:postcode":"31082",
    "sg:province":"GA",
    "sg:tags":[
        "physician",
        "surgeon"
    ],
    "wof:name":"Kitchens W Kim Doctor of Medicine",
    "wof:placetype":"venue"
},
  "geometry": {"coordinates":[-82.80940200000001,32.993143],"type":"Point"}
}