{
  "type": "Feature",
  "properties": {
    "addr:full":"1746 Wedgewood Dr Stone Mountain GA 30088",
    "addr:housenumber":"1746",
    "addr:postcode":"30088",
    "addr:street":"Wedgewood Dr",
    "iso:country":"US",
    "sg:address":"1746 Wedgewood Dr",
    "sg:city":"Stone Mountain",
    "sg:classifiers":[
        {
            "category":"Wholesale",
            "subcategory":"Vending Machines",
            "type":"Manufacturing & Wholesale Goods"
        }
    ],
    "sg:phone":"+1 770 808 7444",
    "sg:postcode":"30088",
    "sg:province":"GA",
    "sg:tags":[
        "operator"
    ],
    "wof:name":"Swc Vending",
    "wof:placetype":"venue"
},
  "geometry": {"coordinates":[-84.185293,33.741318],"type":"Point"}
}