{
  "type": "Feature",
  "properties": {
    "iso:country":"US",
    "sg:address":"2443 Dawsonville Hwy",
    "sg:city":"Gainesville",
    "sg:classifiers":[
        {
            "category":"Home & Garden",
            "subcategory":"Carpets & Floor Coverings",
            "type":"Retail Goods"
        }
    ],
    "sg:phone":"+1 770 536 3629",
    "sg:postcode":"30506",
    "sg:province":"GA",
    "wof:name":"Carpet Barn",
    "wof:placetype":"venue"
},
  "geometry": {"coordinates":[-83.89545099999999,34.331809],"type":"Point"}
}