{
  "type": "Feature",
  "properties": {
    "addr:full":"4243 Dunwoody Club Dr Atlanta GA 30350",
    "addr:housenumber":"4243",
    "addr:postcode":"30350",
    "addr:street":"Dunwoody Club Dr",
    "iso:country":"US",
    "sg:address":"4243 Dunwoody Club Dr",
    "sg:city":"Atlanta",
    "sg:classifiers":[
        {
            "category":"Professional",
            "subcategory":"Business Services",
            "type":"Services"
        }
    ],
    "sg:phone":"+1 770 321 6388",
    "sg:postcode":"30350",
    "sg:province":"GA",
    "sg:tags":[
        "broker"
    ],
    "wof:name":"Mueller Co",
    "wof:placetype":"venue"
},
  "geometry": {"coordinates":[-84.296306,33.959671],"type":"Point"}
}