{
  "type": "Feature",
  "properties": {
    "addr:full":"5231 Buena Vista Rd Columbus GA 31907",
    "addr:housenumber":"5231",
    "addr:postcode":"31907",
    "addr:street":"Buena Vista Rd",
    "iso:country":"US",
    "sg:address":"5231 Buena Vista Rd",
    "sg:city":"Columbus",
    "sg:classifiers":[
        {
            "category":"Retail",
            "subcategory":"Animal Services",
            "type":"Services"
        }
    ],
    "sg:phone":"+1 706 561 6539",
    "sg:postcode":"31907",
    "sg:province":"GA",
    "wof:name":"Doggie Designs",
    "wof:placetype":"venue"
},
  "geometry": {"coordinates":[-84.904115,32.467445],"type":"Point"}
}