{
  "type": "Feature",
  "properties": {
    "iso:country":"US",
    "sg:address":"3661 Suwanee Creek Ct",
    "sg:city":"Suwanee",
    "sg:classifiers":[
        {
            "category":"Professional",
            "type":"Services"
        }
    ],
    "sg:phone":"+1 770 271 9274",
    "sg:postcode":"30024",
    "sg:province":"GA",
    "wof:name":"Suwanee Irrigation Inc",
    "wof:placetype":"venue"
},
  "geometry": {"coordinates":[-84.046711,34.054522],"type":"Point"}
}