{
  "type": "Feature",
  "properties": {
    "addr:full":"5431 Jerry Burris Rd Murrayville GA 30564",
    "addr:housenumber":"5431",
    "addr:postcode":"30564",
    "addr:street":"Jerry Burris Rd",
    "iso:country":"US",
    "sg:address":"5431 Jerry Burris Rd",
    "sg:city":"Murrayville",
    "sg:classifiers":[
        {
            "category":"Building & Trades",
            "subcategory":"Construction",
            "type":"Services"
        }
    ],
    "sg:phone":"+1 770 535 6760",
    "sg:postcode":"30564",
    "sg:province":"GA",
    "sg:tags":[
        "hanging",
        "contractor"
    ],
    "wof:name":"B&C Painting",
    "wof:placetype":"venue"
},
  "geometry": {"coordinates":[-83.89134199999999,34.411346],"type":"Point"}
}