{
  "type": "Feature",
  "properties": {
    "iso:country":"US",
    "sg:address":"310 College Cir",
    "sg:city":"Athens",
    "sg:classifiers":[
        {
            "category":"Professional",
            "subcategory":"Lawyer & Legal Services",
            "type":"Services"
        }
    ],
    "sg:phone":"+1 706 542 0006",
    "sg:postcode":"30605",
    "sg:province":"GA",
    "wof:name":"Univ of Ga/Legal Affairs",
    "wof:placetype":"venue"
},
  "geometry": {"coordinates":[-83.350604,33.924389],"type":"Point"}
}