{
  "type": "Feature",
  "properties": {
    "iso:country":"US",
    "sg:address":"1400 Gray Hwy",
    "sg:city":"Macon",
    "sg:classifiers":[
        {
            "category":"Personal",
            "type":"Services"
        }
    ],
    "sg:phone":"+1 404 401 4948",
    "sg:postcode":"31211",
    "sg:province":"GA",
    "wof:name":"Images Customs Clothing",
    "wof:placetype":"venue"
},
  "geometry": {"coordinates":[-83.614301,32.860685],"type":"Point"}
}