{
  "type": "Feature",
  "properties": {
    "addr:full":"375 Northridge Rd Atlanta GA 30350",
    "addr:housenumber":"375",
    "addr:postcode":"30350",
    "addr:street":"Northridge Rd",
    "iso:country":"US",
    "sg:address":"375 Northridge Rd",
    "sg:city":"Atlanta",
    "sg:classifiers":[
        {
            "category":"Banks & Credit Unions",
            "subcategory":"Bank",
            "type":"Services"
        }
    ],
    "sg:phone":"+1 770 395 1990",
    "sg:postcode":"30350",
    "sg:province":"GA",
    "sg:tags":[
        "personal",
        "institution"
    ],
    "wof:name":"Chase Manhattan",
    "wof:placetype":"venue"
},
  "geometry": {"coordinates":[-84.34950499999999,33.981489],"type":"Point"}
}