{
  "type": "Feature",
  "properties": {
    "addr:full":"250 Spence Ave SE Atlanta GA 30317",
    "addr:housenumber":"250",
    "addr:postcode":"30317",
    "addr:street":"Spence Ave Se",
    "iso:country":"US",
    "sg:address":"250 Spence Ave SE",
    "sg:city":"Atlanta",
    "sg:classifiers":[
        {
            "category":"Building & Trades",
            "subcategory":"Construction",
            "type":"Services"
        }
    ],
    "sg:phone":"+1 404 290 1841",
    "sg:postcode":"30317",
    "sg:province":"GA",
    "sg:tags":[
        "repair",
        "handyman",
        "maintenance",
        "home"
    ],
    "wof:name":"The Handy Man",
    "wof:placetype":"venue"
},
  "geometry": {"coordinates":[-84.2963,33.745626],"type":"Point"}
}