{
  "type": "Feature",
  "properties": {
    "addr:full":"3311 State Rte 5 Douglasville GA 30135",
    "addr:housenumber":"3311",
    "addr:postcode":"30135",
    "addr:street":"State Rte 5",
    "iso:country":"US",
    "sg:address":"3311 State Rte 5",
    "sg:city":"Douglasville",
    "sg:classifiers":[
        {
            "category":"Personal",
            "subcategory":"Beauty Salon",
            "type":"Services"
        }
    ],
    "sg:phone":"+1 770 949 4585",
    "sg:postcode":"30135",
    "sg:province":"GA",
    "sg:tags":[
        "shop"
    ],
    "wof:name":"Angela Cash",
    "wof:placetype":"venue"
},
  "geometry": {"coordinates":[-84.769909,33.713099],"type":"Point"}
}