{
  "type": "Feature",
  "properties": {
    "iso:country":"US",
    "sg:address":"3346 Hidden Forest Dr SW",
    "sg:city":"Snellville",
    "sg:classifiers":[
        {
            "category":"Professional",
            "type":"Services"
        }
    ],
    "sg:phone":"+1 770 837 8500",
    "sg:postcode":"30078",
    "sg:province":"GA",
    "wof:name":"Frances M Morgan",
    "wof:placetype":"venue"
},
  "geometry": {"coordinates":[-83.99269,33.834158],"type":"Point"}
}