{
  "type": "Feature",
  "properties": {
    "addr:full":"3812 Browns Bridge Rd Cumming GA 30041",
    "addr:housenumber":"3812",
    "addr:postcode":"30041",
    "addr:street":"Browns Bridge Rd",
    "iso:country":"US",
    "sg:address":"3812 Browns Bridge Rd",
    "sg:city":"Cumming",
    "sg:classifiers":[
        {
            "category":"Professional",
            "subcategory":"Testing Lab",
            "type":"Services"
        },
        {
            "category":"Health Services",
            "subcategory":"Medical Lab",
            "type":"Services"
        },
        {
            "category":"Health Services",
            "subcategory":"Dentist",
            "type":"Services"
        }
    ],
    "sg:phone":"+1 678 341 6836",
    "sg:postcode":"30041",
    "sg:province":"GA",
    "sg:tags":[
        "laboratory",
        "dental",
        "clinic"
    ],
    "wof:name":"Image Plus Dental Design Of Ge",
    "wof:placetype":"venue"
},
  "geometry": {"coordinates":[-84.08579400000001,34.263119],"type":"Point"}
}