{
  "type": "Feature",
  "properties": {
    "addr:full":"2501 Skidaway Rd Savannah GA 31404",
    "addr:housenumber":"2501",
    "addr:postcode":"31404",
    "addr:street":"Skidaway Rd",
    "iso:country":"US",
    "sg:address":"2501 Skidaway Rd",
    "sg:city":"Savannah",
    "sg:classifiers":[
        {
            "category":"Retail",
            "subcategory":"Laundry & Dry Cleaning",
            "type":"Services"
        }
    ],
    "sg:phone":"+1 912 233 2082",
    "sg:postcode":"31404",
    "sg:province":"GA",
    "sg:tags":[
        "cleaner",
        "operated",
        "dryer",
        "laundries-self",
        "washer",
        "coin"
    ],
    "wof:name":"Kwik-Way Coin Laundry",
    "wof:placetype":"venue"
},
  "geometry": {"coordinates":[-81.06352200000001,32.04369],"type":"Point"}
}