{
  "type": "Feature",
  "properties": {
    "iso:country":"US",
    "sg:address":"1050 North Higland Ave",
    "sg:city":"Atlanta",
    "sg:classifiers":[
        {
            "category":"Food & Beverages",
            "subcategory":"Specialty",
            "type":"Retail Goods"
        }
    ],
    "sg:phone":"+1 404 347 6476",
    "sg:postcode":"30306",
    "sg:province":"GA",
    "sg:website":"www.bellacucina.com",
    "wof:name":"Bella Cucina Artful Food",
    "wof:placetype":"venue"
},
  "geometry": {"coordinates":[-84.35470599999999,33.783276],"type":"Point"}
}