{
  "type": "Feature",
  "properties": {
    "addr:full":"2919 Bob Bettis Rd Marietta GA 30066",
    "addr:housenumber":"2919",
    "addr:postcode":"30066",
    "addr:street":"Bob Bettis Rd",
    "iso:country":"US",
    "sg:address":"2919 Bob Bettis Rd",
    "sg:city":"Marietta",
    "sg:classifiers":[
        {
            "category":"Manufacturing",
            "subcategory":"Tools & Machinery",
            "type":"Manufacturing & Wholesale Goods"
        }
    ],
    "sg:phone":"+1 770 977 6648",
    "sg:postcode":"30066",
    "sg:province":"GA",
    "sg:tags":[
        "transformer",
        "mfg"
    ],
    "wof:name":"S G Power Engineering",
    "wof:placetype":"venue"
},
  "geometry": {"coordinates":[-84.505374,34.020621],"type":"Point"}
}