{
  "type": "Feature",
  "properties": {
    "addr:full":"4760 Hammermill Rd Tucker GA 30084",
    "addr:housenumber":"4760",
    "addr:postcode":"30084",
    "addr:street":"Hammermill Rd",
    "iso:country":"US",
    "sg:address":"4760 Hammermill Rd",
    "sg:city":"Tucker",
    "sg:classifiers":[
        {
            "category":"Manufacturing",
            "subcategory":"Printing",
            "type":"Manufacturing & Wholesale Goods"
        }
    ],
    "sg:phone":"+1 770 939 1340",
    "sg:postcode":"30084",
    "sg:province":"GA",
    "sg:tags":[
        "commercial"
    ],
    "wof:name":"Print Key",
    "wof:placetype":"venue"
},
  "geometry": {"coordinates":[-84.195078,33.837017],"type":"Point"}
}