{
  "type": "Feature",
  "properties": {
    "addr:full":"2419 Old Thompson Bridge Rd Gainesville GA 30501",
    "addr:housenumber":"2419",
    "addr:postcode":"30501",
    "addr:street":"Old Thompson Bridge Rd",
    "iso:country":"US",
    "sg:address":"2419 Old Thompson Bridge Rd",
    "sg:city":"Gainesville",
    "sg:classifiers":[
        {
            "category":"Manufacturing",
            "subcategory":"Metals",
            "type":"Manufacturing & Wholesale Goods"
        },
        {
            "category":"Building & Trades",
            "subcategory":"Construction",
            "type":"Services"
        }
    ],
    "sg:phone":"+1 770 654 9131",
    "sg:postcode":"30501",
    "sg:province":"GA",
    "sg:tags":[
        "repair",
        "fabricates",
        "product",
        "fabricator"
    ],
    "wof:name":"Crm Fabrication & Repair Inc",
    "wof:placetype":"venue"
},
  "geometry": {"coordinates":[-83.845625,34.335466],"type":"Point"}
}