{
  "type": "Feature",
  "properties": {
    "iso:country":"US",
    "sg:address":"1155 Lavista Road",
    "sg:city":"Atlanta",
    "sg:classifiers":[
        {
            "category":"Restaurant",
            "type":"Food & Drink"
        }
    ],
    "sg:phone":"+1 800 758 7950",
    "sg:postcode":"30324",
    "sg:province":"GA",
    "sg:website":"www.azuregourmetandcatering.com",
    "wof:name":"Azure Gourmet and Catering",
    "wof:placetype":"venue"
},
  "geometry": {"coordinates":[-84.350641,33.818075],"type":"Point"}
}