{
  "type": "Feature",
  "properties": {
    "addr:full":"6150 Parkway North Dr Cumming GA 30040",
    "addr:housenumber":"6150",
    "addr:postcode":"30040",
    "addr:street":"Parkway North Dr",
    "iso:country":"US",
    "sg:address":"6150 Parkway North Dr",
    "sg:city":"Cumming",
    "sg:classifiers":[
        {
            "category":"Building & Trades",
            "subcategory":"Construction",
            "type":"Services"
        }
    ],
    "sg:phone":"+1 678 455 0125",
    "sg:postcode":"30040",
    "sg:province":"GA",
    "sg:tags":[
        "tile-contractors"
    ],
    "wof:name":"Mazi",
    "wof:placetype":"venue"
},
  "geometry": {"coordinates":[-84.18386099999999,34.16624],"type":"Point"}
}