{
  "type": "Feature",
  "properties": {
    "iso:country":"US",
    "sg:address":"2038 Sylvan Road SW",
    "sg:city":"Atlanta",
    "sg:classifiers":[
        {
            "category":"Shopping",
            "subcategory":"Beauty & Cosmetics",
            "type":"Retail Goods"
        },
        {
            "category":"Personal",
            "subcategory":"Barber",
            "type":"Services"
        }
    ],
    "sg:phone":"+1 404 758 7573",
    "sg:postcode":"30310",
    "sg:province":"GA",
    "sg:tags":[
        "equipment",
        "salons-equipment",
        "supply"
    ],
    "wof:name":"J &j Beauty Supply",
    "wof:placetype":"venue"
},
  "geometry": {"coordinates":[-84.41844399999999,33.698552],"type":"Point"}
}