{
  "type": "Feature",
  "properties": {
    "iso:country":"US",
    "sg:address":"3525 Piedmont Rd NE",
    "sg:city":"Atlanta",
    "sg:classifiers":[
        {
            "category":"Professional",
            "subcategory":"Lawyer & Legal Services",
            "type":"Services"
        }
    ],
    "sg:phone":"+1 404 256 2422",
    "sg:postcode":"30305",
    "sg:province":"GA",
    "wof:name":"Smith Philip J Atty",
    "wof:placetype":"venue"
},
  "geometry": {"coordinates":[-84.384399,33.8325],"type":"Point"}
}