{
  "type": "Feature",
  "properties": {
    "addr:full":"2295 Orleans Ave Marietta GA 30062",
    "addr:housenumber":"2295",
    "addr:postcode":"30062",
    "addr:street":"Orleans Ave",
    "iso:country":"US",
    "sg:address":"2295 Orleans Ave",
    "sg:city":"Marietta",
    "sg:classifiers":[
        {
            "category":"Shopping",
            "subcategory":"Gifts & Souvenirs",
            "type":"Retail Goods"
        }
    ],
    "sg:phone":"+1 770 565 7522",
    "sg:postcode":"30062",
    "sg:province":"GA",
    "sg:tags":[
        "announcement",
        "invitation"
    ],
    "wof:name":"Invitation & Stationery Rsrs",
    "wof:placetype":"venue"
},
  "geometry": {"coordinates":[-84.484769,33.980109],"type":"Point"}
}