{
  "type": "Feature",
  "properties": {
    "addr:full":"6328 Knights Way Riverdale GA 30296",
    "addr:housenumber":"6328",
    "addr:postcode":"30296",
    "addr:street":"Knights Way",
    "iso:country":"US",
    "sg:address":"6328 Knights Way",
    "sg:city":"Riverdale",
    "sg:classifiers":[
        {
            "category":"Wholesale",
            "subcategory":"Electrical",
            "type":"Manufacturing & Wholesale Goods"
        }
    ],
    "sg:phone":"+1 770 997 9306",
    "sg:postcode":"30296",
    "sg:province":"GA",
    "wof:name":"Maat Ltd",
    "wof:placetype":"venue"
},
  "geometry": {"coordinates":[-84.445509,33.583349],"type":"Point"}
}