{
  "type": "Feature",
  "properties": {
    "iso:country":"US",
    "sg:address":"205 E Spring St",
    "sg:city":"Monroe",
    "sg:classifiers":[
        {
            "category":"Wholesale",
            "subcategory":"Petroleum",
            "type":"Manufacturing & Wholesale Goods"
        }
    ],
    "sg:phone":"+1 770 267 5011",
    "sg:postcode":"30655",
    "sg:province":"GA",
    "sg:tags":[
        "bulk",
        "station",
        "gasoline"
    ],
    "wof:name":"Brown Oil Company",
    "wof:placetype":"venue"
},
  "geometry": {"coordinates":[-83.71078300000001,33.795168],"type":"Point"}
}