{
  "type": "Feature",
  "properties": {
    "addr:full":"4166 Buford Hwy NE Atlanta GA 30345",
    "addr:housenumber":"4166",
    "addr:postcode":"30345",
    "addr:street":"Buford Hwy Ne",
    "iso:country":"US",
    "sg:address":"4166 Buford Hwy NE",
    "sg:city":"Atlanta",
    "sg:classifiers":[
        {
            "category":"Banks & Credit Unions",
            "subcategory":"Bank",
            "type":"Services"
        }
    ],
    "sg:phone":"+1 404 327 8302",
    "sg:postcode":"30345",
    "sg:province":"GA",
    "sg:tags":[
        "money",
        "transfer"
    ],
    "wof:name":"Western Union",
    "wof:placetype":"venue"
},
  "geometry": {"coordinates":[-84.30579899999999,33.863331],"type":"Point"}
}