{
  "type": "Feature",
  "properties": {
    "addr:full":"3400 Peachtree Rd NE # 1300 Atlanta GA 30326",
    "addr:housenumber":"3400",
    "addr:postcode":"30326",
    "addr:street":"Peachtree Rd Ne # 1300",
    "iso:country":"US",
    "sg:address":"3400 Peachtree Rd NE # 1300",
    "sg:city":"Atlanta",
    "sg:classifiers":[
        {
            "category":"Manufacturing",
            "subcategory":"Paper Products",
            "type":"Manufacturing & Wholesale Goods"
        }
    ],
    "sg:phone":"+1 404 841 9189",
    "sg:postcode":"30326",
    "sg:province":"GA",
    "wof:name":"Sappi Fine Paper",
    "wof:placetype":"venue"
},
  "geometry": {"coordinates":[-84.364998,33.84893],"type":"Point"}
}