{
  "type": "Feature",
  "properties": {
    "addr:full":"1401 N Hairston Rd Stone Mountain GA 30083",
    "addr:housenumber":"1401",
    "addr:postcode":"30083",
    "addr:street":"N Hairston Rd",
    "iso:country":"US",
    "sg:address":"1401 N Hairston Rd",
    "sg:city":"Stone Mountain",
    "sg:classifiers":[
        {
            "category":"Arts & Performance",
            "subcategory":"Theater",
            "type":"Entertainment"
        }
    ],
    "sg:phone":"+1 404 246 1498",
    "sg:postcode":"30083",
    "sg:province":"GA",
    "sg:tags":[
        "bureau"
    ],
    "wof:name":"Navigator Entertainment",
    "wof:placetype":"venue"
},
  "geometry": {"coordinates":[-84.193623,33.818887],"type":"Point"}
}