{
  "type": "Feature",
  "properties": {
    "iso:country":"US",
    "sg:address":"5175 Lupine Ln",
    "sg:city":"Acworth",
    "sg:classifiers":[
        {
            "category":"Professional",
            "subcategory":"Business Services",
            "type":"Services"
        }
    ],
    "sg:phone":"+1 678 445 9061",
    "sg:postcode":"30102",
    "sg:province":"GA",
    "wof:name":"Ankh Affiliates Inc",
    "wof:placetype":"venue"
},
  "geometry": {"coordinates":[-84.572816,34.070944],"type":"Point"}
}