{
  "type": "Feature",
  "properties": {
    "addr:full":"1265 Kelleytown Rd Mcdonough GA 30252",
    "addr:housenumber":"1265",
    "addr:postcode":"30252",
    "addr:street":"Kelleytown Rd",
    "iso:country":"US",
    "sg:address":"1265 Kelleytown Rd",
    "sg:city":"Mcdonough",
    "sg:classifiers":[
        {
            "category":"Freight",
            "type":"Transportation"
        }
    ],
    "sg:phone":"+1 770 898 9599",
    "sg:postcode":"30252",
    "sg:province":"GA",
    "sg:tags":[
        "operator",
        "local",
        "hauling",
        "trucking"
    ],
    "wof:name":"Basler Hauling",
    "wof:placetype":"venue"
},
  "geometry": {"coordinates":[-84.105807,33.547446],"type":"Point"}
}