{
  "type": "Feature",
  "properties": {
    "iso:country":"US",
    "sg:address":"182 Hackberry Ln",
    "sg:city":"Ocilla",
    "sg:classifiers":[
        {
            "category":"Building & Trades",
            "subcategory":"Construction",
            "type":"Services"
        }
    ],
    "sg:phone":"+1 229 468 5379",
    "sg:postcode":"31774",
    "sg:province":"GA",
    "sg:tags":[
        "contractor"
    ],
    "wof:name":"Soles Bros Drywall",
    "wof:placetype":"venue"
},
  "geometry": {"coordinates":[-83.39148400000001,31.560843],"type":"Point"}
}