{
  "type": "Feature",
  "properties": {
    "addr:full":"135 Woodberry Ct Athens GA 30605",
    "addr:housenumber":"135",
    "addr:postcode":"30605",
    "addr:street":"Woodberry Ct",
    "iso:country":"US",
    "sg:address":"135 Woodberry Ct",
    "sg:city":"Athens",
    "sg:classifiers":[
        {
            "category":"Organizations",
            "subcategory":"Religious Organization",
            "type":"Services"
        }
    ],
    "sg:phone":"+1 706 353 3772",
    "sg:postcode":"30605",
    "sg:province":"GA",
    "sg:tags":[
        "church"
    ],
    "wof:name":"Faith Evangelical Methodist Ch",
    "wof:placetype":"venue"
},
  "geometry": {"coordinates":[-83.334642,33.904545],"type":"Point"}
}