{
  "type": "Feature",
  "properties": {
    "addr:full":"4939 Winters Chapel Rd # 800 Atlanta GA 30360",
    "addr:housenumber":"4939",
    "addr:postcode":"30360",
    "addr:street":"Winters Chapel Rd # 800",
    "iso:country":"US",
    "sg:address":"4939 Winters Chapel Rd # 800",
    "sg:city":"Atlanta",
    "sg:classifiers":[
        {
            "category":"Retail",
            "subcategory":"Laundry & Dry Cleaning",
            "type":"Services"
        }
    ],
    "sg:phone":"+1 770 392 4300",
    "sg:postcode":"30360",
    "sg:province":"GA",
    "sg:tags":[
        "laundries-self",
        "operated",
        "washer",
        "dryer",
        "coin"
    ],
    "wof:name":"Casa Blanca",
    "wof:placetype":"venue"
},
  "geometry": {"coordinates":[-84.27002299999999,33.940258],"type":"Point"}
}