{
  "type": "Feature",
  "properties": {
    "addr:full":"118 Temple Ave W Newnan GA 30263",
    "addr:housenumber":"118",
    "addr:postcode":"30263",
    "addr:street":"Temple Ave W",
    "iso:country":"US",
    "sg:address":"118 Temple Ave W",
    "sg:city":"Newnan",
    "sg:classifiers":[
        {
            "category":"Autos & Motor Vehicles",
            "subcategory":"Fuel & Gas Station",
            "type":"Retail Goods"
        }
    ],
    "sg:phone":"+1 770 251 5768",
    "sg:postcode":"30263",
    "sg:province":"GA",
    "sg:tags":[
        "station",
        "gasoline"
    ],
    "wof:name":"Amoco",
    "wof:placetype":"venue"
},
  "geometry": {"coordinates":[-84.809578,33.380711],"type":"Point"}
}