{
  "type": "Feature",
  "properties": {
    "addr:full":"3473 Old Norcross Rd Duluth GA 30096",
    "addr:housenumber":"3473",
    "addr:postcode":"30096",
    "addr:street":"Old Norcross Rd",
    "iso:country":"US",
    "sg:address":"3473 Old Norcross Rd",
    "sg:city":"Duluth",
    "sg:classifiers":[
        {
            "category":"Banks & Credit Unions",
            "subcategory":"Bank",
            "type":"Services"
        }
    ],
    "sg:phone":"+1 678 584 9922",
    "sg:postcode":"30096",
    "sg:province":"GA",
    "wof:name":"Keb Ny Financial Corp Atlanta Office",
    "wof:placetype":"venue"
},
  "geometry": {"coordinates":[-84.13295599999999,33.965822],"type":"Point"}
}