{
  "type": "Feature",
  "properties": {
    "addr:full":"3155 Pleasantdale Road Atlanta GA 30340",
    "addr:housenumber":"3155",
    "addr:postcode":"30340",
    "addr:street":"Pleasantdale Road",
    "iso:country":"US",
    "sg:address":"3155 Pleasantdale Road",
    "sg:city":"Atlanta",
    "sg:classifiers":[
        {
            "category":"Food & Beverages",
            "subcategory":"Groceries & Convenience Stores",
            "type":"Retail Goods"
        }
    ],
    "sg:phone":"+1 770 723 1306",
    "sg:postcode":"30340",
    "sg:province":"GA",
    "sg:website":"www.shell.com",
    "wof:name":"Shell Food Mart",
    "wof:placetype":"venue"
},
  "geometry": {"coordinates":[-84.221301,33.884521],"type":"Point"}
}