{
  "type": "Feature",
  "properties": {
    "addr:full":"5214 Ramble Trl Buford GA 30518",
    "addr:housenumber":"5214",
    "addr:postcode":"30518",
    "addr:street":"Ramble Trl",
    "iso:country":"US",
    "sg:address":"5214 Ramble Trl",
    "sg:city":"Buford",
    "sg:classifiers":[
        {
            "category":"Professional",
            "type":"Services"
        }
    ],
    "sg:phone":"+1 770 271 7796",
    "sg:postcode":"30518",
    "sg:province":"GA",
    "wof:name":"Lasting Impressions",
    "wof:placetype":"venue"
},
  "geometry": {"coordinates":[-83.955754,34.137608],"type":"Point"}
}