{
  "type": "Feature",
  "properties": {
    "addr:full":"3615 Lakeside Pt NW Kennesaw GA 30144",
    "addr:housenumber":"3615",
    "addr:postcode":"30144",
    "addr:street":"Lakeside Pt Nw",
    "iso:country":"US",
    "sg:address":"3615 Lakeside Pt NW",
    "sg:city":"Kennesaw",
    "sg:classifiers":[
        {
            "category":"Professional",
            "type":"Services"
        }
    ],
    "sg:phone":"+1 770 514 8970",
    "sg:postcode":"30144",
    "sg:province":"GA",
    "wof:name":"Gloria Mino",
    "wof:placetype":"venue"
},
  "geometry": {"coordinates":[-84.56024499999999,34.040178],"type":"Point"}
}