{
  "type": "Feature",
  "properties": {
    "addr:full":"1200 Ashwood Pkwy Atlanta GA 30338",
    "addr:housenumber":"1200",
    "addr:postcode":"30338",
    "addr:street":"Ashwood Pkwy",
    "iso:country":"US",
    "sg:address":"1200 Ashwood Pkwy",
    "sg:city":"Atlanta",
    "sg:classifiers":[
        {
            "category":"Professional",
            "subcategory":"Management & Consulting",
            "type":"Services"
        },
        {
            "category":"Travel",
            "subcategory":"Hotels & Motels",
            "type":"Entertainment"
        }
    ],
    "sg:phone":"+1 770 206 9888",
    "sg:postcode":"30338",
    "sg:province":"GA",
    "sg:tags":[
        "business"
    ],
    "wof:name":"Starwood Hotels & Resorts",
    "wof:placetype":"venue"
},
  "geometry": {"coordinates":[-84.338841,33.933685],"type":"Point"}
}