{
  "type": "Feature",
  "properties": {
    "addr:full":"154 Selig Dr SW Atlanta GA 30336",
    "addr:housenumber":"154",
    "addr:postcode":"30336",
    "addr:street":"Selig Dr Sw",
    "iso:country":"US",
    "sg:address":"154 Selig Dr SW",
    "sg:city":"Atlanta",
    "sg:classifiers":[
        {
            "category":"Home & Garden",
            "subcategory":"Furniture",
            "type":"Retail Goods"
        }
    ],
    "sg:phone":"+1 404 472 1944",
    "sg:postcode":"30336",
    "sg:province":"GA",
    "sg:tags":[
        "top",
        "counter"
    ],
    "wof:name":"M I Granite",
    "wof:placetype":"venue"
},
  "geometry": {"coordinates":[-84.539907,33.75755],"type":"Point"}
}