{
  "type": "Feature",
  "properties": {
    "addr:full":"1240 Johnson Ferry Rd Marietta GA 30068",
    "addr:housenumber":"1240",
    "addr:postcode":"30068",
    "addr:street":"Johnson Ferry Rd",
    "iso:country":"US",
    "sg:address":"1240 Johnson Ferry Rd",
    "sg:city":"Marietta",
    "sg:classifiers":[
        {
            "category":"Shopping",
            "subcategory":"Computers & Home Electronics",
            "type":"Retail Goods"
        }
    ],
    "sg:phone":"+1 770 448 6633",
    "sg:postcode":"30068",
    "sg:province":"GA",
    "wof:name":"P C Warehouse",
    "wof:placetype":"venue"
},
  "geometry": {"coordinates":[-84.421761,33.979549],"type":"Point"}
}