{
  "type": "Feature",
  "properties": {
    "addr:full":"209 W Currahee St Toccoa GA 30577",
    "addr:housenumber":"209",
    "addr:postcode":"30577",
    "addr:street":"W Currahee St",
    "iso:country":"US",
    "sg:address":"209 W Currahee St",
    "sg:city":"Toccoa",
    "sg:classifiers":[
        {
            "category":"Wholesale",
            "subcategory":"Groceries",
            "type":"Manufacturing & Wholesale Goods"
        }
    ],
    "sg:phone":"+1 706 886 2850",
    "sg:postcode":"30577",
    "sg:province":"GA",
    "sg:tags":[
        "beverage"
    ],
    "wof:name":"Nehi-Royal Crown Bottling Co",
    "wof:placetype":"venue"
},
  "geometry": {"coordinates":[-83.333619,34.57724],"type":"Point"}
}