{
  "type": "Feature",
  "properties": {
    "iso:country":"US",
    "sg:address":"4192 Bath Edie Rd",
    "sg:city":"Hephzibah",
    "sg:classifiers":[
        {
            "category":"Shopping",
            "type":"Retail Goods"
        }
    ],
    "sg:phone":"+1 706 592 0874",
    "sg:postcode":"30815",
    "sg:province":"GA",
    "sg:tags":[
        "merchandise"
    ],
    "wof:name":"Booz International Arts",
    "wof:placetype":"venue"
},
  "geometry": {"coordinates":[-82.160089,33.311612],"type":"Point"}
}