{
  "type": "Feature",
  "properties": {
    "iso:country":"US",
    "sg:address":"360 Creekside Ct",
    "sg:city":"Alpharetta",
    "sg:classifiers":[
        {
            "category":"Wholesale",
            "subcategory":"Durable Goods & Equipment",
            "type":"Manufacturing & Wholesale Goods"
        }
    ],
    "sg:phone":"+1 770 664 0555",
    "sg:postcode":"30022",
    "sg:province":"GA",
    "sg:tags":[
        "professional"
    ],
    "wof:name":"Zambrana Engineering Inc",
    "wof:placetype":"venue"
},
  "geometry": {"coordinates":[-84.225798,34.058359],"type":"Point"}
}