{
  "type": "Feature",
  "properties": {
    "iso:country":"US",
    "sg:address":"200 Riverside Dr",
    "sg:city":"Waycross",
    "sg:classifiers":[
        {
            "category":"Health Services",
            "subcategory":"Medical Lab",
            "type":"Services"
        }
    ],
    "sg:phone":"+1 912 284 0477",
    "sg:postcode":"31501",
    "sg:province":"GA",
    "sg:tags":[
        "laboratory",
        "dental"
    ],
    "wof:name":"Personal Touch Dental Lab",
    "wof:placetype":"venue"
},
  "geometry": {"coordinates":[-82.350921,31.219376],"type":"Point"}
}