{
  "type": "Feature",
  "properties": {
    "iso:country":"US",
    "sg:address":"7257 Lower Meigs Rd",
    "sg:city":"Meigs",
    "sg:classifiers":[
        {
            "category":"Farming",
            "subcategory":"Farm",
            "type":"Manufacturing & Wholesale Goods"
        }
    ],
    "sg:phone":"+1 229 683 3140",
    "sg:postcode":"31765",
    "sg:province":"GA",
    "sg:tags":[
        "crop",
        "general"
    ],
    "wof:name":"White Farms",
    "wof:placetype":"venue"
},
  "geometry": {"coordinates":[-84.003356,31.077568],"type":"Point"}
}