{
  "type": "Feature",
  "properties": {
    "addr:full":"2608 Clay Ct Jonesboro GA 30236",
    "addr:housenumber":"2608",
    "addr:postcode":"30236",
    "addr:street":"Clay Ct",
    "iso:country":"US",
    "sg:address":"2608 Clay Ct",
    "sg:city":"Jonesboro",
    "sg:classifiers":[
        {
            "category":"Building & Trades",
            "subcategory":"Construction",
            "type":"Services"
        }
    ],
    "sg:phone":"+1 770 471 0995",
    "sg:postcode":"30236",
    "sg:province":"GA",
    "sg:tags":[
        "hanging",
        "contractor"
    ],
    "wof:name":"Design Coatings",
    "wof:placetype":"venue"
},
  "geometry": {"coordinates":[-84.306651,33.528015],"type":"Point"}
}