{
  "type": "Feature",
  "properties": {
    "addr:full":"3365 Steve Reynolds Blvd Duluth GA 30096",
    "addr:housenumber":"3365",
    "addr:postcode":"30096",
    "addr:street":"Steve Reynolds Blvd",
    "iso:country":"US",
    "sg:address":"3365 Steve Reynolds Blvd",
    "sg:city":"Duluth",
    "sg:classifiers":[
        {
            "category":"Fast Food",
            "type":"Food & Drink"
        }
    ],
    "sg:phone":"+1 770 476 4632",
    "sg:postcode":"30096",
    "sg:province":"GA",
    "sg:tags":[
        "chicken",
        "wing"
    ],
    "sg:website":"www.worldwingsduluth.com",
    "wof:name":"World Wings",
    "wof:placetype":"venue"
},
  "geometry": {"coordinates":[-84.140636,33.952896],"type":"Point"}
}