{
  "type": "Feature",
  "properties": {
    "addr:full":"28 E 41st St Savannah GA 31401",
    "addr:housenumber":"28",
    "addr:postcode":"31401",
    "addr:street":"E 41St St",
    "iso:country":"US",
    "sg:address":"28 E 41st St",
    "sg:city":"Savannah",
    "sg:classifiers":[
        {
            "category":"Communications",
            "subcategory":"Film & Video Production",
            "type":"Services"
        }
    ],
    "sg:phone":"+1 912 232 3104",
    "sg:postcode":"31401",
    "sg:province":"GA",
    "sg:tags":[
        "multimedia"
    ],
    "wof:name":"Blackbeard Web Hosting",
    "wof:placetype":"venue"
},
  "geometry": {"coordinates":[-81.101257,32.053583],"type":"Point"}
}