{
  "type": "Feature",
  "properties": {
    "addr:full":"9034 Mandarin Dr Jonesboro GA 30236",
    "addr:housenumber":"9034",
    "addr:postcode":"30236",
    "addr:street":"Mandarin Dr",
    "iso:country":"US",
    "sg:address":"9034 Mandarin Dr",
    "sg:city":"Jonesboro",
    "sg:classifiers":[
        {
            "category":"Autos & Motor Vehicles",
            "subcategory":"Fuel & Gas Station",
            "type":"Retail Goods"
        }
    ],
    "sg:phone":"+1 770 477 6083",
    "sg:postcode":"30236",
    "sg:province":"GA",
    "sg:tags":[
        "station",
        "gasoline"
    ],
    "wof:name":"BP Enterprises",
    "wof:placetype":"venue"
},
  "geometry": {"coordinates":[-84.335864,33.508341],"type":"Point"}
}