{
  "type": "Feature",
  "properties": {
    "addr:full":"1432 Vernon Ridge Ct Atlanta GA 30338",
    "addr:housenumber":"1432",
    "addr:postcode":"30338",
    "addr:street":"Vernon Ridge Ct",
    "iso:country":"US",
    "sg:address":"1432 Vernon Ridge Ct",
    "sg:city":"Atlanta",
    "sg:classifiers":[
        {
            "category":"Health Services",
            "subcategory":"Doctor",
            "type":"Services"
        }
    ],
    "sg:phone":"+1 770 396 5799",
    "sg:postcode":"30338",
    "sg:province":"GA",
    "sg:tags":[
        "medical"
    ],
    "wof:name":"E Napier Burson Jr MD",
    "wof:placetype":"venue"
},
  "geometry": {"coordinates":[-84.328148,33.950149],"type":"Point"}
}