{
  "type": "Feature",
  "properties": {
    "iso:country":"US",
    "sg:address":"530 Interchange Dr SW",
    "sg:city":"Atlanta",
    "sg:classifiers":[
        {
            "category":"Wholesale",
            "subcategory":"Hardware",
            "type":"Manufacturing & Wholesale Goods"
        },
        {
            "category":"Building & Trades",
            "subcategory":"Equipment Rental",
            "type":"Services"
        },
        {
            "category":"Home & Garden",
            "subcategory":"Hardware",
            "type":"Retail Goods"
        }
    ],
    "sg:phone":"+1 404 505 8181",
    "sg:postcode":"30336",
    "sg:province":"GA",
    "sg:tags":[
        "contractor",
        "hardware-builders",
        "store",
        "supply"
    ],
    "wof:name":"Southern Laser",
    "wof:placetype":"venue"
},
  "geometry": {"coordinates":[-84.525666,33.769674],"type":"Point"}
}