{
  "type": "Feature",
  "properties": {
    "iso:country":"US",
    "sg:address":"2370 Bankston Cir",
    "sg:city":"Snellville",
    "sg:classifiers":[
        {
            "category":"Building & Trades",
            "subcategory":"Construction",
            "type":"Services"
        }
    ],
    "sg:phone":"+1 770 985 6514",
    "sg:postcode":"30078",
    "sg:province":"GA",
    "sg:tags":[
        "house"
    ],
    "wof:name":"Bellew Construction Co Inc",
    "wof:placetype":"venue"
},
  "geometry": {"coordinates":[-84.033266,33.844044],"type":"Point"}
}