{
  "type": "Feature",
  "properties": {
    "iso:country":"US",
    "sg:address":"430 Connell Rd",
    "sg:city":"Valdosta",
    "sg:classifiers":[
        {
            "category":"Wholesale",
            "subcategory":"Office Equipment",
            "type":"Manufacturing & Wholesale Goods"
        }
    ],
    "sg:phone":"+1 229 242 2679",
    "sg:postcode":"31602",
    "sg:province":"GA",
    "sg:tags":[
        "machine",
        "lease",
        "business",
        "supply"
    ],
    "wof:name":"IKON Office Solutions",
    "wof:placetype":"venue"
},
  "geometry": {"coordinates":[-83.289126,30.871124],"type":"Point"}
}