{
  "type": "Feature",
  "properties": {
    "iso:country":"US",
    "sg:address":"1600 Calhoun Falls Hwy",
    "sg:city":"Elberton",
    "sg:classifiers":[
        {
            "category":"Manufacturing",
            "subcategory":"Tools & Machinery",
            "type":"Manufacturing & Wholesale Goods"
        }
    ],
    "sg:phone":"+1 706 283 5750",
    "sg:postcode":"30635",
    "sg:province":"GA",
    "sg:tags":[
        "farm",
        "machine",
        "mining",
        "mfg"
    ],
    "wof:name":"Johnson Machine Shop Inc",
    "wof:placetype":"venue"
},
  "geometry": {"coordinates":[-82.803403,34.088037],"type":"Point"}
}