{
  "type": "Feature",
  "properties": {
    "addr:full":"Cobb Pkwy Hwy 41 At Atlanta GA 30303",
    "addr:postcode":"30303",
    "addr:street":"Cobb Pkwy Hwy 41 At",
    "iso:country":"US",
    "sg:address":"Cobb Pkwy Hwy 41 At",
    "sg:city":"Atlanta",
    "sg:classifiers":[
        {
            "category":"Autos & Motor Vehicles",
            "subcategory":"Auto Supplies",
            "type":"Retail Goods"
        },
        {
            "category":"Retail",
            "subcategory":"Auto Repair",
            "type":"Services"
        }
    ],
    "sg:phone":"+1 770 426 6563",
    "sg:postcode":"30303",
    "sg:province":"GA",
    "sg:tags":[
        "body",
        "shop",
        "tire"
    ],
    "wof:name":"Hong's Body Shop",
    "wof:placetype":"venue"
},
  "geometry": {"coordinates":[-84.39070100000001,33.756302],"type":"Point"}
}