{
  "type": "Feature",
  "properties": {
    "addr:full":"409 Whiskey Rd Grovetown GA 30813",
    "addr:housenumber":"409",
    "addr:postcode":"30813",
    "addr:street":"Whiskey Rd",
    "iso:country":"US",
    "sg:address":"409 Whiskey Rd",
    "sg:city":"Grovetown",
    "sg:classifiers":[
        {
            "category":"Shopping",
            "subcategory":"Catalog Store",
            "type":"Retail Goods"
        }
    ],
    "sg:phone":"+1 706 868 6527",
    "sg:postcode":"30813",
    "sg:province":"GA",
    "sg:tags":[
        "house",
        "mail"
    ],
    "wof:name":"Kimberlys Catalogs",
    "wof:placetype":"venue"
},
  "geometry": {"coordinates":[-82.20325800000001,33.46115],"type":"Point"}
}