{
  "type": "Feature",
  "properties": {
    "addr:full":"680 Rogers St Roopville GA 30170",
    "addr:housenumber":"680",
    "addr:postcode":"30170",
    "addr:street":"Rogers St",
    "iso:country":"US",
    "sg:address":"680 Rogers St",
    "sg:city":"Roopville",
    "sg:classifiers":[
        {
            "category":"Professional",
            "type":"Services"
        }
    ],
    "sg:phone":"+1 770 854 9211",
    "sg:postcode":"30170",
    "sg:province":"GA",
    "wof:name":"Free & Accepted Masons of",
    "wof:placetype":"venue"
},
  "geometry": {"coordinates":[-85.240893,33.40489],"type":"Point"}
}