{
  "type": "Feature",
  "properties": {
    "iso:country":"US",
    "sg:address":"455 Sheringham Ter",
    "sg:city":"Roswell",
    "sg:classifiers":[
        {
            "category":"Building & Trades",
            "subcategory":"Construction",
            "type":"Services"
        }
    ],
    "sg:phone":"+1 770 552 8654",
    "sg:postcode":"30076",
    "sg:province":"GA",
    "sg:tags":[
        "house"
    ],
    "wof:name":"North Atlanta Homecrafters",
    "wof:placetype":"venue"
},
  "geometry": {"coordinates":[-84.29323100000001,34.033851],"type":"Point"}
}