{
  "type": "Feature",
  "properties": {
    "addr:full":"549 Villa Pl Augusta GA 30907",
    "addr:housenumber":"549",
    "addr:postcode":"30907",
    "addr:street":"Villa Pl",
    "iso:country":"US",
    "sg:address":"549 Villa Pl",
    "sg:city":"Augusta",
    "sg:classifiers":[
        {
            "category":"Building & Trades",
            "subcategory":"Cleaning & Sanitation",
            "type":"Services"
        }
    ],
    "sg:phone":"+1 706 855 9824",
    "sg:postcode":"30907",
    "sg:province":"GA",
    "sg:tags":[
        "janitor"
    ],
    "wof:name":"Hood Cleaners Of Augusta",
    "wof:placetype":"venue"
},
  "geometry": {"coordinates":[-82.092457,33.540626],"type":"Point"}
}