{
  "type": "Feature",
  "properties": {
    "iso:country":"US",
    "sg:address":"100 Galleria Pkwy",
    "sg:city":"Atlanta",
    "sg:classifiers":[
        {
            "category":"Freight",
            "type":"Transportation"
        },
        {
            "category":"Ferry",
            "type":"Transportation"
        }
    ],
    "sg:phone":"+1 770 980 2043",
    "sg:postcode":"30339",
    "sg:province":"GA",
    "sg:tags":[
        "company",
        "deep",
        "sea",
        "steamship"
    ],
    "sg:website":"www.hmm21.com",
    "wof:name":"Hyundai America Shipping AGNCY",
    "wof:placetype":"venue"
},
  "geometry": {"coordinates":[-84.465299,33.882784],"type":"Point"}
}