{
  "type": "Feature",
  "properties": {
    "addr:full":"5538 Whittlesey Blvd Columbus GA 31909",
    "addr:postcode":"5538;31909",
    "addr:street":"Whittlesey Blvd",
    "iso:country":"US",
    "sg:address":"5538 Whittlesey Blvd",
    "sg:city":"Columbus",
    "sg:classifiers":[
        {
            "category":"Banks & Credit Unions",
            "subcategory":"Bank",
            "type":"Services"
        },
        {
            "category":"Banks & Credit Unions",
            "subcategory":"Financial Services",
            "type":"Services"
        }
    ],
    "sg:phone":"+1 706 324 1095",
    "sg:postcode":"31909",
    "sg:province":"GA",
    "sg:tags":[
        "commercial",
        "loan",
        "saving",
        "mortgage"
    ],
    "sg:website":"https://www.wachovia.com/?DCMP=KNL-CPS-DS-Directory-0703&HBX_PK=Banks&HBX_OU=71",
    "wof:name":"Wachovia Bank",
    "wof:placetype":"venue"
},
  "geometry": {"coordinates":[-84.948644,32.542395],"type":"Point"}
}