{
  "type": "Feature",
  "properties": {
    "iso:country":"US",
    "sg:address":"2154 River Cliff Dr",
    "sg:city":"Roswell",
    "sg:classifiers":[
        {
            "category":"Wholesale",
            "subcategory":"Non-durable Goods",
            "type":"Manufacturing & Wholesale Goods"
        }
    ],
    "sg:phone":"+1 770 641 0379",
    "sg:postcode":"30076",
    "sg:province":"GA",
    "sg:tags":[
        "company",
        "holding"
    ],
    "wof:name":"Kudzu Fabrics Inc",
    "wof:placetype":"venue"
},
  "geometry": {"coordinates":[-84.295243,33.992918],"type":"Point"}
}