{
  "type": "Feature",
  "properties": {
    "iso:country":"US",
    "sg:address":"5400 Laurel Springs Pkwy Ste 801",
    "sg:city":"Suwanee",
    "sg:classifiers":[
        {
            "category":"Health Services",
            "subcategory":"Chiropractor",
            "type":"Services"
        }
    ],
    "sg:phone":"+1 770 889 4800",
    "sg:postcode":"30024",
    "sg:province":"GA",
    "wof:name":"Absolute Health Care Centers",
    "wof:placetype":"venue"
},
  "geometry": {"coordinates":[-84.15760899999999,34.084716],"type":"Point"}
}