{
  "type": "Feature",
  "properties": {
    "iso:country":"US",
    "sg:address":"4907 Springfield Dr",
    "sg:city":"Atlanta",
    "sg:classifiers":[
        {
            "category":"Professional",
            "type":"Services"
        }
    ],
    "sg:phone":"+1 770 396 5296",
    "sg:postcode":"30338",
    "sg:province":"GA",
    "wof:name":"A Donly Chase",
    "wof:placetype":"venue"
},
  "geometry": {"coordinates":[-84.323759,33.941358],"type":"Point"}
}