{
  "type": "Feature",
  "properties": {
    "iso:country":"US",
    "sg:address":"315 Riverbend Rd",
    "sg:city":"Athens",
    "sg:classifiers":[
        {
            "category":"Education",
            "subcategory":"College",
            "type":"Public Place"
        }
    ],
    "sg:phone":"+1 706 542 4401",
    "sg:postcode":"30602",
    "sg:province":"GA",
    "wof:name":"Complex Carbohydrate RES Ctr",
    "wof:placetype":"venue"
},
  "geometry": {"coordinates":[-83.36876599999999,33.92777],"type":"Point"}
}