{
  "type": "Feature",
  "properties": {
    "addr:full":"1326 Veterans Pkwy Columbus GA 31901",
    "addr:housenumber":"1326",
    "addr:postcode":"31901",
    "addr:street":"Veterans Pkwy",
    "iso:country":"US",
    "sg:address":"1326 Veterans Pkwy",
    "sg:city":"Columbus",
    "sg:classifiers":[
        {
            "category":"Restaurant",
            "type":"Food & Drink"
        }
    ],
    "sg:phone":"+1 706 327 2556",
    "sg:postcode":"31901",
    "sg:province":"GA",
    "sg:tags":[
        "eating"
    ],
    "wof:name":"Krystal Restaurant",
    "wof:placetype":"venue"
},
  "geometry": {"coordinates":[-84.987459,32.471882],"type":"Point"}
}