{
  "type": "Feature",
  "properties": {
    "iso:country":"US",
    "sg:address":"200 Robinson Dr",
    "sg:city":"Fayetteville",
    "sg:classifiers":[
        {
            "category":"Building & Trades",
            "subcategory":"Electrical",
            "type":"Services"
        }
    ],
    "sg:phone":"+1 770 460 0671",
    "sg:postcode":"30214",
    "sg:province":"GA",
    "sg:tags":[
        "electrical",
        "electric",
        "contractor"
    ],
    "wof:name":"Ken Nix & Associates Inc",
    "wof:placetype":"venue"
},
  "geometry": {"coordinates":[-84.430012,33.456856],"type":"Point"}
}