{
  "type": "Feature",
  "properties": {
    "addr:full":"549 Amsterdam Ave NE Atlanta GA 30306",
    "addr:housenumber":"549",
    "addr:postcode":"30306",
    "addr:street":"Amsterdam Ave Ne",
    "iso:country":"US",
    "sg:address":"549 Amsterdam Ave NE",
    "sg:city":"Atlanta",
    "sg:classifiers":[
        {
            "category":"Shopping",
            "type":"Retail Goods"
        }
    ],
    "sg:phone":"+1 404 881 8672",
    "sg:postcode":"30306",
    "sg:province":"GA",
    "sg:tags":[
        "merchandise"
    ],
    "wof:name":"Furahas A Picture Frame Place",
    "wof:placetype":"venue"
},
  "geometry": {"coordinates":[-84.36752199999999,33.788144],"type":"Point"}
}