{
  "type": "Feature",
  "properties": {
    "addr:full":"1 Co Rd 211 Brunswick GA 31539",
    "addr:housenumber":"1;211",
    "addr:postcode":"31539",
    "addr:street":"Co Rd",
    "iso:country":"US",
    "sg:address":"1 Co Rd 211",
    "sg:city":"Brunswick",
    "sg:classifiers":[
        {
            "category":"Government",
            "subcategory":"Office",
            "type":"Public Place"
        }
    ],
    "sg:phone":"+1 912 262 3173",
    "sg:postcode":"31539",
    "sg:province":"GA",
    "wof:name":"Game Management",
    "wof:placetype":"venue"
},
  "geometry": {"coordinates":[-82.55018200000001,31.893095],"type":"Point"}
}