{
  "type": "Feature",
  "properties": {
    "iso:country":"US",
    "sg:address":"1570 Elgaen Place Dr",
    "sg:city":"Roswell",
    "sg:classifiers":[
        {
            "category":"Professional",
            "subcategory":"Management & Consulting",
            "type":"Services"
        }
    ],
    "sg:phone":"+1 770 650 8682",
    "sg:postcode":"30075",
    "sg:province":"GA",
    "wof:name":"Strategic Marketing Consulting",
    "wof:placetype":"venue"
},
  "geometry": {"coordinates":[-84.382695,34.054226],"type":"Point"}
}