{
  "type": "Feature",
  "properties": {
    "iso:country":"US",
    "sg:address":"1108 1st St",
    "sg:city":"Vidalia",
    "sg:classifiers":[
        {
            "category":"Building & Trades",
            "subcategory":"Construction",
            "type":"Services"
        }
    ],
    "sg:phone":"+1 912 537 7124",
    "sg:postcode":"30474",
    "sg:province":"GA",
    "sg:tags":[
        "house"
    ],
    "wof:name":"Scherer Cnstr Middle GA LLC",
    "wof:placetype":"venue"
},
  "geometry": {"coordinates":[-82.40236299999999,32.212894],"type":"Point"}
}