{
  "type": "Feature",
  "properties": {
    "addr:full":"456 Northside Dr NW Atlanta GA 30318",
    "addr:housenumber":"456",
    "addr:postcode":"30318",
    "addr:street":"Northside Dr Nw",
    "iso:country":"US",
    "sg:address":"456 Northside Dr NW",
    "sg:city":"Atlanta",
    "sg:classifiers":[
        {
            "category":"Organizations",
            "subcategory":"Religious Organization",
            "type":"Services"
        }
    ],
    "sg:phone":"+1 404 522 3051",
    "sg:postcode":"30318",
    "sg:province":"GA",
    "wof:name":"Antioch Urban Ministries Inc",
    "wof:placetype":"venue"
},
  "geometry": {"coordinates":[-84.404861,33.767193],"type":"Point"}
}