{
  "type": "Feature",
  "properties": {
    "addr:full":"521 Pine Springs Trl SE Marietta GA 30067",
    "addr:housenumber":"521",
    "addr:postcode":"30067",
    "addr:street":"Pine Springs Trl Se",
    "iso:country":"US",
    "sg:address":"521 Pine Springs Trl SE",
    "sg:city":"Marietta",
    "sg:classifiers":[
        {
            "category":"Autos & Motor Vehicles",
            "subcategory":"Automobile Sales",
            "type":"Retail Goods"
        }
    ],
    "sg:phone":"+1 770 318 1401",
    "sg:postcode":"30067",
    "sg:province":"GA",
    "sg:tags":[
        "used"
    ],
    "wof:name":"Ferguson Auto Sales Inc",
    "wof:placetype":"venue"
},
  "geometry": {"coordinates":[-84.475176,33.942098],"type":"Point"}
}