{
  "type": "Feature",
  "properties": {
    "iso:country":"US",
    "sg:address":"995 Broadway Ave",
    "sg:city":"Braselton",
    "sg:classifiers":[
        {
            "category":"Professional",
            "type":"Services"
        }
    ],
    "sg:phone":"+1 706 658 0067",
    "sg:postcode":"30517",
    "sg:province":"GA",
    "wof:name":"Conlan Company",
    "wof:placetype":"venue"
},
  "geometry": {"coordinates":[-83.776618,34.105118],"type":"Point"}
}