{
  "type": "Feature",
  "properties": {
    "iso:country":"US",
    "sg:address":"1009 Midway Rd NW",
    "sg:city":"Resaca",
    "sg:classifiers":[
        {
            "category":"Professional",
            "type":"Services"
        }
    ],
    "sg:phone":"+1 706 602 9369",
    "sg:postcode":"30735",
    "sg:province":"GA",
    "wof:name":"Travis D Smith",
    "wof:placetype":"venue"
},
  "geometry": {"coordinates":[-84.993414,34.614281],"type":"Point"}
}