{
  "type": "Feature",
  "properties": {
    "iso:country":"US",
    "sg:address":"6263 Hwy 278 NE",
    "sg:city":"Covington",
    "sg:classifiers":[
        {
            "category":"Home & Garden",
            "subcategory":"Hardware",
            "type":"Retail Goods"
        }
    ],
    "sg:phone":"+1 678 342 7202",
    "sg:postcode":"30014",
    "sg:province":"GA",
    "wof:name":"Top Computer Hardware",
    "wof:placetype":"venue"
},
  "geometry": {"coordinates":[-83.84251500000001,33.602204],"type":"Point"}
}