{
  "type": "Feature",
  "properties": {
    "iso:country":"US",
    "sg:address":"1639 Bradley Park Dr # 228",
    "sg:city":"Columbus",
    "sg:classifiers":[
        {
            "category":"Health Services",
            "subcategory":"Clinic",
            "type":"Services"
        }
    ],
    "sg:phone":"+1 706 442 5815",
    "sg:postcode":"31904",
    "sg:province":"GA",
    "sg:tags":[
        "welfare"
    ],
    "wof:name":"Miles Managament Group",
    "wof:placetype":"venue"
},
  "geometry": {"coordinates":[-84.967356,32.53235],"type":"Point"}
}