{
  "type": "Feature",
  "properties": {
    "addr:full":"6993 Tammy Ln Lithia Springs GA 30122",
    "addr:housenumber":"6993",
    "addr:postcode":"30122",
    "addr:street":"Tammy Ln",
    "iso:country":"US",
    "sg:address":"6993 Tammy Ln",
    "sg:city":"Lithia Springs",
    "sg:classifiers":[
        {
            "category":"Professional",
            "subcategory":"Computer Services",
            "type":"Services"
        }
    ],
    "sg:phone":"+1 770 941 1080",
    "sg:postcode":"30122",
    "sg:province":"GA",
    "sg:tags":[
        "related"
    ],
    "wof:name":"Hallstrom Consultants",
    "wof:placetype":"venue"
},
  "geometry": {"coordinates":[-84.669837,33.785025],"type":"Point"}
}