{
  "type": "Feature",
  "properties": {
    "addr:full":"2904 State Rte 154 Newnan GA 30265",
    "addr:housenumber":"2904",
    "addr:postcode":"30265",
    "addr:street":"State Rte 154",
    "iso:country":"US",
    "sg:address":"2904 State Rte 154",
    "sg:city":"Newnan",
    "sg:classifiers":[
        {
            "category":"Retail",
            "subcategory":"Veterinary Services",
            "type":"Services"
        }
    ],
    "sg:phone":"+1 770 253 1020",
    "sg:postcode":"30265",
    "sg:province":"GA",
    "sg:tags":[
        "hospital",
        "animal"
    ],
    "wof:name":"Crossroads Animal Hospital Brd",
    "wof:placetype":"venue"
},
  "geometry": {"coordinates":[-84.682693,33.411037],"type":"Point"}
}