{
  "type": "Feature",
  "properties": {
    "iso:country":"US",
    "sg:address":"3334 Colville Ave",
    "sg:city":"Atlanta",
    "sg:classifiers":[
        {
            "category":"Food & Beverages",
            "subcategory":"Groceries & Convenience Stores",
            "type":"Retail Goods"
        }
    ],
    "sg:phone":"+1 404 766 0001",
    "sg:postcode":"30354",
    "sg:province":"GA",
    "sg:tags":[
        "restaurant"
    ],
    "wof:name":"U&S American Deli",
    "wof:placetype":"venue"
},
  "geometry": {"coordinates":[-84.418297,33.662971],"type":"Point"}
}