{
  "type": "Feature",
  "properties": {
    "iso:country":"US",
    "sg:address":"200 D W Brooks Dr",
    "sg:city":"Athens",
    "sg:classifiers":[
        {
            "category":"Restaurant",
            "type":"Food & Drink"
        }
    ],
    "sg:phone":"+1 706 542 6359",
    "sg:postcode":"30602",
    "sg:province":"GA",
    "sg:tags":[
        "eating"
    ],
    "wof:name":"Garden Room Cafe",
    "wof:placetype":"venue"
},
  "geometry": {"coordinates":[-83.37591999999999,33.932939],"type":"Point"}
}