{
  "type": "Feature",
  "properties": {
    "addr:full":"211 College Ave SE Gainesville GA 30501",
    "addr:housenumber":"211",
    "addr:postcode":"30501",
    "addr:street":"College Ave Se;Ga",
    "iso:country":"US",
    "sg:address":"211 College Ave SE",
    "sg:city":"Gainesville",
    "sg:classifiers":[
        {
            "category":"Retail",
            "subcategory":"Repair Shop",
            "type":"Services"
        }
    ],
    "sg:phone":"+1 770 534 2888",
    "sg:postcode":"30501",
    "sg:province":"GA",
    "sg:tags":[
        "lock",
        "locksmith"
    ],
    "wof:name":"A Downs Locksmith",
    "wof:placetype":"venue"
},
  "geometry": {"coordinates":[-83.822205,34.296251],"type":"Point"}
}