{
  "type": "Feature",
  "properties": {
    "addr:full":"800 Arbor Forest Pl SW Marietta GA 30064",
    "addr:housenumber":"800",
    "addr:postcode":"30064",
    "addr:street":"Arbor Forest Pl Sw",
    "iso:country":"US",
    "sg:address":"800 Arbor Forest Pl SW",
    "sg:city":"Marietta",
    "sg:classifiers":[
        {
            "category":"Building & Trades",
            "subcategory":"Locksmith",
            "type":"Services"
        }
    ],
    "sg:phone":"+1 770 250 0508",
    "sg:postcode":"30064",
    "sg:province":"GA",
    "sg:tags":[
        "key"
    ],
    "wof:name":"1 0 1 24 A Emerg Locksmith",
    "wof:placetype":"venue"
},
  "geometry": {"coordinates":[-84.619395,33.933532],"type":"Point"}
}