{
  "type": "Feature",
  "properties": {
    "iso:country":"US",
    "sg:address":"994 Jefferson Hwy",
    "sg:city":"Winder",
    "sg:classifiers":[
        {
            "category":"Building & Trades",
            "subcategory":"Plumbing",
            "type":"Services"
        },
        {
            "category":"Building & Trades",
            "subcategory":"Construction",
            "type":"Services"
        },
        {
            "category":"Building & Trades",
            "subcategory":"Cleaning & Sanitation",
            "type":"Services"
        }
    ],
    "sg:phone":"+1 770 867 6647",
    "sg:postcode":"30680",
    "sg:province":"GA",
    "sg:tags":[
        "tank",
        "septic",
        "supply",
        "excavation",
        "system",
        "contractor",
        "tanks-treatment"
    ],
    "wof:name":"Sims Backhoe Services",
    "wof:placetype":"venue"
},
  "geometry": {"coordinates":[-83.670024,34.028334],"type":"Point"}
}