{
  "type": "Feature",
  "properties": {
    "addr:full":"20 E Main St Forsyth GA 31029",
    "addr:housenumber":"20",
    "addr:postcode":"31029",
    "addr:street":"E Main St",
    "iso:country":"US",
    "sg:address":"20 E Main St",
    "sg:city":"Forsyth",
    "sg:classifiers":[
        {
            "category":"Professional",
            "subcategory":"Lawyer & Legal Services",
            "type":"Services"
        }
    ],
    "sg:phone":"+1 478 994 5134",
    "sg:postcode":"31029",
    "sg:province":"GA",
    "sg:tags":[
        "attorney"
    ],
    "wof:name":"W Franklin Freeman Jr",
    "wof:placetype":"venue"
},
  "geometry": {"coordinates":[-83.924699,33.033807],"type":"Point"}
}