{
  "type": "Feature",
  "properties": {
    "addr:full":"8514 Oak Ct Dallas GA 30132",
    "addr:housenumber":"8514",
    "addr:postcode":"30132",
    "addr:street":"Oak Ct",
    "iso:country":"US",
    "sg:address":"8514 Oak Ct",
    "sg:city":"Dallas",
    "sg:classifiers":[
        {
            "category":"Freight",
            "type":"Transportation"
        }
    ],
    "sg:phone":"+1 281 293 1000",
    "sg:postcode":"30132",
    "sg:province":"GA",
    "sg:tags":[
        "operator",
        "local",
        "trucking"
    ],
    "wof:name":"Conoco Oil Co",
    "wof:placetype":"venue"
},
  "geometry": {"coordinates":[-84.84539599999999,33.838211],"type":"Point"}
}