{
  "type": "Feature",
  "properties": {
    "iso:country":"US",
    "sg:address":"5825 Glenridge Dr NE",
    "sg:city":"Atlanta",
    "sg:classifiers":[
        {
            "category":"Wholesale",
            "subcategory":"Non-durable Goods",
            "type":"Manufacturing & Wholesale Goods"
        }
    ],
    "sg:phone":"+1 404 252 2588",
    "sg:postcode":"30328",
    "sg:province":"GA",
    "sg:tags":[
        "advertising",
        "specialty"
    ],
    "sg:website":"www.creativecorporateideas.com",
    "wof:name":"Creative Corporate Ideas Inc",
    "wof:placetype":"venue"
},
  "geometry": {"coordinates":[-84.362297,33.91632],"type":"Point"}
}