{
  "type": "Feature",
  "properties": {
    "iso:country":"US",
    "sg:address":"131 W Ellis Rd",
    "sg:city":"Griffin",
    "sg:classifiers":[
        {
            "category":"Wholesale",
            "subcategory":"Construction Materials",
            "type":"Manufacturing & Wholesale Goods"
        }
    ],
    "sg:phone":"+1 770 227 8519",
    "sg:postcode":"30223",
    "sg:province":"GA",
    "sg:tags":[
        "sand",
        "gravel",
        "haul"
    ],
    "wof:name":"Archer Sand & Gravel Inc",
    "wof:placetype":"venue"
},
  "geometry": {"coordinates":[-84.296583,33.261139],"type":"Point"}
}