{
  "type": "Feature",
  "properties": {
    "addr:full":"110 Dyer Rd Newnan GA 30263",
    "addr:housenumber":"110",
    "addr:postcode":"30263",
    "addr:street":"Dyer Rd",
    "iso:country":"US",
    "sg:address":"110 Dyer Rd",
    "sg:city":"Newnan",
    "sg:classifiers":[
        {
            "category":"Building & Trades",
            "subcategory":"Plumbing",
            "type":"Services"
        }
    ],
    "sg:phone":"+1 770 304 0220",
    "sg:postcode":"30263",
    "sg:province":"GA",
    "sg:tags":[
        "plumbing",
        "contractor"
    ],
    "wof:name":"Helton Bobcat Svc",
    "wof:placetype":"venue"
},
  "geometry": {"coordinates":[-84.90627499999999,33.449297],"type":"Point"}
}