{
  "type": "Feature",
  "properties": {
    "iso:country":"US",
    "sg:address":"4934 Lower Roswell Rd",
    "sg:city":"Marietta",
    "sg:classifiers":[
        {
            "category":"Wholesale",
            "subcategory":"Machinery & Supplies",
            "type":"Manufacturing & Wholesale Goods"
        }
    ],
    "sg:phone":"+1 770 973 0774",
    "sg:postcode":"30068",
    "sg:province":"GA",
    "sg:tags":[
        "equipment",
        "establishment"
    ],
    "wof:name":"Vacuum Place",
    "wof:placetype":"venue"
},
  "geometry": {"coordinates":[-84.40688900000001,33.965722],"type":"Point"}
}