{
  "type": "Feature",
  "properties": {
    "addr:full":"3024 E Victory Dr Savannah GA 31404",
    "addr:housenumber":"3024",
    "addr:postcode":"31404",
    "addr:street":"E Victory Dr",
    "iso:country":"US",
    "sg:address":"3024 E Victory Dr",
    "sg:city":"Savannah",
    "sg:classifiers":[
        {
            "category":"Autos & Motor Vehicles",
            "subcategory":"Automobile Sales",
            "type":"Retail Goods"
        }
    ],
    "sg:phone":"+1 912 356 5092",
    "sg:postcode":"31404",
    "sg:province":"GA",
    "sg:tags":[
        "car",
        "used",
        "dealer"
    ],
    "wof:name":"Auto World",
    "wof:placetype":"venue"
},
  "geometry": {"coordinates":[-81.05665399999999,32.036665],"type":"Point"}
}