{
  "type": "Feature",
  "properties": {
    "addr:full":"1240 Cumberland Mall Atlanta GA 30339",
    "addr:housenumber":"1240",
    "addr:postcode":"30339",
    "addr:street":"Cumberland Mall",
    "iso:country":"US",
    "sg:address":"1240 Cumberland Mall",
    "sg:city":"Atlanta",
    "sg:classifiers":[
        {
            "category":"Shopping",
            "subcategory":"Clothing, Apparel, & Fashions",
            "type":"Retail Goods"
        }
    ],
    "sg:phone":"+1 770 436 4929",
    "sg:postcode":"30339",
    "sg:province":"GA",
    "wof:name":"Petite Sophisticate",
    "wof:placetype":"venue"
},
  "geometry": {"coordinates":[-84.471132,33.879489],"type":"Point"}
}