{
  "type": "Feature",
  "properties": {
    "addr:full":"2516 Martin Luther King Jr Dr SW Atlanta GA 30311",
    "addr:housenumber":"2516",
    "addr:postcode":"30311",
    "addr:street":"Martin Luther King Jr Dr Sw",
    "iso:country":"US",
    "sg:address":"2516 Martin Luther King Jr Dr SW",
    "sg:city":"Atlanta",
    "sg:classifiers":[
        {
            "category":"Autos & Motor Vehicles",
            "subcategory":"Auto Supplies",
            "type":"Retail Goods"
        }
    ],
    "sg:phone":"+1 404 691 2827",
    "sg:postcode":"30311",
    "sg:province":"GA",
    "sg:tags":[
        "automobile",
        "parts"
    ],
    "sg:website":"www.autozone.com",
    "wof:name":"Autozone",
    "wof:placetype":"venue"
},
  "geometry": {"coordinates":[-84.468401,33.752205],"type":"Point"}
}