{
  "type": "Feature",
  "properties": {
    "addr:full":"523 Greg Dr SW Lilburn GA 30047",
    "addr:housenumber":"523",
    "addr:postcode":"30047",
    "addr:street":"Greg Dr Sw",
    "iso:country":"US",
    "sg:address":"523 Greg Dr SW",
    "sg:city":"Lilburn",
    "sg:classifiers":[
        {
            "category":"Professional",
            "subcategory":"Engineering",
            "type":"Services"
        }
    ],
    "sg:phone":"+1 770 923 2477",
    "sg:postcode":"30047",
    "sg:province":"GA",
    "wof:name":"AR Biswas Pe",
    "wof:placetype":"venue"
},
  "geometry": {"coordinates":[-84.125625,33.870205],"type":"Point"}
}