{
  "type": "Feature",
  "properties": {
    "iso:country":"US",
    "sg:address":"6840 Church St",
    "sg:city":"Douglasville",
    "sg:classifiers":[
        {
            "category":"Government",
            "subcategory":"Office",
            "type":"Public Place"
        }
    ],
    "sg:phone":"+1 770 920 3918",
    "sg:postcode":"30134",
    "sg:province":"GA",
    "sg:tags":[
        "state",
        "program"
    ],
    "wof:name":"State Patrol Drivers License",
    "wof:placetype":"venue"
},
  "geometry": {"coordinates":[-84.753865,33.748248],"type":"Point"}
}