{
  "type": "Feature",
  "properties": {
    "iso:country":"US",
    "sg:address":"124 Hight Dr",
    "sg:city":"Watkinsville",
    "sg:classifiers":[
        {
            "category":"Retail",
            "subcategory":"Repair Shop",
            "type":"Services"
        }
    ],
    "sg:phone":"+1 706 769 9429",
    "sg:postcode":"30677",
    "sg:province":"GA",
    "sg:tags":[
        "electrical"
    ],
    "wof:name":"North Georgia Electronics",
    "wof:placetype":"venue"
},
  "geometry": {"coordinates":[-83.41574,33.863147],"type":"Point"}
}