{
  "type": "Feature",
  "properties": {
    "iso:country":"US",
    "sg:address":"3565 Highway 20 SE Ste C",
    "sg:city":"Conyers",
    "sg:classifiers":[
        {
            "category":"Home & Garden",
            "subcategory":"Furniture",
            "type":"Retail Goods"
        }
    ],
    "sg:phone":"+1 770 602 0833",
    "sg:postcode":"30013",
    "sg:province":"GA",
    "sg:tags":[
        "store"
    ],
    "wof:name":"Mattress Emporium",
    "wof:placetype":"venue"
},
  "geometry": {"coordinates":[-84.01494700000001,33.594686],"type":"Point"}
}