{
  "type": "Feature",
  "properties": {
    "addr:full":"3015 McCall Rd Rincon GA 31326",
    "addr:housenumber":"3015",
    "addr:postcode":"31326",
    "addr:street":"Mccall Rd",
    "iso:country":"US",
    "sg:address":"3015 McCall Rd",
    "sg:city":"Rincon",
    "sg:classifiers":[
        {
            "category":"Shopping",
            "type":"Retail Goods"
        }
    ],
    "sg:phone":"+1 912 754 4679",
    "sg:postcode":"31326",
    "sg:province":"GA",
    "sg:tags":[
        "merchandise"
    ],
    "wof:name":"Awards Express",
    "wof:placetype":"venue"
},
  "geometry": {"coordinates":[-81.28278899999999,32.296276],"type":"Point"}
}