{
  "type": "Feature",
  "properties": {
    "iso:country":"US",
    "sg:address":"6110 Littleton Dr",
    "sg:city":"Union City",
    "sg:classifiers":[
        {
            "category":"Building & Trades",
            "subcategory":"Plumbing",
            "type":"Services"
        }
    ],
    "sg:phone":"+1 770 969 1139",
    "sg:postcode":"30291",
    "sg:province":"GA",
    "sg:tags":[
        "septic"
    ],
    "wof:name":"Action Rooter Drain & Septic",
    "wof:placetype":"venue"
},
  "geometry": {"coordinates":[-84.55930499999999,33.596615],"type":"Point"}
}