{
  "type": "Feature",
  "properties": {
    "iso:country":"US",
    "sg:address":"501 8th St NW",
    "sg:city":"Moultrie",
    "sg:classifiers":[
        {
            "category":"Organizations",
            "subcategory":"Religious Organization",
            "type":"Services"
        }
    ],
    "sg:phone":"+1 229 985 3369",
    "sg:postcode":"31768",
    "sg:province":"GA",
    "sg:tags":[
        "churches-baptist",
        "church"
    ],
    "wof:name":"Live Oak Missionary Baptist Church",
    "wof:placetype":"venue"
},
  "geometry": {"coordinates":[-83.79772199999999,31.184561],"type":"Point"}
}