{
  "type": "Feature",
  "properties": {
    "iso:country":"US",
    "sg:address":"505 Augusta Rd",
    "sg:city":"North Augusta",
    "sg:classifiers":[
        {
            "category":"Retail",
            "subcategory":"Portrait Studio",
            "type":"Services"
        }
    ],
    "sg:phone":"+1 803 441 8925",
    "sg:postcode":"29822",
    "sg:province":"SC",
    "sg:tags":[
        "photographer"
    ],
    "sg:website":"www.wilsonstudio.com",
    "wof:name":"Wilson Studio Of Photography",
    "wof:placetype":"venue"
},
  "geometry": {"coordinates":[-81.89204700000001,33.49671],"type":"Point"}
}