{
  "type": "Feature",
  "properties": {
    "iso:country":"US",
    "sg:address":"330 Galloway Vw",
    "sg:city":"Alpharetta",
    "sg:classifiers":[
        {
            "category":"Professional",
            "subcategory":"Accounting & Tax Preparation",
            "type":"Services"
        }
    ],
    "sg:phone":"+1 770 752 1773",
    "sg:postcode":"30004",
    "sg:province":"GA",
    "sg:tags":[
        "public",
        "accountants-certified"
    ],
    "sg:website":"http://www.jfkcpa.net",
    "wof:name":"John F. Keane, Cpa",
    "wof:placetype":"venue"
},
  "geometry": {"coordinates":[-84.327591,34.157285],"type":"Point"}
}