{
  "type": "Feature",
  "properties": {
    "addr:full":"251 Stroud Dr Mableton GA 30126",
    "addr:housenumber":"251",
    "addr:postcode":"30126",
    "addr:street":"Stroud Dr",
    "iso:country":"US",
    "sg:address":"251 Stroud Dr",
    "sg:city":"Mableton",
    "sg:classifiers":[
        {
            "category":"Professional",
            "subcategory":"Business Services",
            "type":"Services"
        }
    ],
    "sg:phone":"+1 770 948 9866",
    "sg:postcode":"30126",
    "sg:province":"GA",
    "wof:name":"Integrated Design Systems Inc",
    "wof:placetype":"venue"
},
  "geometry": {"coordinates":[-84.54640999999999,33.794883],"type":"Point"}
}