{
  "type": "Feature",
  "properties": {
    "addr:full":"975 Johnson Ferry Rd Atlanta GA 30342",
    "addr:housenumber":"975",
    "addr:postcode":"30342",
    "addr:street":"Johnson Ferry Rd",
    "iso:country":"US",
    "sg:address":"975 Johnson Ferry Rd",
    "sg:city":"Atlanta",
    "sg:classifiers":[
        {
            "category":"Health Services",
            "subcategory":"Doctor",
            "type":"Services"
        }
    ],
    "sg:phone":"+1 404 256 1311",
    "sg:postcode":"30342",
    "sg:province":"GA",
    "sg:tags":[
        "physician",
        "surgeon"
    ],
    "wof:name":"Atlanta Plastic Surgery PC",
    "wof:placetype":"venue"
},
  "geometry": {"coordinates":[-84.356098,33.907649],"type":"Point"}
}