{
  "type": "Feature",
  "properties": {
    "iso:country":"US",
    "sg:address":"2011 Old Salem Rd SE",
    "sg:city":"Conyers",
    "sg:classifiers":[
        {
            "category":"Autos & Motor Vehicles",
            "subcategory":"Auto Supplies",
            "type":"Retail Goods"
        }
    ],
    "sg:phone":"+1 770 483 3836",
    "sg:postcode":"30013",
    "sg:province":"GA",
    "wof:name":"Smith Okelly Auto Parts Inc",
    "wof:placetype":"venue"
},
  "geometry": {"coordinates":[-84.00026800000001,33.633997],"type":"Point"}
}