{
  "type": "Feature",
  "properties": {
    "addr:full":"1530 Peachtree Pkwy Cumming GA 30041",
    "addr:housenumber":"1530",
    "addr:postcode":"30041",
    "addr:street":"Peachtree Pkwy",
    "iso:country":"US",
    "sg:address":"1530 Peachtree Pkwy",
    "sg:city":"Cumming",
    "sg:classifiers":[
        {
            "category":"Bars & Pubs",
            "type":"Food & Drink"
        }
    ],
    "sg:menulink":"http://www.allmenus.com/ga/big-creek/244383-fagans-biscuit-barn/menu/",
    "sg:phone":"+1 678 455 5670",
    "sg:postcode":"30041",
    "sg:province":"GA",
    "sg:tags":[
        "american"
    ],
    "wof:name":"Fagan's Biscuit Barn",
    "wof:placetype":"venue"
},
  "geometry": {"coordinates":[-84.171069,34.123794],"type":"Point"}
}