{
  "type": "Feature",
  "properties": {
    "iso:country":"US",
    "sg:address":"1700 Northside Dr NW Ste B4",
    "sg:city":"Atlanta",
    "sg:phone":"+1 404 355 5510",
    "sg:postcode":"30318",
    "sg:province":"GA",
    "wof:name":"The Arena Barber Salon",
    "wof:placetype":"venue"
},
  "geometry": {"coordinates":[-84.40782900000001,33.8013],"type":"Point"}
}