{
  "type": "Feature",
  "properties": {
    "iso:country":"US",
    "sg:address":"140 Bill Quarterman Rd",
    "sg:city":"Hazlehurst",
    "sg:classifiers":[
        {
            "category":"Wholesale",
            "subcategory":"Construction Materials",
            "type":"Manufacturing & Wholesale Goods"
        }
    ],
    "sg:phone":"+1 912 375 4587",
    "sg:postcode":"31539",
    "sg:province":"GA",
    "wof:name":"Worth Silas Monument Company",
    "wof:placetype":"venue"
},
  "geometry": {"coordinates":[-82.541746,31.906177],"type":"Point"}
}