{
  "type": "Feature",
  "properties": {
    "addr:full":"785 Virginia Ave Ste A Atlanta GA 30354",
    "addr:housenumber":"785",
    "addr:postcode":"30354",
    "addr:street":"Virginia Ave Ste A",
    "iso:country":"US",
    "sg:address":"785 Virginia Ave Ste A",
    "sg:city":"Atlanta",
    "sg:classifiers":[
        {
            "category":"Health Services",
            "subcategory":"Dentist",
            "type":"Services"
        }
    ],
    "sg:phone":"+1 404 768 8700",
    "sg:postcode":"30354",
    "sg:province":"GA",
    "wof:name":"Harandi Ali DDS",
    "wof:placetype":"venue"
},
  "geometry": {"coordinates":[-84.415521,33.66014],"type":"Point"}
}