{
  "type": "Feature",
  "properties": {
    "iso:country":"US",
    "sg:address":"3807 Riverside Pkwy",
    "sg:city":"Decatur",
    "sg:classifiers":[
        {
            "category":"Landmark",
            "subcategory":"Tourist Information",
            "type":"Public Place"
        }
    ],
    "sg:phone":"+1 404 292 6216",
    "sg:postcode":"30034",
    "sg:province":"GA",
    "sg:tags":[
        "promoter",
        "tours-operators"
    ],
    "sg:website":"http://www.bentongrouptravel.com",
    "wof:name":"Benton Group Travel",
    "wof:placetype":"venue"
},
  "geometry": {"coordinates":[-84.262967,33.670115],"type":"Point"}
}