{
  "type": "Feature",
  "properties": {
    "iso:country":"US",
    "sg:address":"106 Raindance Rd",
    "sg:city":"Pooler",
    "sg:classifiers":[
        {
            "category":"Professional",
            "type":"Services"
        }
    ],
    "sg:phone":"+1 912 748 5490",
    "sg:postcode":"31322",
    "sg:province":"GA",
    "wof:name":"Phoenix Antiquescollectibles",
    "wof:placetype":"venue"
},
  "geometry": {"coordinates":[-81.261107,32.090584],"type":"Point"}
}