{
  "type": "Feature",
  "properties": {
    "iso:country":"US",
    "sg:address":"524 Plasters Ave NE",
    "sg:city":"Atlanta",
    "sg:classifiers":[
        {
            "category":"Arts & Performance",
            "subcategory":"Dance",
            "type":"Entertainment"
        }
    ],
    "sg:phone":"+1 404 877 0005",
    "sg:postcode":"30324",
    "sg:province":"GA",
    "sg:tags":[
        "instruction",
        "dancing"
    ],
    "wof:name":"Citydance, Inc.",
    "wof:placetype":"venue"
},
  "geometry": {"coordinates":[-84.370364,33.812135],"type":"Point"}
}