{
  "type": "Feature",
  "properties": {
    "iso:country":"US",
    "sg:address":"7207 Timber Trl",
    "sg:city":"Cumming",
    "sg:classifiers":[
        {
            "category":"Building & Trades",
            "subcategory":"Plumbing",
            "type":"Services"
        }
    ],
    "sg:phone":"+1 770 844 8274",
    "sg:postcode":"30041",
    "sg:province":"GA",
    "sg:tags":[
        "plumber",
        "industrial",
        "contractors-commercial"
    ],
    "wof:name":"First Choice Plumbing Inc",
    "wof:placetype":"venue"
},
  "geometry": {"coordinates":[-84.04565700000001,34.217481],"type":"Point"}
}