{
  "type": "Feature",
  "properties": {
    "iso:country":"US",
    "sg:address":"4000 Glenwood Rd",
    "sg:city":"Decatur",
    "sg:classifiers":[
        {
            "category":"Professional",
            "subcategory":"Accounting & Tax Preparation",
            "type":"Services"
        }
    ],
    "sg:phone":"+1 404 284 9509",
    "sg:postcode":"30032",
    "sg:province":"GA",
    "sg:tags":[
        "return"
    ],
    "wof:name":"Pitts & Associates Tax Service",
    "wof:placetype":"venue"
},
  "geometry": {"coordinates":[-84.25505699999999,33.738075],"type":"Point"}
}