{
  "type": "Feature",
  "properties": {
    "addr:full":"387 Hwy 11 N Social Circle GA 30025",
    "addr:housenumber":"387",
    "addr:postcode":"30025",
    "addr:street":"Hwy 11 N;Circle",
    "iso:country":"US",
    "sg:address":"387 Hwy 11 N",
    "sg:city":"Social Circle",
    "sg:classifiers":[
        {
            "category":"Autos & Motor Vehicles",
            "subcategory":"Fuel & Gas Station",
            "type":"Retail Goods"
        }
    ],
    "sg:phone":"+1 770 385 8947",
    "sg:postcode":"30025",
    "sg:province":"GA",
    "sg:tags":[
        "station",
        "gasoline"
    ],
    "wof:name":"Amoco",
    "wof:placetype":"venue"
},
  "geometry": {"coordinates":[-83.75223099999999,33.607001],"type":"Point"}
}