{
  "type": "Feature",
  "properties": {
    "addr:full":"8115 Victoria Ct Cumming GA 30040",
    "addr:housenumber":"8115",
    "addr:postcode":"30040",
    "addr:street":"Victoria Ct",
    "iso:country":"US",
    "sg:address":"8115 Victoria Ct",
    "sg:city":"Cumming",
    "sg:classifiers":[
        {
            "category":"Professional",
            "subcategory":"Business Services",
            "type":"Services"
        }
    ],
    "sg:phone":"+1 770 643 0290",
    "sg:postcode":"30040",
    "sg:province":"GA",
    "wof:name":"Tekton Design & Build",
    "wof:placetype":"venue"
},
  "geometry": {"coordinates":[-84.23116,34.183329],"type":"Point"}
}