{
  "type": "Feature",
  "properties": {
    "iso:country":"US",
    "sg:address":"80 Powers Ferry Rd SE",
    "sg:city":"Marietta",
    "sg:classifiers":[
        {
            "category":"Personal",
            "subcategory":"Nail Salon",
            "type":"Services"
        }
    ],
    "sg:phone":"+1 770 971 8055",
    "sg:postcode":"30067",
    "sg:province":"GA",
    "wof:name":"T L C Nails",
    "wof:placetype":"venue"
},
  "geometry": {"coordinates":[-84.512001,33.950199],"type":"Point"}
}