{
  "type": "Feature",
  "properties": {
    "addr:full":"4271 Lavista Rd Tucker GA 30084",
    "addr:housenumber":"4271",
    "addr:postcode":"30084",
    "addr:street":"Lavista Rd",
    "iso:country":"US",
    "sg:address":"4271 Lavista Rd",
    "sg:city":"Tucker",
    "sg:classifiers":[
        {
            "category":"Food & Beverages",
            "subcategory":"Groceries & Convenience Stores",
            "type":"Retail Goods"
        }
    ],
    "sg:phone":"+1 770 908 0133",
    "sg:postcode":"30084",
    "sg:province":"GA",
    "sg:website":"www.texaco.com",
    "wof:name":"Texaco Food Mart",
    "wof:placetype":"venue"
},
  "geometry": {"coordinates":[-84.24457700000001,33.846728],"type":"Point"}
}