{
  "type": "Feature",
  "properties": {
    "addr:full":"1139 Macon Rd Perry GA 31069",
    "addr:housenumber":"1139",
    "addr:postcode":"31069",
    "addr:street":"Macon Rd",
    "iso:country":"US",
    "sg:address":"1139 Macon Rd",
    "sg:city":"Perry",
    "sg:classifiers":[
        {
            "category":"Shopping",
            "subcategory":"Used Merchandise",
            "type":"Retail Goods"
        }
    ],
    "sg:phone":"+1 478 987 2469",
    "sg:postcode":"31069",
    "sg:province":"GA",
    "sg:tags":[
        "antique"
    ],
    "wof:name":"Antiques From The Shed",
    "wof:placetype":"venue"
},
  "geometry": {"coordinates":[-83.730312,32.462575],"type":"Point"}
}