{
  "type": "Feature",
  "properties": {
    "addr:full":"1119 Whispering Pines Rd Albany GA 31707",
    "addr:housenumber":"1119",
    "addr:postcode":"31707",
    "addr:street":"Whispering Pines Rd",
    "iso:country":"US",
    "sg:address":"1119 Whispering Pines Rd",
    "sg:city":"Albany",
    "sg:classifiers":[
        {
            "category":"Personal",
            "subcategory":"Beauty Salon",
            "type":"Services"
        }
    ],
    "sg:phone":"+1 229 435 5710",
    "sg:postcode":"31707",
    "sg:province":"GA",
    "wof:name":"Betty's Hair Fashions",
    "wof:placetype":"venue"
},
  "geometry": {"coordinates":[-84.179394,31.604989],"type":"Point"}
}