{
  "type": "Feature",
  "properties": {
    "addr:full":"927 Poulan Shingler Rd Poulan GA 31781",
    "addr:housenumber":"927",
    "addr:postcode":"31781",
    "addr:street":"Poulan Shingler Rd",
    "iso:country":"US",
    "sg:address":"927 Poulan Shingler Rd",
    "sg:city":"Poulan",
    "sg:classifiers":[
        {
            "category":"Retail",
            "subcategory":"Laundry & Dry Cleaning",
            "type":"Services"
        }
    ],
    "sg:phone":"+1 229 776 6345",
    "sg:postcode":"31781",
    "sg:province":"GA",
    "wof:name":"Superior Carpet Cleaning",
    "wof:placetype":"venue"
},
  "geometry": {"coordinates":[-83.785059,31.571176],"type":"Point"}
}