{
  "type": "Feature",
  "properties": {
    "iso:country":"US",
    "sg:address":"334 Anderson Ave",
    "sg:city":"Thomson",
    "sg:classifiers":[
        {
            "category":"Social Services",
            "subcategory":"Child Care",
            "type":"Services"
        }
    ],
    "sg:phone":"+1 706 597 0584",
    "sg:postcode":"30824",
    "sg:province":"GA",
    "wof:name":"Shemeka Daycare",
    "wof:placetype":"venue"
},
  "geometry": {"coordinates":[-82.494062,33.472662],"type":"Point"}
}