{
  "type": "Feature",
  "properties": {
    "addr:full":"105 Cottage Cir Fayetteville GA 30215",
    "addr:housenumber":"105",
    "addr:postcode":"30215",
    "addr:street":"Cottage Cir",
    "iso:country":"US",
    "sg:address":"105 Cottage Cir",
    "sg:city":"Fayetteville",
    "sg:classifiers":[
        {
            "category":"Airline",
            "type":"Transportation"
        }
    ],
    "sg:phone":"+1 770 461 4189",
    "sg:postcode":"30215",
    "sg:province":"GA",
    "sg:tags":[
        "nonscheduled",
        "air"
    ],
    "wof:name":"Affordble Chrters of Excllence",
    "wof:placetype":"venue"
},
  "geometry": {"coordinates":[-84.497552,33.435075],"type":"Point"}
}