{
  "type": "Feature",
  "properties": {
    "addr:full":"5669 Whitesville Rd Columbus GA 31904",
    "addr:housenumber":"5669",
    "addr:postcode":"31904",
    "addr:street":"Whitesville Rd",
    "iso:country":"US",
    "sg:address":"5669 Whitesville Rd",
    "sg:city":"Columbus",
    "sg:classifiers":[
        {
            "category":"Health Services",
            "subcategory":"Doctor",
            "type":"Services"
        },
        {
            "category":"Health Services",
            "subcategory":"Nursing And Care Facility",
            "type":"Services"
        }
    ],
    "sg:phone":"+1 706 571 7246",
    "sg:postcode":"31904",
    "sg:province":"GA",
    "sg:tags":[
        "physician",
        "surgeon",
        "management",
        "pain",
        "surgeons"
    ],
    "sg:website":"http://thepaincenter.info",
    "wof:name":"Southeast Regional Pain Center",
    "wof:placetype":"venue"
},
  "geometry": {"coordinates":[-84.960426,32.524959],"type":"Point"}
}