{
  "type": "Feature",
  "properties": {
    "addr:full":"495 Friendship Rd Sylvania GA 30467",
    "addr:housenumber":"495",
    "addr:postcode":"30467",
    "addr:street":"Friendship Rd",
    "iso:country":"US",
    "sg:address":"495 Friendship Rd",
    "sg:city":"Sylvania",
    "sg:classifiers":[
        {
            "category":"Autos & Motor Vehicles",
            "subcategory":"Fuel & Gas Station",
            "type":"Retail Goods"
        },
        {
            "category":"Food & Beverages",
            "subcategory":"Groceries & Convenience Stores",
            "type":"Retail Goods"
        }
    ],
    "sg:phone":"+1 912 564 2002",
    "sg:postcode":"30467",
    "sg:province":"GA",
    "wof:name":"Timesaver",
    "wof:placetype":"venue"
},
  "geometry": {"coordinates":[-81.62210899999999,32.757645],"type":"Point"}
}