{
  "type": "Feature",
  "properties": {
    "addr:full":"245 Shadowbrook Ct Roswell GA 30075",
    "addr:housenumber":"245",
    "addr:postcode":"30075",
    "addr:street":"Shadowbrook Ct",
    "iso:country":"US",
    "sg:address":"245 Shadowbrook Ct",
    "sg:city":"Roswell",
    "sg:classifiers":[
        {
            "category":"Professional",
            "subcategory":"Business Services",
            "type":"Services"
        },
        {
            "category":"Organizations",
            "subcategory":"Professional Association",
            "type":"Services"
        }
    ],
    "sg:phone":"+1 770 641 1658",
    "sg:postcode":"30075",
    "sg:province":"GA",
    "wof:name":"Shadowbrook Homehowners Assoc",
    "wof:placetype":"venue"
},
  "geometry": {"coordinates":[-84.343225,34.017989],"type":"Point"}
}