{
  "type": "Feature",
  "properties": {
    "addr:full":"4585 Highway 225 N Chatsworth GA 30705",
    "addr:housenumber":"4585",
    "addr:postcode":"30705",
    "addr:street":"Highway 225 N",
    "iso:country":"US",
    "sg:address":"4585 Highway 225 N",
    "sg:city":"Chatsworth",
    "sg:classifiers":[
        {
            "category":"Personal",
            "subcategory":"Beauty Salon",
            "type":"Services"
        }
    ],
    "sg:phone":"+1 706 695 1923",
    "sg:postcode":"30705",
    "sg:province":"GA",
    "wof:name":"Salon Open Door Family",
    "wof:placetype":"venue"
},
  "geometry": {"coordinates":[-84.811967,34.823653],"type":"Point"}
}