{
  "type": "Feature",
  "properties": {
    "addr:full":"2871 Quinbery Dr Snellville GA 30039",
    "addr:housenumber":"2871",
    "addr:postcode":"30039",
    "addr:street":"Quinbery Dr",
    "iso:country":"US",
    "sg:address":"2871 Quinbery Dr",
    "sg:city":"Snellville",
    "sg:classifiers":[
        {
            "category":"Building & Trades",
            "subcategory":"Electrical",
            "type":"Services"
        }
    ],
    "sg:phone":"+1 770 985 8038",
    "sg:postcode":"30039",
    "sg:province":"GA",
    "sg:tags":[
        "electrical",
        "contractor"
    ],
    "wof:name":"Wright Electrical Svcs",
    "wof:placetype":"venue"
},
  "geometry": {"coordinates":[-84.050952,33.822063],"type":"Point"}
}