{
  "type": "Feature",
  "properties": {
    "addr:full":"8620 Old Valdosta Rd Hahira GA 31632",
    "addr:housenumber":"8620",
    "addr:postcode":"31632",
    "addr:street":"Old Valdosta Rd",
    "iso:country":"US",
    "sg:address":"8620 Old Valdosta Rd",
    "sg:city":"Hahira",
    "sg:classifiers":[
        {
            "category":"Retail",
            "subcategory":"Auto Repair",
            "type":"Services"
        }
    ],
    "sg:phone":"+1 229 794 2337",
    "sg:postcode":"31632",
    "sg:province":"GA",
    "sg:tags":[
        "repairing",
        "automobile",
        "general"
    ],
    "wof:name":"North Lowndes Automotive Repr",
    "wof:placetype":"venue"
},
  "geometry": {"coordinates":[-83.438996,31.025861],"type":"Point"}
}