{
  "type": "Feature",
  "properties": {
    "addr:full":"4041 Kingston Ct SE Marietta GA 30067",
    "addr:housenumber":"4041",
    "addr:postcode":"30067",
    "addr:street":"Kingston Ct Se",
    "iso:country":"US",
    "sg:address":"4041 Kingston Ct SE",
    "sg:city":"Marietta",
    "sg:classifiers":[
        {
            "category":"Manufacturing",
            "subcategory":"Toys & Sporting Goods",
            "type":"Manufacturing & Wholesale Goods"
        }
    ],
    "sg:phone":"+1 770 988 8108",
    "sg:postcode":"30067",
    "sg:province":"GA",
    "sg:tags":[
        "goods-wholesale",
        "manufacturer"
    ],
    "wof:name":"All Things Audio Distributors Inc",
    "wof:placetype":"venue"
},
  "geometry": {"coordinates":[-84.491784,33.923972],"type":"Point"}
}