{
  "type": "Feature",
  "properties": {
    "addr:full":"4129 Quincy Ln Duluth GA 30096",
    "addr:housenumber":"4129",
    "addr:postcode":"30096",
    "addr:street":"Quincy Ln",
    "iso:country":"US",
    "sg:address":"4129 Quincy Ln",
    "sg:city":"Duluth",
    "sg:classifiers":[
        {
            "category":"Wholesale",
            "subcategory":"Machinery & Supplies",
            "type":"Manufacturing & Wholesale Goods"
        }
    ],
    "sg:phone":"+1 678 584 9171",
    "sg:postcode":"30096",
    "sg:province":"GA",
    "sg:tags":[
        "equipment",
        "establishment"
    ],
    "wof:name":"Syber Assist Virtual Assistant",
    "wof:placetype":"venue"
},
  "geometry": {"coordinates":[-84.169715,34.011766],"type":"Point"}
}