{
  "type": "Feature",
  "properties": {
    "addr:full":"3071 Chelsea Ln Acworth GA 30102",
    "addr:housenumber":"3071",
    "addr:postcode":"30102",
    "addr:street":"Chelsea Ln",
    "iso:country":"US",
    "sg:address":"3071 Chelsea Ln",
    "sg:city":"Acworth",
    "sg:classifiers":[
        {
            "category":"Building & Trades",
            "subcategory":"Construction",
            "type":"Services"
        }
    ],
    "sg:phone":"+1 770 592 3212",
    "sg:postcode":"30102",
    "sg:province":"GA",
    "sg:tags":[
        "woodworker"
    ],
    "wof:name":"Bouchard Enterprises LTD",
    "wof:placetype":"venue"
},
  "geometry": {"coordinates":[-84.612126,34.111796],"type":"Point"}
}