{
  "type": "Feature",
  "properties": {
    "addr:full":"50 Kelsey Way Palmetto GA 30268",
    "addr:housenumber":"50",
    "addr:postcode":"30268",
    "addr:street":"Kelsey Way",
    "iso:country":"US",
    "sg:address":"50 Kelsey Way",
    "sg:city":"Palmetto",
    "sg:classifiers":[
        {
            "category":"Building & Trades",
            "subcategory":"Landscaping Services",
            "type":"Services"
        }
    ],
    "sg:phone":"+1 678 300 4755",
    "sg:postcode":"30268",
    "sg:province":"GA",
    "wof:name":"Terrys Turf Care",
    "wof:placetype":"venue"
},
  "geometry": {"coordinates":[-84.70992,33.505774],"type":"Point"}
}