{
  "type": "Feature",
  "properties": {
    "iso:country":"US",
    "sg:address":"45 Kelly Dr SW",
    "sg:city":"Cartersville",
    "sg:classifiers":[
        {
            "category":"Home & Garden",
            "subcategory":"Hardware",
            "type":"Retail Goods"
        }
    ],
    "sg:phone":"+1 770 607 9353",
    "sg:postcode":"30120",
    "sg:province":"GA",
    "wof:name":"True Lawnscapes",
    "wof:placetype":"venue"
},
  "geometry": {"coordinates":[-84.863021,34.185503],"type":"Point"}
}