{
  "type": "Feature",
  "properties": {
    "addr:full":"6690 Roswell Rd Atlanta GA 30328",
    "addr:housenumber":"6690",
    "addr:postcode":"30328",
    "addr:street":"Roswell Rd",
    "iso:country":"US",
    "sg:address":"6690 Roswell Rd",
    "sg:city":"Atlanta",
    "sg:classifiers":[
        {
            "category":"Banks & Credit Unions",
            "subcategory":"Bank",
            "type":"Services"
        }
    ],
    "sg:phone":"+1 404 843 0271",
    "sg:postcode":"30328",
    "sg:province":"GA",
    "sg:tags":[
        "loan",
        "real estate"
    ],
    "wof:name":"Wells Fargo Home Mortgage",
    "wof:placetype":"venue"
},
  "geometry": {"coordinates":[-84.378334,33.937121],"type":"Point"}
}