{
  "type": "Feature",
  "properties": {
    "addr:full":"2230 Walton Way Augusta GA 30904",
    "addr:housenumber":"2230",
    "addr:postcode":"30904",
    "addr:street":"Walton Way",
    "iso:country":"US",
    "sg:address":"2230 Walton Way",
    "sg:city":"Augusta",
    "sg:classifiers":[
        {
            "category":"Organizations",
            "subcategory":"Religious Organization",
            "type":"Services"
        }
    ],
    "sg:phone":"+1 706 738 3386",
    "sg:postcode":"30904",
    "sg:province":"GA",
    "sg:tags":[
        "school",
        "bookstore",
        "day",
        "church"
    ],
    "wof:name":"Episcopal Day School The",
    "wof:placetype":"venue"
},
  "geometry": {"coordinates":[-82.01544199999999,33.477337],"type":"Point"}
}