{
  "type": "Feature",
  "properties": {
    "addr:full":"218 W Jackson St Thomasville GA 31792",
    "addr:housenumber":"218",
    "addr:postcode":"31792",
    "addr:street":"W Jackson St",
    "iso:country":"US",
    "sg:address":"218 W Jackson St",
    "sg:city":"Thomasville",
    "sg:classifiers":[
        {
            "category":"Professional",
            "type":"Services"
        }
    ],
    "sg:phone":"+1 229 228 5945",
    "sg:postcode":"31792",
    "sg:province":"GA",
    "sg:tags":[
        "establishment"
    ],
    "wof:name":"Focused Imagination",
    "wof:placetype":"venue"
},
  "geometry": {"coordinates":[-83.98126499999999,30.836826],"type":"Point"}
}