{
  "type": "Feature",
  "properties": {
    "addr:full":"6208 Glen Oak Dr Flowery Branch GA 30518",
    "addr:housenumber":"6208",
    "addr:postcode":"30518",
    "addr:street":"Glen Oak Dr",
    "iso:country":"US",
    "sg:address":"6208 Glen Oak Dr",
    "sg:city":"Flowery Branch",
    "sg:classifiers":[
        {
            "category":"Retail",
            "subcategory":"Repair Shop",
            "type":"Services"
        }
    ],
    "sg:phone":"+1 770 967 7777",
    "sg:postcode":"30518",
    "sg:province":"GA",
    "wof:name":"Windows Plus",
    "wof:placetype":"venue"
},
  "geometry": {"coordinates":[-83.951031,34.163717],"type":"Point"}
}