{
  "type": "Feature",
  "properties": {
    "iso:country":"US",
    "sg:address":"3318 State Rte 5",
    "sg:city":"Douglasville",
    "sg:classifiers":[
        {
            "category":"Professional",
            "subcategory":"Business Services",
            "type":"Services"
        }
    ],
    "sg:phone":"+1 770 823 8574",
    "sg:postcode":"30135",
    "sg:province":"GA",
    "sg:tags":[
        "inventory"
    ],
    "wof:name":"Bevinco Of West Georgia",
    "wof:placetype":"venue"
},
  "geometry": {"coordinates":[-84.76952300000001,33.713515],"type":"Point"}
}