{
  "type": "Feature",
  "properties": {
    "iso:country":"US",
    "sg:address":"774 Akin Rd",
    "sg:city":"Jesup",
    "sg:classifiers":[
        {
            "category":"Real Estate",
            "subcategory":"Real Estate Agent",
            "type":"Services"
        }
    ],
    "sg:phone":"+1 912 427 3000",
    "sg:postcode":"31546",
    "sg:province":"GA",
    "wof:name":"Denison Properties & Realty",
    "wof:placetype":"venue"
},
  "geometry": {"coordinates":[-81.693703,31.493742],"type":"Point"}
}