{
  "type": "Feature",
  "properties": {
    "addr:full":"2487 Cedarcrest Rd Acworth GA 30101",
    "addr:housenumber":"2487",
    "addr:postcode":"30101",
    "addr:street":"Cedarcrest Rd",
    "iso:country":"US",
    "sg:address":"2487 Cedarcrest Rd",
    "sg:city":"Acworth",
    "sg:classifiers":[
        {
            "category":"Health Services",
            "subcategory":"Chiropractor",
            "type":"Services"
        }
    ],
    "sg:phone":"+1 770 974 2405",
    "sg:postcode":"30101",
    "sg:province":"GA",
    "sg:website":"www.acworthwellness.com",
    "wof:name":"Di Blasi Jim Dr",
    "wof:placetype":"venue"
},
  "geometry": {"coordinates":[-84.738654,34.057402],"type":"Point"}
}