{
  "type": "Feature",
  "properties": {
    "addr:full":"26 E Kennedy St Statesboro GA 30458",
    "addr:housenumber":"26",
    "addr:postcode":"30458",
    "addr:street":"E Kennedy St",
    "iso:country":"US",
    "sg:address":"26 E Kennedy St",
    "sg:city":"Statesboro",
    "sg:classifiers":[
        {
            "category":"Utilities",
            "subcategory":"Fuel Oil & Lpg",
            "type":"Services"
        }
    ],
    "sg:phone":"+1 912 681 4427",
    "sg:postcode":"30458",
    "sg:province":"GA",
    "sg:tags":[
        "propane",
        "gas"
    ],
    "wof:name":"Ferrellgas",
    "wof:placetype":"venue"
},
  "geometry": {"coordinates":[-81.78448299999999,32.434043],"type":"Point"}
}