{
  "type": "Feature",
  "properties": {
    "addr:full":"562 Buford Dr Lawrenceville GA 30045",
    "addr:housenumber":"562",
    "addr:postcode":"30045",
    "addr:street":"Buford Dr",
    "iso:country":"US",
    "sg:address":"562 Buford Dr",
    "sg:city":"Lawrenceville",
    "sg:classifiers":[
        {
            "category":"Insurance",
            "subcategory":"Insurance Agent",
            "type":"Services"
        }
    ],
    "sg:phone":"+1 770 339 4100",
    "sg:postcode":"30045",
    "sg:province":"GA",
    "wof:name":"Terry Mc Waters Insurance",
    "wof:placetype":"venue"
},
  "geometry": {"coordinates":[-83.986667,33.973445],"type":"Point"}
}