{
  "type": "Feature",
  "properties": {
    "addr:full":"2030 Blackhawk Trl Lawrenceville GA 30043",
    "addr:housenumber":"2030",
    "addr:postcode":"30043",
    "addr:street":"Blackhawk Trl",
    "iso:country":"US",
    "sg:address":"2030 Blackhawk Trl",
    "sg:city":"Lawrenceville",
    "sg:classifiers":[
        {
            "category":"Professional",
            "subcategory":"Art Services",
            "type":"Services"
        }
    ],
    "sg:phone":"+1 770 513 8431",
    "sg:postcode":"30043",
    "sg:province":"GA",
    "sg:tags":[
        "photography",
        "commercial"
    ],
    "wof:name":"Kid Shotz",
    "wof:placetype":"venue"
},
  "geometry": {"coordinates":[-84.05618699999999,33.991735],"type":"Point"}
}