{
  "type": "Feature",
  "properties": {
    "addr:full":"3054 Washington Rd Augusta GA 30907",
    "addr:housenumber":"3054",
    "addr:postcode":"30907",
    "addr:street":"Washington Rd",
    "iso:country":"US",
    "sg:address":"3054 Washington Rd",
    "sg:city":"Augusta",
    "sg:classifiers":[
        {
            "category":"Restaurant",
            "type":"Food & Drink"
        }
    ],
    "sg:menulink":"http://www.allmenus.com/ga/augusta/160602-burger-king/menu/",
    "sg:phone":"+1 706 860 4002",
    "sg:postcode":"30907",
    "sg:province":"GA",
    "sg:tags":[
        "burger",
        "american"
    ],
    "wof:name":"Burger King",
    "wof:placetype":"venue"
},
  "geometry": {"coordinates":[-82.050569,33.51304],"type":"Point"}
}