{
  "type": "Feature",
  "properties": {
    "iso:country":"US",
    "sg:address":"3352 Glen Devon Ln",
    "sg:city":"Duluth",
    "sg:classifiers":[
        {
            "category":"Professional",
            "subcategory":"Management & Consulting",
            "type":"Services"
        }
    ],
    "sg:phone":"+1 770 209 9168",
    "sg:postcode":"30096",
    "sg:province":"GA",
    "sg:tags":[
        "business"
    ],
    "wof:name":"Pen Wal Group Inc",
    "wof:placetype":"venue"
},
  "geometry": {"coordinates":[-84.191492,33.974265],"type":"Point"}
}