{
  "type": "Feature",
  "properties": {
    "iso:country":"US",
    "sg:address":"1745 Peachtree St NE ",
    "sg:city":"Atlanta",
    "sg:classifiers":[
        {
            "category":"Restaurant",
            "type":"Food & Drink"
        }
    ],
    "sg:menulink":"http://www.allmenus.com/ga/atlanta/293620-tuk-tuk-thai-food-loft/menu/",
    "sg:phone":"+1 678 539 6181",
    "sg:postcode":"30309",
    "sg:province":"GA",
    "sg:tags":[
        "thai"
    ],
    "wof:name":"Tuk Tuk Thai Food Loft",
    "wof:placetype":"venue"
},
  "geometry": {"coordinates":[-84.392596,33.802031],"type":"Point"}
}