{
  "type": "Feature",
  "properties": {
    "iso:country":"US",
    "sg:address":"209 7th St",
    "sg:city":"Augusta",
    "sg:classifiers":[
        {
            "category":"Communications",
            "subcategory":"Newspaper",
            "type":"Services"
        }
    ],
    "sg:phone":"+1 706 733 6663",
    "sg:postcode":"30901",
    "sg:province":"GA",
    "sg:tags":[
        "feature",
        "syndicate"
    ],
    "wof:name":"Metro Augusta Parent",
    "wof:placetype":"venue"
},
  "geometry": {"coordinates":[-81.963387,33.474348],"type":"Point"}
}