{
  "type": "Feature",
  "properties": {
    "addr:full":"11908 Idlewood Dr Savannah GA 31419",
    "addr:housenumber":"11908",
    "addr:postcode":"31419",
    "addr:street":"Idlewood Dr",
    "iso:country":"US",
    "sg:address":"11908 Idlewood Dr",
    "sg:city":"Savannah",
    "sg:classifiers":[
        {
            "category":"Building & Trades",
            "subcategory":"Cleaning & Sanitation",
            "type":"Services"
        }
    ],
    "sg:phone":"+1 912 925 5627",
    "sg:postcode":"31419",
    "sg:province":"GA",
    "wof:name":"Rozs Christian Cleaning Svc",
    "wof:placetype":"venue"
},
  "geometry": {"coordinates":[-81.146565,31.981195],"type":"Point"}
}