{
  "type": "Feature",
  "properties": {
    "iso:country":"US",
    "sg:address":"2900 US Hwy 27",
    "sg:city":"Carrollton",
    "sg:classifiers":[
        {
            "category":"Organizations",
            "subcategory":"Religious Organization",
            "type":"Services"
        }
    ],
    "sg:phone":"+1 770 836 7981",
    "sg:postcode":"30117",
    "sg:province":"GA",
    "wof:name":"Grace Life Fellowship",
    "wof:placetype":"venue"
},
  "geometry": {"coordinates":[-85.122798,33.634628],"type":"Point"}
}