{
  "type": "Feature",
  "properties": {
    "addr:full":"1 W Porter St Cartersville GA 30120",
    "addr:housenumber":"1",
    "addr:postcode":"30120",
    "addr:street":"W Porter St",
    "iso:country":"US",
    "sg:address":"1 W Porter St",
    "sg:city":"Cartersville",
    "sg:classifiers":[
        {
            "category":"Wholesale",
            "subcategory":"Scrap",
            "type":"Manufacturing & Wholesale Goods"
        }
    ],
    "sg:phone":"+1 678 721 0022",
    "sg:postcode":"30120",
    "sg:province":"GA",
    "sg:tags":[
        "recycling",
        "center"
    ],
    "wof:name":"Metal Conversion Technologies",
    "wof:placetype":"venue"
},
  "geometry": {"coordinates":[-84.80119999999999,34.178964],"type":"Point"}
}