{
  "type": "Feature",
  "properties": {
    "addr:full":"9300 Stoney Ridge Ln Alpharetta GA 30022",
    "addr:housenumber":"9300",
    "addr:postcode":"30022",
    "addr:street":"Stoney Ridge Ln",
    "iso:country":"US",
    "sg:address":"9300 Stoney Ridge Ln",
    "sg:city":"Alpharetta",
    "sg:classifiers":[
        {
            "category":"Banks & Credit Unions",
            "subcategory":"Bank",
            "type":"Services"
        }
    ],
    "sg:phone":"+1 770 993 4148",
    "sg:postcode":"30022",
    "sg:province":"GA",
    "sg:tags":[
        "financing"
    ],
    "wof:name":"Honess Financial Svc",
    "wof:placetype":"venue"
},
  "geometry": {"coordinates":[-84.25895800000001,34.010677],"type":"Point"}
}