{
  "type": "Feature",
  "properties": {
    "iso:country":"US",
    "sg:address":"206 Brook Ct",
    "sg:city":"Athens",
    "sg:classifiers":[
        {
            "category":"Education",
            "subcategory":"College",
            "type":"Public Place"
        }
    ],
    "sg:phone":"+1 706 542 4290",
    "sg:postcode":"30606",
    "sg:province":"GA",
    "wof:name":"Insurnce Lgal Stdies Ralestate",
    "wof:placetype":"venue"
},
  "geometry": {"coordinates":[-83.45146200000001,33.954667],"type":"Point"}
}