{
  "type": "Feature",
  "properties": {
    "iso:country":"US",
    "sg:address":"2307 Ellis St",
    "sg:city":"Brunswick",
    "sg:classifiers":[
        {
            "category":"Organizations",
            "subcategory":"Religious Organization",
            "type":"Services"
        }
    ],
    "sg:phone":"+1 912 267 9878",
    "sg:postcode":"31520",
    "sg:province":"GA",
    "wof:name":"First Wesleyan Church",
    "wof:placetype":"venue"
},
  "geometry": {"coordinates":[-81.497004,31.161662],"type":"Point"}
}