{
  "type": "Feature",
  "properties": {
    "addr:full":"346 North Ave Atlanta GA 30354",
    "addr:housenumber":"346",
    "addr:postcode":"30354",
    "addr:street":"North Ave",
    "iso:country":"US",
    "sg:address":"346 North Ave",
    "sg:city":"Atlanta",
    "sg:classifiers":[
        {
            "category":"Building & Trades",
            "subcategory":"Locksmith",
            "type":"Services"
        }
    ],
    "sg:phone":"+1 404 492 6665",
    "sg:postcode":"30354",
    "sg:province":"GA",
    "sg:tags":[
        "key"
    ],
    "wof:name":"24-Hours Emergency Locksmith",
    "wof:placetype":"venue"
},
  "geometry": {"coordinates":[-84.398028,33.667254],"type":"Point"}
}