{
  "type": "Feature",
  "properties": {
    "addr:full":"802 Memorial Dr SE Atlanta GA 30316",
    "addr:housenumber":"802",
    "addr:postcode":"30316",
    "addr:street":"Memorial Dr Se",
    "iso:country":"US",
    "sg:address":"802 Memorial Dr SE",
    "sg:city":"Atlanta",
    "sg:classifiers":[
        {
            "category":"Building & Trades",
            "subcategory":"Locksmith",
            "type":"Services"
        }
    ],
    "sg:phone":"+1 678 845 9548",
    "sg:postcode":"30316",
    "sg:province":"GA",
    "sg:tags":[
        "key"
    ],
    "wof:name":"A Emergency A Locksmith",
    "wof:placetype":"venue"
},
  "geometry": {"coordinates":[-84.361195,33.746757],"type":"Point"}
}