{
  "type": "Feature",
  "properties": {
    "iso:country":"US",
    "sg:address":"134 Cherokee Cir",
    "sg:city":"Hinesville",
    "sg:classifiers":[
        {
            "category":"Shopping",
            "subcategory":"Florist",
            "type":"Retail Goods"
        }
    ],
    "sg:phone":"+1 912 448 2380",
    "sg:postcode":"31313",
    "sg:province":"GA",
    "wof:name":"Miami Flowers",
    "wof:placetype":"venue"
},
  "geometry": {"coordinates":[-81.60343899999999,31.815085],"type":"Point"}
}