{
  "type": "Feature",
  "properties": {
    "iso:country":"US",
    "sg:address":"1604 E Forsyth St",
    "sg:city":"Americus",
    "sg:classifiers":[
        {
            "category":"Restaurant",
            "type":"Food & Drink"
        }
    ],
    "sg:menulink":"http://www.allmenus.com/ga/americus/131177-roman-oven-pizza/menu/",
    "sg:phone":"+1 299 928 5050",
    "sg:postcode":"31709",
    "sg:province":"GA",
    "sg:tags":[
        "american",
        "pizza"
    ],
    "wof:name":"Roman Oven Pizza",
    "wof:placetype":"venue"
},
  "geometry": {"coordinates":[-84.210179,32.071471],"type":"Point"}
}