{
  "type": "Feature",
  "properties": {
    "addr:full":"921 Augusta Rd North Augusta SC 29822",
    "addr:housenumber":"921",
    "addr:postcode":"29822",
    "addr:street":"Augusta Rd",
    "iso:country":"US",
    "sg:address":"921 Augusta Rd",
    "sg:city":"North Augusta",
    "sg:classifiers":[
        {
            "category":"Home & Garden",
            "subcategory":"Furniture",
            "type":"Retail Goods"
        }
    ],
    "sg:phone":"+1 803 202 0209",
    "sg:postcode":"29822",
    "sg:province":"SC",
    "sg:website":"www.choicehotels.com",
    "wof:name":"Sleep Inn",
    "wof:placetype":"venue"
},
  "geometry": {"coordinates":[-81.891988,33.496745],"type":"Point"}
}