{
  "type": "Feature",
  "properties": {
    "iso:country":"US",
    "sg:address":"371 Sutton Rd",
    "sg:city":"Demorest",
    "sg:classifiers":[
        {
            "category":"Personal",
            "subcategory":"Beauty Salon",
            "type":"Services"
        }
    ],
    "sg:phone":"+1 706 754 4264",
    "sg:postcode":"30535",
    "sg:province":"GA",
    "wof:name":"Pam's Beauty Shop",
    "wof:placetype":"venue"
},
  "geometry": {"coordinates":[-83.611051,34.612439],"type":"Point"}
}