{
  "type": "Feature",
  "properties": {
    "iso:country":"US",
    "sg:address":"1461 Mountain Reserve Dr",
    "sg:city":"Kennesaw",
    "sg:classifiers":[
        {
            "category":"Retail",
            "subcategory":"Portrait Studio",
            "type":"Services"
        }
    ],
    "sg:phone":"+1 770 427 8772",
    "sg:postcode":"30152",
    "sg:province":"GA",
    "sg:tags":[
        "photo"
    ],
    "wof:name":"Garrett Chan Photography",
    "wof:placetype":"venue"
},
  "geometry": {"coordinates":[-84.59438900000001,33.988403],"type":"Point"}
}