{
  "type": "Feature",
  "properties": {
    "iso:country":"US",
    "sg:address":"182 Courtland St NE",
    "sg:city":"Atlanta",
    "sg:classifiers":[
        {
            "category":"Bars & Pubs",
            "subcategory":"Lounge",
            "type":"Food & Drink"
        },
        {
            "category":"Restaurant",
            "type":"Food & Drink"
        }
    ],
    "sg:phone":"+1 404 525 5151",
    "sg:postcode":"30303",
    "sg:province":"GA",
    "sg:tags":[
        "new",
        "american"
    ],
    "sg:website":"www.minglesatl.com",
    "wof:name":"Mingles Martini Bar & Grill",
    "wof:placetype":"venue"
},
  "geometry": {"coordinates":[-84.38441899999999,33.759386],"type":"Point"}
}