{
  "type": "Feature",
  "properties": {
    "iso:country":"US",
    "sg:address":"14022 Coffee Bluff Rd",
    "sg:city":"Savannah",
    "sg:classifiers":[
        {
            "category":"Organizations",
            "subcategory":"Religious Organization",
            "type":"Services"
        }
    ],
    "sg:phone":"+1 912 927 3178",
    "sg:postcode":"31419",
    "sg:province":"GA",
    "wof:name":"2nd Mt Pleasant Baptist Church",
    "wof:placetype":"venue"
},
  "geometry": {"coordinates":[-81.145758,31.951884],"type":"Point"}
}