{
  "type": "Feature",
  "properties": {
    "iso:country":"US",
    "sg:address":"407 Brentwood Dr",
    "sg:city":"Dublin",
    "sg:classifiers":[
        {
            "category":"Professional",
            "subcategory":"Employment Agencies",
            "type":"Services"
        }
    ],
    "sg:phone":"+1 478 272 3033",
    "sg:postcode":"31021",
    "sg:province":"GA",
    "sg:tags":[
        "help",
        "supply"
    ],
    "wof:name":"Pilot Foundation of Dublin",
    "wof:placetype":"venue"
},
  "geometry": {"coordinates":[-82.94841700000001,32.556182],"type":"Point"}
}