{
  "type": "Feature",
  "properties": {
    "iso:country":"US",
    "sg:address":"6224 Windsor Dr",
    "sg:city":"Columbus",
    "sg:classifiers":[
        {
            "category":"Organizations",
            "subcategory":"Religious Organization",
            "type":"Services"
        }
    ],
    "sg:phone":"+1 706 561 8793",
    "sg:postcode":"31909",
    "sg:province":"GA",
    "wof:name":"Tabernacle Baptist Church",
    "wof:placetype":"venue"
},
  "geometry": {"coordinates":[-84.927492,32.534816],"type":"Point"}
}