{
  "type": "Feature",
  "properties": {
    "addr:full":"1010 Woodlands Rd Watkinsville GA 30677",
    "addr:housenumber":"1010",
    "addr:postcode":"30677",
    "addr:street":"Woodlands Rd",
    "iso:country":"US",
    "sg:address":"1010 Woodlands Rd",
    "sg:city":"Watkinsville",
    "sg:classifiers":[
        {
            "category":"Health Services",
            "subcategory":"Doctor",
            "type":"Services"
        }
    ],
    "sg:phone":"+1 706 769 7727",
    "sg:postcode":"30677",
    "sg:province":"GA",
    "wof:name":"David J Brown DDS",
    "wof:placetype":"venue"
},
  "geometry": {"coordinates":[-83.44703699999999,33.876997],"type":"Point"}
}