{
  "type": "Feature",
  "properties": {
    "addr:full":"128 Airport Park Dr Savannah GA 31408",
    "addr:housenumber":"128",
    "addr:postcode":"31408",
    "addr:street":"Airport Park Dr",
    "iso:country":"US",
    "sg:address":"128 Airport Park Dr",
    "sg:city":"Savannah",
    "sg:classifiers":[
        {
            "category":"Building & Trades",
            "subcategory":"Plumbing",
            "type":"Services"
        }
    ],
    "sg:phone":"+1 912 964 8541",
    "sg:postcode":"31408",
    "sg:province":"GA",
    "sg:tags":[
        "plumbing",
        "air",
        "heating",
        "conditioning",
        "contractor"
    ],
    "wof:name":"IGGC INC",
    "wof:placetype":"venue"
},
  "geometry": {"coordinates":[-81.192847,32.0749],"type":"Point"}
}