{
  "type": "Feature",
  "properties": {
    "iso:country":"US",
    "sg:address":"11585 Jones Bridge Rd Ste 440",
    "sg:city":"Alpharetta",
    "sg:classifiers":[
        {
            "category":"Professional",
            "type":"Services"
        }
    ],
    "sg:phone":"+1 770 753 0055",
    "sg:postcode":"30022",
    "sg:province":"GA",
    "sg:tags":[
        "caterer"
    ],
    "wof:name":"Roasters Rotisserie",
    "wof:placetype":"venue"
},
  "geometry": {"coordinates":[-84.21530199999999,34.0616],"type":"Point"}
}