{
  "type": "Feature",
  "properties": {
    "addr:full":"1367 Iris Dr SE Conyers GA 30013",
    "addr:housenumber":"1367",
    "addr:postcode":"30013",
    "addr:street":"Iris Dr Se",
    "iso:country":"US",
    "sg:address":"1367 Iris Dr SE",
    "sg:city":"Conyers",
    "sg:classifiers":[
        {
            "category":"Personal",
            "subcategory":"Beauty Salon",
            "type":"Services"
        }
    ],
    "sg:phone":"+1 678 210 0446",
    "sg:postcode":"30013",
    "sg:province":"GA",
    "wof:name":"C & C Hair Salon",
    "wof:placetype":"venue"
},
  "geometry": {"coordinates":[-84.008093,33.653796],"type":"Point"}
}