{
  "type": "Feature",
  "properties": {
    "iso:country":"US",
    "sg:address":"2006 Cape Ivy Dr",
    "sg:city":"Conyers",
    "sg:classifiers":[
        {
            "category":"Building & Trades",
            "subcategory":"Construction",
            "type":"Services"
        },
        {
            "category":"Home & Garden",
            "subcategory":"Home Furnishings",
            "type":"Retail Goods"
        }
    ],
    "sg:phone":"+1 770 922 1844",
    "sg:postcode":"30013",
    "sg:province":"GA",
    "sg:tags":[
        "venetian",
        "blind",
        "window",
        "installation"
    ],
    "wof:name":"Window Concepts",
    "wof:placetype":"venue"
},
  "geometry": {"coordinates":[-83.993706,33.603031],"type":"Point"}
}