{
  "type": "Feature",
  "properties": {
    "iso:country":"US",
    "sg:address":"2976 Chapel Hill Rd",
    "sg:city":"Douglasville",
    "sg:classifiers":[
        {
            "category":"Banks & Credit Unions",
            "subcategory":"Bank",
            "type":"Services"
        }
    ],
    "sg:phone":"+1 678 715 5100",
    "sg:postcode":"30135",
    "sg:province":"GA",
    "sg:tags":[
        "loan",
        "real estate"
    ],
    "wof:name":"Homebanc",
    "wof:placetype":"venue"
},
  "geometry": {"coordinates":[-84.734542,33.724253],"type":"Point"}
}