{
  "type": "Feature",
  "properties": {
    "addr:full":"3230 Kingsdale Dr SW Atlanta GA 30311",
    "addr:postcode":"3230;30311",
    "addr:street":"Kingsdale Dr Sw",
    "iso:country":"US",
    "sg:address":"3230 Kingsdale Dr SW",
    "sg:city":"Atlanta",
    "sg:classifiers":[
        {
            "category":"Arts & Performance",
            "subcategory":"Theater",
            "type":"Entertainment"
        }
    ],
    "sg:phone":"+1 404 691 9205",
    "sg:postcode":"30311",
    "sg:province":"GA",
    "sg:tags":[
        "group"
    ],
    "wof:name":"C Amore Music Inc",
    "wof:placetype":"venue"
},
  "geometry": {"coordinates":[-84.49349599999999,33.722222],"type":"Point"}
}