{
  "type": "Feature",
  "properties": {
    "iso:country":"US",
    "sg:address":"8605 Matt Hwy",
    "sg:city":"Ball Ground",
    "sg:classifiers":[
        {
            "category":"Freight",
            "type":"Transportation"
        }
    ],
    "sg:phone":"+1 770 889 9841",
    "sg:postcode":"30107",
    "sg:province":"GA",
    "sg:tags":[
        "operator",
        "local",
        "trucking"
    ],
    "wof:name":"Bb Trucking",
    "wof:placetype":"venue"
},
  "geometry": {"coordinates":[-84.236768,34.298082],"type":"Point"}
}