{
  "type": "Feature",
  "properties": {
    "addr:full":"10300 Brier Mill Ct Alpharetta GA 30022",
    "addr:housenumber":"10300",
    "addr:postcode":"30022",
    "addr:street":"Brier Mill Ct",
    "iso:country":"US",
    "sg:address":"10300 Brier Mill Ct",
    "sg:city":"Alpharetta",
    "sg:classifiers":[
        {
            "category":"Professional",
            "subcategory":"Business Services",
            "type":"Services"
        }
    ],
    "sg:phone":"+1 770 751 1461",
    "sg:postcode":"30022",
    "sg:province":"GA",
    "sg:tags":[
        "convention",
        "meeting",
        "facility"
    ],
    "wof:name":"Barbara Hill Events Inc",
    "wof:placetype":"venue"
},
  "geometry": {"coordinates":[-84.236428,34.031006],"type":"Point"}
}