{
  "type": "Feature",
  "properties": {
    "iso:country":"US",
    "sg:address":"1609 White Oak Dr",
    "sg:city":"Winder",
    "sg:classifiers":[
        {
            "category":"Shopping",
            "subcategory":"Pharmacy",
            "type":"Retail Goods"
        }
    ],
    "sg:phone":"+1 770 725 1660",
    "sg:postcode":"30680",
    "sg:province":"GA",
    "sg:tags":[
        "aid",
        "supply",
        "first"
    ],
    "wof:name":"Aid America First Aid Saf",
    "wof:placetype":"venue"
},
  "geometry": {"coordinates":[-83.60045100000001,34.010719],"type":"Point"}
}