{
  "type": "Feature",
  "properties": {
    "addr:full":"3625 Dallas Hwy SW Ste 400 Marietta GA 30064",
    "addr:housenumber":"3625",
    "addr:postcode":"30064",
    "addr:street":"Dallas Hwy Sw Ste 400",
    "iso:country":"US",
    "sg:address":"3625 Dallas Hwy SW Ste 400",
    "sg:city":"Marietta",
    "sg:classifiers":[
        {
            "category":"Shopping",
            "subcategory":"Books",
            "type":"Retail Goods"
        }
    ],
    "sg:phone":"+1 770 424 0511",
    "sg:postcode":"30064",
    "sg:province":"GA",
    "sg:tags":[
        "bookstore"
    ],
    "sg:website":"http://store-locator.barnesandnoble.com/store/2157",
    "wof:name":"Barnes & Noble Booksellers",
    "wof:placetype":"venue"
},
  "geometry": {"coordinates":[-84.657927,33.953342],"type":"Point"}
}