{
  "type": "Feature",
  "properties": {
    "addr:full":"707 Jackson Ave Helena GA 31037",
    "addr:housenumber":"707",
    "addr:postcode":"31037",
    "addr:street":"Jackson Ave",
    "iso:country":"US",
    "sg:address":"707 Jackson Ave",
    "sg:city":"Helena",
    "sg:classifiers":[
        {
            "category":"Personal",
            "subcategory":"Beauty Salon",
            "type":"Services"
        }
    ],
    "sg:phone":"+1 229 868 2418",
    "sg:postcode":"31037",
    "sg:province":"GA",
    "wof:name":"Linda's Beauty Shop",
    "wof:placetype":"venue"
},
  "geometry": {"coordinates":[-82.919471,32.075725],"type":"Point"}
}