{
  "type": "Feature",
  "properties": {
    "addr:full":"704 3rd St SW Moultrie GA 31768",
    "addr:housenumber":"704",
    "addr:postcode":"31768",
    "addr:street":"3Rd St Sw",
    "iso:country":"US",
    "sg:address":"704 3rd St SW",
    "sg:city":"Moultrie",
    "sg:classifiers":[
        {
            "category":"Travel",
            "subcategory":"Hotels & Motels",
            "type":"Entertainment"
        }
    ],
    "sg:phone":"+1 229 890 0714",
    "sg:postcode":"31768",
    "sg:province":"GA",
    "sg:tags":[
        "breakfast",
        "accommodation",
        "bed"
    ],
    "wof:name":"Barber Tucker House B & B",
    "wof:placetype":"venue"
},
  "geometry": {"coordinates":[-83.792215,31.172898],"type":"Point"}
}