{
  "type": "Feature",
  "properties": {
    "iso:country":"US",
    "sg:address":"1925 Old Concord Dr SE",
    "sg:city":"Covington",
    "sg:classifiers":[
        {
            "category":"Professional",
            "subcategory":"Research",
            "type":"Services"
        }
    ],
    "sg:phone":"+1 770 922 0331",
    "sg:postcode":"30016",
    "sg:province":"GA",
    "sg:tags":[
        "environmental",
        "ecological"
    ],
    "wof:name":"Hendon Safety & Environmental",
    "wof:placetype":"venue"
},
  "geometry": {"coordinates":[-83.976238,33.596614],"type":"Point"}
}