{
  "type": "Feature",
  "properties": {
    "addr:full":"701 S Green St Dalton GA 30721",
    "addr:housenumber":"701",
    "addr:postcode":"30721",
    "addr:street":"S Green St",
    "iso:country":"US",
    "sg:address":"701 S Green St",
    "sg:city":"Dalton",
    "sg:classifiers":[
        {
            "category":"Manufacturing",
            "subcategory":"Tools & Machinery",
            "type":"Manufacturing & Wholesale Goods"
        }
    ],
    "sg:phone":"+1 706 278 9530",
    "sg:postcode":"30721",
    "sg:province":"GA",
    "sg:tags":[
        "textile",
        "parts"
    ],
    "wof:name":"Williams Specialty Co",
    "wof:placetype":"venue"
},
  "geometry": {"coordinates":[-84.963324,34.76318],"type":"Point"}
}