{
  "type": "Feature",
  "properties": {
    "addr:full":"104 Wiley Rd La Grange GA 30240",
    "addr:housenumber":"104",
    "addr:postcode":"30240",
    "addr:street":"Wiley Rd",
    "iso:country":"US",
    "sg:address":"104 Wiley Rd",
    "sg:city":"La Grange",
    "sg:classifiers":[
        {
            "category":"Communications",
            "type":"Services"
        }
    ],
    "sg:phone":"+1 706 812 8296",
    "sg:postcode":"30240",
    "sg:province":"GA",
    "sg:tags":[
        "communication"
    ],
    "wof:name":"Reltec Communications",
    "wof:placetype":"venue"
},
  "geometry": {"coordinates":[-85.046961,32.992714],"type":"Point"}
}