{
  "type": "Feature",
  "properties": {
    "iso:country":"US",
    "sg:address":"1256 Rockbridge Rd NW",
    "sg:city":"Conyers",
    "sg:classifiers":[
        {
            "category":"Professional",
            "subcategory":"Accounting & Tax Preparation",
            "type":"Services"
        }
    ],
    "sg:phone":"+1 770 483 4647",
    "sg:postcode":"30012",
    "sg:province":"GA",
    "sg:tags":[
        "return",
        "filing"
    ],
    "wof:name":"Strouds Income Tax Svc",
    "wof:placetype":"venue"
},
  "geometry": {"coordinates":[-84.02980700000001,33.676341],"type":"Point"}
}