{
  "type": "Feature",
  "properties": {
    "iso:country":"US",
    "sg:address":"2572 Inverloch Cir",
    "sg:city":"Duluth",
    "sg:classifiers":[
        {
            "category":"Professional",
            "type":"Services"
        }
    ],
    "sg:phone":"+1 770 476 9501",
    "sg:postcode":"30096",
    "sg:province":"GA",
    "sg:tags":[
        "establishment"
    ],
    "wof:name":"Productions FAM",
    "wof:placetype":"venue"
},
  "geometry": {"coordinates":[-84.16336800000001,33.969952],"type":"Point"}
}