{
  "type": "Feature",
  "properties": {
    "addr:full":"11700 Haynes Bridge Rd Alpharetta GA 30004",
    "addr:housenumber":"11700",
    "addr:postcode":"30004",
    "addr:street":"Haynes Bridge Rd",
    "iso:country":"US",
    "sg:address":"11700 Haynes Bridge Rd",
    "sg:city":"Alpharetta",
    "sg:classifiers":[
        {
            "category":"Food & Beverages",
            "subcategory":"Groceries & Convenience Stores",
            "type":"Retail Goods"
        }
    ],
    "sg:phone":"+1 770 752 0879",
    "sg:postcode":"30004",
    "sg:province":"GA",
    "wof:name":"Quik Trip",
    "wof:placetype":"venue"
},
  "geometry": {"coordinates":[-84.29306099999999,34.066458],"type":"Point"}
}