{
  "type": "Feature",
  "properties": {
    "addr:full":"1818 Perimeter Rd Dawsonville GA 30534",
    "addr:housenumber":"1818",
    "addr:postcode":"30534",
    "addr:street":"Perimeter Rd",
    "iso:country":"US",
    "sg:address":"1818 Perimeter Rd",
    "sg:city":"Dawsonville",
    "sg:classifiers":[
        {
            "category":"Professional",
            "subcategory":"Research",
            "type":"Services"
        },
        {
            "category":"Professional",
            "subcategory":"Management & Consulting",
            "type":"Services"
        }
    ],
    "sg:phone":"+1 706 579 1607",
    "sg:postcode":"30534",
    "sg:province":"GA",
    "sg:tags":[
        "environmental",
        "ecological"
    ],
    "wof:name":"Mill Creek Environmental Svcs",
    "wof:placetype":"venue"
},
  "geometry": {"coordinates":[-84.105442,34.413438],"type":"Point"}
}