{
  "type": "Feature",
  "properties": {
    "addr:full":"1858 Mcdaniel Mill Rd SW Conyers GA 30094",
    "addr:housenumber":"1858",
    "addr:postcode":"30094",
    "addr:street":"Mcdaniel Mill Rd Sw",
    "iso:country":"US",
    "sg:address":"1858 Mcdaniel Mill Rd SW",
    "sg:city":"Conyers",
    "sg:classifiers":[
        {
            "category":"Building & Trades",
            "subcategory":"Construction",
            "type":"Services"
        }
    ],
    "sg:phone":"+1 770 483 5765",
    "sg:postcode":"30094",
    "sg:province":"GA",
    "sg:tags":[
        "wallcoverings-installation",
        "wallpaper",
        "painting",
        "contractor"
    ],
    "wof:name":"Robertson Painting Inc",
    "wof:placetype":"venue"
},
  "geometry": {"coordinates":[-84.075524,33.638331],"type":"Point"}
}