{
  "type": "Feature",
  "properties": {
    "addr:full":"800 S Hill St Griffin GA 30224",
    "addr:housenumber":"800",
    "addr:postcode":"30224",
    "addr:street":"S Hill St",
    "iso:country":"US",
    "sg:address":"800 S Hill St",
    "sg:city":"Griffin",
    "sg:classifiers":[
        {
            "category":"Insurance",
            "subcategory":"Insurance Agent",
            "type":"Services"
        }
    ],
    "sg:phone":"+1 770 233 9716",
    "sg:postcode":"30224",
    "sg:province":"GA",
    "wof:name":"Alfa Insurance Corp",
    "wof:placetype":"venue"
},
  "geometry": {"coordinates":[-84.26416999999999,33.236079],"type":"Point"}
}