{
  "type": "Feature",
  "properties": {
    "addr:full":"2355 Calhoun Rd NE Rome GA 30161",
    "addr:housenumber":"2355",
    "addr:postcode":"ga 30161",
    "addr:street":"Calhoun Rd Ne",
    "iso:country":"US",
    "sg:address":"2355 Calhoun Rd NE",
    "sg:city":"Rome",
    "sg:classifiers":[
        {
            "category":"Food & Beverages",
            "subcategory":"Groceries & Convenience Stores",
            "type":"Retail Goods"
        }
    ],
    "sg:phone":"+1 706 802 1005",
    "sg:postcode":"30161",
    "sg:province":"GA",
    "wof:name":"North Ridge Stop & Shop",
    "wof:placetype":"venue"
},
  "geometry": {"coordinates":[-85.116434,34.291102],"type":"Point"}
}