{
  "type": "Feature",
  "properties": {
    "addr:full":"5019 Forsyth Rd Macon GA 31210",
    "addr:housenumber":"5019",
    "addr:postcode":"31210",
    "addr:street":"Forsyth Rd",
    "iso:country":"US",
    "sg:address":"5019 Forsyth Rd",
    "sg:city":"Macon",
    "sg:classifiers":[
        {
            "category":"Wholesale",
            "subcategory":"Petroleum",
            "type":"Manufacturing & Wholesale Goods"
        }
    ],
    "sg:phone":"+1 478 477 3551",
    "sg:postcode":"31210",
    "sg:province":"GA",
    "sg:tags":[
        "pipe",
        "refined",
        "pipeline",
        "line",
        "company"
    ],
    "wof:name":"Colonial Pipeline Company",
    "wof:placetype":"venue"
},
  "geometry": {"coordinates":[-83.727661,32.882058],"type":"Point"}
}