{
  "type": "Feature",
  "properties": {
    "addr:full":"2549 Sunset Dr Rising Fawn GA 30738",
    "addr:housenumber":"2549",
    "addr:postcode":"30738",
    "addr:street":"Sunset Dr",
    "iso:country":"US",
    "sg:address":"2549 Sunset Dr",
    "sg:city":"Rising Fawn",
    "sg:classifiers":[
        {
            "category":"Building & Trades",
            "subcategory":"Construction",
            "type":"Services"
        }
    ],
    "sg:phone":"+1 706 398 9356",
    "sg:postcode":"30738",
    "sg:province":"GA",
    "sg:tags":[
        "hanging",
        "contractor"
    ],
    "wof:name":"Earns Painting",
    "wof:placetype":"venue"
},
  "geometry": {"coordinates":[-85.51150699999999,34.806912],"type":"Point"}
}