{
  "type": "Feature",
  "properties": {
    "iso:country":"US",
    "sg:address":"100 Merrick Dr",
    "sg:city":"Peachtree City",
    "sg:classifiers":[
        {
            "category":"Real Estate",
            "subcategory":"Real Estate Operator",
            "type":"Services"
        }
    ],
    "sg:phone":"+1 770 631 1970",
    "sg:postcode":"30269",
    "sg:province":"GA",
    "sg:tags":[
        "apartment"
    ],
    "wof:name":"Summit Peachtree City Apartment Homes",
    "wof:placetype":"venue"
},
  "geometry": {"coordinates":[-84.57379899999999,33.4417],"type":"Point"}
}