{
  "type": "Feature",
  "properties": {
    "addr:full":"608 Twin Brooks Way Marietta GA 30067",
    "addr:housenumber":"608",
    "addr:postcode":"30067",
    "addr:street":"Twin Brooks Way",
    "iso:country":"US",
    "sg:address":"608 Twin Brooks Way",
    "sg:city":"Marietta",
    "sg:classifiers":[
        {
            "category":"Professional",
            "subcategory":"Computer Services",
            "type":"Services"
        }
    ],
    "sg:phone":"+1 770 218 9311",
    "sg:postcode":"30067",
    "sg:province":"GA",
    "sg:tags":[
        "datum"
    ],
    "wof:name":"Dancing Graphics",
    "wof:placetype":"venue"
},
  "geometry": {"coordinates":[-84.50453,33.937087],"type":"Point"}
}