{
  "type": "Feature",
  "properties": {
    "addr:full":"309 Main St S Adairsville GA 30103",
    "addr:housenumber":"309",
    "addr:postcode":"30103",
    "addr:street":"Main St S Adairsville",
    "iso:country":"US",
    "sg:address":"309 Main St S",
    "sg:city":"Adairsville",
    "sg:classifiers":[
        {
            "category":"Building & Trades",
            "subcategory":"Construction",
            "type":"Services"
        }
    ],
    "sg:phone":"+1 770 773 9141",
    "sg:postcode":"30103",
    "sg:province":"GA",
    "sg:tags":[
        "sun",
        "solarium",
        "rooms"
    ],
    "wof:name":"Porch & Patio Plus",
    "wof:placetype":"venue"
},
  "geometry": {"coordinates":[-84.934031,34.363247],"type":"Point"}
}