{
  "type": "Feature",
  "properties": {
    "addr:full":"1010 Golf Club Rd Douglas GA 31533",
    "addr:housenumber":"1010",
    "addr:postcode":"31533",
    "addr:street":"Golf Club Rd",
    "iso:country":"US",
    "sg:address":"1010 Golf Club Rd",
    "sg:city":"Douglas",
    "sg:classifiers":[
        {
            "category":"Professional",
            "type":"Services"
        }
    ],
    "sg:phone":"+1 912 384 0076",
    "sg:postcode":"31533",
    "sg:province":"GA",
    "wof:name":"Marie-Ellen Zeigler",
    "wof:placetype":"venue"
},
  "geometry": {"coordinates":[-82.83652600000001,31.518409],"type":"Point"}
}