{
  "type": "Feature",
  "properties": {
    "iso:country":"US",
    "sg:address":"4650 Jimmy Carter Blvd Suite 133-B",
    "sg:city":"Norcross",
    "sg:classifiers":[
        {
            "category":"Restaurant",
            "type":"Food & Drink"
        }
    ],
    "sg:postcode":"30093",
    "sg:province":"GA",
    "sg:tags":[
        "vietnamese"
    ],
    "wof:name":"I Luv Pho",
    "wof:placetype":"venue"
},
  "geometry": {"coordinates":[-84.192705,33.885416],"type":"Point"}
}