{
  "type": "Feature",
  "properties": {
    "addr:full":"2786 Dixie Rd Covington GA 30014",
    "addr:housenumber":"2786",
    "addr:postcode":"30014",
    "addr:street":"Dixie Rd",
    "iso:country":"US",
    "sg:address":"2786 Dixie Rd",
    "sg:city":"Covington",
    "sg:classifiers":[
        {
            "category":"Organizations",
            "subcategory":"Religious Organization",
            "type":"Services"
        }
    ],
    "sg:phone":"+1 770 786 4293",
    "sg:postcode":"30014",
    "sg:province":"GA",
    "wof:name":"Starrsvlle Untd Methdst Church",
    "wof:placetype":"venue"
},
  "geometry": {"coordinates":[-83.80426799999999,33.532756],"type":"Point"}
}