{
  "type": "Feature",
  "properties": {
    "addr:full":"1050 Ultimate Dr Athens GA 30606",
    "addr:housenumber":"1050",
    "addr:postcode":"30606",
    "addr:street":"Ultimate Dr",
    "iso:country":"US",
    "sg:address":"1050 Ultimate Dr",
    "sg:city":"Athens",
    "sg:classifiers":[
        {
            "category":"Travel",
            "subcategory":"Hotels & Motels",
            "type":"Entertainment"
        }
    ],
    "sg:phone":"+1 706 548 5676",
    "sg:postcode":"30606",
    "sg:province":"GA",
    "wof:name":"Microtel",
    "wof:placetype":"venue"
},
  "geometry": {"coordinates":[-83.44584,33.94345],"type":"Point"}
}