{
  "type": "Feature",
  "properties": {
    "addr:full":"141 W Wieuca Rd NE Atlanta GA 30342",
    "addr:housenumber":"141",
    "addr:postcode":"30342",
    "addr:street":"W Wieuca Rd Ne",
    "iso:country":"US",
    "sg:address":"141 W Wieuca Rd NE",
    "sg:city":"Atlanta",
    "sg:classifiers":[
        {
            "category":"Personal",
            "type":"Services"
        }
    ],
    "sg:phone":"+1 770 855 8522",
    "sg:postcode":"30342",
    "sg:province":"GA",
    "sg:tags":[
        "therapist",
        "massage"
    ],
    "wof:name":"Nunn Therapuetic Massage",
    "wof:placetype":"venue"
},
  "geometry": {"coordinates":[-84.380047,33.877004],"type":"Point"}
}