{
  "type": "Feature",
  "properties": {
    "iso:country":"US",
    "sg:address":"244 Oak St",
    "sg:city":"Homer",
    "sg:classifiers":[
        {
            "category":"Manufacturing",
            "subcategory":"Metals",
            "type":"Manufacturing & Wholesale Goods"
        }
    ],
    "sg:phone":"+1 706 677 1959",
    "sg:postcode":"30547",
    "sg:province":"GA",
    "sg:tags":[
        "blast",
        "furnace",
        "works"
    ],
    "wof:name":"Keiths Iron Handrails & Stairs",
    "wof:placetype":"venue"
},
  "geometry": {"coordinates":[-83.50695899999999,34.327623],"type":"Point"}
}