{
  "type": "Feature",
  "properties": {
    "addr:full":"3981 Sanders Rd SW Marietta GA 30008",
    "addr:housenumber":"3981",
    "addr:postcode":"30008",
    "addr:street":"Sanders Rd Sw",
    "iso:country":"US",
    "sg:address":"3981 Sanders Rd SW",
    "sg:city":"Marietta",
    "sg:classifiers":[
        {
            "category":"Professional",
            "subcategory":"Management & Consulting",
            "type":"Services"
        }
    ],
    "sg:phone":"+1 770 943 8386",
    "sg:postcode":"30008",
    "sg:province":"GA",
    "wof:name":"Giplir Inc",
    "wof:placetype":"venue"
},
  "geometry": {"coordinates":[-84.641141,33.859548],"type":"Point"}
}