{
  "type": "Feature",
  "properties": {
    "addr:full":"118 Hunter Ln Poulan GA 31781",
    "addr:housenumber":"118",
    "addr:postcode":"31781",
    "addr:street":"Hunter Ln",
    "iso:country":"US",
    "sg:address":"118 Hunter Ln",
    "sg:city":"Poulan",
    "sg:classifiers":[
        {
            "category":"Professional",
            "type":"Services"
        }
    ],
    "sg:phone":"+1 229 776 9335",
    "sg:postcode":"31781",
    "sg:province":"GA",
    "wof:name":"Benjamin C Souter",
    "wof:placetype":"venue"
},
  "geometry": {"coordinates":[-83.779861,31.557347],"type":"Point"}
}