{
  "type": "Feature",
  "properties": {
    "addr:full":"2965 Cordite Loop Snellville GA 30039",
    "addr:housenumber":"2965",
    "addr:postcode":"30039",
    "addr:street":"Cordite Loop",
    "iso:country":"US",
    "sg:address":"2965 Cordite Loop",
    "sg:city":"Snellville",
    "sg:classifiers":[
        {
            "category":"Professional",
            "subcategory":"Accounting & Tax Preparation",
            "type":"Services"
        }
    ],
    "sg:phone":"+1 770 736 5004",
    "sg:postcode":"30039",
    "sg:province":"GA",
    "wof:name":"Margaret Donehoo CPA",
    "wof:placetype":"venue"
},
  "geometry": {"coordinates":[-84.042933,33.827376],"type":"Point"}
}