{
  "type": "Feature",
  "properties": {
    "addr:full":"356 River Rd Jonesboro GA 30236",
    "addr:housenumber":"356",
    "addr:postcode":"30236",
    "addr:street":"River Rd",
    "iso:country":"US",
    "sg:address":"356 River Rd",
    "sg:city":"Jonesboro",
    "sg:classifiers":[
        {
            "category":"Social Services",
            "subcategory":"Child Care",
            "type":"Services"
        }
    ],
    "sg:phone":"+1 770 473 0796",
    "sg:postcode":"30236",
    "sg:province":"GA",
    "sg:tags":[
        "day"
    ],
    "wof:name":"Archibalds Daycare",
    "wof:placetype":"venue"
},
  "geometry": {"coordinates":[-84.37796299999999,33.571313],"type":"Point"}
}