{
  "type": "Feature",
  "properties": {
    "iso:country":"US",
    "sg:address":"2134 Fair Ridge Ct",
    "sg:city":"Jonesboro",
    "sg:classifiers":[
        {
            "category":"Manufacturing",
            "subcategory":"Textiles",
            "type":"Manufacturing & Wholesale Goods"
        }
    ],
    "sg:phone":"+1 770 471 8415",
    "sg:postcode":"30236",
    "sg:province":"GA",
    "sg:tags":[
        "retail"
    ],
    "wof:name":"Futuristic Apparel and Design",
    "wof:placetype":"venue"
},
  "geometry": {"coordinates":[-84.32092299999999,33.496699],"type":"Point"}
}