{
  "type": "Feature",
  "properties": {
    "addr:full":"2424 Clark Ave Albany GA 31705",
    "addr:housenumber":"2424",
    "addr:postcode":"31705",
    "addr:street":"Clark Ave",
    "iso:country":"US",
    "sg:address":"2424 Clark Ave",
    "sg:city":"Albany",
    "sg:classifiers":[
        {
            "category":"Food & Beverages",
            "subcategory":"Groceries & Convenience Stores",
            "type":"Retail Goods"
        },
        {
            "category":"Autos & Motor Vehicles",
            "subcategory":"Fuel & Gas Station",
            "type":"Retail Goods"
        }
    ],
    "sg:phone":"+1 229 483 0137",
    "sg:postcode":"31705",
    "sg:province":"GA",
    "sg:tags":[
        "station",
        "gasoline"
    ],
    "wof:name":"Enmark Stations Inc",
    "wof:placetype":"venue"
},
  "geometry": {"coordinates":[-84.09108000000001,31.579842],"type":"Point"}
}