{
  "type": "Feature",
  "properties": {
    "iso:country":"US",
    "sg:address":"100 Petty Rd",
    "sg:city":"Lawrenceville",
    "sg:classifiers":[
        {
            "category":"Manufacturing",
            "subcategory":"Printing",
            "type":"Manufacturing & Wholesale Goods"
        }
    ],
    "sg:phone":"+1 770 277 8950",
    "sg:postcode":"30043",
    "sg:province":"GA",
    "sg:tags":[
        "newspaper",
        "retail",
        "direct",
        "sales"
    ],
    "wof:name":"Atlanta Journal & Constitution",
    "wof:placetype":"venue"
},
  "geometry": {"coordinates":[-83.96672100000001,33.987449],"type":"Point"}
}