{
  "type": "Feature",
  "properties": {
    "addr:full":"340 Eisenhower Dr Savannah GA 31406",
    "addr:housenumber":"340",
    "addr:postcode":"31406",
    "addr:street":"Eisenhower Dr",
    "iso:country":"US",
    "sg:address":"340 Eisenhower Dr",
    "sg:city":"Savannah",
    "sg:classifiers":[
        {
            "category":"Health Services",
            "subcategory":"Health Practitioner",
            "type":"Services"
        }
    ],
    "sg:phone":"+1 912 303 9966",
    "sg:postcode":"31406",
    "sg:province":"GA",
    "wof:name":"Paula Ruehling LPC Inc",
    "wof:placetype":"venue"
},
  "geometry": {"coordinates":[-81.10394599999999,32.007499],"type":"Point"}
}