{
  "type": "Feature",
  "properties": {
    "addr:full":"309 Oakland Rd Lawrenceville GA 30044",
    "addr:housenumber":"309",
    "addr:postcode":"30044",
    "addr:street":"Oakland Rd",
    "iso:country":"US",
    "sg:address":"309 Oakland Rd",
    "sg:city":"Lawrenceville",
    "sg:classifiers":[
        {
            "category":"Building & Trades",
            "subcategory":"Cleaning & Sanitation",
            "type":"Services"
        }
    ],
    "sg:phone":"+1 678 376 0841",
    "sg:postcode":"30044",
    "sg:province":"GA",
    "sg:website":"www.thecleaningindustry.com",
    "wof:name":"Management Solutions Group",
    "wof:placetype":"venue"
},
  "geometry": {"coordinates":[-84.06135999999999,33.928526],"type":"Point"}
}