{
  "type": "Feature",
  "properties": {
    "addr:full":"120 Chapel Crossing Rd Brunswick GA 31525",
    "addr:housenumber":"120",
    "addr:postcode":"31525",
    "addr:street":"Chapel Crossing Rd",
    "iso:country":"US",
    "sg:address":"120 Chapel Crossing Rd",
    "sg:city":"Brunswick",
    "sg:classifiers":[
        {
            "category":"Government",
            "subcategory":"Police Station",
            "type":"Public Place"
        }
    ],
    "sg:phone":"+1 912 267 2100",
    "sg:postcode":"31525",
    "sg:province":"GA",
    "sg:tags":[
        "federal"
    ],
    "wof:name":"FEDERAL Law Enforcement Dir",
    "wof:placetype":"venue"
},
  "geometry": {"coordinates":[-81.477598,31.225689],"type":"Point"}
}