{
  "type": "Feature",
  "properties": {
    "addr:full":"4704 Noble Creek Dr NW Atlanta GA 30327",
    "addr:housenumber":"4704",
    "addr:postcode":"30327",
    "addr:street":"Noble Creek Dr Nw",
    "iso:country":"US",
    "sg:address":"4704 Noble Creek Dr NW",
    "sg:city":"Atlanta",
    "sg:classifiers":[
        {
            "category":"Shopping",
            "subcategory":"Computers & Home Electronics",
            "type":"Retail Goods"
        }
    ],
    "sg:phone":"+1 404 350 6999",
    "sg:postcode":"30327",
    "sg:province":"GA",
    "sg:tags":[
        "sales",
        "cleaning"
    ],
    "wof:name":"Computer Cleaning Depot Inc",
    "wof:placetype":"venue"
},
  "geometry": {"coordinates":[-84.427134,33.816191],"type":"Point"}
}