{
  "type": "Feature",
  "properties": {
    "addr:full":"1226 S Harris St Sandersville GA 31082",
    "addr:housenumber":"1226",
    "addr:postcode":"31082",
    "addr:street":"S Harris St",
    "iso:country":"US",
    "sg:address":"1226 S Harris St",
    "sg:city":"Sandersville",
    "sg:classifiers":[
        {
            "category":"Shopping",
            "subcategory":"Discount & Variety Stores",
            "type":"Retail Goods"
        }
    ],
    "sg:phone":"+1 478 553 1000",
    "sg:postcode":"31082",
    "sg:province":"GA",
    "wof:name":"Dollar Junction",
    "wof:placetype":"venue"
},
  "geometry": {"coordinates":[-82.809145,32.958038],"type":"Point"}
}