{
  "type": "Feature",
  "properties": {
    "iso:country":"US",
    "sg:address":"640 Plum St",
    "sg:city":"Macon",
    "sg:classifiers":[
        {
            "category":"Professional",
            "subcategory":"Accounting & Tax Preparation",
            "type":"Services"
        }
    ],
    "sg:phone":"+1 478 743 0711",
    "sg:postcode":"31201",
    "sg:province":"GA",
    "sg:tags":[
        "return",
        "filing"
    ],
    "wof:name":"R H Consulting Tax Firm LLC",
    "wof:placetype":"venue"
},
  "geometry": {"coordinates":[-83.63149900000001,32.833997],"type":"Point"}
}