{
  "type": "Feature",
  "properties": {
    "addr:full":"4690 Berkeley Walk Pt Duluth GA 30096",
    "addr:housenumber":"4690",
    "addr:postcode":"30096",
    "addr:street":"Berkeley Walk Pt",
    "iso:country":"US",
    "sg:address":"4690 Berkeley Walk Pt",
    "sg:city":"Duluth",
    "sg:classifiers":[
        {
            "category":"Building & Trades",
            "subcategory":"Cleaning & Sanitation",
            "type":"Services"
        }
    ],
    "sg:phone":"+1 770 449 8710",
    "sg:postcode":"30096",
    "sg:province":"GA",
    "sg:tags":[
        "maintenance"
    ],
    "wof:name":"Pencor Building Services",
    "wof:placetype":"venue"
},
  "geometry": {"coordinates":[-84.189528,33.97656],"type":"Point"}
}