{
  "type": "Feature",
  "properties": {
    "addr:full":"1020 W Hill St Thomson GA 30824",
    "addr:housenumber":"1020",
    "addr:postcode":"30824",
    "addr:street":"W Hill St",
    "iso:country":"US",
    "sg:address":"1020 W Hill St",
    "sg:city":"Thomson",
    "sg:classifiers":[
        {
            "category":"Health Services",
            "subcategory":"Doctor",
            "type":"Services"
        },
        {
            "category":"Health Services",
            "subcategory":"Hospital",
            "type":"Services"
        }
    ],
    "sg:phone":"+1 706 860 1752",
    "sg:postcode":"30824",
    "sg:province":"GA",
    "sg:tags":[
        "physician",
        "kidneys",
        "surgeons",
        "dialysis",
        "nephrology"
    ],
    "wof:name":"Bma Thomson",
    "wof:placetype":"venue"
},
  "geometry": {"coordinates":[-82.51259,33.45936],"type":"Point"}
}