{
  "type": "Feature",
  "properties": {
    "addr:full":"1060 Franklin Rd SE Marietta GA 30067",
    "addr:housenumber":"1060",
    "addr:postcode":"30067",
    "addr:street":"Franklin Rd Se",
    "iso:country":"US",
    "sg:address":"1060 Franklin Rd SE",
    "sg:city":"Marietta",
    "sg:classifiers":[
        {
            "category":"Social Services",
            "subcategory":"Child Care",
            "type":"Services"
        },
        {
            "category":"Education",
            "subcategory":"Preschool",
            "type":"Public Place"
        }
    ],
    "sg:phone":"+1 678 831 0669",
    "sg:postcode":"30067",
    "sg:province":"GA",
    "sg:tags":[
        "school",
        "homes-children",
        "kindergarten",
        "nursery",
        "day"
    ],
    "wof:name":"First Step Learning Center",
    "wof:placetype":"venue"
},
  "geometry": {"coordinates":[-84.49203900000001,33.925043],"type":"Point"}
}