{
  "type": "Feature",
  "properties": {
    "addr:full":"717 Cameron Rd Blackshear GA 31545",
    "addr:housenumber":"717",
    "addr:postcode":"31545",
    "addr:street":"Cameron Rd",
    "iso:country":"US",
    "sg:address":"717 Cameron Rd",
    "sg:city":"Blackshear",
    "sg:classifiers":[
        {
            "category":"Health Services",
            "subcategory":"Clinic",
            "type":"Services"
        }
    ],
    "sg:phone":"+1 912 449 0780",
    "sg:postcode":"31545",
    "sg:province":"GA",
    "sg:tags":[
        "home",
        "care"
    ],
    "wof:name":"Altamaha Homecare",
    "wof:placetype":"venue"
},
  "geometry": {"coordinates":[-81.9611,31.585716],"type":"Point"}
}