{
  "type": "Feature",
  "properties": {
    "iso:country":"US",
    "sg:address":"999 Peachtree St",
    "sg:city":"Atlanta",
    "sg:classifiers":[
        {
            "category":"Retail",
            "subcategory":"Laundry & Dry Cleaning",
            "type":"Services"
        }
    ],
    "sg:phone":"+1 404 872 1604",
    "sg:postcode":"30309",
    "sg:province":"GA",
    "wof:name":"Gizzelle James Couturiere",
    "wof:placetype":"venue"
},
  "geometry": {"coordinates":[-84.383898,33.782127],"type":"Point"}
}