{
  "type": "Feature",
  "properties": {
    "addr:full":"536 Newnan St Carrollton GA 30117",
    "addr:housenumber":"536",
    "addr:postcode":"30117",
    "addr:street":"Newnan St",
    "iso:country":"US",
    "sg:address":"536 Newnan St",
    "sg:city":"Carrollton",
    "sg:classifiers":[
        {
            "category":"Health Services",
            "subcategory":"Doctor",
            "type":"Services"
        }
    ],
    "sg:phone":"+1 770 832 0089",
    "sg:postcode":"30117",
    "sg:province":"GA",
    "wof:name":"Moses Donna Thomas DMD PC",
    "wof:placetype":"venue"
},
  "geometry": {"coordinates":[-85.06830600000001,33.580451],"type":"Point"}
}