{
  "type": "Feature",
  "properties": {
    "addr:full":"907 Ga Highway 212 NW Milledgeville GA 31061",
    "addr:housenumber":"907",
    "addr:postcode":"31061",
    "addr:street":"Ga Highway 212 Nw",
    "iso:country":"US",
    "sg:address":"907 Ga Highway 212 NW",
    "sg:city":"Milledgeville",
    "sg:classifiers":[
        {
            "category":"Retail",
            "subcategory":"Laundry & Dry Cleaning",
            "type":"Services"
        }
    ],
    "sg:phone":"+1 478 968 0135",
    "sg:postcode":"31061",
    "sg:province":"GA",
    "sg:tags":[
        "chimney"
    ],
    "wof:name":"Clean Sweep Chimney Service",
    "wof:placetype":"venue"
},
  "geometry": {"coordinates":[-83.356048,33.159791],"type":"Point"}
}