{
  "type": "Feature",
  "properties": {
    "addr:full":"1034 Crooked Creek Rd Eatonton GA 31024",
    "addr:housenumber":"1034",
    "addr:postcode":"31024",
    "addr:street":"Crooked Creek Rd",
    "iso:country":"US",
    "sg:address":"1034 Crooked Creek Rd",
    "sg:city":"Eatonton",
    "sg:classifiers":[
        {
            "category":"Shopping",
            "type":"Retail Goods"
        }
    ],
    "sg:phone":"+1 478 945 3823",
    "sg:postcode":"31024",
    "sg:province":"GA",
    "sg:tags":[
        "cosmetic",
        "perfume"
    ],
    "wof:name":"Beauti Control Cosmetics Inc",
    "wof:placetype":"venue"
},
  "geometry": {"coordinates":[-83.24842599999999,33.264251],"type":"Point"}
}