{
  "type": "Feature",
  "properties": {
    "iso:country":"US",
    "sg:address":"195 Peach Tree St",
    "sg:city":"Lincolnton",
    "sg:classifiers":[
        {
            "category":"Retail",
            "subcategory":"Funeral Services",
            "type":"Services"
        }
    ],
    "sg:phone":"+1 706 359 3222",
    "sg:postcode":"30817",
    "sg:province":"GA",
    "sg:tags":[
        "director"
    ],
    "wof:name":"Rees Funeral Home",
    "wof:placetype":"venue"
},
  "geometry": {"coordinates":[-82.47779199999999,33.791925],"type":"Point"}
}