{
  "type": "Feature",
  "properties": {
    "addr:full":"1045 Research Center Dr SW Atlanta GA 30331",
    "addr:housenumber":"1045",
    "addr:postcode":"30331",
    "addr:street":"Research Center Dr Sw",
    "iso:country":"US",
    "sg:address":"1045 Research Center Dr SW",
    "sg:city":"Atlanta",
    "sg:classifiers":[
        {
            "category":"Building & Trades",
            "subcategory":"Construction",
            "type":"Services"
        }
    ],
    "sg:phone":"+1 404 699 2961",
    "sg:postcode":"30331",
    "sg:province":"GA",
    "sg:tags":[
        "floor",
        "work",
        "laying",
        "other",
        "carpet"
    ],
    "wof:name":"T C I",
    "wof:placetype":"venue"
},
  "geometry": {"coordinates":[-84.506024,33.7241],"type":"Point"}
}