{
  "type": "Feature",
  "properties": {
    "addr:full":"575 Juniper St NE Atlanta GA 30308",
    "addr:housenumber":"575",
    "addr:postcode":"30308",
    "addr:street":"Juniper St Ne",
    "iso:country":"US",
    "sg:address":"575 Juniper St NE",
    "sg:city":"Atlanta",
    "sg:classifiers":[
        {
            "category":"Professional",
            "type":"Services"
        }
    ],
    "sg:phone":"+1 404 685 8429",
    "sg:postcode":"30308",
    "sg:province":"GA",
    "wof:name":"Furrytails Inc",
    "wof:placetype":"venue"
},
  "geometry": {"coordinates":[-84.383477,33.771015],"type":"Point"}
}