{
  "type": "Feature",
  "properties": {
    "addr:full":"8020 Riverview Ct Snellville GA 30039",
    "addr:housenumber":"8020",
    "addr:postcode":"30039",
    "addr:street":"Riverview Ct",
    "iso:country":"US",
    "sg:address":"8020 Riverview Ct",
    "sg:city":"Snellville",
    "sg:classifiers":[
        {
            "category":"Social Services",
            "subcategory":"Job Training",
            "type":"Services"
        }
    ],
    "sg:phone":"+1 770 335 8921",
    "sg:postcode":"30039",
    "sg:province":"GA",
    "sg:tags":[
        "employment"
    ],
    "wof:name":"4me, Inc.",
    "wof:placetype":"venue"
},
  "geometry": {"coordinates":[-84.059684,33.768943],"type":"Point"}
}