{
  "type": "Feature",
  "properties": {
    "addr:full":"35 Franklin Loop SE Cartersville GA 30121",
    "addr:housenumber":"35",
    "addr:postcode":"30121",
    "addr:street":"Franklin Loop Se",
    "iso:country":"US",
    "sg:address":"35 Franklin Loop SE",
    "sg:city":"Cartersville",
    "sg:classifiers":[
        {
            "category":"Wholesale",
            "subcategory":"Machinery & Supplies",
            "type":"Manufacturing & Wholesale Goods"
        }
    ],
    "sg:phone":"+1 770 382 4431",
    "sg:postcode":"30121",
    "sg:province":"GA",
    "sg:tags":[
        "equipment",
        "industrial"
    ],
    "wof:name":"Franklin Well Pump Service",
    "wof:placetype":"venue"
},
  "geometry": {"coordinates":[-84.746093,34.105218],"type":"Point"}
}