{
  "type": "Feature",
  "properties": {
    "addr:full":"1625 Pleasant Hill Rd Ste D102 Duluth GA 30096",
    "addr:housenumber":"1625",
    "addr:postcode":"30096",
    "addr:street":"Pleasant Hill Rd Ste D102",
    "iso:country":"US",
    "sg:address":"1625 Pleasant Hill Rd Ste D102",
    "sg:city":"Duluth",
    "sg:classifiers":[
        {
            "category":"Retail",
            "subcategory":"Auto Repair",
            "type":"Services"
        }
    ],
    "sg:phone":"+1 678 380 4354",
    "sg:postcode":"30096",
    "sg:province":"GA",
    "sg:website":"www.justbrakes.com",
    "wof:name":"Just Brakes",
    "wof:placetype":"venue"
},
  "geometry": {"coordinates":[-84.127925,33.943776],"type":"Point"}
}