{
  "type": "Feature",
  "properties": {
    "addr:full":"640 Tidwell Rd Alpharetta GA 30004",
    "addr:housenumber":"640",
    "addr:postcode":"30004",
    "addr:street":"Tidwell Rd",
    "iso:country":"US",
    "sg:address":"640 Tidwell Rd",
    "sg:city":"Alpharetta",
    "sg:classifiers":[
        {
            "category":"Retail",
            "subcategory":"Repair Shop",
            "type":"Services"
        }
    ],
    "sg:phone":"+1 770 475 7276",
    "sg:postcode":"30004",
    "sg:province":"GA",
    "wof:name":"Nolan G Ingram Septic Tank Svc",
    "wof:placetype":"venue"
},
  "geometry": {"coordinates":[-84.25150499999999,34.120508],"type":"Point"}
}