{
  "type": "Feature",
  "properties": {
    "addr:full":"2897 Rosemont Dr NW Lawrenceville GA 30044",
    "addr:housenumber":"2897",
    "addr:postcode":"30044",
    "addr:street":"Rosemont Dr Nw",
    "iso:country":"US",
    "sg:address":"2897 Rosemont Dr NW",
    "sg:city":"Lawrenceville",
    "sg:classifiers":[
        {
            "category":"Professional",
            "subcategory":"Art Services",
            "type":"Services"
        }
    ],
    "sg:phone":"+1 770 921 6120",
    "sg:postcode":"30044",
    "sg:province":"GA",
    "sg:tags":[
        "photo",
        "photography",
        "commercial",
        "studio",
        "portrait"
    ],
    "wof:name":"T G B Enterprises",
    "wof:placetype":"venue"
},
  "geometry": {"coordinates":[-84.074099,33.916201],"type":"Point"}
}