{
  "type": "Feature",
  "properties": {
    "addr:full":"35 Beavers St NE Marietta GA 30060",
    "addr:housenumber":"35",
    "addr:postcode":"30060",
    "addr:street":"Beavers St Ne",
    "iso:country":"US",
    "sg:address":"35 Beavers St NE",
    "sg:city":"Marietta",
    "sg:classifiers":[
        {
            "category":"Retail",
            "subcategory":"Auto Repair",
            "type":"Services"
        }
    ],
    "sg:phone":"+1 770 792 4393",
    "sg:postcode":"30060",
    "sg:province":"GA",
    "wof:name":"Auto Ology",
    "wof:placetype":"venue"
},
  "geometry": {"coordinates":[-84.527496,33.951199],"type":"Point"}
}