{
  "type": "Feature",
  "properties": {
    "addr:full":"603 Veterans Pkwy S Moultrie GA 31788",
    "addr:housenumber":"603",
    "addr:postcode":"31788",
    "addr:street":"Veterans Pkwy S",
    "iso:country":"US",
    "sg:address":"603 Veterans Pkwy S",
    "sg:city":"Moultrie",
    "sg:classifiers":[
        {
            "category":"Restaurant",
            "type":"Food & Drink"
        }
    ],
    "sg:menulink":"http://www.allmenus.com/ga/moultrie/66327-pizza-inn/menu/",
    "sg:phone":"+1 229 985 7402",
    "sg:postcode":"31788",
    "sg:province":"GA",
    "sg:tags":[
        "american",
        "pizza"
    ],
    "wof:name":"Pizza Inn",
    "wof:placetype":"venue"
},
  "geometry": {"coordinates":[-83.76150699999999,31.168308],"type":"Point"}
}