{
  "type": "Feature",
  "properties": {
    "addr:full":"1224 Pine St Augusta GA 30901",
    "addr:housenumber":"1224",
    "addr:postcode":"30901",
    "addr:street":"Pine St",
    "iso:country":"US",
    "sg:address":"1224 Pine St",
    "sg:city":"Augusta",
    "sg:classifiers":[
        {
            "category":"Building & Trades",
            "subcategory":"Landscaping Services",
            "type":"Services"
        }
    ],
    "sg:phone":"+1 706 724 0052",
    "sg:postcode":"30901",
    "sg:province":"GA",
    "sg:tags":[
        "lawn",
        "maintenance",
        "grounds"
    ],
    "wof:name":"Carl's Lawn Care Etc",
    "wof:placetype":"venue"
},
  "geometry": {"coordinates":[-81.97859800000001,33.463484],"type":"Point"}
}