{
  "type": "Feature",
  "properties": {
    "addr:full":"218 Robin Rd Hinesville GA 31313",
    "addr:housenumber":"218",
    "addr:postcode":"31313",
    "addr:street":"Robin Rd",
    "iso:country":"US",
    "sg:address":"218 Robin Rd",
    "sg:city":"Hinesville",
    "sg:classifiers":[
        {
            "category":"Professional",
            "subcategory":"Accounting & Tax Preparation",
            "type":"Services"
        }
    ],
    "sg:phone":"+1 912 369 9592",
    "sg:postcode":"31313",
    "sg:province":"GA",
    "sg:tags":[
        "return"
    ],
    "wof:name":"Tax Express & More",
    "wof:placetype":"venue"
},
  "geometry": {"coordinates":[-81.60468400000001,31.83411],"type":"Point"}
}