{
  "type": "Feature",
  "properties": {
    "addr:full":"1359 Riverstone Pkwy Canton GA 30114",
    "addr:housenumber":"1359",
    "addr:postcode":"30114",
    "addr:street":"Riverstone Pkwy",
    "iso:country":"US",
    "sg:address":"1359 Riverstone Pkwy",
    "sg:city":"Canton",
    "sg:classifiers":[
        {
            "category":"Shopping",
            "subcategory":"Jewelry",
            "type":"Retail Goods"
        }
    ],
    "sg:phone":"+1 770 345 4341",
    "sg:postcode":"30114",
    "sg:province":"GA",
    "sg:tags":[
        "jeweler"
    ],
    "wof:name":"JMA Jewelers",
    "wof:placetype":"venue"
},
  "geometry": {"coordinates":[-84.476726,34.249115],"type":"Point"}
}