{
  "type": "Feature",
  "properties": {
    "addr:full":"3330 Satellite Blvd Duluth GA 30096",
    "addr:housenumber":"3330",
    "addr:postcode":"30096",
    "addr:street":"Satellite Blvd",
    "iso:country":"US",
    "sg:address":"3330 Satellite Blvd",
    "sg:city":"Duluth",
    "sg:phone":"+1 770 476 8132",
    "sg:postcode":"30096",
    "sg:province":"GA",
    "wof:name":"Sun Kissed Tan",
    "wof:placetype":"venue"
},
  "geometry": {"coordinates":[-84.125772,33.964053],"type":"Point"}
}