{
  "type": "Feature",
  "properties": {
    "addr:full":"1815 Hiram Douglasville Hwy Hiram GA 30141",
    "addr:housenumber":"1815",
    "addr:postcode":"30141",
    "addr:street":"Hiram Douglasville Hwy",
    "iso:country":"US",
    "sg:address":"1815 Hiram Douglasville Hwy",
    "sg:city":"Hiram",
    "sg:classifiers":[
        {
            "category":"Education",
            "subcategory":"Library",
            "type":"Public Place"
        }
    ],
    "sg:phone":"+1 770 439 3964",
    "sg:postcode":"30141",
    "sg:province":"GA",
    "wof:name":"Maude P Ragsdale Pub Library",
    "wof:placetype":"venue"
},
  "geometry": {"coordinates":[-84.764667,33.871036],"type":"Point"}
}