{
  "type": "Feature",
  "properties": {
    "iso:country":"US",
    "sg:address":"623 S State St",
    "sg:city":"Lyons",
    "sg:classifiers":[
        {
            "category":"Restaurant",
            "type":"Food & Drink"
        }
    ],
    "sg:phone":"+1 912 526 7156",
    "sg:postcode":"30436",
    "sg:province":"GA",
    "sg:tags":[
        "mexican"
    ],
    "wof:name":"El Rey De Los Tacos",
    "wof:placetype":"venue"
},
  "geometry": {"coordinates":[-82.32627100000001,32.192001],"type":"Point"}
}