{
  "type": "Feature",
  "properties": {
    "addr:full":"122 Francis Dr Macon GA 31216",
    "addr:housenumber":"122",
    "addr:postcode":"31216",
    "addr:street":"Francis Dr",
    "iso:country":"US",
    "sg:address":"122 Francis Dr",
    "sg:city":"Macon",
    "sg:classifiers":[
        {
            "category":"Organizations",
            "subcategory":"Community Association",
            "type":"Services"
        }
    ],
    "sg:phone":"+1 478 784 1993",
    "sg:postcode":"31216",
    "sg:province":"GA",
    "wof:name":"Civitan International",
    "wof:placetype":"venue"
},
  "geometry": {"coordinates":[-83.672578,32.731808],"type":"Point"}
}