{
  "type": "Feature",
  "properties": {
    "iso:country":"US",
    "sg:address":"3273 Bethune Ave",
    "sg:city":"Macon",
    "sg:classifiers":[
        {
            "category":"Organizations",
            "subcategory":"Religious Organization",
            "type":"Services"
        }
    ],
    "sg:phone":"+1 478 746 1934",
    "sg:postcode":"31211",
    "sg:province":"GA",
    "wof:name":"Celestial Praise",
    "wof:placetype":"venue"
},
  "geometry": {"coordinates":[-83.576646,32.870993],"type":"Point"}
}