{
  "type": "Feature",
  "properties": {
    "iso:country":"US",
    "sg:address":"1154 Westchester Dr SW",
    "sg:city":"Lilburn",
    "sg:classifiers":[
        {
            "category":"Professional",
            "subcategory":"Computer Services",
            "type":"Services"
        }
    ],
    "sg:phone":"+1 770 923 3568",
    "sg:postcode":"30047",
    "sg:province":"GA",
    "sg:tags":[
        "programing",
        "custom"
    ],
    "wof:name":"Silas Intrctive Multimedia LLC",
    "wof:placetype":"venue"
},
  "geometry": {"coordinates":[-84.119507,33.850869],"type":"Point"}
}