{
  "type": "Feature",
  "properties": {
    "addr:full":"2364 Dublin Dr Augusta GA 30906",
    "addr:housenumber":"2364",
    "addr:postcode":"30906",
    "addr:street":"Dublin Dr",
    "iso:country":"US",
    "sg:address":"2364 Dublin Dr",
    "sg:city":"Augusta",
    "sg:classifiers":[
        {
            "category":"Professional",
            "subcategory":"Management & Consulting",
            "type":"Services"
        }
    ],
    "sg:phone":"+1 706 790 0085",
    "sg:postcode":"30906",
    "sg:province":"GA",
    "wof:name":"Velma Corp",
    "wof:placetype":"venue"
},
  "geometry": {"coordinates":[-82.096733,33.438363],"type":"Point"}
}