{
  "type": "Feature",
  "properties": {
    "iso:country":"US",
    "sg:address":"1403 Columbia Nitrogen Dr",
    "sg:city":"Augusta",
    "sg:classifiers":[
        {
            "category":"Restaurant",
            "type":"Food & Drink"
        }
    ],
    "sg:phone":"+1 706 826 1700",
    "sg:postcode":"30901",
    "sg:province":"GA",
    "sg:tags":[
        "eating"
    ],
    "wof:name":"Janwiches",
    "wof:placetype":"venue"
},
  "geometry": {"coordinates":[-81.931235,33.44845],"type":"Point"}
}