{
  "type": "Feature",
  "properties": {
    "iso:country":"US",
    "sg:address":"1661 Defoor Ave NW",
    "sg:city":"Atlanta",
    "sg:classifiers":[
        {
            "category":"Professional",
            "subcategory":"Art Services",
            "type":"Services"
        }
    ],
    "sg:phone":"+1 404 350 1700",
    "sg:postcode":"30318",
    "sg:province":"GA",
    "sg:tags":[
        "lithographic",
        "commercial",
        "design",
        "p"
    ],
    "wof:name":"Studio One O One",
    "wof:placetype":"venue"
},
  "geometry": {"coordinates":[-84.418543,33.800978],"type":"Point"}
}