{
  "type": "Feature",
  "properties": {
    "addr:full":"4417 Commerce Cir SW Atlanta GA 30336",
    "addr:housenumber":"4417",
    "addr:postcode":"30336",
    "addr:street":"Commerce Cir Sw",
    "iso:country":"US",
    "sg:address":"4417 Commerce Cir SW",
    "sg:city":"Atlanta",
    "sg:classifiers":[
        {
            "category":"Professional",
            "subcategory":"Advertising",
            "type":"Services"
        }
    ],
    "sg:phone":"+1 404 696 9590",
    "sg:postcode":"30336",
    "sg:province":"GA",
    "wof:name":"IDEALFABRICS.COM",
    "wof:placetype":"venue"
},
  "geometry": {"coordinates":[-84.53295900000001,33.759784],"type":"Point"}
}