{
  "type": "Feature",
  "properties": {
    "iso:country":"US",
    "sg:address":"8090 Nevils Groveland Rd",
    "sg:city":"Statesboro",
    "sg:classifiers":[
        {
            "category":"Food & Beverages",
            "subcategory":"Groceries & Convenience Stores",
            "type":"Retail Goods"
        }
    ],
    "sg:phone":"+1 912 839 3363",
    "sg:postcode":"30458",
    "sg:province":"GA",
    "wof:name":"Ms Dede",
    "wof:placetype":"venue"
},
  "geometry": {"coordinates":[-81.757957,32.286915],"type":"Point"}
}