{
  "type": "Feature",
  "properties": {
    "addr:full":"1050 E Piedmont Rd Marietta GA 30062",
    "addr:housenumber":"1050",
    "addr:postcode":"30062",
    "addr:street":"E Piedmont Rd",
    "iso:country":"US",
    "sg:address":"1050 E Piedmont Rd",
    "sg:city":"Marietta",
    "sg:phone":"+1 678 560 5718",
    "sg:postcode":"30062",
    "sg:province":"GA",
    "sg:website":"http://www.rhyansdesignstudio.com",
    "wof:name":"Rhyans Design Studio LLC",
    "wof:placetype":"venue"
},
  "geometry": {"coordinates":[-84.47982500000001,33.977994],"type":"Point"}
}