{
  "type": "Feature",
  "properties": {
    "addr:full":"211 Chalmers Dr NW Atlanta GA 30318",
    "addr:housenumber":"211",
    "addr:postcode":"30318",
    "addr:street":"Chalmers Dr Nw",
    "iso:country":"US",
    "sg:address":"211 Chalmers Dr NW",
    "sg:city":"Atlanta",
    "sg:classifiers":[
        {
            "category":"Organizations",
            "subcategory":"Religious Organization",
            "type":"Services"
        }
    ],
    "sg:phone":"+1 404 799 0620",
    "sg:postcode":"30318",
    "sg:province":"GA",
    "wof:name":"Emmanuel Southside Community",
    "wof:placetype":"venue"
},
  "geometry": {"coordinates":[-84.477221,33.760509],"type":"Point"}
}