{
  "type": "Feature",
  "properties": {
    "addr:full":"4448 Lane Rd Millen GA 30442",
    "addr:housenumber":"4448",
    "addr:postcode":"30442",
    "addr:street":"Lane Rd",
    "iso:country":"US",
    "sg:address":"4448 Lane Rd",
    "sg:city":"Millen",
    "sg:classifiers":[
        {
            "category":"Building & Trades",
            "subcategory":"Landscaping Services",
            "type":"Services"
        }
    ],
    "sg:phone":"+1 478 982 3541",
    "sg:postcode":"30442",
    "sg:province":"GA",
    "sg:tags":[
        "landscape"
    ],
    "wof:name":"Landing Landscape Inc",
    "wof:placetype":"venue"
},
  "geometry": {"coordinates":[-82.077468,32.72485],"type":"Point"}
}