{
  "type": "Feature",
  "properties": {
    "iso:country":"US",
    "sg:address":"355 Old Oxford Rd",
    "sg:city":"Covington",
    "sg:classifiers":[
        {
            "category":"Utilities",
            "subcategory":"Telephone",
            "type":"Services"
        },
        {
            "category":"Building & Trades",
            "subcategory":"Electrical",
            "type":"Services"
        }
    ],
    "sg:phone":"+1 770 385 1422",
    "sg:postcode":"30014",
    "sg:province":"GA",
    "sg:tags":[
        "cabling",
        "fiber",
        "telecommunication",
        "optic",
        "sales"
    ],
    "wof:name":"Advanced Communications Group",
    "wof:placetype":"venue"
},
  "geometry": {"coordinates":[-83.90080500000001,33.61442],"type":"Point"}
}