{
  "type": "Feature",
  "properties": {
    "addr:full":"2100 Comer Ave Columbus GA 31904",
    "addr:postcode":"2100;31904",
    "addr:street":"Comer Ave",
    "iso:country":"US",
    "sg:address":"2100 Comer Ave",
    "sg:city":"Columbus",
    "sg:classifiers":[
        {
            "category":"Professional",
            "subcategory":"Business Services",
            "type":"Services"
        }
    ],
    "sg:phone":"+1 706 321 6267",
    "sg:postcode":"31904",
    "sg:province":"GA",
    "sg:tags":[
        "medical",
        "administration"
    ],
    "sg:website":"http://www.columbushealth.com",
    "wof:name":"Senior Referral Service",
    "wof:placetype":"venue"
},
  "geometry": {"coordinates":[-84.978897,32.482769],"type":"Point"}
}