{
  "type": "Feature",
  "properties": {
    "addr:full":"543 Lakeland Plz Cumming GA 30040",
    "addr:housenumber":"543",
    "addr:postcode":"30040",
    "addr:street":"Lakeland Plz",
    "iso:country":"US",
    "sg:address":"543 Lakeland Plz",
    "sg:city":"Cumming",
    "sg:classifiers":[
        {
            "category":"Restaurant",
            "type":"Food & Drink"
        }
    ],
    "sg:menulink":"http://www.allmenus.com/ga/cumming/113874-planet-smoothie/menu/",
    "sg:phone":"+1 770 888 8544",
    "sg:postcode":"30040",
    "sg:province":"GA",
    "sg:tags":[
        "smoothy",
        "juice",
        "american"
    ],
    "wof:name":"Planet Smoothie",
    "wof:placetype":"venue"
},
  "geometry": {"coordinates":[-84.144279,34.185354],"type":"Point"}
}