{
  "type": "Feature",
  "properties": {
    "iso:country":"US",
    "sg:address":"3918 Reese Rd",
    "sg:city":"Columbus",
    "sg:classifiers":[
        {
            "category":"Organizations",
            "subcategory":"Religious Organization",
            "type":"Services"
        }
    ],
    "sg:phone":"+1 706 563 3358",
    "sg:postcode":"31907",
    "sg:province":"GA",
    "wof:name":"Russell L Horne Rev",
    "wof:placetype":"venue"
},
  "geometry": {"coordinates":[-84.931209,32.506912],"type":"Point"}
}