{
  "type": "Feature",
  "properties": {
    "addr:full":"1223 Johnson Ferry Rd Marietta GA 30068",
    "addr:housenumber":"1223",
    "addr:postcode":"30068",
    "addr:street":"Johnson Ferry Rd",
    "iso:country":"US",
    "sg:address":"1223 Johnson Ferry Rd",
    "sg:city":"Marietta",
    "sg:classifiers":[
        {
            "category":"Banks & Credit Unions",
            "subcategory":"Bank",
            "type":"Services"
        }
    ],
    "sg:phone":"+1 770 973 5494",
    "sg:postcode":"30068",
    "sg:province":"GA",
    "wof:name":"Fidelity National Bank",
    "wof:placetype":"venue"
},
  "geometry": {"coordinates":[-84.422302,33.9795],"type":"Point"}
}