{
  "type": "Feature",
  "properties": {
    "addr:full":"1061 Lee St SW Atlanta GA 30310",
    "addr:housenumber":"1061",
    "addr:postcode":"30310",
    "addr:street":"Lee St Sw",
    "iso:country":"US",
    "sg:address":"1061 Lee St SW",
    "sg:city":"Atlanta",
    "sg:classifiers":[
        {
            "category":"Food & Beverages",
            "subcategory":"Liquor & Beverages",
            "type":"Retail Goods"
        }
    ],
    "sg:phone":"+1 404 758 2529",
    "sg:postcode":"30310",
    "sg:province":"GA",
    "sg:tags":[
        "beer",
        "spirit",
        "wine"
    ],
    "wof:name":"Li Package Store",
    "wof:placetype":"venue"
},
  "geometry": {"coordinates":[-84.419403,33.725399],"type":"Point"}
}