{
  "type": "Feature",
  "properties": {
    "iso:country":"US",
    "sg:address":"2050 Buford Hwy",
    "sg:city":"Buford",
    "sg:classifiers":[
        {
            "category":"Health Services",
            "subcategory":"Doctor",
            "type":"Services"
        }
    ],
    "sg:phone":"+1 770 614 7366",
    "sg:postcode":"30518",
    "sg:province":"GA",
    "sg:website":"www.childrensmedicine.net",
    "wof:name":"Marlowe Monica MD",
    "wof:placetype":"venue"
},
  "geometry": {"coordinates":[-83.999702,34.109798],"type":"Point"}
}