{
  "type": "Feature",
  "properties": {
    "iso:country":"US",
    "sg:address":"107 Ladell Rd SE",
    "sg:city":"Rome",
    "sg:classifiers":[
        {
            "category":"Building & Trades",
            "subcategory":"Landscaping Services",
            "type":"Services"
        }
    ],
    "sg:phone":"+1 706 378 9512",
    "sg:postcode":"30161",
    "sg:province":"GA",
    "wof:name":"Terhunes Tree Service",
    "wof:placetype":"venue"
},
  "geometry": {"coordinates":[-85.125191,34.192209],"type":"Point"}
}