{
  "type": "Feature",
  "properties": {
    "addr:full":"529 Laney Walker Blvd Exd Augusta GA 30901",
    "addr:housenumber":"529",
    "addr:postcode":"30901",
    "addr:street":"Laney Walker Blvd Exd",
    "iso:country":"US",
    "sg:address":"529 Laney Walker Blvd Exd",
    "sg:city":"Augusta",
    "sg:classifiers":[
        {
            "category":"Retail",
            "subcategory":"Laundry & Dry Cleaning",
            "type":"Services"
        }
    ],
    "sg:phone":"+1 706 724 0748",
    "sg:postcode":"30901",
    "sg:province":"GA",
    "sg:tags":[
        "uniform",
        "supply"
    ],
    "wof:name":"Cintas The Uniform People",
    "wof:placetype":"venue"
},
  "geometry": {"coordinates":[-81.943772,33.455991],"type":"Point"}
}