{
  "type": "Feature",
  "properties": {
    "addr:full":"820 Love Ave Tifton GA 31794",
    "addr:housenumber":"820",
    "addr:postcode":"31794",
    "addr:street":"Love Ave",
    "iso:country":"US",
    "sg:address":"820 Love Ave",
    "sg:city":"Tifton",
    "sg:classifiers":[
        {
            "category":"Health Services",
            "subcategory":"Doctor",
            "type":"Services"
        }
    ],
    "sg:phone":"+1 229 382 3720",
    "sg:postcode":"31794",
    "sg:province":"GA",
    "sg:tags":[
        "physician",
        "surgeon",
        "medical"
    ],
    "wof:name":"Allergy Asthma & Sinus Clinic",
    "wof:placetype":"venue"
},
  "geometry": {"coordinates":[-83.506771,31.46022],"type":"Point"}
}