{
  "type": "Feature",
  "properties": {
    "iso:country":"US",
    "sg:address":"451 Stamp Creek Rd NE",
    "sg:city":"White",
    "sg:classifiers":[
        {
            "category":"Organizations",
            "subcategory":"Religious Organization",
            "type":"Services"
        }
    ],
    "sg:phone":"+1 770 383 3444",
    "sg:postcode":"30184",
    "sg:province":"GA",
    "wof:name":"Stamp Creek Baptist Church",
    "wof:placetype":"venue"
},
  "geometry": {"coordinates":[-84.68087800000001,34.250367],"type":"Point"}
}