{
  "type": "Feature",
  "properties": {
    "iso:country":"US",
    "sg:address":"5470 Oakbrook Pkwy",
    "sg:city":"Norcross",
    "sg:classifiers":[
        {
            "category":"Building & Trades",
            "subcategory":"Construction",
            "type":"Services"
        }
    ],
    "sg:phone":"+1 770 441 9696",
    "sg:postcode":"30093",
    "sg:province":"GA",
    "sg:tags":[
        "layer",
        "contractor",
        "laying",
        "floor",
        "carpet"
    ],
    "wof:name":"Bryant Carpet Installations",
    "wof:placetype":"venue"
},
  "geometry": {"coordinates":[-84.18705300000001,33.919187],"type":"Point"}
}