{
  "type": "Feature",
  "properties": {
    "iso:country":"US",
    "sg:address":"115 Franklin Blvd",
    "sg:city":"Fort Valley",
    "sg:classifiers":[
        {
            "category":"Professional",
            "type":"Services"
        }
    ],
    "sg:phone":"+1 478 825 9289",
    "sg:postcode":"31030",
    "sg:province":"GA",
    "wof:name":"Marion Fleming",
    "wof:placetype":"venue"
},
  "geometry": {"coordinates":[-83.91041,32.556317],"type":"Point"}
}