{
  "type": "Feature",
  "properties": {
    "iso:country":"US",
    "sg:address":"960 Johnson Ferry Rd",
    "sg:city":"Atlanta",
    "sg:classifiers":[
        {
            "category":"Health Services",
            "subcategory":"Doctor",
            "type":"Services"
        }
    ],
    "sg:phone":"+1 404 851 9909",
    "sg:postcode":"30342",
    "sg:province":"GA",
    "sg:tags":[
        "medical"
    ],
    "wof:name":"Sandy Northlake Sprngs Ob/Gyns",
    "wof:placetype":"venue"
},
  "geometry": {"coordinates":[-84.355992,33.907832],"type":"Point"}
}