{
  "type": "Feature",
  "properties": {
    "iso:country":"US",
    "sg:address":"2700 Town Center Dr NW",
    "sg:city":"Kennesaw",
    "sg:classifiers":[
        {
            "category":"Restaurant",
            "type":"Food & Drink"
        }
    ],
    "sg:menulink":"http://www.allmenus.com/ga/acworth-kennesaw/141348-fuji-hana--thai-peppers/menu/",
    "sg:phone":"+1 770 419 9500",
    "sg:postcode":"30144",
    "sg:province":"GA",
    "sg:tags":[
        "thai",
        "asian"
    ],
    "wof:name":"Fuji Hana & Thai Peppers",
    "wof:placetype":"venue"
},
  "geometry": {"coordinates":[-84.565247,34.013007],"type":"Point"}
}