{
  "type": "Feature",
  "properties": {
    "addr:full":"4645 Jettridge Drive NW Atlanta GA 30327",
    "addr:housenumber":"4645",
    "addr:postcode":"30327",
    "addr:street":"Jettridge Drive Nw",
    "iso:country":"US",
    "sg:address":"4645 Jettridge Drive NW",
    "sg:city":"Atlanta",
    "sg:classifiers":[
        {
            "category":"Shopping",
            "subcategory":"Clothing, Apparel, & Fashions",
            "type":"Retail Goods"
        }
    ],
    "sg:phone":"+1 404 255 0155",
    "sg:postcode":"30327",
    "sg:province":"GA",
    "sg:tags":[
        "accessory",
        "clothing",
        "women's"
    ],
    "wof:name":"Be Tees",
    "wof:placetype":"venue"
},
  "geometry": {"coordinates":[-84.406436,33.881454],"type":"Point"}
}