{
  "type": "Feature",
  "properties": {
    "addr:full":"875 Oak Rd Lawrenceville GA 30044",
    "addr:housenumber":"875",
    "addr:postcode":"30044",
    "addr:street":"Oak Rd",
    "iso:country":"US",
    "sg:address":"875 Oak Rd",
    "sg:city":"Lawrenceville",
    "sg:classifiers":[
        {
            "category":"Education",
            "subcategory":"Dance Studio",
            "type":"Public Place"
        }
    ],
    "sg:phone":"+1 770 978 3557",
    "sg:postcode":"30044",
    "sg:province":"GA",
    "sg:tags":[
        "instruction",
        "dancing"
    ],
    "wof:name":"Atlanta Dance Works",
    "wof:placetype":"venue"
},
  "geometry": {"coordinates":[-84.06065599999999,33.887672],"type":"Point"}
}