{
  "type": "Feature",
  "properties": {
    "iso:country":"US",
    "sg:address":"90 Hily Ave",
    "sg:city":"Savannah",
    "sg:classifiers":[
        {
            "category":"Professional",
            "subcategory":"Business Services",
            "type":"Services"
        }
    ],
    "sg:phone":"+1 912 354 4724",
    "sg:postcode":"31406",
    "sg:province":"GA",
    "wof:name":"C&C Home Inspection",
    "wof:placetype":"venue"
},
  "geometry": {"coordinates":[-81.066948,31.996565],"type":"Point"}
}