{
  "type": "Feature",
  "properties": {
    "iso:country":"US",
    "sg:address":"5675 Roswell Rd",
    "sg:city":"Atlanta",
    "sg:classifiers":[
        {
            "category":"Education",
            "subcategory":"Special Training",
            "type":"Public Place"
        }
    ],
    "sg:phone":"+1 404 250 9480",
    "sg:postcode":"30342",
    "sg:province":"GA",
    "sg:tags":[
        "self",
        "motivational",
        "improvement"
    ],
    "wof:name":"Alex-Zan",
    "wof:placetype":"venue"
},
  "geometry": {"coordinates":[-84.37875,33.909787],"type":"Point"}
}