{
  "type": "Feature",
  "properties": {
    "iso:country":"US",
    "sg:address":"1622 Taylor Oaks Ridge",
    "sg:city":"Lawrenceville",
    "sg:classifiers":[
        {
            "category":"Professional",
            "subcategory":"Business Services",
            "type":"Services"
        }
    ],
    "sg:phone":"+1 770 339 9546",
    "sg:postcode":"30043",
    "sg:province":"GA",
    "wof:name":"Jlr Enterprise",
    "wof:placetype":"venue"
},
  "geometry": {"coordinates":[-83.990555,34.01193],"type":"Point"}
}