{
  "type": "Feature",
  "properties": {
    "iso:country":"US",
    "sg:address":"411 21st St",
    "sg:city":"Columbus",
    "sg:classifiers":[
        {
            "category":"Professional",
            "subcategory":"Lawyer & Legal Services",
            "type":"Services"
        }
    ],
    "sg:phone":"+1 706 653 7151",
    "sg:postcode":"31904",
    "sg:province":"GA",
    "sg:tags":[
        "divorce",
        "attorney",
        "criminal",
        "family",
        "law"
    ],
    "wof:name":"Phillips , Michael Scott - Phillips & Se",
    "wof:placetype":"venue"
},
  "geometry": {"coordinates":[-84.986784,32.484375],"type":"Point"}
}