{
  "type": "Feature",
  "properties": {
    "iso:country":"US",
    "sg:address":"2777 Adair Trl",
    "sg:city":"Dacula",
    "sg:classifiers":[
        {
            "category":"Retail",
            "subcategory":"Auto Repair",
            "type":"Services"
        }
    ],
    "sg:phone":"+1 770 277 7956",
    "sg:postcode":"30019",
    "sg:province":"GA",
    "wof:name":"Mobile Master Tech",
    "wof:placetype":"venue"
},
  "geometry": {"coordinates":[-83.921594,34.034697],"type":"Point"}
}