{
  "type": "Feature",
  "properties": {
    "addr:full":"4675 Granite Dr Tucker GA 30084",
    "addr:housenumber":"4675",
    "addr:postcode":"30084",
    "addr:street":"Granite Dr",
    "iso:country":"US",
    "sg:address":"4675 Granite Dr",
    "sg:city":"Tucker",
    "sg:classifiers":[
        {
            "category":"Building & Trades",
            "subcategory":"Locksmith",
            "type":"Services"
        }
    ],
    "sg:phone":"+1 888 505 6124",
    "sg:postcode":"30084",
    "sg:province":"GA",
    "sg:tags":[
        "key"
    ],
    "wof:name":"A 1 Lock & Locksmith",
    "wof:placetype":"venue"
},
  "geometry": {"coordinates":[-84.197097,33.845174],"type":"Point"}
}