{
  "type": "Feature",
  "properties": {
    "addr:full":"100 E Callahan St Rome GA 30161",
    "addr:housenumber":"100",
    "addr:postcode":"ga 30161",
    "addr:street":"E Callahan St",
    "iso:country":"US",
    "sg:address":"100 E Callahan St",
    "sg:city":"Rome",
    "sg:classifiers":[
        {
            "category":"Professional",
            "subcategory":"Business Services",
            "type":"Services"
        }
    ],
    "sg:phone":"+1 706 232 3631",
    "sg:postcode":"30161",
    "sg:province":"GA",
    "sg:tags":[
        "auction",
        "real estate"
    ],
    "wof:name":"Re/Max Acution Group Georgia",
    "wof:placetype":"venue"
},
  "geometry": {"coordinates":[-85.15464,34.266219],"type":"Point"}
}