{
  "type": "Feature",
  "properties": {
    "iso:country":"US",
    "sg:address":"30 E Andrews Drive NW",
    "sg:city":"Atlanta",
    "sg:classifiers":[
        {
            "category":"Shopping",
            "subcategory":"Clothing, Apparel, & Fashions",
            "type":"Retail Goods"
        }
    ],
    "sg:phone":"+1 404 233 6207",
    "sg:postcode":"30305",
    "sg:province":"GA",
    "sg:website":"www.londontradingcompany.com",
    "wof:name":"London Trading Company",
    "wof:placetype":"venue"
},
  "geometry": {"coordinates":[-84.37996099999999,33.843696],"type":"Point"}
}