{
  "type": "Feature",
  "properties": {
    "iso:country":"US",
    "sg:address":"1809 Powell Rd",
    "sg:city":"Augusta",
    "sg:classifiers":[
        {
            "category":"Shopping",
            "subcategory":"Clothing, Apparel, & Fashions",
            "type":"Retail Goods"
        }
    ],
    "sg:phone":"+1 706 267 7986",
    "sg:postcode":"30909",
    "sg:province":"GA",
    "wof:name":"Men In Motion Mim Serv",
    "wof:placetype":"venue"
},
  "geometry": {"coordinates":[-82.138201,33.455127],"type":"Point"}
}