{
  "type": "Feature",
  "properties": {
    "iso:country":"US",
    "sg:address":"4090 Johns Creek Pkwy Ste C",
    "sg:city":"Suwanee",
    "sg:classifiers":[
        {
            "category":"Personal",
            "subcategory":"Beauty Salon",
            "type":"Services"
        },
        {
            "category":"Personal",
            "subcategory":"Tanning Parlor",
            "type":"Services"
        }
    ],
    "sg:phone":"+1 770 232 9852",
    "sg:postcode":"30024",
    "sg:province":"GA",
    "sg:tags":[
        "hair"
    ],
    "sg:website":"www.solarsalonandspa.com/",
    "wof:name":"Solar Salon and Spa",
    "wof:placetype":"venue"
},
  "geometry": {"coordinates":[-84.16538799999999,34.070578],"type":"Point"}
}