{
  "type": "Feature",
  "properties": {
    "addr:full":"1711 Canberra Dr Stone Mountain GA 30088",
    "addr:housenumber":"1711",
    "addr:postcode":"30088",
    "addr:street":"Canberra Dr",
    "iso:country":"US",
    "sg:address":"1711 Canberra Dr",
    "sg:city":"Stone Mountain",
    "sg:classifiers":[
        {
            "category":"Banks & Credit Unions",
            "subcategory":"Bank",
            "type":"Services"
        }
    ],
    "sg:phone":"+1 770 593 2645",
    "sg:postcode":"30088",
    "sg:province":"GA",
    "sg:tags":[
        "personal",
        "institution"
    ],
    "wof:name":"Household Helpers Inc",
    "wof:placetype":"venue"
},
  "geometry": {"coordinates":[-84.19216400000001,33.741522],"type":"Point"}
}