{
  "type": "Feature",
  "properties": {
    "addr:full":"5075 Peachtree Pkwy Ste 106 Norcross GA 30092",
    "addr:housenumber":"5075",
    "addr:postcode":"30092",
    "addr:street":"Peachtree Pkwy Ste 106",
    "iso:country":"US",
    "sg:address":"5075 Peachtree Pkwy Ste 106",
    "sg:city":"Norcross",
    "sg:classifiers":[
        {
            "category":"Community Center",
            "type":"Public Place"
        }
    ],
    "sg:phone":"+1 678 282 0051",
    "sg:postcode":"30092",
    "sg:province":"GA",
    "sg:tags":[
        "medical"
    ],
    "wof:name":"Suburban Medical Center",
    "wof:placetype":"venue"
},
  "geometry": {"coordinates":[-84.21309599999999,33.984781],"type":"Point"}
}