{
  "type": "Feature",
  "properties": {
    "iso:country":"US",
    "sg:address":"1346 Panhandle Way",
    "sg:city":"Hampton",
    "sg:classifiers":[
        {
            "category":"Professional",
            "subcategory":"Management & Consulting",
            "type":"Services"
        }
    ],
    "sg:phone":"+1 770 354 9341",
    "sg:postcode":"30228",
    "sg:province":"GA",
    "sg:tags":[
        "consultant"
    ],
    "wof:name":"Williams Consulting Solutions",
    "wof:placetype":"venue"
},
  "geometry": {"coordinates":[-84.34855399999999,33.438168],"type":"Point"}
}