{
  "type": "Feature",
  "properties": {
    "addr:full":"2713 Cherry Blossom Cir SE Conyers GA 30013",
    "addr:housenumber":"2713",
    "addr:postcode":"30013",
    "addr:street":"Cherry Blossom Cir Se",
    "iso:country":"US",
    "sg:address":"2713 Cherry Blossom Cir SE",
    "sg:city":"Conyers",
    "sg:classifiers":[
        {
            "category":"Social Services",
            "subcategory":"Job Training",
            "type":"Services"
        }
    ],
    "sg:phone":"+1 678 230 9873",
    "sg:postcode":"30013",
    "sg:province":"GA",
    "sg:tags":[
        "employment"
    ],
    "wof:name":"Transition Solutions",
    "wof:placetype":"venue"
},
  "geometry": {"coordinates":[-83.987247,33.625745],"type":"Point"}
}