{
  "type": "Feature",
  "properties": {
    "addr:full":"1259 Oostanaula Bend Rd SW Calhoun GA 30701",
    "addr:housenumber":"1259",
    "addr:postcode":"30701",
    "addr:street":"Oostanaula Bend Rd Sw",
    "iso:country":"US",
    "sg:address":"1259 Oostanaula Bend Rd SW",
    "sg:city":"Calhoun",
    "sg:classifiers":[
        {
            "category":"Professional",
            "subcategory":"Accounting & Tax Preparation",
            "type":"Services"
        }
    ],
    "sg:phone":"+1 706 629 0017",
    "sg:postcode":"30701",
    "sg:province":"GA",
    "sg:tags":[
        "return"
    ],
    "wof:name":"Brenda/Brake-Ms",
    "wof:placetype":"venue"
},
  "geometry": {"coordinates":[-85.01489599999999,34.478621],"type":"Point"}
}