{
  "type": "Feature",
  "properties": {
    "addr:full":"327 W Savannah Ave Valdosta GA 31601",
    "addr:housenumber":"327",
    "addr:postcode":"31601",
    "addr:street":"W Savannah Ave",
    "iso:country":"US",
    "sg:address":"327 W Savannah Ave",
    "sg:city":"Valdosta",
    "sg:classifiers":[
        {
            "category":"Government",
            "subcategory":"Office",
            "type":"Public Place"
        }
    ],
    "sg:phone":"+1 229 333 5277",
    "sg:postcode":"31601",
    "sg:province":"GA",
    "sg:website":"www.sgrdc.com",
    "wof:name":"Regional Development Ctr",
    "wof:placetype":"venue"
},
  "geometry": {"coordinates":[-83.28148299999999,30.828471],"type":"Point"}
}