{
  "type": "Feature",
  "properties": {
    "iso:country":"US",
    "sg:address":"190 N Macon St",
    "sg:city":"Jesup",
    "sg:classifiers":[
        {
            "category":"Personal",
            "subcategory":"Beauty Salon",
            "type":"Services"
        }
    ],
    "sg:phone":"+1 912 530 6787",
    "sg:postcode":"31545",
    "sg:province":"GA",
    "sg:tags":[
        "manicuring"
    ],
    "wof:name":"Nail's By Julia",
    "wof:placetype":"venue"
},
  "geometry": {"coordinates":[-81.883116,31.607091],"type":"Point"}
}