{
  "type": "Feature",
  "properties": {
    "addr:full":"3390 N Lumpkin Rd # 1302 Columbus GA 31903",
    "addr:housenumber":"3390;1302",
    "addr:postcode":"31903",
    "addr:street":"N Lumpkin Rd #",
    "iso:country":"US",
    "sg:address":"3390 N Lumpkin Rd # 1302",
    "sg:city":"Columbus",
    "sg:classifiers":[
        {
            "category":"Taxi",
            "type":"Transportation"
        }
    ],
    "sg:phone":"+1 706 393 6722",
    "sg:postcode":"31903",
    "sg:province":"GA",
    "wof:name":"Gold Star Taxi",
    "wof:placetype":"venue"
},
  "geometry": {"coordinates":[-84.95337600000001,32.434557],"type":"Point"}
}