{
  "type": "Feature",
  "properties": {
    "iso:country":"US",
    "sg:address":"2962 Grandview Ave NE",
    "sg:city":"Atlanta",
    "sg:classifiers":[
        {
            "category":"Personal",
            "subcategory":"Beauty Salon",
            "type":"Services"
        }
    ],
    "sg:phone":"+1 404 261 2740",
    "sg:postcode":"30305",
    "sg:province":"GA",
    "sg:tags":[
        "shop"
    ],
    "wof:name":"Martin Rosie",
    "wof:placetype":"venue"
},
  "geometry": {"coordinates":[-84.37643,33.835977],"type":"Point"}
}