{
  "type": "Feature",
  "properties": {
    "addr:full":"489 Butler Dairy Rd Summerville GA 30747",
    "addr:housenumber":"489",
    "addr:postcode":"30747",
    "addr:street":"Butler Dairy Rd",
    "iso:country":"US",
    "sg:address":"489 Butler Dairy Rd",
    "sg:city":"Summerville",
    "sg:classifiers":[
        {
            "category":"Manufacturing",
            "subcategory":"Lumber",
            "type":"Manufacturing & Wholesale Goods"
        }
    ],
    "sg:phone":"+1 706 822 9961",
    "sg:postcode":"30747",
    "sg:province":"GA",
    "sg:tags":[
        "company",
        "logging"
    ],
    "wof:name":"Triple J Logging Inc",
    "wof:placetype":"venue"
},
  "geometry": {"coordinates":[-85.306859,34.479211],"type":"Point"}
}