{
  "type": "Feature",
  "properties": {
    "addr:full":"205 Christina Ct Peachtree City GA 30269",
    "addr:housenumber":"205",
    "addr:postcode":"30269",
    "addr:street":"Christina Ct",
    "iso:country":"US",
    "sg:address":"205 Christina Ct",
    "sg:city":"Peachtree City",
    "sg:classifiers":[
        {
            "category":"Recreation",
            "type":"Entertainment"
        }
    ],
    "sg:phone":"+1 770 631 0125",
    "sg:postcode":"30269",
    "sg:province":"GA",
    "sg:tags":[
        "amusement"
    ],
    "wof:name":"D Er Motor Sports",
    "wof:placetype":"venue"
},
  "geometry": {"coordinates":[-84.601372,33.416493],"type":"Point"}
}