{
  "type": "Feature",
  "properties": {
    "iso:country":"US",
    "sg:address":"6027 New Peachtree Rd",
    "sg:city":"Atlanta",
    "sg:classifiers":[
        {
            "category":"Retail",
            "subcategory":"Auto Repair",
            "type":"Services"
        }
    ],
    "sg:phone":"+1 770 458 7881",
    "sg:postcode":"30340",
    "sg:province":"GA",
    "sg:tags":[
        "body",
        "painting",
        "repairing",
        "automobile"
    ],
    "wof:name":"Ba's Minor Auto Body",
    "wof:placetype":"venue"
},
  "geometry": {"coordinates":[-84.27909099999999,33.902875],"type":"Point"}
}