{
  "type": "Feature",
  "properties": {
    "addr:full":"3445 Stratford Rd NE Atlanta GA 30326",
    "addr:housenumber":"3445",
    "addr:postcode":"30326",
    "addr:street":"Stratford Rd Ne",
    "iso:country":"US",
    "sg:address":"3445 Stratford Rd NE",
    "sg:city":"Atlanta",
    "sg:classifiers":[
        {
            "category":"Professional",
            "type":"Services"
        }
    ],
    "sg:phone":"+1 404 252 2087",
    "sg:postcode":"30326",
    "sg:province":"GA",
    "wof:name":"Hysm Research LLC",
    "wof:placetype":"venue"
},
  "geometry": {"coordinates":[-84.36687499999999,33.849414],"type":"Point"}
}