{
  "type": "Feature",
  "properties": {
    "addr:full":"4296 Brandywine St SE Conyers GA 30013",
    "addr:housenumber":"4296",
    "addr:postcode":"30013",
    "addr:street":"Brandywine St Se",
    "iso:country":"US",
    "sg:address":"4296 Brandywine St SE",
    "sg:city":"Conyers",
    "sg:classifiers":[
        {
            "category":"Building & Trades",
            "subcategory":"Construction",
            "type":"Services"
        }
    ],
    "sg:phone":"+1 770 922 2545",
    "sg:postcode":"30013",
    "sg:province":"GA",
    "sg:tags":[
        "repairing",
        "house",
        "remodeling",
        "contractor"
    ],
    "wof:name":"Edwards Enterprises Inc",
    "wof:placetype":"venue"
},
  "geometry": {"coordinates":[-84.00369499999999,33.572401],"type":"Point"}
}