{
  "type": "Feature",
  "properties": {
    "iso:country":"US",
    "sg:address":"3545 Cobblestone Way",
    "sg:city":"Loganville",
    "sg:classifiers":[
        {
            "category":"Building & Trades",
            "subcategory":"Construction",
            "type":"Services"
        }
    ],
    "sg:phone":"+1 770 554 0156",
    "sg:postcode":"30052",
    "sg:province":"GA",
    "sg:tags":[
        "house",
        "residential"
    ],
    "wof:name":"Quality Care Construction",
    "wof:placetype":"venue"
},
  "geometry": {"coordinates":[-83.928032,33.803137],"type":"Point"}
}