{
  "type": "Feature",
  "properties": {
    "iso:country":"US",
    "sg:address":"6890 Cedar Mountain Rd",
    "sg:city":"Douglasville",
    "sg:classifiers":[
        {
            "category":"Professional",
            "subcategory":"Business Services",
            "type":"Services"
        }
    ],
    "sg:phone":"+1 770 949 1798",
    "sg:postcode":"30134",
    "sg:province":"GA",
    "wof:name":"Home Inspections",
    "wof:placetype":"venue"
},
  "geometry": {"coordinates":[-84.80480799999999,33.756967],"type":"Point"}
}