{
  "type": "Feature",
  "properties": {
    "addr:full":"1955 1st Dr Marietta GA 30063",
    "addr:housenumber":"1955",
    "addr:postcode":"30063",
    "addr:street":"1St Dr",
    "iso:country":"US",
    "sg:address":"1955 1st Dr",
    "sg:city":"Marietta",
    "sg:classifiers":[
        {
            "category":"Building & Trades",
            "subcategory":"Equipment Rental",
            "type":"Services"
        }
    ],
    "sg:phone":"+1 770 565 7680",
    "sg:postcode":"30063",
    "sg:province":"GA",
    "sg:tags":[
        "furniture"
    ],
    "wof:name":"Performance Capital Of Atlanta",
    "wof:placetype":"venue"
},
  "geometry": {"coordinates":[-84.494696,34.010638],"type":"Point"}
}