{
  "type": "Feature",
  "properties": {
    "iso:country":"US",
    "sg:address":"2150 Boggs Rd",
    "sg:city":"Duluth",
    "sg:classifiers":[
        {
            "category":"Wholesale",
            "subcategory":"Auto Parts",
            "type":"Manufacturing & Wholesale Goods"
        }
    ],
    "sg:phone":"+1 678 475 6666",
    "sg:postcode":"30096",
    "sg:province":"GA",
    "wof:name":"Parts Depot Inc",
    "wof:placetype":"venue"
},
  "geometry": {"coordinates":[-84.099523,33.972858],"type":"Point"}
}