{
  "type": "Feature",
  "properties": {
    "addr:full":"9346 US Hwy 1 Louisville GA 30434",
    "addr:housenumber":"9346",
    "addr:postcode":"30434",
    "addr:street":"Us Hwy 1",
    "iso:country":"US",
    "sg:address":"9346 US Hwy 1",
    "sg:city":"Louisville",
    "sg:classifiers":[
        {
            "category":"Organizations",
            "subcategory":"Religious Organization",
            "type":"Services"
        }
    ],
    "sg:phone":"+1 706 547 0561",
    "sg:postcode":"30434",
    "sg:province":"GA",
    "sg:tags":[
        "church"
    ],
    "wof:name":"Trinity Baptist Church",
    "wof:placetype":"venue"
},
  "geometry": {"coordinates":[-82.4034,33.121289],"type":"Point"}
}