{
  "type": "Feature",
  "properties": {
    "iso:country":"US",
    "sg:address":"327 Dahlonega Rd",
    "sg:city":"Cumming",
    "sg:classifiers":[
        {
            "category":"Wholesale",
            "subcategory":"Durable Goods & Equipment",
            "type":"Manufacturing & Wholesale Goods"
        }
    ],
    "sg:phone":"+1 770 887 5757",
    "sg:postcode":"30040",
    "sg:province":"GA",
    "sg:tags":[
        "importer"
    ],
    "wof:name":"Mccrary & Assoc",
    "wof:placetype":"venue"
},
  "geometry": {"coordinates":[-84.135243,34.216043],"type":"Point"}
}