{
  "type": "Feature",
  "properties": {
    "iso:country":"US",
    "sg:address":"3260 Lakewood Ave",
    "sg:city":"Atlanta",
    "sg:classifiers":[
        {
            "category":"Railroad",
            "type":"Transportation"
        }
    ],
    "sg:phone":"+1 404 753 3336",
    "sg:postcode":"30344",
    "sg:province":"GA",
    "sg:tags":[
        "car",
        "leasing"
    ],
    "wof:name":"Ats Aquistion",
    "wof:placetype":"venue"
},
  "geometry": {"coordinates":[-84.42424699999999,33.697279],"type":"Point"}
}