{
  "type": "Feature",
  "properties": {
    "iso:country":"US",
    "sg:address":"4830 Flat Shoals Pkwy",
    "sg:city":"Decatur",
    "sg:classifiers":[
        {
            "category":"Professional",
            "subcategory":"Secretarial Services",
            "type":"Services"
        }
    ],
    "sg:phone":"+1 770 322 7744",
    "sg:postcode":"30034",
    "sg:province":"GA",
    "sg:tags":[
        "resume"
    ],
    "wof:name":"Resume Authority",
    "wof:placetype":"venue"
},
  "geometry": {"coordinates":[-84.23333,33.683292],"type":"Point"}
}