{
  "type": "Feature",
  "properties": {
    "addr:full":"14230 Phillips Cir Alpharetta GA 30004",
    "addr:housenumber":"14230",
    "addr:postcode":"30004",
    "addr:street":"Phillips Cir",
    "iso:country":"US",
    "sg:address":"14230 Phillips Cir",
    "sg:city":"Alpharetta",
    "sg:classifiers":[
        {
            "category":"Professional",
            "type":"Services"
        }
    ],
    "sg:phone":"+1 678 319 0809",
    "sg:postcode":"30004",
    "sg:province":"GA",
    "wof:name":"Valls & Vaughn",
    "wof:placetype":"venue"
},
  "geometry": {"coordinates":[-84.323358,34.129911],"type":"Point"}
}