{
  "type": "Feature",
  "properties": {
    "addr:full":"2170 Piedmont Rd NE Atlanta GA 30324",
    "addr:housenumber":"2170",
    "addr:postcode":"30324",
    "addr:street":"Piedmont Rd Ne",
    "iso:country":"US",
    "sg:address":"2170 Piedmont Rd NE",
    "sg:city":"Atlanta",
    "sg:classifiers":[
        {
            "category":"Professional",
            "subcategory":"Management & Consulting",
            "type":"Services"
        }
    ],
    "sg:phone":"+1 404 888 2750",
    "sg:postcode":"30324",
    "sg:province":"GA",
    "wof:name":"Rollins Investments Fund",
    "wof:placetype":"venue"
},
  "geometry": {"coordinates":[-84.36685,33.816672],"type":"Point"}
}