{
  "type": "Feature",
  "properties": {
    "addr:full":"5764 Hobbs Rd Dearing GA 30808",
    "addr:housenumber":"5764",
    "addr:postcode":"30808",
    "addr:street":"Hobbs Rd",
    "iso:country":"US",
    "sg:address":"5764 Hobbs Rd",
    "sg:city":"Dearing",
    "sg:classifiers":[
        {
            "category":"Professional",
            "subcategory":"Management & Consulting",
            "type":"Services"
        }
    ],
    "sg:phone":"+1 706 595 1501",
    "sg:postcode":"30808",
    "sg:province":"GA",
    "wof:name":"Merry Marketing",
    "wof:placetype":"venue"
},
  "geometry": {"coordinates":[-82.38079,33.345863],"type":"Point"}
}