{
  "type": "Feature",
  "properties": {
    "addr:full":"1240 Gaddis Rd Canton GA 30115",
    "addr:housenumber":"1240",
    "addr:postcode":"30115",
    "addr:street":"Gaddis Rd",
    "iso:country":"US",
    "sg:address":"1240 Gaddis Rd",
    "sg:city":"Canton",
    "sg:classifiers":[
        {
            "category":"Home & Garden",
            "subcategory":"Hardware",
            "type":"Retail Goods"
        }
    ],
    "sg:phone":"+1 770 664 8260",
    "sg:postcode":"30115",
    "sg:province":"GA",
    "sg:tags":[
        "water",
        "equipment",
        "filtration",
        "purification"
    ],
    "sg:website":"http://www.pollutioncontrolequipment.com",
    "wof:name":"Pollution Control Equipment Inc",
    "wof:placetype":"venue"
},
  "geometry": {"coordinates":[-84.354984,34.222687],"type":"Point"}
}