{
  "type": "Feature",
  "properties": {
    "addr:full":"2229 Bemiss Rd Valdosta GA 31602",
    "addr:housenumber":"2229",
    "addr:postcode":"31602",
    "addr:street":"Bemiss Rd",
    "iso:country":"US",
    "sg:address":"2229 Bemiss Rd",
    "sg:city":"Valdosta",
    "sg:classifiers":[
        {
            "category":"Insurance",
            "subcategory":"Insurance Agent",
            "type":"Services"
        }
    ],
    "sg:phone":"+1 229 249 9494",
    "sg:postcode":"31602",
    "sg:province":"GA",
    "wof:name":"James B Joiner Insurance",
    "wof:placetype":"venue"
},
  "geometry": {"coordinates":[-83.28023,30.863387],"type":"Point"}
}