{
  "type": "Feature",
  "properties": {
    "addr:full":"6719 Skidaway Rd Savannah GA 31406",
    "addr:housenumber":"6719",
    "addr:postcode":"31406",
    "addr:street":"Skidaway Rd",
    "iso:country":"US",
    "sg:address":"6719 Skidaway Rd",
    "sg:city":"Savannah",
    "sg:classifiers":[
        {
            "category":"Home & Garden",
            "subcategory":"Garden Supply",
            "type":"Retail Goods"
        }
    ],
    "sg:phone":"+1 912 355 1950",
    "sg:postcode":"31406",
    "sg:province":"GA",
    "sg:tags":[
        "feed",
        "farm",
        "lawn"
    ],
    "wof:name":"Hester & Zipperer",
    "wof:placetype":"venue"
},
  "geometry": {"coordinates":[-81.07852800000001,32.012485],"type":"Point"}
}