{
  "type": "Feature",
  "properties": {
    "iso:country":"US",
    "sg:address":"1701 E Broad Ave",
    "sg:city":"Albany",
    "sg:classifiers":[
        {
            "category":"Autos & Motor Vehicles",
            "subcategory":"Auto Supplies",
            "type":"Retail Goods"
        }
    ],
    "sg:phone":"+1 229 438 0365",
    "sg:postcode":"31705",
    "sg:province":"GA",
    "sg:tags":[
        "tire"
    ],
    "wof:name":"J & J Used Tires",
    "wof:placetype":"venue"
},
  "geometry": {"coordinates":[-84.106041,31.57567],"type":"Point"}
}