{
  "type": "Feature",
  "properties": {
    "iso:country":"US",
    "sg:address":"6009 Ogeechee Rd",
    "sg:city":"Savannah",
    "sg:classifiers":[
        {
            "category":"Home & Garden",
            "subcategory":"Carpets & Floor Coverings",
            "type":"Retail Goods"
        }
    ],
    "sg:phone":"+1 912 925 7806",
    "sg:postcode":"31419",
    "sg:province":"GA",
    "sg:tags":[
        "dealer",
        "laying",
        "rug",
        "contractor"
    ],
    "wof:name":"Moore's Floor Covering Whse",
    "wof:placetype":"venue"
},
  "geometry": {"coordinates":[-81.24314099999999,32.004907],"type":"Point"}
}