{
  "type": "Feature",
  "properties": {
    "iso:country":"US",
    "sg:address":"7015 Vesta Brook Dr",
    "sg:city":"Morrow",
    "sg:classifiers":[
        {
            "category":"Shopping",
            "subcategory":"Gifts & Souvenirs",
            "type":"Retail Goods"
        }
    ],
    "sg:phone":"+1 770 968 0275",
    "sg:postcode":"30260",
    "sg:province":"GA",
    "sg:tags":[
        "shop"
    ],
    "wof:name":"Designs By Susan",
    "wof:placetype":"venue"
},
  "geometry": {"coordinates":[-84.304261,33.564382],"type":"Point"}
}