{
  "type": "Feature",
  "properties": {
    "iso:country":"US",
    "sg:address":"1111 Forest Pkwy",
    "sg:city":"Forest Park",
    "sg:classifiers":[
        {
            "category":"Arts & Performance",
            "subcategory":"Arts Center",
            "type":"Entertainment"
        }
    ],
    "sg:phone":"+1 404 361 6645",
    "sg:postcode":"30297",
    "sg:province":"GA",
    "sg:tags":[
        "performing"
    ],
    "wof:name":"Joann's School of Dance",
    "wof:placetype":"venue"
},
  "geometry": {"coordinates":[-84.353724,33.616628],"type":"Point"}
}