{
  "type": "Feature",
  "properties": {
    "addr:full":"1453 Chatsworth Hwy Ellijay GA 30540",
    "addr:housenumber":"1453",
    "addr:postcode":"30540",
    "addr:street":"Chatsworth Hwy",
    "iso:country":"US",
    "sg:address":"1453 Chatsworth Hwy",
    "sg:city":"Ellijay",
    "sg:classifiers":[
        {
            "category":"Retail",
            "subcategory":"Auto Repair",
            "type":"Services"
        }
    ],
    "sg:phone":"+1 706 276 6152",
    "sg:postcode":"30540",
    "sg:province":"GA",
    "sg:tags":[
        "repairing",
        "automobile",
        "general"
    ],
    "wof:name":"Harpers Garage",
    "wof:placetype":"venue"
},
  "geometry": {"coordinates":[-84.494446,34.708089],"type":"Point"}
}