{
  "type": "Feature",
  "properties": {
    "addr:full":"1490 Swords Trl Buckhead GA 30625",
    "addr:housenumber":"1490",
    "addr:postcode":"30625",
    "addr:street":"Swords Trl",
    "iso:country":"US",
    "sg:address":"1490 Swords Trl",
    "sg:city":"Buckhead",
    "sg:classifiers":[
        {
            "category":"Building & Trades",
            "subcategory":"Landscaping Services",
            "type":"Services"
        }
    ],
    "sg:phone":"+1 706 342 8806",
    "sg:postcode":"30625",
    "sg:province":"GA",
    "sg:tags":[
        "concrete"
    ],
    "wof:name":"Benchmark Hardscapes",
    "wof:placetype":"venue"
},
  "geometry": {"coordinates":[-83.310794,33.550064],"type":"Point"}
}