{
  "type": "Feature",
  "properties": {
    "addr:full":"3548 Sawmill Ter Marietta GA 30062",
    "addr:housenumber":"3548",
    "addr:postcode":"30062",
    "addr:street":"Sawmill Ter",
    "iso:country":"US",
    "sg:address":"3548 Sawmill Ter",
    "sg:city":"Marietta",
    "sg:classifiers":[
        {
            "category":"Professional",
            "subcategory":"Business Services",
            "type":"Services"
        }
    ],
    "sg:phone":"+1 770 565 3158",
    "sg:postcode":"30062",
    "sg:province":"GA",
    "wof:name":"Lis Associates Inc",
    "wof:placetype":"venue"
},
  "geometry": {"coordinates":[-84.448925,34.032557],"type":"Point"}
}