{
  "type": "Feature",
  "properties": {
    "iso:country":"US",
    "sg:address":"655 College St",
    "sg:city":"Eastman",
    "sg:classifiers":[
        {
            "category":"Fast Food",
            "type":"Food & Drink"
        },
        {
            "category":"Restaurant",
            "type":"Food & Drink"
        }
    ],
    "sg:phone":"+1 478 374 4111",
    "sg:postcode":"31023",
    "sg:province":"GA",
    "sg:tags":[
        "style",
        "take",
        "family"
    ],
    "wof:name":"Chic-King",
    "wof:placetype":"venue"
},
  "geometry": {"coordinates":[-83.17435999999999,32.192387],"type":"Point"}
}