{
  "type": "Feature",
  "properties": {
    "addr:full":"6140 Jimmy Carter Blvd Norcross GA 30093",
    "addr:housenumber":"6140",
    "addr:postcode":"30093",
    "addr:street":"Jimmy Carter Blvd",
    "iso:country":"US",
    "sg:address":"6140 Jimmy Carter Blvd",
    "sg:city":"Norcross",
    "sg:classifiers":[
        {
            "category":"Food & Beverages",
            "subcategory":"Groceries & Convenience Stores",
            "type":"Retail Goods"
        }
    ],
    "sg:phone":"+1 770 840 7505",
    "sg:postcode":"30093",
    "sg:province":"GA",
    "wof:name":"Quik Trip",
    "wof:placetype":"venue"
},
  "geometry": {"coordinates":[-84.217906,33.925792],"type":"Point"}
}