{
  "type": "Feature",
  "properties": {
    "addr:full":"2504 Moody Rd Warner Robins GA 31088",
    "addr:housenumber":"2504",
    "addr:postcode":"31088",
    "addr:street":"Moody Rd",
    "iso:country":"US",
    "sg:address":"2504 Moody Rd",
    "sg:city":"Warner Robins",
    "sg:classifiers":[
        {
            "category":"Organizations",
            "subcategory":"Religious Organization",
            "type":"Services"
        }
    ],
    "sg:phone":"+1 478 923 7101",
    "sg:postcode":"31088",
    "sg:province":"GA",
    "sg:tags":[
        "church"
    ],
    "sg:website":"www.pastorjefflaborg.com",
    "wof:name":"Second Baptist Church",
    "wof:placetype":"venue"
},
  "geometry": {"coordinates":[-83.623794,32.578797],"type":"Point"}
}