{
  "type": "Feature",
  "properties": {
    "iso:country":"US",
    "sg:address":"8426 Sutton Dr",
    "sg:city":"Riverdale",
    "sg:classifiers":[
        {
            "category":"Professional",
            "subcategory":"Business Services",
            "type":"Services"
        }
    ],
    "sg:phone":"+1 770 471 6222",
    "sg:postcode":"30274",
    "sg:province":"GA",
    "sg:tags":[
        "auctioneer"
    ],
    "wof:name":"Intell Auction Traders",
    "wof:placetype":"venue"
},
  "geometry": {"coordinates":[-84.406097,33.52646],"type":"Point"}
}