{
  "type": "Feature",
  "properties": {
    "iso:country":"US",
    "sg:address":"2225 Lakeview Rd",
    "sg:city":"Statesboro",
    "sg:classifiers":[
        {
            "category":"Building & Trades",
            "subcategory":"Construction",
            "type":"Services"
        }
    ],
    "sg:phone":"+1 912 587 7261",
    "sg:postcode":"30461",
    "sg:province":"GA",
    "sg:tags":[
        "general",
        "contractor"
    ],
    "wof:name":"Emmett G Renfroe Construction",
    "wof:placetype":"venue"
},
  "geometry": {"coordinates":[-81.78427000000001,32.520373],"type":"Point"}
}