{
  "type": "Feature",
  "properties": {
    "addr:full":"528 Burketts Ferry Rd Hazlehurst GA 31539",
    "addr:housenumber":"528",
    "addr:postcode":"31539",
    "addr:street":"Burketts Ferry Rd",
    "iso:country":"US",
    "sg:address":"528 Burketts Ferry Rd",
    "sg:city":"Hazlehurst",
    "sg:classifiers":[
        {
            "category":"Airport",
            "type":"Transportation"
        }
    ],
    "sg:phone":"+1 912 375 9222",
    "sg:postcode":"31539",
    "sg:province":"GA",
    "wof:name":"Hazlehurst Airport",
    "wof:placetype":"venue"
},
  "geometry": {"coordinates":[-82.642888,31.876491],"type":"Point"}
}