{
  "type": "Feature",
  "properties": {
    "iso:country":"US",
    "sg:address":"5 Lee St",
    "sg:city":"Newnan",
    "sg:classifiers":[
        {
            "category":"Social Services",
            "type":"Services"
        }
    ],
    "sg:phone":"+1 770 254 2350",
    "sg:postcode":"30263",
    "sg:province":"GA",
    "sg:tags":[
        "probation"
    ],
    "wof:name":"Newnan Probation Office",
    "wof:placetype":"venue"
},
  "geometry": {"coordinates":[-84.798575,33.377311],"type":"Point"}
}