{
  "type": "Feature",
  "properties": {
    "iso:country":"US",
    "sg:address":"1050 Crown Pointe Pkwy",
    "sg:city":"Atlanta",
    "sg:classifiers":[
        {
            "category":"Real Estate",
            "subcategory":"Real Estate Operator",
            "type":"Services"
        }
    ],
    "sg:phone":"+1 770 392 1662",
    "sg:postcode":"30338",
    "sg:province":"GA",
    "sg:tags":[
        "wholesale",
        "operates",
        "convenience",
        "owns",
        "fuel",
        "store"
    ],
    "wof:name":"Nlp Operations LLC",
    "wof:placetype":"venue"
},
  "geometry": {"coordinates":[-84.34433799999999,33.9308],"type":"Point"}
}