{
  "type": "Feature",
  "properties": {
    "addr:full":"1130 Old Bankhead Hwy Mableton GA 30126",
    "addr:housenumber":"1130",
    "addr:postcode":"30126",
    "addr:street":"Old Bankhead Hwy",
    "iso:country":"US",
    "sg:address":"1130 Old Bankhead Hwy",
    "sg:city":"Mableton",
    "sg:classifiers":[
        {
            "category":"Autos & Motor Vehicles",
            "subcategory":"Automobile Sales",
            "type":"Retail Goods"
        }
    ],
    "sg:phone":"+1 770 948 7633",
    "sg:postcode":"30126",
    "sg:province":"GA",
    "sg:tags":[
        "car",
        "dealer"
    ],
    "wof:name":"Bankhead Auto Sales & Rental",
    "wof:placetype":"venue"
},
  "geometry": {"coordinates":[-84.586904,33.815718],"type":"Point"}
}