{
  "type": "Feature",
  "properties": {
    "iso:country":"US",
    "sg:address":"4224 Pleasantdale Rd",
    "sg:city":"Atlanta",
    "sg:classifiers":[
        {
            "category":"Professional",
            "subcategory":"Business Services",
            "type":"Services"
        }
    ],
    "sg:phone":"+1 770 449 5880",
    "sg:postcode":"30340",
    "sg:province":"GA",
    "sg:tags":[
        "delivery",
        "courier"
    ],
    "wof:name":"Atl Courier Inc",
    "wof:placetype":"venue"
},
  "geometry": {"coordinates":[-84.241997,33.8964],"type":"Point"}
}