{
  "type": "Feature",
  "properties": {
    "addr:full":"5010 Willeo Ridge Ct Marietta GA 30068",
    "addr:housenumber":"5010",
    "addr:postcode":"30068",
    "addr:street":"Willeo Ridge Ct",
    "iso:country":"US",
    "sg:address":"5010 Willeo Ridge Ct",
    "sg:city":"Marietta",
    "sg:classifiers":[
        {
            "category":"Professional",
            "subcategory":"Management & Consulting",
            "type":"Services"
        }
    ],
    "sg:phone":"+1 770 993 8950",
    "sg:postcode":"30068",
    "sg:province":"GA",
    "wof:name":"Rattlesnake Marketing Inc",
    "wof:placetype":"venue"
},
  "geometry": {"coordinates":[-84.404641,33.98424],"type":"Point"}
}