{
  "type": "Feature",
  "properties": {
    "addr:full":"110 Register St Montezuma GA 31063",
    "addr:housenumber":"110",
    "addr:postcode":"31063",
    "addr:street":"Register St",
    "iso:country":"US",
    "sg:address":"110 Register St",
    "sg:city":"Montezuma",
    "sg:classifiers":[
        {
            "category":"Organizations",
            "subcategory":"Religious Organization",
            "type":"Services"
        }
    ],
    "sg:phone":"+1 478 472 7142",
    "sg:postcode":"31063",
    "sg:province":"GA",
    "wof:name":"Methodist Parsonage",
    "wof:placetype":"venue"
},
  "geometry": {"coordinates":[-84.022812,32.313677],"type":"Point"}
}