{
  "type": "Feature",
  "properties": {
    "iso:country":"US",
    "sg:address":"25 N Main St",
    "sg:city":"Jasper",
    "sg:classifiers":[
        {
            "category":"Shopping",
            "subcategory":"Clothing, Apparel, & Fashions",
            "type":"Retail Goods"
        }
    ],
    "sg:phone":"+1 706 692 6105",
    "sg:postcode":"30143",
    "sg:province":"GA",
    "sg:tags":[
        "physical"
    ],
    "wof:name":"Main Street Clothing",
    "wof:placetype":"venue"
},
  "geometry": {"coordinates":[-84.430105,34.468351],"type":"Point"}
}