{
  "type": "Feature",
  "properties": {
    "iso:country":"US",
    "sg:address":"1752 Christian Ave",
    "sg:city":"Macon",
    "sg:classifiers":[
        {
            "category":"Real Estate",
            "subcategory":"Surveying",
            "type":"Services"
        }
    ],
    "sg:phone":"+1 478 744 9930",
    "sg:postcode":"31204",
    "sg:province":"GA",
    "sg:tags":[
        "surveyor"
    ],
    "wof:name":"John Wilkes Land Surveyor",
    "wof:placetype":"venue"
},
  "geometry": {"coordinates":[-83.687743,32.820512],"type":"Point"}
}