{
  "type": "Feature",
  "properties": {
    "iso:country":"US",
    "sg:address":"407 Arbor Crossing Dr",
    "sg:city":"Lithonia",
    "sg:classifiers":[
        {
            "category":"Shopping",
            "subcategory":"Catalog Store",
            "type":"Retail Goods"
        }
    ],
    "sg:phone":"+1 770 987 0291",
    "sg:postcode":"30058",
    "sg:province":"GA",
    "sg:tags":[
        "mail",
        "order",
        "online"
    ],
    "wof:name":"Vanessa Moore",
    "wof:placetype":"venue"
},
  "geometry": {"coordinates":[-84.134398,33.711001],"type":"Point"}
}