{
  "type": "Feature",
  "properties": {
    "iso:country":"US",
    "sg:address":"510 W Washington St",
    "sg:city":"Thomasville",
    "sg:classifiers":[
        {
            "category":"Manufacturing",
            "subcategory":"Glass & Minerals",
            "type":"Manufacturing & Wholesale Goods"
        }
    ],
    "sg:phone":"+1 229 226 1585",
    "sg:postcode":"31792",
    "sg:province":"GA",
    "sg:tags":[
        "ready"
    ],
    "wof:name":"Florida Rock Industries Inc",
    "wof:placetype":"venue"
},
  "geometry": {"coordinates":[-83.986028,30.836514],"type":"Point"}
}