{
  "type": "Feature",
  "properties": {
    "addr:full":"1046 Vance Ave NE Atlanta GA 30306",
    "addr:housenumber":"1046",
    "addr:postcode":"30306",
    "addr:street":"Vance Ave Ne",
    "iso:country":"US",
    "sg:address":"1046 Vance Ave NE",
    "sg:city":"Atlanta",
    "sg:classifiers":[
        {
            "category":"Restaurant",
            "type":"Food & Drink"
        }
    ],
    "sg:phone":"+1 404 892 0060",
    "sg:postcode":"30306",
    "sg:province":"GA",
    "sg:tags":[
        "eating",
        "business"
    ],
    "wof:name":"Japanese Translators & Inter",
    "wof:placetype":"venue"
},
  "geometry": {"coordinates":[-84.35584,33.783131],"type":"Point"}
}