{
  "type": "Feature",
  "properties": {
    "addr:full":"133 Misty Hollow Way Woodstock GA 30188",
    "addr:housenumber":"133",
    "addr:postcode":"30188",
    "addr:street":"Misty Hollow Way",
    "iso:country":"US",
    "sg:address":"133 Misty Hollow Way",
    "sg:city":"Woodstock",
    "sg:classifiers":[
        {
            "category":"Shopping",
            "subcategory":"Clothing, Apparel, & Fashions",
            "type":"Retail Goods"
        }
    ],
    "sg:phone":"+1 770 924 0818",
    "sg:postcode":"30188",
    "sg:province":"GA",
    "sg:tags":[
        "wear"
    ],
    "wof:name":"Kidoodles",
    "wof:placetype":"venue"
},
  "geometry": {"coordinates":[-84.50689,34.135667],"type":"Point"}
}