{
  "type": "Feature",
  "properties": {
    "iso:country":"US",
    "sg:address":"654 8th St NW",
    "sg:city":"Atlanta",
    "sg:classifiers":[
        {
            "category":"Organizations",
            "subcategory":"Religious Organization",
            "type":"Services"
        }
    ],
    "sg:phone":"+1 404 249 7540",
    "sg:postcode":"30332",
    "sg:province":"GA",
    "sg:tags":[
        "church"
    ],
    "wof:name":"Gospel Of The World Ministries",
    "wof:placetype":"venue"
},
  "geometry": {"coordinates":[-84.409261,33.779577],"type":"Point"}
}