{
  "type": "Feature",
  "properties": {
    "iso:country":"US",
    "sg:address":"3575 Koger Blvd",
    "sg:city":"Duluth",
    "sg:classifiers":[
        {
            "category":"Banks & Credit Unions",
            "subcategory":"Investment Brokerage",
            "type":"Services"
        },
        {
            "category":"Banks & Credit Unions",
            "subcategory":"Financial Services",
            "type":"Services"
        }
    ],
    "sg:phone":"+1 678 380 7377",
    "sg:postcode":"30096",
    "sg:province":"GA",
    "sg:tags":[
        "investor"
    ],
    "wof:name":"Inversatil Investments",
    "wof:placetype":"venue"
},
  "geometry": {"coordinates":[-84.123504,33.948719],"type":"Point"}
}