{
  "type": "Feature",
  "properties": {
    "addr:full":"715 N Slappey Blvd Albany GA 31701",
    "addr:housenumber":"715",
    "addr:postcode":"31701",
    "addr:street":"N Slappey Blvd",
    "iso:country":"US",
    "sg:address":"715 N Slappey Blvd",
    "sg:city":"Albany",
    "sg:classifiers":[
        {
            "category":"Restaurant",
            "type":"Food & Drink"
        }
    ],
    "sg:phone":"+1 229 439 7827",
    "sg:postcode":"31701",
    "sg:province":"GA",
    "wof:name":"Star Ways Hotdogs & Ice Cream",
    "wof:placetype":"venue"
},
  "geometry": {"coordinates":[-84.176197,31.586896],"type":"Point"}
}