{
  "type": "Feature",
  "properties": {
    "addr:full":"4200 Sun Rise Trl SW Atlanta GA 30349",
    "addr:housenumber":"4200",
    "addr:postcode":"30349",
    "addr:street":"Sun Rise Trl Sw",
    "iso:country":"US",
    "sg:address":"4200 Sun Rise Trl SW",
    "sg:city":"Atlanta",
    "sg:classifiers":[
        {
            "category":"Professional",
            "subcategory":"Secretarial Services",
            "type":"Services"
        }
    ],
    "sg:phone":"+1 404 803 6824",
    "sg:postcode":"30349",
    "sg:province":"GA",
    "sg:tags":[
        "typing"
    ],
    "wof:name":"Max's Administrative",
    "wof:placetype":"venue"
},
  "geometry": {"coordinates":[-84.52354200000001,33.620811],"type":"Point"}
}