{
  "type": "Feature",
  "properties": {
    "iso:country":"US",
    "sg:address":"7187 Jonesboro Rd",
    "sg:city":"Morrow",
    "sg:classifiers":[
        {
            "category":"Professional",
            "subcategory":"Accounting & Tax Preparation",
            "type":"Services"
        }
    ],
    "sg:phone":"+1 770 961 4200",
    "sg:postcode":"30260",
    "sg:province":"GA",
    "sg:tags":[
        "accountant"
    ],
    "sg:website":"www.fultonandkozak.com",
    "wof:name":"D J Fulton CPA",
    "wof:placetype":"venue"
},
  "geometry": {"coordinates":[-84.345241,33.561563],"type":"Point"}
}