{
  "type": "Feature",
  "properties": {
    "addr:full":"989 Athens St Gainesville GA 30501",
    "addr:housenumber":"989",
    "addr:postcode":"30501",
    "addr:street":"Athens St",
    "iso:country":"US",
    "sg:address":"989 Athens St",
    "sg:city":"Gainesville",
    "sg:classifiers":[
        {
            "category":"Professional",
            "subcategory":"Employment Agencies",
            "type":"Services"
        }
    ],
    "sg:phone":"+1 770 532 2088",
    "sg:postcode":"30501",
    "sg:province":"GA",
    "sg:tags":[
        "help",
        "supply"
    ],
    "wof:name":"Labor Ready",
    "wof:placetype":"venue"
},
  "geometry": {"coordinates":[-83.80810700000001,34.292853],"type":"Point"}
}