{
  "type": "Feature",
  "properties": {
    "iso:country":"US",
    "sg:address":"4210 Waterford Pl",
    "sg:city":"Suwanee",
    "sg:classifiers":[
        {
            "category":"Professional",
            "subcategory":"Business Services",
            "type":"Services"
        }
    ],
    "sg:phone":"+1 770 888 9884",
    "sg:postcode":"30024",
    "sg:province":"GA",
    "wof:name":"Corporate Image Creations Inc",
    "wof:placetype":"venue"
},
  "geometry": {"coordinates":[-84.12691,34.091542],"type":"Point"}
}