{
  "type": "Feature",
  "properties": {
    "addr:full":"105 Collier Rd NW Ste B Atlanta GA 30309",
    "addr:housenumber":"105",
    "addr:postcode":"30309",
    "addr:street":"Collier Rd Nw Ste B",
    "iso:country":"US",
    "sg:address":"105 Collier Rd NW Ste B",
    "sg:city":"Atlanta",
    "sg:classifiers":[
        {
            "category":"Health Services",
            "subcategory":"Clinic",
            "type":"Services"
        },
        {
            "category":"Health Services",
            "subcategory":"Hospital",
            "type":"Services"
        }
    ],
    "sg:phone":"+1 404 355 6055",
    "sg:postcode":"30309",
    "sg:province":"GA",
    "sg:tags":[
        "dialysis"
    ],
    "wof:name":"Da Vita Inc",
    "wof:placetype":"venue"
},
  "geometry": {"coordinates":[-84.39795700000001,33.808438],"type":"Point"}
}