{
  "type": "Feature",
  "properties": {
    "iso:country":"US",
    "sg:address":"3835 Doc Elinburg Way NE",
    "sg:city":"Buford",
    "sg:classifiers":[
        {
            "category":"Recreation",
            "type":"Entertainment"
        }
    ],
    "sg:phone":"+1 770 614 0760",
    "sg:postcode":"30519",
    "sg:province":"GA",
    "sg:tags":[
        "pool",
        "swimming"
    ],
    "wof:name":"Elinburg Swimming Pool",
    "wof:placetype":"venue"
},
  "geometry": {"coordinates":[-83.936727,34.114265],"type":"Point"}
}