{
  "type": "Feature",
  "properties": {
    "addr:full":"4660 Sundridge Trl Fairburn GA 30213",
    "addr:housenumber":"4660",
    "addr:postcode":"30213",
    "addr:street":"Sundridge Trl",
    "iso:country":"US",
    "sg:address":"4660 Sundridge Trl",
    "sg:city":"Fairburn",
    "sg:classifiers":[
        {
            "category":"Manufacturing",
            "subcategory":"Printing",
            "type":"Manufacturing & Wholesale Goods"
        }
    ],
    "sg:phone":"+1 770 306 5296",
    "sg:postcode":"30213",
    "sg:province":"GA",
    "sg:tags":[
        "music",
        "publishing"
    ],
    "wof:name":"Cjc Music Publishing",
    "wof:placetype":"venue"
},
  "geometry": {"coordinates":[-84.66195999999999,33.629259],"type":"Point"}
}