{
  "type": "Feature",
  "properties": {
    "iso:country":"US",
    "sg:address":"1600 Rose Garden Ln",
    "sg:city":"Loganville",
    "sg:classifiers":[
        {
            "category":"Professional",
            "type":"Services"
        }
    ],
    "sg:phone":"+1 770 972 4771",
    "sg:postcode":"30052",
    "sg:province":"GA",
    "wof:name":"Larry J O Brien",
    "wof:placetype":"venue"
},
  "geometry": {"coordinates":[-83.96773,33.831407],"type":"Point"}
}