{
  "type": "Feature",
  "properties": {
    "addr:full":"1107 Greer St Cordele GA 31015",
    "addr:housenumber":"1107",
    "addr:postcode":"31015",
    "addr:street":"Greer St",
    "iso:country":"US",
    "sg:address":"1107 Greer St",
    "sg:city":"Cordele",
    "sg:classifiers":[
        {
            "category":"Sports & Exercise",
            "subcategory":"Gym",
            "type":"Entertainment"
        },
        {
            "category":"Sports & Exercise",
            "subcategory":"Sports Center",
            "type":"Entertainment"
        }
    ],
    "sg:phone":"+1 229 271 1900",
    "sg:postcode":"31015",
    "sg:province":"GA",
    "sg:tags":[
        "manager",
        "gymnasium",
        "promoter"
    ],
    "wof:name":"Impact Sports & Fitness",
    "wof:placetype":"venue"
},
  "geometry": {"coordinates":[-83.755993,31.960944],"type":"Point"}
}