{
  "type": "Feature",
  "properties": {
    "addr:full":"1701 Fullenwider Rd Gainesville GA 30507",
    "addr:housenumber":"1701",
    "addr:postcode":"30507",
    "addr:street":"Fullenwider Rd",
    "iso:country":"US",
    "sg:address":"1701 Fullenwider Rd",
    "sg:city":"Gainesville",
    "sg:classifiers":[
        {
            "category":"Building & Trades",
            "subcategory":"Cleaning & Sanitation",
            "type":"Services"
        }
    ],
    "sg:phone":"+1 770 536 3318",
    "sg:postcode":"30507",
    "sg:province":"GA",
    "sg:tags":[
        "maintenance"
    ],
    "wof:name":"City Public Lands & Buildings",
    "wof:placetype":"venue"
},
  "geometry": {"coordinates":[-83.795751,34.252034],"type":"Point"}
}