{
  "type": "Feature",
  "properties": {
    "addr:full":"277 E Paces Ferry Rd NE Atlanta GA 30305",
    "addr:housenumber":"277",
    "addr:postcode":"30305",
    "addr:street":"E Paces Ferry Rd Ne",
    "iso:country":"US",
    "sg:address":"277 E Paces Ferry Rd NE",
    "sg:city":"Atlanta",
    "sg:classifiers":[
        {
            "category":"Professional",
            "subcategory":"Art Services",
            "type":"Services"
        }
    ],
    "sg:phone":"+1 404 869 8844",
    "sg:postcode":"30305",
    "sg:province":"GA",
    "sg:tags":[
        "graphic",
        "designer"
    ],
    "wof:name":"Star Shooters Atlanta",
    "wof:placetype":"venue"
},
  "geometry": {"coordinates":[-84.3792,33.83925],"type":"Point"}
}