{
  "type": "Feature",
  "properties": {
    "addr:full":"6670 Jones Mill Ct Norcross GA 30092",
    "addr:housenumber":"6670",
    "addr:postcode":"30092",
    "addr:street":"Jones Mill Ct",
    "iso:country":"US",
    "sg:address":"6670 Jones Mill Ct",
    "sg:city":"Norcross",
    "sg:classifiers":[
        {
            "category":"Professional",
            "subcategory":"Advertising",
            "type":"Services"
        }
    ],
    "sg:phone":"+1 770 446 8688",
    "sg:postcode":"30092",
    "sg:province":"GA",
    "sg:tags":[
        "mail",
        "direct"
    ],
    "sg:website":"http://www.exceptionalmarketinggroup.com",
    "wof:name":"Exceptional Marketing Group",
    "wof:placetype":"venue"
},
  "geometry": {"coordinates":[-84.252043,33.943704],"type":"Point"}
}