{
  "type": "Feature",
  "properties": {
    "iso:country":"US",
    "sg:address":"2 Milledge Rd",
    "sg:city":"Augusta",
    "sg:classifiers":[
        {
            "category":"Communications",
            "subcategory":"Radio Station",
            "type":"Services"
        }
    ],
    "sg:phone":"+1 706 733 0044",
    "sg:postcode":"30904",
    "sg:province":"GA",
    "sg:tags":[
        "company",
        "broadcasting"
    ],
    "wof:name":"WKZK",
    "wof:placetype":"venue"
},
  "geometry": {"coordinates":[-82.00332400000001,33.493028],"type":"Point"}
}