{
  "type": "Feature",
  "properties": {
    "iso:country":"US",
    "sg:address":"3530 Ashford Dunwoody Rd",
    "sg:city":"Atlanta",
    "sg:classifiers":[
        {
            "category":"Utilities",
            "subcategory":"Telephone",
            "type":"Services"
        }
    ],
    "sg:phone":"+1 770 349 3412",
    "sg:postcode":"30319",
    "sg:province":"GA",
    "sg:tags":[
        "internet",
        "provider"
    ],
    "wof:name":"Joi Internet",
    "wof:placetype":"venue"
},
  "geometry": {"coordinates":[-84.328377,33.893866],"type":"Point"}
}