{
  "type": "Feature",
  "properties": {
    "iso:country":"US",
    "sg:address":"678 McCamey Sumach Rd",
    "sg:city":"Chatsworth",
    "sg:classifiers":[
        {
            "category":"Manufacturing",
            "subcategory":"Tools & Machinery",
            "type":"Manufacturing & Wholesale Goods"
        }
    ],
    "sg:phone":"+1 706 695 8614",
    "sg:postcode":"30705",
    "sg:province":"GA",
    "sg:tags":[
        "textile"
    ],
    "wof:name":"S & J International Sales Inc",
    "wof:placetype":"venue"
},
  "geometry": {"coordinates":[-84.81218699999999,34.880642],"type":"Point"}
}