{
  "type": "Feature",
  "properties": {
    "addr:full":"69 Morris Rd Commerce GA 30530",
    "addr:housenumber":"69",
    "addr:postcode":"30530",
    "addr:street":"Morris Rd",
    "iso:country":"US",
    "sg:address":"69 Morris Rd",
    "sg:city":"Commerce",
    "sg:classifiers":[
        {
            "category":"Building & Trades",
            "subcategory":"Landscaping Services",
            "type":"Services"
        }
    ],
    "sg:phone":"+1 706 335 4740",
    "sg:postcode":"30530",
    "sg:province":"GA",
    "sg:tags":[
        "tree",
        "stump",
        "grinding",
        "removal"
    ],
    "wof:name":"Steve Johnson",
    "wof:placetype":"venue"
},
  "geometry": {"coordinates":[-83.424147,34.21284],"type":"Point"}
}