{
  "type": "Feature",
  "properties": {
    "iso:country":"US",
    "sg:address":"793 Lake Dow Rd",
    "sg:city":"Mc Donough",
    "sg:classifiers":[
        {
            "category":"Building & Trades",
            "subcategory":"Construction",
            "type":"Services"
        }
    ],
    "sg:phone":"+1 770 474 4982",
    "sg:postcode":"30252",
    "sg:province":"GA",
    "sg:tags":[
        "contractor"
    ],
    "wof:name":"L & M Leak Masters",
    "wof:placetype":"venue"
},
  "geometry": {"coordinates":[-84.10167,33.449907],"type":"Point"}
}