{
  "type": "Feature",
  "properties": {
    "addr:full":"463 Lawrence Dr Evans GA 30809",
    "addr:housenumber":"463",
    "addr:postcode":"30809",
    "addr:street":"Lawrence Dr",
    "iso:country":"US",
    "sg:address":"463 Lawrence Dr",
    "sg:city":"Evans",
    "sg:classifiers":[
        {
            "category":"Wholesale",
            "subcategory":"Durable Goods & Equipment",
            "type":"Manufacturing & Wholesale Goods"
        }
    ],
    "sg:phone":"+1 706 863 1590",
    "sg:postcode":"30809",
    "sg:province":"GA",
    "sg:tags":[
        "representative",
        "manufacturer"
    ],
    "wof:name":"Helen's",
    "wof:placetype":"venue"
},
  "geometry": {"coordinates":[-82.136509,33.534801],"type":"Point"}
}