{
  "type": "Feature",
  "properties": {
    "addr:full":"3725 Millstone Run Augusta GA 30906",
    "addr:housenumber":"3725",
    "addr:postcode":"30906",
    "addr:street":"Millstone Run",
    "iso:country":"US",
    "sg:address":"3725 Millstone Run",
    "sg:city":"Augusta",
    "sg:classifiers":[
        {
            "category":"Social Services",
            "subcategory":"Adult Care",
            "type":"Services"
        }
    ],
    "sg:phone":"+1 706 772 4700",
    "sg:postcode":"30906",
    "sg:province":"GA",
    "sg:tags":[
        "nurses-home"
    ],
    "wof:name":"Open Arms Personal Care Home",
    "wof:placetype":"venue"
},
  "geometry": {"coordinates":[-82.038842,33.386076],"type":"Point"}
}