{
  "type": "Feature",
  "properties": {
    "addr:full":"320 Margie Dr Warner Robins GA 31088",
    "addr:housenumber":"320",
    "addr:postcode":"31088",
    "addr:street":"Margie Dr",
    "iso:country":"US",
    "sg:address":"320 Margie Dr",
    "sg:city":"Warner Robins",
    "sg:classifiers":[
        {
            "category":"Health Services",
            "subcategory":"Doctor",
            "type":"Services"
        }
    ],
    "sg:phone":"+1 478 953 4276",
    "sg:postcode":"31088",
    "sg:province":"GA",
    "sg:tags":[
        "clinic"
    ],
    "wof:name":"Fibromyalgia Institute Of Ga",
    "wof:placetype":"venue"
},
  "geometry": {"coordinates":[-83.68977599999999,32.615593],"type":"Point"}
}