{
  "type": "Feature",
  "properties": {
    "addr:full":"1805 Peachcrest Dr Lawrenceville GA 30043",
    "addr:housenumber":"1805",
    "addr:postcode":"30043",
    "addr:street":"Peachcrest Dr",
    "iso:country":"US",
    "sg:address":"1805 Peachcrest Dr",
    "sg:city":"Lawrenceville",
    "sg:classifiers":[
        {
            "category":"Manufacturing",
            "subcategory":"Apparel",
            "type":"Manufacturing & Wholesale Goods"
        }
    ],
    "sg:phone":"+1 770 962 1224",
    "sg:postcode":"30043",
    "sg:province":"GA",
    "sg:tags":[
        "work",
        "clothing",
        "mfg"
    ],
    "wof:name":"W Robert Sturtevant Etal",
    "wof:placetype":"venue"
},
  "geometry": {"coordinates":[-83.94486499999999,34.03401],"type":"Point"}
}