{
  "type": "Feature",
  "properties": {
    "iso:country":"US",
    "sg:address":"2000 Jabco Ct",
    "sg:city":"Lithonia",
    "sg:classifiers":[
        {
            "category":"Retail",
            "subcategory":"Repair Shop",
            "type":"Services"
        }
    ],
    "sg:phone":"+1 678 526 8111",
    "sg:postcode":"30058",
    "sg:province":"GA",
    "sg:tags":[
        "textile"
    ],
    "wof:name":"HTCW Inc",
    "wof:placetype":"venue"
},
  "geometry": {"coordinates":[-84.12106300000001,33.732987],"type":"Point"}
}