{
  "type": "Feature",
  "properties": {
    "addr:full":"1728 Bonnabel Trce Marietta GA 30066",
    "addr:housenumber":"1728",
    "addr:postcode":"30066",
    "addr:street":"Bonnabel Trce",
    "iso:country":"US",
    "sg:address":"1728 Bonnabel Trce",
    "sg:city":"Marietta",
    "sg:classifiers":[
        {
            "category":"Professional",
            "subcategory":"Business Services",
            "type":"Services"
        }
    ],
    "sg:phone":"+1 770 218 3135",
    "sg:postcode":"30066",
    "sg:province":"GA",
    "sg:tags":[
        "arbitration"
    ],
    "wof:name":"Art Of Living",
    "wof:placetype":"venue"
},
  "geometry": {"coordinates":[-84.516076,33.996421],"type":"Point"}
}