{
  "type": "Feature",
  "properties": {
    "iso:country":"US",
    "sg:address":"3545 Cruse Rd NW",
    "sg:city":"Lawrenceville",
    "sg:classifiers":[
        {
            "category":"Real Estate",
            "subcategory":"Real Estate Operator",
            "type":"Services"
        }
    ],
    "sg:phone":"+1 678 640 9732",
    "sg:postcode":"30044",
    "sg:province":"GA",
    "sg:tags":[
        "building",
        "nonresidential"
    ],
    "wof:name":"Pruitts Property Preservation",
    "wof:placetype":"venue"
},
  "geometry": {"coordinates":[-84.110694,33.926187],"type":"Point"}
}