{
  "type": "Feature",
  "properties": {
    "iso:country":"US",
    "sg:address":"331 Elizabeth St NE",
    "sg:city":"Atlanta",
    "sg:classifiers":[
        {
            "category":"Shopping",
            "subcategory":"Mobile Phones",
            "type":"Retail Goods"
        },
        {
            "category":"Building & Trades",
            "subcategory":"Construction",
            "type":"Services"
        }
    ],
    "sg:phone":"+1 404 880 4141",
    "sg:postcode":"30307",
    "sg:province":"GA",
    "sg:tags":[
        "manufactured",
        "housing-communities",
        "home"
    ],
    "wof:name":"Trail-R-Inn Mobile Home Park",
    "wof:placetype":"venue"
},
  "geometry": {"coordinates":[-84.358003,33.763065],"type":"Point"}
}