{
  "type": "Feature",
  "properties": {
    "iso:country":"US",
    "sg:address":"347 Greene St",
    "sg:city":"Augusta",
    "sg:classifiers":[
        {
            "category":"Professional",
            "subcategory":"Lawyer & Legal Services",
            "type":"Services"
        }
    ],
    "sg:phone":"+1 706 724 3331",
    "sg:postcode":"30901",
    "sg:province":"GA",
    "sg:tags":[
        "attorney"
    ],
    "wof:name":"William J Sussman PC",
    "wof:placetype":"venue"
},
  "geometry": {"coordinates":[-81.956166,33.469951],"type":"Point"}
}