{
  "type": "Feature",
  "properties": {
    "iso:country":"US",
    "sg:address":"3529 Anvil Block Rd",
    "sg:city":"Ellenwood",
    "sg:classifiers":[
        {
            "category":"Shopping",
            "subcategory":"Used Merchandise",
            "type":"Retail Goods"
        }
    ],
    "sg:phone":"+1 404 366 9877",
    "sg:postcode":"30294",
    "sg:province":"GA",
    "sg:tags":[
        "antique"
    ],
    "wof:name":"Lyvonne's Antiques",
    "wof:placetype":"venue"
},
  "geometry": {"coordinates":[-84.268818,33.627995],"type":"Point"}
}