{
  "type": "Feature",
  "properties": {
    "addr:full":"750 Hammond Dr NE Atlanta GA 30328",
    "addr:housenumber":"750",
    "addr:postcode":"30328",
    "addr:street":"Hammond Dr Ne",
    "iso:country":"US",
    "sg:address":"750 Hammond Dr NE",
    "sg:city":"Atlanta",
    "sg:classifiers":[
        {
            "category":"Real Estate",
            "subcategory":"Real Estate Services",
            "type":"Services"
        }
    ],
    "sg:phone":"+1 404 256 9000",
    "sg:postcode":"30328",
    "sg:province":"GA",
    "sg:tags":[
        "abstract",
        "title"
    ],
    "wof:name":"Cornerstone Title Company",
    "wof:placetype":"venue"
},
  "geometry": {"coordinates":[-84.36154999999999,33.919065],"type":"Point"}
}