{
  "type": "Feature",
  "properties": {
    "iso:country":"US",
    "sg:address":"846 Lodgeview Dr",
    "sg:city":"Bethlehem",
    "sg:classifiers":[
        {
            "category":"Building & Trades",
            "subcategory":"Electrical",
            "type":"Services"
        }
    ],
    "sg:phone":"+1 770 307 9729",
    "sg:postcode":"30620",
    "sg:province":"GA",
    "sg:tags":[
        "electrical",
        "contractor"
    ],
    "wof:name":"Mlg Electric Inc",
    "wof:placetype":"venue"
},
  "geometry": {"coordinates":[-83.7503,33.949318],"type":"Point"}
}