{
  "type": "Feature",
  "properties": {
    "iso:country":"US",
    "sg:address":"3333 S Dixie Rd",
    "sg:city":"Dalton",
    "sg:classifiers":[
        {
            "category":"Home & Garden",
            "subcategory":"Carpets & Floor Coverings",
            "type":"Retail Goods"
        }
    ],
    "sg:phone":"+1 706 275 0775",
    "sg:postcode":"30720",
    "sg:province":"GA",
    "sg:tags":[
        "internet"
    ],
    "sg:website":"www.carpetcapitol.com",
    "wof:name":"Milestone Floorcovering",
    "wof:placetype":"venue"
},
  "geometry": {"coordinates":[-84.985437,34.702174],"type":"Point"}
}