{
  "type": "Feature",
  "properties": {
    "addr:full":"702 Ellis St Augusta GA 30901",
    "addr:housenumber":"702",
    "addr:postcode":"30901",
    "addr:street":"Ellis St",
    "iso:country":"US",
    "sg:address":"702 Ellis St",
    "sg:city":"Augusta",
    "sg:classifiers":[
        {
            "category":"Retail",
            "subcategory":"Laundry & Dry Cleaning",
            "type":"Services"
        }
    ],
    "sg:phone":"+1 706 722 2088",
    "sg:postcode":"30901",
    "sg:province":"GA",
    "sg:tags":[
        "drycleaning",
        "plant"
    ],
    "wof:name":"One Hour Cleanerizing",
    "wof:placetype":"venue"
},
  "geometry": {"coordinates":[-81.964861,33.473838],"type":"Point"}
}