{
  "type": "Feature",
  "properties": {
    "addr:full":"147 Westchester Park Macon GA 31210",
    "addr:housenumber":"147",
    "addr:postcode":"31210",
    "addr:street":"Westchester Park",
    "iso:country":"US",
    "sg:address":"147 Westchester Park",
    "sg:city":"Macon",
    "sg:classifiers":[
        {
            "category":"Wholesale",
            "subcategory":"Chemicals & Plastics",
            "type":"Manufacturing & Wholesale Goods"
        }
    ],
    "sg:phone":"+1 478 757 9702",
    "sg:postcode":"31210",
    "sg:province":"GA",
    "wof:name":"Zep Manufacturing Co",
    "wof:placetype":"venue"
},
  "geometry": {"coordinates":[-83.704341,32.861061],"type":"Point"}
}