{
  "type": "Feature",
  "properties": {
    "addr:full":"1687 E Clifton Rd NE Atlanta GA 30307",
    "addr:housenumber":"1687",
    "addr:postcode":"30307",
    "addr:street":"E Clifton Rd Ne",
    "iso:country":"US",
    "sg:address":"1687 E Clifton Rd NE",
    "sg:city":"Atlanta",
    "sg:classifiers":[
        {
            "category":"Shopping",
            "subcategory":"Florist",
            "type":"Retail Goods"
        }
    ],
    "sg:phone":"+1 404 377 7848",
    "sg:postcode":"30307",
    "sg:province":"GA",
    "wof:name":"Simply Elegant Flowers",
    "wof:placetype":"venue"
},
  "geometry": {"coordinates":[-84.32096300000001,33.78095],"type":"Point"}
}