{
  "type": "Feature",
  "properties": {
    "addr:full":"5625 Bahia Mar Cir Stone Mountain GA 30087",
    "addr:housenumber":"5625",
    "addr:postcode":"30087",
    "addr:street":"Bahia Mar Cir",
    "iso:country":"US",
    "sg:address":"5625 Bahia Mar Cir",
    "sg:city":"Stone Mountain",
    "sg:classifiers":[
        {
            "category":"Professional",
            "type":"Services"
        }
    ],
    "sg:phone":"+1 770 493 4461",
    "sg:postcode":"30087",
    "sg:province":"GA",
    "wof:name":"Niermann Services LLC",
    "wof:placetype":"venue"
},
  "geometry": {"coordinates":[-84.161056,33.839822],"type":"Point"}
}