{
  "type": "Feature",
  "properties": {
    "iso:country":"US",
    "sg:address":"236 Johnson Ferry Rd NE",
    "sg:city":"Sandy Springs",
    "sg:classifiers":[
        {
            "category":"Food & Beverages",
            "subcategory":"Bakery",
            "type":"Retail Goods"
        },
        {
            "category":"Restaurant",
            "type":"Food & Drink"
        },
        {
            "category":"Bakery",
            "type":"Food & Drink"
        }
    ],
    "sg:phone":"+1 404 255 7402",
    "sg:postcode":"30328",
    "sg:province":"GA",
    "sg:tags":[
        "new",
        "american",
        "sandwich"
    ],
    "sg:website":"www.flavorcafebakery.com",
    "wof:name":"Flavor Cafe Bakery",
    "wof:placetype":"venue"
},
  "geometry": {"coordinates":[-84.380021,33.925425],"type":"Point"}
}