{
  "type": "Feature",
  "properties": {
    "addr:full":"1598 Autumn Hurst Ct Stone Mountain GA 30088",
    "addr:housenumber":"1598",
    "addr:postcode":"30088",
    "addr:street":"Autumn Hurst Ct",
    "iso:country":"US",
    "sg:address":"1598 Autumn Hurst Ct",
    "sg:city":"Stone Mountain",
    "sg:classifiers":[
        {
            "category":"Professional",
            "subcategory":"Business Services",
            "type":"Services"
        }
    ],
    "sg:phone":"+1 770 808 8476",
    "sg:postcode":"30088",
    "sg:province":"GA",
    "wof:name":"Klh & Assoc",
    "wof:placetype":"venue"
},
  "geometry": {"coordinates":[-84.194422,33.748661],"type":"Point"}
}