{
  "type": "Feature",
  "properties": {
    "iso:country":"US",
    "sg:address":"2878 Jonquil Dr",
    "sg:city":"Smyrna",
    "sg:classifiers":[
        {
            "category":"Professional",
            "subcategory":"Business Services",
            "type":"Services"
        }
    ],
    "sg:phone":"+1 770 333 9372",
    "sg:postcode":"30080",
    "sg:province":"GA",
    "wof:name":"Whippoorwill Sound Inc",
    "wof:placetype":"venue"
},
  "geometry": {"coordinates":[-84.504651,33.882205],"type":"Point"}
}