{
  "type": "Feature",
  "properties": {
    "addr:full":"3866 Alabama Hwy Rome GA 30165",
    "addr:housenumber":"3866",
    "addr:postcode":"ga 30165",
    "addr:street":"Alabama Hwy",
    "iso:country":"US",
    "sg:address":"3866 Alabama Hwy",
    "sg:city":"Rome",
    "sg:classifiers":[
        {
            "category":"Personal",
            "subcategory":"Beauty Salon",
            "type":"Services"
        }
    ],
    "sg:phone":"+1 706 295 0888",
    "sg:postcode":"30165",
    "sg:province":"GA",
    "sg:tags":[
        "shop"
    ],
    "wof:name":"New You Hair Salon",
    "wof:placetype":"venue"
},
  "geometry": {"coordinates":[-85.284682,34.26404],"type":"Point"}
}