{
  "type": "Feature",
  "properties": {
    "iso:country":"US",
    "sg:address":"5537 N Henry Blvd",
    "sg:city":"Stockbridge",
    "sg:classifiers":[
        {
            "category":"Restaurant",
            "type":"Food & Drink"
        }
    ],
    "sg:phone":"+1 770 474 6744",
    "sg:postcode":"30281",
    "sg:province":"GA",
    "sg:tags":[
        "pizza"
    ],
    "wof:name":"Olympia Pizza House",
    "wof:placetype":"venue"
},
  "geometry": {"coordinates":[-84.258301,33.552299],"type":"Point"}
}