{
  "type": "Feature",
  "properties": {
    "iso:country":"US",
    "sg:address":"2683 Univeter Rd",
    "sg:city":"Canton",
    "sg:classifiers":[
        {
            "category":"Building & Trades",
            "subcategory":"Pest Control",
            "type":"Services"
        }
    ],
    "sg:phone":"+1 770 479 1598",
    "sg:postcode":"30115",
    "sg:province":"GA",
    "sg:tags":[
        "mothproofing"
    ],
    "wof:name":"Systematic Services",
    "wof:placetype":"venue"
},
  "geometry": {"coordinates":[-84.468992,34.188333],"type":"Point"}
}