{
  "type": "Feature",
  "properties": {
    "addr:full":"825 Brian Ln Forest Park GA 30297",
    "addr:housenumber":"825",
    "addr:postcode":"30297",
    "addr:street":"Brian Ln",
    "iso:country":"US",
    "sg:address":"825 Brian Ln",
    "sg:city":"Forest Park",
    "sg:classifiers":[
        {
            "category":"Building & Trades",
            "subcategory":"Construction",
            "type":"Services"
        }
    ],
    "sg:phone":"+1 404 862 4622",
    "sg:postcode":"30297",
    "sg:province":"GA",
    "sg:tags":[
        "stone",
        "contractor"
    ],
    "wof:name":"F & F Stone Masons",
    "wof:placetype":"venue"
},
  "geometry": {"coordinates":[-84.361403,33.582004],"type":"Point"}
}