{
  "type": "Feature",
  "properties": {
    "addr:full":"5665 Hwy 9 N Alpharetta GA 30004",
    "addr:housenumber":"5665",
    "addr:postcode":"30004",
    "addr:street":"Hwy 9 N",
    "iso:country":"US",
    "sg:address":"5665 Hwy 9 N",
    "sg:city":"Alpharetta",
    "sg:classifiers":[
        {
            "category":"Wholesale",
            "subcategory":"Non-durable Goods",
            "type":"Manufacturing & Wholesale Goods"
        }
    ],
    "sg:phone":"+1 770 844 7434",
    "sg:postcode":"30004",
    "sg:province":"GA",
    "wof:name":"Stirrups Clothing Co",
    "wof:placetype":"venue"
},
  "geometry": {"coordinates":[-84.251735,34.144357],"type":"Point"}
}