{
  "type": "Feature",
  "properties": {
    "addr:full":"8139 Hwy 278 NE Covington GA 30014",
    "addr:housenumber":"8139",
    "addr:postcode":"30014",
    "addr:street":"Hwy 278 Ne",
    "iso:country":"US",
    "sg:address":"8139 Hwy 278 NE",
    "sg:city":"Covington",
    "sg:classifiers":[
        {
            "category":"Home & Garden",
            "subcategory":"Building Materials",
            "type":"Retail Goods"
        }
    ],
    "sg:phone":"+1 770 786 1630",
    "sg:postcode":"30014",
    "sg:province":"GA",
    "sg:tags":[
        "glass",
        "leaded"
    ],
    "wof:name":"A Precision Stained Glass Co",
    "wof:placetype":"venue"
},
  "geometry": {"coordinates":[-83.836789,33.600442],"type":"Point"}
}