{
  "type": "Feature",
  "properties": {
    "addr:full":"724 Cooper Rd Social Circle GA 30025",
    "addr:housenumber":"724",
    "addr:postcode":"30025",
    "addr:street":"Cooper Rd;Circle",
    "iso:country":"US",
    "sg:address":"724 Cooper Rd",
    "sg:city":"Social Circle",
    "sg:classifiers":[
        {
            "category":"Building & Trades",
            "subcategory":"Construction",
            "type":"Services"
        }
    ],
    "sg:phone":"+1 770 385 5421",
    "sg:postcode":"30025",
    "sg:province":"GA",
    "sg:tags":[
        "house"
    ],
    "wof:name":"Martin Const",
    "wof:placetype":"venue"
},
  "geometry": {"coordinates":[-83.713077,33.590042],"type":"Point"}
}