{
  "type": "Feature",
  "properties": {
    "addr:full":"338 Island Rd Savannah GA 31406",
    "addr:housenumber":"338",
    "addr:postcode":"31406",
    "addr:street":"Island Rd",
    "iso:country":"US",
    "sg:address":"338 Island Rd",
    "sg:city":"Savannah",
    "sg:classifiers":[
        {
            "category":"Real Estate",
            "subcategory":"Real Estate Agent",
            "type":"Services"
        }
    ],
    "sg:phone":"+1 912 355 4152",
    "sg:postcode":"31406",
    "sg:province":"GA",
    "sg:tags":[
        "inspection"
    ],
    "wof:name":"House Inspectors Of Savannah",
    "wof:placetype":"venue"
},
  "geometry": {"coordinates":[-81.09243600000001,31.928052],"type":"Point"}
}