{
  "type": "Feature",
  "properties": {
    "iso:country":"US",
    "sg:address":"6336 Old Shadburn Ferry Rd",
    "sg:city":"Buford",
    "sg:classifiers":[
        {
            "category":"Professional",
            "subcategory":"Computer Services",
            "type":"Services"
        }
    ],
    "sg:phone":"+1 770 271 4142",
    "sg:postcode":"30518",
    "sg:province":"GA",
    "sg:tags":[
        "cad",
        "system",
        "programing",
        "custom"
    ],
    "wof:name":"Dentacad Corp",
    "wof:placetype":"venue"
},
  "geometry": {"coordinates":[-84.038921,34.150645],"type":"Point"}
}