{
  "type": "Feature",
  "properties": {
    "addr:full":"6945 Keith Rd Clermont GA 30527",
    "addr:housenumber":"6945",
    "addr:postcode":"30527",
    "addr:street":"Keith Rd",
    "iso:country":"US",
    "sg:address":"6945 Keith Rd",
    "sg:city":"Clermont",
    "sg:classifiers":[
        {
            "category":"Communications",
            "type":"Services"
        }
    ],
    "sg:phone":"+1 770 983 0013",
    "sg:postcode":"30527",
    "sg:province":"GA",
    "wof:name":"Sensible Communication",
    "wof:placetype":"venue"
},
  "geometry": {"coordinates":[-83.781003,34.513156],"type":"Point"}
}