{
  "type": "Feature",
  "properties": {
    "addr:full":"6726 Tara Blvd Jonesboro GA 30236",
    "addr:housenumber":"6726",
    "addr:postcode":"30236",
    "addr:street":"Tara Blvd",
    "iso:country":"US",
    "sg:address":"6726 Tara Blvd",
    "sg:city":"Jonesboro",
    "sg:classifiers":[
        {
            "category":"Local Transit",
            "type":"Transportation"
        }
    ],
    "sg:phone":"+1 678 422 4632",
    "sg:postcode":"30236",
    "sg:province":"GA",
    "wof:name":"Pristine Transit",
    "wof:placetype":"venue"
},
  "geometry": {"coordinates":[-84.37156299999999,33.568609],"type":"Point"}
}