{
  "type": "Feature",
  "properties": {
    "addr:full":"1224 Sherwood Park Dr NE Gainesville GA 30501",
    "addr:housenumber":"1224",
    "addr:postcode":"30501",
    "addr:street":"Sherwood Park Dr Ne;Ga",
    "iso:country":"US",
    "sg:address":"1224 Sherwood Park Dr NE",
    "sg:city":"Gainesville",
    "sg:classifiers":[
        {
            "category":"Health Services",
            "subcategory":"Doctor",
            "type":"Services"
        }
    ],
    "sg:phone":"+1 770 287 0606",
    "sg:postcode":"30501",
    "sg:province":"GA",
    "sg:tags":[
        "medical"
    ],
    "wof:name":"Dr Cisco",
    "wof:placetype":"venue"
},
  "geometry": {"coordinates":[-83.818073,34.306863],"type":"Point"}
}