{
  "type": "Feature",
  "properties": {
    "addr:full":"1700 Riverside Ave Waycross GA 31501",
    "addr:housenumber":"1700",
    "addr:postcode":"31501",
    "addr:street":"Riverside Ave",
    "iso:country":"US",
    "sg:address":"1700 Riverside Ave",
    "sg:city":"Waycross",
    "sg:classifiers":[
        {
            "category":"Government",
            "subcategory":"Office",
            "type":"Public Place"
        }
    ],
    "sg:phone":"+1 912 287 4454",
    "sg:postcode":"31501",
    "sg:province":"GA",
    "wof:name":"Emergency Medical Svc",
    "wof:placetype":"venue"
},
  "geometry": {"coordinates":[-82.35347,31.234211],"type":"Point"}
}