{
  "type": "Feature",
  "properties": {
    "iso:country":"US",
    "sg:address":"747 S Hill St",
    "sg:city":"Griffin",
    "sg:classifiers":[
        {
            "category":"Health Services",
            "subcategory":"Doctor",
            "type":"Services"
        }
    ],
    "sg:phone":"+1 770 228 5407",
    "sg:postcode":"30224",
    "sg:province":"GA",
    "sg:tags":[
        "medicine",
        "physician",
        "practice",
        "surgeons",
        "family"
    ],
    "sg:website":"http://www.mcintoshtrail.com",
    "wof:name":"Mcintosh Trail Family Practice Associates Pc",
    "wof:placetype":"venue"
},
  "geometry": {"coordinates":[-84.26461399999999,33.233758],"type":"Point"}
}