{
  "type": "Feature",
  "properties": {
    "iso:country":"US",
    "sg:address":"1225 Northbrook Pkwy",
    "sg:city":"Suwanee",
    "sg:classifiers":[
        {
            "category":"Professional",
            "subcategory":"Research",
            "type":"Services"
        }
    ],
    "sg:phone":"+1 770 338 6896",
    "sg:postcode":"30024",
    "sg:province":"GA",
    "sg:tags":[
        "commercial",
        "physical"
    ],
    "wof:name":"Electric Corporation America",
    "wof:placetype":"venue"
},
  "geometry": {"coordinates":[-84.067041,34.007792],"type":"Point"}
}