{
  "type": "Feature",
  "properties": {
    "iso:country":"US",
    "sg:address":"121 N West St",
    "sg:city":"Bainbridge",
    "sg:classifiers":[
        {
            "category":"Professional",
            "subcategory":"Business Services",
            "type":"Services"
        }
    ],
    "sg:phone":"+1 229 248 1800",
    "sg:postcode":"39817",
    "sg:province":"GA",
    "wof:name":"Red Lion Studios",
    "wof:placetype":"venue"
},
  "geometry": {"coordinates":[-84.57656299999999,30.906423],"type":"Point"}
}