{
  "type": "Feature",
  "properties": {
    "addr:full":"3512 Kenton Pl SE Atlanta GA 30316",
    "addr:housenumber":"3512",
    "addr:postcode":"30316",
    "addr:street":"Kenton Pl Se",
    "iso:country":"US",
    "sg:address":"3512 Kenton Pl SE",
    "sg:city":"Atlanta",
    "sg:classifiers":[
        {
            "category":"Building & Trades",
            "subcategory":"Plumbing",
            "type":"Services"
        }
    ],
    "sg:phone":"+1 404 627 8059",
    "sg:postcode":"30316",
    "sg:province":"GA",
    "sg:tags":[
        "conditioning",
        "air",
        "system",
        "contractor"
    ],
    "wof:name":"J E Smith Sheet Metal Works",
    "wof:placetype":"venue"
},
  "geometry": {"coordinates":[-84.34157500000001,33.685292],"type":"Point"}
}