{
  "type": "Feature",
  "properties": {
    "addr:full":"1861 Benson Ave SE Smyrna GA 30080",
    "addr:housenumber":"1861",
    "addr:postcode":"30080",
    "addr:street":"Benson Ave Se",
    "iso:country":"US",
    "sg:address":"1861 Benson Ave SE",
    "sg:city":"Smyrna",
    "sg:classifiers":[
        {
            "category":"Building & Trades",
            "subcategory":"Landscaping Services",
            "type":"Services"
        }
    ],
    "sg:phone":"+1 770 438 8320",
    "sg:postcode":"30080",
    "sg:province":"GA",
    "wof:name":"Berry Lawn Care",
    "wof:placetype":"venue"
},
  "geometry": {"coordinates":[-84.533303,33.906082],"type":"Point"}
}