{
  "type": "Feature",
  "properties": {
    "addr:full":"559 Waleska Rd Canton GA 30114",
    "addr:housenumber":"559",
    "addr:postcode":"30114",
    "addr:street":"Waleska Rd",
    "iso:country":"US",
    "sg:address":"559 Waleska Rd",
    "sg:city":"Canton",
    "sg:classifiers":[
        {
            "category":"Retail",
            "subcategory":"Auto Repair",
            "type":"Services"
        }
    ],
    "sg:phone":"+1 770 345 3368",
    "sg:postcode":"30114",
    "sg:province":"GA",
    "sg:tags":[
        "body",
        "automobile",
        "painting"
    ],
    "wof:name":"Oliver's Auto Hail Repair",
    "wof:placetype":"venue"
},
  "geometry": {"coordinates":[-84.494015,34.248865],"type":"Point"}
}