{
  "type": "Feature",
  "properties": {
    "addr:full":"4498 Chamblee Dunwoody Rd Dunwoody GA 30338",
    "addr:housenumber":"4498",
    "addr:postcode":"30338",
    "addr:street":"Chamblee Dunwoody Rd",
    "iso:country":"US",
    "sg:address":"4498 Chamblee Dunwoody Rd",
    "sg:city":"Dunwoody",
    "sg:classifiers":[
        {
            "category":"Shopping",
            "type":"Retail Goods"
        }
    ],
    "sg:phone":"+1 770 234 4498",
    "sg:postcode":"30338",
    "sg:province":"GA",
    "sg:tags":[
        "pet",
        "shop"
    ],
    "wof:name":"Pet Supermarket",
    "wof:placetype":"venue"
},
  "geometry": {"coordinates":[-84.314466,33.922833],"type":"Point"}
}