{
  "type": "Feature",
  "properties": {
    "addr:full":"12813 Hwy 53 E Marble Hill GA 30534",
    "addr:housenumber":"12813",
    "addr:postcode":"30534",
    "addr:street":"Hwy 53 E",
    "iso:country":"US",
    "sg:address":"12813 Hwy 53 E",
    "sg:city":"Marble Hill",
    "sg:classifiers":[
        {
            "category":"Government",
            "subcategory":"Post Office",
            "type":"Public Place"
        }
    ],
    "sg:phone":"+1 770 893 3364",
    "sg:postcode":"30534",
    "sg:province":"GA",
    "wof:name":"Marble Hill Main Office",
    "wof:placetype":"venue"
},
  "geometry": {"coordinates":[-84.270792,34.414604],"type":"Point"}
}