{
  "type": "Feature",
  "properties": {
    "addr:full":"5383 Truman Dr Decatur GA 30035",
    "addr:housenumber":"5383",
    "addr:postcode":"30035",
    "addr:street":"Truman Dr",
    "iso:country":"US",
    "sg:address":"5383 Truman Dr",
    "sg:city":"Decatur",
    "sg:classifiers":[
        {
            "category":"Manufacturing",
            "subcategory":"Paper Products",
            "type":"Manufacturing & Wholesale Goods"
        }
    ],
    "sg:phone":"+1 770 981 5400",
    "sg:postcode":"30035",
    "sg:province":"GA",
    "sg:tags":[
        "bag",
        "packing",
        "materials-shipping",
        "c",
        "mfg"
    ],
    "sg:website":"http://www.hoodpkg.com",
    "wof:name":"Hood Flexible Packaging",
    "wof:placetype":"venue"
},
  "geometry": {"coordinates":[-84.172366,33.714619],"type":"Point"}
}