{
  "type": "Feature",
  "properties": {
    "addr:full":"270 Preston Oaks Dr Alpharetta GA 30022",
    "addr:housenumber":"270",
    "addr:postcode":"30022",
    "addr:street":"Preston Oaks Dr",
    "iso:country":"US",
    "sg:address":"270 Preston Oaks Dr",
    "sg:city":"Alpharetta",
    "sg:classifiers":[
        {
            "category":"Recreation",
            "type":"Entertainment"
        }
    ],
    "sg:phone":"+1 770 663 0788",
    "sg:postcode":"30022",
    "sg:province":"GA",
    "wof:name":"Atlanta Taiji Gongfu Assoc",
    "wof:placetype":"venue"
},
  "geometry": {"coordinates":[-84.258853,34.021803],"type":"Point"}
}