{
  "type": "Feature",
  "properties": {
    "iso:country":"US",
    "sg:address":"1814 Plum St",
    "sg:city":"Valdosta",
    "sg:classifiers":[
        {
            "category":"Food & Beverages",
            "subcategory":"Specialty",
            "type":"Retail Goods"
        }
    ],
    "sg:phone":"+1 229 244 7220",
    "sg:postcode":"31601",
    "sg:province":"GA",
    "sg:tags":[
        "tea",
        "coffee"
    ],
    "wof:name":"Toads & Tea Cups",
    "wof:placetype":"venue"
},
  "geometry": {"coordinates":[-83.307703,30.845904],"type":"Point"}
}