{
  "type": "Feature",
  "properties": {
    "addr:full":"5477 Carter Dr Hahira GA 31632",
    "addr:housenumber":"5477",
    "addr:postcode":"31632",
    "addr:street":"Carter Dr",
    "iso:country":"US",
    "sg:address":"5477 Carter Dr",
    "sg:city":"Hahira",
    "sg:classifiers":[
        {
            "category":"Organizations",
            "subcategory":"Religious Organization",
            "type":"Services"
        }
    ],
    "sg:phone":"+1 229 794 2958",
    "sg:postcode":"31632",
    "sg:province":"GA",
    "wof:name":"Days Baptist Church",
    "wof:placetype":"venue"
},
  "geometry": {"coordinates":[-83.28352099999999,30.971486],"type":"Point"}
}