{
  "type": "Feature",
  "properties": {
    "iso:country":"US",
    "sg:address":"2704 Northlake Rd",
    "sg:city":"Gainesville",
    "sg:classifiers":[
        {
            "category":"Professional",
            "subcategory":"Engineering",
            "type":"Services"
        }
    ],
    "sg:phone":"+1 770 287 0070",
    "sg:postcode":"30506",
    "sg:province":"GA",
    "wof:name":"AEC",
    "wof:placetype":"venue"
},
  "geometry": {"coordinates":[-83.831202,34.364127],"type":"Point"}
}