{
  "type": "Feature",
  "properties": {
    "iso:country":"US",
    "sg:address":"2935 Summitop Rd",
    "sg:city":"Marietta",
    "sg:classifiers":[
        {
            "category":"Banks & Credit Unions",
            "subcategory":"Financial Services",
            "type":"Services"
        }
    ],
    "sg:phone":"+1 770 591 7764",
    "sg:postcode":"30066",
    "sg:province":"GA",
    "sg:tags":[
        "investor"
    ],
    "wof:name":"Callahan Investments Inc",
    "wof:placetype":"venue"
},
  "geometry": {"coordinates":[-84.464112,34.066865],"type":"Point"}
}