{
  "type": "Feature",
  "properties": {
    "addr:full":"2403 Dawson Rd Albany GA 31707",
    "addr:housenumber":"2403",
    "addr:postcode":"31707",
    "addr:street":"Dawson Rd",
    "iso:country":"US",
    "sg:address":"2403 Dawson Rd",
    "sg:city":"Albany",
    "sg:classifiers":[
        {
            "category":"Place Of Worship",
            "type":"Public Place"
        },
        {
            "category":"Place Of Worship",
            "subcategory":"Temple",
            "type":"Public Place"
        }
    ],
    "sg:phone":"+1 229 317 1539",
    "sg:postcode":"31707",
    "sg:province":"GA",
    "sg:tags":[
        "church"
    ],
    "wof:name":"Temple Automotive",
    "wof:placetype":"venue"
},
  "geometry": {"coordinates":[-84.208107,31.607121],"type":"Point"}
}