{
  "type": "Feature",
  "properties": {
    "iso:country":"US",
    "sg:address":"23 Wickham Dr",
    "sg:city":"Columbus",
    "sg:classifiers":[
        {
            "category":"Professional",
            "subcategory":"Business Services",
            "type":"Services"
        }
    ],
    "sg:phone":"+1 706 687 4657",
    "sg:postcode":"31907",
    "sg:province":"GA",
    "wof:name":"Willis Enterprises",
    "wof:placetype":"venue"
},
  "geometry": {"coordinates":[-84.913416,32.441925],"type":"Point"}
}