{
  "type": "Feature",
  "properties": {
    "iso:country":"US",
    "sg:address":"987 Chattahoochee Ave NW",
    "sg:city":"Atlanta",
    "sg:classifiers":[
        {
            "category":"Building & Trades",
            "subcategory":"Construction",
            "type":"Services"
        }
    ],
    "sg:phone":"+1 404 748 9281",
    "sg:postcode":"30318",
    "sg:province":"GA",
    "sg:tags":[
        "window",
        "installation"
    ],
    "sg:website":"www.scardinodoors.com",
    "wof:name":"Scardino Doors Llc",
    "wof:placetype":"venue"
},
  "geometry": {"coordinates":[-84.42036400000001,33.800482],"type":"Point"}
}