{
  "type": "Feature",
  "properties": {
    "iso:country":"US",
    "sg:address":"2736 Sylvan Rd",
    "sg:city":"Atlanta",
    "sg:classifiers":[
        {
            "category":"Personal",
            "subcategory":"Beauty Salon",
            "type":"Services"
        },
        {
            "category":"Personal",
            "subcategory":"Barber",
            "type":"Services"
        }
    ],
    "sg:phone":"+1 404 209 6925",
    "sg:postcode":"30344",
    "sg:province":"GA",
    "wof:name":"Kater 2 U Beauty Salon",
    "wof:placetype":"venue"
},
  "geometry": {"coordinates":[-84.41862999999999,33.680302],"type":"Point"}
}