{
  "type": "Feature",
  "properties": {
    "iso:country":"US",
    "sg:address":"1151 Jones Rd",
    "sg:city":"Bogart",
    "sg:classifiers":[
        {
            "category":"Professional",
            "subcategory":"Business Services",
            "type":"Services"
        }
    ],
    "sg:phone":"+1 706 548 4033",
    "sg:postcode":"30622",
    "sg:province":"GA",
    "wof:name":"Jj Contracting",
    "wof:placetype":"venue"
},
  "geometry": {"coordinates":[-83.48629,33.912898],"type":"Point"}
}