{
  "type": "Feature",
  "properties": {
    "addr:full":"1726 Gene Nix Rd Cleveland GA 30528",
    "addr:housenumber":"1726",
    "addr:postcode":"30528",
    "addr:street":"Gene Nix Rd",
    "iso:country":"US",
    "sg:address":"1726 Gene Nix Rd",
    "sg:city":"Cleveland",
    "sg:classifiers":[
        {
            "category":"Building & Trades",
            "subcategory":"Landscaping Services",
            "type":"Services"
        }
    ],
    "sg:phone":"+1 706 865 0606",
    "sg:postcode":"30528",
    "sg:province":"GA",
    "sg:tags":[
        "seeding"
    ],
    "wof:name":"S & M Hydro Seeding Inc",
    "wof:placetype":"venue"
},
  "geometry": {"coordinates":[-83.82974900000001,34.564192],"type":"Point"}
}