{
  "type": "Feature",
  "properties": {
    "iso:country":"US",
    "sg:address":"216 S College St",
    "sg:city":"Thomasville",
    "sg:classifiers":[
        {
            "category":"Recreation",
            "type":"Entertainment"
        }
    ],
    "sg:phone":"+1 229 228 1460",
    "sg:postcode":"31792",
    "sg:province":"GA",
    "sg:tags":[
        "hall",
        "halls",
        "ballroom",
        "auditorium"
    ],
    "wof:name":"College Terrace Community Bldg",
    "wof:placetype":"venue"
},
  "geometry": {"coordinates":[-83.98321900000001,30.829154],"type":"Point"}
}