{
  "type": "Feature",
  "properties": {
    "iso:country":"US",
    "sg:address":"494 Owens Rd",
    "sg:city":"Woodbury",
    "sg:classifiers":[
        {
            "category":"Organizations",
            "subcategory":"Religious Organization",
            "type":"Services"
        }
    ],
    "sg:phone":"+1 706 553 2756",
    "sg:postcode":"30293",
    "sg:province":"GA",
    "wof:name":"Caine Creek Baptist Church",
    "wof:placetype":"venue"
},
  "geometry": {"coordinates":[-84.64586799999999,32.975296],"type":"Point"}
}