{
  "type": "Feature",
  "properties": {
    "iso:country":"US",
    "sg:address":"1265 Hwy 411 NE",
    "sg:city":"Cartersville",
    "sg:classifiers":[
        {
            "category":"Home & Garden",
            "subcategory":"Building Materials",
            "type":"Retail Goods"
        }
    ],
    "sg:phone":"+1 770 387 0337",
    "sg:postcode":"30121",
    "sg:province":"GA",
    "wof:name":"Wheelers",
    "wof:placetype":"venue"
},
  "geometry": {"coordinates":[-84.79956799999999,34.202609],"type":"Point"}
}