{
  "type": "Feature",
  "properties": {
    "addr:full":"20 Tatum Heights Dr La Grange GA 30240",
    "addr:housenumber":"20",
    "addr:postcode":"30240",
    "addr:street":"Tatum Heights Dr",
    "iso:country":"US",
    "sg:address":"20 Tatum Heights Dr",
    "sg:city":"La Grange",
    "sg:classifiers":[
        {
            "category":"Building & Trades",
            "subcategory":"Construction",
            "type":"Services"
        }
    ],
    "sg:phone":"+1 706 882 1510",
    "sg:postcode":"30240",
    "sg:province":"GA",
    "sg:tags":[
        "boring",
        "well",
        "drilling"
    ],
    "wof:name":"Hales Well Service",
    "wof:placetype":"venue"
},
  "geometry": {"coordinates":[-85.109307,33.033378],"type":"Point"}
}