{
  "type": "Feature",
  "properties": {
    "iso:country":"US",
    "sg:address":"3094 Narroway Church Cir",
    "sg:city":"Dallas",
    "sg:classifiers":[
        {
            "category":"Shopping",
            "subcategory":"Gifts & Souvenirs",
            "type":"Retail Goods"
        }
    ],
    "sg:phone":"+1 770 445 0843",
    "sg:postcode":"30132",
    "sg:province":"GA",
    "wof:name":"Ws Advertising Gifts Co",
    "wof:placetype":"venue"
},
  "geometry": {"coordinates":[-84.852918,34.02674],"type":"Point"}
}