{
  "type": "Feature",
  "properties": {
    "iso:country":"US",
    "sg:address":"501 Wilmington Island Rd",
    "sg:city":"Savannah",
    "sg:classifiers":[
        {
            "category":"Recreation",
            "type":"Entertainment"
        },
        {
            "category":"Restaurant",
            "type":"Food & Drink"
        }
    ],
    "sg:phone":"+1 912 897 1612",
    "sg:postcode":"31410",
    "sg:province":"GA",
    "sg:tags":[
        "course",
        "eating",
        "golf"
    ],
    "wof:name":"Williamington Island Club",
    "wof:placetype":"venue"
},
  "geometry": {"coordinates":[-80.99154,32.005162],"type":"Point"}
}