{
  "type": "Feature",
  "properties": {
    "iso:country":"US",
    "sg:address":"112 McFalls St",
    "sg:city":"Dalton",
    "sg:classifiers":[
        {
            "category":"Manufacturing",
            "subcategory":"Textiles",
            "type":"Manufacturing & Wholesale Goods"
        }
    ],
    "sg:phone":"+1 706 259 9467",
    "sg:postcode":"30721",
    "sg:province":"GA",
    "sg:tags":[
        "mfg"
    ],
    "wof:name":"Stone Mountain Carpet Mil",
    "wof:placetype":"venue"
},
  "geometry": {"coordinates":[-84.960688,34.801282],"type":"Point"}
}