{
  "type": "Feature",
  "properties": {
    "iso:country":"US",
    "sg:address":"1119 Magnolia St",
    "sg:city":"Americus",
    "sg:classifiers":[
        {
            "category":"Social Services",
            "subcategory":"Child Care",
            "type":"Services"
        }
    ],
    "sg:phone":"+1 229 924 2948",
    "sg:postcode":"31719",
    "sg:province":"GA",
    "wof:name":"Clara Childcare",
    "wof:placetype":"venue"
},
  "geometry": {"coordinates":[-84.244732,32.080975],"type":"Point"}
}