{
  "type": "Feature",
  "properties": {
    "addr:full":"49 Garnet Dr Dahlonega GA 30533",
    "addr:housenumber":"49",
    "addr:postcode":"30533",
    "addr:street":"Garnet Dr",
    "iso:country":"US",
    "sg:address":"49 Garnet Dr",
    "sg:city":"Dahlonega",
    "sg:classifiers":[
        {
            "category":"Utilities",
            "subcategory":"Water",
            "type":"Services"
        }
    ],
    "sg:phone":"+1 706 265 5170",
    "sg:postcode":"30533",
    "sg:province":"GA",
    "sg:tags":[
        "bulk",
        "companies-bottled"
    ],
    "wof:name":"Custom Environmental",
    "wof:placetype":"venue"
},
  "geometry": {"coordinates":[-83.89603200000001,34.575934],"type":"Point"}
}