{
  "type": "Feature",
  "properties": {
    "iso:country":"US",
    "sg:address":"4420 Fairfax Dr",
    "sg:city":"Macon",
    "sg:classifiers":[
        {
            "category":"Professional",
            "type":"Services"
        }
    ],
    "sg:phone":"+1 478 781 7162",
    "sg:postcode":"31206",
    "sg:province":"GA",
    "wof:name":"Childrens Destiny",
    "wof:placetype":"venue"
},
  "geometry": {"coordinates":[-83.697577,32.781248],"type":"Point"}
}