{
  "type": "Feature",
  "properties": {
    "iso:country":"US",
    "sg:address":"1475 Mecaslin St NW # 7101",
    "sg:city":"Atlanta",
    "sg:classifiers":[
        {
            "category":"Professional",
            "subcategory":"Management & Consulting",
            "type":"Services"
        }
    ],
    "sg:phone":"+1 404 849 5236",
    "sg:postcode":"30309",
    "sg:province":"GA",
    "sg:tags":[
        "personnel",
        "consultant"
    ],
    "wof:name":"Mon Cheri Amour",
    "wof:placetype":"venue"
},
  "geometry": {"coordinates":[-84.39979599999999,33.795254],"type":"Point"}
}