{
  "type": "Feature",
  "properties": {
    "addr:full":"889 Veterans Memorial Pkwy SE Mableton GA 30126",
    "addr:housenumber":"889",
    "addr:postcode":"30126",
    "addr:street":"Veterans Memorial Pkwy Se",
    "iso:country":"US",
    "sg:address":"889 Veterans Memorial Pkwy SE",
    "sg:city":"Mableton",
    "sg:classifiers":[
        {
            "category":"Cinema",
            "subcategory":"Movie Rental",
            "type":"Entertainment"
        }
    ],
    "sg:phone":"+1 770 819 9860",
    "sg:postcode":"30126",
    "sg:province":"GA",
    "sg:tags":[
        "leasing",
        "video",
        "disc",
        "tape"
    ],
    "wof:name":"Blockbuster Video",
    "wof:placetype":"venue"
},
  "geometry": {"coordinates":[-84.52728,33.805036],"type":"Point"}
}