{
  "type": "Feature",
  "properties": {
    "iso:country":"US",
    "sg:address":"5257 Bouldercrest Rd",
    "sg:city":"Ellenwood",
    "sg:classifiers":[
        {
            "category":"Retail",
            "subcategory":"Repair Shop",
            "type":"Services"
        }
    ],
    "sg:phone":"+1 770 960 8324",
    "sg:postcode":"30294",
    "sg:province":"GA",
    "sg:tags":[
        "related"
    ],
    "wof:name":"L & A On Site Maintenance",
    "wof:placetype":"venue"
},
  "geometry": {"coordinates":[-84.286743,33.611637],"type":"Point"}
}