{
  "type": "Feature",
  "properties": {
    "addr:full":"3370 Shields Lake Dr SW Marietta GA 30008",
    "addr:housenumber":"3370",
    "addr:postcode":"30008",
    "addr:street":"Shields Lake Dr Sw",
    "iso:country":"US",
    "sg:address":"3370 Shields Lake Dr SW",
    "sg:city":"Marietta",
    "sg:classifiers":[
        {
            "category":"Manufacturing",
            "subcategory":"Wood Products",
            "type":"Manufacturing & Wholesale Goods"
        },
        {
            "category":"Home & Garden",
            "subcategory":"Furniture",
            "type":"Retail Goods"
        }
    ],
    "sg:phone":"+1 770 231 6520",
    "sg:postcode":"30008",
    "sg:province":"GA",
    "sg:tags":[
        "manufacturer",
        "cabinets-wholesale",
        "cabinet"
    ],
    "sg:website":"http://www.ncishows.com",
    "wof:name":"Nci",
    "wof:placetype":"venue"
},
  "geometry": {"coordinates":[-84.604215,33.870563],"type":"Point"}
}