{
  "type": "Feature",
  "properties": {
    "iso:country":"US",
    "sg:address":"1756 New Buckeye Rd",
    "sg:city":"Dublin",
    "sg:classifiers":[
        {
            "category":"Food & Beverages",
            "subcategory":"Groceries & Convenience Stores",
            "type":"Retail Goods"
        }
    ],
    "sg:phone":"+1 478 275 4447",
    "sg:postcode":"31027",
    "sg:province":"GA",
    "wof:name":"Wrights Grocery",
    "wof:placetype":"venue"
},
  "geometry": {"coordinates":[-82.868786,32.687745],"type":"Point"}
}