{
  "type": "Feature",
  "properties": {
    "addr:full":"180 Market Sq Cartersville GA 30120",
    "addr:housenumber":"180",
    "addr:postcode":"30120",
    "addr:street":"Market Sq",
    "iso:country":"US",
    "sg:address":"180 Market Sq",
    "sg:city":"Cartersville",
    "sg:classifiers":[
        {
            "category":"Shopping",
            "subcategory":"Hobbies, Toys, & Games",
            "type":"Retail Goods"
        }
    ],
    "sg:phone":"+1 770 386 8777",
    "sg:postcode":"30120",
    "sg:province":"GA",
    "sg:tags":[
        "craft",
        "supply"
    ],
    "wof:name":"Hobby Lobby Creative Center",
    "wof:placetype":"venue"
},
  "geometry": {"coordinates":[-84.788448,34.176401],"type":"Point"}
}