{
  "type": "Feature",
  "properties": {
    "iso:country":"US",
    "sg:address":"1131 Peggy McMillan Dr",
    "sg:city":"Lithonia",
    "sg:phone":"+1 770 271 9664",
    "sg:postcode":"30058",
    "sg:province":"GA",
    "sg:tags":[
        "equipment",
        "commercial"
    ],
    "wof:name":"United Prodcution Equip",
    "wof:placetype":"venue"
},
  "geometry": {"coordinates":[-84.14731500000001,33.76135],"type":"Point"}
}