{
  "type": "Feature",
  "properties": {
    "addr:full":"424 Loyd Rd Peachtree City GA 30269",
    "addr:housenumber":"424",
    "addr:postcode":"30269",
    "addr:street":"Loyd Rd",
    "iso:country":"US",
    "sg:address":"424 Loyd Rd",
    "sg:city":"Peachtree City",
    "sg:classifiers":[
        {
            "category":"Building & Trades",
            "subcategory":"Locksmith",
            "type":"Services"
        }
    ],
    "sg:phone":"+1 678 269 7225",
    "sg:postcode":"30269",
    "sg:province":"GA",
    "sg:tags":[
        "key"
    ],
    "wof:name":"Universal Emergency Locksmith",
    "wof:placetype":"venue"
},
  "geometry": {"coordinates":[-84.562451,33.434874],"type":"Point"}
}