{
  "type": "Feature",
  "properties": {
    "iso:country":"US",
    "sg:address":"1375 Rock Quarry Rd",
    "sg:city":"Stockbridge",
    "sg:classifiers":[
        {
            "category":"Restaurant",
            "type":"Food & Drink"
        }
    ],
    "sg:phone":"+1 770 506 9664",
    "sg:postcode":"30281",
    "sg:province":"GA",
    "sg:tags":[
        "cuban",
        "caribbean"
    ],
    "sg:website":"www.papisgrill.com",
    "wof:name":"Papi's Cuban & Caribbean Grill",
    "wof:placetype":"venue"
},
  "geometry": {"coordinates":[-84.230026,33.513349],"type":"Point"}
}