{
  "type": "Feature",
  "properties": {
    "addr:full":"23 W C St Toms River GA 31823",
    "addr:housenumber":"23",
    "addr:postcode":"31823",
    "addr:street":"W C St",
    "iso:country":"US",
    "sg:address":"23 W C St",
    "sg:city":"Toms River",
    "sg:classifiers":[
        {
            "category":"Wholesale",
            "subcategory":"Electrical",
            "type":"Manufacturing & Wholesale Goods"
        }
    ],
    "sg:phone":"+1 732 240 3636",
    "sg:postcode":"31823",
    "sg:province":"GA",
    "sg:tags":[
        "telecommunication"
    ],
    "wof:name":"Atlantic Telephone",
    "wof:placetype":"venue"
},
  "geometry": {"coordinates":[-84.82043299999999,32.806787],"type":"Point"}
}