{
  "type": "Feature",
  "properties": {
    "addr:full":"1014 Edgewood Ave NE Atlanta GA 30307",
    "addr:housenumber":"1014",
    "addr:postcode":"30307",
    "addr:street":"Edgewood Ave Ne",
    "iso:country":"US",
    "sg:address":"1014 Edgewood Ave NE",
    "sg:city":"Atlanta",
    "sg:classifiers":[
        {
            "category":"Professional",
            "subcategory":"Management & Consulting",
            "type":"Services"
        }
    ],
    "sg:phone":"+1 404 653 2116",
    "sg:postcode":"30307",
    "sg:province":"GA",
    "sg:tags":[
        "consultant",
        "hospital"
    ],
    "wof:name":"Lane Group Inc",
    "wof:placetype":"venue"
},
  "geometry": {"coordinates":[-84.354814,33.756948],"type":"Point"}
}