{
  "type": "Feature",
  "properties": {
    "iso:country":"US",
    "sg:address":"1149 Pink Goss Rd",
    "sg:city":"Woodstock",
    "sg:classifiers":[
        {
            "category":"Building & Trades",
            "subcategory":"Construction",
            "type":"Services"
        }
    ],
    "sg:phone":"+1 770 475 3092",
    "sg:postcode":"30188",
    "sg:province":"GA",
    "sg:tags":[
        "house"
    ],
    "wof:name":"Vin Ware Construction",
    "wof:placetype":"venue"
},
  "geometry": {"coordinates":[-84.391727,34.137277],"type":"Point"}
}