{
  "type": "Feature",
  "properties": {
    "iso:country":"US",
    "sg:address":"403 Pate St",
    "sg:city":"Hawkinsville",
    "sg:classifiers":[
        {
            "category":"Building & Trades",
            "subcategory":"Electrical",
            "type":"Services"
        }
    ],
    "sg:phone":"+1 478 892 9573",
    "sg:postcode":"31036",
    "sg:province":"GA",
    "sg:tags":[
        "electrical",
        "contractor"
    ],
    "wof:name":"Goodroe Electric Co",
    "wof:placetype":"venue"
},
  "geometry": {"coordinates":[-83.47345199999999,32.274414],"type":"Point"}
}