{
  "type": "Feature",
  "properties": {
    "addr:full":"3907 Lawrenceville Hwy Tucker GA 30084",
    "addr:housenumber":"3907",
    "addr:postcode":"30084",
    "addr:street":"Lawrenceville Hwy",
    "iso:country":"US",
    "sg:address":"3907 Lawrenceville Hwy",
    "sg:city":"Tucker",
    "sg:classifiers":[
        {
            "category":"Retail",
            "subcategory":"Auto Rental",
            "type":"Services"
        }
    ],
    "sg:phone":"+1 770 939 7190",
    "sg:postcode":"30084",
    "sg:province":"GA",
    "sg:tags":[
        "trailer",
        "utility"
    ],
    "wof:name":"Great Escape Rv Rental Inc",
    "wof:placetype":"venue"
},
  "geometry": {"coordinates":[-84.222233,33.849671],"type":"Point"}
}