{
  "type": "Feature",
  "properties": {
    "addr:full":"1417 US Hwy 41 N Tifton GA 31794",
    "addr:housenumber":"1417",
    "addr:postcode":"31794",
    "addr:street":"Us Hwy 41 N",
    "iso:country":"US",
    "sg:address":"1417 US Hwy 41 N",
    "sg:city":"Tifton",
    "sg:classifiers":[
        {
            "category":"Organizations",
            "subcategory":"Religious Organization",
            "type":"Services"
        }
    ],
    "sg:phone":"+1 229 386 0865",
    "sg:postcode":"31794",
    "sg:province":"GA",
    "wof:name":"Mell Baptist Assn Ctr",
    "wof:placetype":"venue"
},
  "geometry": {"coordinates":[-83.518607,31.469793],"type":"Point"}
}