{
  "type": "Feature",
  "properties": {
    "iso:country":"US",
    "sg:address":"302 Northside Dr W",
    "sg:city":"Statesboro",
    "sg:classifiers":[
        {
            "category":"Restaurant",
            "type":"Food & Drink"
        }
    ],
    "sg:phone":"+1 912 764 9995",
    "sg:postcode":"30458",
    "sg:province":"GA",
    "wof:name":"Boyd's Bbq & Country Buffet",
    "wof:placetype":"venue"
},
  "geometry": {"coordinates":[-81.786987,32.455201],"type":"Point"}
}