{
  "type": "Feature",
  "properties": {
    "addr:full":"7141 Pipeline Rd Camilla GA 31730",
    "addr:housenumber":"7141",
    "addr:postcode":"31730",
    "addr:street":"Pipeline Rd",
    "iso:country":"US",
    "sg:address":"7141 Pipeline Rd",
    "sg:city":"Camilla",
    "sg:classifiers":[
        {
            "category":"Place Of Worship",
            "subcategory":"Church",
            "type":"Public Place"
        },
        {
            "category":"Place Of Worship",
            "type":"Public Place"
        }
    ],
    "sg:phone":"+1 229 336 8266",
    "sg:postcode":"31730",
    "sg:province":"GA",
    "sg:tags":[
        "churches-baptist-general",
        "churches-baptist"
    ],
    "wof:name":"Oak Grove Baptist Church",
    "wof:placetype":"venue"
},
  "geometry": {"coordinates":[-84.301039,31.214662],"type":"Point"}
}