{
  "type": "Feature",
  "properties": {
    "addr:full":"2145 Roswell Rd Marietta GA 30062",
    "addr:housenumber":"2145",
    "addr:postcode":"30062",
    "addr:street":"Roswell Rd",
    "iso:country":"US",
    "sg:address":"2145 Roswell Rd",
    "sg:city":"Marietta",
    "sg:classifiers":[
        {
            "category":"Health Services",
            "subcategory":"Dentist",
            "type":"Services"
        }
    ],
    "sg:phone":"+1 770 565 1010",
    "sg:postcode":"30062",
    "sg:province":"GA",
    "wof:name":"Family Dentist",
    "wof:placetype":"venue"
},
  "geometry": {"coordinates":[-84.48969200000001,33.968608],"type":"Point"}
}