{
  "type": "Feature",
  "properties": {
    "addr:full":"2990 Pheasant Dr Decatur GA 30034",
    "addr:housenumber":"2990",
    "addr:postcode":"30034",
    "addr:street":"Pheasant Dr",
    "iso:country":"US",
    "sg:address":"2990 Pheasant Dr",
    "sg:city":"Decatur",
    "sg:classifiers":[
        {
            "category":"Professional",
            "subcategory":"Computer Services",
            "type":"Services"
        }
    ],
    "sg:phone":"+1 404 243 5895",
    "sg:postcode":"30034",
    "sg:province":"GA",
    "sg:tags":[
        "consulting",
        "training"
    ],
    "wof:name":"Internetworking Consultants",
    "wof:placetype":"venue"
},
  "geometry": {"coordinates":[-84.245677,33.698161],"type":"Point"}
}