{
  "type": "Feature",
  "properties": {
    "addr:full":"8217 Brookwood Valley Cir NE Atlanta GA 30309",
    "addr:housenumber":"8217",
    "addr:postcode":"30309",
    "addr:street":"Brookwood Valley Cir Ne",
    "iso:country":"US",
    "sg:address":"8217 Brookwood Valley Cir NE",
    "sg:city":"Atlanta",
    "sg:classifiers":[
        {
            "category":"Professional",
            "subcategory":"Management & Consulting",
            "type":"Services"
        }
    ],
    "sg:phone":"+1 404 355 4937",
    "sg:postcode":"30309",
    "sg:province":"GA",
    "sg:tags":[
        "marketing",
        "consultant"
    ],
    "wof:name":"Fortune Hi-Tech Marketing",
    "wof:placetype":"venue"
},
  "geometry": {"coordinates":[-84.391201,33.809063],"type":"Point"}
}