{
  "type": "Feature",
  "properties": {
    "iso:country":"US",
    "sg:address":"8 Harrell Dr",
    "sg:city":"Savannah",
    "sg:classifiers":[
        {
            "category":"Personal",
            "subcategory":"Beauty Salon",
            "type":"Services"
        }
    ],
    "sg:phone":"+1 912 965 0084",
    "sg:postcode":"31408",
    "sg:province":"GA",
    "sg:tags":[
        "shop"
    ],
    "wof:name":"Visions Of Ethnicity",
    "wof:placetype":"venue"
},
  "geometry": {"coordinates":[-81.15388900000001,32.103036],"type":"Point"}
}