{
  "type": "Feature",
  "properties": {
    "iso:country":"US",
    "sg:address":"383-C Marietta Street",
    "sg:city":"Atlanta",
    "sg:phone":"+1 404 826 5213",
    "sg:postcode":"30313",
    "sg:province":"GA",
    "sg:website":"http://www.khemetbotanicals.com",
    "wof:name":"Khemet Botanicals Organic Body Shoppe, Hair Studio & Spa",
    "wof:placetype":"venue"
},
  "geometry": {"coordinates":[-84.39717899999999,33.76339],"type":"Point"}
}