{
  "type": "Feature",
  "properties": {
    "iso:country":"US",
    "sg:address":"2492 Martin Luther King Jr Dr SW",
    "sg:city":"Atlanta",
    "sg:classifiers":[
        {
            "category":"Autos & Motor Vehicles",
            "subcategory":"Automobile Sales",
            "type":"Retail Goods"
        },
        {
            "category":"Autos & Motor Vehicles",
            "subcategory":"Auto Supplies",
            "type":"Retail Goods"
        },
        {
            "category":"Retail",
            "subcategory":"Auto Repair",
            "type":"Services"
        }
    ],
    "sg:phone":"+1 404 691 2290",
    "sg:postcode":"30311",
    "sg:province":"GA",
    "sg:tags":[
        "exhaust",
        "oil",
        "car",
        "system",
        "accessory",
        "lube",
        "part",
        "brake",
        "muffler",
        "new"
    ],
    "wof:name":"M & R Car Care Center",
    "wof:placetype":"venue"
},
  "geometry": {"coordinates":[-84.46907,33.75227],"type":"Point"}
}