{
  "type": "Feature",
  "properties": {
    "iso:country":"US",
    "sg:address":"618 S Patterson St",
    "sg:city":"Valdosta",
    "sg:classifiers":[
        {
            "category":"Freight",
            "type":"Transportation"
        }
    ],
    "sg:phone":"+1 229 244 1361",
    "sg:postcode":"31601",
    "sg:province":"GA",
    "sg:tags":[
        "building",
        "house",
        "mover"
    ],
    "wof:name":"Southeast Propane",
    "wof:placetype":"venue"
},
  "geometry": {"coordinates":[-83.275356,30.824142],"type":"Point"}
}