{
  "type": "Feature",
  "properties": {
    "addr:full":"3856 Tawny Birch Ct Decatur GA 30034",
    "addr:housenumber":"3856",
    "addr:postcode":"30034",
    "addr:street":"Tawny Birch Ct",
    "iso:country":"US",
    "sg:address":"3856 Tawny Birch Ct",
    "sg:city":"Decatur",
    "sg:classifiers":[
        {
            "category":"Banks & Credit Unions",
            "subcategory":"Financial Services",
            "type":"Services"
        }
    ],
    "sg:phone":"+1 404 288 4638",
    "sg:postcode":"30034",
    "sg:province":"GA",
    "sg:tags":[
        "mortgage"
    ],
    "wof:name":"First Start Mortgage",
    "wof:placetype":"venue"
},
  "geometry": {"coordinates":[-84.231629,33.691079],"type":"Point"}
}