{
  "type": "Feature",
  "properties": {
    "iso:country":"US",
    "sg:address":"77 Seminole Trl",
    "sg:city":"Austell",
    "sg:classifiers":[
        {
            "category":"Building & Trades",
            "subcategory":"Construction",
            "type":"Services"
        }
    ],
    "sg:phone":"+1 770 739 0532",
    "sg:postcode":"30168",
    "sg:province":"GA",
    "sg:tags":[
        "equipment",
        "supply",
        "drywall",
        "contractor"
    ],
    "wof:name":"Specialty Drywall",
    "wof:placetype":"venue"
},
  "geometry": {"coordinates":[-84.62763200000001,33.801884],"type":"Point"}
}