{
  "type": "Feature",
  "properties": {
    "iso:country":"US",
    "sg:address":"8530 Cobb Center Dr",
    "sg:city":"Kennesaw",
    "sg:classifiers":[
        {
            "category":"Manufacturing",
            "subcategory":"Building Materials",
            "type":"Manufacturing & Wholesale Goods"
        }
    ],
    "sg:phone":"+1 770 423 9590",
    "sg:postcode":"30152",
    "sg:province":"GA",
    "sg:tags":[
        "cabinet"
    ],
    "sg:website":"www.centennialkitchens.com",
    "wof:name":"Centennial Kitchens",
    "wof:placetype":"venue"
},
  "geometry": {"coordinates":[-84.609188,33.991739],"type":"Point"}
}