{
  "type": "Feature",
  "properties": {
    "iso:country":"US",
    "sg:address":"1051 Villa Ct SE Apt B4",
    "sg:city":"Atlanta",
    "sg:classifiers":[
        {
            "category":"Professional",
            "subcategory":"Art Services",
            "type":"Services"
        }
    ],
    "sg:phone":"+1 678 202 1879",
    "sg:postcode":"30316",
    "sg:province":"GA",
    "sg:tags":[
        "designer",
        "display",
        "producer"
    ],
    "wof:name":"PA Creative Designs",
    "wof:placetype":"venue"
},
  "geometry": {"coordinates":[-84.357973,33.726163],"type":"Point"}
}