{
  "type": "Feature",
  "properties": {
    "addr:full":"3580 Piedmont Rd NE # 113 Atlanta GA 30305",
    "addr:housenumber":"3580",
    "addr:postcode":"30305",
    "addr:street":"Piedmont Rd Ne # 113",
    "iso:country":"US",
    "sg:address":"3580 Piedmont Rd NE # 113",
    "sg:city":"Atlanta",
    "sg:classifiers":[
        {
            "category":"Shopping",
            "subcategory":"Clothing, Apparel, & Fashions",
            "type":"Retail Goods"
        }
    ],
    "sg:phone":"+1 404 231 0552",
    "sg:postcode":"30305",
    "sg:province":"GA",
    "sg:tags":[
        "tuxedo"
    ],
    "sg:website":"http://www.tuxedocosmeticandrestorativedentistry.co",
    "wof:name":"Tuxedo Dental Associates Pc",
    "wof:placetype":"venue"
},
  "geometry": {"coordinates":[-84.379936,33.851785],"type":"Point"}
}