{
  "type": "Feature",
  "properties": {
    "addr:full":"1306 Countryside Pl Smyrna GA 30080",
    "addr:housenumber":"1306",
    "addr:postcode":"30080",
    "addr:street":"Countryside Pl",
    "iso:country":"US",
    "sg:address":"1306 Countryside Pl",
    "sg:city":"Smyrna",
    "sg:classifiers":[
        {
            "category":"Mining & Drilling",
            "type":"Manufacturing & Wholesale Goods"
        }
    ],
    "sg:phone":"+1 770 438 0002",
    "sg:postcode":"30080",
    "sg:province":"GA",
    "sg:tags":[
        "extracting",
        "engaged",
        "processing",
        "metal",
        "re"
    ],
    "wof:name":"Omnicast Inc",
    "wof:placetype":"venue"
},
  "geometry": {"coordinates":[-84.491591,33.880607],"type":"Point"}
}