{
  "type": "Feature",
  "properties": {
    "iso:country":"US",
    "sg:address":"330 Turner McCall Blvd",
    "sg:city":"Rome",
    "sg:classifiers":[
        {
            "category":"Health Services",
            "subcategory":"Doctor",
            "type":"Services"
        }
    ],
    "sg:phone":"+1 706 234 7906",
    "sg:postcode":"30165",
    "sg:province":"GA",
    "sg:tags":[
        "physician",
        "surgeon"
    ],
    "wof:name":"Centrex Pediatrics",
    "wof:placetype":"venue"
},
  "geometry": {"coordinates":[-85.179326,34.260331],"type":"Point"}
}