{
  "type": "Feature",
  "properties": {
    "addr:full":"850 Univeter Rd Canton GA 30115",
    "addr:housenumber":"850",
    "addr:postcode":"30115",
    "addr:street":"Univeter Rd",
    "iso:country":"US",
    "sg:address":"850 Univeter Rd",
    "sg:city":"Canton",
    "sg:classifiers":[
        {
            "category":"Manufacturing",
            "subcategory":"Glass & Minerals",
            "type":"Manufacturing & Wholesale Goods"
        }
    ],
    "sg:phone":"+1 770 345 5156",
    "sg:postcode":"30115",
    "sg:province":"GA",
    "sg:tags":[
        "insulation"
    ],
    "sg:website":"www.schoenins.com",
    "wof:name":"Schoen Insulation Svc Inc",
    "wof:placetype":"venue"
},
  "geometry": {"coordinates":[-84.498464,34.195039],"type":"Point"}
}