{
  "type": "Feature",
  "properties": {
    "addr:full":"7350 Beechwood Ave Savannah GA 31406",
    "addr:housenumber":"7350",
    "addr:postcode":"31406",
    "addr:street":"Beechwood Ave",
    "iso:country":"US",
    "sg:address":"7350 Beechwood Ave",
    "sg:city":"Savannah",
    "sg:classifiers":[
        {
            "category":"Building & Trades",
            "subcategory":"Construction",
            "type":"Services"
        }
    ],
    "sg:phone":"+1 912 352 7300",
    "sg:postcode":"31406",
    "sg:province":"GA",
    "sg:tags":[
        "contractor"
    ],
    "wof:name":"Four Season Pools & Spas",
    "wof:placetype":"venue"
},
  "geometry": {"coordinates":[-81.07624,31.983622],"type":"Point"}
}