{
  "type": "Feature",
  "properties": {
    "iso:country":"US",
    "sg:address":"3100 Cumberland Blvd SE Ste 1400",
    "sg:city":"Atlanta",
    "sg:classifiers":[
        {
            "category":"Professional",
            "subcategory":"Lawyer & Legal Services",
            "type":"Services"
        }
    ],
    "sg:phone":"+1 770 541 7444",
    "sg:postcode":"30339",
    "sg:province":"GA",
    "sg:website":"www.mkiplaw.com",
    "wof:name":"Myers & Kaplan Intellectual Property Law Llc",
    "wof:placetype":"venue"
},
  "geometry": {"coordinates":[-84.46592699999999,33.877684],"type":"Point"}
}