{
  "type": "Feature",
  "properties": {
    "iso:country":"US",
    "sg:address":"185 NW Broad St",
    "sg:city":"Jesup",
    "sg:classifiers":[
        {
            "category":"Food & Beverages",
            "subcategory":"Bakery",
            "type":"Retail Goods"
        }
    ],
    "sg:phone":"+1 912 427 9956",
    "sg:postcode":"31545",
    "sg:province":"GA",
    "sg:tags":[
        "baker"
    ],
    "wof:name":"Sugar & Spice Bake Shop",
    "wof:placetype":"venue"
},
  "geometry": {"coordinates":[-81.877385,31.60993],"type":"Point"}
}