{
  "type": "Feature",
  "properties": {
    "iso:country":"US",
    "sg:address":"90 Martin Luther King Jr Dr",
    "sg:city":"Forsyth",
    "sg:classifiers":[
        {
            "category":"Health Services",
            "subcategory":"Clinic",
            "type":"Services"
        }
    ],
    "sg:phone":"+1 770 775 1080",
    "sg:postcode":"31029",
    "sg:province":"GA",
    "sg:tags":[
        "home",
        "care"
    ],
    "wof:name":"Caresouth Home Health Services",
    "wof:placetype":"venue"
},
  "geometry": {"coordinates":[-83.946367,33.032985],"type":"Point"}
}