{
  "type": "Feature",
  "properties": {
    "iso:country":"US",
    "sg:address":"1707 New Hope Rd",
    "sg:city":"Locust Grove",
    "sg:classifiers":[
        {
            "category":"Building & Trades",
            "subcategory":"Construction",
            "type":"Services"
        }
    ],
    "sg:phone":"+1 770 914 6248",
    "sg:postcode":"30248",
    "sg:province":"GA",
    "sg:tags":[
        "contractor"
    ],
    "wof:name":"Oxley Contracting Inc",
    "wof:placetype":"venue"
},
  "geometry": {"coordinates":[-84.02502699999999,33.399775],"type":"Point"}
}