{
  "type": "Feature",
  "properties": {
    "iso:country":"US",
    "sg:address":"414 S Patterson St",
    "sg:city":"Valdosta",
    "sg:classifiers":[
        {
            "category":"Building & Trades",
            "subcategory":"Cleaning & Sanitation",
            "type":"Services"
        },
        {
            "category":"Real Estate",
            "subcategory":"Real Estate Operator",
            "type":"Services"
        }
    ],
    "sg:phone":"+1 229 244 3925",
    "sg:postcode":"31601",
    "sg:province":"GA",
    "sg:tags":[
        "used",
        "appliance",
        "agent",
        "maid",
        "butler",
        "retail",
        "rental"
    ],
    "wof:name":"Maxi Maids",
    "wof:placetype":"venue"
},
  "geometry": {"coordinates":[-83.27829199999999,30.829608],"type":"Point"}
}