{
  "type": "Feature",
  "properties": {
    "addr:full":"330 Ash St Macon GA 31201",
    "addr:housenumber":"330",
    "addr:postcode":"31201",
    "addr:street":"Ash St",
    "iso:country":"US",
    "sg:address":"330 Ash St",
    "sg:city":"Macon",
    "sg:classifiers":[
        {
            "category":"Wholesale",
            "subcategory":"Metals & Minerals",
            "type":"Manufacturing & Wholesale Goods"
        }
    ],
    "sg:phone":"+1 478 743 7473",
    "sg:postcode":"31201",
    "sg:province":"GA",
    "sg:tags":[
        "pipe"
    ],
    "wof:name":"American Piping Supply",
    "wof:placetype":"venue"
},
  "geometry": {"coordinates":[-83.63384000000001,32.823594],"type":"Point"}
}