{
  "type": "Feature",
  "properties": {
    "iso:country":"US",
    "sg:address":"4855 Lansbury Dr NE",
    "sg:city":"Atlanta",
    "sg:classifiers":[
        {
            "category":"Building & Trades",
            "subcategory":"Construction",
            "type":"Services"
        }
    ],
    "sg:phone":"+1 404 255 3232",
    "sg:postcode":"30342",
    "sg:province":"GA",
    "sg:tags":[
        "designer",
        "dealer",
        "pool",
        "swimming"
    ],
    "wof:name":"Pristine Pools Water Features",
    "wof:placetype":"venue"
},
  "geometry": {"coordinates":[-84.37088799999999,33.885438],"type":"Point"}
}