{
  "type": "Feature",
  "properties": {
    "addr:full":"4130 S Main St Acworth GA 30101",
    "addr:housenumber":"4130",
    "addr:postcode":"30101",
    "addr:street":"S Main St",
    "iso:country":"US",
    "sg:address":"4130 S Main St",
    "sg:city":"Acworth",
    "sg:classifiers":[
        {
            "category":"Autos & Motor Vehicles",
            "subcategory":"Auto Supplies",
            "type":"Retail Goods"
        }
    ],
    "sg:phone":"+1 770 975 0989",
    "sg:postcode":"30101",
    "sg:province":"GA",
    "sg:tags":[
        "automobile",
        "parts"
    ],
    "wof:name":"NAPA Auto Parts",
    "wof:placetype":"venue"
},
  "geometry": {"coordinates":[-84.66457800000001,34.05898],"type":"Point"}
}