{
  "type": "Feature",
  "properties": {
    "iso:country":"US",
    "sg:address":"261 Cleveland St",
    "sg:city":"Ringgold",
    "sg:classifiers":[
        {
            "category":"Retail",
            "subcategory":"Auto Repair",
            "type":"Services"
        }
    ],
    "sg:phone":"+1 706 935 3281",
    "sg:postcode":"30736",
    "sg:province":"GA",
    "sg:tags":[
        "repairing",
        "automobile"
    ],
    "wof:name":"Ringgold Service Ctr",
    "wof:placetype":"venue"
},
  "geometry": {"coordinates":[-85.112448,34.917463],"type":"Point"}
}