{
  "type": "Feature",
  "properties": {
    "iso:country":"US",
    "sg:address":"122 Fire Thorn Ln",
    "sg:city":"Pooler",
    "sg:classifiers":[
        {
            "category":"Personal",
            "type":"Services"
        }
    ],
    "sg:phone":"+1 912 988 3369",
    "sg:postcode":"31322",
    "sg:province":"GA",
    "sg:tags":[
        "consultant",
        "planning",
        "wedding"
    ],
    "wof:name":"Defining Moments",
    "wof:placetype":"venue"
},
  "geometry": {"coordinates":[-81.25600900000001,32.148429],"type":"Point"}
}