{
  "type": "Feature",
  "properties": {
    "addr:full":"106 State Rte 2 Commerce GA 30525",
    "addr:housenumber":"106",
    "addr:postcode":"30525",
    "addr:street":"State Rte 2",
    "iso:country":"US",
    "sg:address":"106 State Rte 2",
    "sg:city":"Commerce",
    "sg:classifiers":[
        {
            "category":"Shopping",
            "subcategory":"Clothing, Apparel, & Fashions",
            "type":"Retail Goods"
        }
    ],
    "sg:phone":"+1 706 335 7148",
    "sg:postcode":"30525",
    "sg:province":"GA",
    "wof:name":"LEggs - Hnes - Bali - Playtex",
    "wof:placetype":"venue"
},
  "geometry": {"coordinates":[-83.39833900000001,34.873597],"type":"Point"}
}