{
  "type": "Feature",
  "properties": {
    "addr:full":"151 Racetrack Rd McDonough GA 30253",
    "addr:housenumber":"151",
    "addr:postcode":"30253",
    "addr:street":"Racetrack Rd",
    "iso:country":"US",
    "sg:address":"151 Racetrack Rd",
    "sg:city":"McDonough",
    "sg:classifiers":[
        {
            "category":"Retail",
            "subcategory":"Auto Repair",
            "type":"Services"
        }
    ],
    "sg:phone":"+1 770 957 7877",
    "sg:postcode":"30253",
    "sg:province":"GA",
    "wof:name":"C L N Auto Service",
    "wof:placetype":"venue"
},
  "geometry": {"coordinates":[-84.139397,33.430901],"type":"Point"}
}