{
  "type": "Feature",
  "properties": {
    "iso:country":"US",
    "sg:address":"159 N Broad St",
    "sg:city":"Winder",
    "sg:classifiers":[
        {
            "category":"Social Services",
            "type":"Services"
        }
    ],
    "sg:phone":"+1 770 868 8621",
    "sg:postcode":"30680",
    "sg:province":"GA",
    "wof:name":"Mg Counseling Service Inc",
    "wof:placetype":"venue"
},
  "geometry": {"coordinates":[-83.714553,33.995867],"type":"Point"}
}