{
  "type": "Feature",
  "properties": {
    "iso:country":"US",
    "sg:address":"4201 S Jimmy Dr",
    "sg:city":"Rocky Face",
    "sg:classifiers":[
        {
            "category":"Shopping",
            "subcategory":"Bicycles & Sporting Goods",
            "type":"Retail Goods"
        }
    ],
    "sg:phone":"+1 706 673 4144",
    "sg:postcode":"30740",
    "sg:province":"GA",
    "wof:name":"Hitching Post",
    "wof:placetype":"venue"
},
  "geometry": {"coordinates":[-85.115999,34.729332],"type":"Point"}
}