{
  "type": "Feature",
  "properties": {
    "iso:country":"US",
    "sg:address":"504 Ash Ln",
    "sg:city":"Monroe",
    "sg:classifiers":[
        {
            "category":"Building & Trades",
            "subcategory":"Construction",
            "type":"Services"
        }
    ],
    "sg:phone":"+1 770 267 4092",
    "sg:postcode":"30655",
    "sg:province":"GA",
    "sg:tags":[
        "house"
    ],
    "wof:name":"Ansleys Home Improvement",
    "wof:placetype":"venue"
},
  "geometry": {"coordinates":[-83.698618,33.788313],"type":"Point"}
}