{
  "type": "Feature",
  "properties": {
    "iso:country":"US",
    "sg:address":"4576 Gilhams Rd",
    "sg:city":"Roswell",
    "sg:classifiers":[
        {
            "category":"Real Estate",
            "subcategory":"Real Estate Operator",
            "type":"Services"
        }
    ],
    "sg:phone":"+1 770 993 9423",
    "sg:postcode":"30075",
    "sg:province":"GA",
    "sg:tags":[
        "building",
        "nonresidential"
    ],
    "wof:name":"Pine Properties Inc",
    "wof:placetype":"venue"
},
  "geometry": {"coordinates":[-84.41686900000001,34.048745],"type":"Point"}
}