{
  "type": "Feature",
  "properties": {
    "addr:full":"411 Edgewater Cir Macon GA 31220",
    "addr:housenumber":"411",
    "addr:postcode":"31220",
    "addr:street":"Edgewater Cir",
    "iso:country":"US",
    "sg:address":"411 Edgewater Cir",
    "sg:city":"Macon",
    "sg:classifiers":[
        {
            "category":"Shopping",
            "subcategory":"Florist",
            "type":"Retail Goods"
        }
    ],
    "sg:phone":"+1 478 477 4814",
    "sg:postcode":"31220",
    "sg:province":"GA",
    "wof:name":"Anfranz Gift & Flower Shop",
    "wof:placetype":"venue"
},
  "geometry": {"coordinates":[-83.76621400000001,32.875341],"type":"Point"}
}