{
  "type": "Feature",
  "properties": {
    "addr:full":"1044 W Main St Lakeland GA 31635",
    "addr:housenumber":"1044",
    "addr:postcode":"31635",
    "addr:street":"W Main St",
    "iso:country":"US",
    "sg:address":"1044 W Main St",
    "sg:city":"Lakeland",
    "sg:classifiers":[
        {
            "category":"Real Estate",
            "subcategory":"Real Estate Operator",
            "type":"Services"
        }
    ],
    "sg:phone":"+1 229 482 3600",
    "sg:postcode":"31635",
    "sg:province":"GA",
    "sg:tags":[
        "apartment"
    ],
    "wof:name":"Lakewood Apartments",
    "wof:placetype":"venue"
},
  "geometry": {"coordinates":[-83.091014,31.037986],"type":"Point"}
}