{
  "type": "Feature",
  "properties": {
    "iso:country":"US",
    "sg:address":"1849 Appling Harlem Rd",
    "sg:city":"Appling",
    "sg:classifiers":[
        {
            "category":"Government",
            "subcategory":"Office",
            "type":"Public Place"
        }
    ],
    "sg:phone":"+1 706 541 1516",
    "sg:postcode":"30802",
    "sg:province":"GA",
    "sg:tags":[
        "government-united",
        "state"
    ],
    "wof:name":"U S Government",
    "wof:placetype":"venue"
},
  "geometry": {"coordinates":[-82.314802,33.538157],"type":"Point"}
}