{
  "type": "Feature",
  "properties": {
    "addr:full":"2301 Wrightsboro Rd Augusta GA 30904",
    "addr:housenumber":"2301",
    "addr:postcode":"30904",
    "addr:street":"Wrightsboro Rd",
    "iso:country":"US",
    "sg:address":"2301 Wrightsboro Rd",
    "sg:city":"Augusta",
    "sg:classifiers":[
        {
            "category":"Health Services",
            "subcategory":"Health Practitioner",
            "type":"Services"
        },
        {
            "category":"Social Services",
            "type":"Services"
        }
    ],
    "sg:phone":"+1 706 733 7029",
    "sg:postcode":"30904",
    "sg:province":"GA",
    "sg:tags":[
        "psychologist"
    ],
    "wof:name":"Summerville Professionals",
    "wof:placetype":"venue"
},
  "geometry": {"coordinates":[-82.02149199999999,33.468049],"type":"Point"}
}