{
  "type": "Feature",
  "properties": {
    "iso:country":"US",
    "sg:address":"3523 Braselton Hwy Ste C-600",
    "sg:city":"Dacula",
    "sg:classifiers":[
        {
            "category":"Shopping",
            "subcategory":"Bicycles & Sporting Goods",
            "type":"Retail Goods"
        },
        {
            "category":"Sports & Exercise",
            "subcategory":"Bicycle Rental",
            "type":"Entertainment"
        }
    ],
    "sg:phone":"+1 770 945 7770",
    "sg:postcode":"30019",
    "sg:province":"GA",
    "sg:tags":[
        "bike"
    ],
    "sg:website":"www.knightbikesandskateboards.com",
    "wof:name":"Knight Bikes and Skateboards",
    "wof:placetype":"venue"
},
  "geometry": {"coordinates":[-83.911614,34.069683],"type":"Point"}
}