{
  "type": "Feature",
  "properties": {
    "addr:full":"255 Scoggins Rd Dallas GA 30157",
    "addr:housenumber":"255",
    "addr:postcode":"30157",
    "addr:street":"Scoggins Rd",
    "iso:country":"US",
    "sg:address":"255 Scoggins Rd",
    "sg:city":"Dallas",
    "sg:classifiers":[
        {
            "category":"Personal",
            "subcategory":"Beauty Salon",
            "type":"Services"
        }
    ],
    "sg:phone":"+1 770 445 6686",
    "sg:postcode":"30157",
    "sg:province":"GA",
    "wof:name":"Amy's Hair & Tanning",
    "wof:placetype":"venue"
},
  "geometry": {"coordinates":[-84.84507000000001,33.866575],"type":"Point"}
}