{
  "type": "Feature",
  "properties": {
    "addr:full":"1118 Knight Dr Columbus GA 31906",
    "addr:housenumber":"1118",
    "addr:postcode":"31906",
    "addr:street":"Knight Dr",
    "iso:country":"US",
    "sg:address":"1118 Knight Dr",
    "sg:city":"Columbus",
    "sg:classifiers":[
        {
            "category":"Building & Trades",
            "subcategory":"Construction",
            "type":"Services"
        }
    ],
    "sg:phone":"+1 706 563 2264",
    "sg:postcode":"31906",
    "sg:province":"GA",
    "sg:tags":[
        "contractor"
    ],
    "wof:name":"Bbs Masonry Inc",
    "wof:placetype":"venue"
},
  "geometry": {"coordinates":[-84.93857,32.469514],"type":"Point"}
}