{
  "type": "Feature",
  "properties": {
    "addr:full":"365 Cattlemans Cir Mcdonough GA 30248",
    "addr:housenumber":"365",
    "addr:postcode":"30248",
    "addr:street":"Cattlemans Cir",
    "iso:country":"US",
    "sg:address":"365 Cattlemans Cir",
    "sg:city":"Mcdonough",
    "sg:classifiers":[
        {
            "category":"Professional",
            "subcategory":"Computer Services",
            "type":"Services"
        }
    ],
    "sg:phone":"+1 678 468 2747",
    "sg:postcode":"30248",
    "sg:province":"GA",
    "wof:name":"Curioxity",
    "wof:placetype":"venue"
},
  "geometry": {"coordinates":[-84.05984100000001,33.422218],"type":"Point"}
}