{
  "type": "Feature",
  "properties": {
    "iso:country":"US",
    "sg:address":"1400 Southlake Mall",
    "sg:city":"Morrow",
    "sg:classifiers":[
        {
            "category":"Shopping",
            "subcategory":"Baby Store",
            "type":"Retail Goods"
        },
        {
            "category":"Shopping",
            "subcategory":"Department Store",
            "type":"Retail Goods"
        },
        {
            "category":"Shopping",
            "subcategory":"Clothing, Apparel, & Fashions",
            "type":"Retail Goods"
        }
    ],
    "sg:phone":"+1 770 961 6211",
    "sg:postcode":"30260",
    "sg:province":"GA",
    "sg:tags":[
        "furniture",
        "clothing",
        "gear",
        "women's"
    ],
    "sg:website":"www.JCPenney.com",
    "wof:name":"JCPenney",
    "wof:placetype":"venue"
},
  "geometry": {"coordinates":[-84.35471200000001,33.576495],"type":"Point"}
}