{
  "type": "Feature",
  "properties": {
    "addr:full":"1646 Bradley Park Dr Columbus GA 31904",
    "addr:housenumber":"1646",
    "addr:postcode":"31904",
    "addr:street":"Bradley Park Dr",
    "iso:country":"US",
    "sg:address":"1646 Bradley Park Dr",
    "sg:city":"Columbus",
    "sg:classifiers":[
        {
            "category":"Restaurant",
            "type":"Food & Drink"
        }
    ],
    "sg:menulink":"http://www.allmenus.com/ga/columbus/140446-waffle-house/menu/",
    "sg:phone":"+1 770 781 4255",
    "sg:postcode":"31904",
    "sg:province":"GA",
    "sg:tags":[
        "american"
    ],
    "wof:name":"Waffle House",
    "wof:placetype":"venue"
},
  "geometry": {"coordinates":[-84.96706399999999,32.532244],"type":"Point"}
}