{
  "type": "Feature",
  "properties": {
    "addr:full":"3143 Canton Rd Marietta GA 30066",
    "addr:housenumber":"3143",
    "addr:postcode":"30066",
    "addr:street":"Canton Rd",
    "iso:country":"US",
    "sg:address":"3143 Canton Rd",
    "sg:city":"Marietta",
    "sg:classifiers":[
        {
            "category":"Wholesale",
            "subcategory":"Drugs",
            "type":"Manufacturing & Wholesale Goods"
        }
    ],
    "sg:phone":"+1 678 766 0686",
    "sg:postcode":"30066",
    "sg:province":"GA",
    "sg:tags":[
        "orthopedic",
        "devices"
    ],
    "wof:name":"Relieve Pain Today",
    "wof:placetype":"venue"
},
  "geometry": {"coordinates":[-84.52794799999999,34.029312],"type":"Point"}
}