{
  "type": "Feature",
  "properties": {
    "iso:country":"US",
    "sg:address":"111 Petrol Pt",
    "sg:city":"Peachtree City",
    "sg:classifiers":[
        {
            "category":"Personal",
            "subcategory":"Massage",
            "type":"Services"
        }
    ],
    "sg:phone":"+1 770 486 9233",
    "sg:postcode":"30269",
    "sg:province":"GA",
    "wof:name":"Peachtree City Therapeutic Massage",
    "wof:placetype":"venue"
},
  "geometry": {"coordinates":[-84.560799,33.411499],"type":"Point"}
}