{
  "type": "Feature",
  "properties": {
    "iso:country":"US",
    "sg:address":"1321 W Nancy Creek Dr NE",
    "sg:city":"Atlanta",
    "sg:classifiers":[
        {
            "category":"Professional",
            "subcategory":"Management & Consulting",
            "type":"Services"
        }
    ],
    "sg:phone":"+1 770 458 7070",
    "sg:postcode":"30319",
    "sg:province":"GA",
    "sg:tags":[
        "business"
    ],
    "wof:name":"Yonah Environmental Serv",
    "wof:placetype":"venue"
},
  "geometry": {"coordinates":[-84.335497,33.904495],"type":"Point"}
}