{
  "type": "Feature",
  "properties": {
    "addr:full":"204 Fairview Park Dr Dublin GA 31021",
    "addr:housenumber":"204",
    "addr:postcode":"31021",
    "addr:street":"Fairview Park Dr",
    "iso:country":"US",
    "sg:address":"204 Fairview Park Dr",
    "sg:city":"Dublin",
    "sg:classifiers":[
        {
            "category":"Health Services",
            "subcategory":"Dentist",
            "type":"Services"
        }
    ],
    "sg:phone":"+1 478 272 6777",
    "sg:postcode":"31021",
    "sg:province":"GA",
    "sg:tags":[
        "dental",
        "hygienist"
    ],
    "wof:name":"Clardy, Richard DMD LLC",
    "wof:placetype":"venue"
},
  "geometry": {"coordinates":[-82.953626,32.531922],"type":"Point"}
}