{
  "type": "Feature",
  "properties": {
    "addr:full":"5710 White Bluff Rd Savannah GA 31405",
    "addr:housenumber":"5710",
    "addr:postcode":"31405",
    "addr:street":"White Bluff Rd",
    "iso:country":"US",
    "sg:address":"5710 White Bluff Rd",
    "sg:city":"Savannah",
    "sg:classifiers":[
        {
            "category":"Travel",
            "subcategory":"Hotels & Motels",
            "type":"Entertainment"
        }
    ],
    "sg:phone":"+1 912 356 3266",
    "sg:postcode":"31405",
    "sg:province":"GA",
    "wof:name":"Residence Inn-Savannah Midtown",
    "wof:placetype":"venue"
},
  "geometry": {"coordinates":[-81.113617,32.020514],"type":"Point"}
}