{
  "type": "Feature",
  "properties": {
    "addr:full":"3849 Rupp Rd Ochlocknee GA 31773",
    "addr:housenumber":"3849",
    "addr:postcode":"31773",
    "addr:street":"Rupp Rd",
    "iso:country":"US",
    "sg:address":"3849 Rupp Rd",
    "sg:city":"Ochlocknee",
    "sg:phone":"+1 229 683 3681",
    "sg:postcode":"31773",
    "sg:province":"GA",
    "sg:tags":[
        "farm",
        "wheat"
    ],
    "wof:name":"Ed Guy",
    "wof:placetype":"venue"
},
  "geometry": {"coordinates":[-84.01514299999999,31.01419],"type":"Point"}
}