{
  "type": "Feature",
  "properties": {
    "iso:country":"US",
    "sg:address":"5197 Salem Rd",
    "sg:city":"Lithonia",
    "sg:classifiers":[
        {
            "category":"Place Of Worship",
            "subcategory":"Church",
            "type":"Public Place"
        },
        {
            "category":"Place Of Worship",
            "type":"Public Place"
        }
    ],
    "sg:phone":"+1 770 981 2601",
    "sg:postcode":"30038",
    "sg:province":"GA",
    "sg:tags":[
        "churches-presbyterian-arp",
        "churches-presbyterian"
    ],
    "wof:name":"First African Presbyterian Church",
    "wof:placetype":"venue"
},
  "geometry": {"coordinates":[-84.175786,33.678522],"type":"Point"}
}