{
  "type": "Feature",
  "properties": {
    "iso:country":"US",
    "sg:address":"894 Clements St",
    "sg:city":"Thomson",
    "sg:classifiers":[
        {
            "category":"Organizations",
            "subcategory":"Religious Organization",
            "type":"Services"
        }
    ],
    "sg:phone":"+1 706 595 4323",
    "sg:postcode":"30824",
    "sg:province":"GA",
    "wof:name":"New Hope Christian Church",
    "wof:placetype":"venue"
},
  "geometry": {"coordinates":[-82.48415300000001,33.477267],"type":"Point"}
}