{
  "type": "Feature",
  "properties": {
    "addr:full":"5441 Shirewick Ln Lithonia GA 30058",
    "addr:housenumber":"5441",
    "addr:postcode":"30058",
    "addr:street":"Shirewick Ln",
    "iso:country":"US",
    "sg:address":"5441 Shirewick Ln",
    "sg:city":"Lithonia",
    "sg:classifiers":[
        {
            "category":"Place Of Worship",
            "subcategory":"Church",
            "type":"Public Place"
        },
        {
            "category":"Personal",
            "type":"Services"
        },
        {
            "category":"Recreation",
            "type":"Entertainment"
        }
    ],
    "sg:phone":"+1 770 808 8877",
    "sg:postcode":"30058",
    "sg:province":"GA",
    "sg:tags":[
        "ceremony",
        "consultant",
        "planning",
        "marriage",
        "wedding",
        "chapel"
    ],
    "wof:name":"A Royal Affair Inc",
    "wof:placetype":"venue"
},
  "geometry": {"coordinates":[-84.158357,33.711391],"type":"Point"}
}