{
  "type": "Feature",
  "properties": {
    "iso:country":"US",
    "sg:address":"2195 Fellowship Rd",
    "sg:city":"Tucker",
    "sg:classifiers":[
        {
            "category":"Building & Trades",
            "subcategory":"Construction",
            "type":"Services"
        }
    ],
    "sg:phone":"+1 770 938 1303",
    "sg:postcode":"30084",
    "sg:province":"GA",
    "sg:tags":[
        "house"
    ],
    "wof:name":"Charles Orr Construnction Co",
    "wof:placetype":"venue"
},
  "geometry": {"coordinates":[-84.217693,33.84829],"type":"Point"}
}