{
  "type": "Feature",
  "properties": {
    "iso:country":"US",
    "sg:address":"7521 Elliot Way",
    "sg:city":"Jonesboro",
    "sg:classifiers":[
        {
            "category":"Building & Trades",
            "subcategory":"Locksmith",
            "type":"Services"
        }
    ],
    "sg:phone":"+1 678 734 9295",
    "sg:postcode":"30236",
    "sg:province":"GA",
    "sg:tags":[
        "key"
    ],
    "wof:name":"24 Hour A Locksmith",
    "wof:placetype":"venue"
},
  "geometry": {"coordinates":[-84.317171,33.549095],"type":"Point"}
}