{
  "type": "Feature",
  "properties": {
    "addr:full":"468 Edwards Pkwy Cleveland GA 30528",
    "addr:housenumber":"468",
    "addr:postcode":"30528",
    "addr:street":"Edwards Pkwy",
    "iso:country":"US",
    "sg:address":"468 Edwards Pkwy",
    "sg:city":"Cleveland",
    "sg:classifiers":[
        {
            "category":"Retail",
            "subcategory":"Auto Rental",
            "type":"Services"
        }
    ],
    "sg:phone":"+1 706 348 7532",
    "sg:postcode":"30528",
    "sg:province":"GA",
    "sg:tags":[
        "trailer",
        "utility"
    ],
    "wof:name":"Hogsed Enterprises LLC",
    "wof:placetype":"venue"
},
  "geometry": {"coordinates":[-83.910003,34.687131],"type":"Point"}
}