{
  "type": "Feature",
  "properties": {
    "iso:country":"US",
    "sg:address":"198 Dutchman's Cove Rd",
    "sg:city":"Midway",
    "sg:classifiers":[
        {
            "category":"Professional",
            "subcategory":"Computer Services",
            "type":"Services"
        }
    ],
    "sg:phone":"+1 912 884 3965",
    "sg:postcode":"31320",
    "sg:province":"GA",
    "sg:tags":[
        "information",
        "retrieval"
    ],
    "wof:name":"Montana Data Basing",
    "wof:placetype":"venue"
},
  "geometry": {"coordinates":[-81.285927,31.770511],"type":"Point"}
}