{
  "type": "Feature",
  "properties": {
    "iso:country":"US",
    "sg:address":"6499 N Point Pkwy",
    "sg:city":"Alpharetta",
    "sg:classifiers":[
        {
            "category":"Banks & Credit Unions",
            "subcategory":"Financial Services",
            "type":"Services"
        }
    ],
    "sg:phone":"+1 770 740 2350",
    "sg:postcode":"30022",
    "sg:province":"GA",
    "sg:website":"http://www.SunTrust.com",
    "wof:name":"SunTrust Bank - North Point Mall",
    "wof:placetype":"venue"
},
  "geometry": {"coordinates":[-84.294044,34.045315],"type":"Point"}
}