{
  "type": "Feature",
  "properties": {
    "addr:full":"1450 Scott Blvd Decatur GA 30030",
    "addr:housenumber":"1450",
    "addr:postcode":"30030",
    "addr:street":"Scott Blvd",
    "iso:country":"US",
    "sg:address":"1450 Scott Blvd",
    "sg:city":"Decatur",
    "sg:classifiers":[
        {
            "category":"Professional",
            "subcategory":"Employment Agencies",
            "type":"Services"
        }
    ],
    "sg:phone":"+1 404 377 0006",
    "sg:postcode":"30030",
    "sg:province":"GA",
    "sg:tags":[
        "temporary"
    ],
    "wof:name":"Express Employment",
    "wof:placetype":"venue"
},
  "geometry": {"coordinates":[-84.291691,33.792523],"type":"Point"}
}