{
  "type": "Feature",
  "properties": {
    "addr:full":"37 Rocky Ln Jasper GA 30143",
    "addr:housenumber":"37",
    "addr:postcode":"30143",
    "addr:street":"Rocky Ln",
    "iso:country":"US",
    "sg:address":"37 Rocky Ln",
    "sg:city":"Jasper",
    "sg:classifiers":[
        {
            "category":"Professional",
            "type":"Services"
        }
    ],
    "sg:phone":"+1 706 253 4347",
    "sg:postcode":"30143",
    "sg:province":"GA",
    "wof:name":"Rohrer Technical Services LLC",
    "wof:placetype":"venue"
},
  "geometry": {"coordinates":[-84.43060699999999,34.519108],"type":"Point"}
}