{
  "type": "Feature",
  "properties": {
    "addr:full":"574 Peachtree Pkwy Cumming GA 30041",
    "addr:housenumber":"574",
    "addr:postcode":"30041",
    "addr:street":"Peachtree Pkwy",
    "iso:country":"US",
    "sg:address":"574 Peachtree Pkwy",
    "sg:city":"Cumming",
    "sg:classifiers":[
        {
            "category":"Professional",
            "subcategory":"Advertising",
            "type":"Services"
        }
    ],
    "sg:phone":"+1 770 888 2212",
    "sg:postcode":"30041",
    "sg:province":"GA",
    "sg:tags":[
        "representative"
    ],
    "wof:name":"Richards Media Group",
    "wof:placetype":"venue"
},
  "geometry": {"coordinates":[-84.17387600000001,34.150866],"type":"Point"}
}