{
  "type": "Feature",
  "properties": {
    "addr:full":"274 New Hermitage Rd NE Rome GA 30161",
    "addr:housenumber":"274",
    "addr:postcode":"ga 30161",
    "addr:street":"New Hermitage Rd Ne",
    "iso:country":"US",
    "sg:address":"274 New Hermitage Rd NE",
    "sg:city":"Rome",
    "sg:classifiers":[
        {
            "category":"Personal",
            "subcategory":"Beauty Salon",
            "type":"Services"
        }
    ],
    "sg:phone":"+1 706 295 4061",
    "sg:postcode":"30161",
    "sg:province":"GA",
    "wof:name":"Kay S Beauty Shop",
    "wof:placetype":"venue"
},
  "geometry": {"coordinates":[-85.068181,34.328947],"type":"Point"}
}