{
  "type": "Feature",
  "properties": {
    "iso:country":"US",
    "sg:address":"2717 Bemiss Rd",
    "sg:city":"Valdosta",
    "sg:classifiers":[
        {
            "category":"Building & Trades",
            "subcategory":"Equipment Rental",
            "type":"Services"
        }
    ],
    "sg:phone":"+1 229 247 5797",
    "sg:postcode":"31602",
    "sg:province":"GA",
    "sg:tags":[
        "repair",
        "yard",
        "sales"
    ],
    "wof:name":"General Rental Center",
    "wof:placetype":"venue"
},
  "geometry": {"coordinates":[-83.276526,30.875027],"type":"Point"}
}