{
  "type": "Feature",
  "properties": {
    "addr:full":"505 Courthouse Ln Augusta GA 30901",
    "addr:housenumber":"505",
    "addr:postcode":"30901",
    "addr:street":"Courthouse Ln",
    "iso:country":"US",
    "sg:address":"505 Courthouse Ln",
    "sg:city":"Augusta",
    "sg:classifiers":[
        {
            "category":"Professional",
            "subcategory":"Lawyer & Legal Services",
            "type":"Services"
        }
    ],
    "sg:phone":"+1 706 722 3746",
    "sg:postcode":"30901",
    "sg:province":"GA",
    "sg:tags":[
        "convention",
        "reporters-court"
    ],
    "wof:name":"Culpepper Reporting",
    "wof:placetype":"venue"
},
  "geometry": {"coordinates":[-81.959919,33.46852],"type":"Point"}
}