{
  "type": "Feature",
  "properties": {
    "addr:full":"154 W Washington St Newnan GA 30263",
    "addr:housenumber":"154",
    "addr:postcode":"30263",
    "addr:street":"W Washington St",
    "iso:country":"US",
    "sg:address":"154 W Washington St",
    "sg:city":"Newnan",
    "sg:classifiers":[
        {
            "category":"Cinema",
            "subcategory":"Movie Rental",
            "type":"Entertainment"
        }
    ],
    "sg:phone":"+1 770 251 9365",
    "sg:postcode":"30263",
    "sg:province":"GA",
    "sg:tags":[
        "video",
        "tape"
    ],
    "wof:name":"Thomas Amey Photo Video",
    "wof:placetype":"venue"
},
  "geometry": {"coordinates":[-84.814854,33.377083],"type":"Point"}
}