{
  "type": "Feature",
  "properties": {
    "addr:full":"2495 Jonesboro Rd SE Atlanta GA 30315",
    "addr:housenumber":"2495",
    "addr:postcode":"30315",
    "addr:street":"Jonesboro Rd Se",
    "iso:country":"US",
    "sg:address":"2495 Jonesboro Rd SE",
    "sg:city":"Atlanta",
    "sg:classifiers":[
        {
            "category":"Professional",
            "type":"Services"
        }
    ],
    "sg:phone":"+1 404 622 2302",
    "sg:postcode":"30315",
    "sg:province":"GA",
    "wof:name":"Seyoum Atenafe",
    "wof:placetype":"venue"
},
  "geometry": {"coordinates":[-84.364102,33.688356],"type":"Point"}
}