{
  "type": "Feature",
  "properties": {
    "addr:full":"4394 Hugh Howell Rd Ste 7 Tucker GA 30084",
    "addr:housenumber":"4394",
    "addr:postcode":"30084",
    "addr:street":"Hugh Howell Rd Ste 7",
    "iso:country":"US",
    "sg:address":"4394 Hugh Howell Rd Ste 7",
    "sg:city":"Tucker",
    "sg:classifiers":[
        {
            "category":"Health Services",
            "subcategory":"Doctor",
            "type":"Services"
        }
    ],
    "sg:phone":"+1 770 621 0830",
    "sg:postcode":"30084",
    "sg:province":"GA",
    "sg:tags":[
        "surgeon",
        "oral"
    ],
    "wof:name":"Brannen J Clem DDS",
    "wof:placetype":"venue"
},
  "geometry": {"coordinates":[-84.207497,33.8512],"type":"Point"}
}