{
  "type": "Feature",
  "properties": {
    "addr:full":"7445 Tara Blvd Jonesboro GA 30236",
    "addr:housenumber":"7445",
    "addr:postcode":"30236",
    "addr:street":"Tara Blvd",
    "iso:country":"US",
    "sg:address":"7445 Tara Blvd",
    "sg:city":"Jonesboro",
    "sg:classifiers":[
        {
            "category":"Autos & Motor Vehicles",
            "subcategory":"Auto Supplies",
            "type":"Retail Goods"
        }
    ],
    "sg:phone":"+1 770 471 6163",
    "sg:postcode":"30236",
    "sg:province":"GA",
    "sg:tags":[
        "wheel",
        "cover"
    ],
    "wof:name":"Rimco",
    "wof:placetype":"venue"
},
  "geometry": {"coordinates":[-84.366258,33.53997],"type":"Point"}
}