{
  "type": "Feature",
  "properties": {
    "addr:full":"2275 Jonesboro Rd Fairburn GA 30213",
    "addr:housenumber":"2275",
    "addr:postcode":"30213",
    "addr:street":"Jonesboro Rd",
    "iso:country":"US",
    "sg:address":"2275 Jonesboro Rd",
    "sg:city":"Fairburn",
    "sg:classifiers":[
        {
            "category":"Fast Food",
            "type":"Food & Drink"
        },
        {
            "category":"Restaurant",
            "type":"Food & Drink"
        },
        {
            "category":"Food & Beverages",
            "subcategory":"Groceries & Convenience Stores",
            "type":"Retail Goods"
        }
    ],
    "sg:phone":"+1 770 994 0437",
    "sg:postcode":"30213",
    "sg:province":"GA",
    "sg:tags":[
        "shop",
        "american",
        "sandwich",
        "take"
    ],
    "wof:name":"Subway",
    "wof:placetype":"venue"
},
  "geometry": {"coordinates":[-84.46597300000001,33.551121],"type":"Point"}
}