{
  "type": "Feature",
  "properties": {
    "iso:country":"US",
    "sg:address":"502 N Wall St",
    "sg:city":"Calhoun",
    "sg:classifiers":[
        {
            "category":"Wholesale",
            "subcategory":"Machinery & Supplies",
            "type":"Manufacturing & Wholesale Goods"
        }
    ],
    "sg:phone":"+1 706 272 9830",
    "sg:postcode":"30701",
    "sg:province":"GA",
    "sg:tags":[
        "machine",
        "sewing"
    ],
    "wof:name":"Blue Diamond Parts & Supplies",
    "wof:placetype":"venue"
},
  "geometry": {"coordinates":[-84.946428,34.515295],"type":"Point"}
}