{
  "type": "Feature",
  "properties": {
    "addr:full":"1464 Washington Rd Thomson GA 30824",
    "addr:housenumber":"1464",
    "addr:postcode":"30824",
    "addr:street":"Washington Rd",
    "iso:country":"US",
    "sg:address":"1464 Washington Rd",
    "sg:city":"Thomson",
    "sg:classifiers":[
        {
            "category":"Banks & Credit Unions",
            "subcategory":"Bank",
            "type":"Services"
        }
    ],
    "sg:phone":"+1 706 595 1482",
    "sg:postcode":"30824",
    "sg:province":"GA",
    "sg:tags":[
        "loan"
    ],
    "wof:name":"Security Finance Corp",
    "wof:placetype":"venue"
},
  "geometry": {"coordinates":[-82.504176,33.494169],"type":"Point"}
}