{
  "type": "Feature",
  "properties": {
    "addr:full":"511 Clear Lake Ln Suwanee GA 30024",
    "addr:housenumber":"511",
    "addr:postcode":"30024",
    "addr:street":"Clear Lake Ln",
    "iso:country":"US",
    "sg:address":"511 Clear Lake Ln",
    "sg:city":"Suwanee",
    "sg:classifiers":[
        {
            "category":"Retail",
            "subcategory":"Animal Services",
            "type":"Services"
        }
    ],
    "sg:phone":"+1 770 995 0203",
    "sg:postcode":"30024",
    "sg:province":"GA",
    "wof:name":"Puppy Adept Inc",
    "wof:placetype":"venue"
},
  "geometry": {"coordinates":[-84.040576,34.01062],"type":"Point"}
}