{
  "type": "Feature",
  "properties": {
    "addr:full":"3802 Roswell Rd NE Atlanta GA 30342",
    "addr:housenumber":"3802;rd",
    "addr:postcode":"30342",
    "addr:street":"Roswell;Ne",
    "iso:country":"US",
    "sg:address":"3802 Roswell Rd NE",
    "sg:city":"Atlanta",
    "sg:classifiers":[
        {
            "category":"Personal",
            "subcategory":"Nail Salon",
            "type":"Services"
        }
    ],
    "sg:phone":"+1 404 261 8256",
    "sg:postcode":"30342",
    "sg:province":"GA",
    "wof:name":"Nail Favor",
    "wof:placetype":"venue"
},
  "geometry": {"coordinates":[-84.38130200000001,33.858002],"type":"Point"}
}