{
  "type": "Feature",
  "properties": {
    "iso:country":"US",
    "sg:address":"167 Dunlevie Rd",
    "sg:city":"Allenhurst",
    "sg:classifiers":[
        {
            "category":"Retail",
            "subcategory":"Auto Repair",
            "type":"Services"
        }
    ],
    "sg:phone":"+1 912 876 2290",
    "sg:postcode":"31301",
    "sg:province":"GA",
    "sg:tags":[
        "body",
        "automobile",
        "painting",
        "repairing"
    ],
    "sg:website":"http://classicpaintandbodyshop.com",
    "wof:name":"Classic Collision Center",
    "wof:placetype":"venue"
},
  "geometry": {"coordinates":[-81.607917,31.783989],"type":"Point"}
}