{
  "type": "Feature",
  "properties": {
    "iso:country":"US",
    "sg:address":"318 Georgia Ave",
    "sg:city":"Homer",
    "sg:classifiers":[
        {
            "category":"Banks & Credit Unions",
            "subcategory":"Bank",
            "type":"Services"
        }
    ],
    "sg:phone":"+1 706 677 3751",
    "sg:postcode":"30533",
    "sg:province":"GA",
    "sg:tags":[
        "loan",
        "real estate"
    ],
    "wof:name":"Cendant Corp",
    "wof:placetype":"venue"
},
  "geometry": {"coordinates":[-83.947042,34.547124],"type":"Point"}
}