{
  "type": "Feature",
  "properties": {
    "iso:country":"US",
    "sg:address":"2697 McCollum Pkwy NW",
    "sg:city":"Kennesaw",
    "sg:classifiers":[
        {
            "category":"Manufacturing",
            "subcategory":"Building Materials",
            "type":"Manufacturing & Wholesale Goods"
        }
    ],
    "sg:phone":"+1 770 427 3742",
    "sg:postcode":"30144",
    "sg:province":"GA",
    "sg:tags":[
        "truss"
    ],
    "sg:website":"www.structuralwoodsystems.com",
    "wof:name":"Structural Wood Systems Of Ga",
    "wof:placetype":"venue"
},
  "geometry": {"coordinates":[-84.599969,34.017771],"type":"Point"}
}