{
  "type": "Feature",
  "properties": {
    "iso:country":"US",
    "sg:address":"1909 Mountain Industrial Blvd",
    "sg:city":"Tucker",
    "sg:classifiers":[
        {
            "category":"Home & Garden",
            "subcategory":"Building Materials",
            "type":"Retail Goods"
        },
        {
            "category":"Building & Trades",
            "subcategory":"Construction",
            "type":"Services"
        }
    ],
    "sg:phone":"+1 678 392 2275",
    "sg:postcode":"30084",
    "sg:province":"GA",
    "sg:tags":[
        "fence-sales",
        "contractor"
    ],
    "sg:website":"http://atlanta.citysearch.com/profile/external/651231640/tucker_ga/fenceworks_of_ga_inc_.html?publisher=yellowpages&reference_id=15&placement=ypwebsitemip",
    "wof:name":"Fenceworks of Ga, Inc.",
    "wof:placetype":"venue"
},
  "geometry": {"coordinates":[-84.200897,33.838265],"type":"Point"}
}