{
  "type": "Feature",
  "properties": {
    "addr:full":"201 12th Ave SE Moultrie GA 31768",
    "addr:housenumber":"201",
    "addr:postcode":"31768",
    "addr:street":"12Th Ave Se",
    "iso:country":"US",
    "sg:address":"201 12th Ave SE",
    "sg:city":"Moultrie",
    "sg:classifiers":[
        {
            "category":"Organizations",
            "subcategory":"Religious Organization",
            "type":"Services"
        }
    ],
    "sg:phone":"+1 229 985 3660",
    "sg:postcode":"31768",
    "sg:province":"GA",
    "sg:website":"www.trinityofmoultrie.org",
    "wof:name":"Trinity Baptist Church",
    "wof:placetype":"venue"
},
  "geometry": {"coordinates":[-83.78645899999999,31.164906],"type":"Point"}
}