{
  "type": "Feature",
  "properties": {
    "addr:full":"632 E Broad St Savannah GA 31401",
    "addr:housenumber":"632",
    "addr:postcode":"31401",
    "addr:street":"E Broad St",
    "iso:country":"US",
    "sg:address":"632 E Broad St",
    "sg:city":"Savannah",
    "sg:classifiers":[
        {
            "category":"Organizations",
            "subcategory":"Religious Organization",
            "type":"Services"
        }
    ],
    "sg:phone":"+1 912 236 2051",
    "sg:postcode":"31401",
    "sg:province":"GA",
    "sg:tags":[
        "church"
    ],
    "wof:name":"Saint James AME Church",
    "wof:placetype":"venue"
},
  "geometry": {"coordinates":[-81.08817000000001,32.067717],"type":"Point"}
}