{
  "type": "Feature",
  "properties": {
    "iso:country":"US",
    "sg:address":"1108 Reeves Station Rd SW",
    "sg:city":"Calhoun",
    "sg:classifiers":[
        {
            "category":"Building & Trades",
            "subcategory":"Construction",
            "type":"Services"
        }
    ],
    "sg:phone":"+1 706 625 4191",
    "sg:postcode":"30701",
    "sg:province":"GA",
    "sg:tags":[
        "contractor"
    ],
    "wof:name":"H&H Roofing",
    "wof:placetype":"venue"
},
  "geometry": {"coordinates":[-85.018333,34.458018],"type":"Point"}
}