{
  "type": "Feature",
  "properties": {
    "iso:country":"US",
    "sg:address":"6 N Riversong Ct",
    "sg:city":"Alpharetta",
    "sg:classifiers":[
        {
            "category":"Banks & Credit Unions",
            "subcategory":"Investment Brokerage",
            "type":"Services"
        }
    ],
    "sg:phone":"+1 770 246 1755",
    "sg:postcode":"30022",
    "sg:province":"GA",
    "sg:tags":[
        "advisory",
        "financial"
    ],
    "wof:name":"GBL Financial",
    "wof:placetype":"venue"
},
  "geometry": {"coordinates":[-84.28273900000001,33.99508],"type":"Point"}
}