{
  "type": "Feature",
  "properties": {
    "addr:full":"1353 Belfaire Trce Dacula GA 30019",
    "addr:housenumber":"1353",
    "addr:postcode":"ga 30019",
    "addr:street":"Belfaire Trce",
    "iso:country":"US",
    "sg:address":"1353 Belfaire Trce",
    "sg:city":"Dacula",
    "sg:classifiers":[
        {
            "category":"Building & Trades",
            "subcategory":"Construction",
            "type":"Services"
        }
    ],
    "sg:phone":"+1 678 442 8558",
    "sg:postcode":"30019",
    "sg:province":"GA",
    "sg:tags":[
        "floor",
        "laying",
        "contractor"
    ],
    "wof:name":"Star Flooring",
    "wof:placetype":"venue"
},
  "geometry": {"coordinates":[-83.916099,34.039089],"type":"Point"}
}