{
  "type": "Feature",
  "properties": {
    "iso:country":"US",
    "sg:address":"655 Duluth Hwy",
    "sg:city":"Lawrenceville",
    "sg:classifiers":[
        {
            "category":"Restaurant",
            "type":"Food & Drink"
        }
    ],
    "sg:phone":"+1 770 339 9752",
    "sg:postcode":"30045",
    "sg:province":"GA",
    "wof:name":"Applebee's Neighborhood Grill & Bar",
    "wof:placetype":"venue"
},
  "geometry": {"coordinates":[-84.008904,33.9655],"type":"Point"}
}