{
  "type": "Feature",
  "properties": {
    "iso:country":"US",
    "sg:address":"6855 Ranch Forest Dr",
    "sg:city":"Columbus",
    "sg:classifiers":[
        {
            "category":"Education",
            "subcategory":"Special Training",
            "type":"Public Place"
        }
    ],
    "sg:phone":"+1 706 323 2831",
    "sg:postcode":"31904",
    "sg:province":"GA",
    "wof:name":"Education Guidence Services",
    "wof:placetype":"venue"
},
  "geometry": {"coordinates":[-84.981956,32.545511],"type":"Point"}
}