{
  "type": "Feature",
  "properties": {
    "iso:country":"US",
    "sg:address":"1230 Peachtree St NE Ste D401",
    "sg:city":"Atlanta",
    "sg:classifiers":[
        {
            "category":"Shopping",
            "subcategory":"Clothing, Apparel, & Fashions",
            "type":"Retail Goods"
        },
        {
            "category":"Shopping",
            "subcategory":"Shoes",
            "type":"Retail Goods"
        }
    ],
    "sg:phone":"+1 404 419 6619",
    "sg:postcode":"30309",
    "sg:province":"GA",
    "sg:tags":[
        "accessory",
        "clothing",
        "store",
        "women's"
    ],
    "sg:website":"www.dragfactory.com",
    "wof:name":"Drag Factory",
    "wof:placetype":"venue"
},
  "geometry": {"coordinates":[-84.385149,33.787975],"type":"Point"}
}