{
  "type": "Feature",
  "properties": {
    "iso:country":"US",
    "sg:address":"2015 Sharpsburg McCullum Rd",
    "sg:city":"Newnan",
    "sg:classifiers":[
        {
            "category":"Banks & Credit Unions",
            "subcategory":"Financial Services",
            "type":"Services"
        },
        {
            "category":"Professional",
            "subcategory":"Accounting & Tax Preparation",
            "type":"Services"
        }
    ],
    "sg:phone":"+1 678 423 2100",
    "sg:postcode":"30265",
    "sg:province":"GA",
    "sg:tags":[
        "accountant",
        "investment",
        "closed"
    ],
    "wof:name":"Cumberland Financial Group",
    "wof:placetype":"venue"
},
  "geometry": {"coordinates":[-84.67316099999999,33.38478],"type":"Point"}
}