{
  "type": "Feature",
  "properties": {
    "addr:full":"312 12th Ave E Cordele GA 31015",
    "addr:housenumber":"312",
    "addr:postcode":"31015",
    "addr:street":"12Th Ave E",
    "iso:country":"US",
    "sg:address":"312 12th Ave E",
    "sg:city":"Cordele",
    "sg:classifiers":[
        {
            "category":"Retail",
            "subcategory":"Portrait Studio",
            "type":"Services"
        }
    ],
    "sg:phone":"+1 229 273 3734",
    "sg:postcode":"31015",
    "sg:province":"GA",
    "sg:tags":[
        "photographer"
    ],
    "wof:name":"Adkins Photography",
    "wof:placetype":"venue"
},
  "geometry": {"coordinates":[-83.778143,31.96796],"type":"Point"}
}