{
  "type": "Feature",
  "properties": {
    "addr:full":"2285 Lower Bethany Rd Canton GA 30114",
    "addr:housenumber":"2285",
    "addr:postcode":"30114",
    "addr:street":"Lower Bethany Rd",
    "iso:country":"US",
    "sg:address":"2285 Lower Bethany Rd",
    "sg:city":"Canton",
    "sg:classifiers":[
        {
            "category":"Shopping",
            "subcategory":"Florist",
            "type":"Retail Goods"
        }
    ],
    "sg:phone":"+1 770 479 4224",
    "sg:postcode":"30114",
    "sg:province":"GA",
    "wof:name":"Community Flower Shop",
    "wof:placetype":"venue"
},
  "geometry": {"coordinates":[-84.49990099999999,34.233398],"type":"Point"}
}