{
  "type": "Feature",
  "properties": {
    "iso:country":"US",
    "sg:address":"132 S Clayton St",
    "sg:city":"Lawrenceville",
    "sg:classifiers":[
        {
            "category":"Insurance",
            "subcategory":"Insurance Agent",
            "type":"Services"
        }
    ],
    "sg:phone":"+1 770 682 3950",
    "sg:postcode":"30045",
    "sg:province":"GA",
    "wof:name":"Abbey Insurance-Lawrenceville",
    "wof:placetype":"venue"
},
  "geometry": {"coordinates":[-83.98832299999999,33.955525],"type":"Point"}
}