{
  "type": "Feature",
  "properties": {
    "iso:country":"US",
    "sg:address":"1601 General Arts Rd NW",
    "sg:city":"Conyers",
    "sg:classifiers":[
        {
            "category":"Wholesale",
            "subcategory":"Non-durable Goods",
            "type":"Manufacturing & Wholesale Goods"
        }
    ],
    "sg:phone":"+1 770 760 9780",
    "sg:postcode":"30012",
    "sg:province":"GA",
    "sg:tags":[
        "corrugated",
        "packaging",
        "display"
    ],
    "wof:name":"Signature Packaging & Ppr LLC",
    "wof:placetype":"venue"
},
  "geometry": {"coordinates":[-84.05441399999999,33.683896],"type":"Point"}
}