{
  "type": "Feature",
  "properties": {
    "iso:country":"US",
    "sg:address":"369 Enota Pl SW",
    "sg:city":"Atlanta",
    "sg:classifiers":[
        {
            "category":"Wholesale",
            "subcategory":"Books, Periodicals, & Newspapers",
            "type":"Manufacturing & Wholesale Goods"
        }
    ],
    "sg:phone":"+1 404 963 1395",
    "sg:postcode":"30310",
    "sg:province":"GA",
    "sg:tags":[
        "publisher",
        "book"
    ],
    "sg:website":"http://www.celestepress.org",
    "wof:name":"Celeste Press",
    "wof:placetype":"venue"
},
  "geometry": {"coordinates":[-84.433924,33.74456],"type":"Point"}
}