{
  "type": "Feature",
  "properties": {
    "iso:country":"US",
    "sg:address":"2075 Marietta Hwy",
    "sg:city":"Canton",
    "sg:classifiers":[
        {
            "category":"Shopping",
            "subcategory":"Department Store",
            "type":"Retail Goods"
        }
    ],
    "sg:phone":"+1 770 479 1716",
    "sg:postcode":"30114",
    "sg:province":"GA",
    "wof:name":"Cherokee Closeouts",
    "wof:placetype":"venue"
},
  "geometry": {"coordinates":[-84.50479900000001,34.221699],"type":"Point"}
}