{
  "type": "Feature",
  "properties": {
    "iso:country":"US",
    "sg:address":"301 W Crawford St Ste 3",
    "sg:city":"Dalton",
    "sg:classifiers":[
        {
            "category":"Real Estate",
            "subcategory":"Surveying",
            "type":"Services"
        }
    ],
    "sg:phone":"+1 706 281 4804",
    "sg:postcode":"30720",
    "sg:province":"GA",
    "sg:tags":[
        "planning",
        "land"
    ],
    "wof:name":"Dalton Whitfield Community Development Corp",
    "wof:placetype":"venue"
},
  "geometry": {"coordinates":[-84.970978,34.77153],"type":"Point"}
}