{
  "type": "Feature",
  "properties": {
    "addr:full":"6203 Jonesboro Rd Morrow GA 30260",
    "addr:housenumber":"6203",
    "addr:postcode":"30260",
    "addr:street":"Jonesboro Rd",
    "iso:country":"US",
    "sg:address":"6203 Jonesboro Rd",
    "sg:city":"Morrow",
    "sg:classifiers":[
        {
            "category":"Professional",
            "subcategory":"Lawyer & Legal Services",
            "type":"Services"
        }
    ],
    "sg:phone":"+1 770 961 5511",
    "sg:postcode":"30260",
    "sg:province":"GA",
    "sg:tags":[
        "plan"
    ],
    "wof:name":"George C Creal Jr",
    "wof:placetype":"venue"
},
  "geometry": {"coordinates":[-84.339039,33.58462],"type":"Point"}
}