{
  "type": "Feature",
  "properties": {
    "iso:country":"US",
    "sg:address":"1225 Summerstone Trce",
    "sg:city":"Austell",
    "sg:classifiers":[
        {
            "category":"Banks & Credit Unions",
            "subcategory":"Bank",
            "type":"Services"
        }
    ],
    "sg:phone":"+1 770 819 4429",
    "sg:postcode":"30168",
    "sg:province":"GA",
    "sg:tags":[
        "broker",
        "mortgage"
    ],
    "wof:name":"Harvestyme Mortgage Co Inc",
    "wof:placetype":"venue"
},
  "geometry": {"coordinates":[-84.589997,33.777073],"type":"Point"}
}