{
  "type": "Feature",
  "properties": {
    "iso:country":"US",
    "sg:address":"1420 White Cir NW",
    "sg:city":"Marietta",
    "sg:classifiers":[
        {
            "category":"Building & Trades",
            "subcategory":"Electrical",
            "type":"Services"
        },
        {
            "category":"Professional",
            "subcategory":"Management & Consulting",
            "type":"Services"
        }
    ],
    "sg:phone":"+1 678 766 6600",
    "sg:postcode":"30060",
    "sg:province":"GA",
    "sg:tags":[
        "communications",
        "consultant",
        "electrical",
        "contractor"
    ],
    "wof:name":"Cana Communications Inc",
    "wof:placetype":"venue"
},
  "geometry": {"coordinates":[-84.569525,33.986304],"type":"Point"}
}