{
  "type": "Feature",
  "properties": {
    "addr:full":"2635 US Hwy 27 Carrollton GA 30117",
    "addr:housenumber":"2635",
    "addr:postcode":"30117",
    "addr:street":"Us Hwy 27",
    "iso:country":"US",
    "sg:address":"2635 US Hwy 27",
    "sg:city":"Carrollton",
    "sg:classifiers":[
        {
            "category":"Autos & Motor Vehicles",
            "subcategory":"Auto Supplies",
            "type":"Retail Goods"
        }
    ],
    "sg:phone":"+1 770 834 4141",
    "sg:postcode":"30117",
    "sg:province":"GA",
    "wof:name":"Northside Used Tires",
    "wof:placetype":"venue"
},
  "geometry": {"coordinates":[-85.118639,33.631676],"type":"Point"}
}