{
  "type": "Feature",
  "properties": {
    "addr:full":"7217 Daniel Dr Stockbridge GA 30281",
    "addr:housenumber":"7217",
    "addr:postcode":"30281",
    "addr:street":"Daniel Dr",
    "iso:country":"US",
    "sg:address":"7217 Daniel Dr",
    "sg:city":"Stockbridge",
    "sg:classifiers":[
        {
            "category":"Home & Garden",
            "subcategory":"Furniture",
            "type":"Retail Goods"
        }
    ],
    "sg:phone":"+1 770 474 0982",
    "sg:postcode":"30281",
    "sg:province":"GA",
    "sg:tags":[
        "equipment",
        "kitchen",
        "cabinet"
    ],
    "wof:name":"Cabinet Distributors-Georgia",
    "wof:placetype":"venue"
},
  "geometry": {"coordinates":[-84.26379300000001,33.556911],"type":"Point"}
}