{
  "type": "Feature",
  "properties": {
    "addr:full":"2157 Old Surrency Rd Baxley GA 31513",
    "addr:housenumber":"2157",
    "addr:postcode":"31513",
    "addr:street":"Old Surrency Rd",
    "iso:country":"US",
    "sg:address":"2157 Old Surrency Rd",
    "sg:city":"Baxley",
    "sg:classifiers":[
        {
            "category":"Manufacturing",
            "subcategory":"Buildings",
            "type":"Manufacturing & Wholesale Goods"
        },
        {
            "category":"Building & Trades",
            "subcategory":"Construction",
            "type":"Services"
        }
    ],
    "sg:phone":"+1 912 367 9977",
    "sg:postcode":"31513",
    "sg:province":"GA",
    "sg:tags":[
        "industrial",
        "system",
        "specialty",
        "builder",
        "heating",
        "contractor",
        "contractors-commercial",
        "home",
        "air conditioning"
    ],
    "wof:name":"Toc",
    "wof:placetype":"venue"
},
  "geometry": {"coordinates":[-82.312772,31.78632],"type":"Point"}
}