{
  "type": "Feature",
  "properties": {
    "iso:country":"US",
    "sg:address":"601 Penn Waller Rd",
    "sg:city":"Savannah",
    "sg:classifiers":[
        {
            "category":"Banks & Credit Unions",
            "subcategory":"Investment Brokerage",
            "type":"Services"
        }
    ],
    "sg:phone":"+1 912 898 4502",
    "sg:postcode":"31410",
    "sg:province":"GA",
    "sg:tags":[
        "advisory"
    ],
    "wof:name":"Taft-Hartley Consultants",
    "wof:placetype":"venue"
},
  "geometry": {"coordinates":[-80.973874,32.011562],"type":"Point"}
}