{
  "type": "Feature",
  "properties": {
    "addr:full":"12385 Crabapple Rd Alpharetta GA 30004",
    "addr:housenumber":"12385",
    "addr:postcode":"30004",
    "addr:street":"Crabapple Rd",
    "iso:country":"US",
    "sg:address":"12385 Crabapple Rd",
    "sg:city":"Alpharetta",
    "sg:classifiers":[
        {
            "category":"Professional",
            "subcategory":"Management & Consulting",
            "type":"Services"
        }
    ],
    "sg:phone":"+1 770 650 1333",
    "sg:postcode":"30004",
    "sg:province":"GA",
    "sg:tags":[
        "consultant",
        "business"
    ],
    "wof:name":"Osa Financial Svc",
    "wof:placetype":"venue"
},
  "geometry": {"coordinates":[-84.352101,34.087302],"type":"Point"}
}