{
  "type": "Feature",
  "properties": {
    "iso:country":"US",
    "sg:address":"2390 Fairburn Rd",
    "sg:city":"Douglasville",
    "sg:classifiers":[
        {
            "category":"Home & Garden",
            "subcategory":"Mobile Homes",
            "type":"Retail Goods"
        }
    ],
    "sg:phone":"+1 678 473 2203",
    "sg:postcode":"30135",
    "sg:province":"GA",
    "wof:name":"Hunters Walk Home Center",
    "wof:placetype":"venue"
},
  "geometry": {"coordinates":[-84.679298,33.740898],"type":"Point"}
}