{
  "type": "Feature",
  "properties": {
    "iso:country":"US",
    "sg:address":"807 Cobb Pkwy",
    "sg:city":"Marietta",
    "sg:classifiers":[
        {
            "category":"Travel",
            "subcategory":"Hotels & Motels",
            "type":"Entertainment"
        }
    ],
    "sg:phone":"+1 770 428 7424",
    "sg:postcode":"30062",
    "sg:province":"GA",
    "sg:tags":[
        "operation"
    ],
    "wof:name":"Travelers Motel",
    "wof:placetype":"venue"
},
  "geometry": {"coordinates":[-84.53872800000001,33.969786],"type":"Point"}
}