{
  "type": "Feature",
  "properties": {
    "addr:full":"5185 Peachtree Pkwy Ste 330 Norcross GA 30092",
    "addr:housenumber":"5185",
    "addr:postcode":"30092",
    "addr:street":"Peachtree Pkwy Ste 330",
    "iso:country":"US",
    "sg:address":"5185 Peachtree Pkwy Ste 330",
    "sg:city":"Norcross",
    "sg:classifiers":[
        {
            "category":"Health Services",
            "subcategory":"Doctor",
            "type":"Services"
        }
    ],
    "sg:phone":"+1 770 476 9885",
    "sg:postcode":"30092",
    "sg:province":"GA",
    "sg:website":"www.panapc.com",
    "wof:name":"Zager Sheri MD",
    "wof:placetype":"venue"
},
  "geometry": {"coordinates":[-84.005506,34.134192],"type":"Point"}
}