{
  "type": "Feature",
  "properties": {
    "addr:full":"1215 Eagles Landing Pkwy Stockbridge GA 30281",
    "addr:housenumber":"1215",
    "addr:postcode":"30281",
    "addr:street":"Eagles Landing Pkwy",
    "iso:country":"US",
    "sg:address":"1215 Eagles Landing Pkwy",
    "sg:city":"Stockbridge",
    "sg:classifiers":[
        {
            "category":"Real Estate",
            "subcategory":"Real Estate Agent",
            "type":"Services"
        }
    ],
    "sg:phone":"+1 770 507 5090",
    "sg:postcode":"30281",
    "sg:province":"GA",
    "wof:name":"Rita D Hutson",
    "wof:placetype":"venue"
},
  "geometry": {"coordinates":[-84.22352100000001,33.510937],"type":"Point"}
}