{
  "type": "Feature",
  "properties": {
    "iso:country":"US",
    "sg:address":"970 Spring St NW",
    "sg:city":"Atlanta",
    "sg:classifiers":[
        {
            "category":"Food & Beverages",
            "subcategory":"Groceries & Convenience Stores",
            "type":"Retail Goods"
        }
    ],
    "sg:phone":"+1 404 874 5440",
    "sg:postcode":"30309",
    "sg:province":"GA",
    "wof:name":"Tenth Street Chevron Food Mart",
    "wof:placetype":"venue"
},
  "geometry": {"coordinates":[-84.389,33.7813],"type":"Point"}
}