{
  "type": "Feature",
  "properties": {
    "iso:country":"US",
    "sg:address":"402 Tanner St",
    "sg:city":"Carrollton",
    "sg:classifiers":[
        {
            "category":"Professional",
            "subcategory":"Lawyer & Legal Services",
            "type":"Services"
        }
    ],
    "sg:phone":"+1 770 832 0300",
    "sg:postcode":"30117",
    "sg:province":"GA",
    "sg:tags":[
        "litigation",
        "attorney",
        "injury",
        "family",
        "personal",
        "civil",
        "trial",
        "law",
        "consumer"
    ],
    "sg:website":"http://www.defect.com",
    "wof:name":"Flinn T Michael",
    "wof:placetype":"venue"
},
  "geometry": {"coordinates":[-85.073674,33.577388],"type":"Point"}
}