{
  "type": "Feature",
  "properties": {
    "addr:full":"887 Forsyth St Macon GA 31201",
    "addr:housenumber":"887",
    "addr:postcode":"31201",
    "addr:street":"Forsyth St",
    "iso:country":"US",
    "sg:address":"887 Forsyth St",
    "sg:city":"Macon",
    "sg:classifiers":[
        {
            "category":"Organizations",
            "subcategory":"Religious Organization",
            "type":"Services"
        }
    ],
    "sg:phone":"+1 478 742 4922",
    "sg:postcode":"31201",
    "sg:province":"GA",
    "sg:tags":[
        "place",
        "worship",
        "church"
    ],
    "wof:name":"Steward Chapel Ame Church Inc",
    "wof:placetype":"venue"
},
  "geometry": {"coordinates":[-83.636278,32.835581],"type":"Point"}
}