{
  "type": "Feature",
  "properties": {
    "addr:full":"5555 Glenridge Connector NE Atlanta GA 30342",
    "addr:housenumber":"5555",
    "addr:postcode":"30342",
    "addr:street":"Glenridge Connector Ne",
    "iso:country":"US",
    "sg:address":"5555 Glenridge Connector NE",
    "sg:city":"Atlanta",
    "sg:classifiers":[
        {
            "category":"Professional",
            "subcategory":"Employment Agencies",
            "type":"Services"
        }
    ],
    "sg:phone":"+1 404 325 8812",
    "sg:postcode":"30342",
    "sg:province":"GA",
    "sg:website":"www.pjredainc.com",
    "wof:name":"Reda P J & Associates Inc",
    "wof:placetype":"venue"
},
  "geometry": {"coordinates":[-84.36002499999999,33.904059],"type":"Point"}
}