{
  "type": "Feature",
  "properties": {
    "iso:country":"US",
    "sg:address":"4553 Calhoun Rd NE",
    "sg:city":"Rome",
    "sg:classifiers":[
        {
            "category":"Organizations",
            "subcategory":"Religious Organization",
            "type":"Services"
        }
    ],
    "sg:phone":"+1 706 295 2248",
    "sg:postcode":"30161",
    "sg:province":"GA",
    "sg:tags":[
        "church"
    ],
    "wof:name":"New Antioch Baptist Church",
    "wof:placetype":"venue"
},
  "geometry": {"coordinates":[-85.07042199999999,34.338242],"type":"Point"}
}