{
  "type": "Feature",
  "properties": {
    "iso:country":"US",
    "sg:address":"1087 Yellow River Dr",
    "sg:city":"Lawrenceville",
    "sg:classifiers":[
        {
            "category":"Building & Trades",
            "subcategory":"Cleaning & Sanitation",
            "type":"Services"
        }
    ],
    "sg:phone":"+1 404 597 7526",
    "sg:postcode":"30043",
    "sg:province":"GA",
    "wof:name":"German Cleaning",
    "wof:placetype":"venue"
},
  "geometry": {"coordinates":[-84.012665,33.981553],"type":"Point"}
}