{
  "type": "Feature",
  "properties": {
    "iso:country":"US",
    "sg:address":"3994 Howell St NW",
    "sg:city":"Duluth",
    "sg:classifiers":[
        {
            "category":"Personal",
            "subcategory":"Barber",
            "type":"Services"
        }
    ],
    "sg:phone":"+1 678 417 8770",
    "sg:postcode":"30096",
    "sg:province":"GA",
    "wof:name":"Family Hair Design Barber",
    "wof:placetype":"venue"
},
  "geometry": {"coordinates":[-84.17193899999999,33.998075],"type":"Point"}
}