{
  "type": "Feature",
  "properties": {
    "iso:country":"US",
    "sg:address":"170 Sharon Cir",
    "sg:city":"Athens",
    "sg:classifiers":[
        {
            "category":"Professional",
            "subcategory":"Lawyer & Legal Services",
            "type":"Services"
        }
    ],
    "sg:phone":"+1 706 543 9685",
    "sg:postcode":"30606",
    "sg:province":"GA",
    "sg:tags":[
        "information",
        "attorney",
        "referral"
    ],
    "wof:name":"Richard S Scott",
    "wof:placetype":"venue"
},
  "geometry": {"coordinates":[-83.42372899999999,33.97707],"type":"Point"}
}