{
  "type": "Feature",
  "properties": {
    "addr:full":"10930 Crabapple Rd Ste 140 Roswell GA 30075",
    "addr:housenumber":"10930",
    "addr:postcode":"30075",
    "addr:street":"Crabapple Rd Ste 140",
    "iso:country":"US",
    "sg:address":"10930 Crabapple Rd Ste 140",
    "sg:city":"Roswell",
    "sg:classifiers":[
        {
            "category":"Health Services",
            "subcategory":"Doctor",
            "type":"Services"
        }
    ],
    "sg:phone":"+1 770 641 8010",
    "sg:postcode":"30075",
    "sg:province":"GA",
    "sg:tags":[
        "surgeon",
        "oral"
    ],
    "sg:website":"www.demercydental.com",
    "wof:name":"Demercy Jeff R DDS",
    "wof:placetype":"venue"
},
  "geometry": {"coordinates":[-84.361239,34.045133],"type":"Point"}
}