{
  "type": "Feature",
  "properties": {
    "addr:full":"140 Runner Rd Savannah GA 31410",
    "addr:housenumber":"140",
    "addr:postcode":"31410",
    "addr:street":"Runner Rd",
    "iso:country":"US",
    "sg:address":"140 Runner Rd",
    "sg:city":"Savannah",
    "sg:classifiers":[
        {
            "category":"Professional",
            "subcategory":"Management & Consulting",
            "type":"Services"
        }
    ],
    "sg:phone":"+1 912 898 8282",
    "sg:postcode":"31410",
    "sg:province":"GA",
    "wof:name":"Top Ten Financial Service",
    "wof:placetype":"venue"
},
  "geometry": {"coordinates":[-80.95932000000001,32.020912],"type":"Point"}
}