{
  "type": "Feature",
  "properties": {
    "addr:full":"337 Margie Dr Warner Robins GA 31088",
    "addr:housenumber":"337",
    "addr:postcode":"31088",
    "addr:street":"Margie Dr",
    "iso:country":"US",
    "sg:address":"337 Margie Dr",
    "sg:city":"Warner Robins",
    "sg:classifiers":[
        {
            "category":"Professional",
            "type":"Services"
        }
    ],
    "sg:phone":"+1 478 971 4686",
    "sg:postcode":"31088",
    "sg:province":"GA",
    "sg:tags":[
        "establishment"
    ],
    "wof:name":"Landmark Systems",
    "wof:placetype":"venue"
},
  "geometry": {"coordinates":[-83.689933,32.615014],"type":"Point"}
}