{
  "type": "Feature",
  "properties": {
    "addr:full":"1445 Flattail Run Lawrenceville GA 30043",
    "addr:housenumber":"1445",
    "addr:postcode":"30043",
    "addr:street":"Flattail Run",
    "iso:country":"US",
    "sg:address":"1445 Flattail Run",
    "sg:city":"Lawrenceville",
    "sg:classifiers":[
        {
            "category":"Organizations",
            "subcategory":"Religious Organization",
            "type":"Services"
        }
    ],
    "sg:phone":"+1 770 513 8481",
    "sg:postcode":"30043",
    "sg:province":"GA",
    "wof:name":"Jesus Oretga",
    "wof:placetype":"venue"
},
  "geometry": {"coordinates":[-84.073368,33.963434],"type":"Point"}
}