{
  "type": "Feature",
  "properties": {
    "addr:full":"6326 Old Dixie Hwy Atlanta GA 30303",
    "addr:housenumber":"6326",
    "addr:postcode":"30303",
    "addr:street":"Old Dixie Hwy",
    "iso:country":"US",
    "sg:address":"6326 Old Dixie Hwy",
    "sg:city":"Atlanta",
    "sg:classifiers":[
        {
            "category":"Restaurant",
            "type":"Food & Drink"
        }
    ],
    "sg:phone":"+1 770 968 7122",
    "sg:postcode":"30303",
    "sg:province":"GA",
    "wof:name":"Benefield's Eatery & Saloon",
    "wof:placetype":"venue"
},
  "geometry": {"coordinates":[-84.39070100000001,33.756302],"type":"Point"}
}