{
  "type": "Feature",
  "properties": {
    "addr:full":"3020 Roswell Rd Marietta GA 30062",
    "addr:housenumber":"3020",
    "addr:postcode":"30062",
    "addr:street":"Roswell Rd",
    "iso:country":"US",
    "sg:address":"3020 Roswell Rd",
    "sg:city":"Marietta",
    "sg:classifiers":[
        {
            "category":"Professional",
            "subcategory":"Business Services",
            "type":"Services"
        }
    ],
    "sg:phone":"+1 770 509 2302",
    "sg:postcode":"30062",
    "sg:province":"GA",
    "wof:name":"Lake Enterprises",
    "wof:placetype":"venue"
},
  "geometry": {"coordinates":[-84.46154,33.979222],"type":"Point"}
}