{
  "type": "Feature",
  "properties": {
    "iso:country":"US",
    "sg:address":"6699 Peachtree Industrial Blvd",
    "sg:city":"Norcross",
    "sg:classifiers":[
        {
            "category":"Building & Trades",
            "subcategory":"Plumbing",
            "type":"Services"
        }
    ],
    "sg:phone":"+1 770 449 0200",
    "sg:postcode":"30092",
    "sg:province":"GA",
    "sg:tags":[
        "heating",
        "contractor"
    ],
    "sg:website":"www.capitalcitymechanical.com",
    "wof:name":"Capital City Mechanical Svc",
    "wof:placetype":"venue"
},
  "geometry": {"coordinates":[-84.250332,33.938278],"type":"Point"}
}