{
  "type": "Feature",
  "properties": {
    "iso:country":"US",
    "sg:address":"115 N 12th St",
    "sg:city":"Griffin",
    "sg:classifiers":[
        {
            "category":"Personal",
            "subcategory":"Beauty Salon",
            "type":"Services"
        }
    ],
    "sg:phone":"+1 770 229 4141",
    "sg:postcode":"30223",
    "sg:province":"GA",
    "sg:tags":[
        "shop"
    ],
    "wof:name":"Hair Dimensions",
    "wof:placetype":"venue"
},
  "geometry": {"coordinates":[-84.271861,33.249544],"type":"Point"}
}