{
  "type": "Feature",
  "properties": {
    "addr:full":"5677 Buford Hwy NE Atlanta GA 30340",
    "addr:housenumber":"5677",
    "addr:postcode":"30340",
    "addr:street":"Buford Hwy Ne",
    "iso:country":"US",
    "sg:address":"5677 Buford Hwy NE",
    "sg:city":"Atlanta",
    "sg:classifiers":[
        {
            "category":"Shopping",
            "subcategory":"Jewelry",
            "type":"Retail Goods"
        },
        {
            "category":"Manufacturing",
            "subcategory":"Jewelry",
            "type":"Manufacturing & Wholesale Goods"
        },
        {
            "category":"Shopping",
            "subcategory":"Pawn Shop",
            "type":"Retail Goods"
        }
    ],
    "sg:phone":"+1 770 457 3333",
    "sg:postcode":"30340",
    "sg:province":"GA",
    "sg:tags":[
        "buyer",
        "designer",
        "pawnbroker",
        "jeweler"
    ],
    "wof:name":"Hk Jewelry & Pawn",
    "wof:placetype":"venue"
},
  "geometry": {"coordinates":[-84.27033900000001,33.905819],"type":"Point"}
}