{
  "type": "Feature",
  "properties": {
    "iso:country":"US",
    "sg:address":"4061 Price Rd",
    "sg:city":"Gainesville",
    "sg:classifiers":[
        {
            "category":"Building & Trades",
            "subcategory":"Construction",
            "type":"Services"
        }
    ],
    "sg:phone":"+1 770 536 0904",
    "sg:postcode":"30506",
    "sg:province":"GA",
    "sg:tags":[
        "mfg",
        "contractor",
        "wood",
        "carpentry",
        "cabinet",
        "maker",
        "kitchen"
    ],
    "wof:name":"Rudy's Custom Cabinets",
    "wof:placetype":"venue"
},
  "geometry": {"coordinates":[-83.89059899999999,34.376426],"type":"Point"}
}