{
  "type": "Feature",
  "properties": {
    "addr:full":"431 W Ponce de Leon Ave Decatur GA 30030",
    "addr:housenumber":"431",
    "addr:postcode":"30030",
    "addr:street":"W Ponce De Leon Ave",
    "iso:country":"US",
    "sg:address":"431 W Ponce de Leon Ave",
    "sg:city":"Decatur",
    "sg:classifiers":[
        {
            "category":"Real Estate",
            "subcategory":"Real Estate Agent",
            "type":"Services"
        }
    ],
    "sg:phone":"+1 404 378 9000",
    "sg:postcode":"30030",
    "sg:province":"GA",
    "wof:name":"Dwellings",
    "wof:placetype":"venue"
},
  "geometry": {"coordinates":[-84.30324400000001,33.775738],"type":"Point"}
}