{
  "type": "Feature",
  "properties": {
    "addr:full":"715 Telfair St Dublin GA 31021",
    "addr:housenumber":"715",
    "addr:postcode":"31021",
    "addr:street":"Telfair St",
    "iso:country":"US",
    "sg:address":"715 Telfair St",
    "sg:city":"Dublin",
    "sg:classifiers":[
        {
            "category":"Autos & Motor Vehicles",
            "subcategory":"Automobile Sales",
            "type":"Retail Goods"
        }
    ],
    "sg:phone":"+1 478 272 6686",
    "sg:postcode":"31021",
    "sg:province":"GA",
    "sg:tags":[
        "car",
        "used",
        "dealer"
    ],
    "wof:name":"Holly's Auto Sale Inc",
    "wof:placetype":"venue"
},
  "geometry": {"coordinates":[-82.91055900000001,32.532615],"type":"Point"}
}