{
  "type": "Feature",
  "properties": {
    "iso:country":"US",
    "sg:address":"4431 State Rte 59",
    "sg:city":"Lavonia",
    "sg:classifiers":[
        {
            "category":"Retail",
            "subcategory":"Repair Shop",
            "type":"Services"
        }
    ],
    "sg:phone":"+1 706 245 6906",
    "sg:postcode":"30553",
    "sg:province":"GA",
    "wof:name":"Rons TV",
    "wof:placetype":"venue"
},
  "geometry": {"coordinates":[-83.096512,34.450788],"type":"Point"}
}