{
  "type": "Feature",
  "properties": {
    "iso:country":"US",
    "sg:address":"456 Clayroot Rd",
    "sg:city":"Dallas",
    "sg:classifiers":[
        {
            "category":"Building & Trades",
            "subcategory":"Construction",
            "type":"Services"
        }
    ],
    "sg:phone":"+1 770 443 6577",
    "sg:postcode":"30132",
    "sg:province":"GA",
    "sg:tags":[
        "wallcoverings-installation",
        "wallpaper",
        "painting",
        "contractor"
    ],
    "wof:name":"Steve Smith Painting & Wall",
    "wof:placetype":"venue"
},
  "geometry": {"coordinates":[-84.87385,34.046966],"type":"Point"}
}