{
  "type": "Feature",
  "properties": {
    "iso:country":"US",
    "sg:address":"5573 Pennybrook Trl",
    "sg:city":"Stone Mountain",
    "sg:classifiers":[
        {
            "category":"Professional",
            "subcategory":"Management & Consulting",
            "type":"Services"
        }
    ],
    "sg:phone":"+1 770 469 3406",
    "sg:postcode":"30087",
    "sg:province":"GA",
    "sg:tags":[
        "training",
        "program"
    ],
    "wof:name":"Rcip Inc",
    "wof:placetype":"venue"
},
  "geometry": {"coordinates":[-84.16001799999999,33.792983],"type":"Point"}
}