{
  "type": "Feature",
  "properties": {
    "iso:country":"US",
    "sg:address":"510 Mitchell St",
    "sg:city":"Adel",
    "sg:classifiers":[
        {
            "category":"Freight",
            "type":"Transportation"
        }
    ],
    "sg:phone":"+1 229 896 8737",
    "sg:postcode":"31620",
    "sg:province":"GA",
    "sg:tags":[
        "general"
    ],
    "wof:name":"Grinder Mini Storage",
    "wof:placetype":"venue"
},
  "geometry": {"coordinates":[-83.420452,31.148676],"type":"Point"}
}