{
  "type": "Feature",
  "properties": {
    "addr:full":"511 Lanier Blvd Brunswick GA 31520",
    "addr:housenumber":"511",
    "addr:postcode":"31520",
    "addr:street":"Lanier Blvd",
    "iso:country":"US",
    "sg:address":"511 Lanier Blvd",
    "sg:city":"Brunswick",
    "sg:classifiers":[
        {
            "category":"Professional",
            "type":"Services"
        }
    ],
    "sg:phone":"+1 912 267 0444",
    "sg:postcode":"31520",
    "sg:province":"GA",
    "wof:name":"Glynn Container Svc",
    "wof:placetype":"venue"
},
  "geometry": {"coordinates":[-81.35118799999999,31.182163],"type":"Point"}
}