{
  "type": "Feature",
  "properties": {
    "iso:country":"US",
    "sg:address":"79 Marietta Street NW",
    "sg:city":"Atlanta",
    "sg:classifiers":[
        {
            "category":"Wholesale",
            "subcategory":"Fruits & Vegetables",
            "type":"Manufacturing & Wholesale Goods"
        },
        {
            "category":"Food & Beverages",
            "subcategory":"Groceries & Convenience Stores",
            "type":"Retail Goods"
        }
    ],
    "sg:phone":"+1 404 221 0821",
    "sg:postcode":"30303",
    "sg:province":"GA",
    "sg:tags":[
        "veggie"
    ],
    "wof:name":"Grace & Leilanis Tropical Fruit",
    "wof:placetype":"venue"
},
  "geometry": {"coordinates":[-84.391813,33.75594],"type":"Point"}
}