{
  "type": "Feature",
  "properties": {
    "addr:full":"4421 Mathis Mill Rd Valdosta GA 31602",
    "addr:housenumber":"4421",
    "addr:postcode":"31602",
    "addr:street":"Mathis Mill Rd",
    "iso:country":"US",
    "sg:address":"4421 Mathis Mill Rd",
    "sg:city":"Valdosta",
    "sg:classifiers":[
        {
            "category":"Wholesale",
            "subcategory":"Stationery",
            "type":"Manufacturing & Wholesale Goods"
        }
    ],
    "sg:phone":"+1 229 245 1677",
    "sg:postcode":"31602",
    "sg:province":"GA",
    "sg:tags":[
        "school",
        "supply"
    ],
    "wof:name":"School Store",
    "wof:placetype":"venue"
},
  "geometry": {"coordinates":[-83.35303999999999,30.916607],"type":"Point"}
}