{
  "type": "Feature",
  "properties": {
    "iso:country":"US",
    "sg:address":"3084 Brookgreen Trl",
    "sg:city":"Lawrenceville",
    "sg:classifiers":[
        {
            "category":"Professional",
            "subcategory":"Computer Services",
            "type":"Services"
        }
    ],
    "sg:phone":"+1 770 682 1714",
    "sg:postcode":"30043",
    "sg:province":"GA",
    "sg:tags":[
        "design",
        "system"
    ],
    "wof:name":"Church Internet Services",
    "wof:placetype":"venue"
},
  "geometry": {"coordinates":[-83.982224,34.025981],"type":"Point"}
}