{
  "type": "Feature",
  "properties": {
    "iso:country":"US",
    "sg:address":"635 Holmes St NW",
    "sg:city":"Atlanta",
    "sg:classifiers":[
        {
            "category":"Professional",
            "subcategory":"Management & Consulting",
            "type":"Services"
        }
    ],
    "sg:phone":"+1 404 355 0375",
    "sg:postcode":"30318",
    "sg:province":"GA",
    "wof:name":"Krebs Management Services",
    "wof:placetype":"venue"
},
  "geometry": {"coordinates":[-84.40929300000001,33.799357],"type":"Point"}
}