{
  "type": "Feature",
  "properties": {
    "iso:country":"US",
    "sg:address":"9180 Four Mile Creek Rd",
    "sg:city":"Gainesville",
    "sg:classifiers":[
        {
            "category":"Shopping",
            "subcategory":"Department Store",
            "type":"Retail Goods"
        },
        {
            "category":"Shopping",
            "subcategory":"Discount & Variety Stores",
            "type":"Retail Goods"
        }
    ],
    "sg:phone":"+1 678 455 9574",
    "sg:postcode":"30506",
    "sg:province":"GA",
    "wof:name":"Santa's Best",
    "wof:placetype":"venue"
},
  "geometry": {"coordinates":[-84.011228,34.232611],"type":"Point"}
}