{
  "type": "Feature",
  "properties": {
    "iso:country":"US",
    "sg:address":"100 Peachtree St NW # 2200",
    "sg:city":"Atlanta",
    "sg:classifiers":[
        {
            "category":"Bars & Pubs",
            "type":"Food & Drink"
        },
        {
            "category":"Restaurant",
            "type":"Food & Drink"
        },
        {
            "category":"Fast Food",
            "type":"Food & Drink"
        }
    ],
    "sg:phone":"+1 404 522 4280",
    "sg:postcode":"30303",
    "sg:province":"GA",
    "sg:tags":[
        "grill",
        "hamburger",
        "american",
        "dog",
        "lunch",
        "hot",
        "take",
        "brunch",
        "breakfast"
    ],
    "wof:name":"Tgi Friday's",
    "wof:placetype":"venue"
},
  "geometry": {"coordinates":[-84.392275,33.751881],"type":"Point"}
}