{
  "type": "Feature",
  "properties": {
    "iso:country":"US",
    "sg:address":"103 N Crawford St",
    "sg:city":"Thomasville",
    "sg:classifiers":[
        {
            "category":"Organizations",
            "subcategory":"Religious Organization",
            "type":"Services"
        }
    ],
    "sg:phone":"+1 229 226 2540",
    "sg:postcode":"31792",
    "sg:province":"GA",
    "sg:tags":[
        "church"
    ],
    "wof:name":"Glory God Pentecostal Church",
    "wof:placetype":"venue"
},
  "geometry": {"coordinates":[-83.979997,30.83942],"type":"Point"}
}