{
  "type": "Feature",
  "properties": {
    "addr:full":"951 Edgewood Ave NE Atlanta GA 30307",
    "addr:housenumber":"951",
    "addr:postcode":"30307",
    "addr:street":"Edgewood Ave Ne",
    "iso:country":"US",
    "sg:address":"951 Edgewood Ave NE",
    "sg:city":"Atlanta",
    "sg:classifiers":[
        {
            "category":"Professional",
            "subcategory":"Advertising",
            "type":"Services"
        }
    ],
    "sg:phone":"+1 404 688 3800",
    "sg:postcode":"30307",
    "sg:province":"GA",
    "sg:tags":[
        "commercials-radio",
        "television",
        "rep"
    ],
    "sg:website":"www.comotionfilms.com",
    "wof:name":"Comotion Films",
    "wof:placetype":"venue"
},
  "geometry": {"coordinates":[-84.35741,33.756169],"type":"Point"}
}