{
  "type": "Feature",
  "properties": {
    "iso:country":"US",
    "sg:address":"300 Woodrow Wilson Dr",
    "sg:city":"Valdosta",
    "sg:classifiers":[
        {
            "category":"Health Services",
            "subcategory":"Clinic",
            "type":"Services"
        }
    ],
    "sg:phone":"+1 229 333 7658",
    "sg:postcode":"31602",
    "sg:province":"GA",
    "wof:name":"Library For The Blind",
    "wof:placetype":"venue"
},
  "geometry": {"coordinates":[-83.285721,30.8596],"type":"Point"}
}