{
  "type": "Feature",
  "properties": {
    "addr:full":"227 Lenox Ct Hiram GA 30141",
    "addr:housenumber":"227",
    "addr:postcode":"30141",
    "addr:street":"Lenox Ct",
    "iso:country":"US",
    "sg:address":"227 Lenox Ct",
    "sg:city":"Hiram",
    "sg:classifiers":[
        {
            "category":"Building & Trades",
            "subcategory":"Landscaping Services",
            "type":"Services"
        }
    ],
    "sg:phone":"+1 770 947 7047",
    "sg:postcode":"30141",
    "sg:province":"GA",
    "wof:name":"Short Cut Lawn Service",
    "wof:placetype":"venue"
},
  "geometry": {"coordinates":[-84.81562,33.842875],"type":"Point"}
}