{
  "type": "Feature",
  "properties": {
    "addr:full":"1281 Kennestone Cir Marietta GA 30066",
    "addr:housenumber":"1281",
    "addr:postcode":"30066",
    "addr:street":"Kennestone Cir",
    "iso:country":"US",
    "sg:address":"1281 Kennestone Cir",
    "sg:city":"Marietta",
    "sg:classifiers":[
        {
            "category":"Professional",
            "subcategory":"Lawyer & Legal Services",
            "type":"Services"
        }
    ],
    "sg:phone":"+1 770 424 8131",
    "sg:postcode":"30066",
    "sg:province":"GA",
    "wof:name":"Lantz Law Firm PC",
    "wof:placetype":"venue"
},
  "geometry": {"coordinates":[-84.54972600000001,33.979965],"type":"Point"}
}