{
  "type": "Feature",
  "properties": {
    "addr:full":"11124 Hawkinsville Rd Warner Robins GA 31093",
    "addr:housenumber":"11124",
    "addr:postcode":"31093",
    "addr:street":"Hawkinsville Rd",
    "iso:country":"US",
    "sg:address":"11124 Hawkinsville Rd",
    "sg:city":"Warner Robins",
    "sg:classifiers":[
        {
            "category":"Autos & Motor Vehicles",
            "subcategory":"Automobile Sales",
            "type":"Retail Goods"
        }
    ],
    "sg:phone":"+1 478 923 9714",
    "sg:postcode":"31093",
    "sg:province":"GA",
    "sg:tags":[
        "car",
        "dealer"
    ],
    "wof:name":"Tim's Used Hondas",
    "wof:placetype":"venue"
},
  "geometry": {"coordinates":[-83.613629,32.654408],"type":"Point"}
}