{
  "type": "Feature",
  "properties": {
    "iso:country":"US",
    "sg:address":"1895 Highway 20 SE",
    "sg:city":"Conyers",
    "sg:classifiers":[
        {
            "category":"Health Services",
            "subcategory":"Chiropractor",
            "type":"Services"
        }
    ],
    "sg:phone":"+1 770 922 0700",
    "sg:postcode":"30013",
    "sg:province":"GA",
    "wof:name":"Bodyzone Com",
    "wof:placetype":"venue"
},
  "geometry": {"coordinates":[-84.014297,33.633499],"type":"Point"}
}