{
  "type": "Feature",
  "properties": {
    "addr:full":"6690 Bobby John Rd Atlanta GA 30349",
    "addr:housenumber":"6690",
    "addr:postcode":"30349",
    "addr:street":"Bobby John Rd",
    "iso:country":"US",
    "sg:address":"6690 Bobby John Rd",
    "sg:city":"Atlanta",
    "sg:classifiers":[
        {
            "category":"Organizations",
            "subcategory":"Non-profit Organization",
            "type":"Services"
        }
    ],
    "sg:phone":"+1 770 964 2050",
    "sg:postcode":"30349",
    "sg:province":"GA",
    "sg:tags":[
        "social"
    ],
    "wof:name":"R J G & Associates Inc",
    "wof:placetype":"venue"
},
  "geometry": {"coordinates":[-84.602609,33.632658],"type":"Point"}
}