{
  "type": "Feature",
  "properties": {
    "iso:country":"US",
    "sg:address":"2400 W Doublegate Dr",
    "sg:city":"Albany",
    "sg:classifiers":[
        {
            "category":"Professional",
            "type":"Services"
        }
    ],
    "sg:phone":"+1 229 432 2860",
    "sg:postcode":"31721",
    "sg:province":"GA",
    "wof:name":"David Campbell Family Partners",
    "wof:placetype":"venue"
},
  "geometry": {"coordinates":[-84.260204,31.603353],"type":"Point"}
}