{
  "type": "Feature",
  "properties": {
    "addr:full":"202 W Waugh St Dalton GA 30720",
    "addr:housenumber":"202",
    "addr:postcode":"30720",
    "addr:street":"W Waugh St",
    "iso:country":"US",
    "sg:address":"202 W Waugh St",
    "sg:city":"Dalton",
    "sg:classifiers":[
        {
            "category":"Building & Trades",
            "subcategory":"Construction",
            "type":"Services"
        }
    ],
    "sg:phone":"+1 706 278 4548",
    "sg:postcode":"30720",
    "sg:province":"GA",
    "sg:tags":[
        "house"
    ],
    "wof:name":"Gwm Construction LLC",
    "wof:placetype":"venue"
},
  "geometry": {"coordinates":[-84.970162,34.774213],"type":"Point"}
}