{
  "type": "Feature",
  "properties": {
    "addr:full":"850 Pickens Industrial Dr Marietta GA 30062",
    "addr:housenumber":"850",
    "addr:postcode":"30062",
    "addr:street":"Pickens Industrial Dr",
    "iso:country":"US",
    "sg:address":"850 Pickens Industrial Dr",
    "sg:city":"Marietta",
    "sg:classifiers":[
        {
            "category":"Shopping",
            "subcategory":"Party Supplies",
            "type":"Retail Goods"
        },
        {
            "category":"Utilities",
            "subcategory":"Water",
            "type":"Services"
        },
        {
            "category":"Building & Trades",
            "subcategory":"Cleaning & Sanitation",
            "type":"Services"
        },
        {
            "category":"Retail",
            "subcategory":"Laundry & Dry Cleaning",
            "type":"Services"
        },
        {
            "category":"Home & Garden",
            "subcategory":"Carpets & Floor Coverings",
            "type":"Retail Goods"
        }
    ],
    "sg:phone":"+1 678 355 6645",
    "sg:postcode":"30062",
    "sg:province":"GA",
    "sg:tags":[
        "cleaner",
        "emergency",
        "cleaners-water",
        "rug",
        "damage",
        "extraction",
        "restoration",
        "extraction-equipment"
    ],
    "sg:website":"http://www.restor-it.net",
    "wof:name":"Restore-It Carpet Systems Inc",
    "wof:placetype":"venue"
},
  "geometry": {"coordinates":[-84.526608,33.972021],"type":"Point"}
}