{
  "type": "Feature",
  "properties": {
    "addr:full":"833 Campbell Hill St NW Marietta GA 30060",
    "addr:housenumber":"833",
    "addr:postcode":"30060",
    "addr:street":"Campbell Hill St Nw",
    "iso:country":"US",
    "sg:address":"833 Campbell Hill St NW",
    "sg:city":"Marietta",
    "sg:classifiers":[
        {
            "category":"Health Services",
            "subcategory":"Doctor",
            "type":"Services"
        }
    ],
    "sg:phone":"+1 770 424 8254",
    "sg:postcode":"30060",
    "sg:province":"GA",
    "sg:tags":[
        "physician",
        "surgeon"
    ],
    "wof:name":"Jose M Fernandez MD",
    "wof:placetype":"venue"
},
  "geometry": {"coordinates":[-84.552114,33.970803],"type":"Point"}
}