{
  "type": "Feature",
  "properties": {
    "addr:full":"772 North Ave Macon GA 31211",
    "addr:housenumber":"772",
    "addr:postcode":"31211",
    "addr:street":"North Ave",
    "iso:country":"US",
    "sg:address":"772 North Ave",
    "sg:city":"Macon",
    "sg:classifiers":[
        {
            "category":"Manufacturing",
            "subcategory":"Retail Goods",
            "type":"Manufacturing & Wholesale Goods"
        }
    ],
    "sg:phone":"+1 478 750 0510",
    "sg:postcode":"31211",
    "sg:province":"GA",
    "sg:tags":[
        "product",
        "mfg"
    ],
    "wof:name":"Cosmo Industries",
    "wof:placetype":"venue"
},
  "geometry": {"coordinates":[-83.623334,32.85221],"type":"Point"}
}