{
  "type": "Feature",
  "properties": {
    "addr:full":"958 Lafayette St Ringgold GA 30736",
    "addr:housenumber":"958",
    "addr:postcode":"30736",
    "addr:street":"Lafayette St",
    "iso:country":"US",
    "sg:address":"958 Lafayette St",
    "sg:city":"Ringgold",
    "sg:classifiers":[
        {
            "category":"Personal",
            "subcategory":"Beauty Salon",
            "type":"Services"
        }
    ],
    "sg:phone":"+1 706 935 6888",
    "sg:postcode":"30736",
    "sg:province":"GA",
    "wof:name":"Jaz Styling Studio",
    "wof:placetype":"venue"
},
  "geometry": {"coordinates":[-85.109717,34.915326],"type":"Point"}
}