{
  "type": "Feature",
  "properties": {
    "iso:country":"US",
    "sg:address":"1151 North Ave NE",
    "sg:city":"Atlanta",
    "sg:classifiers":[
        {
            "category":"Shopping",
            "type":"Retail Goods"
        }
    ],
    "sg:phone":"+1 404 255 7717",
    "sg:postcode":"30307",
    "sg:province":"GA",
    "sg:tags":[
        "equipment",
        "merchandise"
    ],
    "wof:name":"Biomet-Atlanta Orthopaedics",
    "wof:placetype":"venue"
},
  "geometry": {"coordinates":[-84.349594,33.771002],"type":"Point"}
}