{
  "type": "Feature",
  "properties": {
    "addr:full":"1205 Commerce Rd Athens GA 30607",
    "addr:housenumber":"1205",
    "addr:postcode":"30607",
    "addr:street":"Commerce Rd",
    "iso:country":"US",
    "sg:address":"1205 Commerce Rd",
    "sg:city":"Athens",
    "sg:classifiers":[
        {
            "category":"Wholesale",
            "subcategory":"Electrical",
            "type":"Manufacturing & Wholesale Goods"
        }
    ],
    "sg:phone":"+1 706 546 0595",
    "sg:postcode":"30607",
    "sg:province":"GA",
    "sg:tags":[
        "electric",
        "motor"
    ],
    "wof:name":"Grainger Inc",
    "wof:placetype":"venue"
},
  "geometry": {"coordinates":[-83.377043,33.982913],"type":"Point"}
}