{
  "type": "Feature",
  "properties": {
    "iso:country":"US",
    "sg:address":"52 N Main St",
    "sg:city":"Alpharetta",
    "sg:classifiers":[
        {
            "category":"Shopping",
            "subcategory":"Antiques",
            "type":"Retail Goods"
        }
    ],
    "sg:phone":"+1 770 777 2050",
    "sg:postcode":"30009",
    "sg:province":"GA",
    "wof:name":"Ivy Interiors",
    "wof:placetype":"venue"
},
  "geometry": {"coordinates":[-84.29468799999999,34.076901],"type":"Point"}
}