{
  "type": "Feature",
  "properties": {
    "addr:full":"6430 Ridge Rd Appling GA 30802",
    "addr:housenumber":"6430",
    "addr:postcode":"30802",
    "addr:street":"Ridge Rd",
    "iso:country":"US",
    "sg:address":"6430 Ridge Rd",
    "sg:city":"Appling",
    "sg:classifiers":[
        {
            "category":"Real Estate",
            "subcategory":"Developer",
            "type":"Services"
        }
    ],
    "sg:phone":"+1 706 541 0818",
    "sg:postcode":"30802",
    "sg:province":"GA",
    "wof:name":"Dew Land Development Co Inc",
    "wof:placetype":"venue"
},
  "geometry": {"coordinates":[-82.322046,33.661864],"type":"Point"}
}