{
  "type": "Feature",
  "properties": {
    "iso:country":"US",
    "sg:address":"510 Tift Ave S",
    "sg:city":"Tifton",
    "sg:classifiers":[
        {
            "category":"Recreation",
            "type":"Entertainment"
        }
    ],
    "sg:phone":"+1 229 387 8400",
    "sg:postcode":"31794",
    "sg:province":"GA",
    "sg:tags":[
        "parlor",
        "billiard"
    ],
    "wof:name":"Spot Shot Billiard",
    "wof:placetype":"venue"
},
  "geometry": {"coordinates":[-83.50716300000001,31.455213],"type":"Point"}
}