{
  "type": "Feature",
  "properties": {
    "addr:full":"340 W Church St Jasper GA 30143",
    "addr:housenumber":"340",
    "addr:postcode":"30143",
    "addr:street":"W Church St",
    "iso:country":"US",
    "sg:address":"340 W Church St",
    "sg:city":"Jasper",
    "sg:classifiers":[
        {
            "category":"Cinema",
            "subcategory":"Movie Rental",
            "type":"Entertainment"
        }
    ],
    "sg:phone":"+1 706 692 3147",
    "sg:postcode":"30143",
    "sg:province":"GA",
    "sg:tags":[
        "leasing",
        "video",
        "disc",
        "tape"
    ],
    "wof:name":"Movie Gallery",
    "wof:placetype":"venue"
},
  "geometry": {"coordinates":[-84.435237,34.466073],"type":"Point"}
}