{
  "type": "Feature",
  "properties": {
    "addr:full":"17161 Birmingham Hwy Alpharetta GA 30004",
    "addr:housenumber":"17161",
    "addr:postcode":"30004",
    "addr:street":"Birmingham Hwy",
    "iso:country":"US",
    "sg:address":"17161 Birmingham Hwy",
    "sg:city":"Alpharetta",
    "sg:classifiers":[
        {
            "category":"Organizations",
            "subcategory":"Community Association",
            "type":"Services"
        }
    ],
    "sg:phone":"+1 678 624 9331",
    "sg:postcode":"30004",
    "sg:province":"GA",
    "sg:tags":[
        "club"
    ],
    "wof:name":"Georgia Tech Club",
    "wof:placetype":"venue"
},
  "geometry": {"coordinates":[-84.318338,34.184804],"type":"Point"}
}