{
  "type": "Feature",
  "properties": {
    "iso:country":"US",
    "sg:address":"1899 Powers Ferry Rd SE",
    "sg:city":"Atlanta",
    "sg:classifiers":[
        {
            "category":"Personal",
            "type":"Services"
        }
    ],
    "sg:phone":"+1 770 980 0828",
    "sg:postcode":"30339",
    "sg:province":"GA",
    "sg:tags":[
        "hair",
        "replacement"
    ],
    "wof:name":"Hair Club For Men of Georgia",
    "wof:placetype":"venue"
},
  "geometry": {"coordinates":[-84.464608,33.906716],"type":"Point"}
}