{
  "type": "Feature",
  "properties": {
    "addr:full":"1651 Horizon Pkwy Ste 700 Buford GA 30518",
    "addr:housenumber":"1651",
    "addr:postcode":"30518",
    "addr:street":"Horizon Pkwy Ste 700",
    "iso:country":"US",
    "sg:address":"1651 Horizon Pkwy Ste 700",
    "sg:city":"Buford",
    "sg:classifiers":[
        {
            "category":"Shopping",
            "subcategory":"Bicycles & Sporting Goods",
            "type":"Retail Goods"
        }
    ],
    "sg:phone":"+1 770 614 4780",
    "sg:postcode":"30518",
    "sg:province":"GA",
    "wof:name":"Good Sports the",
    "wof:placetype":"venue"
},
  "geometry": {"coordinates":[-83.997545,34.083187],"type":"Point"}
}