{
  "type": "Feature",
  "properties": {
    "iso:country":"US",
    "sg:address":"275 Marion Blvd",
    "sg:city":"Fayetteville",
    "sg:classifiers":[
        {
            "category":"Professional",
            "subcategory":"Management & Consulting",
            "type":"Services"
        }
    ],
    "sg:phone":"+1 678 817 1505",
    "sg:postcode":"30215",
    "sg:province":"GA",
    "sg:tags":[
        "consultant",
        "business"
    ],
    "wof:name":"Talx CORP",
    "wof:placetype":"venue"
},
  "geometry": {"coordinates":[-84.433348,33.424168],"type":"Point"}
}