{
  "type": "Feature",
  "properties": {
    "iso:country":"US",
    "sg:address":"195 S Boulevard St",
    "sg:city":"Camilla",
    "sg:classifiers":[
        {
            "category":"Autos & Motor Vehicles",
            "subcategory":"Fuel & Gas Station",
            "type":"Retail Goods"
        },
        {
            "category":"Shopping",
            "type":"Retail Goods"
        },
        {
            "category":"Food & Beverages",
            "subcategory":"Groceries & Convenience Stores",
            "type":"Retail Goods"
        }
    ],
    "sg:phone":"+1 229 336 0412",
    "sg:postcode":"31730",
    "sg:province":"GA",
    "sg:tags":[
        "merchandise"
    ],
    "sg:website":"http://www.bp.com",
    "wof:name":"Amoco Food Shop 28",
    "wof:placetype":"venue"
},
  "geometry": {"coordinates":[-84.21291100000001,31.222605],"type":"Point"}
}