{
  "type": "Feature",
  "properties": {
    "addr:full":"8572 Pinecliff Rd Camilla GA 31730",
    "addr:housenumber":"8572",
    "addr:postcode":"31730",
    "addr:street":"Pinecliff Rd",
    "iso:country":"US",
    "sg:address":"8572 Pinecliff Rd",
    "sg:city":"Camilla",
    "sg:classifiers":[
        {
            "category":"Place Of Worship",
            "subcategory":"Church",
            "type":"Public Place"
        },
        {
            "category":"Place Of Worship",
            "type":"Public Place"
        },
        {
            "category":"Organizations",
            "subcategory":"Religious Organization",
            "type":"Services"
        }
    ],
    "sg:phone":"+1 229 336 5661",
    "sg:postcode":"31730",
    "sg:province":"GA",
    "sg:tags":[
        "churches-baptist-general",
        "churches-baptist"
    ],
    "wof:name":"Mount Zion Baptist Church",
    "wof:placetype":"venue"
},
  "geometry": {"coordinates":[-84.34013,31.241949],"type":"Point"}
}