{
  "type": "Feature",
  "properties": {
    "addr:full":"3338 Country Club Rd Valdosta GA 31605",
    "addr:housenumber":"3338",
    "addr:postcode":"31605",
    "addr:street":"Country Club Rd",
    "iso:country":"US",
    "sg:address":"3338 Country Club Rd",
    "sg:city":"Valdosta",
    "sg:phone":"+1 229 244 5314",
    "sg:postcode":"31605",
    "sg:province":"GA",
    "sg:website":"http://www.southgadrx.com",
    "wof:name":"Pridgen Chiropractic",
    "wof:placetype":"venue"
},
  "geometry": {"coordinates":[-83.29631000000001,30.87999],"type":"Point"}
}