{
  "type": "Feature",
  "properties": {
    "addr:full":"925 Main St Stone Mountain GA 30083",
    "addr:housenumber":"925",
    "addr:postcode":"30083",
    "addr:street":"Main St",
    "iso:country":"US",
    "sg:address":"925 Main St",
    "sg:city":"Stone Mountain",
    "sg:classifiers":[
        {
            "category":"Professional",
            "subcategory":"Computer Services",
            "type":"Services"
        }
    ],
    "sg:phone":"+1 770 413 8996",
    "sg:postcode":"30083",
    "sg:province":"GA",
    "sg:tags":[
        "repair"
    ],
    "sg:website":"www.virtualoffice2001.com",
    "wof:name":"Vision Tech Computer Svc",
    "wof:placetype":"venue"
},
  "geometry": {"coordinates":[-84.170267,33.806254],"type":"Point"}
}