{
  "type": "Feature",
  "properties": {
    "iso:country":"US",
    "sg:address":"121 Castle Oak Ct",
    "sg:city":"Kingsland",
    "sg:classifiers":[
        {
            "category":"Professional",
            "subcategory":"Accounting & Tax Preparation",
            "type":"Services"
        }
    ],
    "sg:phone":"+1 912 673 6919",
    "sg:postcode":"31548",
    "sg:province":"GA",
    "sg:tags":[
        "accountant"
    ],
    "wof:name":"JMH Bookkeeping Svc",
    "wof:placetype":"venue"
},
  "geometry": {"coordinates":[-81.709372,30.80396],"type":"Point"}
}