{
  "type": "Feature",
  "properties": {
    "addr:full":"1005 Hogansville Rd Lagrange GA 30241",
    "addr:housenumber":"1005",
    "addr:postcode":"30241",
    "addr:street":"Hogansville Rd",
    "iso:country":"US",
    "sg:address":"1005 Hogansville Rd",
    "sg:city":"Lagrange",
    "sg:classifiers":[
        {
            "category":"Autos & Motor Vehicles",
            "subcategory":"Automobile Sales",
            "type":"Retail Goods"
        }
    ],
    "sg:phone":"+1 706 882 6643",
    "sg:postcode":"30241",
    "sg:province":"GA",
    "sg:tags":[
        "dealers-used",
        "car",
        "used",
        "cars-wholesale"
    ],
    "wof:name":"Motormax Of La Grange Inc",
    "wof:placetype":"venue"
},
  "geometry": {"coordinates":[-85.00931,33.049853],"type":"Point"}
}