{
  "type": "Feature",
  "properties": {
    "addr:full":"1120 Arya Dr Roswell GA 30076",
    "addr:housenumber":"1120",
    "addr:postcode":"30076",
    "addr:street":"Arya Dr",
    "iso:country":"US",
    "sg:address":"1120 Arya Dr",
    "sg:city":"Roswell",
    "sg:classifiers":[
        {
            "category":"Professional",
            "subcategory":"Business Services",
            "type":"Services"
        }
    ],
    "sg:phone":"+1 678 895 7475",
    "sg:postcode":"30076",
    "sg:province":"GA",
    "wof:name":"Arcada Solutions",
    "wof:placetype":"venue"
},
  "geometry": {"coordinates":[-84.339997,34.064128],"type":"Point"}
}