{
  "type": "Feature",
  "properties": {
    "iso:country":"US",
    "sg:address":"1649 Sands Pl",
    "sg:city":"Marietta",
    "sg:classifiers":[
        {
            "category":"Wholesale",
            "subcategory":"Auto Parts",
            "type":"Manufacturing & Wholesale Goods"
        }
    ],
    "sg:phone":"+1 770 953 3425",
    "sg:postcode":"30067",
    "sg:province":"GA",
    "sg:tags":[
        "automobile",
        "rebuilt"
    ],
    "wof:name":"Japanese Engine Of Atlanta",
    "wof:placetype":"venue"
},
  "geometry": {"coordinates":[-84.493618,33.914912],"type":"Point"}
}