{
  "type": "Feature",
  "properties": {
    "iso:country":"US",
    "sg:address":"13 Smith St",
    "sg:city":"Fairburn",
    "sg:classifiers":[
        {
            "category":"Restaurant",
            "type":"Food & Drink"
        }
    ],
    "sg:phone":"+1 770 964 9909",
    "sg:postcode":"30213",
    "sg:province":"GA",
    "sg:tags":[
        "mexican"
    ],
    "wof:name":"Taqueria Iztaccihuatl",
    "wof:placetype":"venue"
},
  "geometry": {"coordinates":[-84.582477,33.565933],"type":"Point"}
}