{
  "type": "Feature",
  "properties": {
    "addr:full":"30581 US Hwy 441 S Commerce GA 30529",
    "addr:postcode":"30581;30529",
    "addr:street":"Us Hwy 441 S",
    "iso:country":"US",
    "sg:address":"30581 US Hwy 441 S",
    "sg:city":"Commerce",
    "sg:classifiers":[
        {
            "category":"Food & Beverages",
            "subcategory":"Groceries & Convenience Stores",
            "type":"Retail Goods"
        }
    ],
    "sg:phone":"+1 706 335 6396",
    "sg:postcode":"30529",
    "sg:province":"GA",
    "wof:name":"Sam's Food Mart",
    "wof:placetype":"venue"
},
  "geometry": {"coordinates":[-83.464084,34.257008],"type":"Point"}
}