{
  "type": "Feature",
  "properties": {
    "iso:country":"US",
    "sg:address":"402 N Park Dr",
    "sg:city":"Dalton",
    "sg:classifiers":[
        {
            "category":"Professional",
            "subcategory":"Art Services",
            "type":"Services"
        }
    ],
    "sg:phone":"+1 706 272 6320",
    "sg:postcode":"30720",
    "sg:province":"GA",
    "sg:tags":[
        "photographer",
        "photography",
        "commercial"
    ],
    "wof:name":"Studio Graphics",
    "wof:placetype":"venue"
},
  "geometry": {"coordinates":[-84.979366,34.799523],"type":"Point"}
}