{
  "type": "Feature",
  "properties": {
    "iso:country":"US",
    "sg:address":"928 Blacklawn Rd SW",
    "sg:city":"Conyers",
    "sg:classifiers":[
        {
            "category":"Real Estate",
            "subcategory":"Surveying",
            "type":"Services"
        }
    ],
    "sg:phone":"+1 770 483 9745",
    "sg:postcode":"30094",
    "sg:province":"GA",
    "sg:tags":[
        "surveyor",
        "engineering",
        "land"
    ],
    "wof:name":"Patrick & Associates Inc",
    "wof:placetype":"venue"
},
  "geometry": {"coordinates":[-84.039525,33.666976],"type":"Point"}
}