{
  "type": "Feature",
  "properties": {
    "addr:full":"1500 Comfort Rd Augusta GA 30909",
    "addr:housenumber":"1500",
    "addr:postcode":"30909",
    "addr:street":"Comfort Rd",
    "iso:country":"US",
    "sg:address":"1500 Comfort Rd",
    "sg:city":"Augusta",
    "sg:classifiers":[
        {
            "category":"Organizations",
            "subcategory":"Professional Association",
            "type":"Services"
        }
    ],
    "sg:phone":"+1 706 736 6222",
    "sg:postcode":"30909",
    "sg:province":"GA",
    "wof:name":"Augusta Golf Assn",
    "wof:placetype":"venue"
},
  "geometry": {"coordinates":[-82.046486,33.472976],"type":"Point"}
}