{
  "type": "Feature",
  "properties": {
    "addr:full":"8290 Roswell Rd Atlanta GA 30350",
    "addr:housenumber":"8290",
    "addr:postcode":"30350",
    "addr:street":"Roswell Rd",
    "iso:country":"US",
    "sg:address":"8290 Roswell Rd",
    "sg:city":"Atlanta",
    "sg:classifiers":[
        {
            "category":"Restaurant",
            "type":"Food & Drink"
        }
    ],
    "sg:menulink":"http://www.allmenus.com/ga/atlanta/246745-chips-authentic-southern-cooking/menu/",
    "sg:phone":"+1 678 822 2200",
    "sg:postcode":"30350",
    "sg:province":"GA",
    "sg:tags":[
        "american",
        "southern"
    ],
    "wof:name":"Chips Authentic Southern Cooking",
    "wof:placetype":"venue"
},
  "geometry": {"coordinates":[-84.351122,33.981236],"type":"Point"}
}