{
  "type": "Feature",
  "properties": {
    "addr:full":"2860 Carmain Dr Marietta GA 30064",
    "addr:housenumber":"2860",
    "addr:postcode":"30064",
    "addr:street":"Carmain Dr",
    "iso:country":"US",
    "sg:address":"2860 Carmain Dr",
    "sg:city":"Marietta",
    "sg:classifiers":[
        {
            "category":"Professional",
            "subcategory":"Computer Services",
            "type":"Services"
        }
    ],
    "sg:phone":"+1 770 309 2124",
    "sg:postcode":"30064",
    "sg:province":"GA",
    "sg:website":"www.stjamesmarietta.com",
    "wof:name":"Computer Aid Inc",
    "wof:placetype":"venue"
},
  "geometry": {"coordinates":[-84.634443,33.962317],"type":"Point"}
}