{
  "type": "Feature",
  "properties": {
    "addr:full":"3001 Woodward Park Way Suwanee GA 30024",
    "addr:housenumber":"3001",
    "addr:postcode":"30024",
    "addr:street":"Woodward Park Way",
    "iso:country":"US",
    "sg:address":"3001 Woodward Park Way",
    "sg:city":"Suwanee",
    "sg:classifiers":[
        {
            "category":"Insurance",
            "subcategory":"Insurance Agent",
            "type":"Services"
        }
    ],
    "sg:phone":"+1 770 476 4088",
    "sg:postcode":"30024",
    "sg:province":"GA",
    "wof:name":"Rodger Wood & Associates",
    "wof:placetype":"venue"
},
  "geometry": {"coordinates":[-84.068634,34.021169],"type":"Point"}
}