{
  "type": "Feature",
  "properties": {
    "addr:full":"1960 Mount Zion Rd Morrow GA 30260",
    "addr:housenumber":"1960",
    "addr:postcode":"30260",
    "addr:street":"Mount Zion Rd",
    "iso:country":"US",
    "sg:address":"1960 Mount Zion Rd",
    "sg:city":"Morrow",
    "sg:classifiers":[
        {
            "category":"Shopping",
            "subcategory":"Clothing, Apparel, & Fashions",
            "type":"Retail Goods"
        }
    ],
    "sg:phone":"+1 770 477 5111",
    "sg:postcode":"30260",
    "sg:province":"GA",
    "wof:name":"Mothers Work",
    "wof:placetype":"venue"
},
  "geometry": {"coordinates":[-84.32670899999999,33.565528],"type":"Point"}
}