{
  "type": "Feature",
  "properties": {
    "addr:full":"1022 Riverbend Rd Dalton GA 30721",
    "addr:housenumber":"1022",
    "addr:postcode":"30721",
    "addr:street":"Riverbend Rd",
    "iso:country":"US",
    "sg:address":"1022 Riverbend Rd",
    "sg:city":"Dalton",
    "sg:classifiers":[
        {
            "category":"Restaurant",
            "type":"Food & Drink"
        }
    ],
    "sg:phone":"+1 706 278 2273",
    "sg:postcode":"30721",
    "sg:province":"GA",
    "sg:tags":[
        "style",
        "family"
    ],
    "wof:name":"Kenny's Restaurant",
    "wof:placetype":"venue"
},
  "geometry": {"coordinates":[-84.9508,34.757869],"type":"Point"}
}