{
  "type": "Feature",
  "properties": {
    "iso:country":"US",
    "sg:address":"1010 James Burgess Rd",
    "sg:city":"Suwanee",
    "sg:classifiers":[
        {
            "category":"Building & Trades",
            "subcategory":"Electrical",
            "type":"Services"
        }
    ],
    "sg:phone":"+1 770 886 0752",
    "sg:postcode":"30024",
    "sg:province":"GA",
    "sg:tags":[
        "electrical",
        "contractor"
    ],
    "wof:name":"Blackstock Electric Inc",
    "wof:placetype":"venue"
},
  "geometry": {"coordinates":[-84.118139,34.116978],"type":"Point"}
}