{
  "type": "Feature",
  "properties": {
    "addr:full":"715 Woodbrook Way Lawrenceville GA 30043",
    "addr:housenumber":"715",
    "addr:postcode":"30043",
    "addr:street":"Woodbrook Way",
    "iso:country":"US",
    "sg:address":"715 Woodbrook Way",
    "sg:city":"Lawrenceville",
    "sg:classifiers":[
        {
            "category":"Professional",
            "type":"Services"
        }
    ],
    "sg:phone":"+1 770 339 9533",
    "sg:postcode":"30043",
    "sg:province":"GA",
    "wof:name":"William Flanagan",
    "wof:placetype":"venue"
},
  "geometry": {"coordinates":[-84.016291,34.034163],"type":"Point"}
}