{
  "type": "Feature",
  "properties": {
    "iso:country":"US",
    "sg:address":"1215 S Hairston Rd",
    "sg:city":"Stone Mountain",
    "sg:classifiers":[
        {
            "category":"Restaurant",
            "type":"Food & Drink"
        }
    ],
    "sg:phone":"+1 404 292 0404",
    "sg:postcode":"30088",
    "sg:province":"GA",
    "wof:name":"KFC",
    "wof:placetype":"venue"
},
  "geometry": {"coordinates":[-84.19710600000001,33.758173],"type":"Point"}
}