{
  "type": "Feature",
  "properties": {
    "addr:full":"601 Broad St Hawkinsville GA 31036",
    "addr:housenumber":"601",
    "addr:postcode":"31036",
    "addr:street":"Broad St",
    "iso:country":"US",
    "sg:address":"601 Broad St",
    "sg:city":"Hawkinsville",
    "sg:classifiers":[
        {
            "category":"Building & Trades",
            "subcategory":"Pest Control",
            "type":"Services"
        }
    ],
    "sg:phone":"+1 478 892 3307",
    "sg:postcode":"31036",
    "sg:province":"GA",
    "wof:name":"Orkin Exterminating Co Inc",
    "wof:placetype":"venue"
},
  "geometry": {"coordinates":[-83.479934,32.28134],"type":"Point"}
}