{
  "type": "Feature",
  "properties": {
    "iso:country":"US",
    "sg:address":"3636 Dallas Hwy SW",
    "sg:city":"Marietta",
    "sg:classifiers":[
        {
            "category":"Restaurant",
            "type":"Food & Drink"
        }
    ],
    "sg:menulink":"http://www.allmenus.com/ga/acworth-kennesaw/89548-moes-southwest-grill/menu/",
    "sg:phone":"+1 678 354 0331",
    "sg:postcode":"30064",
    "sg:province":"GA",
    "sg:tags":[
        "mexican"
    ],
    "wof:name":"Moe's Southwest Grill",
    "wof:placetype":"venue"
},
  "geometry": {"coordinates":[-84.65818,33.95354],"type":"Point"}
}