{
  "type": "Feature",
  "properties": {
    "addr:full":"1439 Toms Creek Rd Fargo GA 31631",
    "addr:housenumber":"1439",
    "addr:postcode":"31631",
    "addr:street":"Toms Creek Rd",
    "iso:country":"US",
    "sg:address":"1439 Toms Creek Rd",
    "sg:city":"Fargo",
    "sg:classifiers":[
        {
            "category":"Professional",
            "subcategory":"Business Services",
            "type":"Services"
        }
    ],
    "sg:phone":"+1 912 637 5575",
    "sg:postcode":"31631",
    "sg:province":"GA",
    "wof:name":"Applied Technologies Inc",
    "wof:placetype":"venue"
},
  "geometry": {"coordinates":[-82.756297,30.653648],"type":"Point"}
}