{
  "type": "Feature",
  "properties": {
    "addr:full":"5505 Peachtree Rd Atlanta GA 30341",
    "addr:housenumber":"5505",
    "addr:postcode":"30341",
    "addr:street":"Peachtree Rd",
    "iso:country":"US",
    "sg:address":"5505 Peachtree Rd",
    "sg:city":"Atlanta",
    "sg:classifiers":[
        {
            "category":"Health Services",
            "subcategory":"Medical Lab",
            "type":"Services"
        }
    ],
    "sg:phone":"+1 404 256 2336",
    "sg:postcode":"30341",
    "sg:province":"GA",
    "sg:tags":[
        "laboratory"
    ],
    "sg:website":"http://www.questdiagnostics.com",
    "wof:name":"Quest Diagnostics Incorporated",
    "wof:placetype":"venue"
},
  "geometry": {"coordinates":[-84.29863899999999,33.89413],"type":"Point"}
}