{
  "type": "Feature",
  "properties": {
    "addr:full":"124 E Montgomery St Villa Rica GA 30180",
    "addr:housenumber":"124",
    "addr:postcode":"30180",
    "addr:street":"E Montgomery St",
    "iso:country":"US",
    "sg:address":"124 E Montgomery St",
    "sg:city":"Villa Rica",
    "sg:classifiers":[
        {
            "category":"Shopping",
            "subcategory":"Clothing, Apparel, & Fashions",
            "type":"Retail Goods"
        }
    ],
    "sg:phone":"+1 770 459 6028",
    "sg:postcode":"30180",
    "sg:province":"GA",
    "wof:name":"Elizabeths Fashion Boutique",
    "wof:placetype":"venue"
},
  "geometry": {"coordinates":[-84.917304,33.729579],"type":"Point"}
}