{
  "type": "Feature",
  "properties": {
    "addr:full":"1983 Valley Ridge Ln Duluth GA 30096",
    "addr:housenumber":"1983",
    "addr:postcode":"30096",
    "addr:street":"Valley Ridge Ln",
    "iso:country":"US",
    "sg:address":"1983 Valley Ridge Ln",
    "sg:city":"Duluth",
    "sg:classifiers":[
        {
            "category":"Building & Trades",
            "subcategory":"Landscaping Services",
            "type":"Services"
        }
    ],
    "sg:phone":"+1 404 259 5943",
    "sg:postcode":"30096",
    "sg:province":"GA",
    "wof:name":"Precision Tree Experts",
    "wof:placetype":"venue"
},
  "geometry": {"coordinates":[-84.165987,33.939312],"type":"Point"}
}