{
  "type": "Feature",
  "properties": {
    "iso:country":"US",
    "sg:address":"2420 Chapman Ct",
    "sg:city":"Augusta",
    "sg:classifiers":[
        {
            "category":"Professional",
            "type":"Services"
        }
    ],
    "sg:phone":"+1 706 481 1996",
    "sg:postcode":"30909",
    "sg:province":"GA",
    "wof:name":"Errand Eraser",
    "wof:placetype":"venue"
},
  "geometry": {"coordinates":[-82.023478,33.505675],"type":"Point"}
}