{
  "type": "Feature",
  "properties": {
    "iso:country":"US",
    "sg:address":"5824 Western Hills Dr",
    "sg:city":"Norcross",
    "sg:classifiers":[
        {
            "category":"Wholesale",
            "subcategory":"Vending Machines",
            "type":"Manufacturing & Wholesale Goods"
        }
    ],
    "sg:phone":"+1 770 441 2074",
    "sg:postcode":"30071",
    "sg:province":"GA",
    "sg:tags":[
        "operator"
    ],
    "wof:name":"Help Yourself Vending",
    "wof:placetype":"venue"
},
  "geometry": {"coordinates":[-84.206834,33.924188],"type":"Point"}
}