{
  "type": "Feature",
  "properties": {
    "iso:country":"US",
    "sg:address":"364 Louis Parker Rd",
    "sg:city":"Dublin",
    "sg:classifiers":[
        {
            "category":"Professional",
            "type":"Services"
        }
    ],
    "sg:phone":"+1 478 275 3247",
    "sg:postcode":"31021",
    "sg:province":"GA",
    "wof:name":"Breaux Electricaal",
    "wof:placetype":"venue"
},
  "geometry": {"coordinates":[-82.896649,32.568718],"type":"Point"}
}