{
  "type": "Feature",
  "properties": {
    "iso:country":"US",
    "sg:address":"127 Buckeye Rd",
    "sg:city":"Fayetteville",
    "sg:classifiers":[
        {
            "category":"Manufacturing",
            "subcategory":"Wood Products",
            "type":"Manufacturing & Wholesale Goods"
        }
    ],
    "sg:phone":"+1 770 964 3025",
    "sg:postcode":"30214",
    "sg:province":"GA",
    "sg:tags":[
        "mfg"
    ],
    "wof:name":"Maces Woodcraft",
    "wof:placetype":"venue"
},
  "geometry": {"coordinates":[-84.52706999999999,33.504136],"type":"Point"}
}