{
  "type": "Feature",
  "properties": {
    "addr:full":"1612 Collins Hill Rd Lawrenceville GA 30043",
    "addr:housenumber":"1612",
    "addr:postcode":"30043",
    "addr:street":"Collins Hill Rd",
    "iso:country":"US",
    "sg:address":"1612 Collins Hill Rd",
    "sg:city":"Lawrenceville",
    "sg:classifiers":[
        {
            "category":"Organizations",
            "subcategory":"Religious Organization",
            "type":"Services"
        }
    ],
    "sg:phone":"+1 770 962 0642",
    "sg:postcode":"30043",
    "sg:province":"GA",
    "sg:tags":[
        "education"
    ],
    "sg:website":"www.chcscrusaders.org",
    "wof:name":"Collins Hill Baptist Church & Christian School",
    "wof:placetype":"venue"
},
  "geometry": {"coordinates":[-84.012604,33.9977],"type":"Point"}
}