{
  "type": "Feature",
  "properties": {
    "addr:full":"2712 Parkwood Dr Brunswick GA 31520",
    "addr:housenumber":"2712",
    "addr:postcode":"31520",
    "addr:street":"Parkwood Dr",
    "iso:country":"US",
    "sg:address":"2712 Parkwood Dr",
    "sg:city":"Brunswick",
    "sg:classifiers":[
        {
            "category":"Health Services",
            "subcategory":"Doctor",
            "type":"Services"
        }
    ],
    "sg:phone":"+1 912 267 7780",
    "sg:postcode":"31520",
    "sg:province":"GA",
    "sg:tags":[
        "physician",
        "surgeon"
    ],
    "wof:name":"Anna Cabeca PC",
    "wof:placetype":"venue"
},
  "geometry": {"coordinates":[-81.481465,31.173291],"type":"Point"}
}