{
  "type": "Feature",
  "properties": {
    "addr:full":"2500 McCurdy Way Decatur GA 30033",
    "addr:housenumber":"2500",
    "addr:postcode":"30033",
    "addr:street":"Mccurdy Way",
    "iso:country":"US",
    "sg:address":"2500 McCurdy Way",
    "sg:city":"Decatur",
    "sg:classifiers":[
        {
            "category":"Personal",
            "type":"Services"
        }
    ],
    "sg:phone":"+1 404 321 0508",
    "sg:postcode":"30033",
    "sg:province":"GA",
    "sg:tags":[
        "miscellaneous"
    ],
    "wof:name":"Axis Fine Art Installation Inc",
    "wof:placetype":"venue"
},
  "geometry": {"coordinates":[-84.288231,33.799192],"type":"Point"}
}