{
  "type": "Feature",
  "properties": {
    "addr:full":"301 Mary Sue Dr Warner Robins GA 31093",
    "addr:housenumber":"301",
    "addr:postcode":"31093",
    "addr:street":"Mary Sue Dr",
    "iso:country":"US",
    "sg:address":"301 Mary Sue Dr",
    "sg:city":"Warner Robins",
    "sg:classifiers":[
        {
            "category":"Retail",
            "subcategory":"Portrait Studio",
            "type":"Services"
        }
    ],
    "sg:phone":"+1 478 781 1111",
    "sg:postcode":"31093",
    "sg:province":"GA",
    "sg:tags":[
        "photo"
    ],
    "wof:name":"Michael Kinsaul Photography",
    "wof:placetype":"venue"
},
  "geometry": {"coordinates":[-83.68915699999999,32.665484],"type":"Point"}
}