{
  "type": "Feature",
  "properties": {
    "addr:full":"1534 N Decatur Rd NE Atlanta GA 30307",
    "addr:housenumber":"1534",
    "addr:postcode":"30307",
    "addr:street":"N Decatur Rd Ne",
    "iso:country":"US",
    "sg:address":"1534 N Decatur Rd NE",
    "sg:city":"Atlanta",
    "sg:classifiers":[
        {
            "category":"Health Services",
            "subcategory":"Doctor",
            "type":"Services"
        }
    ],
    "sg:phone":"+1 404 371 0077",
    "sg:postcode":"30307",
    "sg:province":"GA",
    "sg:tags":[
        "physician",
        "surgeon"
    ],
    "wof:name":"Howard Michael S MD",
    "wof:placetype":"venue"
},
  "geometry": {"coordinates":[-84.327904,33.787601],"type":"Point"}
}