{
  "type": "Feature",
  "properties": {
    "addr:full":"1013 Arbor Trce NE Atlanta GA 30319",
    "addr:housenumber":"1013",
    "addr:postcode":"30319",
    "addr:street":"Arbor Trce Ne",
    "iso:country":"US",
    "sg:address":"1013 Arbor Trce NE",
    "sg:city":"Atlanta",
    "sg:classifiers":[
        {
            "category":"Wholesale",
            "subcategory":"Durable Goods & Equipment",
            "type":"Manufacturing & Wholesale Goods"
        }
    ],
    "sg:phone":"+1 404 881 5870",
    "sg:postcode":"30319",
    "sg:province":"GA",
    "sg:tags":[
        "representative",
        "manufacturer"
    ],
    "wof:name":"W W Group Inc",
    "wof:placetype":"venue"
},
  "geometry": {"coordinates":[-84.34721999999999,33.851544],"type":"Point"}
}