{
  "type": "Feature",
  "properties": {
    "iso:country":"US",
    "sg:address":"900 11th St",
    "sg:city":"Macon",
    "sg:classifiers":[
        {
            "category":"Retail",
            "subcategory":"Auto Repair",
            "type":"Services"
        }
    ],
    "sg:phone":"+1 478 744 0036",
    "sg:postcode":"31201",
    "sg:province":"GA",
    "sg:tags":[
        "wrecker"
    ],
    "wof:name":"Ackerman",
    "wof:placetype":"venue"
},
  "geometry": {"coordinates":[-83.620853,32.819051],"type":"Point"}
}