{
  "type": "Feature",
  "properties": {
    "iso:country":"US",
    "sg:address":"198 Goddard Rd",
    "sg:city":"Athens",
    "sg:classifiers":[
        {
            "category":"Personal",
            "subcategory":"Beauty Salon",
            "type":"Services"
        }
    ],
    "sg:phone":"+1 706 369 1811",
    "sg:postcode":"30607",
    "sg:province":"GA",
    "sg:tags":[
        "shop"
    ],
    "wof:name":"P JS Styling Salon",
    "wof:placetype":"venue"
},
  "geometry": {"coordinates":[-83.420143,34.005254],"type":"Point"}
}