{
  "type": "Feature",
  "properties": {
    "addr:full":"3400 Old Milton Pkwy Alpharetta GA 30005",
    "addr:housenumber":"3400",
    "addr:postcode":"30005",
    "addr:street":"Old Milton Pkwy",
    "iso:country":"US",
    "sg:address":"3400 Old Milton Pkwy",
    "sg:city":"Alpharetta",
    "sg:classifiers":[
        {
            "category":"Health Services",
            "subcategory":"Dentist",
            "type":"Services"
        }
    ],
    "sg:phone":"+1 770 667 0669",
    "sg:postcode":"30005",
    "sg:province":"GA",
    "wof:name":"Dr Michael L Golsen",
    "wof:placetype":"venue"
},
  "geometry": {"coordinates":[-84.2677,34.068901],"type":"Point"}
}