{
  "type": "Feature",
  "properties": {
    "iso:country":"US",
    "sg:address":"1490 North Rd SW",
    "sg:city":"Snellville",
    "sg:classifiers":[
        {
            "category":"Professional",
            "type":"Services"
        }
    ],
    "sg:phone":"+1 678 344 0961",
    "sg:postcode":"30078",
    "sg:province":"GA",
    "wof:name":"Tag A Long Forklift Svcs",
    "wof:placetype":"venue"
},
  "geometry": {"coordinates":[-84.00643599999999,33.88898],"type":"Point"}
}