{
  "type": "Feature",
  "properties": {
    "iso:country":"US",
    "sg:address":"2857 N Druid Hills Rd NE",
    "sg:city":"Atlanta",
    "sg:classifiers":[
        {
            "category":"Professional",
            "subcategory":"Lawyer & Legal Services",
            "type":"Services"
        }
    ],
    "sg:phone":"+1 404 321 5396",
    "sg:postcode":"30329",
    "sg:province":"GA",
    "sg:tags":[
        "personal",
        "injury"
    ],
    "wof:name":"Lerner Stephen M Atty",
    "wof:placetype":"venue"
},
  "geometry": {"coordinates":[-84.31089799999999,33.816299],"type":"Point"}
}