{
  "type": "Feature",
  "properties": {
    "addr:full":"4565 Lawrenceville Hwy NW Lilburn GA 30047",
    "addr:housenumber":"4565",
    "addr:postcode":"30047",
    "addr:street":"Lawrenceville Hwy Nw",
    "iso:country":"US",
    "sg:address":"4565 Lawrenceville Hwy NW",
    "sg:city":"Lilburn",
    "sg:classifiers":[
        {
            "category":"Home & Garden",
            "subcategory":"Furniture",
            "type":"Retail Goods"
        },
        {
            "category":"Home & Garden",
            "subcategory":"Carpets & Floor Coverings",
            "type":"Retail Goods"
        }
    ],
    "sg:phone":"+1 770 925 0100",
    "sg:postcode":"30047",
    "sg:province":"GA",
    "sg:tags":[
        "store",
        "mattress"
    ],
    "sg:website":"www.heritagefurniture.com",
    "wof:name":"Heritage Furniture",
    "wof:placetype":"venue"
},
  "geometry": {"coordinates":[-84.134201,33.899399],"type":"Point"}
}