{
  "type": "Feature",
  "properties": {
    "addr:full":"3610 Wheeler Rd Augusta GA 30909",
    "addr:housenumber":"3610",
    "addr:postcode":"30909",
    "addr:street":"Wheeler Rd",
    "iso:country":"US",
    "sg:address":"3610 Wheeler Rd",
    "sg:city":"Augusta",
    "sg:classifiers":[
        {
            "category":"Health Services",
            "subcategory":"Doctor",
            "type":"Services"
        }
    ],
    "sg:phone":"+1 706 210 9500",
    "sg:postcode":"30909",
    "sg:province":"GA",
    "sg:tags":[
        "medical"
    ],
    "wof:name":"University Open MRI",
    "wof:placetype":"venue"
},
  "geometry": {"coordinates":[-82.094408,33.482687],"type":"Point"}
}