{
  "type": "Feature",
  "properties": {
    "addr:full":"844 Hickman Rd Augusta GA 30904",
    "addr:housenumber":"844",
    "addr:postcode":"30904",
    "addr:street":"Hickman Rd",
    "iso:country":"US",
    "sg:address":"844 Hickman Rd",
    "sg:city":"Augusta",
    "sg:classifiers":[
        {
            "category":"Professional",
            "subcategory":"Business Services",
            "type":"Services"
        }
    ],
    "sg:phone":"+1 706 733 4371",
    "sg:postcode":"30904",
    "sg:province":"GA",
    "wof:name":"Inner Dimension Group",
    "wof:placetype":"venue"
},
  "geometry": {"coordinates":[-82.009248,33.47566],"type":"Point"}
}