{
  "type": "Feature",
  "properties": {
    "iso:country":"US",
    "sg:address":"120 Cecil Ct",
    "sg:city":"Fayetteville",
    "sg:classifiers":[
        {
            "category":"Wholesale",
            "subcategory":"Electrical",
            "type":"Manufacturing & Wholesale Goods"
        }
    ],
    "sg:phone":"+1 770 716 5400",
    "sg:postcode":"30214",
    "sg:province":"GA",
    "sg:tags":[
        "equipment",
        "electric",
        "supply"
    ],
    "wof:name":"G C Electrical Solutions",
    "wof:placetype":"venue"
},
  "geometry": {"coordinates":[-84.43501500000001,33.501307],"type":"Point"}
}