{
  "type": "Feature",
  "properties": {
    "iso:country":"US",
    "sg:address":"101 Service Rd",
    "sg:city":"Austell",
    "sg:classifiers":[
        {
            "category":"Restaurant",
            "type":"Food & Drink"
        }
    ],
    "sg:phone":"+1 770 941 9893",
    "sg:postcode":"30107",
    "sg:province":"GA",
    "wof:name":"Waffle House",
    "wof:placetype":"venue"
},
  "geometry": {"coordinates":[-84.39255799999999,34.363882],"type":"Point"}
}