{
  "type": "Feature",
  "properties": {
    "addr:full":"810 Nicholson St Richland GA 31825",
    "addr:housenumber":"810",
    "addr:postcode":"31825",
    "addr:street":"Nicholson St",
    "iso:country":"US",
    "sg:address":"810 Nicholson St",
    "sg:city":"Richland",
    "sg:classifiers":[
        {
            "category":"Restaurant",
            "type":"Food & Drink"
        }
    ],
    "sg:menulink":"http://www.allmenus.com/ga/richland/67799-foxs-pizza-den/menu/",
    "sg:phone":"+1 229 887 0207",
    "sg:postcode":"31825",
    "sg:province":"GA",
    "sg:tags":[
        "american",
        "pizza"
    ],
    "wof:name":"Fox's Pizza Den",
    "wof:placetype":"venue"
},
  "geometry": {"coordinates":[-84.654878,32.088183],"type":"Point"}
}