{
  "type": "Feature",
  "properties": {
    "addr:full":"2109 E 16th Ave Cordele GA 31015",
    "addr:housenumber":"2109",
    "addr:postcode":"31015",
    "addr:street":"E 16Th Ave",
    "iso:country":"US",
    "sg:address":"2109 E 16th Ave",
    "sg:city":"Cordele",
    "sg:classifiers":[
        {
            "category":"Travel",
            "subcategory":"Hotels & Motels",
            "type":"Entertainment"
        }
    ],
    "sg:phone":"+1 229 273 7366",
    "sg:postcode":"31015",
    "sg:province":"GA",
    "sg:tags":[
        "lodging"
    ],
    "sg:website":"http://www.daysinn.com",
    "wof:name":"Days Inn",
    "wof:placetype":"venue"
},
  "geometry": {"coordinates":[-83.74683400000001,31.959093],"type":"Point"}
}