{
  "type": "Feature",
  "properties": {
    "addr:full":"1498 US Hwy 78 Temple GA 30179",
    "addr:housenumber":"1498",
    "addr:postcode":"30179",
    "addr:street":"Us Hwy 78",
    "iso:country":"US",
    "sg:address":"1498 US Hwy 78",
    "sg:city":"Temple",
    "sg:classifiers":[
        {
            "category":"Retail",
            "subcategory":"Auto Repair",
            "type":"Services"
        }
    ],
    "sg:phone":"+1 770 459 9977",
    "sg:postcode":"30179",
    "sg:province":"GA",
    "sg:tags":[
        "general"
    ],
    "wof:name":"Riverside Automotive",
    "wof:placetype":"venue"
},
  "geometry": {"coordinates":[-84.98151799999999,33.737592],"type":"Point"}
}