{
  "type": "Feature",
  "properties": {
    "iso:country":"US",
    "sg:address":"527 Liberty St",
    "sg:city":"Waynesboro",
    "sg:classifiers":[
        {
            "category":"Shopping",
            "subcategory":"Used Merchandise",
            "type":"Retail Goods"
        }
    ],
    "sg:phone":"+1 706 554 9854",
    "sg:postcode":"30830",
    "sg:province":"GA",
    "sg:tags":[
        "antique"
    ],
    "wof:name":"William's Antiques",
    "wof:placetype":"venue"
},
  "geometry": {"coordinates":[-82.013926,33.086871],"type":"Point"}
}