{
  "type": "Feature",
  "properties": {
    "addr:full":"13 E River St Savannah GA 31401",
    "addr:housenumber":"13",
    "addr:postcode":"31401",
    "addr:street":"E River St",
    "iso:country":"US",
    "sg:address":"13 E River St",
    "sg:city":"Savannah",
    "sg:classifiers":[
        {
            "category":"Food & Beverages",
            "subcategory":"Candy",
            "type":"Retail Goods"
        }
    ],
    "sg:phone":"+1 912 234 4608",
    "sg:postcode":"31401",
    "sg:province":"GA",
    "sg:tags":[
        "confectionery"
    ],
    "sg:website":"www.riverstreetsweets.com",
    "wof:name":"River Street Sweets",
    "wof:placetype":"venue"
},
  "geometry": {"coordinates":[-81.09083800000001,32.081539],"type":"Point"}
}