{
  "type": "Feature",
  "properties": {
    "addr:full":"171 Williams Rd Thomaston GA 30286",
    "addr:housenumber":"171",
    "addr:postcode":"30286",
    "addr:street":"Williams Rd",
    "iso:country":"US",
    "sg:address":"171 Williams Rd",
    "sg:city":"Thomaston",
    "sg:classifiers":[
        {
            "category":"Restaurant",
            "type":"Food & Drink"
        }
    ],
    "sg:phone":"+1 706 648 2625",
    "sg:postcode":"30286",
    "sg:province":"GA",
    "sg:tags":[
        "eating"
    ],
    "wof:name":"Terry Helms Catering",
    "wof:placetype":"venue"
},
  "geometry": {"coordinates":[-84.43604499999999,32.873884],"type":"Point"}
}