{
  "type": "Feature",
  "properties": {
    "iso:country":"US",
    "sg:address":"3901 Roswell Rd",
    "sg:city":"Marietta",
    "sg:classifiers":[
        {
            "category":"Wholesale",
            "subcategory":"Durable Goods & Equipment",
            "type":"Manufacturing & Wholesale Goods"
        }
    ],
    "sg:phone":"+1 678 560 3777",
    "sg:postcode":"30062",
    "sg:province":"GA",
    "sg:tags":[
        "exporter"
    ],
    "wof:name":"Software Paradigms Intl",
    "wof:placetype":"venue"
},
  "geometry": {"coordinates":[-84.437867,33.978017],"type":"Point"}
}