{
  "type": "Feature",
  "properties": {
    "iso:country":"US",
    "sg:address":"893 Jackson Rd",
    "sg:city":"Fitzgerald",
    "sg:classifiers":[
        {
            "category":"Freight",
            "type":"Transportation"
        }
    ],
    "sg:phone":"+1 229 831 5712",
    "sg:postcode":"31750",
    "sg:province":"GA",
    "sg:tags":[
        "hauling",
        "trucking"
    ],
    "wof:name":"William's Way Trucking",
    "wof:placetype":"venue"
},
  "geometry": {"coordinates":[-83.337249,31.681818],"type":"Point"}
}