{
  "type": "Feature",
  "properties": {
    "addr:full":"400 Jamie Dr Hiram GA 30141",
    "addr:housenumber":"400",
    "addr:postcode":"30141",
    "addr:street":"Jamie Dr",
    "iso:country":"US",
    "sg:address":"400 Jamie Dr",
    "sg:city":"Hiram",
    "sg:classifiers":[
        {
            "category":"Shopping",
            "subcategory":"Party Supplies",
            "type":"Retail Goods"
        }
    ],
    "sg:phone":"+1 770 489 3506",
    "sg:postcode":"30141",
    "sg:province":"GA",
    "sg:tags":[
        "wedding"
    ],
    "wof:name":"Budget Video Productions",
    "wof:placetype":"venue"
},
  "geometry": {"coordinates":[-84.809479,33.81408],"type":"Point"}
}