{
  "type": "Feature",
  "properties": {
    "iso:country":"US",
    "sg:address":"820 E de Renne Ave",
    "sg:city":"Savannah",
    "sg:classifiers":[
        {
            "category":"Personal",
            "subcategory":"Barber",
            "type":"Services"
        }
    ],
    "sg:phone":"+1 912 355 7177",
    "sg:postcode":"31405",
    "sg:province":"GA",
    "sg:tags":[
        "shop"
    ],
    "wof:name":"Repetes Barbr Sp Old New Cuts",
    "wof:placetype":"venue"
},
  "geometry": {"coordinates":[-81.095837,32.024886],"type":"Point"}
}