{
  "type": "Feature",
  "properties": {
    "addr:full":"1502 Santa Rosa Dr Augusta GA 30906",
    "addr:housenumber":"1502",
    "addr:postcode":"30906",
    "addr:street":"Santa Rosa Dr",
    "iso:country":"US",
    "sg:address":"1502 Santa Rosa Dr",
    "sg:city":"Augusta",
    "sg:classifiers":[
        {
            "category":"Shopping",
            "type":"Retail Goods"
        }
    ],
    "sg:phone":"+1 706 793 2300",
    "sg:postcode":"30906",
    "sg:province":"GA",
    "sg:tags":[
        "merchandise"
    ],
    "wof:name":"Lucent Avaya Authorized Svc",
    "wof:placetype":"venue"
},
  "geometry": {"coordinates":[-81.978314,33.354035],"type":"Point"}
}