{
  "type": "Feature",
  "properties": {
    "addr:full":"5037 Bethpage Dr Suwanee GA 30024",
    "addr:postcode":"5037;30024",
    "addr:street":"Bethpage Dr",
    "iso:country":"US",
    "sg:address":"5037 Bethpage Dr",
    "sg:city":"Suwanee",
    "sg:classifiers":[
        {
            "category":"Restaurant",
            "type":"Food & Drink"
        }
    ],
    "sg:phone":"+1 770 310 2691",
    "sg:postcode":"30024",
    "sg:province":"GA",
    "wof:name":"East Gwinnett Restaurant Inc",
    "wof:placetype":"venue"
},
  "geometry": {"coordinates":[-84.069486,34.092158],"type":"Point"}
}