{
  "type": "Feature",
  "properties": {
    "addr:full":"5030 Kingswood Dr Roswell GA 30075",
    "addr:housenumber":"5030",
    "addr:postcode":"30075",
    "addr:street":"Kingswood Dr",
    "iso:country":"US",
    "sg:address":"5030 Kingswood Dr",
    "sg:city":"Roswell",
    "sg:classifiers":[
        {
            "category":"Manufacturing",
            "subcategory":"Glass & Minerals",
            "type":"Manufacturing & Wholesale Goods"
        }
    ],
    "sg:phone":"+1 770 587 3195",
    "sg:postcode":"30075",
    "sg:province":"GA",
    "sg:tags":[
        "concrete",
        "additive",
        "mfg"
    ],
    "wof:name":"Construction Concrete Supply",
    "wof:placetype":"venue"
},
  "geometry": {"coordinates":[-84.40227299999999,34.021072],"type":"Point"}
}