{
  "type": "Feature",
  "properties": {
    "iso:country":"US",
    "sg:address":"1800 Montreal Ct",
    "sg:city":"Tucker",
    "sg:classifiers":[
        {
            "category":"Wholesale",
            "subcategory":"Construction Materials",
            "type":"Manufacturing & Wholesale Goods"
        }
    ],
    "sg:phone":"+1 770 934 6800",
    "sg:postcode":"30084",
    "sg:province":"GA",
    "sg:tags":[
        "lumber"
    ],
    "sg:website":"www.bc.com",
    "wof:name":"Boise Cascade Corp",
    "wof:placetype":"venue"
},
  "geometry": {"coordinates":[-84.25071,33.834558],"type":"Point"}
}