{
  "type": "Feature",
  "properties": {
    "iso:country":"US",
    "sg:address":"3035 Scenic Hwy S",
    "sg:city":"Snellville",
    "sg:phone":"+1 770 982 0655",
    "sg:postcode":"30039",
    "sg:province":"GA",
    "sg:website":"http://www.scottsfoods.com",
    "wof:name":"Kroger-Snellville",
    "wof:placetype":"venue"
},
  "geometry": {"coordinates":[-84.031918,33.824891],"type":"Point"}
}