{
  "type": "Feature",
  "properties": {
    "iso:country":"US",
    "sg:address":"AUBURN AVE",
    "sg:city":"Atlanta",
    "sg:classifiers":[
        {
            "category":"Shopping",
            "subcategory":"Department Store",
            "type":"Retail Goods"
        },
        {
            "category":"Shopping",
            "subcategory":"Hobbies, Toys, & Games",
            "type":"Retail Goods"
        },
        {
            "category":"Home & Garden",
            "subcategory":"Hardware",
            "type":"Retail Goods"
        },
        {
            "category":"Professional",
            "type":"Services"
        }
    ],
    "sg:phone":"+1 888 968 6222",
    "sg:postcode":"30312",
    "sg:province":"GA",
    "sg:tags":[
        "cleaner",
        "supply",
        "personal",
        "valet",
        "equipment",
        "janitor"
    ],
    "sg:website":"http://www.abcdrycleaners.com",
    "wof:name":"ABC Dry Cleaners Dot Com",
    "wof:placetype":"venue"
},
  "geometry": {"coordinates":[-84.388847,33.738396],"type":"Point"}
}