{
  "type": "Feature",
  "properties": {
    "addr:full":"1297 Broad St Augusta GA 30901",
    "addr:housenumber":"1297",
    "addr:postcode":"30901",
    "addr:street":"Broad St",
    "iso:country":"US",
    "sg:address":"1297 Broad St",
    "sg:city":"Augusta",
    "sg:classifiers":[
        {
            "category":"Wholesale",
            "subcategory":"Home Furnishings",
            "type":"Manufacturing & Wholesale Goods"
        }
    ],
    "sg:phone":"+1 706 828 0118",
    "sg:postcode":"30901",
    "sg:province":"GA",
    "wof:name":"Bargain Mart Sales & Rentals",
    "wof:placetype":"venue"
},
  "geometry": {"coordinates":[-81.97274,33.477929],"type":"Point"}
}