{
  "type": "Feature",
  "properties": {
    "addr:full":"2794 Heath Ln Duluth GA 30096",
    "addr:housenumber":"2794",
    "addr:postcode":"30096",
    "addr:street":"Heath Ln",
    "iso:country":"US",
    "sg:address":"2794 Heath Ln",
    "sg:city":"Duluth",
    "sg:classifiers":[
        {
            "category":"Bars & Pubs",
            "type":"Food & Drink"
        }
    ],
    "sg:phone":"+1 770 476 5083",
    "sg:postcode":"30096",
    "sg:province":"GA",
    "sg:tags":[
        "drinking"
    ],
    "wof:name":"Duluth Dugout Club Inc",
    "wof:placetype":"venue"
},
  "geometry": {"coordinates":[-84.128022,33.998055],"type":"Point"}
}