{
  "type": "Feature",
  "properties": {
    "iso:country":"US",
    "sg:address":"3401 Border Dr SW",
    "sg:city":"Stone Mountain",
    "sg:classifiers":[
        {
            "category":"Professional",
            "subcategory":"Accounting & Tax Preparation",
            "type":"Services"
        }
    ],
    "sg:phone":"+1 770 465 4316",
    "sg:postcode":"30087",
    "sg:province":"GA",
    "sg:tags":[
        "billing"
    ],
    "wof:name":"Swiftstrke Billng Ctr",
    "wof:placetype":"venue"
},
  "geometry": {"coordinates":[-84.08411599999999,33.787594],"type":"Point"}
}