{
  "type": "Feature",
  "properties": {
    "iso:country":"US",
    "sg:address":"2049 Stanton Rd",
    "sg:city":"East Point",
    "sg:classifiers":[
        {
            "category":"Professional",
            "subcategory":"Computer Services",
            "type":"Services"
        }
    ],
    "sg:phone":"+1 404 684 0504",
    "sg:postcode":"30344",
    "sg:province":"GA",
    "sg:tags":[
        "repair"
    ],
    "wof:name":"Computers On Deck",
    "wof:placetype":"venue"
},
  "geometry": {"coordinates":[-84.44847,33.698963],"type":"Point"}
}