{
  "type": "Feature",
  "properties": {
    "addr:full":"1460 Moreland Ave SE Atlanta GA 30316",
    "addr:housenumber":"1460",
    "addr:postcode":"30316",
    "addr:street":"Moreland Ave Se",
    "iso:country":"US",
    "sg:address":"1460 Moreland Ave SE",
    "sg:city":"Atlanta",
    "sg:classifiers":[
        {
            "category":"Freight",
            "type":"Transportation"
        }
    ],
    "sg:phone":"+1 404 622 3468",
    "sg:postcode":"30316",
    "sg:province":"GA",
    "sg:tags":[
        "trucking"
    ],
    "wof:name":"Bill's Hauling & Demo",
    "wof:placetype":"venue"
},
  "geometry": {"coordinates":[-84.349585,33.711061],"type":"Point"}
}