{
  "type": "Feature",
  "properties": {
    "addr:full":"613 Old Creek Rd Bethlehem GA 30607",
    "addr:housenumber":"613",
    "addr:postcode":"30607",
    "addr:street":"Old Creek Rd",
    "iso:country":"US",
    "sg:address":"613 Old Creek Rd",
    "sg:city":"Bethlehem",
    "sg:classifiers":[
        {
            "category":"Shopping",
            "subcategory":"Clothing, Apparel, & Fashions",
            "type":"Retail Goods"
        }
    ],
    "sg:phone":"+1 770 867 4436",
    "sg:postcode":"30607",
    "sg:province":"GA",
    "sg:tags":[
        "family"
    ],
    "wof:name":"Signals",
    "wof:placetype":"venue"
},
  "geometry": {"coordinates":[-83.378122,33.996676],"type":"Point"}
}