{
  "type": "Feature",
  "properties": {
    "addr:full":"155 Marquis Dr Fayetteville GA 30214",
    "addr:housenumber":"155",
    "addr:postcode":"30214",
    "addr:street":"Marquis Dr",
    "iso:country":"US",
    "sg:address":"155 Marquis Dr",
    "sg:city":"Fayetteville",
    "sg:classifiers":[
        {
            "category":"Insurance",
            "subcategory":"Hazard Insurance",
            "type":"Services"
        }
    ],
    "sg:phone":"+1 770 371 8247",
    "sg:postcode":"30214",
    "sg:province":"GA",
    "sg:tags":[
        "commercial",
        "business"
    ],
    "wof:name":"Tcis",
    "wof:placetype":"venue"
},
  "geometry": {"coordinates":[-84.481753,33.45069],"type":"Point"}
}