{
  "type": "Feature",
  "properties": {
    "iso:country":"US",
    "sg:address":"725 Caribbean Dr",
    "sg:city":"Forest Park",
    "sg:classifiers":[
        {
            "category":"Retail",
            "subcategory":"Repair Shop",
            "type":"Services"
        }
    ],
    "sg:phone":"+1 404 361 7485",
    "sg:postcode":"30297",
    "sg:province":"GA",
    "wof:name":"Southside Repair & Maintenance",
    "wof:placetype":"venue"
},
  "geometry": {"coordinates":[-84.36707800000001,33.58619],"type":"Point"}
}