{
  "type": "Feature",
  "properties": {
    "iso:country":"US",
    "sg:address":"6238 Benbrooke Dr NW",
    "sg:city":"Acworth",
    "sg:classifiers":[
        {
            "category":"Professional",
            "subcategory":"Business Services",
            "type":"Services"
        }
    ],
    "sg:phone":"+1 678 354 4093",
    "sg:postcode":"30101",
    "sg:province":"GA",
    "wof:name":"Raised Impressions",
    "wof:placetype":"venue"
},
  "geometry": {"coordinates":[-84.733598,33.986291],"type":"Point"}
}