{
  "type": "Feature",
  "properties": {
    "addr:full":"1057 Boulevard Dr SE Atlanta GA 30312",
    "addr:housenumber":"1057",
    "addr:postcode":"30312",
    "addr:street":"Boulevard Dr Se",
    "iso:country":"US",
    "sg:address":"1057 Boulevard Dr SE",
    "sg:city":"Atlanta",
    "sg:classifiers":[
        {
            "category":"Wholesale",
            "subcategory":"Auto Parts",
            "type":"Manufacturing & Wholesale Goods"
        }
    ],
    "sg:phone":"+1 404 622 9363",
    "sg:postcode":"30312",
    "sg:province":"GA",
    "sg:tags":[
        "automobile",
        "used"
    ],
    "wof:name":"Boles Parts Supply Inc",
    "wof:placetype":"venue"
},
  "geometry": {"coordinates":[-84.368516,33.724891],"type":"Point"}
}