{
  "type": "Feature",
  "properties": {
    "addr:full":"1021 N Westover Blvd Albany GA 31707",
    "addr:housenumber":"1021",
    "addr:postcode":"31707",
    "addr:street":"N Westover Blvd",
    "iso:country":"US",
    "sg:address":"1021 N Westover Blvd",
    "sg:city":"Albany",
    "sg:classifiers":[
        {
            "category":"Personal",
            "subcategory":"Beauty Salon",
            "type":"Services"
        }
    ],
    "sg:phone":"+1 229 888 6560",
    "sg:postcode":"31707",
    "sg:province":"GA",
    "sg:tags":[
        "shop"
    ],
    "wof:name":"Angel Nails",
    "wof:placetype":"venue"
},
  "geometry": {"coordinates":[-84.21738499999999,31.620786],"type":"Point"}
}