{
  "type": "Feature",
  "properties": {
    "iso:country":"US",
    "sg:address":"3815 Mundy Mill Rd",
    "sg:city":"Oakwood",
    "sg:classifiers":[
        {
            "category":"Restaurant",
            "type":"Food & Drink"
        }
    ],
    "sg:menulink":"http://www.allmenus.com/ga/oakwood/70891-pizza-hut/menu/",
    "sg:phone":"+1 770 536 3681",
    "sg:postcode":"30566",
    "sg:province":"GA",
    "sg:tags":[
        "american",
        "pizza"
    ],
    "wof:name":"Pizza Hut",
    "wof:placetype":"venue"
},
  "geometry": {"coordinates":[-83.870346,34.2316],"type":"Point"}
}