{
  "type": "Feature",
  "properties": {
    "addr:full":"316 Grayson Hwy Lawrenceville GA 30045",
    "addr:housenumber":"316",
    "addr:postcode":"30045",
    "addr:street":"Grayson Hwy",
    "iso:country":"US",
    "sg:address":"316 Grayson Hwy",
    "sg:city":"Lawrenceville",
    "sg:classifiers":[
        {
            "category":"Insurance",
            "subcategory":"Insurance Agent",
            "type":"Services"
        }
    ],
    "sg:phone":"+1 770 995 5335",
    "sg:postcode":"30045",
    "sg:province":"GA",
    "wof:name":"Esquire Insurance",
    "wof:placetype":"venue"
},
  "geometry": {"coordinates":[-83.98470399999999,33.94526],"type":"Point"}
}