{
  "type": "Feature",
  "properties": {
    "addr:full":"2100 Hamilton Rd Columbus GA 31904",
    "addr:housenumber":"2100",
    "addr:postcode":"31904",
    "addr:street":"Hamilton Rd",
    "iso:country":"US",
    "sg:address":"2100 Hamilton Rd",
    "sg:city":"Columbus",
    "sg:classifiers":[
        {
            "category":"Organizations",
            "subcategory":"Religious Organization",
            "type":"Services"
        }
    ],
    "sg:phone":"+1 706 322 8514",
    "sg:postcode":"31904",
    "sg:province":"GA",
    "sg:tags":[
        "church"
    ],
    "wof:name":"Rose Hill Baptist Church Inc",
    "wof:placetype":"venue"
},
  "geometry": {"coordinates":[-84.98401,32.484749],"type":"Point"}
}