{
  "type": "Feature",
  "properties": {
    "addr:full":"210 W Hall St Savannah GA 31401",
    "addr:housenumber":"210",
    "addr:postcode":"31401",
    "addr:street":"W Hall St",
    "iso:country":"US",
    "sg:address":"210 W Hall St",
    "sg:city":"Savannah",
    "sg:classifiers":[
        {
            "category":"Professional",
            "subcategory":"Business Services",
            "type":"Services"
        }
    ],
    "sg:phone":"+1 912 238 0223",
    "sg:postcode":"31401",
    "sg:province":"GA",
    "wof:name":"Scott Design",
    "wof:placetype":"venue"
},
  "geometry": {"coordinates":[-81.09859400000001,32.068954],"type":"Point"}
}