{
  "type": "Feature",
  "properties": {
    "iso:country":"US",
    "sg:address":"912 2nd Ave",
    "sg:city":"Columbus",
    "sg:classifiers":[
        {
            "category":"Professional",
            "subcategory":"Lawyer & Legal Services",
            "type":"Services"
        }
    ],
    "sg:phone":"+1 706 571 8701",
    "sg:postcode":"31901",
    "sg:province":"GA",
    "sg:tags":[
        "attorney"
    ],
    "wof:name":"Richard F Dodelin",
    "wof:placetype":"venue"
},
  "geometry": {"coordinates":[-84.990302,32.464545],"type":"Point"}
}