{
  "type": "Feature",
  "properties": {
    "addr:full":"301 W Jones St Savannah GA 31401",
    "addr:housenumber":"301",
    "addr:postcode":"31401",
    "addr:street":"W Jones St",
    "iso:country":"US",
    "sg:address":"301 W Jones St",
    "sg:city":"Savannah",
    "sg:classifiers":[
        {
            "category":"Real Estate",
            "subcategory":"Real Estate Agent",
            "type":"Services"
        }
    ],
    "sg:phone":"+1 912 231 2320",
    "sg:postcode":"31401",
    "sg:province":"GA",
    "wof:name":"Inman Park Properties",
    "wof:placetype":"venue"
},
  "geometry": {"coordinates":[-81.097459,32.073459],"type":"Point"}
}