{
  "type": "Feature",
  "properties": {
    "addr:full":"361 Blanton Rd NW Atlanta GA 30342",
    "addr:housenumber":"361",
    "addr:postcode":"30342",
    "addr:street":"Blanton Rd Nw",
    "iso:country":"US",
    "sg:address":"361 Blanton Rd NW",
    "sg:city":"Atlanta",
    "sg:classifiers":[
        {
            "category":"Wholesale",
            "subcategory":"Home Furnishings",
            "type":"Manufacturing & Wholesale Goods"
        }
    ],
    "sg:phone":"+1 404 255 9266",
    "sg:postcode":"30342",
    "sg:province":"GA",
    "sg:tags":[
        "manufacturer",
        "baskets-wholesale"
    ],
    "wof:name":"Buckhead Baskets",
    "wof:placetype":"venue"
},
  "geometry": {"coordinates":[-84.399107,33.872131],"type":"Point"}
}