{
  "type": "Feature",
  "properties": {
    "addr:full":"4735 Satellite Blvd Duluth GA 30096",
    "addr:housenumber":"4735",
    "addr:postcode":"30096",
    "addr:street":"Satellite Blvd",
    "iso:country":"US",
    "sg:address":"4735 Satellite Blvd",
    "sg:city":"Duluth",
    "sg:classifiers":[
        {
            "category":"Professional",
            "subcategory":"Art Services",
            "type":"Services"
        }
    ],
    "sg:phone":"+1 770 448 0192",
    "sg:postcode":"30096",
    "sg:province":"GA",
    "sg:tags":[
        "photography",
        "commercial"
    ],
    "wof:name":"Mark Najjar Studios",
    "wof:placetype":"venue"
},
  "geometry": {"coordinates":[-84.167619,33.940177],"type":"Point"}
}