{
  "type": "Feature",
  "properties": {
    "iso:country":"US",
    "sg:address":"147 Reinhardt College Pkwy",
    "sg:city":"Canton",
    "sg:classifiers":[
        {
            "category":"Restaurant",
            "type":"Food & Drink"
        }
    ],
    "sg:phone":"+1 770 720 8037",
    "sg:postcode":"30114",
    "sg:province":"GA",
    "wof:name":"Partake",
    "wof:placetype":"venue"
},
  "geometry": {"coordinates":[-84.477598,34.249468],"type":"Point"}
}