{
  "type": "Feature",
  "properties": {
    "iso:country":"US",
    "sg:address":"2300 Pleasant Hill Rd",
    "sg:city":"Duluth",
    "sg:classifiers":[
        {
            "category":"Government",
            "subcategory":"Office",
            "type":"Public Place"
        }
    ],
    "sg:phone":"+1 770 495 7281",
    "sg:postcode":"30096",
    "sg:province":"GA",
    "sg:tags":[
        "state",
        "resource"
    ],
    "wof:name":"Child Support Enforcement",
    "wof:placetype":"venue"
},
  "geometry": {"coordinates":[-84.13582599999999,33.960792],"type":"Point"}
}