{
  "type": "Feature",
  "properties": {
    "iso:country":"US",
    "sg:address":"1620 E Church St",
    "sg:city":"Jasper",
    "sg:classifiers":[
        {
            "category":"Freight",
            "type":"Transportation"
        }
    ],
    "sg:phone":"+1 706 253 6113",
    "sg:postcode":"30143",
    "sg:province":"GA",
    "sg:tags":[
        "commercial",
        "household",
        "storage"
    ],
    "wof:name":"Mini Storage & Oaks Climate",
    "wof:placetype":"venue"
},
  "geometry": {"coordinates":[-84.40716,34.453902],"type":"Point"}
}