{
  "type": "Feature",
  "properties": {
    "iso:country":"US",
    "sg:address":"1306 Powers Ferry Rd SE",
    "sg:city":"Marietta",
    "sg:classifiers":[
        {
            "category":"Education",
            "subcategory":"School",
            "type":"Public Place"
        }
    ],
    "sg:phone":"+1 770 916 2200",
    "sg:postcode":"30067",
    "sg:province":"GA",
    "sg:tags":[
        "elementary"
    ],
    "sg:website":"www.cobbk12.org",
    "wof:name":"Brumby Elementary School",
    "wof:placetype":"venue"
},
  "geometry": {"coordinates":[-84.46729999999999,33.919701],"type":"Point"}
}