{
  "type": "Feature",
  "properties": {
    "addr:full":"1157 S Harris St Sandersville GA 31082",
    "addr:housenumber":"1157",
    "addr:postcode":"31082",
    "addr:street":"S Harris St",
    "iso:country":"US",
    "sg:address":"1157 S Harris St",
    "sg:city":"Sandersville",
    "sg:classifiers":[
        {
            "category":"Shopping",
            "subcategory":"Used Merchandise",
            "type":"Retail Goods"
        }
    ],
    "sg:phone":"+1 478 552 9008",
    "sg:postcode":"31082",
    "sg:province":"GA",
    "sg:tags":[
        "flea",
        "market"
    ],
    "wof:name":"WACO Flea Market & Yard Sale",
    "wof:placetype":"venue"
},
  "geometry": {"coordinates":[-82.809015,32.959652],"type":"Point"}
}