{
  "type": "Feature",
  "properties": {
    "addr:full":"1778 Panola Rd Ellenwood GA 30294",
    "addr:housenumber":"1778",
    "addr:postcode":"30294",
    "addr:street":"Panola Rd",
    "iso:country":"US",
    "sg:address":"1778 Panola Rd",
    "sg:city":"Ellenwood",
    "sg:classifiers":[
        {
            "category":"Shopping",
            "subcategory":"Clothing, Apparel, & Fashions",
            "type":"Retail Goods"
        }
    ],
    "sg:phone":"+1 770 322 1965",
    "sg:postcode":"30294",
    "sg:province":"GA",
    "sg:tags":[
        "woman",
        "accessory"
    ],
    "wof:name":"Wear For Less Boutique",
    "wof:placetype":"venue"
},
  "geometry": {"coordinates":[-84.233682,33.622446],"type":"Point"}
}