{
  "type": "Feature",
  "properties": {
    "addr:full":"3641 Gin Way Snellville GA 30039",
    "addr:housenumber":"3641",
    "addr:postcode":"30039",
    "addr:street":"Gin Way",
    "iso:country":"US",
    "sg:address":"3641 Gin Way",
    "sg:city":"Snellville",
    "sg:classifiers":[
        {
            "category":"Professional",
            "subcategory":"Business Services",
            "type":"Services"
        }
    ],
    "sg:phone":"+1 770 483 2788",
    "sg:postcode":"30039",
    "sg:province":"GA",
    "wof:name":"D R Stuckey & Associates Inc",
    "wof:placetype":"venue"
},
  "geometry": {"coordinates":[-84.017799,33.778399],"type":"Point"}
}