{
  "type": "Feature",
  "properties": {
    "addr:full":"990 Edgewood Avenue Atlanta GA 30307",
    "addr:housenumber":"990",
    "addr:postcode":"30307",
    "addr:street":"Edgewood Avenue",
    "iso:country":"US",
    "sg:address":"990 Edgewood Avenue",
    "sg:city":"Atlanta",
    "sg:phone":"+1 404 507 2152",
    "sg:postcode":"30307",
    "sg:province":"GA",
    "sg:website":"http://www.ayonnajohnson.com",
    "wof:name":"Ayonna Johnson Counseling, LLC",
    "wof:placetype":"venue"
},
  "geometry": {"coordinates":[-84.356455,33.756384],"type":"Point"}
}