{
  "type": "Feature",
  "properties": {
    "addr:full":"4801 Buena Vista Rd Columbus GA 31907",
    "addr:housenumber":"4801",
    "addr:postcode":"31907",
    "addr:street":"Buena Vista Rd",
    "iso:country":"US",
    "sg:address":"4801 Buena Vista Rd",
    "sg:city":"Columbus",
    "sg:classifiers":[
        {
            "category":"Restaurant",
            "type":"Food & Drink"
        }
    ],
    "sg:menulink":"http://www.allmenus.com/ga/columbus/80876-papa-johns-pizza/menu/",
    "sg:phone":"+1 706 561 7272",
    "sg:postcode":"31907",
    "sg:province":"GA",
    "sg:tags":[
        "american",
        "pizza"
    ],
    "wof:name":"Papa John's Pizza",
    "wof:placetype":"venue"
},
  "geometry": {"coordinates":[-84.91297299999999,32.467474],"type":"Point"}
}