{
  "type": "Feature",
  "properties": {
    "iso:country":"US",
    "sg:address":"595 Franklin Rd SE",
    "sg:city":"Marietta",
    "sg:phone":"+1 770 427 9292",
    "sg:postcode":"30067",
    "sg:province":"GA",
    "wof:name":"Southcare Funeral Home",
    "wof:placetype":"venue"
},
  "geometry": {"coordinates":[-84.506755,33.937674],"type":"Point"}
}