{
  "type": "Feature",
  "properties": {
    "iso:country":"US",
    "sg:address":"6594 Oakwood Dr",
    "sg:city":"Douglasville",
    "sg:classifiers":[
        {
            "category":"Retail",
            "subcategory":"Repair Shop",
            "type":"Services"
        }
    ],
    "sg:phone":"+1 770 947 9473",
    "sg:postcode":"30135",
    "sg:province":"GA",
    "wof:name":"Satellite Repair",
    "wof:placetype":"venue"
},
  "geometry": {"coordinates":[-84.747276,33.714766],"type":"Point"}
}