{
  "type": "Feature",
  "properties": {
    "iso:country":"US",
    "sg:address":"1413 Woodmont Ln NW",
    "sg:city":"Atlanta",
    "sg:classifiers":[
        {
            "category":"Wholesale",
            "subcategory":"Electrical",
            "type":"Manufacturing & Wholesale Goods"
        }
    ],
    "sg:phone":"+1 404 355 6766",
    "sg:postcode":"30318",
    "sg:province":"GA",
    "sg:tags":[
        "equipment",
        "electronic",
        "supply"
    ],
    "wof:name":"Lamda Audio Engineering",
    "wof:placetype":"venue"
},
  "geometry": {"coordinates":[-84.434575,33.803661],"type":"Point"}
}