{
  "type": "Feature",
  "properties": {
    "iso:country":"US",
    "sg:address":"385 N Cross Lane Rd",
    "sg:city":"Monroe",
    "sg:classifiers":[
        {
            "category":"Building & Trades",
            "subcategory":"Landscaping Services",
            "type":"Services"
        }
    ],
    "sg:phone":"+1 770 267 3117",
    "sg:postcode":"30656",
    "sg:province":"GA",
    "sg:tags":[
        "lawn",
        "maintenance",
        "grounds"
    ],
    "wof:name":"Eagle Greens Maintenence",
    "wof:placetype":"venue"
},
  "geometry": {"coordinates":[-83.77507,33.906374],"type":"Point"}
}