{
  "type": "Feature",
  "properties": {
    "addr:full":"5116 5th Ave Eastman GA 31023",
    "addr:housenumber":"5116",
    "addr:postcode":"31023",
    "addr:street":"5Th Ave",
    "iso:country":"US",
    "sg:address":"5116 5th Ave",
    "sg:city":"Eastman",
    "sg:classifiers":[
        {
            "category":"Banks & Credit Unions",
            "subcategory":"Bank",
            "type":"Services"
        }
    ],
    "sg:phone":"+1 478 374 4333",
    "sg:postcode":"31023",
    "sg:province":"GA",
    "sg:tags":[
        "loan"
    ],
    "wof:name":"First Franklin Financial Corp",
    "wof:placetype":"venue"
},
  "geometry": {"coordinates":[-83.176928,32.198825],"type":"Point"}
}