{
  "type": "Feature",
  "properties": {
    "iso:country":"US",
    "sg:address":"4214 Meritas Dr",
    "sg:city":"Columbus",
    "sg:classifiers":[
        {
            "category":"Retail",
            "subcategory":"Auto Repair",
            "type":"Services"
        }
    ],
    "sg:phone":"+1 706 322 5830",
    "sg:postcode":"31904",
    "sg:province":"GA",
    "sg:tags":[
        "repairing",
        "automobile"
    ],
    "wof:name":"Davo Auto Repair & Body Work",
    "wof:placetype":"venue"
},
  "geometry": {"coordinates":[-84.981859,32.504987],"type":"Point"}
}