{
  "type": "Feature",
  "properties": {
    "iso:country":"US",
    "sg:address":"6432 Ridge Ct",
    "sg:city":"Riverdale",
    "sg:classifiers":[
        {
            "category":"Professional",
            "type":"Services"
        }
    ],
    "sg:phone":"+1 770 991 0083",
    "sg:postcode":"30274",
    "sg:province":"GA",
    "wof:name":"Brown Javice",
    "wof:placetype":"venue"
},
  "geometry": {"coordinates":[-84.39734199999999,33.578874],"type":"Point"}
}