{
  "type": "Feature",
  "properties": {
    "addr:full":"240 Clay St SE Atlanta GA 30317",
    "addr:housenumber":"240",
    "addr:postcode":"30317",
    "addr:street":"Clay St Se",
    "iso:country":"US",
    "sg:address":"240 Clay St SE",
    "sg:city":"Atlanta",
    "sg:classifiers":[
        {
            "category":"Building & Trades",
            "subcategory":"Locksmith",
            "type":"Services"
        }
    ],
    "sg:phone":"+1 678 845 9870",
    "sg:postcode":"30317",
    "sg:province":"GA",
    "sg:tags":[
        "key"
    ],
    "wof:name":"A Always Available Speedy A Locksmith",
    "wof:placetype":"venue"
},
  "geometry": {"coordinates":[-84.330281,33.748096],"type":"Point"}
}