{
  "type": "Feature",
  "properties": {
    "iso:country":"US",
    "sg:address":"1417 Hall Ave",
    "sg:city":"Tifton",
    "sg:classifiers":[
        {
            "category":"Organizations",
            "subcategory":"Religious Organization",
            "type":"Services"
        }
    ],
    "sg:phone":"+1 229 391 9027",
    "sg:postcode":"31794",
    "sg:province":"GA",
    "wof:name":"Michael Taylor Rev",
    "wof:placetype":"venue"
},
  "geometry": {"coordinates":[-83.51484499999999,31.468619],"type":"Point"}
}