{
  "type": "Feature",
  "properties": {
    "iso:country":"US",
    "sg:address":"2903 Monticello Pl",
    "sg:city":"Decatur",
    "sg:classifiers":[
        {
            "category":"Health Services",
            "subcategory":"Health Practitioner",
            "type":"Services"
        }
    ],
    "sg:phone":"+1 770 713 5793",
    "sg:postcode":"30030",
    "sg:province":"GA",
    "sg:tags":[
        "therapy",
        "physical"
    ],
    "wof:name":"The Art of Reiki",
    "wof:placetype":"venue"
},
  "geometry": {"coordinates":[-84.271326,33.756009],"type":"Point"}
}