{
  "type": "Feature",
  "properties": {
    "addr:full":"103 N Jackson St Americus GA 31709",
    "addr:housenumber":"103",
    "addr:postcode":"31709",
    "addr:street":"N Jackson St",
    "iso:country":"US",
    "sg:address":"103 N Jackson St",
    "sg:city":"Americus",
    "sg:classifiers":[
        {
            "category":"Shopping",
            "subcategory":"Beauty & Cosmetics",
            "type":"Retail Goods"
        }
    ],
    "sg:phone":"+1 229 924 5967",
    "sg:postcode":"31709",
    "sg:province":"GA",
    "sg:tags":[
        "shop",
        "clothing",
        "merchandise"
    ],
    "wof:name":"Merle Norman Cosmetics",
    "wof:placetype":"venue"
},
  "geometry": {"coordinates":[-84.233795,32.072226],"type":"Point"}
}