{
  "type": "Feature",
  "properties": {
    "addr:full":"120 Brumbelow Rd Carrollton GA 30117",
    "addr:housenumber":"120",
    "addr:postcode":"30117",
    "addr:street":"Brumbelow Rd",
    "iso:country":"US",
    "sg:address":"120 Brumbelow Rd",
    "sg:city":"Carrollton",
    "sg:classifiers":[
        {
            "category":"Professional",
            "type":"Services"
        }
    ],
    "sg:phone":"+1 770 836 1305",
    "sg:postcode":"30117",
    "sg:province":"GA",
    "sg:tags":[
        "establishment"
    ],
    "wof:name":"Colorado Refugio",
    "wof:placetype":"venue"
},
  "geometry": {"coordinates":[-85.098387,33.576597],"type":"Point"}
}