{
  "type": "Feature",
  "properties": {
    "iso:country":"US",
    "sg:address":"Stokeswood Ave SE",
    "sg:city":"Atlanta",
    "sg:classifiers":[
        {
            "category":"Restaurant",
            "type":"Food & Drink"
        }
    ],
    "sg:postcode":"30316",
    "sg:province":"GA",
    "sg:tags":[
        "barbeque"
    ],
    "wof:name":"Hinds Grill and Rotisserie",
    "wof:placetype":"venue"
},
  "geometry": {"coordinates":[-84.344736,33.732186],"type":"Point"}
}