{
  "type": "Feature",
  "properties": {
    "iso:country":"US",
    "sg:address":"2470 Wrightsboro Rd",
    "sg:city":"Augusta",
    "sg:classifiers":[
        {
            "category":"Social Services",
            "subcategory":"Child Care",
            "type":"Services"
        }
    ],
    "sg:phone":"+1 706 733 1099",
    "sg:postcode":"30904",
    "sg:province":"GA",
    "sg:tags":[
        "day"
    ],
    "wof:name":"A Child's World",
    "wof:placetype":"venue"
},
  "geometry": {"coordinates":[-82.02550599999999,33.468372],"type":"Point"}
}