{
  "type": "Feature",
  "properties": {
    "addr:full":"6095 Paddock Ln Cumming GA 30040",
    "addr:housenumber":"6095",
    "addr:postcode":"30040",
    "addr:street":"Paddock Ln",
    "iso:country":"US",
    "sg:address":"6095 Paddock Ln",
    "sg:city":"Cumming",
    "sg:classifiers":[
        {
            "category":"Building & Trades",
            "subcategory":"Landscaping Services",
            "type":"Services"
        }
    ],
    "sg:phone":"+1 770 844 7611",
    "sg:postcode":"30040",
    "sg:province":"GA",
    "wof:name":"Metro Atlanta Landscape Group",
    "wof:placetype":"venue"
},
  "geometry": {"coordinates":[-84.210307,34.18456],"type":"Point"}
}