{
  "type": "Feature",
  "properties": {
    "addr:full":"1907 Burroughs St Savannah GA 31415",
    "addr:housenumber":"1907",
    "addr:postcode":"31415",
    "addr:street":"Burroughs St",
    "iso:country":"US",
    "sg:address":"1907 Burroughs St",
    "sg:city":"Savannah",
    "sg:classifiers":[
        {
            "category":"Place Of Worship",
            "subcategory":"Church",
            "type":"Public Place"
        },
        {
            "category":"Place Of Worship",
            "type":"Public Place"
        }
    ],
    "sg:phone":"+1 912 349 1926",
    "sg:postcode":"31415",
    "sg:province":"GA",
    "sg:tags":[
        "churches-interdenominational",
        "churches-various",
        "denomination"
    ],
    "wof:name":"New Vision Ministries",
    "wof:placetype":"venue"
},
  "geometry": {"coordinates":[-81.106008,32.060421],"type":"Point"}
}