{
  "type": "Feature",
  "properties": {
    "iso:country":"US",
    "sg:address":"103 W Kelly St",
    "sg:city":"Sylvester",
    "sg:classifiers":[
        {
            "category":"Retail",
            "subcategory":"Laundry & Dry Cleaning",
            "type":"Services"
        }
    ],
    "sg:phone":"+1 229 776 2505",
    "sg:postcode":"31791",
    "sg:province":"GA",
    "sg:tags":[
        "drycleaning",
        "plant",
        "cleaners"
    ],
    "wof:name":"Joe's Cleaners",
    "wof:placetype":"venue"
},
  "geometry": {"coordinates":[-83.83899,31.527634],"type":"Point"}
}