{
  "type": "Feature",
  "properties": {
    "addr:full":"3042 Oakcliff Rd Atlanta GA 30340",
    "addr:housenumber":"3042",
    "addr:postcode":"30340",
    "addr:street":"Oakcliff Rd",
    "iso:country":"US",
    "sg:address":"3042 Oakcliff Rd",
    "sg:city":"Atlanta",
    "sg:classifiers":[
        {
            "category":"Banks & Credit Unions",
            "subcategory":"Financial Services",
            "type":"Services"
        }
    ],
    "sg:phone":"+1 770 234 9414",
    "sg:postcode":"30340",
    "sg:province":"GA",
    "sg:tags":[
        "broker",
        "mortgage"
    ],
    "wof:name":"United Mortgage Funding",
    "wof:placetype":"venue"
},
  "geometry": {"coordinates":[-84.263571,33.911417],"type":"Point"}
}