{
  "type": "Feature",
  "properties": {
    "iso:country":"US",
    "sg:address":"1297 Dogwood Ln",
    "sg:city":"Tucker",
    "sg:classifiers":[
        {
            "category":"Farming",
            "subcategory":"Livestock Farm",
            "type":"Manufacturing & Wholesale Goods"
        }
    ],
    "sg:phone":"+1 770 270 1775",
    "sg:postcode":"30084",
    "sg:province":"GA",
    "sg:tags":[
        "equine"
    ],
    "wof:name":"Tag Distributors",
    "wof:placetype":"venue"
},
  "geometry": {"coordinates":[-84.21686,33.892117],"type":"Point"}
}