{
  "type": "Feature",
  "properties": {
    "addr:full":"1761 S Cedar St Mc Donough GA 30253",
    "addr:housenumber":"1761",
    "addr:postcode":"30253",
    "addr:street":"S Cedar St",
    "iso:country":"US",
    "sg:address":"1761 S Cedar St",
    "sg:city":"Mc Donough",
    "sg:classifiers":[
        {
            "category":"Personal",
            "subcategory":"Beauty Salon",
            "type":"Services"
        }
    ],
    "sg:phone":"+1 770 898 5885",
    "sg:postcode":"30253",
    "sg:province":"GA",
    "sg:tags":[
        "shop"
    ],
    "wof:name":"Perfection Hair Salon",
    "wof:placetype":"venue"
},
  "geometry": {"coordinates":[-84.14388099999999,33.426515],"type":"Point"}
}