{
  "type": "Feature",
  "properties": {
    "addr:full":"1631 Ashmar Ln Marietta GA 30064",
    "addr:housenumber":"1631",
    "addr:postcode":"30064",
    "addr:street":"Ashmar Ln",
    "iso:country":"US",
    "sg:address":"1631 Ashmar Ln",
    "sg:city":"Marietta",
    "sg:classifiers":[
        {
            "category":"Personal",
            "type":"Services"
        }
    ],
    "sg:phone":"+1 678 354 1222",
    "sg:postcode":"30064",
    "sg:province":"GA",
    "wof:name":"Bishop Training Center",
    "wof:placetype":"venue"
},
  "geometry": {"coordinates":[-84.639974,33.915452],"type":"Point"}
}