{
  "type": "Feature",
  "properties": {
    "iso:country":"US",
    "sg:address":"5 Nelson Ln",
    "sg:city":"Brunswick",
    "sg:classifiers":[
        {
            "category":"Health Services",
            "subcategory":"Doctor",
            "type":"Services"
        }
    ],
    "sg:phone":"+1 912 635 9666",
    "sg:postcode":"31527",
    "sg:province":"GA",
    "sg:tags":[
        "medical"
    ],
    "wof:name":"John E Barnett Jr MD PC",
    "wof:placetype":"venue"
},
  "geometry": {"coordinates":[-81.404239,31.076428],"type":"Point"}
}