{
  "type": "Feature",
  "properties": {
    "addr:full":"211 W Residence Ave Albany GA 31701",
    "addr:housenumber":"211",
    "addr:postcode":"31701",
    "addr:street":"W Residence Ave",
    "iso:country":"US",
    "sg:address":"211 W Residence Ave",
    "sg:city":"Albany",
    "sg:classifiers":[
        {
            "category":"Building & Trades",
            "subcategory":"Construction",
            "type":"Services"
        }
    ],
    "sg:phone":"+1 229 420 1648",
    "sg:postcode":"31701",
    "sg:province":"GA",
    "sg:tags":[
        "house"
    ],
    "wof:name":"Hedrick Construction Company",
    "wof:placetype":"venue"
},
  "geometry": {"coordinates":[-84.153502,31.583159],"type":"Point"}
}