{
  "type": "Feature",
  "properties": {
    "addr:full":"1083 Columbia Dr Decatur GA 30030",
    "addr:housenumber":"1083",
    "addr:postcode":"30030",
    "addr:street":"Columbia Dr",
    "iso:country":"US",
    "sg:address":"1083 Columbia Dr",
    "sg:city":"Decatur",
    "sg:classifiers":[
        {
            "category":"Education",
            "subcategory":"School",
            "type":"Public Place"
        }
    ],
    "sg:phone":"+1 404 292 9002",
    "sg:postcode":"30030",
    "sg:province":"GA",
    "wof:name":"Aya Educational Institute",
    "wof:placetype":"venue"
},
  "geometry": {"coordinates":[-84.269728,33.755977],"type":"Point"}
}