{
  "type": "Feature",
  "properties": {
    "addr:full":"900 State Rte 138 W Stockbridge GA 30281",
    "addr:housenumber":"900",
    "addr:postcode":"30281",
    "addr:street":"State Rte 138 W",
    "iso:country":"US",
    "sg:address":"900 State Rte 138 W",
    "sg:city":"Stockbridge",
    "sg:phone":"+1 770 506 3409",
    "sg:postcode":"30281",
    "sg:province":"GA",
    "sg:tags":[
        "oil"
    ],
    "wof:name":"First American Petroleum",
    "wof:placetype":"venue"
},
  "geometry": {"coordinates":[-84.263109,33.553794],"type":"Point"}
}