{
  "type": "Feature",
  "properties": {
    "iso:country":"US",
    "sg:address":"101 Carrick Way",
    "sg:city":"Macon",
    "sg:classifiers":[
        {
            "category":"Transit Center",
            "subcategory":"Freight",
            "type":"Transportation"
        },
        {
            "category":"Professional",
            "subcategory":"Advertising",
            "type":"Services"
        }
    ],
    "sg:phone":"+1 478 808 0310",
    "sg:postcode":"31210",
    "sg:province":"GA",
    "sg:tags":[
        "outdoor"
    ],
    "wof:name":"Outdoor Media Solutions",
    "wof:placetype":"venue"
},
  "geometry": {"coordinates":[-83.711838,32.85416],"type":"Point"}
}