{
  "type": "Feature",
  "properties": {
    "iso:country":"US",
    "sg:address":"3905 Roberts Rd",
    "sg:city":"Augusta",
    "sg:classifiers":[
        {
            "category":"Building & Trades",
            "subcategory":"Construction",
            "type":"Services"
        }
    ],
    "sg:phone":"+1 706 855 7459",
    "sg:postcode":"30907",
    "sg:province":"GA",
    "sg:tags":[
        "painter"
    ],
    "wof:name":"B C Painting Inc",
    "wof:placetype":"venue"
},
  "geometry": {"coordinates":[-82.097223,33.511441],"type":"Point"}
}