{
  "type": "Feature",
  "properties": {
    "iso:country":"US",
    "sg:address":"2509 Marietta Blvd NW",
    "sg:city":"Atlanta",
    "sg:classifiers":[
        {
            "category":"Building & Trades",
            "subcategory":"Locksmith",
            "type":"Services"
        }
    ],
    "sg:phone":"+1 404 639 9030",
    "sg:postcode":"30303",
    "sg:province":"GA",
    "sg:tags":[
        "key"
    ],
    "wof:name":"A A Dusty Locksmith",
    "wof:placetype":"venue"
},
  "geometry": {"coordinates":[-84.455569,33.821718],"type":"Point"}
}