{
  "type": "Feature",
  "properties": {
    "iso:country":"US",
    "sg:address":"2540 Atlanta Rd SE",
    "sg:city":"Smyrna",
    "sg:classifiers":[
        {
            "category":"Restaurant",
            "type":"Food & Drink"
        }
    ],
    "sg:phone":"+1 770 432 0051",
    "sg:postcode":"30080",
    "sg:province":"GA",
    "sg:tags":[
        "eating"
    ],
    "wof:name":"Tropicanna Billiards & Grill",
    "wof:placetype":"venue"
},
  "geometry": {"coordinates":[-84.51701199999999,33.890159],"type":"Point"}
}