{
  "type": "Feature",
  "properties": {
    "iso:country":"US",
    "sg:address":"5 Dean Dr NE",
    "sg:city":"Cartersville",
    "sg:classifiers":[
        {
            "category":"Manufacturing",
            "subcategory":"Pet Food",
            "type":"Manufacturing & Wholesale Goods"
        }
    ],
    "sg:phone":"+1 770 607 3000",
    "sg:postcode":"30121",
    "sg:province":"GA",
    "sg:tags":[
        "mill",
        "mfg"
    ],
    "wof:name":"Schwans Home Service Inc",
    "wof:placetype":"venue"
},
  "geometry": {"coordinates":[-84.793054,34.216944],"type":"Point"}
}