{
  "type": "Feature",
  "properties": {
    "addr:full":"1229 Johnson Ferry Rd Marietta GA 30068",
    "addr:housenumber":"1229",
    "addr:postcode":"30068",
    "addr:street":"Johnson Ferry Rd",
    "iso:country":"US",
    "sg:address":"1229 Johnson Ferry Rd",
    "sg:city":"Marietta",
    "sg:classifiers":[
        {
            "category":"Professional",
            "subcategory":"Testing Lab",
            "type":"Services"
        }
    ],
    "sg:phone":"+1 770 565 2323",
    "sg:postcode":"30068",
    "sg:province":"GA",
    "sg:tags":[
        "laboratory"
    ],
    "wof:name":"Psychemedics Corporation",
    "wof:placetype":"venue"
},
  "geometry": {"coordinates":[-84.41761700000001,33.978207],"type":"Point"}
}