{
  "type": "Feature",
  "properties": {
    "iso:country":"US",
    "sg:address":"80 Bass Rd",
    "sg:city":"Richmond Hill",
    "sg:classifiers":[
        {
            "category":"Manufacturing",
            "subcategory":"Building Materials",
            "type":"Manufacturing & Wholesale Goods"
        }
    ],
    "sg:phone":"+1 912 756 8245",
    "sg:postcode":"31301",
    "sg:province":"GA",
    "wof:name":"Coastal Atlantic Millworks",
    "wof:placetype":"venue"
},
  "geometry": {"coordinates":[-81.613362,31.766214],"type":"Point"}
}