{
  "type": "Feature",
  "properties": {
    "addr:full":"14 Sloan St Roswell GA 30075",
    "addr:housenumber":"14",
    "addr:postcode":"30075",
    "addr:street":"Sloan St",
    "iso:country":"US",
    "sg:address":"14 Sloan St",
    "sg:city":"Roswell",
    "sg:classifiers":[
        {
            "category":"Personal",
            "subcategory":"Beauty Salon",
            "type":"Services"
        }
    ],
    "sg:phone":"+1 770 645 9300",
    "sg:postcode":"30075",
    "sg:province":"GA",
    "wof:name":"Purple Sage Salon",
    "wof:placetype":"venue"
},
  "geometry": {"coordinates":[-84.36142100000001,34.01548],"type":"Point"}
}