{
  "type": "Feature",
  "properties": {
    "iso:country":"US",
    "sg:address":"11459 Johns Creek Pkwy",
    "sg:city":"Duluth",
    "sg:classifiers":[
        {
            "category":"Health Services",
            "subcategory":"Doctor",
            "type":"Services"
        }
    ],
    "sg:phone":"+1 770 497 1555",
    "sg:postcode":"30097",
    "sg:province":"GA",
    "sg:tags":[
        "practice",
        "family"
    ],
    "sg:website":"www.allurainfo.com",
    "wof:name":"Ellis Paul D MD",
    "wof:placetype":"venue"
},
  "geometry": {"coordinates":[-84.172354,34.055931],"type":"Point"}
}