{
  "type": "Feature",
  "properties": {
    "addr:full":"171 Burketts Ferry Rd Hazlehurst GA 31539",
    "addr:housenumber":"171",
    "addr:postcode":"31539",
    "addr:street":"Burketts Ferry Rd",
    "iso:country":"US",
    "sg:address":"171 Burketts Ferry Rd",
    "sg:city":"Hazlehurst",
    "sg:classifiers":[
        {
            "category":"Health Services",
            "subcategory":"Chiropractor",
            "type":"Services"
        }
    ],
    "sg:phone":"+1 912 375 4893",
    "sg:postcode":"31539",
    "sg:province":"GA",
    "wof:name":"Janie W Baxter DC",
    "wof:placetype":"venue"
},
  "geometry": {"coordinates":[-82.6177,31.873044],"type":"Point"}
}