{
  "type": "Feature",
  "properties": {
    "iso:country":"US",
    "sg:address":"149 Bo Simpson Pkwy",
    "sg:city":"Mcdonough",
    "sg:classifiers":[
        {
            "category":"Building & Trades",
            "subcategory":"Landscaping Services",
            "type":"Services"
        }
    ],
    "sg:phone":"+1 770 957 0660",
    "sg:postcode":"30253",
    "sg:province":"GA",
    "sg:tags":[
        "lawn",
        "maintenance",
        "grounds"
    ],
    "wof:name":"Off Duty Lawn Svc",
    "wof:placetype":"venue"
},
  "geometry": {"coordinates":[-84.207403,33.405189],"type":"Point"}
}