{
  "type": "Feature",
  "properties": {
    "iso:country":"US",
    "sg:address":"175 Burdette Rd NW",
    "sg:city":"Atlanta",
    "sg:classifiers":[
        {
            "category":"Shopping",
            "type":"Retail Goods"
        }
    ],
    "sg:phone":"+1 404 255 1652",
    "sg:postcode":"30327",
    "sg:province":"GA",
    "sg:tags":[
        "merchandise"
    ],
    "wof:name":"Decor Master Co",
    "wof:placetype":"venue"
},
  "geometry": {"coordinates":[-84.39354899999999,33.900468],"type":"Point"}
}