{
  "type": "Feature",
  "properties": {
    "iso:country":"US",
    "sg:address":"1924 Norwich St",
    "sg:city":"Brunswick",
    "sg:classifiers":[
        {
            "category":"Sports & Exercise",
            "subcategory":"Gym",
            "type":"Entertainment"
        }
    ],
    "sg:phone":"+1 912 264 5216",
    "sg:postcode":"31520",
    "sg:province":"GA",
    "sg:tags":[
        "body",
        "auto",
        "fitness",
        "physical",
        "facility"
    ],
    "wof:name":"Work Your Body Exercise Club",
    "wof:placetype":"venue"
},
  "geometry": {"coordinates":[-81.493706,31.156495],"type":"Point"}
}