{
  "type": "Feature",
  "properties": {
    "iso:country":"US",
    "sg:address":"4419 Cowan Rd",
    "sg:city":"Tucker",
    "sg:classifiers":[
        {
            "category":"Education",
            "subcategory":"School",
            "type":"Public Place"
        }
    ],
    "sg:phone":"+1 770 270 6901",
    "sg:postcode":"30084",
    "sg:province":"GA",
    "wof:name":"Soaring Eagles Christian Acad",
    "wof:placetype":"venue"
},
  "geometry": {"coordinates":[-84.208575,33.850387],"type":"Point"}
}