{
  "type": "Feature",
  "properties": {
    "iso:country":"US",
    "sg:address":"168 Freys Gin Rd SE",
    "sg:city":"Marietta",
    "sg:classifiers":[
        {
            "category":"Wholesale",
            "subcategory":"Construction Materials",
            "type":"Manufacturing & Wholesale Goods"
        }
    ],
    "sg:phone":"+1 770 422 5371",
    "sg:postcode":"30067",
    "sg:province":"GA",
    "sg:tags":[
        "stone",
        "quarried",
        "rock"
    ],
    "wof:name":"Jimco Stone Centers",
    "wof:placetype":"venue"
},
  "geometry": {"coordinates":[-84.516543,33.947456],"type":"Point"}
}