{
  "type": "Feature",
  "properties": {
    "iso:country":"US",
    "sg:address":"2637 Gold Rust Dr",
    "sg:city":"Buford",
    "sg:classifiers":[
        {
            "category":"Building & Trades",
            "subcategory":"Construction",
            "type":"Services"
        }
    ],
    "sg:phone":"+1 770 831 9662",
    "sg:postcode":"30519",
    "sg:province":"GA",
    "sg:tags":[
        "house"
    ],
    "wof:name":"Blythe Builders Group",
    "wof:placetype":"venue"
},
  "geometry": {"coordinates":[-83.96307899999999,34.089968],"type":"Point"}
}