{
  "type": "Feature",
  "properties": {
    "addr:full":"2080 Lullwater Pl Lawrenceville GA 30043",
    "addr:housenumber":"2080",
    "addr:postcode":"30043",
    "addr:street":"Lullwater Pl",
    "iso:country":"US",
    "sg:address":"2080 Lullwater Pl",
    "sg:city":"Lawrenceville",
    "sg:classifiers":[
        {
            "category":"Professional",
            "subcategory":"Business Services",
            "type":"Services"
        }
    ],
    "sg:phone":"+1 770 822 4600",
    "sg:postcode":"30043",
    "sg:province":"GA",
    "wof:name":"Chattahoochee Home Oxygen Svc",
    "wof:placetype":"venue"
},
  "geometry": {"coordinates":[-84.06867099999999,33.987781],"type":"Point"}
}