{
  "type": "Feature",
  "properties": {
    "addr:full":"414 Ponce de Leon Ave NE Atlanta GA 30308",
    "addr:housenumber":"414",
    "addr:postcode":"30308",
    "addr:street":"Ponce De Leon Ave Ne",
    "iso:country":"US",
    "sg:address":"414 Ponce de Leon Ave NE",
    "sg:city":"Atlanta",
    "sg:classifiers":[
        {
            "category":"Personal",
            "subcategory":"Massage",
            "type":"Services"
        },
        {
            "category":"Health Services",
            "subcategory":"Health Practitioner",
            "type":"Services"
        }
    ],
    "sg:phone":"+1 404 421 5029",
    "sg:postcode":"30308",
    "sg:province":"GA",
    "sg:tags":[
        "nutritionist"
    ],
    "sg:website":"www.activelifemassage.com",
    "wof:name":"Active Life Massage",
    "wof:placetype":"venue"
},
  "geometry": {"coordinates":[-84.37373700000001,33.773304],"type":"Point"}
}