{
  "type": "Feature",
  "properties": {
    "addr:full":"965 Duluth Hwy Lawrenceville GA 30043",
    "addr:housenumber":"965",
    "addr:postcode":"30043",
    "addr:street":"Duluth Hwy",
    "iso:country":"US",
    "sg:address":"965 Duluth Hwy",
    "sg:city":"Lawrenceville",
    "sg:classifiers":[
        {
            "category":"Utilities",
            "subcategory":"Telephone",
            "type":"Services"
        },
        {
            "category":"Shopping",
            "subcategory":"Mobile Phones",
            "type":"Retail Goods"
        },
        {
            "category":"Manufacturing",
            "subcategory":"Electronics",
            "type":"Manufacturing & Wholesale Goods"
        },
        {
            "category":"Shopping",
            "subcategory":"Computers & Home Electronics",
            "type":"Retail Goods"
        },
        {
            "category":"Communications",
            "type":"Services"
        }
    ],
    "sg:phone":"+1 678 985 9756",
    "sg:postcode":"30043",
    "sg:province":"GA",
    "sg:tags":[
        "sound",
        "television",
        "theater",
        "supply",
        "system",
        "equipment",
        "radio",
        "cellular",
        "telecommunications-equipment",
        "consumer",
        "store"
    ],
    "sg:website":"http://www.radioshack.com",
    "wof:name":"RadioShack",
    "wof:placetype":"venue"
},
  "geometry": {"coordinates":[-84.027843,33.968942],"type":"Point"}
}