{
  "type": "Feature",
  "properties": {
    "iso:country":"US",
    "sg:address":"2948 Woodrow Dr",
    "sg:city":"Lithonia",
    "sg:classifiers":[
        {
            "category":"Building & Trades",
            "subcategory":"Equipment Rental",
            "type":"Services"
        }
    ],
    "sg:phone":"+1 770 484 9540",
    "sg:postcode":"30038",
    "sg:province":"GA",
    "wof:name":"Black Box Rehearsal Studios",
    "wof:placetype":"venue"
},
  "geometry": {"coordinates":[-84.117797,33.695989],"type":"Point"}
}