{
  "type": "Feature",
  "properties": {
    "iso:country":"US",
    "sg:address":"204 S Camellia Blvd",
    "sg:city":"Fort Valley",
    "sg:classifiers":[
        {
            "category":"Retail",
            "subcategory":"Laundry & Dry Cleaning",
            "type":"Services"
        }
    ],
    "sg:phone":"+1 478 825 8211",
    "sg:postcode":"31030",
    "sg:province":"GA",
    "sg:tags":[
        "drycleaning",
        "plant"
    ],
    "wof:name":"One Hour Martinizing",
    "wof:placetype":"venue"
},
  "geometry": {"coordinates":[-83.88716100000001,32.552637],"type":"Point"}
}