{
  "type": "Feature",
  "properties": {
    "iso:country":"US",
    "sg:address":"3200 Stone Mountain Hwy",
    "sg:city":"Snellville",
    "sg:classifiers":[
        {
            "category":"Home & Garden",
            "subcategory":"Carpets & Floor Coverings",
            "type":"Retail Goods"
        }
    ],
    "sg:phone":"+1 770 653 5531",
    "sg:postcode":"30078",
    "sg:province":"GA",
    "sg:tags":[
        "material"
    ],
    "wof:name":"Rugs Plus",
    "wof:placetype":"venue"
},
  "geometry": {"coordinates":[-84.044022,33.851341],"type":"Point"}
}