{
  "type": "Feature",
  "properties": {
    "iso:country":"US",
    "sg:address":"1060 Windward Ridge Pkwy",
    "sg:city":"Alpharetta",
    "sg:classifiers":[
        {
            "category":"Wholesale",
            "subcategory":"Computers",
            "type":"Manufacturing & Wholesale Goods"
        }
    ],
    "sg:phone":"+1 770 625 0000",
    "sg:postcode":"30005",
    "sg:province":"GA",
    "sg:tags":[
        "computer-wholesale",
        "manufacturer"
    ],
    "wof:name":"Computone Corp",
    "wof:placetype":"venue"
},
  "geometry": {"coordinates":[-84.207353,34.096564],"type":"Point"}
}