{
  "type": "Feature",
  "properties": {
    "addr:full":"820 N Wayne St Milledgeville GA 31061",
    "addr:housenumber":"820",
    "addr:postcode":"31061",
    "addr:street":"N Wayne St",
    "iso:country":"US",
    "sg:address":"820 N Wayne St",
    "sg:city":"Milledgeville",
    "sg:classifiers":[
        {
            "category":"Restaurant",
            "type":"Food & Drink"
        }
    ],
    "sg:phone":"+1 478 452 1016",
    "sg:postcode":"31061",
    "sg:province":"GA",
    "wof:name":"On The Move",
    "wof:placetype":"venue"
},
  "geometry": {"coordinates":[-83.230267,33.092136],"type":"Point"}
}