{
  "type": "Feature",
  "properties": {
    "iso:country":"US",
    "sg:address":"3330 Sugarloaf Pkwy",
    "sg:city":"Lawrenceville",
    "sg:classifiers":[
        {
            "category":"Cinema",
            "subcategory":"Movie Rental",
            "type":"Entertainment"
        }
    ],
    "sg:phone":"+1 770 513 3805",
    "sg:postcode":"30044",
    "sg:province":"GA",
    "sg:tags":[
        "leasing",
        "video",
        "disc",
        "tape"
    ],
    "wof:name":"Hollywood Video",
    "wof:placetype":"venue"
},
  "geometry": {"coordinates":[-84.017532,33.923724],"type":"Point"}
}