{
  "type": "Feature",
  "properties": {
    "addr:full":"2053 State Rte 136 La Fayette GA 30728",
    "addr:housenumber":"2053",
    "addr:postcode":"30728",
    "addr:street":"State Rte 136 La Fayette",
    "iso:country":"US",
    "sg:address":"2053 State Rte 136",
    "sg:city":"La Fayette",
    "sg:classifiers":[
        {
            "category":"Home & Garden",
            "subcategory":"Building Materials",
            "type":"Retail Goods"
        }
    ],
    "sg:phone":"+1 706 638 3360",
    "sg:postcode":"30728",
    "sg:province":"GA",
    "wof:name":"Turman Builder Supply",
    "wof:placetype":"venue"
},
  "geometry": {"coordinates":[-85.245392,34.696753],"type":"Point"}
}