{
  "type": "Feature",
  "properties": {
    "iso:country":"US",
    "sg:address":"3490 Piedmont Rd NE",
    "sg:city":"Atlanta",
    "sg:classifiers":[
        {
            "category":"Professional",
            "subcategory":"Management & Consulting",
            "type":"Services"
        },
        {
            "category":"Professional",
            "subcategory":"Employment Agencies",
            "type":"Services"
        }
    ],
    "sg:phone":"+1 770 640 7317",
    "sg:postcode":"30305",
    "sg:province":"GA",
    "sg:tags":[
        "consultant",
        "search",
        "executive",
        "opportunity"
    ],
    "sg:website":"http://www.aldebaranassociates.com",
    "wof:name":"Aldebaran Associates",
    "wof:placetype":"venue"
},
  "geometry": {"coordinates":[-84.375969,33.849209],"type":"Point"}
}