{
  "type": "Feature",
  "properties": {
    "addr:full":"2601 Carrington Dr Hephzibah GA 30815",
    "addr:housenumber":"2601",
    "addr:postcode":"30815",
    "addr:street":"Carrington Dr",
    "iso:country":"US",
    "sg:address":"2601 Carrington Dr",
    "sg:city":"Hephzibah",
    "sg:classifiers":[
        {
            "category":"Shopping",
            "subcategory":"Clothing, Apparel, & Fashions",
            "type":"Retail Goods"
        }
    ],
    "sg:phone":"+1 706 792 0502",
    "sg:postcode":"30815",
    "sg:province":"GA",
    "sg:tags":[
        "accessory",
        "jewelry",
        "shoes"
    ],
    "wof:name":"Youngs Fashions Inc",
    "wof:placetype":"venue"
},
  "geometry": {"coordinates":[-82.09373600000001,33.37203],"type":"Point"}
}