{
  "type": "Feature",
  "properties": {
    "iso:country":"US",
    "sg:address":"1891 McFarland Rd",
    "sg:city":"Alpharetta",
    "sg:classifiers":[
        {
            "category":"Professional",
            "type":"Services"
        }
    ],
    "sg:phone":"+1 678 393 8922",
    "sg:postcode":"30005",
    "sg:province":"GA",
    "sg:tags":[
        "establishment"
    ],
    "wof:name":"Auto Source",
    "wof:placetype":"venue"
},
  "geometry": {"coordinates":[-84.21641700000001,34.103952],"type":"Point"}
}