{
  "type": "Feature",
  "properties": {
    "iso:country":"US",
    "sg:address":"1575 Sheridan Rd NE",
    "sg:city":"Atlanta",
    "sg:classifiers":[
        {
            "category":"Communications",
            "subcategory":"Film & Video Production",
            "type":"Services"
        }
    ],
    "sg:phone":"+1 404 325 5885",
    "sg:postcode":"30324",
    "sg:province":"GA",
    "sg:tags":[
        "motion",
        "picture",
        "technician"
    ],
    "wof:name":"D P Editorial",
    "wof:placetype":"venue"
},
  "geometry": {"coordinates":[-84.335154,33.82478],"type":"Point"}
}