{
  "type": "Feature",
  "properties": {
    "iso:country":"US",
    "sg:address":"3027 Longleaf Ct",
    "sg:city":"Augusta",
    "sg:classifiers":[
        {
            "category":"Personal",
            "subcategory":"Beauty Salon",
            "type":"Services"
        }
    ],
    "sg:phone":"+1 706 796 0319",
    "sg:postcode":"30906",
    "sg:province":"GA",
    "sg:tags":[
        "shop"
    ],
    "wof:name":"Smiths Magic Touch",
    "wof:placetype":"venue"
},
  "geometry": {"coordinates":[-82.048857,33.441533],"type":"Point"}
}