{
  "type": "Feature",
  "properties": {
    "addr:full":"1411 Carl-Bethlehem Rd Auburn GA 30680",
    "addr:housenumber":"1411",
    "addr:postcode":"30680",
    "addr:street":"Carl-Bethlehem Rd",
    "iso:country":"US",
    "sg:address":"1411 Carl-Bethlehem Rd",
    "sg:city":"Auburn",
    "sg:classifiers":[
        {
            "category":"Home & Garden",
            "subcategory":"Furniture",
            "type":"Retail Goods"
        }
    ],
    "sg:phone":"+1 770 867 7385",
    "sg:postcode":"30680",
    "sg:province":"GA",
    "sg:tags":[
        "custom",
        "cabinet"
    ],
    "wof:name":"Woods Specialties",
    "wof:placetype":"venue"
},
  "geometry": {"coordinates":[-83.80345199999999,33.994849],"type":"Point"}
}