{
  "type": "Feature",
  "properties": {
    "iso:country":"US",
    "sg:address":"912 S Morningside Dr",
    "sg:city":"Bainbridge",
    "sg:classifiers":[
        {
            "category":"Food & Beverages",
            "subcategory":"Fruits & Vegetables",
            "type":"Retail Goods"
        }
    ],
    "sg:phone":"+1 229 246 6990",
    "sg:postcode":"39819",
    "sg:province":"FL",
    "sg:tags":[
        "produce"
    ],
    "wof:name":"J Hatcher Produce Inc",
    "wof:placetype":"venue"
},
  "geometry": {"coordinates":[-84.556964,30.897423],"type":"Point"}
}