{
  "type": "Feature",
  "properties": {
    "iso:country":"US",
    "sg:address":"22 W Jefferson St Ste 2",
    "sg:city":"Hazlehurst",
    "sg:classifiers":[
        {
            "category":"Personal",
            "subcategory":"Tanning Parlor",
            "type":"Services"
        }
    ],
    "sg:phone":"+1 912 375 2429",
    "sg:postcode":"31539",
    "sg:province":"GA",
    "sg:tags":[
        "salon"
    ],
    "wof:name":"Sunny Dayz Tanning",
    "wof:placetype":"venue"
},
  "geometry": {"coordinates":[-82.60498800000001,31.86245],"type":"Point"}
}