{
  "type": "Feature",
  "properties": {
    "addr:full":"1280 Canal Rd Brunswick GA 31525",
    "addr:housenumber":"1280",
    "addr:postcode":"31525",
    "addr:street":"Canal Rd",
    "iso:country":"US",
    "sg:address":"1280 Canal Rd",
    "sg:city":"Brunswick",
    "sg:classifiers":[
        {
            "category":"Building & Trades",
            "subcategory":"Construction",
            "type":"Services"
        }
    ],
    "sg:phone":"+1 912 264 1253",
    "sg:postcode":"31525",
    "sg:province":"GA",
    "sg:tags":[
        "clearing",
        "land",
        "leveling"
    ],
    "wof:name":"Merritt & Son Construction Inc",
    "wof:placetype":"venue"
},
  "geometry": {"coordinates":[-81.488328,31.260067],"type":"Point"}
}