{
  "type": "Feature",
  "properties": {
    "iso:country":"US",
    "sg:address":"332 Osprey Pt",
    "sg:city":"Stone Mountain",
    "sg:classifiers":[
        {
            "category":"Professional",
            "subcategory":"Research",
            "type":"Services"
        }
    ],
    "sg:phone":"+1 770 879 5100",
    "sg:postcode":"30087",
    "sg:province":"GA",
    "sg:tags":[
        "market",
        "analysis"
    ],
    "sg:website":"www.headfirstinc.com",
    "wof:name":"Head First Market Research",
    "wof:placetype":"venue"
},
  "geometry": {"coordinates":[-84.08717799999999,33.785052],"type":"Point"}
}