{
  "type": "Feature",
  "properties": {
    "addr:full":"888 Pleasant Hill Rd NW Lilburn GA 30047",
    "addr:housenumber":"888",
    "addr:postcode":"30047",
    "addr:street":"Pleasant Hill Rd Nw",
    "iso:country":"US",
    "sg:address":"888 Pleasant Hill Rd NW",
    "sg:city":"Lilburn",
    "sg:classifiers":[
        {
            "category":"Education",
            "subcategory":"Special Training",
            "type":"Public Place"
        }
    ],
    "sg:phone":"+1 770 279 2616",
    "sg:postcode":"30047",
    "sg:province":"GA",
    "sg:tags":[
        "school",
        "language"
    ],
    "wof:name":"Urumex Spanish Services",
    "wof:placetype":"venue"
},
  "geometry": {"coordinates":[-84.113862,33.924563],"type":"Point"}
}