{
  "type": "Feature",
  "properties": {
    "addr:full":"9030 Walnut Cove Ct Gainesville GA 30506",
    "addr:housenumber":"9030",
    "addr:postcode":"30506",
    "addr:street":"Walnut Cove Ct",
    "iso:country":"US",
    "sg:address":"9030 Walnut Cove Ct",
    "sg:city":"Gainesville",
    "sg:classifiers":[
        {
            "category":"Professional",
            "subcategory":"Management & Consulting",
            "type":"Services"
        }
    ],
    "sg:phone":"+1 770 205 6745",
    "sg:postcode":"30506",
    "sg:province":"GA",
    "wof:name":"Safelink Inc",
    "wof:placetype":"venue"
},
  "geometry": {"coordinates":[-84.008537,34.230365],"type":"Point"}
}