{
  "type": "Feature",
  "properties": {
    "iso:country":"US",
    "sg:address":"2495 Lois Ln",
    "sg:city":"Jonesboro",
    "sg:classifiers":[
        {
            "category":"Professional",
            "type":"Services"
        }
    ],
    "sg:phone":"+1 770 478 9592",
    "sg:postcode":"30236",
    "sg:province":"GA",
    "wof:name":"Perkinson Darry",
    "wof:placetype":"venue"
},
  "geometry": {"coordinates":[-84.310237,33.545816],"type":"Point"}
}