{
  "type": "Feature",
  "properties": {
    "addr:full":"113 W King St Dalton GA 30720",
    "addr:housenumber":"113",
    "addr:postcode":"30720",
    "addr:street":"W King St",
    "iso:country":"US",
    "sg:address":"113 W King St",
    "sg:city":"Dalton",
    "sg:classifiers":[
        {
            "category":"Restaurant",
            "type":"Food & Drink"
        }
    ],
    "sg:phone":"+1 706 277 4557",
    "sg:postcode":"30720",
    "sg:province":"GA",
    "sg:tags":[
        "style",
        "family"
    ],
    "wof:name":"Chef's Pantry",
    "wof:placetype":"venue"
},
  "geometry": {"coordinates":[-84.96845999999999,34.772282],"type":"Point"}
}