{
  "type": "Feature",
  "properties": {
    "iso:country":"US",
    "sg:address":"755 Mount Vernon Hwy NE # 270",
    "sg:city":"Atlanta",
    "sg:classifiers":[
        {
            "category":"Professional",
            "subcategory":"Testing Lab",
            "type":"Services"
        }
    ],
    "sg:phone":"+1 404 843 3170",
    "sg:postcode":"30328",
    "sg:province":"GA",
    "sg:tags":[
        "analytical",
        "laboratory"
    ],
    "sg:website":"http://www.labcorp.com",
    "wof:name":"LabCorp - Patient Service Center",
    "wof:placetype":"venue"
},
  "geometry": {"coordinates":[-84.363795,33.928037],"type":"Point"}
}