{
  "type": "Feature",
  "properties": {
    "addr:full":"6265 Dogwood Trl Lithonia GA 30058",
    "addr:housenumber":"6265",
    "addr:postcode":"30058",
    "addr:street":"Dogwood Trl",
    "iso:country":"US",
    "sg:address":"6265 Dogwood Trl",
    "sg:city":"Lithonia",
    "sg:classifiers":[
        {
            "category":"Retail",
            "subcategory":"Portrait Studio",
            "type":"Services"
        },
        {
            "category":"Professional",
            "subcategory":"Art Services",
            "type":"Services"
        }
    ],
    "sg:phone":"+1 678 925 9770",
    "sg:postcode":"30058",
    "sg:province":"GA",
    "sg:tags":[
        "rental",
        "photographers-portrait",
        "photographic",
        "darkroom"
    ],
    "wof:name":"Parkins Digital Solutions",
    "wof:placetype":"venue"
},
  "geometry": {"coordinates":[-84.135448,33.750912],"type":"Point"}
}