{
  "type": "Feature",
  "properties": {
    "iso:country":"US",
    "sg:address":"4303 Pleasantdale Rd",
    "sg:city":"Atlanta",
    "sg:classifiers":[
        {
            "category":"Shopping",
            "subcategory":"Gifts & Souvenirs",
            "type":"Retail Goods"
        },
        {
            "category":"Manufacturing",
            "subcategory":"Retail Goods",
            "type":"Manufacturing & Wholesale Goods"
        }
    ],
    "sg:phone":"+1 770 662 8118",
    "sg:postcode":"30340",
    "sg:province":"GA",
    "sg:tags":[
        "shop",
        "giftware's-wholesale",
        "manufacturer"
    ],
    "wof:name":"E G Wholesale",
    "wof:placetype":"venue"
},
  "geometry": {"coordinates":[-84.246678,33.908806],"type":"Point"}
}