{
  "type": "Feature",
  "properties": {
    "iso:country":"US",
    "sg:address":"1443 Drowning Creek Rd",
    "sg:city":"Dacula",
    "sg:classifiers":[
        {
            "category":"Retail",
            "subcategory":"Auto Repair",
            "type":"Services"
        }
    ],
    "sg:phone":"+1 770 513 7999",
    "sg:postcode":"30019",
    "sg:province":"GA",
    "sg:tags":[
        "automotive"
    ],
    "wof:name":"Webbs Auto Machine",
    "wof:placetype":"venue"
},
  "geometry": {"coordinates":[-83.85193200000001,33.971204],"type":"Point"}
}