{
  "type": "Feature",
  "properties": {
    "iso:country":"US",
    "sg:address":"2206 Hanfred Ln",
    "sg:city":"Tucker",
    "sg:classifiers":[
        {
            "category":"Professional",
            "subcategory":"Management & Consulting",
            "type":"Services"
        }
    ],
    "sg:phone":"+1 770 621 0505",
    "sg:postcode":"30084",
    "sg:province":"GA",
    "sg:tags":[
        "marketing",
        "consultant"
    ],
    "wof:name":"Telmar",
    "wof:placetype":"venue"
},
  "geometry": {"coordinates":[-84.209396,33.848365],"type":"Point"}
}