{
  "type": "Feature",
  "properties": {
    "iso:country":"US",
    "sg:address":"207 Russell Pkwy",
    "sg:city":"Warner Robins",
    "sg:classifiers":[
        {
            "category":"Shopping",
            "subcategory":"Mobile Phones",
            "type":"Retail Goods"
        }
    ],
    "sg:phone":"+1 478 922 6272",
    "sg:postcode":"31088",
    "sg:province":"GA",
    "wof:name":"Telepage Wr",
    "wof:placetype":"venue"
},
  "geometry": {"coordinates":[-83.626878,32.593723],"type":"Point"}
}