{
  "type": "Feature",
  "properties": {
    "iso:country":"US",
    "sg:address":"4475 Cherie Glen Trl",
    "sg:city":"Stone Mountain",
    "sg:classifiers":[
        {
            "category":"Professional",
            "subcategory":"Detective & Security Services",
            "type":"Services"
        }
    ],
    "sg:phone":"+1 404 296 0887",
    "sg:postcode":"30083",
    "sg:province":"GA",
    "sg:tags":[
        "system"
    ],
    "wof:name":"Moore Efx",
    "wof:placetype":"venue"
},
  "geometry": {"coordinates":[-84.201815,33.815521],"type":"Point"}
}