{
  "type": "Feature",
  "properties": {
    "addr:full":"210 Middle Creek Rd Springfield GA 31329",
    "addr:housenumber":"210",
    "addr:postcode":"31329",
    "addr:street":"Middle Creek Rd",
    "iso:country":"US",
    "sg:address":"210 Middle Creek Rd",
    "sg:city":"Springfield",
    "sg:classifiers":[
        {
            "category":"Professional",
            "subcategory":"Art Services",
            "type":"Services"
        }
    ],
    "sg:phone":"+1 912 754 7900",
    "sg:postcode":"31329",
    "sg:province":"GA",
    "sg:tags":[
        "designer",
        "display",
        "producer"
    ],
    "wof:name":"Custom Flooring Designs",
    "wof:placetype":"venue"
},
  "geometry": {"coordinates":[-81.241798,32.400089],"type":"Point"}
}