{
  "type": "Feature",
  "properties": {
    "iso:country":"US",
    "sg:address":"501E Johnson Ferry Rd # 150",
    "sg:city":"Marietta",
    "sg:classifiers":[
        {
            "category":"Health Services",
            "subcategory":"Health Practitioner",
            "type":"Services"
        }
    ],
    "sg:phone":"+1 770 509 1344",
    "sg:postcode":"30068",
    "sg:province":"GA",
    "sg:tags":[
        "dietitian"
    ],
    "wof:name":"Dietician",
    "wof:placetype":"venue"
},
  "geometry": {"coordinates":[-84.411781,33.96043],"type":"Point"}
}