{
  "type": "Feature",
  "properties": {
    "iso:country":"US",
    "sg:address":"210 S Coffee Ave",
    "sg:city":"Douglas",
    "sg:classifiers":[
        {
            "category":"Government",
            "subcategory":"Office",
            "type":"Public Place"
        }
    ],
    "sg:phone":"+1 912 383 7600",
    "sg:postcode":"31533",
    "sg:province":"GA",
    "wof:name":"Coffee County Victim Witness",
    "wof:placetype":"venue"
},
  "geometry": {"coordinates":[-82.846912,31.507885],"type":"Point"}
}