{
  "type": "Feature",
  "properties": {
    "iso:country":"US",
    "sg:address":"340 Town Center Ave",
    "sg:city":"Suwanee",
    "sg:classifiers":[
        {
            "category":"Personal",
            "type":"Services"
        }
    ],
    "sg:phone":"+1 770 945 3737",
    "sg:postcode":"30024",
    "sg:province":"GA",
    "sg:tags":[
        "party",
        "planning",
        "event"
    ],
    "sg:website":"www.ottavern.com",
    "wof:name":"Olde Towne Tavern & Grille",
    "wof:placetype":"venue"
},
  "geometry": {"coordinates":[-84.06391000000001,34.055664],"type":"Point"}
}