{
  "type": "Feature",
  "properties": {
    "addr:full":"705 Jones St Ray City GA 31645",
    "addr:housenumber":"705",
    "addr:postcode":"31645",
    "addr:street":"Jones St",
    "iso:country":"US",
    "sg:address":"705 Jones St",
    "sg:city":"Ray City",
    "sg:classifiers":[
        {
            "category":"Organizations",
            "subcategory":"Religious Organization",
            "type":"Services"
        }
    ],
    "sg:phone":"+1 229 455 4411",
    "sg:postcode":"31645",
    "sg:province":"GA",
    "sg:tags":[
        "church"
    ],
    "wof:name":"Ray City Methodist",
    "wof:placetype":"venue"
},
  "geometry": {"coordinates":[-83.1962,31.0761],"type":"Point"}
}