{
  "type": "Feature",
  "properties": {
    "addr:full":"2841 Greenbriar Pkwy SW Atlanta GA 30331",
    "addr:housenumber":"2841",
    "addr:postcode":"30331",
    "addr:street":"Greenbriar Pkwy Sw",
    "iso:country":"US",
    "sg:address":"2841 Greenbriar Pkwy SW",
    "sg:city":"Atlanta",
    "sg:classifiers":[
        {
            "category":"Shopping",
            "subcategory":"Clothing, Apparel, & Fashions",
            "type":"Retail Goods"
        }
    ],
    "sg:phone":"+1 404 349 3404",
    "sg:postcode":"30331",
    "sg:province":"GA",
    "sg:tags":[
        "apparel",
        "racing",
        "sportswear",
        "merchandise"
    ],
    "wof:name":"Mark-It, The",
    "wof:placetype":"venue"
},
  "geometry": {"coordinates":[-84.489051,33.689626],"type":"Point"}
}