{
  "type": "Feature",
  "properties": {
    "addr:full":"4394 Windchime Way NW Kennesaw GA 30152",
    "addr:housenumber":"4394",
    "addr:postcode":"30152",
    "addr:street":"Windchime Way Nw",
    "iso:country":"US",
    "sg:address":"4394 Windchime Way NW",
    "sg:city":"Kennesaw",
    "sg:classifiers":[
        {
            "category":"Travel",
            "subcategory":"Travel Agent",
            "type":"Entertainment"
        }
    ],
    "sg:phone":"+1 770 425 3183",
    "sg:postcode":"30152",
    "sg:province":"GA",
    "sg:tags":[
        "agency"
    ],
    "wof:name":"Marietta Travel",
    "wof:placetype":"venue"
},
  "geometry": {"coordinates":[-84.679091,33.994514],"type":"Point"}
}