{
  "type": "Feature",
  "properties": {
    "iso:country":"US",
    "sg:address":"4248 Buena Vista Rd",
    "sg:city":"Columbus",
    "sg:classifiers":[
        {
            "category":"Restaurant",
            "type":"Food & Drink"
        }
    ],
    "sg:phone":"+1 706 568 7554",
    "sg:postcode":"31907",
    "sg:province":"GA",
    "wof:name":"Chef Lee's Peking Restaurant",
    "wof:placetype":"venue"
},
  "geometry": {"coordinates":[-84.921075,32.464705],"type":"Point"}
}