{
  "type": "Feature",
  "properties": {
    "iso:country":"US",
    "sg:address":"3990 Pleasantdale Road",
    "sg:city":"Atlanta",
    "sg:classifiers":[
        {
            "category":"Building & Trades",
            "subcategory":"Locksmith",
            "type":"Services"
        }
    ],
    "sg:phone":"+1 678 814 0591",
    "sg:postcode":"30340",
    "sg:province":"GA",
    "sg:tags":[
        "key"
    ],
    "wof:name":"Emergency 24 Hour A Locksmith",
    "wof:placetype":"venue"
},
  "geometry": {"coordinates":[-84.24266,33.897651],"type":"Point"}
}