{
  "type": "Feature",
  "properties": {
    "iso:country":"US",
    "sg:address":"635 Fieldwood Ln",
    "sg:city":"Alpharetta",
    "sg:classifiers":[
        {
            "category":"Personal",
            "subcategory":"Beauty Salon",
            "type":"Services"
        }
    ],
    "sg:phone":"+1 770 771 4048",
    "sg:postcode":"30022",
    "sg:province":"GA",
    "wof:name":"Secret Passions",
    "wof:placetype":"venue"
},
  "geometry": {"coordinates":[-84.24528100000001,34.039016],"type":"Point"}
}