{
  "type": "Feature",
  "properties": {
    "addr:full":"757 Athens Rd Lexington GA 30648",
    "addr:housenumber":"757",
    "addr:postcode":"30648",
    "addr:street":"Athens Rd",
    "iso:country":"US",
    "sg:address":"757 Athens Rd",
    "sg:city":"Lexington",
    "sg:classifiers":[
        {
            "category":"Education",
            "subcategory":"School",
            "type":"Public Place"
        }
    ],
    "sg:phone":"+1 706 743 8146",
    "sg:postcode":"30648",
    "sg:province":"GA",
    "sg:tags":[
        "middle"
    ],
    "wof:name":"Oglethorpe County Middle School",
    "wof:placetype":"venue"
},
  "geometry": {"coordinates":[-83.12834700000001,33.887058],"type":"Point"}
}