{
  "type": "Feature",
  "properties": {
    "addr:full":"2439 Fairburn Rd SW Atlanta GA 30331",
    "addr:housenumber":"2439",
    "addr:postcode":"30331",
    "addr:street":"Fairburn Rd Sw",
    "iso:country":"US",
    "sg:address":"2439 Fairburn Rd SW",
    "sg:city":"Atlanta",
    "sg:classifiers":[
        {
            "category":"Professional",
            "subcategory":"Accounting & Tax Preparation",
            "type":"Services"
        }
    ],
    "sg:phone":"+1 404 346 1662",
    "sg:postcode":"30331",
    "sg:province":"GA",
    "wof:name":"Alisons Accounting Service",
    "wof:placetype":"venue"
},
  "geometry": {"coordinates":[-84.51174399999999,33.688077],"type":"Point"}
}