{
  "type": "Feature",
  "properties": {
    "addr:full":"115 N Jackson St Baconton GA 31716",
    "addr:housenumber":"115",
    "addr:postcode":"31716",
    "addr:street":"N Jackson St",
    "iso:country":"US",
    "sg:address":"115 N Jackson St",
    "sg:city":"Baconton",
    "sg:classifiers":[
        {
            "category":"Government",
            "subcategory":"Office",
            "type":"Public Place"
        }
    ],
    "sg:phone":"+1 229 787 2062",
    "sg:postcode":"31716",
    "sg:province":"GA",
    "sg:tags":[
        "parish",
        "government-county"
    ],
    "wof:name":"Mitchell County Ems",
    "wof:placetype":"venue"
},
  "geometry": {"coordinates":[-84.15349000000001,31.375522],"type":"Point"}
}