{
  "type": "Feature",
  "properties": {
    "addr:full":"4291 Royal Mustang Way Lithonia GA 30039",
    "addr:housenumber":"4291",
    "addr:postcode":"30039",
    "addr:street":"Royal Mustang Way",
    "iso:country":"US",
    "sg:address":"4291 Royal Mustang Way",
    "sg:city":"Lithonia",
    "sg:classifiers":[
        {
            "category":"Building & Trades",
            "subcategory":"Construction",
            "type":"Services"
        }
    ],
    "sg:phone":"+1 770 979 5254",
    "sg:postcode":"30039",
    "sg:province":"GA",
    "sg:tags":[
        "general",
        "contractor"
    ],
    "wof:name":"Homes By Scarborough",
    "wof:placetype":"venue"
},
  "geometry": {"coordinates":[-84.06451199999999,33.81375],"type":"Point"}
}