{
  "type": "Feature",
  "properties": {
    "addr:full":"510 N Madison St Quitman GA 31643",
    "addr:housenumber":"510",
    "addr:postcode":"31643",
    "addr:street":"N Madison St",
    "iso:country":"US",
    "sg:address":"510 N Madison St",
    "sg:city":"Quitman",
    "sg:classifiers":[
        {
            "category":"Professional",
            "type":"Services"
        }
    ],
    "sg:phone":"+1 229 263 7017",
    "sg:postcode":"31643",
    "sg:province":"GA",
    "wof:name":"William L McCoggle Dr",
    "wof:placetype":"venue"
},
  "geometry": {"coordinates":[-83.56084799999999,30.789852],"type":"Point"}
}