{
  "type": "Feature",
  "properties": {
    "iso:country":"US",
    "sg:address":"346 1st Ave",
    "sg:city":"Arabi",
    "sg:classifiers":[
        {
            "category":"Farming",
            "subcategory":"Farm & Veterinary Services",
            "type":"Manufacturing & Wholesale Goods"
        }
    ],
    "sg:phone":"+1 229 273 2891",
    "sg:postcode":"31712",
    "sg:province":"GA",
    "sg:tags":[
        "gin",
        "cotton"
    ],
    "wof:name":"Arabi Gin Co",
    "wof:placetype":"venue"
},
  "geometry": {"coordinates":[-83.74146500000001,31.829251],"type":"Point"}
}