{
  "type": "Feature",
  "properties": {
    "addr:full":"969 Windy Hill Rd SE Smyrna GA 30082",
    "addr:housenumber":"969",
    "addr:postcode":"30082",
    "addr:street":"Windy Hill Rd Se",
    "iso:country":"US",
    "sg:address":"969 Windy Hill Rd SE",
    "sg:city":"Smyrna",
    "sg:classifiers":[
        {
            "category":"Travel",
            "subcategory":"Travel Agent",
            "type":"Entertainment"
        }
    ],
    "sg:phone":"+1 770 803 9405",
    "sg:postcode":"30082",
    "sg:province":"GA",
    "sg:tags":[
        "agency"
    ],
    "wof:name":"Latino Travel",
    "wof:placetype":"venue"
},
  "geometry": {"coordinates":[-84.524619,33.894318],"type":"Point"}
}