{
  "type": "Feature",
  "properties": {
    "iso:country":"US",
    "sg:address":"2007 Greenwood St",
    "sg:city":"Savannah",
    "sg:classifiers":[
        {
            "category":"Building & Trades",
            "subcategory":"Construction",
            "type":"Services"
        }
    ],
    "sg:phone":"+1 912 234 6765",
    "sg:postcode":"31404",
    "sg:province":"GA",
    "sg:tags":[
        "carpentry",
        "contractor"
    ],
    "wof:name":"Windows Plus Cabinets",
    "wof:placetype":"venue"
},
  "geometry": {"coordinates":[-81.05665399999999,32.065051],"type":"Point"}
}