{
  "type": "Feature",
  "properties": {
    "iso:country":"US",
    "sg:address":"680 N Kingsley Dr",
    "sg:city":"Lithia Springs",
    "sg:classifiers":[
        {
            "category":"Wholesale",
            "subcategory":"Vending Machines",
            "type":"Manufacturing & Wholesale Goods"
        }
    ],
    "sg:phone":"+1 770 948 7574",
    "sg:postcode":"30122",
    "sg:province":"GA",
    "sg:tags":[
        "operator"
    ],
    "wof:name":"Vending Solutions",
    "wof:placetype":"venue"
},
  "geometry": {"coordinates":[-84.644042,33.786854],"type":"Point"}
}