{
  "type": "Feature",
  "properties": {
    "addr:full":"505 Commerce Park Dr Marietta GA 30060",
    "addr:housenumber":"505",
    "addr:postcode":"30060",
    "addr:street":"Commerce Park Dr",
    "iso:country":"US",
    "sg:address":"505 Commerce Park Dr",
    "sg:city":"Marietta",
    "sg:classifiers":[
        {
            "category":"Professional",
            "subcategory":"Art Services",
            "type":"Services"
        }
    ],
    "sg:phone":"+1 770 428 9007",
    "sg:postcode":"30060",
    "sg:province":"GA",
    "sg:tags":[
        "graphic",
        "designer"
    ],
    "wof:name":"Vision 575",
    "wof:placetype":"venue"
},
  "geometry": {"coordinates":[-84.53337500000001,33.939404],"type":"Point"}
}