{
  "type": "Feature",
  "properties": {
    "addr:full":"5140 Memorial Dr Stone Mountain GA 30083",
    "addr:housenumber":"5140",
    "addr:postcode":"30083",
    "addr:street":"Memorial Dr",
    "iso:country":"US",
    "sg:address":"5140 Memorial Dr",
    "sg:city":"Stone Mountain",
    "sg:classifiers":[
        {
            "category":"Social Services",
            "subcategory":"Child Care",
            "type":"Services"
        }
    ],
    "sg:phone":"+1 404 296 1783",
    "sg:postcode":"30083",
    "sg:province":"GA",
    "sg:tags":[
        "day"
    ],
    "wof:name":"Presby Cmnty Chldrens Program",
    "wof:placetype":"venue"
},
  "geometry": {"coordinates":[-84.226001,33.795302],"type":"Point"}
}