{
  "type": "Feature",
  "properties": {
    "iso:country":"US",
    "sg:address":"63 East Ct",
    "sg:city":"Ringgold",
    "sg:classifiers":[
        {
            "category":"Retail",
            "subcategory":"Animal Services",
            "type":"Services"
        }
    ],
    "sg:phone":"+1 706 861 3163",
    "sg:postcode":"30736",
    "sg:province":"GA",
    "sg:tags":[
        "pet",
        "boarding",
        "sitting"
    ],
    "wof:name":"Home-A-Lone Pet Sitters",
    "wof:placetype":"venue"
},
  "geometry": {"coordinates":[-85.203051,34.912391],"type":"Point"}
}