{
  "type": "Feature",
  "properties": {
    "addr:full":"2541 Milledgeville Rd Augusta GA 30904",
    "addr:housenumber":"2541",
    "addr:postcode":"30904",
    "addr:street":"Milledgeville Rd",
    "iso:country":"US",
    "sg:address":"2541 Milledgeville Rd",
    "sg:city":"Augusta",
    "sg:classifiers":[
        {
            "category":"Health Services",
            "subcategory":"Hospital",
            "type":"Services"
        }
    ],
    "sg:phone":"+1 706 738 2581",
    "sg:postcode":"30904",
    "sg:province":"GA",
    "wof:name":"UniHealth Post Acute Care Augusta",
    "wof:placetype":"venue"
},
  "geometry": {"coordinates":[-82.017635,33.446652],"type":"Point"}
}