{
  "type": "Feature",
  "properties": {
    "addr:full":"288 Rachel Dr Dallas GA 30157",
    "addr:housenumber":"288",
    "addr:postcode":"30157",
    "addr:street":"Rachel Dr",
    "iso:country":"US",
    "sg:address":"288 Rachel Dr",
    "sg:city":"Dallas",
    "sg:classifiers":[
        {
            "category":"Building & Trades",
            "subcategory":"Construction",
            "type":"Services"
        }
    ],
    "sg:phone":"+1 770 459 4075",
    "sg:postcode":"30157",
    "sg:province":"GA",
    "sg:tags":[
        "house"
    ],
    "wof:name":"Zachs Remodeling",
    "wof:placetype":"venue"
},
  "geometry": {"coordinates":[-84.990236,33.856578],"type":"Point"}
}