{
  "type": "Feature",
  "properties": {
    "iso:country":"US",
    "sg:address":"3300 Peachtree Rd NW",
    "sg:city":"Atlanta",
    "sg:classifiers":[
        {
            "category":"Restaurant",
            "type":"Food & Drink"
        }
    ],
    "sg:menulink":"http://www.allmenus.com/ga/atlanta/23252-cassis-at-the-grand-hyatt/menu/",
    "sg:phone":"+1 404 364 3933",
    "sg:postcode":"30305",
    "sg:province":"GA",
    "sg:tags":[
        "seafood",
        "american"
    ],
    "wof:name":"Cassis at the Grand Hyatt",
    "wof:placetype":"venue"
},
  "geometry": {"coordinates":[-84.36935699999999,33.844909],"type":"Point"}
}