{
  "type": "Feature",
  "properties": {
    "iso:country":"US",
    "sg:address":"168 Thompson St",
    "sg:city":"Bloomingdale",
    "sg:classifiers":[
        {
            "category":"Professional",
            "type":"Services"
        }
    ],
    "sg:phone":"+1 912 748 0428",
    "sg:postcode":"31302",
    "sg:province":"GA",
    "wof:name":"Oscar Criswell",
    "wof:placetype":"venue"
},
  "geometry": {"coordinates":[-81.33469599999999,32.146653],"type":"Point"}
}