{
  "type": "Feature",
  "properties": {
    "iso:country":"US",
    "sg:address":"690 Campbell Rd",
    "sg:city":"Covington",
    "sg:classifiers":[
        {
            "category":"Building & Trades",
            "subcategory":"Landscaping Services",
            "type":"Services"
        }
    ],
    "sg:phone":"+1 770 385 9423",
    "sg:postcode":"30014",
    "sg:province":"GA",
    "sg:tags":[
        "landscape"
    ],
    "wof:name":"Weaver & Sons Services",
    "wof:placetype":"venue"
},
  "geometry": {"coordinates":[-83.85354100000001,33.404062],"type":"Point"}
}