{
  "type": "Feature",
  "properties": {
    "iso:country":"US",
    "sg:address":"3600 Cherokee St NW Ste 117",
    "sg:city":"Kennesaw",
    "sg:classifiers":[
        {
            "category":"Health Services",
            "subcategory":"Dentist",
            "type":"Services"
        }
    ],
    "sg:phone":"+1 770 424 8077",
    "sg:postcode":"30144",
    "sg:province":"GA",
    "wof:name":"Olson David E DMD",
    "wof:placetype":"venue"
},
  "geometry": {"coordinates":[-84.6035,34.040901],"type":"Point"}
}