{
  "type": "Feature",
  "properties": {
    "addr:full":"5072 Riverview Rd NW Atlanta GA 30327",
    "addr:housenumber":"5072",
    "addr:postcode":"30327",
    "addr:street":"Riverview Rd Nw",
    "iso:country":"US",
    "sg:address":"5072 Riverview Rd NW",
    "sg:city":"Atlanta",
    "sg:classifiers":[
        {
            "category":"Professional",
            "type":"Services"
        }
    ],
    "sg:phone":"+1 770 955 1855",
    "sg:postcode":"30327",
    "sg:province":"GA",
    "wof:name":"Two Hearts Inc",
    "wof:placetype":"venue"
},
  "geometry": {"coordinates":[-84.437735,33.898601],"type":"Point"}
}