{
  "type": "Feature",
  "properties": {
    "addr:full":"2300 Henderson Mill Rd NE Atlanta GA 30345",
    "addr:housenumber":"2300",
    "addr:postcode":"30345",
    "addr:street":"Henderson Mill Rd Ne",
    "iso:country":"US",
    "sg:address":"2300 Henderson Mill Rd NE",
    "sg:city":"Atlanta",
    "sg:classifiers":[
        {
            "category":"Education",
            "subcategory":"Special Training",
            "type":"Public Place"
        }
    ],
    "sg:phone":"+1 770 491 1239",
    "sg:postcode":"30345",
    "sg:province":"GA",
    "sg:tags":[
        "program"
    ],
    "sg:website":"www.corstrat.org",
    "wof:name":"Corporate Strategies Inc",
    "wof:placetype":"venue"
},
  "geometry": {"coordinates":[-84.25853499999999,33.850878],"type":"Point"}
}