{
  "type": "Feature",
  "properties": {
    "addr:full":"150 Oak Rd Fayetteville GA 30214",
    "addr:housenumber":"150",
    "addr:postcode":"30214",
    "addr:street":"Oak Rd",
    "iso:country":"US",
    "sg:address":"150 Oak Rd",
    "sg:city":"Fayetteville",
    "sg:classifiers":[
        {
            "category":"Professional",
            "type":"Services"
        }
    ],
    "sg:phone":"+1 770 719 2343",
    "sg:postcode":"30214",
    "sg:province":"GA",
    "wof:name":"Clark Systems Corporation",
    "wof:placetype":"venue"
},
  "geometry": {"coordinates":[-84.448661,33.483682],"type":"Point"}
}