{
  "type": "Feature",
  "properties": {
    "addr:full":"1550 S Broad St Monroe GA 30655",
    "addr:housenumber":"1550",
    "addr:postcode":"30655",
    "addr:street":"S Broad St",
    "iso:country":"US",
    "sg:address":"1550 S Broad St",
    "sg:city":"Monroe",
    "sg:classifiers":[
        {
            "category":"Building & Trades",
            "subcategory":"Construction",
            "type":"Services"
        }
    ],
    "sg:phone":"+1 770 267 9628",
    "sg:postcode":"30655",
    "sg:province":"GA",
    "sg:tags":[
        "maker",
        "cabinet"
    ],
    "wof:name":"Custom Wood Interiors Inc",
    "wof:placetype":"venue"
},
  "geometry": {"coordinates":[-83.703416,33.774374],"type":"Point"}
}