{
  "type": "Feature",
  "properties": {
    "iso:country":"US",
    "sg:address":"3665 Wheeler Rd",
    "sg:city":"Augusta",
    "sg:classifiers":[
        {
            "category":"Health Services",
            "subcategory":"Chiropractor",
            "type":"Services"
        }
    ],
    "sg:phone":"+1 706 855 8777",
    "sg:postcode":"30909",
    "sg:province":"GA",
    "wof:name":"Cynthia Poppell Dr",
    "wof:placetype":"venue"
},
  "geometry": {"coordinates":[-82.09201400000001,33.482589],"type":"Point"}
}