{
  "type": "Feature",
  "properties": {
    "addr:full":"1223 Firestone Dr Albany GA 31707",
    "addr:housenumber":"1223",
    "addr:postcode":"31707",
    "addr:street":"Firestone Dr",
    "iso:country":"US",
    "sg:address":"1223 Firestone Dr",
    "sg:city":"Albany",
    "sg:classifiers":[
        {
            "category":"Personal",
            "subcategory":"Beauty Salon",
            "type":"Services"
        }
    ],
    "sg:phone":"+1 229 432 5422",
    "sg:postcode":"31707",
    "sg:province":"GA",
    "wof:name":"Le S Beauty Salon",
    "wof:placetype":"venue"
},
  "geometry": {"coordinates":[-84.20590199999999,31.55728],"type":"Point"}
}