{
  "type": "Feature",
  "properties": {
    "iso:country":"US",
    "sg:address":"3671 Spratlin Mill Rd",
    "sg:city":"Hull",
    "sg:classifiers":[
        {
            "category":"Building & Trades",
            "subcategory":"Construction",
            "type":"Services"
        }
    ],
    "sg:phone":"+1 706 548 3752",
    "sg:postcode":"30646",
    "sg:province":"GA",
    "sg:tags":[
        "fuel",
        "dealer"
    ],
    "wof:name":"Adams Firewood",
    "wof:placetype":"venue"
},
  "geometry": {"coordinates":[-83.286913,34.02205],"type":"Point"}
}