{
  "type": "Feature",
  "properties": {
    "iso:country":"US",
    "sg:address":"725 Neese Rd",
    "sg:city":"Woodstock",
    "sg:classifiers":[
        {
            "category":"Retail",
            "subcategory":"Auto Repair",
            "type":"Services"
        }
    ],
    "sg:phone":"+1 770 928 4671",
    "sg:postcode":"30188",
    "sg:province":"GA",
    "sg:tags":[
        "automotive"
    ],
    "wof:name":"Neese Towing Service Inc",
    "wof:placetype":"venue"
},
  "geometry": {"coordinates":[-84.492858,34.093299],"type":"Point"}
}