{
  "type": "Feature",
  "properties": {
    "iso:country":"US",
    "sg:address":"6000 Pechtre Indstrl Blvd",
    "sg:city":"Norcross",
    "sg:classifiers":[
        {
            "category":"Food & Beverages",
            "subcategory":"Candy",
            "type":"Retail Goods"
        }
    ],
    "sg:phone":"+1 770 446 1299",
    "sg:postcode":"30071",
    "sg:province":"GA",
    "sg:tags":[
        "store"
    ],
    "wof:name":"Maggie Lyon Inc",
    "wof:placetype":"venue"
},
  "geometry": {"coordinates":[-84.203796,33.935902],"type":"Point"}
}