{
  "type": "Feature",
  "properties": {
    "addr:full":"125 Southern Magnolia Ln Rex GA 30273",
    "addr:housenumber":"125",
    "addr:postcode":"30273",
    "addr:street":"Southern Magnolia Ln",
    "iso:country":"US",
    "sg:address":"125 Southern Magnolia Ln",
    "sg:city":"Rex",
    "sg:classifiers":[
        {
            "category":"Professional",
            "subcategory":"Computer Services",
            "type":"Services"
        }
    ],
    "sg:phone":"+1 770 506 6864",
    "sg:postcode":"30273",
    "sg:province":"GA",
    "wof:name":"User PC Solutions",
    "wof:placetype":"venue"
},
  "geometry": {"coordinates":[-84.258788,33.579999],"type":"Point"}
}