{
  "type": "Feature",
  "properties": {
    "addr:full":"112 2nd Ave Mc Rae GA 31055",
    "addr:housenumber":"112",
    "addr:postcode":"31055",
    "addr:street":"2Nd Ave Mc Rae",
    "iso:country":"US",
    "sg:address":"112 2nd Ave",
    "sg:city":"Mc Rae",
    "sg:classifiers":[
        {
            "category":"Shopping",
            "subcategory":"Pharmacy",
            "type":"Retail Goods"
        }
    ],
    "sg:phone":"+1 229 868 6735",
    "sg:postcode":"31055",
    "sg:province":"GA",
    "wof:name":"Ryals Drug Store",
    "wof:placetype":"venue"
},
  "geometry": {"coordinates":[-82.900773,32.064414],"type":"Point"}
}