{
  "type": "Feature",
  "properties": {
    "iso:country":"US",
    "sg:address":"275 Carpenter Dr NE",
    "sg:city":"Atlanta",
    "sg:classifiers":[
        {
            "category":"Wholesale",
            "subcategory":"Home Furnishings",
            "type":"Manufacturing & Wholesale Goods"
        }
    ],
    "sg:phone":"+1 404 843 8011",
    "sg:postcode":"30328",
    "sg:province":"GA",
    "sg:tags":[
        "automobile"
    ],
    "wof:name":"Alumi Bunk USA",
    "wof:placetype":"venue"
},
  "geometry": {"coordinates":[-84.375794,33.914377],"type":"Point"}
}