{
  "type": "Feature",
  "properties": {
    "addr:full":"2499 Airport Throughway Columbus GA 31904",
    "addr:housenumber":"2499",
    "addr:postcode":"31904",
    "addr:street":"Airport Throughway",
    "iso:country":"US",
    "sg:address":"2499 Airport Throughway",
    "sg:city":"Columbus",
    "sg:classifiers":[
        {
            "category":"Shopping",
            "type":"Retail Goods"
        }
    ],
    "sg:phone":"+1 706 322 0777",
    "sg:postcode":"31904",
    "sg:province":"GA",
    "sg:tags":[
        "coin",
        "dealer",
        "supply"
    ],
    "wof:name":"O'Connell's Coins & Jewelry",
    "wof:placetype":"venue"
},
  "geometry": {"coordinates":[-84.954787,32.519245],"type":"Point"}
}