{
  "type": "Feature",
  "properties": {
    "addr:full":"218 Beall St Thomaston GA 30286",
    "addr:housenumber":"218",
    "addr:postcode":"30286",
    "addr:street":"Beall St",
    "iso:country":"US",
    "sg:address":"218 Beall St",
    "sg:city":"Thomaston",
    "sg:classifiers":[
        {
            "category":"Organizations",
            "subcategory":"Membership Organization",
            "type":"Services"
        }
    ],
    "sg:phone":"+1 404 914 4527",
    "sg:postcode":"30286",
    "sg:province":"GA",
    "sg:tags":[
        "support",
        "group"
    ],
    "wof:name":"Rays House Of Hope Ministry Limited Liability Company",
    "wof:placetype":"venue"
},
  "geometry": {"coordinates":[-84.320217,32.888899],"type":"Point"}
}