{
  "type": "Feature",
  "properties": {
    "addr:full":"2955 Athena Ln Lithonia GA 30038",
    "addr:housenumber":"2955",
    "addr:postcode":"30038",
    "addr:street":"Athena Ln",
    "iso:country":"US",
    "sg:address":"2955 Athena Ln",
    "sg:city":"Lithonia",
    "sg:classifiers":[
        {
            "category":"Professional",
            "subcategory":"Management & Consulting",
            "type":"Services"
        }
    ],
    "sg:phone":"+1 770 987 5791",
    "sg:postcode":"30038",
    "sg:province":"GA",
    "wof:name":"Turn Time  Inc",
    "wof:placetype":"venue"
},
  "geometry": {"coordinates":[-84.144851,33.700539],"type":"Point"}
}