{
  "type": "Feature",
  "properties": {
    "addr:full":"4788 Wyndam Dr Stone Mountain GA 30088",
    "addr:housenumber":"4788",
    "addr:postcode":"30088",
    "addr:street":"Wyndam Dr",
    "iso:country":"US",
    "sg:address":"4788 Wyndam Dr",
    "sg:city":"Stone Mountain",
    "sg:classifiers":[
        {
            "category":"Social Services",
            "subcategory":"Child Care",
            "type":"Services"
        }
    ],
    "sg:phone":"+1 770 593 9055",
    "sg:postcode":"30088",
    "sg:province":"GA",
    "wof:name":"Carlyle's Daycare",
    "wof:placetype":"venue"
},
  "geometry": {"coordinates":[-84.192448,33.756408],"type":"Point"}
}