{
  "type": "Feature",
  "properties": {
    "addr:full":"482 Cricket Hill Trl Lawrenceville GA 30044",
    "addr:housenumber":"482",
    "addr:postcode":"30044",
    "addr:street":"Cricket Hill Trl",
    "iso:country":"US",
    "sg:address":"482 Cricket Hill Trl",
    "sg:city":"Lawrenceville",
    "sg:classifiers":[
        {
            "category":"Real Estate",
            "subcategory":"Architect",
            "type":"Services"
        }
    ],
    "sg:phone":"+1 770 972 1689",
    "sg:postcode":"30044",
    "sg:province":"GA",
    "sg:tags":[
        "architectural"
    ],
    "wof:name":"Ludic Inc",
    "wof:placetype":"venue"
},
  "geometry": {"coordinates":[-84.0476,33.908614],"type":"Point"}
}