{
  "type": "Feature",
  "properties": {
    "addr:full":"983 Oakwood Chase Cir Stone Mountain GA 30083",
    "addr:housenumber":"983",
    "addr:postcode":"30083",
    "addr:street":"Oakwood Chase Cir",
    "iso:country":"US",
    "sg:address":"983 Oakwood Chase Cir",
    "sg:city":"Stone Mountain",
    "sg:classifiers":[
        {
            "category":"Shopping",
            "type":"Retail Goods"
        }
    ],
    "sg:phone":"+1 404 294 4173",
    "sg:postcode":"30083",
    "sg:province":"GA",
    "sg:tags":[
        "establishment",
        "e",
        "merchandise"
    ],
    "wof:name":"International Chemical Inc",
    "wof:placetype":"venue"
},
  "geometry": {"coordinates":[-84.20769799999999,33.764213],"type":"Point"}
}