{
  "type": "Feature",
  "properties": {
    "iso:country":"US",
    "sg:address":"1234 Powers Ferry Rd SE # 102",
    "sg:city":"Marietta",
    "sg:classifiers":[
        {
            "category":"Banks & Credit Unions",
            "subcategory":"Investment Brokerage",
            "type":"Services"
        },
        {
            "category":"Insurance",
            "subcategory":"Hazard Insurance",
            "type":"Services"
        }
    ],
    "sg:phone":"+1 770 952 7725",
    "sg:postcode":"30067",
    "sg:province":"GA",
    "sg:tags":[
        "agent",
        "resume"
    ],
    "sg:website":"http://www.bbocala.com",
    "wof:name":"Insurance Marketing Group",
    "wof:placetype":"venue"
},
  "geometry": {"coordinates":[-84.467665,33.921337],"type":"Point"}
}