{
  "type": "Feature",
  "properties": {
    "addr:full":"2722 N Decatur Rd Decatur Ga Decatur GA 30033",
    "addr:housenumber":"2722",
    "addr:postcode":"30033",
    "addr:street":"N Decatur Rd",
    "iso:country":"US",
    "sg:address":"2722 N Decatur Rd Decatur Ga",
    "sg:city":"Decatur",
    "sg:classifiers":[
        {
            "category":"Health Services",
            "subcategory":"Clinic",
            "type":"Services"
        },
        {
            "category":"Health Services",
            "subcategory":"Nursing And Care Facility",
            "type":"Services"
        },
        {
            "category":"Health Services",
            "subcategory":"Health Practitioner",
            "type":"Services"
        },
        {
            "category":"Social Services",
            "subcategory":"Retirement Home",
            "type":"Services"
        },
        {
            "category":"Social Services",
            "subcategory":"Job Training",
            "type":"Services"
        }
    ],
    "sg:phone":"+1 404 296 5440",
    "sg:postcode":"30033",
    "sg:province":"GA",
    "sg:tags":[
        "homes-skilled",
        "convalescent",
        "therapist",
        "homes-intermediate",
        "rehabilitation",
        "physical"
    ],
    "sg:website":"http://www.manorcare.com/DecaturGA",
    "wof:name":"ManorCare Rehabilitation Center - Decatur",
    "wof:placetype":"venue"
},
  "geometry": {"coordinates":[-84.281792,33.792453],"type":"Point"}
}