{
  "type": "Feature",
  "properties": {
    "addr:full":"95 Graystone Dr Covington GA 30014",
    "addr:housenumber":"95",
    "addr:postcode":"30014",
    "addr:street":"Graystone Dr",
    "iso:country":"US",
    "sg:address":"95 Graystone Dr",
    "sg:city":"Covington",
    "sg:classifiers":[
        {
            "category":"Professional",
            "type":"Services"
        }
    ],
    "sg:phone":"+1 770 787 0727",
    "sg:postcode":"30014",
    "sg:province":"GA",
    "wof:name":"Csk Services",
    "wof:placetype":"venue"
},
  "geometry": {"coordinates":[-83.797044,33.544217],"type":"Point"}
}