{
  "type": "Feature",
  "properties": {
    "iso:country":"US",
    "sg:address":"1490 Northwold Dr",
    "sg:city":"Atlanta",
    "sg:classifiers":[
        {
            "category":"Travel",
            "subcategory":"Travel Agent",
            "type":"Entertainment"
        }
    ],
    "sg:phone":"+1 770 394 6389",
    "sg:postcode":"30350",
    "sg:province":"GA",
    "sg:tags":[
        "agency",
        "bureau"
    ],
    "sg:website":"www.turnertravels.com",
    "wof:name":"Turner Travels",
    "wof:placetype":"venue"
},
  "geometry": {"coordinates":[-84.340659,33.975347],"type":"Point"}
}