{
  "type": "Feature",
  "properties": {
    "addr:full":"630 Pine Cone Rd Dublin GA 31021",
    "addr:housenumber":"630",
    "addr:postcode":"31021",
    "addr:street":"Pine Cone Rd",
    "iso:country":"US",
    "sg:address":"630 Pine Cone Rd",
    "sg:city":"Dublin",
    "sg:classifiers":[
        {
            "category":"Real Estate",
            "subcategory":"Real Estate Agent",
            "type":"Services"
        }
    ],
    "sg:phone":"+1 478 275 3709",
    "sg:postcode":"31021",
    "sg:province":"GA",
    "wof:name":"Momas Properties Inc",
    "wof:placetype":"venue"
},
  "geometry": {"coordinates":[-82.90019700000001,32.49903],"type":"Point"}
}