{
  "type": "Feature",
  "properties": {
    "addr:full":"954 Rose Creek Run Woodstock GA 30189",
    "addr:housenumber":"954",
    "addr:postcode":"30189",
    "addr:street":"Rose Creek Run",
    "iso:country":"US",
    "sg:address":"954 Rose Creek Run",
    "sg:city":"Woodstock",
    "sg:classifiers":[
        {
            "category":"Organizations",
            "subcategory":"Religious Organization",
            "type":"Services"
        }
    ],
    "sg:phone":"+1 770 592 9959",
    "sg:postcode":"30189",
    "sg:province":"GA",
    "sg:tags":[
        "clergy"
    ],
    "wof:name":"W Wayne Pugh",
    "wof:placetype":"venue"
},
  "geometry": {"coordinates":[-84.580572,34.120553],"type":"Point"}
}