{
  "type": "Feature",
  "properties": {
    "iso:country":"US",
    "sg:address":"6344 Stephens Rd",
    "sg:city":"Young Harris",
    "sg:classifiers":[
        {
            "category":"Personal",
            "subcategory":"Beauty Salon",
            "type":"Services"
        }
    ],
    "sg:phone":"+1 706 379 3984",
    "sg:postcode":"30582",
    "sg:province":"GA",
    "sg:tags":[
        "shop"
    ],
    "wof:name":"Mikes Hair Design",
    "wof:placetype":"venue"
},
  "geometry": {"coordinates":[-83.869069,34.918877],"type":"Point"}
}