{
  "type": "Feature",
  "properties": {
    "iso:country":"US",
    "sg:address":"615 N Jefferson Ave",
    "sg:city":"Eatonton",
    "sg:classifiers":[
        {
            "category":"Food & Beverages",
            "subcategory":"Groceries & Convenience Stores",
            "type":"Retail Goods"
        }
    ],
    "sg:phone":"+1 706 485 5535",
    "sg:postcode":"31024",
    "sg:province":"GA",
    "sg:tags":[
        "grocer"
    ],
    "wof:name":"Lucerito",
    "wof:placetype":"venue"
},
  "geometry": {"coordinates":[-83.39291900000001,33.334802],"type":"Point"}
}