{
  "type": "Feature",
  "properties": {
    "addr:full":"3277 Satellite Blvd Duluth GA 30096",
    "addr:housenumber":"3277",
    "addr:postcode":"30096",
    "addr:street":"Satellite Blvd",
    "iso:country":"US",
    "sg:address":"3277 Satellite Blvd",
    "sg:city":"Duluth",
    "sg:classifiers":[
        {
            "category":"Autos & Motor Vehicles",
            "subcategory":"Automobile Sales",
            "type":"Retail Goods"
        }
    ],
    "sg:phone":"+1 678 957 5260",
    "sg:postcode":"30096",
    "sg:province":"GA",
    "sg:tags":[
        "car"
    ],
    "wof:name":"Gwinnett Place",
    "wof:placetype":"venue"
},
  "geometry": {"coordinates":[-84.12400100000001,33.9636],"type":"Point"}
}