{
  "type": "Feature",
  "properties": {
    "addr:full":"1439 Old Salem Rd SE Conyers GA 30013",
    "addr:housenumber":"1439",
    "addr:postcode":"30013",
    "addr:street":"Old Salem Rd Se",
    "iso:country":"US",
    "sg:address":"1439 Old Salem Rd SE",
    "sg:city":"Conyers",
    "sg:classifiers":[
        {
            "category":"Building & Trades",
            "subcategory":"Locksmith",
            "type":"Services"
        }
    ],
    "sg:phone":"+1 404 418 6501",
    "sg:postcode":"30013",
    "sg:province":"GA",
    "sg:tags":[
        "key"
    ],
    "wof:name":"All Day Emergency Locksmith",
    "wof:placetype":"venue"
},
  "geometry": {"coordinates":[-84.005532,33.649503],"type":"Point"}
}