{
  "type": "Feature",
  "properties": {
    "iso:country":"US",
    "sg:address":"15 Reinhardt College Pkwy Ste 102",
    "sg:city":"Canton",
    "sg:classifiers":[
        {
            "category":"Health Services",
            "subcategory":"Doctor",
            "type":"Services"
        }
    ],
    "sg:phone":"+1 770 704 9499",
    "sg:postcode":"30114",
    "sg:province":"GA",
    "sg:tags":[
        "medicine",
        "internal"
    ],
    "wof:name":"Gani Karim MD",
    "wof:placetype":"venue"
},
  "geometry": {"coordinates":[-84.47995299999999,34.252492],"type":"Point"}
}