{
  "type": "Feature",
  "properties": {
    "addr:full":"1100 Abernathy Rd NE Atlanta GA 30328",
    "addr:housenumber":"1100",
    "addr:postcode":"30328",
    "addr:street":"Abernathy Rd Ne",
    "iso:country":"US",
    "sg:address":"1100 Abernathy Rd NE",
    "sg:city":"Atlanta",
    "sg:classifiers":[
        {
            "category":"Insurance",
            "subcategory":"Insurance Agent",
            "type":"Services"
        }
    ],
    "sg:phone":"+1 770 512 0091",
    "sg:postcode":"30328",
    "sg:province":"GA",
    "sg:website":"www.genworth.com",
    "wof:name":"G E Financial",
    "wof:placetype":"venue"
},
  "geometry": {"coordinates":[-84.351319,33.933799],"type":"Point"}
}