{
  "type": "Feature",
  "properties": {
    "addr:full":"2345 Athens Hwy Gainesville GA 30507",
    "addr:housenumber":"2345",
    "addr:postcode":"30507",
    "addr:street":"Athens Hwy",
    "iso:country":"US",
    "sg:address":"2345 Athens Hwy",
    "sg:city":"Gainesville",
    "sg:classifiers":[
        {
            "category":"Travel",
            "subcategory":"Travel Agent",
            "type":"Entertainment"
        }
    ],
    "sg:phone":"+1 770 534 2033",
    "sg:postcode":"30507",
    "sg:province":"GA",
    "sg:tags":[
        "agency",
        "bureau"
    ],
    "wof:name":"American International Travel",
    "wof:placetype":"venue"
},
  "geometry": {"coordinates":[-83.778143,34.268788],"type":"Point"}
}