{
  "type": "Feature",
  "properties": {
    "iso:country":"US",
    "sg:address":"4443 Napier Ave",
    "sg:city":"Macon",
    "sg:classifiers":[
        {
            "category":"Professional",
            "subcategory":"Business Services",
            "type":"Services"
        }
    ],
    "sg:phone":"+1 478 952 6748",
    "sg:postcode":"31210",
    "sg:province":"GA",
    "sg:tags":[
        "construction",
        "broker"
    ],
    "wof:name":"C&S Construction Counselor Svc",
    "wof:placetype":"venue"
},
  "geometry": {"coordinates":[-83.69830899999999,32.866233],"type":"Point"}
}