{
  "type": "Feature",
  "properties": {
    "iso:country":"US",
    "sg:address":"1725 Spindle Top Ct SW",
    "sg:city":"Lilburn",
    "sg:classifiers":[
        {
            "category":"Health Services",
            "subcategory":"Clinic",
            "type":"Services"
        }
    ],
    "sg:phone":"+1 770 978 6457",
    "sg:postcode":"30047",
    "sg:province":"GA",
    "wof:name":"Edwardian Healthcare",
    "wof:placetype":"venue"
},
  "geometry": {"coordinates":[-84.075734,33.849392],"type":"Point"}
}