{
  "type": "Feature",
  "properties": {
    "iso:country":"US",
    "sg:address":"6605 Abercorn St Exn",
    "sg:city":"Savannah",
    "sg:classifiers":[
        {
            "category":"Government",
            "subcategory":"Office",
            "type":"Public Place"
        }
    ],
    "sg:phone":"+1 912 356 3840",
    "sg:postcode":"31405",
    "sg:province":"GA",
    "sg:tags":[
        "armed",
        "force",
        "recruiting"
    ],
    "wof:name":"US Air Force Recruiting",
    "wof:placetype":"venue"
},
  "geometry": {"coordinates":[-81.11264300000001,32.015923],"type":"Point"}
}