{
  "type": "Feature",
  "properties": {
    "iso:country":"US",
    "sg:address":"349 Geneva Rd",
    "sg:city":"Buena Vista",
    "sg:classifiers":[
        {
            "category":"Health Services",
            "subcategory":"Nursing And Care Facility",
            "type":"Services"
        }
    ],
    "sg:phone":"+1 229 649 7100",
    "sg:postcode":"31803",
    "sg:province":"GA",
    "sg:tags":[
        "home",
        "convalescent"
    ],
    "wof:name":"Marion Memorial Nursing Home",
    "wof:placetype":"venue"
},
  "geometry": {"coordinates":[-84.52633899999999,32.329435],"type":"Point"}
}