{
  "type": "Feature",
  "properties": {
    "iso:country":"US",
    "sg:address":"6842 Douglas Blvd Ste H",
    "sg:city":"Douglasville",
    "sg:classifiers":[
        {
            "category":"Shopping",
            "subcategory":"Party Supplies",
            "type":"Retail Goods"
        },
        {
            "category":"Organizations",
            "subcategory":"Non-profit Organization",
            "type":"Services"
        }
    ],
    "sg:phone":"+1 770 942 0171",
    "sg:postcode":"30135",
    "sg:province":"GA",
    "sg:tags":[
        "bridal",
        "registry",
        "wedding"
    ],
    "wof:name":"Brides Atlanta",
    "wof:placetype":"venue"
},
  "geometry": {"coordinates":[-84.755157,33.728119],"type":"Point"}
}