{
  "type": "Feature",
  "properties": {
    "addr:full":"140 Wright Rd Cobb GA 31796",
    "addr:housenumber":"140",
    "addr:postcode":"31796",
    "addr:street":"Wright Rd",
    "iso:country":"US",
    "sg:address":"140 Wright Rd",
    "sg:city":"Cobb",
    "sg:classifiers":[
        {
            "category":"Organizations",
            "subcategory":"Religious Organization",
            "type":"Services"
        }
    ],
    "sg:phone":"+1 229 853 7140",
    "sg:postcode":"31796",
    "sg:province":"GA",
    "sg:tags":[
        "church"
    ],
    "wof:name":"New Beulah Baptist Church",
    "wof:placetype":"venue"
},
  "geometry": {"coordinates":[-83.885217,31.809574],"type":"Point"}
}