{
  "type": "Feature",
  "properties": {
    "iso:country":"US",
    "sg:address":"2300 Holcomb Bridge Rd",
    "sg:city":"Roswell",
    "sg:classifiers":[
        {
            "category":"Insurance",
            "subcategory":"Insurance Agent",
            "type":"Services"
        }
    ],
    "sg:phone":"+1 770 645 9330",
    "sg:postcode":"30076",
    "sg:province":"GA",
    "wof:name":"Ralph Saul & Assoc Inc",
    "wof:placetype":"venue"
},
  "geometry": {"coordinates":[-84.29742899999999,34.005044],"type":"Point"}
}