{
  "type": "Feature",
  "properties": {
    "iso:country":"US",
    "sg:address":"733 Pimento Ave",
    "sg:city":"Griffin",
    "sg:classifiers":[
        {
            "category":"Organizations",
            "subcategory":"Religious Organization",
            "type":"Services"
        }
    ],
    "sg:phone":"+1 770 227 2420",
    "sg:postcode":"30224",
    "sg:province":"GA",
    "sg:tags":[
        "church"
    ],
    "wof:name":"Springhill Baptist Church",
    "wof:placetype":"venue"
},
  "geometry": {"coordinates":[-84.27396299999999,33.240755],"type":"Point"}
}