{
  "type": "Feature",
  "properties": {
    "addr:full":"1275 State Rte 54 Fayetteville GA 30214",
    "addr:housenumber":"1275",
    "addr:postcode":"30214",
    "addr:street":"State Rte 54",
    "iso:country":"US",
    "sg:address":"1275 State Rte 54",
    "sg:city":"Fayetteville",
    "sg:classifiers":[
        {
            "category":"Building & Trades",
            "subcategory":"Construction",
            "type":"Services"
        }
    ],
    "sg:phone":"+1 678 610 3238",
    "sg:postcode":"30214",
    "sg:province":"GA",
    "sg:tags":[
        "elevator"
    ],
    "wof:name":"Fayetteville Mac Inc Elevator",
    "wof:placetype":"venue"
},
  "geometry": {"coordinates":[-84.509186,33.450842],"type":"Point"}
}