{
  "type": "Feature",
  "properties": {
    "iso:country":"US",
    "sg:address":"521 Shirley Ave",
    "sg:city":"Douglas",
    "sg:classifiers":[
        {
            "category":"Shopping",
            "subcategory":"Tobacco",
            "type":"Retail Goods"
        }
    ],
    "sg:phone":"+1 912 383 7262",
    "sg:postcode":"31533",
    "sg:province":"GA",
    "sg:tags":[
        "cigarette",
        "cigar"
    ],
    "wof:name":"Mid South Distribution Services Inc",
    "wof:placetype":"venue"
},
  "geometry": {"coordinates":[-82.86162299999999,31.505344],"type":"Point"}
}