{
  "type": "Feature",
  "properties": {
    "addr:full":"10960 State Bridge Rd Alpharetta GA 30097",
    "addr:housenumber":"10960",
    "addr:postcode":"30097",
    "addr:street":"State Bridge Rd",
    "iso:country":"US",
    "sg:address":"10960 State Bridge Rd",
    "sg:city":"Alpharetta",
    "sg:classifiers":[
        {
            "category":"Restaurant",
            "type":"Food & Drink"
        }
    ],
    "sg:phone":"+1 678 762 0762",
    "sg:postcode":"30097",
    "sg:province":"GA",
    "sg:tags":[
        "eating"
    ],
    "wof:name":"KFC",
    "wof:placetype":"venue"
},
  "geometry": {"coordinates":[-84.181208,34.008682],"type":"Point"}
}