{
  "type": "Feature",
  "properties": {
    "addr:full":"403 High St Ringgold GA 30736",
    "addr:housenumber":"403",
    "addr:postcode":"30736",
    "addr:street":"High St",
    "iso:country":"US",
    "sg:address":"403 High St",
    "sg:city":"Ringgold",
    "sg:classifiers":[
        {
            "category":"Wholesale",
            "subcategory":"Machinery & Supplies",
            "type":"Manufacturing & Wholesale Goods"
        }
    ],
    "sg:phone":"+1 706 937 9030",
    "sg:postcode":"30736",
    "sg:province":"GA",
    "sg:tags":[
        "poultry",
        "equipment"
    ],
    "wof:name":"Ringgold Poultry Supply",
    "wof:placetype":"venue"
},
  "geometry": {"coordinates":[-85.106736,34.917366],"type":"Point"}
}