{
  "type": "Feature",
  "properties": {
    "addr:full":"393 Smithville Rd Leesburg GA 31763",
    "addr:housenumber":"393",
    "addr:postcode":"31763",
    "addr:street":"Smithville Rd",
    "iso:country":"US",
    "sg:address":"393 Smithville Rd",
    "sg:city":"Leesburg",
    "sg:classifiers":[
        {
            "category":"Professional",
            "type":"Services"
        }
    ],
    "sg:phone":"+1 229 759 6885",
    "sg:postcode":"31763",
    "sg:province":"GA",
    "wof:name":"Greg L Mall",
    "wof:placetype":"venue"
},
  "geometry": {"coordinates":[-84.171966,31.755115],"type":"Point"}
}