{
  "type": "Feature",
  "properties": {
    "iso:country":"US",
    "sg:address":"122 Chapel Crossing Rd",
    "sg:city":"Brunswick",
    "sg:classifiers":[
        {
            "category":"Building & Trades",
            "subcategory":"Construction",
            "type":"Services"
        }
    ],
    "sg:phone":"+1 912 265 0434",
    "sg:postcode":"31525",
    "sg:province":"GA",
    "sg:website":"www.omnicorporation.com",
    "wof:name":"Omni Corp",
    "wof:placetype":"venue"
},
  "geometry": {"coordinates":[-81.477627,31.225688],"type":"Point"}
}