{
  "type": "Feature",
  "properties": {
    "addr:full":"165 Laurel Forest Cir NE Atlanta GA 30342",
    "addr:housenumber":"165",
    "addr:postcode":"30342",
    "addr:street":"Laurel Forest Cir Ne",
    "iso:country":"US",
    "sg:address":"165 Laurel Forest Cir NE",
    "sg:city":"Atlanta",
    "sg:classifiers":[
        {
            "category":"Building & Trades",
            "subcategory":"Locksmith",
            "type":"Services"
        }
    ],
    "sg:phone":"+1 404 260 0040",
    "sg:postcode":"30342",
    "sg:province":"GA",
    "sg:tags":[
        "key"
    ],
    "wof:name":"A A Emerg A A A Locksmith",
    "wof:placetype":"venue"
},
  "geometry": {"coordinates":[-84.38305800000001,33.862392],"type":"Point"}
}