{
  "type": "Feature",
  "properties": {
    "addr:full":"352 Crosland Scooterville Rd Omega GA 31775",
    "addr:housenumber":"352",
    "addr:postcode":"31775",
    "addr:street":"Crosland Scooterville Rd",
    "iso:country":"US",
    "sg:address":"352 Crosland Scooterville Rd",
    "sg:city":"Omega",
    "sg:classifiers":[
        {
            "category":"Home & Garden",
            "subcategory":"Garden Supply",
            "type":"Retail Goods"
        }
    ],
    "sg:phone":"+1 229 528 4583",
    "sg:postcode":"31775",
    "sg:province":"GA",
    "wof:name":"Warrior Creek Tree Farm",
    "wof:placetype":"venue"
},
  "geometry": {"coordinates":[-83.646748,31.318696],"type":"Point"}
}