{
  "type": "Feature",
  "properties": {
    "addr:full":"355 Canton Rd Cumming GA 30040",
    "addr:housenumber":"355",
    "addr:postcode":"30040",
    "addr:street":"Canton Rd",
    "iso:country":"US",
    "sg:address":"355 Canton Rd",
    "sg:city":"Cumming",
    "sg:classifiers":[
        {
            "category":"Utilities",
            "subcategory":"Mobile Phone",
            "type":"Services"
        },
        {
            "category":"Utilities",
            "subcategory":"Telephone",
            "type":"Services"
        },
        {
            "category":"Manufacturing",
            "subcategory":"Electronics",
            "type":"Manufacturing & Wholesale Goods"
        }
    ],
    "sg:phone":"+1 770 888 9166",
    "sg:postcode":"30040",
    "sg:province":"GA",
    "sg:tags":[
        "telecommunications-equipment",
        "supply",
        "communication",
        "system",
        "wireless",
        "equipment"
    ],
    "wof:name":"Sky Wireless",
    "wof:placetype":"venue"
},
  "geometry": {"coordinates":[-84.145776,34.214208],"type":"Point"}
}