{
  "type": "Feature",
  "properties": {
    "addr:full":"4001 Presidential Pkwy Doraville GA 30340",
    "addr:housenumber":"4001",
    "addr:postcode":"30340",
    "addr:street":"Presidential Pkwy",
    "iso:country":"US",
    "sg:address":"4001 Presidential Pkwy",
    "sg:city":"Doraville",
    "sg:classifiers":[
        {
            "category":"Education",
            "subcategory":"Dance Studio",
            "type":"Public Place"
        }
    ],
    "sg:phone":"+1 770 216 9500",
    "sg:postcode":"30340",
    "sg:province":"GA",
    "sg:tags":[
        "ballroom"
    ],
    "sg:website":"www.cbs-atlanta.com",
    "wof:name":"Miami Entertainment",
    "wof:placetype":"venue"
},
  "geometry": {"coordinates":[-84.25798399999999,33.888798],"type":"Point"}
}