{
  "type": "Feature",
  "properties": {
    "addr:full":"508 Hillcrest Industrial Blvd Macon GA 31204",
    "addr:housenumber":"508",
    "addr:postcode":"31204",
    "addr:street":"Hillcrest Industrial Blvd",
    "iso:country":"US",
    "sg:address":"508 Hillcrest Industrial Blvd",
    "sg:city":"Macon",
    "sg:classifiers":[
        {
            "category":"Food & Beverages",
            "subcategory":"Groceries & Convenience Stores",
            "type":"Retail Goods"
        }
    ],
    "sg:phone":"+1 478 742 6393",
    "sg:postcode":"31204",
    "sg:province":"GA",
    "sg:tags":[
        "grocer"
    ],
    "wof:name":"Mini-Food Stores Inc",
    "wof:placetype":"venue"
},
  "geometry": {"coordinates":[-83.67280700000001,32.845824],"type":"Point"}
}