{
  "type": "Feature",
  "properties": {
    "addr:full":"3404 Buena Vista Rd Columbus GA 31906",
    "addr:housenumber":"3404",
    "addr:postcode":"31906",
    "addr:street":"Buena Vista Rd",
    "iso:country":"US",
    "sg:address":"3404 Buena Vista Rd",
    "sg:city":"Columbus",
    "sg:classifiers":[
        {
            "category":"Personal",
            "subcategory":"Beauty Salon",
            "type":"Services"
        }
    ],
    "sg:phone":"+1 706 689 3100",
    "sg:postcode":"31906",
    "sg:province":"GA",
    "wof:name":"Tracey's World Of Beauty",
    "wof:placetype":"venue"
},
  "geometry": {"coordinates":[-84.938289,32.455068],"type":"Point"}
}