{
  "type": "Feature",
  "properties": {
    "iso:country":"US",
    "sg:address":"2929 Panthersville Rd",
    "sg:city":"Decatur",
    "sg:classifiers":[
        {
            "category":"Freight",
            "type":"Transportation"
        }
    ],
    "sg:phone":"+1 404 822 6508",
    "sg:postcode":"30034",
    "sg:province":"GA",
    "sg:tags":[
        "mover"
    ],
    "wof:name":"MMG Moving & Storage Svc Inc",
    "wof:placetype":"venue"
},
  "geometry": {"coordinates":[-84.270712,33.69981],"type":"Point"}
}