{
  "type": "Feature",
  "properties": {
    "iso:country":"US",
    "sg:address":"568 N Fairground St NE",
    "sg:city":"Marietta",
    "sg:classifiers":[
        {
            "category":"Social Services",
            "subcategory":"Child Care",
            "type":"Services"
        }
    ],
    "sg:phone":"+1 770 428 1625",
    "sg:postcode":"30060",
    "sg:province":"GA",
    "sg:tags":[
        "day"
    ],
    "wof:name":"Kidz Palace Academy",
    "wof:placetype":"venue"
},
  "geometry": {"coordinates":[-84.53673999999999,33.964958],"type":"Point"}
}