{
  "type": "Feature",
  "properties": {
    "addr:full":"5035 Cowan Rd Acworth GA 30101",
    "addr:housenumber":"5035",
    "addr:postcode":"30101",
    "addr:street":"Cowan Rd",
    "iso:country":"US",
    "sg:address":"5035 Cowan Rd",
    "sg:city":"Acworth",
    "sg:classifiers":[
        {
            "category":"Travel",
            "subcategory":"Hotels & Motels",
            "type":"Entertainment"
        }
    ],
    "sg:phone":"+1 770 974 1700",
    "sg:postcode":"30101",
    "sg:province":"GA",
    "wof:name":"Days Inn",
    "wof:placetype":"venue"
},
  "geometry": {"coordinates":[-84.654601,34.074965],"type":"Point"}
}