{
  "type": "Feature",
  "properties": {
    "addr:full":"700 S Main St Swainsboro GA 30401",
    "addr:housenumber":"700",
    "addr:postcode":"30401",
    "addr:street":"S Main St",
    "iso:country":"US",
    "sg:address":"700 S Main St",
    "sg:city":"Swainsboro",
    "sg:classifiers":[
        {
            "category":"Autos & Motor Vehicles",
            "subcategory":"Automobile Sales",
            "type":"Retail Goods"
        }
    ],
    "sg:phone":"+1 478 237 5736",
    "sg:postcode":"30401",
    "sg:province":"GA",
    "sg:tags":[
        "new",
        "used",
        "dealer",
        "car"
    ],
    "wof:name":"Georgia Chrysler Dodge Jeep",
    "wof:placetype":"venue"
},
  "geometry": {"coordinates":[-82.316597,32.577281],"type":"Point"}
}