{
  "type": "Feature",
  "properties": {
    "iso:country":"US",
    "sg:address":"102 7th St N",
    "sg:city":"Cordele",
    "sg:classifiers":[
        {
            "category":"Shopping",
            "subcategory":"Clothing, Apparel, & Fashions",
            "type":"Retail Goods"
        }
    ],
    "sg:phone":"+1 229 273 4876",
    "sg:postcode":"31015",
    "sg:province":"GA",
    "sg:tags":[
        "alteration"
    ],
    "wof:name":"Fancy Stitchin",
    "wof:placetype":"venue"
},
  "geometry": {"coordinates":[-83.782601,31.969578],"type":"Point"}
}