{
  "type": "Feature",
  "properties": {
    "iso:country":"US",
    "sg:address":"725 Ga Highway 96",
    "sg:city":"Bonaire",
    "sg:classifiers":[
        {
            "category":"Real Estate",
            "subcategory":"Real Estate Operator",
            "type":"Services"
        }
    ],
    "sg:phone":"+1 478 988 1315",
    "sg:postcode":"31005",
    "sg:province":"GA",
    "sg:tags":[
        "apartment"
    ],
    "sg:website":"www.sandiaeast.com",
    "wof:name":"Sandia East Apartments",
    "wof:placetype":"venue"
},
  "geometry": {"coordinates":[-83.65450300000001,32.5546],"type":"Point"}
}