{
  "type": "Feature",
  "properties": {
    "addr:full":"506 Fair Rd Statesboro GA 30458",
    "addr:housenumber":"506",
    "addr:postcode":"30458",
    "addr:street":"Fair Rd",
    "iso:country":"US",
    "sg:address":"506 Fair Rd",
    "sg:city":"Statesboro",
    "sg:classifiers":[
        {
            "category":"Banks & Credit Unions",
            "subcategory":"Bank",
            "type":"Services"
        }
    ],
    "sg:phone":"+1 912 764 0258",
    "sg:postcode":"30458",
    "sg:province":"GA",
    "sg:tags":[
        "state",
        "commercial"
    ],
    "wof:name":"BB&T",
    "wof:placetype":"venue"
},
  "geometry": {"coordinates":[-81.782003,32.434415],"type":"Point"}
}