{
  "type": "Feature",
  "properties": {
    "iso:country":"US",
    "sg:address":"1 Ravinia Dr",
    "sg:city":"Atlanta",
    "sg:classifiers":[
        {
            "category":"Professional",
            "subcategory":"Lawyer & Legal Services",
            "type":"Services"
        }
    ],
    "sg:phone":"+1 404 658 8009",
    "sg:postcode":"30346",
    "sg:province":"GA",
    "wof:name":"Edge J Dexter Jr Atty",
    "wof:placetype":"venue"
},
  "geometry": {"coordinates":[-84.33609800000001,33.919601],"type":"Point"}
}