{
  "type": "Feature",
  "properties": {
    "iso:country":"US",
    "sg:address":"400 Falling Leaf Ct",
    "sg:city":"Mc Donough",
    "sg:classifiers":[
        {
            "category":"Shopping",
            "type":"Retail Goods"
        }
    ],
    "sg:phone":"+1 678 432 8565",
    "sg:postcode":"30253",
    "sg:province":"GA",
    "sg:tags":[
        "merchandise"
    ],
    "wof:name":"Plaque Center",
    "wof:placetype":"venue"
},
  "geometry": {"coordinates":[-84.149029,33.455773],"type":"Point"}
}