{
  "type": "Feature",
  "properties": {
    "iso:country":"US",
    "sg:address":"7042 Moon Rd",
    "sg:city":"Columbus",
    "sg:classifiers":[
        {
            "category":"Restaurant",
            "type":"Food & Drink"
        }
    ],
    "sg:menulink":"http://www.allmenus.com/ga/columbus/67793-foxs-pizza-den/menu/",
    "sg:phone":"+1 706 653 8500",
    "sg:postcode":"31909",
    "sg:province":"GA",
    "sg:tags":[
        "american",
        "pizza"
    ],
    "wof:name":"Fox's Pizza Den",
    "wof:placetype":"venue"
},
  "geometry": {"coordinates":[-84.927015,32.545287],"type":"Point"}
}