{
  "type": "Feature",
  "properties": {
    "iso:country":"US",
    "sg:address":"22660 Main St",
    "sg:city":"Shady Dale",
    "sg:classifiers":[
        {
            "category":"Manufacturing",
            "subcategory":"Wood Products",
            "type":"Manufacturing & Wholesale Goods"
        }
    ],
    "sg:phone":"+1 706 468 6518",
    "sg:postcode":"31085",
    "sg:province":"GA",
    "sg:tags":[
        "pallet",
        "skid"
    ],
    "wof:name":"Champion Lumber Co",
    "wof:placetype":"venue"
},
  "geometry": {"coordinates":[-83.58801699999999,33.401694],"type":"Point"}
}