{
  "type": "Feature",
  "properties": {
    "iso:country":"US",
    "sg:address":"1180 W Peachtree Street NW Suite 820",
    "sg:city":"Atlanta",
    "sg:classifiers":[
        {
            "category":"Professional",
            "subcategory":"Lawyer & Legal Services",
            "type":"Services"
        }
    ],
    "sg:phone":"+1 404 253 6975",
    "sg:postcode":"30309",
    "sg:province":"GA",
    "wof:name":"Melarti Claus D Atty",
    "wof:placetype":"venue"
},
  "geometry": {"coordinates":[-84.387816,33.786997],"type":"Point"}
}