{
  "type": "Feature",
  "properties": {
    "addr:full":"3520 Downing St Cumming GA 30066",
    "addr:housenumber":"3520",
    "addr:postcode":"30066",
    "addr:street":"Downing St",
    "iso:country":"US",
    "sg:address":"3520 Downing St",
    "sg:city":"Cumming",
    "sg:classifiers":[
        {
            "category":"Building & Trades",
            "subcategory":"Construction",
            "type":"Services"
        }
    ],
    "sg:phone":"+1 770 887 0783",
    "sg:postcode":"30066",
    "sg:province":"GA",
    "sg:tags":[
        "home",
        "builder"
    ],
    "wof:name":"Beazer Homes",
    "wof:placetype":"venue"
},
  "geometry": {"coordinates":[-84.488567,34.03609],"type":"Point"}
}