{
  "type": "Feature",
  "properties": {
    "iso:country":"US",
    "sg:address":"6765 Peachtree Industrial Blvd",
    "sg:city":"Atlanta",
    "sg:classifiers":[
        {
            "category":"Wholesale",
            "subcategory":"Office Equipment",
            "type":"Manufacturing & Wholesale Goods"
        },
        {
            "category":"Shopping",
            "subcategory":"Clothing, Apparel, & Fashions",
            "type":"Retail Goods"
        }
    ],
    "sg:phone":"+1 770 903 4606",
    "sg:postcode":"30360",
    "sg:province":"GA",
    "sg:tags":[
        "uniforms-manufacturers",
        "uniform"
    ],
    "wof:name":"Hispanic Business Solutions",
    "wof:placetype":"venue"
},
  "geometry": {"coordinates":[-84.268281,33.929171],"type":"Point"}
}