{
  "type": "Feature",
  "properties": {
    "iso:country":"US",
    "sg:address":"500 Pharr Rd NE",
    "sg:city":"Atlanta",
    "sg:phone":"+1 404 237 2941",
    "sg:postcode":"30305",
    "sg:province":"GA",
    "wof:name":"Pricci",
    "wof:placetype":"venue"
},
  "geometry": {"coordinates":[-84.371033,33.83699],"type":"Point"}
}