{
  "type": "Feature",
  "properties": {
    "iso:country":"US",
    "sg:address":"200 Market Place",
    "sg:city":"Roswell",
    "sg:classifiers":[
        {
            "category":"Personal",
            "subcategory":"Beauty Salon",
            "type":"Services"
        }
    ],
    "sg:phone":"+1 404 953 1212",
    "sg:postcode":"30076",
    "sg:province":"GA",
    "sg:tags":[
        "spa"
    ],
    "sg:website":"www.smilebright.info",
    "wof:name":"Smile Bright Teeth Whitening",
    "wof:placetype":"venue"
},
  "geometry": {"coordinates":[-84.33883899999999,34.029522],"type":"Point"}
}