{
  "type": "Feature",
  "properties": {
    "addr:full":"11991 Colerain Rd St Marys GA 31558",
    "addr:housenumber":"11991",
    "addr:postcode":"31558",
    "addr:street":"Colerain Rd",
    "iso:country":"US",
    "sg:address":"11991 Colerain Rd",
    "sg:city":"St Marys",
    "sg:classifiers":[
        {
            "category":"Insurance",
            "subcategory":"Insurance Agent",
            "type":"Services"
        }
    ],
    "sg:phone":"+1 912 673 7200",
    "sg:postcode":"31558",
    "sg:province":"GA",
    "wof:name":"Geico Corp",
    "wof:placetype":"venue"
},
  "geometry": {"coordinates":[-81.579718,30.769758],"type":"Point"}
}