{
  "type": "Feature",
  "properties": {
    "iso:country":"US",
    "sg:address":"3600 Frederica Rd",
    "sg:city":"Saint Simons Island",
    "sg:classifiers":[
        {
            "category":"Food & Beverages",
            "subcategory":"Liquor & Beverages",
            "type":"Retail Goods"
        }
    ],
    "sg:phone":"+1 912 638 8610",
    "sg:postcode":"31522",
    "sg:province":"GA",
    "sg:tags":[
        "alcoholic"
    ],
    "wof:name":"19th Hole",
    "wof:placetype":"venue"
},
  "geometry": {"coordinates":[-81.37679900000001,31.189132],"type":"Point"}
}