{
  "type": "Feature",
  "properties": {
    "addr:full":"113 W Water St Bainbridge GA 39817",
    "addr:housenumber":"113",
    "addr:postcode":"39817",
    "addr:street":"W Water St",
    "iso:country":"US",
    "sg:address":"113 W Water St",
    "sg:city":"Bainbridge",
    "sg:classifiers":[
        {
            "category":"Restaurant",
            "type":"Food & Drink"
        }
    ],
    "sg:phone":"+1 229 243 0505",
    "sg:postcode":"39817",
    "sg:province":"GA",
    "sg:tags":[
        "eating"
    ],
    "wof:name":"Royal Palm Cafe",
    "wof:placetype":"venue"
},
  "geometry": {"coordinates":[-84.577207,30.906495],"type":"Point"}
}