{
  "type": "Feature",
  "properties": {
    "addr:full":"2923 Argyle Dr NW Atlanta GA 30318",
    "addr:housenumber":"2923",
    "addr:postcode":"30318",
    "addr:street":"Argyle Dr Nw",
    "iso:country":"US",
    "sg:address":"2923 Argyle Dr NW",
    "sg:city":"Atlanta",
    "sg:classifiers":[
        {
            "category":"Building & Trades",
            "subcategory":"Locksmith",
            "type":"Services"
        }
    ],
    "sg:phone":"+1 404 682 1824",
    "sg:postcode":"30318",
    "sg:province":"GA",
    "sg:tags":[
        "key"
    ],
    "wof:name":"1 1 24 Hour Any Locksmith",
    "wof:placetype":"venue"
},
  "geometry": {"coordinates":[-84.483143,33.800333],"type":"Point"}
}