{
  "type": "Feature",
  "properties": {
    "addr:full":"1848 Thompson Bridge Rd Gainesville GA 30501",
    "addr:housenumber":"1848",
    "addr:postcode":"30501",
    "addr:street":"Thompson Bridge Rd",
    "iso:country":"US",
    "sg:address":"1848 Thompson Bridge Rd",
    "sg:city":"Gainesville",
    "sg:classifiers":[
        {
            "category":"Building & Trades",
            "subcategory":"Construction",
            "type":"Services"
        }
    ],
    "sg:phone":"+1 770 536 5003",
    "sg:postcode":"30501",
    "sg:province":"GA",
    "sg:tags":[
        "maker",
        "cabinet"
    ],
    "wof:name":"Northeast Ga Cabinets & Tops",
    "wof:placetype":"venue"
},
  "geometry": {"coordinates":[-83.836967,34.328251],"type":"Point"}
}