{
  "type": "Feature",
  "properties": {
    "addr:full":"1070 Chasewood Trl Alpharetta GA 30005",
    "addr:housenumber":"1070",
    "addr:postcode":"30005",
    "addr:street":"Chasewood Trl",
    "iso:country":"US",
    "sg:address":"1070 Chasewood Trl",
    "sg:city":"Alpharetta",
    "sg:classifiers":[
        {
            "category":"Shopping",
            "subcategory":"Computers & Home Electronics",
            "type":"Retail Goods"
        },
        {
            "category":"Professional",
            "subcategory":"Computer Services",
            "type":"Services"
        }
    ],
    "sg:phone":"+1 770 569 7545",
    "sg:postcode":"30005",
    "sg:province":"GA",
    "sg:tags":[
        "development",
        "software"
    ],
    "sg:website":"www.creativesoftworx.com",
    "wof:name":"Creative Softworx Inc",
    "wof:placetype":"venue"
},
  "geometry": {"coordinates":[-84.21475599999999,34.094066],"type":"Point"}
}