{
  "type": "Feature",
  "properties": {
    "addr:full":"3628 Kimbrough Pt Douglasville GA 30135",
    "addr:housenumber":"3628",
    "addr:postcode":"30135",
    "addr:street":"Kimbrough Pt",
    "iso:country":"US",
    "sg:address":"3628 Kimbrough Pt",
    "sg:city":"Douglasville",
    "sg:classifiers":[
        {
            "category":"Building & Trades",
            "subcategory":"Equipment Rental",
            "type":"Services"
        }
    ],
    "sg:phone":"+1 770 577 9698",
    "sg:postcode":"30135",
    "sg:province":"GA",
    "sg:tags":[
        "supply",
        "contractor"
    ],
    "wof:name":"N. W. Howell & Associates",
    "wof:placetype":"venue"
},
  "geometry": {"coordinates":[-84.72350299999999,33.708121],"type":"Point"}
}