{
  "type": "Feature",
  "properties": {
    "addr:full":"1035 Peachtree Industrial Blvd Suwanee GA 30024",
    "addr:housenumber":"1035",
    "addr:postcode":"30024",
    "addr:street":"Peachtree Industrial Blvd",
    "iso:country":"US",
    "sg:address":"1035 Peachtree Industrial Blvd",
    "sg:city":"Suwanee",
    "sg:classifiers":[
        {
            "category":"Fast Food",
            "type":"Food & Drink"
        }
    ],
    "sg:phone":"+1 770 831 1177",
    "sg:postcode":"30024",
    "sg:province":"GA",
    "sg:tags":[
        "chicken",
        "wing"
    ],
    "sg:website":"www.chick-fil-a.com",
    "wof:name":"Chick-Fil-A",
    "wof:placetype":"venue"
},
  "geometry": {"coordinates":[-84.09051700000001,34.051103],"type":"Point"}
}