{
  "type": "Feature",
  "properties": {
    "iso:country":"US",
    "sg:address":"1860 Austin Dr",
    "sg:city":"Decatur",
    "sg:classifiers":[
        {
            "category":"Autos & Motor Vehicles",
            "subcategory":"Auto Supplies",
            "type":"Retail Goods"
        }
    ],
    "sg:phone":"+1 404 534 0403",
    "sg:postcode":"30032",
    "sg:province":"GA",
    "sg:tags":[
        "automobile",
        "used"
    ],
    "wof:name":"Top E Motors Inc",
    "wof:placetype":"venue"
},
  "geometry": {"coordinates":[-84.234196,33.735511],"type":"Point"}
}