{
  "type": "Feature",
  "properties": {
    "addr:full":"4165 Bemiss Rd Valdosta GA 31605",
    "addr:housenumber":"4165",
    "addr:postcode":"31605",
    "addr:street":"Bemiss Rd",
    "iso:country":"US",
    "sg:address":"4165 Bemiss Rd",
    "sg:city":"Valdosta",
    "sg:classifiers":[
        {
            "category":"Restaurant",
            "type":"Food & Drink"
        }
    ],
    "sg:menulink":"http://www.allmenus.com/ga/barretts/72268-bucks-pizza/menu/",
    "sg:phone":"+1 229 249 5112",
    "sg:postcode":"31605",
    "sg:province":"GA",
    "sg:tags":[
        "american",
        "wing",
        "pizza"
    ],
    "wof:name":"Buck's Pizza",
    "wof:placetype":"venue"
},
  "geometry": {"coordinates":[-83.255138,30.918922],"type":"Point"}
}