{
  "type": "Feature",
  "properties": {
    "iso:country":"US",
    "sg:address":"630 Grove Pkwy",
    "sg:city":"Marietta",
    "sg:classifiers":[
        {
            "category":"Building & Trades",
            "subcategory":"Construction",
            "type":"Services"
        }
    ],
    "sg:phone":"+1 770 612 9960",
    "sg:postcode":"30067",
    "sg:province":"GA",
    "sg:tags":[
        "concrete",
        "contractor"
    ],
    "wof:name":"Hemma Concrete & Pavers",
    "wof:placetype":"venue"
},
  "geometry": {"coordinates":[-84.46911,33.935378],"type":"Point"}
}