{
  "type": "Feature",
  "properties": {
    "addr:full":"4430 Myrtle Hill Rd NE Kennesaw GA 30144",
    "addr:housenumber":"4430",
    "addr:postcode":"30144",
    "addr:street":"Myrtle Hill Rd Ne",
    "iso:country":"US",
    "sg:address":"4430 Myrtle Hill Rd NE",
    "sg:city":"Kennesaw",
    "sg:classifiers":[
        {
            "category":"Professional",
            "subcategory":"Computer Services",
            "type":"Services"
        }
    ],
    "sg:phone":"+1 770 517 8481",
    "sg:postcode":"30144",
    "sg:province":"GA",
    "sg:tags":[
        "related"
    ],
    "wof:name":"Data Matrix Systems Inc",
    "wof:placetype":"venue"
},
  "geometry": {"coordinates":[-84.550904,34.061331],"type":"Point"}
}