{
  "type": "Feature",
  "properties": {
    "iso:country":"US",
    "sg:address":"6033 Whispering Pines Dr",
    "sg:city":"Buford",
    "sg:classifiers":[
        {
            "category":"Building & Trades",
            "subcategory":"Cleaning & Sanitation",
            "type":"Services"
        }
    ],
    "sg:phone":"+1 770 932 6940",
    "sg:postcode":"30518",
    "sg:province":"GA",
    "sg:tags":[
        "carpet"
    ],
    "wof:name":"Carpet Image",
    "wof:placetype":"venue"
},
  "geometry": {"coordinates":[-83.95522200000001,34.137638],"type":"Point"}
}