{
  "type": "Feature",
  "properties": {
    "iso:country":"US",
    "sg:address":"1655 Mclendon Ave NE",
    "sg:city":"Atlanta",
    "sg:classifiers":[
        {
            "category":"Cafe",
            "type":"Food & Drink"
        },
        {
            "category":"Restaurant",
            "type":"Food & Drink"
        }
    ],
    "sg:menulink":"http://www.allmenus.com/ga/atlanta-decatur/113999-the-flying-biscuit-cafe/menu/",
    "sg:phone":"+1 404 687 8888",
    "sg:postcode":"30307",
    "sg:province":"GA",
    "sg:tags":[
        "wrap",
        "american",
        "sandwich",
        "salad"
    ],
    "wof:name":"The Flying Biscuit Cafe",
    "wof:placetype":"venue"
},
  "geometry": {"coordinates":[-84.33334000000001,33.764847],"type":"Point"}
}