{
  "type": "Feature",
  "properties": {
    "addr:full":"415 Pine Ave Ste 101 Albany GA 31701",
    "addr:housenumber":"415",
    "addr:postcode":"31701",
    "addr:street":"Pine Ave Ste 101",
    "iso:country":"US",
    "sg:address":"415 Pine Ave Ste 101",
    "sg:city":"Albany",
    "sg:classifiers":[
        {
            "category":"Professional",
            "subcategory":"Lawyer & Legal Services",
            "type":"Services"
        }
    ],
    "sg:phone":"+1 229 883 5556",
    "sg:postcode":"31701",
    "sg:province":"GA",
    "sg:tags":[
        "attorney",
        "practice",
        "worker",
        "benefit",
        "labor",
        "compensation",
        "employee",
        "law",
        "employment"
    ],
    "wof:name":"Mathis Billy C Jr",
    "wof:placetype":"venue"
},
  "geometry": {"coordinates":[-84.156413,31.578448],"type":"Point"}
}