{
  "type": "Feature",
  "properties": {
    "iso:country":"US",
    "sg:address":"1046 W College St Exd",
    "sg:city":"Griffin",
    "sg:classifiers":[
        {
            "category":"Restaurant",
            "type":"Food & Drink"
        }
    ],
    "sg:phone":"+1 770 233 6808",
    "sg:postcode":"30224",
    "sg:province":"GA",
    "sg:tags":[
        "eating"
    ],
    "wof:name":"Taste Buds Presents",
    "wof:placetype":"venue"
},
  "geometry": {"coordinates":[-84.279563,33.243855],"type":"Point"}
}