{
  "type": "Feature",
  "properties": {
    "iso:country":"US",
    "sg:address":"240 E Belle Isle Rd NE",
    "sg:city":"Atlanta",
    "sg:classifiers":[
        {
            "category":"Professional",
            "subcategory":"Computer Services",
            "type":"Services"
        }
    ],
    "sg:phone":"+1 404 250 1787",
    "sg:postcode":"30342",
    "sg:province":"GA",
    "sg:tags":[
        "graphics"
    ],
    "wof:name":"Mayos Electronic Prepress",
    "wof:placetype":"venue"
},
  "geometry": {"coordinates":[-84.37922399999999,33.890608],"type":"Point"}
}