{
  "type": "Feature",
  "properties": {
    "addr:full":"3519 Kindling Dr Augusta GA 30906",
    "addr:housenumber":"3519",
    "addr:postcode":"30906",
    "addr:street":"Kindling Dr",
    "iso:country":"US",
    "sg:address":"3519 Kindling Dr",
    "sg:city":"Augusta",
    "sg:classifiers":[
        {
            "category":"Professional",
            "type":"Services"
        }
    ],
    "sg:phone":"+1 706 792 1433",
    "sg:postcode":"30906",
    "sg:province":"GA",
    "wof:name":"Helen Dashiells",
    "wof:placetype":"venue"
},
  "geometry": {"coordinates":[-82.062682,33.412743],"type":"Point"}
}