{
  "type": "Feature",
  "properties": {
    "addr:full":"63 Blackberry Creek Dr Carrollton GA 30116",
    "addr:housenumber":"63",
    "addr:postcode":"30116",
    "addr:street":"Blackberry Creek Dr",
    "iso:country":"US",
    "sg:address":"63 Blackberry Creek Dr",
    "sg:city":"Carrollton",
    "sg:classifiers":[
        {
            "category":"Building & Trades",
            "subcategory":"Construction",
            "type":"Services"
        }
    ],
    "sg:phone":"+1 770 838 1082",
    "sg:postcode":"30116",
    "sg:province":"GA",
    "sg:tags":[
        "carpentry",
        "contractor"
    ],
    "wof:name":"Donald Woods",
    "wof:placetype":"venue"
},
  "geometry": {"coordinates":[-84.965228,33.629255],"type":"Point"}
}