{
  "type": "Feature",
  "properties": {
    "iso:country":"US",
    "sg:address":"71 Price Quarters Rd",
    "sg:city":"Mcdonough",
    "sg:classifiers":[
        {
            "category":"Personal",
            "subcategory":"Tanning Parlor",
            "type":"Services"
        }
    ],
    "sg:phone":"+1 678 432 9191",
    "sg:postcode":"30253",
    "sg:province":"GA",
    "sg:tags":[
        "salon"
    ],
    "wof:name":"Solaris Tan Ctr",
    "wof:placetype":"venue"
},
  "geometry": {"coordinates":[-84.14714499999999,33.508891],"type":"Point"}
}