{
  "type": "Feature",
  "properties": {
    "addr:full":"1833 Clifton Road NE Atlanta GA 30329",
    "addr:housenumber":"1833",
    "addr:postcode":"30329",
    "addr:street":"Clifton Road Ne",
    "iso:country":"US",
    "sg:address":"1833 Clifton Road NE",
    "sg:city":"Atlanta",
    "sg:classifiers":[
        {
            "category":"Health Services",
            "subcategory":"Doctor",
            "type":"Services"
        }
    ],
    "sg:phone":"+1 404 728 6363",
    "sg:postcode":"30329",
    "sg:province":"GA",
    "sg:tags":[
        "dermatologist"
    ],
    "wof:name":"Lipton Cathy MD",
    "wof:placetype":"venue"
},
  "geometry": {"coordinates":[-84.33357599999999,33.803375],"type":"Point"}
}