{
  "type": "Feature",
  "properties": {
    "addr:full":"3324 S Dixie Rd Dalton GA 30720",
    "addr:housenumber":"3324",
    "addr:postcode":"30720",
    "addr:street":"S Dixie Rd",
    "iso:country":"US",
    "sg:address":"3324 S Dixie Rd",
    "sg:city":"Dalton",
    "sg:classifiers":[
        {
            "category":"Manufacturing",
            "subcategory":"Tools & Machinery",
            "type":"Manufacturing & Wholesale Goods"
        }
    ],
    "sg:phone":"+1 706 370 4914",
    "sg:postcode":"30720",
    "sg:province":"GA",
    "sg:tags":[
        "machine",
        "shop",
        "industrial",
        "mfg"
    ],
    "wof:name":"Stark's Custom Machinery Inc",
    "wof:placetype":"venue"
},
  "geometry": {"coordinates":[-84.985418,34.702503],"type":"Point"}
}