{
  "type": "Feature",
  "properties": {
    "iso:country":"US",
    "sg:address":"6776 Covington Hwy",
    "sg:city":"Lithonia",
    "sg:classifiers":[
        {
            "category":"Real Estate",
            "subcategory":"Real Estate Operator",
            "type":"Services"
        }
    ],
    "sg:phone":"+1 770 981 8268",
    "sg:postcode":"30058",
    "sg:province":"GA",
    "sg:tags":[
        "apartment"
    ],
    "wof:name":"Hampton Woods",
    "wof:placetype":"venue"
},
  "geometry": {"coordinates":[-84.14069600000001,33.717011],"type":"Point"}
}