{
  "type": "Feature",
  "properties": {
    "iso:country":"US",
    "sg:address":"1080 Upper Hembree Rd",
    "sg:city":"Roswell",
    "sg:classifiers":[
        {
            "category":"Building & Trades",
            "subcategory":"Construction",
            "type":"Services"
        }
    ],
    "sg:phone":"+1 770 442 9912",
    "sg:postcode":"30076",
    "sg:province":"GA",
    "sg:tags":[
        "house"
    ],
    "wof:name":"Millen Associates",
    "wof:placetype":"venue"
},
  "geometry": {"coordinates":[-84.329897,34.069064],"type":"Point"}
}