{
  "type": "Feature",
  "properties": {
    "addr:full":"1838 Meredith Dr NW Atlanta GA 30318",
    "addr:housenumber":"1838",
    "addr:postcode":"30318",
    "addr:street":"Meredith Dr Nw",
    "iso:country":"US",
    "sg:address":"1838 Meredith Dr NW",
    "sg:city":"Atlanta",
    "sg:classifiers":[
        {
            "category":"Professional",
            "type":"Services"
        }
    ],
    "sg:phone":"+1 404 355 0298",
    "sg:postcode":"30318",
    "sg:province":"GA",
    "wof:name":"Ryan Dunlap",
    "wof:placetype":"venue"
},
  "geometry": {"coordinates":[-84.40422700000001,33.805307],"type":"Point"}
}