{
  "type": "Feature",
  "properties": {
    "iso:country":"US",
    "sg:address":"6170 Pointer Way",
    "sg:city":"Douglasville",
    "sg:classifiers":[
        {
            "category":"Building & Trades",
            "subcategory":"Construction",
            "type":"Services"
        }
    ],
    "sg:phone":"+1 770 942 0492",
    "sg:postcode":"30135",
    "sg:province":"GA",
    "sg:tags":[
        "flooring",
        "contractor"
    ],
    "wof:name":"Peachy Clean Carpet Care",
    "wof:placetype":"venue"
},
  "geometry": {"coordinates":[-84.777737,33.710368],"type":"Point"}
}