{
  "type": "Feature",
  "properties": {
    "addr:full":"8351 Roswell Rd Atlanta GA 30350",
    "addr:housenumber":"8351",
    "addr:postcode":"30350",
    "addr:street":"Roswell Rd",
    "iso:country":"US",
    "sg:address":"8351 Roswell Rd",
    "sg:city":"Atlanta",
    "sg:classifiers":[
        {
            "category":"Restaurant",
            "type":"Food & Drink"
        }
    ],
    "sg:phone":"+1 770 645 5700",
    "sg:postcode":"30350",
    "sg:province":"GA",
    "sg:tags":[
        "pizza"
    ],
    "wof:name":"Little Caesars",
    "wof:placetype":"venue"
},
  "geometry": {"coordinates":[-84.350335,33.982604],"type":"Point"}
}