{
  "type": "Feature",
  "properties": {
    "iso:country":"US",
    "sg:address":"712 Avenue A NE",
    "sg:city":"Rome",
    "sg:classifiers":[
        {
            "category":"Travel",
            "subcategory":"Hotels & Motels",
            "type":"Entertainment"
        },
        {
            "category":"Travel",
            "subcategory":"Bed & Breakfast",
            "type":"Entertainment"
        }
    ],
    "sg:phone":"+1 706 314 1115",
    "sg:postcode":"30165",
    "sg:province":"GA",
    "sg:tags":[
        "inn",
        "lodging"
    ],
    "wof:name":"Country Hearth Inn & Suites",
    "wof:placetype":"venue"
},
  "geometry": {"coordinates":[-85.17368999999999,34.262228],"type":"Point"}
}