{
  "type": "Feature",
  "properties": {
    "iso:country":"US",
    "sg:address":"5815 Rex Mill Dr",
    "sg:city":"Rex",
    "sg:classifiers":[
        {
            "category":"Real Estate",
            "subcategory":"Real Estate Agent",
            "type":"Services"
        }
    ],
    "sg:phone":"+1 678 284 1090",
    "sg:postcode":"30273",
    "sg:province":"GA",
    "sg:tags":[
        "investment"
    ],
    "wof:name":"One Family Ventures LLC",
    "wof:placetype":"venue"
},
  "geometry": {"coordinates":[-84.26667999999999,33.596454],"type":"Point"}
}