{
  "type": "Feature",
  "properties": {
    "addr:full":"442 Lincoln St Savannah GA 31401",
    "addr:housenumber":"442",
    "addr:postcode":"31401",
    "addr:street":"Lincoln St",
    "iso:country":"US",
    "sg:address":"442 Lincoln St",
    "sg:city":"Savannah",
    "sg:classifiers":[
        {
            "category":"Professional",
            "subcategory":"Secretarial Services",
            "type":"Services"
        }
    ],
    "sg:phone":"+1 912 233 1883",
    "sg:postcode":"31401",
    "sg:province":"GA",
    "sg:tags":[
        "convention",
        "court",
        "reporter"
    ],
    "wof:name":"Tom Crites & Assoc",
    "wof:placetype":"venue"
},
  "geometry": {"coordinates":[-81.09152400000001,32.069926],"type":"Point"}
}