{
  "type": "Feature",
  "properties": {
    "addr:full":"2116 Hiram Acworth Hwy Dallas GA 30157",
    "addr:housenumber":"2116",
    "addr:postcode":"30157",
    "addr:street":"Hiram Acworth Hwy",
    "iso:country":"US",
    "sg:address":"2116 Hiram Acworth Hwy",
    "sg:city":"Dallas",
    "sg:classifiers":[
        {
            "category":"Building & Trades",
            "subcategory":"Construction",
            "type":"Services"
        }
    ],
    "sg:phone":"+1 678 363 5277",
    "sg:postcode":"30157",
    "sg:province":"GA",
    "sg:tags":[
        "designer",
        "contractor",
        "merchandise",
        "dealer",
        "pool",
        "swimming"
    ],
    "wof:name":"Brown's Pools & Spas",
    "wof:placetype":"venue"
},
  "geometry": {"coordinates":[-84.746258,33.922376],"type":"Point"}
}