{
  "type": "Feature",
  "properties": {
    "iso:country":"US",
    "sg:address":"Lindbergh Plaza 2581 Piedmont Rd",
    "sg:city":"Atlanta",
    "sg:classifiers":[
        {
            "category":"Restaurant",
            "type":"Food & Drink"
        }
    ],
    "sg:phone":"+1 404 869 9215",
    "sg:postcode":"30324",
    "sg:province":"GA",
    "sg:tags":[
        "diner"
    ],
    "sg:website":"www.wafflehouse.com/",
    "wof:name":"Waffle House",
    "wof:placetype":"venue"
},
  "geometry": {"coordinates":[-84.365988,33.825097],"type":"Point"}
}