{
  "type": "Feature",
  "properties": {
    "iso:country":"US",
    "sg:address":"150 Griffin Dr",
    "sg:city":"Carrollton",
    "sg:classifiers":[
        {
            "category":"Wholesale",
            "subcategory":"Durable Goods & Equipment",
            "type":"Manufacturing & Wholesale Goods"
        }
    ],
    "sg:phone":"+1 770 834 9793",
    "sg:postcode":"30117",
    "sg:province":"GA",
    "sg:tags":[
        "representative",
        "manufacturer"
    ],
    "wof:name":"D & S Ind Sales Inc",
    "wof:placetype":"venue"
},
  "geometry": {"coordinates":[-85.093549,33.570684],"type":"Point"}
}