{
  "type": "Feature",
  "properties": {
    "addr:full":"1163 Johnson Ferry Rd Ste 100 Marietta GA 30068",
    "addr:housenumber":"1163",
    "addr:postcode":"30068",
    "addr:street":"Johnson Ferry Rd Ste 100",
    "iso:country":"US",
    "sg:address":"1163 Johnson Ferry Rd Ste 100",
    "sg:city":"Marietta",
    "sg:classifiers":[
        {
            "category":"Health Services",
            "subcategory":"Doctor",
            "type":"Services"
        }
    ],
    "sg:phone":"+1 770 321 0155",
    "sg:postcode":"30068",
    "sg:province":"GA",
    "sg:tags":[
        "medicine",
        "sport",
        "orthopedist"
    ],
    "wof:name":"Neurosport Physical Therapy and Rhblttn Spclst Inc",
    "wof:placetype":"venue"
},
  "geometry": {"coordinates":[-84.437202,33.9715],"type":"Point"}
}