{
  "type": "Feature",
  "properties": {
    "addr:full":"6043 N Henry Blvd Stockbridge GA 30281",
    "addr:housenumber":"6043",
    "addr:postcode":"30281",
    "addr:street":"N Henry Blvd",
    "iso:country":"US",
    "sg:address":"6043 N Henry Blvd",
    "sg:city":"Stockbridge",
    "sg:classifiers":[
        {
            "category":"Organizations",
            "subcategory":"Religious Organization",
            "type":"Services"
        }
    ],
    "sg:phone":"+1 770 474 9092",
    "sg:postcode":"30281",
    "sg:province":"GA",
    "sg:tags":[
        "church"
    ],
    "wof:name":"Salvation Christian Ctr",
    "wof:placetype":"venue"
},
  "geometry": {"coordinates":[-84.25997700000001,33.557241],"type":"Point"}
}