{
  "type": "Feature",
  "properties": {
    "addr:full":"925 Desoto Ave Rome GA 30165",
    "addr:housenumber":"925",
    "addr:postcode":"ga 30165",
    "addr:street":"Desoto Ave",
    "iso:country":"US",
    "sg:address":"925 Desoto Ave",
    "sg:city":"Rome",
    "sg:classifiers":[
        {
            "category":"Retail",
            "subcategory":"Auto Repair",
            "type":"Services"
        }
    ],
    "sg:phone":"+1 706 291 1609",
    "sg:postcode":"30165",
    "sg:province":"GA",
    "sg:tags":[
        "wrecker"
    ],
    "wof:name":"Bishop's Wrecker Svc",
    "wof:placetype":"venue"
},
  "geometry": {"coordinates":[-85.18265,34.262546],"type":"Point"}
}