{
  "type": "Feature",
  "properties": {
    "addr:full":"3655 Gurley Dr Columbus GA 31904",
    "addr:housenumber":"3655",
    "addr:postcode":"31904",
    "addr:street":"Gurley Dr",
    "iso:country":"US",
    "sg:address":"3655 Gurley Dr",
    "sg:city":"Columbus",
    "sg:classifiers":[
        {
            "category":"Health Services",
            "subcategory":"Clinic",
            "type":"Services"
        },
        {
            "category":"Social Services",
            "type":"Services"
        }
    ],
    "sg:phone":"+1 706 641 9914",
    "sg:postcode":"31904",
    "sg:province":"GA",
    "sg:tags":[
        "home",
        "senior",
        "citizen",
        "care"
    ],
    "wof:name":"Home Instead Senior Care",
    "wof:placetype":"venue"
},
  "geometry": {"coordinates":[-84.955848,32.500578],"type":"Point"}
}