{
  "type": "Feature",
  "properties": {
    "addr:full":"12180 Wexford Club Dr Roswell GA 30075",
    "addr:housenumber":"12180",
    "addr:postcode":"30075",
    "addr:street":"Wexford Club Dr",
    "iso:country":"US",
    "sg:address":"12180 Wexford Club Dr",
    "sg:city":"Roswell",
    "sg:classifiers":[
        {
            "category":"Building & Trades",
            "subcategory":"Construction",
            "type":"Services"
        }
    ],
    "sg:phone":"+1 770 645 8542",
    "sg:postcode":"30075",
    "sg:province":"GA",
    "sg:tags":[
        "carpentry",
        "contractor"
    ],
    "wof:name":"Lane Collier Carpentry",
    "wof:placetype":"venue"
},
  "geometry": {"coordinates":[-84.374199,34.076424],"type":"Point"}
}