{
  "type": "Feature",
  "properties": {
    "iso:country":"US",
    "sg:address":"771 Shallowford Rd NE",
    "sg:city":"Kennesaw",
    "sg:classifiers":[
        {
            "category":"Professional",
            "type":"Services"
        }
    ],
    "sg:phone":"+1 770 569 2070",
    "sg:postcode":"30144",
    "sg:province":"GA",
    "sg:tags":[
        "establishment"
    ],
    "wof:name":"Innovative Digital Imaging",
    "wof:placetype":"venue"
},
  "geometry": {"coordinates":[-84.526454,34.067806],"type":"Point"}
}