{
  "type": "Feature",
  "properties": {
    "iso:country":"US",
    "sg:address":"3283 Chamblee Dunwoody Rd",
    "sg:city":"Atlanta",
    "sg:classifiers":[
        {
            "category":"Travel",
            "subcategory":"Travel Agent",
            "type":"Entertainment"
        }
    ],
    "sg:phone":"+1 770 457 8566",
    "sg:postcode":"30341",
    "sg:province":"GA",
    "sg:tags":[
        "agency",
        "gift"
    ],
    "wof:name":"Sukhuthai Travel",
    "wof:placetype":"venue"
},
  "geometry": {"coordinates":[-84.29333699999999,33.891868],"type":"Point"}
}