{
  "type": "Feature",
  "properties": {
    "addr:full":"7611 Houston Rd Byron GA 31008",
    "addr:housenumber":"7611",
    "addr:postcode":"31008",
    "addr:street":"Houston Rd",
    "iso:country":"US",
    "sg:address":"7611 Houston Rd",
    "sg:city":"Byron",
    "sg:classifiers":[
        {
            "category":"Wholesale",
            "subcategory":"Auto Parts",
            "type":"Manufacturing & Wholesale Goods"
        }
    ],
    "sg:phone":"+1 478 788 4918",
    "sg:postcode":"31008",
    "sg:province":"GA",
    "sg:tags":[
        "automobile",
        "rebuilt"
    ],
    "wof:name":"Bob's Auto Salvage Inc",
    "wof:placetype":"venue"
},
  "geometry": {"coordinates":[-83.70189499999999,32.681987],"type":"Point"}
}