{
  "type": "Feature",
  "properties": {
    "iso:country":"US",
    "sg:address":"60 Bear Creek Marina Dr",
    "sg:city":"Mansfield",
    "sg:classifiers":[
        {
            "category":"Restaurant",
            "type":"Food & Drink"
        }
    ],
    "sg:phone":"+1 770 787 9621",
    "sg:postcode":"30055",
    "sg:province":"GA",
    "sg:tags":[
        "style",
        "family"
    ],
    "wof:name":"Bear Creek Marina & Restaurant",
    "wof:placetype":"venue"
},
  "geometry": {"coordinates":[-83.81926199999999,33.419211],"type":"Point"}
}