{
  "type": "Feature",
  "properties": {
    "addr:full":"2224 Thompson Bridge Rd Gainesville GA 30501",
    "addr:housenumber":"2224",
    "addr:postcode":"30501",
    "addr:street":"Thompson Bridge Rd",
    "iso:country":"US",
    "sg:address":"2224 Thompson Bridge Rd",
    "sg:city":"Gainesville",
    "sg:classifiers":[
        {
            "category":"Restaurant",
            "type":"Food & Drink"
        }
    ],
    "sg:menulink":"http://www.allmenus.com/ga/gainesville/80818-papa-johns-pizza/menu/",
    "sg:phone":"+1 770 297 7474",
    "sg:postcode":"30501",
    "sg:province":"GA",
    "sg:tags":[
        "american",
        "pizza"
    ],
    "wof:name":"Papa John's Pizza",
    "wof:placetype":"venue"
},
  "geometry": {"coordinates":[-83.843395,34.334524],"type":"Point"}
}