{
  "type": "Feature",
  "properties": {
    "addr:full":"4429 Skidaway Rd Savannah GA 31404",
    "addr:housenumber":"4429",
    "addr:postcode":"31404",
    "addr:street":"Skidaway Rd",
    "iso:country":"US",
    "sg:address":"4429 Skidaway Rd",
    "sg:city":"Savannah",
    "sg:classifiers":[
        {
            "category":"Bars & Pubs",
            "type":"Food & Drink"
        }
    ],
    "sg:phone":"+1 912 353 7573",
    "sg:postcode":"31404",
    "sg:province":"GA",
    "sg:tags":[
        "drinking"
    ],
    "wof:name":"Old Memories Lounge & Rest",
    "wof:placetype":"venue"
},
  "geometry": {"coordinates":[-81.07040499999999,32.028189],"type":"Point"}
}