{
  "type": "Feature",
  "properties": {
    "iso:country":"US",
    "sg:address":"3887 Highway 138 SE",
    "sg:city":"Stockbridge",
    "sg:classifiers":[
        {
            "category":"Restaurant",
            "type":"Food & Drink"
        }
    ],
    "sg:phone":"+1 770 389 5422",
    "sg:postcode":"30281",
    "sg:province":"GA",
    "sg:website":"www.tacobell.com",
    "wof:name":"Taco Bell",
    "wof:placetype":"venue"
},
  "geometry": {"coordinates":[-84.2593,33.553299],"type":"Point"}
}