{
  "type": "Feature",
  "properties": {
    "iso:country":"US",
    "sg:address":"4756 Bemiss Rd",
    "sg:city":"Valdosta",
    "sg:classifiers":[
        {
            "category":"Sports & Exercise",
            "subcategory":"Swimming Pool",
            "type":"Entertainment"
        }
    ],
    "sg:phone":"+1 229 630 4864",
    "sg:postcode":"31605",
    "sg:province":"GA",
    "wof:name":"Mulligan Pools",
    "wof:placetype":"venue"
},
  "geometry": {"coordinates":[-83.242859,30.93342],"type":"Point"}
}