{
  "type": "Feature",
  "properties": {
    "iso:country":"US",
    "sg:address":"35 Yorktown Ave",
    "sg:city":"Hampton",
    "sg:classifiers":[
        {
            "category":"Freight",
            "type":"Transportation"
        }
    ],
    "sg:phone":"+1 770 946 4890",
    "sg:postcode":"30228",
    "sg:province":"GA",
    "sg:tags":[
        "operator",
        "trucking"
    ],
    "wof:name":"Ronny Cox Trucking",
    "wof:placetype":"venue"
},
  "geometry": {"coordinates":[-84.296121,33.39717],"type":"Point"}
}