{
  "type": "Feature",
  "properties": {
    "iso:country":"US",
    "sg:address":"54 Merganser Way",
    "sg:city":"Woodbine",
    "sg:classifiers":[
        {
            "category":"Professional",
            "type":"Services"
        }
    ],
    "sg:phone":"+1 912 673 7617",
    "sg:postcode":"31569",
    "sg:province":"GA",
    "wof:name":"J Sloop",
    "wof:placetype":"venue"
},
  "geometry": {"coordinates":[-81.623527,30.860403],"type":"Point"}
}