{
  "type": "Feature",
  "properties": {
    "iso:country":"US",
    "sg:address":"3745 Hickory Pl SE",
    "sg:city":"Smyrna",
    "sg:classifiers":[
        {
            "category":"Professional",
            "subcategory":"Employment Agencies",
            "type":"Services"
        }
    ],
    "sg:phone":"+1 770 434 1870",
    "sg:postcode":"30080",
    "sg:province":"GA",
    "sg:tags":[
        "opportunity"
    ],
    "wof:name":"Cosmos Placements Inc",
    "wof:placetype":"venue"
},
  "geometry": {"coordinates":[-84.508698,33.862598],"type":"Point"}
}