{
  "type": "Feature",
  "properties": {
    "iso:country":"US",
    "sg:address":"1690 Cobb Xing SE",
    "sg:city":"Smyrna",
    "sg:classifiers":[
        {
            "category":"Travel",
            "subcategory":"Travel Agent",
            "type":"Entertainment"
        }
    ],
    "sg:phone":"+1 770 984 0637",
    "sg:postcode":"30080",
    "sg:province":"GA",
    "sg:tags":[
        "agency",
        "bureau"
    ],
    "wof:name":"Going Places Travel Intl",
    "wof:placetype":"venue"
},
  "geometry": {"coordinates":[-84.491218,33.836057],"type":"Point"}
}