{
  "type": "Feature",
  "properties": {
    "iso:country":"US",
    "sg:address":"1810 Hudson Bridge Rd",
    "sg:city":"Stockbridge",
    "sg:classifiers":[
        {
            "category":"Banks & Credit Unions",
            "subcategory":"Financial Services",
            "type":"Services"
        }
    ],
    "sg:phone":"+1 770 389 8012",
    "sg:postcode":"30281",
    "sg:province":"GA",
    "sg:tags":[
        "broker",
        "mortgage"
    ],
    "wof:name":"First Metro Mortgage",
    "wof:placetype":"venue"
},
  "geometry": {"coordinates":[-84.245796,33.500401],"type":"Point"}
}