{
  "type": "Feature",
  "properties": {
    "iso:country":"US",
    "sg:address":"1975 County Line Rd NW",
    "sg:city":"Acworth",
    "sg:classifiers":[
        {
            "category":"Building & Trades",
            "subcategory":"Electrical",
            "type":"Services"
        }
    ],
    "sg:phone":"+1 770 795 0240",
    "sg:postcode":"30101",
    "sg:province":"GA",
    "sg:tags":[
        "electrical",
        "contractor"
    ],
    "wof:name":"Electric Service Specialist",
    "wof:placetype":"venue"
},
  "geometry": {"coordinates":[-84.721739,34.003539],"type":"Point"}
}