{
  "type": "Feature",
  "properties": {
    "addr:full":"2525 Sandy Plains Rd Marietta GA 30066",
    "addr:housenumber":"2525",
    "addr:postcode":"30066",
    "addr:street":"Sandy Plains Rd",
    "iso:country":"US",
    "sg:address":"2525 Sandy Plains Rd",
    "sg:city":"Marietta",
    "sg:classifiers":[
        {
            "category":"Education",
            "subcategory":"School",
            "type":"Public Place"
        }
    ],
    "sg:phone":"+1 770 578 3200",
    "sg:postcode":"30066",
    "sg:province":"GA",
    "sg:website":"www.sprayberry.org",
    "wof:name":"Sprayberry High School",
    "wof:placetype":"venue"
},
  "geometry": {"coordinates":[-84.489475,34.020546],"type":"Point"}
}