{
  "type": "Feature",
  "properties": {
    "iso:country":"US",
    "sg:address":"4633 Vermack Pl",
    "sg:city":"Dunwoody",
    "sg:classifiers":[
        {
            "category":"Professional",
            "subcategory":"Advertising",
            "type":"Services"
        }
    ],
    "sg:phone":"+1 770 350 0943",
    "sg:postcode":"30338",
    "sg:province":"GA",
    "sg:tags":[
        "marketing"
    ],
    "wof:name":"mirj media consulting",
    "wof:placetype":"venue"
},
  "geometry": {"coordinates":[-84.314671,33.932194],"type":"Point"}
}