{
  "type": "Feature",
  "properties": {
    "iso:country":"US",
    "sg:address":"5415 Preserve Cir",
    "sg:city":"Alpharetta",
    "sg:classifiers":[
        {
            "category":"Restaurant",
            "type":"Food & Drink"
        }
    ],
    "sg:phone":"+1 770 664 5979",
    "sg:postcode":"30005",
    "sg:province":"GA",
    "sg:tags":[
        "eating"
    ],
    "wof:name":"Working It Out",
    "wof:placetype":"venue"
},
  "geometry": {"coordinates":[-84.189159,34.084284],"type":"Point"}
}