{
  "type": "Feature",
  "properties": {
    "iso:country":"US",
    "sg:address":"1135 Pinehurst Trl",
    "sg:city":"Grayson",
    "sg:classifiers":[
        {
            "category":"Insurance",
            "subcategory":"Insurance Agent",
            "type":"Services"
        }
    ],
    "sg:phone":"+1 770 736 0620",
    "sg:postcode":"30017",
    "sg:province":"GA",
    "wof:name":"Affordable Ins Educators",
    "wof:placetype":"venue"
},
  "geometry": {"coordinates":[-83.978342,33.880396],"type":"Point"}
}