{
  "type": "Feature",
  "properties": {
    "addr:full":"2833 Peachtree Industrial Blvd Duluth GA 30097",
    "addr:housenumber":"2833",
    "addr:postcode":"30097",
    "addr:street":"Peachtree Industrial Blvd",
    "iso:country":"US",
    "sg:address":"2833 Peachtree Industrial Blvd",
    "sg:city":"Duluth",
    "sg:classifiers":[
        {
            "category":"Sports & Exercise",
            "subcategory":"Golf",
            "type":"Entertainment"
        }
    ],
    "sg:phone":"+1 770 497 9265",
    "sg:postcode":"30097",
    "sg:province":"GA",
    "sg:tags":[
        "range",
        "practice"
    ],
    "wof:name":"Peachtree Golf Centers",
    "wof:placetype":"venue"
},
  "geometry": {"coordinates":[-84.147154,34.023072],"type":"Point"}
}