{
  "type": "Feature",
  "properties": {
    "addr:full":"110 Camilla Ct Fairburn GA 30213",
    "addr:housenumber":"110",
    "addr:postcode":"30213",
    "addr:street":"Camilla Ct",
    "iso:country":"US",
    "sg:address":"110 Camilla Ct",
    "sg:city":"Fairburn",
    "sg:classifiers":[
        {
            "category":"Banks & Credit Unions",
            "subcategory":"Bank",
            "type":"Services"
        }
    ],
    "sg:phone":"+1 404 222 0503",
    "sg:postcode":"30213",
    "sg:province":"GA",
    "sg:tags":[
        "personal",
        "short",
        "institution",
        "business"
    ],
    "wof:name":"Bridge Financial Group Inc",
    "wof:placetype":"venue"
},
  "geometry": {"coordinates":[-84.4679,33.531718],"type":"Point"}
}