{
  "type": "Feature",
  "properties": {
    "iso:country":"US",
    "sg:address":"2192 State Rte 20",
    "sg:city":"Grayson",
    "sg:classifiers":[
        {
            "category":"Banks & Credit Unions",
            "subcategory":"Bank",
            "type":"Services"
        }
    ],
    "sg:phone":"+1 770 513 4400",
    "sg:postcode":"30017",
    "sg:province":"GA",
    "sg:tags":[
        "broker",
        "mortgage"
    ],
    "wof:name":"L W Keith and Associates Inc",
    "wof:placetype":"venue"
},
  "geometry": {"coordinates":[-83.952546,33.892796],"type":"Point"}
}