{
  "type": "Feature",
  "properties": {
    "iso:country":"US",
    "sg:address":"332 Dylan Way",
    "sg:city":"Mc Donough",
    "sg:classifiers":[
        {
            "category":"Building & Trades",
            "subcategory":"Cleaning & Sanitation",
            "type":"Services"
        }
    ],
    "sg:phone":"+1 678 432 6444",
    "sg:postcode":"30252",
    "sg:province":"GA",
    "sg:tags":[
        "maintenance"
    ],
    "wof:name":"Toss Sweep Enterprises",
    "wof:placetype":"venue"
},
  "geometry": {"coordinates":[-84.01613500000001,33.426524],"type":"Point"}
}