{
  "type": "Feature",
  "properties": {
    "addr:full":"97 Lake Dow Rd Mcdonough GA 30252",
    "addr:housenumber":"97",
    "addr:postcode":"30252",
    "addr:street":"Lake Dow Rd",
    "iso:country":"US",
    "sg:address":"97 Lake Dow Rd",
    "sg:city":"Mcdonough",
    "sg:classifiers":[
        {
            "category":"Food & Beverages",
            "subcategory":"Farmers Market",
            "type":"Retail Goods"
        }
    ],
    "sg:phone":"+1 770 288 8421",
    "sg:postcode":"30252",
    "sg:province":"GA",
    "sg:tags":[
        "vegetable",
        "fruit"
    ],
    "wof:name":"Henry County",
    "wof:placetype":"venue"
},
  "geometry": {"coordinates":[-84.121568,33.440106],"type":"Point"}
}