{
  "type": "Feature",
  "properties": {
    "addr:full":"2050 Lumpkin Rd Augusta GA 30906",
    "addr:housenumber":"2050",
    "addr:postcode":"30906",
    "addr:street":"Lumpkin Rd",
    "iso:country":"US",
    "sg:address":"2050 Lumpkin Rd",
    "sg:city":"Augusta",
    "sg:classifiers":[
        {
            "category":"Shopping",
            "subcategory":"Clothing, Apparel, & Fashions",
            "type":"Retail Goods"
        }
    ],
    "sg:phone":"+1 706 771 1155",
    "sg:postcode":"30906",
    "sg:province":"GA",
    "sg:tags":[
        "navy",
        "army"
    ],
    "wof:name":"Sergeant Major's Bunker",
    "wof:placetype":"venue"
},
  "geometry": {"coordinates":[-82.022143,33.418621],"type":"Point"}
}