{
  "type": "Feature",
  "properties": {
    "iso:country":"US",
    "sg:address":"1326 Roberts Dr SE",
    "sg:city":"Atlanta",
    "sg:classifiers":[
        {
            "category":"Real Estate",
            "subcategory":"Real Estate Operator",
            "type":"Services"
        }
    ],
    "sg:phone":"+1 404 627 9955",
    "sg:postcode":"30315",
    "sg:province":"GA",
    "sg:tags":[
        "building",
        "apartment"
    ],
    "wof:name":"Gladstone Apartments",
    "wof:placetype":"venue"
},
  "geometry": {"coordinates":[-84.37004399999999,33.720529],"type":"Point"}
}