{
  "type": "Feature",
  "properties": {
    "addr:full":"1717 Connolly Dr NW Kennesaw GA 30144",
    "addr:housenumber":"1717",
    "addr:postcode":"30144",
    "addr:street":"Connolly Dr Nw",
    "iso:country":"US",
    "sg:address":"1717 Connolly Dr NW",
    "sg:city":"Kennesaw",
    "sg:classifiers":[
        {
            "category":"Retail",
            "subcategory":"Repair Shop",
            "type":"Services"
        }
    ],
    "sg:phone":"+1 770 590 0812",
    "sg:postcode":"30144",
    "sg:province":"GA",
    "wof:name":"Metropolitan Fiberglass Repair",
    "wof:placetype":"venue"
},
  "geometry": {"coordinates":[-84.57276299999999,34.045631],"type":"Point"}
}