{
  "type": "Feature",
  "properties": {
    "addr:full":"5011 Georgia Highway 85 Forest Park GA 30297",
    "addr:housenumber":"5011",
    "addr:postcode":"30297",
    "addr:street":"Georgia Highway 85;Park",
    "iso:country":"US",
    "sg:address":"5011 Georgia Highway 85",
    "sg:city":"Forest Park",
    "sg:classifiers":[
        {
            "category":"Autos & Motor Vehicles",
            "subcategory":"Auto Supplies",
            "type":"Retail Goods"
        }
    ],
    "sg:phone":"+1 404 767 3232",
    "sg:postcode":"30297",
    "sg:province":"GA",
    "sg:tags":[
        "glass"
    ],
    "wof:name":"Above All Glass & Glazing",
    "wof:placetype":"venue"
},
  "geometry": {"coordinates":[-84.40242499999999,33.618864],"type":"Point"}
}