{
  "type": "Feature",
  "properties": {
    "addr:full":"270 Ben Lane Rd Garfield GA 30425",
    "addr:housenumber":"270",
    "addr:postcode":"30425",
    "addr:street":"Ben Lane Rd",
    "iso:country":"US",
    "sg:address":"270 Ben Lane Rd",
    "sg:city":"Garfield",
    "sg:classifiers":[
        {
            "category":"Farming",
            "subcategory":"Farm",
            "type":"Manufacturing & Wholesale Goods"
        }
    ],
    "sg:phone":"+1 478 763 2742",
    "sg:postcode":"30425",
    "sg:province":"GA",
    "sg:tags":[
        "crop",
        "general"
    ],
    "wof:name":"Linus Robinson",
    "wof:placetype":"venue"
},
  "geometry": {"coordinates":[-82.045087,32.593675],"type":"Point"}
}