{
  "type": "Feature",
  "properties": {
    "addr:full":"12005 Fox Rd Alpharetta GA 30005",
    "addr:housenumber":"12005",
    "addr:postcode":"30005",
    "addr:street":"Fox Rd",
    "iso:country":"US",
    "sg:address":"12005 Fox Rd",
    "sg:city":"Alpharetta",
    "sg:classifiers":[
        {
            "category":"Professional",
            "subcategory":"Management & Consulting",
            "type":"Services"
        }
    ],
    "sg:phone":"+1 770 664 5008",
    "sg:postcode":"30005",
    "sg:province":"GA",
    "wof:name":"Franklin Brooke & Spence Inc",
    "wof:placetype":"venue"
},
  "geometry": {"coordinates":[-84.21486299999999,34.072147],"type":"Point"}
}