{
  "type": "Feature",
  "properties": {
    "addr:full":"4095 Dollar Cir Suwanee GA 30024",
    "addr:housenumber":"4095",
    "addr:postcode":"30024",
    "addr:street":"Dollar Cir",
    "iso:country":"US",
    "sg:address":"4095 Dollar Cir",
    "sg:city":"Suwanee",
    "sg:classifiers":[
        {
            "category":"Building & Trades",
            "subcategory":"Construction",
            "type":"Services"
        }
    ],
    "sg:phone":"+1 770 945 8303",
    "sg:postcode":"30024",
    "sg:province":"GA",
    "sg:tags":[
        "concrete",
        "contractor"
    ],
    "wof:name":"Mudslingers Inc",
    "wof:placetype":"venue"
},
  "geometry": {"coordinates":[-84.059923,34.06266],"type":"Point"}
}