{
  "type": "Feature",
  "properties": {
    "iso:country":"US",
    "sg:address":"185 E Hancock Ave",
    "sg:city":"Athens",
    "sg:classifiers":[
        {
            "category":"Place Of Worship",
            "subcategory":"Church",
            "type":"Public Place"
        },
        {
            "category":"Place Of Worship",
            "type":"Public Place"
        }
    ],
    "sg:phone":"+1 706 543 4338",
    "sg:postcode":"30601",
    "sg:province":"GA",
    "sg:tags":[
        "churches-presbyterian",
        "churches-presbyterian-usa"
    ],
    "sg:website":"http://www.athensfirstpres.com",
    "wof:name":"First Presbyterian Church",
    "wof:placetype":"venue"
},
  "geometry": {"coordinates":[-83.376385,33.960066],"type":"Point"}
}