{
  "type": "Feature",
  "properties": {
    "iso:country":"US",
    "sg:address":"2880 Johnson Ferry Rd",
    "sg:city":"Marietta",
    "sg:classifiers":[
        {
            "category":"Professional",
            "type":"Services"
        }
    ],
    "sg:phone":"+1 770 321 2366",
    "sg:postcode":"30062",
    "sg:province":"GA",
    "sg:tags":[
        "establishment"
    ],
    "wof:name":"Premier Financial Group",
    "wof:placetype":"venue"
},
  "geometry": {"coordinates":[-84.428724,34.017871],"type":"Point"}
}