{
  "type": "Feature",
  "properties": {
    "iso:country":"US",
    "sg:address":"45 Ashlee Ct",
    "sg:city":"Stockbridge",
    "sg:classifiers":[
        {
            "category":"Building & Trades",
            "subcategory":"Construction",
            "type":"Services"
        }
    ],
    "sg:phone":"+1 770 474 7676",
    "sg:postcode":"30281",
    "sg:province":"GA",
    "sg:tags":[
        "house",
        "builder",
        "operative"
    ],
    "wof:name":"B Montgomery Builders Inc",
    "wof:placetype":"venue"
},
  "geometry": {"coordinates":[-84.251065,33.506683],"type":"Point"}
}