{
  "type": "Feature",
  "properties": {
    "iso:country":"US",
    "sg:address":"1628 Amity Woodlawn Rd",
    "sg:city":"Lincolnton",
    "sg:classifiers":[
        {
            "category":"Wholesale",
            "subcategory":"Painting Supplies",
            "type":"Manufacturing & Wholesale Goods"
        },
        {
            "category":"Home & Garden",
            "subcategory":"Building Materials",
            "type":"Retail Goods"
        },
        {
            "category":"Building & Trades",
            "subcategory":"Construction",
            "type":"Services"
        }
    ],
    "sg:phone":"+1 706 359 5836",
    "sg:postcode":"30817",
    "sg:province":"GA",
    "sg:tags":[
        "wallcoverings-installation",
        "wallpaper",
        "wallcoverings",
        "paint",
        "contractor"
    ],
    "wof:name":"A & R Paint Co Inc",
    "wof:placetype":"venue"
},
  "geometry": {"coordinates":[-82.45779400000001,33.697197],"type":"Point"}
}