{
  "type": "Feature",
  "properties": {
    "addr:full":"245 Riviera Dr Carrollton GA 30116",
    "addr:housenumber":"245",
    "addr:postcode":"30116",
    "addr:street":"Riviera Dr",
    "iso:country":"US",
    "sg:address":"245 Riviera Dr",
    "sg:city":"Carrollton",
    "sg:classifiers":[
        {
            "category":"Organizations",
            "subcategory":"Religious Organization",
            "type":"Services"
        }
    ],
    "sg:phone":"+1 770 832 3426",
    "sg:postcode":"30116",
    "sg:province":"GA",
    "wof:name":"Anointed Call Ministries Inc",
    "wof:placetype":"venue"
},
  "geometry": {"coordinates":[-85.01487,33.597179],"type":"Point"}
}