{
  "type": "Feature",
  "properties": {
    "addr:full":"300 Tower Rd NE Marietta GA 30060",
    "addr:housenumber":"300",
    "addr:postcode":"30060",
    "addr:street":"Tower Rd Ne",
    "iso:country":"US",
    "sg:address":"300 Tower Rd NE",
    "sg:city":"Marietta",
    "sg:classifiers":[
        {
            "category":"Health Services",
            "subcategory":"Doctor",
            "type":"Services"
        }
    ],
    "sg:phone":"+1 770 427 5717",
    "sg:postcode":"30060",
    "sg:province":"GA",
    "sg:tags":[
        "orthopedist"
    ],
    "wof:name":"Bender Jay MD",
    "wof:placetype":"venue"
},
  "geometry": {"coordinates":[-84.554885,33.970527],"type":"Point"}
}