{
  "type": "Feature",
  "properties": {
    "iso:country":"US",
    "sg:address":"1724 State Rte 81",
    "sg:city":"Loganville",
    "sg:classifiers":[
        {
            "category":"Wholesale",
            "subcategory":"Auto Parts",
            "type":"Manufacturing & Wholesale Goods"
        }
    ],
    "sg:phone":"+1 770 466 1060",
    "sg:postcode":"30052",
    "sg:province":"GA",
    "sg:tags":[
        "tire"
    ],
    "wof:name":"Toby Sexton Tire Co",
    "wof:placetype":"venue"
},
  "geometry": {"coordinates":[-83.851201,33.760567],"type":"Point"}
}