{
  "type": "Feature",
  "properties": {
    "iso:country":"US",
    "sg:address":"1112 Bankhead Hwy",
    "sg:city":"Carrollton",
    "sg:classifiers":[
        {
            "category":"Banks & Credit Unions",
            "subcategory":"Bank",
            "type":"Services"
        },
        {
            "category":"Banks & Credit Unions",
            "subcategory":"Financial Services",
            "type":"Services"
        }
    ],
    "sg:phone":"+1 770 214 5409",
    "sg:postcode":"30117",
    "sg:province":"GA",
    "sg:tags":[
        "commercial",
        "loan",
        "saving"
    ],
    "sg:website":"http://www.suntrustbank.com",
    "wof:name":"SunTrust Bank",
    "wof:placetype":"venue"
},
  "geometry": {"coordinates":[-85.04193100000001,33.59383],"type":"Point"}
}