{
  "type": "Feature",
  "properties": {
    "addr:full":"322 E Mccarty St Sandersville GA 31082",
    "addr:housenumber":"322",
    "addr:postcode":"31082",
    "addr:street":"E Mccarty St",
    "iso:country":"US",
    "sg:address":"322 E Mccarty St",
    "sg:city":"Sandersville",
    "sg:classifiers":[
        {
            "category":"Retail",
            "subcategory":"Auto Repair",
            "type":"Services"
        }
    ],
    "sg:phone":"+1 478 553 0500",
    "sg:postcode":"31082",
    "sg:province":"GA",
    "sg:tags":[
        "body",
        "painting",
        "repairing",
        "automobile"
    ],
    "wof:name":"Seals Car Shop",
    "wof:placetype":"venue"
},
  "geometry": {"coordinates":[-82.80688600000001,32.988754],"type":"Point"}
}