{
  "type": "Feature",
  "properties": {
    "addr:full":"72 Spring St SW Atlanta GA 30303",
    "addr:housenumber":"72",
    "addr:postcode":"30303",
    "addr:street":"Spring St Sw",
    "iso:country":"US",
    "sg:address":"72 Spring St SW",
    "sg:city":"Atlanta",
    "sg:classifiers":[
        {
            "category":"Banks & Credit Unions",
            "subcategory":"Atm",
            "type":"Services"
        }
    ],
    "sg:phone":"+1 888 552 8180",
    "sg:postcode":"30303",
    "sg:province":"GA",
    "sg:tags":[
        "bankruptcy"
    ],
    "sg:website":"www.atlantabankruptcylawinfo.com/",
    "wof:name":"Law Offices of Michael R. Rethinger",
    "wof:placetype":"venue"
},
  "geometry": {"coordinates":[-84.39551,33.752566],"type":"Point"}
}