{
  "type": "Feature",
  "properties": {
    "addr:full":"2930 River Ridge Dr SW Atlanta GA 30354",
    "addr:housenumber":"2930",
    "addr:postcode":"30354",
    "addr:street":"River Ridge Dr Sw",
    "iso:country":"US",
    "sg:address":"2930 River Ridge Dr SW",
    "sg:city":"Atlanta",
    "sg:classifiers":[
        {
            "category":"Personal",
            "subcategory":"Beauty Salon",
            "type":"Services"
        }
    ],
    "sg:phone":"+1 404 366 2032",
    "sg:postcode":"30354",
    "sg:province":"GA",
    "sg:tags":[
        "shop"
    ],
    "wof:name":"Braidery Ect",
    "wof:placetype":"venue"
},
  "geometry": {"coordinates":[-84.380853,33.675026],"type":"Point"}
}