{
  "type": "Feature",
  "properties": {
    "addr:full":"3244 Craig Dr Duluth GA 30096",
    "addr:housenumber":"3244",
    "addr:postcode":"30096",
    "addr:street":"Craig Dr",
    "iso:country":"US",
    "sg:address":"3244 Craig Dr",
    "sg:city":"Duluth",
    "sg:classifiers":[
        {
            "category":"Professional",
            "subcategory":"Art Services",
            "type":"Services"
        }
    ],
    "sg:phone":"+1 770 622 9534",
    "sg:postcode":"30096",
    "sg:province":"GA",
    "sg:tags":[
        "designer",
        "display",
        "producer"
    ],
    "wof:name":"Digital Design Concepts",
    "wof:placetype":"venue"
},
  "geometry": {"coordinates":[-84.15569000000001,34.013885],"type":"Point"}
}