{
  "type": "Feature",
  "properties": {
    "iso:country":"US",
    "sg:address":"1950 Stetham Ferry Xing",
    "sg:city":"Alpharetta",
    "sg:classifiers":[
        {
            "category":"Professional",
            "type":"Services"
        }
    ],
    "sg:phone":"+1 770 448 2084",
    "sg:postcode":"30022",
    "sg:province":"GA",
    "wof:name":"Donald H Gordon Co Inc",
    "wof:placetype":"venue"
},
  "geometry": {"coordinates":[-84.218211,34.005476],"type":"Point"}
}