{
  "type": "Feature",
  "properties": {
    "iso:country":"US",
    "sg:address":"265 Boulevard NE",
    "sg:city":"Atlanta",
    "sg:classifiers":[
        {
            "category":"Government",
            "subcategory":"Office",
            "type":"Public Place"
        }
    ],
    "sg:phone":"+1 404 730 4779",
    "sg:postcode":"30312",
    "sg:province":"GA",
    "sg:tags":[
        "parish",
        "government-county"
    ],
    "wof:name":"Fulton County Government Public Library",
    "wof:placetype":"venue"
},
  "geometry": {"coordinates":[-84.37198600000001,33.76186],"type":"Point"}
}