{
  "type": "Feature",
  "properties": {
    "addr:full":"104 Blue Ct Augusta GA 30907",
    "addr:housenumber":"104",
    "addr:postcode":"30907",
    "addr:street":"Blue Ct",
    "iso:country":"US",
    "sg:address":"104 Blue Ct",
    "sg:city":"Augusta",
    "sg:classifiers":[
        {
            "category":"Building & Trades",
            "subcategory":"Construction",
            "type":"Services"
        }
    ],
    "sg:phone":"+1 706 306 6803",
    "sg:postcode":"30907",
    "sg:province":"GA",
    "sg:tags":[
        "concrete",
        "contractor"
    ],
    "wof:name":"Absolute Quality Concrete",
    "wof:placetype":"venue"
},
  "geometry": {"coordinates":[-82.121674,33.50836],"type":"Point"}
}