{
  "type": "Feature",
  "properties": {
    "addr:full":"4265 Macon Rd Columbus GA 31907",
    "addr:housenumber":"4265",
    "addr:postcode":"31907",
    "addr:street":"Macon Rd",
    "iso:country":"US",
    "sg:address":"4265 Macon Rd",
    "sg:city":"Columbus",
    "sg:classifiers":[
        {
            "category":"Travel",
            "subcategory":"Hotels & Motels",
            "type":"Entertainment"
        }
    ],
    "sg:phone":"+1 706 561 2170",
    "sg:postcode":"31907",
    "sg:province":"GA",
    "wof:name":"Edgewood Motel",
    "wof:placetype":"venue"
},
  "geometry": {"coordinates":[-84.91827499999999,32.49046],"type":"Point"}
}