{
  "type": "Feature",
  "properties": {
    "iso:country":"US",
    "sg:address":"63 Depot St",
    "sg:city":"Hartwell",
    "sg:classifiers":[
        {
            "category":"Restaurant",
            "type":"Food & Drink"
        }
    ],
    "sg:phone":"+1 706 377 3055",
    "sg:postcode":"30643",
    "sg:province":"GA",
    "sg:tags":[
        "eating"
    ],
    "wof:name":"Downtown Cafe",
    "wof:placetype":"venue"
},
  "geometry": {"coordinates":[-82.934129,34.352037],"type":"Point"}
}