{
  "type": "Feature",
  "properties": {
    "addr:full":"3444 Waldrop Trl Decatur GA 30034",
    "addr:housenumber":"3444",
    "addr:postcode":"30034",
    "addr:street":"Waldrop Trl",
    "iso:country":"US",
    "sg:address":"3444 Waldrop Trl",
    "sg:city":"Decatur",
    "sg:classifiers":[
        {
            "category":"Real Estate",
            "subcategory":"Real Estate Services",
            "type":"Services"
        },
        {
            "category":"Building & Trades",
            "subcategory":"Cleaning & Sanitation",
            "type":"Services"
        }
    ],
    "sg:phone":"+1 678 698 5987",
    "sg:postcode":"30034",
    "sg:province":"GA",
    "sg:tags":[
        "maintenance",
        "cleaners-interior"
    ],
    "wof:name":"Superior One Cleaning Service",
    "wof:placetype":"venue"
},
  "geometry": {"coordinates":[-84.26156,33.683222],"type":"Point"}
}