{
  "type": "Feature",
  "properties": {
    "addr:full":"304 Whitehall St Washington GA 30673",
    "addr:housenumber":"304",
    "addr:postcode":"30673",
    "addr:street":"Whitehall St",
    "iso:country":"US",
    "sg:address":"304 Whitehall St",
    "sg:city":"Washington",
    "sg:classifiers":[
        {
            "category":"Organizations",
            "subcategory":"Community Association",
            "type":"Services"
        }
    ],
    "sg:phone":"+1 706 678 7671",
    "sg:postcode":"30673",
    "sg:province":"GA",
    "sg:tags":[
        "recreation",
        "civic",
        "club",
        "membership",
        "social",
        "sport"
    ],
    "wof:name":"Bookers Social Center",
    "wof:placetype":"venue"
},
  "geometry": {"coordinates":[-82.754178,33.731844],"type":"Point"}
}