{
  "type": "Feature",
  "properties": {
    "addr:full":"6441 Looper Lake Dr Flowery Branch GA 30542",
    "addr:postcode":"6441;30542",
    "addr:street":"Looper Lake Dr",
    "iso:country":"US",
    "sg:address":"6441 Looper Lake Dr",
    "sg:city":"Flowery Branch",
    "sg:classifiers":[
        {
            "category":"Building & Trades",
            "subcategory":"Landscaping Services",
            "type":"Services"
        }
    ],
    "sg:phone":"+1 770 965 2884",
    "sg:postcode":"30542",
    "sg:province":"GA",
    "wof:name":"Seasonal Scapes LLC",
    "wof:placetype":"venue"
},
  "geometry": {"coordinates":[-83.89481000000001,34.144501],"type":"Point"}
}