{
  "type": "Feature",
  "properties": {
    "iso:country":"US",
    "sg:address":"170 Woodlake Dr",
    "sg:city":"Newnan",
    "sg:classifiers":[
        {
            "category":"Building & Trades",
            "subcategory":"Plumbing",
            "type":"Services"
        }
    ],
    "sg:phone":"+1 770 254 9692",
    "sg:postcode":"30265",
    "sg:province":"GA",
    "sg:tags":[
        "plumber",
        "industrial",
        "contractors-commercial"
    ],
    "wof:name":"Nw Plumbing",
    "wof:placetype":"venue"
},
  "geometry": {"coordinates":[-84.706805,33.388622],"type":"Point"}
}