{
  "type": "Feature",
  "properties": {
    "addr:full":"502 Connell Ave SW Atlanta GA 30315",
    "addr:housenumber":"502",
    "addr:postcode":"30315",
    "addr:street":"Connell Ave Sw",
    "iso:country":"US",
    "sg:address":"502 Connell Ave SW",
    "sg:city":"Atlanta",
    "sg:classifiers":[
        {
            "category":"Professional",
            "subcategory":"Business Services",
            "type":"Services"
        }
    ],
    "sg:phone":"+1 404 767 9755",
    "sg:postcode":"30315",
    "sg:province":"GA",
    "wof:name":"Tumlin Enterprises Inc",
    "wof:placetype":"venue"
},
  "geometry": {"coordinates":[-84.405332,33.683075],"type":"Point"}
}