{
  "type": "Feature",
  "properties": {
    "addr:full":"4369 Roswell Rd Marietta GA 30062",
    "addr:housenumber":"4369",
    "addr:postcode":"30062",
    "addr:street":"Roswell Rd",
    "iso:country":"US",
    "sg:address":"4369 Roswell Rd",
    "sg:city":"Marietta",
    "sg:classifiers":[
        {
            "category":"Personal",
            "type":"Services"
        }
    ],
    "sg:phone":"+1 770 973 2109",
    "sg:postcode":"30062",
    "sg:province":"GA",
    "sg:tags":[
        "control",
        "weight"
    ],
    "wof:name":"Jenny Craig Weight Loss Ctr",
    "wof:placetype":"venue"
},
  "geometry": {"coordinates":[-84.421997,33.986364],"type":"Point"}
}