{
  "type": "Feature",
  "properties": {
    "addr:full":"786 E Broad St Athens GA 30601",
    "addr:housenumber":"786",
    "addr:postcode":"30601",
    "addr:street":"E Broad St",
    "iso:country":"US",
    "sg:address":"786 E Broad St",
    "sg:city":"Athens",
    "sg:classifiers":[
        {
            "category":"Manufacturing",
            "subcategory":"Tools & Machinery",
            "type":"Manufacturing & Wholesale Goods"
        }
    ],
    "sg:phone":"+1 706 549 1914",
    "sg:postcode":"30601",
    "sg:province":"GA",
    "sg:tags":[
        "packaging"
    ],
    "sg:website":"www.dixiecanner.com",
    "wof:name":"Dixie Canner Co",
    "wof:placetype":"venue"
},
  "geometry": {"coordinates":[-83.370186,33.958505],"type":"Point"}
}