{
  "type": "Feature",
  "properties": {
    "iso:country":"US",
    "sg:address":"5093 Buford Hwy NE",
    "sg:city":"Atlanta",
    "sg:classifiers":[
        {
            "category":"Shopping",
            "subcategory":"Bicycles & Sporting Goods",
            "type":"Retail Goods"
        }
    ],
    "sg:phone":"+1 770 451 4239",
    "sg:postcode":"30340",
    "sg:province":"GA",
    "sg:tags":[
        "firearm",
        "accessory"
    ],
    "wof:name":"Gun Store Inc",
    "wof:placetype":"venue"
},
  "geometry": {"coordinates":[-84.285347,33.890522],"type":"Point"}
}