{
  "type": "Feature",
  "properties": {
    "iso:country":"US",
    "sg:address":"4535 Scarborough Rd SW",
    "sg:city":"Atlanta",
    "sg:classifiers":[
        {
            "category":"Building & Trades",
            "subcategory":"Cleaning & Sanitation",
            "type":"Services"
        }
    ],
    "sg:phone":"+1 404 768 8574",
    "sg:postcode":"30349",
    "sg:province":"GA",
    "sg:tags":[
        "maintenance"
    ],
    "wof:name":"Housekeeping To Go",
    "wof:placetype":"venue"
},
  "geometry": {"coordinates":[-84.543617,33.627309],"type":"Point"}
}