{
  "type": "Feature",
  "properties": {
    "addr:full":"702 US Hwy 341 Barnesville GA 30204",
    "addr:housenumber":"702",
    "addr:postcode":"30204",
    "addr:street":"Us Hwy 341",
    "iso:country":"US",
    "sg:address":"702 US Hwy 341",
    "sg:city":"Barnesville",
    "sg:classifiers":[
        {
            "category":"Health Services",
            "subcategory":"Doctor",
            "type":"Services"
        }
    ],
    "sg:phone":"+1 770 358 7802",
    "sg:postcode":"30204",
    "sg:province":"GA",
    "sg:tags":[
        "physician",
        "surgeon"
    ],
    "wof:name":"Orthopaedic & Sports Injury",
    "wof:placetype":"venue"
},
  "geometry": {"coordinates":[-84.16999300000001,33.046436],"type":"Point"}
}