{
  "type": "Feature",
  "properties": {
    "addr:full":"615 E Central Ave Fitzgerald GA 31750",
    "addr:housenumber":"615",
    "addr:postcode":"31750",
    "addr:street":"E Central Ave",
    "iso:country":"US",
    "sg:address":"615 E Central Ave",
    "sg:city":"Fitzgerald",
    "sg:classifiers":[
        {
            "category":"Food & Beverages",
            "subcategory":"Liquor & Beverages",
            "type":"Retail Goods"
        }
    ],
    "sg:phone":"+1 229 423 5116",
    "sg:postcode":"31750",
    "sg:province":"GA",
    "wof:name":"Eastside Package Store",
    "wof:placetype":"venue"
},
  "geometry": {"coordinates":[-83.246422,31.714919],"type":"Point"}
}