{
  "type": "Feature",
  "properties": {
    "iso:country":"US",
    "sg:address":"4701 State Rte 15",
    "sg:city":"White Plains",
    "sg:classifiers":[
        {
            "category":"Restaurant",
            "type":"Food & Drink"
        }
    ],
    "sg:phone":"+1 706 467 1340",
    "sg:postcode":"30678",
    "sg:province":"GA",
    "sg:tags":[
        "eating"
    ],
    "wof:name":"Mithchells Fast Food",
    "wof:placetype":"venue"
},
  "geometry": {"coordinates":[-83.048945,33.510458],"type":"Point"}
}