{
  "type": "Feature",
  "properties": {
    "addr:full":"107 Johnson St Cartersville GA 30120",
    "addr:housenumber":"107",
    "addr:postcode":"30120",
    "addr:street":"Johnson St",
    "iso:country":"US",
    "sg:address":"107 Johnson St",
    "sg:city":"Cartersville",
    "sg:classifiers":[
        {
            "category":"Professional",
            "type":"Services"
        }
    ],
    "sg:phone":"+1 678 721 4000",
    "sg:postcode":"30120",
    "sg:province":"GA",
    "sg:tags":[
        "establishment"
    ],
    "wof:name":"Dispatch",
    "wof:placetype":"venue"
},
  "geometry": {"coordinates":[-84.797411,34.174216],"type":"Point"}
}