{
  "type": "Feature",
  "properties": {
    "addr:full":"145 Plantation Trce Woodstock GA 30188",
    "addr:housenumber":"145",
    "addr:postcode":"30188",
    "addr:street":"Plantation Trce",
    "iso:country":"US",
    "sg:address":"145 Plantation Trce",
    "sg:city":"Woodstock",
    "sg:classifiers":[
        {
            "category":"Shopping",
            "type":"Retail Goods"
        }
    ],
    "sg:phone":"+1 770 442 0947",
    "sg:postcode":"30188",
    "sg:province":"GA",
    "sg:tags":[
        "merchandise"
    ],
    "wof:name":"Lovettas Frames & Things",
    "wof:placetype":"venue"
},
  "geometry": {"coordinates":[-84.39068,34.125401],"type":"Point"}
}