{
  "type": "Feature",
  "properties": {
    "addr:full":"4500 Knox Bridge Hwy Canton GA 30114",
    "addr:housenumber":"4500",
    "addr:postcode":"30114",
    "addr:street":"Knox Bridge Hwy",
    "iso:country":"US",
    "sg:address":"4500 Knox Bridge Hwy",
    "sg:city":"Canton",
    "sg:classifiers":[
        {
            "category":"Building & Trades",
            "subcategory":"Electrical",
            "type":"Services"
        }
    ],
    "sg:phone":"+1 770 720 3079",
    "sg:postcode":"30114",
    "sg:province":"GA",
    "sg:tags":[
        "electrician"
    ],
    "wof:name":"R&L Electrical Contractors, Inc",
    "wof:placetype":"venue"
},
  "geometry": {"coordinates":[-84.58888,34.210818],"type":"Point"}
}