{
  "type": "Feature",
  "properties": {
    "addr:full":"408 Hurricane Shoals Rd Lawrenceville GA 30046",
    "addr:housenumber":"408",
    "addr:postcode":"30046",
    "addr:street":"Hurricane Shoals Rd",
    "iso:country":"US",
    "sg:address":"408 Hurricane Shoals Rd",
    "sg:city":"Lawrenceville",
    "sg:classifiers":[
        {
            "category":"Government",
            "subcategory":"City Hall",
            "type":"Public Place"
        }
    ],
    "sg:phone":"+1 678 518 4800",
    "sg:postcode":"30046",
    "sg:province":"GA",
    "wof:name":"Gwinnett County Dept of Fire & Emergency Services",
    "wof:placetype":"venue"
},
  "geometry": {"coordinates":[-84.00636299999999,33.966954],"type":"Point"}
}