{
  "type": "Feature",
  "properties": {
    "iso:country":"US",
    "sg:address":"4087 Spartan Ln",
    "sg:city":"Stone Mountain",
    "sg:classifiers":[
        {
            "category":"Building & Trades",
            "subcategory":"Cleaning & Sanitation",
            "type":"Services"
        }
    ],
    "sg:phone":"+1 404 299 2656",
    "sg:postcode":"30083",
    "sg:province":"GA",
    "sg:tags":[
        "house"
    ],
    "wof:name":"Gwen's Cleaning Svc",
    "wof:placetype":"venue"
},
  "geometry": {"coordinates":[-84.221898,33.804433],"type":"Point"}
}