{
  "type": "Feature",
  "properties": {
    "addr:full":"6690 Roswell Rd Sandy Springs GA 30328",
    "addr:housenumber":"6690",
    "addr:postcode":"30328",
    "addr:street":"Roswell Rd",
    "iso:country":"US",
    "sg:address":"6690 Roswell Rd",
    "sg:city":"Sandy Springs",
    "sg:classifiers":[
        {
            "category":"Restaurant",
            "type":"Food & Drink"
        }
    ],
    "sg:phone":"+1 404 257 1288",
    "sg:postcode":"30328",
    "sg:province":"GA",
    "sg:tags":[
        "japanese",
        "buffet"
    ],
    "sg:website":"www.norinori.com",
    "wof:name":"Nori Nori",
    "wof:placetype":"venue"
},
  "geometry": {"coordinates":[-84.377309,33.938245],"type":"Point"}
}