{
  "type": "Feature",
  "properties": {
    "iso:country":"US",
    "sg:address":"3909 Bemiss Rd",
    "sg:city":"Valdosta",
    "sg:classifiers":[
        {
            "category":"Place Of Worship",
            "type":"Public Place"
        },
        {
            "category":"Organizations",
            "subcategory":"Religious Organization",
            "type":"Services"
        }
    ],
    "sg:phone":"+1 229 244 6824",
    "sg:postcode":"31605",
    "sg:province":"GA",
    "sg:tags":[
        "church"
    ],
    "wof:name":"United Pentacostal Church",
    "wof:placetype":"venue"
},
  "geometry": {"coordinates":[-83.26478899999999,30.906034],"type":"Point"}
}