{
  "type": "Feature",
  "properties": {
    "addr:full":"315 Windsor Dr Fayetteville GA 30215",
    "addr:housenumber":"315",
    "addr:postcode":"30215",
    "addr:street":"Windsor Dr",
    "iso:country":"US",
    "sg:address":"315 Windsor Dr",
    "sg:city":"Fayetteville",
    "sg:classifiers":[
        {
            "category":"Banks & Credit Unions",
            "subcategory":"Financial Services",
            "type":"Services"
        }
    ],
    "sg:phone":"+1 770 719 0957",
    "sg:postcode":"30215",
    "sg:province":"GA",
    "sg:tags":[
        "investor"
    ],
    "wof:name":"Smart Asset Management Inc",
    "wof:placetype":"venue"
},
  "geometry": {"coordinates":[-84.42813,33.399636],"type":"Point"}
}