{
  "type": "Feature",
  "properties": {
    "addr:full":"2801 Buford Hwy NE Ste 280 Atlanta GA 30329",
    "addr:housenumber":"2801",
    "addr:postcode":"30329",
    "addr:street":"Buford Hwy Ne Ste 280",
    "iso:country":"US",
    "sg:address":"2801 Buford Hwy NE Ste 280",
    "sg:city":"Atlanta",
    "sg:classifiers":[
        {
            "category":"Real Estate",
            "subcategory":"Architect",
            "type":"Services"
        }
    ],
    "sg:phone":"+1 404 633 4586",
    "sg:postcode":"30329",
    "sg:province":"GA",
    "sg:website":"www.miltonpate.com",
    "wof:name":"Milton Pate Architects Inc",
    "wof:placetype":"venue"
},
  "geometry": {"coordinates":[-84.342697,33.831402],"type":"Point"}
}