{
  "type": "Feature",
  "properties": {
    "iso:country":"US",
    "sg:address":"2012 Hwy 42 N",
    "sg:city":"Mcdonough",
    "sg:classifiers":[
        {
            "category":"Home & Garden",
            "subcategory":"Hardware",
            "type":"Retail Goods"
        }
    ],
    "sg:phone":"+1 770 898 5557",
    "sg:postcode":"30253",
    "sg:province":"GA",
    "sg:tags":[
        "saw"
    ],
    "wof:name":"Campbell's",
    "wof:placetype":"venue"
},
  "geometry": {"coordinates":[-84.182125,33.498921],"type":"Point"}
}