{
  "type": "Feature",
  "properties": {
    "iso:country":"US",
    "sg:address":"1004 Park Colony Dr",
    "sg:city":"Norcross",
    "sg:classifiers":[
        {
            "category":"Building & Trades",
            "subcategory":"Construction",
            "type":"Services"
        }
    ],
    "sg:phone":"+1 678 794 0572",
    "sg:postcode":"30093",
    "sg:province":"GA",
    "sg:tags":[
        "contractor"
    ],
    "wof:name":"Diaz Drywall LLC",
    "wof:placetype":"venue"
},
  "geometry": {"coordinates":[-84.20944900000001,33.895294],"type":"Point"}
}