{
  "type": "Feature",
  "properties": {
    "addr:full":"825 Elm Dr Ellabell GA 31308",
    "addr:housenumber":"825",
    "addr:postcode":"31308",
    "addr:street":"Elm Dr",
    "iso:country":"US",
    "sg:address":"825 Elm Dr",
    "sg:city":"Ellabell",
    "sg:classifiers":[
        {
            "category":"Personal",
            "subcategory":"Tanning Parlor",
            "type":"Services"
        }
    ],
    "sg:phone":"+1 912 858 2336",
    "sg:postcode":"31308",
    "sg:province":"GA",
    "sg:tags":[
        "salon"
    ],
    "wof:name":"Karen's Tanning Salon",
    "wof:placetype":"venue"
},
  "geometry": {"coordinates":[-81.510673,32.187235],"type":"Point"}
}