{
  "type": "Feature",
  "properties": {
    "iso:country":"US",
    "sg:address":"5398 N Henry Blvd",
    "sg:city":"Stockbridge",
    "sg:classifiers":[
        {
            "category":"Shopping",
            "subcategory":"Mobile Phones",
            "type":"Retail Goods"
        }
    ],
    "sg:phone":"+1 678 289 2260",
    "sg:postcode":"30281",
    "sg:province":"GA",
    "wof:name":"Metro Pcs Authorized Dealer",
    "wof:placetype":"venue"
},
  "geometry": {"coordinates":[-84.254645,33.549859],"type":"Point"}
}