{
  "type": "Feature",
  "properties": {
    "addr:full":"3309 Centerville Hwy Snellville GA 30039",
    "addr:housenumber":"3309",
    "addr:postcode":"30039",
    "addr:street":"Centerville Hwy",
    "iso:country":"US",
    "sg:address":"3309 Centerville Hwy",
    "sg:city":"Snellville",
    "sg:classifiers":[
        {
            "category":"Restaurant",
            "type":"Food & Drink"
        }
    ],
    "sg:menulink":"http://www.allmenus.com/ga/snellville-grayson/95764-waffle-house/menu/",
    "sg:phone":"+1 770 979 1440",
    "sg:postcode":"30039",
    "sg:province":"GA",
    "sg:tags":[
        "american"
    ],
    "wof:name":"Waffle House",
    "wof:placetype":"venue"
},
  "geometry": {"coordinates":[-84.042548,33.811824],"type":"Point"}
}