{
  "type": "Feature",
  "properties": {
    "iso:country":"US",
    "sg:address":"579 Hwy 42 N",
    "sg:city":"Mc Donough",
    "sg:classifiers":[
        {
            "category":"Restaurant",
            "type":"Food & Drink"
        }
    ],
    "sg:phone":"+1 678 432 6747",
    "sg:postcode":"30253",
    "sg:province":"GA",
    "sg:tags":[
        "eating"
    ],
    "wof:name":"Coley Enterprises",
    "wof:placetype":"venue"
},
  "geometry": {"coordinates":[-84.15669800000001,33.465048],"type":"Point"}
}