{
  "type": "Feature",
  "properties": {
    "addr:full":"211 Fargo St Tennille GA 31089",
    "addr:housenumber":"211",
    "addr:postcode":"31089",
    "addr:street":"Fargo St",
    "iso:country":"US",
    "sg:address":"211 Fargo St",
    "sg:city":"Tennille",
    "sg:classifiers":[
        {
            "category":"Building & Trades",
            "subcategory":"Construction",
            "type":"Services"
        }
    ],
    "sg:phone":"+1 478 552 0438",
    "sg:postcode":"31089",
    "sg:province":"GA",
    "sg:tags":[
        "general",
        "contractor"
    ],
    "wof:name":"Andrews Construction",
    "wof:placetype":"venue"
},
  "geometry": {"coordinates":[-82.813874,32.941821],"type":"Point"}
}