{
  "type": "Feature",
  "properties": {
    "addr:full":"1314 E Cobb Dr Marietta GA 30068",
    "addr:housenumber":"1314",
    "addr:postcode":"30068",
    "addr:street":"E Cobb Dr",
    "iso:country":"US",
    "sg:address":"1314 E Cobb Dr",
    "sg:city":"Marietta",
    "sg:classifiers":[
        {
            "category":"Retail",
            "subcategory":"Veterinary Services",
            "type":"Services"
        }
    ],
    "sg:phone":"+1 770 973 2286",
    "sg:postcode":"30068",
    "sg:province":"GA",
    "sg:tags":[
        "pet",
        "veterinarian"
    ],
    "sg:website":"http://www.eastcobbvet.com/",
    "wof:name":"East Cobb Veterinary Clinic",
    "wof:placetype":"venue"
},
  "geometry": {"coordinates":[-84.42535100000001,33.980989],"type":"Point"}
}