{
  "type": "Feature",
  "properties": {
    "addr:full":"1510 Maple Pointe Ct Lawrenceville GA 30043",
    "addr:housenumber":"1510",
    "addr:postcode":"30043",
    "addr:street":"Maple Pointe Ct",
    "iso:country":"US",
    "sg:address":"1510 Maple Pointe Ct",
    "sg:city":"Lawrenceville",
    "sg:classifiers":[
        {
            "category":"Shopping",
            "subcategory":"Used Merchandise",
            "type":"Retail Goods"
        }
    ],
    "sg:phone":"+1 770 237 9353",
    "sg:postcode":"30043",
    "sg:province":"GA",
    "wof:name":"All Your Favorite Music",
    "wof:placetype":"venue"
},
  "geometry": {"coordinates":[-84.07370299999999,33.96677],"type":"Point"}
}