{
  "type": "Feature",
  "properties": {
    "iso:country":"US",
    "sg:address":"111 Appleby Rd",
    "sg:city":"Port Wentworth",
    "sg:classifiers":[
        {
            "category":"Professional",
            "subcategory":"Lawyer & Legal Services",
            "type":"Services"
        }
    ],
    "sg:phone":"+1 912 966 1813",
    "sg:postcode":"31407",
    "sg:province":"GA",
    "sg:tags":[
        "attorney"
    ],
    "wof:name":"C Grant Washington",
    "wof:placetype":"venue"
},
  "geometry": {"coordinates":[-81.163707,32.159114],"type":"Point"}
}