{
  "type": "Feature",
  "properties": {
    "addr:full":"1059 Retner Dr SW Mableton GA 30126",
    "addr:housenumber":"1059",
    "addr:postcode":"30126",
    "addr:street":"Retner Dr Sw",
    "iso:country":"US",
    "sg:address":"1059 Retner Dr SW",
    "sg:city":"Mableton",
    "sg:classifiers":[
        {
            "category":"Retail",
            "subcategory":"Photofinishing",
            "type":"Services"
        }
    ],
    "sg:phone":"+1 770 941 4741",
    "sg:postcode":"30126",
    "sg:province":"GA",
    "sg:tags":[
        "laboratory"
    ],
    "wof:name":"One of A Kind",
    "wof:placetype":"venue"
},
  "geometry": {"coordinates":[-84.58614300000001,33.832003],"type":"Point"}
}