{
  "type": "Feature",
  "properties": {
    "iso:country":"US",
    "sg:address":"53 Perimeter Ctr E",
    "sg:city":"Atlanta",
    "sg:classifiers":[
        {
            "category":"Professional",
            "subcategory":"Employment Agencies",
            "type":"Services"
        }
    ],
    "sg:phone":"+1 678 730 0854",
    "sg:postcode":"30346",
    "sg:province":"GA",
    "sg:website":"www.hireaccountability.com",
    "wof:name":"Hire Accountability",
    "wof:placetype":"venue"
},
  "geometry": {"coordinates":[-84.33101600000001,33.92185],"type":"Point"}
}