{
  "type": "Feature",
  "properties": {
    "addr:full":"3855 Cusseta Rd Columbus GA 31903",
    "addr:postcode":"3855;31903",
    "addr:street":"Cusseta Rd",
    "iso:country":"US",
    "sg:address":"3855 Cusseta Rd",
    "sg:city":"Columbus",
    "sg:classifiers":[
        {
            "category":"Wholesale",
            "subcategory":"Auto Parts",
            "type":"Manufacturing & Wholesale Goods"
        }
    ],
    "sg:phone":"+1 706 687 8001",
    "sg:postcode":"31903",
    "sg:province":"GA",
    "sg:tags":[
        "used"
    ],
    "wof:name":"F & W Garage",
    "wof:placetype":"venue"
},
  "geometry": {"coordinates":[-84.93467699999999,32.434278],"type":"Point"}
}