{
  "type": "Feature",
  "properties": {
    "addr:full":"6000 Hillvale Rd Lithonia GA 30058",
    "addr:housenumber":"6000",
    "addr:postcode":"30058",
    "addr:street":"Hillvale Rd",
    "iso:country":"US",
    "sg:address":"6000 Hillvale Rd",
    "sg:city":"Lithonia",
    "sg:classifiers":[
        {
            "category":"Professional",
            "type":"Services"
        }
    ],
    "sg:phone":"+1 770 686 8358",
    "sg:postcode":"30058",
    "sg:province":"GA",
    "wof:name":"Linda Shaw Embroidery",
    "wof:placetype":"venue"
},
  "geometry": {"coordinates":[-84.14726400000001,33.716211],"type":"Point"}
}