{
  "type": "Feature",
  "properties": {
    "addr:full":"386 Old Hollow Trl Cohutta GA 30710",
    "addr:housenumber":"386",
    "addr:postcode":"30710",
    "addr:street":"Old Hollow Trl",
    "iso:country":"US",
    "sg:address":"386 Old Hollow Trl",
    "sg:city":"Cohutta",
    "sg:classifiers":[
        {
            "category":"Home & Garden",
            "subcategory":"Carpets & Floor Coverings",
            "type":"Retail Goods"
        }
    ],
    "sg:phone":"+1 706 694 2393",
    "sg:postcode":"30710",
    "sg:province":"GA",
    "sg:tags":[
        "dealer",
        "rug"
    ],
    "wof:name":"American Home Designs LLC",
    "wof:placetype":"venue"
},
  "geometry": {"coordinates":[-84.95953799999999,34.918647],"type":"Point"}
}