{
  "type": "Feature",
  "properties": {
    "addr:full":"3825 Riversong Dr NW Suwanee GA 30024",
    "addr:postcode":"3825;30024",
    "addr:street":"Riversong Dr Nw",
    "iso:country":"US",
    "sg:address":"3825 Riversong Dr NW",
    "sg:city":"Suwanee",
    "sg:classifiers":[
        {
            "category":"Professional",
            "subcategory":"Management & Consulting",
            "type":"Services"
        }
    ],
    "sg:phone":"+1 770 831 7446",
    "sg:postcode":"30024",
    "sg:province":"GA",
    "sg:tags":[
        "business"
    ],
    "wof:name":"Dedique Consulting LLC",
    "wof:placetype":"venue"
},
  "geometry": {"coordinates":[-84.105199,34.036084],"type":"Point"}
}