{
  "type": "Feature",
  "properties": {
    "iso:country":"US",
    "sg:address":"5570 Lawrenceville Hwy NW",
    "sg:city":"Lilburn",
    "sg:classifiers":[
        {
            "category":"Personal",
            "subcategory":"Beauty Salon",
            "type":"Services"
        }
    ],
    "sg:phone":"+1 770 923 2460",
    "sg:postcode":"30047",
    "sg:province":"GA",
    "sg:tags":[
        "hair",
        "stylist"
    ],
    "wof:name":"Shear Looks Inc",
    "wof:placetype":"venue"
},
  "geometry": {"coordinates":[-84.163567,33.881672],"type":"Point"}
}