{
  "type": "Feature",
  "properties": {
    "addr:full":"3149 Rockingham Dr NW Atlanta GA 30327",
    "addr:housenumber":"3149",
    "addr:postcode":"30327",
    "addr:street":"Rockingham Dr Nw",
    "iso:country":"US",
    "sg:address":"3149 Rockingham Dr NW",
    "sg:city":"Atlanta",
    "sg:classifiers":[
        {
            "category":"Professional",
            "subcategory":"Business Services",
            "type":"Services"
        }
    ],
    "sg:phone":"+1 404 351 2386",
    "sg:postcode":"30327",
    "sg:province":"GA",
    "wof:name":"Buckhead Partners",
    "wof:placetype":"venue"
},
  "geometry": {"coordinates":[-84.415843,33.836387],"type":"Point"}
}