{
  "type": "Feature",
  "properties": {
    "iso:country":"US",
    "sg:address":"10389 Tara Blvd",
    "sg:city":"Jonesboro",
    "sg:classifiers":[
        {
            "category":"Personal",
            "subcategory":"Nail Salon",
            "type":"Services"
        }
    ],
    "sg:phone":"+1 770 472 2202",
    "sg:postcode":"30236",
    "sg:province":"GA",
    "wof:name":"D & K Nail and Tan",
    "wof:placetype":"venue"
},
  "geometry": {"coordinates":[-84.33609800000001,33.470001],"type":"Point"}
}