{
  "type": "Feature",
  "properties": {
    "iso:country":"US",
    "sg:address":"2373 Access Rd",
    "sg:city":"Covington",
    "sg:classifiers":[
        {
            "category":"Shopping",
            "subcategory":"Computers & Home Electronics",
            "type":"Retail Goods"
        }
    ],
    "sg:phone":"+1 770 784 0890",
    "sg:postcode":"30016",
    "sg:province":"GA",
    "sg:tags":[
        "consumer"
    ],
    "wof:name":"RC Electronics Inc",
    "wof:placetype":"venue"
},
  "geometry": {"coordinates":[-83.939702,33.624725],"type":"Point"}
}