{
  "type": "Feature",
  "properties": {
    "addr:full":"1416 Andover Ct Evans GA 30809",
    "addr:housenumber":"1416",
    "addr:postcode":"30809",
    "addr:street":"Andover Ct",
    "iso:country":"US",
    "sg:address":"1416 Andover Ct",
    "sg:city":"Evans",
    "sg:classifiers":[
        {
            "category":"Professional",
            "subcategory":"Management & Consulting",
            "type":"Services"
        }
    ],
    "sg:phone":"+1 706 650 0871",
    "sg:postcode":"30809",
    "sg:province":"GA",
    "sg:tags":[
        "web",
        "based",
        "environmental",
        "health",
        "provides",
        "safety"
    ],
    "wof:name":"National Envmtl Trainers",
    "wof:placetype":"venue"
},
  "geometry": {"coordinates":[-82.14770900000001,33.58433],"type":"Point"}
}