{
  "type": "Feature",
  "properties": {
    "addr:full":"504 Plant Ave Waycross GA 31501",
    "addr:housenumber":"504",
    "addr:postcode":"31501",
    "addr:street":"Plant Ave",
    "iso:country":"US",
    "sg:address":"504 Plant Ave",
    "sg:city":"Waycross",
    "sg:classifiers":[
        {
            "category":"Shopping",
            "subcategory":"Gifts & Souvenirs",
            "type":"Retail Goods"
        }
    ],
    "sg:phone":"+1 912 285 3545",
    "sg:postcode":"31501",
    "sg:province":"GA",
    "sg:tags":[
        "collectible"
    ],
    "wof:name":"It's Showtime",
    "wof:placetype":"venue"
},
  "geometry": {"coordinates":[-82.349143,31.217368],"type":"Point"}
}