{
  "type": "Feature",
  "properties": {
    "addr:full":"755 E Broad St Athens GA 30601",
    "addr:housenumber":"755",
    "addr:postcode":"30601",
    "addr:street":"E Broad St",
    "iso:country":"US",
    "sg:address":"755 E Broad St",
    "sg:city":"Athens",
    "sg:classifiers":[
        {
            "category":"Manufacturing",
            "subcategory":"Pet Food",
            "type":"Manufacturing & Wholesale Goods"
        }
    ],
    "sg:phone":"+1 706 548 1371",
    "sg:postcode":"30601",
    "sg:province":"GA",
    "sg:tags":[
        "feed",
        "mfg",
        "supply"
    ],
    "wof:name":"Clarke County Milling Co  Inc",
    "wof:placetype":"venue"
},
  "geometry": {"coordinates":[-83.369731,33.95867],"type":"Point"}
}