{
  "type": "Feature",
  "properties": {
    "addr:full":"4009 Lake Acworth Dr Acworth GA 30101",
    "addr:housenumber":"4009",
    "addr:postcode":"30101",
    "addr:street":"Lake Acworth Dr",
    "iso:country":"US",
    "sg:address":"4009 Lake Acworth Dr",
    "sg:city":"Acworth",
    "sg:classifiers":[
        {
            "category":"Food & Beverages",
            "subcategory":"Fruits & Vegetables",
            "type":"Retail Goods"
        }
    ],
    "sg:phone":"+1 770 974 7080",
    "sg:postcode":"30101",
    "sg:province":"GA",
    "sg:tags":[
        "produce"
    ],
    "wof:name":"Farmer John's Produce",
    "wof:placetype":"venue"
},
  "geometry": {"coordinates":[-84.666937,34.076492],"type":"Point"}
}