{
  "type": "Feature",
  "properties": {
    "iso:country":"US",
    "sg:address":"733 Buford Dr",
    "sg:city":"Lawrenceville",
    "sg:classifiers":[
        {
            "category":"Professional",
            "type":"Services"
        }
    ],
    "sg:phone":"+1 770 236 9902",
    "sg:postcode":"30043",
    "sg:province":"GA",
    "sg:tags":[
        "establishment"
    ],
    "wof:name":"Eagle Prepaid",
    "wof:placetype":"venue"
},
  "geometry": {"coordinates":[-83.985156,33.980715],"type":"Point"}
}