{
  "type": "Feature",
  "properties": {
    "addr:full":"2400 Herodian Way Smyrna GA 30080",
    "addr:housenumber":"2400",
    "addr:postcode":"30080",
    "addr:street":"Herodian Way",
    "iso:country":"US",
    "sg:address":"2400 Herodian Way",
    "sg:city":"Smyrna",
    "sg:classifiers":[
        {
            "category":"Real Estate",
            "subcategory":"Real Estate Agent",
            "type":"Services"
        }
    ],
    "sg:phone":"+1 770 989 0051",
    "sg:postcode":"30080",
    "sg:province":"GA",
    "sg:tags":[
        "appraiser"
    ],
    "wof:name":"Nationwide Appraisal Inc",
    "wof:placetype":"venue"
},
  "geometry": {"coordinates":[-84.472629,33.894313],"type":"Point"}
}