{
  "type": "Feature",
  "properties": {
    "addr:full":"5855 Oakbrook Pkwy Ste P Norcross GA 30093",
    "addr:housenumber":"5855",
    "addr:postcode":"30093",
    "addr:street":"Oakbrook Pkwy Ste P",
    "iso:country":"US",
    "sg:address":"5855 Oakbrook Pkwy Ste P",
    "sg:city":"Norcross",
    "sg:classifiers":[
        {
            "category":"Home & Garden",
            "subcategory":"Building Materials",
            "type":"Retail Goods"
        }
    ],
    "sg:phone":"+1 770 242 3026",
    "sg:postcode":"30093",
    "sg:province":"GA",
    "sg:tags":[
        "supply"
    ],
    "wof:name":"Nichiha USA Inc",
    "wof:placetype":"venue"
},
  "geometry": {"coordinates":[-84.198601,33.9151],"type":"Point"}
}