{
  "type": "Feature",
  "properties": {
    "iso:country":"US",
    "sg:address":"400 Ernest W Barrett Pkwy",
    "sg:city":"Kennesaw",
    "sg:classifiers":[
        {
            "category":"Retail",
            "subcategory":"Portrait Studio",
            "type":"Services"
        }
    ],
    "sg:phone":"+1 770 421 1482",
    "sg:postcode":"30144",
    "sg:province":"GA",
    "sg:tags":[
        "photographer",
        "photo"
    ],
    "wof:name":"Picture People Inc",
    "wof:placetype":"venue"
},
  "geometry": {"coordinates":[-84.56442199999999,34.011907],"type":"Point"}
}