{
  "type": "Feature",
  "properties": {
    "iso:country":"US",
    "sg:address":"432 Ty Ty Omega Rd",
    "sg:city":"Tifton",
    "sg:classifiers":[
        {
            "category":"Farming",
            "subcategory":"Nursery",
            "type":"Manufacturing & Wholesale Goods"
        }
    ],
    "sg:phone":"+1 229 386 8701",
    "sg:postcode":"31793",
    "sg:province":"GA",
    "sg:tags":[
        "ornamental",
        "station",
        "gasoline"
    ],
    "wof:name":"Seminis Inc",
    "wof:placetype":"venue"
},
  "geometry": {"coordinates":[-83.615803,31.435734],"type":"Point"}
}