{
  "type": "Feature",
  "properties": {
    "iso:country":"US",
    "sg:address":"198 Alonzo Wade Rd",
    "sg:city":"Alto",
    "sg:classifiers":[
        {
            "category":"Retail",
            "subcategory":"Auto Repair",
            "type":"Services"
        }
    ],
    "sg:phone":"+1 706 778 6400",
    "sg:postcode":"30510",
    "sg:province":"GA",
    "sg:tags":[
        "general"
    ],
    "wof:name":"Wades Junk Yard",
    "wof:placetype":"venue"
},
  "geometry": {"coordinates":[-83.61894599999999,34.452096],"type":"Point"}
}