{
  "type": "Feature",
  "properties": {
    "addr:full":"5324 Valley Forest Way Flowery Branch GA 30542",
    "addr:housenumber":"5324",
    "addr:postcode":"30542",
    "addr:street":"Valley Forest Way",
    "iso:country":"US",
    "sg:address":"5324 Valley Forest Way",
    "sg:city":"Flowery Branch",
    "sg:classifiers":[
        {
            "category":"Building & Trades",
            "subcategory":"Construction",
            "type":"Services"
        }
    ],
    "sg:phone":"+1 770 967 1947",
    "sg:postcode":"30542",
    "sg:province":"GA",
    "sg:tags":[
        "hanging",
        "contractor"
    ],
    "wof:name":"Hullon Frix Painting",
    "wof:placetype":"venue"
},
  "geometry": {"coordinates":[-83.927544,34.155912],"type":"Point"}
}