{
  "type": "Feature",
  "properties": {
    "iso:country":"US",
    "sg:address":"510 River Overlook Dr NE",
    "sg:city":"Lawrenceville",
    "sg:classifiers":[
        {
            "category":"Professional",
            "subcategory":"Management & Consulting",
            "type":"Services"
        }
    ],
    "sg:phone":"+1 770 962 4067",
    "sg:postcode":"30043",
    "sg:province":"GA",
    "sg:tags":[
        "consultant",
        "energy",
        "conservation"
    ],
    "wof:name":"KMB Svc",
    "wof:placetype":"venue"
},
  "geometry": {"coordinates":[-84.016729,33.978431],"type":"Point"}
}