{
  "type": "Feature",
  "properties": {
    "iso:country":"US",
    "sg:address":"3343 W Hospital Ave",
    "sg:city":"Atlanta",
    "sg:classifiers":[
        {
            "category":"Professional",
            "subcategory":"Computer Services",
            "type":"Services"
        }
    ],
    "sg:phone":"+1 770 451 8944",
    "sg:postcode":"30341",
    "sg:province":"GA",
    "sg:tags":[
        "control",
        "industrial",
        "design",
        "system",
        "build"
    ],
    "wof:name":"Atlanta Automation Inc",
    "wof:placetype":"venue"
},
  "geometry": {"coordinates":[-84.294572,33.890177],"type":"Point"}
}