{
  "type": "Feature",
  "properties": {
    "addr:full":"130 Windfield Dr Savannah GA 31406",
    "addr:housenumber":"130",
    "addr:postcode":"31406",
    "addr:street":"Windfield Dr",
    "iso:country":"US",
    "sg:address":"130 Windfield Dr",
    "sg:city":"Savannah",
    "sg:classifiers":[
        {
            "category":"Professional",
            "subcategory":"Advertising",
            "type":"Services"
        }
    ],
    "sg:phone":"+1 912 352 7554",
    "sg:postcode":"31406",
    "sg:province":"GA",
    "sg:tags":[
        "mail"
    ],
    "wof:name":"Mailsouth",
    "wof:placetype":"venue"
},
  "geometry": {"coordinates":[-81.066255,32.009638],"type":"Point"}
}