{
  "type": "Feature",
  "properties": {
    "iso:country":"US",
    "sg:address":"1951 River Forest Dr",
    "sg:city":"Marietta",
    "sg:classifiers":[
        {
            "category":"Professional",
            "subcategory":"Business Services",
            "type":"Services"
        }
    ],
    "sg:phone":"+1 770 645 6415",
    "sg:postcode":"30068",
    "sg:province":"GA",
    "wof:name":"Alme Enterprises LLC",
    "wof:placetype":"venue"
},
  "geometry": {"coordinates":[-84.394221,33.997292],"type":"Point"}
}