{
  "type": "Feature",
  "properties": {
    "addr:full":"107 Lindsey Dr Cartersville GA 30165",
    "addr:housenumber":"107",
    "addr:postcode":"30165",
    "addr:street":"Lindsey Dr",
    "iso:country":"US",
    "sg:address":"107 Lindsey Dr",
    "sg:city":"Cartersville",
    "sg:classifiers":[
        {
            "category":"Shopping",
            "subcategory":"Computers & Home Electronics",
            "type":"Retail Goods"
        }
    ],
    "sg:phone":"+1 770 607 5020",
    "sg:postcode":"30165",
    "sg:province":"GA",
    "wof:name":"Watts Computer Electronics",
    "wof:placetype":"venue"
},
  "geometry": {"coordinates":[-85.223703,34.293645],"type":"Point"}
}