{
  "type": "Feature",
  "properties": {
    "addr:full":"2103 Treehills Pkwy Stone Mountain GA 30088",
    "addr:housenumber":"2103",
    "addr:postcode":"30088",
    "addr:street":"Treehills Pkwy",
    "iso:country":"US",
    "sg:address":"2103 Treehills Pkwy",
    "sg:city":"Stone Mountain",
    "sg:classifiers":[
        {
            "category":"Utilities",
            "subcategory":"Telephone",
            "type":"Services"
        }
    ],
    "sg:phone":"+1 678 596 5543",
    "sg:postcode":"30088",
    "sg:province":"GA",
    "sg:tags":[
        "communications"
    ],
    "wof:name":"Deals That R Steals Co",
    "wof:placetype":"venue"
},
  "geometry": {"coordinates":[-84.193862,33.753418],"type":"Point"}
}