{
  "type": "Feature",
  "properties": {
    "iso:country":"US",
    "sg:address":"2200 Northlake Pkwy",
    "sg:city":"Tucker",
    "sg:classifiers":[
        {
            "category":"Building & Trades",
            "subcategory":"Cleaning & Sanitation",
            "type":"Services"
        }
    ],
    "sg:phone":"+1 770 270 8927",
    "sg:postcode":"30084",
    "sg:province":"GA",
    "sg:tags":[
        "janitor"
    ],
    "wof:name":"Pinnacle Building Svc",
    "wof:placetype":"venue"
},
  "geometry": {"coordinates":[-84.244608,33.8469],"type":"Point"}
}