{
  "type": "Feature",
  "properties": {
    "iso:country":"US",
    "sg:address":"1715 W Savannah Ave",
    "sg:city":"Valdosta",
    "sg:classifiers":[
        {
            "category":"Restaurant",
            "type":"Food & Drink"
        }
    ],
    "sg:phone":"+1 229 253 0986",
    "sg:postcode":"31601",
    "sg:province":"GA",
    "wof:name":"Barfield Supreme",
    "wof:placetype":"venue"
},
  "geometry": {"coordinates":[-83.301912,30.820485],"type":"Point"}
}