{
  "type": "Feature",
  "properties": {
    "addr:full":"1939 Whiddon Mill Rd Tifton GA 31794",
    "addr:housenumber":"1939",
    "addr:postcode":"31794",
    "addr:street":"Whiddon Mill Rd",
    "iso:country":"US",
    "sg:address":"1939 Whiddon Mill Rd",
    "sg:city":"Tifton",
    "sg:classifiers":[
        {
            "category":"Food & Beverages",
            "subcategory":"Groceries & Convenience Stores",
            "type":"Retail Goods"
        }
    ],
    "sg:phone":"+1 229 382 3121",
    "sg:postcode":"31794",
    "sg:province":"GA",
    "wof:name":"Speego No 1",
    "wof:placetype":"venue"
},
  "geometry": {"coordinates":[-83.544336,31.466745],"type":"Point"}
}