{
  "type": "Feature",
  "properties": {
    "iso:country":"US",
    "sg:address":"813 Park Dr",
    "sg:city":"Warner Robins",
    "sg:classifiers":[
        {
            "category":"Professional",
            "subcategory":"Engineering",
            "type":"Services"
        }
    ],
    "sg:phone":"+1 478 923 0500",
    "sg:postcode":"31088",
    "sg:province":"GA",
    "sg:tags":[
        "engineer"
    ],
    "wof:name":"General Dynamics Advanced Info",
    "wof:placetype":"venue"
},
  "geometry": {"coordinates":[-83.61211900000001,32.596779],"type":"Point"}
}