{
  "type": "Feature",
  "properties": {
    "iso:country":"US",
    "sg:address":"3275 Flowers Rd S",
    "sg:city":"Atlanta",
    "sg:classifiers":[
        {
            "category":"Banks & Credit Unions",
            "subcategory":"Bank",
            "type":"Services"
        }
    ],
    "sg:phone":"+1 770 455 9114",
    "sg:postcode":"30341",
    "sg:province":"GA",
    "sg:tags":[
        "cashing",
        "check"
    ],
    "wof:name":"D & A Check Recovery",
    "wof:placetype":"venue"
},
  "geometry": {"coordinates":[-84.256563,33.873327],"type":"Point"}
}