{
  "type": "Feature",
  "properties": {
    "addr:full":"1120 Liberty Ln Bogart GA 30622",
    "addr:housenumber":"1120",
    "addr:postcode":"30622",
    "addr:street":"Liberty Ln",
    "iso:country":"US",
    "sg:address":"1120 Liberty Ln",
    "sg:city":"Bogart",
    "sg:classifiers":[
        {
            "category":"Manufacturing",
            "subcategory":"Tools & Machinery",
            "type":"Manufacturing & Wholesale Goods"
        }
    ],
    "sg:phone":"+1 678 753 1177",
    "sg:postcode":"30622",
    "sg:province":"GA",
    "sg:tags":[
        "equipment",
        "electric"
    ],
    "wof:name":"Roxtec Inc-Atlantic",
    "wof:placetype":"venue"
},
  "geometry": {"coordinates":[-83.545749,33.915624],"type":"Point"}
}