{
  "type": "Feature",
  "properties": {
    "addr:full":"973 Palmetto Tyrone Rd Sharpsburg GA 30277",
    "addr:housenumber":"973",
    "addr:postcode":"30277",
    "addr:street":"Palmetto Tyrone Rd",
    "iso:country":"US",
    "sg:address":"973 Palmetto Tyrone Rd",
    "sg:city":"Sharpsburg",
    "sg:classifiers":[
        {
            "category":"Real Estate",
            "subcategory":"Real Estate Agent",
            "type":"Services"
        }
    ],
    "sg:phone":"+1 404 636 2616",
    "sg:postcode":"30277",
    "sg:province":"GA",
    "wof:name":"Briarcliff Brokers",
    "wof:placetype":"venue"
},
  "geometry": {"coordinates":[-84.65413700000001,33.477369],"type":"Point"}
}