{
  "type": "Feature",
  "properties": {
    "iso:country":"US",
    "sg:address":"104 King St",
    "sg:city":"Adairsville",
    "sg:classifiers":[
        {
            "category":"Organizations",
            "subcategory":"Religious Organization",
            "type":"Services"
        }
    ],
    "sg:phone":"+1 770 877 9035",
    "sg:postcode":"30103",
    "sg:province":"GA",
    "wof:name":"Rick Baggett Rev",
    "wof:placetype":"venue"
},
  "geometry": {"coordinates":[-84.935738,34.370523],"type":"Point"}
}