{
  "type": "Feature",
  "properties": {
    "addr:full":"1090 Willingham Ave Baldwin GA 30511",
    "addr:housenumber":"1090",
    "addr:postcode":"30511",
    "addr:street":"Willingham Ave",
    "iso:country":"US",
    "sg:address":"1090 Willingham Ave",
    "sg:city":"Baldwin",
    "sg:classifiers":[
        {
            "category":"Government",
            "subcategory":"Post Office",
            "type":"Public Place"
        }
    ],
    "sg:phone":"+1 706 778 2751",
    "sg:postcode":"30511",
    "sg:province":"GA",
    "sg:website":"http://www.usps.com",
    "wof:name":"Us Post Office",
    "wof:placetype":"venue"
},
  "geometry": {"coordinates":[-83.537907,34.491415],"type":"Point"}
}