{
  "type": "Feature",
  "properties": {
    "iso:country":"US",
    "sg:address":"801 W Oxford Ln",
    "sg:city":"Hinesville",
    "sg:classifiers":[
        {
            "category":"Utilities",
            "subcategory":"Telephone",
            "type":"Services"
        }
    ],
    "sg:phone":"+1 912 368 5050",
    "sg:postcode":"31313",
    "sg:province":"GA",
    "sg:tags":[
        "communications"
    ],
    "wof:name":"World Gaming Syndicate",
    "wof:placetype":"venue"
},
  "geometry": {"coordinates":[-81.58729099999999,31.825084],"type":"Point"}
}