{
  "type": "Feature",
  "properties": {
    "addr:full":"101 N Carter St Lakeland GA 31635",
    "addr:housenumber":"101",
    "addr:postcode":"31635",
    "addr:street":"N Carter St",
    "iso:country":"US",
    "sg:address":"101 N Carter St",
    "sg:city":"Lakeland",
    "sg:classifiers":[
        {
            "category":"Autos & Motor Vehicles",
            "subcategory":"Fuel & Gas Station",
            "type":"Retail Goods"
        }
    ],
    "sg:phone":"+1 229 482 2724",
    "sg:postcode":"31635",
    "sg:province":"GA",
    "sg:tags":[
        "oil"
    ],
    "wof:name":"Bobbys Citgo",
    "wof:placetype":"venue"
},
  "geometry": {"coordinates":[-83.075259,31.041946],"type":"Point"}
}