{
  "type": "Feature",
  "properties": {
    "iso:country":"US",
    "sg:address":"1915 Augusta Rd",
    "sg:city":"North Augusta",
    "sg:classifiers":[
        {
            "category":"Manufacturing",
            "subcategory":"Food",
            "type":"Manufacturing & Wholesale Goods"
        }
    ],
    "sg:phone":"+1 803 613 0012",
    "sg:postcode":"29822",
    "sg:province":"SC",
    "sg:tags":[
        "desert",
        "ice",
        "mfg"
    ],
    "wof:name":"Coburg Dairy LLC",
    "wof:placetype":"venue"
},
  "geometry": {"coordinates":[-81.891848,33.496829],"type":"Point"}
}