{
  "type": "Feature",
  "properties": {
    "addr:full":"112 Longview Rd Fayetteville GA 30214",
    "addr:housenumber":"112",
    "addr:postcode":"30214",
    "addr:street":"Longview Rd",
    "iso:country":"US",
    "sg:address":"112 Longview Rd",
    "sg:city":"Fayetteville",
    "sg:classifiers":[
        {
            "category":"Retail",
            "subcategory":"Auto Repair",
            "type":"Services"
        }
    ],
    "sg:phone":"+1 770 461 6479",
    "sg:postcode":"30214",
    "sg:province":"GA",
    "sg:tags":[
        "automotive"
    ],
    "wof:name":"C W Holt Alignment",
    "wof:placetype":"venue"
},
  "geometry": {"coordinates":[-84.450281,33.487359],"type":"Point"}
}