{
  "type": "Feature",
  "properties": {
    "iso:country":"US",
    "sg:address":"2081 Forest Hill Rd",
    "sg:city":"Macon",
    "sg:classifiers":[
        {
            "category":"Organizations",
            "subcategory":"Religious Organization",
            "type":"Services"
        }
    ],
    "sg:phone":"+1 478 474 3400",
    "sg:postcode":"31210",
    "sg:province":"GA",
    "wof:name":"Lundy Chapel Baptist Church",
    "wof:placetype":"venue"
},
  "geometry": {"coordinates":[-83.708057,32.906762],"type":"Point"}
}