{
  "type": "Feature",
  "properties": {
    "addr:full":"711 10th St NW Atlanta GA 30318",
    "addr:housenumber":"711",
    "addr:postcode":"30318",
    "addr:street":"10Th St Nw",
    "iso:country":"US",
    "sg:address":"711 10th St NW",
    "sg:city":"Atlanta",
    "sg:classifiers":[
        {
            "category":"Professional",
            "subcategory":"Art Services",
            "type":"Services"
        }
    ],
    "sg:phone":"+1 404 876 7002",
    "sg:postcode":"30318",
    "sg:province":"GA",
    "sg:tags":[
        "photographer"
    ],
    "wof:name":"Macuch Studio",
    "wof:placetype":"venue"
},
  "geometry": {"coordinates":[-84.410628,33.781646],"type":"Point"}
}