{
  "type": "Feature",
  "properties": {
    "iso:country":"US",
    "sg:address":"189 Cobb Pkwy",
    "sg:city":"Marietta",
    "sg:classifiers":[
        {
            "category":"Manufacturing",
            "subcategory":"Tools & Machinery",
            "type":"Manufacturing & Wholesale Goods"
        }
    ],
    "sg:phone":"+1 678 331 8001",
    "sg:postcode":"30062",
    "sg:province":"GA",
    "sg:tags":[
        "cutting"
    ],
    "wof:name":"Ruko Tool",
    "wof:placetype":"venue"
},
  "geometry": {"coordinates":[-84.52255100000001,33.954214],"type":"Point"}
}