{
  "type": "Feature",
  "properties": {
    "addr:full":"297 Prince Ave Athens GA 30601",
    "addr:housenumber":"297",
    "addr:postcode":"30601",
    "addr:street":"Prince Ave",
    "iso:country":"US",
    "sg:address":"297 Prince Ave",
    "sg:city":"Athens",
    "sg:classifiers":[
        {
            "category":"Communications",
            "subcategory":"Film & Video Production",
            "type":"Services"
        }
    ],
    "sg:phone":"+1 706 353 9530",
    "sg:postcode":"30601",
    "sg:province":"GA",
    "sg:tags":[
        "motion",
        "picture",
        "taping"
    ],
    "wof:name":"Radar Multimedia Productions",
    "wof:placetype":"venue"
},
  "geometry": {"coordinates":[-83.382739,33.960242],"type":"Point"}
}