{
  "type": "Feature",
  "properties": {
    "addr:full":"1128 Brett Dr SW Conyers GA 30094",
    "addr:housenumber":"1128",
    "addr:postcode":"30094",
    "addr:street":"Brett Dr Sw",
    "iso:country":"US",
    "sg:address":"1128 Brett Dr SW",
    "sg:city":"Conyers",
    "sg:classifiers":[
        {
            "category":"Manufacturing",
            "subcategory":"Printing",
            "type":"Manufacturing & Wholesale Goods"
        }
    ],
    "sg:phone":"+1 770 483 2022",
    "sg:postcode":"30094",
    "sg:province":"GA",
    "sg:tags":[
        "newspaper",
        "distribution"
    ],
    "wof:name":"Atlanta Constitution",
    "wof:placetype":"venue"
},
  "geometry": {"coordinates":[-84.025267,33.653123],"type":"Point"}
}