{
  "type": "Feature",
  "properties": {
    "addr:full":"4415 Woodcliff Ct Gainesville GA 30507",
    "addr:housenumber":"4415",
    "addr:postcode":"30507",
    "addr:street":"Woodcliff Ct",
    "iso:country":"US",
    "sg:address":"4415 Woodcliff Ct",
    "sg:city":"Gainesville",
    "sg:classifiers":[
        {
            "category":"Building & Trades",
            "subcategory":"Construction",
            "type":"Services"
        }
    ],
    "sg:phone":"+1 770 967 6571",
    "sg:postcode":"30507",
    "sg:province":"GA",
    "sg:tags":[
        "contractor"
    ],
    "wof:name":"La Designs",
    "wof:placetype":"venue"
},
  "geometry": {"coordinates":[-83.824422,34.191061],"type":"Point"}
}