{
  "type": "Feature",
  "properties": {
    "iso:country":"US",
    "sg:address":"152 Hurricane Shoals Rd NE",
    "sg:city":"Lawrenceville",
    "sg:classifiers":[
        {
            "category":"Personal",
            "subcategory":"Beauty Salon",
            "type":"Services"
        }
    ],
    "sg:phone":"+1 770 962 6052",
    "sg:postcode":"30045",
    "sg:province":"GA",
    "sg:tags":[
        "shop"
    ],
    "wof:name":"Beginning Inc",
    "wof:placetype":"venue"
},
  "geometry": {"coordinates":[-83.98891999999999,33.973371],"type":"Point"}
}