{
  "type": "Feature",
  "properties": {
    "iso:country":"US",
    "sg:address":"4553 Tillman Bluff Rd",
    "sg:city":"Valdosta",
    "sg:classifiers":[
        {
            "category":"Real Estate",
            "subcategory":"Real Estate Agent",
            "type":"Services"
        }
    ],
    "sg:phone":"+1 229 242 8357",
    "sg:postcode":"31602",
    "sg:province":"GA",
    "wof:name":"Tl Properties Inc",
    "wof:placetype":"venue"
},
  "geometry": {"coordinates":[-83.355834,30.909815],"type":"Point"}
}