{
  "type": "Feature",
  "properties": {
    "iso:country":"US",
    "sg:address":"1386 Anderson Mill Rd",
    "sg:city":"Austell",
    "sg:classifiers":[
        {
            "category":"Social Services",
            "subcategory":"Child Care",
            "type":"Services"
        }
    ],
    "sg:phone":"+1 770 745 9474",
    "sg:postcode":"30106",
    "sg:province":"GA",
    "sg:tags":[
        "day"
    ],
    "wof:name":"Always Kids",
    "wof:placetype":"venue"
},
  "geometry": {"coordinates":[-84.59699999999999,33.847698],"type":"Point"}
}