{
  "type": "Feature",
  "properties": {
    "iso:country":"US",
    "sg:address":"6448 Suwanee Dam Rd",
    "sg:city":"Buford",
    "sg:classifiers":[
        {
            "category":"Home & Garden",
            "subcategory":"Home Furnishings",
            "type":"Retail Goods"
        }
    ],
    "sg:phone":"+1 770 652 6106",
    "sg:postcode":"30518",
    "sg:province":"GA",
    "sg:tags":[
        "cutlery"
    ],
    "wof:name":"Shaw Cutlery",
    "wof:placetype":"venue"
},
  "geometry": {"coordinates":[-84.063956,34.144406],"type":"Point"}
}