{
  "type": "Feature",
  "properties": {
    "iso:country":"US",
    "sg:address":"3387 Glenrose Pt",
    "sg:city":"Atlanta",
    "sg:classifiers":[
        {
            "category":"Professional",
            "subcategory":"Lawyer & Legal Services",
            "type":"Services"
        }
    ],
    "sg:phone":"+1 404 523 5614",
    "sg:postcode":"30341",
    "sg:province":"GA",
    "sg:tags":[
        "attorney"
    ],
    "wof:name":"Jeffrey R Nickerson",
    "wof:placetype":"venue"
},
  "geometry": {"coordinates":[-84.25029499999999,33.863816],"type":"Point"}
}