{
  "type": "Feature",
  "properties": {
    "addr:full":"558 Bruce Way SW Lilburn GA 30047",
    "addr:housenumber":"558",
    "addr:postcode":"30047",
    "addr:street":"Bruce Way Sw",
    "iso:country":"US",
    "sg:address":"558 Bruce Way SW",
    "sg:city":"Lilburn",
    "sg:classifiers":[
        {
            "category":"Building & Trades",
            "subcategory":"Construction",
            "type":"Services"
        }
    ],
    "sg:phone":"+1 770 638 7039",
    "sg:postcode":"30047",
    "sg:province":"GA",
    "sg:tags":[
        "contractor"
    ],
    "wof:name":"Jose Cuevas Drywall",
    "wof:placetype":"venue"
},
  "geometry": {"coordinates":[-84.10307400000001,33.877574],"type":"Point"}
}