{
  "type": "Feature",
  "properties": {
    "addr:full":"2255 Sussex Ct Snellville GA 30078",
    "addr:housenumber":"2255",
    "addr:postcode":"30078",
    "addr:street":"Sussex Ct",
    "iso:country":"US",
    "sg:address":"2255 Sussex Ct",
    "sg:city":"Snellville",
    "sg:classifiers":[
        {
            "category":"Wholesale",
            "subcategory":"Non-durable Goods",
            "type":"Manufacturing & Wholesale Goods"
        }
    ],
    "sg:phone":"+1 770 979 8866",
    "sg:postcode":"30078",
    "sg:province":"GA",
    "sg:tags":[
        "advertising",
        "specialty"
    ],
    "wof:name":"Ad Counsel Associates Inc",
    "wof:placetype":"venue"
},
  "geometry": {"coordinates":[-84.03264,33.85014],"type":"Point"}
}