{
  "type": "Feature",
  "properties": {
    "iso:country":"US",
    "sg:address":"396 Auburn Ave NE",
    "sg:city":"Atlanta",
    "sg:classifiers":[
        {
            "category":"Education",
            "subcategory":"Library",
            "type":"Public Place"
        }
    ],
    "sg:phone":"+1 404 589 0033",
    "sg:postcode":"30312",
    "sg:province":"GA",
    "wof:name":"All Eyes On Egypt",
    "wof:placetype":"venue"
},
  "geometry": {"coordinates":[-84.375269,33.755574],"type":"Point"}
}