{
  "type": "Feature",
  "properties": {
    "iso:country":"US",
    "sg:address":"5160 Cowan Rd",
    "sg:city":"Acworth",
    "sg:classifiers":[
        {
            "category":"Autos & Motor Vehicles",
            "subcategory":"Fuel & Gas Station",
            "type":"Retail Goods"
        }
    ],
    "sg:phone":"+1 770 974 9146",
    "sg:postcode":"30101",
    "sg:province":"GA",
    "sg:tags":[
        "station",
        "gasoline",
        "oil"
    ],
    "wof:name":"Shell Travel Plaza",
    "wof:placetype":"venue"
},
  "geometry": {"coordinates":[-84.653229,34.077188],"type":"Point"}
}