{
  "type": "Feature",
  "properties": {
    "iso:country":"US",
    "sg:address":"3645 Mercer University Dr",
    "sg:city":"Macon",
    "sg:classifiers":[
        {
            "category":"Real Estate",
            "subcategory":"Real Estate Operator",
            "type":"Services"
        }
    ],
    "sg:phone":"+1 478 474 3073",
    "sg:postcode":"31204",
    "sg:province":"GA",
    "sg:tags":[
        "building",
        "apartment"
    ],
    "wof:name":"River Bend Apartments Inc",
    "wof:placetype":"venue"
},
  "geometry": {"coordinates":[-83.695886,32.821176],"type":"Point"}
}