{
  "type": "Feature",
  "properties": {
    "addr:full":"9880 Main St Woodstock GA 30188",
    "addr:housenumber":"9880",
    "addr:postcode":"30188",
    "addr:street":"Main St",
    "iso:country":"US",
    "sg:address":"9880 Main St",
    "sg:city":"Woodstock",
    "sg:classifiers":[
        {
            "category":"Retail",
            "subcategory":"Auto Repair",
            "type":"Services"
        }
    ],
    "sg:phone":"+1 770 516 7110",
    "sg:postcode":"30188",
    "sg:province":"GA",
    "wof:name":"Aamco Transmissions",
    "wof:placetype":"venue"
},
  "geometry": {"coordinates":[-84.519896,34.082173],"type":"Point"}
}