{
  "type": "Feature",
  "properties": {
    "addr:full":"3636 Ukraine Dr Columbus GA 31906",
    "addr:housenumber":"3636",
    "addr:postcode":"31906",
    "addr:street":"Ukraine Dr",
    "iso:country":"US",
    "sg:address":"3636 Ukraine Dr",
    "sg:city":"Columbus",
    "sg:classifiers":[
        {
            "category":"Organizations",
            "subcategory":"Religious Organization",
            "type":"Services"
        }
    ],
    "sg:phone":"+1 706 687 2161",
    "sg:postcode":"31906",
    "sg:province":"GA",
    "wof:name":"Canaan Baptist Church",
    "wof:placetype":"venue"
},
  "geometry": {"coordinates":[-84.93006800000001,32.441747],"type":"Point"}
}