{
  "type": "Feature",
  "properties": {
    "iso:country":"US",
    "sg:address":"2561 Austell Rd SW Ste 220",
    "sg:city":"Marietta",
    "sg:classifiers":[
        {
            "category":"Retail",
            "subcategory":"Laundry & Dry Cleaning",
            "type":"Services"
        }
    ],
    "sg:phone":"+1 770 438 0479",
    "sg:postcode":"30008",
    "sg:province":"GA",
    "wof:name":"M & S Laundry",
    "wof:placetype":"venue"
},
  "geometry": {"coordinates":[-84.578592,33.890977],"type":"Point"}
}