{
  "type": "Feature",
  "properties": {
    "addr:full":"86 Allen Rd NE Atlanta GA 30328",
    "addr:housenumber":"86",
    "addr:postcode":"30328",
    "addr:street":"Allen Rd Ne",
    "iso:country":"US",
    "sg:address":"86 Allen Rd NE",
    "sg:city":"Atlanta",
    "sg:classifiers":[
        {
            "category":"Building & Trades",
            "subcategory":"Electrical",
            "type":"Services"
        },
        {
            "category":"Professional",
            "subcategory":"Management & Consulting",
            "type":"Services"
        }
    ],
    "sg:phone":"+1 404 252 7119",
    "sg:postcode":"30328",
    "sg:province":"GA",
    "sg:tags":[
        "consultant",
        "lighting",
        "landscape"
    ],
    "wof:name":"Nite Time Decor",
    "wof:placetype":"venue"
},
  "geometry": {"coordinates":[-84.38424999999999,33.91358],"type":"Point"}
}