{
  "type": "Feature",
  "properties": {
    "iso:country":"US",
    "sg:address":"652 Miami Cir NE",
    "sg:city":"Atlanta",
    "sg:classifiers":[
        {
            "category":"Professional",
            "subcategory":"Business Services",
            "type":"Services"
        }
    ],
    "sg:phone":"+1 404 869 3582",
    "sg:postcode":"30324",
    "sg:province":"GA",
    "wof:name":"Iron Design",
    "wof:placetype":"venue"
},
  "geometry": {"coordinates":[-84.362993,33.830449],"type":"Point"}
}