{
  "type": "Feature",
  "properties": {
    "iso:country":"US",
    "sg:address":"5230 Regency Lake Ct",
    "sg:city":"Buford",
    "sg:classifiers":[
        {
            "category":"Shopping",
            "subcategory":"Gifts & Souvenirs",
            "type":"Retail Goods"
        }
    ],
    "sg:phone":"+1 770 614 0478",
    "sg:postcode":"30518",
    "sg:province":"GA",
    "wof:name":"Card Robert J Etal",
    "wof:placetype":"venue"
},
  "geometry": {"coordinates":[-84.06738300000001,34.100495],"type":"Point"}
}