{
  "type": "Feature",
  "properties": {
    "addr:full":"101 Redmond Rd Rome GA 30165",
    "addr:housenumber":"101",
    "addr:postcode":"ga 30165",
    "addr:street":"Redmond Rd",
    "iso:country":"US",
    "sg:address":"101 Redmond Rd",
    "sg:city":"Rome",
    "sg:classifiers":[
        {
            "category":"Health Services",
            "subcategory":"Health Practitioner",
            "type":"Services"
        }
    ],
    "sg:phone":"+1 706 236 6475",
    "sg:postcode":"30165",
    "sg:province":"GA",
    "sg:tags":[
        "psychologist"
    ],
    "wof:name":"Harbin Clinic Sleep Lab",
    "wof:placetype":"venue"
},
  "geometry": {"coordinates":[-85.186815,34.27815],"type":"Point"}
}