{
  "type": "Feature",
  "properties": {
    "addr:full":"792 Elma G Miles Pkwy Hinesville GA 31313",
    "addr:housenumber":"792;g",
    "addr:postcode":"31313",
    "addr:street":"Elma;Miles Pkwy",
    "iso:country":"US",
    "sg:address":"792 Elma G Miles Pkwy",
    "sg:city":"Hinesville",
    "sg:classifiers":[
        {
            "category":"Insurance",
            "subcategory":"Insurance Agent",
            "type":"Services"
        }
    ],
    "sg:phone":"+1 912 876 3254",
    "sg:postcode":"31313",
    "sg:province":"GA",
    "wof:name":"AFLAC",
    "wof:placetype":"venue"
},
  "geometry": {"coordinates":[-81.614842,31.830826],"type":"Point"}
}