{
  "type": "Feature",
  "properties": {
    "addr:full":"419 Commerce Dr Peachtree City GA 30269",
    "addr:housenumber":"419",
    "addr:postcode":"30269",
    "addr:street":"Commerce Dr",
    "iso:country":"US",
    "sg:address":"419 Commerce Dr",
    "sg:city":"Peachtree City",
    "sg:classifiers":[
        {
            "category":"Government",
            "subcategory":"Office",
            "type":"Public Place"
        }
    ],
    "sg:phone":"+1 770 487 1892",
    "sg:postcode":"30269",
    "sg:province":"GA",
    "sg:tags":[
        "national",
        "security"
    ],
    "wof:name":"Army United States Dept of",
    "wof:placetype":"venue"
},
  "geometry": {"coordinates":[-84.589995,33.398947],"type":"Point"}
}