{
  "type": "Feature",
  "properties": {
    "addr:full":"4550 Olde Perimeter Way Atlanta GA 30346",
    "addr:housenumber":"4550",
    "addr:postcode":"30346",
    "addr:street":"Olde Perimeter Way",
    "iso:country":"US",
    "sg:address":"4550 Olde Perimeter Way",
    "sg:city":"Atlanta",
    "sg:classifiers":[
        {
            "category":"Home & Garden",
            "subcategory":"Furniture",
            "type":"Retail Goods"
        }
    ],
    "sg:phone":"+1 770 698 7699",
    "sg:postcode":"30346",
    "sg:province":"GA",
    "sg:tags":[
        "store"
    ],
    "sg:website":"www.henredon.com",
    "wof:name":"Henredon Furniture",
    "wof:placetype":"venue"
},
  "geometry": {"coordinates":[-84.343582,33.929853],"type":"Point"}
}