{
  "type": "Feature",
  "properties": {
    "iso:country":"US",
    "sg:address":"3241 Richardson Rd",
    "sg:city":"Villa Rica",
    "sg:classifiers":[
        {
            "category":"Building & Trades",
            "subcategory":"Cleaning & Sanitation",
            "type":"Services"
        }
    ],
    "sg:phone":"+1 770 942 4913",
    "sg:postcode":"30180",
    "sg:province":"GA",
    "sg:tags":[
        "maintenance"
    ],
    "wof:name":"Zachery",
    "wof:placetype":"venue"
},
  "geometry": {"coordinates":[-84.842659,33.711331],"type":"Point"}
}