{
  "type": "Feature",
  "properties": {
    "addr:full":"870 Martin Luther King Dr Atlanta GA 30314",
    "addr:housenumber":"870",
    "addr:postcode":"30314",
    "addr:street":"Martin Luther King Dr",
    "iso:country":"US",
    "sg:address":"870 Martin Luther King Dr",
    "sg:city":"Atlanta",
    "sg:classifiers":[
        {
            "category":"Fast Food",
            "type":"Food & Drink"
        },
        {
            "category":"Food & Beverages",
            "subcategory":"Bakery",
            "type":"Retail Goods"
        }
    ],
    "sg:phone":"+1 404 521 9903",
    "sg:postcode":"30314",
    "sg:province":"GA",
    "sg:tags":[
        "sandwich"
    ],
    "sg:website":"mreverythingcafe.blogspot.com/",
    "wof:name":"Mr Everything Cafe",
    "wof:placetype":"venue"
},
  "geometry": {"coordinates":[-84.41600800000001,33.754719],"type":"Point"}
}