{
  "type": "Feature",
  "properties": {
    "addr:full":"200 Oak Forest Ln Warner Robins GA 31088",
    "addr:housenumber":"200",
    "addr:postcode":"31088",
    "addr:street":"Oak Forest Ln",
    "iso:country":"US",
    "sg:address":"200 Oak Forest Ln",
    "sg:city":"Warner Robins",
    "sg:classifiers":[
        {
            "category":"Professional",
            "subcategory":"Business Services",
            "type":"Services"
        }
    ],
    "sg:phone":"+1 478 922 7672",
    "sg:postcode":"31088",
    "sg:province":"GA",
    "sg:tags":[
        "consulting",
        "logistic"
    ],
    "wof:name":"Blue Ribbon Services",
    "wof:placetype":"venue"
},
  "geometry": {"coordinates":[-83.633769,32.59847],"type":"Point"}
}