{
  "type": "Feature",
  "properties": {
    "addr:full":"461 Cook St Royston GA 30662",
    "addr:housenumber":"461",
    "addr:postcode":"30662",
    "addr:street":"Cook St",
    "iso:country":"US",
    "sg:address":"461 Cook St",
    "sg:city":"Royston",
    "sg:classifiers":[
        {
            "category":"Social Services",
            "type":"Services"
        }
    ],
    "sg:phone":"+1 706 245 1473",
    "sg:postcode":"30662",
    "sg:province":"GA",
    "sg:tags":[
        "counseling"
    ],
    "wof:name":"Rhoades, Harold G Phd Pc",
    "wof:placetype":"venue"
},
  "geometry": {"coordinates":[-83.11690400000001,34.283769],"type":"Point"}
}