{
  "type": "Feature",
  "properties": {
    "iso:country":"US",
    "sg:address":"400 Ponce de Leon Ave NE",
    "sg:city":"Atlanta",
    "sg:classifiers":[
        {
            "category":"Organizations",
            "subcategory":"Membership Organization",
            "type":"Services"
        }
    ],
    "sg:phone":"+1 404 815 9320",
    "sg:postcode":"30308",
    "sg:province":"GA",
    "sg:tags":[
        "fraternal"
    ],
    "wof:name":"Shrine, Mosque",
    "wof:placetype":"venue"
},
  "geometry": {"coordinates":[-84.375119,33.772391],"type":"Point"}
}