{
  "type": "Feature",
  "properties": {
    "addr:full":"3773 Rivaridge Dr Marietta GA 30062",
    "addr:housenumber":"3773",
    "addr:postcode":"30062",
    "addr:street":"Rivaridge Dr",
    "iso:country":"US",
    "sg:address":"3773 Rivaridge Dr",
    "sg:city":"Marietta",
    "sg:classifiers":[
        {
            "category":"Wholesale",
            "subcategory":"Construction Materials",
            "type":"Manufacturing & Wholesale Goods"
        }
    ],
    "sg:phone":"+1 770 587 5343",
    "sg:postcode":"30062",
    "sg:province":"GA",
    "wof:name":"Dial Roofing Service Inc",
    "wof:placetype":"venue"
},
  "geometry": {"coordinates":[-84.43810499999999,34.046017],"type":"Point"}
}