{
  "type": "Feature",
  "properties": {
    "iso:country":"US",
    "sg:address":"150 Felton Burr Rd",
    "sg:city":"Rockmart",
    "sg:classifiers":[
        {
            "category":"Autos & Motor Vehicles",
            "subcategory":"Automobile Sales",
            "type":"Retail Goods"
        }
    ],
    "sg:phone":"+1 678 757 9962",
    "sg:postcode":"30153",
    "sg:province":"GA",
    "sg:tags":[
        "used"
    ],
    "wof:name":"Thompson Rockmart",
    "wof:placetype":"venue"
},
  "geometry": {"coordinates":[-84.99799299999999,33.888951],"type":"Point"}
}