{
  "type": "Feature",
  "properties": {
    "iso:country":"US",
    "sg:address":"3700 Crestwood Pkwy",
    "sg:city":"Duluth",
    "sg:classifiers":[
        {
            "category":"Professional",
            "subcategory":"Advertising",
            "type":"Services"
        }
    ],
    "sg:phone":"+1 678 584 9994",
    "sg:postcode":"30096",
    "sg:province":"GA",
    "sg:tags":[
        "outdoor"
    ],
    "wof:name":"Crown Media",
    "wof:placetype":"venue"
},
  "geometry": {"coordinates":[-84.12698899999999,33.947173],"type":"Point"}
}