{
  "type": "Feature",
  "properties": {
    "iso:country":"US",
    "sg:address":"4300 S Lee St",
    "sg:city":"Buford",
    "sg:classifiers":[
        {
            "category":"Organizations",
            "subcategory":"Religious Organization",
            "type":"Services"
        }
    ],
    "sg:phone":"+1 770 945 0200",
    "sg:postcode":"30518",
    "sg:province":"GA",
    "sg:tags":[
        "clergy"
    ],
    "wof:name":"C Cook",
    "wof:placetype":"venue"
},
  "geometry": {"coordinates":[-83.998788,34.092641],"type":"Point"}
}