{
  "type": "Feature",
  "properties": {
    "iso:country":"US",
    "sg:address":"36 Ledford Rd",
    "sg:city":"Dahlonega",
    "sg:classifiers":[
        {
            "category":"Home & Garden",
            "subcategory":"Home Furnishings",
            "type":"Retail Goods"
        }
    ],
    "sg:phone":"+1 706 746 3660",
    "sg:postcode":"30533",
    "sg:province":"GA",
    "sg:tags":[
        "window",
        "treatment"
    ],
    "wof:name":"Mountain Window Magic",
    "wof:placetype":"venue"
},
  "geometry": {"coordinates":[-83.910923,34.486452],"type":"Point"}
}