{
  "type": "Feature",
  "properties": {
    "addr:full":"1634 S Hairston Rd Stone Mountain GA 30088",
    "addr:housenumber":"1634",
    "addr:postcode":"30088",
    "addr:street":"S Hairston Rd",
    "iso:country":"US",
    "sg:address":"1634 S Hairston Rd",
    "sg:city":"Stone Mountain",
    "sg:classifiers":[
        {
            "category":"Building & Trades",
            "subcategory":"Plumbing",
            "type":"Services"
        }
    ],
    "sg:phone":"+1 770 484 6828",
    "sg:postcode":"30088",
    "sg:province":"GA",
    "sg:tags":[
        "contractor"
    ],
    "wof:name":"Plumtech Plumbing",
    "wof:placetype":"venue"
},
  "geometry": {"coordinates":[-84.196437,33.746579],"type":"Point"}
}