{
  "type": "Feature",
  "properties": {
    "addr:full":"4185 Merritt Dr Cumming GA 30041",
    "addr:housenumber":"4185",
    "addr:postcode":"30041",
    "addr:street":"Merritt Dr",
    "iso:country":"US",
    "sg:address":"4185 Merritt Dr",
    "sg:city":"Cumming",
    "sg:classifiers":[
        {
            "category":"Professional",
            "type":"Services"
        }
    ],
    "sg:phone":"+1 770 888 4711",
    "sg:postcode":"30041",
    "sg:province":"GA",
    "wof:name":"Robert A Ullian",
    "wof:placetype":"venue"
},
  "geometry": {"coordinates":[-84.089755,34.207468],"type":"Point"}
}