{
  "type": "Feature",
  "properties": {
    "iso:country":"US",
    "sg:address":"3910 Campbellton Rd",
    "sg:city":"Atlanta",
    "sg:classifiers":[
        {
            "category":"Banks & Credit Unions",
            "subcategory":"Bank",
            "type":"Services"
        }
    ],
    "sg:phone":"+1 404 344 4343",
    "sg:postcode":"30331",
    "sg:province":"GA",
    "sg:tags":[
        "personal",
        "institution"
    ],
    "wof:name":"Household Technician LLC",
    "wof:placetype":"venue"
},
  "geometry": {"coordinates":[-84.51390499999999,33.690899],"type":"Point"}
}