{
  "type": "Feature",
  "properties": {
    "iso:country":"US",
    "sg:address":"467 Jackie Hart Rd",
    "sg:city":"Statesboro",
    "sg:classifiers":[
        {
            "category":"Building & Trades",
            "subcategory":"Electrical",
            "type":"Services"
        }
    ],
    "sg:phone":"+1 912 587 5344",
    "sg:postcode":"30461",
    "sg:province":"GA",
    "sg:tags":[
        "electrical",
        "electric",
        "contractor"
    ],
    "wof:name":"Eagle Alarm and Electrical",
    "wof:placetype":"venue"
},
  "geometry": {"coordinates":[-81.682627,32.45583],"type":"Point"}
}