{
  "type": "Feature",
  "properties": {
    "iso:country":"US",
    "sg:address":"3715 Lakeheath Dr",
    "sg:city":"Cumming",
    "sg:classifiers":[
        {
            "category":"Building & Trades",
            "subcategory":"Cleaning & Sanitation",
            "type":"Services"
        }
    ],
    "sg:phone":"+1 770 424 8982",
    "sg:postcode":"30041",
    "sg:province":"GA",
    "sg:tags":[
        "carpet"
    ],
    "wof:name":"Quality Carpet & Upholstery Inc",
    "wof:placetype":"venue"
},
  "geometry": {"coordinates":[-84.177002,34.086498],"type":"Point"}
}