{
  "type": "Feature",
  "properties": {
    "iso:country":"US",
    "sg:address":"1303 Fallsbrook Ter",
    "sg:city":"Acworth",
    "sg:classifiers":[
        {
            "category":"Wholesale",
            "subcategory":"Machinery & Supplies",
            "type":"Manufacturing & Wholesale Goods"
        }
    ],
    "sg:phone":"+1 770 425 3353",
    "sg:postcode":"30101",
    "sg:province":"GA",
    "sg:tags":[
        "tension",
        "chuck",
        "system",
        "shaft",
        "web"
    ],
    "wof:name":"CST Systems",
    "wof:placetype":"venue"
},
  "geometry": {"coordinates":[-84.717962,33.99077],"type":"Point"}
}