{
  "type": "Feature",
  "properties": {
    "iso:country":"US",
    "sg:address":"2490 7th St",
    "sg:city":"Waycross",
    "sg:classifiers":[
        {
            "category":"Building & Trades",
            "subcategory":"Pest Control",
            "type":"Services"
        }
    ],
    "sg:phone":"+1 912 283 4464",
    "sg:postcode":"31503",
    "sg:province":"GA",
    "sg:tags":[
        "mothproofing"
    ],
    "wof:name":"Trusdell & Trusdell Pest Control",
    "wof:placetype":"venue"
},
  "geometry": {"coordinates":[-82.42029100000001,31.16175],"type":"Point"}
}