{
  "type": "Feature",
  "properties": {
    "addr:full":"2009 W Hill Ave Valdosta GA 31601",
    "addr:housenumber":"2009",
    "addr:postcode":"31601",
    "addr:street":"W Hill Ave",
    "iso:country":"US",
    "sg:address":"2009 W Hill Ave",
    "sg:city":"Valdosta",
    "sg:classifiers":[
        {
            "category":"Autos & Motor Vehicles",
            "subcategory":"Fuel & Gas Station",
            "type":"Retail Goods"
        }
    ],
    "sg:phone":"+1 229 244 5707",
    "sg:postcode":"31601",
    "sg:province":"GA",
    "sg:tags":[
        "station"
    ],
    "wof:name":"Valdosta Phillips 66",
    "wof:placetype":"venue"
},
  "geometry": {"coordinates":[-83.315298,30.818744],"type":"Point"}
}