{
  "type": "Feature",
  "properties": {
    "addr:full":"1506 Alice St Waycross GA 31501",
    "addr:housenumber":"1506",
    "addr:postcode":"31501",
    "addr:street":"Alice St",
    "iso:country":"US",
    "sg:address":"1506 Alice St",
    "sg:city":"Waycross",
    "sg:classifiers":[
        {
            "category":"Shopping",
            "type":"Retail Goods"
        }
    ],
    "sg:phone":"+1 912 284 9191",
    "sg:postcode":"31501",
    "sg:province":"GA",
    "sg:tags":[
        "equipment",
        "care",
        "health",
        "home"
    ],
    "wof:name":"Barnes Healthcare Svc",
    "wof:placetype":"venue"
},
  "geometry": {"coordinates":[-82.34969,31.221983],"type":"Point"}
}