{
  "type": "Feature",
  "properties": {
    "iso:country":"US",
    "sg:address":"1020 Barber Creek Dr",
    "sg:city":"Watkinsville",
    "sg:classifiers":[
        {
            "category":"Personal",
            "subcategory":"Barber",
            "type":"Services"
        }
    ],
    "sg:phone":"+1 706 353 0139",
    "sg:postcode":"30677",
    "sg:province":"GA",
    "wof:name":"Barber Creek Investment Group",
    "wof:placetype":"venue"
},
  "geometry": {"coordinates":[-83.46323099999999,33.903968],"type":"Point"}
}