{
  "type": "Feature",
  "properties": {
    "addr:full":"716 Ashley Pl Stone Mountain GA 30083",
    "addr:housenumber":"716",
    "addr:postcode":"30083",
    "addr:street":"Ashley Pl",
    "iso:country":"US",
    "sg:address":"716 Ashley Pl",
    "sg:city":"Stone Mountain",
    "sg:classifiers":[
        {
            "category":"Real Estate",
            "subcategory":"Real Estate Agent",
            "type":"Services"
        }
    ],
    "sg:phone":"+1 404 297 8360",
    "sg:postcode":"30083",
    "sg:province":"GA",
    "wof:name":"830 Macon St Real Estate",
    "wof:placetype":"venue"
},
  "geometry": {"coordinates":[-84.20728699999999,33.7975],"type":"Point"}
}