{
  "type": "Feature",
  "properties": {
    "iso:country":"US",
    "sg:address":"9730 Medlock Bridge Rd",
    "sg:city":"Duluth",
    "sg:classifiers":[
        {
            "category":"Food & Beverages",
            "subcategory":"Liquor & Beverages",
            "type":"Retail Goods"
        }
    ],
    "sg:phone":"+1 770 623 3939",
    "sg:postcode":"30097",
    "sg:province":"GA",
    "sg:tags":[
        "beer",
        "spirit",
        "wine"
    ],
    "wof:name":"Fairway Package Store",
    "wof:placetype":"venue"
},
  "geometry": {"coordinates":[-84.190102,34.0173],"type":"Point"}
}