{
  "type": "Feature",
  "properties": {
    "addr:full":"1188 Larson Ln Marietta GA 30064",
    "addr:housenumber":"1188",
    "addr:postcode":"30064",
    "addr:street":"Larson Ln",
    "iso:country":"US",
    "sg:address":"1188 Larson Ln",
    "sg:city":"Marietta",
    "sg:classifiers":[
        {
            "category":"Farming",
            "subcategory":"Nursery",
            "type":"Manufacturing & Wholesale Goods"
        }
    ],
    "sg:phone":"+1 678 290 1942",
    "sg:postcode":"30064",
    "sg:province":"GA",
    "sg:tags":[
        "ornamental"
    ],
    "wof:name":"Sod Couple Inc",
    "wof:placetype":"venue"
},
  "geometry": {"coordinates":[-84.600537,33.924776],"type":"Point"}
}